Workbook

Sheet README
A1: Argentina Macro Analysis — Workbook Guide
A2: Refresh Haver downloads on raw tabs and run standard quarterly / monthly / annual analyses with 2-yr projections.
A4: TAB OVERVIEW
A5: • Real and nominal GDP — raw Haver download (quarterly). Paste new data over rows 8+, keep column order.
A6: • CPI — raw Haver download (monthly). Paste new data over rows 8+.
A7: • GDP Analysis — pre-linked. Quarterly + Annual + Nominal GDP USD + Projections + Charts.
A8: • CPI Analysis — pre-linked. Monthly + Quarterly + Annual + Projections + Charts.
A9: • TEMPLATE - Quarterly / Monthly / Annual — reusable templates for any new metric.
A11: REFRESHING HAVER DATA
A12: 1. Download with the same layout: header rows 1–7, data row 8+. Date in col A, period code in col B.
A13: 2. Paste over rows 8+ on the matching raw tab. All Analysis tabs and charts auto-recalculate.
A14: 3. Formulas extend to row 220 (quarterly, ~55 yrs buffer) / row 260 (monthly, ~21 yrs buffer).
... A43: • Year derivation parses the Haver period code: '244'→2024Q4, '2603'→2026M03.

Sheet Real and nominal GDP
C1: SA | D1: SA | E1: SA | F1: SA | G1: NSA | H1: NSA | I1: NSA
A2: Date | C2: Real GDP | D2: Consumption | E2: Gvt. Expenditures | F2: Investment | G2: Real GDP | H2: Nominal | I2: CPI | J2: FX | K2: FX informal
B3: 1041 !Q NA_ | C3: S213NGPC@EMERGELA | D3: S213NCPC@EMERGELA | E3: S213NCGC@EMERGELA | F3: S213NFC@EMERGELA | G3: N213NGPC@EMERGELA | H3: N213NGDP@EMERGELA | I3: N213PC@EMERGELA | J3: N213XUSV@EMERGELA | K3: X213DIM@EMERGELA
B4: .DESC | C4: Argentina: Gross Domestic Product at Market Prices (SAAR, Mil.2004.Pesos) | D4: Argentina: GDP: Private Consumption Expenditure (SAAR, Mil.2004.Pesos) | E4: Argentina: GDP: Govt Consumption Expenditure (SAAR, Mil.2004.Pesos) | F4: Argentina: GDP: Gross Fixed Capital Formation (SAAR, Mil.2004.Pesos) | G4: Argentina: Gross Domestic Product at Market Prices (NSAAR, Mil.2004.Pesos) | H4: Argentina: Gross Domestic Product at Market Prices (NSAAR, Mil.Pesos) | I4: Argentina: Consumer Price Index (NSA, Dec-16=100) | J4: Argentina: Exchange Rate: United States (Avg, Argentinian Peso/US$) | K4: Argentina: Informal US$ Exchange Rate, Mid Rate (Avg, Peso/US$)
B5: .SOURCE | C5: INDEC | D5: INDEC | E5: INDEC | F5: INDEC | G5: INDEC | H5: INDEC | I5: INDEC | J5: BCRA | K5: AMB
B6: .DATA_TYPE | C6: LocCur | D6: LocCur | E6: LocCur | F6: LocCur | G6: LocCur | H6: LocCur | I6: INDEX | J6: RATIO | K6: LC/US$
B7: .MAG | C7: 6 | D7: 6 | E7: 6 | F7: 6 | G7: 6 | H7: 6 | I7: 0 | J7: 0 | K7: 0
A8: 38047 | B8: 041 | C8: 476036.53 | D8: 302781.11 | E8: 52668.16 | F8: 74498.627 | G8: 460369.44 | H8: 439196 | J8: 2.9072667 | K8: 2.9163333
A9: 38139 | B9: 042 | C9: 470010.07 | D9: 304361.81 | E9: 52818.974 | F9: 76869.591 | G9: 514395.68 | H9: 509499 | J9: 2.9050733 | K9: 2.9093333
A10: 38231 | B10: 043 | C10: 493895.12 | D10: 316912.03 | E10: 54483.809 | F10: 77809.682 | G10: 481151.98 | H10: 488462 | J10: 2.9879933 | K10: 2.9956667
A11: 38322 | B11: 044 | C11: 500519.07 | D11: 324272.59 | E11: 55704.211 | F11: 79234.809 | G11: 484543.68 | H11: 503304 | J11: 2.9646167
A12: 38412 | B12: 051 | C12: 514918.46 | D12: 318967.71 | E12: 57528.588 | F12: 85178.716 | G12: 493602.53 | H12: 510703 | J12: 2.9297667 | K12: 2.9343333
A13: 38504 | B13: 052 | C13: 527084.2 | D13: 346690.41 | E13: 58964.326 | F13: 87994.464 | G13: 581668.25 | H13: 605772 | J13: 2.89173 | K13: 2.8986667
A14: 38596 | B14: 053 | C14: 530101.96 | D14: 331326.97 | E14: 59826.06 | F14: 88235.413 | G14: 514697.79 | H14: 590220 | J14: 2.8896033 | K14: 2.8846667
A15: 38687 | B15: 054 | C15: 540119.16 | D15: 343626.04 | E15: 60611.905 | F15: 95820.827 | G15: 522255.2 | H15: 623458 | J15: 2.98288 | K15: 2.9876667
A16: 38777 | B16: 061 | C16: 554455.77 | D16: 353511.32 | E16: 60524.269 | F16: 97450.782 | G16: 532348.21 | H16: 643562 | J16: 3.0649333 | K16: 3.0796667
A17: 38869 | B17: 062 | C17: 561157.22 | D17: 371905.79 | E17: 60706.294 | F17: 100741.05 | G17: 614076.39 | H17: 727989 | J17: 3.06794 | K17: 3.083
A18: 38961 | B18: 063 | C18: 577088.46 | D18: 381137.22 | E18: 61658.229 | F18: 103927.85 | G18: 562978.97 | H18: 729299 | J18: 3.0872567 | K18: 3.1033333
A19: 39052 | B19: 064 | C19: 589496.16 | D19: 380937.31 | E19: 62861.894 | F19: 106810.9 | G19: 572794.05 | H19: 762766 | J19: 3.0774 | K19: 3.098
A20: 39142 | B20: 071 | C20: 603483.21 | D20: 392667.41 | E20: 65392.759 | F20: 116267.52 | G20: 576846.89 | H20: 774388 | J20: 3.09675 | K20: 3.114
A21: 39234 | B21: 072 | C21: 616073.37 | D21: 402296.08 | E21: 65948.641 | F21: 121508.99 | G21: 674620.56 | H21: 904350 | J21: 3.0828667 | K21: 3.111
A22: 39326 | B22: 073 | C22: 624446.9 | D22: 412291.88 | E22: 66182.353 | F22: 125653.67 | G22: 610425.69 | H22: 914104 | J22: 3.1380133 | K22: 3.1816667
A23: 39417 | B23: 074 | C23: 643766.54 | D23: 419150.79 | E23: 67468.668 | F23: 129139.78 | G23: 625876.87 | H23: 995079 | J23: 3.1450767 | K23: 3.1746667
... A41: 41061 | B41: 122 | C41: 683593.32 | D41: 493768.88 | E41: 82764.047 | F41: 133906.72 | G41: 730838.27 | H41: 2651098 | J41: 4.4497267 | K41: 5.468
A42: 41153 | B42: 123 | C42: 705293.74 | D42: 515643.41 | E42: 84004.922 | F42: 143391.77 | G42: 703461.65 | H42: 2704828 | I42: 29.739833 | J42: 4.6116067 | K42: 6.2866667
A43: 41244 | B43: 124 | C43: 716708.04 | D43: 519592.21 | E43: 84715.909 | F43: 148410.68 | G43: 706958.04 | H43: 2850170 | I43: 31.3387 | J43: 4.80352 | K43: 6.3916667
A44: 41334 | B44: 131 | C44: 715943.74 | D44: 514386.79 | E44: 86326.806 | F44: 145736 | G44: 677085.53 | H44: 2888981 | I44: 33.105433 | J44: 5.0156467 | K44: 7.721
A45: 41426 | B45: 132 | C45: 720882.85 | D45: 517251.74 | E45: 87404.109 | F45: 147670.82 | G45: 776486.6 | H45: 3387811 | I45: 34.798233 | J45: 5.2423567 | K45: 8.7116667
A46: 41518 | B46: 133 | C46: 725588.38 | D46: 535655.93 | E46: 87951.009 | F46: 145972.59 | G46: 721458.94 | H46: 3436547 | I46: 37.0408 | J46: 5.58808 | K46: 8.8253333
A47: 41609 | B47: 134 | C47: 719213.45 | D47: 535403.67 | E47: 89983.227 | F47: 144846.87 | G47: 706597.34 | H47: 3679896 | I47: 39.5626 | J47: 6.0668567 | K47: 9.723
A48: 41699 | B48: 141 | C48: 708278.97 | D48: 521790.9 | E48: 90817.606 | F48: 141725.87 | G48: 671066.05 | H48: 3917649 | I48: 44.1826 | J48: 7.6322467 | K48: 11.300333
A49: 41791 | B49: 142 | C49: 702914.57 | D49: 498942.24 | E49: 89305.792 | F49: 139110.59 | G49: 760576.87 | H49: 4702630 | I49: 48.474633 | J49: 8.0561933 | K49: 11.125333
A50: 41883 | B50: 143 | C50: 697281.49 | D50: 490465.14 | E50: 90467.767 | F50: 133831.35 | G50: 690879.8 | H50: 4685503 | I50: 51.884633 | J50: 8.2984567 | K50: 13.411
A51: 41974 | B51: 144 | C51: 700749.15 | D51: 499859.46 | E51: 91430.632 | F51: 130090.78 | G51: 686701.47 | H51: 5010564 | I51: 54.994467 | J51: 8.51345 | K51: 13.700333
A52: 42064 | B52: 151 | C52: 710714.75 | D52: 508612.97 | E52: 94414.588 | F52: 138222.16 | G52: 672749.81 | H52: 5092694 | I52: 57.8225 | J52: 8.69027 | K52: 13.172667
A53: 42156 | B53: 152 | C53: 728934.83 | D53: 532927.69 | E53: 97682.915 | F53: 141538.9 | G53: 791235.97 | H53: 5951479 | I53: 61.293333 | J53: 8.9531667 | K53: 12.678333
... A95: 45992 | B95: 254 | C95: 744527.79 | D95: 557631.51 | E95: 95985.853 | F95: 137468.13 | G95: 733788.67 | H95: 939450203 | I95: 9855.5306 | J95: 1437.0627 | K95: 1453.069
A96: 46082 | B96: 261 | I96: 10734.906 | J96: 1417.7638 | K96: 1443.6893

Sheet CPI
C2: Headline | D2: Core
B3: 11501 !M | C3: N213PC@EMERGELA | D3: N213PCXQ@EMERGELA
B4: .DESC | C4: Argentina: Consumer Price Index (NSA, Dec-16=100) | D4: Argentina: CPI Ex Seasonal & Regulated (NSA, Dec-16=100)
B5: .SOURCE | C5: INDEC | D5: INDEC
B6: .DATA_TYPE | C6: INDEX | D6: INDEX
B7: .MAG | C7: 0 | D7: 0
B8: 1501 | C8: 56.9509 | D8: =#N/A -> #N/A
B9: 1502 | C9: 57.7781 | D9: =#N/A -> #N/A
B10: 1503 | C10: 58.7385 | D10: =#N/A -> #N/A
B11: 1504 | C11: 60.1294 | D11: =#N/A -> #N/A
B12: 1505 | C12: 61.4604 | D12: =#N/A -> #N/A
B13: 1506 | C13: 62.2902 | D13: =#N/A -> #N/A
B14: 1507 | C14: 63.5612 | D14: =#N/A -> #N/A
B15: 1508 | C15: 64.7251 | D15: =#N/A -> #N/A
B16: 1509 | C16: 65.7976 | D16: =#N/A -> #N/A
B17: 1510 | C17: 66.9172 | D17: =#N/A -> #N/A
B18: 1511 | C18: 68.2246 | D18: =#N/A -> #N/A
B19: 1512 | C19: 70.8969 | D19: =#N/A -> #N/A
... B30: 1611 | C30: 98.7735 | D30: =#N/A -> #N/A
B31: 1612 | C31: 100 | D31: 100
B32: 1701 | C32: 101.5859 | D32: 101.5039
B33: 1702 | C33: 103.6859 | D33: 103.2105
B34: 1703 | C34: 106.1476 | D34: 105.2057
B35: 1704 | C35: 108.9667 | D35: 107.427
B36: 1705 | C36: 110.5301 | D36: 109.2069
B37: 1706 | C37: 111.8477 | D37: 110.6653
B38: 1707 | C38: 113.7852 | D38: 112.6183
B39: 1708 | C39: 115.3819 | D39: 114.231
B40: 1709 | C40: 117.5719 | D40: 116.0978
B41: 1710 | C41: 119.3528 | D41: 117.6245
B42: 1711 | C42: 120.994 | D42: 119.1358
... B142: 2603 | C142: 11077.061 | D142: 11344.457

Sheet GDP Analysis
A1: GDP Analysis — Argentina
A2: Linked to raw tab 'Real and nominal GDP'. Refresh by pasting new Haver download over row 8+. Formulas extend to row 224 (≈53 yrs buffer).
A4: SETTINGS
A5: Annual aggregation | B5: Per-column (Sum for flow vars; Average for indices/rates)
A7: PROJECTION ASSUMPTIONS (annual YoY %)
A8: Series | B8: Year +1 YoY % | C8: Year +2 YoY %
A9: Real GDP (SA) | B9: 0.03 | C9: 0.025
A10: Consumption | B10: 0.03 | C10: 0.025
A11: Gvt Exp. | B11: 0.02 | C11: 0.02
A12: Investment | B12: 0.05 | C12: 0.04
A13: Real GDP (NSA) | B13: 0.03 | C13: 0.025
A14: Nominal GDP | B14: 0.5 | C14: 0.3
A15: CPI | B15: 0.5 | C15: 0.3
A16: FX (off) | B16: 0.4 | C16: 0.3
A17: FX (informal) | B17: 0.35 | C17: 0.25
A19: DATA & ANALYTICS (linked from raw tab) | V19: ANNUAL AGGREGATION | AI19: PROJECTIONS (annual)
A20: Date | B20: Period | C20: Year | D20: Real GDP (SA) | E20: Consumption | F20: Gvt Exp. | G20: Investment | H20: Real GDP (NSA) | I20: Nominal GDP | J20: CPI | K20: FX (off) | L20: FX (informal) | M20: YoY % Real GDP (SA) | N20: QoQ % Real GDP (SA) | O20: YoY % Nominal GDP | P20: 4Q sum Real GDP (SA) | Q20: 4Q sum Nominal GDP | R20: Nominal GDP USD off (mm) | S20: Nominal GDP USD inf (mm) | V20: Year | W20: Real GDP (SA) | X20: Consumption | Y20: Gvt Exp. | Z20: Investment | AA20: Real GDP (NSA) | AB20: Nominal GDP | AC20: CPI | AD20: FX (off) | AE20: FX (informal) | AF20: YoY % Real GDP (SA) | AI20: Year | AJ20: Real GDP (SA) (proj.) | AK20: Consumption (proj.) | AL20: Gvt Exp. (proj.) | AM20: Investment (proj.) | AN20: Real GDP (NSA) (proj.) | AO20: Nominal GDP (proj.) | AP20: CPI (proj.) | AQ20: FX (off) (proj.) | AR20: FX (informal) (proj.) | AS20: Nominal GDP USD (proj., off)
A21: =IFERROR(IF(ISNUMBER('Real and nominal GDP'!A8),'Real and nominal GDP'!A8,NA()),NA()) -> 38047 | B21: =IFERROR(IF('Real and nominal GDP'!B8="",NA(),'Real and nominal GDP'!B8),NA()) -> 041 | C21: =IFERROR(YEAR(A21),0) -> 2004 | D21: =IFERROR(IF('Real and nominal GDP'!C8="",NA(),IF(ISNUMBER('Real and nominal GDP'!C8),'Real and nominal GDP'!C8,NA())),NA()) -> 476036.53 | E21: =IFERROR(IF('Real and nominal GDP'!D8="",NA(),IF(ISNUMBER('Real and nominal GDP'!D8),'Real and nominal GDP'!D8,NA())),NA()) -> 302781.11 | F21: =IFERROR(IF('Real and nominal GDP'!E8="",NA(),IF(ISNUMBER('Real and nominal GDP'!E8),'Real and nominal GDP'!E8,NA())),NA()) -> 52668.16 | G21: =IFERROR(IF('Real and nominal GDP'!F8="",NA(),IF(ISNUMBER('Real and nominal GDP'!F8),'Real and nominal GDP'!F8,NA())),NA()) -> 74498.627 | H21: =IFERROR(IF('Real and nominal GDP'!G8="",NA(),IF(ISNUMBER('Real and nominal GDP'!G8),'Real and nominal GDP'!G8,NA())),NA()) -> 460369.44 | I21: =IFERROR(IF('Real and nominal GDP'!H8="",NA(),IF(ISNUMBER('Real and nominal GDP'!H8),'Real and nominal GDP'!H8,NA())),NA()) -> 439196 | J21: =IFERROR(IF('Real and nominal GDP'!I8="",NA(),IF(ISNUMBER('Real and nominal GDP'!I8),'Real and nominal GDP'!I8,NA())),NA()) -> #N/A | K21: =IFERROR(IF('Real and nominal GDP'!J8="",NA(),IF(ISNUMBER('Real and nominal GDP'!J8),'Real and nominal GDP'!J8,NA())),NA()) -> 2.9072667 | L21: =IFERROR(IF('Real and nominal GDP'!K8="",NA(),IF(ISNUMBER('Real and nominal GDP'!K8),'Real and nominal GDP'!K8,NA())),NA()) -> 2.9163333 | M21: =NA() -> #N/A | N21: =NA() -> #N/A | O21: =NA() -> #N/A | P21: =NA() -> #N/A | Q21: =NA() -> #N/A | R21: =IFERROR(I21/K21,NA()) -> 151068.36 | S21: =IFERROR(I21/L21,NA()) -> 150598.7 | V21: 2004 | W21: =IF(SUMPRODUCT(($C$21:$C$233=$V$21)*ISNUMBER($D$21:$D$233))=0,NA(),SUMPRODUCT(($C$21:$C$233=$V$21)*IFERROR($D$21:$D$233,0))) -> 1940460.8 | X21: =IF(SUMPRODUCT(($C$21:$C$233=$V$21)*ISNUMBER($E$21:$E$233))=0,NA(),SUMPRODUCT(($C$21:$C$233=$V$21)*IFERROR($E$21:$E$233,0))) -> 1248327.5 | Y21: =IF(SUMPRODUCT(($C$21:$C$233=$V$21)*ISNUMBER($F$21:$F$233))=0,NA(),SUMPRODUCT(($C$21:$C$233=$V$21)*IFERROR($F$21:$F$233,0))) -> 215675.15 | Z21: =IF(SUMPRODUCT(($C$21:$C$233=$V$21)*ISNUMBER($G$21:$G$233))=0,NA(),SUMPRODUCT(($C$21:$C$233=$V$21)*IFERROR($G$21:$G$233,0))) -> 308412.71 | AA21: =IF(SUMPRODUCT(($C$21:$C$233=$V$21)*ISNUMBER($H$21:$H$233))=0,NA(),SUMPRODUCT(($C$21:$C$233=$V$21)*IFERROR($H$21:$H$233,0))) -> 1940460.8 | AB21: =IF(SUMPRODUCT(($C$21:$C$233=$V$21)*ISNUMBER($I$21:$I$233))=0,NA(),SUMPRODUCT(($C$21:$C$233=$V$21)*IFERROR($I$21:$I$233,0))) -> 1940461 | AC21: =IF(SUMPRODUCT(($C$21:$C$233=$V$21)*ISNUMBER($J$21:$J$233))=0,NA(),SUMPRODUCT(($C$21:$C$233=$V$21)*IFERROR($J$21:$J$233,0))/SUMPRODUCT(($C$21:$C$233=$V$21)*ISNUMBER($J$21:$J$233))) -> #N/A | AD21: =IF(SUMPRODUCT(($C$21:$C$233=$V$21)*ISNUMBER($K$21:$K$233))=0,NA(),SUMPRODUCT(($C$21:$C$233=$V$21)*IFERROR($K$21:$K$233,0))/SUMPRODUCT(($C$21:$C$233=$V$21)*ISNUMBER($K$21:$K$233))) -> 2.9412375 | AE21: =IF(SUMPRODUCT(($C$21:$C$233=$V$21)*ISNUMBER($L$21:$L$233))=0,NA(),SUMPRODUCT(($C$21:$C$233=$V$21)*IFERROR($L$21:$L$233,0))/SUMPRODUCT(($C$21:$C$233=$V$21)*ISNUMBER($L$21:$L$233))) -> 2.9404444 | AF21: =NA() -> #N/A | AI21: =IFERROR(IFERROR(LOOKUP(2,1/ISNUMBER(W21:W50),V21:V50),NA())+1,NA()) -> 2026 | AJ21: =IFERROR((IFERROR(INDEX(W21:W50,MATCH(AI21-1,V21:V50,0)),NA()))*(1+$B9),NA()) -> 3044913.8 | AK21: =IFERROR((IFERROR(INDEX(X21:X50,MATCH(AI21-1,V21:V50,0)),NA()))*(1+$B10),NA()) -> 2266003.6 | AL21: =IFERROR((IFERROR(INDEX(Y21:Y50,MATCH(AI21-1,V21:V50,0)),NA()))*(1+$B11),NA()) -> 392792.12 | AM21: =IFERROR((IFERROR(INDEX(Z21:Z50,MATCH(AI21-1,V21:V50,0)),NA()))*(1+$B12),NA()) -> 608643.62 | AN21: =IFERROR((IFERROR(INDEX(AA21:AA50,MATCH(AI21-1,V21:V50,0)),NA()))*(1+$B13),NA()) -> 3044913.8 | AO21: =IFERROR((IFERROR(INDEX(AB21:AB50,MATCH(AI21-1,V21:V50,0)),NA()))*(1+$B9)*(1+$B15),NA()) -> 5.2383094e+09 | AP21: =IFERROR((IFERROR(INDEX(AC21:AC50,MATCH(AI21-1,V21:V50,0)),NA()))*(1+$B15),NA()) -> 13449.25 | AQ21: =IFERROR((IFERROR(INDEX(AD21:AD50,MATCH(AI21-1,V21:V50,0)),NA()))*(1+$B16),NA()) -> 1742.3515 | AR21: =IFERROR((IFERROR(INDEX(AE21:AE50,MATCH(AI21-1,V21:V50,0)),NA()))*(1+$B17),NA()) -> 1761.4922 | AS21: =IFERROR(AO21/AQ21,NA()) -> 3006459.6
A22: =IFERROR(IF(ISNUMBER('Real and nominal GDP'!A9),'Real and nominal GDP'!A9,NA()),NA()) -> 38139 | B22: =IFERROR(IF('Real and nominal GDP'!B9="",NA(),'Real and nominal GDP'!B9),NA()) -> 042 | C22: =IFERROR(YEAR(A22),0) -> 2004 | D22: =IFERROR(IF('Real and nominal GDP'!C9="",NA(),IF(ISNUMBER('Real and nominal GDP'!C9),'Real and nominal GDP'!C9,NA())),NA()) -> 470010.07 | E22: =IFERROR(IF('Real and nominal GDP'!D9="",NA(),IF(ISNUMBER('Real and nominal GDP'!D9),'Real and nominal GDP'!D9,NA())),NA()) -> 304361.81 | F22: =IFERROR(IF('Real and nominal GDP'!E9="",NA(),IF(ISNUMBER('Real and nominal GDP'!E9),'Real and nominal GDP'!E9,NA())),NA()) -> 52818.974 | G22: =IFERROR(IF('Real and nominal GDP'!F9="",NA(),IF(ISNUMBER('Real and nominal GDP'!F9),'Real and nominal GDP'!F9,NA())),NA()) -> 76869.591 | H22: =IFERROR(IF('Real and nominal GDP'!G9="",NA(),IF(ISNUMBER('Real and nominal GDP'!G9),'Real and nominal GDP'!G9,NA())),NA()) -> 514395.68 | I22: =IFERROR(IF('Real and nominal GDP'!H9="",NA(),IF(ISNUMBER('Real and nominal GDP'!H9),'Real and nominal GDP'!H9,NA())),NA()) -> 509499 | J22: =IFERROR(IF('Real and nominal GDP'!I9="",NA(),IF(ISNUMBER('Real and nominal GDP'!I9),'Real and nominal GDP'!I9,NA())),NA()) -> #N/A | K22: =IFERROR(IF('Real and nominal GDP'!J9="",NA(),IF(ISNUMBER('Real and nominal GDP'!J9),'Real and nominal GDP'!J9,NA())),NA()) -> 2.9050733 | L22: =IFERROR(IF('Real and nominal GDP'!K9="",NA(),IF(ISNUMBER('Real and nominal GDP'!K9),'Real and nominal GDP'!K9,NA())),NA()) -> 2.9093333 | M22: =NA() -> #N/A | N22: =IFERROR(D22/D21-1,NA()) -> -0.012659661 | O22: =NA() -> #N/A | P22: =NA() -> #N/A | Q22: =NA() -> #N/A | R22: =IFERROR(I22/K22,NA()) -> 175382.49 | S22: =IFERROR(I22/L22,NA()) -> 175125.69 | V22: 2005 | W22: =IF(SUMPRODUCT(($C$21:$C$233=$V$22)*ISNUMBER($D$21:$D$233))=0,NA(),SUMPRODUCT(($C$21:$C$233=$V$22)*IFERROR($D$21:$D$233,0))) -> 2112223.8 | X22: =IF(SUMPRODUCT(($C$21:$C$233=$V$22)*ISNUMBER($E$21:$E$233))=0,NA(),SUMPRODUCT(($C$21:$C$233=$V$22)*IFERROR($E$21:$E$233,0))) -> 1340611.1 | Y22: =IF(SUMPRODUCT(($C$21:$C$233=$V$22)*ISNUMBER($F$21:$F$233))=0,NA(),SUMPRODUCT(($C$21:$C$233=$V$22)*IFERROR($F$21:$F$233,0))) -> 236930.88 | Z22: =IF(SUMPRODUCT(($C$21:$C$233=$V$22)*ISNUMBER($G$21:$G$233))=0,NA(),SUMPRODUCT(($C$21:$C$233=$V$22)*IFERROR($G$21:$G$233,0))) -> 357229.42 | AA22: =IF(SUMPRODUCT(($C$21:$C$233=$V$22)*ISNUMBER($H$21:$H$233))=0,NA(),SUMPRODUCT(($C$21:$C$233=$V$22)*IFERROR($H$21:$H$233,0))) -> 2112223.8 | AB22: =IF(SUMPRODUCT(($C$21:$C$233=$V$22)*ISNUMBER($I$21:$I$233))=0,NA(),SUMPRODUCT(($C$21:$C$233=$V$22)*IFERROR($I$21:$I$233,0))) -> 2330153 | AC22: =IF(SUMPRODUCT(($C$21:$C$233=$V$22)*ISNUMBER($J$21:$J$233))=0,NA(),SUMPRODUCT(($C$21:$C$233=$V$22)*IFERROR($J$21:$J$233,0))/SUMPRODUCT(($C$21:$C$233=$V$22)*ISNUMBER($J$21:$J$233))) -> #N/A | AD22: =IF(SUMPRODUCT(($C$21:$C$233=$V$22)*ISNUMBER($K$21:$K$233))=0,NA(),SUMPRODUCT(($C$21:$C$233=$V$22)*IFERROR($K$21:$K$233,0))/SUMPRODUCT(($C$21:$C$233=$V$22)*ISNUMBER($K$21:$K$233))) -> 2.923495 | AE22: =IF(SUMPRODUCT(($C$21:$C$233=$V$22)*ISNUMBER($L$21:$L$233))=0,NA(),SUMPRODUCT(($C$21:$C$233=$V$22)*IFERROR($L$21:$L$233,0))/SUMPRODUCT(($C$21:$C$233=$V$22)*ISNUMBER($L$21:$L$233))) -> 2.9263333 | AF22: =IFERROR(W22/W21-1,NA()) -> 0.088516599 | AI22: =AI21+1 -> 2027 | AJ22: =IFERROR(AJ21*(1+$C9),NA()) -> 3121036.6 | AK22: =IFERROR(AK21*(1+$C10),NA()) -> 2322653.7 | AL22: =IFERROR(AL21*(1+$C11),NA()) -> 400647.97 | AM22: =IFERROR(AM21*(1+$C12),NA()) -> 632989.37 | AN22: =IFERROR(AN21*(1+$C13),NA()) -> 3121036.6 | AO22: =IFERROR(AO21*(1+$C9)*(1+$C15),NA()) -> 6.9800472e+09 | AP22: =IFERROR(AP21*(1+$C15),NA()) -> 17484.025 | AQ22: =IFERROR(AQ21*(1+$C16),NA()) -> 2265.0569 | AR22: =IFERROR(AR21*(1+$C17),NA()) -> 2201.8652 | AS22: =IFERROR(AO22/AQ22,NA()) -> 3081621.1
A23: =IFERROR(IF(ISNUMBER('Real and nominal GDP'!A10),'Real and nominal GDP'!A10,NA()),NA()) -> 38231 | B23: =IFERROR(IF('Real and nominal GDP'!B10="",NA(),'Real and nominal GDP'!B10),NA()) -> 043 | C23: =IFERROR(YEAR(A23),0) -> 2004 | D23: =IFERROR(IF('Real and nominal GDP'!C10="",NA(),IF(ISNUMBER('Real and nominal GDP'!C10),'Real and nominal GDP'!C10,NA())),NA()) -> 493895.12 | E23: =IFERROR(IF('Real and nominal GDP'!D10="",NA(),IF(ISNUMBER('Real and nominal GDP'!D10),'Real and nominal GDP'!D10,NA())),NA()) -> 316912.03 | F23: =IFERROR(IF('Real and nominal GDP'!E10="",NA(),IF(ISNUMBER('Real and nominal GDP'!E10),'Real and nominal GDP'!E10,NA())),NA()) -> 54483.809 | G23: =IFERROR(IF('Real and nominal GDP'!F10="",NA(),IF(ISNUMBER('Real and nominal GDP'!F10),'Real and nominal GDP'!F10,NA())),NA()) -> 77809.682 | H23: =IFERROR(IF('Real and nominal GDP'!G10="",NA(),IF(ISNUMBER('Real and nominal GDP'!G10),'Real and nominal GDP'!G10,NA())),NA()) -> 481151.98 | I23: =IFERROR(IF('Real and nominal GDP'!H10="",NA(),IF(ISNUMBER('Real and nominal GDP'!H10),'Real and nominal GDP'!H10,NA())),NA()) -> 488462 | J23: =IFERROR(IF('Real and nominal GDP'!I10="",NA(),IF(ISNUMBER('Real and nominal GDP'!I10),'Real and nominal GDP'!I10,NA())),NA()) -> #N/A | K23: =IFERROR(IF('Real and nominal GDP'!J10="",NA(),IF(ISNUMBER('Real and nominal GDP'!J10),'Real and nominal GDP'!J10,NA())),NA()) -> 2.9879933 | L23: =IFERROR(IF('Real and nominal GDP'!K10="",NA(),IF(ISNUMBER('Real and nominal GDP'!K10),'Real and nominal GDP'!K10,NA())),NA()) -> 2.9956667 | M23: =NA() -> #N/A | N23: =IFERROR(D23/D22-1,NA()) -> 0.050818178 | O23: =NA() -> #N/A | P23: =NA() -> #N/A | Q23: =NA() -> #N/A | R23: =IFERROR(I23/K23,NA()) -> 163474.93 | S23: =IFERROR(I23/L23,NA()) -> 163056.19 | V23: 2006 | W23: =IF(SUMPRODUCT(($C$21:$C$233=$V$23)*ISNUMBER($D$21:$D$233))=0,NA(),SUMPRODUCT(($C$21:$C$233=$V$23)*IFERROR($D$21:$D$233,0))) -> 2282197.6 | X23: =IF(SUMPRODUCT(($C$21:$C$233=$V$23)*ISNUMBER($E$21:$E$233))=0,NA(),SUMPRODUCT(($C$21:$C$233=$V$23)*IFERROR($E$21:$E$233,0))) -> 1487491.6 | Y23: =IF(SUMPRODUCT(($C$21:$C$233=$V$23)*ISNUMBER($F$21:$F$233))=0,NA(),SUMPRODUCT(($C$21:$C$233=$V$23)*IFERROR($F$21:$F$233,0))) -> 245750.69 | Z23: =IF(SUMPRODUCT(($C$21:$C$233=$V$23)*ISNUMBER($G$21:$G$233))=0,NA(),SUMPRODUCT(($C$21:$C$233=$V$23)*IFERROR($G$21:$G$233,0))) -> 408930.58 | AA23: =IF(SUMPRODUCT(($C$21:$C$233=$V$23)*ISNUMBER($H$21:$H$233))=0,NA(),SUMPRODUCT(($C$21:$C$233=$V$23)*IFERROR($H$21:$H$233,0))) -> 2282197.6 | AB23: =IF(SUMPRODUCT(($C$21:$C$233=$V$23)*ISNUMBER($I$21:$I$233))=0,NA(),SUMPRODUCT(($C$21:$C$233=$V$23)*IFERROR($I$21:$I$233,0))) -> 2863616 | AC23: =IF(SUMPRODUCT(($C$21:$C$233=$V$23)*ISNUMBER($J$21:$J$233))=0,NA(),SUMPRODUCT(($C$21:$C$233=$V$23)*IFERROR($J$21:$J$233,0))/SUMPRODUCT(($C$21:$C$233=$V$23)*ISNUMBER($J$21:$J$233))) -> #N/A | AD23: =IF(SUMPRODUCT(($C$21:$C$233=$V$23)*ISNUMBER($K$21:$K$233))=0,NA(),SUMPRODUCT(($C$21:$C$233=$V$23)*IFERROR($K$21:$K$233,0))/SUMPRODUCT(($C$21:$C$233=$V$23)*ISNUMBER($K$21:$K$233))) -> 3.0743825 | AE23: =IF(SUMPRODUCT(($C$21:$C$233=$V$23)*ISNUMBER($L$21:$L$233))=0,NA(),SUMPRODUCT(($C$21:$C$233=$V$23)*IFERROR($L$21:$L$233,0))/SUMPRODUCT(($C$21:$C$233=$V$23)*ISNUMBER($L$21:$L$233))) -> 3.091 | AF23: =IFERROR(W23/W22-1,NA()) -> 0.080471515
A24: =IFERROR(IF(ISNUMBER('Real and nominal GDP'!A11),'Real and nominal GDP'!A11,NA()),NA()) -> 38322 | B24: =IFERROR(IF('Real and nominal GDP'!B11="",NA(),'Real and nominal GDP'!B11),NA()) -> 044 | C24: =IFERROR(YEAR(A24),0) -> 2004 | D24: =IFERROR(IF('Real and nominal GDP'!C11="",NA(),IF(ISNUMBER('Real and nominal GDP'!C11),'Real and nominal GDP'!C11,NA())),NA()) -> 500519.07 | E24: =IFERROR(IF('Real and nominal GDP'!D11="",NA(),IF(ISNUMBER('Real and nominal GDP'!D11),'Real and nominal GDP'!D11,NA())),NA()) -> 324272.59 | F24: =IFERROR(IF('Real and nominal GDP'!E11="",NA(),IF(ISNUMBER('Real and nominal GDP'!E11),'Real and nominal GDP'!E11,NA())),NA()) -> 55704.211 | G24: =IFERROR(IF('Real and nominal GDP'!F11="",NA(),IF(ISNUMBER('Real and nominal GDP'!F11),'Real and nominal GDP'!F11,NA())),NA()) -> 79234.809 | H24: =IFERROR(IF('Real and nominal GDP'!G11="",NA(),IF(ISNUMBER('Real and nominal GDP'!G11),'Real and nominal GDP'!G11,NA())),NA()) -> 484543.68 | I24: =IFERROR(IF('Real and nominal GDP'!H11="",NA(),IF(ISNUMBER('Real and nominal GDP'!H11),'Real and nominal GDP'!H11,NA())),NA()) -> 503304 | J24: =IFERROR(IF('Real and nominal GDP'!I11="",NA(),IF(ISNUMBER('Real and nominal GDP'!I11),'Real and nominal GDP'!I11,NA())),NA()) -> #N/A | K24: =IFERROR(IF('Real and nominal GDP'!J11="",NA(),IF(ISNUMBER('Real and nominal GDP'!J11),'Real and nominal GDP'!J11,NA())),NA()) -> 2.9646167 | L24: =IFERROR(IF('Real and nominal GDP'!K11="",NA(),IF(ISNUMBER('Real and nominal GDP'!K11),'Real and nominal GDP'!K11,NA())),NA()) -> #N/A | M24: =NA() -> #N/A | N24: =IFERROR(D24/D23-1,NA()) -> 0.013411645 | O24: =NA() -> #N/A | P24: =IF(COUNT(D21:D24)=4,SUM(D21:D24),NA()) -> 1940460.8 | Q24: =IF(COUNT(I21:I24)=4,SUM(I21:I24),NA()) -> 1940461 | R24: =IFERROR(I24/K24,NA()) -> 169770.35 | S24: =IFERROR(I24/L24,NA()) -> #N/A | V24: 2007 | W24: =IF(SUMPRODUCT(($C$21:$C$233=$V$24)*ISNUMBER($D$21:$D$233))=0,NA(),SUMPRODUCT(($C$21:$C$233=$V$24)*IFERROR($D$21:$D$233,0))) -> 2487770 | X24: =IF(SUMPRODUCT(($C$21:$C$233=$V$24)*ISNUMBER($E$21:$E$233))=0,NA(),SUMPRODUCT(($C$21:$C$233=$V$24)*IFERROR($E$21:$E$233,0))) -> 1626406.2 | Y24: =IF(SUMPRODUCT(($C$21:$C$233=$V$24)*ISNUMBER($F$21:$F$233))=0,NA(),SUMPRODUCT(($C$21:$C$233=$V$24)*IFERROR($F$21:$F$233,0))) -> 264992.42 | Z24: =IF(SUMPRODUCT(($C$21:$C$233=$V$24)*ISNUMBER($G$21:$G$233))=0,NA(),SUMPRODUCT(($C$21:$C$233=$V$24)*IFERROR($G$21:$G$233,0))) -> 492569.96 | AA24: =IF(SUMPRODUCT(($C$21:$C$233=$V$24)*ISNUMBER($H$21:$H$233))=0,NA(),SUMPRODUCT(($C$21:$C$233=$V$24)*IFERROR($H$21:$H$233,0))) -> 2487770 | AB24: =IF(SUMPRODUCT(($C$21:$C$233=$V$24)*ISNUMBER($I$21:$I$233))=0,NA(),SUMPRODUCT(($C$21:$C$233=$V$24)*IFERROR($I$21:$I$233,0))) -> 3587921 | AC24: =IF(SUMPRODUCT(($C$21:$C$233=$V$24)*ISNUMBER($J$21:$J$233))=0,NA(),SUMPRODUCT(($C$21:$C$233=$V$24)*IFERROR($J$21:$J$233,0))/SUMPRODUCT(($C$21:$C$233=$V$24)*ISNUMBER($J$21:$J$233))) -> #N/A | AD24: =IF(SUMPRODUCT(($C$21:$C$233=$V$24)*ISNUMBER($K$21:$K$233))=0,NA(),SUMPRODUCT(($C$21:$C$233=$V$24)*IFERROR($K$21:$K$233,0))/SUMPRODUCT(($C$21:$C$233=$V$24)*ISNUMBER($K$21:$K$233))) -> 3.1156767 | AE24: =IF(SUMPRODUCT(($C$21:$C$233=$V$24)*ISNUMBER($L$21:$L$233))=0,NA(),SUMPRODUCT(($C$21:$C$233=$V$24)*IFERROR($L$21:$L$233,0))/SUMPRODUCT(($C$21:$C$233=$V$24)*ISNUMBER($L$21:$L$233))) -> 3.1453333 | AF24: =IFERROR(W24/W23-1,NA()) -> 0.090076509
A25: =IFERROR(IF(ISNUMBER('Real and nominal GDP'!A12),'Real and nominal GDP'!A12,NA()),NA()) -> 38412 | B25: =IFERROR(IF('Real and nominal GDP'!B12="",NA(),'Real and nominal GDP'!B12),NA()) -> 051 | C25: =IFERROR(YEAR(A25),0) -> 2005 | D25: =IFERROR(IF('Real and nominal GDP'!C12="",NA(),IF(ISNUMBER('Real and nominal GDP'!C12),'Real and nominal GDP'!C12,NA())),NA()) -> 514918.46 | E25: =IFERROR(IF('Real and nominal GDP'!D12="",NA(),IF(ISNUMBER('Real and nominal GDP'!D12),'Real and nominal GDP'!D12,NA())),NA()) -> 318967.71 | F25: =IFERROR(IF('Real and nominal GDP'!E12="",NA(),IF(ISNUMBER('Real and nominal GDP'!E12),'Real and nominal GDP'!E12,NA())),NA()) -> 57528.588 | G25: =IFERROR(IF('Real and nominal GDP'!F12="",NA(),IF(ISNUMBER('Real and nominal GDP'!F12),'Real and nominal GDP'!F12,NA())),NA()) -> 85178.716 | H25: =IFERROR(IF('Real and nominal GDP'!G12="",NA(),IF(ISNUMBER('Real and nominal GDP'!G12),'Real and nominal GDP'!G12,NA())),NA()) -> 493602.53 | I25: =IFERROR(IF('Real and nominal GDP'!H12="",NA(),IF(ISNUMBER('Real and nominal GDP'!H12),'Real and nominal GDP'!H12,NA())),NA()) -> 510703 | J25: =IFERROR(IF('Real and nominal GDP'!I12="",NA(),IF(ISNUMBER('Real and nominal GDP'!I12),'Real and nominal GDP'!I12,NA())),NA()) -> #N/A | K25: =IFERROR(IF('Real and nominal GDP'!J12="",NA(),IF(ISNUMBER('Real and nominal GDP'!J12),'Real and nominal GDP'!J12,NA())),NA()) -> 2.9297667 | L25: =IFERROR(IF('Real and nominal GDP'!K12="",NA(),IF(ISNUMBER('Real and nominal GDP'!K12),'Real and nominal GDP'!K12,NA())),NA()) -> 2.9343333 | M25: =IFERROR(D25/D21-1,NA()) -> 0.081678463 | N25: =IFERROR(D25/D24-1,NA()) -> 0.028768918 | O25: =IFERROR(I25/I21-1,NA()) -> 0.16281341 | P25: =IF(COUNT(D22:D25)=4,SUM(D22:D25),NA()) -> 1979342.7 | Q25: =IF(COUNT(I22:I25)=4,SUM(I22:I25),NA()) -> 2011968 | R25: =IFERROR(I25/K25,NA()) -> 174315.25 | S25: =IFERROR(I25/L25,NA()) -> 174043.96 | V25: 2008 | W25: =IF(SUMPRODUCT(($C$21:$C$233=$V$25)*ISNUMBER($D$21:$D$233))=0,NA(),SUMPRODUCT(($C$21:$C$233=$V$25)*IFERROR($D$21:$D$233,0))) -> 2588704.6 | X25: =IF(SUMPRODUCT(($C$21:$C$233=$V$25)*ISNUMBER($E$21:$E$233))=0,NA(),SUMPRODUCT(($C$21:$C$233=$V$25)*IFERROR($E$21:$E$233,0))) -> 1744233.6 | Y25: =IF(SUMPRODUCT(($C$21:$C$233=$V$25)*ISNUMBER($F$21:$F$233))=0,NA(),SUMPRODUCT(($C$21:$C$233=$V$25)*IFERROR($F$21:$F$233,0))) -> 278282 | Z25: =IF(SUMPRODUCT(($C$21:$C$233=$V$25)*ISNUMBER($G$21:$G$233))=0,NA(),SUMPRODUCT(($C$21:$C$233=$V$25)*IFERROR($G$21:$G$233,0))) -> 535401.06 | AA25: =IF(SUMPRODUCT(($C$21:$C$233=$V$25)*ISNUMBER($H$21:$H$233))=0,NA(),SUMPRODUCT(($C$21:$C$233=$V$25)*IFERROR($H$21:$H$233,0))) -> 2588704.6 | AB25: =IF(SUMPRODUCT(($C$21:$C$233=$V$25)*ISNUMBER($I$21:$I$233))=0,NA(),SUMPRODUCT(($C$21:$C$233=$V$25)*IFERROR($I$21:$I$233,0))) -> 4598584 | AC25: =IF(SUMPRODUCT(($C$21:$C$233=$V$25)*ISNUMBER($J$21:$J$233))=0,NA(),SUMPRODUCT(($C$21:$C$233=$V$25)*IFERROR($J$21:$J$233,0))/SUMPRODUCT(($C$21:$C$233=$V$25)*ISNUMBER($J$21:$J$233))) -> #N/A | AD25: =IF(SUMPRODUCT(($C$21:$C$233=$V$25)*ISNUMBER($K$21:$K$233))=0,NA(),SUMPRODUCT(($C$21:$C$233=$V$25)*IFERROR($K$21:$K$233,0))/SUMPRODUCT(($C$21:$C$233=$V$25)*ISNUMBER($K$21:$K$233))) -> 3.1634033 | AE25: =IF(SUMPRODUCT(($C$21:$C$233=$V$25)*ISNUMBER($L$21:$L$233))=0,NA(),SUMPRODUCT(($C$21:$C$233=$V$25)*IFERROR($L$21:$L$233,0))/SUMPRODUCT(($C$21:$C$233=$V$25)*ISNUMBER($L$21:$L$233))) -> 3.2099167 | AF25: =IFERROR(W25/W24-1,NA()) -> 0.040572331
A26: =IFERROR(IF(ISNUMBER('Real and nominal GDP'!A13),'Real and nominal GDP'!A13,NA()),NA()) -> 38504 | B26: =IFERROR(IF('Real and nominal GDP'!B13="",NA(),'Real and nominal GDP'!B13),NA()) -> 052 | C26: =IFERROR(YEAR(A26),0) -> 2005 | D26: =IFERROR(IF('Real and nominal GDP'!C13="",NA(),IF(ISNUMBER('Real and nominal GDP'!C13),'Real and nominal GDP'!C13,NA())),NA()) -> 527084.2 | E26: =IFERROR(IF('Real and nominal GDP'!D13="",NA(),IF(ISNUMBER('Real and nominal GDP'!D13),'Real and nominal GDP'!D13,NA())),NA()) -> 346690.41 | F26: =IFERROR(IF('Real and nominal GDP'!E13="",NA(),IF(ISNUMBER('Real and nominal GDP'!E13),'Real and nominal GDP'!E13,NA())),NA()) -> 58964.326 | G26: =IFERROR(IF('Real and nominal GDP'!F13="",NA(),IF(ISNUMBER('Real and nominal GDP'!F13),'Real and nominal GDP'!F13,NA())),NA()) -> 87994.464 | H26: =IFERROR(IF('Real and nominal GDP'!G13="",NA(),IF(ISNUMBER('Real and nominal GDP'!G13),'Real and nominal GDP'!G13,NA())),NA()) -> 581668.25 | I26: =IFERROR(IF('Real and nominal GDP'!H13="",NA(),IF(ISNUMBER('Real and nominal GDP'!H13),'Real and nominal GDP'!H13,NA())),NA()) -> 605772 | J26: =IFERROR(IF('Real and nominal GDP'!I13="",NA(),IF(ISNUMBER('Real and nominal GDP'!I13),'Real and nominal GDP'!I13,NA())),NA()) -> #N/A | K26: =IFERROR(IF('Real and nominal GDP'!J13="",NA(),IF(ISNUMBER('Real and nominal GDP'!J13),'Real and nominal GDP'!J13,NA())),NA()) -> 2.89173 | L26: =IFERROR(IF('Real and nominal GDP'!K13="",NA(),IF(ISNUMBER('Real and nominal GDP'!K13),'Real and nominal GDP'!K13,NA())),NA()) -> 2.8986667 | M26: =IFERROR(D26/D22-1,NA()) -> 0.12143172 | N26: =IFERROR(D26/D25-1,NA()) -> 0.023626535 | O26: =IFERROR(I26/I22-1,NA()) -> 0.18895621 | P26: =IF(COUNT(D23:D26)=4,SUM(D23:D26),NA()) -> 2036416.8 | Q26: =IF(COUNT(I23:I26)=4,SUM(I23:I26),NA()) -> 2108241 | R26: =IFERROR(I26/K26,NA()) -> 209484.29 | S26: =IFERROR(I26/L26,NA()) -> 208982.98 | V26: 2009 | W26: =IF(SUMPRODUCT(($C$21:$C$233=$V$26)*ISNUMBER($D$21:$D$233))=0,NA(),SUMPRODUCT(($C$21:$C$233=$V$26)*IFERROR($D$21:$D$233,0))) -> 2435491.5 | X26: =IF(SUMPRODUCT(($C$21:$C$233=$V$26)*ISNUMBER($E$21:$E$233))=0,NA(),SUMPRODUCT(($C$21:$C$233=$V$26)*IFERROR($E$21:$E$233,0))) -> 1650085.9 | Y26: =IF(SUMPRODUCT(($C$21:$C$233=$V$26)*ISNUMBER($F$21:$F$233))=0,NA(),SUMPRODUCT(($C$21:$C$233=$V$26)*IFERROR($F$21:$F$233,0))) -> 293961.11 | Z26: =IF(SUMPRODUCT(($C$21:$C$233=$V$26)*ISNUMBER($G$21:$G$233))=0,NA(),SUMPRODUCT(($C$21:$C$233=$V$26)*IFERROR($G$21:$G$233,0))) -> 414545.77 | AA26: =IF(SUMPRODUCT(($C$21:$C$233=$V$26)*ISNUMBER($H$21:$H$233))=0,NA(),SUMPRODUCT(($C$21:$C$233=$V$26)*IFERROR($H$21:$H$233,0))) -> 2435491.5 | AB26: =IF(SUMPRODUCT(($C$21:$C$233=$V$26)*ISNUMBER($I$21:$I$233))=0,NA(),SUMPRODUCT(($C$21:$C$233=$V$26)*IFERROR($I$21:$I$233,0))) -> 4991717 | AC26: =IF(SUMPRODUCT(($C$21:$C$233=$V$26)*ISNUMBER($J$21:$J$233))=0,NA(),SUMPRODUCT(($C$21:$C$233=$V$26)*IFERROR($J$21:$J$233,0))/SUMPRODUCT(($C$21:$C$233=$V$26)*ISNUMBER($J$21:$J$233))) -> #N/A | AD26: =IF(SUMPRODUCT(($C$21:$C$233=$V$26)*ISNUMBER($K$21:$K$233))=0,NA(),SUMPRODUCT(($C$21:$C$233=$V$26)*IFERROR($K$21:$K$233,0))/SUMPRODUCT(($C$21:$C$233=$V$26)*ISNUMBER($K$21:$K$233))) -> 3.7296117 | AE26: =IF(SUMPRODUCT(($C$21:$C$233=$V$26)*ISNUMBER($L$21:$L$233))=0,NA(),SUMPRODUCT(($C$21:$C$233=$V$26)*IFERROR($L$21:$L$233,0))/SUMPRODUCT(($C$21:$C$233=$V$26)*ISNUMBER($L$21:$L$233))) -> 3.7694167 | AF26: =IFERROR(W26/W25-1,NA()) -> -0.059185251
A27: =IFERROR(IF(ISNUMBER('Real and nominal GDP'!A14),'Real and nominal GDP'!A14,NA()),NA()) -> 38596 | B27: =IFERROR(IF('Real and nominal GDP'!B14="",NA(),'Real and nominal GDP'!B14),NA()) -> 053 | C27: =IFERROR(YEAR(A27),0) -> 2005 | D27: =IFERROR(IF('Real and nominal GDP'!C14="",NA(),IF(ISNUMBER('Real and nominal GDP'!C14),'Real and nominal GDP'!C14,NA())),NA()) -> 530101.96 | E27: =IFERROR(IF('Real and nominal GDP'!D14="",NA(),IF(ISNUMBER('Real and nominal GDP'!D14),'Real and nominal GDP'!D14,NA())),NA()) -> 331326.97 | F27: =IFERROR(IF('Real and nominal GDP'!E14="",NA(),IF(ISNUMBER('Real and nominal GDP'!E14),'Real and nominal GDP'!E14,NA())),NA()) -> 59826.06 | G27: =IFERROR(IF('Real and nominal GDP'!F14="",NA(),IF(ISNUMBER('Real and nominal GDP'!F14),'Real and nominal GDP'!F14,NA())),NA()) -> 88235.413 | H27: =IFERROR(IF('Real and nominal GDP'!G14="",NA(),IF(ISNUMBER('Real and nominal GDP'!G14),'Real and nominal GDP'!G14,NA())),NA()) -> 514697.79 | I27: =IFERROR(IF('Real and nominal GDP'!H14="",NA(),IF(ISNUMBER('Real and nominal GDP'!H14),'Real and nominal GDP'!H14,NA())),NA()) -> 590220 | J27: =IFERROR(IF('Real and nominal GDP'!I14="",NA(),IF(ISNUMBER('Real and nominal GDP'!I14),'Real and nominal GDP'!I14,NA())),NA()) -> #N/A | K27: =IFERROR(IF('Real and nominal GDP'!J14="",NA(),IF(ISNUMBER('Real and nominal GDP'!J14),'Real and nominal GDP'!J14,NA())),NA()) -> 2.8896033 | L27: =IFERROR(IF('Real and nominal GDP'!K14="",NA(),IF(ISNUMBER('Real and nominal GDP'!K14),'Real and nominal GDP'!K14,NA())),NA()) -> 2.8846667 | M27: =IFERROR(D27/D23-1,NA()) -> 0.073308756 | N27: =IFERROR(D27/D26-1,NA()) -> 0.0057253851 | O27: =IFERROR(I27/I23-1,NA()) -> 0.20832327 | P27: =IF(COUNT(D24:D27)=4,SUM(D24:D27),NA()) -> 2072623.7 | Q27: =IF(COUNT(I24:I27)=4,SUM(I24:I27),NA()) -> 2209999 | R27: =IFERROR(I27/K27,NA()) -> 204256.41 | S27: =IFERROR(I27/L27,NA()) -> 204605.96 | V27: 2010 | W27: =IF(SUMPRODUCT(($C$21:$C$233=$V$27)*ISNUMBER($D$21:$D$233))=0,NA(),SUMPRODUCT(($C$21:$C$233=$V$27)*IFERROR($D$21:$D$233,0))) -> 2682094.7 | X27: =IF(SUMPRODUCT(($C$21:$C$233=$V$27)*ISNUMBER($E$21:$E$233))=0,NA(),SUMPRODUCT(($C$21:$C$233=$V$27)*IFERROR($E$21:$E$233,0))) -> 1834700.7 | Y27: =IF(SUMPRODUCT(($C$21:$C$233=$V$27)*ISNUMBER($F$21:$F$233))=0,NA(),SUMPRODUCT(($C$21:$C$233=$V$27)*IFERROR($F$21:$F$233,0))) -> 309988.39 | Z27: =IF(SUMPRODUCT(($C$21:$C$233=$V$27)*ISNUMBER($G$21:$G$233))=0,NA(),SUMPRODUCT(($C$21:$C$233=$V$27)*IFERROR($G$21:$G$233,0))) -> 523383.03 | AA27: =IF(SUMPRODUCT(($C$21:$C$233=$V$27)*ISNUMBER($H$21:$H$233))=0,NA(),SUMPRODUCT(($C$21:$C$233=$V$27)*IFERROR($H$21:$H$233,0))) -> 2682094.7 | AB27: =IF(SUMPRODUCT(($C$21:$C$233=$V$27)*ISNUMBER($I$21:$I$233))=0,NA(),SUMPRODUCT(($C$21:$C$233=$V$27)*IFERROR($I$21:$I$233,0))) -> 6646884 | AC27: =IF(SUMPRODUCT(($C$21:$C$233=$V$27)*ISNUMBER($J$21:$J$233))=0,NA(),SUMPRODUCT(($C$21:$C$233=$V$27)*IFERROR($J$21:$J$233,0))/SUMPRODUCT(($C$21:$C$233=$V$27)*ISNUMBER($J$21:$J$233))) -> #N/A | AD27: =IF(SUMPRODUCT(($C$21:$C$233=$V$27)*ISNUMBER($K$21:$K$233))=0,NA(),SUMPRODUCT(($C$21:$C$233=$V$27)*IFERROR($K$21:$K$233,0))/SUMPRODUCT(($C$21:$C$233=$V$27)*ISNUMBER($K$21:$K$233))) -> 3.9123375 | AE27: =IF(SUMPRODUCT(($C$21:$C$233=$V$27)*ISNUMBER($L$21:$L$233))=0,NA(),SUMPRODUCT(($C$21:$C$233=$V$27)*IFERROR($L$21:$L$233,0))/SUMPRODUCT(($C$21:$C$233=$V$27)*ISNUMBER($L$21:$L$233))) -> 3.975 | AF27: =IFERROR(W27/W26-1,NA()) -> 0.10125398
A28: =IFERROR(IF(ISNUMBER('Real and nominal GDP'!A15),'Real and nominal GDP'!A15,NA()),NA()) -> 38687 | B28: =IFERROR(IF('Real and nominal GDP'!B15="",NA(),'Real and nominal GDP'!B15),NA()) -> 054 | C28: =IFERROR(YEAR(A28),0) -> 2005 | D28: =IFERROR(IF('Real and nominal GDP'!C15="",NA(),IF(ISNUMBER('Real and nominal GDP'!C15),'Real and nominal GDP'!C15,NA())),NA()) -> 540119.16 | E28: =IFERROR(IF('Real and nominal GDP'!D15="",NA(),IF(ISNUMBER('Real and nominal GDP'!D15),'Real and nominal GDP'!D15,NA())),NA()) -> 343626.04 | F28: =IFERROR(IF('Real and nominal GDP'!E15="",NA(),IF(ISNUMBER('Real and nominal GDP'!E15),'Real and nominal GDP'!E15,NA())),NA()) -> 60611.905 | G28: =IFERROR(IF('Real and nominal GDP'!F15="",NA(),IF(ISNUMBER('Real and nominal GDP'!F15),'Real and nominal GDP'!F15,NA())),NA()) -> 95820.827 | H28: =IFERROR(IF('Real and nominal GDP'!G15="",NA(),IF(ISNUMBER('Real and nominal GDP'!G15),'Real and nominal GDP'!G15,NA())),NA()) -> 522255.2 | I28: =IFERROR(IF('Real and nominal GDP'!H15="",NA(),IF(ISNUMBER('Real and nominal GDP'!H15),'Real and nominal GDP'!H15,NA())),NA()) -> 623458 | J28: =IFERROR(IF('Real and nominal GDP'!I15="",NA(),IF(ISNUMBER('Real and nominal GDP'!I15),'Real and nominal GDP'!I15,NA())),NA()) -> #N/A | K28: =IFERROR(IF('Real and nominal GDP'!J15="",NA(),IF(ISNUMBER('Real and nominal GDP'!J15),'Real and nominal GDP'!J15,NA())),NA()) -> 2.98288 | L28: =IFERROR(IF('Real and nominal GDP'!K15="",NA(),IF(ISNUMBER('Real and nominal GDP'!K15),'Real and nominal GDP'!K15,NA())),NA()) -> 2.9876667 | M28: =IFERROR(D28/D24-1,NA()) -> 0.079118041 | N28: =IFERROR(D28/D27-1,NA()) -> 0.018896736 | O28: =IFERROR(I28/I24-1,NA()) -> 0.23873047 | P28: =IF(COUNT(D25:D28)=4,SUM(D25:D28),NA()) -> 2112223.8 | Q28: =IF(COUNT(I25:I28)=4,SUM(I25:I28),NA()) -> 2330153 | R28: =IFERROR(I28/K28,NA()) -> 209012.1 | S28: =IFERROR(I28/L28,NA()) -> 208677.23 | V28: 2011 | W28: =IF(SUMPRODUCT(($C$21:$C$233=$V$28)*ISNUMBER($D$21:$D$233))=0,NA(),SUMPRODUCT(($C$21:$C$233=$V$28)*IFERROR($D$21:$D$233,0))) -> 2843126.4 | X28: =IF(SUMPRODUCT(($C$21:$C$233=$V$28)*ISNUMBER($E$21:$E$233))=0,NA(),SUMPRODUCT(($C$21:$C$233=$V$28)*IFERROR($E$21:$E$233,0))) -> 2006588.6 | Y28: =IF(SUMPRODUCT(($C$21:$C$233=$V$28)*ISNUMBER($F$21:$F$233))=0,NA(),SUMPRODUCT(($C$21:$C$233=$V$28)*IFERROR($F$21:$F$233,0))) -> 324139.08 | Z28: =IF(SUMPRODUCT(($C$21:$C$233=$V$28)*ISNUMBER($G$21:$G$233))=0,NA(),SUMPRODUCT(($C$21:$C$233=$V$28)*IFERROR($G$21:$G$233,0))) -> 614336.34 | AA28: =IF(SUMPRODUCT(($C$21:$C$233=$V$28)*ISNUMBER($H$21:$H$233))=0,NA(),SUMPRODUCT(($C$21:$C$233=$V$28)*IFERROR($H$21:$H$233,0))) -> 2843126.4 | AB28: =IF(SUMPRODUCT(($C$21:$C$233=$V$28)*ISNUMBER($I$21:$I$233))=0,NA(),SUMPRODUCT(($C$21:$C$233=$V$28)*IFERROR($I$21:$I$233,0))) -> 8716096 | AC28: =IF(SUMPRODUCT(($C$21:$C$233=$V$28)*ISNUMBER($J$21:$J$233))=0,NA(),SUMPRODUCT(($C$21:$C$233=$V$28)*IFERROR($J$21:$J$233,0))/SUMPRODUCT(($C$21:$C$233=$V$28)*ISNUMBER($J$21:$J$233))) -> #N/A | AD28: =IF(SUMPRODUCT(($C$21:$C$233=$V$28)*ISNUMBER($K$21:$K$233))=0,NA(),SUMPRODUCT(($C$21:$C$233=$V$28)*IFERROR($K$21:$K$233,0))/SUMPRODUCT(($C$21:$C$233=$V$28)*ISNUMBER($K$21:$K$233))) -> 4.1300142 | AE28: =IF(SUMPRODUCT(($C$21:$C$233=$V$28)*ISNUMBER($L$21:$L$233))=0,NA(),SUMPRODUCT(($C$21:$C$233=$V$28)*IFERROR($L$21:$L$233,0))/SUMPRODUCT(($C$21:$C$233=$V$28)*ISNUMBER($L$21:$L$233))) -> 4.3434167 | AF28: =IFERROR(W28/W27-1,NA()) -> 0.060039517
A29: =IFERROR(IF(ISNUMBER('Real and nominal GDP'!A16),'Real and nominal GDP'!A16,NA()),NA()) -> 38777 | B29: =IFERROR(IF('Real and nominal GDP'!B16="",NA(),'Real and nominal GDP'!B16),NA()) -> 061 | C29: =IFERROR(YEAR(A29),0) -> 2006 | D29: =IFERROR(IF('Real and nominal GDP'!C16="",NA(),IF(ISNUMBER('Real and nominal GDP'!C16),'Real and nominal GDP'!C16,NA())),NA()) -> 554455.77 | E29: =IFERROR(IF('Real and nominal GDP'!D16="",NA(),IF(ISNUMBER('Real and nominal GDP'!D16),'Real and nominal GDP'!D16,NA())),NA()) -> 353511.32 | F29: =IFERROR(IF('Real and nominal GDP'!E16="",NA(),IF(ISNUMBER('Real and nominal GDP'!E16),'Real and nominal GDP'!E16,NA())),NA()) -> 60524.269 | G29: =IFERROR(IF('Real and nominal GDP'!F16="",NA(),IF(ISNUMBER('Real and nominal GDP'!F16),'Real and nominal GDP'!F16,NA())),NA()) -> 97450.782 | H29: =IFERROR(IF('Real and nominal GDP'!G16="",NA(),IF(ISNUMBER('Real and nominal GDP'!G16),'Real and nominal GDP'!G16,NA())),NA()) -> 532348.21 | I29: =IFERROR(IF('Real and nominal GDP'!H16="",NA(),IF(ISNUMBER('Real and nominal GDP'!H16),'Real and nominal GDP'!H16,NA())),NA()) -> 643562 | J29: =IFERROR(IF('Real and nominal GDP'!I16="",NA(),IF(ISNUMBER('Real and nominal GDP'!I16),'Real and nominal GDP'!I16,NA())),NA()) -> #N/A | K29: =IFERROR(IF('Real and nominal GDP'!J16="",NA(),IF(ISNUMBER('Real and nominal GDP'!J16),'Real and nominal GDP'!J16,NA())),NA()) -> 3.0649333 | L29: =IFERROR(IF('Real and nominal GDP'!K16="",NA(),IF(ISNUMBER('Real and nominal GDP'!K16),'Real and nominal GDP'!K16,NA())),NA()) -> 3.0796667 | M29: =IFERROR(D29/D25-1,NA()) -> 0.076783639 | N29: =IFERROR(D29/D28-1,NA()) -> 0.026543434 | O29: =IFERROR(I29/I25-1,NA()) -> 0.26014925 | P29: =IF(COUNT(D26:D29)=4,SUM(D26:D29),NA()) -> 2151761.1 | Q29: =IF(COUNT(I26:I29)=4,SUM(I26:I29),NA()) -> 2463012 | R29: =IFERROR(I29/K29,NA()) -> 209975.86 | S29: =IFERROR(I29/L29,NA()) -> 208971.32 | V29: 2012 | W29: =IF(SUMPRODUCT(($C$21:$C$233=$V$29)*ISNUMBER($D$21:$D$233))=0,NA(),SUMPRODUCT(($C$21:$C$233=$V$29)*IFERROR($D$21:$D$233,0))) -> 2813944 | X29: =IF(SUMPRODUCT(($C$21:$C$233=$V$29)*ISNUMBER($E$21:$E$233))=0,NA(),SUMPRODUCT(($C$21:$C$233=$V$29)*IFERROR($E$21:$E$233,0))) -> 2028867.4 | Y29: =IF(SUMPRODUCT(($C$21:$C$233=$V$29)*ISNUMBER($F$21:$F$233))=0,NA(),SUMPRODUCT(($C$21:$C$233=$V$29)*IFERROR($F$21:$F$233,0))) -> 333893.38 | Z29: =IF(SUMPRODUCT(($C$21:$C$233=$V$29)*ISNUMBER($G$21:$G$233))=0,NA(),SUMPRODUCT(($C$21:$C$233=$V$29)*IFERROR($G$21:$G$233,0))) -> 570870.81 | AA29: =IF(SUMPRODUCT(($C$21:$C$233=$V$29)*ISNUMBER($H$21:$H$233))=0,NA(),SUMPRODUCT(($C$21:$C$233=$V$29)*IFERROR($H$21:$H$233,0))) -> 2813944 | AB29: =IF(SUMPRODUCT(($C$21:$C$233=$V$29)*ISNUMBER($I$21:$I$233))=0,NA(),SUMPRODUCT(($C$21:$C$233=$V$29)*IFERROR($I$21:$I$233,0))) -> 10551656 | AC29: =IF(SUMPRODUCT(($C$21:$C$233=$V$29)*ISNUMBER($J$21:$J$233))=0,NA(),SUMPRODUCT(($C$21:$C$233=$V$29)*IFERROR($J$21:$J$233,0))/SUMPRODUCT(($C$21:$C$233=$V$29)*ISNUMBER($J$21:$J$233))) -> 30.539267 | AD29: =IF(SUMPRODUCT(($C$21:$C$233=$V$29)*ISNUMBER($K$21:$K$233))=0,NA(),SUMPRODUCT(($C$21:$C$233=$V$29)*IFERROR($K$21:$K$233,0))/SUMPRODUCT(($C$21:$C$233=$V$29)*ISNUMBER($K$21:$K$233))) -> 4.5515483 | AE29: =IF(SUMPRODUCT(($C$21:$C$233=$V$29)*ISNUMBER($L$21:$L$233))=0,NA(),SUMPRODUCT(($C$21:$C$233=$V$29)*IFERROR($L$21:$L$233,0))/SUMPRODUCT(($C$21:$C$233=$V$29)*ISNUMBER($L$21:$L$233))) -> 5.7314167 | AF29: =IFERROR(W29/W28-1,NA()) -> -0.010264205
A30: =IFERROR(IF(ISNUMBER('Real and nominal GDP'!A17),'Real and nominal GDP'!A17,NA()),NA()) -> 38869 | B30: =IFERROR(IF('Real and nominal GDP'!B17="",NA(),'Real and nominal GDP'!B17),NA()) -> 062 | C30: =IFERROR(YEAR(A30),0) -> 2006 | D30: =IFERROR(IF('Real and nominal GDP'!C17="",NA(),IF(ISNUMBER('Real and nominal GDP'!C17),'Real and nominal GDP'!C17,NA())),NA()) -> 561157.22 | E30: =IFERROR(IF('Real and nominal GDP'!D17="",NA(),IF(ISNUMBER('Real and nominal GDP'!D17),'Real and nominal GDP'!D17,NA())),NA()) -> 371905.79 | F30: =IFERROR(IF('Real and nominal GDP'!E17="",NA(),IF(ISNUMBER('Real and nominal GDP'!E17),'Real and nominal GDP'!E17,NA())),NA()) -> 60706.294 | G30: =IFERROR(IF('Real and nominal GDP'!F17="",NA(),IF(ISNUMBER('Real and nominal GDP'!F17),'Real and nominal GDP'!F17,NA())),NA()) -> 100741.05 | H30: =IFERROR(IF('Real and nominal GDP'!G17="",NA(),IF(ISNUMBER('Real and nominal GDP'!G17),'Real and nominal GDP'!G17,NA())),NA()) -> 614076.39 | I30: =IFERROR(IF('Real and nominal GDP'!H17="",NA(),IF(ISNUMBER('Real and nominal GDP'!H17),'Real and nominal GDP'!H17,NA())),NA()) -> 727989 | J30: =IFERROR(IF('Real and nominal GDP'!I17="",NA(),IF(ISNUMBER('Real and nominal GDP'!I17),'Real and nominal GDP'!I17,NA())),NA()) -> #N/A | K30: =IFERROR(IF('Real and nominal GDP'!J17="",NA(),IF(ISNUMBER('Real and nominal GDP'!J17),'Real and nominal GDP'!J17,NA())),NA()) -> 3.06794 | L30: =IFERROR(IF('Real and nominal GDP'!K17="",NA(),IF(ISNUMBER('Real and nominal GDP'!K17),'Real and nominal GDP'!K17,NA())),NA()) -> 3.083 | M30: =IFERROR(D30/D26-1,NA()) -> 0.064644368 | N30: =IFERROR(D30/D29-1,NA()) -> 0.012086538 | O30: =IFERROR(I30/I26-1,NA()) -> 0.20175413 | P30: =IF(COUNT(D27:D30)=4,SUM(D27:D30),NA()) -> 2185834.1 | Q30: =IF(COUNT(I27:I30)=4,SUM(I27:I30),NA()) -> 2585229 | R30: =IFERROR(I30/K30,NA()) -> 237289.19 | S30: =IFERROR(I30/L30,NA()) -> 236130.07 | V30: 2013 | W30: =IF(SUMPRODUCT(($C$21:$C$233=$V$30)*ISNUMBER($D$21:$D$233))=0,NA(),SUMPRODUCT(($C$21:$C$233=$V$30)*IFERROR($D$21:$D$233,0))) -> 2881628.4 | X30: =IF(SUMPRODUCT(($C$21:$C$233=$V$30)*ISNUMBER($E$21:$E$233))=0,NA(),SUMPRODUCT(($C$21:$C$233=$V$30)*IFERROR($E$21:$E$233,0))) -> 2102698.1 | Y30: =IF(SUMPRODUCT(($C$21:$C$233=$V$30)*ISNUMBER($F$21:$F$233))=0,NA(),SUMPRODUCT(($C$21:$C$233=$V$30)*IFERROR($F$21:$F$233,0))) -> 351665.15 | Z30: =IF(SUMPRODUCT(($C$21:$C$233=$V$30)*ISNUMBER($G$21:$G$233))=0,NA(),SUMPRODUCT(($C$21:$C$233=$V$30)*IFERROR($G$21:$G$233,0))) -> 584226.27 | AA30: =IF(SUMPRODUCT(($C$21:$C$233=$V$30)*ISNUMBER($H$21:$H$233))=0,NA(),SUMPRODUCT(($C$21:$C$233=$V$30)*IFERROR($H$21:$H$233,0))) -> 2881628.4 | AB30: =IF(SUMPRODUCT(($C$21:$C$233=$V$30)*ISNUMBER($I$21:$I$233))=0,NA(),SUMPRODUCT(($C$21:$C$233=$V$30)*IFERROR($I$21:$I$233,0))) -> 13393235 | AC30: =IF(SUMPRODUCT(($C$21:$C$233=$V$30)*ISNUMBER($J$21:$J$233))=0,NA(),SUMPRODUCT(($C$21:$C$233=$V$30)*IFERROR($J$21:$J$233,0))/SUMPRODUCT(($C$21:$C$233=$V$30)*ISNUMBER($J$21:$J$233))) -> 36.126767 | AD30: =IF(SUMPRODUCT(($C$21:$C$233=$V$30)*ISNUMBER($K$21:$K$233))=0,NA(),SUMPRODUCT(($C$21:$C$233=$V$30)*IFERROR($K$21:$K$233,0))/SUMPRODUCT(($C$21:$C$233=$V$30)*ISNUMBER($K$21:$K$233))) -> 5.478235 | AE30: =IF(SUMPRODUCT(($C$21:$C$233=$V$30)*ISNUMBER($L$21:$L$233))=0,NA(),SUMPRODUCT(($C$21:$C$233=$V$30)*IFERROR($L$21:$L$233,0))/SUMPRODUCT(($C$21:$C$233=$V$30)*ISNUMBER($L$21:$L$233))) -> 8.74525 | AF30: =IFERROR(W30/W29-1,NA()) -> 0.024053238
A31: =IFERROR(IF(ISNUMBER('Real and nominal GDP'!A18),'Real and nominal GDP'!A18,NA()),NA()) -> 38961 | B31: =IFERROR(IF('Real and nominal GDP'!B18="",NA(),'Real and nominal GDP'!B18),NA()) -> 063 | C31: =IFERROR(YEAR(A31),0) -> 2006 | D31: =IFERROR(IF('Real and nominal GDP'!C18="",NA(),IF(ISNUMBER('Real and nominal GDP'!C18),'Real and nominal GDP'!C18,NA())),NA()) -> 577088.46 | E31: =IFERROR(IF('Real and nominal GDP'!D18="",NA(),IF(ISNUMBER('Real and nominal GDP'!D18),'Real and nominal GDP'!D18,NA())),NA()) -> 381137.22 | F31: =IFERROR(IF('Real and nominal GDP'!E18="",NA(),IF(ISNUMBER('Real and nominal GDP'!E18),'Real and nominal GDP'!E18,NA())),NA()) -> 61658.229 | G31: =IFERROR(IF('Real and nominal GDP'!F18="",NA(),IF(ISNUMBER('Real and nominal GDP'!F18),'Real and nominal GDP'!F18,NA())),NA()) -> 103927.85 | H31: =IFERROR(IF('Real and nominal GDP'!G18="",NA(),IF(ISNUMBER('Real and nominal GDP'!G18),'Real and nominal GDP'!G18,NA())),NA()) -> 562978.97 | I31: =IFERROR(IF('Real and nominal GDP'!H18="",NA(),IF(ISNUMBER('Real and nominal GDP'!H18),'Real and nominal GDP'!H18,NA())),NA()) -> 729299 | J31: =IFERROR(IF('Real and nominal GDP'!I18="",NA(),IF(ISNUMBER('Real and nominal GDP'!I18),'Real and nominal GDP'!I18,NA())),NA()) -> #N/A | K31: =IFERROR(IF('Real and nominal GDP'!J18="",NA(),IF(ISNUMBER('Real and nominal GDP'!J18),'Real and nominal GDP'!J18,NA())),NA()) -> 3.0872567 | L31: =IFERROR(IF('Real and nominal GDP'!K18="",NA(),IF(ISNUMBER('Real and nominal GDP'!K18),'Real and nominal GDP'!K18,NA())),NA()) -> 3.1033333 | M31: =IFERROR(D31/D27-1,NA()) -> 0.088636722 | N31: =IFERROR(D31/D30-1,NA()) -> 0.028389967 | O31: =IFERROR(I31/I27-1,NA()) -> 0.23563925 | P31: =IF(COUNT(D28:D31)=4,SUM(D28:D31),NA()) -> 2232820.6 | Q31: =IF(COUNT(I28:I31)=4,SUM(I28:I31),NA()) -> 2724308 | R31: =IFERROR(I31/K31,NA()) -> 236228.82 | S31: =IFERROR(I31/L31,NA()) -> 235005.05 | V31: 2014 | W31: =IF(SUMPRODUCT(($C$21:$C$233=$V$31)*ISNUMBER($D$21:$D$233))=0,NA(),SUMPRODUCT(($C$21:$C$233=$V$31)*IFERROR($D$21:$D$233,0))) -> 2809224.2 | X31: =IF(SUMPRODUCT(($C$21:$C$233=$V$31)*ISNUMBER($E$21:$E$233))=0,NA(),SUMPRODUCT(($C$21:$C$233=$V$31)*IFERROR($E$21:$E$233,0))) -> 2011057.7 | Y31: =IF(SUMPRODUCT(($C$21:$C$233=$V$31)*ISNUMBER($F$21:$F$233))=0,NA(),SUMPRODUCT(($C$21:$C$233=$V$31)*IFERROR($F$21:$F$233,0))) -> 362021.8 | Z31: =IF(SUMPRODUCT(($C$21:$C$233=$V$31)*ISNUMBER($G$21:$G$233))=0,NA(),SUMPRODUCT(($C$21:$C$233=$V$31)*IFERROR($G$21:$G$233,0))) -> 544758.59 | AA31: =IF(SUMPRODUCT(($C$21:$C$233=$V$31)*ISNUMBER($H$21:$H$233))=0,NA(),SUMPRODUCT(($C$21:$C$233=$V$31)*IFERROR($H$21:$H$233,0))) -> 2809224.2 | AB31: =IF(SUMPRODUCT(($C$21:$C$233=$V$31)*ISNUMBER($I$21:$I$233))=0,NA(),SUMPRODUCT(($C$21:$C$233=$V$31)*IFERROR($I$21:$I$233,0))) -> 18316346 | AC31: =IF(SUMPRODUCT(($C$21:$C$233=$V$31)*ISNUMBER($J$21:$J$233))=0,NA(),SUMPRODUCT(($C$21:$C$233=$V$31)*IFERROR($J$21:$J$233,0))/SUMPRODUCT(($C$21:$C$233=$V$31)*ISNUMBER($J$21:$J$233))) -> 49.884083 | AD31: =IF(SUMPRODUCT(($C$21:$C$233=$V$31)*ISNUMBER($K$21:$K$233))=0,NA(),SUMPRODUCT(($C$21:$C$233=$V$31)*IFERROR($K$21:$K$233,0))/SUMPRODUCT(($C$21:$C$233=$V$31)*ISNUMBER($K$21:$K$233))) -> 8.1250867 | AE31: =IF(SUMPRODUCT(($C$21:$C$233=$V$31)*ISNUMBER($L$21:$L$233))=0,NA(),SUMPRODUCT(($C$21:$C$233=$V$31)*IFERROR($L$21:$L$233,0))/SUMPRODUCT(($C$21:$C$233=$V$31)*ISNUMBER($L$21:$L$233))) -> 12.38425 | AF31: =IFERROR(W31/W30-1,NA()) -> -0.025126153
A32: =IFERROR(IF(ISNUMBER('Real and nominal GDP'!A19),'Real and nominal GDP'!A19,NA()),NA()) -> 39052 | B32: =IFERROR(IF('Real and nominal GDP'!B19="",NA(),'Real and nominal GDP'!B19),NA()) -> 064 | C32: =IFERROR(YEAR(A32),0) -> 2006 | D32: =IFERROR(IF('Real and nominal GDP'!C19="",NA(),IF(ISNUMBER('Real and nominal GDP'!C19),'Real and nominal GDP'!C19,NA())),NA()) -> 589496.16 | E32: =IFERROR(IF('Real and nominal GDP'!D19="",NA(),IF(ISNUMBER('Real and nominal GDP'!D19),'Real and nominal GDP'!D19,NA())),NA()) -> 380937.31 | F32: =IFERROR(IF('Real and nominal GDP'!E19="",NA(),IF(ISNUMBER('Real and nominal GDP'!E19),'Real and nominal GDP'!E19,NA())),NA()) -> 62861.894 | G32: =IFERROR(IF('Real and nominal GDP'!F19="",NA(),IF(ISNUMBER('Real and nominal GDP'!F19),'Real and nominal GDP'!F19,NA())),NA()) -> 106810.9 | H32: =IFERROR(IF('Real and nominal GDP'!G19="",NA(),IF(ISNUMBER('Real and nominal GDP'!G19),'Real and nominal GDP'!G19,NA())),NA()) -> 572794.05 | I32: =IFERROR(IF('Real and nominal GDP'!H19="",NA(),IF(ISNUMBER('Real and nominal GDP'!H19),'Real and nominal GDP'!H19,NA())),NA()) -> 762766 | J32: =IFERROR(IF('Real and nominal GDP'!I19="",NA(),IF(ISNUMBER('Real and nominal GDP'!I19),'Real and nominal GDP'!I19,NA())),NA()) -> #N/A | K32: =IFERROR(IF('Real and nominal GDP'!J19="",NA(),IF(ISNUMBER('Real and nominal GDP'!J19),'Real and nominal GDP'!J19,NA())),NA()) -> 3.0774 | L32: =IFERROR(IF('Real and nominal GDP'!K19="",NA(),IF(ISNUMBER('Real and nominal GDP'!K19),'Real and nominal GDP'!K19,NA())),NA()) -> 3.098 | M32: =IFERROR(D32/D28-1,NA()) -> 0.091418731 | N32: =IFERROR(D32/D31-1,NA()) -> 0.021500525 | O32: =IFERROR(I32/I28-1,NA()) -> 0.22344408 | P32: =IF(COUNT(D29:D32)=4,SUM(D29:D32),NA()) -> 2282197.6 | Q32: =IF(COUNT(I29:I32)=4,SUM(I29:I32),NA()) -> 2863616 | R32: =IFERROR(I32/K32,NA()) -> 247860.53 | S32: =IFERROR(I32/L32,NA()) -> 246212.4 | V32: 2015 | W32: =IF(SUMPRODUCT(($C$21:$C$233=$V$32)*ISNUMBER($D$21:$D$233))=0,NA(),SUMPRODUCT(($C$21:$C$233=$V$32)*IFERROR($D$21:$D$233,0))) -> 2885948.6 | X32: =IF(SUMPRODUCT(($C$21:$C$233=$V$32)*ISNUMBER($E$21:$E$233))=0,NA(),SUMPRODUCT(($C$21:$C$233=$V$32)*IFERROR($E$21:$E$233,0))) -> 2084586 | Y32: =IF(SUMPRODUCT(($C$21:$C$233=$V$32)*ISNUMBER($F$21:$F$233))=0,NA(),SUMPRODUCT(($C$21:$C$233=$V$32)*IFERROR($F$21:$F$233,0))) -> 387167.85 | Z32: =IF(SUMPRODUCT(($C$21:$C$233=$V$32)*ISNUMBER($G$21:$G$233))=0,NA(),SUMPRODUCT(($C$21:$C$233=$V$32)*IFERROR($G$21:$G$233,0))) -> 563620.88 | AA32: =IF(SUMPRODUCT(($C$21:$C$233=$V$32)*ISNUMBER($H$21:$H$233))=0,NA(),SUMPRODUCT(($C$21:$C$233=$V$32)*IFERROR($H$21:$H$233,0))) -> 2885948.6 | AB32: =IF(SUMPRODUCT(($C$21:$C$233=$V$32)*ISNUMBER($I$21:$I$233))=0,NA(),SUMPRODUCT(($C$21:$C$233=$V$32)*IFERROR($I$21:$I$233,0))) -> 23818044 | AC32: =IF(SUMPRODUCT(($C$21:$C$233=$V$32)*ISNUMBER($J$21:$J$233))=0,NA(),SUMPRODUCT(($C$21:$C$233=$V$32)*IFERROR($J$21:$J$233,0))/SUMPRODUCT(($C$21:$C$233=$V$32)*ISNUMBER($J$21:$J$233))) -> 63.122508 | AD32: =IF(SUMPRODUCT(($C$21:$C$233=$V$32)*ISNUMBER($K$21:$K$233))=0,NA(),SUMPRODUCT(($C$21:$C$233=$V$32)*IFERROR($K$21:$K$233,0))/SUMPRODUCT(($C$21:$C$233=$V$32)*ISNUMBER($K$21:$K$233))) -> 9.2673817 | AE32: =IF(SUMPRODUCT(($C$21:$C$233=$V$32)*ISNUMBER($L$21:$L$233))=0,NA(),SUMPRODUCT(($C$21:$C$233=$V$32)*IFERROR($L$21:$L$233,0))/SUMPRODUCT(($C$21:$C$233=$V$32)*ISNUMBER($L$21:$L$233))) -> 13.982583 | AF32: =IFERROR(W32/W31-1,NA()) -> 0.027311598
A33: =IFERROR(IF(ISNUMBER('Real and nominal GDP'!A20),'Real and nominal GDP'!A20,NA()),NA()) -> 39142 | B33: =IFERROR(IF('Real and nominal GDP'!B20="",NA(),'Real and nominal GDP'!B20),NA()) -> 071 | C33: =IFERROR(YEAR(A33),0) -> 2007 | D33: =IFERROR(IF('Real and nominal GDP'!C20="",NA(),IF(ISNUMBER('Real and nominal GDP'!C20),'Real and nominal GDP'!C20,NA())),NA()) -> 603483.21 | E33: =IFERROR(IF('Real and nominal GDP'!D20="",NA(),IF(ISNUMBER('Real and nominal GDP'!D20),'Real and nominal GDP'!D20,NA())),NA()) -> 392667.41 | F33: =IFERROR(IF('Real and nominal GDP'!E20="",NA(),IF(ISNUMBER('Real and nominal GDP'!E20),'Real and nominal GDP'!E20,NA())),NA()) -> 65392.759 | G33: =IFERROR(IF('Real and nominal GDP'!F20="",NA(),IF(ISNUMBER('Real and nominal GDP'!F20),'Real and nominal GDP'!F20,NA())),NA()) -> 116267.52 | H33: =IFERROR(IF('Real and nominal GDP'!G20="",NA(),IF(ISNUMBER('Real and nominal GDP'!G20),'Real and nominal GDP'!G20,NA())),NA()) -> 576846.89 | I33: =IFERROR(IF('Real and nominal GDP'!H20="",NA(),IF(ISNUMBER('Real and nominal GDP'!H20),'Real and nominal GDP'!H20,NA())),NA()) -> 774388 | J33: =IFERROR(IF('Real and nominal GDP'!I20="",NA(),IF(ISNUMBER('Real and nominal GDP'!I20),'Real and nominal GDP'!I20,NA())),NA()) -> #N/A | K33: =IFERROR(IF('Real and nominal GDP'!J20="",NA(),IF(ISNUMBER('Real and nominal GDP'!J20),'Real and nominal GDP'!J20,NA())),NA()) -> 3.09675 | L33: =IFERROR(IF('Real and nominal GDP'!K20="",NA(),IF(ISNUMBER('Real and nominal GDP'!K20),'Real and nominal GDP'!K20,NA())),NA()) -> 3.114 | M33: =IFERROR(D33/D29-1,NA()) -> 0.088424429 | N33: =IFERROR(D33/D32-1,NA()) -> 0.023727116 | O33: =IFERROR(I33/I29-1,NA()) -> 0.20328422 | P33: =IF(COUNT(D30:D33)=4,SUM(D30:D33),NA()) -> 2331225.1 | Q33: =IF(COUNT(I30:I33)=4,SUM(I30:I33),NA()) -> 2994442 | R33: =IFERROR(I33/K33,NA()) -> 250064.75 | S33: =IFERROR(I33/L33,NA()) -> 248679.51 | V33: 2016 | W33: =IF(SUMPRODUCT(($C$21:$C$233=$V$33)*ISNUMBER($D$21:$D$233))=0,NA(),SUMPRODUCT(($C$21:$C$233=$V$33)*IFERROR($D$21:$D$233,0))) -> 2825911.4 | X33: =IF(SUMPRODUCT(($C$21:$C$233=$V$33)*ISNUMBER($E$21:$E$233))=0,NA(),SUMPRODUCT(($C$21:$C$233=$V$33)*IFERROR($E$21:$E$233,0))) -> 2068320.6 | Y33: =IF(SUMPRODUCT(($C$21:$C$233=$V$33)*ISNUMBER($F$21:$F$233))=0,NA(),SUMPRODUCT(($C$21:$C$233=$V$33)*IFERROR($F$21:$F$233,0))) -> 385137.64 | Z33: =IF(SUMPRODUCT(($C$21:$C$233=$V$33)*ISNUMBER($G$21:$G$233))=0,NA(),SUMPRODUCT(($C$21:$C$233=$V$33)*IFERROR($G$21:$G$233,0))) -> 531052.22 | AA33: =IF(SUMPRODUCT(($C$21:$C$233=$V$33)*ISNUMBER($H$21:$H$233))=0,NA(),SUMPRODUCT(($C$21:$C$233=$V$33)*IFERROR($H$21:$H$233,0))) -> 2825911.4 | AB33: =IF(SUMPRODUCT(($C$21:$C$233=$V$33)*ISNUMBER($I$21:$I$233))=0,NA(),SUMPRODUCT(($C$21:$C$233=$V$33)*IFERROR($I$21:$I$233,0))) -> 32912638 | AC33: =IF(SUMPRODUCT(($C$21:$C$233=$V$33)*ISNUMBER($J$21:$J$233))=0,NA(),SUMPRODUCT(($C$21:$C$233=$V$33)*IFERROR($J$21:$J$233,0))/SUMPRODUCT(($C$21:$C$233=$V$33)*ISNUMBER($J$21:$J$233))) -> 89.248583 | AD33: =IF(SUMPRODUCT(($C$21:$C$233=$V$33)*ISNUMBER($K$21:$K$233))=0,NA(),SUMPRODUCT(($C$21:$C$233=$V$33)*IFERROR($K$21:$K$233,0))/SUMPRODUCT(($C$21:$C$233=$V$33)*ISNUMBER($K$21:$K$233))) -> 14.781018 | AE33: =IF(SUMPRODUCT(($C$21:$C$233=$V$33)*ISNUMBER($L$21:$L$233))=0,NA(),SUMPRODUCT(($C$21:$C$233=$V$33)*IFERROR($L$21:$L$233,0))/SUMPRODUCT(($C$21:$C$233=$V$33)*ISNUMBER($L$21:$L$233))) -> 15.0565 | AF33: =IFERROR(W33/W32-1,NA()) -> -0.020803278
A34: =IFERROR(IF(ISNUMBER('Real and nominal GDP'!A21),'Real and nominal GDP'!A21,NA()),NA()) -> 39234 | B34: =IFERROR(IF('Real and nominal GDP'!B21="",NA(),'Real and nominal GDP'!B21),NA()) -> 072 | C34: =IFERROR(YEAR(A34),0) -> 2007 | D34: =IFERROR(IF('Real and nominal GDP'!C21="",NA(),IF(ISNUMBER('Real and nominal GDP'!C21),'Real and nominal GDP'!C21,NA())),NA()) -> 616073.37 | E34: =IFERROR(IF('Real and nominal GDP'!D21="",NA(),IF(ISNUMBER('Real and nominal GDP'!D21),'Real and nominal GDP'!D21,NA())),NA()) -> 402296.08 | F34: =IFERROR(IF('Real and nominal GDP'!E21="",NA(),IF(ISNUMBER('Real and nominal GDP'!E21),'Real and nominal GDP'!E21,NA())),NA()) -> 65948.641 | G34: =IFERROR(IF('Real and nominal GDP'!F21="",NA(),IF(ISNUMBER('Real and nominal GDP'!F21),'Real and nominal GDP'!F21,NA())),NA()) -> 121508.99 | H34: =IFERROR(IF('Real and nominal GDP'!G21="",NA(),IF(ISNUMBER('Real and nominal GDP'!G21),'Real and nominal GDP'!G21,NA())),NA()) -> 674620.56 | I34: =IFERROR(IF('Real and nominal GDP'!H21="",NA(),IF(ISNUMBER('Real and nominal GDP'!H21),'Real and nominal GDP'!H21,NA())),NA()) -> 904350 | J34: =IFERROR(IF('Real and nominal GDP'!I21="",NA(),IF(ISNUMBER('Real and nominal GDP'!I21),'Real and nominal GDP'!I21,NA())),NA()) -> #N/A | K34: =IFERROR(IF('Real and nominal GDP'!J21="",NA(),IF(ISNUMBER('Real and nominal GDP'!J21),'Real and nominal GDP'!J21,NA())),NA()) -> 3.0828667 | L34: =IFERROR(IF('Real and nominal GDP'!K21="",NA(),IF(ISNUMBER('Real and nominal GDP'!K21),'Real and nominal GDP'!K21,NA())),NA()) -> 3.111 | M34: =IFERROR(D34/D30-1,NA()) -> 0.097862312 | N34: =IFERROR(D34/D33-1,NA()) -> 0.020862484 | O34: =IFERROR(I34/I30-1,NA()) -> 0.24225778 | P34: =IF(COUNT(D31:D34)=4,SUM(D31:D34),NA()) -> 2386141.2 | Q34: =IF(COUNT(I31:I34)=4,SUM(I31:I34),NA()) -> 3170803 | R34: =IFERROR(I34/K34,NA()) -> 293347.1 | S34: =IFERROR(I34/L34,NA()) -> 290694.31 | V34: 2017 | W34: =IF(SUMPRODUCT(($C$21:$C$233=$V$34)*ISNUMBER($D$21:$D$233))=0,NA(),SUMPRODUCT(($C$21:$C$233=$V$34)*IFERROR($D$21:$D$233,0))) -> 2905559.8 | X34: =IF(SUMPRODUCT(($C$21:$C$233=$V$34)*ISNUMBER($E$21:$E$233))=0,NA(),SUMPRODUCT(($C$21:$C$233=$V$34)*IFERROR($E$21:$E$233,0))) -> 2154330.5 | Y34: =IF(SUMPRODUCT(($C$21:$C$233=$V$34)*ISNUMBER($F$21:$F$233))=0,NA(),SUMPRODUCT(($C$21:$C$233=$V$34)*IFERROR($F$21:$F$233,0))) -> 395294.2 | Z34: =IF(SUMPRODUCT(($C$21:$C$233=$V$34)*ISNUMBER($G$21:$G$233))=0,NA(),SUMPRODUCT(($C$21:$C$233=$V$34)*IFERROR($G$21:$G$233,0))) -> 602110.06 | AA34: =IF(SUMPRODUCT(($C$21:$C$233=$V$34)*ISNUMBER($H$21:$H$233))=0,NA(),SUMPRODUCT(($C$21:$C$233=$V$34)*IFERROR($H$21:$H$233,0))) -> 2905559.8 | AB34: =IF(SUMPRODUCT(($C$21:$C$233=$V$34)*ISNUMBER($I$21:$I$233))=0,NA(),SUMPRODUCT(($C$21:$C$233=$V$34)*IFERROR($I$21:$I$233,0))) -> 42640914 | AC34: =IF(SUMPRODUCT(($C$21:$C$233=$V$34)*ISNUMBER($J$21:$J$233))=0,NA(),SUMPRODUCT(($C$21:$C$233=$V$34)*IFERROR($J$21:$J$233,0))/SUMPRODUCT(($C$21:$C$233=$V$34)*ISNUMBER($J$21:$J$233))) -> 112.88711 | AD34: =IF(SUMPRODUCT(($C$21:$C$233=$V$34)*ISNUMBER($K$21:$K$233))=0,NA(),SUMPRODUCT(($C$21:$C$233=$V$34)*IFERROR($K$21:$K$233,0))/SUMPRODUCT(($C$21:$C$233=$V$34)*ISNUMBER($K$21:$K$233))) -> 16.561602 | AE34: =IF(SUMPRODUCT(($C$21:$C$233=$V$34)*ISNUMBER($L$21:$L$233))=0,NA(),SUMPRODUCT(($C$21:$C$233=$V$34)*IFERROR($L$21:$L$233,0))/SUMPRODUCT(($C$21:$C$233=$V$34)*ISNUMBER($L$21:$L$233))) -> 16.974583 | AF34: =IFERROR(W34/W33-1,NA()) -> 0.02818503
A35: =IFERROR(IF(ISNUMBER('Real and nominal GDP'!A22),'Real and nominal GDP'!A22,NA()),NA()) -> 39326 | B35: =IFERROR(IF('Real and nominal GDP'!B22="",NA(),'Real and nominal GDP'!B22),NA()) -> 073 | C35: =IFERROR(YEAR(A35),0) -> 2007 | D35: =IFERROR(IF('Real and nominal GDP'!C22="",NA(),IF(ISNUMBER('Real and nominal GDP'!C22),'Real and nominal GDP'!C22,NA())),NA()) -> 624446.9 | E35: =IFERROR(IF('Real and nominal GDP'!D22="",NA(),IF(ISNUMBER('Real and nominal GDP'!D22),'Real and nominal GDP'!D22,NA())),NA()) -> 412291.88 | F35: =IFERROR(IF('Real and nominal GDP'!E22="",NA(),IF(ISNUMBER('Real and nominal GDP'!E22),'Real and nominal GDP'!E22,NA())),NA()) -> 66182.353 | G35: =IFERROR(IF('Real and nominal GDP'!F22="",NA(),IF(ISNUMBER('Real and nominal GDP'!F22),'Real and nominal GDP'!F22,NA())),NA()) -> 125653.67 | H35: =IFERROR(IF('Real and nominal GDP'!G22="",NA(),IF(ISNUMBER('Real and nominal GDP'!G22),'Real and nominal GDP'!G22,NA())),NA()) -> 610425.69 | I35: =IFERROR(IF('Real and nominal GDP'!H22="",NA(),IF(ISNUMBER('Real and nominal GDP'!H22),'Real and nominal GDP'!H22,NA())),NA()) -> 914104 | J35: =IFERROR(IF('Real and nominal GDP'!I22="",NA(),IF(ISNUMBER('Real and nominal GDP'!I22),'Real and nominal GDP'!I22,NA())),NA()) -> #N/A | K35: =IFERROR(IF('Real and nominal GDP'!J22="",NA(),IF(ISNUMBER('Real and nominal GDP'!J22),'Real and nominal GDP'!J22,NA())),NA()) -> 3.1380133 | L35: =IFERROR(IF('Real and nominal GDP'!K22="",NA(),IF(ISNUMBER('Real and nominal GDP'!K22),'Real and nominal GDP'!K22,NA())),NA()) -> 3.1816667 | M35: =IFERROR(D35/D31-1,NA()) -> 0.082064433 | N35: =IFERROR(D35/D34-1,NA()) -> 0.013591772 | O35: =IFERROR(I35/I31-1,NA()) -> 0.25340087 | P35: =IF(COUNT(D32:D35)=4,SUM(D32:D35),NA()) -> 2433499.6 | Q35: =IF(COUNT(I32:I35)=4,SUM(I32:I35),NA()) -> 3355608 | R35: =IFERROR(I35/K35,NA()) -> 291300.23 | S35: =IFERROR(I35/L35,NA()) -> 287303.51 | V35: 2018 | W35: =IF(SUMPRODUCT(($C$21:$C$233=$V$35)*ISNUMBER($D$21:$D$233))=0,NA(),SUMPRODUCT(($C$21:$C$233=$V$35)*IFERROR($D$21:$D$233,0))) -> 2829509.8 | X35: =IF(SUMPRODUCT(($C$21:$C$233=$V$35)*ISNUMBER($E$21:$E$233))=0,NA(),SUMPRODUCT(($C$21:$C$233=$V$35)*IFERROR($E$21:$E$233,0))) -> 2105950.1 | Y35: =IF(SUMPRODUCT(($C$21:$C$233=$V$35)*ISNUMBER($F$21:$F$233))=0,NA(),SUMPRODUCT(($C$21:$C$233=$V$35)*IFERROR($F$21:$F$233,0))) -> 387817.57 | Z35: =IF(SUMPRODUCT(($C$21:$C$233=$V$35)*ISNUMBER($G$21:$G$233))=0,NA(),SUMPRODUCT(($C$21:$C$233=$V$35)*IFERROR($G$21:$G$233,0))) -> 567514.93 | AA35: =IF(SUMPRODUCT(($C$21:$C$233=$V$35)*ISNUMBER($H$21:$H$233))=0,NA(),SUMPRODUCT(($C$21:$C$233=$V$35)*IFERROR($H$21:$H$233,0))) -> 2829509.8 | AB35: =IF(SUMPRODUCT(($C$21:$C$233=$V$35)*ISNUMBER($I$21:$I$233))=0,NA(),SUMPRODUCT(($C$21:$C$233=$V$35)*IFERROR($I$21:$I$233,0))) -> 58979243 | AC35: =IF(SUMPRODUCT(($C$21:$C$233=$V$35)*ISNUMBER($J$21:$J$233))=0,NA(),SUMPRODUCT(($C$21:$C$233=$V$35)*IFERROR($J$21:$J$233,0))/SUMPRODUCT(($C$21:$C$233=$V$35)*ISNUMBER($J$21:$J$233))) -> 151.58167 | AD35: =IF(SUMPRODUCT(($C$21:$C$233=$V$35)*ISNUMBER($K$21:$K$233))=0,NA(),SUMPRODUCT(($C$21:$C$233=$V$35)*IFERROR($K$21:$K$233,0))/SUMPRODUCT(($C$21:$C$233=$V$35)*ISNUMBER($K$21:$K$233))) -> 28.111742 | AE35: =IF(SUMPRODUCT(($C$21:$C$233=$V$35)*ISNUMBER($L$21:$L$233))=0,NA(),SUMPRODUCT(($C$21:$C$233=$V$35)*IFERROR($L$21:$L$233,0))/SUMPRODUCT(($C$21:$C$233=$V$35)*ISNUMBER($L$21:$L$233))) -> 28.18775 | AF35: =IFERROR(W35/W34-1,NA()) -> -0.026173965
A36: =IFERROR(IF(ISNUMBER('Real and nominal GDP'!A23),'Real and nominal GDP'!A23,NA()),NA()) -> 39417 | B36: =IFERROR(IF('Real and nominal GDP'!B23="",NA(),'Real and nominal GDP'!B23),NA()) -> 074 | C36: =IFERROR(YEAR(A36),0) -> 2007 | D36: =IFERROR(IF('Real and nominal GDP'!C23="",NA(),IF(ISNUMBER('Real and nominal GDP'!C23),'Real and nominal GDP'!C23,NA())),NA()) -> 643766.54 | E36: =IFERROR(IF('Real and nominal GDP'!D23="",NA(),IF(ISNUMBER('Real and nominal GDP'!D23),'Real and nominal GDP'!D23,NA())),NA()) -> 419150.79 | F36: =IFERROR(IF('Real and nominal GDP'!E23="",NA(),IF(ISNUMBER('Real and nominal GDP'!E23),'Real and nominal GDP'!E23,NA())),NA()) -> 67468.668 | G36: =IFERROR(IF('Real and nominal GDP'!F23="",NA(),IF(ISNUMBER('Real and nominal GDP'!F23),'Real and nominal GDP'!F23,NA())),NA()) -> 129139.78 | H36: =IFERROR(IF('Real and nominal GDP'!G23="",NA(),IF(ISNUMBER('Real and nominal GDP'!G23),'Real and nominal GDP'!G23,NA())),NA()) -> 625876.87 | I36: =IFERROR(IF('Real and nominal GDP'!H23="",NA(),IF(ISNUMBER('Real and nominal GDP'!H23),'Real and nominal GDP'!H23,NA())),NA()) -> 995079 | J36: =IFERROR(IF('Real and nominal GDP'!I23="",NA(),IF(ISNUMBER('Real and nominal GDP'!I23),'Real and nominal GDP'!I23,NA())),NA()) -> #N/A | K36: =IFERROR(IF('Real and nominal GDP'!J23="",NA(),IF(ISNUMBER('Real and nominal GDP'!J23),'Real and nominal GDP'!J23,NA())),NA()) -> 3.1450767 | L36: =IFERROR(IF('Real and nominal GDP'!K23="",NA(),IF(ISNUMBER('Real and nominal GDP'!K23),'Real and nominal GDP'!K23,NA())),NA()) -> 3.1746667 | M36: =IFERROR(D36/D32-1,NA()) -> 0.092062313 | N36: =IFERROR(D36/D35-1,NA()) -> 0.030938817 | O36: =IFERROR(I36/I32-1,NA()) -> 0.30456654 | P36: =IF(COUNT(D33:D36)=4,SUM(D33:D36),NA()) -> 2487770 | Q36: =IF(COUNT(I33:I36)=4,SUM(I33:I36),NA()) -> 3587921 | R36: =IFERROR(I36/K36,NA()) -> 316392.61 | S36: =IFERROR(I36/L36,NA()) -> 313443.62 | V36: 2019 | W36: =IF(SUMPRODUCT(($C$21:$C$233=$V$36)*ISNUMBER($D$21:$D$233))=0,NA(),SUMPRODUCT(($C$21:$C$233=$V$36)*IFERROR($D$21:$D$233,0))) -> 2772895.2 | X36: =IF(SUMPRODUCT(($C$21:$C$233=$V$36)*ISNUMBER($E$21:$E$233))=0,NA(),SUMPRODUCT(($C$21:$C$233=$V$36)*IFERROR($E$21:$E$233,0))) -> 1976920.5 | Y36: =IF(SUMPRODUCT(($C$21:$C$233=$V$36)*ISNUMBER($F$21:$F$233))=0,NA(),SUMPRODUCT(($C$21:$C$233=$V$36)*IFERROR($F$21:$F$233,0))) -> 362996.74 | Z36: =IF(SUMPRODUCT(($C$21:$C$233=$V$36)*ISNUMBER($G$21:$G$233))=0,NA(),SUMPRODUCT(($C$21:$C$233=$V$36)*IFERROR($G$21:$G$233,0))) -> 476987.49 | AA36: =IF(SUMPRODUCT(($C$21:$C$233=$V$36)*ISNUMBER($H$21:$H$233))=0,NA(),SUMPRODUCT(($C$21:$C$233=$V$36)*IFERROR($H$21:$H$233,0))) -> 2772895.2 | AB36: =IF(SUMPRODUCT(($C$21:$C$233=$V$36)*ISNUMBER($I$21:$I$233))=0,NA(),SUMPRODUCT(($C$21:$C$233=$V$36)*IFERROR($I$21:$I$233,0))) -> 86233777 | AC36: =IF(SUMPRODUCT(($C$21:$C$233=$V$36)*ISNUMBER($J$21:$J$233))=0,NA(),SUMPRODUCT(($C$21:$C$233=$V$36)*IFERROR($J$21:$J$233,0))/SUMPRODUCT(($C$21:$C$233=$V$36)*ISNUMBER($J$21:$J$233))) -> 232.75109 | AD36: =IF(SUMPRODUCT(($C$21:$C$233=$V$36)*ISNUMBER($K$21:$K$233))=0,NA(),SUMPRODUCT(($C$21:$C$233=$V$36)*IFERROR($K$21:$K$233,0))/SUMPRODUCT(($C$21:$C$233=$V$36)*ISNUMBER($K$21:$K$233))) -> 48.24785 | AE36: =IF(SUMPRODUCT(($C$21:$C$233=$V$36)*ISNUMBER($L$21:$L$233))=0,NA(),SUMPRODUCT(($C$21:$C$233=$V$36)*IFERROR($L$21:$L$233,0))/SUMPRODUCT(($C$21:$C$233=$V$36)*ISNUMBER($L$21:$L$233))) -> 50.480833 | AF36: =IFERROR(W36/W35-1,NA()) -> -0.02000861
A37: =IFERROR(IF(ISNUMBER('Real and nominal GDP'!A24),'Real and nominal GDP'!A24,NA()),NA()) -> 39508 | B37: =IFERROR(IF('Real and nominal GDP'!B24="",NA(),'Real and nominal GDP'!B24),NA()) -> 081 | C37: =IFERROR(YEAR(A37),0) -> 2008 | D37: =IFERROR(IF('Real and nominal GDP'!C24="",NA(),IF(ISNUMBER('Real and nominal GDP'!C24),'Real and nominal GDP'!C24,NA())),NA()) -> 650003.26 | E37: =IFERROR(IF('Real and nominal GDP'!D24="",NA(),IF(ISNUMBER('Real and nominal GDP'!D24),'Real and nominal GDP'!D24,NA())),NA()) -> 436248.07 | F37: =IFERROR(IF('Real and nominal GDP'!E24="",NA(),IF(ISNUMBER('Real and nominal GDP'!E24),'Real and nominal GDP'!E24,NA())),NA()) -> 68277.412 | G37: =IFERROR(IF('Real and nominal GDP'!F24="",NA(),IF(ISNUMBER('Real and nominal GDP'!F24),'Real and nominal GDP'!F24,NA())),NA()) -> 139051.97 | H37: =IFERROR(IF('Real and nominal GDP'!G24="",NA(),IF(ISNUMBER('Real and nominal GDP'!G24),'Real and nominal GDP'!G24,NA())),NA()) -> 616720.36 | I37: =IFERROR(IF('Real and nominal GDP'!H24="",NA(),IF(ISNUMBER('Real and nominal GDP'!H24),'Real and nominal GDP'!H24,NA())),NA()) -> 1032357 | J37: =IFERROR(IF('Real and nominal GDP'!I24="",NA(),IF(ISNUMBER('Real and nominal GDP'!I24),'Real and nominal GDP'!I24,NA())),NA()) -> #N/A | K37: =IFERROR(IF('Real and nominal GDP'!J24="",NA(),IF(ISNUMBER('Real and nominal GDP'!J24),'Real and nominal GDP'!J24,NA())),NA()) -> 3.1534067 | L37: =IFERROR(IF('Real and nominal GDP'!K24="",NA(),IF(ISNUMBER('Real and nominal GDP'!K24),'Real and nominal GDP'!K24,NA())),NA()) -> 3.177 | M37: =IFERROR(D37/D33-1,NA()) -> 0.077085906 | N37: =IFERROR(D37/D36-1,NA()) -> 0.0096878505 | O37: =IFERROR(I37/I33-1,NA()) -> 0.33312629 | P37: =IF(COUNT(D34:D37)=4,SUM(D34:D37),NA()) -> 2534290.1 | Q37: =IF(COUNT(I34:I37)=4,SUM(I34:I37),NA()) -> 3845890 | R37: =IFERROR(I37/K37,NA()) -> 327378.33 | S37: =IFERROR(I37/L37,NA()) -> 324947.12 | V37: 2020 | W37: =IF(SUMPRODUCT(($C$21:$C$233=$V$37)*ISNUMBER($D$21:$D$233))=0,NA(),SUMPRODUCT(($C$21:$C$233=$V$37)*IFERROR($D$21:$D$233,0))) -> 2498365.1 | X37: =IF(SUMPRODUCT(($C$21:$C$233=$V$37)*ISNUMBER($E$21:$E$233))=0,NA(),SUMPRODUCT(($C$21:$C$233=$V$37)*IFERROR($E$21:$E$233,0))) -> 1736302.2 | Y37: =IF(SUMPRODUCT(($C$21:$C$233=$V$37)*ISNUMBER($F$21:$F$233))=0,NA(),SUMPRODUCT(($C$21:$C$233=$V$37)*IFERROR($F$21:$F$233,0))) -> 355658.5 | Z37: =IF(SUMPRODUCT(($C$21:$C$233=$V$37)*ISNUMBER($G$21:$G$233))=0,NA(),SUMPRODUCT(($C$21:$C$233=$V$37)*IFERROR($G$21:$G$233,0))) -> 414664.51 | AA37: =IF(SUMPRODUCT(($C$21:$C$233=$V$37)*ISNUMBER($H$21:$H$233))=0,NA(),SUMPRODUCT(($C$21:$C$233=$V$37)*IFERROR($H$21:$H$233,0))) -> 2498365.1 | AB37: =IF(SUMPRODUCT(($C$21:$C$233=$V$37)*ISNUMBER($I$21:$I$233))=0,NA(),SUMPRODUCT(($C$21:$C$233=$V$37)*IFERROR($I$21:$I$233,0))) -> 108839257 | AC37: =IF(SUMPRODUCT(($C$21:$C$233=$V$37)*ISNUMBER($J$21:$J$233))=0,NA(),SUMPRODUCT(($C$21:$C$233=$V$37)*IFERROR($J$21:$J$233,0))/SUMPRODUCT(($C$21:$C$233=$V$37)*ISNUMBER($J$21:$J$233))) -> 330.54168 | AD37: =IF(SUMPRODUCT(($C$21:$C$233=$V$37)*ISNUMBER($K$21:$K$233))=0,NA(),SUMPRODUCT(($C$21:$C$233=$V$37)*IFERROR($K$21:$K$233,0))/SUMPRODUCT(($C$21:$C$233=$V$37)*ISNUMBER($K$21:$K$233))) -> 70.645793 | AE37: =IF(SUMPRODUCT(($C$21:$C$233=$V$37)*ISNUMBER($L$21:$L$233))=0,NA(),SUMPRODUCT(($C$21:$C$233=$V$37)*IFERROR($L$21:$L$233,0))/SUMPRODUCT(($C$21:$C$233=$V$37)*ISNUMBER($L$21:$L$233))) -> 120.03783 | AF37: =IFERROR(W37/W36-1,NA()) -> -0.099004848
A38: =IFERROR(IF(ISNUMBER('Real and nominal GDP'!A25),'Real and nominal GDP'!A25,NA()),NA()) -> 39600 | B38: =IFERROR(IF('Real and nominal GDP'!B25="",NA(),'Real and nominal GDP'!B25),NA()) -> 082 | C38: =IFERROR(YEAR(A38),0) -> 2008 | D38: =IFERROR(IF('Real and nominal GDP'!C25="",NA(),IF(ISNUMBER('Real and nominal GDP'!C25),'Real and nominal GDP'!C25,NA())),NA()) -> 653467.95 | E38: =IFERROR(IF('Real and nominal GDP'!D25="",NA(),IF(ISNUMBER('Real and nominal GDP'!D25),'Real and nominal GDP'!D25,NA())),NA()) -> 443435.14 | F38: =IFERROR(IF('Real and nominal GDP'!E25="",NA(),IF(ISNUMBER('Real and nominal GDP'!E25),'Real and nominal GDP'!E25,NA())),NA()) -> 69644.284 | G38: =IFERROR(IF('Real and nominal GDP'!F25="",NA(),IF(ISNUMBER('Real and nominal GDP'!F25),'Real and nominal GDP'!F25,NA())),NA()) -> 142263.68 | H38: =IFERROR(IF('Real and nominal GDP'!G25="",NA(),IF(ISNUMBER('Real and nominal GDP'!G25),'Real and nominal GDP'!G25,NA())),NA()) -> 711405.5 | I38: =IFERROR(IF('Real and nominal GDP'!H25="",NA(),IF(ISNUMBER('Real and nominal GDP'!H25),'Real and nominal GDP'!H25,NA())),NA()) -> 1213883 | J38: =IFERROR(IF('Real and nominal GDP'!I25="",NA(),IF(ISNUMBER('Real and nominal GDP'!I25),'Real and nominal GDP'!I25,NA())),NA()) -> #N/A | K38: =IFERROR(IF('Real and nominal GDP'!J25="",NA(),IF(ISNUMBER('Real and nominal GDP'!J25),'Real and nominal GDP'!J25,NA())),NA()) -> 3.1210567 | L38: =IFERROR(IF('Real and nominal GDP'!K25="",NA(),IF(ISNUMBER('Real and nominal GDP'!K25),'Real and nominal GDP'!K25,NA())),NA()) -> 3.1846667 | M38: =IFERROR(D38/D34-1,NA()) -> 0.060698271 | N38: =IFERROR(D38/D37-1,NA()) -> 0.0053302764 | O38: =IFERROR(I38/I34-1,NA()) -> 0.34227124 | P38: =IF(COUNT(D35:D38)=4,SUM(D35:D38),NA()) -> 2571684.6 | Q38: =IF(COUNT(I35:I38)=4,SUM(I35:I38),NA()) -> 4155423 | R38: =IFERROR(I38/K38,NA()) -> 388933.34 | S38: =IFERROR(I38/L38,NA()) -> 381164.85 | V38: 2021 | W38: =IF(SUMPRODUCT(($C$21:$C$233=$V$38)*ISNUMBER($D$21:$D$233))=0,NA(),SUMPRODUCT(($C$21:$C$233=$V$38)*IFERROR($D$21:$D$233,0))) -> 2759239.7 | X38: =IF(SUMPRODUCT(($C$21:$C$233=$V$38)*ISNUMBER($E$21:$E$233))=0,NA(),SUMPRODUCT(($C$21:$C$233=$V$38)*IFERROR($E$21:$E$233,0))) -> 1900664 | Y38: =IF(SUMPRODUCT(($C$21:$C$233=$V$38)*ISNUMBER($F$21:$F$233))=0,NA(),SUMPRODUCT(($C$21:$C$233=$V$38)*IFERROR($F$21:$F$233,0))) -> 380997.69 | Z38: =IF(SUMPRODUCT(($C$21:$C$233=$V$38)*ISNUMBER($G$21:$G$233))=0,NA(),SUMPRODUCT(($C$21:$C$233=$V$38)*IFERROR($G$21:$G$233,0))) -> 555718.97 | AA38: =IF(SUMPRODUCT(($C$21:$C$233=$V$38)*ISNUMBER($H$21:$H$233))=0,NA(),SUMPRODUCT(($C$21:$C$233=$V$38)*IFERROR($H$21:$H$233,0))) -> 2759239.7 | AB38: =IF(SUMPRODUCT(($C$21:$C$233=$V$38)*ISNUMBER($I$21:$I$233))=0,NA(),SUMPRODUCT(($C$21:$C$233=$V$38)*IFERROR($I$21:$I$233,0))) -> 184876334 | AC38: =IF(SUMPRODUCT(($C$21:$C$233=$V$38)*ISNUMBER($J$21:$J$233))=0,NA(),SUMPRODUCT(($C$21:$C$233=$V$38)*IFERROR($J$21:$J$233,0))/SUMPRODUCT(($C$21:$C$233=$V$38)*ISNUMBER($J$21:$J$233))) -> 490.55486 | AD38: =IF(SUMPRODUCT(($C$21:$C$233=$V$38)*ISNUMBER($K$21:$K$233))=0,NA(),SUMPRODUCT(($C$21:$C$233=$V$38)*IFERROR($K$21:$K$233,0))/SUMPRODUCT(($C$21:$C$233=$V$38)*ISNUMBER($K$21:$K$233))) -> 95.095893 | AE38: =IF(SUMPRODUCT(($C$21:$C$233=$V$38)*ISNUMBER($L$21:$L$233))=0,NA(),SUMPRODUCT(($C$21:$C$233=$V$38)*IFERROR($L$21:$L$233,0))/SUMPRODUCT(($C$21:$C$233=$V$38)*ISNUMBER($L$21:$L$233))) -> 168.12342 | AF38: =IFERROR(W38/W37-1,NA()) -> 0.10441812
A39: =IFERROR(IF(ISNUMBER('Real and nominal GDP'!A26),'Real and nominal GDP'!A26,NA()),NA()) -> 39692 | B39: =IFERROR(IF('Real and nominal GDP'!B26="",NA(),'Real and nominal GDP'!B26),NA()) -> 083 | C39: =IFERROR(YEAR(A39),0) -> 2008 | D39: =IFERROR(IF('Real and nominal GDP'!C26="",NA(),IF(ISNUMBER('Real and nominal GDP'!C26),'Real and nominal GDP'!C26,NA())),NA()) -> 657695.28 | E39: =IFERROR(IF('Real and nominal GDP'!D26="",NA(),IF(ISNUMBER('Real and nominal GDP'!D26),'Real and nominal GDP'!D26,NA())),NA()) -> 435469.49 | F39: =IFERROR(IF('Real and nominal GDP'!E26="",NA(),IF(ISNUMBER('Real and nominal GDP'!E26),'Real and nominal GDP'!E26,NA())),NA()) -> 70201.012 | G39: =IFERROR(IF('Real and nominal GDP'!F26="",NA(),IF(ISNUMBER('Real and nominal GDP'!F26),'Real and nominal GDP'!F26,NA())),NA()) -> 134229.04 | H39: =IFERROR(IF('Real and nominal GDP'!G26="",NA(),IF(ISNUMBER('Real and nominal GDP'!G26),'Real and nominal GDP'!G26,NA())),NA()) -> 647087.96 | I39: =IFERROR(IF('Real and nominal GDP'!H26="",NA(),IF(ISNUMBER('Real and nominal GDP'!H26),'Real and nominal GDP'!H26,NA())),NA()) -> 1183692 | J39: =IFERROR(IF('Real and nominal GDP'!I26="",NA(),IF(ISNUMBER('Real and nominal GDP'!I26),'Real and nominal GDP'!I26,NA())),NA()) -> #N/A | K39: =IFERROR(IF('Real and nominal GDP'!J26="",NA(),IF(ISNUMBER('Real and nominal GDP'!J26),'Real and nominal GDP'!J26,NA())),NA()) -> 3.0464767 | L39: =IFERROR(IF('Real and nominal GDP'!K26="",NA(),IF(ISNUMBER('Real and nominal GDP'!K26),'Real and nominal GDP'!K26,NA())),NA()) -> 3.0863333 | M39: =IFERROR(D39/D35-1,NA()) -> 0.053244542 | N39: =IFERROR(D39/D38-1,NA()) -> 0.0064690701 | O39: =IFERROR(I39/I35-1,NA()) -> 0.29492049 | P39: =IF(COUNT(D36:D39)=4,SUM(D36:D39),NA()) -> 2604933 | Q39: =IF(COUNT(I36:I39)=4,SUM(I36:I39),NA()) -> 4425011 | R39: =IFERROR(I39/K39,NA()) -> 388544.58 | S39: =IFERROR(I39/L39,NA()) -> 383526.95 | V39: 2022 | W39: =IF(SUMPRODUCT(($C$21:$C$233=$V$39)*ISNUMBER($D$21:$D$233))=0,NA(),SUMPRODUCT(($C$21:$C$233=$V$39)*IFERROR($D$21:$D$233,0))) -> 2925366.5 | X39: =IF(SUMPRODUCT(($C$21:$C$233=$V$39)*ISNUMBER($E$21:$E$233))=0,NA(),SUMPRODUCT(($C$21:$C$233=$V$39)*IFERROR($E$21:$E$233,0))) -> 2080585.2 | Y39: =IF(SUMPRODUCT(($C$21:$C$233=$V$39)*ISNUMBER($F$21:$F$233))=0,NA(),SUMPRODUCT(($C$21:$C$233=$V$39)*IFERROR($F$21:$F$233,0))) -> 391538.64 | Z39: =IF(SUMPRODUCT(($C$21:$C$233=$V$39)*ISNUMBER($G$21:$G$233))=0,NA(),SUMPRODUCT(($C$21:$C$233=$V$39)*IFERROR($G$21:$G$233,0))) -> 613809.25 | AA39: =IF(SUMPRODUCT(($C$21:$C$233=$V$39)*ISNUMBER($H$21:$H$233))=0,NA(),SUMPRODUCT(($C$21:$C$233=$V$39)*IFERROR($H$21:$H$233,0))) -> 2925366.5 | AB39: =IF(SUMPRODUCT(($C$21:$C$233=$V$39)*ISNUMBER($I$21:$I$233))=0,NA(),SUMPRODUCT(($C$21:$C$233=$V$39)*IFERROR($I$21:$I$233,0))) -> 331240181 | AC39: =IF(SUMPRODUCT(($C$21:$C$233=$V$39)*ISNUMBER($J$21:$J$233))=0,NA(),SUMPRODUCT(($C$21:$C$233=$V$39)*IFERROR($J$21:$J$233,0))/SUMPRODUCT(($C$21:$C$233=$V$39)*ISNUMBER($J$21:$J$233))) -> 845.86746 | AD39: =IF(SUMPRODUCT(($C$21:$C$233=$V$39)*ISNUMBER($K$21:$K$233))=0,NA(),SUMPRODUCT(($C$21:$C$233=$V$39)*IFERROR($K$21:$K$233,0))/SUMPRODUCT(($C$21:$C$233=$V$39)*ISNUMBER($K$21:$K$233))) -> 130.71673 | AE39: =IF(SUMPRODUCT(($C$21:$C$233=$V$39)*ISNUMBER($L$21:$L$233))=0,NA(),SUMPRODUCT(($C$21:$C$233=$V$39)*IFERROR($L$21:$L$233,0))/SUMPRODUCT(($C$21:$C$233=$V$39)*ISNUMBER($L$21:$L$233))) -> 250.362 | AF39: =IFERROR(W39/W38-1,NA()) -> 0.060207453
A40: =IFERROR(IF(ISNUMBER('Real and nominal GDP'!A27),'Real and nominal GDP'!A27,NA()),NA()) -> 39783 | B40: =IFERROR(IF('Real and nominal GDP'!B27="",NA(),'Real and nominal GDP'!B27),NA()) -> 084 | C40: =IFERROR(YEAR(A40),0) -> 2008 | D40: =IFERROR(IF('Real and nominal GDP'!C27="",NA(),IF(ISNUMBER('Real and nominal GDP'!C27),'Real and nominal GDP'!C27,NA())),NA()) -> 627538.14 | E40: =IFERROR(IF('Real and nominal GDP'!D27="",NA(),IF(ISNUMBER('Real and nominal GDP'!D27),'Real and nominal GDP'!D27,NA())),NA()) -> 429080.86 | F40: =IFERROR(IF('Real and nominal GDP'!E27="",NA(),IF(ISNUMBER('Real and nominal GDP'!E27),'Real and nominal GDP'!E27,NA())),NA()) -> 70159.29 | G40: =IFERROR(IF('Real and nominal GDP'!F27="",NA(),IF(ISNUMBER('Real and nominal GDP'!F27),'Real and nominal GDP'!F27,NA())),NA()) -> 119856.37 | H40: =IFERROR(IF('Real and nominal GDP'!G27="",NA(),IF(ISNUMBER('Real and nominal GDP'!G27),'Real and nominal GDP'!G27,NA())),NA()) -> 613490.82 | I40: =IFERROR(IF('Real and nominal GDP'!H27="",NA(),IF(ISNUMBER('Real and nominal GDP'!H27),'Real and nominal GDP'!H27,NA())),NA()) -> 1168652 | J40: =IFERROR(IF('Real and nominal GDP'!I27="",NA(),IF(ISNUMBER('Real and nominal GDP'!I27),'Real and nominal GDP'!I27,NA())),NA()) -> #N/A | K40: =IFERROR(IF('Real and nominal GDP'!J27="",NA(),IF(ISNUMBER('Real and nominal GDP'!J27),'Real and nominal GDP'!J27,NA())),NA()) -> 3.3326733 | L40: =IFERROR(IF('Real and nominal GDP'!K27="",NA(),IF(ISNUMBER('Real and nominal GDP'!K27),'Real and nominal GDP'!K27,NA())),NA()) -> 3.3916667 | M40: =IFERROR(D40/D36-1,NA()) -> -0.025208516 | N40: =IFERROR(D40/D39-1,NA()) -> -0.045852754 | O40: =IFERROR(I40/I36-1,NA()) -> 0.17443138 | P40: =IF(COUNT(D37:D40)=4,SUM(D37:D40),NA()) -> 2588704.6 | Q40: =IF(COUNT(I37:I40)=4,SUM(I37:I40),NA()) -> 4598584 | R40: =IFERROR(I40/K40,NA()) -> 350665.03 | S40: =IFERROR(I40/L40,NA()) -> 344565.7 | V40: 2023 | W40: =IF(SUMPRODUCT(($C$21:$C$233=$V$40)*ISNUMBER($D$21:$D$233))=0,NA(),SUMPRODUCT(($C$21:$C$233=$V$40)*IFERROR($D$21:$D$233,0))) -> 2871077.9 | X40: =IF(SUMPRODUCT(($C$21:$C$233=$V$40)*ISNUMBER($E$21:$E$233))=0,NA(),SUMPRODUCT(($C$21:$C$233=$V$40)*IFERROR($E$21:$E$233,0))) -> 2100804.8 | Y40: =IF(SUMPRODUCT(($C$21:$C$233=$V$40)*ISNUMBER($F$21:$F$233))=0,NA(),SUMPRODUCT(($C$21:$C$233=$V$40)*IFERROR($F$21:$F$233,0))) -> 399609.15 | Z40: =IF(SUMPRODUCT(($C$21:$C$233=$V$40)*ISNUMBER($G$21:$G$233))=0,NA(),SUMPRODUCT(($C$21:$C$233=$V$40)*IFERROR($G$21:$G$233,0))) -> 601834.4 | AA40: =IF(SUMPRODUCT(($C$21:$C$233=$V$40)*ISNUMBER($H$21:$H$233))=0,NA(),SUMPRODUCT(($C$21:$C$233=$V$40)*IFERROR($H$21:$H$233,0))) -> 2871077.9 | AB40: =IF(SUMPRODUCT(($C$21:$C$233=$V$40)*ISNUMBER($I$21:$I$233))=0,NA(),SUMPRODUCT(($C$21:$C$233=$V$40)*IFERROR($I$21:$I$233,0))) -> 769632992 | AC40: =IF(SUMPRODUCT(($C$21:$C$233=$V$40)*ISNUMBER($J$21:$J$233))=0,NA(),SUMPRODUCT(($C$21:$C$233=$V$40)*IFERROR($J$21:$J$233,0))/SUMPRODUCT(($C$21:$C$233=$V$40)*ISNUMBER($J$21:$J$233))) -> 1975.0069 | AD40: =IF(SUMPRODUCT(($C$21:$C$233=$V$40)*ISNUMBER($K$21:$K$233))=0,NA(),SUMPRODUCT(($C$21:$C$233=$V$40)*IFERROR($K$21:$K$233,0))/SUMPRODUCT(($C$21:$C$233=$V$40)*ISNUMBER($K$21:$K$233))) -> 296.60518 | AE40: =IF(SUMPRODUCT(($C$21:$C$233=$V$40)*ISNUMBER($L$21:$L$233))=0,NA(),SUMPRODUCT(($C$21:$C$233=$V$40)*IFERROR($L$21:$L$233,0))/SUMPRODUCT(($C$21:$C$233=$V$40)*ISNUMBER($L$21:$L$233))) -> 604.67358 | AF40: =IFERROR(W40/W39-1,NA()) -> -0.01855788
A41: =IFERROR(IF(ISNUMBER('Real and nominal GDP'!A28),'Real and nominal GDP'!A28,NA()),NA()) -> 39873 | B41: =IFERROR(IF('Real and nominal GDP'!B28="",NA(),'Real and nominal GDP'!B28),NA()) -> 091 | C41: =IFERROR(YEAR(A41),0) -> 2009 | D41: =IFERROR(IF('Real and nominal GDP'!C28="",NA(),IF(ISNUMBER('Real and nominal GDP'!C28),'Real and nominal GDP'!C28,NA())),NA()) -> 604940.28 | E41: =IFERROR(IF('Real and nominal GDP'!D28="",NA(),IF(ISNUMBER('Real and nominal GDP'!D28),'Real and nominal GDP'!D28,NA())),NA()) -> 410138.8 | F41: =IFERROR(IF('Real and nominal GDP'!E28="",NA(),IF(ISNUMBER('Real and nominal GDP'!E28),'Real and nominal GDP'!E28,NA())),NA()) -> 70950.321 | G41: =IFERROR(IF('Real and nominal GDP'!F28="",NA(),IF(ISNUMBER('Real and nominal GDP'!F28),'Real and nominal GDP'!F28,NA())),NA()) -> 103713.6 | H41: =IFERROR(IF('Real and nominal GDP'!G28="",NA(),IF(ISNUMBER('Real and nominal GDP'!G28),'Real and nominal GDP'!G28,NA())),NA()) -> 578553.04 | I41: =IFERROR(IF('Real and nominal GDP'!H28="",NA(),IF(ISNUMBER('Real and nominal GDP'!H28),'Real and nominal GDP'!H28,NA())),NA()) -> 1112307 | J41: =IFERROR(IF('Real and nominal GDP'!I28="",NA(),IF(ISNUMBER('Real and nominal GDP'!I28),'Real and nominal GDP'!I28,NA())),NA()) -> #N/A | K41: =IFERROR(IF('Real and nominal GDP'!J28="",NA(),IF(ISNUMBER('Real and nominal GDP'!J28),'Real and nominal GDP'!J28,NA())),NA()) -> 3.5442867 | L41: =IFERROR(IF('Real and nominal GDP'!K28="",NA(),IF(ISNUMBER('Real and nominal GDP'!K28),'Real and nominal GDP'!K28,NA())),NA()) -> 3.6166667 | M41: =IFERROR(D41/D37-1,NA()) -> -0.069327303 | N41: =IFERROR(D41/D40-1,NA()) -> -0.036010337 | O41: =IFERROR(I41/I37-1,NA()) -> 0.07744414 | P41: =IF(COUNT(D38:D41)=4,SUM(D38:D41),NA()) -> 2543641.7 | Q41: =IF(COUNT(I38:I41)=4,SUM(I38:I41),NA()) -> 4678534 | R41: =IFERROR(I41/K41,NA()) -> 313830.99 | S41: =IFERROR(I41/L41,NA()) -> 307550.32 | V41: 2024 | W41: =IF(SUMPRODUCT(($C$21:$C$233=$V$41)*ISNUMBER($D$21:$D$233))=0,NA(),SUMPRODUCT(($C$21:$C$233=$V$41)*IFERROR($D$21:$D$233,0))) -> 2832521.3 | X41: =IF(SUMPRODUCT(($C$21:$C$233=$V$41)*ISNUMBER($E$21:$E$233))=0,NA(),SUMPRODUCT(($C$21:$C$233=$V$41)*IFERROR($E$21:$E$233,0))) -> 2039418.5 | Y41: =IF(SUMPRODUCT(($C$21:$C$233=$V$41)*ISNUMBER($F$21:$F$233))=0,NA(),SUMPRODUCT(($C$21:$C$233=$V$41)*IFERROR($F$21:$F$233,0))) -> 384240.87 | Z41: =IF(SUMPRODUCT(($C$21:$C$233=$V$41)*ISNUMBER($G$21:$G$233))=0,NA(),SUMPRODUCT(($C$21:$C$233=$V$41)*IFERROR($G$21:$G$233,0))) -> 498170.63 | AA41: =IF(SUMPRODUCT(($C$21:$C$233=$V$41)*ISNUMBER($H$21:$H$233))=0,NA(),SUMPRODUCT(($C$21:$C$233=$V$41)*IFERROR($H$21:$H$233,0))) -> 2832521.3 | AB41: =IF(SUMPRODUCT(($C$21:$C$233=$V$41)*ISNUMBER($I$21:$I$233))=0,NA(),SUMPRODUCT(($C$21:$C$233=$V$41)*IFERROR($I$21:$I$233,0))) -> 2335638461 | AC41: =IF(SUMPRODUCT(($C$21:$C$233=$V$41)*ISNUMBER($J$21:$J$233))=0,NA(),SUMPRODUCT(($C$21:$C$233=$V$41)*IFERROR($J$21:$J$233,0))/SUMPRODUCT(($C$21:$C$233=$V$41)*ISNUMBER($J$21:$J$233))) -> 6317.7413 | AD41: =IF(SUMPRODUCT(($C$21:$C$233=$V$41)*ISNUMBER($K$21:$K$233))=0,NA(),SUMPRODUCT(($C$21:$C$233=$V$41)*IFERROR($K$21:$K$233,0))/SUMPRODUCT(($C$21:$C$233=$V$41)*ISNUMBER($K$21:$K$233))) -> 916.28509 | AE41: =IF(SUMPRODUCT(($C$21:$C$233=$V$41)*ISNUMBER($L$21:$L$233))=0,NA(),SUMPRODUCT(($C$21:$C$233=$V$41)*IFERROR($L$21:$L$233,0))/SUMPRODUCT(($C$21:$C$233=$V$41)*ISNUMBER($L$21:$L$233))) -> 1174.0622 | AF41: =IFERROR(W41/W40-1,NA()) -> -0.013429307
A42: =IFERROR(IF(ISNUMBER('Real and nominal GDP'!A29),'Real and nominal GDP'!A29,NA()),NA()) -> 39965 | B42: =IFERROR(IF('Real and nominal GDP'!B29="",NA(),'Real and nominal GDP'!B29),NA()) -> 092 | C42: =IFERROR(YEAR(A42),0) -> 2009 | D42: =IFERROR(IF('Real and nominal GDP'!C29="",NA(),IF(ISNUMBER('Real and nominal GDP'!C29),'Real and nominal GDP'!C29,NA())),NA()) -> 590529.03 | E42: =IFERROR(IF('Real and nominal GDP'!D29="",NA(),IF(ISNUMBER('Real and nominal GDP'!D29),'Real and nominal GDP'!D29,NA())),NA()) -> 392881.86 | F42: =IFERROR(IF('Real and nominal GDP'!E29="",NA(),IF(ISNUMBER('Real and nominal GDP'!E29),'Real and nominal GDP'!E29,NA())),NA()) -> 71924.292 | G42: =IFERROR(IF('Real and nominal GDP'!F29="",NA(),IF(ISNUMBER('Real and nominal GDP'!F29),'Real and nominal GDP'!F29,NA())),NA()) -> 97931.009 | H42: =IFERROR(IF('Real and nominal GDP'!G29="",NA(),IF(ISNUMBER('Real and nominal GDP'!G29),'Real and nominal GDP'!G29,NA())),NA()) -> 631197.75 | I42: =IFERROR(IF('Real and nominal GDP'!H29="",NA(),IF(ISNUMBER('Real and nominal GDP'!H29),'Real and nominal GDP'!H29,NA())),NA()) -> 1251465 | J42: =IFERROR(IF('Real and nominal GDP'!I29="",NA(),IF(ISNUMBER('Real and nominal GDP'!I29),'Real and nominal GDP'!I29,NA())),NA()) -> #N/A | K42: =IFERROR(IF('Real and nominal GDP'!J29="",NA(),IF(ISNUMBER('Real and nominal GDP'!J29),'Real and nominal GDP'!J29,NA())),NA()) -> 3.7293033 | L42: =IFERROR(IF('Real and nominal GDP'!K29="",NA(),IF(ISNUMBER('Real and nominal GDP'!K29),'Real and nominal GDP'!K29,NA())),NA()) -> 3.781 | M42: =IFERROR(D42/D38-1,NA()) -> -0.096315245 | N42: =IFERROR(D42/D41-1,NA()) -> -0.023822609 | O42: =IFERROR(I42/I38-1,NA()) -> 0.03096015 | P42: =IF(COUNT(D39:D42)=4,SUM(D39:D42),NA()) -> 2480702.7 | Q42: =IF(COUNT(I39:I42)=4,SUM(I39:I42),NA()) -> 4716116 | R42: =IFERROR(I42/K42,NA()) -> 335576.08 | S42: =IFERROR(I42/L42,NA()) -> 330987.83 | V42: 2025 | W42: =IF(SUMPRODUCT(($C$21:$C$233=$V$42)*ISNUMBER($D$21:$D$233))=0,NA(),SUMPRODUCT(($C$21:$C$233=$V$42)*IFERROR($D$21:$D$233,0))) -> 2956227 | X42: =IF(SUMPRODUCT(($C$21:$C$233=$V$42)*ISNUMBER($E$21:$E$233))=0,NA(),SUMPRODUCT(($C$21:$C$233=$V$42)*IFERROR($E$21:$E$233,0))) -> 2200003.5 | Y42: =IF(SUMPRODUCT(($C$21:$C$233=$V$42)*ISNUMBER($F$21:$F$233))=0,NA(),SUMPRODUCT(($C$21:$C$233=$V$42)*IFERROR($F$21:$F$233,0))) -> 385090.32 | Z42: =IF(SUMPRODUCT(($C$21:$C$233=$V$42)*ISNUMBER($G$21:$G$233))=0,NA(),SUMPRODUCT(($C$21:$C$233=$V$42)*IFERROR($G$21:$G$233,0))) -> 579660.59 | AA42: =IF(SUMPRODUCT(($C$21:$C$233=$V$42)*ISNUMBER($H$21:$H$233))=0,NA(),SUMPRODUCT(($C$21:$C$233=$V$42)*IFERROR($H$21:$H$233,0))) -> 2956227 | AB42: =IF(SUMPRODUCT(($C$21:$C$233=$V$42)*ISNUMBER($I$21:$I$233))=0,NA(),SUMPRODUCT(($C$21:$C$233=$V$42)*IFERROR($I$21:$I$233,0))) -> 3390491491 | AC42: =IF(SUMPRODUCT(($C$21:$C$233=$V$42)*ISNUMBER($J$21:$J$233))=0,NA(),SUMPRODUCT(($C$21:$C$233=$V$42)*IFERROR($J$21:$J$233,0))/SUMPRODUCT(($C$21:$C$233=$V$42)*ISNUMBER($J$21:$J$233))) -> 8966.1665 | AD42: =IF(SUMPRODUCT(($C$21:$C$233=$V$42)*ISNUMBER($K$21:$K$233))=0,NA(),SUMPRODUCT(($C$21:$C$233=$V$42)*IFERROR($K$21:$K$233,0))/SUMPRODUCT(($C$21:$C$233=$V$42)*ISNUMBER($K$21:$K$233))) -> 1244.5368 | AE42: =IF(SUMPRODUCT(($C$21:$C$233=$V$42)*ISNUMBER($L$21:$L$233))=0,NA(),SUMPRODUCT(($C$21:$C$233=$V$42)*IFERROR($L$21:$L$233,0))/SUMPRODUCT(($C$21:$C$233=$V$42)*ISNUMBER($L$21:$L$233))) -> 1304.809 | AF42: =IFERROR(W42/W41-1,NA()) -> 0.043673333
A43: =IFERROR(IF(ISNUMBER('Real and nominal GDP'!A30),'Real and nominal GDP'!A30,NA()),NA()) -> 40057 | B43: =IFERROR(IF('Real and nominal GDP'!B30="",NA(),'Real and nominal GDP'!B30),NA()) -> 093 | C43: =IFERROR(YEAR(A43),0) -> 2009 | D43: =IFERROR(IF('Real and nominal GDP'!C30="",NA(),IF(ISNUMBER('Real and nominal GDP'!C30),'Real and nominal GDP'!C30,NA())),NA()) -> 613800.26 | E43: =IFERROR(IF('Real and nominal GDP'!D30="",NA(),IF(ISNUMBER('Real and nominal GDP'!D30),'Real and nominal GDP'!D30,NA())),NA()) -> 426604.68 | F43: =IFERROR(IF('Real and nominal GDP'!E30="",NA(),IF(ISNUMBER('Real and nominal GDP'!E30),'Real and nominal GDP'!E30,NA())),NA()) -> 74810.009 | G43: =IFERROR(IF('Real and nominal GDP'!F30="",NA(),IF(ISNUMBER('Real and nominal GDP'!F30),'Real and nominal GDP'!F30,NA())),NA()) -> 103383.82 | H43: =IFERROR(IF('Real and nominal GDP'!G30="",NA(),IF(ISNUMBER('Real and nominal GDP'!G30),'Real and nominal GDP'!G30,NA())),NA()) -> 610519.85 | I43: =IFERROR(IF('Real and nominal GDP'!H30="",NA(),IF(ISNUMBER('Real and nominal GDP'!H30),'Real and nominal GDP'!H30,NA())),NA()) -> 1269735 | J43: =IFERROR(IF('Real and nominal GDP'!I30="",NA(),IF(ISNUMBER('Real and nominal GDP'!I30),'Real and nominal GDP'!I30,NA())),NA()) -> #N/A | K43: =IFERROR(IF('Real and nominal GDP'!J30="",NA(),IF(ISNUMBER('Real and nominal GDP'!J30),'Real and nominal GDP'!J30,NA())),NA()) -> 3.83043 | L43: =IFERROR(IF('Real and nominal GDP'!K30="",NA(),IF(ISNUMBER('Real and nominal GDP'!K30),'Real and nominal GDP'!K30,NA())),NA()) -> 3.857 | M43: =IFERROR(D43/D39-1,NA()) -> -0.066740675 | N43: =IFERROR(D43/D42-1,NA()) -> 0.039407426 | O43: =IFERROR(I43/I39-1,NA()) -> 0.072690362 | P43: =IF(COUNT(D40:D43)=4,SUM(D40:D43),NA()) -> 2436807.7 | Q43: =IF(COUNT(I40:I43)=4,SUM(I40:I43),NA()) -> 4802159 | R43: =IFERROR(I43/K43,NA()) -> 331486.28 | S43: =IFERROR(I43/L43,NA()) -> 329202.75 | V43: 2026 | W43: =IF(SUMPRODUCT(($C$21:$C$233=$V$43)*ISNUMBER($D$21:$D$233))=0,NA(),SUMPRODUCT(($C$21:$C$233=$V$43)*IFERROR($D$21:$D$233,0))) -> #N/A | X43: =IF(SUMPRODUCT(($C$21:$C$233=$V$43)*ISNUMBER($E$21:$E$233))=0,NA(),SUMPRODUCT(($C$21:$C$233=$V$43)*IFERROR($E$21:$E$233,0))) -> #N/A | Y43: =IF(SUMPRODUCT(($C$21:$C$233=$V$43)*ISNUMBER($F$21:$F$233))=0,NA(),SUMPRODUCT(($C$21:$C$233=$V$43)*IFERROR($F$21:$F$233,0))) -> #N/A | Z43: =IF(SUMPRODUCT(($C$21:$C$233=$V$43)*ISNUMBER($G$21:$G$233))=0,NA(),SUMPRODUCT(($C$21:$C$233=$V$43)*IFERROR($G$21:$G$233,0))) -> #N/A | AA43: =IF(SUMPRODUCT(($C$21:$C$233=$V$43)*ISNUMBER($H$21:$H$233))=0,NA(),SUMPRODUCT(($C$21:$C$233=$V$43)*IFERROR($H$21:$H$233,0))) -> #N/A | AB43: =IF(SUMPRODUCT(($C$21:$C$233=$V$43)*ISNUMBER($I$21:$I$233))=0,NA(),SUMPRODUCT(($C$21:$C$233=$V$43)*IFERROR($I$21:$I$233,0))) -> #N/A | AC43: =IF(SUMPRODUCT(($C$21:$C$233=$V$43)*ISNUMBER($J$21:$J$233))=0,NA(),SUMPRODUCT(($C$21:$C$233=$V$43)*IFERROR($J$21:$J$233,0))/SUMPRODUCT(($C$21:$C$233=$V$43)*ISNUMBER($J$21:$J$233))) -> 10734.906 | AD43: =IF(SUMPRODUCT(($C$21:$C$233=$V$43)*ISNUMBER($K$21:$K$233))=0,NA(),SUMPRODUCT(($C$21:$C$233=$V$43)*IFERROR($K$21:$K$233,0))/SUMPRODUCT(($C$21:$C$233=$V$43)*ISNUMBER($K$21:$K$233))) -> 1417.7638 | AE43: =IF(SUMPRODUCT(($C$21:$C$233=$V$43)*ISNUMBER($L$21:$L$233))=0,NA(),SUMPRODUCT(($C$21:$C$233=$V$43)*IFERROR($L$21:$L$233,0))/SUMPRODUCT(($C$21:$C$233=$V$43)*ISNUMBER($L$21:$L$233))) -> 1443.6893 | AF43: =IFERROR(W43/W42-1,NA()) -> #N/A
A44: =IFERROR(IF(ISNUMBER('Real and nominal GDP'!A31),'Real and nominal GDP'!A31,NA()),NA()) -> 40148 | B44: =IFERROR(IF('Real and nominal GDP'!B31="",NA(),'Real and nominal GDP'!B31),NA()) -> 094 | C44: =IFERROR(YEAR(A44),0) -> 2009 | D44: =IFERROR(IF('Real and nominal GDP'!C31="",NA(),IF(ISNUMBER('Real and nominal GDP'!C31),'Real and nominal GDP'!C31,NA())),NA()) -> 626221.94 | E44: =IFERROR(IF('Real and nominal GDP'!D31="",NA(),IF(ISNUMBER('Real and nominal GDP'!D31),'Real and nominal GDP'!D31,NA())),NA()) -> 420460.57 | F44: =IFERROR(IF('Real and nominal GDP'!E31="",NA(),IF(ISNUMBER('Real and nominal GDP'!E31),'Real and nominal GDP'!E31,NA())),NA()) -> 76276.492 | G44: =IFERROR(IF('Real and nominal GDP'!F31="",NA(),IF(ISNUMBER('Real and nominal GDP'!F31),'Real and nominal GDP'!F31,NA())),NA()) -> 109517.35 | H44: =IFERROR(IF('Real and nominal GDP'!G31="",NA(),IF(ISNUMBER('Real and nominal GDP'!G31),'Real and nominal GDP'!G31,NA())),NA()) -> 615220.85 | I44: =IFERROR(IF('Real and nominal GDP'!H31="",NA(),IF(ISNUMBER('Real and nominal GDP'!H31),'Real and nominal GDP'!H31,NA())),NA()) -> 1358210 | J44: =IFERROR(IF('Real and nominal GDP'!I31="",NA(),IF(ISNUMBER('Real and nominal GDP'!I31),'Real and nominal GDP'!I31,NA())),NA()) -> #N/A | K44: =IFERROR(IF('Real and nominal GDP'!J31="",NA(),IF(ISNUMBER('Real and nominal GDP'!J31),'Real and nominal GDP'!J31,NA())),NA()) -> 3.8144267 | L44: =IFERROR(IF('Real and nominal GDP'!K31="",NA(),IF(ISNUMBER('Real and nominal GDP'!K31),'Real and nominal GDP'!K31,NA())),NA()) -> 3.823 | M44: =IFERROR(D44/D40-1,NA()) -> -0.0020974135 | N44: =IFERROR(D44/D43-1,NA()) -> 0.020237333 | O44: =IFERROR(I44/I40-1,NA()) -> 0.16220226 | P44: =IF(COUNT(D41:D44)=4,SUM(D41:D44),NA()) -> 2435491.5 | Q44: =IF(COUNT(I41:I44)=4,SUM(I41:I44),NA()) -> 4991717 | R44: =IFERROR(I44/K44,NA()) -> 356071.86 | S44: =IFERROR(I44/L44,NA()) -> 355273.35 | V44: 2027 | W44: =IF(SUMPRODUCT(($C$21:$C$233=$V$44)*ISNUMBER($D$21:$D$233))=0,NA(),SUMPRODUCT(($C$21:$C$233=$V$44)*IFERROR($D$21:$D$233,0))) -> #N/A | X44: =IF(SUMPRODUCT(($C$21:$C$233=$V$44)*ISNUMBER($E$21:$E$233))=0,NA(),SUMPRODUCT(($C$21:$C$233=$V$44)*IFERROR($E$21:$E$233,0))) -> #N/A | Y44: =IF(SUMPRODUCT(($C$21:$C$233=$V$44)*ISNUMBER($F$21:$F$233))=0,NA(),SUMPRODUCT(($C$21:$C$233=$V$44)*IFERROR($F$21:$F$233,0))) -> #N/A | Z44: =IF(SUMPRODUCT(($C$21:$C$233=$V$44)*ISNUMBER($G$21:$G$233))=0,NA(),SUMPRODUCT(($C$21:$C$233=$V$44)*IFERROR($G$21:$G$233,0))) -> #N/A | AA44: =IF(SUMPRODUCT(($C$21:$C$233=$V$44)*ISNUMBER($H$21:$H$233))=0,NA(),SUMPRODUCT(($C$21:$C$233=$V$44)*IFERROR($H$21:$H$233,0))) -> #N/A | AB44: =IF(SUMPRODUCT(($C$21:$C$233=$V$44)*ISNUMBER($I$21:$I$233))=0,NA(),SUMPRODUCT(($C$21:$C$233=$V$44)*IFERROR($I$21:$I$233,0))) -> #N/A | AC44: =IF(SUMPRODUCT(($C$21:$C$233=$V$44)*ISNUMBER($J$21:$J$233))=0,NA(),SUMPRODUCT(($C$21:$C$233=$V$44)*IFERROR($J$21:$J$233,0))/SUMPRODUCT(($C$21:$C$233=$V$44)*ISNUMBER($J$21:$J$233))) -> #N/A | AD44: =IF(SUMPRODUCT(($C$21:$C$233=$V$44)*ISNUMBER($K$21:$K$233))=0,NA(),SUMPRODUCT(($C$21:$C$233=$V$44)*IFERROR($K$21:$K$233,0))/SUMPRODUCT(($C$21:$C$233=$V$44)*ISNUMBER($K$21:$K$233))) -> #N/A | AE44: =IF(SUMPRODUCT(($C$21:$C$233=$V$44)*ISNUMBER($L$21:$L$233))=0,NA(),SUMPRODUCT(($C$21:$C$233=$V$44)*IFERROR($L$21:$L$233,0))/SUMPRODUCT(($C$21:$C$233=$V$44)*ISNUMBER($L$21:$L$233))) -> #N/A | AF44: =IFERROR(W44/W43-1,NA()) -> #N/A
A45: =IFERROR(IF(ISNUMBER('Real and nominal GDP'!A32),'Real and nominal GDP'!A32,NA()),NA()) -> 40238 | B45: =IFERROR(IF('Real and nominal GDP'!B32="",NA(),'Real and nominal GDP'!B32),NA()) -> 101 | C45: =IFERROR(YEAR(A45),0) -> 2010 | D45: =IFERROR(IF('Real and nominal GDP'!C32="",NA(),IF(ISNUMBER('Real and nominal GDP'!C32),'Real and nominal GDP'!C32,NA())),NA()) -> 645514 | E45: =IFERROR(IF('Real and nominal GDP'!D32="",NA(),IF(ISNUMBER('Real and nominal GDP'!D32),'Real and nominal GDP'!D32,NA())),NA()) -> 440950.58 | F45: =IFERROR(IF('Real and nominal GDP'!E32="",NA(),IF(ISNUMBER('Real and nominal GDP'!E32),'Real and nominal GDP'!E32,NA())),NA()) -> 76147.371 | G45: =IFERROR(IF('Real and nominal GDP'!F32="",NA(),IF(ISNUMBER('Real and nominal GDP'!F32),'Real and nominal GDP'!F32,NA())),NA()) -> 118311.46 | H45: =IFERROR(IF('Real and nominal GDP'!G32="",NA(),IF(ISNUMBER('Real and nominal GDP'!G32),'Real and nominal GDP'!G32,NA())),NA()) -> 611607.34 | I45: =IFERROR(IF('Real and nominal GDP'!H32="",NA(),IF(ISNUMBER('Real and nominal GDP'!H32),'Real and nominal GDP'!H32,NA())),NA()) -> 1418858 | J45: =IFERROR(IF('Real and nominal GDP'!I32="",NA(),IF(ISNUMBER('Real and nominal GDP'!I32),'Real and nominal GDP'!I32,NA())),NA()) -> #N/A | K45: =IFERROR(IF('Real and nominal GDP'!J32="",NA(),IF(ISNUMBER('Real and nominal GDP'!J32),'Real and nominal GDP'!J32,NA())),NA()) -> 3.8391733 | L45: =IFERROR(IF('Real and nominal GDP'!K32="",NA(),IF(ISNUMBER('Real and nominal GDP'!K32),'Real and nominal GDP'!K32,NA())),NA()) -> 3.8996667 | M45: =IFERROR(D45/D41-1,NA()) -> 0.067070609 | N45: =IFERROR(D45/D44-1,NA()) -> 0.030807065 | O45: =IFERROR(I45/I41-1,NA()) -> 0.27559927 | P45: =IF(COUNT(D42:D45)=4,SUM(D42:D45),NA()) -> 2476065.2 | Q45: =IF(COUNT(I42:I45)=4,SUM(I42:I45),NA()) -> 5298268 | R45: =IFERROR(I45/K45,NA()) -> 369573.83 | S45: =IFERROR(I45/L45,NA()) -> 363840.84 | V45: 2028 | W45: =IF(SUMPRODUCT(($C$21:$C$233=$V$45)*ISNUMBER($D$21:$D$233))=0,NA(),SUMPRODUCT(($C$21:$C$233=$V$45)*IFERROR($D$21:$D$233,0))) -> #N/A | X45: =IF(SUMPRODUCT(($C$21:$C$233=$V$45)*ISNUMBER($E$21:$E$233))=0,NA(),SUMPRODUCT(($C$21:$C$233=$V$45)*IFERROR($E$21:$E$233,0))) -> #N/A | Y45: =IF(SUMPRODUCT(($C$21:$C$233=$V$45)*ISNUMBER($F$21:$F$233))=0,NA(),SUMPRODUCT(($C$21:$C$233=$V$45)*IFERROR($F$21:$F$233,0))) -> #N/A | Z45: =IF(SUMPRODUCT(($C$21:$C$233=$V$45)*ISNUMBER($G$21:$G$233))=0,NA(),SUMPRODUCT(($C$21:$C$233=$V$45)*IFERROR($G$21:$G$233,0))) -> #N/A | AA45: =IF(SUMPRODUCT(($C$21:$C$233=$V$45)*ISNUMBER($H$21:$H$233))=0,NA(),SUMPRODUCT(($C$21:$C$233=$V$45)*IFERROR($H$21:$H$233,0))) -> #N/A | AB45: =IF(SUMPRODUCT(($C$21:$C$233=$V$45)*ISNUMBER($I$21:$I$233))=0,NA(),SUMPRODUCT(($C$21:$C$233=$V$45)*IFERROR($I$21:$I$233,0))) -> #N/A | AC45: =IF(SUMPRODUCT(($C$21:$C$233=$V$45)*ISNUMBER($J$21:$J$233))=0,NA(),SUMPRODUCT(($C$21:$C$233=$V$45)*IFERROR($J$21:$J$233,0))/SUMPRODUCT(($C$21:$C$233=$V$45)*ISNUMBER($J$21:$J$233))) -> #N/A | AD45: =IF(SUMPRODUCT(($C$21:$C$233=$V$45)*ISNUMBER($K$21:$K$233))=0,NA(),SUMPRODUCT(($C$21:$C$233=$V$45)*IFERROR($K$21:$K$233,0))/SUMPRODUCT(($C$21:$C$233=$V$45)*ISNUMBER($K$21:$K$233))) -> #N/A | AE45: =IF(SUMPRODUCT(($C$21:$C$233=$V$45)*ISNUMBER($L$21:$L$233))=0,NA(),SUMPRODUCT(($C$21:$C$233=$V$45)*IFERROR($L$21:$L$233,0))/SUMPRODUCT(($C$21:$C$233=$V$45)*ISNUMBER($L$21:$L$233))) -> #N/A | AF45: =IFERROR(W45/W44-1,NA()) -> #N/A
A46: =IFERROR(IF(ISNUMBER('Real and nominal GDP'!A33),'Real and nominal GDP'!A33,NA()),NA()) -> 40330 | B46: =IFERROR(IF('Real and nominal GDP'!B33="",NA(),'Real and nominal GDP'!B33),NA()) -> 102 | C46: =IFERROR(YEAR(A46),0) -> 2010 | D46: =IFERROR(IF('Real and nominal GDP'!C33="",NA(),IF(ISNUMBER('Real and nominal GDP'!C33),'Real and nominal GDP'!C33,NA())),NA()) -> 674164.23 | E46: =IFERROR(IF('Real and nominal GDP'!D33="",NA(),IF(ISNUMBER('Real and nominal GDP'!D33),'Real and nominal GDP'!D33,NA())),NA()) -> 457719.24 | F46: =IFERROR(IF('Real and nominal GDP'!E33="",NA(),IF(ISNUMBER('Real and nominal GDP'!E33),'Real and nominal GDP'!E33,NA())),NA()) -> 77531.513 | G46: =IFERROR(IF('Real and nominal GDP'!F33="",NA(),IF(ISNUMBER('Real and nominal GDP'!F33),'Real and nominal GDP'!F33,NA())),NA()) -> 129032.37 | H46: =IFERROR(IF('Real and nominal GDP'!G33="",NA(),IF(ISNUMBER('Real and nominal GDP'!G33),'Real and nominal GDP'!G33,NA())),NA()) -> 733730.77 | I46: =IFERROR(IF('Real and nominal GDP'!H33="",NA(),IF(ISNUMBER('Real and nominal GDP'!H33),'Real and nominal GDP'!H33,NA())),NA()) -> 1686067 | J46: =IFERROR(IF('Real and nominal GDP'!I33="",NA(),IF(ISNUMBER('Real and nominal GDP'!I33),'Real and nominal GDP'!I33,NA())),NA()) -> #N/A | K46: =IFERROR(IF('Real and nominal GDP'!J33="",NA(),IF(ISNUMBER('Real and nominal GDP'!J33),'Real and nominal GDP'!J33,NA())),NA()) -> 3.9013767 | L46: =IFERROR(IF('Real and nominal GDP'!K33="",NA(),IF(ISNUMBER('Real and nominal GDP'!K33),'Real and nominal GDP'!K33,NA())),NA()) -> 3.95 | M46: =IFERROR(D46/D42-1,NA()) -> 0.1416276 | N46: =IFERROR(D46/D45-1,NA()) -> 0.044383605 | O46: =IFERROR(I46/I42-1,NA()) -> 0.34727459 | P46: =IF(COUNT(D43:D46)=4,SUM(D43:D46),NA()) -> 2559700.4 | Q46: =IF(COUNT(I43:I46)=4,SUM(I43:I46),NA()) -> 5732870 | R46: =IFERROR(I46/K46,NA()) -> 432172.32 | S46: =IFERROR(I46/L46,NA()) -> 426852.41 | V46: 2029 | W46: =IF(SUMPRODUCT(($C$21:$C$233=$V$46)*ISNUMBER($D$21:$D$233))=0,NA(),SUMPRODUCT(($C$21:$C$233=$V$46)*IFERROR($D$21:$D$233,0))) -> #N/A | X46: =IF(SUMPRODUCT(($C$21:$C$233=$V$46)*ISNUMBER($E$21:$E$233))=0,NA(),SUMPRODUCT(($C$21:$C$233=$V$46)*IFERROR($E$21:$E$233,0))) -> #N/A | Y46: =IF(SUMPRODUCT(($C$21:$C$233=$V$46)*ISNUMBER($F$21:$F$233))=0,NA(),SUMPRODUCT(($C$21:$C$233=$V$46)*IFERROR($F$21:$F$233,0))) -> #N/A | Z46: =IF(SUMPRODUCT(($C$21:$C$233=$V$46)*ISNUMBER($G$21:$G$233))=0,NA(),SUMPRODUCT(($C$21:$C$233=$V$46)*IFERROR($G$21:$G$233,0))) -> #N/A | AA46: =IF(SUMPRODUCT(($C$21:$C$233=$V$46)*ISNUMBER($H$21:$H$233))=0,NA(),SUMPRODUCT(($C$21:$C$233=$V$46)*IFERROR($H$21:$H$233,0))) -> #N/A | AB46: =IF(SUMPRODUCT(($C$21:$C$233=$V$46)*ISNUMBER($I$21:$I$233))=0,NA(),SUMPRODUCT(($C$21:$C$233=$V$46)*IFERROR($I$21:$I$233,0))) -> #N/A | AC46: =IF(SUMPRODUCT(($C$21:$C$233=$V$46)*ISNUMBER($J$21:$J$233))=0,NA(),SUMPRODUCT(($C$21:$C$233=$V$46)*IFERROR($J$21:$J$233,0))/SUMPRODUCT(($C$21:$C$233=$V$46)*ISNUMBER($J$21:$J$233))) -> #N/A | AD46: =IF(SUMPRODUCT(($C$21:$C$233=$V$46)*ISNUMBER($K$21:$K$233))=0,NA(),SUMPRODUCT(($C$21:$C$233=$V$46)*IFERROR($K$21:$K$233,0))/SUMPRODUCT(($C$21:$C$233=$V$46)*ISNUMBER($K$21:$K$233))) -> #N/A | AE46: =IF(SUMPRODUCT(($C$21:$C$233=$V$46)*ISNUMBER($L$21:$L$233))=0,NA(),SUMPRODUCT(($C$21:$C$233=$V$46)*IFERROR($L$21:$L$233,0))/SUMPRODUCT(($C$21:$C$233=$V$46)*ISNUMBER($L$21:$L$233))) -> #N/A | AF46: =IFERROR(W46/W45-1,NA()) -> #N/A
A47: =IFERROR(IF(ISNUMBER('Real and nominal GDP'!A34),'Real and nominal GDP'!A34,NA()),NA()) -> 40422 | B47: =IFERROR(IF('Real and nominal GDP'!B34="",NA(),'Real and nominal GDP'!B34),NA()) -> 103 | C47: =IFERROR(YEAR(A47),0) -> 2010 | D47: =IFERROR(IF('Real and nominal GDP'!C34="",NA(),IF(ISNUMBER('Real and nominal GDP'!C34),'Real and nominal GDP'!C34,NA())),NA()) -> 676995.54 | E47: =IFERROR(IF('Real and nominal GDP'!D34="",NA(),IF(ISNUMBER('Real and nominal GDP'!D34),'Real and nominal GDP'!D34,NA())),NA()) -> 462315.45 | F47: =IFERROR(IF('Real and nominal GDP'!E34="",NA(),IF(ISNUMBER('Real and nominal GDP'!E34),'Real and nominal GDP'!E34,NA())),NA()) -> 76551.465 | G47: =IFERROR(IF('Real and nominal GDP'!F34="",NA(),IF(ISNUMBER('Real and nominal GDP'!F34),'Real and nominal GDP'!F34,NA())),NA()) -> 133774.83 | H47: =IFERROR(IF('Real and nominal GDP'!G34="",NA(),IF(ISNUMBER('Real and nominal GDP'!G34),'Real and nominal GDP'!G34,NA())),NA()) -> 668566.51 | I47: =IFERROR(IF('Real and nominal GDP'!H34="",NA(),IF(ISNUMBER('Real and nominal GDP'!H34),'Real and nominal GDP'!H34,NA())),NA()) -> 1712835 | J47: =IFERROR(IF('Real and nominal GDP'!I34="",NA(),IF(ISNUMBER('Real and nominal GDP'!I34),'Real and nominal GDP'!I34,NA())),NA()) -> #N/A | K47: =IFERROR(IF('Real and nominal GDP'!J34="",NA(),IF(ISNUMBER('Real and nominal GDP'!J34),'Real and nominal GDP'!J34,NA())),NA()) -> 3.94155 | L47: =IFERROR(IF('Real and nominal GDP'!K34="",NA(),IF(ISNUMBER('Real and nominal GDP'!K34),'Real and nominal GDP'!K34,NA())),NA()) -> 4.0066667 | M47: =IFERROR(D47/D43-1,NA()) -> 0.10295741 | N47: =IFERROR(D47/D46-1,NA()) -> 0.0041997259 | O47: =IFERROR(I47/I43-1,NA()) -> 0.34897045 | P47: =IF(COUNT(D44:D47)=4,SUM(D44:D47),NA()) -> 2622895.7 | Q47: =IF(COUNT(I44:I47)=4,SUM(I44:I47),NA()) -> 6175970 | R47: =IFERROR(I47/K47,NA()) -> 434558.74 | S47: =IFERROR(I47/L47,NA()) -> 427496.26 | V47: 2030 | W47: =IF(SUMPRODUCT(($C$21:$C$233=$V$47)*ISNUMBER($D$21:$D$233))=0,NA(),SUMPRODUCT(($C$21:$C$233=$V$47)*IFERROR($D$21:$D$233,0))) -> #N/A | X47: =IF(SUMPRODUCT(($C$21:$C$233=$V$47)*ISNUMBER($E$21:$E$233))=0,NA(),SUMPRODUCT(($C$21:$C$233=$V$47)*IFERROR($E$21:$E$233,0))) -> #N/A | Y47: =IF(SUMPRODUCT(($C$21:$C$233=$V$47)*ISNUMBER($F$21:$F$233))=0,NA(),SUMPRODUCT(($C$21:$C$233=$V$47)*IFERROR($F$21:$F$233,0))) -> #N/A | Z47: =IF(SUMPRODUCT(($C$21:$C$233=$V$47)*ISNUMBER($G$21:$G$233))=0,NA(),SUMPRODUCT(($C$21:$C$233=$V$47)*IFERROR($G$21:$G$233,0))) -> #N/A | AA47: =IF(SUMPRODUCT(($C$21:$C$233=$V$47)*ISNUMBER($H$21:$H$233))=0,NA(),SUMPRODUCT(($C$21:$C$233=$V$47)*IFERROR($H$21:$H$233,0))) -> #N/A | AB47: =IF(SUMPRODUCT(($C$21:$C$233=$V$47)*ISNUMBER($I$21:$I$233))=0,NA(),SUMPRODUCT(($C$21:$C$233=$V$47)*IFERROR($I$21:$I$233,0))) -> #N/A | AC47: =IF(SUMPRODUCT(($C$21:$C$233=$V$47)*ISNUMBER($J$21:$J$233))=0,NA(),SUMPRODUCT(($C$21:$C$233=$V$47)*IFERROR($J$21:$J$233,0))/SUMPRODUCT(($C$21:$C$233=$V$47)*ISNUMBER($J$21:$J$233))) -> #N/A | AD47: =IF(SUMPRODUCT(($C$21:$C$233=$V$47)*ISNUMBER($K$21:$K$233))=0,NA(),SUMPRODUCT(($C$21:$C$233=$V$47)*IFERROR($K$21:$K$233,0))/SUMPRODUCT(($C$21:$C$233=$V$47)*ISNUMBER($K$21:$K$233))) -> #N/A | AE47: =IF(SUMPRODUCT(($C$21:$C$233=$V$47)*ISNUMBER($L$21:$L$233))=0,NA(),SUMPRODUCT(($C$21:$C$233=$V$47)*IFERROR($L$21:$L$233,0))/SUMPRODUCT(($C$21:$C$233=$V$47)*ISNUMBER($L$21:$L$233))) -> #N/A | AF47: =IFERROR(W47/W46-1,NA()) -> #N/A
A48: =IFERROR(IF(ISNUMBER('Real and nominal GDP'!A35),'Real and nominal GDP'!A35,NA()),NA()) -> 40513 | B48: =IFERROR(IF('Real and nominal GDP'!B35="",NA(),'Real and nominal GDP'!B35),NA()) -> 104 | C48: =IFERROR(YEAR(A48),0) -> 2010 | D48: =IFERROR(IF('Real and nominal GDP'!C35="",NA(),IF(ISNUMBER('Real and nominal GDP'!C35),'Real and nominal GDP'!C35,NA())),NA()) -> 685420.94 | E48: =IFERROR(IF('Real and nominal GDP'!D35="",NA(),IF(ISNUMBER('Real and nominal GDP'!D35),'Real and nominal GDP'!D35,NA())),NA()) -> 473715.39 | F48: =IFERROR(IF('Real and nominal GDP'!E35="",NA(),IF(ISNUMBER('Real and nominal GDP'!E35),'Real and nominal GDP'!E35,NA())),NA()) -> 79758.041 | G48: =IFERROR(IF('Real and nominal GDP'!F35="",NA(),IF(ISNUMBER('Real and nominal GDP'!F35),'Real and nominal GDP'!F35,NA())),NA()) -> 142264.38 | H48: =IFERROR(IF('Real and nominal GDP'!G35="",NA(),IF(ISNUMBER('Real and nominal GDP'!G35),'Real and nominal GDP'!G35,NA())),NA()) -> 668190.1 | I48: =IFERROR(IF('Real and nominal GDP'!H35="",NA(),IF(ISNUMBER('Real and nominal GDP'!H35),'Real and nominal GDP'!H35,NA())),NA()) -> 1829124 | J48: =IFERROR(IF('Real and nominal GDP'!I35="",NA(),IF(ISNUMBER('Real and nominal GDP'!I35),'Real and nominal GDP'!I35,NA())),NA()) -> #N/A | K48: =IFERROR(IF('Real and nominal GDP'!J35="",NA(),IF(ISNUMBER('Real and nominal GDP'!J35),'Real and nominal GDP'!J35,NA())),NA()) -> 3.96725 | L48: =IFERROR(IF('Real and nominal GDP'!K35="",NA(),IF(ISNUMBER('Real and nominal GDP'!K35),'Real and nominal GDP'!K35,NA())),NA()) -> 4.0436667 | M48: =IFERROR(D48/D44-1,NA()) -> 0.09453359 | N48: =IFERROR(D48/D47-1,NA()) -> 0.012445289 | O48: =IFERROR(I48/I44-1,NA()) -> 0.34671663 | P48: =IF(COUNT(D45:D48)=4,SUM(D45:D48),NA()) -> 2682094.7 | Q48: =IF(COUNT(I45:I48)=4,SUM(I45:I48),NA()) -> 6646884 | R48: =IFERROR(I48/K48,NA()) -> 461055.9 | S48: =IFERROR(I48/L48,NA()) -> 452342.92 | V48: 2031 | W48: =IF(SUMPRODUCT(($C$21:$C$233=$V$48)*ISNUMBER($D$21:$D$233))=0,NA(),SUMPRODUCT(($C$21:$C$233=$V$48)*IFERROR($D$21:$D$233,0))) -> #N/A | X48: =IF(SUMPRODUCT(($C$21:$C$233=$V$48)*ISNUMBER($E$21:$E$233))=0,NA(),SUMPRODUCT(($C$21:$C$233=$V$48)*IFERROR($E$21:$E$233,0))) -> #N/A | Y48: =IF(SUMPRODUCT(($C$21:$C$233=$V$48)*ISNUMBER($F$21:$F$233))=0,NA(),SUMPRODUCT(($C$21:$C$233=$V$48)*IFERROR($F$21:$F$233,0))) -> #N/A | Z48: =IF(SUMPRODUCT(($C$21:$C$233=$V$48)*ISNUMBER($G$21:$G$233))=0,NA(),SUMPRODUCT(($C$21:$C$233=$V$48)*IFERROR($G$21:$G$233,0))) -> #N/A | AA48: =IF(SUMPRODUCT(($C$21:$C$233=$V$48)*ISNUMBER($H$21:$H$233))=0,NA(),SUMPRODUCT(($C$21:$C$233=$V$48)*IFERROR($H$21:$H$233,0))) -> #N/A | AB48: =IF(SUMPRODUCT(($C$21:$C$233=$V$48)*ISNUMBER($I$21:$I$233))=0,NA(),SUMPRODUCT(($C$21:$C$233=$V$48)*IFERROR($I$21:$I$233,0))) -> #N/A | AC48: =IF(SUMPRODUCT(($C$21:$C$233=$V$48)*ISNUMBER($J$21:$J$233))=0,NA(),SUMPRODUCT(($C$21:$C$233=$V$48)*IFERROR($J$21:$J$233,0))/SUMPRODUCT(($C$21:$C$233=$V$48)*ISNUMBER($J$21:$J$233))) -> #N/A | AD48: =IF(SUMPRODUCT(($C$21:$C$233=$V$48)*ISNUMBER($K$21:$K$233))=0,NA(),SUMPRODUCT(($C$21:$C$233=$V$48)*IFERROR($K$21:$K$233,0))/SUMPRODUCT(($C$21:$C$233=$V$48)*ISNUMBER($K$21:$K$233))) -> #N/A | AE48: =IF(SUMPRODUCT(($C$21:$C$233=$V$48)*ISNUMBER($L$21:$L$233))=0,NA(),SUMPRODUCT(($C$21:$C$233=$V$48)*IFERROR($L$21:$L$233,0))/SUMPRODUCT(($C$21:$C$233=$V$48)*ISNUMBER($L$21:$L$233))) -> #N/A | AF48: =IFERROR(W48/W47-1,NA()) -> #N/A
A49: =IFERROR(IF(ISNUMBER('Real and nominal GDP'!A36),'Real and nominal GDP'!A36,NA()),NA()) -> 40603 | B49: =IFERROR(IF('Real and nominal GDP'!B36="",NA(),'Real and nominal GDP'!B36),NA()) -> 111 | C49: =IFERROR(YEAR(A49),0) -> 2011 | D49: =IFERROR(IF('Real and nominal GDP'!C36="",NA(),IF(ISNUMBER('Real and nominal GDP'!C36),'Real and nominal GDP'!C36,NA())),NA()) -> 701686.92 | E49: =IFERROR(IF('Real and nominal GDP'!D36="",NA(),IF(ISNUMBER('Real and nominal GDP'!D36),'Real and nominal GDP'!D36,NA())),NA()) -> 488345.02 | F49: =IFERROR(IF('Real and nominal GDP'!E36="",NA(),IF(ISNUMBER('Real and nominal GDP'!E36),'Real and nominal GDP'!E36,NA())),NA()) -> 79621.178 | G49: =IFERROR(IF('Real and nominal GDP'!F36="",NA(),IF(ISNUMBER('Real and nominal GDP'!F36),'Real and nominal GDP'!F36,NA())),NA()) -> 149901.36 | H49: =IFERROR(IF('Real and nominal GDP'!G36="",NA(),IF(ISNUMBER('Real and nominal GDP'!G36),'Real and nominal GDP'!G36,NA())),NA()) -> 662325.59 | I49: =IFERROR(IF('Real and nominal GDP'!H36="",NA(),IF(ISNUMBER('Real and nominal GDP'!H36),'Real and nominal GDP'!H36,NA())),NA()) -> 1888827 | J49: =IFERROR(IF('Real and nominal GDP'!I36="",NA(),IF(ISNUMBER('Real and nominal GDP'!I36),'Real and nominal GDP'!I36,NA())),NA()) -> #N/A | K49: =IFERROR(IF('Real and nominal GDP'!J36="",NA(),IF(ISNUMBER('Real and nominal GDP'!J36),'Real and nominal GDP'!J36,NA())),NA()) -> 4.01408 | L49: =IFERROR(IF('Real and nominal GDP'!K36="",NA(),IF(ISNUMBER('Real and nominal GDP'!K36),'Real and nominal GDP'!K36,NA())),NA()) -> 4.143 | M49: =IFERROR(D49/D45-1,NA()) -> 0.087020459 | N49: =IFERROR(D49/D48-1,NA()) -> 0.023731367 | O49: =IFERROR(I49/I45-1,NA()) -> 0.33123047 | P49: =IF(COUNT(D46:D49)=4,SUM(D46:D49),NA()) -> 2738267.6 | Q49: =IF(COUNT(I46:I49)=4,SUM(I46:I49),NA()) -> 7116853 | R49: =IFERROR(I49/K49,NA()) -> 470550.41 | S49: =IFERROR(I49/L49,NA()) -> 455908.04 | V49: 2032 | W49: =IF(SUMPRODUCT(($C$21:$C$233=$V$49)*ISNUMBER($D$21:$D$233))=0,NA(),SUMPRODUCT(($C$21:$C$233=$V$49)*IFERROR($D$21:$D$233,0))) -> #N/A | X49: =IF(SUMPRODUCT(($C$21:$C$233=$V$49)*ISNUMBER($E$21:$E$233))=0,NA(),SUMPRODUCT(($C$21:$C$233=$V$49)*IFERROR($E$21:$E$233,0))) -> #N/A | Y49: =IF(SUMPRODUCT(($C$21:$C$233=$V$49)*ISNUMBER($F$21:$F$233))=0,NA(),SUMPRODUCT(($C$21:$C$233=$V$49)*IFERROR($F$21:$F$233,0))) -> #N/A | Z49: =IF(SUMPRODUCT(($C$21:$C$233=$V$49)*ISNUMBER($G$21:$G$233))=0,NA(),SUMPRODUCT(($C$21:$C$233=$V$49)*IFERROR($G$21:$G$233,0))) -> #N/A | AA49: =IF(SUMPRODUCT(($C$21:$C$233=$V$49)*ISNUMBER($H$21:$H$233))=0,NA(),SUMPRODUCT(($C$21:$C$233=$V$49)*IFERROR($H$21:$H$233,0))) -> #N/A | AB49: =IF(SUMPRODUCT(($C$21:$C$233=$V$49)*ISNUMBER($I$21:$I$233))=0,NA(),SUMPRODUCT(($C$21:$C$233=$V$49)*IFERROR($I$21:$I$233,0))) -> #N/A | AC49: =IF(SUMPRODUCT(($C$21:$C$233=$V$49)*ISNUMBER($J$21:$J$233))=0,NA(),SUMPRODUCT(($C$21:$C$233=$V$49)*IFERROR($J$21:$J$233,0))/SUMPRODUCT(($C$21:$C$233=$V$49)*ISNUMBER($J$21:$J$233))) -> #N/A | AD49: =IF(SUMPRODUCT(($C$21:$C$233=$V$49)*ISNUMBER($K$21:$K$233))=0,NA(),SUMPRODUCT(($C$21:$C$233=$V$49)*IFERROR($K$21:$K$233,0))/SUMPRODUCT(($C$21:$C$233=$V$49)*ISNUMBER($K$21:$K$233))) -> #N/A | AE49: =IF(SUMPRODUCT(($C$21:$C$233=$V$49)*ISNUMBER($L$21:$L$233))=0,NA(),SUMPRODUCT(($C$21:$C$233=$V$49)*IFERROR($L$21:$L$233,0))/SUMPRODUCT(($C$21:$C$233=$V$49)*ISNUMBER($L$21:$L$233))) -> #N/A | AF49: =IFERROR(W49/W48-1,NA()) -> #N/A
A50: =IFERROR(IF(ISNUMBER('Real and nominal GDP'!A37),'Real and nominal GDP'!A37,NA()),NA()) -> 40695 | B50: =IFERROR(IF('Real and nominal GDP'!B37="",NA(),'Real and nominal GDP'!B37),NA()) -> 112 | C50: =IFERROR(YEAR(A50),0) -> 2011 | D50: =IFERROR(IF('Real and nominal GDP'!C37="",NA(),IF(ISNUMBER('Real and nominal GDP'!C37),'Real and nominal GDP'!C37,NA())),NA()) -> 710326.16 | E50: =IFERROR(IF('Real and nominal GDP'!D37="",NA(),IF(ISNUMBER('Real and nominal GDP'!D37),'Real and nominal GDP'!D37,NA())),NA()) -> 496352.55 | F50: =IFERROR(IF('Real and nominal GDP'!E37="",NA(),IF(ISNUMBER('Real and nominal GDP'!E37),'Real and nominal GDP'!E37,NA())),NA()) -> 81079.657 | G50: =IFERROR(IF('Real and nominal GDP'!F37="",NA(),IF(ISNUMBER('Real and nominal GDP'!F37),'Real and nominal GDP'!F37,NA())),NA()) -> 153356.92 | H50: =IFERROR(IF('Real and nominal GDP'!G37="",NA(),IF(ISNUMBER('Real and nominal GDP'!G37),'Real and nominal GDP'!G37,NA())),NA()) -> 766332.95 | I50: =IFERROR(IF('Real and nominal GDP'!H37="",NA(),IF(ISNUMBER('Real and nominal GDP'!H37),'Real and nominal GDP'!H37,NA())),NA()) -> 2237124 | J50: =IFERROR(IF('Real and nominal GDP'!I37="",NA(),IF(ISNUMBER('Real and nominal GDP'!I37),'Real and nominal GDP'!I37,NA())),NA()) -> #N/A | K50: =IFERROR(IF('Real and nominal GDP'!J37="",NA(),IF(ISNUMBER('Real and nominal GDP'!J37),'Real and nominal GDP'!J37,NA())),NA()) -> 4.0820167 | L50: =IFERROR(IF('Real and nominal GDP'!K37="",NA(),IF(ISNUMBER('Real and nominal GDP'!K37),'Real and nominal GDP'!K37,NA())),NA()) -> 4.2636667 | M50: =IFERROR(D50/D46-1,NA()) -> 0.05363963 | N50: =IFERROR(D50/D49-1,NA()) -> 0.012312092 | O50: =IFERROR(I50/I46-1,NA()) -> 0.32682984 | P50: =IF(COUNT(D47:D50)=4,SUM(D47:D50),NA()) -> 2774429.6 | Q50: =IF(COUNT(I47:I50)=4,SUM(I47:I50),NA()) -> 7667910 | R50: =IFERROR(I50/K50,NA()) -> 548043.82 | S50: =IFERROR(I50/L50,NA()) -> 524694.86 | V50: 2033 | W50: =IF(SUMPRODUCT(($C$21:$C$233=$V$50)*ISNUMBER($D$21:$D$233))=0,NA(),SUMPRODUCT(($C$21:$C$233=$V$50)*IFERROR($D$21:$D$233,0))) -> #N/A | X50: =IF(SUMPRODUCT(($C$21:$C$233=$V$50)*ISNUMBER($E$21:$E$233))=0,NA(),SUMPRODUCT(($C$21:$C$233=$V$50)*IFERROR($E$21:$E$233,0))) -> #N/A | Y50: =IF(SUMPRODUCT(($C$21:$C$233=$V$50)*ISNUMBER($F$21:$F$233))=0,NA(),SUMPRODUCT(($C$21:$C$233=$V$50)*IFERROR($F$21:$F$233,0))) -> #N/A | Z50: =IF(SUMPRODUCT(($C$21:$C$233=$V$50)*ISNUMBER($G$21:$G$233))=0,NA(),SUMPRODUCT(($C$21:$C$233=$V$50)*IFERROR($G$21:$G$233,0))) -> #N/A | AA50: =IF(SUMPRODUCT(($C$21:$C$233=$V$50)*ISNUMBER($H$21:$H$233))=0,NA(),SUMPRODUCT(($C$21:$C$233=$V$50)*IFERROR($H$21:$H$233,0))) -> #N/A | AB50: =IF(SUMPRODUCT(($C$21:$C$233=$V$50)*ISNUMBER($I$21:$I$233))=0,NA(),SUMPRODUCT(($C$21:$C$233=$V$50)*IFERROR($I$21:$I$233,0))) -> #N/A | AC50: =IF(SUMPRODUCT(($C$21:$C$233=$V$50)*ISNUMBER($J$21:$J$233))=0,NA(),SUMPRODUCT(($C$21:$C$233=$V$50)*IFERROR($J$21:$J$233,0))/SUMPRODUCT(($C$21:$C$233=$V$50)*ISNUMBER($J$21:$J$233))) -> #N/A | AD50: =IF(SUMPRODUCT(($C$21:$C$233=$V$50)*ISNUMBER($K$21:$K$233))=0,NA(),SUMPRODUCT(($C$21:$C$233=$V$50)*IFERROR($K$21:$K$233,0))/SUMPRODUCT(($C$21:$C$233=$V$50)*ISNUMBER($K$21:$K$233))) -> #N/A | AE50: =IF(SUMPRODUCT(($C$21:$C$233=$V$50)*ISNUMBER($L$21:$L$233))=0,NA(),SUMPRODUCT(($C$21:$C$233=$V$50)*IFERROR($L$21:$L$233,0))/SUMPRODUCT(($C$21:$C$233=$V$50)*ISNUMBER($L$21:$L$233))) -> #N/A | AF50: =IFERROR(W50/W49-1,NA()) -> #N/A
A51: =IFERROR(IF(ISNUMBER('Real and nominal GDP'!A38),'Real and nominal GDP'!A38,NA()),NA()) -> 40787 | B51: =IFERROR(IF('Real and nominal GDP'!B38="",NA(),'Real and nominal GDP'!B38),NA()) -> 113 | C51: =IFERROR(YEAR(A51),0) -> 2011 | D51: =IFERROR(IF('Real and nominal GDP'!C38="",NA(),IF(ISNUMBER('Real and nominal GDP'!C38),'Real and nominal GDP'!C38,NA())),NA()) -> 715883.91 | E51: =IFERROR(IF('Real and nominal GDP'!D38="",NA(),IF(ISNUMBER('Real and nominal GDP'!D38),'Real and nominal GDP'!D38,NA())),NA()) -> 510643.56 | F51: =IFERROR(IF('Real and nominal GDP'!E38="",NA(),IF(ISNUMBER('Real and nominal GDP'!E38),'Real and nominal GDP'!E38,NA())),NA()) -> 81880.489 | G51: =IFERROR(IF('Real and nominal GDP'!F38="",NA(),IF(ISNUMBER('Real and nominal GDP'!F38),'Real and nominal GDP'!F38,NA())),NA()) -> 157856.26 | H51: =IFERROR(IF('Real and nominal GDP'!G38="",NA(),IF(ISNUMBER('Real and nominal GDP'!G38),'Real and nominal GDP'!G38,NA())),NA()) -> 711417.39 | I51: =IFERROR(IF('Real and nominal GDP'!H38="",NA(),IF(ISNUMBER('Real and nominal GDP'!H38),'Real and nominal GDP'!H38,NA())),NA()) -> 2250487 | J51: =IFERROR(IF('Real and nominal GDP'!I38="",NA(),IF(ISNUMBER('Real and nominal GDP'!I38),'Real and nominal GDP'!I38,NA())),NA()) -> #N/A | K51: =IFERROR(IF('Real and nominal GDP'!J38="",NA(),IF(ISNUMBER('Real and nominal GDP'!J38),'Real and nominal GDP'!J38,NA())),NA()) -> 4.1667833 | L51: =IFERROR(IF('Real and nominal GDP'!K38="",NA(),IF(ISNUMBER('Real and nominal GDP'!K38),'Real and nominal GDP'!K38,NA())),NA()) -> 4.365 | M51: =IFERROR(D51/D47-1,NA()) -> 0.057442581 | N51: =IFERROR(D51/D50-1,NA()) -> 0.0078242311 | O51: =IFERROR(I51/I47-1,NA()) -> 0.31389597 | P51: =IF(COUNT(D48:D51)=4,SUM(D48:D51),NA()) -> 2813317.9 | Q51: =IF(COUNT(I48:I51)=4,SUM(I48:I51),NA()) -> 8205562 | R51: =IFERROR(I51/K51,NA()) -> 540101.76 | S51: =IFERROR(I51/L51,NA()) -> 515575.49
A52: =IFERROR(IF(ISNUMBER('Real and nominal GDP'!A39),'Real and nominal GDP'!A39,NA()),NA()) -> 40878 | B52: =IFERROR(IF('Real and nominal GDP'!B39="",NA(),'Real and nominal GDP'!B39),NA()) -> 114 | C52: =IFERROR(YEAR(A52),0) -> 2011 | D52: =IFERROR(IF('Real and nominal GDP'!C39="",NA(),IF(ISNUMBER('Real and nominal GDP'!C39),'Real and nominal GDP'!C39,NA())),NA()) -> 715229.4 | E52: =IFERROR(IF('Real and nominal GDP'!D39="",NA(),IF(ISNUMBER('Real and nominal GDP'!D39),'Real and nominal GDP'!D39,NA())),NA()) -> 511247.49 | F52: =IFERROR(IF('Real and nominal GDP'!E39="",NA(),IF(ISNUMBER('Real and nominal GDP'!E39),'Real and nominal GDP'!E39,NA())),NA()) -> 81557.755 | G52: =IFERROR(IF('Real and nominal GDP'!F39="",NA(),IF(ISNUMBER('Real and nominal GDP'!F39),'Real and nominal GDP'!F39,NA())),NA()) -> 153221.8 | H52: =IFERROR(IF('Real and nominal GDP'!G39="",NA(),IF(ISNUMBER('Real and nominal GDP'!G39),'Real and nominal GDP'!G39,NA())),NA()) -> 703050.46 | I52: =IFERROR(IF('Real and nominal GDP'!H39="",NA(),IF(ISNUMBER('Real and nominal GDP'!H39),'Real and nominal GDP'!H39,NA())),NA()) -> 2339658 | J52: =IFERROR(IF('Real and nominal GDP'!I39="",NA(),IF(ISNUMBER('Real and nominal GDP'!I39),'Real and nominal GDP'!I39,NA())),NA()) -> #N/A | K52: =IFERROR(IF('Real and nominal GDP'!J39="",NA(),IF(ISNUMBER('Real and nominal GDP'!J39),'Real and nominal GDP'!J39,NA())),NA()) -> 4.2571767 | L52: =IFERROR(IF('Real and nominal GDP'!K39="",NA(),IF(ISNUMBER('Real and nominal GDP'!K39),'Real and nominal GDP'!K39,NA())),NA()) -> 4.602 | M52: =IFERROR(D52/D48-1,NA()) -> 0.043489271 | N52: =IFERROR(D52/D51-1,NA()) -> -0.00091426695 | O52: =IFERROR(I52/I48-1,NA()) -> 0.27911394 | P52: =IF(COUNT(D49:D52)=4,SUM(D49:D52),NA()) -> 2843126.4 | Q52: =IF(COUNT(I49:I52)=4,SUM(I49:I52),NA()) -> 8716096 | R52: =IFERROR(I52/K52,NA()) -> 549579.73 | S52: =IFERROR(I52/L52,NA()) -> 508400.26
A53: =IFERROR(IF(ISNUMBER('Real and nominal GDP'!A40),'Real and nominal GDP'!A40,NA()),NA()) -> 40969 | B53: =IFERROR(IF('Real and nominal GDP'!B40="",NA(),'Real and nominal GDP'!B40),NA()) -> 121 | C53: =IFERROR(YEAR(A53),0) -> 2012 | D53: =IFERROR(IF('Real and nominal GDP'!C40="",NA(),IF(ISNUMBER('Real and nominal GDP'!C40),'Real and nominal GDP'!C40,NA())),NA()) -> 708348.86 | E53: =IFERROR(IF('Real and nominal GDP'!D40="",NA(),IF(ISNUMBER('Real and nominal GDP'!D40),'Real and nominal GDP'!D40,NA())),NA()) -> 499862.9 | F53: =IFERROR(IF('Real and nominal GDP'!E40="",NA(),IF(ISNUMBER('Real and nominal GDP'!E40),'Real and nominal GDP'!E40,NA())),NA()) -> 82408.506 | G53: =IFERROR(IF('Real and nominal GDP'!F40="",NA(),IF(ISNUMBER('Real and nominal GDP'!F40),'Real and nominal GDP'!F40,NA())),NA()) -> 145161.64 | H53: =IFERROR(IF('Real and nominal GDP'!G40="",NA(),IF(ISNUMBER('Real and nominal GDP'!G40),'Real and nominal GDP'!G40,NA())),NA()) -> 672685.99 | I53: =IFERROR(IF('Real and nominal GDP'!H40="",NA(),IF(ISNUMBER('Real and nominal GDP'!H40),'Real and nominal GDP'!H40,NA())),NA()) -> 2345560 | J53: =IFERROR(IF('Real and nominal GDP'!I40="",NA(),IF(ISNUMBER('Real and nominal GDP'!I40),'Real and nominal GDP'!I40,NA())),NA()) -> #N/A | K53: =IFERROR(IF('Real and nominal GDP'!J40="",NA(),IF(ISNUMBER('Real and nominal GDP'!J40),'Real and nominal GDP'!J40,NA())),NA()) -> 4.34134 | L53: =IFERROR(IF('Real and nominal GDP'!K40="",NA(),IF(ISNUMBER('Real and nominal GDP'!K40),'Real and nominal GDP'!K40,NA())),NA()) -> 4.7793333 | M53: =IFERROR(D53/D49-1,NA()) -> 0.0094941772 | N53: =IFERROR(D53/D52-1,NA()) -> -0.0096200478 | O53: =IFERROR(I53/I49-1,NA()) -> 0.24180775 | P53: =IF(COUNT(D50:D53)=4,SUM(D50:D53),NA()) -> 2849788.3 | Q53: =IF(COUNT(I50:I53)=4,SUM(I50:I53),NA()) -> 9172829 | R53: =IFERROR(I53/K53,NA()) -> 540284.8 | S53: =IFERROR(I53/L53,NA()) -> 490771.38
A54: =IFERROR(IF(ISNUMBER('Real and nominal GDP'!A41),'Real and nominal GDP'!A41,NA()),NA()) -> 41061 | B54: =IFERROR(IF('Real and nominal GDP'!B41="",NA(),'Real and nominal GDP'!B41),NA()) -> 122 | C54: =IFERROR(YEAR(A54),0) -> 2012 | D54: =IFERROR(IF('Real and nominal GDP'!C41="",NA(),IF(ISNUMBER('Real and nominal GDP'!C41),'Real and nominal GDP'!C41,NA())),NA()) -> 683593.32 | E54: =IFERROR(IF('Real and nominal GDP'!D41="",NA(),IF(ISNUMBER('Real and nominal GDP'!D41),'Real and nominal GDP'!D41,NA())),NA()) -> 493768.88 | F54: =IFERROR(IF('Real and nominal GDP'!E41="",NA(),IF(ISNUMBER('Real and nominal GDP'!E41),'Real and nominal GDP'!E41,NA())),NA()) -> 82764.047 | G54: =IFERROR(IF('Real and nominal GDP'!F41="",NA(),IF(ISNUMBER('Real and nominal GDP'!F41),'Real and nominal GDP'!F41,NA())),NA()) -> 133906.72 | H54: =IFERROR(IF('Real and nominal GDP'!G41="",NA(),IF(ISNUMBER('Real and nominal GDP'!G41),'Real and nominal GDP'!G41,NA())),NA()) -> 730838.27 | I54: =IFERROR(IF('Real and nominal GDP'!H41="",NA(),IF(ISNUMBER('Real and nominal GDP'!H41),'Real and nominal GDP'!H41,NA())),NA()) -> 2651098 | J54: =IFERROR(IF('Real and nominal GDP'!I41="",NA(),IF(ISNUMBER('Real and nominal GDP'!I41),'Real and nominal GDP'!I41,NA())),NA()) -> #N/A | K54: =IFERROR(IF('Real and nominal GDP'!J41="",NA(),IF(ISNUMBER('Real and nominal GDP'!J41),'Real and nominal GDP'!J41,NA())),NA()) -> 4.4497267 | L54: =IFERROR(IF('Real and nominal GDP'!K41="",NA(),IF(ISNUMBER('Real and nominal GDP'!K41),'Real and nominal GDP'!K41,NA())),NA()) -> 5.468 | M54: =IFERROR(D54/D50-1,NA()) -> -0.037634598 | N54: =IFERROR(D54/D53-1,NA()) -> -0.034948239 | O54: =IFERROR(I54/I50-1,NA()) -> 0.18504741 | P54: =IF(COUNT(D51:D54)=4,SUM(D51:D54),NA()) -> 2823055.5 | Q54: =IF(COUNT(I51:I54)=4,SUM(I51:I54),NA()) -> 9586803 | R54: =IFERROR(I54/K54,NA()) -> 595788.95 | S54: =IFERROR(I54/L54,NA()) -> 484838.7
A55: =IFERROR(IF(ISNUMBER('Real and nominal GDP'!A42),'Real and nominal GDP'!A42,NA()),NA()) -> 41153 | B55: =IFERROR(IF('Real and nominal GDP'!B42="",NA(),'Real and nominal GDP'!B42),NA()) -> 123 | C55: =IFERROR(YEAR(A55),0) -> 2012 | D55: =IFERROR(IF('Real and nominal GDP'!C42="",NA(),IF(ISNUMBER('Real and nominal GDP'!C42),'Real and nominal GDP'!C42,NA())),NA()) -> 705293.74 | E55: =IFERROR(IF('Real and nominal GDP'!D42="",NA(),IF(ISNUMBER('Real and nominal GDP'!D42),'Real and nominal GDP'!D42,NA())),NA()) -> 515643.41 | F55: =IFERROR(IF('Real and nominal GDP'!E42="",NA(),IF(ISNUMBER('Real and nominal GDP'!E42),'Real and nominal GDP'!E42,NA())),NA()) -> 84004.922 | G55: =IFERROR(IF('Real and nominal GDP'!F42="",NA(),IF(ISNUMBER('Real and nominal GDP'!F42),'Real and nominal GDP'!F42,NA())),NA()) -> 143391.77 | H55: =IFERROR(IF('Real and nominal GDP'!G42="",NA(),IF(ISNUMBER('Real and nominal GDP'!G42),'Real and nominal GDP'!G42,NA())),NA()) -> 703461.65 | I55: =IFERROR(IF('Real and nominal GDP'!H42="",NA(),IF(ISNUMBER('Real and nominal GDP'!H42),'Real and nominal GDP'!H42,NA())),NA()) -> 2704828 | J55: =IFERROR(IF('Real and nominal GDP'!I42="",NA(),IF(ISNUMBER('Real and nominal GDP'!I42),'Real and nominal GDP'!I42,NA())),NA()) -> 29.739833 | K55: =IFERROR(IF('Real and nominal GDP'!J42="",NA(),IF(ISNUMBER('Real and nominal GDP'!J42),'Real and nominal GDP'!J42,NA())),NA()) -> 4.6116067 | L55: =IFERROR(IF('Real and nominal GDP'!K42="",NA(),IF(ISNUMBER('Real and nominal GDP'!K42),'Real and nominal GDP'!K42,NA())),NA()) -> 6.2866667 | M55: =IFERROR(D55/D51-1,NA()) -> -0.014793135 | N55: =IFERROR(D55/D54-1,NA()) -> 0.031744646 | O55: =IFERROR(I55/I51-1,NA()) -> 0.20188564 | P55: =IF(COUNT(D52:D55)=4,SUM(D52:D55),NA()) -> 2812465.3 | Q55: =IF(COUNT(I52:I55)=4,SUM(I52:I55),NA()) -> 10041144 | R55: =IFERROR(I55/K55,NA()) -> 586526.17 | S55: =IFERROR(I55/L55,NA()) -> 430248.36
A56: =IFERROR(IF(ISNUMBER('Real and nominal GDP'!A43),'Real and nominal GDP'!A43,NA()),NA()) -> 41244 | B56: =IFERROR(IF('Real and nominal GDP'!B43="",NA(),'Real and nominal GDP'!B43),NA()) -> 124 | C56: =IFERROR(YEAR(A56),0) -> 2012 | D56: =IFERROR(IF('Real and nominal GDP'!C43="",NA(),IF(ISNUMBER('Real and nominal GDP'!C43),'Real and nominal GDP'!C43,NA())),NA()) -> 716708.04 | E56: =IFERROR(IF('Real and nominal GDP'!D43="",NA(),IF(ISNUMBER('Real and nominal GDP'!D43),'Real and nominal GDP'!D43,NA())),NA()) -> 519592.21 | F56: =IFERROR(IF('Real and nominal GDP'!E43="",NA(),IF(ISNUMBER('Real and nominal GDP'!E43),'Real and nominal GDP'!E43,NA())),NA()) -> 84715.909 | G56: =IFERROR(IF('Real and nominal GDP'!F43="",NA(),IF(ISNUMBER('Real and nominal GDP'!F43),'Real and nominal GDP'!F43,NA())),NA()) -> 148410.68 | H56: =IFERROR(IF('Real and nominal GDP'!G43="",NA(),IF(ISNUMBER('Real and nominal GDP'!G43),'Real and nominal GDP'!G43,NA())),NA()) -> 706958.04 | I56: =IFERROR(IF('Real and nominal GDP'!H43="",NA(),IF(ISNUMBER('Real and nominal GDP'!H43),'Real and nominal GDP'!H43,NA())),NA()) -> 2850170 | J56: =IFERROR(IF('Real and nominal GDP'!I43="",NA(),IF(ISNUMBER('Real and nominal GDP'!I43),'Real and nominal GDP'!I43,NA())),NA()) -> 31.3387 | K56: =IFERROR(IF('Real and nominal GDP'!J43="",NA(),IF(ISNUMBER('Real and nominal GDP'!J43),'Real and nominal GDP'!J43,NA())),NA()) -> 4.80352 | L56: =IFERROR(IF('Real and nominal GDP'!K43="",NA(),IF(ISNUMBER('Real and nominal GDP'!K43),'Real and nominal GDP'!K43,NA())),NA()) -> 6.3916667 | M56: =IFERROR(D56/D52-1,NA()) -> 0.0020673563 | N56: =IFERROR(D56/D55-1,NA()) -> 0.016183742 | O56: =IFERROR(I56/I52-1,NA()) -> 0.21819941 | P56: =IF(COUNT(D53:D56)=4,SUM(D53:D56),NA()) -> 2813944 | Q56: =IF(COUNT(I53:I56)=4,SUM(I53:I56),NA()) -> 10551656 | R56: =IFERROR(I56/K56,NA()) -> 593350.29 | S56: =IFERROR(I56/L56,NA()) -> 445919.69
A57: =IFERROR(IF(ISNUMBER('Real and nominal GDP'!A44),'Real and nominal GDP'!A44,NA()),NA()) -> 41334 | B57: =IFERROR(IF('Real and nominal GDP'!B44="",NA(),'Real and nominal GDP'!B44),NA()) -> 131 | C57: =IFERROR(YEAR(A57),0) -> 2013 | D57: =IFERROR(IF('Real and nominal GDP'!C44="",NA(),IF(ISNUMBER('Real and nominal GDP'!C44),'Real and nominal GDP'!C44,NA())),NA()) -> 715943.74 | E57: =IFERROR(IF('Real and nominal GDP'!D44="",NA(),IF(ISNUMBER('Real and nominal GDP'!D44),'Real and nominal GDP'!D44,NA())),NA()) -> 514386.79 | F57: =IFERROR(IF('Real and nominal GDP'!E44="",NA(),IF(ISNUMBER('Real and nominal GDP'!E44),'Real and nominal GDP'!E44,NA())),NA()) -> 86326.806 | G57: =IFERROR(IF('Real and nominal GDP'!F44="",NA(),IF(ISNUMBER('Real and nominal GDP'!F44),'Real and nominal GDP'!F44,NA())),NA()) -> 145736 | H57: =IFERROR(IF('Real and nominal GDP'!G44="",NA(),IF(ISNUMBER('Real and nominal GDP'!G44),'Real and nominal GDP'!G44,NA())),NA()) -> 677085.53 | I57: =IFERROR(IF('Real and nominal GDP'!H44="",NA(),IF(ISNUMBER('Real and nominal GDP'!H44),'Real and nominal GDP'!H44,NA())),NA()) -> 2888981 | J57: =IFERROR(IF('Real and nominal GDP'!I44="",NA(),IF(ISNUMBER('Real and nominal GDP'!I44),'Real and nominal GDP'!I44,NA())),NA()) -> 33.105433 | K57: =IFERROR(IF('Real and nominal GDP'!J44="",NA(),IF(ISNUMBER('Real and nominal GDP'!J44),'Real and nominal GDP'!J44,NA())),NA()) -> 5.0156467 | L57: =IFERROR(IF('Real and nominal GDP'!K44="",NA(),IF(ISNUMBER('Real and nominal GDP'!K44),'Real and nominal GDP'!K44,NA())),NA()) -> 7.721 | M57: =IFERROR(D57/D53-1,NA()) -> 0.010721944 | N57: =IFERROR(D57/D56-1,NA()) -> -0.0010664008 | O57: =IFERROR(I57/I53-1,NA()) -> 0.23168071 | P57: =IF(COUNT(D54:D57)=4,SUM(D54:D57),NA()) -> 2821538.8 | Q57: =IF(COUNT(I54:I57)=4,SUM(I54:I57),NA()) -> 11095077 | R57: =IFERROR(I57/K57,NA()) -> 575993.72 | S57: =IFERROR(I57/L57,NA()) -> 374171.87
A58: =IFERROR(IF(ISNUMBER('Real and nominal GDP'!A45),'Real and nominal GDP'!A45,NA()),NA()) -> 41426 | B58: =IFERROR(IF('Real and nominal GDP'!B45="",NA(),'Real and nominal GDP'!B45),NA()) -> 132 | C58: =IFERROR(YEAR(A58),0) -> 2013 | D58: =IFERROR(IF('Real and nominal GDP'!C45="",NA(),IF(ISNUMBER('Real and nominal GDP'!C45),'Real and nominal GDP'!C45,NA())),NA()) -> 720882.85 | E58: =IFERROR(IF('Real and nominal GDP'!D45="",NA(),IF(ISNUMBER('Real and nominal GDP'!D45),'Real and nominal GDP'!D45,NA())),NA()) -> 517251.74 | F58: =IFERROR(IF('Real and nominal GDP'!E45="",NA(),IF(ISNUMBER('Real and nominal GDP'!E45),'Real and nominal GDP'!E45,NA())),NA()) -> 87404.109 | G58: =IFERROR(IF('Real and nominal GDP'!F45="",NA(),IF(ISNUMBER('Real and nominal GDP'!F45),'Real and nominal GDP'!F45,NA())),NA()) -> 147670.82 | H58: =IFERROR(IF('Real and nominal GDP'!G45="",NA(),IF(ISNUMBER('Real and nominal GDP'!G45),'Real and nominal GDP'!G45,NA())),NA()) -> 776486.6 | I58: =IFERROR(IF('Real and nominal GDP'!H45="",NA(),IF(ISNUMBER('Real and nominal GDP'!H45),'Real and nominal GDP'!H45,NA())),NA()) -> 3387811 | J58: =IFERROR(IF('Real and nominal GDP'!I45="",NA(),IF(ISNUMBER('Real and nominal GDP'!I45),'Real and nominal GDP'!I45,NA())),NA()) -> 34.798233 | K58: =IFERROR(IF('Real and nominal GDP'!J45="",NA(),IF(ISNUMBER('Real and nominal GDP'!J45),'Real and nominal GDP'!J45,NA())),NA()) -> 5.2423567 | L58: =IFERROR(IF('Real and nominal GDP'!K45="",NA(),IF(ISNUMBER('Real and nominal GDP'!K45),'Real and nominal GDP'!K45,NA())),NA()) -> 8.7116667 | M58: =IFERROR(D58/D54-1,NA()) -> 0.054549299 | N58: =IFERROR(D58/D57-1,NA()) -> 0.006898746 | O58: =IFERROR(I58/I54-1,NA()) -> 0.27788976 | P58: =IF(COUNT(D55:D58)=4,SUM(D55:D58),NA()) -> 2858828.4 | Q58: =IF(COUNT(I55:I58)=4,SUM(I55:I58),NA()) -> 11831790 | R58: =IFERROR(I58/K58,NA()) -> 646238.17 | S58: =IFERROR(I58/L58,NA()) -> 388882.07
A59: =IFERROR(IF(ISNUMBER('Real and nominal GDP'!A46),'Real and nominal GDP'!A46,NA()),NA()) -> 41518 | B59: =IFERROR(IF('Real and nominal GDP'!B46="",NA(),'Real and nominal GDP'!B46),NA()) -> 133 | C59: =IFERROR(YEAR(A59),0) -> 2013 | D59: =IFERROR(IF('Real and nominal GDP'!C46="",NA(),IF(ISNUMBER('Real and nominal GDP'!C46),'Real and nominal GDP'!C46,NA())),NA()) -> 725588.38 | E59: =IFERROR(IF('Real and nominal GDP'!D46="",NA(),IF(ISNUMBER('Real and nominal GDP'!D46),'Real and nominal GDP'!D46,NA())),NA()) -> 535655.93 | F59: =IFERROR(IF('Real and nominal GDP'!E46="",NA(),IF(ISNUMBER('Real and nominal GDP'!E46),'Real and nominal GDP'!E46,NA())),NA()) -> 87951.009 | G59: =IFERROR(IF('Real and nominal GDP'!F46="",NA(),IF(ISNUMBER('Real and nominal GDP'!F46),'Real and nominal GDP'!F46,NA())),NA()) -> 145972.59 | H59: =IFERROR(IF('Real and nominal GDP'!G46="",NA(),IF(ISNUMBER('Real and nominal GDP'!G46),'Real and nominal GDP'!G46,NA())),NA()) -> 721458.94 | I59: =IFERROR(IF('Real and nominal GDP'!H46="",NA(),IF(ISNUMBER('Real and nominal GDP'!H46),'Real and nominal GDP'!H46,NA())),NA()) -> 3436547 | J59: =IFERROR(IF('Real and nominal GDP'!I46="",NA(),IF(ISNUMBER('Real and nominal GDP'!I46),'Real and nominal GDP'!I46,NA())),NA()) -> 37.0408 | K59: =IFERROR(IF('Real and nominal GDP'!J46="",NA(),IF(ISNUMBER('Real and nominal GDP'!J46),'Real and nominal GDP'!J46,NA())),NA()) -> 5.58808 | L59: =IFERROR(IF('Real and nominal GDP'!K46="",NA(),IF(ISNUMBER('Real and nominal GDP'!K46),'Real and nominal GDP'!K46,NA())),NA()) -> 8.8253333 | M59: =IFERROR(D59/D55-1,NA()) -> 0.028774731 | N59: =IFERROR(D59/D58-1,NA()) -> 0.0065274545 | O59: =IFERROR(I59/I55-1,NA()) -> 0.2705233 | P59: =IF(COUNT(D56:D59)=4,SUM(D56:D59),NA()) -> 2879123 | Q59: =IF(COUNT(I56:I59)=4,SUM(I56:I59),NA()) -> 12563509 | R59: =IFERROR(I59/K59,NA()) -> 614978.13 | S59: =IFERROR(I59/L59,NA()) -> 389395.72
A60: =IFERROR(IF(ISNUMBER('Real and nominal GDP'!A47),'Real and nominal GDP'!A47,NA()),NA()) -> 41609 | B60: =IFERROR(IF('Real and nominal GDP'!B47="",NA(),'Real and nominal GDP'!B47),NA()) -> 134 | C60: =IFERROR(YEAR(A60),0) -> 2013 | D60: =IFERROR(IF('Real and nominal GDP'!C47="",NA(),IF(ISNUMBER('Real and nominal GDP'!C47),'Real and nominal GDP'!C47,NA())),NA()) -> 719213.45 | E60: =IFERROR(IF('Real and nominal GDP'!D47="",NA(),IF(ISNUMBER('Real and nominal GDP'!D47),'Real and nominal GDP'!D47,NA())),NA()) -> 535403.67 | F60: =IFERROR(IF('Real and nominal GDP'!E47="",NA(),IF(ISNUMBER('Real and nominal GDP'!E47),'Real and nominal GDP'!E47,NA())),NA()) -> 89983.227 | G60: =IFERROR(IF('Real and nominal GDP'!F47="",NA(),IF(ISNUMBER('Real and nominal GDP'!F47),'Real and nominal GDP'!F47,NA())),NA()) -> 144846.87 | H60: =IFERROR(IF('Real and nominal GDP'!G47="",NA(),IF(ISNUMBER('Real and nominal GDP'!G47),'Real and nominal GDP'!G47,NA())),NA()) -> 706597.34 | I60: =IFERROR(IF('Real and nominal GDP'!H47="",NA(),IF(ISNUMBER('Real and nominal GDP'!H47),'Real and nominal GDP'!H47,NA())),NA()) -> 3679896 | J60: =IFERROR(IF('Real and nominal GDP'!I47="",NA(),IF(ISNUMBER('Real and nominal GDP'!I47),'Real and nominal GDP'!I47,NA())),NA()) -> 39.5626 | K60: =IFERROR(IF('Real and nominal GDP'!J47="",NA(),IF(ISNUMBER('Real and nominal GDP'!J47),'Real and nominal GDP'!J47,NA())),NA()) -> 6.0668567 | L60: =IFERROR(IF('Real and nominal GDP'!K47="",NA(),IF(ISNUMBER('Real and nominal GDP'!K47),'Real and nominal GDP'!K47,NA())),NA()) -> 9.723 | M60: =IFERROR(D60/D56-1,NA()) -> 0.0034957247 | N60: =IFERROR(D60/D59-1,NA()) -> -0.0087858794 | O60: =IFERROR(I60/I56-1,NA()) -> 0.29111457 | P60: =IF(COUNT(D57:D60)=4,SUM(D57:D60),NA()) -> 2881628.4 | Q60: =IF(COUNT(I57:I60)=4,SUM(I57:I60),NA()) -> 13393235 | R60: =IFERROR(I60/K60,NA()) -> 606557.27 | S60: =IFERROR(I60/L60,NA()) -> 378473.31
A61: =IFERROR(IF(ISNUMBER('Real and nominal GDP'!A48),'Real and nominal GDP'!A48,NA()),NA()) -> 41699 | B61: =IFERROR(IF('Real and nominal GDP'!B48="",NA(),'Real and nominal GDP'!B48),NA()) -> 141 | C61: =IFERROR(YEAR(A61),0) -> 2014 | D61: =IFERROR(IF('Real and nominal GDP'!C48="",NA(),IF(ISNUMBER('Real and nominal GDP'!C48),'Real and nominal GDP'!C48,NA())),NA()) -> 708278.97 | E61: =IFERROR(IF('Real and nominal GDP'!D48="",NA(),IF(ISNUMBER('Real and nominal GDP'!D48),'Real and nominal GDP'!D48,NA())),NA()) -> 521790.9 | F61: =IFERROR(IF('Real and nominal GDP'!E48="",NA(),IF(ISNUMBER('Real and nominal GDP'!E48),'Real and nominal GDP'!E48,NA())),NA()) -> 90817.606 | G61: =IFERROR(IF('Real and nominal GDP'!F48="",NA(),IF(ISNUMBER('Real and nominal GDP'!F48),'Real and nominal GDP'!F48,NA())),NA()) -> 141725.87 | H61: =IFERROR(IF('Real and nominal GDP'!G48="",NA(),IF(ISNUMBER('Real and nominal GDP'!G48),'Real and nominal GDP'!G48,NA())),NA()) -> 671066.05 | I61: =IFERROR(IF('Real and nominal GDP'!H48="",NA(),IF(ISNUMBER('Real and nominal GDP'!H48),'Real and nominal GDP'!H48,NA())),NA()) -> 3917649 | J61: =IFERROR(IF('Real and nominal GDP'!I48="",NA(),IF(ISNUMBER('Real and nominal GDP'!I48),'Real and nominal GDP'!I48,NA())),NA()) -> 44.1826 | K61: =IFERROR(IF('Real and nominal GDP'!J48="",NA(),IF(ISNUMBER('Real and nominal GDP'!J48),'Real and nominal GDP'!J48,NA())),NA()) -> 7.6322467 | L61: =IFERROR(IF('Real and nominal GDP'!K48="",NA(),IF(ISNUMBER('Real and nominal GDP'!K48),'Real and nominal GDP'!K48,NA())),NA()) -> 11.300333 | M61: =IFERROR(D61/D57-1,NA()) -> -0.01070582 | N61: =IFERROR(D61/D60-1,NA()) -> -0.015203382 | O61: =IFERROR(I61/I57-1,NA()) -> 0.35606603 | P61: =IF(COUNT(D58:D61)=4,SUM(D58:D61),NA()) -> 2873963.7 | Q61: =IF(COUNT(I58:I61)=4,SUM(I58:I61),NA()) -> 14421903 | R61: =IFERROR(I61/K61,NA()) -> 513302.2 | S61: =IFERROR(I61/L61,NA()) -> 346684.38
A62: =IFERROR(IF(ISNUMBER('Real and nominal GDP'!A49),'Real and nominal GDP'!A49,NA()),NA()) -> 41791 | B62: =IFERROR(IF('Real and nominal GDP'!B49="",NA(),'Real and nominal GDP'!B49),NA()) -> 142 | C62: =IFERROR(YEAR(A62),0) -> 2014 | D62: =IFERROR(IF('Real and nominal GDP'!C49="",NA(),IF(ISNUMBER('Real and nominal GDP'!C49),'Real and nominal GDP'!C49,NA())),NA()) -> 702914.57 | E62: =IFERROR(IF('Real and nominal GDP'!D49="",NA(),IF(ISNUMBER('Real and nominal GDP'!D49),'Real and nominal GDP'!D49,NA())),NA()) -> 498942.24 | F62: =IFERROR(IF('Real and nominal GDP'!E49="",NA(),IF(ISNUMBER('Real and nominal GDP'!E49),'Real and nominal GDP'!E49,NA())),NA()) -> 89305.792 | G62: =IFERROR(IF('Real and nominal GDP'!F49="",NA(),IF(ISNUMBER('Real and nominal GDP'!F49),'Real and nominal GDP'!F49,NA())),NA()) -> 139110.59 | H62: =IFERROR(IF('Real and nominal GDP'!G49="",NA(),IF(ISNUMBER('Real and nominal GDP'!G49),'Real and nominal GDP'!G49,NA())),NA()) -> 760576.87 | I62: =IFERROR(IF('Real and nominal GDP'!H49="",NA(),IF(ISNUMBER('Real and nominal GDP'!H49),'Real and nominal GDP'!H49,NA())),NA()) -> 4702630 | J62: =IFERROR(IF('Real and nominal GDP'!I49="",NA(),IF(ISNUMBER('Real and nominal GDP'!I49),'Real and nominal GDP'!I49,NA())),NA()) -> 48.474633 | K62: =IFERROR(IF('Real and nominal GDP'!J49="",NA(),IF(ISNUMBER('Real and nominal GDP'!J49),'Real and nominal GDP'!J49,NA())),NA()) -> 8.0561933 | L62: =IFERROR(IF('Real and nominal GDP'!K49="",NA(),IF(ISNUMBER('Real and nominal GDP'!K49),'Real and nominal GDP'!K49,NA())),NA()) -> 11.125333 | M62: =IFERROR(D62/D58-1,NA()) -> -0.024925381 | N62: =IFERROR(D62/D61-1,NA()) -> -0.0075738532 | O62: =IFERROR(I62/I58-1,NA()) -> 0.38810282 | P62: =IF(COUNT(D59:D62)=4,SUM(D59:D62),NA()) -> 2855995.4 | Q62: =IF(COUNT(I59:I62)=4,SUM(I59:I62),NA()) -> 15736722 | R62: =IFERROR(I62/K62,NA()) -> 583728.54 | S62: =IFERROR(I62/L62,NA()) -> 422695.65
... A233: =IFERROR(IF(ISNUMBER('Real and nominal GDP'!A220),'Real and nominal GDP'!A220,NA()),NA()) -> #N/A | B233: =IFERROR(IF('Real and nominal GDP'!B220="",NA(),'Real and nominal GDP'!B220),NA()) -> #N/A | C233: =IFERROR(YEAR(A233),0) -> 0 | D233: =IFERROR(IF('Real and nominal GDP'!C220="",NA(),IF(ISNUMBER('Real and nominal GDP'!C220),'Real and nominal GDP'!C220,NA())),NA()) -> #N/A | E233: =IFERROR(IF('Real and nominal GDP'!D220="",NA(),IF(ISNUMBER('Real and nominal GDP'!D220),'Real and nominal GDP'!D220,NA())),NA()) -> #N/A | F233: =IFERROR(IF('Real and nominal GDP'!E220="",NA(),IF(ISNUMBER('Real and nominal GDP'!E220),'Real and nominal GDP'!E220,NA())),NA()) -> #N/A | G233: =IFERROR(IF('Real and nominal GDP'!F220="",NA(),IF(ISNUMBER('Real and nominal GDP'!F220),'Real and nominal GDP'!F220,NA())),NA()) -> #N/A | H233: =IFERROR(IF('Real and nominal GDP'!G220="",NA(),IF(ISNUMBER('Real and nominal GDP'!G220),'Real and nominal GDP'!G220,NA())),NA()) -> #N/A | I233: =IFERROR(IF('Real and nominal GDP'!H220="",NA(),IF(ISNUMBER('Real and nominal GDP'!H220),'Real and nominal GDP'!H220,NA())),NA()) -> #N/A | J233: =IFERROR(IF('Real and nominal GDP'!I220="",NA(),IF(ISNUMBER('Real and nominal GDP'!I220),'Real and nominal GDP'!I220,NA())),NA()) -> #N/A | K233: =IFERROR(IF('Real and nominal GDP'!J220="",NA(),IF(ISNUMBER('Real and nominal GDP'!J220),'Real and nominal GDP'!J220,NA())),NA()) -> #N/A | L233: =IFERROR(IF('Real and nominal GDP'!K220="",NA(),IF(ISNUMBER('Real and nominal GDP'!K220),'Real and nominal GDP'!K220,NA())),NA()) -> #N/A | M233: =IFERROR(D233/D229-1,NA()) -> #N/A | N233: =IFERROR(D233/D232-1,NA()) -> #N/A | O233: =IFERROR(I233/I229-1,NA()) -> #N/A | P233: =IF(COUNT(D230:D233)=4,SUM(D230:D233),NA()) -> #N/A | Q233: =IF(COUNT(I230:I233)=4,SUM(I230:I233),NA()) -> #N/A | R233: =IFERROR(I233/K233,NA()) -> #N/A | S233: =IFERROR(I233/L233,NA()) -> #N/A

Sheet CPI Analysis
A1: CPI Analysis — Argentina
A2: Linked to raw tab 'CPI'. Refresh by pasting new Haver download over row 8+. Formulas extend to row 264 (≈21 yrs buffer).
A4: SETTINGS
A5: Annual aggregation method | B5: Average | D5: (Sum = flow vars; Average = indices/rates; End of Period = stocks)
A7: PROJECTION ASSUMPTIONS (annual YoY %)
A8: Series | B8: Year +1 YoY % | C8: Year +2 YoY %
A9: Headline CPI | B9: 0.4 | C9: 0.25
A10: Core CPI | B10: 0.38 | C10: 0.24
A12: DATA & ANALYTICS (linked from raw tab) | L12: ANNUAL AGGREGATION | R12: PROJECTIONS (annual)
A13: Date | B13: Period | C13: Year | D13: Headline CPI | E13: Core CPI | F13: YoY % Headline CPI | G13: MoM % Headline CPI | H13: 3M MA | I13: YoY %, 3M avg | L13: Year | M13: Headline CPI | N13: Core CPI | O13: YoY % Headline CPI | R13: Year | S13: Headline CPI (proj.) | T13: Core CPI (proj.)
A14: =IFERROR(IF(LEN(TRIM(TEXT(CPI!B8,"@")))<3,NA(),DATE(2000+VALUE(LEFT(CPI!B8,LEN(CPI!B8)-2)),VALUE(RIGHT(CPI!B8,2)),1)),NA()) -> 42005 | B14: =IFERROR(IF(CPI!B8="",NA(),CPI!B8),NA()) -> 1501 | C14: =IFERROR(YEAR(A14),0) -> 2015 | D14: =IFERROR(IF(CPI!C8="",NA(),IF(ISNUMBER(CPI!C8),CPI!C8,NA())),NA()) -> 56.9509 | E14: =IFERROR(IF(CPI!D8="",NA(),IF(ISNUMBER(CPI!D8),CPI!D8,NA())),NA()) -> #N/A | F14: =NA() -> #N/A | G14: =NA() -> #N/A | H14: =NA() -> #N/A | I14: =NA() -> #N/A | L14: 2004 | M14: =IF(SUMPRODUCT(($C$14:$C$266=$L$14)*ISNUMBER($D$14:$D$266))=0,NA(),SUMPRODUCT(($C$14:$C$266=$L$14)*IFERROR($D$14:$D$266,0))/SUMPRODUCT(($C$14:$C$266=$L$14)*ISNUMBER($D$14:$D$266))) -> #N/A | N14: =IF(SUMPRODUCT(($C$14:$C$266=$L$14)*ISNUMBER($E$14:$E$266))=0,NA(),SUMPRODUCT(($C$14:$C$266=$L$14)*IFERROR($E$14:$E$266,0))/SUMPRODUCT(($C$14:$C$266=$L$14)*ISNUMBER($E$14:$E$266))) -> #N/A | O14: =NA() -> #N/A | R14: =IFERROR(IFERROR(LOOKUP(2,1/ISNUMBER(M14:M43),L14:L43),NA())+1,NA()) -> 2027 | S14: =IFERROR((IFERROR(INDEX(M14:M43,MATCH(R14-1,L14:L43,0)),NA()))*(1+$B9),NA()) -> 15028.868 | T14: =IFERROR((IFERROR(INDEX(N14:N43,MATCH(R14-1,L14:L43,0)),NA()))*(1+$B10),NA()) -> 15181.922
A15: =IFERROR(IF(LEN(TRIM(TEXT(CPI!B9,"@")))<3,NA(),DATE(2000+VALUE(LEFT(CPI!B9,LEN(CPI!B9)-2)),VALUE(RIGHT(CPI!B9,2)),1)),NA()) -> 42036 | B15: =IFERROR(IF(CPI!B9="",NA(),CPI!B9),NA()) -> 1502 | C15: =IFERROR(YEAR(A15),0) -> 2015 | D15: =IFERROR(IF(CPI!C9="",NA(),IF(ISNUMBER(CPI!C9),CPI!C9,NA())),NA()) -> 57.7781 | E15: =IFERROR(IF(CPI!D9="",NA(),IF(ISNUMBER(CPI!D9),CPI!D9,NA())),NA()) -> #N/A | F15: =NA() -> #N/A | G15: =IFERROR(D15/D14-1,NA()) -> 0.014524792 | H15: =NA() -> #N/A | I15: =NA() -> #N/A | L15: 2005 | M15: =IF(SUMPRODUCT(($C$14:$C$266=$L$15)*ISNUMBER($D$14:$D$266))=0,NA(),SUMPRODUCT(($C$14:$C$266=$L$15)*IFERROR($D$14:$D$266,0))/SUMPRODUCT(($C$14:$C$266=$L$15)*ISNUMBER($D$14:$D$266))) -> #N/A | N15: =IF(SUMPRODUCT(($C$14:$C$266=$L$15)*ISNUMBER($E$14:$E$266))=0,NA(),SUMPRODUCT(($C$14:$C$266=$L$15)*IFERROR($E$14:$E$266,0))/SUMPRODUCT(($C$14:$C$266=$L$15)*ISNUMBER($E$14:$E$266))) -> #N/A | O15: =IFERROR(M15/M14-1,NA()) -> #N/A | R15: =R14+1 -> 2028 | S15: =IFERROR(S14*(1+$C9),NA()) -> 18786.085 | T15: =IFERROR(T14*(1+$C10),NA()) -> 18825.583
A16: =IFERROR(IF(LEN(TRIM(TEXT(CPI!B10,"@")))<3,NA(),DATE(2000+VALUE(LEFT(CPI!B10,LEN(CPI!B10)-2)),VALUE(RIGHT(CPI!B10,2)),1)),NA()) -> 42064 | B16: =IFERROR(IF(CPI!B10="",NA(),CPI!B10),NA()) -> 1503 | C16: =IFERROR(YEAR(A16),0) -> 2015 | D16: =IFERROR(IF(CPI!C10="",NA(),IF(ISNUMBER(CPI!C10),CPI!C10,NA())),NA()) -> 58.7385 | E16: =IFERROR(IF(CPI!D10="",NA(),IF(ISNUMBER(CPI!D10),CPI!D10,NA())),NA()) -> #N/A | F16: =NA() -> #N/A | G16: =IFERROR(D16/D15-1,NA()) -> 0.016622215 | H16: =IF(COUNT(D14:D16)=3,AVERAGE(D14:D16),NA()) -> 57.8225 | I16: =NA() -> #N/A | L16: 2006 | M16: =IF(SUMPRODUCT(($C$14:$C$266=$L$16)*ISNUMBER($D$14:$D$266))=0,NA(),SUMPRODUCT(($C$14:$C$266=$L$16)*IFERROR($D$14:$D$266,0))/SUMPRODUCT(($C$14:$C$266=$L$16)*ISNUMBER($D$14:$D$266))) -> #N/A | N16: =IF(SUMPRODUCT(($C$14:$C$266=$L$16)*ISNUMBER($E$14:$E$266))=0,NA(),SUMPRODUCT(($C$14:$C$266=$L$16)*IFERROR($E$14:$E$266,0))/SUMPRODUCT(($C$14:$C$266=$L$16)*ISNUMBER($E$14:$E$266))) -> #N/A | O16: =IFERROR(M16/M15-1,NA()) -> #N/A
A17: =IFERROR(IF(LEN(TRIM(TEXT(CPI!B11,"@")))<3,NA(),DATE(2000+VALUE(LEFT(CPI!B11,LEN(CPI!B11)-2)),VALUE(RIGHT(CPI!B11,2)),1)),NA()) -> 42095 | B17: =IFERROR(IF(CPI!B11="",NA(),CPI!B11),NA()) -> 1504 | C17: =IFERROR(YEAR(A17),0) -> 2015 | D17: =IFERROR(IF(CPI!C11="",NA(),IF(ISNUMBER(CPI!C11),CPI!C11,NA())),NA()) -> 60.1294 | E17: =IFERROR(IF(CPI!D11="",NA(),IF(ISNUMBER(CPI!D11),CPI!D11,NA())),NA()) -> #N/A | F17: =NA() -> #N/A | G17: =IFERROR(D17/D16-1,NA()) -> 0.023679529 | H17: =IF(COUNT(D15:D17)=3,AVERAGE(D15:D17),NA()) -> 58.882 | I17: =NA() -> #N/A | L17: 2007 | M17: =IF(SUMPRODUCT(($C$14:$C$266=$L$17)*ISNUMBER($D$14:$D$266))=0,NA(),SUMPRODUCT(($C$14:$C$266=$L$17)*IFERROR($D$14:$D$266,0))/SUMPRODUCT(($C$14:$C$266=$L$17)*ISNUMBER($D$14:$D$266))) -> #N/A | N17: =IF(SUMPRODUCT(($C$14:$C$266=$L$17)*ISNUMBER($E$14:$E$266))=0,NA(),SUMPRODUCT(($C$14:$C$266=$L$17)*IFERROR($E$14:$E$266,0))/SUMPRODUCT(($C$14:$C$266=$L$17)*ISNUMBER($E$14:$E$266))) -> #N/A | O17: =IFERROR(M17/M16-1,NA()) -> #N/A
A18: =IFERROR(IF(LEN(TRIM(TEXT(CPI!B12,"@")))<3,NA(),DATE(2000+VALUE(LEFT(CPI!B12,LEN(CPI!B12)-2)),VALUE(RIGHT(CPI!B12,2)),1)),NA()) -> 42125 | B18: =IFERROR(IF(CPI!B12="",NA(),CPI!B12),NA()) -> 1505 | C18: =IFERROR(YEAR(A18),0) -> 2015 | D18: =IFERROR(IF(CPI!C12="",NA(),IF(ISNUMBER(CPI!C12),CPI!C12,NA())),NA()) -> 61.4604 | E18: =IFERROR(IF(CPI!D12="",NA(),IF(ISNUMBER(CPI!D12),CPI!D12,NA())),NA()) -> #N/A | F18: =NA() -> #N/A | G18: =IFERROR(D18/D17-1,NA()) -> 0.022135594 | H18: =IF(COUNT(D16:D18)=3,AVERAGE(D16:D18),NA()) -> 60.109433 | I18: =NA() -> #N/A | L18: 2008 | M18: =IF(SUMPRODUCT(($C$14:$C$266=$L$18)*ISNUMBER($D$14:$D$266))=0,NA(),SUMPRODUCT(($C$14:$C$266=$L$18)*IFERROR($D$14:$D$266,0))/SUMPRODUCT(($C$14:$C$266=$L$18)*ISNUMBER($D$14:$D$266))) -> #N/A | N18: =IF(SUMPRODUCT(($C$14:$C$266=$L$18)*ISNUMBER($E$14:$E$266))=0,NA(),SUMPRODUCT(($C$14:$C$266=$L$18)*IFERROR($E$14:$E$266,0))/SUMPRODUCT(($C$14:$C$266=$L$18)*ISNUMBER($E$14:$E$266))) -> #N/A | O18: =IFERROR(M18/M17-1,NA()) -> #N/A
A19: =IFERROR(IF(LEN(TRIM(TEXT(CPI!B13,"@")))<3,NA(),DATE(2000+VALUE(LEFT(CPI!B13,LEN(CPI!B13)-2)),VALUE(RIGHT(CPI!B13,2)),1)),NA()) -> 42156 | B19: =IFERROR(IF(CPI!B13="",NA(),CPI!B13),NA()) -> 1506 | C19: =IFERROR(YEAR(A19),0) -> 2015 | D19: =IFERROR(IF(CPI!C13="",NA(),IF(ISNUMBER(CPI!C13),CPI!C13,NA())),NA()) -> 62.2902 | E19: =IFERROR(IF(CPI!D13="",NA(),IF(ISNUMBER(CPI!D13),CPI!D13,NA())),NA()) -> #N/A | F19: =NA() -> #N/A | G19: =IFERROR(D19/D18-1,NA()) -> 0.013501376 | H19: =IF(COUNT(D17:D19)=3,AVERAGE(D17:D19),NA()) -> 61.293333 | I19: =NA() -> #N/A | L19: 2009 | M19: =IF(SUMPRODUCT(($C$14:$C$266=$L$19)*ISNUMBER($D$14:$D$266))=0,NA(),SUMPRODUCT(($C$14:$C$266=$L$19)*IFERROR($D$14:$D$266,0))/SUMPRODUCT(($C$14:$C$266=$L$19)*ISNUMBER($D$14:$D$266))) -> #N/A | N19: =IF(SUMPRODUCT(($C$14:$C$266=$L$19)*ISNUMBER($E$14:$E$266))=0,NA(),SUMPRODUCT(($C$14:$C$266=$L$19)*IFERROR($E$14:$E$266,0))/SUMPRODUCT(($C$14:$C$266=$L$19)*ISNUMBER($E$14:$E$266))) -> #N/A | O19: =IFERROR(M19/M18-1,NA()) -> #N/A
A20: =IFERROR(IF(LEN(TRIM(TEXT(CPI!B14,"@")))<3,NA(),DATE(2000+VALUE(LEFT(CPI!B14,LEN(CPI!B14)-2)),VALUE(RIGHT(CPI!B14,2)),1)),NA()) -> 42186 | B20: =IFERROR(IF(CPI!B14="",NA(),CPI!B14),NA()) -> 1507 | C20: =IFERROR(YEAR(A20),0) -> 2015 | D20: =IFERROR(IF(CPI!C14="",NA(),IF(ISNUMBER(CPI!C14),CPI!C14,NA())),NA()) -> 63.5612 | E20: =IFERROR(IF(CPI!D14="",NA(),IF(ISNUMBER(CPI!D14),CPI!D14,NA())),NA()) -> #N/A | F20: =NA() -> #N/A | G20: =IFERROR(D20/D19-1,NA()) -> 0.020404494 | H20: =IF(COUNT(D18:D20)=3,AVERAGE(D18:D20),NA()) -> 62.437267 | I20: =NA() -> #N/A | L20: 2010 | M20: =IF(SUMPRODUCT(($C$14:$C$266=$L$20)*ISNUMBER($D$14:$D$266))=0,NA(),SUMPRODUCT(($C$14:$C$266=$L$20)*IFERROR($D$14:$D$266,0))/SUMPRODUCT(($C$14:$C$266=$L$20)*ISNUMBER($D$14:$D$266))) -> #N/A | N20: =IF(SUMPRODUCT(($C$14:$C$266=$L$20)*ISNUMBER($E$14:$E$266))=0,NA(),SUMPRODUCT(($C$14:$C$266=$L$20)*IFERROR($E$14:$E$266,0))/SUMPRODUCT(($C$14:$C$266=$L$20)*ISNUMBER($E$14:$E$266))) -> #N/A | O20: =IFERROR(M20/M19-1,NA()) -> #N/A
A21: =IFERROR(IF(LEN(TRIM(TEXT(CPI!B15,"@")))<3,NA(),DATE(2000+VALUE(LEFT(CPI!B15,LEN(CPI!B15)-2)),VALUE(RIGHT(CPI!B15,2)),1)),NA()) -> 42217 | B21: =IFERROR(IF(CPI!B15="",NA(),CPI!B15),NA()) -> 1508 | C21: =IFERROR(YEAR(A21),0) -> 2015 | D21: =IFERROR(IF(CPI!C15="",NA(),IF(ISNUMBER(CPI!C15),CPI!C15,NA())),NA()) -> 64.7251 | E21: =IFERROR(IF(CPI!D15="",NA(),IF(ISNUMBER(CPI!D15),CPI!D15,NA())),NA()) -> #N/A | F21: =NA() -> #N/A | G21: =IFERROR(D21/D20-1,NA()) -> 0.018311486 | H21: =IF(COUNT(D19:D21)=3,AVERAGE(D19:D21),NA()) -> 63.5255 | I21: =NA() -> #N/A | L21: 2011 | M21: =IF(SUMPRODUCT(($C$14:$C$266=$L$21)*ISNUMBER($D$14:$D$266))=0,NA(),SUMPRODUCT(($C$14:$C$266=$L$21)*IFERROR($D$14:$D$266,0))/SUMPRODUCT(($C$14:$C$266=$L$21)*ISNUMBER($D$14:$D$266))) -> #N/A | N21: =IF(SUMPRODUCT(($C$14:$C$266=$L$21)*ISNUMBER($E$14:$E$266))=0,NA(),SUMPRODUCT(($C$14:$C$266=$L$21)*IFERROR($E$14:$E$266,0))/SUMPRODUCT(($C$14:$C$266=$L$21)*ISNUMBER($E$14:$E$266))) -> #N/A | O21: =IFERROR(M21/M20-1,NA()) -> #N/A
A22: =IFERROR(IF(LEN(TRIM(TEXT(CPI!B16,"@")))<3,NA(),DATE(2000+VALUE(LEFT(CPI!B16,LEN(CPI!B16)-2)),VALUE(RIGHT(CPI!B16,2)),1)),NA()) -> 42248 | B22: =IFERROR(IF(CPI!B16="",NA(),CPI!B16),NA()) -> 1509 | C22: =IFERROR(YEAR(A22),0) -> 2015 | D22: =IFERROR(IF(CPI!C16="",NA(),IF(ISNUMBER(CPI!C16),CPI!C16,NA())),NA()) -> 65.7976 | E22: =IFERROR(IF(CPI!D16="",NA(),IF(ISNUMBER(CPI!D16),CPI!D16,NA())),NA()) -> #N/A | F22: =NA() -> #N/A | G22: =IFERROR(D22/D21-1,NA()) -> 0.016570079 | H22: =IF(COUNT(D20:D22)=3,AVERAGE(D20:D22),NA()) -> 64.694633 | I22: =NA() -> #N/A | L22: 2012 | M22: =IF(SUMPRODUCT(($C$14:$C$266=$L$22)*ISNUMBER($D$14:$D$266))=0,NA(),SUMPRODUCT(($C$14:$C$266=$L$22)*IFERROR($D$14:$D$266,0))/SUMPRODUCT(($C$14:$C$266=$L$22)*ISNUMBER($D$14:$D$266))) -> #N/A | N22: =IF(SUMPRODUCT(($C$14:$C$266=$L$22)*ISNUMBER($E$14:$E$266))=0,NA(),SUMPRODUCT(($C$14:$C$266=$L$22)*IFERROR($E$14:$E$266,0))/SUMPRODUCT(($C$14:$C$266=$L$22)*ISNUMBER($E$14:$E$266))) -> #N/A | O22: =IFERROR(M22/M21-1,NA()) -> #N/A
A23: =IFERROR(IF(LEN(TRIM(TEXT(CPI!B17,"@")))<3,NA(),DATE(2000+VALUE(LEFT(CPI!B17,LEN(CPI!B17)-2)),VALUE(RIGHT(CPI!B17,2)),1)),NA()) -> 42278 | B23: =IFERROR(IF(CPI!B17="",NA(),CPI!B17),NA()) -> 1510 | C23: =IFERROR(YEAR(A23),0) -> 2015 | D23: =IFERROR(IF(CPI!C17="",NA(),IF(ISNUMBER(CPI!C17),CPI!C17,NA())),NA()) -> 66.9172 | E23: =IFERROR(IF(CPI!D17="",NA(),IF(ISNUMBER(CPI!D17),CPI!D17,NA())),NA()) -> #N/A | F23: =NA() -> #N/A | G23: =IFERROR(D23/D22-1,NA()) -> 0.017015818 | H23: =IF(COUNT(D21:D23)=3,AVERAGE(D21:D23),NA()) -> 65.8133 | I23: =NA() -> #N/A | L23: 2013 | M23: =IF(SUMPRODUCT(($C$14:$C$266=$L$23)*ISNUMBER($D$14:$D$266))=0,NA(),SUMPRODUCT(($C$14:$C$266=$L$23)*IFERROR($D$14:$D$266,0))/SUMPRODUCT(($C$14:$C$266=$L$23)*ISNUMBER($D$14:$D$266))) -> #N/A | N23: =IF(SUMPRODUCT(($C$14:$C$266=$L$23)*ISNUMBER($E$14:$E$266))=0,NA(),SUMPRODUCT(($C$14:$C$266=$L$23)*IFERROR($E$14:$E$266,0))/SUMPRODUCT(($C$14:$C$266=$L$23)*ISNUMBER($E$14:$E$266))) -> #N/A | O23: =IFERROR(M23/M22-1,NA()) -> #N/A
A24: =IFERROR(IF(LEN(TRIM(TEXT(CPI!B18,"@")))<3,NA(),DATE(2000+VALUE(LEFT(CPI!B18,LEN(CPI!B18)-2)),VALUE(RIGHT(CPI!B18,2)),1)),NA()) -> 42309 | B24: =IFERROR(IF(CPI!B18="",NA(),CPI!B18),NA()) -> 1511 | C24: =IFERROR(YEAR(A24),0) -> 2015 | D24: =IFERROR(IF(CPI!C18="",NA(),IF(ISNUMBER(CPI!C18),CPI!C18,NA())),NA()) -> 68.2246 | E24: =IFERROR(IF(CPI!D18="",NA(),IF(ISNUMBER(CPI!D18),CPI!D18,NA())),NA()) -> #N/A | F24: =NA() -> #N/A | G24: =IFERROR(D24/D23-1,NA()) -> 0.019537578 | H24: =IF(COUNT(D22:D24)=3,AVERAGE(D22:D24),NA()) -> 66.9798 | I24: =NA() -> #N/A | L24: 2014 | M24: =IF(SUMPRODUCT(($C$14:$C$266=$L$24)*ISNUMBER($D$14:$D$266))=0,NA(),SUMPRODUCT(($C$14:$C$266=$L$24)*IFERROR($D$14:$D$266,0))/SUMPRODUCT(($C$14:$C$266=$L$24)*ISNUMBER($D$14:$D$266))) -> #N/A | N24: =IF(SUMPRODUCT(($C$14:$C$266=$L$24)*ISNUMBER($E$14:$E$266))=0,NA(),SUMPRODUCT(($C$14:$C$266=$L$24)*IFERROR($E$14:$E$266,0))/SUMPRODUCT(($C$14:$C$266=$L$24)*ISNUMBER($E$14:$E$266))) -> #N/A | O24: =IFERROR(M24/M23-1,NA()) -> #N/A
A25: =IFERROR(IF(LEN(TRIM(TEXT(CPI!B19,"@")))<3,NA(),DATE(2000+VALUE(LEFT(CPI!B19,LEN(CPI!B19)-2)),VALUE(RIGHT(CPI!B19,2)),1)),NA()) -> 42339 | B25: =IFERROR(IF(CPI!B19="",NA(),CPI!B19),NA()) -> 1512 | C25: =IFERROR(YEAR(A25),0) -> 2015 | D25: =IFERROR(IF(CPI!C19="",NA(),IF(ISNUMBER(CPI!C19),CPI!C19,NA())),NA()) -> 70.8969 | E25: =IFERROR(IF(CPI!D19="",NA(),IF(ISNUMBER(CPI!D19),CPI!D19,NA())),NA()) -> #N/A | F25: =NA() -> #N/A | G25: =IFERROR(D25/D24-1,NA()) -> 0.039169156 | H25: =IF(COUNT(D23:D25)=3,AVERAGE(D23:D25),NA()) -> 68.679567 | I25: =NA() -> #N/A | L25: 2015 | M25: =IF(SUMPRODUCT(($C$14:$C$266=$L$25)*ISNUMBER($D$14:$D$266))=0,NA(),SUMPRODUCT(($C$14:$C$266=$L$25)*IFERROR($D$14:$D$266,0))/SUMPRODUCT(($C$14:$C$266=$L$25)*ISNUMBER($D$14:$D$266))) -> 63.122508 | N25: =IF(SUMPRODUCT(($C$14:$C$266=$L$25)*ISNUMBER($E$14:$E$266))=0,NA(),SUMPRODUCT(($C$14:$C$266=$L$25)*IFERROR($E$14:$E$266,0))/SUMPRODUCT(($C$14:$C$266=$L$25)*ISNUMBER($E$14:$E$266))) -> #N/A | O25: =IFERROR(M25/M24-1,NA()) -> #N/A
A26: =IFERROR(IF(LEN(TRIM(TEXT(CPI!B20,"@")))<3,NA(),DATE(2000+VALUE(LEFT(CPI!B20,LEN(CPI!B20)-2)),VALUE(RIGHT(CPI!B20,2)),1)),NA()) -> 42370 | B26: =IFERROR(IF(CPI!B20="",NA(),CPI!B20),NA()) -> 1601 | C26: =IFERROR(YEAR(A26),0) -> 2016 | D26: =IFERROR(IF(CPI!C20="",NA(),IF(ISNUMBER(CPI!C20),CPI!C20,NA())),NA()) -> 73.8302 | E26: =IFERROR(IF(CPI!D20="",NA(),IF(ISNUMBER(CPI!D20),CPI!D20,NA())),NA()) -> #N/A | F26: =IFERROR(D26/D14-1,NA()) -> 0.29638338 | G26: =IFERROR(D26/D25-1,NA()) -> 0.041374164 | H26: =IF(COUNT(D24:D26)=3,AVERAGE(D24:D26),NA()) -> 70.9839 | I26: =NA() -> #N/A | L26: 2016 | M26: =IF(SUMPRODUCT(($C$14:$C$266=$L$26)*ISNUMBER($D$14:$D$266))=0,NA(),SUMPRODUCT(($C$14:$C$266=$L$26)*IFERROR($D$14:$D$266,0))/SUMPRODUCT(($C$14:$C$266=$L$26)*ISNUMBER($D$14:$D$266))) -> 89.248583 | N26: =IF(SUMPRODUCT(($C$14:$C$266=$L$26)*ISNUMBER($E$14:$E$266))=0,NA(),SUMPRODUCT(($C$14:$C$266=$L$26)*IFERROR($E$14:$E$266,0))/SUMPRODUCT(($C$14:$C$266=$L$26)*ISNUMBER($E$14:$E$266))) -> 100 | O26: =IFERROR(M26/M25-1,NA()) -> 0.41389475
A27: =IFERROR(IF(LEN(TRIM(TEXT(CPI!B21,"@")))<3,NA(),DATE(2000+VALUE(LEFT(CPI!B21,LEN(CPI!B21)-2)),VALUE(RIGHT(CPI!B21,2)),1)),NA()) -> 42401 | B27: =IFERROR(IF(CPI!B21="",NA(),CPI!B21),NA()) -> 1602 | C27: =IFERROR(YEAR(A27),0) -> 2016 | D27: =IFERROR(IF(CPI!C21="",NA(),IF(ISNUMBER(CPI!C21),CPI!C21,NA())),NA()) -> 76.7609 | E27: =IFERROR(IF(CPI!D21="",NA(),IF(ISNUMBER(CPI!D21),CPI!D21,NA())),NA()) -> #N/A | F27: =IFERROR(D27/D15-1,NA()) -> 0.32854663 | G27: =IFERROR(D27/D26-1,NA()) -> 0.039695138 | H27: =IF(COUNT(D25:D27)=3,AVERAGE(D25:D27),NA()) -> 73.829333 | I27: =NA() -> #N/A | L27: 2017 | M27: =IF(SUMPRODUCT(($C$14:$C$266=$L$27)*ISNUMBER($D$14:$D$266))=0,NA(),SUMPRODUCT(($C$14:$C$266=$L$27)*IFERROR($D$14:$D$266,0))/SUMPRODUCT(($C$14:$C$266=$L$27)*ISNUMBER($D$14:$D$266))) -> 112.88711 | N27: =IF(SUMPRODUCT(($C$14:$C$266=$L$27)*ISNUMBER($E$14:$E$266))=0,NA(),SUMPRODUCT(($C$14:$C$266=$L$27)*IFERROR($E$14:$E$266,0))/SUMPRODUCT(($C$14:$C$266=$L$27)*ISNUMBER($E$14:$E$266))) -> 111.50442 | O27: =IFERROR(M27/M26-1,NA()) -> 0.26486163
A28: =IFERROR(IF(LEN(TRIM(TEXT(CPI!B22,"@")))<3,NA(),DATE(2000+VALUE(LEFT(CPI!B22,LEN(CPI!B22)-2)),VALUE(RIGHT(CPI!B22,2)),1)),NA()) -> 42430 | B28: =IFERROR(IF(CPI!B22="",NA(),CPI!B22),NA()) -> 1603 | C28: =IFERROR(YEAR(A28),0) -> 2016 | D28: =IFERROR(IF(CPI!C22="",NA(),IF(ISNUMBER(CPI!C22),CPI!C22,NA())),NA()) -> 79.3079 | E28: =IFERROR(IF(CPI!D22="",NA(),IF(ISNUMBER(CPI!D22),CPI!D22,NA())),NA()) -> #N/A | F28: =IFERROR(D28/D16-1,NA()) -> 0.35018599 | G28: =IFERROR(D28/D27-1,NA()) -> 0.033180955 | H28: =IF(COUNT(D26:D28)=3,AVERAGE(D26:D28),NA()) -> 76.633 | I28: =IFERROR(IF(AND(COUNT(D26:D28)=3,COUNT(D14:D16)=3),AVERAGE(D26:D28)/AVERAGE(D14:D16)-1,NA()),NA()) -> 0.32531454 | L28: 2018 | M28: =IF(SUMPRODUCT(($C$14:$C$266=$L$28)*ISNUMBER($D$14:$D$266))=0,NA(),SUMPRODUCT(($C$14:$C$266=$L$28)*IFERROR($D$14:$D$266,0))/SUMPRODUCT(($C$14:$C$266=$L$28)*ISNUMBER($D$14:$D$266))) -> 151.58167 | N28: =IF(SUMPRODUCT(($C$14:$C$266=$L$28)*ISNUMBER($E$14:$E$266))=0,NA(),SUMPRODUCT(($C$14:$C$266=$L$28)*IFERROR($E$14:$E$266,0))/SUMPRODUCT(($C$14:$C$266=$L$28)*ISNUMBER($E$14:$E$266))) -> 146.82387 | O28: =IFERROR(M28/M27-1,NA()) -> 0.34277224
A29: =IFERROR(IF(LEN(TRIM(TEXT(CPI!B23,"@")))<3,NA(),DATE(2000+VALUE(LEFT(CPI!B23,LEN(CPI!B23)-2)),VALUE(RIGHT(CPI!B23,2)),1)),NA()) -> 42461 | B29: =IFERROR(IF(CPI!B23="",NA(),CPI!B23),NA()) -> 1604 | C29: =IFERROR(YEAR(A29),0) -> 2016 | D29: =IFERROR(IF(CPI!C23="",NA(),IF(ISNUMBER(CPI!C23),CPI!C23,NA())),NA()) -> 84.4986 | E29: =IFERROR(IF(CPI!D23="",NA(),IF(ISNUMBER(CPI!D23),CPI!D23,NA())),NA()) -> #N/A | F29: =IFERROR(D29/D17-1,NA()) -> 0.40527928 | G29: =IFERROR(D29/D28-1,NA()) -> 0.065449974 | H29: =IF(COUNT(D27:D29)=3,AVERAGE(D27:D29),NA()) -> 80.189133 | I29: =IFERROR(IF(AND(COUNT(D27:D29)=3,COUNT(D15:D17)=3),AVERAGE(D27:D29)/AVERAGE(D15:D17)-1,NA()),NA()) -> 0.36186158 | L29: 2019 | M29: =IF(SUMPRODUCT(($C$14:$C$266=$L$29)*ISNUMBER($D$14:$D$266))=0,NA(),SUMPRODUCT(($C$14:$C$266=$L$29)*IFERROR($D$14:$D$266,0))/SUMPRODUCT(($C$14:$C$266=$L$29)*ISNUMBER($D$14:$D$266))) -> 232.75109 | N29: =IF(SUMPRODUCT(($C$14:$C$266=$L$29)*ISNUMBER($E$14:$E$266))=0,NA(),SUMPRODUCT(($C$14:$C$266=$L$29)*IFERROR($E$14:$E$266,0))/SUMPRODUCT(($C$14:$C$266=$L$29)*ISNUMBER($E$14:$E$266))) -> 228.29128 | O29: =IFERROR(M29/M28-1,NA()) -> 0.53548304
A30: =IFERROR(IF(LEN(TRIM(TEXT(CPI!B24,"@")))<3,NA(),DATE(2000+VALUE(LEFT(CPI!B24,LEN(CPI!B24)-2)),VALUE(RIGHT(CPI!B24,2)),1)),NA()) -> 42491 | B30: =IFERROR(IF(CPI!B24="",NA(),CPI!B24),NA()) -> 1605 | C30: =IFERROR(YEAR(A30),0) -> 2016 | D30: =IFERROR(IF(CPI!C24="",NA(),IF(ISNUMBER(CPI!C24),CPI!C24,NA())),NA()) -> 88.7523 | E30: =IFERROR(IF(CPI!D24="",NA(),IF(ISNUMBER(CPI!D24),CPI!D24,NA())),NA()) -> #N/A | F30: =IFERROR(D30/D18-1,NA()) -> 0.44405666 | G30: =IFERROR(D30/D29-1,NA()) -> 0.050340479 | H30: =IF(COUNT(D28:D30)=3,AVERAGE(D28:D30),NA()) -> 84.186267 | I30: =IFERROR(IF(AND(COUNT(D28:D30)=3,COUNT(D16:D18)=3),AVERAGE(D28:D30)/AVERAGE(D16:D18)-1,NA()),NA()) -> 0.40055 | L30: 2020 | M30: =IF(SUMPRODUCT(($C$14:$C$266=$L$30)*ISNUMBER($D$14:$D$266))=0,NA(),SUMPRODUCT(($C$14:$C$266=$L$30)*IFERROR($D$14:$D$266,0))/SUMPRODUCT(($C$14:$C$266=$L$30)*ISNUMBER($D$14:$D$266))) -> 330.54168 | N30: =IF(SUMPRODUCT(($C$14:$C$266=$L$30)*ISNUMBER($E$14:$E$266))=0,NA(),SUMPRODUCT(($C$14:$C$266=$L$30)*IFERROR($E$14:$E$266,0))/SUMPRODUCT(($C$14:$C$266=$L$30)*ISNUMBER($E$14:$E$266))) -> 330.19351 | O30: =IFERROR(M30/M29-1,NA()) -> 0.42015095
A31: =IFERROR(IF(LEN(TRIM(TEXT(CPI!B25,"@")))<3,NA(),DATE(2000+VALUE(LEFT(CPI!B25,LEN(CPI!B25)-2)),VALUE(RIGHT(CPI!B25,2)),1)),NA()) -> 42522 | B31: =IFERROR(IF(CPI!B25="",NA(),CPI!B25),NA()) -> 1606 | C31: =IFERROR(YEAR(A31),0) -> 2016 | D31: =IFERROR(IF(CPI!C25="",NA(),IF(ISNUMBER(CPI!C25),CPI!C25,NA())),NA()) -> 91.6125 | E31: =IFERROR(IF(CPI!D25="",NA(),IF(ISNUMBER(CPI!D25),CPI!D25,NA())),NA()) -> #N/A | F31: =IFERROR(D31/D19-1,NA()) -> 0.47073697 | G31: =IFERROR(D31/D30-1,NA()) -> 0.03222677 | H31: =IF(COUNT(D29:D31)=3,AVERAGE(D29:D31),NA()) -> 88.2878 | I31: =IFERROR(IF(AND(COUNT(D29:D31)=3,COUNT(D17:D19)=3),AVERAGE(D29:D31)/AVERAGE(D17:D19)-1,NA()),NA()) -> 0.4404144 | L31: 2021 | M31: =IF(SUMPRODUCT(($C$14:$C$266=$L$31)*ISNUMBER($D$14:$D$266))=0,NA(),SUMPRODUCT(($C$14:$C$266=$L$31)*IFERROR($D$14:$D$266,0))/SUMPRODUCT(($C$14:$C$266=$L$31)*ISNUMBER($D$14:$D$266))) -> 490.55486 | N31: =IF(SUMPRODUCT(($C$14:$C$266=$L$31)*ISNUMBER($E$14:$E$266))=0,NA(),SUMPRODUCT(($C$14:$C$266=$L$31)*IFERROR($E$14:$E$266,0))/SUMPRODUCT(($C$14:$C$266=$L$31)*ISNUMBER($E$14:$E$266))) -> 502.71798 | O31: =IFERROR(M31/M30-1,NA()) -> 0.48409379
A32: =IFERROR(IF(LEN(TRIM(TEXT(CPI!B26,"@")))<3,NA(),DATE(2000+VALUE(LEFT(CPI!B26,LEN(CPI!B26)-2)),VALUE(RIGHT(CPI!B26,2)),1)),NA()) -> 42552 | B32: =IFERROR(IF(CPI!B26="",NA(),CPI!B26),NA()) -> 1607 | C32: =IFERROR(YEAR(A32),0) -> 2016 | D32: =IFERROR(IF(CPI!C26="",NA(),IF(ISNUMBER(CPI!C26),CPI!C26,NA())),NA()) -> 93.588 | E32: =IFERROR(IF(CPI!D26="",NA(),IF(ISNUMBER(CPI!D26),CPI!D26,NA())),NA()) -> #N/A | F32: =IFERROR(D32/D20-1,NA()) -> 0.4724077 | G32: =IFERROR(D32/D31-1,NA()) -> 0.021563651 | H32: =IF(COUNT(D30:D32)=3,AVERAGE(D30:D32),NA()) -> 91.3176 | I32: =IFERROR(IF(AND(COUNT(D30:D32)=3,COUNT(D18:D20)=3),AVERAGE(D30:D32)/AVERAGE(D18:D20)-1,NA()),NA()) -> 0.46254961 | L32: 2022 | M32: =IF(SUMPRODUCT(($C$14:$C$266=$L$32)*ISNUMBER($D$14:$D$266))=0,NA(),SUMPRODUCT(($C$14:$C$266=$L$32)*IFERROR($D$14:$D$266,0))/SUMPRODUCT(($C$14:$C$266=$L$32)*ISNUMBER($D$14:$D$266))) -> 845.86746 | N32: =IF(SUMPRODUCT(($C$14:$C$266=$L$32)*ISNUMBER($E$14:$E$266))=0,NA(),SUMPRODUCT(($C$14:$C$266=$L$32)*IFERROR($E$14:$E$266,0))/SUMPRODUCT(($C$14:$C$266=$L$32)*ISNUMBER($E$14:$E$266))) -> 868.3323 | O32: =IFERROR(M32/M31-1,NA()) -> 0.72430758
A33: =IFERROR(IF(LEN(TRIM(TEXT(CPI!B27,"@")))<3,NA(),DATE(2000+VALUE(LEFT(CPI!B27,LEN(CPI!B27)-2)),VALUE(RIGHT(CPI!B27,2)),1)),NA()) -> 42583 | B33: =IFERROR(IF(CPI!B27="",NA(),CPI!B27),NA()) -> 1608 | C33: =IFERROR(YEAR(A33),0) -> 2016 | D33: =IFERROR(IF(CPI!C27="",NA(),IF(ISNUMBER(CPI!C27),CPI!C27,NA())),NA()) -> 92.8782 | E33: =IFERROR(IF(CPI!D27="",NA(),IF(ISNUMBER(CPI!D27),CPI!D27,NA())),NA()) -> #N/A | F33: =IFERROR(D33/D21-1,NA()) -> 0.43496418 | G33: =IFERROR(D33/D32-1,NA()) -> -0.0075843057 | H33: =IF(COUNT(D31:D33)=3,AVERAGE(D31:D33),NA()) -> 92.6929 | I33: =IFERROR(IF(AND(COUNT(D31:D33)=3,COUNT(D19:D21)=3),AVERAGE(D31:D33)/AVERAGE(D19:D21)-1,NA()),NA()) -> 0.45914475 | L33: 2023 | M33: =IF(SUMPRODUCT(($C$14:$C$266=$L$33)*ISNUMBER($D$14:$D$266))=0,NA(),SUMPRODUCT(($C$14:$C$266=$L$33)*IFERROR($D$14:$D$266,0))/SUMPRODUCT(($C$14:$C$266=$L$33)*ISNUMBER($D$14:$D$266))) -> 1975.0069 | N33: =IF(SUMPRODUCT(($C$14:$C$266=$L$33)*ISNUMBER($E$14:$E$266))=0,NA(),SUMPRODUCT(($C$14:$C$266=$L$33)*IFERROR($E$14:$E$266,0))/SUMPRODUCT(($C$14:$C$266=$L$33)*ISNUMBER($E$14:$E$266))) -> 2049.0474 | O33: =IFERROR(M33/M32-1,NA()) -> 1.3348894
A34: =IFERROR(IF(LEN(TRIM(TEXT(CPI!B28,"@")))<3,NA(),DATE(2000+VALUE(LEFT(CPI!B28,LEN(CPI!B28)-2)),VALUE(RIGHT(CPI!B28,2)),1)),NA()) -> 42614 | B34: =IFERROR(IF(CPI!B28="",NA(),CPI!B28),NA()) -> 1609 | C34: =IFERROR(YEAR(A34),0) -> 2016 | D34: =IFERROR(IF(CPI!C28="",NA(),IF(ISNUMBER(CPI!C28),CPI!C28,NA())),NA()) -> 94.1256 | E34: =IFERROR(IF(CPI!D28="",NA(),IF(ISNUMBER(CPI!D28),CPI!D28,NA())),NA()) -> #N/A | F34: =IFERROR(D34/D22-1,NA()) -> 0.43053242 | G34: =IFERROR(D34/D33-1,NA()) -> 0.013430493 | H34: =IF(COUNT(D32:D34)=3,AVERAGE(D32:D34),NA()) -> 93.5306 | I34: =IFERROR(IF(AND(COUNT(D32:D34)=3,COUNT(D20:D22)=3),AVERAGE(D32:D34)/AVERAGE(D20:D22)-1,NA()),NA()) -> 0.44572425 | L34: 2024 | M34: =IF(SUMPRODUCT(($C$14:$C$266=$L$34)*ISNUMBER($D$14:$D$266))=0,NA(),SUMPRODUCT(($C$14:$C$266=$L$34)*IFERROR($D$14:$D$266,0))/SUMPRODUCT(($C$14:$C$266=$L$34)*ISNUMBER($D$14:$D$266))) -> 6317.7413 | N34: =IF(SUMPRODUCT(($C$14:$C$266=$L$34)*ISNUMBER($E$14:$E$266))=0,NA(),SUMPRODUCT(($C$14:$C$266=$L$34)*IFERROR($E$14:$E$266,0))/SUMPRODUCT(($C$14:$C$266=$L$34)*ISNUMBER($E$14:$E$266))) -> 6447.4058 | O34: =IFERROR(M34/M33-1,NA()) -> 2.1988451
A35: =IFERROR(IF(LEN(TRIM(TEXT(CPI!B29,"@")))<3,NA(),DATE(2000+VALUE(LEFT(CPI!B29,LEN(CPI!B29)-2)),VALUE(RIGHT(CPI!B29,2)),1)),NA()) -> 42644 | B35: =IFERROR(IF(CPI!B29="",NA(),CPI!B29),NA()) -> 1610 | C35: =IFERROR(YEAR(A35),0) -> 2016 | D35: =IFERROR(IF(CPI!C29="",NA(),IF(ISNUMBER(CPI!C29),CPI!C29,NA())),NA()) -> 96.8553 | E35: =IFERROR(IF(CPI!D29="",NA(),IF(ISNUMBER(CPI!D29),CPI!D29,NA())),NA()) -> #N/A | F35: =IFERROR(D35/D23-1,NA()) -> 0.44739021 | G35: =IFERROR(D35/D34-1,NA()) -> 0.029000612 | H35: =IF(COUNT(D33:D35)=3,AVERAGE(D33:D35),NA()) -> 94.6197 | I35: =IFERROR(IF(AND(COUNT(D33:D35)=3,COUNT(D21:D23)=3),AVERAGE(D33:D35)/AVERAGE(D21:D23)-1,NA()),NA()) -> 0.43769876 | L35: 2025 | M35: =IF(SUMPRODUCT(($C$14:$C$266=$L$35)*ISNUMBER($D$14:$D$266))=0,NA(),SUMPRODUCT(($C$14:$C$266=$L$35)*IFERROR($D$14:$D$266,0))/SUMPRODUCT(($C$14:$C$266=$L$35)*ISNUMBER($D$14:$D$266))) -> 8966.1665 | N35: =IF(SUMPRODUCT(($C$14:$C$266=$L$35)*ISNUMBER($E$14:$E$266))=0,NA(),SUMPRODUCT(($C$14:$C$266=$L$35)*IFERROR($E$14:$E$266,0))/SUMPRODUCT(($C$14:$C$266=$L$35)*ISNUMBER($E$14:$E$266))) -> 9179.4361 | O35: =IFERROR(M35/M34-1,NA()) -> 0.41920444
A36: =IFERROR(IF(LEN(TRIM(TEXT(CPI!B30,"@")))<3,NA(),DATE(2000+VALUE(LEFT(CPI!B30,LEN(CPI!B30)-2)),VALUE(RIGHT(CPI!B30,2)),1)),NA()) -> 42675 | B36: =IFERROR(IF(CPI!B30="",NA(),CPI!B30),NA()) -> 1611 | C36: =IFERROR(YEAR(A36),0) -> 2016 | D36: =IFERROR(IF(CPI!C30="",NA(),IF(ISNUMBER(CPI!C30),CPI!C30,NA())),NA()) -> 98.7735 | E36: =IFERROR(IF(CPI!D30="",NA(),IF(ISNUMBER(CPI!D30),CPI!D30,NA())),NA()) -> #N/A | F36: =IFERROR(D36/D24-1,NA()) -> 0.44776957 | G36: =IFERROR(D36/D35-1,NA()) -> 0.019804802 | H36: =IF(COUNT(D34:D36)=3,AVERAGE(D34:D36),NA()) -> 96.5848 | I36: =IFERROR(IF(AND(COUNT(D34:D36)=3,COUNT(D22:D24)=3),AVERAGE(D34:D36)/AVERAGE(D22:D24)-1,NA()),NA()) -> 0.44199893 | L36: 2026 | M36: =IF(SUMPRODUCT(($C$14:$C$266=$L$36)*ISNUMBER($D$14:$D$266))=0,NA(),SUMPRODUCT(($C$14:$C$266=$L$36)*IFERROR($D$14:$D$266,0))/SUMPRODUCT(($C$14:$C$266=$L$36)*ISNUMBER($D$14:$D$266))) -> 10734.906 | N36: =IF(SUMPRODUCT(($C$14:$C$266=$L$36)*ISNUMBER($E$14:$E$266))=0,NA(),SUMPRODUCT(($C$14:$C$266=$L$36)*IFERROR($E$14:$E$266,0))/SUMPRODUCT(($C$14:$C$266=$L$36)*ISNUMBER($E$14:$E$266))) -> 11001.393 | O36: =IFERROR(M36/M35-1,NA()) -> 0.19726816
A37: =IFERROR(IF(LEN(TRIM(TEXT(CPI!B31,"@")))<3,NA(),DATE(2000+VALUE(LEFT(CPI!B31,LEN(CPI!B31)-2)),VALUE(RIGHT(CPI!B31,2)),1)),NA()) -> 42705 | B37: =IFERROR(IF(CPI!B31="",NA(),CPI!B31),NA()) -> 1612 | C37: =IFERROR(YEAR(A37),0) -> 2016 | D37: =IFERROR(IF(CPI!C31="",NA(),IF(ISNUMBER(CPI!C31),CPI!C31,NA())),NA()) -> 100 | E37: =IFERROR(IF(CPI!D31="",NA(),IF(ISNUMBER(CPI!D31),CPI!D31,NA())),NA()) -> 100 | F37: =IFERROR(D37/D25-1,NA()) -> 0.41049891 | G37: =IFERROR(D37/D36-1,NA()) -> 0.012417298 | H37: =IF(COUNT(D35:D37)=3,AVERAGE(D35:D37),NA()) -> 98.542933 | I37: =IFERROR(IF(AND(COUNT(D35:D37)=3,COUNT(D23:D25)=3),AVERAGE(D35:D37)/AVERAGE(D23:D25)-1,NA()),NA()) -> 0.43482171 | L37: 2027 | M37: =IF(SUMPRODUCT(($C$14:$C$266=$L$37)*ISNUMBER($D$14:$D$266))=0,NA(),SUMPRODUCT(($C$14:$C$266=$L$37)*IFERROR($D$14:$D$266,0))/SUMPRODUCT(($C$14:$C$266=$L$37)*ISNUMBER($D$14:$D$266))) -> #N/A | N37: =IF(SUMPRODUCT(($C$14:$C$266=$L$37)*ISNUMBER($E$14:$E$266))=0,NA(),SUMPRODUCT(($C$14:$C$266=$L$37)*IFERROR($E$14:$E$266,0))/SUMPRODUCT(($C$14:$C$266=$L$37)*ISNUMBER($E$14:$E$266))) -> #N/A | O37: =IFERROR(M37/M36-1,NA()) -> #N/A
A38: =IFERROR(IF(LEN(TRIM(TEXT(CPI!B32,"@")))<3,NA(),DATE(2000+VALUE(LEFT(CPI!B32,LEN(CPI!B32)-2)),VALUE(RIGHT(CPI!B32,2)),1)),NA()) -> 42736 | B38: =IFERROR(IF(CPI!B32="",NA(),CPI!B32),NA()) -> 1701 | C38: =IFERROR(YEAR(A38),0) -> 2017 | D38: =IFERROR(IF(CPI!C32="",NA(),IF(ISNUMBER(CPI!C32),CPI!C32,NA())),NA()) -> 101.5859 | E38: =IFERROR(IF(CPI!D32="",NA(),IF(ISNUMBER(CPI!D32),CPI!D32,NA())),NA()) -> 101.5039 | F38: =IFERROR(D38/D26-1,NA()) -> 0.37593966 | G38: =IFERROR(D38/D37-1,NA()) -> 0.015859 | H38: =IF(COUNT(D36:D38)=3,AVERAGE(D36:D38),NA()) -> 100.1198 | I38: =IFERROR(IF(AND(COUNT(D36:D38)=3,COUNT(D24:D26)=3),AVERAGE(D36:D38)/AVERAGE(D24:D26)-1,NA()),NA()) -> 0.41045786 | L38: 2028 | M38: =IF(SUMPRODUCT(($C$14:$C$266=$L$38)*ISNUMBER($D$14:$D$266))=0,NA(),SUMPRODUCT(($C$14:$C$266=$L$38)*IFERROR($D$14:$D$266,0))/SUMPRODUCT(($C$14:$C$266=$L$38)*ISNUMBER($D$14:$D$266))) -> #N/A | N38: =IF(SUMPRODUCT(($C$14:$C$266=$L$38)*ISNUMBER($E$14:$E$266))=0,NA(),SUMPRODUCT(($C$14:$C$266=$L$38)*IFERROR($E$14:$E$266,0))/SUMPRODUCT(($C$14:$C$266=$L$38)*ISNUMBER($E$14:$E$266))) -> #N/A | O38: =IFERROR(M38/M37-1,NA()) -> #N/A
A39: =IFERROR(IF(LEN(TRIM(TEXT(CPI!B33,"@")))<3,NA(),DATE(2000+VALUE(LEFT(CPI!B33,LEN(CPI!B33)-2)),VALUE(RIGHT(CPI!B33,2)),1)),NA()) -> 42767 | B39: =IFERROR(IF(CPI!B33="",NA(),CPI!B33),NA()) -> 1702 | C39: =IFERROR(YEAR(A39),0) -> 2017 | D39: =IFERROR(IF(CPI!C33="",NA(),IF(ISNUMBER(CPI!C33),CPI!C33,NA())),NA()) -> 103.6859 | E39: =IFERROR(IF(CPI!D33="",NA(),IF(ISNUMBER(CPI!D33),CPI!D33,NA())),NA()) -> 103.2105 | F39: =IFERROR(D39/D27-1,NA()) -> 0.35076452 | G39: =IFERROR(D39/D38-1,NA()) -> 0.02067216 | H39: =IF(COUNT(D37:D39)=3,AVERAGE(D37:D39),NA()) -> 101.75727 | I39: =IFERROR(IF(AND(COUNT(D37:D39)=3,COUNT(D25:D27)=3),AVERAGE(D37:D39)/AVERAGE(D25:D27)-1,NA()),NA()) -> 0.37827693 | L39: 2029 | M39: =IF(SUMPRODUCT(($C$14:$C$266=$L$39)*ISNUMBER($D$14:$D$266))=0,NA(),SUMPRODUCT(($C$14:$C$266=$L$39)*IFERROR($D$14:$D$266,0))/SUMPRODUCT(($C$14:$C$266=$L$39)*ISNUMBER($D$14:$D$266))) -> #N/A | N39: =IF(SUMPRODUCT(($C$14:$C$266=$L$39)*ISNUMBER($E$14:$E$266))=0,NA(),SUMPRODUCT(($C$14:$C$266=$L$39)*IFERROR($E$14:$E$266,0))/SUMPRODUCT(($C$14:$C$266=$L$39)*ISNUMBER($E$14:$E$266))) -> #N/A | O39: =IFERROR(M39/M38-1,NA()) -> #N/A
A40: =IFERROR(IF(LEN(TRIM(TEXT(CPI!B34,"@")))<3,NA(),DATE(2000+VALUE(LEFT(CPI!B34,LEN(CPI!B34)-2)),VALUE(RIGHT(CPI!B34,2)),1)),NA()) -> 42795 | B40: =IFERROR(IF(CPI!B34="",NA(),CPI!B34),NA()) -> 1703 | C40: =IFERROR(YEAR(A40),0) -> 2017 | D40: =IFERROR(IF(CPI!C34="",NA(),IF(ISNUMBER(CPI!C34),CPI!C34,NA())),NA()) -> 106.1476 | E40: =IFERROR(IF(CPI!D34="",NA(),IF(ISNUMBER(CPI!D34),CPI!D34,NA())),NA()) -> 105.2057 | F40: =IFERROR(D40/D28-1,NA()) -> 0.33842404 | G40: =IFERROR(D40/D39-1,NA()) -> 0.023741897 | H40: =IF(COUNT(D38:D40)=3,AVERAGE(D38:D40),NA()) -> 103.80647 | I40: =IFERROR(IF(AND(COUNT(D38:D40)=3,COUNT(D26:D28)=3),AVERAGE(D38:D40)/AVERAGE(D26:D28)-1,NA()),NA()) -> 0.35459223 | L40: 2030 | M40: =IF(SUMPRODUCT(($C$14:$C$266=$L$40)*ISNUMBER($D$14:$D$266))=0,NA(),SUMPRODUCT(($C$14:$C$266=$L$40)*IFERROR($D$14:$D$266,0))/SUMPRODUCT(($C$14:$C$266=$L$40)*ISNUMBER($D$14:$D$266))) -> #N/A | N40: =IF(SUMPRODUCT(($C$14:$C$266=$L$40)*ISNUMBER($E$14:$E$266))=0,NA(),SUMPRODUCT(($C$14:$C$266=$L$40)*IFERROR($E$14:$E$266,0))/SUMPRODUCT(($C$14:$C$266=$L$40)*ISNUMBER($E$14:$E$266))) -> #N/A | O40: =IFERROR(M40/M39-1,NA()) -> #N/A
A41: =IFERROR(IF(LEN(TRIM(TEXT(CPI!B35,"@")))<3,NA(),DATE(2000+VALUE(LEFT(CPI!B35,LEN(CPI!B35)-2)),VALUE(RIGHT(CPI!B35,2)),1)),NA()) -> 42826 | B41: =IFERROR(IF(CPI!B35="",NA(),CPI!B35),NA()) -> 1704 | C41: =IFERROR(YEAR(A41),0) -> 2017 | D41: =IFERROR(IF(CPI!C35="",NA(),IF(ISNUMBER(CPI!C35),CPI!C35,NA())),NA()) -> 108.9667 | E41: =IFERROR(IF(CPI!D35="",NA(),IF(ISNUMBER(CPI!D35),CPI!D35,NA())),NA()) -> 107.427 | F41: =IFERROR(D41/D29-1,NA()) -> 0.28956811 | G41: =IFERROR(D41/D40-1,NA()) -> 0.026558302 | H41: =IF(COUNT(D39:D41)=3,AVERAGE(D39:D41),NA()) -> 106.26673 | I41: =IFERROR(IF(AND(COUNT(D39:D41)=3,COUNT(D27:D29)=3),AVERAGE(D39:D41)/AVERAGE(D27:D29)-1,NA()),NA()) -> 0.32520117 | L41: 2031 | M41: =IF(SUMPRODUCT(($C$14:$C$266=$L$41)*ISNUMBER($D$14:$D$266))=0,NA(),SUMPRODUCT(($C$14:$C$266=$L$41)*IFERROR($D$14:$D$266,0))/SUMPRODUCT(($C$14:$C$266=$L$41)*ISNUMBER($D$14:$D$266))) -> #N/A | N41: =IF(SUMPRODUCT(($C$14:$C$266=$L$41)*ISNUMBER($E$14:$E$266))=0,NA(),SUMPRODUCT(($C$14:$C$266=$L$41)*IFERROR($E$14:$E$266,0))/SUMPRODUCT(($C$14:$C$266=$L$41)*ISNUMBER($E$14:$E$266))) -> #N/A | O41: =IFERROR(M41/M40-1,NA()) -> #N/A
A42: =IFERROR(IF(LEN(TRIM(TEXT(CPI!B36,"@")))<3,NA(),DATE(2000+VALUE(LEFT(CPI!B36,LEN(CPI!B36)-2)),VALUE(RIGHT(CPI!B36,2)),1)),NA()) -> 42856 | B42: =IFERROR(IF(CPI!B36="",NA(),CPI!B36),NA()) -> 1705 | C42: =IFERROR(YEAR(A42),0) -> 2017 | D42: =IFERROR(IF(CPI!C36="",NA(),IF(ISNUMBER(CPI!C36),CPI!C36,NA())),NA()) -> 110.5301 | E42: =IFERROR(IF(CPI!D36="",NA(),IF(ISNUMBER(CPI!D36),CPI!D36,NA())),NA()) -> 109.2069 | F42: =IFERROR(D42/D30-1,NA()) -> 0.2453773 | G42: =IFERROR(D42/D41-1,NA()) -> 0.014347502 | H42: =IF(COUNT(D40:D42)=3,AVERAGE(D40:D42),NA()) -> 108.54813 | I42: =IFERROR(IF(AND(COUNT(D40:D42)=3,COUNT(D28:D30)=3),AVERAGE(D40:D42)/AVERAGE(D28:D30)-1,NA()),NA()) -> 0.28938053 | L42: 2032 | M42: =IF(SUMPRODUCT(($C$14:$C$266=$L$42)*ISNUMBER($D$14:$D$266))=0,NA(),SUMPRODUCT(($C$14:$C$266=$L$42)*IFERROR($D$14:$D$266,0))/SUMPRODUCT(($C$14:$C$266=$L$42)*ISNUMBER($D$14:$D$266))) -> #N/A | N42: =IF(SUMPRODUCT(($C$14:$C$266=$L$42)*ISNUMBER($E$14:$E$266))=0,NA(),SUMPRODUCT(($C$14:$C$266=$L$42)*IFERROR($E$14:$E$266,0))/SUMPRODUCT(($C$14:$C$266=$L$42)*ISNUMBER($E$14:$E$266))) -> #N/A | O42: =IFERROR(M42/M41-1,NA()) -> #N/A
A43: =IFERROR(IF(LEN(TRIM(TEXT(CPI!B37,"@")))<3,NA(),DATE(2000+VALUE(LEFT(CPI!B37,LEN(CPI!B37)-2)),VALUE(RIGHT(CPI!B37,2)),1)),NA()) -> 42887 | B43: =IFERROR(IF(CPI!B37="",NA(),CPI!B37),NA()) -> 1706 | C43: =IFERROR(YEAR(A43),0) -> 2017 | D43: =IFERROR(IF(CPI!C37="",NA(),IF(ISNUMBER(CPI!C37),CPI!C37,NA())),NA()) -> 111.8477 | E43: =IFERROR(IF(CPI!D37="",NA(),IF(ISNUMBER(CPI!D37),CPI!D37,NA())),NA()) -> 110.6653 | F43: =IFERROR(D43/D31-1,NA()) -> 0.22087816 | G43: =IFERROR(D43/D42-1,NA()) -> 0.011920735 | H43: =IF(COUNT(D41:D43)=3,AVERAGE(D41:D43),NA()) -> 110.44817 | I43: =IFERROR(IF(AND(COUNT(D41:D43)=3,COUNT(D29:D31)=3),AVERAGE(D41:D43)/AVERAGE(D29:D31)-1,NA()),NA()) -> 0.25100146 | L43: 2033 | M43: =IF(SUMPRODUCT(($C$14:$C$266=$L$43)*ISNUMBER($D$14:$D$266))=0,NA(),SUMPRODUCT(($C$14:$C$266=$L$43)*IFERROR($D$14:$D$266,0))/SUMPRODUCT(($C$14:$C$266=$L$43)*ISNUMBER($D$14:$D$266))) -> #N/A | N43: =IF(SUMPRODUCT(($C$14:$C$266=$L$43)*ISNUMBER($E$14:$E$266))=0,NA(),SUMPRODUCT(($C$14:$C$266=$L$43)*IFERROR($E$14:$E$266,0))/SUMPRODUCT(($C$14:$C$266=$L$43)*ISNUMBER($E$14:$E$266))) -> #N/A | O43: =IFERROR(M43/M42-1,NA()) -> #N/A
A44: =IFERROR(IF(LEN(TRIM(TEXT(CPI!B38,"@")))<3,NA(),DATE(2000+VALUE(LEFT(CPI!B38,LEN(CPI!B38)-2)),VALUE(RIGHT(CPI!B38,2)),1)),NA()) -> 42917 | B44: =IFERROR(IF(CPI!B38="",NA(),CPI!B38),NA()) -> 1707 | C44: =IFERROR(YEAR(A44),0) -> 2017 | D44: =IFERROR(IF(CPI!C38="",NA(),IF(ISNUMBER(CPI!C38),CPI!C38,NA())),NA()) -> 113.7852 | E44: =IFERROR(IF(CPI!D38="",NA(),IF(ISNUMBER(CPI!D38),CPI!D38,NA())),NA()) -> 112.6183 | F44: =IFERROR(D44/D32-1,NA()) -> 0.21580972 | G44: =IFERROR(D44/D43-1,NA()) -> 0.017322663 | H44: =IF(COUNT(D42:D44)=3,AVERAGE(D42:D44),NA()) -> 112.05433 | I44: =IFERROR(IF(AND(COUNT(D42:D44)=3,COUNT(D30:D32)=3),AVERAGE(D42:D44)/AVERAGE(D30:D32)-1,NA()),NA()) -> 0.22708364
A45: =IFERROR(IF(LEN(TRIM(TEXT(CPI!B39,"@")))<3,NA(),DATE(2000+VALUE(LEFT(CPI!B39,LEN(CPI!B39)-2)),VALUE(RIGHT(CPI!B39,2)),1)),NA()) -> 42948 | B45: =IFERROR(IF(CPI!B39="",NA(),CPI!B39),NA()) -> 1708 | C45: =IFERROR(YEAR(A45),0) -> 2017 | D45: =IFERROR(IF(CPI!C39="",NA(),IF(ISNUMBER(CPI!C39),CPI!C39,NA())),NA()) -> 115.3819 | E45: =IFERROR(IF(CPI!D39="",NA(),IF(ISNUMBER(CPI!D39),CPI!D39,NA())),NA()) -> 114.231 | F45: =IFERROR(D45/D33-1,NA()) -> 0.24229259 | G45: =IFERROR(D45/D44-1,NA()) -> 0.014032581 | H45: =IF(COUNT(D43:D45)=3,AVERAGE(D43:D45),NA()) -> 113.6716 | I45: =IFERROR(IF(AND(COUNT(D43:D45)=3,COUNT(D31:D33)=3),AVERAGE(D43:D45)/AVERAGE(D31:D33)-1,NA()),NA()) -> 0.22632478
A46: =IFERROR(IF(LEN(TRIM(TEXT(CPI!B40,"@")))<3,NA(),DATE(2000+VALUE(LEFT(CPI!B40,LEN(CPI!B40)-2)),VALUE(RIGHT(CPI!B40,2)),1)),NA()) -> 42979 | B46: =IFERROR(IF(CPI!B40="",NA(),CPI!B40),NA()) -> 1709 | C46: =IFERROR(YEAR(A46),0) -> 2017 | D46: =IFERROR(IF(CPI!C40="",NA(),IF(ISNUMBER(CPI!C40),CPI!C40,NA())),NA()) -> 117.5719 | E46: =IFERROR(IF(CPI!D40="",NA(),IF(ISNUMBER(CPI!D40),CPI!D40,NA())),NA()) -> 116.0978 | F46: =IFERROR(D46/D34-1,NA()) -> 0.24909589 | G46: =IFERROR(D46/D45-1,NA()) -> 0.018980447 | H46: =IF(COUNT(D44:D46)=3,AVERAGE(D44:D46),NA()) -> 115.57967 | I46: =IFERROR(IF(AND(COUNT(D44:D46)=3,COUNT(D32:D34)=3),AVERAGE(D44:D46)/AVERAGE(D32:D34)-1,NA()),NA()) -> 0.23574174
A47: =IFERROR(IF(LEN(TRIM(TEXT(CPI!B41,"@")))<3,NA(),DATE(2000+VALUE(LEFT(CPI!B41,LEN(CPI!B41)-2)),VALUE(RIGHT(CPI!B41,2)),1)),NA()) -> 43009 | B47: =IFERROR(IF(CPI!B41="",NA(),CPI!B41),NA()) -> 1710 | C47: =IFERROR(YEAR(A47),0) -> 2017 | D47: =IFERROR(IF(CPI!C41="",NA(),IF(ISNUMBER(CPI!C41),CPI!C41,NA())),NA()) -> 119.3528 | E47: =IFERROR(IF(CPI!D41="",NA(),IF(ISNUMBER(CPI!D41),CPI!D41,NA())),NA()) -> 117.6245 | F47: =IFERROR(D47/D35-1,NA()) -> 0.23227949 | G47: =IFERROR(D47/D46-1,NA()) -> 0.015147327 | H47: =IF(COUNT(D45:D47)=3,AVERAGE(D45:D47),NA()) -> 117.43553 | I47: =IFERROR(IF(AND(COUNT(D45:D47)=3,COUNT(D33:D35)=3),AVERAGE(D45:D47)/AVERAGE(D33:D35)-1,NA()),NA()) -> 0.24113196
A48: =IFERROR(IF(LEN(TRIM(TEXT(CPI!B42,"@")))<3,NA(),DATE(2000+VALUE(LEFT(CPI!B42,LEN(CPI!B42)-2)),VALUE(RIGHT(CPI!B42,2)),1)),NA()) -> 43040 | B48: =IFERROR(IF(CPI!B42="",NA(),CPI!B42),NA()) -> 1711 | C48: =IFERROR(YEAR(A48),0) -> 2017 | D48: =IFERROR(IF(CPI!C42="",NA(),IF(ISNUMBER(CPI!C42),CPI!C42,NA())),NA()) -> 120.994 | E48: =IFERROR(IF(CPI!D42="",NA(),IF(ISNUMBER(CPI!D42),CPI!D42,NA())),NA()) -> 119.1358 | F48: =IFERROR(D48/D36-1,NA()) -> 0.22496419 | G48: =IFERROR(D48/D47-1,NA()) -> 0.013750829 | H48: =IF(COUNT(D46:D48)=3,AVERAGE(D46:D48),NA()) -> 119.30623 | I48: =IFERROR(IF(AND(COUNT(D46:D48)=3,COUNT(D34:D36)=3),AVERAGE(D46:D48)/AVERAGE(D34:D36)-1,NA()),NA()) -> 0.23524854
A49: =IFERROR(IF(LEN(TRIM(TEXT(CPI!B43,"@")))<3,NA(),DATE(2000+VALUE(LEFT(CPI!B43,LEN(CPI!B43)-2)),VALUE(RIGHT(CPI!B43,2)),1)),NA()) -> 43070 | B49: =IFERROR(IF(CPI!B43="",NA(),CPI!B43),NA()) -> 1712 | C49: =IFERROR(YEAR(A49),0) -> 2017 | D49: =IFERROR(IF(CPI!C43="",NA(),IF(ISNUMBER(CPI!C43),CPI!C43,NA())),NA()) -> 124.7956 | E49: =IFERROR(IF(CPI!D43="",NA(),IF(ISNUMBER(CPI!D43),CPI!D43,NA())),NA()) -> 121.1263 | F49: =IFERROR(D49/D37-1,NA()) -> 0.247956 | G49: =IFERROR(D49/D48-1,NA()) -> 0.03141974 | H49: =IF(COUNT(D47:D49)=3,AVERAGE(D47:D49),NA()) -> 121.71413 | I49: =IFERROR(IF(AND(COUNT(D47:D49)=3,COUNT(D35:D37)=3),AVERAGE(D47:D49)/AVERAGE(D35:D37)-1,NA()),NA()) -> 0.23513812
A50: =IFERROR(IF(LEN(TRIM(TEXT(CPI!B44,"@")))<3,NA(),DATE(2000+VALUE(LEFT(CPI!B44,LEN(CPI!B44)-2)),VALUE(RIGHT(CPI!B44,2)),1)),NA()) -> 43101 | B50: =IFERROR(IF(CPI!B44="",NA(),CPI!B44),NA()) -> 1801 | C50: =IFERROR(YEAR(A50),0) -> 2018 | D50: =IFERROR(IF(CPI!C44="",NA(),IF(ISNUMBER(CPI!C44),CPI!C44,NA())),NA()) -> 126.9887 | E50: =IFERROR(IF(CPI!D44="",NA(),IF(ISNUMBER(CPI!D44),CPI!D44,NA())),NA()) -> 122.9418 | F50: =IFERROR(D50/D38-1,NA()) -> 0.25006226 | G50: =IFERROR(D50/D49-1,NA()) -> 0.017573536 | H50: =IF(COUNT(D48:D50)=3,AVERAGE(D48:D50),NA()) -> 124.25943 | I50: =IFERROR(IF(AND(COUNT(D48:D50)=3,COUNT(D36:D38)=3),AVERAGE(D48:D50)/AVERAGE(D36:D38)-1,NA()),NA()) -> 0.24110749
A51: =IFERROR(IF(LEN(TRIM(TEXT(CPI!B45,"@")))<3,NA(),DATE(2000+VALUE(LEFT(CPI!B45,LEN(CPI!B45)-2)),VALUE(RIGHT(CPI!B45,2)),1)),NA()) -> 43132 | B51: =IFERROR(IF(CPI!B45="",NA(),CPI!B45),NA()) -> 1802 | C51: =IFERROR(YEAR(A51),0) -> 2018 | D51: =IFERROR(IF(CPI!C45="",NA(),IF(ISNUMBER(CPI!C45),CPI!C45,NA())),NA()) -> 130.0606 | E51: =IFERROR(IF(CPI!D45="",NA(),IF(ISNUMBER(CPI!D45),CPI!D45,NA())),NA()) -> 125.5123 | F51: =IFERROR(D51/D39-1,NA()) -> 0.25437113 | G51: =IFERROR(D51/D50-1,NA()) -> 0.024190341 | H51: =IF(COUNT(D49:D51)=3,AVERAGE(D49:D51),NA()) -> 127.28163 | I51: =IFERROR(IF(AND(COUNT(D49:D51)=3,COUNT(D37:D39)=3),AVERAGE(D49:D51)/AVERAGE(D37:D39)-1,NA()),NA()) -> 0.25083581
A52: =IFERROR(IF(LEN(TRIM(TEXT(CPI!B46,"@")))<3,NA(),DATE(2000+VALUE(LEFT(CPI!B46,LEN(CPI!B46)-2)),VALUE(RIGHT(CPI!B46,2)),1)),NA()) -> 43160 | B52: =IFERROR(IF(CPI!B46="",NA(),CPI!B46),NA()) -> 1803 | C52: =IFERROR(YEAR(A52),0) -> 2018 | D52: =IFERROR(IF(CPI!C46="",NA(),IF(ISNUMBER(CPI!C46),CPI!C46,NA())),NA()) -> 133.1054 | E52: =IFERROR(IF(CPI!D46="",NA(),IF(ISNUMBER(CPI!D46),CPI!D46,NA())),NA()) -> 128.746 | F52: =IFERROR(D52/D40-1,NA()) -> 0.25396523 | G52: =IFERROR(D52/D51-1,NA()) -> 0.023410626 | H52: =IF(COUNT(D50:D52)=3,AVERAGE(D50:D52),NA()) -> 130.05157 | I52: =IFERROR(IF(AND(COUNT(D50:D52)=3,COUNT(D38:D40)=3),AVERAGE(D50:D52)/AVERAGE(D38:D40)-1,NA()),NA()) -> 0.25282722
A53: =IFERROR(IF(LEN(TRIM(TEXT(CPI!B47,"@")))<3,NA(),DATE(2000+VALUE(LEFT(CPI!B47,LEN(CPI!B47)-2)),VALUE(RIGHT(CPI!B47,2)),1)),NA()) -> 43191 | B53: =IFERROR(IF(CPI!B47="",NA(),CPI!B47),NA()) -> 1804 | C53: =IFERROR(YEAR(A53),0) -> 2018 | D53: =IFERROR(IF(CPI!C47="",NA(),IF(ISNUMBER(CPI!C47),CPI!C47,NA())),NA()) -> 136.7512 | E53: =IFERROR(IF(CPI!D47="",NA(),IF(ISNUMBER(CPI!D47),CPI!D47,NA())),NA()) -> 131.4884 | F53: =IFERROR(D53/D41-1,NA()) -> 0.25498157 | G53: =IFERROR(D53/D52-1,NA()) -> 0.027390324 | H53: =IF(COUNT(D51:D53)=3,AVERAGE(D51:D53),NA()) -> 133.30573 | I53: =IFERROR(IF(AND(COUNT(D51:D53)=3,COUNT(D39:D41)=3),AVERAGE(D51:D53)/AVERAGE(D39:D41)-1,NA()),NA()) -> 0.25444463
A54: =IFERROR(IF(LEN(TRIM(TEXT(CPI!B48,"@")))<3,NA(),DATE(2000+VALUE(LEFT(CPI!B48,LEN(CPI!B48)-2)),VALUE(RIGHT(CPI!B48,2)),1)),NA()) -> 43221 | B54: =IFERROR(IF(CPI!B48="",NA(),CPI!B48),NA()) -> 1805 | C54: =IFERROR(YEAR(A54),0) -> 2018 | D54: =IFERROR(IF(CPI!C48="",NA(),IF(ISNUMBER(CPI!C48),CPI!C48,NA())),NA()) -> 139.5893 | E54: =IFERROR(IF(CPI!D48="",NA(),IF(ISNUMBER(CPI!D48),CPI!D48,NA())),NA()) -> 134.9794 | F54: =IFERROR(D54/D42-1,NA()) -> 0.26290757 | G54: =IFERROR(D54/D53-1,NA()) -> 0.020753748 | H54: =IF(COUNT(D52:D54)=3,AVERAGE(D52:D54),NA()) -> 136.48197 | I54: =IFERROR(IF(AND(COUNT(D52:D54)=3,COUNT(D40:D42)=3),AVERAGE(D52:D54)/AVERAGE(D40:D42)-1,NA()),NA()) -> 0.25734052
A55: =IFERROR(IF(LEN(TRIM(TEXT(CPI!B49,"@")))<3,NA(),DATE(2000+VALUE(LEFT(CPI!B49,LEN(CPI!B49)-2)),VALUE(RIGHT(CPI!B49,2)),1)),NA()) -> 43252 | B55: =IFERROR(IF(CPI!B49="",NA(),CPI!B49),NA()) -> 1806 | C55: =IFERROR(YEAR(A55),0) -> 2018 | D55: =IFERROR(IF(CPI!C49="",NA(),IF(ISNUMBER(CPI!C49),CPI!C49,NA())),NA()) -> 144.8053 | E55: =IFERROR(IF(CPI!D49="",NA(),IF(ISNUMBER(CPI!D49),CPI!D49,NA())),NA()) -> 140.4784 | F55: =IFERROR(D55/D43-1,NA()) -> 0.29466498 | G55: =IFERROR(D55/D54-1,NA()) -> 0.037366761 | H55: =IF(COUNT(D53:D55)=3,AVERAGE(D53:D55),NA()) -> 140.38193 | I55: =IFERROR(IF(AND(COUNT(D53:D55)=3,COUNT(D41:D43)=3),AVERAGE(D53:D55)/AVERAGE(D41:D43)-1,NA()),NA()) -> 0.27102095
... A266: =IFERROR(IF(LEN(TRIM(TEXT(CPI!B260,"@")))<3,NA(),DATE(2000+VALUE(LEFT(CPI!B260,LEN(CPI!B260)-2)),VALUE(RIGHT(CPI!B260,2)),1)),NA()) -> #N/A | B266: =IFERROR(IF(CPI!B260="",NA(),CPI!B260),NA()) -> #N/A | C266: =IFERROR(YEAR(A266),0) -> 0 | D266: =IFERROR(IF(CPI!C260="",NA(),IF(ISNUMBER(CPI!C260),CPI!C260,NA())),NA()) -> #N/A | E266: =IFERROR(IF(CPI!D260="",NA(),IF(ISNUMBER(CPI!D260),CPI!D260,NA())),NA()) -> #N/A | F266: =IFERROR(D266/D254-1,NA()) -> #N/A | G266: =IFERROR(D266/D265-1,NA()) -> #N/A | H266: =IF(COUNT(D264:D266)=3,AVERAGE(D264:D266),NA()) -> #N/A | I266: =IFERROR(IF(AND(COUNT(D264:D266)=3,COUNT(D252:D254)=3),AVERAGE(D264:D266)/AVERAGE(D252:D254)-1,NA()),NA()) -> #N/A

Sheet TEMPLATE - Quarterly
A1: TEMPLATE — Quarterly Series
A2: Copy this tab (right-click → Move or Copy → 'Create a copy') and paste your data into Date (col A) and Value (col B) starting row 16. OR link to a raw tab via formula (e.g., =Reserves!A8).
A4: METADATA
A5: Series name | B5: New quarterly metric
A6: Country | B6: Argentina
A7: Units | B7: Local currency, mm
A9: SETTINGS
A10: Annual aggregation method | B10: Sum | D10: (Sum = flow vars; Average = indices/rates; End of Period = stocks)
A11: Year +1 YoY % (proj.) | B11: 0.05
A12: Year +2 YoY % (proj.) | B12: 0.04
A14: QUARTERLY DATA (paste Date & Value below; computed columns auto-update) | I14: ANNUAL AGGREGATION | N14: PROJECTIONS
A15: Date | B15: Period | C15: Year | D15: Value | E15: QoQ % | F15: YoY % | G15: 4Q sum | I15: Year | J15: Value | K15: YoY % | N15: Year | O15: Value (proj.) | P15: YoY %
B16: =IFERROR(IF(ISNUMBER(A16),TEXT(YEAR(A16)-2000,"00")&CEILING(MONTH(A16)/3,1),NA()),NA()) -> #N/A | C16: =IFERROR(YEAR(A16),0) -> 1899 | E16: =NA() -> #N/A | F16: =NA() -> #N/A | G16: =NA() -> #N/A | I16: 2000 | J16: =CHOOSE(MATCH($B$10,{"Sum","Average","End of Period"},0),IF(SUMPRODUCT(($C$16:$C$215=$I$16)*ISNUMBER($D$16:$D$215))=0,NA(),SUMPRODUCT(($C$16:$C$215=$I$16)*IFERROR($D$16:$D$215,0))),IF(SUMPRODUCT(($C$16:$C$215=$I$16)*ISNUMBER($D$16:$D$215))=0,NA(),SUMPRODUCT(($C$16:$C$215=$I$16)*IFERROR($D$16:$D$215,0))/SUMPRODUCT(($C$16:$C$215=$I$16)*ISNUMBER($D$16:$D$215))),IFERROR(LOOKUP(2,1/(($C$16:$C$215=$I$16)*ISNUMBER($D$16:$D$215)),$D$16:$D$215),NA())) -> #N/A | K16: =NA() -> #N/A | N16: =IFERROR(IFERROR(LOOKUP(2,1/ISNUMBER(J16:J50),I16:I50),NA())+1,NA()) -> #N/A | O16: =IFERROR((IFERROR(INDEX(J16:J50,MATCH(N16-1,I16:I50,0)),NA()))*(1+$B$11),NA()) -> #N/A | P16: =$B$11 -> 0.05
B17: =IFERROR(IF(ISNUMBER(A17),TEXT(YEAR(A17)-2000,"00")&CEILING(MONTH(A17)/3,1),NA()),NA()) -> #N/A | C17: =IFERROR(YEAR(A17),0) -> 1899 | E17: =IFERROR(D17/D16-1,NA()) -> #N/A | F17: =NA() -> #N/A | G17: =NA() -> #N/A | I17: 2001 | J17: =CHOOSE(MATCH($B$10,{"Sum","Average","End of Period"},0),IF(SUMPRODUCT(($C$16:$C$215=$I$17)*ISNUMBER($D$16:$D$215))=0,NA(),SUMPRODUCT(($C$16:$C$215=$I$17)*IFERROR($D$16:$D$215,0))),IF(SUMPRODUCT(($C$16:$C$215=$I$17)*ISNUMBER($D$16:$D$215))=0,NA(),SUMPRODUCT(($C$16:$C$215=$I$17)*IFERROR($D$16:$D$215,0))/SUMPRODUCT(($C$16:$C$215=$I$17)*ISNUMBER($D$16:$D$215))),IFERROR(LOOKUP(2,1/(($C$16:$C$215=$I$17)*ISNUMBER($D$16:$D$215)),$D$16:$D$215),NA())) -> #N/A | K17: =IFERROR(J17/J16-1,NA()) -> #N/A | N17: =N16+1 -> #N/A | O17: =IFERROR(O16*(1+$B$12),NA()) -> #N/A | P17: =$B$12 -> 0.04
B18: =IFERROR(IF(ISNUMBER(A18),TEXT(YEAR(A18)-2000,"00")&CEILING(MONTH(A18)/3,1),NA()),NA()) -> #N/A | C18: =IFERROR(YEAR(A18),0) -> 1899 | E18: =IFERROR(D18/D17-1,NA()) -> #N/A | F18: =NA() -> #N/A | G18: =NA() -> #N/A | I18: 2002 | J18: =CHOOSE(MATCH($B$10,{"Sum","Average","End of Period"},0),IF(SUMPRODUCT(($C$16:$C$215=$I$18)*ISNUMBER($D$16:$D$215))=0,NA(),SUMPRODUCT(($C$16:$C$215=$I$18)*IFERROR($D$16:$D$215,0))),IF(SUMPRODUCT(($C$16:$C$215=$I$18)*ISNUMBER($D$16:$D$215))=0,NA(),SUMPRODUCT(($C$16:$C$215=$I$18)*IFERROR($D$16:$D$215,0))/SUMPRODUCT(($C$16:$C$215=$I$18)*ISNUMBER($D$16:$D$215))),IFERROR(LOOKUP(2,1/(($C$16:$C$215=$I$18)*ISNUMBER($D$16:$D$215)),$D$16:$D$215),NA())) -> #N/A | K18: =IFERROR(J18/J17-1,NA()) -> #N/A
B19: =IFERROR(IF(ISNUMBER(A19),TEXT(YEAR(A19)-2000,"00")&CEILING(MONTH(A19)/3,1),NA()),NA()) -> #N/A | C19: =IFERROR(YEAR(A19),0) -> 1899 | E19: =IFERROR(D19/D18-1,NA()) -> #N/A | F19: =NA() -> #N/A | G19: =IF(COUNT(D16:D19)=4,SUM(D16:D19),NA()) -> #N/A | I19: 2003 | J19: =CHOOSE(MATCH($B$10,{"Sum","Average","End of Period"},0),IF(SUMPRODUCT(($C$16:$C$215=$I$19)*ISNUMBER($D$16:$D$215))=0,NA(),SUMPRODUCT(($C$16:$C$215=$I$19)*IFERROR($D$16:$D$215,0))),IF(SUMPRODUCT(($C$16:$C$215=$I$19)*ISNUMBER($D$16:$D$215))=0,NA(),SUMPRODUCT(($C$16:$C$215=$I$19)*IFERROR($D$16:$D$215,0))/SUMPRODUCT(($C$16:$C$215=$I$19)*ISNUMBER($D$16:$D$215))),IFERROR(LOOKUP(2,1/(($C$16:$C$215=$I$19)*ISNUMBER($D$16:$D$215)),$D$16:$D$215),NA())) -> #N/A | K19: =IFERROR(J19/J18-1,NA()) -> #N/A
B20: =IFERROR(IF(ISNUMBER(A20),TEXT(YEAR(A20)-2000,"00")&CEILING(MONTH(A20)/3,1),NA()),NA()) -> #N/A | C20: =IFERROR(YEAR(A20),0) -> 1899 | E20: =IFERROR(D20/D19-1,NA()) -> #N/A | F20: =IFERROR(D20/D16-1,NA()) -> #N/A | G20: =IF(COUNT(D17:D20)=4,SUM(D17:D20),NA()) -> #N/A | I20: 2004 | J20: =CHOOSE(MATCH($B$10,{"Sum","Average","End of Period"},0),IF(SUMPRODUCT(($C$16:$C$215=$I$20)*ISNUMBER($D$16:$D$215))=0,NA(),SUMPRODUCT(($C$16:$C$215=$I$20)*IFERROR($D$16:$D$215,0))),IF(SUMPRODUCT(($C$16:$C$215=$I$20)*ISNUMBER($D$16:$D$215))=0,NA(),SUMPRODUCT(($C$16:$C$215=$I$20)*IFERROR($D$16:$D$215,0))/SUMPRODUCT(($C$16:$C$215=$I$20)*ISNUMBER($D$16:$D$215))),IFERROR(LOOKUP(2,1/(($C$16:$C$215=$I$20)*ISNUMBER($D$16:$D$215)),$D$16:$D$215),NA())) -> #N/A | K20: =IFERROR(J20/J19-1,NA()) -> #N/A
B21: =IFERROR(IF(ISNUMBER(A21),TEXT(YEAR(A21)-2000,"00")&CEILING(MONTH(A21)/3,1),NA()),NA()) -> #N/A | C21: =IFERROR(YEAR(A21),0) -> 1899 | E21: =IFERROR(D21/D20-1,NA()) -> #N/A | F21: =IFERROR(D21/D17-1,NA()) -> #N/A | G21: =IF(COUNT(D18:D21)=4,SUM(D18:D21),NA()) -> #N/A | I21: 2005 | J21: =CHOOSE(MATCH($B$10,{"Sum","Average","End of Period"},0),IF(SUMPRODUCT(($C$16:$C$215=$I$21)*ISNUMBER($D$16:$D$215))=0,NA(),SUMPRODUCT(($C$16:$C$215=$I$21)*IFERROR($D$16:$D$215,0))),IF(SUMPRODUCT(($C$16:$C$215=$I$21)*ISNUMBER($D$16:$D$215))=0,NA(),SUMPRODUCT(($C$16:$C$215=$I$21)*IFERROR($D$16:$D$215,0))/SUMPRODUCT(($C$16:$C$215=$I$21)*ISNUMBER($D$16:$D$215))),IFERROR(LOOKUP(2,1/(($C$16:$C$215=$I$21)*ISNUMBER($D$16:$D$215)),$D$16:$D$215),NA())) -> #N/A | K21: =IFERROR(J21/J20-1,NA()) -> #N/A
B22: =IFERROR(IF(ISNUMBER(A22),TEXT(YEAR(A22)-2000,"00")&CEILING(MONTH(A22)/3,1),NA()),NA()) -> #N/A | C22: =IFERROR(YEAR(A22),0) -> 1899 | E22: =IFERROR(D22/D21-1,NA()) -> #N/A | F22: =IFERROR(D22/D18-1,NA()) -> #N/A | G22: =IF(COUNT(D19:D22)=4,SUM(D19:D22),NA()) -> #N/A | I22: 2006 | J22: =CHOOSE(MATCH($B$10,{"Sum","Average","End of Period"},0),IF(SUMPRODUCT(($C$16:$C$215=$I$22)*ISNUMBER($D$16:$D$215))=0,NA(),SUMPRODUCT(($C$16:$C$215=$I$22)*IFERROR($D$16:$D$215,0))),IF(SUMPRODUCT(($C$16:$C$215=$I$22)*ISNUMBER($D$16:$D$215))=0,NA(),SUMPRODUCT(($C$16:$C$215=$I$22)*IFERROR($D$16:$D$215,0))/SUMPRODUCT(($C$16:$C$215=$I$22)*ISNUMBER($D$16:$D$215))),IFERROR(LOOKUP(2,1/(($C$16:$C$215=$I$22)*ISNUMBER($D$16:$D$215)),$D$16:$D$215),NA())) -> #N/A | K22: =IFERROR(J22/J21-1,NA()) -> #N/A
B23: =IFERROR(IF(ISNUMBER(A23),TEXT(YEAR(A23)-2000,"00")&CEILING(MONTH(A23)/3,1),NA()),NA()) -> #N/A | C23: =IFERROR(YEAR(A23),0) -> 1899 | E23: =IFERROR(D23/D22-1,NA()) -> #N/A | F23: =IFERROR(D23/D19-1,NA()) -> #N/A | G23: =IF(COUNT(D20:D23)=4,SUM(D20:D23),NA()) -> #N/A | I23: 2007 | J23: =CHOOSE(MATCH($B$10,{"Sum","Average","End of Period"},0),IF(SUMPRODUCT(($C$16:$C$215=$I$23)*ISNUMBER($D$16:$D$215))=0,NA(),SUMPRODUCT(($C$16:$C$215=$I$23)*IFERROR($D$16:$D$215,0))),IF(SUMPRODUCT(($C$16:$C$215=$I$23)*ISNUMBER($D$16:$D$215))=0,NA(),SUMPRODUCT(($C$16:$C$215=$I$23)*IFERROR($D$16:$D$215,0))/SUMPRODUCT(($C$16:$C$215=$I$23)*ISNUMBER($D$16:$D$215))),IFERROR(LOOKUP(2,1/(($C$16:$C$215=$I$23)*ISNUMBER($D$16:$D$215)),$D$16:$D$215),NA())) -> #N/A | K23: =IFERROR(J23/J22-1,NA()) -> #N/A
B24: =IFERROR(IF(ISNUMBER(A24),TEXT(YEAR(A24)-2000,"00")&CEILING(MONTH(A24)/3,1),NA()),NA()) -> #N/A | C24: =IFERROR(YEAR(A24),0) -> 1899 | E24: =IFERROR(D24/D23-1,NA()) -> #N/A | F24: =IFERROR(D24/D20-1,NA()) -> #N/A | G24: =IF(COUNT(D21:D24)=4,SUM(D21:D24),NA()) -> #N/A | I24: 2008 | J24: =CHOOSE(MATCH($B$10,{"Sum","Average","End of Period"},0),IF(SUMPRODUCT(($C$16:$C$215=$I$24)*ISNUMBER($D$16:$D$215))=0,NA(),SUMPRODUCT(($C$16:$C$215=$I$24)*IFERROR($D$16:$D$215,0))),IF(SUMPRODUCT(($C$16:$C$215=$I$24)*ISNUMBER($D$16:$D$215))=0,NA(),SUMPRODUCT(($C$16:$C$215=$I$24)*IFERROR($D$16:$D$215,0))/SUMPRODUCT(($C$16:$C$215=$I$24)*ISNUMBER($D$16:$D$215))),IFERROR(LOOKUP(2,1/(($C$16:$C$215=$I$24)*ISNUMBER($D$16:$D$215)),$D$16:$D$215),NA())) -> #N/A | K24: =IFERROR(J24/J23-1,NA()) -> #N/A
B25: =IFERROR(IF(ISNUMBER(A25),TEXT(YEAR(A25)-2000,"00")&CEILING(MONTH(A25)/3,1),NA()),NA()) -> #N/A | C25: =IFERROR(YEAR(A25),0) -> 1899 | E25: =IFERROR(D25/D24-1,NA()) -> #N/A | F25: =IFERROR(D25/D21-1,NA()) -> #N/A | G25: =IF(COUNT(D22:D25)=4,SUM(D22:D25),NA()) -> #N/A | I25: 2009 | J25: =CHOOSE(MATCH($B$10,{"Sum","Average","End of Period"},0),IF(SUMPRODUCT(($C$16:$C$215=$I$25)*ISNUMBER($D$16:$D$215))=0,NA(),SUMPRODUCT(($C$16:$C$215=$I$25)*IFERROR($D$16:$D$215,0))),IF(SUMPRODUCT(($C$16:$C$215=$I$25)*ISNUMBER($D$16:$D$215))=0,NA(),SUMPRODUCT(($C$16:$C$215=$I$25)*IFERROR($D$16:$D$215,0))/SUMPRODUCT(($C$16:$C$215=$I$25)*ISNUMBER($D$16:$D$215))),IFERROR(LOOKUP(2,1/(($C$16:$C$215=$I$25)*ISNUMBER($D$16:$D$215)),$D$16:$D$215),NA())) -> #N/A | K25: =IFERROR(J25/J24-1,NA()) -> #N/A
B26: =IFERROR(IF(ISNUMBER(A26),TEXT(YEAR(A26)-2000,"00")&CEILING(MONTH(A26)/3,1),NA()),NA()) -> #N/A | C26: =IFERROR(YEAR(A26),0) -> 1899 | E26: =IFERROR(D26/D25-1,NA()) -> #N/A | F26: =IFERROR(D26/D22-1,NA()) -> #N/A | G26: =IF(COUNT(D23:D26)=4,SUM(D23:D26),NA()) -> #N/A | I26: 2010 | J26: =CHOOSE(MATCH($B$10,{"Sum","Average","End of Period"},0),IF(SUMPRODUCT(($C$16:$C$215=$I$26)*ISNUMBER($D$16:$D$215))=0,NA(),SUMPRODUCT(($C$16:$C$215=$I$26)*IFERROR($D$16:$D$215,0))),IF(SUMPRODUCT(($C$16:$C$215=$I$26)*ISNUMBER($D$16:$D$215))=0,NA(),SUMPRODUCT(($C$16:$C$215=$I$26)*IFERROR($D$16:$D$215,0))/SUMPRODUCT(($C$16:$C$215=$I$26)*ISNUMBER($D$16:$D$215))),IFERROR(LOOKUP(2,1/(($C$16:$C$215=$I$26)*ISNUMBER($D$16:$D$215)),$D$16:$D$215),NA())) -> #N/A | K26: =IFERROR(J26/J25-1,NA()) -> #N/A
B27: =IFERROR(IF(ISNUMBER(A27),TEXT(YEAR(A27)-2000,"00")&CEILING(MONTH(A27)/3,1),NA()),NA()) -> #N/A | C27: =IFERROR(YEAR(A27),0) -> 1899 | E27: =IFERROR(D27/D26-1,NA()) -> #N/A | F27: =IFERROR(D27/D23-1,NA()) -> #N/A | G27: =IF(COUNT(D24:D27)=4,SUM(D24:D27),NA()) -> #N/A | I27: 2011 | J27: =CHOOSE(MATCH($B$10,{"Sum","Average","End of Period"},0),IF(SUMPRODUCT(($C$16:$C$215=$I$27)*ISNUMBER($D$16:$D$215))=0,NA(),SUMPRODUCT(($C$16:$C$215=$I$27)*IFERROR($D$16:$D$215,0))),IF(SUMPRODUCT(($C$16:$C$215=$I$27)*ISNUMBER($D$16:$D$215))=0,NA(),SUMPRODUCT(($C$16:$C$215=$I$27)*IFERROR($D$16:$D$215,0))/SUMPRODUCT(($C$16:$C$215=$I$27)*ISNUMBER($D$16:$D$215))),IFERROR(LOOKUP(2,1/(($C$16:$C$215=$I$27)*ISNUMBER($D$16:$D$215)),$D$16:$D$215),NA())) -> #N/A | K27: =IFERROR(J27/J26-1,NA()) -> #N/A
B28: =IFERROR(IF(ISNUMBER(A28),TEXT(YEAR(A28)-2000,"00")&CEILING(MONTH(A28)/3,1),NA()),NA()) -> #N/A | C28: =IFERROR(YEAR(A28),0) -> 1899 | E28: =IFERROR(D28/D27-1,NA()) -> #N/A | F28: =IFERROR(D28/D24-1,NA()) -> #N/A | G28: =IF(COUNT(D25:D28)=4,SUM(D25:D28),NA()) -> #N/A | I28: 2012 | J28: =CHOOSE(MATCH($B$10,{"Sum","Average","End of Period"},0),IF(SUMPRODUCT(($C$16:$C$215=$I$28)*ISNUMBER($D$16:$D$215))=0,NA(),SUMPRODUCT(($C$16:$C$215=$I$28)*IFERROR($D$16:$D$215,0))),IF(SUMPRODUCT(($C$16:$C$215=$I$28)*ISNUMBER($D$16:$D$215))=0,NA(),SUMPRODUCT(($C$16:$C$215=$I$28)*IFERROR($D$16:$D$215,0))/SUMPRODUCT(($C$16:$C$215=$I$28)*ISNUMBER($D$16:$D$215))),IFERROR(LOOKUP(2,1/(($C$16:$C$215=$I$28)*ISNUMBER($D$16:$D$215)),$D$16:$D$215),NA())) -> #N/A | K28: =IFERROR(J28/J27-1,NA()) -> #N/A
B29: =IFERROR(IF(ISNUMBER(A29),TEXT(YEAR(A29)-2000,"00")&CEILING(MONTH(A29)/3,1),NA()),NA()) -> #N/A | C29: =IFERROR(YEAR(A29),0) -> 1899 | E29: =IFERROR(D29/D28-1,NA()) -> #N/A | F29: =IFERROR(D29/D25-1,NA()) -> #N/A | G29: =IF(COUNT(D26:D29)=4,SUM(D26:D29),NA()) -> #N/A | I29: 2013 | J29: =CHOOSE(MATCH($B$10,{"Sum","Average","End of Period"},0),IF(SUMPRODUCT(($C$16:$C$215=$I$29)*ISNUMBER($D$16:$D$215))=0,NA(),SUMPRODUCT(($C$16:$C$215=$I$29)*IFERROR($D$16:$D$215,0))),IF(SUMPRODUCT(($C$16:$C$215=$I$29)*ISNUMBER($D$16:$D$215))=0,NA(),SUMPRODUCT(($C$16:$C$215=$I$29)*IFERROR($D$16:$D$215,0))/SUMPRODUCT(($C$16:$C$215=$I$29)*ISNUMBER($D$16:$D$215))),IFERROR(LOOKUP(2,1/(($C$16:$C$215=$I$29)*ISNUMBER($D$16:$D$215)),$D$16:$D$215),NA())) -> #N/A | K29: =IFERROR(J29/J28-1,NA()) -> #N/A
B30: =IFERROR(IF(ISNUMBER(A30),TEXT(YEAR(A30)-2000,"00")&CEILING(MONTH(A30)/3,1),NA()),NA()) -> #N/A | C30: =IFERROR(YEAR(A30),0) -> 1899 | E30: =IFERROR(D30/D29-1,NA()) -> #N/A | F30: =IFERROR(D30/D26-1,NA()) -> #N/A | G30: =IF(COUNT(D27:D30)=4,SUM(D27:D30),NA()) -> #N/A | I30: 2014 | J30: =CHOOSE(MATCH($B$10,{"Sum","Average","End of Period"},0),IF(SUMPRODUCT(($C$16:$C$215=$I$30)*ISNUMBER($D$16:$D$215))=0,NA(),SUMPRODUCT(($C$16:$C$215=$I$30)*IFERROR($D$16:$D$215,0))),IF(SUMPRODUCT(($C$16:$C$215=$I$30)*ISNUMBER($D$16:$D$215))=0,NA(),SUMPRODUCT(($C$16:$C$215=$I$30)*IFERROR($D$16:$D$215,0))/SUMPRODUCT(($C$16:$C$215=$I$30)*ISNUMBER($D$16:$D$215))),IFERROR(LOOKUP(2,1/(($C$16:$C$215=$I$30)*ISNUMBER($D$16:$D$215)),$D$16:$D$215),NA())) -> #N/A | K30: =IFERROR(J30/J29-1,NA()) -> #N/A
B31: =IFERROR(IF(ISNUMBER(A31),TEXT(YEAR(A31)-2000,"00")&CEILING(MONTH(A31)/3,1),NA()),NA()) -> #N/A | C31: =IFERROR(YEAR(A31),0) -> 1899 | E31: =IFERROR(D31/D30-1,NA()) -> #N/A | F31: =IFERROR(D31/D27-1,NA()) -> #N/A | G31: =IF(COUNT(D28:D31)=4,SUM(D28:D31),NA()) -> #N/A | I31: 2015 | J31: =CHOOSE(MATCH($B$10,{"Sum","Average","End of Period"},0),IF(SUMPRODUCT(($C$16:$C$215=$I$31)*ISNUMBER($D$16:$D$215))=0,NA(),SUMPRODUCT(($C$16:$C$215=$I$31)*IFERROR($D$16:$D$215,0))),IF(SUMPRODUCT(($C$16:$C$215=$I$31)*ISNUMBER($D$16:$D$215))=0,NA(),SUMPRODUCT(($C$16:$C$215=$I$31)*IFERROR($D$16:$D$215,0))/SUMPRODUCT(($C$16:$C$215=$I$31)*ISNUMBER($D$16:$D$215))),IFERROR(LOOKUP(2,1/(($C$16:$C$215=$I$31)*ISNUMBER($D$16:$D$215)),$D$16:$D$215),NA())) -> #N/A | K31: =IFERROR(J31/J30-1,NA()) -> #N/A
B32: =IFERROR(IF(ISNUMBER(A32),TEXT(YEAR(A32)-2000,"00")&CEILING(MONTH(A32)/3,1),NA()),NA()) -> #N/A | C32: =IFERROR(YEAR(A32),0) -> 1899 | E32: =IFERROR(D32/D31-1,NA()) -> #N/A | F32: =IFERROR(D32/D28-1,NA()) -> #N/A | G32: =IF(COUNT(D29:D32)=4,SUM(D29:D32),NA()) -> #N/A | I32: 2016 | J32: =CHOOSE(MATCH($B$10,{"Sum","Average","End of Period"},0),IF(SUMPRODUCT(($C$16:$C$215=$I$32)*ISNUMBER($D$16:$D$215))=0,NA(),SUMPRODUCT(($C$16:$C$215=$I$32)*IFERROR($D$16:$D$215,0))),IF(SUMPRODUCT(($C$16:$C$215=$I$32)*ISNUMBER($D$16:$D$215))=0,NA(),SUMPRODUCT(($C$16:$C$215=$I$32)*IFERROR($D$16:$D$215,0))/SUMPRODUCT(($C$16:$C$215=$I$32)*ISNUMBER($D$16:$D$215))),IFERROR(LOOKUP(2,1/(($C$16:$C$215=$I$32)*ISNUMBER($D$16:$D$215)),$D$16:$D$215),NA())) -> #N/A | K32: =IFERROR(J32/J31-1,NA()) -> #N/A
B33: =IFERROR(IF(ISNUMBER(A33),TEXT(YEAR(A33)-2000,"00")&CEILING(MONTH(A33)/3,1),NA()),NA()) -> #N/A | C33: =IFERROR(YEAR(A33),0) -> 1899 | E33: =IFERROR(D33/D32-1,NA()) -> #N/A | F33: =IFERROR(D33/D29-1,NA()) -> #N/A | G33: =IF(COUNT(D30:D33)=4,SUM(D30:D33),NA()) -> #N/A | I33: 2017 | J33: =CHOOSE(MATCH($B$10,{"Sum","Average","End of Period"},0),IF(SUMPRODUCT(($C$16:$C$215=$I$33)*ISNUMBER($D$16:$D$215))=0,NA(),SUMPRODUCT(($C$16:$C$215=$I$33)*IFERROR($D$16:$D$215,0))),IF(SUMPRODUCT(($C$16:$C$215=$I$33)*ISNUMBER($D$16:$D$215))=0,NA(),SUMPRODUCT(($C$16:$C$215=$I$33)*IFERROR($D$16:$D$215,0))/SUMPRODUCT(($C$16:$C$215=$I$33)*ISNUMBER($D$16:$D$215))),IFERROR(LOOKUP(2,1/(($C$16:$C$215=$I$33)*ISNUMBER($D$16:$D$215)),$D$16:$D$215),NA())) -> #N/A | K33: =IFERROR(J33/J32-1,NA()) -> #N/A
B34: =IFERROR(IF(ISNUMBER(A34),TEXT(YEAR(A34)-2000,"00")&CEILING(MONTH(A34)/3,1),NA()),NA()) -> #N/A | C34: =IFERROR(YEAR(A34),0) -> 1899 | E34: =IFERROR(D34/D33-1,NA()) -> #N/A | F34: =IFERROR(D34/D30-1,NA()) -> #N/A | G34: =IF(COUNT(D31:D34)=4,SUM(D31:D34),NA()) -> #N/A | I34: 2018 | J34: =CHOOSE(MATCH($B$10,{"Sum","Average","End of Period"},0),IF(SUMPRODUCT(($C$16:$C$215=$I$34)*ISNUMBER($D$16:$D$215))=0,NA(),SUMPRODUCT(($C$16:$C$215=$I$34)*IFERROR($D$16:$D$215,0))),IF(SUMPRODUCT(($C$16:$C$215=$I$34)*ISNUMBER($D$16:$D$215))=0,NA(),SUMPRODUCT(($C$16:$C$215=$I$34)*IFERROR($D$16:$D$215,0))/SUMPRODUCT(($C$16:$C$215=$I$34)*ISNUMBER($D$16:$D$215))),IFERROR(LOOKUP(2,1/(($C$16:$C$215=$I$34)*ISNUMBER($D$16:$D$215)),$D$16:$D$215),NA())) -> #N/A | K34: =IFERROR(J34/J33-1,NA()) -> #N/A
B35: =IFERROR(IF(ISNUMBER(A35),TEXT(YEAR(A35)-2000,"00")&CEILING(MONTH(A35)/3,1),NA()),NA()) -> #N/A | C35: =IFERROR(YEAR(A35),0) -> 1899 | E35: =IFERROR(D35/D34-1,NA()) -> #N/A | F35: =IFERROR(D35/D31-1,NA()) -> #N/A | G35: =IF(COUNT(D32:D35)=4,SUM(D32:D35),NA()) -> #N/A | I35: 2019 | J35: =CHOOSE(MATCH($B$10,{"Sum","Average","End of Period"},0),IF(SUMPRODUCT(($C$16:$C$215=$I$35)*ISNUMBER($D$16:$D$215))=0,NA(),SUMPRODUCT(($C$16:$C$215=$I$35)*IFERROR($D$16:$D$215,0))),IF(SUMPRODUCT(($C$16:$C$215=$I$35)*ISNUMBER($D$16:$D$215))=0,NA(),SUMPRODUCT(($C$16:$C$215=$I$35)*IFERROR($D$16:$D$215,0))/SUMPRODUCT(($C$16:$C$215=$I$35)*ISNUMBER($D$16:$D$215))),IFERROR(LOOKUP(2,1/(($C$16:$C$215=$I$35)*ISNUMBER($D$16:$D$215)),$D$16:$D$215),NA())) -> #N/A | K35: =IFERROR(J35/J34-1,NA()) -> #N/A
B36: =IFERROR(IF(ISNUMBER(A36),TEXT(YEAR(A36)-2000,"00")&CEILING(MONTH(A36)/3,1),NA()),NA()) -> #N/A | C36: =IFERROR(YEAR(A36),0) -> 1899 | E36: =IFERROR(D36/D35-1,NA()) -> #N/A | F36: =IFERROR(D36/D32-1,NA()) -> #N/A | G36: =IF(COUNT(D33:D36)=4,SUM(D33:D36),NA()) -> #N/A | I36: 2020 | J36: =CHOOSE(MATCH($B$10,{"Sum","Average","End of Period"},0),IF(SUMPRODUCT(($C$16:$C$215=$I$36)*ISNUMBER($D$16:$D$215))=0,NA(),SUMPRODUCT(($C$16:$C$215=$I$36)*IFERROR($D$16:$D$215,0))),IF(SUMPRODUCT(($C$16:$C$215=$I$36)*ISNUMBER($D$16:$D$215))=0,NA(),SUMPRODUCT(($C$16:$C$215=$I$36)*IFERROR($D$16:$D$215,0))/SUMPRODUCT(($C$16:$C$215=$I$36)*ISNUMBER($D$16:$D$215))),IFERROR(LOOKUP(2,1/(($C$16:$C$215=$I$36)*ISNUMBER($D$16:$D$215)),$D$16:$D$215),NA())) -> #N/A | K36: =IFERROR(J36/J35-1,NA()) -> #N/A
B37: =IFERROR(IF(ISNUMBER(A37),TEXT(YEAR(A37)-2000,"00")&CEILING(MONTH(A37)/3,1),NA()),NA()) -> #N/A | C37: =IFERROR(YEAR(A37),0) -> 1899 | E37: =IFERROR(D37/D36-1,NA()) -> #N/A | F37: =IFERROR(D37/D33-1,NA()) -> #N/A | G37: =IF(COUNT(D34:D37)=4,SUM(D34:D37),NA()) -> #N/A | I37: 2021 | J37: =CHOOSE(MATCH($B$10,{"Sum","Average","End of Period"},0),IF(SUMPRODUCT(($C$16:$C$215=$I$37)*ISNUMBER($D$16:$D$215))=0,NA(),SUMPRODUCT(($C$16:$C$215=$I$37)*IFERROR($D$16:$D$215,0))),IF(SUMPRODUCT(($C$16:$C$215=$I$37)*ISNUMBER($D$16:$D$215))=0,NA(),SUMPRODUCT(($C$16:$C$215=$I$37)*IFERROR($D$16:$D$215,0))/SUMPRODUCT(($C$16:$C$215=$I$37)*ISNUMBER($D$16:$D$215))),IFERROR(LOOKUP(2,1/(($C$16:$C$215=$I$37)*ISNUMBER($D$16:$D$215)),$D$16:$D$215),NA())) -> #N/A | K37: =IFERROR(J37/J36-1,NA()) -> #N/A
