Workbook

Sheet Read me
B2: Argentina — national public sector, revenue, spending and the fiscal adjustment
B3: SPNF base caja (IMIG), millions of pesos, monthly Jan-2016 to May-2026.
B5: What's here
B6: Data | C6: Every published IMIG line, monthly. Blue = source. Capital spending is derived as a residual (total revenue less current primary spending less the primary balance) and reproduces the sum of the twelve published capital lines exactly.
B7: Monthly | C7: Raw monthly flows. Argentine fiscal data is violently seasonal — December alone carries bonus payments and arrears — so never read a single month.
B8: Rolling 12m | C8: Trailing twelve-month sums, nominal. This is the frame to read.
B9: Rolling 12m %GDP | C9: The same sums over trailing four-quarter nominal GDP. Scale-free, so 2017 and 2026 are directly comparable despite a price level that has risen roughly 120-fold.
B10: Annual | C10: Calendar years, nominal and as a share of GDP, plus 2026 year-to-date.
B11: Adjustment | C11: The heart of it: change in each line as a share of GDP between chosen dates, so you can see exactly which spending lines delivered the consolidation and how much each contributed.
B13: Three things to know
B14: Interest is CASH, not accrued | C14: The base caja interest line records interest actually paid. Capitalising instruments (LECAP, BONCAP, duales) accrue interest that never appears here until it is paid. In some months since 2024 that accrual has exceeded the reported overall balance, so the headline financial surplus overstates the accrual position. This is the single biggest caveat in the pack.
B15: Quarterly GDP is at ANNUAL rates | C15: A year's nominal GDP is the AVERAGE of its four quarters, never the sum. The monthly GDP path here is the quarterly flow (level/4) interpolated log-linearly and renormalised so each quarter's three months sum exactly to that quarter.
B16: Q2-2026 GDP is estimated | C16: National accounts run to Q1-2026. Q2-2026 is extrapolated at the Q1 y/y rate to let the ratios run to the last fiscal month. Any month after Mar-2026 carries that assumption.
B18: Validation | C18: Primary balance less interest equals the overall balance on all 125 months (max error 1, rounding). Derived capital spending is positive throughout. Annual nominal GDP for 2025 computes to 850,239,798 million pesos, matching INDEC.
B19: Source | C19: Secretaria de Hacienda, Ministerio de Economia — Informe Mensual de Ingresos y Gastos del SPNF, distribution 452.3 via datos.gob.ar. GDP: INDEC via SSPM distribution 4.4.

Sheet Data
B2: IMIG monthly source data
B3: Millions of pesos. Blue = published. Green = derived / linked.
B6: Month | C6: Year | D6: iva | E6: gan | F6: ss | G6: debcred | H6: bp | I6: internos | J6: comb | K6: dex | L6: dim | M6: restotrib | N6: fgs | O6: rentas | P6: notrib | Q6: transfctes | R6: restoctes | S6: ingcap | T6: jub | U6: asig | V6: pnc | W6: pami | X6: otrosprog | Y6: energia | Z6: transporte | AA6: otrasfunc | AB6: sal | AC6: otrosfunc | AD6: tpeduc | AE6: tpss | AF6: tpds | AG6: tpsalud | AH6: tpotras | AI6: univ | AJ6: emppub | AK6: otrosctes | AL6: cap | AM6: rprim | AN6: int | AO6: rfin | AP6: GDP (month, mn $) | AQ6: Check prim-int-fin
B7: 2016-01 | C7: 2016 | D7: 20467 | E7: 20340 | F7: 50824 | G7: 7765 | H7: 162 | I7: 1570 | J7: 1115 | K7: 5103 | L7: 3846 | M7: 5140 | N7: 1335 | O7: 270 | P7: 2476 | Q7: 30 | R7: 1175 | S7: 3 | T7: 44935 | U7: 5000 | V7: 7270 | W7: 5437 | X7: 1052 | Y7: 3754 | Z7: 5732 | AA7: 138 | AB7: 19099 | AC7: 4448 | AD7: 813 | AE7: 0 | AF7: 27 | AG7: 339 | AH7: 475 | AI7: 4411 | AJ7: 281 | AK7: 2817 | AL7: 14852 | AM7: 741 | AN7: 2938 | AO7: -2197 | AP7: 563619.95 | AQ7: =AM7-AN7-AO7 -> 0
B8: 2016-02 | C8: 2016 | D8: 20110 | E8: 15531 | F8: 37246 | G8: 7233 | H8: 559 | I8: 1692 | J8: 1960 | K8: 3512 | L8: 3679 | M8: 4319 | N8: 792 | O8: 234 | P8: 2293 | Q8: 32 | R8: 1481 | S8: 5 | T8: 40460 | U8: 5842 | V8: 4493 | W8: 5667 | X8: 2302 | Y8: 6464 | Z8: 4963 | AA8: 73 | AB8: 19032 | AC8: 4943 | AD8: 938 | AE8: 0 | AF8: 66 | AG8: 266 | AH8: 158 | AI8: 4187 | AJ8: 1976 | AK8: 5761 | AL8: 9729 | AM8: -16642 | AN8: 3894 | AO8: -20537 | AP8: 576502.06 | AQ8: =AM8-AN8-AO8 -> 1
B9: 2016-03 | C9: 2016 | D9: 21943 | E9: 12671 | F9: 37907 | G9: 7891 | H9: 160 | I9: 1590 | J9: 1855 | K9: 6750 | L9: 4680 | M9: 4287 | N9: 1726 | O9: 481 | P9: 3200 | Q9: 2513 | R9: 1162 | S9: 17 | T9: 47092 | U9: 12034 | V9: 6211 | W9: 5911 | X9: 1475 | Y9: 8585 | Z9: 6181 | AA9: 57 | AB9: 18491 | AC9: 5162 | AD9: 2173 | AE9: 400 | AF9: 260 | AG9: 643 | AH9: 629 | AI9: 4324 | AJ9: 605 | AK9: 5776 | AL9: 12836 | AM9: -30012 | AN9: 11820 | AO9: -41832 | AP9: 611539.25 | AQ9: =AM9-AN9-AO9 -> 0
B10: 2016-04 | C10: 2016 | D10: 22904 | E10: 11898 | F10: 42731 | G10: 8815 | H10: 381 | I10: 1683 | J10: 1894 | K10: 12214 | L10: 4630 | M10: 4854 | N10: 1914 | O10: 493 | P10: 2682 | Q10: 83 | R10: 968 | S10: 3 | T10: 47795 | U10: 7707 | V10: 6169 | W10: 5271 | X10: 2081 | Y10: 8525 | Z10: 6489 | AA10: 166 | AB10: 16944 | AC10: 5068 | AD10: 1668 | AE10: 0 | AF10: 178 | AG10: 352 | AH10: 533 | AI10: 4628 | AJ10: 151 | AK10: 3365 | AL10: 11950 | AM10: -10893 | AN10: 6181 | AO10: -17075 | AP10: 671946.8 | AQ10: =AM10-AN10-AO10 -> 1
B11: 2016-05 | C11: 2016 | D11: 26738 | E11: 25961 | F11: 42640 | G11: 8919 | H11: 2288 | I11: 2108 | J11: 1905 | K11: 8199 | L11: 4519 | M11: 5856 | N11: 1813 | O11: 1008 | P11: 3002 | Q11: 808 | R11: 1175 | S11: 86 | T11: 48802 | U11: 10586 | V11: 7183 | W11: 5893 | X11: 2296 | Y11: 14618 | Z11: 6641 | AA11: 144 | AB11: 17530 | AC11: 6109 | AD11: 1831 | AE11: 0 | AF11: 57 | AG11: 350 | AH11: 677 | AI11: 4874 | AJ11: 985 | AK11: 4609 | AL11: 15814 | AM11: -11974 | AN11: 12019 | AO11: -23994 | AP11: 714236.31 | AQ11: =AM11-AN11-AO11 -> 1
B12: 2016-06 | C12: 2016 | D12: 22218 | E12: 25274 | F12: 43030 | G12: 9263 | H12: 1306 | I12: 2091 | J12: 2690 | K12: 5004 | L12: 4612 | M12: 7201 | N12: 1242 | O12: 440 | P12: 3707 | Q12: 548 | R12: 1360 | S12: 66 | T12: 70396 | U12: 8682 | V12: 8055 | W12: 6271 | X12: 1405 | Y12: 17158 | Z12: 6993 | AA12: 410 | AB12: 20272 | AC12: 6286 | AD12: 1573 | AE12: 0 | AF12: 462 | AG12: 395 | AH12: 680 | AI12: 4671 | AJ12: 745 | AK12: 4544 | AL12: 15062 | AM12: -44008 | AN12: 28579 | AO12: -72587 | AP12: 717456.02 | AQ12: =AM12-AN12-AO12 -> 0
B13: 2016-07 | C13: 2016 | D13: 22482 | E13: 18614 | F13: 59399 | G13: 10098 | H13: 692 | I13: 2098 | J13: 2716 | K13: 7698 | L13: 4727 | M13: 7425 | N13: 1371 | O13: 1229 | P13: 3534 | Q13: 814 | R13: 1372 | S13: 4 | T13: 49197 | U13: 7996 | V13: 5974 | W13: 6323 | X13: 1975 | Y13: 21771 | Z13: 6543 | AA13: 178 | AB13: 27085 | AC13: 6464 | AD13: 2124 | AE13: 6207 | AF13: 363 | AG13: 623 | AH13: 632 | AI13: 7403 | AJ13: 236 | AK13: 5029 | AL13: 12516 | AM13: -24366 | AN13: 3218 | AO13: -27584 | AP13: 704519.81 | AQ13: =AM13-AN13-AO13 -> 0
B14: 2016-08 | C14: 2016 | D14: 24007 | E14: 17507 | F14: 46452 | G14: 9019 | H14: 657 | I14: 2422 | J14: 3041 | K14: 4465 | L14: 4998 | M14: 7160 | N14: 1922 | O14: 1665 | P14: 3785 | Q14: 585 | R14: 1408 | S14: 16 | T14: 49948 | U14: 8868 | V14: 6165 | W14: 9908 | X14: 2422 | Y14: 14912 | Z14: 7910 | AA14: 133 | AB14: 23009 | AC14: 6144 | AD14: 2035 | AE14: 1479 | AF14: 213 | AG14: 805 | AH14: 777 | AI14: 5203 | AJ14: 814 | AK14: 4770 | AL14: 19010 | AM14: -35416 | AN14: 3360 | AO14: -38775 | AP14: 707695.72 | AQ14: =AM14-AN14-AO14 -> -1
B15: 2016-09 | C15: 2016 | D15: 25256 | E15: 17402 | F15: 46070 | G15: 10122 | H15: 250 | I15: 2463 | J15: 2309 | K15: 5249 | L15: 5294 | M15: 6565 | N15: 1940 | O15: 1387 | P15: 4019 | Q15: 1053 | R15: 2372 | S15: 15 | T15: 56049 | U15: 9669 | V15: 6807 | W15: 6615 | X15: 2593 | Y15: 20204 | Z15: 6592 | AA15: 100 | AB15: 24103 | AC15: 6431 | AD15: 2103 | AE15: 1949 | AF15: 598 | AG15: 423 | AH15: 191 | AI15: 4570 | AJ15: 514 | AK15: 5383 | AL15: 13889 | AM15: -37017 | AN15: 11979 | AO15: -48996 | AP15: 719691.67 | AQ15: =AM15-AN15-AO15 -> 0
B16: 2016-10 | C16: 2016 | D16: 22917 | E16: 17777 | F16: 46476 | G16: 9186 | H16: 609 | I16: 2498 | J16: 2443 | K16: 4507 | L16: 4790 | M16: 9138 | N16: 1159 | O16: 641 | P16: 4076 | Q16: 698 | R16: 1107 | S16: 51 | T16: 57252 | U16: 9716 | V16: 6742 | W16: 8106 | X16: 2632 | Y16: 25779 | Z16: 6842 | AA16: 106 | AB16: 23635 | AC16: 11007 | AD16: 1688 | AE16: 1620 | AF16: 398 | AG16: 465 | AH16: 1334 | AI16: 5250 | AJ16: 104 | AK16: 4127 | AL16: 23138 | AM16: -61868 | AN16: 15632 | AO16: -77500 | AP16: 736175.31 | AQ16: =AM16-AN16-AO16 -> 0
B17: 2016-11 | C17: 2016 | D17: 23911 | E17: 19152 | F17: 51942 | G17: 10188 | H17: 176 | I17: 2631 | J17: 2474 | K17: 4313 | L17: 4411 | M17: 18733 | N17: 851 | O17: 489 | P17: 4184 | Q17: 1168 | R17: 997 | S17: 165 | T17: 57463 | U17: 9766 | V17: 9389 | W17: 6946 | X17: 2236 | Y17: 10606 | Z17: 6498 | AA17: 95 | AB17: 22753 | AC17: 8268 | AD17: 816 | AE17: 3081 | AF17: 367 | AG17: 796 | AH17: 1113 | AI17: 5056 | AJ17: 396 | AK17: 2461 | AL17: 10979 | AM17: -13300 | AN17: 6558 | AO17: -19858 | AP17: 748654.01 | AQ17: =AM17-AN17-AO17 -> 0
B18: 2016-12 | C18: 2016 | D18: 24889 | E18: 21295 | F18: 53371 | G18: 10840 | H18: 569 | I18: 2704 | J18: 3594 | K18: 5104 | L18: 5210 | M18: 96513 | N18: 820 | O18: 2339 | P18: 4323 | Q18: 714 | R18: 1654 | S18: 13 | T18: 85081 | U18: 12294 | V18: 5791 | W18: 9061 | X18: 7833 | Y18: 56827 | Z18: 8863 | AA18: 121 | AB18: 34877 | AC18: 9010 | AD18: 2763 | AE18: 4435 | AF18: 723 | AG18: 603 | AH18: 16926 | AI18: 7925 | AJ18: 1332 | AK18: 5988 | AL18: 22268 | AM18: -58769 | AN18: 25081 | AO18: -83850 | AP18: 756122.65 | AQ18: =AM18-AN18-AO18 -> 0
... B131: 2026-05 | C131: 2026 | D131: 2433370 | E131: 2970423 | F131: 4736191 | G131: 1419595 | H131: 27837 | I131: 135477 | J131: 0 | K131: 545337 | L131: 394152 | M131: 872399 | N131: 157659 | O131: 277880 | P131: 380800 | Q131: 9515 | R131: 157201 | S131: 13820 | T131: 5253082 | U131: 900085 | V131: 424468 | W131: 850633 | X131: 953150 | Y131: 523417 | Z131: 258687 | AA131: 2073 | AB131: 1618197 | AC131: 471191 | AD131: 86624 | AE131: 47167 | AF131: 0 | AG131: 16971 | AH131: 9537 | AI131: 780000 | AJ131: 0 | AK131: 228489 | AL131: 183518 | AM131: 1924367 | AN131: 1445754 | AO131: 478613 | AP131: 94319731 | AQ131: =AM131-AN131-AO131 -> 0
B133: Capital spending is the residual of the published identity and matches the sum of the twelve capital lines in the source file.

Sheet Monthly
B2: Monthly flows, nominal
B3: Millions of pesos. Seasonal — do not read a single month in isolation.
B6: Month | C6: TOTAL REVENUE | D6: Tax revenue | E6: VAT (net) | F6: Income tax | G6: Export duties | H6: Import duties | I6: Debits & credits | J6: Other taxes | K6: Social security contrib. | L6: Non-tax and capital | M6: PRIMARY EXPENDITURE | N6: Social benefits | O6: Contributory pensions | P6: Family allowances | Q6: Non-contrib. pensions | R6: PAMI | S6: Other social programmes | T6: Economic subsidies | U6: Energy | V6: Transport | W6: Wages | X6: Other operating | Y6: Transfers to provinces | Z6: Universities | AA6: Public enterprises | AB6: Other current | AC6: Capital expenditure | AD6: PRIMARY BALANCE | AE6: Interest (net) | AF6: OVERALL BALANCE
B7: =Data!B7 -> 2016-01 | C7: =Data!D7+Data!E7+Data!F7+Data!G7+Data!H7+Data!I7+Data!J7+Data!K7+Data!L7+Data!M7+Data!N7+Data!O7+Data!P7+Data!Q7+Data!R7+Data!S7 -> 121621 | D7: =Data!D7+Data!E7+Data!G7+Data!H7+Data!I7+Data!J7+Data!K7+Data!L7+Data!M7 -> 65508 | E7: =Data!D7 -> 20467 | F7: =Data!E7 -> 20340 | G7: =Data!K7 -> 5103 | H7: =Data!L7 -> 3846 | I7: =Data!G7 -> 7765 | J7: =Data!H7+Data!I7+Data!J7+Data!M7 -> 7987 | K7: =Data!F7 -> 50824 | L7: =Data!N7+Data!O7+Data!P7+Data!Q7+Data!R7+Data!S7 -> 5289 | M7: =Data!T7+Data!U7+Data!V7+Data!W7+Data!X7+Data!Y7+Data!Z7+Data!AA7+Data!AB7+Data!AC7+Data!AD7+Data!AE7+Data!AF7+Data!AG7+Data!AH7+Data!AI7+Data!AJ7+Data!AK7+Data!AL7 -> 120880 | N7: =Data!T7+Data!U7+Data!V7+Data!W7 -> 62642 | O7: =Data!T7 -> 44935 | P7: =Data!U7 -> 5000 | Q7: =Data!V7 -> 7270 | R7: =Data!W7 -> 5437 | S7: =Data!X7 -> 1052 | T7: =Data!Y7+Data!Z7+Data!AA7 -> 9624 | U7: =Data!Y7 -> 3754 | V7: =Data!Z7 -> 5732 | W7: =Data!AB7 -> 19099 | X7: =Data!AC7 -> 4448 | Y7: =Data!AD7+Data!AE7+Data!AF7+Data!AG7+Data!AH7 -> 1654 | Z7: =Data!AI7 -> 4411 | AA7: =Data!AJ7 -> 281 | AB7: =Data!AK7 -> 2817 | AC7: =Data!AL7 -> 14852 | AD7: =Data!AM7 -> 741 | AE7: =Data!AN7 -> 2938 | AF7: =Data!AO7 -> -2197
B8: =Data!B8 -> 2016-02 | C8: =Data!D8+Data!E8+Data!F8+Data!G8+Data!H8+Data!I8+Data!J8+Data!K8+Data!L8+Data!M8+Data!N8+Data!O8+Data!P8+Data!Q8+Data!R8+Data!S8 -> 100678 | D8: =Data!D8+Data!E8+Data!G8+Data!H8+Data!I8+Data!J8+Data!K8+Data!L8+Data!M8 -> 58595 | E8: =Data!D8 -> 20110 | F8: =Data!E8 -> 15531 | G8: =Data!K8 -> 3512 | H8: =Data!L8 -> 3679 | I8: =Data!G8 -> 7233 | J8: =Data!H8+Data!I8+Data!J8+Data!M8 -> 8530 | K8: =Data!F8 -> 37246 | L8: =Data!N8+Data!O8+Data!P8+Data!Q8+Data!R8+Data!S8 -> 4837 | M8: =Data!T8+Data!U8+Data!V8+Data!W8+Data!X8+Data!Y8+Data!Z8+Data!AA8+Data!AB8+Data!AC8+Data!AD8+Data!AE8+Data!AF8+Data!AG8+Data!AH8+Data!AI8+Data!AJ8+Data!AK8+Data!AL8 -> 117320 | N8: =Data!T8+Data!U8+Data!V8+Data!W8 -> 56462 | O8: =Data!T8 -> 40460 | P8: =Data!U8 -> 5842 | Q8: =Data!V8 -> 4493 | R8: =Data!W8 -> 5667 | S8: =Data!X8 -> 2302 | T8: =Data!Y8+Data!Z8+Data!AA8 -> 11500 | U8: =Data!Y8 -> 6464 | V8: =Data!Z8 -> 4963 | W8: =Data!AB8 -> 19032 | X8: =Data!AC8 -> 4943 | Y8: =Data!AD8+Data!AE8+Data!AF8+Data!AG8+Data!AH8 -> 1428 | Z8: =Data!AI8 -> 4187 | AA8: =Data!AJ8 -> 1976 | AB8: =Data!AK8 -> 5761 | AC8: =Data!AL8 -> 9729 | AD8: =Data!AM8 -> -16642 | AE8: =Data!AN8 -> 3894 | AF8: =Data!AO8 -> -20537
B9: =Data!B9 -> 2016-03 | C9: =Data!D9+Data!E9+Data!F9+Data!G9+Data!H9+Data!I9+Data!J9+Data!K9+Data!L9+Data!M9+Data!N9+Data!O9+Data!P9+Data!Q9+Data!R9+Data!S9 -> 108833 | D9: =Data!D9+Data!E9+Data!G9+Data!H9+Data!I9+Data!J9+Data!K9+Data!L9+Data!M9 -> 61827 | E9: =Data!D9 -> 21943 | F9: =Data!E9 -> 12671 | G9: =Data!K9 -> 6750 | H9: =Data!L9 -> 4680 | I9: =Data!G9 -> 7891 | J9: =Data!H9+Data!I9+Data!J9+Data!M9 -> 7892 | K9: =Data!F9 -> 37907 | L9: =Data!N9+Data!O9+Data!P9+Data!Q9+Data!R9+Data!S9 -> 9099 | M9: =Data!T9+Data!U9+Data!V9+Data!W9+Data!X9+Data!Y9+Data!Z9+Data!AA9+Data!AB9+Data!AC9+Data!AD9+Data!AE9+Data!AF9+Data!AG9+Data!AH9+Data!AI9+Data!AJ9+Data!AK9+Data!AL9 -> 138845 | N9: =Data!T9+Data!U9+Data!V9+Data!W9 -> 71248 | O9: =Data!T9 -> 47092 | P9: =Data!U9 -> 12034 | Q9: =Data!V9 -> 6211 | R9: =Data!W9 -> 5911 | S9: =Data!X9 -> 1475 | T9: =Data!Y9+Data!Z9+Data!AA9 -> 14823 | U9: =Data!Y9 -> 8585 | V9: =Data!Z9 -> 6181 | W9: =Data!AB9 -> 18491 | X9: =Data!AC9 -> 5162 | Y9: =Data!AD9+Data!AE9+Data!AF9+Data!AG9+Data!AH9 -> 4105 | Z9: =Data!AI9 -> 4324 | AA9: =Data!AJ9 -> 605 | AB9: =Data!AK9 -> 5776 | AC9: =Data!AL9 -> 12836 | AD9: =Data!AM9 -> -30012 | AE9: =Data!AN9 -> 11820 | AF9: =Data!AO9 -> -41832
B10: =Data!B10 -> 2016-04 | C10: =Data!D10+Data!E10+Data!F10+Data!G10+Data!H10+Data!I10+Data!J10+Data!K10+Data!L10+Data!M10+Data!N10+Data!O10+Data!P10+Data!Q10+Data!R10+Data!S10 -> 118147 | D10: =Data!D10+Data!E10+Data!G10+Data!H10+Data!I10+Data!J10+Data!K10+Data!L10+Data!M10 -> 69273 | E10: =Data!D10 -> 22904 | F10: =Data!E10 -> 11898 | G10: =Data!K10 -> 12214 | H10: =Data!L10 -> 4630 | I10: =Data!G10 -> 8815 | J10: =Data!H10+Data!I10+Data!J10+Data!M10 -> 8812 | K10: =Data!F10 -> 42731 | L10: =Data!N10+Data!O10+Data!P10+Data!Q10+Data!R10+Data!S10 -> 6143 | M10: =Data!T10+Data!U10+Data!V10+Data!W10+Data!X10+Data!Y10+Data!Z10+Data!AA10+Data!AB10+Data!AC10+Data!AD10+Data!AE10+Data!AF10+Data!AG10+Data!AH10+Data!AI10+Data!AJ10+Data!AK10+Data!AL10 -> 129040 | N10: =Data!T10+Data!U10+Data!V10+Data!W10 -> 66942 | O10: =Data!T10 -> 47795 | P10: =Data!U10 -> 7707 | Q10: =Data!V10 -> 6169 | R10: =Data!W10 -> 5271 | S10: =Data!X10 -> 2081 | T10: =Data!Y10+Data!Z10+Data!AA10 -> 15180 | U10: =Data!Y10 -> 8525 | V10: =Data!Z10 -> 6489 | W10: =Data!AB10 -> 16944 | X10: =Data!AC10 -> 5068 | Y10: =Data!AD10+Data!AE10+Data!AF10+Data!AG10+Data!AH10 -> 2731 | Z10: =Data!AI10 -> 4628 | AA10: =Data!AJ10 -> 151 | AB10: =Data!AK10 -> 3365 | AC10: =Data!AL10 -> 11950 | AD10: =Data!AM10 -> -10893 | AE10: =Data!AN10 -> 6181 | AF10: =Data!AO10 -> -17075
B11: =Data!B11 -> 2016-05 | C11: =Data!D11+Data!E11+Data!F11+Data!G11+Data!H11+Data!I11+Data!J11+Data!K11+Data!L11+Data!M11+Data!N11+Data!O11+Data!P11+Data!Q11+Data!R11+Data!S11 -> 137025 | D11: =Data!D11+Data!E11+Data!G11+Data!H11+Data!I11+Data!J11+Data!K11+Data!L11+Data!M11 -> 86493 | E11: =Data!D11 -> 26738 | F11: =Data!E11 -> 25961 | G11: =Data!K11 -> 8199 | H11: =Data!L11 -> 4519 | I11: =Data!G11 -> 8919 | J11: =Data!H11+Data!I11+Data!J11+Data!M11 -> 12157 | K11: =Data!F11 -> 42640 | L11: =Data!N11+Data!O11+Data!P11+Data!Q11+Data!R11+Data!S11 -> 7892 | M11: =Data!T11+Data!U11+Data!V11+Data!W11+Data!X11+Data!Y11+Data!Z11+Data!AA11+Data!AB11+Data!AC11+Data!AD11+Data!AE11+Data!AF11+Data!AG11+Data!AH11+Data!AI11+Data!AJ11+Data!AK11+Data!AL11 -> 148999 | N11: =Data!T11+Data!U11+Data!V11+Data!W11 -> 72464 | O11: =Data!T11 -> 48802 | P11: =Data!U11 -> 10586 | Q11: =Data!V11 -> 7183 | R11: =Data!W11 -> 5893 | S11: =Data!X11 -> 2296 | T11: =Data!Y11+Data!Z11+Data!AA11 -> 21403 | U11: =Data!Y11 -> 14618 | V11: =Data!Z11 -> 6641 | W11: =Data!AB11 -> 17530 | X11: =Data!AC11 -> 6109 | Y11: =Data!AD11+Data!AE11+Data!AF11+Data!AG11+Data!AH11 -> 2915 | Z11: =Data!AI11 -> 4874 | AA11: =Data!AJ11 -> 985 | AB11: =Data!AK11 -> 4609 | AC11: =Data!AL11 -> 15814 | AD11: =Data!AM11 -> -11974 | AE11: =Data!AN11 -> 12019 | AF11: =Data!AO11 -> -23994
B12: =Data!B12 -> 2016-06 | C12: =Data!D12+Data!E12+Data!F12+Data!G12+Data!H12+Data!I12+Data!J12+Data!K12+Data!L12+Data!M12+Data!N12+Data!O12+Data!P12+Data!Q12+Data!R12+Data!S12 -> 130052 | D12: =Data!D12+Data!E12+Data!G12+Data!H12+Data!I12+Data!J12+Data!K12+Data!L12+Data!M12 -> 79659 | E12: =Data!D12 -> 22218 | F12: =Data!E12 -> 25274 | G12: =Data!K12 -> 5004 | H12: =Data!L12 -> 4612 | I12: =Data!G12 -> 9263 | J12: =Data!H12+Data!I12+Data!J12+Data!M12 -> 13288 | K12: =Data!F12 -> 43030 | L12: =Data!N12+Data!O12+Data!P12+Data!Q12+Data!R12+Data!S12 -> 7363 | M12: =Data!T12+Data!U12+Data!V12+Data!W12+Data!X12+Data!Y12+Data!Z12+Data!AA12+Data!AB12+Data!AC12+Data!AD12+Data!AE12+Data!AF12+Data!AG12+Data!AH12+Data!AI12+Data!AJ12+Data!AK12+Data!AL12 -> 174060 | N12: =Data!T12+Data!U12+Data!V12+Data!W12 -> 93404 | O12: =Data!T12 -> 70396 | P12: =Data!U12 -> 8682 | Q12: =Data!V12 -> 8055 | R12: =Data!W12 -> 6271 | S12: =Data!X12 -> 1405 | T12: =Data!Y12+Data!Z12+Data!AA12 -> 24561 | U12: =Data!Y12 -> 17158 | V12: =Data!Z12 -> 6993 | W12: =Data!AB12 -> 20272 | X12: =Data!AC12 -> 6286 | Y12: =Data!AD12+Data!AE12+Data!AF12+Data!AG12+Data!AH12 -> 3110 | Z12: =Data!AI12 -> 4671 | AA12: =Data!AJ12 -> 745 | AB12: =Data!AK12 -> 4544 | AC12: =Data!AL12 -> 15062 | AD12: =Data!AM12 -> -44008 | AE12: =Data!AN12 -> 28579 | AF12: =Data!AO12 -> -72587
B13: =Data!B13 -> 2016-07 | C13: =Data!D13+Data!E13+Data!F13+Data!G13+Data!H13+Data!I13+Data!J13+Data!K13+Data!L13+Data!M13+Data!N13+Data!O13+Data!P13+Data!Q13+Data!R13+Data!S13 -> 144273 | D13: =Data!D13+Data!E13+Data!G13+Data!H13+Data!I13+Data!J13+Data!K13+Data!L13+Data!M13 -> 76550 | E13: =Data!D13 -> 22482 | F13: =Data!E13 -> 18614 | G13: =Data!K13 -> 7698 | H13: =Data!L13 -> 4727 | I13: =Data!G13 -> 10098 | J13: =Data!H13+Data!I13+Data!J13+Data!M13 -> 12931 | K13: =Data!F13 -> 59399 | L13: =Data!N13+Data!O13+Data!P13+Data!Q13+Data!R13+Data!S13 -> 8324 | M13: =Data!T13+Data!U13+Data!V13+Data!W13+Data!X13+Data!Y13+Data!Z13+Data!AA13+Data!AB13+Data!AC13+Data!AD13+Data!AE13+Data!AF13+Data!AG13+Data!AH13+Data!AI13+Data!AJ13+Data!AK13+Data!AL13 -> 168639 | N13: =Data!T13+Data!U13+Data!V13+Data!W13 -> 69490 | O13: =Data!T13 -> 49197 | P13: =Data!U13 -> 7996 | Q13: =Data!V13 -> 5974 | R13: =Data!W13 -> 6323 | S13: =Data!X13 -> 1975 | T13: =Data!Y13+Data!Z13+Data!AA13 -> 28492 | U13: =Data!Y13 -> 21771 | V13: =Data!Z13 -> 6543 | W13: =Data!AB13 -> 27085 | X13: =Data!AC13 -> 6464 | Y13: =Data!AD13+Data!AE13+Data!AF13+Data!AG13+Data!AH13 -> 9949 | Z13: =Data!AI13 -> 7403 | AA13: =Data!AJ13 -> 236 | AB13: =Data!AK13 -> 5029 | AC13: =Data!AL13 -> 12516 | AD13: =Data!AM13 -> -24366 | AE13: =Data!AN13 -> 3218 | AF13: =Data!AO13 -> -27584
B14: =Data!B14 -> 2016-08 | C14: =Data!D14+Data!E14+Data!F14+Data!G14+Data!H14+Data!I14+Data!J14+Data!K14+Data!L14+Data!M14+Data!N14+Data!O14+Data!P14+Data!Q14+Data!R14+Data!S14 -> 129109 | D14: =Data!D14+Data!E14+Data!G14+Data!H14+Data!I14+Data!J14+Data!K14+Data!L14+Data!M14 -> 73276 | E14: =Data!D14 -> 24007 | F14: =Data!E14 -> 17507 | G14: =Data!K14 -> 4465 | H14: =Data!L14 -> 4998 | I14: =Data!G14 -> 9019 | J14: =Data!H14+Data!I14+Data!J14+Data!M14 -> 13280 | K14: =Data!F14 -> 46452 | L14: =Data!N14+Data!O14+Data!P14+Data!Q14+Data!R14+Data!S14 -> 9381 | M14: =Data!T14+Data!U14+Data!V14+Data!W14+Data!X14+Data!Y14+Data!Z14+Data!AA14+Data!AB14+Data!AC14+Data!AD14+Data!AE14+Data!AF14+Data!AG14+Data!AH14+Data!AI14+Data!AJ14+Data!AK14+Data!AL14 -> 164525 | N14: =Data!T14+Data!U14+Data!V14+Data!W14 -> 74889 | O14: =Data!T14 -> 49948 | P14: =Data!U14 -> 8868 | Q14: =Data!V14 -> 6165 | R14: =Data!W14 -> 9908 | S14: =Data!X14 -> 2422 | T14: =Data!Y14+Data!Z14+Data!AA14 -> 22955 | U14: =Data!Y14 -> 14912 | V14: =Data!Z14 -> 7910 | W14: =Data!AB14 -> 23009 | X14: =Data!AC14 -> 6144 | Y14: =Data!AD14+Data!AE14+Data!AF14+Data!AG14+Data!AH14 -> 5309 | Z14: =Data!AI14 -> 5203 | AA14: =Data!AJ14 -> 814 | AB14: =Data!AK14 -> 4770 | AC14: =Data!AL14 -> 19010 | AD14: =Data!AM14 -> -35416 | AE14: =Data!AN14 -> 3360 | AF14: =Data!AO14 -> -38775
B15: =Data!B15 -> 2016-09 | C15: =Data!D15+Data!E15+Data!F15+Data!G15+Data!H15+Data!I15+Data!J15+Data!K15+Data!L15+Data!M15+Data!N15+Data!O15+Data!P15+Data!Q15+Data!R15+Data!S15 -> 131766 | D15: =Data!D15+Data!E15+Data!G15+Data!H15+Data!I15+Data!J15+Data!K15+Data!L15+Data!M15 -> 74910 | E15: =Data!D15 -> 25256 | F15: =Data!E15 -> 17402 | G15: =Data!K15 -> 5249 | H15: =Data!L15 -> 5294 | I15: =Data!G15 -> 10122 | J15: =Data!H15+Data!I15+Data!J15+Data!M15 -> 11587 | K15: =Data!F15 -> 46070 | L15: =Data!N15+Data!O15+Data!P15+Data!Q15+Data!R15+Data!S15 -> 10786 | M15: =Data!T15+Data!U15+Data!V15+Data!W15+Data!X15+Data!Y15+Data!Z15+Data!AA15+Data!AB15+Data!AC15+Data!AD15+Data!AE15+Data!AF15+Data!AG15+Data!AH15+Data!AI15+Data!AJ15+Data!AK15+Data!AL15 -> 168783 | N15: =Data!T15+Data!U15+Data!V15+Data!W15 -> 79140 | O15: =Data!T15 -> 56049 | P15: =Data!U15 -> 9669 | Q15: =Data!V15 -> 6807 | R15: =Data!W15 -> 6615 | S15: =Data!X15 -> 2593 | T15: =Data!Y15+Data!Z15+Data!AA15 -> 26896 | U15: =Data!Y15 -> 20204 | V15: =Data!Z15 -> 6592 | W15: =Data!AB15 -> 24103 | X15: =Data!AC15 -> 6431 | Y15: =Data!AD15+Data!AE15+Data!AF15+Data!AG15+Data!AH15 -> 5264 | Z15: =Data!AI15 -> 4570 | AA15: =Data!AJ15 -> 514 | AB15: =Data!AK15 -> 5383 | AC15: =Data!AL15 -> 13889 | AD15: =Data!AM15 -> -37017 | AE15: =Data!AN15 -> 11979 | AF15: =Data!AO15 -> -48996
B16: =Data!B16 -> 2016-10 | C16: =Data!D16+Data!E16+Data!F16+Data!G16+Data!H16+Data!I16+Data!J16+Data!K16+Data!L16+Data!M16+Data!N16+Data!O16+Data!P16+Data!Q16+Data!R16+Data!S16 -> 128073 | D16: =Data!D16+Data!E16+Data!G16+Data!H16+Data!I16+Data!J16+Data!K16+Data!L16+Data!M16 -> 73865 | E16: =Data!D16 -> 22917 | F16: =Data!E16 -> 17777 | G16: =Data!K16 -> 4507 | H16: =Data!L16 -> 4790 | I16: =Data!G16 -> 9186 | J16: =Data!H16+Data!I16+Data!J16+Data!M16 -> 14688 | K16: =Data!F16 -> 46476 | L16: =Data!N16+Data!O16+Data!P16+Data!Q16+Data!R16+Data!S16 -> 7732 | M16: =Data!T16+Data!U16+Data!V16+Data!W16+Data!X16+Data!Y16+Data!Z16+Data!AA16+Data!AB16+Data!AC16+Data!AD16+Data!AE16+Data!AF16+Data!AG16+Data!AH16+Data!AI16+Data!AJ16+Data!AK16+Data!AL16 -> 189941 | N16: =Data!T16+Data!U16+Data!V16+Data!W16 -> 81816 | O16: =Data!T16 -> 57252 | P16: =Data!U16 -> 9716 | Q16: =Data!V16 -> 6742 | R16: =Data!W16 -> 8106 | S16: =Data!X16 -> 2632 | T16: =Data!Y16+Data!Z16+Data!AA16 -> 32727 | U16: =Data!Y16 -> 25779 | V16: =Data!Z16 -> 6842 | W16: =Data!AB16 -> 23635 | X16: =Data!AC16 -> 11007 | Y16: =Data!AD16+Data!AE16+Data!AF16+Data!AG16+Data!AH16 -> 5505 | Z16: =Data!AI16 -> 5250 | AA16: =Data!AJ16 -> 104 | AB16: =Data!AK16 -> 4127 | AC16: =Data!AL16 -> 23138 | AD16: =Data!AM16 -> -61868 | AE16: =Data!AN16 -> 15632 | AF16: =Data!AO16 -> -77500
B17: =Data!B17 -> 2016-11 | C17: =Data!D17+Data!E17+Data!F17+Data!G17+Data!H17+Data!I17+Data!J17+Data!K17+Data!L17+Data!M17+Data!N17+Data!O17+Data!P17+Data!Q17+Data!R17+Data!S17 -> 145785 | D17: =Data!D17+Data!E17+Data!G17+Data!H17+Data!I17+Data!J17+Data!K17+Data!L17+Data!M17 -> 85989 | E17: =Data!D17 -> 23911 | F17: =Data!E17 -> 19152 | G17: =Data!K17 -> 4313 | H17: =Data!L17 -> 4411 | I17: =Data!G17 -> 10188 | J17: =Data!H17+Data!I17+Data!J17+Data!M17 -> 24014 | K17: =Data!F17 -> 51942 | L17: =Data!N17+Data!O17+Data!P17+Data!Q17+Data!R17+Data!S17 -> 7854 | M17: =Data!T17+Data!U17+Data!V17+Data!W17+Data!X17+Data!Y17+Data!Z17+Data!AA17+Data!AB17+Data!AC17+Data!AD17+Data!AE17+Data!AF17+Data!AG17+Data!AH17+Data!AI17+Data!AJ17+Data!AK17+Data!AL17 -> 159085 | N17: =Data!T17+Data!U17+Data!V17+Data!W17 -> 83564 | O17: =Data!T17 -> 57463 | P17: =Data!U17 -> 9766 | Q17: =Data!V17 -> 9389 | R17: =Data!W17 -> 6946 | S17: =Data!X17 -> 2236 | T17: =Data!Y17+Data!Z17+Data!AA17 -> 17199 | U17: =Data!Y17 -> 10606 | V17: =Data!Z17 -> 6498 | W17: =Data!AB17 -> 22753 | X17: =Data!AC17 -> 8268 | Y17: =Data!AD17+Data!AE17+Data!AF17+Data!AG17+Data!AH17 -> 6173 | Z17: =Data!AI17 -> 5056 | AA17: =Data!AJ17 -> 396 | AB17: =Data!AK17 -> 2461 | AC17: =Data!AL17 -> 10979 | AD17: =Data!AM17 -> -13300 | AE17: =Data!AN17 -> 6558 | AF17: =Data!AO17 -> -19858
B18: =Data!B18 -> 2016-12 | C18: =Data!D18+Data!E18+Data!F18+Data!G18+Data!H18+Data!I18+Data!J18+Data!K18+Data!L18+Data!M18+Data!N18+Data!O18+Data!P18+Data!Q18+Data!R18+Data!S18 -> 233952 | D18: =Data!D18+Data!E18+Data!G18+Data!H18+Data!I18+Data!J18+Data!K18+Data!L18+Data!M18 -> 170718 | E18: =Data!D18 -> 24889 | F18: =Data!E18 -> 21295 | G18: =Data!K18 -> 5104 | H18: =Data!L18 -> 5210 | I18: =Data!G18 -> 10840 | J18: =Data!H18+Data!I18+Data!J18+Data!M18 -> 103380 | K18: =Data!F18 -> 53371 | L18: =Data!N18+Data!O18+Data!P18+Data!Q18+Data!R18+Data!S18 -> 9863 | M18: =Data!T18+Data!U18+Data!V18+Data!W18+Data!X18+Data!Y18+Data!Z18+Data!AA18+Data!AB18+Data!AC18+Data!AD18+Data!AE18+Data!AF18+Data!AG18+Data!AH18+Data!AI18+Data!AJ18+Data!AK18+Data!AL18 -> 292721 | N18: =Data!T18+Data!U18+Data!V18+Data!W18 -> 112227 | O18: =Data!T18 -> 85081 | P18: =Data!U18 -> 12294 | Q18: =Data!V18 -> 5791 | R18: =Data!W18 -> 9061 | S18: =Data!X18 -> 7833 | T18: =Data!Y18+Data!Z18+Data!AA18 -> 65811 | U18: =Data!Y18 -> 56827 | V18: =Data!Z18 -> 8863 | W18: =Data!AB18 -> 34877 | X18: =Data!AC18 -> 9010 | Y18: =Data!AD18+Data!AE18+Data!AF18+Data!AG18+Data!AH18 -> 25450 | Z18: =Data!AI18 -> 7925 | AA18: =Data!AJ18 -> 1332 | AB18: =Data!AK18 -> 5988 | AC18: =Data!AL18 -> 22268 | AD18: =Data!AM18 -> -58769 | AE18: =Data!AN18 -> 25081 | AF18: =Data!AO18 -> -83850
... B131: =Data!B131 -> 2026-05 | C131: =Data!D131+Data!E131+Data!F131+Data!G131+Data!H131+Data!I131+Data!J131+Data!K131+Data!L131+Data!M131+Data!N131+Data!O131+Data!P131+Data!Q131+Data!R131+Data!S131 -> 14531656 | D131: =Data!D131+Data!E131+Data!G131+Data!H131+Data!I131+Data!J131+Data!K131+Data!L131+Data!M131 -> 8798590 | E131: =Data!D131 -> 2433370 | F131: =Data!E131 -> 2970423 | G131: =Data!K131 -> 545337 | H131: =Data!L131 -> 394152 | I131: =Data!G131 -> 1419595 | J131: =Data!H131+Data!I131+Data!J131+Data!M131 -> 1035713 | K131: =Data!F131 -> 4736191 | L131: =Data!N131+Data!O131+Data!P131+Data!Q131+Data!R131+Data!S131 -> 996875 | M131: =Data!T131+Data!U131+Data!V131+Data!W131+Data!X131+Data!Y131+Data!Z131+Data!AA131+Data!AB131+Data!AC131+Data!AD131+Data!AE131+Data!AF131+Data!AG131+Data!AH131+Data!AI131+Data!AJ131+Data!AK131+Data!AL131 -> 12607289 | N131: =Data!T131+Data!U131+Data!V131+Data!W131 -> 7428268 | O131: =Data!T131 -> 5253082 | P131: =Data!U131 -> 900085 | Q131: =Data!V131 -> 424468 | R131: =Data!W131 -> 850633 | S131: =Data!X131 -> 953150 | T131: =Data!Y131+Data!Z131+Data!AA131 -> 784177 | U131: =Data!Y131 -> 523417 | V131: =Data!Z131 -> 258687 | W131: =Data!AB131 -> 1618197 | X131: =Data!AC131 -> 471191 | Y131: =Data!AD131+Data!AE131+Data!AF131+Data!AG131+Data!AH131 -> 160299 | Z131: =Data!AI131 -> 780000 | AA131: =Data!AJ131 -> 0 | AB131: =Data!AK131 -> 228489 | AC131: =Data!AL131 -> 183518 | AD131: =Data!AM131 -> 1924367 | AE131: =Data!AN131 -> 1445754 | AF131: =Data!AO131 -> 478613

Sheet Rolling 12m
B2: Trailing twelve-month sums, nominal
B3: Millions of pesos. The frame to read.
B6: Month | C6: TOTAL REVENUE | D6: Tax revenue | E6: VAT (net) | F6: Income tax | G6: Export duties | H6: Import duties | I6: Debits & credits | J6: Other taxes | K6: Social security contrib. | L6: Non-tax and capital | M6: PRIMARY EXPENDITURE | N6: Social benefits | O6: Contributory pensions | P6: Family allowances | Q6: Non-contrib. pensions | R6: PAMI | S6: Other social programmes | T6: Economic subsidies | U6: Energy | V6: Transport | W6: Wages | X6: Other operating | Y6: Transfers to provinces | Z6: Universities | AA6: Public enterprises | AB6: Other current | AC6: Capital expenditure | AD6: PRIMARY BALANCE | AE6: Interest (net) | AF6: OVERALL BALANCE
B7: =Data!B7 -> 2016-01
B8: =Data!B8 -> 2016-02
B9: =Data!B9 -> 2016-03
B10: =Data!B10 -> 2016-04
B11: =Data!B11 -> 2016-05
B12: =Data!B12 -> 2016-06
B13: =Data!B13 -> 2016-07
B14: =Data!B14 -> 2016-08
B15: =Data!B15 -> 2016-09
B16: =Data!B16 -> 2016-10
B17: =Data!B17 -> 2016-11
B18: =Data!B18 -> 2016-12 | C18: =Data!D7+Data!E7+Data!F7+Data!G7+Data!H7+Data!I7+Data!J7+Data!K7+Data!L7+Data!M7+Data!N7+Data!O7+Data!P7+Data!Q7+Data!R7+Data!S7+Data!D8+Data!E8+Data!F8+Data!G8+Data!H8+Data!I8+Data!J8+Data!K8+Data!L8+Data!M8+Data!N8+Data!O8+Data!P8+Data!Q8+Data!R8+Data!S8+Data!D9+Data!E9+Data!F9+Data!G9+Data!H9+Data!I9+Data!J9+Data!K9+Data!L9+Data!M9+Data!N9+Data!O9+Data!P9+Data!Q9+Data!R9+Data!S9+Data!D10+Data!E10+Data!F10+Data!G10+Data!H10+Data!I10+Data!J10+Data!K10+Data!L10+Data!M10+Data!N10+Data!O10+Data!P10+Data!Q10+Data!R10+Data!S10+Data!D11+Data!E11+Data!F11+Data!G11+Data!H11+Data!I11+Data!J11+Data!K11+Data!L11+Data!M11+Data!N11+Data!O11+Data!P11+Data!Q11+Data!R11+Data!S11+Data!D12+Data!E12+Data!F12+Data!G12+Data!H12+Data!I12+Data!J12+Data!K12+Data!L12+Data!M12+Data!N12+Data!O12+Data!P12+Data!Q12+Data!R12+Data!S12+Data!D13+Data!E13+Data!F13+Data!G13+Data!H13+Data!I13+Data!J13+Data!K13+Data!L13+Data!M13+Data!N13+Data!O13+Data!P13+Data!Q13+Data!R13+Data!S13+Data!D14+Data!E14+Data!F14+Data!G14+Data!H14+Data!I14+Data!J14+Data!K14+Data!L14+Data!M14+Data!N14+Data!O14+Data!P14+Data!Q14+Data!R14+Data!S14+Data!D15+Data!E15+Data!F15+Data!G15+Data!H15+Data!I15+Data!J15+Data!K15+Data!L15+Data!M15+Data!N15+Data!O15+Data!P15+Data!Q15+Data!R15+Data!S15+Data!D16+Data!E16+Data!F16+Data!G16+Data!H16+Data!I16+Data!J16+Data!K16+Data!L16+Data!M16+Data!N16+Data!O16+Data!P16+Data!Q16+Data!R16+Data!S16+Data!D17+Data!E17+Data!F17+Data!G17+Data!H17+Data!I17+Data!J17+Data!K17+Data!L17+Data!M17+Data!N17+Data!O17+Data!P17+Data!Q17+Data!R17+Data!S17+Data!D18+Data!E18+Data!F18+Data!G18+Data!H18+Data!I18+Data!J18+Data!K18+Data!L18+Data!M18+Data!N18+Data!O18+Data!P18+Data!Q18+Data!R18+Data!S18 -> 1629314 | D18: =Data!D7+Data!E7+Data!G7+Data!H7+Data!I7+Data!J7+Data!K7+Data!L7+Data!M7+Data!D8+Data!E8+Data!G8+Data!H8+Data!I8+Data!J8+Data!K8+Data!L8+Data!M8+Data!D9+Data!E9+Data!G9+Data!H9+Data!I9+Data!J9+Data!K9+Data!L9+Data!M9+Data!D10+Data!E10+Data!G10+Data!H10+Data!I10+Data!J10+Data!K10+Data!L10+Data!M10+Data!D11+Data!E11+Data!G11+Data!H11+Data!I11+Data!J11+Data!K11+Data!L11+Data!M11+Data!D12+Data!E12+Data!G12+Data!H12+Data!I12+Data!J12+Data!K12+Data!L12+Data!M12+Data!D13+Data!E13+Data!G13+Data!H13+Data!I13+Data!J13+Data!K13+Data!L13+Data!M13+Data!D14+Data!E14+Data!G14+Data!H14+Data!I14+Data!J14+Data!K14+Data!L14+Data!M14+Data!D15+Data!E15+Data!G15+Data!H15+Data!I15+Data!J15+Data!K15+Data!L15+Data!M15+Data!D16+Data!E16+Data!G16+Data!H16+Data!I16+Data!J16+Data!K16+Data!L16+Data!M16+Data!D17+Data!E17+Data!G17+Data!H17+Data!I17+Data!J17+Data!K17+Data!L17+Data!M17+Data!D18+Data!E18+Data!G18+Data!H18+Data!I18+Data!J18+Data!K18+Data!L18+Data!M18 -> 976663 | E18: =Data!D7+Data!D8+Data!D9+Data!D10+Data!D11+Data!D12+Data!D13+Data!D14+Data!D15+Data!D16+Data!D17+Data!D18 -> 277842 | F18: =Data!E7+Data!E8+Data!E9+Data!E10+Data!E11+Data!E12+Data!E13+Data!E14+Data!E15+Data!E16+Data!E17+Data!E18 -> 223422 | G18: =Data!K7+Data!K8+Data!K9+Data!K10+Data!K11+Data!K12+Data!K13+Data!K14+Data!K15+Data!K16+Data!K17+Data!K18 -> 72118 | H18: =Data!L7+Data!L8+Data!L9+Data!L10+Data!L11+Data!L12+Data!L13+Data!L14+Data!L15+Data!L16+Data!L17+Data!L18 -> 55396 | I18: =Data!G7+Data!G8+Data!G9+Data!G10+Data!G11+Data!G12+Data!G13+Data!G14+Data!G15+Data!G16+Data!G17+Data!G18 -> 109339 | J18: =Data!H7+Data!I7+Data!J7+Data!M7+Data!H8+Data!I8+Data!J8+Data!M8+Data!H9+Data!I9+Data!J9+Data!M9+Data!H10+Data!I10+Data!J10+Data!M10+Data!H11+Data!I11+Data!J11+Data!M11+Data!H12+Data!I12+Data!J12+Data!M12+Data!H13+Data!I13+Data!J13+Data!M13+Data!H14+Data!I14+Data!J14+Data!M14+Data!H15+Data!I15+Data!J15+Data!M15+Data!H16+Data!I16+Data!J16+Data!M16+Data!H17+Data!I17+Data!J17+Data!M17+Data!H18+Data!I18+Data!J18+Data!M18 -> 238546 | K18: =Data!F7+Data!F8+Data!F9+Data!F10+Data!F11+Data!F12+Data!F13+Data!F14+Data!F15+Data!F16+Data!F17+Data!F18 -> 558088 | L18: =Data!N7+Data!O7+Data!P7+Data!Q7+Data!R7+Data!S7+Data!N8+Data!O8+Data!P8+Data!Q8+Data!R8+Data!S8+Data!N9+Data!O9+Data!P9+Data!Q9+Data!R9+Data!S9+Data!N10+Data!O10+Data!P10+Data!Q10+Data!R10+Data!S10+Data!N11+Data!O11+Data!P11+Data!Q11+Data!R11+Data!S11+Data!N12+Data!O12+Data!P12+Data!Q12+Data!R12+Data!S12+Data!N13+Data!O13+Data!P13+Data!Q13+Data!R13+Data!S13+Data!N14+Data!O14+Data!P14+Data!Q14+Data!R14+Data!S14+Data!N15+Data!O15+Data!P15+Data!Q15+Data!R15+Data!S15+Data!N16+Data!O16+Data!P16+Data!Q16+Data!R16+Data!S16+Data!N17+Data!O17+Data!P17+Data!Q17+Data!R17+Data!S17+Data!N18+Data!O18+Data!P18+Data!Q18+Data!R18+Data!S18 -> 94563 | M18: =Data!T7+Data!U7+Data!V7+Data!W7+Data!X7+Data!Y7+Data!Z7+Data!AA7+Data!AB7+Data!AC7+Data!AD7+Data!AE7+Data!AF7+Data!AG7+Data!AH7+Data!AI7+Data!AJ7+Data!AK7+Data!AL7+Data!T8+Data!U8+Data!V8+Data!W8+Data!X8+Data!Y8+Data!Z8+Data!AA8+Data!AB8+Data!AC8+Data!AD8+Data!AE8+Data!AF8+Data!AG8+Data!AH8+Data!AI8+Data!AJ8+Data!AK8+Data!AL8+Data!T9+Data!U9+Data!V9+Data!W9+Data!X9+Data!Y9+Data!Z9+Data!AA9+Data!AB9+Data!AC9+Data!AD9+Data!AE9+Data!AF9+Data!AG9+Data!AH9+Data!AI9+Data!AJ9+Data!AK9+Data!AL9+Data!T10+Data!U10+Data!V10+Data!W10+Data!X10+Data!Y10+Data!Z10+Data!AA10+Data!AB10+Data!AC10+Data!AD10+Data!AE10+Data!AF10+Data!AG10+Data!AH10+Data!AI10+Data!AJ10+Data!AK10+Data!AL10+Data!T11+Data!U11+Data!V11+Data!W11+Data!X11+Data!Y11+Data!Z11+Data!AA11+Data!AB11+Data!AC11+Data!AD11+Data!AE11+Data!AF11+Data!AG11+Data!AH11+Data!AI11+Data!AJ11+Data!AK11+Data!AL11+Data!T12+Data!U12+Data!V12+Data!W12+Data!X12+Data!Y12+Data!Z12+Data!AA12+Data!AB12+Data!AC12+Data!AD12+Data!AE12+Data!AF12+Data!AG12+Data!AH12+Data!AI12+Data!AJ12+Data!AK12+Data!AL12+Data!T13+Data!U13+Data!V13+Data!W13+Data!X13+Data!Y13+Data!Z13+Data!AA13+Data!AB13+Data!AC13+Data!AD13+Data!AE13+Data!AF13+Data!AG13+Data!AH13+Data!AI13+Data!AJ13+Data!AK13+Data!AL13+Data!T14+Data!U14+Data!V14+Data!W14+Data!X14+Data!Y14+Data!Z14+Data!AA14+Data!AB14+Data!AC14+Data!AD14+Data!AE14+Data!AF14+Data!AG14+Data!AH14+Data!AI14+Data!AJ14+Data!AK14+Data!AL14+Data!T15+Data!U15+Data!V15+Data!W15+Data!X15+Data!Y15+Data!Z15+Data!AA15+Data!AB15+Data!AC15+Data!AD15+Data!AE15+Data!AF15+Data!AG15+Data!AH15+Data!AI15+Data!AJ15+Data!AK15+Data!AL15+Data!T16+Data!U16+Data!V16+Data!W16+Data!X16+Data!Y16+Data!Z16+Data!AA16+Data!AB16+Data!AC16+Data!AD16+Data!AE16+Data!AF16+Data!AG16+Data!AH16+Data!AI16+Data!AJ16+Data!AK16+Data!AL16+Data!T17+Data!U17+Data!V17+Data!W17+Data!X17+Data!Y17+Data!Z17+Data!AA17+Data!AB17+Data!AC17+Data!AD17+Data!AE17+Data!AF17+Data!AG17+Data!AH17+Data!AI17+Data!AJ17+Data!AK17+Data!AL17+Data!T18+Data!U18+Data!V18+Data!W18+Data!X18+Data!Y18+Data!Z18+Data!AA18+Data!AB18+Data!AC18+Data!AD18+Data!AE18+Data!AF18+Data!AG18+Data!AH18+Data!AI18+Data!AJ18+Data!AK18+Data!AL18 -> 1972838 | N18: =Data!T7+Data!U7+Data!V7+Data!W7+Data!T8+Data!U8+Data!V8+Data!W8+Data!T9+Data!U9+Data!V9+Data!W9+Data!T10+Data!U10+Data!V10+Data!W10+Data!T11+Data!U11+Data!V11+Data!W11+Data!T12+Data!U12+Data!V12+Data!W12+Data!T13+Data!U13+Data!V13+Data!W13+Data!T14+Data!U14+Data!V14+Data!W14+Data!T15+Data!U15+Data!V15+Data!W15+Data!T16+Data!U16+Data!V16+Data!W16+Data!T17+Data!U17+Data!V17+Data!W17+Data!T18+Data!U18+Data!V18+Data!W18 -> 924288 | O18: =Data!T7+Data!T8+Data!T9+Data!T10+Data!T11+Data!T12+Data!T13+Data!T14+Data!T15+Data!T16+Data!T17+Data!T18 -> 654470 | P18: =Data!U7+Data!U8+Data!U9+Data!U10+Data!U11+Data!U12+Data!U13+Data!U14+Data!U15+Data!U16+Data!U17+Data!U18 -> 108160 | Q18: =Data!V7+Data!V8+Data!V9+Data!V10+Data!V11+Data!V12+Data!V13+Data!V14+Data!V15+Data!V16+Data!V17+Data!V18 -> 80249 | R18: =Data!W7+Data!W8+Data!W9+Data!W10+Data!W11+Data!W12+Data!W13+Data!W14+Data!W15+Data!W16+Data!W17+Data!W18 -> 81409 | S18: =Data!X7+Data!X8+Data!X9+Data!X10+Data!X11+Data!X12+Data!X13+Data!X14+Data!X15+Data!X16+Data!X17+Data!X18 -> 30302 | T18: =Data!Y7+Data!Z7+Data!AA7+Data!Y8+Data!Z8+Data!AA8+Data!Y9+Data!Z9+Data!AA9+Data!Y10+Data!Z10+Data!AA10+Data!Y11+Data!Z11+Data!AA11+Data!Y12+Data!Z12+Data!AA12+Data!Y13+Data!Z13+Data!AA13+Data!Y14+Data!Z14+Data!AA14+Data!Y15+Data!Z15+Data!AA15+Data!Y16+Data!Z16+Data!AA16+Data!Y17+Data!Z17+Data!AA17+Data!Y18+Data!Z18+Data!AA18 -> 291171 | U18: =Data!Y7+Data!Y8+Data!Y9+Data!Y10+Data!Y11+Data!Y12+Data!Y13+Data!Y14+Data!Y15+Data!Y16+Data!Y17+Data!Y18 -> 209203 | V18: =Data!Z7+Data!Z8+Data!Z9+Data!Z10+Data!Z11+Data!Z12+Data!Z13+Data!Z14+Data!Z15+Data!Z16+Data!Z17+Data!Z18 -> 80247 | W18: =Data!AB7+Data!AB8+Data!AB9+Data!AB10+Data!AB11+Data!AB12+Data!AB13+Data!AB14+Data!AB15+Data!AB16+Data!AB17+Data!AB18 -> 266830 | X18: =Data!AC7+Data!AC8+Data!AC9+Data!AC10+Data!AC11+Data!AC12+Data!AC13+Data!AC14+Data!AC15+Data!AC16+Data!AC17+Data!AC18 -> 79340 | Y18: =Data!AD7+Data!AE7+Data!AF7+Data!AG7+Data!AH7+Data!AD8+Data!AE8+Data!AF8+Data!AG8+Data!AH8+Data!AD9+Data!AE9+Data!AF9+Data!AG9+Data!AH9+Data!AD10+Data!AE10+Data!AF10+Data!AG10+Data!AH10+Data!AD11+Data!AE11+Data!AF11+Data!AG11+Data!AH11+Data!AD12+Data!AE12+Data!AF12+Data!AG12+Data!AH12+Data!AD13+Data!AE13+Data!AF13+Data!AG13+Data!AH13+Data!AD14+Data!AE14+Data!AF14+Data!AG14+Data!AH14+Data!AD15+Data!AE15+Data!AF15+Data!AG15+Data!AH15+Data!AD16+Data!AE16+Data!AF16+Data!AG16+Data!AH16+Data!AD17+Data!AE17+Data!AF17+Data!AG17+Data!AH17+Data!AD18+Data!AE18+Data!AF18+Data!AG18+Data!AH18 -> 73593 | Z18: =Data!AI7+Data!AI8+Data!AI9+Data!AI10+Data!AI11+Data!AI12+Data!AI13+Data!AI14+Data!AI15+Data!AI16+Data!AI17+Data!AI18 -> 62502 | AA18: =Data!AJ7+Data!AJ8+Data!AJ9+Data!AJ10+Data!AJ11+Data!AJ12+Data!AJ13+Data!AJ14+Data!AJ15+Data!AJ16+Data!AJ17+Data!AJ18 -> 8139 | AB18: =Data!AK7+Data!AK8+Data!AK9+Data!AK10+Data!AK11+Data!AK12+Data!AK13+Data!AK14+Data!AK15+Data!AK16+Data!AK17+Data!AK18 -> 54630 | AC18: =Data!AL7+Data!AL8+Data!AL9+Data!AL10+Data!AL11+Data!AL12+Data!AL13+Data!AL14+Data!AL15+Data!AL16+Data!AL17+Data!AL18 -> 182043 | AD18: =Data!AM7+Data!AM8+Data!AM9+Data!AM10+Data!AM11+Data!AM12+Data!AM13+Data!AM14+Data!AM15+Data!AM16+Data!AM17+Data!AM18 -> -343524 | AE18: =Data!AN7+Data!AN8+Data!AN9+Data!AN10+Data!AN11+Data!AN12+Data!AN13+Data!AN14+Data!AN15+Data!AN16+Data!AN17+Data!AN18 -> 131259 | AF18: =Data!AO7+Data!AO8+Data!AO9+Data!AO10+Data!AO11+Data!AO12+Data!AO13+Data!AO14+Data!AO15+Data!AO16+Data!AO17+Data!AO18 -> -474785
B19: =Data!B19 -> 2017-01 | C19: =Data!D8+Data!E8+Data!F8+Data!G8+Data!H8+Data!I8+Data!J8+Data!K8+Data!L8+Data!M8+Data!N8+Data!O8+Data!P8+Data!Q8+Data!R8+Data!S8+Data!D9+Data!E9+Data!F9+Data!G9+Data!H9+Data!I9+Data!J9+Data!K9+Data!L9+Data!M9+Data!N9+Data!O9+Data!P9+Data!Q9+Data!R9+Data!S9+Data!D10+Data!E10+Data!F10+Data!G10+Data!H10+Data!I10+Data!J10+Data!K10+Data!L10+Data!M10+Data!N10+Data!O10+Data!P10+Data!Q10+Data!R10+Data!S10+Data!D11+Data!E11+Data!F11+Data!G11+Data!H11+Data!I11+Data!J11+Data!K11+Data!L11+Data!M11+Data!N11+Data!O11+Data!P11+Data!Q11+Data!R11+Data!S11+Data!D12+Data!E12+Data!F12+Data!G12+Data!H12+Data!I12+Data!J12+Data!K12+Data!L12+Data!M12+Data!N12+Data!O12+Data!P12+Data!Q12+Data!R12+Data!S12+Data!D13+Data!E13+Data!F13+Data!G13+Data!H13+Data!I13+Data!J13+Data!K13+Data!L13+Data!M13+Data!N13+Data!O13+Data!P13+Data!Q13+Data!R13+Data!S13+Data!D14+Data!E14+Data!F14+Data!G14+Data!H14+Data!I14+Data!J14+Data!K14+Data!L14+Data!M14+Data!N14+Data!O14+Data!P14+Data!Q14+Data!R14+Data!S14+Data!D15+Data!E15+Data!F15+Data!G15+Data!H15+Data!I15+Data!J15+Data!K15+Data!L15+Data!M15+Data!N15+Data!O15+Data!P15+Data!Q15+Data!R15+Data!S15+Data!D16+Data!E16+Data!F16+Data!G16+Data!H16+Data!I16+Data!J16+Data!K16+Data!L16+Data!M16+Data!N16+Data!O16+Data!P16+Data!Q16+Data!R16+Data!S16+Data!D17+Data!E17+Data!F17+Data!G17+Data!H17+Data!I17+Data!J17+Data!K17+Data!L17+Data!M17+Data!N17+Data!O17+Data!P17+Data!Q17+Data!R17+Data!S17+Data!D18+Data!E18+Data!F18+Data!G18+Data!H18+Data!I18+Data!J18+Data!K18+Data!L18+Data!M18+Data!N18+Data!O18+Data!P18+Data!Q18+Data!R18+Data!S18+Data!D19+Data!E19+Data!F19+Data!G19+Data!H19+Data!I19+Data!J19+Data!K19+Data!L19+Data!M19+Data!N19+Data!O19+Data!P19+Data!Q19+Data!R19+Data!S19 -> 1677949 | D19: =Data!D8+Data!E8+Data!G8+Data!H8+Data!I8+Data!J8+Data!K8+Data!L8+Data!M8+Data!D9+Data!E9+Data!G9+Data!H9+Data!I9+Data!J9+Data!K9+Data!L9+Data!M9+Data!D10+Data!E10+Data!G10+Data!H10+Data!I10+Data!J10+Data!K10+Data!L10+Data!M10+Data!D11+Data!E11+Data!G11+Data!H11+Data!I11+Data!J11+Data!K11+Data!L11+Data!M11+Data!D12+Data!E12+Data!G12+Data!H12+Data!I12+Data!J12+Data!K12+Data!L12+Data!M12+Data!D13+Data!E13+Data!G13+Data!H13+Data!I13+Data!J13+Data!K13+Data!L13+Data!M13+Data!D14+Data!E14+Data!G14+Data!H14+Data!I14+Data!J14+Data!K14+Data!L14+Data!M14+Data!D15+Data!E15+Data!G15+Data!H15+Data!I15+Data!J15+Data!K15+Data!L15+Data!M15+Data!D16+Data!E16+Data!G16+Data!H16+Data!I16+Data!J16+Data!K16+Data!L16+Data!M16+Data!D17+Data!E17+Data!G17+Data!H17+Data!I17+Data!J17+Data!K17+Data!L17+Data!M17+Data!D18+Data!E18+Data!G18+Data!H18+Data!I18+Data!J18+Data!K18+Data!L18+Data!M18+Data!D19+Data!E19+Data!G19+Data!H19+Data!I19+Data!J19+Data!K19+Data!L19+Data!M19 -> 1004340 | E19: =Data!D8+Data!D9+Data!D10+Data!D11+Data!D12+Data!D13+Data!D14+Data!D15+Data!D16+Data!D17+Data!D18+Data!D19 -> 283872 | F19: =Data!E8+Data!E9+Data!E10+Data!E11+Data!E12+Data!E13+Data!E14+Data!E15+Data!E16+Data!E17+Data!E18+Data!E19 -> 224706 | G19: =Data!K8+Data!K9+Data!K10+Data!K11+Data!K12+Data!K13+Data!K14+Data!K15+Data!K16+Data!K17+Data!K18+Data!K19 -> 73014 | H19: =Data!L8+Data!L9+Data!L10+Data!L11+Data!L12+Data!L13+Data!L14+Data!L15+Data!L16+Data!L17+Data!L18+Data!L19 -> 56581 | I19: =Data!G8+Data!G9+Data!G10+Data!G11+Data!G12+Data!G13+Data!G14+Data!G15+Data!G16+Data!G17+Data!G18+Data!G19 -> 112443 | J19: =Data!H8+Data!I8+Data!J8+Data!M8+Data!H9+Data!I9+Data!J9+Data!M9+Data!H10+Data!I10+Data!J10+Data!M10+Data!H11+Data!I11+Data!J11+Data!M11+Data!H12+Data!I12+Data!J12+Data!M12+Data!H13+Data!I13+Data!J13+Data!M13+Data!H14+Data!I14+Data!J14+Data!M14+Data!H15+Data!I15+Data!J15+Data!M15+Data!H16+Data!I16+Data!J16+Data!M16+Data!H17+Data!I17+Data!J17+Data!M17+Data!H18+Data!I18+Data!J18+Data!M18+Data!H19+Data!I19+Data!J19+Data!M19 -> 253724 | K19: =Data!F8+Data!F9+Data!F10+Data!F11+Data!F12+Data!F13+Data!F14+Data!F15+Data!F16+Data!F17+Data!F18+Data!F19 -> 574456 | L19: =Data!N8+Data!O8+Data!P8+Data!Q8+Data!R8+Data!S8+Data!N9+Data!O9+Data!P9+Data!Q9+Data!R9+Data!S9+Data!N10+Data!O10+Data!P10+Data!Q10+Data!R10+Data!S10+Data!N11+Data!O11+Data!P11+Data!Q11+Data!R11+Data!S11+Data!N12+Data!O12+Data!P12+Data!Q12+Data!R12+Data!S12+Data!N13+Data!O13+Data!P13+Data!Q13+Data!R13+Data!S13+Data!N14+Data!O14+Data!P14+Data!Q14+Data!R14+Data!S14+Data!N15+Data!O15+Data!P15+Data!Q15+Data!R15+Data!S15+Data!N16+Data!O16+Data!P16+Data!Q16+Data!R16+Data!S16+Data!N17+Data!O17+Data!P17+Data!Q17+Data!R17+Data!S17+Data!N18+Data!O18+Data!P18+Data!Q18+Data!R18+Data!S18+Data!N19+Data!O19+Data!P19+Data!Q19+Data!R19+Data!S19 -> 99153 | M19: =Data!T8+Data!U8+Data!V8+Data!W8+Data!X8+Data!Y8+Data!Z8+Data!AA8+Data!AB8+Data!AC8+Data!AD8+Data!AE8+Data!AF8+Data!AG8+Data!AH8+Data!AI8+Data!AJ8+Data!AK8+Data!AL8+Data!T9+Data!U9+Data!V9+Data!W9+Data!X9+Data!Y9+Data!Z9+Data!AA9+Data!AB9+Data!AC9+Data!AD9+Data!AE9+Data!AF9+Data!AG9+Data!AH9+Data!AI9+Data!AJ9+Data!AK9+Data!AL9+Data!T10+Data!U10+Data!V10+Data!W10+Data!X10+Data!Y10+Data!Z10+Data!AA10+Data!AB10+Data!AC10+Data!AD10+Data!AE10+Data!AF10+Data!AG10+Data!AH10+Data!AI10+Data!AJ10+Data!AK10+Data!AL10+Data!T11+Data!U11+Data!V11+Data!W11+Data!X11+Data!Y11+Data!Z11+Data!AA11+Data!AB11+Data!AC11+Data!AD11+Data!AE11+Data!AF11+Data!AG11+Data!AH11+Data!AI11+Data!AJ11+Data!AK11+Data!AL11+Data!T12+Data!U12+Data!V12+Data!W12+Data!X12+Data!Y12+Data!Z12+Data!AA12+Data!AB12+Data!AC12+Data!AD12+Data!AE12+Data!AF12+Data!AG12+Data!AH12+Data!AI12+Data!AJ12+Data!AK12+Data!AL12+Data!T13+Data!U13+Data!V13+Data!W13+Data!X13+Data!Y13+Data!Z13+Data!AA13+Data!AB13+Data!AC13+Data!AD13+Data!AE13+Data!AF13+Data!AG13+Data!AH13+Data!AI13+Data!AJ13+Data!AK13+Data!AL13+Data!T14+Data!U14+Data!V14+Data!W14+Data!X14+Data!Y14+Data!Z14+Data!AA14+Data!AB14+Data!AC14+Data!AD14+Data!AE14+Data!AF14+Data!AG14+Data!AH14+Data!AI14+Data!AJ14+Data!AK14+Data!AL14+Data!T15+Data!U15+Data!V15+Data!W15+Data!X15+Data!Y15+Data!Z15+Data!AA15+Data!AB15+Data!AC15+Data!AD15+Data!AE15+Data!AF15+Data!AG15+Data!AH15+Data!AI15+Data!AJ15+Data!AK15+Data!AL15+Data!T16+Data!U16+Data!V16+Data!W16+Data!X16+Data!Y16+Data!Z16+Data!AA16+Data!AB16+Data!AC16+Data!AD16+Data!AE16+Data!AF16+Data!AG16+Data!AH16+Data!AI16+Data!AJ16+Data!AK16+Data!AL16+Data!T17+Data!U17+Data!V17+Data!W17+Data!X17+Data!Y17+Data!Z17+Data!AA17+Data!AB17+Data!AC17+Data!AD17+Data!AE17+Data!AF17+Data!AG17+Data!AH17+Data!AI17+Data!AJ17+Data!AK17+Data!AL17+Data!T18+Data!U18+Data!V18+Data!W18+Data!X18+Data!Y18+Data!Z18+Data!AA18+Data!AB18+Data!AC18+Data!AD18+Data!AE18+Data!AF18+Data!AG18+Data!AH18+Data!AI18+Data!AJ18+Data!AK18+Data!AL18+Data!T19+Data!U19+Data!V19+Data!W19+Data!X19+Data!Y19+Data!Z19+Data!AA19+Data!AB19+Data!AC19+Data!AD19+Data!AE19+Data!AF19+Data!AG19+Data!AH19+Data!AI19+Data!AJ19+Data!AK19+Data!AL19 -> 2018627 | N19: =Data!T8+Data!U8+Data!V8+Data!W8+Data!T9+Data!U9+Data!V9+Data!W9+Data!T10+Data!U10+Data!V10+Data!W10+Data!T11+Data!U11+Data!V11+Data!W11+Data!T12+Data!U12+Data!V12+Data!W12+Data!T13+Data!U13+Data!V13+Data!W13+Data!T14+Data!U14+Data!V14+Data!W14+Data!T15+Data!U15+Data!V15+Data!W15+Data!T16+Data!U16+Data!V16+Data!W16+Data!T17+Data!U17+Data!V17+Data!W17+Data!T18+Data!U18+Data!V18+Data!W18+Data!T19+Data!U19+Data!V19+Data!W19 -> 950075 | O19: =Data!T8+Data!T9+Data!T10+Data!T11+Data!T12+Data!T13+Data!T14+Data!T15+Data!T16+Data!T17+Data!T18+Data!T19 -> 672515 | P19: =Data!U8+Data!U9+Data!U10+Data!U11+Data!U12+Data!U13+Data!U14+Data!U15+Data!U16+Data!U17+Data!U18+Data!U19 -> 112645 | Q19: =Data!V8+Data!V9+Data!V10+Data!V11+Data!V12+Data!V13+Data!V14+Data!V15+Data!V16+Data!V17+Data!V18+Data!V19 -> 81141 | R19: =Data!W8+Data!W9+Data!W10+Data!W11+Data!W12+Data!W13+Data!W14+Data!W15+Data!W16+Data!W17+Data!W18+Data!W19 -> 83774 | S19: =Data!X8+Data!X9+Data!X10+Data!X11+Data!X12+Data!X13+Data!X14+Data!X15+Data!X16+Data!X17+Data!X18+Data!X19 -> 31453 | T19: =Data!Y8+Data!Z8+Data!AA8+Data!Y9+Data!Z9+Data!AA9+Data!Y10+Data!Z10+Data!AA10+Data!Y11+Data!Z11+Data!AA11+Data!Y12+Data!Z12+Data!AA12+Data!Y13+Data!Z13+Data!AA13+Data!Y14+Data!Z14+Data!AA14+Data!Y15+Data!Z15+Data!AA15+Data!Y16+Data!Z16+Data!AA16+Data!Y17+Data!Z17+Data!AA17+Data!Y18+Data!Z18+Data!AA18+Data!Y19+Data!Z19+Data!AA19 -> 290528 | U19: =Data!Y8+Data!Y9+Data!Y10+Data!Y11+Data!Y12+Data!Y13+Data!Y14+Data!Y15+Data!Y16+Data!Y17+Data!Y18+Data!Y19 -> 208340 | V19: =Data!Z8+Data!Z9+Data!Z10+Data!Z11+Data!Z12+Data!Z13+Data!Z14+Data!Z15+Data!Z16+Data!Z17+Data!Z18+Data!Z19 -> 80387 | W19: =Data!AB8+Data!AB9+Data!AB10+Data!AB11+Data!AB12+Data!AB13+Data!AB14+Data!AB15+Data!AB16+Data!AB17+Data!AB18+Data!AB19 -> 273836 | X19: =Data!AC8+Data!AC9+Data!AC10+Data!AC11+Data!AC12+Data!AC13+Data!AC14+Data!AC15+Data!AC16+Data!AC17+Data!AC18+Data!AC19 -> 82865 | Y19: =Data!AD8+Data!AE8+Data!AF8+Data!AG8+Data!AH8+Data!AD9+Data!AE9+Data!AF9+Data!AG9+Data!AH9+Data!AD10+Data!AE10+Data!AF10+Data!AG10+Data!AH10+Data!AD11+Data!AE11+Data!AF11+Data!AG11+Data!AH11+Data!AD12+Data!AE12+Data!AF12+Data!AG12+Data!AH12+Data!AD13+Data!AE13+Data!AF13+Data!AG13+Data!AH13+Data!AD14+Data!AE14+Data!AF14+Data!AG14+Data!AH14+Data!AD15+Data!AE15+Data!AF15+Data!AG15+Data!AH15+Data!AD16+Data!AE16+Data!AF16+Data!AG16+Data!AH16+Data!AD17+Data!AE17+Data!AF17+Data!AG17+Data!AH17+Data!AD18+Data!AE18+Data!AF18+Data!AG18+Data!AH18+Data!AD19+Data!AE19+Data!AF19+Data!AG19+Data!AH19 -> 76934 | Z19: =Data!AI8+Data!AI9+Data!AI10+Data!AI11+Data!AI12+Data!AI13+Data!AI14+Data!AI15+Data!AI16+Data!AI17+Data!AI18+Data!AI19 -> 63965 | AA19: =Data!AJ8+Data!AJ9+Data!AJ10+Data!AJ11+Data!AJ12+Data!AJ13+Data!AJ14+Data!AJ15+Data!AJ16+Data!AJ17+Data!AJ18+Data!AJ19 -> 8141 | AB19: =Data!AK8+Data!AK9+Data!AK10+Data!AK11+Data!AK12+Data!AK13+Data!AK14+Data!AK15+Data!AK16+Data!AK17+Data!AK18+Data!AK19 -> 56691 | AC19: =Data!AL8+Data!AL9+Data!AL10+Data!AL11+Data!AL12+Data!AL13+Data!AL14+Data!AL15+Data!AL16+Data!AL17+Data!AL18+Data!AL19 -> 184139 | AD19: =Data!AM8+Data!AM9+Data!AM10+Data!AM11+Data!AM12+Data!AM13+Data!AM14+Data!AM15+Data!AM16+Data!AM17+Data!AM18+Data!AM19 -> -340678 | AE19: =Data!AN8+Data!AN9+Data!AN10+Data!AN11+Data!AN12+Data!AN13+Data!AN14+Data!AN15+Data!AN16+Data!AN17+Data!AN18+Data!AN19 -> 137464 | AF19: =Data!AO8+Data!AO9+Data!AO10+Data!AO11+Data!AO12+Data!AO13+Data!AO14+Data!AO15+Data!AO16+Data!AO17+Data!AO18+Data!AO19 -> -478144
B20: =Data!B20 -> 2017-02 | C20: =Data!D9+Data!E9+Data!F9+Data!G9+Data!H9+Data!I9+Data!J9+Data!K9+Data!L9+Data!M9+Data!N9+Data!O9+Data!P9+Data!Q9+Data!R9+Data!S9+Data!D10+Data!E10+Data!F10+Data!G10+Data!H10+Data!I10+Data!J10+Data!K10+Data!L10+Data!M10+Data!N10+Data!O10+Data!P10+Data!Q10+Data!R10+Data!S10+Data!D11+Data!E11+Data!F11+Data!G11+Data!H11+Data!I11+Data!J11+Data!K11+Data!L11+Data!M11+Data!N11+Data!O11+Data!P11+Data!Q11+Data!R11+Data!S11+Data!D12+Data!E12+Data!F12+Data!G12+Data!H12+Data!I12+Data!J12+Data!K12+Data!L12+Data!M12+Data!N12+Data!O12+Data!P12+Data!Q12+Data!R12+Data!S12+Data!D13+Data!E13+Data!F13+Data!G13+Data!H13+Data!I13+Data!J13+Data!K13+Data!L13+Data!M13+Data!N13+Data!O13+Data!P13+Data!Q13+Data!R13+Data!S13+Data!D14+Data!E14+Data!F14+Data!G14+Data!H14+Data!I14+Data!J14+Data!K14+Data!L14+Data!M14+Data!N14+Data!O14+Data!P14+Data!Q14+Data!R14+Data!S14+Data!D15+Data!E15+Data!F15+Data!G15+Data!H15+Data!I15+Data!J15+Data!K15+Data!L15+Data!M15+Data!N15+Data!O15+Data!P15+Data!Q15+Data!R15+Data!S15+Data!D16+Data!E16+Data!F16+Data!G16+Data!H16+Data!I16+Data!J16+Data!K16+Data!L16+Data!M16+Data!N16+Data!O16+Data!P16+Data!Q16+Data!R16+Data!S16+Data!D17+Data!E17+Data!F17+Data!G17+Data!H17+Data!I17+Data!J17+Data!K17+Data!L17+Data!M17+Data!N17+Data!O17+Data!P17+Data!Q17+Data!R17+Data!S17+Data!D18+Data!E18+Data!F18+Data!G18+Data!H18+Data!I18+Data!J18+Data!K18+Data!L18+Data!M18+Data!N18+Data!O18+Data!P18+Data!Q18+Data!R18+Data!S18+Data!D19+Data!E19+Data!F19+Data!G19+Data!H19+Data!I19+Data!J19+Data!K19+Data!L19+Data!M19+Data!N19+Data!O19+Data!P19+Data!Q19+Data!R19+Data!S19+Data!D20+Data!E20+Data!F20+Data!G20+Data!H20+Data!I20+Data!J20+Data!K20+Data!L20+Data!M20+Data!N20+Data!O20+Data!P20+Data!Q20+Data!R20+Data!S20 -> 1713761 | D20: =Data!D9+Data!E9+Data!G9+Data!H9+Data!I9+Data!J9+Data!K9+Data!L9+Data!M9+Data!D10+Data!E10+Data!G10+Data!H10+Data!I10+Data!J10+Data!K10+Data!L10+Data!M10+Data!D11+Data!E11+Data!G11+Data!H11+Data!I11+Data!J11+Data!K11+Data!L11+Data!M11+Data!D12+Data!E12+Data!G12+Data!H12+Data!I12+Data!J12+Data!K12+Data!L12+Data!M12+Data!D13+Data!E13+Data!G13+Data!H13+Data!I13+Data!J13+Data!K13+Data!L13+Data!M13+Data!D14+Data!E14+Data!G14+Data!H14+Data!I14+Data!J14+Data!K14+Data!L14+Data!M14+Data!D15+Data!E15+Data!G15+Data!H15+Data!I15+Data!J15+Data!K15+Data!L15+Data!M15+Data!D16+Data!E16+Data!G16+Data!H16+Data!I16+Data!J16+Data!K16+Data!L16+Data!M16+Data!D17+Data!E17+Data!G17+Data!H17+Data!I17+Data!J17+Data!K17+Data!L17+Data!M17+Data!D18+Data!E18+Data!G18+Data!H18+Data!I18+Data!J18+Data!K18+Data!L18+Data!M18+Data!D19+Data!E19+Data!G19+Data!H19+Data!I19+Data!J19+Data!K19+Data!L19+Data!M19+Data!D20+Data!E20+Data!G20+Data!H20+Data!I20+Data!J20+Data!K20+Data!L20+Data!M20 -> 1015958 | E20: =Data!D9+Data!D10+Data!D11+Data!D12+Data!D13+Data!D14+Data!D15+Data!D16+Data!D17+Data!D18+Data!D19+Data!D20 -> 287830 | F20: =Data!E9+Data!E10+Data!E11+Data!E12+Data!E13+Data!E14+Data!E15+Data!E16+Data!E17+Data!E18+Data!E19+Data!E20 -> 226551 | G20: =Data!K9+Data!K10+Data!K11+Data!K12+Data!K13+Data!K14+Data!K15+Data!K16+Data!K17+Data!K18+Data!K19+Data!K20 -> 70613 | H20: =Data!L9+Data!L10+Data!L11+Data!L12+Data!L13+Data!L14+Data!L15+Data!L16+Data!L17+Data!L18+Data!L19+Data!L20 -> 57084 | I20: =Data!G9+Data!G10+Data!G11+Data!G12+Data!G13+Data!G14+Data!G15+Data!G16+Data!G17+Data!G18+Data!G19+Data!G20 -> 114729 | J20: =Data!H9+Data!I9+Data!J9+Data!M9+Data!H10+Data!I10+Data!J10+Data!M10+Data!H11+Data!I11+Data!J11+Data!M11+Data!H12+Data!I12+Data!J12+Data!M12+Data!H13+Data!I13+Data!J13+Data!M13+Data!H14+Data!I14+Data!J14+Data!M14+Data!H15+Data!I15+Data!J15+Data!M15+Data!H16+Data!I16+Data!J16+Data!M16+Data!H17+Data!I17+Data!J17+Data!M17+Data!H18+Data!I18+Data!J18+Data!M18+Data!H19+Data!I19+Data!J19+Data!M19+Data!H20+Data!I20+Data!J20+Data!M20 -> 259151 | K20: =Data!F9+Data!F10+Data!F11+Data!F12+Data!F13+Data!F14+Data!F15+Data!F16+Data!F17+Data!F18+Data!F19+Data!F20 -> 589182 | L20: =Data!N9+Data!O9+Data!P9+Data!Q9+Data!R9+Data!S9+Data!N10+Data!O10+Data!P10+Data!Q10+Data!R10+Data!S10+Data!N11+Data!O11+Data!P11+Data!Q11+Data!R11+Data!S11+Data!N12+Data!O12+Data!P12+Data!Q12+Data!R12+Data!S12+Data!N13+Data!O13+Data!P13+Data!Q13+Data!R13+Data!S13+Data!N14+Data!O14+Data!P14+Data!Q14+Data!R14+Data!S14+Data!N15+Data!O15+Data!P15+Data!Q15+Data!R15+Data!S15+Data!N16+Data!O16+Data!P16+Data!Q16+Data!R16+Data!S16+Data!N17+Data!O17+Data!P17+Data!Q17+Data!R17+Data!S17+Data!N18+Data!O18+Data!P18+Data!Q18+Data!R18+Data!S18+Data!N19+Data!O19+Data!P19+Data!Q19+Data!R19+Data!S19+Data!N20+Data!O20+Data!P20+Data!Q20+Data!R20+Data!S20 -> 108621 | M20: =Data!T9+Data!U9+Data!V9+Data!W9+Data!X9+Data!Y9+Data!Z9+Data!AA9+Data!AB9+Data!AC9+Data!AD9+Data!AE9+Data!AF9+Data!AG9+Data!AH9+Data!AI9+Data!AJ9+Data!AK9+Data!AL9+Data!T10+Data!U10+Data!V10+Data!W10+Data!X10+Data!Y10+Data!Z10+Data!AA10+Data!AB10+Data!AC10+Data!AD10+Data!AE10+Data!AF10+Data!AG10+Data!AH10+Data!AI10+Data!AJ10+Data!AK10+Data!AL10+Data!T11+Data!U11+Data!V11+Data!W11+Data!X11+Data!Y11+Data!Z11+Data!AA11+Data!AB11+Data!AC11+Data!AD11+Data!AE11+Data!AF11+Data!AG11+Data!AH11+Data!AI11+Data!AJ11+Data!AK11+Data!AL11+Data!T12+Data!U12+Data!V12+Data!W12+Data!X12+Data!Y12+Data!Z12+Data!AA12+Data!AB12+Data!AC12+Data!AD12+Data!AE12+Data!AF12+Data!AG12+Data!AH12+Data!AI12+Data!AJ12+Data!AK12+Data!AL12+Data!T13+Data!U13+Data!V13+Data!W13+Data!X13+Data!Y13+Data!Z13+Data!AA13+Data!AB13+Data!AC13+Data!AD13+Data!AE13+Data!AF13+Data!AG13+Data!AH13+Data!AI13+Data!AJ13+Data!AK13+Data!AL13+Data!T14+Data!U14+Data!V14+Data!W14+Data!X14+Data!Y14+Data!Z14+Data!AA14+Data!AB14+Data!AC14+Data!AD14+Data!AE14+Data!AF14+Data!AG14+Data!AH14+Data!AI14+Data!AJ14+Data!AK14+Data!AL14+Data!T15+Data!U15+Data!V15+Data!W15+Data!X15+Data!Y15+Data!Z15+Data!AA15+Data!AB15+Data!AC15+Data!AD15+Data!AE15+Data!AF15+Data!AG15+Data!AH15+Data!AI15+Data!AJ15+Data!AK15+Data!AL15+Data!T16+Data!U16+Data!V16+Data!W16+Data!X16+Data!Y16+Data!Z16+Data!AA16+Data!AB16+Data!AC16+Data!AD16+Data!AE16+Data!AF16+Data!AG16+Data!AH16+Data!AI16+Data!AJ16+Data!AK16+Data!AL16+Data!T17+Data!U17+Data!V17+Data!W17+Data!X17+Data!Y17+Data!Z17+Data!AA17+Data!AB17+Data!AC17+Data!AD17+Data!AE17+Data!AF17+Data!AG17+Data!AH17+Data!AI17+Data!AJ17+Data!AK17+Data!AL17+Data!T18+Data!U18+Data!V18+Data!W18+Data!X18+Data!Y18+Data!Z18+Data!AA18+Data!AB18+Data!AC18+Data!AD18+Data!AE18+Data!AF18+Data!AG18+Data!AH18+Data!AI18+Data!AJ18+Data!AK18+Data!AL18+Data!T19+Data!U19+Data!V19+Data!W19+Data!X19+Data!Y19+Data!Z19+Data!AA19+Data!AB19+Data!AC19+Data!AD19+Data!AE19+Data!AF19+Data!AG19+Data!AH19+Data!AI19+Data!AJ19+Data!AK19+Data!AL19+Data!T20+Data!U20+Data!V20+Data!W20+Data!X20+Data!Y20+Data!Z20+Data!AA20+Data!AB20+Data!AC20+Data!AD20+Data!AE20+Data!AF20+Data!AG20+Data!AH20+Data!AI20+Data!AJ20+Data!AK20+Data!AL20 -> 2064544 | N20: =Data!T9+Data!U9+Data!V9+Data!W9+Data!T10+Data!U10+Data!V10+Data!W10+Data!T11+Data!U11+Data!V11+Data!W11+Data!T12+Data!U12+Data!V12+Data!W12+Data!T13+Data!U13+Data!V13+Data!W13+Data!T14+Data!U14+Data!V14+Data!W14+Data!T15+Data!U15+Data!V15+Data!W15+Data!T16+Data!U16+Data!V16+Data!W16+Data!T17+Data!U17+Data!V17+Data!W17+Data!T18+Data!U18+Data!V18+Data!W18+Data!T19+Data!U19+Data!V19+Data!W19+Data!T20+Data!U20+Data!V20+Data!W20 -> 978059 | O20: =Data!T9+Data!T10+Data!T11+Data!T12+Data!T13+Data!T14+Data!T15+Data!T16+Data!T17+Data!T18+Data!T19+Data!T20 -> 692538 | P20: =Data!U9+Data!U10+Data!U11+Data!U12+Data!U13+Data!U14+Data!U15+Data!U16+Data!U17+Data!U18+Data!U19+Data!U20 -> 116473 | Q20: =Data!V9+Data!V10+Data!V11+Data!V12+Data!V13+Data!V14+Data!V15+Data!V16+Data!V17+Data!V18+Data!V19+Data!V20 -> 83696 | R20: =Data!W9+Data!W10+Data!W11+Data!W12+Data!W13+Data!W14+Data!W15+Data!W16+Data!W17+Data!W18+Data!W19+Data!W20 -> 85352 | S20: =Data!X9+Data!X10+Data!X11+Data!X12+Data!X13+Data!X14+Data!X15+Data!X16+Data!X17+Data!X18+Data!X19+Data!X20 -> 31135 | T20: =Data!Y9+Data!Z9+Data!AA9+Data!Y10+Data!Z10+Data!AA10+Data!Y11+Data!Z11+Data!AA11+Data!Y12+Data!Z12+Data!AA12+Data!Y13+Data!Z13+Data!AA13+Data!Y14+Data!Z14+Data!AA14+Data!Y15+Data!Z15+Data!AA15+Data!Y16+Data!Z16+Data!AA16+Data!Y17+Data!Z17+Data!AA17+Data!Y18+Data!Z18+Data!AA18+Data!Y19+Data!Z19+Data!AA19+Data!Y20+Data!Z20+Data!AA20 -> 293480 | U20: =Data!Y9+Data!Y10+Data!Y11+Data!Y12+Data!Y13+Data!Y14+Data!Y15+Data!Y16+Data!Y17+Data!Y18+Data!Y19+Data!Y20 -> 207955 | V20: =Data!Z9+Data!Z10+Data!Z11+Data!Z12+Data!Z13+Data!Z14+Data!Z15+Data!Z16+Data!Z17+Data!Z18+Data!Z19+Data!Z20 -> 83211 | W20: =Data!AB9+Data!AB10+Data!AB11+Data!AB12+Data!AB13+Data!AB14+Data!AB15+Data!AB16+Data!AB17+Data!AB18+Data!AB19+Data!AB20 -> 279416 | X20: =Data!AC9+Data!AC10+Data!AC11+Data!AC12+Data!AC13+Data!AC14+Data!AC15+Data!AC16+Data!AC17+Data!AC18+Data!AC19+Data!AC20 -> 82885 | Y20: =Data!AD9+Data!AE9+Data!AF9+Data!AG9+Data!AH9+Data!AD10+Data!AE10+Data!AF10+Data!AG10+Data!AH10+Data!AD11+Data!AE11+Data!AF11+Data!AG11+Data!AH11+Data!AD12+Data!AE12+Data!AF12+Data!AG12+Data!AH12+Data!AD13+Data!AE13+Data!AF13+Data!AG13+Data!AH13+Data!AD14+Data!AE14+Data!AF14+Data!AG14+Data!AH14+Data!AD15+Data!AE15+Data!AF15+Data!AG15+Data!AH15+Data!AD16+Data!AE16+Data!AF16+Data!AG16+Data!AH16+Data!AD17+Data!AE17+Data!AF17+Data!AG17+Data!AH17+Data!AD18+Data!AE18+Data!AF18+Data!AG18+Data!AH18+Data!AD19+Data!AE19+Data!AF19+Data!AG19+Data!AH19+Data!AD20+Data!AE20+Data!AF20+Data!AG20+Data!AH20 -> 81201 | Z20: =Data!AI9+Data!AI10+Data!AI11+Data!AI12+Data!AI13+Data!AI14+Data!AI15+Data!AI16+Data!AI17+Data!AI18+Data!AI19+Data!AI20 -> 66537 | AA20: =Data!AJ9+Data!AJ10+Data!AJ11+Data!AJ12+Data!AJ13+Data!AJ14+Data!AJ15+Data!AJ16+Data!AJ17+Data!AJ18+Data!AJ19+Data!AJ20 -> 6209 | AB20: =Data!AK9+Data!AK10+Data!AK11+Data!AK12+Data!AK13+Data!AK14+Data!AK15+Data!AK16+Data!AK17+Data!AK18+Data!AK19+Data!AK20 -> 55255 | AC20: =Data!AL9+Data!AL10+Data!AL11+Data!AL12+Data!AL13+Data!AL14+Data!AL15+Data!AL16+Data!AL17+Data!AL18+Data!AL19+Data!AL20 -> 190367 | AD20: =Data!AM9+Data!AM10+Data!AM11+Data!AM12+Data!AM13+Data!AM14+Data!AM15+Data!AM16+Data!AM17+Data!AM18+Data!AM19+Data!AM20 -> -350783 | AE20: =Data!AN9+Data!AN10+Data!AN11+Data!AN12+Data!AN13+Data!AN14+Data!AN15+Data!AN16+Data!AN17+Data!AN18+Data!AN19+Data!AN20 -> 136823 | AF20: =Data!AO9+Data!AO10+Data!AO11+Data!AO12+Data!AO13+Data!AO14+Data!AO15+Data!AO16+Data!AO17+Data!AO18+Data!AO19+Data!AO20 -> -487607
B21: =Data!B21 -> 2017-03 | C21: =Data!D10+Data!E10+Data!F10+Data!G10+Data!H10+Data!I10+Data!J10+Data!K10+Data!L10+Data!M10+Data!N10+Data!O10+Data!P10+Data!Q10+Data!R10+Data!S10+Data!D11+Data!E11+Data!F11+Data!G11+Data!H11+Data!I11+Data!J11+Data!K11+Data!L11+Data!M11+Data!N11+Data!O11+Data!P11+Data!Q11+Data!R11+Data!S11+Data!D12+Data!E12+Data!F12+Data!G12+Data!H12+Data!I12+Data!J12+Data!K12+Data!L12+Data!M12+Data!N12+Data!O12+Data!P12+Data!Q12+Data!R12+Data!S12+Data!D13+Data!E13+Data!F13+Data!G13+Data!H13+Data!I13+Data!J13+Data!K13+Data!L13+Data!M13+Data!N13+Data!O13+Data!P13+Data!Q13+Data!R13+Data!S13+Data!D14+Data!E14+Data!F14+Data!G14+Data!H14+Data!I14+Data!J14+Data!K14+Data!L14+Data!M14+Data!N14+Data!O14+Data!P14+Data!Q14+Data!R14+Data!S14+Data!D15+Data!E15+Data!F15+Data!G15+Data!H15+Data!I15+Data!J15+Data!K15+Data!L15+Data!M15+Data!N15+Data!O15+Data!P15+Data!Q15+Data!R15+Data!S15+Data!D16+Data!E16+Data!F16+Data!G16+Data!H16+Data!I16+Data!J16+Data!K16+Data!L16+Data!M16+Data!N16+Data!O16+Data!P16+Data!Q16+Data!R16+Data!S16+Data!D17+Data!E17+Data!F17+Data!G17+Data!H17+Data!I17+Data!J17+Data!K17+Data!L17+Data!M17+Data!N17+Data!O17+Data!P17+Data!Q17+Data!R17+Data!S17+Data!D18+Data!E18+Data!F18+Data!G18+Data!H18+Data!I18+Data!J18+Data!K18+Data!L18+Data!M18+Data!N18+Data!O18+Data!P18+Data!Q18+Data!R18+Data!S18+Data!D19+Data!E19+Data!F19+Data!G19+Data!H19+Data!I19+Data!J19+Data!K19+Data!L19+Data!M19+Data!N19+Data!O19+Data!P19+Data!Q19+Data!R19+Data!S19+Data!D20+Data!E20+Data!F20+Data!G20+Data!H20+Data!I20+Data!J20+Data!K20+Data!L20+Data!M20+Data!N20+Data!O20+Data!P20+Data!Q20+Data!R20+Data!S20+Data!D21+Data!E21+Data!F21+Data!G21+Data!H21+Data!I21+Data!J21+Data!K21+Data!L21+Data!M21+Data!N21+Data!O21+Data!P21+Data!Q21+Data!R21+Data!S21 -> 1765869 | D21: =Data!D10+Data!E10+Data!G10+Data!H10+Data!I10+Data!J10+Data!K10+Data!L10+Data!M10+Data!D11+Data!E11+Data!G11+Data!H11+Data!I11+Data!J11+Data!K11+Data!L11+Data!M11+Data!D12+Data!E12+Data!G12+Data!H12+Data!I12+Data!J12+Data!K12+Data!L12+Data!M12+Data!D13+Data!E13+Data!G13+Data!H13+Data!I13+Data!J13+Data!K13+Data!L13+Data!M13+Data!D14+Data!E14+Data!G14+Data!H14+Data!I14+Data!J14+Data!K14+Data!L14+Data!M14+Data!D15+Data!E15+Data!G15+Data!H15+Data!I15+Data!J15+Data!K15+Data!L15+Data!M15+Data!D16+Data!E16+Data!G16+Data!H16+Data!I16+Data!J16+Data!K16+Data!L16+Data!M16+Data!D17+Data!E17+Data!G17+Data!H17+Data!I17+Data!J17+Data!K17+Data!L17+Data!M17+Data!D18+Data!E18+Data!G18+Data!H18+Data!I18+Data!J18+Data!K18+Data!L18+Data!M18+Data!D19+Data!E19+Data!G19+Data!H19+Data!I19+Data!J19+Data!K19+Data!L19+Data!M19+Data!D20+Data!E20+Data!G20+Data!H20+Data!I20+Data!J20+Data!K20+Data!L20+Data!M20+Data!D21+Data!E21+Data!G21+Data!H21+Data!I21+Data!J21+Data!K21+Data!L21+Data!M21 -> 1048366 | E21: =Data!D10+Data!D11+Data!D12+Data!D13+Data!D14+Data!D15+Data!D16+Data!D17+Data!D18+Data!D19+Data!D20+Data!D21 -> 289731 | F21: =Data!E10+Data!E11+Data!E12+Data!E13+Data!E14+Data!E15+Data!E16+Data!E17+Data!E18+Data!E19+Data!E20+Data!E21 -> 230174 | G21: =Data!K10+Data!K11+Data!K12+Data!K13+Data!K14+Data!K15+Data!K16+Data!K17+Data!K18+Data!K19+Data!K20+Data!K21 -> 69738 | H21: =Data!L10+Data!L11+Data!L12+Data!L13+Data!L14+Data!L15+Data!L16+Data!L17+Data!L18+Data!L19+Data!L20+Data!L21 -> 57696 | I21: =Data!G10+Data!G11+Data!G12+Data!G13+Data!G14+Data!G15+Data!G16+Data!G17+Data!G18+Data!G19+Data!G20+Data!G21 -> 117779 | J21: =Data!H10+Data!I10+Data!J10+Data!M10+Data!H11+Data!I11+Data!J11+Data!M11+Data!H12+Data!I12+Data!J12+Data!M12+Data!H13+Data!I13+Data!J13+Data!M13+Data!H14+Data!I14+Data!J14+Data!M14+Data!H15+Data!I15+Data!J15+Data!M15+Data!H16+Data!I16+Data!J16+Data!M16+Data!H17+Data!I17+Data!J17+Data!M17+Data!H18+Data!I18+Data!J18+Data!M18+Data!H19+Data!I19+Data!J19+Data!M19+Data!H20+Data!I20+Data!J20+Data!M20+Data!H21+Data!I21+Data!J21+Data!M21 -> 283248 | K21: =Data!F10+Data!F11+Data!F12+Data!F13+Data!F14+Data!F15+Data!F16+Data!F17+Data!F18+Data!F19+Data!F20+Data!F21 -> 605587 | L21: =Data!N10+Data!O10+Data!P10+Data!Q10+Data!R10+Data!S10+Data!N11+Data!O11+Data!P11+Data!Q11+Data!R11+Data!S11+Data!N12+Data!O12+Data!P12+Data!Q12+Data!R12+Data!S12+Data!N13+Data!O13+Data!P13+Data!Q13+Data!R13+Data!S13+Data!N14+Data!O14+Data!P14+Data!Q14+Data!R14+Data!S14+Data!N15+Data!O15+Data!P15+Data!Q15+Data!R15+Data!S15+Data!N16+Data!O16+Data!P16+Data!Q16+Data!R16+Data!S16+Data!N17+Data!O17+Data!P17+Data!Q17+Data!R17+Data!S17+Data!N18+Data!O18+Data!P18+Data!Q18+Data!R18+Data!S18+Data!N19+Data!O19+Data!P19+Data!Q19+Data!R19+Data!S19+Data!N20+Data!O20+Data!P20+Data!Q20+Data!R20+Data!S20+Data!N21+Data!O21+Data!P21+Data!Q21+Data!R21+Data!S21 -> 111916 | M21: =Data!T10+Data!U10+Data!V10+Data!W10+Data!X10+Data!Y10+Data!Z10+Data!AA10+Data!AB10+Data!AC10+Data!AD10+Data!AE10+Data!AF10+Data!AG10+Data!AH10+Data!AI10+Data!AJ10+Data!AK10+Data!AL10+Data!T11+Data!U11+Data!V11+Data!W11+Data!X11+Data!Y11+Data!Z11+Data!AA11+Data!AB11+Data!AC11+Data!AD11+Data!AE11+Data!AF11+Data!AG11+Data!AH11+Data!AI11+Data!AJ11+Data!AK11+Data!AL11+Data!T12+Data!U12+Data!V12+Data!W12+Data!X12+Data!Y12+Data!Z12+Data!AA12+Data!AB12+Data!AC12+Data!AD12+Data!AE12+Data!AF12+Data!AG12+Data!AH12+Data!AI12+Data!AJ12+Data!AK12+Data!AL12+Data!T13+Data!U13+Data!V13+Data!W13+Data!X13+Data!Y13+Data!Z13+Data!AA13+Data!AB13+Data!AC13+Data!AD13+Data!AE13+Data!AF13+Data!AG13+Data!AH13+Data!AI13+Data!AJ13+Data!AK13+Data!AL13+Data!T14+Data!U14+Data!V14+Data!W14+Data!X14+Data!Y14+Data!Z14+Data!AA14+Data!AB14+Data!AC14+Data!AD14+Data!AE14+Data!AF14+Data!AG14+Data!AH14+Data!AI14+Data!AJ14+Data!AK14+Data!AL14+Data!T15+Data!U15+Data!V15+Data!W15+Data!X15+Data!Y15+Data!Z15+Data!AA15+Data!AB15+Data!AC15+Data!AD15+Data!AE15+Data!AF15+Data!AG15+Data!AH15+Data!AI15+Data!AJ15+Data!AK15+Data!AL15+Data!T16+Data!U16+Data!V16+Data!W16+Data!X16+Data!Y16+Data!Z16+Data!AA16+Data!AB16+Data!AC16+Data!AD16+Data!AE16+Data!AF16+Data!AG16+Data!AH16+Data!AI16+Data!AJ16+Data!AK16+Data!AL16+Data!T17+Data!U17+Data!V17+Data!W17+Data!X17+Data!Y17+Data!Z17+Data!AA17+Data!AB17+Data!AC17+Data!AD17+Data!AE17+Data!AF17+Data!AG17+Data!AH17+Data!AI17+Data!AJ17+Data!AK17+Data!AL17+Data!T18+Data!U18+Data!V18+Data!W18+Data!X18+Data!Y18+Data!Z18+Data!AA18+Data!AB18+Data!AC18+Data!AD18+Data!AE18+Data!AF18+Data!AG18+Data!AH18+Data!AI18+Data!AJ18+Data!AK18+Data!AL18+Data!T19+Data!U19+Data!V19+Data!W19+Data!X19+Data!Y19+Data!Z19+Data!AA19+Data!AB19+Data!AC19+Data!AD19+Data!AE19+Data!AF19+Data!AG19+Data!AH19+Data!AI19+Data!AJ19+Data!AK19+Data!AL19+Data!T20+Data!U20+Data!V20+Data!W20+Data!X20+Data!Y20+Data!Z20+Data!AA20+Data!AB20+Data!AC20+Data!AD20+Data!AE20+Data!AF20+Data!AG20+Data!AH20+Data!AI20+Data!AJ20+Data!AK20+Data!AL20+Data!T21+Data!U21+Data!V21+Data!W21+Data!X21+Data!Y21+Data!Z21+Data!AA21+Data!AB21+Data!AC21+Data!AD21+Data!AE21+Data!AF21+Data!AG21+Data!AH21+Data!AI21+Data!AJ21+Data!AK21+Data!AL21 -> 2104824 | N21: =Data!T10+Data!U10+Data!V10+Data!W10+Data!T11+Data!U11+Data!V11+Data!W11+Data!T12+Data!U12+Data!V12+Data!W12+Data!T13+Data!U13+Data!V13+Data!W13+Data!T14+Data!U14+Data!V14+Data!W14+Data!T15+Data!U15+Data!V15+Data!W15+Data!T16+Data!U16+Data!V16+Data!W16+Data!T17+Data!U17+Data!V17+Data!W17+Data!T18+Data!U18+Data!V18+Data!W18+Data!T19+Data!U19+Data!V19+Data!W19+Data!T20+Data!U20+Data!V20+Data!W20+Data!T21+Data!U21+Data!V21+Data!W21 -> 1005468 | O21: =Data!T10+Data!T11+Data!T12+Data!T13+Data!T14+Data!T15+Data!T16+Data!T17+Data!T18+Data!T19+Data!T20+Data!T21 -> 711955 | P21: =Data!U10+Data!U11+Data!U12+Data!U13+Data!U14+Data!U15+Data!U16+Data!U17+Data!U18+Data!U19+Data!U20+Data!U21 -> 120789 | Q21: =Data!V10+Data!V11+Data!V12+Data!V13+Data!V14+Data!V15+Data!V16+Data!V17+Data!V18+Data!V19+Data!V20+Data!V21 -> 85396 | R21: =Data!W10+Data!W11+Data!W12+Data!W13+Data!W14+Data!W15+Data!W16+Data!W17+Data!W18+Data!W19+Data!W20+Data!W21 -> 87328 | S21: =Data!X10+Data!X11+Data!X12+Data!X13+Data!X14+Data!X15+Data!X16+Data!X17+Data!X18+Data!X19+Data!X20+Data!X21 -> 32241 | T21: =Data!Y10+Data!Z10+Data!AA10+Data!Y11+Data!Z11+Data!AA11+Data!Y12+Data!Z12+Data!AA12+Data!Y13+Data!Z13+Data!AA13+Data!Y14+Data!Z14+Data!AA14+Data!Y15+Data!Z15+Data!AA15+Data!Y16+Data!Z16+Data!AA16+Data!Y17+Data!Z17+Data!AA17+Data!Y18+Data!Z18+Data!AA18+Data!Y19+Data!Z19+Data!AA19+Data!Y20+Data!Z20+Data!AA20+Data!Y21+Data!Z21+Data!AA21 -> 291135 | U21: =Data!Y10+Data!Y11+Data!Y12+Data!Y13+Data!Y14+Data!Y15+Data!Y16+Data!Y17+Data!Y18+Data!Y19+Data!Y20+Data!Y21 -> 205123 | V21: =Data!Z10+Data!Z11+Data!Z12+Data!Z13+Data!Z14+Data!Z15+Data!Z16+Data!Z17+Data!Z18+Data!Z19+Data!Z20+Data!Z21 -> 83172 | W21: =Data!AB10+Data!AB11+Data!AB12+Data!AB13+Data!AB14+Data!AB15+Data!AB16+Data!AB17+Data!AB18+Data!AB19+Data!AB20+Data!AB21 -> 284795 | X21: =Data!AC10+Data!AC11+Data!AC12+Data!AC13+Data!AC14+Data!AC15+Data!AC16+Data!AC17+Data!AC18+Data!AC19+Data!AC20+Data!AC21 -> 84367 | Y21: =Data!AD10+Data!AE10+Data!AF10+Data!AG10+Data!AH10+Data!AD11+Data!AE11+Data!AF11+Data!AG11+Data!AH11+Data!AD12+Data!AE12+Data!AF12+Data!AG12+Data!AH12+Data!AD13+Data!AE13+Data!AF13+Data!AG13+Data!AH13+Data!AD14+Data!AE14+Data!AF14+Data!AG14+Data!AH14+Data!AD15+Data!AE15+Data!AF15+Data!AG15+Data!AH15+Data!AD16+Data!AE16+Data!AF16+Data!AG16+Data!AH16+Data!AD17+Data!AE17+Data!AF17+Data!AG17+Data!AH17+Data!AD18+Data!AE18+Data!AF18+Data!AG18+Data!AH18+Data!AD19+Data!AE19+Data!AF19+Data!AG19+Data!AH19+Data!AD20+Data!AE20+Data!AF20+Data!AG20+Data!AH20+Data!AD21+Data!AE21+Data!AF21+Data!AG21+Data!AH21 -> 83239 | Z21: =Data!AI10+Data!AI11+Data!AI12+Data!AI13+Data!AI14+Data!AI15+Data!AI16+Data!AI17+Data!AI18+Data!AI19+Data!AI20+Data!AI21 -> 68511 | AA21: =Data!AJ10+Data!AJ11+Data!AJ12+Data!AJ13+Data!AJ14+Data!AJ15+Data!AJ16+Data!AJ17+Data!AJ18+Data!AJ19+Data!AJ20+Data!AJ21 -> 5627 | AB21: =Data!AK10+Data!AK11+Data!AK12+Data!AK13+Data!AK14+Data!AK15+Data!AK16+Data!AK17+Data!AK18+Data!AK19+Data!AK20+Data!AK21 -> 53422 | AC21: =Data!AL10+Data!AL11+Data!AL12+Data!AL13+Data!AL14+Data!AL15+Data!AL16+Data!AL17+Data!AL18+Data!AL19+Data!AL20+Data!AL21 -> 196019 | AD21: =Data!AM10+Data!AM11+Data!AM12+Data!AM13+Data!AM14+Data!AM15+Data!AM16+Data!AM17+Data!AM18+Data!AM19+Data!AM20+Data!AM21 -> -338955 | AE21: =Data!AN10+Data!AN11+Data!AN12+Data!AN13+Data!AN14+Data!AN15+Data!AN16+Data!AN17+Data!AN18+Data!AN19+Data!AN20+Data!AN21 -> 141900 | AF21: =Data!AO10+Data!AO11+Data!AO12+Data!AO13+Data!AO14+Data!AO15+Data!AO16+Data!AO17+Data!AO18+Data!AO19+Data!AO20+Data!AO21 -> -480856
B22: =Data!B22 -> 2017-04 | C22: =Data!D11+Data!E11+Data!F11+Data!G11+Data!H11+Data!I11+Data!J11+Data!K11+Data!L11+Data!M11+Data!N11+Data!O11+Data!P11+Data!Q11+Data!R11+Data!S11+Data!D12+Data!E12+Data!F12+Data!G12+Data!H12+Data!I12+Data!J12+Data!K12+Data!L12+Data!M12+Data!N12+Data!O12+Data!P12+Data!Q12+Data!R12+Data!S12+Data!D13+Data!E13+Data!F13+Data!G13+Data!H13+Data!I13+Data!J13+Data!K13+Data!L13+Data!M13+Data!N13+Data!O13+Data!P13+Data!Q13+Data!R13+Data!S13+Data!D14+Data!E14+Data!F14+Data!G14+Data!H14+Data!I14+Data!J14+Data!K14+Data!L14+Data!M14+Data!N14+Data!O14+Data!P14+Data!Q14+Data!R14+Data!S14+Data!D15+Data!E15+Data!F15+Data!G15+Data!H15+Data!I15+Data!J15+Data!K15+Data!L15+Data!M15+Data!N15+Data!O15+Data!P15+Data!Q15+Data!R15+Data!S15+Data!D16+Data!E16+Data!F16+Data!G16+Data!H16+Data!I16+Data!J16+Data!K16+Data!L16+Data!M16+Data!N16+Data!O16+Data!P16+Data!Q16+Data!R16+Data!S16+Data!D17+Data!E17+Data!F17+Data!G17+Data!H17+Data!I17+Data!J17+Data!K17+Data!L17+Data!M17+Data!N17+Data!O17+Data!P17+Data!Q17+Data!R17+Data!S17+Data!D18+Data!E18+Data!F18+Data!G18+Data!H18+Data!I18+Data!J18+Data!K18+Data!L18+Data!M18+Data!N18+Data!O18+Data!P18+Data!Q18+Data!R18+Data!S18+Data!D19+Data!E19+Data!F19+Data!G19+Data!H19+Data!I19+Data!J19+Data!K19+Data!L19+Data!M19+Data!N19+Data!O19+Data!P19+Data!Q19+Data!R19+Data!S19+Data!D20+Data!E20+Data!F20+Data!G20+Data!H20+Data!I20+Data!J20+Data!K20+Data!L20+Data!M20+Data!N20+Data!O20+Data!P20+Data!Q20+Data!R20+Data!S20+Data!D21+Data!E21+Data!F21+Data!G21+Data!H21+Data!I21+Data!J21+Data!K21+Data!L21+Data!M21+Data!N21+Data!O21+Data!P21+Data!Q21+Data!R21+Data!S21+Data!D22+Data!E22+Data!F22+Data!G22+Data!H22+Data!I22+Data!J22+Data!K22+Data!L22+Data!M22+Data!N22+Data!O22+Data!P22+Data!Q22+Data!R22+Data!S22 -> 1807280 | D22: =Data!D11+Data!E11+Data!G11+Data!H11+Data!I11+Data!J11+Data!K11+Data!L11+Data!M11+Data!D12+Data!E12+Data!G12+Data!H12+Data!I12+Data!J12+Data!K12+Data!L12+Data!M12+Data!D13+Data!E13+Data!G13+Data!H13+Data!I13+Data!J13+Data!K13+Data!L13+Data!M13+Data!D14+Data!E14+Data!G14+Data!H14+Data!I14+Data!J14+Data!K14+Data!L14+Data!M14+Data!D15+Data!E15+Data!G15+Data!H15+Data!I15+Data!J15+Data!K15+Data!L15+Data!M15+Data!D16+Data!E16+Data!G16+Data!H16+Data!I16+Data!J16+Data!K16+Data!L16+Data!M16+Data!D17+Data!E17+Data!G17+Data!H17+Data!I17+Data!J17+Data!K17+Data!L17+Data!M17+Data!D18+Data!E18+Data!G18+Data!H18+Data!I18+Data!J18+Data!K18+Data!L18+Data!M18+Data!D19+Data!E19+Data!G19+Data!H19+Data!I19+Data!J19+Data!K19+Data!L19+Data!M19+Data!D20+Data!E20+Data!G20+Data!H20+Data!I20+Data!J20+Data!K20+Data!L20+Data!M20+Data!D21+Data!E21+Data!G21+Data!H21+Data!I21+Data!J21+Data!K21+Data!L21+Data!M21+Data!D22+Data!E22+Data!G22+Data!H22+Data!I22+Data!J22+Data!K22+Data!L22+Data!M22 -> 1071738 | E22: =Data!D11+Data!D12+Data!D13+Data!D14+Data!D15+Data!D16+Data!D17+Data!D18+Data!D19+Data!D20+Data!D21+Data!D22 -> 293746 | F22: =Data!E11+Data!E12+Data!E13+Data!E14+Data!E15+Data!E16+Data!E17+Data!E18+Data!E19+Data!E20+Data!E21+Data!E22 -> 232828 | G22: =Data!K11+Data!K12+Data!K13+Data!K14+Data!K15+Data!K16+Data!K17+Data!K18+Data!K19+Data!K20+Data!K21+Data!K22 -> 66747 | H22: =Data!L11+Data!L12+Data!L13+Data!L14+Data!L15+Data!L16+Data!L17+Data!L18+Data!L19+Data!L20+Data!L21+Data!L22 -> 57750 | I22: =Data!G11+Data!G12+Data!G13+Data!G14+Data!G15+Data!G16+Data!G17+Data!G18+Data!G19+Data!G20+Data!G21+Data!G22 -> 119782 | J22: =Data!H11+Data!I11+Data!J11+Data!M11+Data!H12+Data!I12+Data!J12+Data!M12+Data!H13+Data!I13+Data!J13+Data!M13+Data!H14+Data!I14+Data!J14+Data!M14+Data!H15+Data!I15+Data!J15+Data!M15+Data!H16+Data!I16+Data!J16+Data!M16+Data!H17+Data!I17+Data!J17+Data!M17+Data!H18+Data!I18+Data!J18+Data!M18+Data!H19+Data!I19+Data!J19+Data!M19+Data!H20+Data!I20+Data!J20+Data!M20+Data!H21+Data!I21+Data!J21+Data!M21+Data!H22+Data!I22+Data!J22+Data!M22 -> 300885 | K22: =Data!F11+Data!F12+Data!F13+Data!F14+Data!F15+Data!F16+Data!F17+Data!F18+Data!F19+Data!F20+Data!F21+Data!F22 -> 619142 | L22: =Data!N11+Data!O11+Data!P11+Data!Q11+Data!R11+Data!S11+Data!N12+Data!O12+Data!P12+Data!Q12+Data!R12+Data!S12+Data!N13+Data!O13+Data!P13+Data!Q13+Data!R13+Data!S13+Data!N14+Data!O14+Data!P14+Data!Q14+Data!R14+Data!S14+Data!N15+Data!O15+Data!P15+Data!Q15+Data!R15+Data!S15+Data!N16+Data!O16+Data!P16+Data!Q16+Data!R16+Data!S16+Data!N17+Data!O17+Data!P17+Data!Q17+Data!R17+Data!S17+Data!N18+Data!O18+Data!P18+Data!Q18+Data!R18+Data!S18+Data!N19+Data!O19+Data!P19+Data!Q19+Data!R19+Data!S19+Data!N20+Data!O20+Data!P20+Data!Q20+Data!R20+Data!S20+Data!N21+Data!O21+Data!P21+Data!Q21+Data!R21+Data!S21+Data!N22+Data!O22+Data!P22+Data!Q22+Data!R22+Data!S22 -> 116400 | M22: =Data!T11+Data!U11+Data!V11+Data!W11+Data!X11+Data!Y11+Data!Z11+Data!AA11+Data!AB11+Data!AC11+Data!AD11+Data!AE11+Data!AF11+Data!AG11+Data!AH11+Data!AI11+Data!AJ11+Data!AK11+Data!AL11+Data!T12+Data!U12+Data!V12+Data!W12+Data!X12+Data!Y12+Data!Z12+Data!AA12+Data!AB12+Data!AC12+Data!AD12+Data!AE12+Data!AF12+Data!AG12+Data!AH12+Data!AI12+Data!AJ12+Data!AK12+Data!AL12+Data!T13+Data!U13+Data!V13+Data!W13+Data!X13+Data!Y13+Data!Z13+Data!AA13+Data!AB13+Data!AC13+Data!AD13+Data!AE13+Data!AF13+Data!AG13+Data!AH13+Data!AI13+Data!AJ13+Data!AK13+Data!AL13+Data!T14+Data!U14+Data!V14+Data!W14+Data!X14+Data!Y14+Data!Z14+Data!AA14+Data!AB14+Data!AC14+Data!AD14+Data!AE14+Data!AF14+Data!AG14+Data!AH14+Data!AI14+Data!AJ14+Data!AK14+Data!AL14+Data!T15+Data!U15+Data!V15+Data!W15+Data!X15+Data!Y15+Data!Z15+Data!AA15+Data!AB15+Data!AC15+Data!AD15+Data!AE15+Data!AF15+Data!AG15+Data!AH15+Data!AI15+Data!AJ15+Data!AK15+Data!AL15+Data!T16+Data!U16+Data!V16+Data!W16+Data!X16+Data!Y16+Data!Z16+Data!AA16+Data!AB16+Data!AC16+Data!AD16+Data!AE16+Data!AF16+Data!AG16+Data!AH16+Data!AI16+Data!AJ16+Data!AK16+Data!AL16+Data!T17+Data!U17+Data!V17+Data!W17+Data!X17+Data!Y17+Data!Z17+Data!AA17+Data!AB17+Data!AC17+Data!AD17+Data!AE17+Data!AF17+Data!AG17+Data!AH17+Data!AI17+Data!AJ17+Data!AK17+Data!AL17+Data!T18+Data!U18+Data!V18+Data!W18+Data!X18+Data!Y18+Data!Z18+Data!AA18+Data!AB18+Data!AC18+Data!AD18+Data!AE18+Data!AF18+Data!AG18+Data!AH18+Data!AI18+Data!AJ18+Data!AK18+Data!AL18+Data!T19+Data!U19+Data!V19+Data!W19+Data!X19+Data!Y19+Data!Z19+Data!AA19+Data!AB19+Data!AC19+Data!AD19+Data!AE19+Data!AF19+Data!AG19+Data!AH19+Data!AI19+Data!AJ19+Data!AK19+Data!AL19+Data!T20+Data!U20+Data!V20+Data!W20+Data!X20+Data!Y20+Data!Z20+Data!AA20+Data!AB20+Data!AC20+Data!AD20+Data!AE20+Data!AF20+Data!AG20+Data!AH20+Data!AI20+Data!AJ20+Data!AK20+Data!AL20+Data!T21+Data!U21+Data!V21+Data!W21+Data!X21+Data!Y21+Data!Z21+Data!AA21+Data!AB21+Data!AC21+Data!AD21+Data!AE21+Data!AF21+Data!AG21+Data!AH21+Data!AI21+Data!AJ21+Data!AK21+Data!AL21+Data!T22+Data!U22+Data!V22+Data!W22+Data!X22+Data!Y22+Data!Z22+Data!AA22+Data!AB22+Data!AC22+Data!AD22+Data!AE22+Data!AF22+Data!AG22+Data!AH22+Data!AI22+Data!AJ22+Data!AK22+Data!AL22 -> 2154006 | N22: =Data!T11+Data!U11+Data!V11+Data!W11+Data!T12+Data!U12+Data!V12+Data!W12+Data!T13+Data!U13+Data!V13+Data!W13+Data!T14+Data!U14+Data!V14+Data!W14+Data!T15+Data!U15+Data!V15+Data!W15+Data!T16+Data!U16+Data!V16+Data!W16+Data!T17+Data!U17+Data!V17+Data!W17+Data!T18+Data!U18+Data!V18+Data!W18+Data!T19+Data!U19+Data!V19+Data!W19+Data!T20+Data!U20+Data!V20+Data!W20+Data!T21+Data!U21+Data!V21+Data!W21+Data!T22+Data!U22+Data!V22+Data!W22 -> 1028553 | O22: =Data!T11+Data!T12+Data!T13+Data!T14+Data!T15+Data!T16+Data!T17+Data!T18+Data!T19+Data!T20+Data!T21+Data!T22 -> 729346 | P22: =Data!U11+Data!U12+Data!U13+Data!U14+Data!U15+Data!U16+Data!U17+Data!U18+Data!U19+Data!U20+Data!U21+Data!U22 -> 123286 | Q22: =Data!V11+Data!V12+Data!V13+Data!V14+Data!V15+Data!V16+Data!V17+Data!V18+Data!V19+Data!V20+Data!V21+Data!V22 -> 86784 | R22: =Data!W11+Data!W12+Data!W13+Data!W14+Data!W15+Data!W16+Data!W17+Data!W18+Data!W19+Data!W20+Data!W21+Data!W22 -> 89137 | S22: =Data!X11+Data!X12+Data!X13+Data!X14+Data!X15+Data!X16+Data!X17+Data!X18+Data!X19+Data!X20+Data!X21+Data!X22 -> 32118 | T22: =Data!Y11+Data!Z11+Data!AA11+Data!Y12+Data!Z12+Data!AA12+Data!Y13+Data!Z13+Data!AA13+Data!Y14+Data!Z14+Data!AA14+Data!Y15+Data!Z15+Data!AA15+Data!Y16+Data!Z16+Data!AA16+Data!Y17+Data!Z17+Data!AA17+Data!Y18+Data!Z18+Data!AA18+Data!Y19+Data!Z19+Data!AA19+Data!Y20+Data!Z20+Data!AA20+Data!Y21+Data!Z21+Data!AA21+Data!Y22+Data!Z22+Data!AA22 -> 294833 | U22: =Data!Y11+Data!Y12+Data!Y13+Data!Y14+Data!Y15+Data!Y16+Data!Y17+Data!Y18+Data!Y19+Data!Y20+Data!Y21+Data!Y22 -> 206357 | V22: =Data!Z11+Data!Z12+Data!Z13+Data!Z14+Data!Z15+Data!Z16+Data!Z17+Data!Z18+Data!Z19+Data!Z20+Data!Z21+Data!Z22 -> 85023 | W22: =Data!AB11+Data!AB12+Data!AB13+Data!AB14+Data!AB15+Data!AB16+Data!AB17+Data!AB18+Data!AB19+Data!AB20+Data!AB21+Data!AB22 -> 291598 | X22: =Data!AC11+Data!AC12+Data!AC13+Data!AC14+Data!AC15+Data!AC16+Data!AC17+Data!AC18+Data!AC19+Data!AC20+Data!AC21+Data!AC22 -> 86764 | Y22: =Data!AD11+Data!AE11+Data!AF11+Data!AG11+Data!AH11+Data!AD12+Data!AE12+Data!AF12+Data!AG12+Data!AH12+Data!AD13+Data!AE13+Data!AF13+Data!AG13+Data!AH13+Data!AD14+Data!AE14+Data!AF14+Data!AG14+Data!AH14+Data!AD15+Data!AE15+Data!AF15+Data!AG15+Data!AH15+Data!AD16+Data!AE16+Data!AF16+Data!AG16+Data!AH16+Data!AD17+Data!AE17+Data!AF17+Data!AG17+Data!AH17+Data!AD18+Data!AE18+Data!AF18+Data!AG18+Data!AH18+Data!AD19+Data!AE19+Data!AF19+Data!AG19+Data!AH19+Data!AD20+Data!AE20+Data!AF20+Data!AG20+Data!AH20+Data!AD21+Data!AE21+Data!AF21+Data!AG21+Data!AH21+Data!AD22+Data!AE22+Data!AF22+Data!AG22+Data!AH22 -> 85113 | Z22: =Data!AI11+Data!AI12+Data!AI13+Data!AI14+Data!AI15+Data!AI16+Data!AI17+Data!AI18+Data!AI19+Data!AI20+Data!AI21+Data!AI22 -> 70402 | AA22: =Data!AJ11+Data!AJ12+Data!AJ13+Data!AJ14+Data!AJ15+Data!AJ16+Data!AJ17+Data!AJ18+Data!AJ19+Data!AJ20+Data!AJ21+Data!AJ22 -> 6374 | AB22: =Data!AK11+Data!AK12+Data!AK13+Data!AK14+Data!AK15+Data!AK16+Data!AK17+Data!AK18+Data!AK19+Data!AK20+Data!AK21+Data!AK22 -> 54207 | AC22: =Data!AL11+Data!AL12+Data!AL13+Data!AL14+Data!AL15+Data!AL16+Data!AL17+Data!AL18+Data!AL19+Data!AL20+Data!AL21+Data!AL22 -> 204044 | AD22: =Data!AM11+Data!AM12+Data!AM13+Data!AM14+Data!AM15+Data!AM16+Data!AM17+Data!AM18+Data!AM19+Data!AM20+Data!AM21+Data!AM22 -> -346726 | AE22: =Data!AN11+Data!AN12+Data!AN13+Data!AN14+Data!AN15+Data!AN16+Data!AN17+Data!AN18+Data!AN19+Data!AN20+Data!AN21+Data!AN22 -> 166067 | AF22: =Data!AO11+Data!AO12+Data!AO13+Data!AO14+Data!AO15+Data!AO16+Data!AO17+Data!AO18+Data!AO19+Data!AO20+Data!AO21+Data!AO22 -> -512793
B23: =Data!B23 -> 2017-05 | C23: =Data!D12+Data!E12+Data!F12+Data!G12+Data!H12+Data!I12+Data!J12+Data!K12+Data!L12+Data!M12+Data!N12+Data!O12+Data!P12+Data!Q12+Data!R12+Data!S12+Data!D13+Data!E13+Data!F13+Data!G13+Data!H13+Data!I13+Data!J13+Data!K13+Data!L13+Data!M13+Data!N13+Data!O13+Data!P13+Data!Q13+Data!R13+Data!S13+Data!D14+Data!E14+Data!F14+Data!G14+Data!H14+Data!I14+Data!J14+Data!K14+Data!L14+Data!M14+Data!N14+Data!O14+Data!P14+Data!Q14+Data!R14+Data!S14+Data!D15+Data!E15+Data!F15+Data!G15+Data!H15+Data!I15+Data!J15+Data!K15+Data!L15+Data!M15+Data!N15+Data!O15+Data!P15+Data!Q15+Data!R15+Data!S15+Data!D16+Data!E16+Data!F16+Data!G16+Data!H16+Data!I16+Data!J16+Data!K16+Data!L16+Data!M16+Data!N16+Data!O16+Data!P16+Data!Q16+Data!R16+Data!S16+Data!D17+Data!E17+Data!F17+Data!G17+Data!H17+Data!I17+Data!J17+Data!K17+Data!L17+Data!M17+Data!N17+Data!O17+Data!P17+Data!Q17+Data!R17+Data!S17+Data!D18+Data!E18+Data!F18+Data!G18+Data!H18+Data!I18+Data!J18+Data!K18+Data!L18+Data!M18+Data!N18+Data!O18+Data!P18+Data!Q18+Data!R18+Data!S18+Data!D19+Data!E19+Data!F19+Data!G19+Data!H19+Data!I19+Data!J19+Data!K19+Data!L19+Data!M19+Data!N19+Data!O19+Data!P19+Data!Q19+Data!R19+Data!S19+Data!D20+Data!E20+Data!F20+Data!G20+Data!H20+Data!I20+Data!J20+Data!K20+Data!L20+Data!M20+Data!N20+Data!O20+Data!P20+Data!Q20+Data!R20+Data!S20+Data!D21+Data!E21+Data!F21+Data!G21+Data!H21+Data!I21+Data!J21+Data!K21+Data!L21+Data!M21+Data!N21+Data!O21+Data!P21+Data!Q21+Data!R21+Data!S21+Data!D22+Data!E22+Data!F22+Data!G22+Data!H22+Data!I22+Data!J22+Data!K22+Data!L22+Data!M22+Data!N22+Data!O22+Data!P22+Data!Q22+Data!R22+Data!S22+Data!D23+Data!E23+Data!F23+Data!G23+Data!H23+Data!I23+Data!J23+Data!K23+Data!L23+Data!M23+Data!N23+Data!O23+Data!P23+Data!Q23+Data!R23+Data!S23 -> 1827192 | D23: =Data!D12+Data!E12+Data!G12+Data!H12+Data!I12+Data!J12+Data!K12+Data!L12+Data!M12+Data!D13+Data!E13+Data!G13+Data!H13+Data!I13+Data!J13+Data!K13+Data!L13+Data!M13+Data!D14+Data!E14+Data!G14+Data!H14+Data!I14+Data!J14+Data!K14+Data!L14+Data!M14+Data!D15+Data!E15+Data!G15+Data!H15+Data!I15+Data!J15+Data!K15+Data!L15+Data!M15+Data!D16+Data!E16+Data!G16+Data!H16+Data!I16+Data!J16+Data!K16+Data!L16+Data!M16+Data!D17+Data!E17+Data!G17+Data!H17+Data!I17+Data!J17+Data!K17+Data!L17+Data!M17+Data!D18+Data!E18+Data!G18+Data!H18+Data!I18+Data!J18+Data!K18+Data!L18+Data!M18+Data!D19+Data!E19+Data!G19+Data!H19+Data!I19+Data!J19+Data!K19+Data!L19+Data!M19+Data!D20+Data!E20+Data!G20+Data!H20+Data!I20+Data!J20+Data!K20+Data!L20+Data!M20+Data!D21+Data!E21+Data!G21+Data!H21+Data!I21+Data!J21+Data!K21+Data!L21+Data!M21+Data!D22+Data!E22+Data!G22+Data!H22+Data!I22+Data!J22+Data!K22+Data!L22+Data!M22+Data!D23+Data!E23+Data!G23+Data!H23+Data!I23+Data!J23+Data!K23+Data!L23+Data!M23 -> 1074880 | E23: =Data!D12+Data!D13+Data!D14+Data!D15+Data!D16+Data!D17+Data!D18+Data!D19+Data!D20+Data!D21+Data!D22+Data!D23 -> 293740 | F23: =Data!E12+Data!E13+Data!E14+Data!E15+Data!E16+Data!E17+Data!E18+Data!E19+Data!E20+Data!E21+Data!E22+Data!E23 -> 232550 | G23: =Data!K12+Data!K13+Data!K14+Data!K15+Data!K16+Data!K17+Data!K18+Data!K19+Data!K20+Data!K21+Data!K22+Data!K23 -> 64710 | H23: =Data!L12+Data!L13+Data!L14+Data!L15+Data!L16+Data!L17+Data!L18+Data!L19+Data!L20+Data!L21+Data!L22+Data!L23 -> 58153 | I23: =Data!G12+Data!G13+Data!G14+Data!G15+Data!G16+Data!G17+Data!G18+Data!G19+Data!G20+Data!G21+Data!G22+Data!G23 -> 121621 | J23: =Data!H12+Data!I12+Data!J12+Data!M12+Data!H13+Data!I13+Data!J13+Data!M13+Data!H14+Data!I14+Data!J14+Data!M14+Data!H15+Data!I15+Data!J15+Data!M15+Data!H16+Data!I16+Data!J16+Data!M16+Data!H17+Data!I17+Data!J17+Data!M17+Data!H18+Data!I18+Data!J18+Data!M18+Data!H19+Data!I19+Data!J19+Data!M19+Data!H20+Data!I20+Data!J20+Data!M20+Data!H21+Data!I21+Data!J21+Data!M21+Data!H22+Data!I22+Data!J22+Data!M22+Data!H23+Data!I23+Data!J23+Data!M23 -> 304106 | K23: =Data!F12+Data!F13+Data!F14+Data!F15+Data!F16+Data!F17+Data!F18+Data!F19+Data!F20+Data!F21+Data!F22+Data!F23 -> 633744 | L23: =Data!N12+Data!O12+Data!P12+Data!Q12+Data!R12+Data!S12+Data!N13+Data!O13+Data!P13+Data!Q13+Data!R13+Data!S13+Data!N14+Data!O14+Data!P14+Data!Q14+Data!R14+Data!S14+Data!N15+Data!O15+Data!P15+Data!Q15+Data!R15+Data!S15+Data!N16+Data!O16+Data!P16+Data!Q16+Data!R16+Data!S16+Data!N17+Data!O17+Data!P17+Data!Q17+Data!R17+Data!S17+Data!N18+Data!O18+Data!P18+Data!Q18+Data!R18+Data!S18+Data!N19+Data!O19+Data!P19+Data!Q19+Data!R19+Data!S19+Data!N20+Data!O20+Data!P20+Data!Q20+Data!R20+Data!S20+Data!N21+Data!O21+Data!P21+Data!Q21+Data!R21+Data!S21+Data!N22+Data!O22+Data!P22+Data!Q22+Data!R22+Data!S22+Data!N23+Data!O23+Data!P23+Data!Q23+Data!R23+Data!S23 -> 118568 | M23: =Data!T12+Data!U12+Data!V12+Data!W12+Data!X12+Data!Y12+Data!Z12+Data!AA12+Data!AB12+Data!AC12+Data!AD12+Data!AE12+Data!AF12+Data!AG12+Data!AH12+Data!AI12+Data!AJ12+Data!AK12+Data!AL12+Data!T13+Data!U13+Data!V13+Data!W13+Data!X13+Data!Y13+Data!Z13+Data!AA13+Data!AB13+Data!AC13+Data!AD13+Data!AE13+Data!AF13+Data!AG13+Data!AH13+Data!AI13+Data!AJ13+Data!AK13+Data!AL13+Data!T14+Data!U14+Data!V14+Data!W14+Data!X14+Data!Y14+Data!Z14+Data!AA14+Data!AB14+Data!AC14+Data!AD14+Data!AE14+Data!AF14+Data!AG14+Data!AH14+Data!AI14+Data!AJ14+Data!AK14+Data!AL14+Data!T15+Data!U15+Data!V15+Data!W15+Data!X15+Data!Y15+Data!Z15+Data!AA15+Data!AB15+Data!AC15+Data!AD15+Data!AE15+Data!AF15+Data!AG15+Data!AH15+Data!AI15+Data!AJ15+Data!AK15+Data!AL15+Data!T16+Data!U16+Data!V16+Data!W16+Data!X16+Data!Y16+Data!Z16+Data!AA16+Data!AB16+Data!AC16+Data!AD16+Data!AE16+Data!AF16+Data!AG16+Data!AH16+Data!AI16+Data!AJ16+Data!AK16+Data!AL16+Data!T17+Data!U17+Data!V17+Data!W17+Data!X17+Data!Y17+Data!Z17+Data!AA17+Data!AB17+Data!AC17+Data!AD17+Data!AE17+Data!AF17+Data!AG17+Data!AH17+Data!AI17+Data!AJ17+Data!AK17+Data!AL17+Data!T18+Data!U18+Data!V18+Data!W18+Data!X18+Data!Y18+Data!Z18+Data!AA18+Data!AB18+Data!AC18+Data!AD18+Data!AE18+Data!AF18+Data!AG18+Data!AH18+Data!AI18+Data!AJ18+Data!AK18+Data!AL18+Data!T19+Data!U19+Data!V19+Data!W19+Data!X19+Data!Y19+Data!Z19+Data!AA19+Data!AB19+Data!AC19+Data!AD19+Data!AE19+Data!AF19+Data!AG19+Data!AH19+Data!AI19+Data!AJ19+Data!AK19+Data!AL19+Data!T20+Data!U20+Data!V20+Data!W20+Data!X20+Data!Y20+Data!Z20+Data!AA20+Data!AB20+Data!AC20+Data!AD20+Data!AE20+Data!AF20+Data!AG20+Data!AH20+Data!AI20+Data!AJ20+Data!AK20+Data!AL20+Data!T21+Data!U21+Data!V21+Data!W21+Data!X21+Data!Y21+Data!Z21+Data!AA21+Data!AB21+Data!AC21+Data!AD21+Data!AE21+Data!AF21+Data!AG21+Data!AH21+Data!AI21+Data!AJ21+Data!AK21+Data!AL21+Data!T22+Data!U22+Data!V22+Data!W22+Data!X22+Data!Y22+Data!Z22+Data!AA22+Data!AB22+Data!AC22+Data!AD22+Data!AE22+Data!AF22+Data!AG22+Data!AH22+Data!AI22+Data!AJ22+Data!AK22+Data!AL22+Data!T23+Data!U23+Data!V23+Data!W23+Data!X23+Data!Y23+Data!Z23+Data!AA23+Data!AB23+Data!AC23+Data!AD23+Data!AE23+Data!AF23+Data!AG23+Data!AH23+Data!AI23+Data!AJ23+Data!AK23+Data!AL23 -> 2189183 | N23: =Data!T12+Data!U12+Data!V12+Data!W12+Data!T13+Data!U13+Data!V13+Data!W13+Data!T14+Data!U14+Data!V14+Data!W14+Data!T15+Data!U15+Data!V15+Data!W15+Data!T16+Data!U16+Data!V16+Data!W16+Data!T17+Data!U17+Data!V17+Data!W17+Data!T18+Data!U18+Data!V18+Data!W18+Data!T19+Data!U19+Data!V19+Data!W19+Data!T20+Data!U20+Data!V20+Data!W20+Data!T21+Data!U21+Data!V21+Data!W21+Data!T22+Data!U22+Data!V22+Data!W22+Data!T23+Data!U23+Data!V23+Data!W23 -> 1054188 | O23: =Data!T12+Data!T13+Data!T14+Data!T15+Data!T16+Data!T17+Data!T18+Data!T19+Data!T20+Data!T21+Data!T22+Data!T23 -> 750380 | P23: =Data!U12+Data!U13+Data!U14+Data!U15+Data!U16+Data!U17+Data!U18+Data!U19+Data!U20+Data!U21+Data!U22+Data!U23 -> 124732 | Q23: =Data!V12+Data!V13+Data!V14+Data!V15+Data!V16+Data!V17+Data!V18+Data!V19+Data!V20+Data!V21+Data!V22+Data!V23 -> 87958 | R23: =Data!W12+Data!W13+Data!W14+Data!W15+Data!W16+Data!W17+Data!W18+Data!W19+Data!W20+Data!W21+Data!W22+Data!W23 -> 91118 | S23: =Data!X12+Data!X13+Data!X14+Data!X15+Data!X16+Data!X17+Data!X18+Data!X19+Data!X20+Data!X21+Data!X22+Data!X23 -> 32414 | T23: =Data!Y12+Data!Z12+Data!AA12+Data!Y13+Data!Z13+Data!AA13+Data!Y14+Data!Z14+Data!AA14+Data!Y15+Data!Z15+Data!AA15+Data!Y16+Data!Z16+Data!AA16+Data!Y17+Data!Z17+Data!AA17+Data!Y18+Data!Z18+Data!AA18+Data!Y19+Data!Z19+Data!AA19+Data!Y20+Data!Z20+Data!AA20+Data!Y21+Data!Z21+Data!AA21+Data!Y22+Data!Z22+Data!AA22+Data!Y23+Data!Z23+Data!AA23 -> 291546 | U23: =Data!Y12+Data!Y13+Data!Y14+Data!Y15+Data!Y16+Data!Y17+Data!Y18+Data!Y19+Data!Y20+Data!Y21+Data!Y22+Data!Y23 -> 200980 | V23: =Data!Z12+Data!Z13+Data!Z14+Data!Z15+Data!Z16+Data!Z17+Data!Z18+Data!Z19+Data!Z20+Data!Z21+Data!Z22+Data!Z23 -> 86117 | W23: =Data!AB12+Data!AB13+Data!AB14+Data!AB15+Data!AB16+Data!AB17+Data!AB18+Data!AB19+Data!AB20+Data!AB21+Data!AB22+Data!AB23 -> 297989 | X23: =Data!AC12+Data!AC13+Data!AC14+Data!AC15+Data!AC16+Data!AC17+Data!AC18+Data!AC19+Data!AC20+Data!AC21+Data!AC22+Data!AC23 -> 89117 | Y23: =Data!AD12+Data!AE12+Data!AF12+Data!AG12+Data!AH12+Data!AD13+Data!AE13+Data!AF13+Data!AG13+Data!AH13+Data!AD14+Data!AE14+Data!AF14+Data!AG14+Data!AH14+Data!AD15+Data!AE15+Data!AF15+Data!AG15+Data!AH15+Data!AD16+Data!AE16+Data!AF16+Data!AG16+Data!AH16+Data!AD17+Data!AE17+Data!AF17+Data!AG17+Data!AH17+Data!AD18+Data!AE18+Data!AF18+Data!AG18+Data!AH18+Data!AD19+Data!AE19+Data!AF19+Data!AG19+Data!AH19+Data!AD20+Data!AE20+Data!AF20+Data!AG20+Data!AH20+Data!AD21+Data!AE21+Data!AF21+Data!AG21+Data!AH21+Data!AD22+Data!AE22+Data!AF22+Data!AG22+Data!AH22+Data!AD23+Data!AE23+Data!AF23+Data!AG23+Data!AH23 -> 86969 | Z23: =Data!AI12+Data!AI13+Data!AI14+Data!AI15+Data!AI16+Data!AI17+Data!AI18+Data!AI19+Data!AI20+Data!AI21+Data!AI22+Data!AI23 -> 72007 | AA23: =Data!AJ12+Data!AJ13+Data!AJ14+Data!AJ15+Data!AJ16+Data!AJ17+Data!AJ18+Data!AJ19+Data!AJ20+Data!AJ21+Data!AJ22+Data!AJ23 -> 5458 | AB23: =Data!AK12+Data!AK13+Data!AK14+Data!AK15+Data!AK16+Data!AK17+Data!AK18+Data!AK19+Data!AK20+Data!AK21+Data!AK22+Data!AK23 -> 52962 | AC23: =Data!AL12+Data!AL13+Data!AL14+Data!AL15+Data!AL16+Data!AL17+Data!AL18+Data!AL19+Data!AL20+Data!AL21+Data!AL22+Data!AL23 -> 206533 | AD23: =Data!AM12+Data!AM13+Data!AM14+Data!AM15+Data!AM16+Data!AM17+Data!AM18+Data!AM19+Data!AM20+Data!AM21+Data!AM22+Data!AM23 -> -361991 | AE23: =Data!AN12+Data!AN13+Data!AN14+Data!AN15+Data!AN16+Data!AN17+Data!AN18+Data!AN19+Data!AN20+Data!AN21+Data!AN22+Data!AN23 -> 170854 | AF23: =Data!AO12+Data!AO13+Data!AO14+Data!AO15+Data!AO16+Data!AO17+Data!AO18+Data!AO19+Data!AO20+Data!AO21+Data!AO22+Data!AO23 -> -532844
B24: =Data!B24 -> 2017-06 | C24: =Data!D13+Data!E13+Data!F13+Data!G13+Data!H13+Data!I13+Data!J13+Data!K13+Data!L13+Data!M13+Data!N13+Data!O13+Data!P13+Data!Q13+Data!R13+Data!S13+Data!D14+Data!E14+Data!F14+Data!G14+Data!H14+Data!I14+Data!J14+Data!K14+Data!L14+Data!M14+Data!N14+Data!O14+Data!P14+Data!Q14+Data!R14+Data!S14+Data!D15+Data!E15+Data!F15+Data!G15+Data!H15+Data!I15+Data!J15+Data!K15+Data!L15+Data!M15+Data!N15+Data!O15+Data!P15+Data!Q15+Data!R15+Data!S15+Data!D16+Data!E16+Data!F16+Data!G16+Data!H16+Data!I16+Data!J16+Data!K16+Data!L16+Data!M16+Data!N16+Data!O16+Data!P16+Data!Q16+Data!R16+Data!S16+Data!D17+Data!E17+Data!F17+Data!G17+Data!H17+Data!I17+Data!J17+Data!K17+Data!L17+Data!M17+Data!N17+Data!O17+Data!P17+Data!Q17+Data!R17+Data!S17+Data!D18+Data!E18+Data!F18+Data!G18+Data!H18+Data!I18+Data!J18+Data!K18+Data!L18+Data!M18+Data!N18+Data!O18+Data!P18+Data!Q18+Data!R18+Data!S18+Data!D19+Data!E19+Data!F19+Data!G19+Data!H19+Data!I19+Data!J19+Data!K19+Data!L19+Data!M19+Data!N19+Data!O19+Data!P19+Data!Q19+Data!R19+Data!S19+Data!D20+Data!E20+Data!F20+Data!G20+Data!H20+Data!I20+Data!J20+Data!K20+Data!L20+Data!M20+Data!N20+Data!O20+Data!P20+Data!Q20+Data!R20+Data!S20+Data!D21+Data!E21+Data!F21+Data!G21+Data!H21+Data!I21+Data!J21+Data!K21+Data!L21+Data!M21+Data!N21+Data!O21+Data!P21+Data!Q21+Data!R21+Data!S21+Data!D22+Data!E22+Data!F22+Data!G22+Data!H22+Data!I22+Data!J22+Data!K22+Data!L22+Data!M22+Data!N22+Data!O22+Data!P22+Data!Q22+Data!R22+Data!S22+Data!D23+Data!E23+Data!F23+Data!G23+Data!H23+Data!I23+Data!J23+Data!K23+Data!L23+Data!M23+Data!N23+Data!O23+Data!P23+Data!Q23+Data!R23+Data!S23+Data!D24+Data!E24+Data!F24+Data!G24+Data!H24+Data!I24+Data!J24+Data!K24+Data!L24+Data!M24+Data!N24+Data!O24+Data!P24+Data!Q24+Data!R24+Data!S24 -> 1858790 | D24: =Data!D13+Data!E13+Data!G13+Data!H13+Data!I13+Data!J13+Data!K13+Data!L13+Data!M13+Data!D14+Data!E14+Data!G14+Data!H14+Data!I14+Data!J14+Data!K14+Data!L14+Data!M14+Data!D15+Data!E15+Data!G15+Data!H15+Data!I15+Data!J15+Data!K15+Data!L15+Data!M15+Data!D16+Data!E16+Data!G16+Data!H16+Data!I16+Data!J16+Data!K16+Data!L16+Data!M16+Data!D17+Data!E17+Data!G17+Data!H17+Data!I17+Data!J17+Data!K17+Data!L17+Data!M17+Data!D18+Data!E18+Data!G18+Data!H18+Data!I18+Data!J18+Data!K18+Data!L18+Data!M18+Data!D19+Data!E19+Data!G19+Data!H19+Data!I19+Data!J19+Data!K19+Data!L19+Data!M19+Data!D20+Data!E20+Data!G20+Data!H20+Data!I20+Data!J20+Data!K20+Data!L20+Data!M20+Data!D21+Data!E21+Data!G21+Data!H21+Data!I21+Data!J21+Data!K21+Data!L21+Data!M21+Data!D22+Data!E22+Data!G22+Data!H22+Data!I22+Data!J22+Data!K22+Data!L22+Data!M22+Data!D23+Data!E23+Data!G23+Data!H23+Data!I23+Data!J23+Data!K23+Data!L23+Data!M23+Data!D24+Data!E24+Data!G24+Data!H24+Data!I24+Data!J24+Data!K24+Data!L24+Data!M24 -> 1092969 | E24: =Data!D13+Data!D14+Data!D15+Data!D16+Data!D17+Data!D18+Data!D19+Data!D20+Data!D21+Data!D22+Data!D23+Data!D24 -> 299710 | F24: =Data!E13+Data!E14+Data!E15+Data!E16+Data!E17+Data!E18+Data!E19+Data!E20+Data!E21+Data!E22+Data!E23+Data!E24 -> 237235 | G24: =Data!K13+Data!K14+Data!K15+Data!K16+Data!K17+Data!K18+Data!K19+Data!K20+Data!K21+Data!K22+Data!K23+Data!K24 -> 65125 | H24: =Data!L13+Data!L14+Data!L15+Data!L16+Data!L17+Data!L18+Data!L19+Data!L20+Data!L21+Data!L22+Data!L23+Data!L24 -> 59060 | I24: =Data!G13+Data!G14+Data!G15+Data!G16+Data!G17+Data!G18+Data!G19+Data!G20+Data!G21+Data!G22+Data!G23+Data!G24 -> 124512 | J24: =Data!H13+Data!I13+Data!J13+Data!M13+Data!H14+Data!I14+Data!J14+Data!M14+Data!H15+Data!I15+Data!J15+Data!M15+Data!H16+Data!I16+Data!J16+Data!M16+Data!H17+Data!I17+Data!J17+Data!M17+Data!H18+Data!I18+Data!J18+Data!M18+Data!H19+Data!I19+Data!J19+Data!M19+Data!H20+Data!I20+Data!J20+Data!M20+Data!H21+Data!I21+Data!J21+Data!M21+Data!H22+Data!I22+Data!J22+Data!M22+Data!H23+Data!I23+Data!J23+Data!M23+Data!H24+Data!I24+Data!J24+Data!M24 -> 307327 | K24: =Data!F13+Data!F14+Data!F15+Data!F16+Data!F17+Data!F18+Data!F19+Data!F20+Data!F21+Data!F22+Data!F23+Data!F24 -> 644629 | L24: =Data!N13+Data!O13+Data!P13+Data!Q13+Data!R13+Data!S13+Data!N14+Data!O14+Data!P14+Data!Q14+Data!R14+Data!S14+Data!N15+Data!O15+Data!P15+Data!Q15+Data!R15+Data!S15+Data!N16+Data!O16+Data!P16+Data!Q16+Data!R16+Data!S16+Data!N17+Data!O17+Data!P17+Data!Q17+Data!R17+Data!S17+Data!N18+Data!O18+Data!P18+Data!Q18+Data!R18+Data!S18+Data!N19+Data!O19+Data!P19+Data!Q19+Data!R19+Data!S19+Data!N20+Data!O20+Data!P20+Data!Q20+Data!R20+Data!S20+Data!N21+Data!O21+Data!P21+Data!Q21+Data!R21+Data!S21+Data!N22+Data!O22+Data!P22+Data!Q22+Data!R22+Data!S22+Data!N23+Data!O23+Data!P23+Data!Q23+Data!R23+Data!S23+Data!N24+Data!O24+Data!P24+Data!Q24+Data!R24+Data!S24 -> 121192 | M24: =Data!T13+Data!U13+Data!V13+Data!W13+Data!X13+Data!Y13+Data!Z13+Data!AA13+Data!AB13+Data!AC13+Data!AD13+Data!AE13+Data!AF13+Data!AG13+Data!AH13+Data!AI13+Data!AJ13+Data!AK13+Data!AL13+Data!T14+Data!U14+Data!V14+Data!W14+Data!X14+Data!Y14+Data!Z14+Data!AA14+Data!AB14+Data!AC14+Data!AD14+Data!AE14+Data!AF14+Data!AG14+Data!AH14+Data!AI14+Data!AJ14+Data!AK14+Data!AL14+Data!T15+Data!U15+Data!V15+Data!W15+Data!X15+Data!Y15+Data!Z15+Data!AA15+Data!AB15+Data!AC15+Data!AD15+Data!AE15+Data!AF15+Data!AG15+Data!AH15+Data!AI15+Data!AJ15+Data!AK15+Data!AL15+Data!T16+Data!U16+Data!V16+Data!W16+Data!X16+Data!Y16+Data!Z16+Data!AA16+Data!AB16+Data!AC16+Data!AD16+Data!AE16+Data!AF16+Data!AG16+Data!AH16+Data!AI16+Data!AJ16+Data!AK16+Data!AL16+Data!T17+Data!U17+Data!V17+Data!W17+Data!X17+Data!Y17+Data!Z17+Data!AA17+Data!AB17+Data!AC17+Data!AD17+Data!AE17+Data!AF17+Data!AG17+Data!AH17+Data!AI17+Data!AJ17+Data!AK17+Data!AL17+Data!T18+Data!U18+Data!V18+Data!W18+Data!X18+Data!Y18+Data!Z18+Data!AA18+Data!AB18+Data!AC18+Data!AD18+Data!AE18+Data!AF18+Data!AG18+Data!AH18+Data!AI18+Data!AJ18+Data!AK18+Data!AL18+Data!T19+Data!U19+Data!V19+Data!W19+Data!X19+Data!Y19+Data!Z19+Data!AA19+Data!AB19+Data!AC19+Data!AD19+Data!AE19+Data!AF19+Data!AG19+Data!AH19+Data!AI19+Data!AJ19+Data!AK19+Data!AL19+Data!T20+Data!U20+Data!V20+Data!W20+Data!X20+Data!Y20+Data!Z20+Data!AA20+Data!AB20+Data!AC20+Data!AD20+Data!AE20+Data!AF20+Data!AG20+Data!AH20+Data!AI20+Data!AJ20+Data!AK20+Data!AL20+Data!T21+Data!U21+Data!V21+Data!W21+Data!X21+Data!Y21+Data!Z21+Data!AA21+Data!AB21+Data!AC21+Data!AD21+Data!AE21+Data!AF21+Data!AG21+Data!AH21+Data!AI21+Data!AJ21+Data!AK21+Data!AL21+Data!T22+Data!U22+Data!V22+Data!W22+Data!X22+Data!Y22+Data!Z22+Data!AA22+Data!AB22+Data!AC22+Data!AD22+Data!AE22+Data!AF22+Data!AG22+Data!AH22+Data!AI22+Data!AJ22+Data!AK22+Data!AL22+Data!T23+Data!U23+Data!V23+Data!W23+Data!X23+Data!Y23+Data!Z23+Data!AA23+Data!AB23+Data!AC23+Data!AD23+Data!AE23+Data!AF23+Data!AG23+Data!AH23+Data!AI23+Data!AJ23+Data!AK23+Data!AL23+Data!T24+Data!U24+Data!V24+Data!W24+Data!X24+Data!Y24+Data!Z24+Data!AA24+Data!AB24+Data!AC24+Data!AD24+Data!AE24+Data!AF24+Data!AG24+Data!AH24+Data!AI24+Data!AJ24+Data!AK24+Data!AL24 -> 2233812 | N24: =Data!T13+Data!U13+Data!V13+Data!W13+Data!T14+Data!U14+Data!V14+Data!W14+Data!T15+Data!U15+Data!V15+Data!W15+Data!T16+Data!U16+Data!V16+Data!W16+Data!T17+Data!U17+Data!V17+Data!W17+Data!T18+Data!U18+Data!V18+Data!W18+Data!T19+Data!U19+Data!V19+Data!W19+Data!T20+Data!U20+Data!V20+Data!W20+Data!T21+Data!U21+Data!V21+Data!W21+Data!T22+Data!U22+Data!V22+Data!W22+Data!T23+Data!U23+Data!V23+Data!W23+Data!T24+Data!U24+Data!V24+Data!W24 -> 1089154 | O24: =Data!T13+Data!T14+Data!T15+Data!T16+Data!T17+Data!T18+Data!T19+Data!T20+Data!T21+Data!T22+Data!T23+Data!T24 -> 778324 | P24: =Data!U13+Data!U14+Data!U15+Data!U16+Data!U17+Data!U18+Data!U19+Data!U20+Data!U21+Data!U22+Data!U23+Data!U24 -> 127803 | Q24: =Data!V13+Data!V14+Data!V15+Data!V16+Data!V17+Data!V18+Data!V19+Data!V20+Data!V21+Data!V22+Data!V23+Data!V24 -> 89945 | R24: =Data!W13+Data!W14+Data!W15+Data!W16+Data!W17+Data!W18+Data!W19+Data!W20+Data!W21+Data!W22+Data!W23+Data!W24 -> 93082 | S24: =Data!X13+Data!X14+Data!X15+Data!X16+Data!X17+Data!X18+Data!X19+Data!X20+Data!X21+Data!X22+Data!X23+Data!X24 -> 34787 | T24: =Data!Y13+Data!Z13+Data!AA13+Data!Y14+Data!Z14+Data!AA14+Data!Y15+Data!Z15+Data!AA15+Data!Y16+Data!Z16+Data!AA16+Data!Y17+Data!Z17+Data!AA17+Data!Y18+Data!Z18+Data!AA18+Data!Y19+Data!Z19+Data!AA19+Data!Y20+Data!Z20+Data!AA20+Data!Y21+Data!Z21+Data!AA21+Data!Y22+Data!Z22+Data!AA22+Data!Y23+Data!Z23+Data!AA23+Data!Y24+Data!Z24+Data!AA24 -> 286209 | U24: =Data!Y13+Data!Y14+Data!Y15+Data!Y16+Data!Y17+Data!Y18+Data!Y19+Data!Y20+Data!Y21+Data!Y22+Data!Y23+Data!Y24 -> 194621 | V24: =Data!Z13+Data!Z14+Data!Z15+Data!Z16+Data!Z17+Data!Z18+Data!Z19+Data!Z20+Data!Z21+Data!Z22+Data!Z23+Data!Z24 -> 85874 | W24: =Data!AB13+Data!AB14+Data!AB15+Data!AB16+Data!AB17+Data!AB18+Data!AB19+Data!AB20+Data!AB21+Data!AB22+Data!AB23+Data!AB24 -> 303630 | X24: =Data!AC13+Data!AC14+Data!AC15+Data!AC16+Data!AC17+Data!AC18+Data!AC19+Data!AC20+Data!AC21+Data!AC22+Data!AC23+Data!AC24 -> 94365 | Y24: =Data!AD13+Data!AE13+Data!AF13+Data!AG13+Data!AH13+Data!AD14+Data!AE14+Data!AF14+Data!AG14+Data!AH14+Data!AD15+Data!AE15+Data!AF15+Data!AG15+Data!AH15+Data!AD16+Data!AE16+Data!AF16+Data!AG16+Data!AH16+Data!AD17+Data!AE17+Data!AF17+Data!AG17+Data!AH17+Data!AD18+Data!AE18+Data!AF18+Data!AG18+Data!AH18+Data!AD19+Data!AE19+Data!AF19+Data!AG19+Data!AH19+Data!AD20+Data!AE20+Data!AF20+Data!AG20+Data!AH20+Data!AD21+Data!AE21+Data!AF21+Data!AG21+Data!AH21+Data!AD22+Data!AE22+Data!AF22+Data!AG22+Data!AH22+Data!AD23+Data!AE23+Data!AF23+Data!AG23+Data!AH23+Data!AD24+Data!AE24+Data!AF24+Data!AG24+Data!AH24 -> 88946 | Z24: =Data!AI13+Data!AI14+Data!AI15+Data!AI16+Data!AI17+Data!AI18+Data!AI19+Data!AI20+Data!AI21+Data!AI22+Data!AI23+Data!AI24 -> 73174 | AA24: =Data!AJ13+Data!AJ14+Data!AJ15+Data!AJ16+Data!AJ17+Data!AJ18+Data!AJ19+Data!AJ20+Data!AJ21+Data!AJ22+Data!AJ23+Data!AJ24 -> 5869 | AB24: =Data!AK13+Data!AK14+Data!AK15+Data!AK16+Data!AK17+Data!AK18+Data!AK19+Data!AK20+Data!AK21+Data!AK22+Data!AK23+Data!AK24 -> 51091 | AC24: =Data!AL13+Data!AL14+Data!AL15+Data!AL16+Data!AL17+Data!AL18+Data!AL19+Data!AL20+Data!AL21+Data!AL22+Data!AL23+Data!AL24 -> 206587 | AD24: =Data!AM13+Data!AM14+Data!AM15+Data!AM16+Data!AM17+Data!AM18+Data!AM19+Data!AM20+Data!AM21+Data!AM22+Data!AM23+Data!AM24 -> -375022 | AE24: =Data!AN13+Data!AN14+Data!AN15+Data!AN16+Data!AN17+Data!AN18+Data!AN19+Data!AN20+Data!AN21+Data!AN22+Data!AN23+Data!AN24 -> 177088 | AF24: =Data!AO13+Data!AO14+Data!AO15+Data!AO16+Data!AO17+Data!AO18+Data!AO19+Data!AO20+Data!AO21+Data!AO22+Data!AO23+Data!AO24 -> -552109
B25: =Data!B25 -> 2017-07 | C25: =Data!D14+Data!E14+Data!F14+Data!G14+Data!H14+Data!I14+Data!J14+Data!K14+Data!L14+Data!M14+Data!N14+Data!O14+Data!P14+Data!Q14+Data!R14+Data!S14+Data!D15+Data!E15+Data!F15+Data!G15+Data!H15+Data!I15+Data!J15+Data!K15+Data!L15+Data!M15+Data!N15+Data!O15+Data!P15+Data!Q15+Data!R15+Data!S15+Data!D16+Data!E16+Data!F16+Data!G16+Data!H16+Data!I16+Data!J16+Data!K16+Data!L16+Data!M16+Data!N16+Data!O16+Data!P16+Data!Q16+Data!R16+Data!S16+Data!D17+Data!E17+Data!F17+Data!G17+Data!H17+Data!I17+Data!J17+Data!K17+Data!L17+Data!M17+Data!N17+Data!O17+Data!P17+Data!Q17+Data!R17+Data!S17+Data!D18+Data!E18+Data!F18+Data!G18+Data!H18+Data!I18+Data!J18+Data!K18+Data!L18+Data!M18+Data!N18+Data!O18+Data!P18+Data!Q18+Data!R18+Data!S18+Data!D19+Data!E19+Data!F19+Data!G19+Data!H19+Data!I19+Data!J19+Data!K19+Data!L19+Data!M19+Data!N19+Data!O19+Data!P19+Data!Q19+Data!R19+Data!S19+Data!D20+Data!E20+Data!F20+Data!G20+Data!H20+Data!I20+Data!J20+Data!K20+Data!L20+Data!M20+Data!N20+Data!O20+Data!P20+Data!Q20+Data!R20+Data!S20+Data!D21+Data!E21+Data!F21+Data!G21+Data!H21+Data!I21+Data!J21+Data!K21+Data!L21+Data!M21+Data!N21+Data!O21+Data!P21+Data!Q21+Data!R21+Data!S21+Data!D22+Data!E22+Data!F22+Data!G22+Data!H22+Data!I22+Data!J22+Data!K22+Data!L22+Data!M22+Data!N22+Data!O22+Data!P22+Data!Q22+Data!R22+Data!S22+Data!D23+Data!E23+Data!F23+Data!G23+Data!H23+Data!I23+Data!J23+Data!K23+Data!L23+Data!M23+Data!N23+Data!O23+Data!P23+Data!Q23+Data!R23+Data!S23+Data!D24+Data!E24+Data!F24+Data!G24+Data!H24+Data!I24+Data!J24+Data!K24+Data!L24+Data!M24+Data!N24+Data!O24+Data!P24+Data!Q24+Data!R24+Data!S24+Data!D25+Data!E25+Data!F25+Data!G25+Data!H25+Data!I25+Data!J25+Data!K25+Data!L25+Data!M25+Data!N25+Data!O25+Data!P25+Data!Q25+Data!R25+Data!S25 -> 1899655 | D25: =Data!D14+Data!E14+Data!G14+Data!H14+Data!I14+Data!J14+Data!K14+Data!L14+Data!M14+Data!D15+Data!E15+Data!G15+Data!H15+Data!I15+Data!J15+Data!K15+Data!L15+Data!M15+Data!D16+Data!E16+Data!G16+Data!H16+Data!I16+Data!J16+Data!K16+Data!L16+Data!M16+Data!D17+Data!E17+Data!G17+Data!H17+Data!I17+Data!J17+Data!K17+Data!L17+Data!M17+Data!D18+Data!E18+Data!G18+Data!H18+Data!I18+Data!J18+Data!K18+Data!L18+Data!M18+Data!D19+Data!E19+Data!G19+Data!H19+Data!I19+Data!J19+Data!K19+Data!L19+Data!M19+Data!D20+Data!E20+Data!G20+Data!H20+Data!I20+Data!J20+Data!K20+Data!L20+Data!M20+Data!D21+Data!E21+Data!G21+Data!H21+Data!I21+Data!J21+Data!K21+Data!L21+Data!M21+Data!D22+Data!E22+Data!G22+Data!H22+Data!I22+Data!J22+Data!K22+Data!L22+Data!M22+Data!D23+Data!E23+Data!G23+Data!H23+Data!I23+Data!J23+Data!K23+Data!L23+Data!M23+Data!D24+Data!E24+Data!G24+Data!H24+Data!I24+Data!J24+Data!K24+Data!L24+Data!M24+Data!D25+Data!E25+Data!G25+Data!H25+Data!I25+Data!J25+Data!K25+Data!L25+Data!M25 -> 1112393 | E25: =Data!D14+Data!D15+Data!D16+Data!D17+Data!D18+Data!D19+Data!D20+Data!D21+Data!D22+Data!D23+Data!D24+Data!D25 -> 306428 | F25: =Data!E14+Data!E15+Data!E16+Data!E17+Data!E18+Data!E19+Data!E20+Data!E21+Data!E22+Data!E23+Data!E24+Data!E25 -> 243994 | G25: =Data!K14+Data!K15+Data!K16+Data!K17+Data!K18+Data!K19+Data!K20+Data!K21+Data!K22+Data!K23+Data!K24+Data!K25 -> 65048 | H25: =Data!L14+Data!L15+Data!L16+Data!L17+Data!L18+Data!L19+Data!L20+Data!L21+Data!L22+Data!L23+Data!L24+Data!L25 -> 59884 | I25: =Data!G14+Data!G15+Data!G16+Data!G17+Data!G18+Data!G19+Data!G20+Data!G21+Data!G22+Data!G23+Data!G24+Data!G25 -> 126666 | J25: =Data!H14+Data!I14+Data!J14+Data!M14+Data!H15+Data!I15+Data!J15+Data!M15+Data!H16+Data!I16+Data!J16+Data!M16+Data!H17+Data!I17+Data!J17+Data!M17+Data!H18+Data!I18+Data!J18+Data!M18+Data!H19+Data!I19+Data!J19+Data!M19+Data!H20+Data!I20+Data!J20+Data!M20+Data!H21+Data!I21+Data!J21+Data!M21+Data!H22+Data!I22+Data!J22+Data!M22+Data!H23+Data!I23+Data!J23+Data!M23+Data!H24+Data!I24+Data!J24+Data!M24+Data!H25+Data!I25+Data!J25+Data!M25 -> 310373 | K25: =Data!F14+Data!F15+Data!F16+Data!F17+Data!F18+Data!F19+Data!F20+Data!F21+Data!F22+Data!F23+Data!F24+Data!F25 -> 663141 | L25: =Data!N14+Data!O14+Data!P14+Data!Q14+Data!R14+Data!S14+Data!N15+Data!O15+Data!P15+Data!Q15+Data!R15+Data!S15+Data!N16+Data!O16+Data!P16+Data!Q16+Data!R16+Data!S16+Data!N17+Data!O17+Data!P17+Data!Q17+Data!R17+Data!S17+Data!N18+Data!O18+Data!P18+Data!Q18+Data!R18+Data!S18+Data!N19+Data!O19+Data!P19+Data!Q19+Data!R19+Data!S19+Data!N20+Data!O20+Data!P20+Data!Q20+Data!R20+Data!S20+Data!N21+Data!O21+Data!P21+Data!Q21+Data!R21+Data!S21+Data!N22+Data!O22+Data!P22+Data!Q22+Data!R22+Data!S22+Data!N23+Data!O23+Data!P23+Data!Q23+Data!R23+Data!S23+Data!N24+Data!O24+Data!P24+Data!Q24+Data!R24+Data!S24+Data!N25+Data!O25+Data!P25+Data!Q25+Data!R25+Data!S25 -> 124121 | M25: =Data!T14+Data!U14+Data!V14+Data!W14+Data!X14+Data!Y14+Data!Z14+Data!AA14+Data!AB14+Data!AC14+Data!AD14+Data!AE14+Data!AF14+Data!AG14+Data!AH14+Data!AI14+Data!AJ14+Data!AK14+Data!AL14+Data!T15+Data!U15+Data!V15+Data!W15+Data!X15+Data!Y15+Data!Z15+Data!AA15+Data!AB15+Data!AC15+Data!AD15+Data!AE15+Data!AF15+Data!AG15+Data!AH15+Data!AI15+Data!AJ15+Data!AK15+Data!AL15+Data!T16+Data!U16+Data!V16+Data!W16+Data!X16+Data!Y16+Data!Z16+Data!AA16+Data!AB16+Data!AC16+Data!AD16+Data!AE16+Data!AF16+Data!AG16+Data!AH16+Data!AI16+Data!AJ16+Data!AK16+Data!AL16+Data!T17+Data!U17+Data!V17+Data!W17+Data!X17+Data!Y17+Data!Z17+Data!AA17+Data!AB17+Data!AC17+Data!AD17+Data!AE17+Data!AF17+Data!AG17+Data!AH17+Data!AI17+Data!AJ17+Data!AK17+Data!AL17+Data!T18+Data!U18+Data!V18+Data!W18+Data!X18+Data!Y18+Data!Z18+Data!AA18+Data!AB18+Data!AC18+Data!AD18+Data!AE18+Data!AF18+Data!AG18+Data!AH18+Data!AI18+Data!AJ18+Data!AK18+Data!AL18+Data!T19+Data!U19+Data!V19+Data!W19+Data!X19+Data!Y19+Data!Z19+Data!AA19+Data!AB19+Data!AC19+Data!AD19+Data!AE19+Data!AF19+Data!AG19+Data!AH19+Data!AI19+Data!AJ19+Data!AK19+Data!AL19+Data!T20+Data!U20+Data!V20+Data!W20+Data!X20+Data!Y20+Data!Z20+Data!AA20+Data!AB20+Data!AC20+Data!AD20+Data!AE20+Data!AF20+Data!AG20+Data!AH20+Data!AI20+Data!AJ20+Data!AK20+Data!AL20+Data!T21+Data!U21+Data!V21+Data!W21+Data!X21+Data!Y21+Data!Z21+Data!AA21+Data!AB21+Data!AC21+Data!AD21+Data!AE21+Data!AF21+Data!AG21+Data!AH21+Data!AI21+Data!AJ21+Data!AK21+Data!AL21+Data!T22+Data!U22+Data!V22+Data!W22+Data!X22+Data!Y22+Data!Z22+Data!AA22+Data!AB22+Data!AC22+Data!AD22+Data!AE22+Data!AF22+Data!AG22+Data!AH22+Data!AI22+Data!AJ22+Data!AK22+Data!AL22+Data!T23+Data!U23+Data!V23+Data!W23+Data!X23+Data!Y23+Data!Z23+Data!AA23+Data!AB23+Data!AC23+Data!AD23+Data!AE23+Data!AF23+Data!AG23+Data!AH23+Data!AI23+Data!AJ23+Data!AK23+Data!AL23+Data!T24+Data!U24+Data!V24+Data!W24+Data!X24+Data!Y24+Data!Z24+Data!AA24+Data!AB24+Data!AC24+Data!AD24+Data!AE24+Data!AF24+Data!AG24+Data!AH24+Data!AI24+Data!AJ24+Data!AK24+Data!AL24+Data!T25+Data!U25+Data!V25+Data!W25+Data!X25+Data!Y25+Data!Z25+Data!AA25+Data!AB25+Data!AC25+Data!AD25+Data!AE25+Data!AF25+Data!AG25+Data!AH25+Data!AI25+Data!AJ25+Data!AK25+Data!AL25 -> 2272401 | N25: =Data!T14+Data!U14+Data!V14+Data!W14+Data!T15+Data!U15+Data!V15+Data!W15+Data!T16+Data!U16+Data!V16+Data!W16+Data!T17+Data!U17+Data!V17+Data!W17+Data!T18+Data!U18+Data!V18+Data!W18+Data!T19+Data!U19+Data!V19+Data!W19+Data!T20+Data!U20+Data!V20+Data!W20+Data!T21+Data!U21+Data!V21+Data!W21+Data!T22+Data!U22+Data!V22+Data!W22+Data!T23+Data!U23+Data!V23+Data!W23+Data!T24+Data!U24+Data!V24+Data!W24+Data!T25+Data!U25+Data!V25+Data!W25 -> 1121317 | O25: =Data!T14+Data!T15+Data!T16+Data!T17+Data!T18+Data!T19+Data!T20+Data!T21+Data!T22+Data!T23+Data!T24+Data!T25 -> 801709 | P25: =Data!U14+Data!U15+Data!U16+Data!U17+Data!U18+Data!U19+Data!U20+Data!U21+Data!U22+Data!U23+Data!U24+Data!U25 -> 130752 | Q25: =Data!V14+Data!V15+Data!V16+Data!V17+Data!V18+Data!V19+Data!V20+Data!V21+Data!V22+Data!V23+Data!V24+Data!V25 -> 91741 | R25: =Data!W14+Data!W15+Data!W16+Data!W17+Data!W18+Data!W19+Data!W20+Data!W21+Data!W22+Data!W23+Data!W24+Data!W25 -> 97115 | S25: =Data!X14+Data!X15+Data!X16+Data!X17+Data!X18+Data!X19+Data!X20+Data!X21+Data!X22+Data!X23+Data!X24+Data!X25 -> 35440 | T25: =Data!Y14+Data!Z14+Data!AA14+Data!Y15+Data!Z15+Data!AA15+Data!Y16+Data!Z16+Data!AA16+Data!Y17+Data!Z17+Data!AA17+Data!Y18+Data!Z18+Data!AA18+Data!Y19+Data!Z19+Data!AA19+Data!Y20+Data!Z20+Data!AA20+Data!Y21+Data!Z21+Data!AA21+Data!Y22+Data!Z22+Data!AA22+Data!Y23+Data!Z23+Data!AA23+Data!Y24+Data!Z24+Data!AA24+Data!Y25+Data!Z25+Data!AA25 -> 277869 | U25: =Data!Y14+Data!Y15+Data!Y16+Data!Y17+Data!Y18+Data!Y19+Data!Y20+Data!Y21+Data!Y22+Data!Y23+Data!Y24+Data!Y25 -> 183955 | V25: =Data!Z14+Data!Z15+Data!Z16+Data!Z17+Data!Z18+Data!Z19+Data!Z20+Data!Z21+Data!Z22+Data!Z23+Data!Z24+Data!Z25 -> 87355 | W25: =Data!AB14+Data!AB15+Data!AB16+Data!AB17+Data!AB18+Data!AB19+Data!AB20+Data!AB21+Data!AB22+Data!AB23+Data!AB24+Data!AB25 -> 311586 | X25: =Data!AC14+Data!AC15+Data!AC16+Data!AC17+Data!AC18+Data!AC19+Data!AC20+Data!AC21+Data!AC22+Data!AC23+Data!AC24+Data!AC25 -> 96728 | Y25: =Data!AD14+Data!AE14+Data!AF14+Data!AG14+Data!AH14+Data!AD15+Data!AE15+Data!AF15+Data!AG15+Data!AH15+Data!AD16+Data!AE16+Data!AF16+Data!AG16+Data!AH16+Data!AD17+Data!AE17+Data!AF17+Data!AG17+Data!AH17+Data!AD18+Data!AE18+Data!AF18+Data!AG18+Data!AH18+Data!AD19+Data!AE19+Data!AF19+Data!AG19+Data!AH19+Data!AD20+Data!AE20+Data!AF20+Data!AG20+Data!AH20+Data!AD21+Data!AE21+Data!AF21+Data!AG21+Data!AH21+Data!AD22+Data!AE22+Data!AF22+Data!AG22+Data!AH22+Data!AD23+Data!AE23+Data!AF23+Data!AG23+Data!AH23+Data!AD24+Data!AE24+Data!AF24+Data!AG24+Data!AH24+Data!AD25+Data!AE25+Data!AF25+Data!AG25+Data!AH25 -> 85026 | Z25: =Data!AI14+Data!AI15+Data!AI16+Data!AI17+Data!AI18+Data!AI19+Data!AI20+Data!AI21+Data!AI22+Data!AI23+Data!AI24+Data!AI25 -> 74626 | AA25: =Data!AJ14+Data!AJ15+Data!AJ16+Data!AJ17+Data!AJ18+Data!AJ19+Data!AJ20+Data!AJ21+Data!AJ22+Data!AJ23+Data!AJ24+Data!AJ25 -> 5665 | AB25: =Data!AK14+Data!AK15+Data!AK16+Data!AK17+Data!AK18+Data!AK19+Data!AK20+Data!AK21+Data!AK22+Data!AK23+Data!AK24+Data!AK25 -> 49298 | AC25: =Data!AL14+Data!AL15+Data!AL16+Data!AL17+Data!AL18+Data!AL19+Data!AL20+Data!AL21+Data!AL22+Data!AL23+Data!AL24+Data!AL25 -> 214846 | AD25: =Data!AM14+Data!AM15+Data!AM16+Data!AM17+Data!AM18+Data!AM19+Data!AM20+Data!AM21+Data!AM22+Data!AM23+Data!AM24+Data!AM25 -> -372746 | AE25: =Data!AN14+Data!AN15+Data!AN16+Data!AN17+Data!AN18+Data!AN19+Data!AN20+Data!AN21+Data!AN22+Data!AN23+Data!AN24+Data!AN25 -> 184501 | AF25: =Data!AO14+Data!AO15+Data!AO16+Data!AO17+Data!AO18+Data!AO19+Data!AO20+Data!AO21+Data!AO22+Data!AO23+Data!AO24+Data!AO25 -> -557246
B26: =Data!B26 -> 2017-08 | C26: =Data!D15+Data!E15+Data!F15+Data!G15+Data!H15+Data!I15+Data!J15+Data!K15+Data!L15+Data!M15+Data!N15+Data!O15+Data!P15+Data!Q15+Data!R15+Data!S15+Data!D16+Data!E16+Data!F16+Data!G16+Data!H16+Data!I16+Data!J16+Data!K16+Data!L16+Data!M16+Data!N16+Data!O16+Data!P16+Data!Q16+Data!R16+Data!S16+Data!D17+Data!E17+Data!F17+Data!G17+Data!H17+Data!I17+Data!J17+Data!K17+Data!L17+Data!M17+Data!N17+Data!O17+Data!P17+Data!Q17+Data!R17+Data!S17+Data!D18+Data!E18+Data!F18+Data!G18+Data!H18+Data!I18+Data!J18+Data!K18+Data!L18+Data!M18+Data!N18+Data!O18+Data!P18+Data!Q18+Data!R18+Data!S18+Data!D19+Data!E19+Data!F19+Data!G19+Data!H19+Data!I19+Data!J19+Data!K19+Data!L19+Data!M19+Data!N19+Data!O19+Data!P19+Data!Q19+Data!R19+Data!S19+Data!D20+Data!E20+Data!F20+Data!G20+Data!H20+Data!I20+Data!J20+Data!K20+Data!L20+Data!M20+Data!N20+Data!O20+Data!P20+Data!Q20+Data!R20+Data!S20+Data!D21+Data!E21+Data!F21+Data!G21+Data!H21+Data!I21+Data!J21+Data!K21+Data!L21+Data!M21+Data!N21+Data!O21+Data!P21+Data!Q21+Data!R21+Data!S21+Data!D22+Data!E22+Data!F22+Data!G22+Data!H22+Data!I22+Data!J22+Data!K22+Data!L22+Data!M22+Data!N22+Data!O22+Data!P22+Data!Q22+Data!R22+Data!S22+Data!D23+Data!E23+Data!F23+Data!G23+Data!H23+Data!I23+Data!J23+Data!K23+Data!L23+Data!M23+Data!N23+Data!O23+Data!P23+Data!Q23+Data!R23+Data!S23+Data!D24+Data!E24+Data!F24+Data!G24+Data!H24+Data!I24+Data!J24+Data!K24+Data!L24+Data!M24+Data!N24+Data!O24+Data!P24+Data!Q24+Data!R24+Data!S24+Data!D25+Data!E25+Data!F25+Data!G25+Data!H25+Data!I25+Data!J25+Data!K25+Data!L25+Data!M25+Data!N25+Data!O25+Data!P25+Data!Q25+Data!R25+Data!S25+Data!D26+Data!E26+Data!F26+Data!G26+Data!H26+Data!I26+Data!J26+Data!K26+Data!L26+Data!M26+Data!N26+Data!O26+Data!P26+Data!Q26+Data!R26+Data!S26 -> 1939034 | D26: =Data!D15+Data!E15+Data!G15+Data!H15+Data!I15+Data!J15+Data!K15+Data!L15+Data!M15+Data!D16+Data!E16+Data!G16+Data!H16+Data!I16+Data!J16+Data!K16+Data!L16+Data!M16+Data!D17+Data!E17+Data!G17+Data!H17+Data!I17+Data!J17+Data!K17+Data!L17+Data!M17+Data!D18+Data!E18+Data!G18+Data!H18+Data!I18+Data!J18+Data!K18+Data!L18+Data!M18+Data!D19+Data!E19+Data!G19+Data!H19+Data!I19+Data!J19+Data!K19+Data!L19+Data!M19+Data!D20+Data!E20+Data!G20+Data!H20+Data!I20+Data!J20+Data!K20+Data!L20+Data!M20+Data!D21+Data!E21+Data!G21+Data!H21+Data!I21+Data!J21+Data!K21+Data!L21+Data!M21+Data!D22+Data!E22+Data!G22+Data!H22+Data!I22+Data!J22+Data!K22+Data!L22+Data!M22+Data!D23+Data!E23+Data!G23+Data!H23+Data!I23+Data!J23+Data!K23+Data!L23+Data!M23+Data!D24+Data!E24+Data!G24+Data!H24+Data!I24+Data!J24+Data!K24+Data!L24+Data!M24+Data!D25+Data!E25+Data!G25+Data!H25+Data!I25+Data!J25+Data!K25+Data!L25+Data!M25+Data!D26+Data!E26+Data!G26+Data!H26+Data!I26+Data!J26+Data!K26+Data!L26+Data!M26 -> 1135798 | E26: =Data!D15+Data!D16+Data!D17+Data!D18+Data!D19+Data!D20+Data!D21+Data!D22+Data!D23+Data!D24+Data!D25+Data!D26 -> 314168 | F26: =Data!E15+Data!E16+Data!E17+Data!E18+Data!E19+Data!E20+Data!E21+Data!E22+Data!E23+Data!E24+Data!E25+Data!E26 -> 250274 | G26: =Data!K15+Data!K16+Data!K17+Data!K18+Data!K19+Data!K20+Data!K21+Data!K22+Data!K23+Data!K24+Data!K25+Data!K26 -> 67033 | H26: =Data!L15+Data!L16+Data!L17+Data!L18+Data!L19+Data!L20+Data!L21+Data!L22+Data!L23+Data!L24+Data!L25+Data!L26 -> 61666 | I26: =Data!G15+Data!G16+Data!G17+Data!G18+Data!G19+Data!G20+Data!G21+Data!G22+Data!G23+Data!G24+Data!G25+Data!G26 -> 129676 | J26: =Data!H15+Data!I15+Data!J15+Data!M15+Data!H16+Data!I16+Data!J16+Data!M16+Data!H17+Data!I17+Data!J17+Data!M17+Data!H18+Data!I18+Data!J18+Data!M18+Data!H19+Data!I19+Data!J19+Data!M19+Data!H20+Data!I20+Data!J20+Data!M20+Data!H21+Data!I21+Data!J21+Data!M21+Data!H22+Data!I22+Data!J22+Data!M22+Data!H23+Data!I23+Data!J23+Data!M23+Data!H24+Data!I24+Data!J24+Data!M24+Data!H25+Data!I25+Data!J25+Data!M25+Data!H26+Data!I26+Data!J26+Data!M26 -> 312981 | K26: =Data!F15+Data!F16+Data!F17+Data!F18+Data!F19+Data!F20+Data!F21+Data!F22+Data!F23+Data!F24+Data!F25+Data!F26 -> 675148 | L26: =Data!N15+Data!O15+Data!P15+Data!Q15+Data!R15+Data!S15+Data!N16+Data!O16+Data!P16+Data!Q16+Data!R16+Data!S16+Data!N17+Data!O17+Data!P17+Data!Q17+Data!R17+Data!S17+Data!N18+Data!O18+Data!P18+Data!Q18+Data!R18+Data!S18+Data!N19+Data!O19+Data!P19+Data!Q19+Data!R19+Data!S19+Data!N20+Data!O20+Data!P20+Data!Q20+Data!R20+Data!S20+Data!N21+Data!O21+Data!P21+Data!Q21+Data!R21+Data!S21+Data!N22+Data!O22+Data!P22+Data!Q22+Data!R22+Data!S22+Data!N23+Data!O23+Data!P23+Data!Q23+Data!R23+Data!S23+Data!N24+Data!O24+Data!P24+Data!Q24+Data!R24+Data!S24+Data!N25+Data!O25+Data!P25+Data!Q25+Data!R25+Data!S25+Data!N26+Data!O26+Data!P26+Data!Q26+Data!R26+Data!S26 -> 128088 | M26: =Data!T15+Data!U15+Data!V15+Data!W15+Data!X15+Data!Y15+Data!Z15+Data!AA15+Data!AB15+Data!AC15+Data!AD15+Data!AE15+Data!AF15+Data!AG15+Data!AH15+Data!AI15+Data!AJ15+Data!AK15+Data!AL15+Data!T16+Data!U16+Data!V16+Data!W16+Data!X16+Data!Y16+Data!Z16+Data!AA16+Data!AB16+Data!AC16+Data!AD16+Data!AE16+Data!AF16+Data!AG16+Data!AH16+Data!AI16+Data!AJ16+Data!AK16+Data!AL16+Data!T17+Data!U17+Data!V17+Data!W17+Data!X17+Data!Y17+Data!Z17+Data!AA17+Data!AB17+Data!AC17+Data!AD17+Data!AE17+Data!AF17+Data!AG17+Data!AH17+Data!AI17+Data!AJ17+Data!AK17+Data!AL17+Data!T18+Data!U18+Data!V18+Data!W18+Data!X18+Data!Y18+Data!Z18+Data!AA18+Data!AB18+Data!AC18+Data!AD18+Data!AE18+Data!AF18+Data!AG18+Data!AH18+Data!AI18+Data!AJ18+Data!AK18+Data!AL18+Data!T19+Data!U19+Data!V19+Data!W19+Data!X19+Data!Y19+Data!Z19+Data!AA19+Data!AB19+Data!AC19+Data!AD19+Data!AE19+Data!AF19+Data!AG19+Data!AH19+Data!AI19+Data!AJ19+Data!AK19+Data!AL19+Data!T20+Data!U20+Data!V20+Data!W20+Data!X20+Data!Y20+Data!Z20+Data!AA20+Data!AB20+Data!AC20+Data!AD20+Data!AE20+Data!AF20+Data!AG20+Data!AH20+Data!AI20+Data!AJ20+Data!AK20+Data!AL20+Data!T21+Data!U21+Data!V21+Data!W21+Data!X21+Data!Y21+Data!Z21+Data!AA21+Data!AB21+Data!AC21+Data!AD21+Data!AE21+Data!AF21+Data!AG21+Data!AH21+Data!AI21+Data!AJ21+Data!AK21+Data!AL21+Data!T22+Data!U22+Data!V22+Data!W22+Data!X22+Data!Y22+Data!Z22+Data!AA22+Data!AB22+Data!AC22+Data!AD22+Data!AE22+Data!AF22+Data!AG22+Data!AH22+Data!AI22+Data!AJ22+Data!AK22+Data!AL22+Data!T23+Data!U23+Data!V23+Data!W23+Data!X23+Data!Y23+Data!Z23+Data!AA23+Data!AB23+Data!AC23+Data!AD23+Data!AE23+Data!AF23+Data!AG23+Data!AH23+Data!AI23+Data!AJ23+Data!AK23+Data!AL23+Data!T24+Data!U24+Data!V24+Data!W24+Data!X24+Data!Y24+Data!Z24+Data!AA24+Data!AB24+Data!AC24+Data!AD24+Data!AE24+Data!AF24+Data!AG24+Data!AH24+Data!AI24+Data!AJ24+Data!AK24+Data!AL24+Data!T25+Data!U25+Data!V25+Data!W25+Data!X25+Data!Y25+Data!Z25+Data!AA25+Data!AB25+Data!AC25+Data!AD25+Data!AE25+Data!AF25+Data!AG25+Data!AH25+Data!AI25+Data!AJ25+Data!AK25+Data!AL25+Data!T26+Data!U26+Data!V26+Data!W26+Data!X26+Data!Y26+Data!Z26+Data!AA26+Data!AB26+Data!AC26+Data!AD26+Data!AE26+Data!AF26+Data!AG26+Data!AH26+Data!AI26+Data!AJ26+Data!AK26+Data!AL26 -> 2301015 | N26: =Data!T15+Data!U15+Data!V15+Data!W15+Data!T16+Data!U16+Data!V16+Data!W16+Data!T17+Data!U17+Data!V17+Data!W17+Data!T18+Data!U18+Data!V18+Data!W18+Data!T19+Data!U19+Data!V19+Data!W19+Data!T20+Data!U20+Data!V20+Data!W20+Data!T21+Data!U21+Data!V21+Data!W21+Data!T22+Data!U22+Data!V22+Data!W22+Data!T23+Data!U23+Data!V23+Data!W23+Data!T24+Data!U24+Data!V24+Data!W24+Data!T25+Data!U25+Data!V25+Data!W25+Data!T26+Data!U26+Data!V26+Data!W26 -> 1144904 | O26: =Data!T15+Data!T16+Data!T17+Data!T18+Data!T19+Data!T20+Data!T21+Data!T22+Data!T23+Data!T24+Data!T25+Data!T26 -> 822063 | P26: =Data!U15+Data!U16+Data!U17+Data!U18+Data!U19+Data!U20+Data!U21+Data!U22+Data!U23+Data!U24+Data!U25+Data!U26 -> 133519 | Q26: =Data!V15+Data!V16+Data!V17+Data!V18+Data!V19+Data!V20+Data!V21+Data!V22+Data!V23+Data!V24+Data!V25+Data!V26 -> 93526 | R26: =Data!W15+Data!W16+Data!W17+Data!W18+Data!W19+Data!W20+Data!W21+Data!W22+Data!W23+Data!W24+Data!W25+Data!W26 -> 95796 | S26: =Data!X15+Data!X16+Data!X17+Data!X18+Data!X19+Data!X20+Data!X21+Data!X22+Data!X23+Data!X24+Data!X25+Data!X26 -> 36661 | T26: =Data!Y15+Data!Z15+Data!AA15+Data!Y16+Data!Z16+Data!AA16+Data!Y17+Data!Z17+Data!AA17+Data!Y18+Data!Z18+Data!AA18+Data!Y19+Data!Z19+Data!AA19+Data!Y20+Data!Z20+Data!AA20+Data!Y21+Data!Z21+Data!AA21+Data!Y22+Data!Z22+Data!AA22+Data!Y23+Data!Z23+Data!AA23+Data!Y24+Data!Z24+Data!AA24+Data!Y25+Data!Z25+Data!AA25+Data!Y26+Data!Z26+Data!AA26 -> 270981 | U26: =Data!Y15+Data!Y16+Data!Y17+Data!Y18+Data!Y19+Data!Y20+Data!Y21+Data!Y22+Data!Y23+Data!Y24+Data!Y25+Data!Y26 -> 178200 | V26: =Data!Z15+Data!Z16+Data!Z17+Data!Z18+Data!Z19+Data!Z20+Data!Z21+Data!Z22+Data!Z23+Data!Z24+Data!Z25+Data!Z26 -> 85521 | W26: =Data!AB15+Data!AB16+Data!AB17+Data!AB18+Data!AB19+Data!AB20+Data!AB21+Data!AB22+Data!AB23+Data!AB24+Data!AB25+Data!AB26 -> 315650 | X26: =Data!AC15+Data!AC16+Data!AC17+Data!AC18+Data!AC19+Data!AC20+Data!AC21+Data!AC22+Data!AC23+Data!AC24+Data!AC25+Data!AC26 -> 99279 | Y26: =Data!AD15+Data!AE15+Data!AF15+Data!AG15+Data!AH15+Data!AD16+Data!AE16+Data!AF16+Data!AG16+Data!AH16+Data!AD17+Data!AE17+Data!AF17+Data!AG17+Data!AH17+Data!AD18+Data!AE18+Data!AF18+Data!AG18+Data!AH18+Data!AD19+Data!AE19+Data!AF19+Data!AG19+Data!AH19+Data!AD20+Data!AE20+Data!AF20+Data!AG20+Data!AH20+Data!AD21+Data!AE21+Data!AF21+Data!AG21+Data!AH21+Data!AD22+Data!AE22+Data!AF22+Data!AG22+Data!AH22+Data!AD23+Data!AE23+Data!AF23+Data!AG23+Data!AH23+Data!AD24+Data!AE24+Data!AF24+Data!AG24+Data!AH24+Data!AD25+Data!AE25+Data!AF25+Data!AG25+Data!AH25+Data!AD26+Data!AE26+Data!AF26+Data!AG26+Data!AH26 -> 85466 | Z26: =Data!AI15+Data!AI16+Data!AI17+Data!AI18+Data!AI19+Data!AI20+Data!AI21+Data!AI22+Data!AI23+Data!AI24+Data!AI25+Data!AI26 -> 76599 | AA26: =Data!AJ15+Data!AJ16+Data!AJ17+Data!AJ18+Data!AJ19+Data!AJ20+Data!AJ21+Data!AJ22+Data!AJ23+Data!AJ24+Data!AJ25+Data!AJ26 -> 7685 | AB26: =Data!AK15+Data!AK16+Data!AK17+Data!AK18+Data!AK19+Data!AK20+Data!AK21+Data!AK22+Data!AK23+Data!AK24+Data!AK25+Data!AK26 -> 48566 | AC26: =Data!AL15+Data!AL16+Data!AL17+Data!AL18+Data!AL19+Data!AL20+Data!AL21+Data!AL22+Data!AL23+Data!AL24+Data!AL25+Data!AL26 -> 215224 | AD26: =Data!AM15+Data!AM16+Data!AM17+Data!AM18+Data!AM19+Data!AM20+Data!AM21+Data!AM22+Data!AM23+Data!AM24+Data!AM25+Data!AM26 -> -361981 | AE26: =Data!AN15+Data!AN16+Data!AN17+Data!AN18+Data!AN19+Data!AN20+Data!AN21+Data!AN22+Data!AN23+Data!AN24+Data!AN25+Data!AN26 -> 188036 | AF26: =Data!AO15+Data!AO16+Data!AO17+Data!AO18+Data!AO19+Data!AO20+Data!AO21+Data!AO22+Data!AO23+Data!AO24+Data!AO25+Data!AO26 -> -550016
B27: =Data!B27 -> 2017-09 | C27: =Data!D16+Data!E16+Data!F16+Data!G16+Data!H16+Data!I16+Data!J16+Data!K16+Data!L16+Data!M16+Data!N16+Data!O16+Data!P16+Data!Q16+Data!R16+Data!S16+Data!D17+Data!E17+Data!F17+Data!G17+Data!H17+Data!I17+Data!J17+Data!K17+Data!L17+Data!M17+Data!N17+Data!O17+Data!P17+Data!Q17+Data!R17+Data!S17+Data!D18+Data!E18+Data!F18+Data!G18+Data!H18+Data!I18+Data!J18+Data!K18+Data!L18+Data!M18+Data!N18+Data!O18+Data!P18+Data!Q18+Data!R18+Data!S18+Data!D19+Data!E19+Data!F19+Data!G19+Data!H19+Data!I19+Data!J19+Data!K19+Data!L19+Data!M19+Data!N19+Data!O19+Data!P19+Data!Q19+Data!R19+Data!S19+Data!D20+Data!E20+Data!F20+Data!G20+Data!H20+Data!I20+Data!J20+Data!K20+Data!L20+Data!M20+Data!N20+Data!O20+Data!P20+Data!Q20+Data!R20+Data!S20+Data!D21+Data!E21+Data!F21+Data!G21+Data!H21+Data!I21+Data!J21+Data!K21+Data!L21+Data!M21+Data!N21+Data!O21+Data!P21+Data!Q21+Data!R21+Data!S21+Data!D22+Data!E22+Data!F22+Data!G22+Data!H22+Data!I22+Data!J22+Data!K22+Data!L22+Data!M22+Data!N22+Data!O22+Data!P22+Data!Q22+Data!R22+Data!S22+Data!D23+Data!E23+Data!F23+Data!G23+Data!H23+Data!I23+Data!J23+Data!K23+Data!L23+Data!M23+Data!N23+Data!O23+Data!P23+Data!Q23+Data!R23+Data!S23+Data!D24+Data!E24+Data!F24+Data!G24+Data!H24+Data!I24+Data!J24+Data!K24+Data!L24+Data!M24+Data!N24+Data!O24+Data!P24+Data!Q24+Data!R24+Data!S24+Data!D25+Data!E25+Data!F25+Data!G25+Data!H25+Data!I25+Data!J25+Data!K25+Data!L25+Data!M25+Data!N25+Data!O25+Data!P25+Data!Q25+Data!R25+Data!S25+Data!D26+Data!E26+Data!F26+Data!G26+Data!H26+Data!I26+Data!J26+Data!K26+Data!L26+Data!M26+Data!N26+Data!O26+Data!P26+Data!Q26+Data!R26+Data!S26+Data!D27+Data!E27+Data!F27+Data!G27+Data!H27+Data!I27+Data!J27+Data!K27+Data!L27+Data!M27+Data!N27+Data!O27+Data!P27+Data!Q27+Data!R27+Data!S27 -> 1973973 | D27: =Data!D16+Data!E16+Data!G16+Data!H16+Data!I16+Data!J16+Data!K16+Data!L16+Data!M16+Data!D17+Data!E17+Data!G17+Data!H17+Data!I17+Data!J17+Data!K17+Data!L17+Data!M17+Data!D18+Data!E18+Data!G18+Data!H18+Data!I18+Data!J18+Data!K18+Data!L18+Data!M18+Data!D19+Data!E19+Data!G19+Data!H19+Data!I19+Data!J19+Data!K19+Data!L19+Data!M19+Data!D20+Data!E20+Data!G20+Data!H20+Data!I20+Data!J20+Data!K20+Data!L20+Data!M20+Data!D21+Data!E21+Data!G21+Data!H21+Data!I21+Data!J21+Data!K21+Data!L21+Data!M21+Data!D22+Data!E22+Data!G22+Data!H22+Data!I22+Data!J22+Data!K22+Data!L22+Data!M22+Data!D23+Data!E23+Data!G23+Data!H23+Data!I23+Data!J23+Data!K23+Data!L23+Data!M23+Data!D24+Data!E24+Data!G24+Data!H24+Data!I24+Data!J24+Data!K24+Data!L24+Data!M24+Data!D25+Data!E25+Data!G25+Data!H25+Data!I25+Data!J25+Data!K25+Data!L25+Data!M25+Data!D26+Data!E26+Data!G26+Data!H26+Data!I26+Data!J26+Data!K26+Data!L26+Data!M26+Data!D27+Data!E27+Data!G27+Data!H27+Data!I27+Data!J27+Data!K27+Data!L27+Data!M27 -> 1157654 | E27: =Data!D16+Data!D17+Data!D18+Data!D19+Data!D20+Data!D21+Data!D22+Data!D23+Data!D24+Data!D25+Data!D26+Data!D27 -> 320302 | F27: =Data!E16+Data!E17+Data!E18+Data!E19+Data!E20+Data!E21+Data!E22+Data!E23+Data!E24+Data!E25+Data!E26+Data!E27 -> 258254 | G27: =Data!K16+Data!K17+Data!K18+Data!K19+Data!K20+Data!K21+Data!K22+Data!K23+Data!K24+Data!K25+Data!K26+Data!K27 -> 66596 | H27: =Data!L16+Data!L17+Data!L18+Data!L19+Data!L20+Data!L21+Data!L22+Data!L23+Data!L24+Data!L25+Data!L26+Data!L27 -> 62867 | I27: =Data!G16+Data!G17+Data!G18+Data!G19+Data!G20+Data!G21+Data!G22+Data!G23+Data!G24+Data!G25+Data!G26+Data!G27 -> 132754 | J27: =Data!H16+Data!I16+Data!J16+Data!M16+Data!H17+Data!I17+Data!J17+Data!M17+Data!H18+Data!I18+Data!J18+Data!M18+Data!H19+Data!I19+Data!J19+Data!M19+Data!H20+Data!I20+Data!J20+Data!M20+Data!H21+Data!I21+Data!J21+Data!M21+Data!H22+Data!I22+Data!J22+Data!M22+Data!H23+Data!I23+Data!J23+Data!M23+Data!H24+Data!I24+Data!J24+Data!M24+Data!H25+Data!I25+Data!J25+Data!M25+Data!H26+Data!I26+Data!J26+Data!M26+Data!H27+Data!I27+Data!J27+Data!M27 -> 316881 | K27: =Data!F16+Data!F17+Data!F18+Data!F19+Data!F20+Data!F21+Data!F22+Data!F23+Data!F24+Data!F25+Data!F26+Data!F27 -> 689292 | L27: =Data!N16+Data!O16+Data!P16+Data!Q16+Data!R16+Data!S16+Data!N17+Data!O17+Data!P17+Data!Q17+Data!R17+Data!S17+Data!N18+Data!O18+Data!P18+Data!Q18+Data!R18+Data!S18+Data!N19+Data!O19+Data!P19+Data!Q19+Data!R19+Data!S19+Data!N20+Data!O20+Data!P20+Data!Q20+Data!R20+Data!S20+Data!N21+Data!O21+Data!P21+Data!Q21+Data!R21+Data!S21+Data!N22+Data!O22+Data!P22+Data!Q22+Data!R22+Data!S22+Data!N23+Data!O23+Data!P23+Data!Q23+Data!R23+Data!S23+Data!N24+Data!O24+Data!P24+Data!Q24+Data!R24+Data!S24+Data!N25+Data!O25+Data!P25+Data!Q25+Data!R25+Data!S25+Data!N26+Data!O26+Data!P26+Data!Q26+Data!R26+Data!S26+Data!N27+Data!O27+Data!P27+Data!Q27+Data!R27+Data!S27 -> 127027 | M27: =Data!T16+Data!U16+Data!V16+Data!W16+Data!X16+Data!Y16+Data!Z16+Data!AA16+Data!AB16+Data!AC16+Data!AD16+Data!AE16+Data!AF16+Data!AG16+Data!AH16+Data!AI16+Data!AJ16+Data!AK16+Data!AL16+Data!T17+Data!U17+Data!V17+Data!W17+Data!X17+Data!Y17+Data!Z17+Data!AA17+Data!AB17+Data!AC17+Data!AD17+Data!AE17+Data!AF17+Data!AG17+Data!AH17+Data!AI17+Data!AJ17+Data!AK17+Data!AL17+Data!T18+Data!U18+Data!V18+Data!W18+Data!X18+Data!Y18+Data!Z18+Data!AA18+Data!AB18+Data!AC18+Data!AD18+Data!AE18+Data!AF18+Data!AG18+Data!AH18+Data!AI18+Data!AJ18+Data!AK18+Data!AL18+Data!T19+Data!U19+Data!V19+Data!W19+Data!X19+Data!Y19+Data!Z19+Data!AA19+Data!AB19+Data!AC19+Data!AD19+Data!AE19+Data!AF19+Data!AG19+Data!AH19+Data!AI19+Data!AJ19+Data!AK19+Data!AL19+Data!T20+Data!U20+Data!V20+Data!W20+Data!X20+Data!Y20+Data!Z20+Data!AA20+Data!AB20+Data!AC20+Data!AD20+Data!AE20+Data!AF20+Data!AG20+Data!AH20+Data!AI20+Data!AJ20+Data!AK20+Data!AL20+Data!T21+Data!U21+Data!V21+Data!W21+Data!X21+Data!Y21+Data!Z21+Data!AA21+Data!AB21+Data!AC21+Data!AD21+Data!AE21+Data!AF21+Data!AG21+Data!AH21+Data!AI21+Data!AJ21+Data!AK21+Data!AL21+Data!T22+Data!U22+Data!V22+Data!W22+Data!X22+Data!Y22+Data!Z22+Data!AA22+Data!AB22+Data!AC22+Data!AD22+Data!AE22+Data!AF22+Data!AG22+Data!AH22+Data!AI22+Data!AJ22+Data!AK22+Data!AL22+Data!T23+Data!U23+Data!V23+Data!W23+Data!X23+Data!Y23+Data!Z23+Data!AA23+Data!AB23+Data!AC23+Data!AD23+Data!AE23+Data!AF23+Data!AG23+Data!AH23+Data!AI23+Data!AJ23+Data!AK23+Data!AL23+Data!T24+Data!U24+Data!V24+Data!W24+Data!X24+Data!Y24+Data!Z24+Data!AA24+Data!AB24+Data!AC24+Data!AD24+Data!AE24+Data!AF24+Data!AG24+Data!AH24+Data!AI24+Data!AJ24+Data!AK24+Data!AL24+Data!T25+Data!U25+Data!V25+Data!W25+Data!X25+Data!Y25+Data!Z25+Data!AA25+Data!AB25+Data!AC25+Data!AD25+Data!AE25+Data!AF25+Data!AG25+Data!AH25+Data!AI25+Data!AJ25+Data!AK25+Data!AL25+Data!T26+Data!U26+Data!V26+Data!W26+Data!X26+Data!Y26+Data!Z26+Data!AA26+Data!AB26+Data!AC26+Data!AD26+Data!AE26+Data!AF26+Data!AG26+Data!AH26+Data!AI26+Data!AJ26+Data!AK26+Data!AL26+Data!T27+Data!U27+Data!V27+Data!W27+Data!X27+Data!Y27+Data!Z27+Data!AA27+Data!AB27+Data!AC27+Data!AD27+Data!AE27+Data!AF27+Data!AG27+Data!AH27+Data!AI27+Data!AJ27+Data!AK27+Data!AL27 -> 2330290 | N27: =Data!T16+Data!U16+Data!V16+Data!W16+Data!T17+Data!U17+Data!V17+Data!W17+Data!T18+Data!U18+Data!V18+Data!W18+Data!T19+Data!U19+Data!V19+Data!W19+Data!T20+Data!U20+Data!V20+Data!W20+Data!T21+Data!U21+Data!V21+Data!W21+Data!T22+Data!U22+Data!V22+Data!W22+Data!T23+Data!U23+Data!V23+Data!W23+Data!T24+Data!U24+Data!V24+Data!W24+Data!T25+Data!U25+Data!V25+Data!W25+Data!T26+Data!U26+Data!V26+Data!W26+Data!T27+Data!U27+Data!V27+Data!W27 -> 1173159 | O27: =Data!T16+Data!T17+Data!T18+Data!T19+Data!T20+Data!T21+Data!T22+Data!T23+Data!T24+Data!T25+Data!T26+Data!T27 -> 843827 | P27: =Data!U16+Data!U17+Data!U18+Data!U19+Data!U20+Data!U21+Data!U22+Data!U23+Data!U24+Data!U25+Data!U26+Data!U27 -> 135983 | Q27: =Data!V16+Data!V17+Data!V18+Data!V19+Data!V20+Data!V21+Data!V22+Data!V23+Data!V24+Data!V25+Data!V26+Data!V27 -> 95312 | R27: =Data!W16+Data!W17+Data!W18+Data!W19+Data!W20+Data!W21+Data!W22+Data!W23+Data!W24+Data!W25+Data!W26+Data!W27 -> 98037 | S27: =Data!X16+Data!X17+Data!X18+Data!X19+Data!X20+Data!X21+Data!X22+Data!X23+Data!X24+Data!X25+Data!X26+Data!X27 -> 38156 | T27: =Data!Y16+Data!Z16+Data!AA16+Data!Y17+Data!Z17+Data!AA17+Data!Y18+Data!Z18+Data!AA18+Data!Y19+Data!Z19+Data!AA19+Data!Y20+Data!Z20+Data!AA20+Data!Y21+Data!Z21+Data!AA21+Data!Y22+Data!Z22+Data!AA22+Data!Y23+Data!Z23+Data!AA23+Data!Y24+Data!Z24+Data!AA24+Data!Y25+Data!Z25+Data!AA25+Data!Y26+Data!Z26+Data!AA26+Data!Y27+Data!Z27+Data!AA27 -> 259660 | U27: =Data!Y16+Data!Y17+Data!Y18+Data!Y19+Data!Y20+Data!Y21+Data!Y22+Data!Y23+Data!Y24+Data!Y25+Data!Y26+Data!Y27 -> 166291 | V27: =Data!Z16+Data!Z17+Data!Z18+Data!Z19+Data!Z20+Data!Z21+Data!Z22+Data!Z23+Data!Z24+Data!Z25+Data!Z26+Data!Z27 -> 85181 | W27: =Data!AB16+Data!AB17+Data!AB18+Data!AB19+Data!AB20+Data!AB21+Data!AB22+Data!AB23+Data!AB24+Data!AB25+Data!AB26+Data!AB27 -> 318996 | X27: =Data!AC16+Data!AC17+Data!AC18+Data!AC19+Data!AC20+Data!AC21+Data!AC22+Data!AC23+Data!AC24+Data!AC25+Data!AC26+Data!AC27 -> 102281 | Y27: =Data!AD16+Data!AE16+Data!AF16+Data!AG16+Data!AH16+Data!AD17+Data!AE17+Data!AF17+Data!AG17+Data!AH17+Data!AD18+Data!AE18+Data!AF18+Data!AG18+Data!AH18+Data!AD19+Data!AE19+Data!AF19+Data!AG19+Data!AH19+Data!AD20+Data!AE20+Data!AF20+Data!AG20+Data!AH20+Data!AD21+Data!AE21+Data!AF21+Data!AG21+Data!AH21+Data!AD22+Data!AE22+Data!AF22+Data!AG22+Data!AH22+Data!AD23+Data!AE23+Data!AF23+Data!AG23+Data!AH23+Data!AD24+Data!AE24+Data!AF24+Data!AG24+Data!AH24+Data!AD25+Data!AE25+Data!AF25+Data!AG25+Data!AH25+Data!AD26+Data!AE26+Data!AF26+Data!AG26+Data!AH26+Data!AD27+Data!AE27+Data!AF27+Data!AG27+Data!AH27 -> 85932 | Z27: =Data!AI16+Data!AI17+Data!AI18+Data!AI19+Data!AI20+Data!AI21+Data!AI22+Data!AI23+Data!AI24+Data!AI25+Data!AI26+Data!AI27 -> 78922 | AA27: =Data!AJ16+Data!AJ17+Data!AJ18+Data!AJ19+Data!AJ20+Data!AJ21+Data!AJ22+Data!AJ23+Data!AJ24+Data!AJ25+Data!AJ26+Data!AJ27 -> 7787 | AB27: =Data!AK16+Data!AK17+Data!AK18+Data!AK19+Data!AK20+Data!AK21+Data!AK22+Data!AK23+Data!AK24+Data!AK25+Data!AK26+Data!AK27 -> 46639 | AC27: =Data!AL16+Data!AL17+Data!AL18+Data!AL19+Data!AL20+Data!AL21+Data!AL22+Data!AL23+Data!AL24+Data!AL25+Data!AL26+Data!AL27 -> 218758 | AD27: =Data!AM16+Data!AM17+Data!AM18+Data!AM19+Data!AM20+Data!AM21+Data!AM22+Data!AM23+Data!AM24+Data!AM25+Data!AM26+Data!AM27 -> -356317 | AE27: =Data!AN16+Data!AN17+Data!AN18+Data!AN19+Data!AN20+Data!AN21+Data!AN22+Data!AN23+Data!AN24+Data!AN25+Data!AN26+Data!AN27 -> 195881 | AF27: =Data!AO16+Data!AO17+Data!AO18+Data!AO19+Data!AO20+Data!AO21+Data!AO22+Data!AO23+Data!AO24+Data!AO25+Data!AO26+Data!AO27 -> -552197
B28: =Data!B28 -> 2017-10 | C28: =Data!D17+Data!E17+Data!F17+Data!G17+Data!H17+Data!I17+Data!J17+Data!K17+Data!L17+Data!M17+Data!N17+Data!O17+Data!P17+Data!Q17+Data!R17+Data!S17+Data!D18+Data!E18+Data!F18+Data!G18+Data!H18+Data!I18+Data!J18+Data!K18+Data!L18+Data!M18+Data!N18+Data!O18+Data!P18+Data!Q18+Data!R18+Data!S18+Data!D19+Data!E19+Data!F19+Data!G19+Data!H19+Data!I19+Data!J19+Data!K19+Data!L19+Data!M19+Data!N19+Data!O19+Data!P19+Data!Q19+Data!R19+Data!S19+Data!D20+Data!E20+Data!F20+Data!G20+Data!H20+Data!I20+Data!J20+Data!K20+Data!L20+Data!M20+Data!N20+Data!O20+Data!P20+Data!Q20+Data!R20+Data!S20+Data!D21+Data!E21+Data!F21+Data!G21+Data!H21+Data!I21+Data!J21+Data!K21+Data!L21+Data!M21+Data!N21+Data!O21+Data!P21+Data!Q21+Data!R21+Data!S21+Data!D22+Data!E22+Data!F22+Data!G22+Data!H22+Data!I22+Data!J22+Data!K22+Data!L22+Data!M22+Data!N22+Data!O22+Data!P22+Data!Q22+Data!R22+Data!S22+Data!D23+Data!E23+Data!F23+Data!G23+Data!H23+Data!I23+Data!J23+Data!K23+Data!L23+Data!M23+Data!N23+Data!O23+Data!P23+Data!Q23+Data!R23+Data!S23+Data!D24+Data!E24+Data!F24+Data!G24+Data!H24+Data!I24+Data!J24+Data!K24+Data!L24+Data!M24+Data!N24+Data!O24+Data!P24+Data!Q24+Data!R24+Data!S24+Data!D25+Data!E25+Data!F25+Data!G25+Data!H25+Data!I25+Data!J25+Data!K25+Data!L25+Data!M25+Data!N25+Data!O25+Data!P25+Data!Q25+Data!R25+Data!S25+Data!D26+Data!E26+Data!F26+Data!G26+Data!H26+Data!I26+Data!J26+Data!K26+Data!L26+Data!M26+Data!N26+Data!O26+Data!P26+Data!Q26+Data!R26+Data!S26+Data!D27+Data!E27+Data!F27+Data!G27+Data!H27+Data!I27+Data!J27+Data!K27+Data!L27+Data!M27+Data!N27+Data!O27+Data!P27+Data!Q27+Data!R27+Data!S27+Data!D28+Data!E28+Data!F28+Data!G28+Data!H28+Data!I28+Data!J28+Data!K28+Data!L28+Data!M28+Data!N28+Data!O28+Data!P28+Data!Q28+Data!R28+Data!S28 -> 2014656 | D28: =Data!D17+Data!E17+Data!G17+Data!H17+Data!I17+Data!J17+Data!K17+Data!L17+Data!M17+Data!D18+Data!E18+Data!G18+Data!H18+Data!I18+Data!J18+Data!K18+Data!L18+Data!M18+Data!D19+Data!E19+Data!G19+Data!H19+Data!I19+Data!J19+Data!K19+Data!L19+Data!M19+Data!D20+Data!E20+Data!G20+Data!H20+Data!I20+Data!J20+Data!K20+Data!L20+Data!M20+Data!D21+Data!E21+Data!G21+Data!H21+Data!I21+Data!J21+Data!K21+Data!L21+Data!M21+Data!D22+Data!E22+Data!G22+Data!H22+Data!I22+Data!J22+Data!K22+Data!L22+Data!M22+Data!D23+Data!E23+Data!G23+Data!H23+Data!I23+Data!J23+Data!K23+Data!L23+Data!M23+Data!D24+Data!E24+Data!G24+Data!H24+Data!I24+Data!J24+Data!K24+Data!L24+Data!M24+Data!D25+Data!E25+Data!G25+Data!H25+Data!I25+Data!J25+Data!K25+Data!L25+Data!M25+Data!D26+Data!E26+Data!G26+Data!H26+Data!I26+Data!J26+Data!K26+Data!L26+Data!M26+Data!D27+Data!E27+Data!G27+Data!H27+Data!I27+Data!J27+Data!K27+Data!L27+Data!M27+Data!D28+Data!E28+Data!G28+Data!H28+Data!I28+Data!J28+Data!K28+Data!L28+Data!M28 -> 1177081 | E28: =Data!D17+Data!D18+Data!D19+Data!D20+Data!D21+Data!D22+Data!D23+Data!D24+Data!D25+Data!D26+Data!D27+Data!D28 -> 329144 | F28: =Data!E17+Data!E18+Data!E19+Data!E20+Data!E21+Data!E22+Data!E23+Data!E24+Data!E25+Data!E26+Data!E27+Data!E28 -> 264450 | G28: =Data!K17+Data!K18+Data!K19+Data!K20+Data!K21+Data!K22+Data!K23+Data!K24+Data!K25+Data!K26+Data!K27+Data!K28 -> 65830 | H28: =Data!L17+Data!L18+Data!L19+Data!L20+Data!L21+Data!L22+Data!L23+Data!L24+Data!L25+Data!L26+Data!L27+Data!L28 -> 64601 | I28: =Data!G17+Data!G18+Data!G19+Data!G20+Data!G21+Data!G22+Data!G23+Data!G24+Data!G25+Data!G26+Data!G27+Data!G28 -> 135360 | J28: =Data!H17+Data!I17+Data!J17+Data!M17+Data!H18+Data!I18+Data!J18+Data!M18+Data!H19+Data!I19+Data!J19+Data!M19+Data!H20+Data!I20+Data!J20+Data!M20+Data!H21+Data!I21+Data!J21+Data!M21+Data!H22+Data!I22+Data!J22+Data!M22+Data!H23+Data!I23+Data!J23+Data!M23+Data!H24+Data!I24+Data!J24+Data!M24+Data!H25+Data!I25+Data!J25+Data!M25+Data!H26+Data!I26+Data!J26+Data!M26+Data!H27+Data!I27+Data!J27+Data!M27+Data!H28+Data!I28+Data!J28+Data!M28 -> 317696 | K28: =Data!F17+Data!F18+Data!F19+Data!F20+Data!F21+Data!F22+Data!F23+Data!F24+Data!F25+Data!F26+Data!F27+Data!F28 -> 705281 | L28: =Data!N17+Data!O17+Data!P17+Data!Q17+Data!R17+Data!S17+Data!N18+Data!O18+Data!P18+Data!Q18+Data!R18+Data!S18+Data!N19+Data!O19+Data!P19+Data!Q19+Data!R19+Data!S19+Data!N20+Data!O20+Data!P20+Data!Q20+Data!R20+Data!S20+Data!N21+Data!O21+Data!P21+Data!Q21+Data!R21+Data!S21+Data!N22+Data!O22+Data!P22+Data!Q22+Data!R22+Data!S22+Data!N23+Data!O23+Data!P23+Data!Q23+Data!R23+Data!S23+Data!N24+Data!O24+Data!P24+Data!Q24+Data!R24+Data!S24+Data!N25+Data!O25+Data!P25+Data!Q25+Data!R25+Data!S25+Data!N26+Data!O26+Data!P26+Data!Q26+Data!R26+Data!S26+Data!N27+Data!O27+Data!P27+Data!Q27+Data!R27+Data!S27+Data!N28+Data!O28+Data!P28+Data!Q28+Data!R28+Data!S28 -> 132294 | M28: =Data!T17+Data!U17+Data!V17+Data!W17+Data!X17+Data!Y17+Data!Z17+Data!AA17+Data!AB17+Data!AC17+Data!AD17+Data!AE17+Data!AF17+Data!AG17+Data!AH17+Data!AI17+Data!AJ17+Data!AK17+Data!AL17+Data!T18+Data!U18+Data!V18+Data!W18+Data!X18+Data!Y18+Data!Z18+Data!AA18+Data!AB18+Data!AC18+Data!AD18+Data!AE18+Data!AF18+Data!AG18+Data!AH18+Data!AI18+Data!AJ18+Data!AK18+Data!AL18+Data!T19+Data!U19+Data!V19+Data!W19+Data!X19+Data!Y19+Data!Z19+Data!AA19+Data!AB19+Data!AC19+Data!AD19+Data!AE19+Data!AF19+Data!AG19+Data!AH19+Data!AI19+Data!AJ19+Data!AK19+Data!AL19+Data!T20+Data!U20+Data!V20+Data!W20+Data!X20+Data!Y20+Data!Z20+Data!AA20+Data!AB20+Data!AC20+Data!AD20+Data!AE20+Data!AF20+Data!AG20+Data!AH20+Data!AI20+Data!AJ20+Data!AK20+Data!AL20+Data!T21+Data!U21+Data!V21+Data!W21+Data!X21+Data!Y21+Data!Z21+Data!AA21+Data!AB21+Data!AC21+Data!AD21+Data!AE21+Data!AF21+Data!AG21+Data!AH21+Data!AI21+Data!AJ21+Data!AK21+Data!AL21+Data!T22+Data!U22+Data!V22+Data!W22+Data!X22+Data!Y22+Data!Z22+Data!AA22+Data!AB22+Data!AC22+Data!AD22+Data!AE22+Data!AF22+Data!AG22+Data!AH22+Data!AI22+Data!AJ22+Data!AK22+Data!AL22+Data!T23+Data!U23+Data!V23+Data!W23+Data!X23+Data!Y23+Data!Z23+Data!AA23+Data!AB23+Data!AC23+Data!AD23+Data!AE23+Data!AF23+Data!AG23+Data!AH23+Data!AI23+Data!AJ23+Data!AK23+Data!AL23+Data!T24+Data!U24+Data!V24+Data!W24+Data!X24+Data!Y24+Data!Z24+Data!AA24+Data!AB24+Data!AC24+Data!AD24+Data!AE24+Data!AF24+Data!AG24+Data!AH24+Data!AI24+Data!AJ24+Data!AK24+Data!AL24+Data!T25+Data!U25+Data!V25+Data!W25+Data!X25+Data!Y25+Data!Z25+Data!AA25+Data!AB25+Data!AC25+Data!AD25+Data!AE25+Data!AF25+Data!AG25+Data!AH25+Data!AI25+Data!AJ25+Data!AK25+Data!AL25+Data!T26+Data!U26+Data!V26+Data!W26+Data!X26+Data!Y26+Data!Z26+Data!AA26+Data!AB26+Data!AC26+Data!AD26+Data!AE26+Data!AF26+Data!AG26+Data!AH26+Data!AI26+Data!AJ26+Data!AK26+Data!AL26+Data!T27+Data!U27+Data!V27+Data!W27+Data!X27+Data!Y27+Data!Z27+Data!AA27+Data!AB27+Data!AC27+Data!AD27+Data!AE27+Data!AF27+Data!AG27+Data!AH27+Data!AI27+Data!AJ27+Data!AK27+Data!AL27+Data!T28+Data!U28+Data!V28+Data!W28+Data!X28+Data!Y28+Data!Z28+Data!AA28+Data!AB28+Data!AC28+Data!AD28+Data!AE28+Data!AF28+Data!AG28+Data!AH28+Data!AI28+Data!AJ28+Data!AK28+Data!AL28 -> 2341600 | N28: =Data!T17+Data!U17+Data!V17+Data!W17+Data!T18+Data!U18+Data!V18+Data!W18+Data!T19+Data!U19+Data!V19+Data!W19+Data!T20+Data!U20+Data!V20+Data!W20+Data!T21+Data!U21+Data!V21+Data!W21+Data!T22+Data!U22+Data!V22+Data!W22+Data!T23+Data!U23+Data!V23+Data!W23+Data!T24+Data!U24+Data!V24+Data!W24+Data!T25+Data!U25+Data!V25+Data!W25+Data!T26+Data!U26+Data!V26+Data!W26+Data!T27+Data!U27+Data!V27+Data!W27+Data!T28+Data!U28+Data!V28+Data!W28 -> 1202068 | O28: =Data!T17+Data!T18+Data!T19+Data!T20+Data!T21+Data!T22+Data!T23+Data!T24+Data!T25+Data!T26+Data!T27+Data!T28 -> 867978 | P28: =Data!U17+Data!U18+Data!U19+Data!U20+Data!U21+Data!U22+Data!U23+Data!U24+Data!U25+Data!U26+Data!U27+Data!U28 -> 138457 | Q28: =Data!V17+Data!V18+Data!V19+Data!V20+Data!V21+Data!V22+Data!V23+Data!V24+Data!V25+Data!V26+Data!V27+Data!V28 -> 97058 | R28: =Data!W17+Data!W18+Data!W19+Data!W20+Data!W21+Data!W22+Data!W23+Data!W24+Data!W25+Data!W26+Data!W27+Data!W28 -> 98575 | S28: =Data!X17+Data!X18+Data!X19+Data!X20+Data!X21+Data!X22+Data!X23+Data!X24+Data!X25+Data!X26+Data!X27+Data!X28 -> 38741 | T28: =Data!Y17+Data!Z17+Data!AA17+Data!Y18+Data!Z18+Data!AA18+Data!Y19+Data!Z19+Data!AA19+Data!Y20+Data!Z20+Data!AA20+Data!Y21+Data!Z21+Data!AA21+Data!Y22+Data!Z22+Data!AA22+Data!Y23+Data!Z23+Data!AA23+Data!Y24+Data!Z24+Data!AA24+Data!Y25+Data!Z25+Data!AA25+Data!Y26+Data!Z26+Data!AA26+Data!Y27+Data!Z27+Data!AA27+Data!Y28+Data!Z28+Data!AA28 -> 243583 | U28: =Data!Y17+Data!Y18+Data!Y19+Data!Y20+Data!Y21+Data!Y22+Data!Y23+Data!Y24+Data!Y25+Data!Y26+Data!Y27+Data!Y28 -> 149620 | V28: =Data!Z17+Data!Z18+Data!Z19+Data!Z20+Data!Z21+Data!Z22+Data!Z23+Data!Z24+Data!Z25+Data!Z26+Data!Z27+Data!Z28 -> 85078 | W28: =Data!AB17+Data!AB18+Data!AB19+Data!AB20+Data!AB21+Data!AB22+Data!AB23+Data!AB24+Data!AB25+Data!AB26+Data!AB27+Data!AB28 -> 323060 | X28: =Data!AC17+Data!AC18+Data!AC19+Data!AC20+Data!AC21+Data!AC22+Data!AC23+Data!AC24+Data!AC25+Data!AC26+Data!AC27+Data!AC28 -> 99588 | Y28: =Data!AD17+Data!AE17+Data!AF17+Data!AG17+Data!AH17+Data!AD18+Data!AE18+Data!AF18+Data!AG18+Data!AH18+Data!AD19+Data!AE19+Data!AF19+Data!AG19+Data!AH19+Data!AD20+Data!AE20+Data!AF20+Data!AG20+Data!AH20+Data!AD21+Data!AE21+Data!AF21+Data!AG21+Data!AH21+Data!AD22+Data!AE22+Data!AF22+Data!AG22+Data!AH22+Data!AD23+Data!AE23+Data!AF23+Data!AG23+Data!AH23+Data!AD24+Data!AE24+Data!AF24+Data!AG24+Data!AH24+Data!AD25+Data!AE25+Data!AF25+Data!AG25+Data!AH25+Data!AD26+Data!AE26+Data!AF26+Data!AG26+Data!AH26+Data!AD27+Data!AE27+Data!AF27+Data!AG27+Data!AH27+Data!AD28+Data!AE28+Data!AF28+Data!AG28+Data!AH28 -> 85933 | Z28: =Data!AI17+Data!AI18+Data!AI19+Data!AI20+Data!AI21+Data!AI22+Data!AI23+Data!AI24+Data!AI25+Data!AI26+Data!AI27+Data!AI28 -> 80514 | AA28: =Data!AJ17+Data!AJ18+Data!AJ19+Data!AJ20+Data!AJ21+Data!AJ22+Data!AJ23+Data!AJ24+Data!AJ25+Data!AJ26+Data!AJ27+Data!AJ28 -> 8535 | AB28: =Data!AK17+Data!AK18+Data!AK19+Data!AK20+Data!AK21+Data!AK22+Data!AK23+Data!AK24+Data!AK25+Data!AK26+Data!AK27+Data!AK28 -> 47236 | AC28: =Data!AL17+Data!AL18+Data!AL19+Data!AL20+Data!AL21+Data!AL22+Data!AL23+Data!AL24+Data!AL25+Data!AL26+Data!AL27+Data!AL28 -> 212342 | AD28: =Data!AM17+Data!AM18+Data!AM19+Data!AM20+Data!AM21+Data!AM22+Data!AM23+Data!AM24+Data!AM25+Data!AM26+Data!AM27+Data!AM28 -> -326944 | AE28: =Data!AN17+Data!AN18+Data!AN19+Data!AN20+Data!AN21+Data!AN22+Data!AN23+Data!AN24+Data!AN25+Data!AN26+Data!AN27+Data!AN28 -> 209686 | AF28: =Data!AO17+Data!AO18+Data!AO19+Data!AO20+Data!AO21+Data!AO22+Data!AO23+Data!AO24+Data!AO25+Data!AO26+Data!AO27+Data!AO28 -> -536629
B29: =Data!B29 -> 2017-11 | C29: =Data!D18+Data!E18+Data!F18+Data!G18+Data!H18+Data!I18+Data!J18+Data!K18+Data!L18+Data!M18+Data!N18+Data!O18+Data!P18+Data!Q18+Data!R18+Data!S18+Data!D19+Data!E19+Data!F19+Data!G19+Data!H19+Data!I19+Data!J19+Data!K19+Data!L19+Data!M19+Data!N19+Data!O19+Data!P19+Data!Q19+Data!R19+Data!S19+Data!D20+Data!E20+Data!F20+Data!G20+Data!H20+Data!I20+Data!J20+Data!K20+Data!L20+Data!M20+Data!N20+Data!O20+Data!P20+Data!Q20+Data!R20+Data!S20+Data!D21+Data!E21+Data!F21+Data!G21+Data!H21+Data!I21+Data!J21+Data!K21+Data!L21+Data!M21+Data!N21+Data!O21+Data!P21+Data!Q21+Data!R21+Data!S21+Data!D22+Data!E22+Data!F22+Data!G22+Data!H22+Data!I22+Data!J22+Data!K22+Data!L22+Data!M22+Data!N22+Data!O22+Data!P22+Data!Q22+Data!R22+Data!S22+Data!D23+Data!E23+Data!F23+Data!G23+Data!H23+Data!I23+Data!J23+Data!K23+Data!L23+Data!M23+Data!N23+Data!O23+Data!P23+Data!Q23+Data!R23+Data!S23+Data!D24+Data!E24+Data!F24+Data!G24+Data!H24+Data!I24+Data!J24+Data!K24+Data!L24+Data!M24+Data!N24+Data!O24+Data!P24+Data!Q24+Data!R24+Data!S24+Data!D25+Data!E25+Data!F25+Data!G25+Data!H25+Data!I25+Data!J25+Data!K25+Data!L25+Data!M25+Data!N25+Data!O25+Data!P25+Data!Q25+Data!R25+Data!S25+Data!D26+Data!E26+Data!F26+Data!G26+Data!H26+Data!I26+Data!J26+Data!K26+Data!L26+Data!M26+Data!N26+Data!O26+Data!P26+Data!Q26+Data!R26+Data!S26+Data!D27+Data!E27+Data!F27+Data!G27+Data!H27+Data!I27+Data!J27+Data!K27+Data!L27+Data!M27+Data!N27+Data!O27+Data!P27+Data!Q27+Data!R27+Data!S27+Data!D28+Data!E28+Data!F28+Data!G28+Data!H28+Data!I28+Data!J28+Data!K28+Data!L28+Data!M28+Data!N28+Data!O28+Data!P28+Data!Q28+Data!R28+Data!S28+Data!D29+Data!E29+Data!F29+Data!G29+Data!H29+Data!I29+Data!J29+Data!K29+Data!L29+Data!M29+Data!N29+Data!O29+Data!P29+Data!Q29+Data!R29+Data!S29 -> 2041545 | D29: =Data!D18+Data!E18+Data!G18+Data!H18+Data!I18+Data!J18+Data!K18+Data!L18+Data!M18+Data!D19+Data!E19+Data!G19+Data!H19+Data!I19+Data!J19+Data!K19+Data!L19+Data!M19+Data!D20+Data!E20+Data!G20+Data!H20+Data!I20+Data!J20+Data!K20+Data!L20+Data!M20+Data!D21+Data!E21+Data!G21+Data!H21+Data!I21+Data!J21+Data!K21+Data!L21+Data!M21+Data!D22+Data!E22+Data!G22+Data!H22+Data!I22+Data!J22+Data!K22+Data!L22+Data!M22+Data!D23+Data!E23+Data!G23+Data!H23+Data!I23+Data!J23+Data!K23+Data!L23+Data!M23+Data!D24+Data!E24+Data!G24+Data!H24+Data!I24+Data!J24+Data!K24+Data!L24+Data!M24+Data!D25+Data!E25+Data!G25+Data!H25+Data!I25+Data!J25+Data!K25+Data!L25+Data!M25+Data!D26+Data!E26+Data!G26+Data!H26+Data!I26+Data!J26+Data!K26+Data!L26+Data!M26+Data!D27+Data!E27+Data!G27+Data!H27+Data!I27+Data!J27+Data!K27+Data!L27+Data!M27+Data!D28+Data!E28+Data!G28+Data!H28+Data!I28+Data!J28+Data!K28+Data!L28+Data!M28+Data!D29+Data!E29+Data!G29+Data!H29+Data!I29+Data!J29+Data!K29+Data!L29+Data!M29 -> 1187490 | E29: =Data!D18+Data!D19+Data!D20+Data!D21+Data!D22+Data!D23+Data!D24+Data!D25+Data!D26+Data!D27+Data!D28+Data!D29 -> 339075 | F29: =Data!E18+Data!E19+Data!E20+Data!E21+Data!E22+Data!E23+Data!E24+Data!E25+Data!E26+Data!E27+Data!E28+Data!E29 -> 268591 | G29: =Data!K18+Data!K19+Data!K20+Data!K21+Data!K22+Data!K23+Data!K24+Data!K25+Data!K26+Data!K27+Data!K28+Data!K29 -> 65591 | H29: =Data!L18+Data!L19+Data!L20+Data!L21+Data!L22+Data!L23+Data!L24+Data!L25+Data!L26+Data!L27+Data!L28+Data!L29 -> 66786 | I29: =Data!G18+Data!G19+Data!G20+Data!G21+Data!G22+Data!G23+Data!G24+Data!G25+Data!G26+Data!G27+Data!G28+Data!G29 -> 138120 | J29: =Data!H18+Data!I18+Data!J18+Data!M18+Data!H19+Data!I19+Data!J19+Data!M19+Data!H20+Data!I20+Data!J20+Data!M20+Data!H21+Data!I21+Data!J21+Data!M21+Data!H22+Data!I22+Data!J22+Data!M22+Data!H23+Data!I23+Data!J23+Data!M23+Data!H24+Data!I24+Data!J24+Data!M24+Data!H25+Data!I25+Data!J25+Data!M25+Data!H26+Data!I26+Data!J26+Data!M26+Data!H27+Data!I27+Data!J27+Data!M27+Data!H28+Data!I28+Data!J28+Data!M28+Data!H29+Data!I29+Data!J29+Data!M29 -> 309327 | K29: =Data!F18+Data!F19+Data!F20+Data!F21+Data!F22+Data!F23+Data!F24+Data!F25+Data!F26+Data!F27+Data!F28+Data!F29 -> 715754 | L29: =Data!N18+Data!O18+Data!P18+Data!Q18+Data!R18+Data!S18+Data!N19+Data!O19+Data!P19+Data!Q19+Data!R19+Data!S19+Data!N20+Data!O20+Data!P20+Data!Q20+Data!R20+Data!S20+Data!N21+Data!O21+Data!P21+Data!Q21+Data!R21+Data!S21+Data!N22+Data!O22+Data!P22+Data!Q22+Data!R22+Data!S22+Data!N23+Data!O23+Data!P23+Data!Q23+Data!R23+Data!S23+Data!N24+Data!O24+Data!P24+Data!Q24+Data!R24+Data!S24+Data!N25+Data!O25+Data!P25+Data!Q25+Data!R25+Data!S25+Data!N26+Data!O26+Data!P26+Data!Q26+Data!R26+Data!S26+Data!N27+Data!O27+Data!P27+Data!Q27+Data!R27+Data!S27+Data!N28+Data!O28+Data!P28+Data!Q28+Data!R28+Data!S28+Data!N29+Data!O29+Data!P29+Data!Q29+Data!R29+Data!S29 -> 138301 | M29: =Data!T18+Data!U18+Data!V18+Data!W18+Data!X18+Data!Y18+Data!Z18+Data!AA18+Data!AB18+Data!AC18+Data!AD18+Data!AE18+Data!AF18+Data!AG18+Data!AH18+Data!AI18+Data!AJ18+Data!AK18+Data!AL18+Data!T19+Data!U19+Data!V19+Data!W19+Data!X19+Data!Y19+Data!Z19+Data!AA19+Data!AB19+Data!AC19+Data!AD19+Data!AE19+Data!AF19+Data!AG19+Data!AH19+Data!AI19+Data!AJ19+Data!AK19+Data!AL19+Data!T20+Data!U20+Data!V20+Data!W20+Data!X20+Data!Y20+Data!Z20+Data!AA20+Data!AB20+Data!AC20+Data!AD20+Data!AE20+Data!AF20+Data!AG20+Data!AH20+Data!AI20+Data!AJ20+Data!AK20+Data!AL20+Data!T21+Data!U21+Data!V21+Data!W21+Data!X21+Data!Y21+Data!Z21+Data!AA21+Data!AB21+Data!AC21+Data!AD21+Data!AE21+Data!AF21+Data!AG21+Data!AH21+Data!AI21+Data!AJ21+Data!AK21+Data!AL21+Data!T22+Data!U22+Data!V22+Data!W22+Data!X22+Data!Y22+Data!Z22+Data!AA22+Data!AB22+Data!AC22+Data!AD22+Data!AE22+Data!AF22+Data!AG22+Data!AH22+Data!AI22+Data!AJ22+Data!AK22+Data!AL22+Data!T23+Data!U23+Data!V23+Data!W23+Data!X23+Data!Y23+Data!Z23+Data!AA23+Data!AB23+Data!AC23+Data!AD23+Data!AE23+Data!AF23+Data!AG23+Data!AH23+Data!AI23+Data!AJ23+Data!AK23+Data!AL23+Data!T24+Data!U24+Data!V24+Data!W24+Data!X24+Data!Y24+Data!Z24+Data!AA24+Data!AB24+Data!AC24+Data!AD24+Data!AE24+Data!AF24+Data!AG24+Data!AH24+Data!AI24+Data!AJ24+Data!AK24+Data!AL24+Data!T25+Data!U25+Data!V25+Data!W25+Data!X25+Data!Y25+Data!Z25+Data!AA25+Data!AB25+Data!AC25+Data!AD25+Data!AE25+Data!AF25+Data!AG25+Data!AH25+Data!AI25+Data!AJ25+Data!AK25+Data!AL25+Data!T26+Data!U26+Data!V26+Data!W26+Data!X26+Data!Y26+Data!Z26+Data!AA26+Data!AB26+Data!AC26+Data!AD26+Data!AE26+Data!AF26+Data!AG26+Data!AH26+Data!AI26+Data!AJ26+Data!AK26+Data!AL26+Data!T27+Data!U27+Data!V27+Data!W27+Data!X27+Data!Y27+Data!Z27+Data!AA27+Data!AB27+Data!AC27+Data!AD27+Data!AE27+Data!AF27+Data!AG27+Data!AH27+Data!AI27+Data!AJ27+Data!AK27+Data!AL27+Data!T28+Data!U28+Data!V28+Data!W28+Data!X28+Data!Y28+Data!Z28+Data!AA28+Data!AB28+Data!AC28+Data!AD28+Data!AE28+Data!AF28+Data!AG28+Data!AH28+Data!AI28+Data!AJ28+Data!AK28+Data!AL28+Data!T29+Data!U29+Data!V29+Data!W29+Data!X29+Data!Y29+Data!Z29+Data!AA29+Data!AB29+Data!AC29+Data!AD29+Data!AE29+Data!AF29+Data!AG29+Data!AH29+Data!AI29+Data!AJ29+Data!AK29+Data!AL29 -> 2384850 | N29: =Data!T18+Data!U18+Data!V18+Data!W18+Data!T19+Data!U19+Data!V19+Data!W19+Data!T20+Data!U20+Data!V20+Data!W20+Data!T21+Data!U21+Data!V21+Data!W21+Data!T22+Data!U22+Data!V22+Data!W22+Data!T23+Data!U23+Data!V23+Data!W23+Data!T24+Data!U24+Data!V24+Data!W24+Data!T25+Data!U25+Data!V25+Data!W25+Data!T26+Data!U26+Data!V26+Data!W26+Data!T27+Data!U27+Data!V27+Data!W27+Data!T28+Data!U28+Data!V28+Data!W28+Data!T29+Data!U29+Data!V29+Data!W29 -> 1229703 | O29: =Data!T18+Data!T19+Data!T20+Data!T21+Data!T22+Data!T23+Data!T24+Data!T25+Data!T26+Data!T27+Data!T28+Data!T29 -> 891401 | P29: =Data!U18+Data!U19+Data!U20+Data!U21+Data!U22+Data!U23+Data!U24+Data!U25+Data!U26+Data!U27+Data!U28+Data!U29 -> 141140 | Q29: =Data!V18+Data!V19+Data!V20+Data!V21+Data!V22+Data!V23+Data!V24+Data!V25+Data!V26+Data!V27+Data!V28+Data!V29 -> 96860 | R29: =Data!W18+Data!W19+Data!W20+Data!W21+Data!W22+Data!W23+Data!W24+Data!W25+Data!W26+Data!W27+Data!W28+Data!W29 -> 100302 | S29: =Data!X18+Data!X19+Data!X20+Data!X21+Data!X22+Data!X23+Data!X24+Data!X25+Data!X26+Data!X27+Data!X28+Data!X29 -> 40523 | T29: =Data!Y18+Data!Z18+Data!AA18+Data!Y19+Data!Z19+Data!AA19+Data!Y20+Data!Z20+Data!AA20+Data!Y21+Data!Z21+Data!AA21+Data!Y22+Data!Z22+Data!AA22+Data!Y23+Data!Z23+Data!AA23+Data!Y24+Data!Z24+Data!AA24+Data!Y25+Data!Z25+Data!AA25+Data!Y26+Data!Z26+Data!AA26+Data!Y27+Data!Z27+Data!AA27+Data!Y28+Data!Z28+Data!AA28+Data!Y29+Data!Z29+Data!AA29 -> 243214 | U29: =Data!Y18+Data!Y19+Data!Y20+Data!Y21+Data!Y22+Data!Y23+Data!Y24+Data!Y25+Data!Y26+Data!Y27+Data!Y28+Data!Y29 -> 147288 | V29: =Data!Z18+Data!Z19+Data!Z20+Data!Z21+Data!Z22+Data!Z23+Data!Z24+Data!Z25+Data!Z26+Data!Z27+Data!Z28+Data!Z29 -> 86820 | W29: =Data!AB18+Data!AB19+Data!AB20+Data!AB21+Data!AB22+Data!AB23+Data!AB24+Data!AB25+Data!AB26+Data!AB27+Data!AB28+Data!AB29 -> 328647 | X29: =Data!AC18+Data!AC19+Data!AC20+Data!AC21+Data!AC22+Data!AC23+Data!AC24+Data!AC25+Data!AC26+Data!AC27+Data!AC28+Data!AC29 -> 103073 | Y29: =Data!AD18+Data!AE18+Data!AF18+Data!AG18+Data!AH18+Data!AD19+Data!AE19+Data!AF19+Data!AG19+Data!AH19+Data!AD20+Data!AE20+Data!AF20+Data!AG20+Data!AH20+Data!AD21+Data!AE21+Data!AF21+Data!AG21+Data!AH21+Data!AD22+Data!AE22+Data!AF22+Data!AG22+Data!AH22+Data!AD23+Data!AE23+Data!AF23+Data!AG23+Data!AH23+Data!AD24+Data!AE24+Data!AF24+Data!AG24+Data!AH24+Data!AD25+Data!AE25+Data!AF25+Data!AG25+Data!AH25+Data!AD26+Data!AE26+Data!AF26+Data!AG26+Data!AH26+Data!AD27+Data!AE27+Data!AF27+Data!AG27+Data!AH27+Data!AD28+Data!AE28+Data!AF28+Data!AG28+Data!AH28+Data!AD29+Data!AE29+Data!AF29+Data!AG29+Data!AH29 -> 86127 | Z29: =Data!AI18+Data!AI19+Data!AI20+Data!AI21+Data!AI22+Data!AI23+Data!AI24+Data!AI25+Data!AI26+Data!AI27+Data!AI28+Data!AI29 -> 82347 | AA29: =Data!AJ18+Data!AJ19+Data!AJ20+Data!AJ21+Data!AJ22+Data!AJ23+Data!AJ24+Data!AJ25+Data!AJ26+Data!AJ27+Data!AJ28+Data!AJ29 -> 8301 | AB29: =Data!AK18+Data!AK19+Data!AK20+Data!AK21+Data!AK22+Data!AK23+Data!AK24+Data!AK25+Data!AK26+Data!AK27+Data!AK28+Data!AK29 -> 49439 | AC29: =Data!AL18+Data!AL19+Data!AL20+Data!AL21+Data!AL22+Data!AL23+Data!AL24+Data!AL25+Data!AL26+Data!AL27+Data!AL28+Data!AL29 -> 213476 | AD29: =Data!AM18+Data!AM19+Data!AM20+Data!AM21+Data!AM22+Data!AM23+Data!AM24+Data!AM25+Data!AM26+Data!AM27+Data!AM28+Data!AM29 -> -343305 | AE29: =Data!AN18+Data!AN19+Data!AN20+Data!AN21+Data!AN22+Data!AN23+Data!AN24+Data!AN25+Data!AN26+Data!AN27+Data!AN28+Data!AN29 -> 219488 | AF29: =Data!AO18+Data!AO19+Data!AO20+Data!AO21+Data!AO22+Data!AO23+Data!AO24+Data!AO25+Data!AO26+Data!AO27+Data!AO28+Data!AO29 -> -562792
... B131: =Data!B131 -> 2026-05 | C131: =Data!D120+Data!E120+Data!F120+Data!G120+Data!H120+Data!I120+Data!J120+Data!K120+Data!L120+Data!M120+Data!N120+Data!O120+Data!P120+Data!Q120+Data!R120+Data!S120+Data!D121+Data!E121+Data!F121+Data!G121+Data!H121+Data!I121+Data!J121+Data!K121+Data!L121+Data!M121+Data!N121+Data!O121+Data!P121+Data!Q121+Data!R121+Data!S121+Data!D122+Data!E122+Data!F122+Data!G122+Data!H122+Data!I122+Data!J122+Data!K122+Data!L122+Data!M122+Data!N122+Data!O122+Data!P122+Data!Q122+Data!R122+Data!S122+Data!D123+Data!E123+Data!F123+Data!G123+Data!H123+Data!I123+Data!J123+Data!K123+Data!L123+Data!M123+Data!N123+Data!O123+Data!P123+Data!Q123+Data!R123+Data!S123+Data!D124+Data!E124+Data!F124+Data!G124+Data!H124+Data!I124+Data!J124+Data!K124+Data!L124+Data!M124+Data!N124+Data!O124+Data!P124+Data!Q124+Data!R124+Data!S124+Data!D125+Data!E125+Data!F125+Data!G125+Data!H125+Data!I125+Data!J125+Data!K125+Data!L125+Data!M125+Data!N125+Data!O125+Data!P125+Data!Q125+Data!R125+Data!S125+Data!D126+Data!E126+Data!F126+Data!G126+Data!H126+Data!I126+Data!J126+Data!K126+Data!L126+Data!M126+Data!N126+Data!O126+Data!P126+Data!Q126+Data!R126+Data!S126+Data!D127+Data!E127+Data!F127+Data!G127+Data!H127+Data!I127+Data!J127+Data!K127+Data!L127+Data!M127+Data!N127+Data!O127+Data!P127+Data!Q127+Data!R127+Data!S127+Data!D128+Data!E128+Data!F128+Data!G128+Data!H128+Data!I128+Data!J128+Data!K128+Data!L128+Data!M128+Data!N128+Data!O128+Data!P128+Data!Q128+Data!R128+Data!S128+Data!D129+Data!E129+Data!F129+Data!G129+Data!H129+Data!I129+Data!J129+Data!K129+Data!L129+Data!M129+Data!N129+Data!O129+Data!P129+Data!Q129+Data!R129+Data!S129+Data!D130+Data!E130+Data!F130+Data!G130+Data!H130+Data!I130+Data!J130+Data!K130+Data!L130+Data!M130+Data!N130+Data!O130+Data!P130+Data!Q130+Data!R130+Data!S130+Data!D131+Data!E131+Data!F131+Data!G131+Data!H131+Data!I131+Data!J131+Data!K131+Data!L131+Data!M131+Data!N131+Data!O131+Data!P131+Data!Q131+Data!R131+Data!S131 -> 149243585 | D131: =Data!D120+Data!E120+Data!G120+Data!H120+Data!I120+Data!J120+Data!K120+Data!L120+Data!M120+Data!D121+Data!E121+Data!G121+Data!H121+Data!I121+Data!J121+Data!K121+Data!L121+Data!M121+Data!D122+Data!E122+Data!G122+Data!H122+Data!I122+Data!J122+Data!K122+Data!L122+Data!M122+Data!D123+Data!E123+Data!G123+Data!H123+Data!I123+Data!J123+Data!K123+Data!L123+Data!M123+Data!D124+Data!E124+Data!G124+Data!H124+Data!I124+Data!J124+Data!K124+Data!L124+Data!M124+Data!D125+Data!E125+Data!G125+Data!H125+Data!I125+Data!J125+Data!K125+Data!L125+Data!M125+Data!D126+Data!E126+Data!G126+Data!H126+Data!I126+Data!J126+Data!K126+Data!L126+Data!M126+Data!D127+Data!E127+Data!G127+Data!H127+Data!I127+Data!J127+Data!K127+Data!L127+Data!M127+Data!D128+Data!E128+Data!G128+Data!H128+Data!I128+Data!J128+Data!K128+Data!L128+Data!M128+Data!D129+Data!E129+Data!G129+Data!H129+Data!I129+Data!J129+Data!K129+Data!L129+Data!M129+Data!D130+Data!E130+Data!G130+Data!H130+Data!I130+Data!J130+Data!K130+Data!L130+Data!M130+Data!D131+Data!E131+Data!G131+Data!H131+Data!I131+Data!J131+Data!K131+Data!L131+Data!M131 -> 83885327 | E131: =Data!D120+Data!D121+Data!D122+Data!D123+Data!D124+Data!D125+Data!D126+Data!D127+Data!D128+Data!D129+Data!D130+Data!D131 -> 30336733 | F131: =Data!E120+Data!E121+Data!E122+Data!E123+Data!E124+Data!E125+Data!E126+Data!E127+Data!E128+Data!E129+Data!E130+Data!E131 -> 14424986 | G131: =Data!K120+Data!K121+Data!K122+Data!K123+Data!K124+Data!K125+Data!K126+Data!K127+Data!K128+Data!K129+Data!K130+Data!K131 -> 6547802 | H131: =Data!L120+Data!L121+Data!L122+Data!L123+Data!L124+Data!L125+Data!L126+Data!L127+Data!L128+Data!L129+Data!L130+Data!L131 -> 5650073 | I131: =Data!G120+Data!G121+Data!G122+Data!G123+Data!G124+Data!G125+Data!G126+Data!G127+Data!G128+Data!G129+Data!G130+Data!G131 -> 15317925 | J131: =Data!H120+Data!I120+Data!J120+Data!M120+Data!H121+Data!I121+Data!J121+Data!M121+Data!H122+Data!I122+Data!J122+Data!M122+Data!H123+Data!I123+Data!J123+Data!M123+Data!H124+Data!I124+Data!J124+Data!M124+Data!H125+Data!I125+Data!J125+Data!M125+Data!H126+Data!I126+Data!J126+Data!M126+Data!H127+Data!I127+Data!J127+Data!M127+Data!H128+Data!I128+Data!J128+Data!M128+Data!H129+Data!I129+Data!J129+Data!M129+Data!H130+Data!I130+Data!J130+Data!M130+Data!H131+Data!I131+Data!J131+Data!M131 -> 11607808 | K131: =Data!F120+Data!F121+Data!F122+Data!F123+Data!F124+Data!F125+Data!F126+Data!F127+Data!F128+Data!F129+Data!F130+Data!F131 -> 52186514 | L131: =Data!N120+Data!O120+Data!P120+Data!Q120+Data!R120+Data!S120+Data!N121+Data!O121+Data!P121+Data!Q121+Data!R121+Data!S121+Data!N122+Data!O122+Data!P122+Data!Q122+Data!R122+Data!S122+Data!N123+Data!O123+Data!P123+Data!Q123+Data!R123+Data!S123+Data!N124+Data!O124+Data!P124+Data!Q124+Data!R124+Data!S124+Data!N125+Data!O125+Data!P125+Data!Q125+Data!R125+Data!S125+Data!N126+Data!O126+Data!P126+Data!Q126+Data!R126+Data!S126+Data!N127+Data!O127+Data!P127+Data!Q127+Data!R127+Data!S127+Data!N128+Data!O128+Data!P128+Data!Q128+Data!R128+Data!S128+Data!N129+Data!O129+Data!P129+Data!Q129+Data!R129+Data!S129+Data!N130+Data!O130+Data!P130+Data!Q130+Data!R130+Data!S130+Data!N131+Data!O131+Data!P131+Data!Q131+Data!R131+Data!S131 -> 13171744 | M131: =Data!T120+Data!U120+Data!V120+Data!W120+Data!X120+Data!Y120+Data!Z120+Data!AA120+Data!AB120+Data!AC120+Data!AD120+Data!AE120+Data!AF120+Data!AG120+Data!AH120+Data!AI120+Data!AJ120+Data!AK120+Data!AL120+Data!T121+Data!U121+Data!V121+Data!W121+Data!X121+Data!Y121+Data!Z121+Data!AA121+Data!AB121+Data!AC121+Data!AD121+Data!AE121+Data!AF121+Data!AG121+Data!AH121+Data!AI121+Data!AJ121+Data!AK121+Data!AL121+Data!T122+Data!U122+Data!V122+Data!W122+Data!X122+Data!Y122+Data!Z122+Data!AA122+Data!AB122+Data!AC122+Data!AD122+Data!AE122+Data!AF122+Data!AG122+Data!AH122+Data!AI122+Data!AJ122+Data!AK122+Data!AL122+Data!T123+Data!U123+Data!V123+Data!W123+Data!X123+Data!Y123+Data!Z123+Data!AA123+Data!AB123+Data!AC123+Data!AD123+Data!AE123+Data!AF123+Data!AG123+Data!AH123+Data!AI123+Data!AJ123+Data!AK123+Data!AL123+Data!T124+Data!U124+Data!V124+Data!W124+Data!X124+Data!Y124+Data!Z124+Data!AA124+Data!AB124+Data!AC124+Data!AD124+Data!AE124+Data!AF124+Data!AG124+Data!AH124+Data!AI124+Data!AJ124+Data!AK124+Data!AL124+Data!T125+Data!U125+Data!V125+Data!W125+Data!X125+Data!Y125+Data!Z125+Data!AA125+Data!AB125+Data!AC125+Data!AD125+Data!AE125+Data!AF125+Data!AG125+Data!AH125+Data!AI125+Data!AJ125+Data!AK125+Data!AL125+Data!T126+Data!U126+Data!V126+Data!W126+Data!X126+Data!Y126+Data!Z126+Data!AA126+Data!AB126+Data!AC126+Data!AD126+Data!AE126+Data!AF126+Data!AG126+Data!AH126+Data!AI126+Data!AJ126+Data!AK126+Data!AL126+Data!T127+Data!U127+Data!V127+Data!W127+Data!X127+Data!Y127+Data!Z127+Data!AA127+Data!AB127+Data!AC127+Data!AD127+Data!AE127+Data!AF127+Data!AG127+Data!AH127+Data!AI127+Data!AJ127+Data!AK127+Data!AL127+Data!T128+Data!U128+Data!V128+Data!W128+Data!X128+Data!Y128+Data!Z128+Data!AA128+Data!AB128+Data!AC128+Data!AD128+Data!AE128+Data!AF128+Data!AG128+Data!AH128+Data!AI128+Data!AJ128+Data!AK128+Data!AL128+Data!T129+Data!U129+Data!V129+Data!W129+Data!X129+Data!Y129+Data!Z129+Data!AA129+Data!AB129+Data!AC129+Data!AD129+Data!AE129+Data!AF129+Data!AG129+Data!AH129+Data!AI129+Data!AJ129+Data!AK129+Data!AL129+Data!T130+Data!U130+Data!V130+Data!W130+Data!X130+Data!Y130+Data!Z130+Data!AA130+Data!AB130+Data!AC130+Data!AD130+Data!AE130+Data!AF130+Data!AG130+Data!AH130+Data!AI130+Data!AJ130+Data!AK130+Data!AL130+Data!T131+Data!U131+Data!V131+Data!W131+Data!X131+Data!Y131+Data!Z131+Data!AA131+Data!AB131+Data!AC131+Data!AD131+Data!AE131+Data!AF131+Data!AG131+Data!AH131+Data!AI131+Data!AJ131+Data!AK131+Data!AL131 -> 136350481 | N131: =Data!T120+Data!U120+Data!V120+Data!W120+Data!T121+Data!U121+Data!V121+Data!W121+Data!T122+Data!U122+Data!V122+Data!W122+Data!T123+Data!U123+Data!V123+Data!W123+Data!T124+Data!U124+Data!V124+Data!W124+Data!T125+Data!U125+Data!V125+Data!W125+Data!T126+Data!U126+Data!V126+Data!W126+Data!T127+Data!U127+Data!V127+Data!W127+Data!T128+Data!U128+Data!V128+Data!W128+Data!T129+Data!U129+Data!V129+Data!W129+Data!T130+Data!U130+Data!V130+Data!W130+Data!T131+Data!U131+Data!V131+Data!W131 -> 82111141 | O131: =Data!T120+Data!T121+Data!T122+Data!T123+Data!T124+Data!T125+Data!T126+Data!T127+Data!T128+Data!T129+Data!T130+Data!T131 -> 58857409 | P131: =Data!U120+Data!U121+Data!U122+Data!U123+Data!U124+Data!U125+Data!U126+Data!U127+Data!U128+Data!U129+Data!U130+Data!U131 -> 9953400 | Q131: =Data!V120+Data!V121+Data!V122+Data!V123+Data!V124+Data!V125+Data!V126+Data!V127+Data!V128+Data!V129+Data!V130+Data!V131 -> 4822177 | R131: =Data!W120+Data!W121+Data!W122+Data!W123+Data!W124+Data!W125+Data!W126+Data!W127+Data!W128+Data!W129+Data!W130+Data!W131 -> 8478155 | S131: =Data!X120+Data!X121+Data!X122+Data!X123+Data!X124+Data!X125+Data!X126+Data!X127+Data!X128+Data!X129+Data!X130+Data!X131 -> 8863064 | T131: =Data!Y120+Data!Z120+Data!AA120+Data!Y121+Data!Z121+Data!AA121+Data!Y122+Data!Z122+Data!AA122+Data!Y123+Data!Z123+Data!AA123+Data!Y124+Data!Z124+Data!AA124+Data!Y125+Data!Z125+Data!AA125+Data!Y126+Data!Z126+Data!AA126+Data!Y127+Data!Z127+Data!AA127+Data!Y128+Data!Z128+Data!AA128+Data!Y129+Data!Z129+Data!AA129+Data!Y130+Data!Z130+Data!AA130+Data!Y131+Data!Z131+Data!AA131 -> 9927918 | U131: =Data!Y120+Data!Y121+Data!Y122+Data!Y123+Data!Y124+Data!Y125+Data!Y126+Data!Y127+Data!Y128+Data!Y129+Data!Y130+Data!Y131 -> 7074957 | V131: =Data!Z120+Data!Z121+Data!Z122+Data!Z123+Data!Z124+Data!Z125+Data!Z126+Data!Z127+Data!Z128+Data!Z129+Data!Z130+Data!Z131 -> 2816345 | W131: =Data!AB120+Data!AB121+Data!AB122+Data!AB123+Data!AB124+Data!AB125+Data!AB126+Data!AB127+Data!AB128+Data!AB129+Data!AB130+Data!AB131 -> 17863235 | X131: =Data!AC120+Data!AC121+Data!AC122+Data!AC123+Data!AC124+Data!AC125+Data!AC126+Data!AC127+Data!AC128+Data!AC129+Data!AC130+Data!AC131 -> 5199155 | Y131: =Data!AD120+Data!AE120+Data!AF120+Data!AG120+Data!AH120+Data!AD121+Data!AE121+Data!AF121+Data!AG121+Data!AH121+Data!AD122+Data!AE122+Data!AF122+Data!AG122+Data!AH122+Data!AD123+Data!AE123+Data!AF123+Data!AG123+Data!AH123+Data!AD124+Data!AE124+Data!AF124+Data!AG124+Data!AH124+Data!AD125+Data!AE125+Data!AF125+Data!AG125+Data!AH125+Data!AD126+Data!AE126+Data!AF126+Data!AG126+Data!AH126+Data!AD127+Data!AE127+Data!AF127+Data!AG127+Data!AH127+Data!AD128+Data!AE128+Data!AF128+Data!AG128+Data!AH128+Data!AD129+Data!AE129+Data!AF129+Data!AG129+Data!AH129+Data!AD130+Data!AE130+Data!AF130+Data!AG130+Data!AH130+Data!AD131+Data!AE131+Data!AF131+Data!AG131+Data!AH131 -> 2192725 | Z131: =Data!AI120+Data!AI121+Data!AI122+Data!AI123+Data!AI124+Data!AI125+Data!AI126+Data!AI127+Data!AI128+Data!AI129+Data!AI130+Data!AI131 -> 4799857 | AA131: =Data!AJ120+Data!AJ121+Data!AJ122+Data!AJ123+Data!AJ124+Data!AJ125+Data!AJ126+Data!AJ127+Data!AJ128+Data!AJ129+Data!AJ130+Data!AJ131 -> 0 | AB131: =Data!AK120+Data!AK121+Data!AK122+Data!AK123+Data!AK124+Data!AK125+Data!AK126+Data!AK127+Data!AK128+Data!AK129+Data!AK130+Data!AK131 -> 2120005 | AC131: =Data!AL120+Data!AL121+Data!AL122+Data!AL123+Data!AL124+Data!AL125+Data!AL126+Data!AL127+Data!AL128+Data!AL129+Data!AL130+Data!AL131 -> 3273381 | AD131: =Data!AM120+Data!AM121+Data!AM122+Data!AM123+Data!AM124+Data!AM125+Data!AM126+Data!AM127+Data!AM128+Data!AM129+Data!AM130+Data!AM131 -> 12893104 | AE131: =Data!AN120+Data!AN121+Data!AN122+Data!AN123+Data!AN124+Data!AN125+Data!AN126+Data!AN127+Data!AN128+Data!AN129+Data!AN130+Data!AN131 -> 11502053 | AF131: =Data!AO120+Data!AO121+Data!AO122+Data!AO123+Data!AO124+Data!AO125+Data!AO126+Data!AO127+Data!AO128+Data!AO129+Data!AO130+Data!AO131 -> 1391052

Sheet Rolling 12m %GDP
B2: Trailing twelve-month sums, share of GDP
B3: Trailing twelve-month flows over trailing four-quarter nominal GDP. Scale-free.
B6: Month | C6: TOTAL REVENUE | D6: Tax revenue | E6: VAT (net) | F6: Income tax | G6: Export duties | H6: Import duties | I6: Debits & credits | J6: Other taxes | K6: Social security contrib. | L6: Non-tax and capital | M6: PRIMARY EXPENDITURE | N6: Social benefits | O6: Contributory pensions | P6: Family allowances | Q6: Non-contrib. pensions | R6: PAMI | S6: Other social programmes | T6: Economic subsidies | U6: Energy | V6: Transport | W6: Wages | X6: Other operating | Y6: Transfers to provinces | Z6: Universities | AA6: Public enterprises | AB6: Other current | AC6: Capital expenditure | AD6: PRIMARY BALANCE | AE6: Interest (net) | AF6: OVERALL BALANCE
B7: =Data!B7 -> 2016-01
B8: =Data!B8 -> 2016-02
B9: =Data!B9 -> 2016-03
B10: =Data!B10 -> 2016-04
B11: =Data!B11 -> 2016-05
B12: =Data!B12 -> 2016-06
B13: =Data!B13 -> 2016-07
B14: =Data!B14 -> 2016-08
B15: =Data!B15 -> 2016-09
B16: =Data!B16 -> 2016-10
B17: =Data!B17 -> 2016-11
B18: =Data!B18 -> 2016-12 | C18: =(Data!D7+Data!E7+Data!F7+Data!G7+Data!H7+Data!I7+Data!J7+Data!K7+Data!L7+Data!M7+Data!N7+Data!O7+Data!P7+Data!Q7+Data!R7+Data!S7+Data!D8+Data!E8+Data!F8+Data!G8+Data!H8+Data!I8+Data!J8+Data!K8+Data!L8+Data!M8+Data!N8+Data!O8+Data!P8+Data!Q8+Data!R8+Data!S8+Data!D9+Data!E9+Data!F9+Data!G9+Data!H9+Data!I9+Data!J9+Data!K9+Data!L9+Data!M9+Data!N9+Data!O9+Data!P9+Data!Q9+Data!R9+Data!S9+Data!D10+Data!E10+Data!F10+Data!G10+Data!H10+Data!I10+Data!J10+Data!K10+Data!L10+Data!M10+Data!N10+Data!O10+Data!P10+Data!Q10+Data!R10+Data!S10+Data!D11+Data!E11+Data!F11+Data!G11+Data!H11+Data!I11+Data!J11+Data!K11+Data!L11+Data!M11+Data!N11+Data!O11+Data!P11+Data!Q11+Data!R11+Data!S11+Data!D12+Data!E12+Data!F12+Data!G12+Data!H12+Data!I12+Data!J12+Data!K12+Data!L12+Data!M12+Data!N12+Data!O12+Data!P12+Data!Q12+Data!R12+Data!S12+Data!D13+Data!E13+Data!F13+Data!G13+Data!H13+Data!I13+Data!J13+Data!K13+Data!L13+Data!M13+Data!N13+Data!O13+Data!P13+Data!Q13+Data!R13+Data!S13+Data!D14+Data!E14+Data!F14+Data!G14+Data!H14+Data!I14+Data!J14+Data!K14+Data!L14+Data!M14+Data!N14+Data!O14+Data!P14+Data!Q14+Data!R14+Data!S14+Data!D15+Data!E15+Data!F15+Data!G15+Data!H15+Data!I15+Data!J15+Data!K15+Data!L15+Data!M15+Data!N15+Data!O15+Data!P15+Data!Q15+Data!R15+Data!S15+Data!D16+Data!E16+Data!F16+Data!G16+Data!H16+Data!I16+Data!J16+Data!K16+Data!L16+Data!M16+Data!N16+Data!O16+Data!P16+Data!Q16+Data!R16+Data!S16+Data!D17+Data!E17+Data!F17+Data!G17+Data!H17+Data!I17+Data!J17+Data!K17+Data!L17+Data!M17+Data!N17+Data!O17+Data!P17+Data!Q17+Data!R17+Data!S17+Data!D18+Data!E18+Data!F18+Data!G18+Data!H18+Data!I18+Data!J18+Data!K18+Data!L18+Data!M18+Data!N18+Data!O18+Data!P18+Data!Q18+Data!R18+Data!S18)/(Data!AP7+Data!AP8+Data!AP9+Data!AP10+Data!AP11+Data!AP12+Data!AP13+Data!AP14+Data!AP15+Data!AP16+Data!AP17+Data!AP18) -> 0.19801682 | D18: =(Data!D7+Data!E7+Data!G7+Data!H7+Data!I7+Data!J7+Data!K7+Data!L7+Data!M7+Data!D8+Data!E8+Data!G8+Data!H8+Data!I8+Data!J8+Data!K8+Data!L8+Data!M8+Data!D9+Data!E9+Data!G9+Data!H9+Data!I9+Data!J9+Data!K9+Data!L9+Data!M9+Data!D10+Data!E10+Data!G10+Data!H10+Data!I10+Data!J10+Data!K10+Data!L10+Data!M10+Data!D11+Data!E11+Data!G11+Data!H11+Data!I11+Data!J11+Data!K11+Data!L11+Data!M11+Data!D12+Data!E12+Data!G12+Data!H12+Data!I12+Data!J12+Data!K12+Data!L12+Data!M12+Data!D13+Data!E13+Data!G13+Data!H13+Data!I13+Data!J13+Data!K13+Data!L13+Data!M13+Data!D14+Data!E14+Data!G14+Data!H14+Data!I14+Data!J14+Data!K14+Data!L14+Data!M14+Data!D15+Data!E15+Data!G15+Data!H15+Data!I15+Data!J15+Data!K15+Data!L15+Data!M15+Data!D16+Data!E16+Data!G16+Data!H16+Data!I16+Data!J16+Data!K16+Data!L16+Data!M16+Data!D17+Data!E17+Data!G17+Data!H17+Data!I17+Data!J17+Data!K17+Data!L17+Data!M17+Data!D18+Data!E18+Data!G18+Data!H18+Data!I18+Data!J18+Data!K18+Data!L18+Data!M18)/(Data!AP7+Data!AP8+Data!AP9+Data!AP10+Data!AP11+Data!AP12+Data!AP13+Data!AP14+Data!AP15+Data!AP16+Data!AP17+Data!AP18) -> 0.11869763 | E18: =(Data!D7+Data!D8+Data!D9+Data!D10+Data!D11+Data!D12+Data!D13+Data!D14+Data!D15+Data!D16+Data!D17+Data!D18)/(Data!AP7+Data!AP8+Data!AP9+Data!AP10+Data!AP11+Data!AP12+Data!AP13+Data!AP14+Data!AP15+Data!AP16+Data!AP17+Data!AP18) -> 0.033767211 | F18: =(Data!E7+Data!E8+Data!E9+Data!E10+Data!E11+Data!E12+Data!E13+Data!E14+Data!E15+Data!E16+Data!E17+Data!E18)/(Data!AP7+Data!AP8+Data!AP9+Data!AP10+Data!AP11+Data!AP12+Data!AP13+Data!AP14+Data!AP15+Data!AP16+Data!AP17+Data!AP18) -> 0.027153338 | G18: =(Data!K7+Data!K8+Data!K9+Data!K10+Data!K11+Data!K12+Data!K13+Data!K14+Data!K15+Data!K16+Data!K17+Data!K18)/(Data!AP7+Data!AP8+Data!AP9+Data!AP10+Data!AP11+Data!AP12+Data!AP13+Data!AP14+Data!AP15+Data!AP16+Data!AP17+Data!AP18) -> 0.008764779 | H18: =(Data!L7+Data!L8+Data!L9+Data!L10+Data!L11+Data!L12+Data!L13+Data!L14+Data!L15+Data!L16+Data!L17+Data!L18)/(Data!AP7+Data!AP8+Data!AP9+Data!AP10+Data!AP11+Data!AP12+Data!AP13+Data!AP14+Data!AP15+Data!AP16+Data!AP17+Data!AP18) -> 0.0067324898 | I18: =(Data!G7+Data!G8+Data!G9+Data!G10+Data!G11+Data!G12+Data!G13+Data!G14+Data!G15+Data!G16+Data!G17+Data!G18)/(Data!AP7+Data!AP8+Data!AP9+Data!AP10+Data!AP11+Data!AP12+Data!AP13+Data!AP14+Data!AP15+Data!AP16+Data!AP17+Data!AP18) -> 0.013288391 | J18: =(Data!H7+Data!I7+Data!J7+Data!M7+Data!H8+Data!I8+Data!J8+Data!M8+Data!H9+Data!I9+Data!J9+Data!M9+Data!H10+Data!I10+Data!J10+Data!M10+Data!H11+Data!I11+Data!J11+Data!M11+Data!H12+Data!I12+Data!J12+Data!M12+Data!H13+Data!I13+Data!J13+Data!M13+Data!H14+Data!I14+Data!J14+Data!M14+Data!H15+Data!I15+Data!J15+Data!M15+Data!H16+Data!I16+Data!J16+Data!M16+Data!H17+Data!I17+Data!J17+Data!M17+Data!H18+Data!I18+Data!J18+Data!M18)/(Data!AP7+Data!AP8+Data!AP9+Data!AP10+Data!AP11+Data!AP12+Data!AP13+Data!AP14+Data!AP15+Data!AP16+Data!AP17+Data!AP18) -> 0.028991416 | K18: =(Data!F7+Data!F8+Data!F9+Data!F10+Data!F11+Data!F12+Data!F13+Data!F14+Data!F15+Data!F16+Data!F17+Data!F18)/(Data!AP7+Data!AP8+Data!AP9+Data!AP10+Data!AP11+Data!AP12+Data!AP13+Data!AP14+Data!AP15+Data!AP16+Data!AP17+Data!AP18) -> 0.067826589 | L18: =(Data!N7+Data!O7+Data!P7+Data!Q7+Data!R7+Data!S7+Data!N8+Data!O8+Data!P8+Data!Q8+Data!R8+Data!S8+Data!N9+Data!O9+Data!P9+Data!Q9+Data!R9+Data!S9+Data!N10+Data!O10+Data!P10+Data!Q10+Data!R10+Data!S10+Data!N11+Data!O11+Data!P11+Data!Q11+Data!R11+Data!S11+Data!N12+Data!O12+Data!P12+Data!Q12+Data!R12+Data!S12+Data!N13+Data!O13+Data!P13+Data!Q13+Data!R13+Data!S13+Data!N14+Data!O14+Data!P14+Data!Q14+Data!R14+Data!S14+Data!N15+Data!O15+Data!P15+Data!Q15+Data!R15+Data!S15+Data!N16+Data!O16+Data!P16+Data!Q16+Data!R16+Data!S16+Data!N17+Data!O17+Data!P17+Data!Q17+Data!R17+Data!S17+Data!N18+Data!O18+Data!P18+Data!Q18+Data!R18+Data!S18)/(Data!AP7+Data!AP8+Data!AP9+Data!AP10+Data!AP11+Data!AP12+Data!AP13+Data!AP14+Data!AP15+Data!AP16+Data!AP17+Data!AP18) -> 0.011492606 | M18: =(Data!T7+Data!U7+Data!V7+Data!W7+Data!X7+Data!Y7+Data!Z7+Data!AA7+Data!AB7+Data!AC7+Data!AD7+Data!AE7+Data!AF7+Data!AG7+Data!AH7+Data!AI7+Data!AJ7+Data!AK7+Data!AL7+Data!T8+Data!U8+Data!V8+Data!W8+Data!X8+Data!Y8+Data!Z8+Data!AA8+Data!AB8+Data!AC8+Data!AD8+Data!AE8+Data!AF8+Data!AG8+Data!AH8+Data!AI8+Data!AJ8+Data!AK8+Data!AL8+Data!T9+Data!U9+Data!V9+Data!W9+Data!X9+Data!Y9+Data!Z9+Data!AA9+Data!AB9+Data!AC9+Data!AD9+Data!AE9+Data!AF9+Data!AG9+Data!AH9+Data!AI9+Data!AJ9+Data!AK9+Data!AL9+Data!T10+Data!U10+Data!V10+Data!W10+Data!X10+Data!Y10+Data!Z10+Data!AA10+Data!AB10+Data!AC10+Data!AD10+Data!AE10+Data!AF10+Data!AG10+Data!AH10+Data!AI10+Data!AJ10+Data!AK10+Data!AL10+Data!T11+Data!U11+Data!V11+Data!W11+Data!X11+Data!Y11+Data!Z11+Data!AA11+Data!AB11+Data!AC11+Data!AD11+Data!AE11+Data!AF11+Data!AG11+Data!AH11+Data!AI11+Data!AJ11+Data!AK11+Data!AL11+Data!T12+Data!U12+Data!V12+Data!W12+Data!X12+Data!Y12+Data!Z12+Data!AA12+Data!AB12+Data!AC12+Data!AD12+Data!AE12+Data!AF12+Data!AG12+Data!AH12+Data!AI12+Data!AJ12+Data!AK12+Data!AL12+Data!T13+Data!U13+Data!V13+Data!W13+Data!X13+Data!Y13+Data!Z13+Data!AA13+Data!AB13+Data!AC13+Data!AD13+Data!AE13+Data!AF13+Data!AG13+Data!AH13+Data!AI13+Data!AJ13+Data!AK13+Data!AL13+Data!T14+Data!U14+Data!V14+Data!W14+Data!X14+Data!Y14+Data!Z14+Data!AA14+Data!AB14+Data!AC14+Data!AD14+Data!AE14+Data!AF14+Data!AG14+Data!AH14+Data!AI14+Data!AJ14+Data!AK14+Data!AL14+Data!T15+Data!U15+Data!V15+Data!W15+Data!X15+Data!Y15+Data!Z15+Data!AA15+Data!AB15+Data!AC15+Data!AD15+Data!AE15+Data!AF15+Data!AG15+Data!AH15+Data!AI15+Data!AJ15+Data!AK15+Data!AL15+Data!T16+Data!U16+Data!V16+Data!W16+Data!X16+Data!Y16+Data!Z16+Data!AA16+Data!AB16+Data!AC16+Data!AD16+Data!AE16+Data!AF16+Data!AG16+Data!AH16+Data!AI16+Data!AJ16+Data!AK16+Data!AL16+Data!T17+Data!U17+Data!V17+Data!W17+Data!X17+Data!Y17+Data!Z17+Data!AA17+Data!AB17+Data!AC17+Data!AD17+Data!AE17+Data!AF17+Data!AG17+Data!AH17+Data!AI17+Data!AJ17+Data!AK17+Data!AL17+Data!T18+Data!U18+Data!V18+Data!W18+Data!X18+Data!Y18+Data!Z18+Data!AA18+Data!AB18+Data!AC18+Data!AD18+Data!AE18+Data!AF18+Data!AG18+Data!AH18+Data!AI18+Data!AJ18+Data!AK18+Data!AL18)/(Data!AP7+Data!AP8+Data!AP9+Data!AP10+Data!AP11+Data!AP12+Data!AP13+Data!AP14+Data!AP15+Data!AP16+Data!AP17+Data!AP18) -> 0.23976662 | N18: =(Data!T7+Data!U7+Data!V7+Data!W7+Data!T8+Data!U8+Data!V8+Data!W8+Data!T9+Data!U9+Data!V9+Data!W9+Data!T10+Data!U10+Data!V10+Data!W10+Data!T11+Data!U11+Data!V11+Data!W11+Data!T12+Data!U12+Data!V12+Data!W12+Data!T13+Data!U13+Data!V13+Data!W13+Data!T14+Data!U14+Data!V14+Data!W14+Data!T15+Data!U15+Data!V15+Data!W15+Data!T16+Data!U16+Data!V16+Data!W16+Data!T17+Data!U17+Data!V17+Data!W17+Data!T18+Data!U18+Data!V18+Data!W18)/(Data!AP7+Data!AP8+Data!AP9+Data!AP10+Data!AP11+Data!AP12+Data!AP13+Data!AP14+Data!AP15+Data!AP16+Data!AP17+Data!AP18) -> 0.11233229 | O18: =(Data!T7+Data!T8+Data!T9+Data!T10+Data!T11+Data!T12+Data!T13+Data!T14+Data!T15+Data!T16+Data!T17+Data!T18)/(Data!AP7+Data!AP8+Data!AP9+Data!AP10+Data!AP11+Data!AP12+Data!AP13+Data!AP14+Data!AP15+Data!AP16+Data!AP17+Data!AP18) -> 0.079540266 | P18: =(Data!U7+Data!U8+Data!U9+Data!U10+Data!U11+Data!U12+Data!U13+Data!U14+Data!U15+Data!U16+Data!U17+Data!U18)/(Data!AP7+Data!AP8+Data!AP9+Data!AP10+Data!AP11+Data!AP12+Data!AP13+Data!AP14+Data!AP15+Data!AP16+Data!AP17+Data!AP18) -> 0.013145102 | Q18: =(Data!V7+Data!V8+Data!V9+Data!V10+Data!V11+Data!V12+Data!V13+Data!V14+Data!V15+Data!V16+Data!V17+Data!V18)/(Data!AP7+Data!AP8+Data!AP9+Data!AP10+Data!AP11+Data!AP12+Data!AP13+Data!AP14+Data!AP15+Data!AP16+Data!AP17+Data!AP18) -> 0.0097529708 | R18: =(Data!W7+Data!W8+Data!W9+Data!W10+Data!W11+Data!W12+Data!W13+Data!W14+Data!W15+Data!W16+Data!W17+Data!W18)/(Data!AP7+Data!AP8+Data!AP9+Data!AP10+Data!AP11+Data!AP12+Data!AP13+Data!AP14+Data!AP15+Data!AP16+Data!AP17+Data!AP18) -> 0.0098939501 | S18: =(Data!X7+Data!X8+Data!X9+Data!X10+Data!X11+Data!X12+Data!X13+Data!X14+Data!X15+Data!X16+Data!X17+Data!X18)/(Data!AP7+Data!AP8+Data!AP9+Data!AP10+Data!AP11+Data!AP12+Data!AP13+Data!AP14+Data!AP15+Data!AP16+Data!AP17+Data!AP18) -> 0.0036827191 | T18: =(Data!Y7+Data!Z7+Data!AA7+Data!Y8+Data!Z8+Data!AA8+Data!Y9+Data!Z9+Data!AA9+Data!Y10+Data!Z10+Data!AA10+Data!Y11+Data!Z11+Data!AA11+Data!Y12+Data!Z12+Data!AA12+Data!Y13+Data!Z13+Data!AA13+Data!Y14+Data!Z14+Data!AA14+Data!Y15+Data!Z15+Data!AA15+Data!Y16+Data!Z16+Data!AA16+Data!Y17+Data!Z17+Data!AA17+Data!Y18+Data!Z18+Data!AA18)/(Data!AP7+Data!AP8+Data!AP9+Data!AP10+Data!AP11+Data!AP12+Data!AP13+Data!AP14+Data!AP15+Data!AP16+Data!AP17+Data!AP18) -> 0.035387136 | U18: =(Data!Y7+Data!Y8+Data!Y9+Data!Y10+Data!Y11+Data!Y12+Data!Y13+Data!Y14+Data!Y15+Data!Y16+Data!Y17+Data!Y18)/(Data!AP7+Data!AP8+Data!AP9+Data!AP10+Data!AP11+Data!AP12+Data!AP13+Data!AP14+Data!AP15+Data!AP16+Data!AP17+Data!AP18) -> 0.025425248 | V18: =(Data!Z7+Data!Z8+Data!Z9+Data!Z10+Data!Z11+Data!Z12+Data!Z13+Data!Z14+Data!Z15+Data!Z16+Data!Z17+Data!Z18)/(Data!AP7+Data!AP8+Data!AP9+Data!AP10+Data!AP11+Data!AP12+Data!AP13+Data!AP14+Data!AP15+Data!AP16+Data!AP17+Data!AP18) -> 0.0097527277 | W18: =(Data!AB7+Data!AB8+Data!AB9+Data!AB10+Data!AB11+Data!AB12+Data!AB13+Data!AB14+Data!AB15+Data!AB16+Data!AB17+Data!AB18)/(Data!AP7+Data!AP8+Data!AP9+Data!AP10+Data!AP11+Data!AP12+Data!AP13+Data!AP14+Data!AP15+Data!AP16+Data!AP17+Data!AP18) -> 0.03242888 | X18: =(Data!AC7+Data!AC8+Data!AC9+Data!AC10+Data!AC11+Data!AC12+Data!AC13+Data!AC14+Data!AC15+Data!AC16+Data!AC17+Data!AC18)/(Data!AP7+Data!AP8+Data!AP9+Data!AP10+Data!AP11+Data!AP12+Data!AP13+Data!AP14+Data!AP15+Data!AP16+Data!AP17+Data!AP18) -> 0.0096424965 | Y18: =(Data!AD7+Data!AE7+Data!AF7+Data!AG7+Data!AH7+Data!AD8+Data!AE8+Data!AF8+Data!AG8+Data!AH8+Data!AD9+Data!AE9+Data!AF9+Data!AG9+Data!AH9+Data!AD10+Data!AE10+Data!AF10+Data!AG10+Data!AH10+Data!AD11+Data!AE11+Data!AF11+Data!AG11+Data!AH11+Data!AD12+Data!AE12+Data!AF12+Data!AG12+Data!AH12+Data!AD13+Data!AE13+Data!AF13+Data!AG13+Data!AH13+Data!AD14+Data!AE14+Data!AF14+Data!AG14+Data!AH14+Data!AD15+Data!AE15+Data!AF15+Data!AG15+Data!AH15+Data!AD16+Data!AE16+Data!AF16+Data!AG16+Data!AH16+Data!AD17+Data!AE17+Data!AF17+Data!AG17+Data!AH17+Data!AD18+Data!AE18+Data!AF18+Data!AG18+Data!AH18)/(Data!AP7+Data!AP8+Data!AP9+Data!AP10+Data!AP11+Data!AP12+Data!AP13+Data!AP14+Data!AP15+Data!AP16+Data!AP17+Data!AP18) -> 0.0089440414 | Z18: =(Data!AI7+Data!AI8+Data!AI9+Data!AI10+Data!AI11+Data!AI12+Data!AI13+Data!AI14+Data!AI15+Data!AI16+Data!AI17+Data!AI18)/(Data!AP7+Data!AP8+Data!AP9+Data!AP10+Data!AP11+Data!AP12+Data!AP13+Data!AP14+Data!AP15+Data!AP16+Data!AP17+Data!AP18) -> 0.0075961094 | AA18: =(Data!AJ7+Data!AJ8+Data!AJ9+Data!AJ10+Data!AJ11+Data!AJ12+Data!AJ13+Data!AJ14+Data!AJ15+Data!AJ16+Data!AJ17+Data!AJ18)/(Data!AP7+Data!AP8+Data!AP9+Data!AP10+Data!AP11+Data!AP12+Data!AP13+Data!AP14+Data!AP15+Data!AP16+Data!AP17+Data!AP18) -> 0.00098916409 | AB18: =(Data!AK7+Data!AK8+Data!AK9+Data!AK10+Data!AK11+Data!AK12+Data!AK13+Data!AK14+Data!AK15+Data!AK16+Data!AK17+Data!AK18)/(Data!AP7+Data!AP8+Data!AP9+Data!AP10+Data!AP11+Data!AP12+Data!AP13+Data!AP14+Data!AP15+Data!AP16+Data!AP17+Data!AP18) -> 0.0066393948 | AC18: =(Data!AL7+Data!AL8+Data!AL9+Data!AL10+Data!AL11+Data!AL12+Data!AL13+Data!AL14+Data!AL15+Data!AL16+Data!AL17+Data!AL18)/(Data!AP7+Data!AP8+Data!AP9+Data!AP10+Data!AP11+Data!AP12+Data!AP13+Data!AP14+Data!AP15+Data!AP16+Data!AP17+Data!AP18) -> 0.022124389 | AD18: =(Data!AM7+Data!AM8+Data!AM9+Data!AM10+Data!AM11+Data!AM12+Data!AM13+Data!AM14+Data!AM15+Data!AM16+Data!AM17+Data!AM18)/(Data!AP7+Data!AP8+Data!AP9+Data!AP10+Data!AP11+Data!AP12+Data!AP13+Data!AP14+Data!AP15+Data!AP16+Data!AP17+Data!AP18) -> -0.041749798 | AE18: =(Data!AN7+Data!AN8+Data!AN9+Data!AN10+Data!AN11+Data!AN12+Data!AN13+Data!AN14+Data!AN15+Data!AN16+Data!AN17+Data!AN18)/(Data!AP7+Data!AP8+Data!AP9+Data!AP10+Data!AP11+Data!AP12+Data!AP13+Data!AP14+Data!AP15+Data!AP16+Data!AP17+Data!AP18) -> 0.015952413 | AF18: =(Data!AO7+Data!AO8+Data!AO9+Data!AO10+Data!AO11+Data!AO12+Data!AO13+Data!AO14+Data!AO15+Data!AO16+Data!AO17+Data!AO18)/(Data!AP7+Data!AP8+Data!AP9+Data!AP10+Data!AP11+Data!AP12+Data!AP13+Data!AP14+Data!AP15+Data!AP16+Data!AP17+Data!AP18) -> -0.057702454
B19: =Data!B19 -> 2017-01 | C19: =(Data!D8+Data!E8+Data!F8+Data!G8+Data!H8+Data!I8+Data!J8+Data!K8+Data!L8+Data!M8+Data!N8+Data!O8+Data!P8+Data!Q8+Data!R8+Data!S8+Data!D9+Data!E9+Data!F9+Data!G9+Data!H9+Data!I9+Data!J9+Data!K9+Data!L9+Data!M9+Data!N9+Data!O9+Data!P9+Data!Q9+Data!R9+Data!S9+Data!D10+Data!E10+Data!F10+Data!G10+Data!H10+Data!I10+Data!J10+Data!K10+Data!L10+Data!M10+Data!N10+Data!O10+Data!P10+Data!Q10+Data!R10+Data!S10+Data!D11+Data!E11+Data!F11+Data!G11+Data!H11+Data!I11+Data!J11+Data!K11+Data!L11+Data!M11+Data!N11+Data!O11+Data!P11+Data!Q11+Data!R11+Data!S11+Data!D12+Data!E12+Data!F12+Data!G12+Data!H12+Data!I12+Data!J12+Data!K12+Data!L12+Data!M12+Data!N12+Data!O12+Data!P12+Data!Q12+Data!R12+Data!S12+Data!D13+Data!E13+Data!F13+Data!G13+Data!H13+Data!I13+Data!J13+Data!K13+Data!L13+Data!M13+Data!N13+Data!O13+Data!P13+Data!Q13+Data!R13+Data!S13+Data!D14+Data!E14+Data!F14+Data!G14+Data!H14+Data!I14+Data!J14+Data!K14+Data!L14+Data!M14+Data!N14+Data!O14+Data!P14+Data!Q14+Data!R14+Data!S14+Data!D15+Data!E15+Data!F15+Data!G15+Data!H15+Data!I15+Data!J15+Data!K15+Data!L15+Data!M15+Data!N15+Data!O15+Data!P15+Data!Q15+Data!R15+Data!S15+Data!D16+Data!E16+Data!F16+Data!G16+Data!H16+Data!I16+Data!J16+Data!K16+Data!L16+Data!M16+Data!N16+Data!O16+Data!P16+Data!Q16+Data!R16+Data!S16+Data!D17+Data!E17+Data!F17+Data!G17+Data!H17+Data!I17+Data!J17+Data!K17+Data!L17+Data!M17+Data!N17+Data!O17+Data!P17+Data!Q17+Data!R17+Data!S17+Data!D18+Data!E18+Data!F18+Data!G18+Data!H18+Data!I18+Data!J18+Data!K18+Data!L18+Data!M18+Data!N18+Data!O18+Data!P18+Data!Q18+Data!R18+Data!S18+Data!D19+Data!E19+Data!F19+Data!G19+Data!H19+Data!I19+Data!J19+Data!K19+Data!L19+Data!M19+Data!N19+Data!O19+Data!P19+Data!Q19+Data!R19+Data!S19)/(Data!AP8+Data!AP9+Data!AP10+Data!AP11+Data!AP12+Data!AP13+Data!AP14+Data!AP15+Data!AP16+Data!AP17+Data!AP18+Data!AP19) -> 0.19931551 | D19: =(Data!D8+Data!E8+Data!G8+Data!H8+Data!I8+Data!J8+Data!K8+Data!L8+Data!M8+Data!D9+Data!E9+Data!G9+Data!H9+Data!I9+Data!J9+Data!K9+Data!L9+Data!M9+Data!D10+Data!E10+Data!G10+Data!H10+Data!I10+Data!J10+Data!K10+Data!L10+Data!M10+Data!D11+Data!E11+Data!G11+Data!H11+Data!I11+Data!J11+Data!K11+Data!L11+Data!M11+Data!D12+Data!E12+Data!G12+Data!H12+Data!I12+Data!J12+Data!K12+Data!L12+Data!M12+Data!D13+Data!E13+Data!G13+Data!H13+Data!I13+Data!J13+Data!K13+Data!L13+Data!M13+Data!D14+Data!E14+Data!G14+Data!H14+Data!I14+Data!J14+Data!K14+Data!L14+Data!M14+Data!D15+Data!E15+Data!G15+Data!H15+Data!I15+Data!J15+Data!K15+Data!L15+Data!M15+Data!D16+Data!E16+Data!G16+Data!H16+Data!I16+Data!J16+Data!K16+Data!L16+Data!M16+Data!D17+Data!E17+Data!G17+Data!H17+Data!I17+Data!J17+Data!K17+Data!L17+Data!M17+Data!D18+Data!E18+Data!G18+Data!H18+Data!I18+Data!J18+Data!K18+Data!L18+Data!M18+Data!D19+Data!E19+Data!G19+Data!H19+Data!I19+Data!J19+Data!K19+Data!L19+Data!M19)/(Data!AP8+Data!AP9+Data!AP10+Data!AP11+Data!AP12+Data!AP13+Data!AP14+Data!AP15+Data!AP16+Data!AP17+Data!AP18+Data!AP19) -> 0.11930073 | E19: =(Data!D8+Data!D9+Data!D10+Data!D11+Data!D12+Data!D13+Data!D14+Data!D15+Data!D16+Data!D17+Data!D18+Data!D19)/(Data!AP8+Data!AP9+Data!AP10+Data!AP11+Data!AP12+Data!AP13+Data!AP14+Data!AP15+Data!AP16+Data!AP17+Data!AP18+Data!AP19) -> 0.033719792 | F19: =(Data!E8+Data!E9+Data!E10+Data!E11+Data!E12+Data!E13+Data!E14+Data!E15+Data!E16+Data!E17+Data!E18+Data!E19)/(Data!AP8+Data!AP9+Data!AP10+Data!AP11+Data!AP12+Data!AP13+Data!AP14+Data!AP15+Data!AP16+Data!AP17+Data!AP18+Data!AP19) -> 0.026691747 | G19: =(Data!K8+Data!K9+Data!K10+Data!K11+Data!K12+Data!K13+Data!K14+Data!K15+Data!K16+Data!K17+Data!K18+Data!K19)/(Data!AP8+Data!AP9+Data!AP10+Data!AP11+Data!AP12+Data!AP13+Data!AP14+Data!AP15+Data!AP16+Data!AP17+Data!AP18+Data!AP19) -> 0.0086729826 | H19: =(Data!L8+Data!L9+Data!L10+Data!L11+Data!L12+Data!L13+Data!L14+Data!L15+Data!L16+Data!L17+Data!L18+Data!L19)/(Data!AP8+Data!AP9+Data!AP10+Data!AP11+Data!AP12+Data!AP13+Data!AP14+Data!AP15+Data!AP16+Data!AP17+Data!AP18+Data!AP19) -> 0.0067209854 | I19: =(Data!G8+Data!G9+Data!G10+Data!G11+Data!G12+Data!G13+Data!G14+Data!G15+Data!G16+Data!G17+Data!G18+Data!G19)/(Data!AP8+Data!AP9+Data!AP10+Data!AP11+Data!AP12+Data!AP13+Data!AP14+Data!AP15+Data!AP16+Data!AP17+Data!AP18+Data!AP19) -> 0.013356564 | J19: =(Data!H8+Data!I8+Data!J8+Data!M8+Data!H9+Data!I9+Data!J9+Data!M9+Data!H10+Data!I10+Data!J10+Data!M10+Data!H11+Data!I11+Data!J11+Data!M11+Data!H12+Data!I12+Data!J12+Data!M12+Data!H13+Data!I13+Data!J13+Data!M13+Data!H14+Data!I14+Data!J14+Data!M14+Data!H15+Data!I15+Data!J15+Data!M15+Data!H16+Data!I16+Data!J16+Data!M16+Data!H17+Data!I17+Data!J17+Data!M17+Data!H18+Data!I18+Data!J18+Data!M18+Data!H19+Data!I19+Data!J19+Data!M19)/(Data!AP8+Data!AP9+Data!AP10+Data!AP11+Data!AP12+Data!AP13+Data!AP14+Data!AP15+Data!AP16+Data!AP17+Data!AP18+Data!AP19) -> 0.030138656 | K19: =(Data!F8+Data!F9+Data!F10+Data!F11+Data!F12+Data!F13+Data!F14+Data!F15+Data!F16+Data!F17+Data!F18+Data!F19)/(Data!AP8+Data!AP9+Data!AP10+Data!AP11+Data!AP12+Data!AP13+Data!AP14+Data!AP15+Data!AP16+Data!AP17+Data!AP18+Data!AP19) -> 0.068236871 | L19: =(Data!N8+Data!O8+Data!P8+Data!Q8+Data!R8+Data!S8+Data!N9+Data!O9+Data!P9+Data!Q9+Data!R9+Data!S9+Data!N10+Data!O10+Data!P10+Data!Q10+Data!R10+Data!S10+Data!N11+Data!O11+Data!P11+Data!Q11+Data!R11+Data!S11+Data!N12+Data!O12+Data!P12+Data!Q12+Data!R12+Data!S12+Data!N13+Data!O13+Data!P13+Data!Q13+Data!R13+Data!S13+Data!N14+Data!O14+Data!P14+Data!Q14+Data!R14+Data!S14+Data!N15+Data!O15+Data!P15+Data!Q15+Data!R15+Data!S15+Data!N16+Data!O16+Data!P16+Data!Q16+Data!R16+Data!S16+Data!N17+Data!O17+Data!P17+Data!Q17+Data!R17+Data!S17+Data!N18+Data!O18+Data!P18+Data!Q18+Data!R18+Data!S18+Data!N19+Data!O19+Data!P19+Data!Q19+Data!R19+Data!S19)/(Data!AP8+Data!AP9+Data!AP10+Data!AP11+Data!AP12+Data!AP13+Data!AP14+Data!AP15+Data!AP16+Data!AP17+Data!AP18+Data!AP19) -> 0.011777909 | M19: =(Data!T8+Data!U8+Data!V8+Data!W8+Data!X8+Data!Y8+Data!Z8+Data!AA8+Data!AB8+Data!AC8+Data!AD8+Data!AE8+Data!AF8+Data!AG8+Data!AH8+Data!AI8+Data!AJ8+Data!AK8+Data!AL8+Data!T9+Data!U9+Data!V9+Data!W9+Data!X9+Data!Y9+Data!Z9+Data!AA9+Data!AB9+Data!AC9+Data!AD9+Data!AE9+Data!AF9+Data!AG9+Data!AH9+Data!AI9+Data!AJ9+Data!AK9+Data!AL9+Data!T10+Data!U10+Data!V10+Data!W10+Data!X10+Data!Y10+Data!Z10+Data!AA10+Data!AB10+Data!AC10+Data!AD10+Data!AE10+Data!AF10+Data!AG10+Data!AH10+Data!AI10+Data!AJ10+Data!AK10+Data!AL10+Data!T11+Data!U11+Data!V11+Data!W11+Data!X11+Data!Y11+Data!Z11+Data!AA11+Data!AB11+Data!AC11+Data!AD11+Data!AE11+Data!AF11+Data!AG11+Data!AH11+Data!AI11+Data!AJ11+Data!AK11+Data!AL11+Data!T12+Data!U12+Data!V12+Data!W12+Data!X12+Data!Y12+Data!Z12+Data!AA12+Data!AB12+Data!AC12+Data!AD12+Data!AE12+Data!AF12+Data!AG12+Data!AH12+Data!AI12+Data!AJ12+Data!AK12+Data!AL12+Data!T13+Data!U13+Data!V13+Data!W13+Data!X13+Data!Y13+Data!Z13+Data!AA13+Data!AB13+Data!AC13+Data!AD13+Data!AE13+Data!AF13+Data!AG13+Data!AH13+Data!AI13+Data!AJ13+Data!AK13+Data!AL13+Data!T14+Data!U14+Data!V14+Data!W14+Data!X14+Data!Y14+Data!Z14+Data!AA14+Data!AB14+Data!AC14+Data!AD14+Data!AE14+Data!AF14+Data!AG14+Data!AH14+Data!AI14+Data!AJ14+Data!AK14+Data!AL14+Data!T15+Data!U15+Data!V15+Data!W15+Data!X15+Data!Y15+Data!Z15+Data!AA15+Data!AB15+Data!AC15+Data!AD15+Data!AE15+Data!AF15+Data!AG15+Data!AH15+Data!AI15+Data!AJ15+Data!AK15+Data!AL15+Data!T16+Data!U16+Data!V16+Data!W16+Data!X16+Data!Y16+Data!Z16+Data!AA16+Data!AB16+Data!AC16+Data!AD16+Data!AE16+Data!AF16+Data!AG16+Data!AH16+Data!AI16+Data!AJ16+Data!AK16+Data!AL16+Data!T17+Data!U17+Data!V17+Data!W17+Data!X17+Data!Y17+Data!Z17+Data!AA17+Data!AB17+Data!AC17+Data!AD17+Data!AE17+Data!AF17+Data!AG17+Data!AH17+Data!AI17+Data!AJ17+Data!AK17+Data!AL17+Data!T18+Data!U18+Data!V18+Data!W18+Data!X18+Data!Y18+Data!Z18+Data!AA18+Data!AB18+Data!AC18+Data!AD18+Data!AE18+Data!AF18+Data!AG18+Data!AH18+Data!AI18+Data!AJ18+Data!AK18+Data!AL18+Data!T19+Data!U19+Data!V19+Data!W19+Data!X19+Data!Y19+Data!Z19+Data!AA19+Data!AB19+Data!AC19+Data!AD19+Data!AE19+Data!AF19+Data!AG19+Data!AH19+Data!AI19+Data!AJ19+Data!AK19+Data!AL19)/(Data!AP8+Data!AP9+Data!AP10+Data!AP11+Data!AP12+Data!AP13+Data!AP14+Data!AP15+Data!AP16+Data!AP17+Data!AP18+Data!AP19) -> 0.23978301 | N19: =(Data!T8+Data!U8+Data!V8+Data!W8+Data!T9+Data!U9+Data!V9+Data!W9+Data!T10+Data!U10+Data!V10+Data!W10+Data!T11+Data!U11+Data!V11+Data!W11+Data!T12+Data!U12+Data!V12+Data!W12+Data!T13+Data!U13+Data!V13+Data!W13+Data!T14+Data!U14+Data!V14+Data!W14+Data!T15+Data!U15+Data!V15+Data!W15+Data!T16+Data!U16+Data!V16+Data!W16+Data!T17+Data!U17+Data!V17+Data!W17+Data!T18+Data!U18+Data!V18+Data!W18+Data!T19+Data!U19+Data!V19+Data!W19)/(Data!AP8+Data!AP9+Data!AP10+Data!AP11+Data!AP12+Data!AP13+Data!AP14+Data!AP15+Data!AP16+Data!AP17+Data!AP18+Data!AP19) -> 0.11285485 | O19: =(Data!T8+Data!T9+Data!T10+Data!T11+Data!T12+Data!T13+Data!T14+Data!T15+Data!T16+Data!T17+Data!T18+Data!T19)/(Data!AP8+Data!AP9+Data!AP10+Data!AP11+Data!AP12+Data!AP13+Data!AP14+Data!AP15+Data!AP16+Data!AP17+Data!AP18+Data!AP19) -> 0.079884829 | P19: =(Data!U8+Data!U9+Data!U10+Data!U11+Data!U12+Data!U13+Data!U14+Data!U15+Data!U16+Data!U17+Data!U18+Data!U19)/(Data!AP8+Data!AP9+Data!AP10+Data!AP11+Data!AP12+Data!AP13+Data!AP14+Data!AP15+Data!AP16+Data!AP17+Data!AP18+Data!AP19) -> 0.013380559 | Q19: =(Data!V8+Data!V9+Data!V10+Data!V11+Data!V12+Data!V13+Data!V14+Data!V15+Data!V16+Data!V17+Data!V18+Data!V19)/(Data!AP8+Data!AP9+Data!AP10+Data!AP11+Data!AP12+Data!AP13+Data!AP14+Data!AP15+Data!AP16+Data!AP17+Data!AP18+Data!AP19) -> 0.0096383499 | R19: =(Data!W8+Data!W9+Data!W10+Data!W11+Data!W12+Data!W13+Data!W14+Data!W15+Data!W16+Data!W17+Data!W18+Data!W19)/(Data!AP8+Data!AP9+Data!AP10+Data!AP11+Data!AP12+Data!AP13+Data!AP14+Data!AP15+Data!AP16+Data!AP17+Data!AP18+Data!AP19) -> 0.0099511114 | S19: =(Data!X8+Data!X9+Data!X10+Data!X11+Data!X12+Data!X13+Data!X14+Data!X15+Data!X16+Data!X17+Data!X18+Data!X19)/(Data!AP8+Data!AP9+Data!AP10+Data!AP11+Data!AP12+Data!AP13+Data!AP14+Data!AP15+Data!AP16+Data!AP17+Data!AP18+Data!AP19) -> 0.0037361509 | T19: =(Data!Y8+Data!Z8+Data!AA8+Data!Y9+Data!Z9+Data!AA9+Data!Y10+Data!Z10+Data!AA10+Data!Y11+Data!Z11+Data!AA11+Data!Y12+Data!Z12+Data!AA12+Data!Y13+Data!Z13+Data!AA13+Data!Y14+Data!Z14+Data!AA14+Data!Y15+Data!Z15+Data!AA15+Data!Y16+Data!Z16+Data!AA16+Data!Y17+Data!Z17+Data!AA17+Data!Y18+Data!Z18+Data!AA18+Data!Y19+Data!Z19+Data!AA19)/(Data!AP8+Data!AP9+Data!AP10+Data!AP11+Data!AP12+Data!AP13+Data!AP14+Data!AP15+Data!AP16+Data!AP17+Data!AP18+Data!AP19) -> 0.034510427 | U19: =(Data!Y8+Data!Y9+Data!Y10+Data!Y11+Data!Y12+Data!Y13+Data!Y14+Data!Y15+Data!Y16+Data!Y17+Data!Y18+Data!Y19)/(Data!AP8+Data!AP9+Data!AP10+Data!AP11+Data!AP12+Data!AP13+Data!AP14+Data!AP15+Data!AP16+Data!AP17+Data!AP18+Data!AP19) -> 0.024747709 | V19: =(Data!Z8+Data!Z9+Data!Z10+Data!Z11+Data!Z12+Data!Z13+Data!Z14+Data!Z15+Data!Z16+Data!Z17+Data!Z18+Data!Z19)/(Data!AP8+Data!AP9+Data!AP10+Data!AP11+Data!AP12+Data!AP13+Data!AP14+Data!AP15+Data!AP16+Data!AP17+Data!AP18+Data!AP19) -> 0.0095487859 | W19: =(Data!AB8+Data!AB9+Data!AB10+Data!AB11+Data!AB12+Data!AB13+Data!AB14+Data!AB15+Data!AB16+Data!AB17+Data!AB18+Data!AB19)/(Data!AP8+Data!AP9+Data!AP10+Data!AP11+Data!AP12+Data!AP13+Data!AP14+Data!AP15+Data!AP16+Data!AP17+Data!AP18+Data!AP19) -> 0.032527664 | X19: =(Data!AC8+Data!AC9+Data!AC10+Data!AC11+Data!AC12+Data!AC13+Data!AC14+Data!AC15+Data!AC16+Data!AC17+Data!AC18+Data!AC19)/(Data!AP8+Data!AP9+Data!AP10+Data!AP11+Data!AP12+Data!AP13+Data!AP14+Data!AP15+Data!AP16+Data!AP17+Data!AP18+Data!AP19) -> 0.0098431356 | Y19: =(Data!AD8+Data!AE8+Data!AF8+Data!AG8+Data!AH8+Data!AD9+Data!AE9+Data!AF9+Data!AG9+Data!AH9+Data!AD10+Data!AE10+Data!AF10+Data!AG10+Data!AH10+Data!AD11+Data!AE11+Data!AF11+Data!AG11+Data!AH11+Data!AD12+Data!AE12+Data!AF12+Data!AG12+Data!AH12+Data!AD13+Data!AE13+Data!AF13+Data!AG13+Data!AH13+Data!AD14+Data!AE14+Data!AF14+Data!AG14+Data!AH14+Data!AD15+Data!AE15+Data!AF15+Data!AG15+Data!AH15+Data!AD16+Data!AE16+Data!AF16+Data!AG16+Data!AH16+Data!AD17+Data!AE17+Data!AF17+Data!AG17+Data!AH17+Data!AD18+Data!AE18+Data!AF18+Data!AG18+Data!AH18+Data!AD19+Data!AE19+Data!AF19+Data!AG19+Data!AH19)/(Data!AP8+Data!AP9+Data!AP10+Data!AP11+Data!AP12+Data!AP13+Data!AP14+Data!AP15+Data!AP16+Data!AP17+Data!AP18+Data!AP19) -> 0.0091386206 | Z19: =(Data!AI8+Data!AI9+Data!AI10+Data!AI11+Data!AI12+Data!AI13+Data!AI14+Data!AI15+Data!AI16+Data!AI17+Data!AI18+Data!AI19)/(Data!AP8+Data!AP9+Data!AP10+Data!AP11+Data!AP12+Data!AP13+Data!AP14+Data!AP15+Data!AP16+Data!AP17+Data!AP18+Data!AP19) -> 0.0075980953 | AA19: =(Data!AJ8+Data!AJ9+Data!AJ10+Data!AJ11+Data!AJ12+Data!AJ13+Data!AJ14+Data!AJ15+Data!AJ16+Data!AJ17+Data!AJ18+Data!AJ19)/(Data!AP8+Data!AP9+Data!AP10+Data!AP11+Data!AP12+Data!AP13+Data!AP14+Data!AP15+Data!AP16+Data!AP17+Data!AP18+Data!AP19) -> 0.00096703031 | AB19: =(Data!AK8+Data!AK9+Data!AK10+Data!AK11+Data!AK12+Data!AK13+Data!AK14+Data!AK15+Data!AK16+Data!AK17+Data!AK18+Data!AK19)/(Data!AP8+Data!AP9+Data!AP10+Data!AP11+Data!AP12+Data!AP13+Data!AP14+Data!AP15+Data!AP16+Data!AP17+Data!AP18+Data!AP19) -> 0.0067340518 | AC19: =(Data!AL8+Data!AL9+Data!AL10+Data!AL11+Data!AL12+Data!AL13+Data!AL14+Data!AL15+Data!AL16+Data!AL17+Data!AL18+Data!AL19)/(Data!AP8+Data!AP9+Data!AP10+Data!AP11+Data!AP12+Data!AP13+Data!AP14+Data!AP15+Data!AP16+Data!AP17+Data!AP18+Data!AP19) -> 0.021872988 | AD19: =(Data!AM8+Data!AM9+Data!AM10+Data!AM11+Data!AM12+Data!AM13+Data!AM14+Data!AM15+Data!AM16+Data!AM17+Data!AM18+Data!AM19)/(Data!AP8+Data!AP9+Data!AP10+Data!AP11+Data!AP12+Data!AP13+Data!AP14+Data!AP15+Data!AP16+Data!AP17+Data!AP18+Data!AP19) -> -0.040467504 | AE19: =(Data!AN8+Data!AN9+Data!AN10+Data!AN11+Data!AN12+Data!AN13+Data!AN14+Data!AN15+Data!AN16+Data!AN17+Data!AN18+Data!AN19)/(Data!AP8+Data!AP9+Data!AP10+Data!AP11+Data!AP12+Data!AP13+Data!AP14+Data!AP15+Data!AP16+Data!AP17+Data!AP18+Data!AP19) -> 0.016328689 | AF19: =(Data!AO8+Data!AO9+Data!AO10+Data!AO11+Data!AO12+Data!AO13+Data!AO14+Data!AO15+Data!AO16+Data!AO17+Data!AO18+Data!AO19)/(Data!AP8+Data!AP9+Data!AP10+Data!AP11+Data!AP12+Data!AP13+Data!AP14+Data!AP15+Data!AP16+Data!AP17+Data!AP18+Data!AP19) -> -0.056796431
