Workbook
Name Forecast_Base27: Forecast!$D$46

Sheet Read me
B2: Argentina inflation — the Milei disinflation and the road to October 2027
B3: Thematic pack. INDEC data through 2026-08. Built 30-Sep-2026.
B5: THE QUESTION
C6: What did Milei inherit, what did his people change, what has been accomplished, and where is CPI when voters choose on 24 October 2027.
B8: THE FOUR FINDINGS
B9: 1. Not hyperinflation | C9: Argentina did NOT reach hyperinflation and on the price metric was not close. Dec-2023 printed 25.5% m/m — 51% of Cagan's 50%/month threshold, annualising to 1,427% against the 12,875% the threshold implies. The 1989 peak was 197% m/m, 7.7x higher. The danger sat in the BALANCE SHEET, not the CPI: remunerated liabilities at 2.92x base money, a quasi-fiscal deficit of 10.5% of GDP, net reserves at minus USD 11.2bn, and base money collapsed to 3.1% of GDP. Say the honest thing, then pivot to the overhang — that is where the argument is.
B10: 2. The anchor was withdrawn | C10: On 1-Jan-2026 the FX band's edges stopped crawling at a fixed +/-1%/month and began indexing to the last reported monthly CPI (t-2 lag). That converted the band from a NOMINAL ANCHOR into an INDEXATION MECHANISM. It is the single most important policy change of 2026 and the structural reason inflation now converges TO the crawl rather than below it.
B11: 3. Disinflation is understated | C11: Regulated prices have risen 61% RELATIVE to core since Dec-2023. Core inflation Jan-Aug 2026 (19.8%) is running BELOW the same window of 2025 (20.8%), while headline (21.3%) runs ABOVE 2025 (19.5%). The entire difference is regulados (28.5% vs 20.0%). Underlying disinflation is better than the headline shows; the headline is held up by a deliberate, ongoing relative-price correction.
B12: 4. Inflation is no longer the vote | C12: Approval has moved INVERSELY to the disinflation. ICG fell from 2.86 (Dec-2023) to 1.94 (Sep-2026), a 32% decline, while inflation fell from 25.5% m/m to 1.67% m/m. What approval tracks is REAL INCOME. Across nine presidential elections, 'the incumbent wins iff real wages rose' is right 8 of 9 times; 'iff inflation is below 20%' is right 6 of 9. And inflation has already been displaced as the most-named problem — 20.8% in Jun-2026, down from 44% in May-2024, at 33.5% measured inflation.
B14: TABS
B15: Sources | C15: Every primary document behind every number, plus the explicit list of series that could NOT be sourced. Read the gaps list before publishing anything from this pack.
B16: CPI Data | C16: INDEC national CPI: headline, nucleo, regulados, estacionales as index levels (blue) with m/m, 3m annualised, 6m annualised, y/y and YTD all calculated in-sheet.
B17: Seasonality | C17: Month x year matrix of m/m by calendar year, for headline and core, plus scale-free seasonal factors.
B18: Momentum | C18: 3m and 6m annualised against y/y. The annualised measures turn roughly nine months before the y/y does.
B19: Components | C19: Nucleo vs regulados vs estacionales, and the relative price shift index (Dec-2023 = 100) that quantifies the tariff catch-up.
B20: Inheritance | C20: The monetary financing of the deficit 2019-2023: adelantos transitorios and utilidades, the indirect channels that circumvented the IMF ceiling, letras intransferibles, the LELIQ/pases stock, the quasi-fiscal deficit, money demand collapse and reserves.
B21: Hyperinflation | C21: Distance to Cagan, computed in-sheet: annualised rates, doubling times, and the balance-sheet markers that were the real risk.
B22: Real Rates | C22: Nominal reference rate -> TEM -> real ex-post against realised CPI and real ex-ante against REM expectations. Note there is NO continuous policy rate series: the instrument was abolished on 9-Jun-2025.
B23: Expectations | C23: REM drift by round, household expectations, the LECAP/BONCAP curve and the CER breakevens. The ordering government 18.0% < REM 20.0% < market ~24.6% for 2027 is the note's cleanest single finding.
B24: Models | C24: SIX independent models of where CPI lands in the 3-6 months before the vote, converging into one comparison table. This is the analytical core of the pack.
B25: Forecast | C25: The bull/base/bear monthly paths to Dec-2027 with the assumptions behind each, probability-weighted, benchmarked to the REM and the Budget.
B26: Approval Model | C26: The transparent logistic scoring device mapping inflation level, inflation direction and real wages to an incumbent win probability, with a sensitivity grid. NINE observations and three parameters — a device for organising priors, not a forecast.
... B28: Elections | C28: The eleven-election record: pre-vote inflation, momentum, real wage direction and outcome.
B30: CONVENTIONS
B31: Blue cells | C31: Hardcoded inputs from a cited source. Every one is traceable on the Sources tab.
B32: Black cells | C32: Calculated in-sheet. Change a blue cell and every black cell downstream updates.
B33: Red cells | C33: Derived parameters — computed from the data by a stated method rather than read from a source. There are only a handful and each carries a cell comment with its derivation.
B34: Yellow rows | C34: Empty forecast months on the CPI Data tab. Paste a new INDEC print in and the whole workbook updates.
B35: Pink cells | C35: Reconstructed values, not published ones. See the caveat below.
B37: !! Jul & Aug-2026 caveat | C37: The July-2026 and August-2026 index LEVELS are RECONSTRUCTED, not pulled from the INDEC API, which could not be reached. They were solved from the published press releases, each of which pins every series with three independent figures — the m/m, the change vs December-2025 and the y/y. For every series those three constraints intersect in a band narrower than 0.07% of the level, and the midpoint is what is entered. Every percentage this workbook DISPLAYS therefore matches the published print to INDEC's own decimal. Treat the two index levels as accurate to about +/-0.035%.
B38: Validation gate | C38: Compounded monthly rates reproduce INDEC's published Dec/Dec prints exactly: 2019 53.8%, 2020 36.1%, 2021 50.9%, 2022 94.8%, 2023 211.4%, 2024 117.8%, 2025 31.5%. The August-2026 print also reconciles across all four series: headline 1.7 / 21.3 / 33.5, nucleo 1.8 / 19.8 / 31.9, regulados 2.2 / 28.5 / 43.7, estacionales -0.9 / 16.8 / 24.0.
B40: WHAT THIS PACK DOES NOT DO
B41: No filled gaps | C41: Where a series could not be sourced it is left empty with the source identifier recorded, per standing practice. The Sources tab lists fourteen such gaps. Several are closable only with an interactive session or a Bloomberg pull — the BCRA statistical files, the UTDT history file and the REM XLSX are all behind blocks that a headless run cannot pass.
B42: No merged definitions | C42: Monetary financing as % of GDP mixes two definitions across years (IMF includes valuation-gain transfers; BCRA does not). They are labelled separately and never plotted on one line. The same discipline applies to net reserves, where four estimates use four incompatible methodologies.
B43: No misery index | C43: Inflation and the labour variable are kept separate. An equal-weighted sum is numerically dominated by the inflation term in an economy where inflation moved from 25% m/m to 1.7% m/m while unemployment moved inside a 6-8% band — it would be an inflation index with noise added.

Sheet Sources
B2: Sources and gaps
B3: Primary documents first. Where a figure rests on press reporting of official data it says so.
B5: Series | C5: Source | D5: Document / identifier | E5: Note
B6: CPI | C6: INDEC, Indice de precios al consumidor nacional, base dic-2016=100 | D6: apis.datos.gob.ar series 148.3_INIVELNAL_DICI_M_26, _INUCLEONAL_DICI_M_19, _IREGULANAL_DICI_M_22, _IESTACINAL_DICI_M_25 | E6: Primary. Jul/Aug-2026 levels reconstructed from the press release - see Read me.
B7: CPI validation | C7: INDEC, informes de prensa IPC | D7: Monthly press releases | E7: Compounded m/m reproduces published Dec/Dec: 2019 53.8, 2020 36.1, 2021 50.9, 2022 94.8, 2023 211.4, 2024 117.8, 2025 31.5.
B8: Monetary financing | C8: BCRA, Informe Monetario Mensual, December editions | D8: Bol1219, Bol1220, Bol1221, Bol1222, informe-monetario-mensual-dic-2023 | E8: Factores de variacion de la base monetaria.
B9: Monetary financing % GDP | C9: IMF Country Report 25/3 (Ex-Post Evaluation of the 2022 EFF) para.6 p.12, para.31 p.33; IMF CR 22/92 Box 2 p.35 | D9: CR 25/3; CR 22/92 | E9: MIXED DEFINITION vs BCRA - see Read me.
B10: Quasi-fiscal / net credit | C10: IMF Country Report 25/3, Ex-Post Evaluation, para.31 p.33 | D10: CR 25/3 | E10: Quasi-fiscal 3.3 / 5.2 / 10.5% GDP 2021-23; BCRA net credit to government 24.6% GDP end-2023.
B11: Remunerated liabilities | C11: BCRA, Informe al Congreso 2023, pp.15-17; IMM Nov-2023 and Dec-2023 | D11: Informecongreso2023 | E11: Note: the Informe p.17 mistypes the stock by a factor of 10 - cite the IMM.
B12: Letras intransferibles | C12: Decreto DNU 1599/2005; Resolucion Conjunta 1/2006 y 4/2006; BCRA balance sheet 23-Dec-2023 | D12: argentina.gob.ar/normativa norma-112207, norma-112815 | E12: Stock read from the balance sheet by Romano Group via Infobae 5-Jan-2024.
B13: Carta Organica limits | C13: Carta Organica del BCRA, Arts. 19, 20, 38, as amended by Leyes 25.562 and 26.739 | D13: InfoLeg norma 66194 | E13: Art.38 profit-transfer channel has NO quantitative ceiling.
B14: Hyperinflation benchmark | C14: Cagan via Fischer, Sahay & Vegh, 'Modern Hyper- and High Inflations', NBER WP 8930, p.2 | D14: NBER WP 8930 | E14: 50% per month.
B15: Hyperinflation comparators | C15: Hanke & Krus, 'The Hyperinflation Table', Cato Institute | D15: Cato | E15: Venezuela absent from the version retrieved - NOT SOURCED.
B16: Fiscal outturns | C16: MECON / Secretaria de Hacienda releases; IMF Art.IV 2026 | D16: IMF CR 2026/105 | E16: 2025 overall EXCLUDES zero-coupon interest recorded below the line - not like-for-like with 2023.
... B30: EXCLUDED | C30: teleSUR | D30: - | E30: Excluded as unreliable per standing research policy. Not used anywhere in this workbook.
B33: Series requested but NOT sourced — do not fill without new primary data
B34: Series | C34: Why, and the route to closing it
B35: Adelantos transitorios + utilidades, 2003-2018 | C35: No multi-year table in BCRA Informe al Congreso 2019 or CEPAL chapters. Route: BCRA Balance Semanal / Cuentas Analiticas historical files.
B36: Adelantos and utilidades separately by year | C36: BCRA publishes them as a single combined line in the factores de variacion.
B37: Letras intransferibles stock by year | C37: Only the 23-Dec-2023 point and administration-level totals, both press readings of the balance sheet. Route: BCRA audited Estados Contables annexes.
B38: Seigniorage / inflation tax, % GDP, any year | C38: Not published by BCRA; not tabulated in the IMF documents reviewed. Computing it from dBM/GDP would be a modelled proxy - declined.
B39: 1989-90 monthly INDEC CPI | C39: Only the Hanke-Krus peak (Jul-1989, 197% m/m). Spanish Wikipedia is unusable: cites Trading Economics and conflates m/m with annualised.
B40: Regulated vs headline cumulative 2019-2023 | C40: NOT COMPUTABLE from INDEC national - the regulados sub-index begins Jan-2022.
B41: Real ex-ante rate before Mar-2026 | C41: Requires the REM next-month expected CPI per round; the REM PDF summary tables would not machine-read in any round attempted.
B42: TAMAR and BADLAR before Oct-2025 | C42: Largest quantitative gap in the rates section. Route: BCRA Boletin Estadistico.
B43: UTDT ICG and ICC monthly history 2001-2023 | C43: utdt.edu:443 refused by the egress proxy; download path robots-disallowed. This is what a true empirical inflation-band mapping needs.
B44: REM 2027 median, Aug-2026 round | C44: Not in the PDF's readable text and absent from all press coverage found. The Jul-2026 round's 20.0% is carried forward.
B45: Discrete 2027 / 2028 market breakevens | C45: Needs the CER and fixed-rate curves priced simultaneously off BYMA/MAE or Bloomberg.
... B48: Buenos Aires province share of the national roll | C48: argentina.gob.ar Observatorio Electoral returned 403. ~37-38% is approximate - verify before publishing.

Sheet CPI Data
B2: INDEC IPC nacional — index levels and every derived rate
B3: Blue = published index level. Black = formula. Paste a new print into the yellow row and the workbook updates.
B5: Month | C5: Year | D5: M# | E5: Nivel General (index) | F5: Nucleo (index) | G5: Regulados (index) | H5: Estacionales (index) | I5: m/m Nivel Gen. | J5: m/m Nucleo | K5: m/m Regulados | L5: m/m Estacion. | M5: y/y Nivel Gen. | N5: y/y Nucleo | O5: y/y Regulados | P5: 3m ann. Nivel Gen. | Q5: 3m ann. Nucleo | R5: 6m ann. Nivel Gen. | S5: YTD Nivel Gen. | T5: Reg less core m/m (pp) | U5: Reg/core Dec-23=100
B6: 2018-12 | C6: 2018 | D6: 12 | E6: 184.2552 | F6: 178.9326 | T6: =IF(OR(K6="",J6=""),"",(K6-J6)*100) | U6: =IF(OR(G6="",F6=""),"",(G6/INDEX($G:$G,MATCH("2023-12",$B:$B,0)))/(F6/INDEX($F:$F,MATCH("2023-12",$B:$B,0)))*100)
B7: 2019-01 | C7: 2019 | D7: 1 | E7: 189.6101 | F7: 184.3056 | I7: =IF(OR(E7="",E6=""),"",E7/E6-1) | J7: =IF(OR(F7="",F6=""),"",F7/F6-1) | K7: =IF(OR(G7="",G6=""),"",G7/G6-1) | L7: =IF(OR(H7="",H6=""),"",H7/H6-1) | S7: =IF(E7="","",IFERROR(E7/INDEX($E:$E,MATCH(C7-1&"-12",$B:$B,0))-1,"")) | T7: =IF(OR(K7="",J7=""),"",(K7-J7)*100) | U7: =IF(OR(G7="",F7=""),"",(G7/INDEX($G:$G,MATCH("2023-12",$B:$B,0)))/(F7/INDEX($F:$F,MATCH("2023-12",$B:$B,0)))*100)
B8: 2019-02 | C8: 2019 | D8: 2 | E8: 196.7501 | F8: 191.4115 | I8: =IF(OR(E8="",E7=""),"",E8/E7-1) | J8: =IF(OR(F8="",F7=""),"",F8/F7-1) | K8: =IF(OR(G8="",G7=""),"",G8/G7-1) | L8: =IF(OR(H8="",H7=""),"",H8/H7-1) | S8: =IF(E8="","",IFERROR(E8/INDEX($E:$E,MATCH(C8-1&"-12",$B:$B,0))-1,"")) | T8: =IF(OR(K8="",J8=""),"",(K8-J8)*100) | U8: =IF(OR(G8="",F8=""),"",(G8/INDEX($G:$G,MATCH("2023-12",$B:$B,0)))/(F8/INDEX($F:$F,MATCH("2023-12",$B:$B,0)))*100)
B9: 2019-03 | C9: 2019 | D9: 3 | E9: 205.9571 | F9: 200.1771 | I9: =IF(OR(E9="",E8=""),"",E9/E8-1) | J9: =IF(OR(F9="",F8=""),"",F9/F8-1) | K9: =IF(OR(G9="",G8=""),"",G9/G8-1) | L9: =IF(OR(H9="",H8=""),"",H9/H8-1) | P9: =IF(OR(E9="",E6=""),"",(E9/E6)^4-1) | Q9: =IF(OR(F9="",F6=""),"",(F9/F6)^4-1) | S9: =IF(E9="","",IFERROR(E9/INDEX($E:$E,MATCH(C9-1&"-12",$B:$B,0))-1,"")) | T9: =IF(OR(K9="",J9=""),"",(K9-J9)*100) | U9: =IF(OR(G9="",F9=""),"",(G9/INDEX($G:$G,MATCH("2023-12",$B:$B,0)))/(F9/INDEX($F:$F,MATCH("2023-12",$B:$B,0)))*100)
B10: 2019-04 | C10: 2019 | D10: 4 | E10: 212.95964 | F10: 207.7179 | I10: =IF(OR(E10="",E9=""),"",E10/E9-1) | J10: =IF(OR(F10="",F9=""),"",F10/F9-1) | K10: =IF(OR(G10="",G9=""),"",G10/G9-1) | L10: =IF(OR(H10="",H9=""),"",H10/H9-1) | P10: =IF(OR(E10="",E7=""),"",(E10/E7)^4-1) | Q10: =IF(OR(F10="",F7=""),"",(F10/F7)^4-1) | S10: =IF(E10="","",IFERROR(E10/INDEX($E:$E,MATCH(C10-1&"-12",$B:$B,0))-1,"")) | T10: =IF(OR(K10="",J10=""),"",(K10-J10)*100) | U10: =IF(OR(G10="",F10=""),"",(G10/INDEX($G:$G,MATCH("2023-12",$B:$B,0)))/(F10/INDEX($F:$F,MATCH("2023-12",$B:$B,0)))*100)
B11: 2019-05 | C11: 2019 | D11: 5 | E11: 219.5691 | F11: 214.3182 | I11: =IF(OR(E11="",E10=""),"",E11/E10-1) | J11: =IF(OR(F11="",F10=""),"",F11/F10-1) | K11: =IF(OR(G11="",G10=""),"",G11/G10-1) | L11: =IF(OR(H11="",H10=""),"",H11/H10-1) | P11: =IF(OR(E11="",E8=""),"",(E11/E8)^4-1) | Q11: =IF(OR(F11="",F8=""),"",(F11/F8)^4-1) | S11: =IF(E11="","",IFERROR(E11/INDEX($E:$E,MATCH(C11-1&"-12",$B:$B,0))-1,"")) | T11: =IF(OR(K11="",J11=""),"",(K11-J11)*100) | U11: =IF(OR(G11="",F11=""),"",(G11/INDEX($G:$G,MATCH("2023-12",$B:$B,0)))/(F11/INDEX($F:$F,MATCH("2023-12",$B:$B,0)))*100)
B12: 2019-06 | C12: 2019 | D12: 6 | E12: 225.537 | F12: 220.1725 | I12: =IF(OR(E12="",E11=""),"",E12/E11-1) | J12: =IF(OR(F12="",F11=""),"",F12/F11-1) | K12: =IF(OR(G12="",G11=""),"",G12/G11-1) | L12: =IF(OR(H12="",H11=""),"",H12/H11-1) | P12: =IF(OR(E12="",E9=""),"",(E12/E9)^4-1) | Q12: =IF(OR(F12="",F9=""),"",(F12/F9)^4-1) | R12: =IF(OR(E12="",E6=""),"",(E12/E6)^2-1) | S12: =IF(E12="","",IFERROR(E12/INDEX($E:$E,MATCH(C12-1&"-12",$B:$B,0))-1,"")) | T12: =IF(OR(K12="",J12=""),"",(K12-J12)*100) | U12: =IF(OR(G12="",F12=""),"",(G12/INDEX($G:$G,MATCH("2023-12",$B:$B,0)))/(F12/INDEX($F:$F,MATCH("2023-12",$B:$B,0)))*100)
B13: 2019-07 | C13: 2019 | D13: 7 | E13: 230.494 | F13: 224.9011 | I13: =IF(OR(E13="",E12=""),"",E13/E12-1) | J13: =IF(OR(F13="",F12=""),"",F13/F12-1) | K13: =IF(OR(G13="",G12=""),"",G13/G12-1) | L13: =IF(OR(H13="",H12=""),"",H13/H12-1) | P13: =IF(OR(E13="",E10=""),"",(E13/E10)^4-1) | Q13: =IF(OR(F13="",F10=""),"",(F13/F10)^4-1) | R13: =IF(OR(E13="",E7=""),"",(E13/E7)^2-1) | S13: =IF(E13="","",IFERROR(E13/INDEX($E:$E,MATCH(C13-1&"-12",$B:$B,0))-1,"")) | T13: =IF(OR(K13="",J13=""),"",(K13-J13)*100) | U13: =IF(OR(G13="",F13=""),"",(G13/INDEX($G:$G,MATCH("2023-12",$B:$B,0)))/(F13/INDEX($F:$F,MATCH("2023-12",$B:$B,0)))*100)
B14: 2019-08 | C14: 2019 | D14: 8 | E14: 239.6077 | F14: 235.3317 | I14: =IF(OR(E14="",E13=""),"",E14/E13-1) | J14: =IF(OR(F14="",F13=""),"",F14/F13-1) | K14: =IF(OR(G14="",G13=""),"",G14/G13-1) | L14: =IF(OR(H14="",H13=""),"",H14/H13-1) | P14: =IF(OR(E14="",E11=""),"",(E14/E11)^4-1) | Q14: =IF(OR(F14="",F11=""),"",(F14/F11)^4-1) | R14: =IF(OR(E14="",E8=""),"",(E14/E8)^2-1) | S14: =IF(E14="","",IFERROR(E14/INDEX($E:$E,MATCH(C14-1&"-12",$B:$B,0))-1,"")) | T14: =IF(OR(K14="",J14=""),"",(K14-J14)*100) | U14: =IF(OR(G14="",F14=""),"",(G14/INDEX($G:$G,MATCH("2023-12",$B:$B,0)))/(F14/INDEX($F:$F,MATCH("2023-12",$B:$B,0)))*100)
B15: 2019-09 | C15: 2019 | D15: 9 | E15: 253.7102 | F15: 250.4818 | I15: =IF(OR(E15="",E14=""),"",E15/E14-1) | J15: =IF(OR(F15="",F14=""),"",F15/F14-1) | K15: =IF(OR(G15="",G14=""),"",G15/G14-1) | L15: =IF(OR(H15="",H14=""),"",H15/H14-1) | P15: =IF(OR(E15="",E12=""),"",(E15/E12)^4-1) | Q15: =IF(OR(F15="",F12=""),"",(F15/F12)^4-1) | R15: =IF(OR(E15="",E9=""),"",(E15/E9)^2-1) | S15: =IF(E15="","",IFERROR(E15/INDEX($E:$E,MATCH(C15-1&"-12",$B:$B,0))-1,"")) | T15: =IF(OR(K15="",J15=""),"",(K15-J15)*100) | U15: =IF(OR(G15="",F15=""),"",(G15/INDEX($G:$G,MATCH("2023-12",$B:$B,0)))/(F15/INDEX($F:$F,MATCH("2023-12",$B:$B,0)))*100)
B16: 2019-10 | C16: 2019 | D16: 10 | E16: 262.0661 | F16: 260.0118 | I16: =IF(OR(E16="",E15=""),"",E16/E15-1) | J16: =IF(OR(F16="",F15=""),"",F16/F15-1) | K16: =IF(OR(G16="",G15=""),"",G16/G15-1) | L16: =IF(OR(H16="",H15=""),"",H16/H15-1) | P16: =IF(OR(E16="",E13=""),"",(E16/E13)^4-1) | Q16: =IF(OR(F16="",F13=""),"",(F16/F13)^4-1) | R16: =IF(OR(E16="",E10=""),"",(E16/E10)^2-1) | S16: =IF(E16="","",IFERROR(E16/INDEX($E:$E,MATCH(C16-1&"-12",$B:$B,0))-1,"")) | T16: =IF(OR(K16="",J16=""),"",(K16-J16)*100) | U16: =IF(OR(G16="",F16=""),"",(G16/INDEX($G:$G,MATCH("2023-12",$B:$B,0)))/(F16/INDEX($F:$F,MATCH("2023-12",$B:$B,0)))*100)
B17: 2019-11 | C17: 2019 | D17: 11 | E17: 273.2158 | F17: 270.3554 | I17: =IF(OR(E17="",E16=""),"",E17/E16-1) | J17: =IF(OR(F17="",F16=""),"",F17/F16-1) | K17: =IF(OR(G17="",G16=""),"",G17/G16-1) | L17: =IF(OR(H17="",H16=""),"",H17/H16-1) | P17: =IF(OR(E17="",E14=""),"",(E17/E14)^4-1) | Q17: =IF(OR(F17="",F14=""),"",(F17/F14)^4-1) | R17: =IF(OR(E17="",E11=""),"",(E17/E11)^2-1) | S17: =IF(E17="","",IFERROR(E17/INDEX($E:$E,MATCH(C17-1&"-12",$B:$B,0))-1,"")) | T17: =IF(OR(K17="",J17=""),"",(K17-J17)*100) | U17: =IF(OR(G17="",F17=""),"",(G17/INDEX($G:$G,MATCH("2023-12",$B:$B,0)))/(F17/INDEX($F:$F,MATCH("2023-12",$B:$B,0)))*100)
B18: 2019-12 | C18: 2019 | D18: 12 | E18: 283.4442 | F18: 280.3107 | I18: =IF(OR(E18="",E17=""),"",E18/E17-1) | J18: =IF(OR(F18="",F17=""),"",F18/F17-1) | K18: =IF(OR(G18="",G17=""),"",G18/G17-1) | L18: =IF(OR(H18="",H17=""),"",H18/H17-1) | M18: =IF(OR(E18="",E6=""),"",E18/E6-1) | N18: =IF(OR(F18="",F6=""),"",F18/F6-1) | O18: =IF(OR(G18="",G6=""),"",G18/G6-1) | P18: =IF(OR(E18="",E15=""),"",(E18/E15)^4-1) | Q18: =IF(OR(F18="",F15=""),"",(F18/F15)^4-1) | R18: =IF(OR(E18="",E12=""),"",(E18/E12)^2-1) | S18: =IF(E18="","",IFERROR(E18/INDEX($E:$E,MATCH(C18-1&"-12",$B:$B,0))-1,"")) | T18: =IF(OR(K18="",J18=""),"",(K18-J18)*100) | U18: =IF(OR(G18="",F18=""),"",(G18/INDEX($G:$G,MATCH("2023-12",$B:$B,0)))/(F18/INDEX($F:$F,MATCH("2023-12",$B:$B,0)))*100)
B19: 2020-01 | C19: 2020 | D19: 1 | E19: 289.8299 | F19: 287.1529 | I19: =IF(OR(E19="",E18=""),"",E19/E18-1) | J19: =IF(OR(F19="",F18=""),"",F19/F18-1) | K19: =IF(OR(G19="",G18=""),"",G19/G18-1) | L19: =IF(OR(H19="",H18=""),"",H19/H18-1) | M19: =IF(OR(E19="",E7=""),"",E19/E7-1) | N19: =IF(OR(F19="",F7=""),"",F19/F7-1) | O19: =IF(OR(G19="",G7=""),"",G19/G7-1) | P19: =IF(OR(E19="",E16=""),"",(E19/E16)^4-1) | Q19: =IF(OR(F19="",F16=""),"",(F19/F16)^4-1) | R19: =IF(OR(E19="",E13=""),"",(E19/E13)^2-1) | S19: =IF(E19="","",IFERROR(E19/INDEX($E:$E,MATCH(C19-1&"-12",$B:$B,0))-1,"")) | T19: =IF(OR(K19="",J19=""),"",(K19-J19)*100) | U19: =IF(OR(G19="",F19=""),"",(G19/INDEX($G:$G,MATCH("2023-12",$B:$B,0)))/(F19/INDEX($F:$F,MATCH("2023-12",$B:$B,0)))*100)
B20: 2020-02 | C20: 2020 | D20: 2 | E20: 295.666 | F20: 293.9922 | I20: =IF(OR(E20="",E19=""),"",E20/E19-1) | J20: =IF(OR(F20="",F19=""),"",F20/F19-1) | K20: =IF(OR(G20="",G19=""),"",G20/G19-1) | L20: =IF(OR(H20="",H19=""),"",H20/H19-1) | M20: =IF(OR(E20="",E8=""),"",E20/E8-1) | N20: =IF(OR(F20="",F8=""),"",F20/F8-1) | O20: =IF(OR(G20="",G8=""),"",G20/G8-1) | P20: =IF(OR(E20="",E17=""),"",(E20/E17)^4-1) | Q20: =IF(OR(F20="",F17=""),"",(F20/F17)^4-1) | R20: =IF(OR(E20="",E14=""),"",(E20/E14)^2-1) | S20: =IF(E20="","",IFERROR(E20/INDEX($E:$E,MATCH(C20-1&"-12",$B:$B,0))-1,"")) | T20: =IF(OR(K20="",J20=""),"",(K20-J20)*100) | U20: =IF(OR(G20="",F20=""),"",(G20/INDEX($G:$G,MATCH("2023-12",$B:$B,0)))/(F20/INDEX($F:$F,MATCH("2023-12",$B:$B,0)))*100)
B21: 2020-03 | C21: 2020 | D21: 3 | E21: 305.5515 | F21: 303.1665 | I21: =IF(OR(E21="",E20=""),"",E21/E20-1) | J21: =IF(OR(F21="",F20=""),"",F21/F20-1) | K21: =IF(OR(G21="",G20=""),"",G21/G20-1) | L21: =IF(OR(H21="",H20=""),"",H21/H20-1) | M21: =IF(OR(E21="",E9=""),"",E21/E9-1) | N21: =IF(OR(F21="",F9=""),"",F21/F9-1) | O21: =IF(OR(G21="",G9=""),"",G21/G9-1) | P21: =IF(OR(E21="",E18=""),"",(E21/E18)^4-1) | Q21: =IF(OR(F21="",F18=""),"",(F21/F18)^4-1) | R21: =IF(OR(E21="",E15=""),"",(E21/E15)^2-1) | S21: =IF(E21="","",IFERROR(E21/INDEX($E:$E,MATCH(C21-1&"-12",$B:$B,0))-1,"")) | T21: =IF(OR(K21="",J21=""),"",(K21-J21)*100) | U21: =IF(OR(G21="",F21=""),"",(G21/INDEX($G:$G,MATCH("2023-12",$B:$B,0)))/(F21/INDEX($F:$F,MATCH("2023-12",$B:$B,0)))*100)
B22: 2020-04 | C22: 2020 | D22: 4 | E22: 310.1243 | F22: 308.3681 | I22: =IF(OR(E22="",E21=""),"",E22/E21-1) | J22: =IF(OR(F22="",F21=""),"",F22/F21-1) | K22: =IF(OR(G22="",G21=""),"",G22/G21-1) | L22: =IF(OR(H22="",H21=""),"",H22/H21-1) | M22: =IF(OR(E22="",E10=""),"",E22/E10-1) | N22: =IF(OR(F22="",F10=""),"",F22/F10-1) | O22: =IF(OR(G22="",G10=""),"",G22/G10-1) | P22: =IF(OR(E22="",E19=""),"",(E22/E19)^4-1) | Q22: =IF(OR(F22="",F19=""),"",(F22/F19)^4-1) | R22: =IF(OR(E22="",E16=""),"",(E22/E16)^2-1) | S22: =IF(E22="","",IFERROR(E22/INDEX($E:$E,MATCH(C22-1&"-12",$B:$B,0))-1,"")) | T22: =IF(OR(K22="",J22=""),"",(K22-J22)*100) | U22: =IF(OR(G22="",F22=""),"",(G22/INDEX($G:$G,MATCH("2023-12",$B:$B,0)))/(F22/INDEX($F:$F,MATCH("2023-12",$B:$B,0)))*100)
B23: 2020-05 | C23: 2020 | D23: 5 | E23: 314.9087 | F23: 313.3195 | I23: =IF(OR(E23="",E22=""),"",E23/E22-1) | J23: =IF(OR(F23="",F22=""),"",F23/F22-1) | K23: =IF(OR(G23="",G22=""),"",G23/G22-1) | L23: =IF(OR(H23="",H22=""),"",H23/H22-1) | M23: =IF(OR(E23="",E11=""),"",E23/E11-1) | N23: =IF(OR(F23="",F11=""),"",F23/F11-1) | O23: =IF(OR(G23="",G11=""),"",G23/G11-1) | P23: =IF(OR(E23="",E20=""),"",(E23/E20)^4-1) | Q23: =IF(OR(F23="",F20=""),"",(F23/F20)^4-1) | R23: =IF(OR(E23="",E17=""),"",(E23/E17)^2-1) | S23: =IF(E23="","",IFERROR(E23/INDEX($E:$E,MATCH(C23-1&"-12",$B:$B,0))-1,"")) | T23: =IF(OR(K23="",J23=""),"",(K23-J23)*100) | U23: =IF(OR(G23="",F23=""),"",(G23/INDEX($G:$G,MATCH("2023-12",$B:$B,0)))/(F23/INDEX($F:$F,MATCH("2023-12",$B:$B,0)))*100)
B24: 2020-06 | C24: 2020 | D24: 6 | E24: 321.9738 | F24: 320.5733 | I24: =IF(OR(E24="",E23=""),"",E24/E23-1) | J24: =IF(OR(F24="",F23=""),"",F24/F23-1) | K24: =IF(OR(G24="",G23=""),"",G24/G23-1) | L24: =IF(OR(H24="",H23=""),"",H24/H23-1) | M24: =IF(OR(E24="",E12=""),"",E24/E12-1) | N24: =IF(OR(F24="",F12=""),"",F24/F12-1) | O24: =IF(OR(G24="",G12=""),"",G24/G12-1) | P24: =IF(OR(E24="",E21=""),"",(E24/E21)^4-1) | Q24: =IF(OR(F24="",F21=""),"",(F24/F21)^4-1) | R24: =IF(OR(E24="",E18=""),"",(E24/E18)^2-1) | S24: =IF(E24="","",IFERROR(E24/INDEX($E:$E,MATCH(C24-1&"-12",$B:$B,0))-1,"")) | T24: =IF(OR(K24="",J24=""),"",(K24-J24)*100) | U24: =IF(OR(G24="",F24=""),"",(G24/INDEX($G:$G,MATCH("2023-12",$B:$B,0)))/(F24/INDEX($F:$F,MATCH("2023-12",$B:$B,0)))*100)
B25: 2020-07 | C25: 2020 | D25: 7 | E25: 328.2014 | F25: 328.6943 | I25: =IF(OR(E25="",E24=""),"",E25/E24-1) | J25: =IF(OR(F25="",F24=""),"",F25/F24-1) | K25: =IF(OR(G25="",G24=""),"",G25/G24-1) | L25: =IF(OR(H25="",H24=""),"",H25/H24-1) | M25: =IF(OR(E25="",E13=""),"",E25/E13-1) | N25: =IF(OR(F25="",F13=""),"",F25/F13-1) | O25: =IF(OR(G25="",G13=""),"",G25/G13-1) | P25: =IF(OR(E25="",E22=""),"",(E25/E22)^4-1) | Q25: =IF(OR(F25="",F22=""),"",(F25/F22)^4-1) | R25: =IF(OR(E25="",E19=""),"",(E25/E19)^2-1) | S25: =IF(E25="","",IFERROR(E25/INDEX($E:$E,MATCH(C25-1&"-12",$B:$B,0))-1,"")) | T25: =IF(OR(K25="",J25=""),"",(K25-J25)*100) | U25: =IF(OR(G25="",F25=""),"",(G25/INDEX($G:$G,MATCH("2023-12",$B:$B,0)))/(F25/INDEX($F:$F,MATCH("2023-12",$B:$B,0)))*100)
B26: 2020-08 | C26: 2020 | D26: 8 | E26: 337.0632 | F26: 338.6645 | I26: =IF(OR(E26="",E25=""),"",E26/E25-1) | J26: =IF(OR(F26="",F25=""),"",F26/F25-1) | K26: =IF(OR(G26="",G25=""),"",G26/G25-1) | L26: =IF(OR(H26="",H25=""),"",H26/H25-1) | M26: =IF(OR(E26="",E14=""),"",E26/E14-1) | N26: =IF(OR(F26="",F14=""),"",F26/F14-1) | O26: =IF(OR(G26="",G14=""),"",G26/G14-1) | P26: =IF(OR(E26="",E23=""),"",(E26/E23)^4-1) | Q26: =IF(OR(F26="",F23=""),"",(F26/F23)^4-1) | R26: =IF(OR(E26="",E20=""),"",(E26/E20)^2-1) | S26: =IF(E26="","",IFERROR(E26/INDEX($E:$E,MATCH(C26-1&"-12",$B:$B,0))-1,"")) | T26: =IF(OR(K26="",J26=""),"",(K26-J26)*100) | U26: =IF(OR(G26="",F26=""),"",(G26/INDEX($G:$G,MATCH("2023-12",$B:$B,0)))/(F26/INDEX($F:$F,MATCH("2023-12",$B:$B,0)))*100)
B27: 2020-09 | C27: 2020 | D27: 9 | E27: 346.6207 | F27: 346.511 | I27: =IF(OR(E27="",E26=""),"",E27/E26-1) | J27: =IF(OR(F27="",F26=""),"",F27/F26-1) | K27: =IF(OR(G27="",G26=""),"",G27/G26-1) | L27: =IF(OR(H27="",H26=""),"",H27/H26-1) | M27: =IF(OR(E27="",E15=""),"",E27/E15-1) | N27: =IF(OR(F27="",F15=""),"",F27/F15-1) | O27: =IF(OR(G27="",G15=""),"",G27/G15-1) | P27: =IF(OR(E27="",E24=""),"",(E27/E24)^4-1) | Q27: =IF(OR(F27="",F24=""),"",(F27/F24)^4-1) | R27: =IF(OR(E27="",E21=""),"",(E27/E21)^2-1) | S27: =IF(E27="","",IFERROR(E27/INDEX($E:$E,MATCH(C27-1&"-12",$B:$B,0))-1,"")) | T27: =IF(OR(K27="",J27=""),"",(K27-J27)*100) | U27: =IF(OR(G27="",F27=""),"",(G27/INDEX($G:$G,MATCH("2023-12",$B:$B,0)))/(F27/INDEX($F:$F,MATCH("2023-12",$B:$B,0)))*100)
B28: 2020-10 | C28: 2020 | D28: 10 | E28: 359.657 | F28: 358.4989 | I28: =IF(OR(E28="",E27=""),"",E28/E27-1) | J28: =IF(OR(F28="",F27=""),"",F28/F27-1) | K28: =IF(OR(G28="",G27=""),"",G28/G27-1) | L28: =IF(OR(H28="",H27=""),"",H28/H27-1) | M28: =IF(OR(E28="",E16=""),"",E28/E16-1) | N28: =IF(OR(F28="",F16=""),"",F28/F16-1) | O28: =IF(OR(G28="",G16=""),"",G28/G16-1) | P28: =IF(OR(E28="",E25=""),"",(E28/E25)^4-1) | Q28: =IF(OR(F28="",F25=""),"",(F28/F25)^4-1) | R28: =IF(OR(E28="",E22=""),"",(E28/E22)^2-1) | S28: =IF(E28="","",IFERROR(E28/INDEX($E:$E,MATCH(C28-1&"-12",$B:$B,0))-1,"")) | T28: =IF(OR(K28="",J28=""),"",(K28-J28)*100) | U28: =IF(OR(G28="",F28=""),"",(G28/INDEX($G:$G,MATCH("2023-12",$B:$B,0)))/(F28/INDEX($F:$F,MATCH("2023-12",$B:$B,0)))*100)
B29: 2020-11 | C29: 2020 | D29: 11 | E29: 371.0211 | F29: 372.6154 | I29: =IF(OR(E29="",E28=""),"",E29/E28-1) | J29: =IF(OR(F29="",F28=""),"",F29/F28-1) | K29: =IF(OR(G29="",G28=""),"",G29/G28-1) | L29: =IF(OR(H29="",H28=""),"",H29/H28-1) | M29: =IF(OR(E29="",E17=""),"",E29/E17-1) | N29: =IF(OR(F29="",F17=""),"",F29/F17-1) | O29: =IF(OR(G29="",G17=""),"",G29/G17-1) | P29: =IF(OR(E29="",E26=""),"",(E29/E26)^4-1) | Q29: =IF(OR(F29="",F26=""),"",(F29/F26)^4-1) | R29: =IF(OR(E29="",E23=""),"",(E29/E23)^2-1) | S29: =IF(E29="","",IFERROR(E29/INDEX($E:$E,MATCH(C29-1&"-12",$B:$B,0))-1,"")) | T29: =IF(OR(K29="",J29=""),"",(K29-J29)*100) | U29: =IF(OR(G29="",F29=""),"",(G29/INDEX($G:$G,MATCH("2023-12",$B:$B,0)))/(F29/INDEX($F:$F,MATCH("2023-12",$B:$B,0)))*100)
... B42: 2021-12 | C42: 2021 | D42: 12 | E42: 582.4575 | F42: 605.1759 | I42: =IF(OR(E42="",E41=""),"",E42/E41-1) | J42: =IF(OR(F42="",F41=""),"",F42/F41-1) | K42: =IF(OR(G42="",G41=""),"",G42/G41-1) | L42: =IF(OR(H42="",H41=""),"",H42/H41-1) | M42: =IF(OR(E42="",E30=""),"",E42/E30-1) | N42: =IF(OR(F42="",F30=""),"",F42/F30-1) | O42: =IF(OR(G42="",G30=""),"",G42/G30-1) | P42: =IF(OR(E42="",E39=""),"",(E42/E39)^4-1) | Q42: =IF(OR(F42="",F39=""),"",(F42/F39)^4-1) | R42: =IF(OR(E42="",E36=""),"",(E42/E36)^2-1) | S42: =IF(E42="","",IFERROR(E42/INDEX($E:$E,MATCH(C42-1&"-12",$B:$B,0))-1,"")) | T42: =IF(OR(K42="",J42=""),"",(K42-J42)*100) | U42: =IF(OR(G42="",F42=""),"",(G42/INDEX($G:$G,MATCH("2023-12",$B:$B,0)))/(F42/INDEX($F:$F,MATCH("2023-12",$B:$B,0)))*100)
B43: 2022-01 | C43: 2022 | D43: 1 | E43: 605.0317 | F43: 625.1594 | G43: 512.3766 | H43: 658.2543 | I43: =IF(OR(E43="",E42=""),"",E43/E42-1) | J43: =IF(OR(F43="",F42=""),"",F43/F42-1) | K43: =IF(OR(G43="",G42=""),"",G43/G42-1) | L43: =IF(OR(H43="",H42=""),"",H43/H42-1) | M43: =IF(OR(E43="",E31=""),"",E43/E31-1) | N43: =IF(OR(F43="",F31=""),"",F43/F31-1) | O43: =IF(OR(G43="",G31=""),"",G43/G31-1) | P43: =IF(OR(E43="",E40=""),"",(E43/E40)^4-1) | Q43: =IF(OR(F43="",F40=""),"",(F43/F40)^4-1) | R43: =IF(OR(E43="",E37=""),"",(E43/E37)^2-1) | S43: =IF(E43="","",IFERROR(E43/INDEX($E:$E,MATCH(C43-1&"-12",$B:$B,0))-1,"")) | T43: =IF(OR(K43="",J43=""),"",(K43-J43)*100) | U43: =IF(OR(G43="",F43=""),"",(G43/INDEX($G:$G,MATCH("2023-12",$B:$B,0)))/(F43/INDEX($F:$F,MATCH("2023-12",$B:$B,0)))*100)
B44: 2022-02 | C44: 2022 | D44: 2 | E44: 633.4341 | F44: 652.9838 | G44: 528.2683 | H44: 713.7013 | I44: =IF(OR(E44="",E43=""),"",E44/E43-1) | J44: =IF(OR(F44="",F43=""),"",F44/F43-1) | K44: =IF(OR(G44="",G43=""),"",G44/G43-1) | L44: =IF(OR(H44="",H43=""),"",H44/H43-1) | M44: =IF(OR(E44="",E32=""),"",E44/E32-1) | N44: =IF(OR(F44="",F32=""),"",F44/F32-1) | O44: =IF(OR(G44="",G32=""),"",G44/G32-1) | P44: =IF(OR(E44="",E41=""),"",(E44/E41)^4-1) | Q44: =IF(OR(F44="",F41=""),"",(F44/F41)^4-1) | R44: =IF(OR(E44="",E38=""),"",(E44/E38)^2-1) | S44: =IF(E44="","",IFERROR(E44/INDEX($E:$E,MATCH(C44-1&"-12",$B:$B,0))-1,"")) | T44: =IF(OR(K44="",J44=""),"",(K44-J44)*100) | U44: =IF(OR(G44="",F44=""),"",(G44/INDEX($G:$G,MATCH("2023-12",$B:$B,0)))/(F44/INDEX($F:$F,MATCH("2023-12",$B:$B,0)))*100)
B45: 2022-03 | C45: 2022 | D45: 3 | E45: 676.0566 | F45: 694.7515 | G45: 572.7992 | H45: 757.8963 | I45: =IF(OR(E45="",E44=""),"",E45/E44-1) | J45: =IF(OR(F45="",F44=""),"",F45/F44-1) | K45: =IF(OR(G45="",G44=""),"",G45/G44-1) | L45: =IF(OR(H45="",H44=""),"",H45/H44-1) | M45: =IF(OR(E45="",E33=""),"",E45/E33-1) | N45: =IF(OR(F45="",F33=""),"",F45/F33-1) | O45: =IF(OR(G45="",G33=""),"",G45/G33-1) | P45: =IF(OR(E45="",E42=""),"",(E45/E42)^4-1) | Q45: =IF(OR(F45="",F42=""),"",(F45/F42)^4-1) | R45: =IF(OR(E45="",E39=""),"",(E45/E39)^2-1) | S45: =IF(E45="","",IFERROR(E45/INDEX($E:$E,MATCH(C45-1&"-12",$B:$B,0))-1,"")) | T45: =IF(OR(K45="",J45=""),"",(K45-J45)*100) | U45: =IF(OR(G45="",F45=""),"",(G45/INDEX($G:$G,MATCH("2023-12",$B:$B,0)))/(F45/INDEX($F:$F,MATCH("2023-12",$B:$B,0)))*100)
B46: 2022-04 | C46: 2022 | D46: 4 | E46: 716.9399 | F46: 741.3622 | G46: 595.2223 | H46: 799.0308 | I46: =IF(OR(E46="",E45=""),"",E46/E45-1) | J46: =IF(OR(F46="",F45=""),"",F46/F45-1) | K46: =IF(OR(G46="",G45=""),"",G46/G45-1) | L46: =IF(OR(H46="",H45=""),"",H46/H45-1) | M46: =IF(OR(E46="",E34=""),"",E46/E34-1) | N46: =IF(OR(F46="",F34=""),"",F46/F34-1) | O46: =IF(OR(G46="",G34=""),"",G46/G34-1) | P46: =IF(OR(E46="",E43=""),"",(E46/E43)^4-1) | Q46: =IF(OR(F46="",F43=""),"",(F46/F43)^4-1) | R46: =IF(OR(E46="",E40=""),"",(E46/E40)^2-1) | S46: =IF(E46="","",IFERROR(E46/INDEX($E:$E,MATCH(C46-1&"-12",$B:$B,0))-1,"")) | T46: =IF(OR(K46="",J46=""),"",(K46-J46)*100) | U46: =IF(OR(G46="",F46=""),"",(G46/INDEX($G:$G,MATCH("2023-12",$B:$B,0)))/(F46/INDEX($F:$F,MATCH("2023-12",$B:$B,0)))*100)
B47: 2022-05 | C47: 2022 | D47: 5 | E47: 753.147 | F47: 779.9267 | G47: 629.0029 | H47: 825.8088 | I47: =IF(OR(E47="",E46=""),"",E47/E46-1) | J47: =IF(OR(F47="",F46=""),"",F47/F46-1) | K47: =IF(OR(G47="",G46=""),"",G47/G46-1) | L47: =IF(OR(H47="",H46=""),"",H47/H46-1) | M47: =IF(OR(E47="",E35=""),"",E47/E35-1) | N47: =IF(OR(F47="",F35=""),"",F47/F35-1) | O47: =IF(OR(G47="",G35=""),"",G47/G35-1) | P47: =IF(OR(E47="",E44=""),"",(E47/E44)^4-1) | Q47: =IF(OR(F47="",F44=""),"",(F47/F44)^4-1) | R47: =IF(OR(E47="",E41=""),"",(E47/E41)^2-1) | S47: =IF(E47="","",IFERROR(E47/INDEX($E:$E,MATCH(C47-1&"-12",$B:$B,0))-1,"")) | T47: =IF(OR(K47="",J47=""),"",(K47-J47)*100) | U47: =IF(OR(G47="",F47=""),"",(G47/INDEX($G:$G,MATCH("2023-12",$B:$B,0)))/(F47/INDEX($F:$F,MATCH("2023-12",$B:$B,0)))*100)
B48: 2022-06 | C48: 2022 | D48: 6 | E48: 793.0278 | F48: 819.5734 | G48: 662.0938 | H48: 880.3186 | I48: =IF(OR(E48="",E47=""),"",E48/E47-1) | J48: =IF(OR(F48="",F47=""),"",F48/F47-1) | K48: =IF(OR(G48="",G47=""),"",G48/G47-1) | L48: =IF(OR(H48="",H47=""),"",H48/H47-1) | M48: =IF(OR(E48="",E36=""),"",E48/E36-1) | N48: =IF(OR(F48="",F36=""),"",F48/F36-1) | O48: =IF(OR(G48="",G36=""),"",G48/G36-1) | P48: =IF(OR(E48="",E45=""),"",(E48/E45)^4-1) | Q48: =IF(OR(F48="",F45=""),"",(F48/F45)^4-1) | R48: =IF(OR(E48="",E42=""),"",(E48/E42)^2-1) | S48: =IF(E48="","",IFERROR(E48/INDEX($E:$E,MATCH(C48-1&"-12",$B:$B,0))-1,"")) | T48: =IF(OR(K48="",J48=""),"",(K48-J48)*100) | U48: =IF(OR(G48="",F48=""),"",(G48/INDEX($G:$G,MATCH("2023-12",$B:$B,0)))/(F48/INDEX($F:$F,MATCH("2023-12",$B:$B,0)))*100)
B49: 2022-07 | C49: 2022 | D49: 7 | E49: 851.761 | F49: 879.6383 | G49: 694.6115 | H49: 979.7957 | I49: =IF(OR(E49="",E48=""),"",E49/E48-1) | J49: =IF(OR(F49="",F48=""),"",F49/F48-1) | K49: =IF(OR(G49="",G48=""),"",G49/G48-1) | L49: =IF(OR(H49="",H48=""),"",H49/H48-1) | M49: =IF(OR(E49="",E37=""),"",E49/E37-1) | N49: =IF(OR(F49="",F37=""),"",F49/F37-1) | O49: =IF(OR(G49="",G37=""),"",G49/G37-1) | P49: =IF(OR(E49="",E46=""),"",(E49/E46)^4-1) | Q49: =IF(OR(F49="",F46=""),"",(F49/F46)^4-1) | R49: =IF(OR(E49="",E43=""),"",(E49/E43)^2-1) | S49: =IF(E49="","",IFERROR(E49/INDEX($E:$E,MATCH(C49-1&"-12",$B:$B,0))-1,"")) | T49: =IF(OR(K49="",J49=""),"",(K49-J49)*100) | U49: =IF(OR(G49="",F49=""),"",(G49/INDEX($G:$G,MATCH("2023-12",$B:$B,0)))/(F49/INDEX($F:$F,MATCH("2023-12",$B:$B,0)))*100)
B50: 2022-08 | C50: 2022 | D50: 8 | E50: 911.1316 | F50: 939.4677 | G50: 738.3105 | H50: 1064.731 | I50: =IF(OR(E50="",E49=""),"",E50/E49-1) | J50: =IF(OR(F50="",F49=""),"",F50/F49-1) | K50: =IF(OR(G50="",G49=""),"",G50/G49-1) | L50: =IF(OR(H50="",H49=""),"",H50/H49-1) | M50: =IF(OR(E50="",E38=""),"",E50/E38-1) | N50: =IF(OR(F50="",F38=""),"",F50/F38-1) | O50: =IF(OR(G50="",G38=""),"",G50/G38-1) | P50: =IF(OR(E50="",E47=""),"",(E50/E47)^4-1) | Q50: =IF(OR(F50="",F47=""),"",(F50/F47)^4-1) | R50: =IF(OR(E50="",E44=""),"",(E50/E44)^2-1) | S50: =IF(E50="","",IFERROR(E50/INDEX($E:$E,MATCH(C50-1&"-12",$B:$B,0))-1,"")) | T50: =IF(OR(K50="",J50=""),"",(K50-J50)*100) | U50: =IF(OR(G50="",F50=""),"",(G50/INDEX($G:$G,MATCH("2023-12",$B:$B,0)))/(F50/INDEX($F:$F,MATCH("2023-12",$B:$B,0)))*100)
B51: 2022-09 | C51: 2022 | D51: 9 | E51: 967.3076 | F51: 991.2585 | G51: 771.8891 | H51: 1189.6609 | I51: =IF(OR(E51="",E50=""),"",E51/E50-1) | J51: =IF(OR(F51="",F50=""),"",F51/F50-1) | K51: =IF(OR(G51="",G50=""),"",G51/G50-1) | L51: =IF(OR(H51="",H50=""),"",H51/H50-1) | M51: =IF(OR(E51="",E39=""),"",E51/E39-1) | N51: =IF(OR(F51="",F39=""),"",F51/F39-1) | O51: =IF(OR(G51="",G39=""),"",G51/G39-1) | P51: =IF(OR(E51="",E48=""),"",(E51/E48)^4-1) | Q51: =IF(OR(F51="",F48=""),"",(F51/F48)^4-1) | R51: =IF(OR(E51="",E45=""),"",(E51/E45)^2-1) | S51: =IF(E51="","",IFERROR(E51/INDEX($E:$E,MATCH(C51-1&"-12",$B:$B,0))-1,"")) | T51: =IF(OR(K51="",J51=""),"",(K51-J51)*100) | U51: =IF(OR(G51="",F51=""),"",(G51/INDEX($G:$G,MATCH("2023-12",$B:$B,0)))/(F51/INDEX($F:$F,MATCH("2023-12",$B:$B,0)))*100)
B52: 2022-10 | C52: 2022 | D52: 10 | E52: 1028.706 | F52: 1046.265 | G52: 829.1011 | H52: 1297.2889 | I52: =IF(OR(E52="",E51=""),"",E52/E51-1) | J52: =IF(OR(F52="",F51=""),"",F52/F51-1) | K52: =IF(OR(G52="",G51=""),"",G52/G51-1) | L52: =IF(OR(H52="",H51=""),"",H52/H51-1) | M52: =IF(OR(E52="",E40=""),"",E52/E40-1) | N52: =IF(OR(F52="",F40=""),"",F52/F40-1) | O52: =IF(OR(G52="",G40=""),"",G52/G40-1) | P52: =IF(OR(E52="",E49=""),"",(E52/E49)^4-1) | Q52: =IF(OR(F52="",F49=""),"",(F52/F49)^4-1) | R52: =IF(OR(E52="",E46=""),"",(E52/E46)^2-1) | S52: =IF(E52="","",IFERROR(E52/INDEX($E:$E,MATCH(C52-1&"-12",$B:$B,0))-1,"")) | T52: =IF(OR(K52="",J52=""),"",(K52-J52)*100) | U52: =IF(OR(G52="",F52=""),"",(G52/INDEX($G:$G,MATCH("2023-12",$B:$B,0)))/(F52/INDEX($F:$F,MATCH("2023-12",$B:$B,0)))*100)
B53: 2022-11 | C53: 2022 | D53: 11 | E53: 1079.2787 | F53: 1096.024 | G53: 880.7676 | H53: 1350.5167 | I53: =IF(OR(E53="",E52=""),"",E53/E52-1) | J53: =IF(OR(F53="",F52=""),"",F53/F52-1) | K53: =IF(OR(G53="",G52=""),"",G53/G52-1) | L53: =IF(OR(H53="",H52=""),"",H53/H52-1) | M53: =IF(OR(E53="",E41=""),"",E53/E41-1) | N53: =IF(OR(F53="",F41=""),"",F53/F41-1) | O53: =IF(OR(G53="",G41=""),"",G53/G41-1) | P53: =IF(OR(E53="",E50=""),"",(E53/E50)^4-1) | Q53: =IF(OR(F53="",F50=""),"",(F53/F50)^4-1) | R53: =IF(OR(E53="",E47=""),"",(E53/E47)^2-1) | S53: =IF(E53="","",IFERROR(E53/INDEX($E:$E,MATCH(C53-1&"-12",$B:$B,0))-1,"")) | T53: =IF(OR(K53="",J53=""),"",(K53-J53)*100) | U53: =IF(OR(G53="",F53=""),"",(G53/INDEX($G:$G,MATCH("2023-12",$B:$B,0)))/(F53/INDEX($F:$F,MATCH("2023-12",$B:$B,0)))*100)
B54: 2022-12 | C54: 2022 | D54: 12 | E54: 1134.5875 | F54: 1153.5771 | G54: 925.7853 | H54: 1413.2059 | I54: =IF(OR(E54="",E53=""),"",E54/E53-1) | J54: =IF(OR(F54="",F53=""),"",F54/F53-1) | K54: =IF(OR(G54="",G53=""),"",G54/G53-1) | L54: =IF(OR(H54="",H53=""),"",H54/H53-1) | M54: =IF(OR(E54="",E42=""),"",E54/E42-1) | N54: =IF(OR(F54="",F42=""),"",F54/F42-1) | O54: =IF(OR(G54="",G42=""),"",G54/G42-1) | P54: =IF(OR(E54="",E51=""),"",(E54/E51)^4-1) | Q54: =IF(OR(F54="",F51=""),"",(F54/F51)^4-1) | R54: =IF(OR(E54="",E48=""),"",(E54/E48)^2-1) | S54: =IF(E54="","",IFERROR(E54/INDEX($E:$E,MATCH(C54-1&"-12",$B:$B,0))-1,"")) | T54: =IF(OR(K54="",J54=""),"",(K54-J54)*100) | U54: =IF(OR(G54="",F54=""),"",(G54/INDEX($G:$G,MATCH("2023-12",$B:$B,0)))/(F54/INDEX($F:$F,MATCH("2023-12",$B:$B,0)))*100)
... B98: 2026-08 | C98: 2026 | D98: 8 | E98: 12275.481 | F98: 12447.343 | G98: 12935.84 | H98: 10089.143 | I98: =IF(OR(E98="",E97=""),"",E98/E97-1) | J98: =IF(OR(F98="",F97=""),"",F98/F97-1) | K98: =IF(OR(G98="",G97=""),"",G98/G97-1) | L98: =IF(OR(H98="",H97=""),"",H98/H97-1) | M98: =IF(OR(E98="",E86=""),"",E98/E86-1) | N98: =IF(OR(F98="",F86=""),"",F98/F86-1) | O98: =IF(OR(G98="",G86=""),"",G98/G86-1) | P98: =IF(OR(E98="",E95=""),"",(E98/E95)^4-1) | Q98: =IF(OR(F98="",F95=""),"",(F98/F95)^4-1) | R98: =IF(OR(E98="",E92=""),"",(E98/E92)^2-1) | S98: =IF(E98="","",IFERROR(E98/INDEX($E:$E,MATCH(C98-1&"-12",$B:$B,0))-1,"")) | T98: =IF(OR(K98="",J98=""),"",(K98-J98)*100) | U98: =IF(OR(G98="",F98=""),"",(G98/INDEX($G:$G,MATCH("2023-12",$B:$B,0)))/(F98/INDEX($F:$F,MATCH("2023-12",$B:$B,0)))*100)
B99: 2026-09 | C99: 2026 | D99: 9 | I99: =IF(OR(E99="",E98=""),"",E99/E98-1) | J99: =IF(OR(F99="",F98=""),"",F99/F98-1) | K99: =IF(OR(G99="",G98=""),"",G99/G98-1) | L99: =IF(OR(H99="",H98=""),"",H99/H98-1) | M99: =IF(OR(E99="",E87=""),"",E99/E87-1) | N99: =IF(OR(F99="",F87=""),"",F99/F87-1) | O99: =IF(OR(G99="",G87=""),"",G99/G87-1) | P99: =IF(OR(E99="",E96=""),"",(E99/E96)^4-1) | Q99: =IF(OR(F99="",F96=""),"",(F99/F96)^4-1) | R99: =IF(OR(E99="",E93=""),"",(E99/E93)^2-1) | S99: =IF(E99="","",IFERROR(E99/INDEX($E:$E,MATCH(C99-1&"-12",$B:$B,0))-1,"")) | T99: =IF(OR(K99="",J99=""),"",(K99-J99)*100) | U99: =IF(OR(G99="",F99=""),"",(G99/INDEX($G:$G,MATCH("2023-12",$B:$B,0)))/(F99/INDEX($F:$F,MATCH("2023-12",$B:$B,0)))*100)
B100: 2026-10 | C100: 2026 | D100: 10 | I100: =IF(OR(E100="",E99=""),"",E100/E99-1) | J100: =IF(OR(F100="",F99=""),"",F100/F99-1) | K100: =IF(OR(G100="",G99=""),"",G100/G99-1) | L100: =IF(OR(H100="",H99=""),"",H100/H99-1) | M100: =IF(OR(E100="",E88=""),"",E100/E88-1) | N100: =IF(OR(F100="",F88=""),"",F100/F88-1) | O100: =IF(OR(G100="",G88=""),"",G100/G88-1) | P100: =IF(OR(E100="",E97=""),"",(E100/E97)^4-1) | Q100: =IF(OR(F100="",F97=""),"",(F100/F97)^4-1) | R100: =IF(OR(E100="",E94=""),"",(E100/E94)^2-1) | S100: =IF(E100="","",IFERROR(E100/INDEX($E:$E,MATCH(C100-1&"-12",$B:$B,0))-1,"")) | T100: =IF(OR(K100="",J100=""),"",(K100-J100)*100) | U100: =IF(OR(G100="",F100=""),"",(G100/INDEX($G:$G,MATCH("2023-12",$B:$B,0)))/(F100/INDEX($F:$F,MATCH("2023-12",$B:$B,0)))*100)
B101: 2026-11 | C101: 2026 | D101: 11 | I101: =IF(OR(E101="",E100=""),"",E101/E100-1) | J101: =IF(OR(F101="",F100=""),"",F101/F100-1) | K101: =IF(OR(G101="",G100=""),"",G101/G100-1) | L101: =IF(OR(H101="",H100=""),"",H101/H100-1) | M101: =IF(OR(E101="",E89=""),"",E101/E89-1) | N101: =IF(OR(F101="",F89=""),"",F101/F89-1) | O101: =IF(OR(G101="",G89=""),"",G101/G89-1) | P101: =IF(OR(E101="",E98=""),"",(E101/E98)^4-1) | Q101: =IF(OR(F101="",F98=""),"",(F101/F98)^4-1) | R101: =IF(OR(E101="",E95=""),"",(E101/E95)^2-1) | S101: =IF(E101="","",IFERROR(E101/INDEX($E:$E,MATCH(C101-1&"-12",$B:$B,0))-1,"")) | T101: =IF(OR(K101="",J101=""),"",(K101-J101)*100) | U101: =IF(OR(G101="",F101=""),"",(G101/INDEX($G:$G,MATCH("2023-12",$B:$B,0)))/(F101/INDEX($F:$F,MATCH("2023-12",$B:$B,0)))*100)
B102: 2026-12 | C102: 2026 | D102: 12 | I102: =IF(OR(E102="",E101=""),"",E102/E101-1) | J102: =IF(OR(F102="",F101=""),"",F102/F101-1) | K102: =IF(OR(G102="",G101=""),"",G102/G101-1) | L102: =IF(OR(H102="",H101=""),"",H102/H101-1) | M102: =IF(OR(E102="",E90=""),"",E102/E90-1) | N102: =IF(OR(F102="",F90=""),"",F102/F90-1) | O102: =IF(OR(G102="",G90=""),"",G102/G90-1) | P102: =IF(OR(E102="",E99=""),"",(E102/E99)^4-1) | Q102: =IF(OR(F102="",F99=""),"",(F102/F99)^4-1) | R102: =IF(OR(E102="",E96=""),"",(E102/E96)^2-1) | S102: =IF(E102="","",IFERROR(E102/INDEX($E:$E,MATCH(C102-1&"-12",$B:$B,0))-1,"")) | T102: =IF(OR(K102="",J102=""),"",(K102-J102)*100) | U102: =IF(OR(G102="",F102=""),"",(G102/INDEX($G:$G,MATCH("2023-12",$B:$B,0)))/(F102/INDEX($F:$F,MATCH("2023-12",$B:$B,0)))*100)
B103: 2027-01 | C103: 2027 | D103: 1 | I103: =IF(OR(E103="",E102=""),"",E103/E102-1) | J103: =IF(OR(F103="",F102=""),"",F103/F102-1) | K103: =IF(OR(G103="",G102=""),"",G103/G102-1) | L103: =IF(OR(H103="",H102=""),"",H103/H102-1) | M103: =IF(OR(E103="",E91=""),"",E103/E91-1) | N103: =IF(OR(F103="",F91=""),"",F103/F91-1) | O103: =IF(OR(G103="",G91=""),"",G103/G91-1) | P103: =IF(OR(E103="",E100=""),"",(E103/E100)^4-1) | Q103: =IF(OR(F103="",F100=""),"",(F103/F100)^4-1) | R103: =IF(OR(E103="",E97=""),"",(E103/E97)^2-1) | S103: =IF(E103="","",IFERROR(E103/INDEX($E:$E,MATCH(C103-1&"-12",$B:$B,0))-1,"")) | T103: =IF(OR(K103="",J103=""),"",(K103-J103)*100) | U103: =IF(OR(G103="",F103=""),"",(G103/INDEX($G:$G,MATCH("2023-12",$B:$B,0)))/(F103/INDEX($F:$F,MATCH("2023-12",$B:$B,0)))*100)
B104: 2027-02 | C104: 2027 | D104: 2 | I104: =IF(OR(E104="",E103=""),"",E104/E103-1) | J104: =IF(OR(F104="",F103=""),"",F104/F103-1) | K104: =IF(OR(G104="",G103=""),"",G104/G103-1) | L104: =IF(OR(H104="",H103=""),"",H104/H103-1) | M104: =IF(OR(E104="",E92=""),"",E104/E92-1) | N104: =IF(OR(F104="",F92=""),"",F104/F92-1) | O104: =IF(OR(G104="",G92=""),"",G104/G92-1) | P104: =IF(OR(E104="",E101=""),"",(E104/E101)^4-1) | Q104: =IF(OR(F104="",F101=""),"",(F104/F101)^4-1) | R104: =IF(OR(E104="",E98=""),"",(E104/E98)^2-1) | S104: =IF(E104="","",IFERROR(E104/INDEX($E:$E,MATCH(C104-1&"-12",$B:$B,0))-1,"")) | T104: =IF(OR(K104="",J104=""),"",(K104-J104)*100) | U104: =IF(OR(G104="",F104=""),"",(G104/INDEX($G:$G,MATCH("2023-12",$B:$B,0)))/(F104/INDEX($F:$F,MATCH("2023-12",$B:$B,0)))*100)
B105: 2027-03 | C105: 2027 | D105: 3 | I105: =IF(OR(E105="",E104=""),"",E105/E104-1) | J105: =IF(OR(F105="",F104=""),"",F105/F104-1) | K105: =IF(OR(G105="",G104=""),"",G105/G104-1) | L105: =IF(OR(H105="",H104=""),"",H105/H104-1) | M105: =IF(OR(E105="",E93=""),"",E105/E93-1) | N105: =IF(OR(F105="",F93=""),"",F105/F93-1) | O105: =IF(OR(G105="",G93=""),"",G105/G93-1) | P105: =IF(OR(E105="",E102=""),"",(E105/E102)^4-1) | Q105: =IF(OR(F105="",F102=""),"",(F105/F102)^4-1) | R105: =IF(OR(E105="",E99=""),"",(E105/E99)^2-1) | S105: =IF(E105="","",IFERROR(E105/INDEX($E:$E,MATCH(C105-1&"-12",$B:$B,0))-1,"")) | T105: =IF(OR(K105="",J105=""),"",(K105-J105)*100) | U105: =IF(OR(G105="",F105=""),"",(G105/INDEX($G:$G,MATCH("2023-12",$B:$B,0)))/(F105/INDEX($F:$F,MATCH("2023-12",$B:$B,0)))*100)
B106: 2027-04 | C106: 2027 | D106: 4 | I106: =IF(OR(E106="",E105=""),"",E106/E105-1) | J106: =IF(OR(F106="",F105=""),"",F106/F105-1) | K106: =IF(OR(G106="",G105=""),"",G106/G105-1) | L106: =IF(OR(H106="",H105=""),"",H106/H105-1) | M106: =IF(OR(E106="",E94=""),"",E106/E94-1) | N106: =IF(OR(F106="",F94=""),"",F106/F94-1) | O106: =IF(OR(G106="",G94=""),"",G106/G94-1) | P106: =IF(OR(E106="",E103=""),"",(E106/E103)^4-1) | Q106: =IF(OR(F106="",F103=""),"",(F106/F103)^4-1) | R106: =IF(OR(E106="",E100=""),"",(E106/E100)^2-1) | S106: =IF(E106="","",IFERROR(E106/INDEX($E:$E,MATCH(C106-1&"-12",$B:$B,0))-1,"")) | T106: =IF(OR(K106="",J106=""),"",(K106-J106)*100) | U106: =IF(OR(G106="",F106=""),"",(G106/INDEX($G:$G,MATCH("2023-12",$B:$B,0)))/(F106/INDEX($F:$F,MATCH("2023-12",$B:$B,0)))*100)
B107: 2027-05 | C107: 2027 | D107: 5 | I107: =IF(OR(E107="",E106=""),"",E107/E106-1) | J107: =IF(OR(F107="",F106=""),"",F107/F106-1) | K107: =IF(OR(G107="",G106=""),"",G107/G106-1) | L107: =IF(OR(H107="",H106=""),"",H107/H106-1) | M107: =IF(OR(E107="",E95=""),"",E107/E95-1) | N107: =IF(OR(F107="",F95=""),"",F107/F95-1) | O107: =IF(OR(G107="",G95=""),"",G107/G95-1) | P107: =IF(OR(E107="",E104=""),"",(E107/E104)^4-1) | Q107: =IF(OR(F107="",F104=""),"",(F107/F104)^4-1) | R107: =IF(OR(E107="",E101=""),"",(E107/E101)^2-1) | S107: =IF(E107="","",IFERROR(E107/INDEX($E:$E,MATCH(C107-1&"-12",$B:$B,0))-1,"")) | T107: =IF(OR(K107="",J107=""),"",(K107-J107)*100) | U107: =IF(OR(G107="",F107=""),"",(G107/INDEX($G:$G,MATCH("2023-12",$B:$B,0)))/(F107/INDEX($F:$F,MATCH("2023-12",$B:$B,0)))*100)
B108: 2027-06 | C108: 2027 | D108: 6 | I108: =IF(OR(E108="",E107=""),"",E108/E107-1) | J108: =IF(OR(F108="",F107=""),"",F108/F107-1) | K108: =IF(OR(G108="",G107=""),"",G108/G107-1) | L108: =IF(OR(H108="",H107=""),"",H108/H107-1) | M108: =IF(OR(E108="",E96=""),"",E108/E96-1) | N108: =IF(OR(F108="",F96=""),"",F108/F96-1) | O108: =IF(OR(G108="",G96=""),"",G108/G96-1) | P108: =IF(OR(E108="",E105=""),"",(E108/E105)^4-1) | Q108: =IF(OR(F108="",F105=""),"",(F108/F105)^4-1) | R108: =IF(OR(E108="",E102=""),"",(E108/E102)^2-1) | S108: =IF(E108="","",IFERROR(E108/INDEX($E:$E,MATCH(C108-1&"-12",$B:$B,0))-1,"")) | T108: =IF(OR(K108="",J108=""),"",(K108-J108)*100) | U108: =IF(OR(G108="",F108=""),"",(G108/INDEX($G:$G,MATCH("2023-12",$B:$B,0)))/(F108/INDEX($F:$F,MATCH("2023-12",$B:$B,0)))*100)
B109: 2027-07 | C109: 2027 | D109: 7 | I109: =IF(OR(E109="",E108=""),"",E109/E108-1) | J109: =IF(OR(F109="",F108=""),"",F109/F108-1) | K109: =IF(OR(G109="",G108=""),"",G109/G108-1) | L109: =IF(OR(H109="",H108=""),"",H109/H108-1) | M109: =IF(OR(E109="",E97=""),"",E109/E97-1) | N109: =IF(OR(F109="",F97=""),"",F109/F97-1) | O109: =IF(OR(G109="",G97=""),"",G109/G97-1) | P109: =IF(OR(E109="",E106=""),"",(E109/E106)^4-1) | Q109: =IF(OR(F109="",F106=""),"",(F109/F106)^4-1) | R109: =IF(OR(E109="",E103=""),"",(E109/E103)^2-1) | S109: =IF(E109="","",IFERROR(E109/INDEX($E:$E,MATCH(C109-1&"-12",$B:$B,0))-1,"")) | T109: =IF(OR(K109="",J109=""),"",(K109-J109)*100) | U109: =IF(OR(G109="",F109=""),"",(G109/INDEX($G:$G,MATCH("2023-12",$B:$B,0)))/(F109/INDEX($F:$F,MATCH("2023-12",$B:$B,0)))*100)
B110: 2027-08 | C110: 2027 | D110: 8 | I110: =IF(OR(E110="",E109=""),"",E110/E109-1) | J110: =IF(OR(F110="",F109=""),"",F110/F109-1) | K110: =IF(OR(G110="",G109=""),"",G110/G109-1) | L110: =IF(OR(H110="",H109=""),"",H110/H109-1) | M110: =IF(OR(E110="",E98=""),"",E110/E98-1) | N110: =IF(OR(F110="",F98=""),"",F110/F98-1) | O110: =IF(OR(G110="",G98=""),"",G110/G98-1) | P110: =IF(OR(E110="",E107=""),"",(E110/E107)^4-1) | Q110: =IF(OR(F110="",F107=""),"",(F110/F107)^4-1) | R110: =IF(OR(E110="",E104=""),"",(E110/E104)^2-1) | S110: =IF(E110="","",IFERROR(E110/INDEX($E:$E,MATCH(C110-1&"-12",$B:$B,0))-1,"")) | T110: =IF(OR(K110="",J110=""),"",(K110-J110)*100) | U110: =IF(OR(G110="",F110=""),"",(G110/INDEX($G:$G,MATCH("2023-12",$B:$B,0)))/(F110/INDEX($F:$F,MATCH("2023-12",$B:$B,0)))*100)
... B114: 2027-12 | C114: 2027 | D114: 12 | I114: =IF(OR(E114="",E113=""),"",E114/E113-1) | J114: =IF(OR(F114="",F113=""),"",F114/F113-1) | K114: =IF(OR(G114="",G113=""),"",G114/G113-1) | L114: =IF(OR(H114="",H113=""),"",H114/H113-1) | M114: =IF(OR(E114="",E102=""),"",E114/E102-1) | N114: =IF(OR(F114="",F102=""),"",F114/F102-1) | O114: =IF(OR(G114="",G102=""),"",G114/G102-1) | P114: =IF(OR(E114="",E111=""),"",(E114/E111)^4-1) | Q114: =IF(OR(F114="",F111=""),"",(F114/F111)^4-1) | R114: =IF(OR(E114="",E108=""),"",(E114/E108)^2-1) | S114: =IF(E114="","",IFERROR(E114/INDEX($E:$E,MATCH(C114-1&"-12",$B:$B,0))-1,"")) | T114: =IF(OR(K114="",J114=""),"",(K114-J114)*100) | U114: =IF(OR(G114="",F114=""),"",(G114/INDEX($G:$G,MATCH("2023-12",$B:$B,0)))/(F114/INDEX($F:$F,MATCH("2023-12",$B:$B,0)))*100)

Sheet Seasonality Headline
B2: Seasonality — IPC Nivel General (headline): month-on-month % by calendar year
B3: One line per calendar year. Recent years darker; 2026 in UBS red.
B5: Month | C5: 2019 | D5: 2020 | E5: 2021 | F5: 2022 | G5: 2023 | H5: 2024 | I5: 2025 | J5: 2026
B6: Jan | C6: =IF(COUNTIFS('CPI Data'!$C$6:$C$114,C$5,'CPI Data'!$D$6:$D$114,1,'CPI Data'!$E$6:$E$114,">0")=0,"",SUMIFS('CPI Data'!$I$6:$I$114,'CPI Data'!$C$6:$C$114,C$5,'CPI Data'!$D$6:$D$114,1)) | D6: =IF(COUNTIFS('CPI Data'!$C$6:$C$114,D$5,'CPI Data'!$D$6:$D$114,1,'CPI Data'!$E$6:$E$114,">0")=0,"",SUMIFS('CPI Data'!$I$6:$I$114,'CPI Data'!$C$6:$C$114,D$5,'CPI Data'!$D$6:$D$114,1)) | E6: =IF(COUNTIFS('CPI Data'!$C$6:$C$114,E$5,'CPI Data'!$D$6:$D$114,1,'CPI Data'!$E$6:$E$114,">0")=0,"",SUMIFS('CPI Data'!$I$6:$I$114,'CPI Data'!$C$6:$C$114,E$5,'CPI Data'!$D$6:$D$114,1)) | F6: =IF(COUNTIFS('CPI Data'!$C$6:$C$114,F$5,'CPI Data'!$D$6:$D$114,1,'CPI Data'!$E$6:$E$114,">0")=0,"",SUMIFS('CPI Data'!$I$6:$I$114,'CPI Data'!$C$6:$C$114,F$5,'CPI Data'!$D$6:$D$114,1)) | G6: =IF(COUNTIFS('CPI Data'!$C$6:$C$114,G$5,'CPI Data'!$D$6:$D$114,1,'CPI Data'!$E$6:$E$114,">0")=0,"",SUMIFS('CPI Data'!$I$6:$I$114,'CPI Data'!$C$6:$C$114,G$5,'CPI Data'!$D$6:$D$114,1)) | H6: =IF(COUNTIFS('CPI Data'!$C$6:$C$114,H$5,'CPI Data'!$D$6:$D$114,1,'CPI Data'!$E$6:$E$114,">0")=0,"",SUMIFS('CPI Data'!$I$6:$I$114,'CPI Data'!$C$6:$C$114,H$5,'CPI Data'!$D$6:$D$114,1)) | I6: =IF(COUNTIFS('CPI Data'!$C$6:$C$114,I$5,'CPI Data'!$D$6:$D$114,1,'CPI Data'!$E$6:$E$114,">0")=0,"",SUMIFS('CPI Data'!$I$6:$I$114,'CPI Data'!$C$6:$C$114,I$5,'CPI Data'!$D$6:$D$114,1)) | J6: =IF(COUNTIFS('CPI Data'!$C$6:$C$114,J$5,'CPI Data'!$D$6:$D$114,1,'CPI Data'!$E$6:$E$114,">0")=0,"",SUMIFS('CPI Data'!$I$6:$I$114,'CPI Data'!$C$6:$C$114,J$5,'CPI Data'!$D$6:$D$114,1))
B7: Feb | C7: =IF(COUNTIFS('CPI Data'!$C$6:$C$114,C$5,'CPI Data'!$D$6:$D$114,2,'CPI Data'!$E$6:$E$114,">0")=0,"",SUMIFS('CPI Data'!$I$6:$I$114,'CPI Data'!$C$6:$C$114,C$5,'CPI Data'!$D$6:$D$114,2)) | D7: =IF(COUNTIFS('CPI Data'!$C$6:$C$114,D$5,'CPI Data'!$D$6:$D$114,2,'CPI Data'!$E$6:$E$114,">0")=0,"",SUMIFS('CPI Data'!$I$6:$I$114,'CPI Data'!$C$6:$C$114,D$5,'CPI Data'!$D$6:$D$114,2)) | E7: =IF(COUNTIFS('CPI Data'!$C$6:$C$114,E$5,'CPI Data'!$D$6:$D$114,2,'CPI Data'!$E$6:$E$114,">0")=0,"",SUMIFS('CPI Data'!$I$6:$I$114,'CPI Data'!$C$6:$C$114,E$5,'CPI Data'!$D$6:$D$114,2)) | F7: =IF(COUNTIFS('CPI Data'!$C$6:$C$114,F$5,'CPI Data'!$D$6:$D$114,2,'CPI Data'!$E$6:$E$114,">0")=0,"",SUMIFS('CPI Data'!$I$6:$I$114,'CPI Data'!$C$6:$C$114,F$5,'CPI Data'!$D$6:$D$114,2)) | G7: =IF(COUNTIFS('CPI Data'!$C$6:$C$114,G$5,'CPI Data'!$D$6:$D$114,2,'CPI Data'!$E$6:$E$114,">0")=0,"",SUMIFS('CPI Data'!$I$6:$I$114,'CPI Data'!$C$6:$C$114,G$5,'CPI Data'!$D$6:$D$114,2)) | H7: =IF(COUNTIFS('CPI Data'!$C$6:$C$114,H$5,'CPI Data'!$D$6:$D$114,2,'CPI Data'!$E$6:$E$114,">0")=0,"",SUMIFS('CPI Data'!$I$6:$I$114,'CPI Data'!$C$6:$C$114,H$5,'CPI Data'!$D$6:$D$114,2)) | I7: =IF(COUNTIFS('CPI Data'!$C$6:$C$114,I$5,'CPI Data'!$D$6:$D$114,2,'CPI Data'!$E$6:$E$114,">0")=0,"",SUMIFS('CPI Data'!$I$6:$I$114,'CPI Data'!$C$6:$C$114,I$5,'CPI Data'!$D$6:$D$114,2)) | J7: =IF(COUNTIFS('CPI Data'!$C$6:$C$114,J$5,'CPI Data'!$D$6:$D$114,2,'CPI Data'!$E$6:$E$114,">0")=0,"",SUMIFS('CPI Data'!$I$6:$I$114,'CPI Data'!$C$6:$C$114,J$5,'CPI Data'!$D$6:$D$114,2))
B8: Mar | C8: =IF(COUNTIFS('CPI Data'!$C$6:$C$114,C$5,'CPI Data'!$D$6:$D$114,3,'CPI Data'!$E$6:$E$114,">0")=0,"",SUMIFS('CPI Data'!$I$6:$I$114,'CPI Data'!$C$6:$C$114,C$5,'CPI Data'!$D$6:$D$114,3)) | D8: =IF(COUNTIFS('CPI Data'!$C$6:$C$114,D$5,'CPI Data'!$D$6:$D$114,3,'CPI Data'!$E$6:$E$114,">0")=0,"",SUMIFS('CPI Data'!$I$6:$I$114,'CPI Data'!$C$6:$C$114,D$5,'CPI Data'!$D$6:$D$114,3)) | E8: =IF(COUNTIFS('CPI Data'!$C$6:$C$114,E$5,'CPI Data'!$D$6:$D$114,3,'CPI Data'!$E$6:$E$114,">0")=0,"",SUMIFS('CPI Data'!$I$6:$I$114,'CPI Data'!$C$6:$C$114,E$5,'CPI Data'!$D$6:$D$114,3)) | F8: =IF(COUNTIFS('CPI Data'!$C$6:$C$114,F$5,'CPI Data'!$D$6:$D$114,3,'CPI Data'!$E$6:$E$114,">0")=0,"",SUMIFS('CPI Data'!$I$6:$I$114,'CPI Data'!$C$6:$C$114,F$5,'CPI Data'!$D$6:$D$114,3)) | G8: =IF(COUNTIFS('CPI Data'!$C$6:$C$114,G$5,'CPI Data'!$D$6:$D$114,3,'CPI Data'!$E$6:$E$114,">0")=0,"",SUMIFS('CPI Data'!$I$6:$I$114,'CPI Data'!$C$6:$C$114,G$5,'CPI Data'!$D$6:$D$114,3)) | H8: =IF(COUNTIFS('CPI Data'!$C$6:$C$114,H$5,'CPI Data'!$D$6:$D$114,3,'CPI Data'!$E$6:$E$114,">0")=0,"",SUMIFS('CPI Data'!$I$6:$I$114,'CPI Data'!$C$6:$C$114,H$5,'CPI Data'!$D$6:$D$114,3)) | I8: =IF(COUNTIFS('CPI Data'!$C$6:$C$114,I$5,'CPI Data'!$D$6:$D$114,3,'CPI Data'!$E$6:$E$114,">0")=0,"",SUMIFS('CPI Data'!$I$6:$I$114,'CPI Data'!$C$6:$C$114,I$5,'CPI Data'!$D$6:$D$114,3)) | J8: =IF(COUNTIFS('CPI Data'!$C$6:$C$114,J$5,'CPI Data'!$D$6:$D$114,3,'CPI Data'!$E$6:$E$114,">0")=0,"",SUMIFS('CPI Data'!$I$6:$I$114,'CPI Data'!$C$6:$C$114,J$5,'CPI Data'!$D$6:$D$114,3))
B9: Apr | C9: =IF(COUNTIFS('CPI Data'!$C$6:$C$114,C$5,'CPI Data'!$D$6:$D$114,4,'CPI Data'!$E$6:$E$114,">0")=0,"",SUMIFS('CPI Data'!$I$6:$I$114,'CPI Data'!$C$6:$C$114,C$5,'CPI Data'!$D$6:$D$114,4)) | D9: =IF(COUNTIFS('CPI Data'!$C$6:$C$114,D$5,'CPI Data'!$D$6:$D$114,4,'CPI Data'!$E$6:$E$114,">0")=0,"",SUMIFS('CPI Data'!$I$6:$I$114,'CPI Data'!$C$6:$C$114,D$5,'CPI Data'!$D$6:$D$114,4)) | E9: =IF(COUNTIFS('CPI Data'!$C$6:$C$114,E$5,'CPI Data'!$D$6:$D$114,4,'CPI Data'!$E$6:$E$114,">0")=0,"",SUMIFS('CPI Data'!$I$6:$I$114,'CPI Data'!$C$6:$C$114,E$5,'CPI Data'!$D$6:$D$114,4)) | F9: =IF(COUNTIFS('CPI Data'!$C$6:$C$114,F$5,'CPI Data'!$D$6:$D$114,4,'CPI Data'!$E$6:$E$114,">0")=0,"",SUMIFS('CPI Data'!$I$6:$I$114,'CPI Data'!$C$6:$C$114,F$5,'CPI Data'!$D$6:$D$114,4)) | G9: =IF(COUNTIFS('CPI Data'!$C$6:$C$114,G$5,'CPI Data'!$D$6:$D$114,4,'CPI Data'!$E$6:$E$114,">0")=0,"",SUMIFS('CPI Data'!$I$6:$I$114,'CPI Data'!$C$6:$C$114,G$5,'CPI Data'!$D$6:$D$114,4)) | H9: =IF(COUNTIFS('CPI Data'!$C$6:$C$114,H$5,'CPI Data'!$D$6:$D$114,4,'CPI Data'!$E$6:$E$114,">0")=0,"",SUMIFS('CPI Data'!$I$6:$I$114,'CPI Data'!$C$6:$C$114,H$5,'CPI Data'!$D$6:$D$114,4)) | I9: =IF(COUNTIFS('CPI Data'!$C$6:$C$114,I$5,'CPI Data'!$D$6:$D$114,4,'CPI Data'!$E$6:$E$114,">0")=0,"",SUMIFS('CPI Data'!$I$6:$I$114,'CPI Data'!$C$6:$C$114,I$5,'CPI Data'!$D$6:$D$114,4)) | J9: =IF(COUNTIFS('CPI Data'!$C$6:$C$114,J$5,'CPI Data'!$D$6:$D$114,4,'CPI Data'!$E$6:$E$114,">0")=0,"",SUMIFS('CPI Data'!$I$6:$I$114,'CPI Data'!$C$6:$C$114,J$5,'CPI Data'!$D$6:$D$114,4))
B10: May | C10: =IF(COUNTIFS('CPI Data'!$C$6:$C$114,C$5,'CPI Data'!$D$6:$D$114,5,'CPI Data'!$E$6:$E$114,">0")=0,"",SUMIFS('CPI Data'!$I$6:$I$114,'CPI Data'!$C$6:$C$114,C$5,'CPI Data'!$D$6:$D$114,5)) | D10: =IF(COUNTIFS('CPI Data'!$C$6:$C$114,D$5,'CPI Data'!$D$6:$D$114,5,'CPI Data'!$E$6:$E$114,">0")=0,"",SUMIFS('CPI Data'!$I$6:$I$114,'CPI Data'!$C$6:$C$114,D$5,'CPI Data'!$D$6:$D$114,5)) | E10: =IF(COUNTIFS('CPI Data'!$C$6:$C$114,E$5,'CPI Data'!$D$6:$D$114,5,'CPI Data'!$E$6:$E$114,">0")=0,"",SUMIFS('CPI Data'!$I$6:$I$114,'CPI Data'!$C$6:$C$114,E$5,'CPI Data'!$D$6:$D$114,5)) | F10: =IF(COUNTIFS('CPI Data'!$C$6:$C$114,F$5,'CPI Data'!$D$6:$D$114,5,'CPI Data'!$E$6:$E$114,">0")=0,"",SUMIFS('CPI Data'!$I$6:$I$114,'CPI Data'!$C$6:$C$114,F$5,'CPI Data'!$D$6:$D$114,5)) | G10: =IF(COUNTIFS('CPI Data'!$C$6:$C$114,G$5,'CPI Data'!$D$6:$D$114,5,'CPI Data'!$E$6:$E$114,">0")=0,"",SUMIFS('CPI Data'!$I$6:$I$114,'CPI Data'!$C$6:$C$114,G$5,'CPI Data'!$D$6:$D$114,5)) | H10: =IF(COUNTIFS('CPI Data'!$C$6:$C$114,H$5,'CPI Data'!$D$6:$D$114,5,'CPI Data'!$E$6:$E$114,">0")=0,"",SUMIFS('CPI Data'!$I$6:$I$114,'CPI Data'!$C$6:$C$114,H$5,'CPI Data'!$D$6:$D$114,5)) | I10: =IF(COUNTIFS('CPI Data'!$C$6:$C$114,I$5,'CPI Data'!$D$6:$D$114,5,'CPI Data'!$E$6:$E$114,">0")=0,"",SUMIFS('CPI Data'!$I$6:$I$114,'CPI Data'!$C$6:$C$114,I$5,'CPI Data'!$D$6:$D$114,5)) | J10: =IF(COUNTIFS('CPI Data'!$C$6:$C$114,J$5,'CPI Data'!$D$6:$D$114,5,'CPI Data'!$E$6:$E$114,">0")=0,"",SUMIFS('CPI Data'!$I$6:$I$114,'CPI Data'!$C$6:$C$114,J$5,'CPI Data'!$D$6:$D$114,5))
B11: Jun | C11: =IF(COUNTIFS('CPI Data'!$C$6:$C$114,C$5,'CPI Data'!$D$6:$D$114,6,'CPI Data'!$E$6:$E$114,">0")=0,"",SUMIFS('CPI Data'!$I$6:$I$114,'CPI Data'!$C$6:$C$114,C$5,'CPI Data'!$D$6:$D$114,6)) | D11: =IF(COUNTIFS('CPI Data'!$C$6:$C$114,D$5,'CPI Data'!$D$6:$D$114,6,'CPI Data'!$E$6:$E$114,">0")=0,"",SUMIFS('CPI Data'!$I$6:$I$114,'CPI Data'!$C$6:$C$114,D$5,'CPI Data'!$D$6:$D$114,6)) | E11: =IF(COUNTIFS('CPI Data'!$C$6:$C$114,E$5,'CPI Data'!$D$6:$D$114,6,'CPI Data'!$E$6:$E$114,">0")=0,"",SUMIFS('CPI Data'!$I$6:$I$114,'CPI Data'!$C$6:$C$114,E$5,'CPI Data'!$D$6:$D$114,6)) | F11: =IF(COUNTIFS('CPI Data'!$C$6:$C$114,F$5,'CPI Data'!$D$6:$D$114,6,'CPI Data'!$E$6:$E$114,">0")=0,"",SUMIFS('CPI Data'!$I$6:$I$114,'CPI Data'!$C$6:$C$114,F$5,'CPI Data'!$D$6:$D$114,6)) | G11: =IF(COUNTIFS('CPI Data'!$C$6:$C$114,G$5,'CPI Data'!$D$6:$D$114,6,'CPI Data'!$E$6:$E$114,">0")=0,"",SUMIFS('CPI Data'!$I$6:$I$114,'CPI Data'!$C$6:$C$114,G$5,'CPI Data'!$D$6:$D$114,6)) | H11: =IF(COUNTIFS('CPI Data'!$C$6:$C$114,H$5,'CPI Data'!$D$6:$D$114,6,'CPI Data'!$E$6:$E$114,">0")=0,"",SUMIFS('CPI Data'!$I$6:$I$114,'CPI Data'!$C$6:$C$114,H$5,'CPI Data'!$D$6:$D$114,6)) | I11: =IF(COUNTIFS('CPI Data'!$C$6:$C$114,I$5,'CPI Data'!$D$6:$D$114,6,'CPI Data'!$E$6:$E$114,">0")=0,"",SUMIFS('CPI Data'!$I$6:$I$114,'CPI Data'!$C$6:$C$114,I$5,'CPI Data'!$D$6:$D$114,6)) | J11: =IF(COUNTIFS('CPI Data'!$C$6:$C$114,J$5,'CPI Data'!$D$6:$D$114,6,'CPI Data'!$E$6:$E$114,">0")=0,"",SUMIFS('CPI Data'!$I$6:$I$114,'CPI Data'!$C$6:$C$114,J$5,'CPI Data'!$D$6:$D$114,6))
B12: Jul | C12: =IF(COUNTIFS('CPI Data'!$C$6:$C$114,C$5,'CPI Data'!$D$6:$D$114,7,'CPI Data'!$E$6:$E$114,">0")=0,"",SUMIFS('CPI Data'!$I$6:$I$114,'CPI Data'!$C$6:$C$114,C$5,'CPI Data'!$D$6:$D$114,7)) | D12: =IF(COUNTIFS('CPI Data'!$C$6:$C$114,D$5,'CPI Data'!$D$6:$D$114,7,'CPI Data'!$E$6:$E$114,">0")=0,"",SUMIFS('CPI Data'!$I$6:$I$114,'CPI Data'!$C$6:$C$114,D$5,'CPI Data'!$D$6:$D$114,7)) | E12: =IF(COUNTIFS('CPI Data'!$C$6:$C$114,E$5,'CPI Data'!$D$6:$D$114,7,'CPI Data'!$E$6:$E$114,">0")=0,"",SUMIFS('CPI Data'!$I$6:$I$114,'CPI Data'!$C$6:$C$114,E$5,'CPI Data'!$D$6:$D$114,7)) | F12: =IF(COUNTIFS('CPI Data'!$C$6:$C$114,F$5,'CPI Data'!$D$6:$D$114,7,'CPI Data'!$E$6:$E$114,">0")=0,"",SUMIFS('CPI Data'!$I$6:$I$114,'CPI Data'!$C$6:$C$114,F$5,'CPI Data'!$D$6:$D$114,7)) | G12: =IF(COUNTIFS('CPI Data'!$C$6:$C$114,G$5,'CPI Data'!$D$6:$D$114,7,'CPI Data'!$E$6:$E$114,">0")=0,"",SUMIFS('CPI Data'!$I$6:$I$114,'CPI Data'!$C$6:$C$114,G$5,'CPI Data'!$D$6:$D$114,7)) | H12: =IF(COUNTIFS('CPI Data'!$C$6:$C$114,H$5,'CPI Data'!$D$6:$D$114,7,'CPI Data'!$E$6:$E$114,">0")=0,"",SUMIFS('CPI Data'!$I$6:$I$114,'CPI Data'!$C$6:$C$114,H$5,'CPI Data'!$D$6:$D$114,7)) | I12: =IF(COUNTIFS('CPI Data'!$C$6:$C$114,I$5,'CPI Data'!$D$6:$D$114,7,'CPI Data'!$E$6:$E$114,">0")=0,"",SUMIFS('CPI Data'!$I$6:$I$114,'CPI Data'!$C$6:$C$114,I$5,'CPI Data'!$D$6:$D$114,7)) | J12: =IF(COUNTIFS('CPI Data'!$C$6:$C$114,J$5,'CPI Data'!$D$6:$D$114,7,'CPI Data'!$E$6:$E$114,">0")=0,"",SUMIFS('CPI Data'!$I$6:$I$114,'CPI Data'!$C$6:$C$114,J$5,'CPI Data'!$D$6:$D$114,7))
B13: Aug | C13: =IF(COUNTIFS('CPI Data'!$C$6:$C$114,C$5,'CPI Data'!$D$6:$D$114,8,'CPI Data'!$E$6:$E$114,">0")=0,"",SUMIFS('CPI Data'!$I$6:$I$114,'CPI Data'!$C$6:$C$114,C$5,'CPI Data'!$D$6:$D$114,8)) | D13: =IF(COUNTIFS('CPI Data'!$C$6:$C$114,D$5,'CPI Data'!$D$6:$D$114,8,'CPI Data'!$E$6:$E$114,">0")=0,"",SUMIFS('CPI Data'!$I$6:$I$114,'CPI Data'!$C$6:$C$114,D$5,'CPI Data'!$D$6:$D$114,8)) | E13: =IF(COUNTIFS('CPI Data'!$C$6:$C$114,E$5,'CPI Data'!$D$6:$D$114,8,'CPI Data'!$E$6:$E$114,">0")=0,"",SUMIFS('CPI Data'!$I$6:$I$114,'CPI Data'!$C$6:$C$114,E$5,'CPI Data'!$D$6:$D$114,8)) | F13: =IF(COUNTIFS('CPI Data'!$C$6:$C$114,F$5,'CPI Data'!$D$6:$D$114,8,'CPI Data'!$E$6:$E$114,">0")=0,"",SUMIFS('CPI Data'!$I$6:$I$114,'CPI Data'!$C$6:$C$114,F$5,'CPI Data'!$D$6:$D$114,8)) | G13: =IF(COUNTIFS('CPI Data'!$C$6:$C$114,G$5,'CPI Data'!$D$6:$D$114,8,'CPI Data'!$E$6:$E$114,">0")=0,"",SUMIFS('CPI Data'!$I$6:$I$114,'CPI Data'!$C$6:$C$114,G$5,'CPI Data'!$D$6:$D$114,8)) | H13: =IF(COUNTIFS('CPI Data'!$C$6:$C$114,H$5,'CPI Data'!$D$6:$D$114,8,'CPI Data'!$E$6:$E$114,">0")=0,"",SUMIFS('CPI Data'!$I$6:$I$114,'CPI Data'!$C$6:$C$114,H$5,'CPI Data'!$D$6:$D$114,8)) | I13: =IF(COUNTIFS('CPI Data'!$C$6:$C$114,I$5,'CPI Data'!$D$6:$D$114,8,'CPI Data'!$E$6:$E$114,">0")=0,"",SUMIFS('CPI Data'!$I$6:$I$114,'CPI Data'!$C$6:$C$114,I$5,'CPI Data'!$D$6:$D$114,8)) | J13: =IF(COUNTIFS('CPI Data'!$C$6:$C$114,J$5,'CPI Data'!$D$6:$D$114,8,'CPI Data'!$E$6:$E$114,">0")=0,"",SUMIFS('CPI Data'!$I$6:$I$114,'CPI Data'!$C$6:$C$114,J$5,'CPI Data'!$D$6:$D$114,8))
B14: Sep | C14: =IF(COUNTIFS('CPI Data'!$C$6:$C$114,C$5,'CPI Data'!$D$6:$D$114,9,'CPI Data'!$E$6:$E$114,">0")=0,"",SUMIFS('CPI Data'!$I$6:$I$114,'CPI Data'!$C$6:$C$114,C$5,'CPI Data'!$D$6:$D$114,9)) | D14: =IF(COUNTIFS('CPI Data'!$C$6:$C$114,D$5,'CPI Data'!$D$6:$D$114,9,'CPI Data'!$E$6:$E$114,">0")=0,"",SUMIFS('CPI Data'!$I$6:$I$114,'CPI Data'!$C$6:$C$114,D$5,'CPI Data'!$D$6:$D$114,9)) | E14: =IF(COUNTIFS('CPI Data'!$C$6:$C$114,E$5,'CPI Data'!$D$6:$D$114,9,'CPI Data'!$E$6:$E$114,">0")=0,"",SUMIFS('CPI Data'!$I$6:$I$114,'CPI Data'!$C$6:$C$114,E$5,'CPI Data'!$D$6:$D$114,9)) | F14: =IF(COUNTIFS('CPI Data'!$C$6:$C$114,F$5,'CPI Data'!$D$6:$D$114,9,'CPI Data'!$E$6:$E$114,">0")=0,"",SUMIFS('CPI Data'!$I$6:$I$114,'CPI Data'!$C$6:$C$114,F$5,'CPI Data'!$D$6:$D$114,9)) | G14: =IF(COUNTIFS('CPI Data'!$C$6:$C$114,G$5,'CPI Data'!$D$6:$D$114,9,'CPI Data'!$E$6:$E$114,">0")=0,"",SUMIFS('CPI Data'!$I$6:$I$114,'CPI Data'!$C$6:$C$114,G$5,'CPI Data'!$D$6:$D$114,9)) | H14: =IF(COUNTIFS('CPI Data'!$C$6:$C$114,H$5,'CPI Data'!$D$6:$D$114,9,'CPI Data'!$E$6:$E$114,">0")=0,"",SUMIFS('CPI Data'!$I$6:$I$114,'CPI Data'!$C$6:$C$114,H$5,'CPI Data'!$D$6:$D$114,9)) | I14: =IF(COUNTIFS('CPI Data'!$C$6:$C$114,I$5,'CPI Data'!$D$6:$D$114,9,'CPI Data'!$E$6:$E$114,">0")=0,"",SUMIFS('CPI Data'!$I$6:$I$114,'CPI Data'!$C$6:$C$114,I$5,'CPI Data'!$D$6:$D$114,9)) | J14: =IF(COUNTIFS('CPI Data'!$C$6:$C$114,J$5,'CPI Data'!$D$6:$D$114,9,'CPI Data'!$E$6:$E$114,">0")=0,"",SUMIFS('CPI Data'!$I$6:$I$114,'CPI Data'!$C$6:$C$114,J$5,'CPI Data'!$D$6:$D$114,9))
B15: Oct | C15: =IF(COUNTIFS('CPI Data'!$C$6:$C$114,C$5,'CPI Data'!$D$6:$D$114,10,'CPI Data'!$E$6:$E$114,">0")=0,"",SUMIFS('CPI Data'!$I$6:$I$114,'CPI Data'!$C$6:$C$114,C$5,'CPI Data'!$D$6:$D$114,10)) | D15: =IF(COUNTIFS('CPI Data'!$C$6:$C$114,D$5,'CPI Data'!$D$6:$D$114,10,'CPI Data'!$E$6:$E$114,">0")=0,"",SUMIFS('CPI Data'!$I$6:$I$114,'CPI Data'!$C$6:$C$114,D$5,'CPI Data'!$D$6:$D$114,10)) | E15: =IF(COUNTIFS('CPI Data'!$C$6:$C$114,E$5,'CPI Data'!$D$6:$D$114,10,'CPI Data'!$E$6:$E$114,">0")=0,"",SUMIFS('CPI Data'!$I$6:$I$114,'CPI Data'!$C$6:$C$114,E$5,'CPI Data'!$D$6:$D$114,10)) | F15: =IF(COUNTIFS('CPI Data'!$C$6:$C$114,F$5,'CPI Data'!$D$6:$D$114,10,'CPI Data'!$E$6:$E$114,">0")=0,"",SUMIFS('CPI Data'!$I$6:$I$114,'CPI Data'!$C$6:$C$114,F$5,'CPI Data'!$D$6:$D$114,10)) | G15: =IF(COUNTIFS('CPI Data'!$C$6:$C$114,G$5,'CPI Data'!$D$6:$D$114,10,'CPI Data'!$E$6:$E$114,">0")=0,"",SUMIFS('CPI Data'!$I$6:$I$114,'CPI Data'!$C$6:$C$114,G$5,'CPI Data'!$D$6:$D$114,10)) | H15: =IF(COUNTIFS('CPI Data'!$C$6:$C$114,H$5,'CPI Data'!$D$6:$D$114,10,'CPI Data'!$E$6:$E$114,">0")=0,"",SUMIFS('CPI Data'!$I$6:$I$114,'CPI Data'!$C$6:$C$114,H$5,'CPI Data'!$D$6:$D$114,10)) | I15: =IF(COUNTIFS('CPI Data'!$C$6:$C$114,I$5,'CPI Data'!$D$6:$D$114,10,'CPI Data'!$E$6:$E$114,">0")=0,"",SUMIFS('CPI Data'!$I$6:$I$114,'CPI Data'!$C$6:$C$114,I$5,'CPI Data'!$D$6:$D$114,10)) | J15: =IF(COUNTIFS('CPI Data'!$C$6:$C$114,J$5,'CPI Data'!$D$6:$D$114,10,'CPI Data'!$E$6:$E$114,">0")=0,"",SUMIFS('CPI Data'!$I$6:$I$114,'CPI Data'!$C$6:$C$114,J$5,'CPI Data'!$D$6:$D$114,10))
B16: Nov | C16: =IF(COUNTIFS('CPI Data'!$C$6:$C$114,C$5,'CPI Data'!$D$6:$D$114,11,'CPI Data'!$E$6:$E$114,">0")=0,"",SUMIFS('CPI Data'!$I$6:$I$114,'CPI Data'!$C$6:$C$114,C$5,'CPI Data'!$D$6:$D$114,11)) | D16: =IF(COUNTIFS('CPI Data'!$C$6:$C$114,D$5,'CPI Data'!$D$6:$D$114,11,'CPI Data'!$E$6:$E$114,">0")=0,"",SUMIFS('CPI Data'!$I$6:$I$114,'CPI Data'!$C$6:$C$114,D$5,'CPI Data'!$D$6:$D$114,11)) | E16: =IF(COUNTIFS('CPI Data'!$C$6:$C$114,E$5,'CPI Data'!$D$6:$D$114,11,'CPI Data'!$E$6:$E$114,">0")=0,"",SUMIFS('CPI Data'!$I$6:$I$114,'CPI Data'!$C$6:$C$114,E$5,'CPI Data'!$D$6:$D$114,11)) | F16: =IF(COUNTIFS('CPI Data'!$C$6:$C$114,F$5,'CPI Data'!$D$6:$D$114,11,'CPI Data'!$E$6:$E$114,">0")=0,"",SUMIFS('CPI Data'!$I$6:$I$114,'CPI Data'!$C$6:$C$114,F$5,'CPI Data'!$D$6:$D$114,11)) | G16: =IF(COUNTIFS('CPI Data'!$C$6:$C$114,G$5,'CPI Data'!$D$6:$D$114,11,'CPI Data'!$E$6:$E$114,">0")=0,"",SUMIFS('CPI Data'!$I$6:$I$114,'CPI Data'!$C$6:$C$114,G$5,'CPI Data'!$D$6:$D$114,11)) | H16: =IF(COUNTIFS('CPI Data'!$C$6:$C$114,H$5,'CPI Data'!$D$6:$D$114,11,'CPI Data'!$E$6:$E$114,">0")=0,"",SUMIFS('CPI Data'!$I$6:$I$114,'CPI Data'!$C$6:$C$114,H$5,'CPI Data'!$D$6:$D$114,11)) | I16: =IF(COUNTIFS('CPI Data'!$C$6:$C$114,I$5,'CPI Data'!$D$6:$D$114,11,'CPI Data'!$E$6:$E$114,">0")=0,"",SUMIFS('CPI Data'!$I$6:$I$114,'CPI Data'!$C$6:$C$114,I$5,'CPI Data'!$D$6:$D$114,11)) | J16: =IF(COUNTIFS('CPI Data'!$C$6:$C$114,J$5,'CPI Data'!$D$6:$D$114,11,'CPI Data'!$E$6:$E$114,">0")=0,"",SUMIFS('CPI Data'!$I$6:$I$114,'CPI Data'!$C$6:$C$114,J$5,'CPI Data'!$D$6:$D$114,11))
B17: Dec | C17: =IF(COUNTIFS('CPI Data'!$C$6:$C$114,C$5,'CPI Data'!$D$6:$D$114,12,'CPI Data'!$E$6:$E$114,">0")=0,"",SUMIFS('CPI Data'!$I$6:$I$114,'CPI Data'!$C$6:$C$114,C$5,'CPI Data'!$D$6:$D$114,12)) | D17: =IF(COUNTIFS('CPI Data'!$C$6:$C$114,D$5,'CPI Data'!$D$6:$D$114,12,'CPI Data'!$E$6:$E$114,">0")=0,"",SUMIFS('CPI Data'!$I$6:$I$114,'CPI Data'!$C$6:$C$114,D$5,'CPI Data'!$D$6:$D$114,12)) | E17: =IF(COUNTIFS('CPI Data'!$C$6:$C$114,E$5,'CPI Data'!$D$6:$D$114,12,'CPI Data'!$E$6:$E$114,">0")=0,"",SUMIFS('CPI Data'!$I$6:$I$114,'CPI Data'!$C$6:$C$114,E$5,'CPI Data'!$D$6:$D$114,12)) | F17: =IF(COUNTIFS('CPI Data'!$C$6:$C$114,F$5,'CPI Data'!$D$6:$D$114,12,'CPI Data'!$E$6:$E$114,">0")=0,"",SUMIFS('CPI Data'!$I$6:$I$114,'CPI Data'!$C$6:$C$114,F$5,'CPI Data'!$D$6:$D$114,12)) | G17: =IF(COUNTIFS('CPI Data'!$C$6:$C$114,G$5,'CPI Data'!$D$6:$D$114,12,'CPI Data'!$E$6:$E$114,">0")=0,"",SUMIFS('CPI Data'!$I$6:$I$114,'CPI Data'!$C$6:$C$114,G$5,'CPI Data'!$D$6:$D$114,12)) | H17: =IF(COUNTIFS('CPI Data'!$C$6:$C$114,H$5,'CPI Data'!$D$6:$D$114,12,'CPI Data'!$E$6:$E$114,">0")=0,"",SUMIFS('CPI Data'!$I$6:$I$114,'CPI Data'!$C$6:$C$114,H$5,'CPI Data'!$D$6:$D$114,12)) | I17: =IF(COUNTIFS('CPI Data'!$C$6:$C$114,I$5,'CPI Data'!$D$6:$D$114,12,'CPI Data'!$E$6:$E$114,">0")=0,"",SUMIFS('CPI Data'!$I$6:$I$114,'CPI Data'!$C$6:$C$114,I$5,'CPI Data'!$D$6:$D$114,12)) | J17: =IF(COUNTIFS('CPI Data'!$C$6:$C$114,J$5,'CPI Data'!$D$6:$D$114,12,'CPI Data'!$E$6:$E$114,">0")=0,"",SUMIFS('CPI Data'!$I$6:$I$114,'CPI Data'!$C$6:$C$114,J$5,'CPI Data'!$D$6:$D$114,12))
B19: Dec/Dec* | C19: =IFERROR(INDEX('CPI Data'!$E:$E,MATCH("2019-12",'CPI Data'!$B:$B,0))/INDEX('CPI Data'!$E:$E,MATCH("2018-12",'CPI Data'!$B:$B,0))-1,"") | D19: =IFERROR(INDEX('CPI Data'!$E:$E,MATCH("2020-12",'CPI Data'!$B:$B,0))/INDEX('CPI Data'!$E:$E,MATCH("2019-12",'CPI Data'!$B:$B,0))-1,"") | E19: =IFERROR(INDEX('CPI Data'!$E:$E,MATCH("2021-12",'CPI Data'!$B:$B,0))/INDEX('CPI Data'!$E:$E,MATCH("2020-12",'CPI Data'!$B:$B,0))-1,"") | F19: =IFERROR(INDEX('CPI Data'!$E:$E,MATCH("2022-12",'CPI Data'!$B:$B,0))/INDEX('CPI Data'!$E:$E,MATCH("2021-12",'CPI Data'!$B:$B,0))-1,"") | G19: =IFERROR(INDEX('CPI Data'!$E:$E,MATCH("2023-12",'CPI Data'!$B:$B,0))/INDEX('CPI Data'!$E:$E,MATCH("2022-12",'CPI Data'!$B:$B,0))-1,"") | H19: =IFERROR(INDEX('CPI Data'!$E:$E,MATCH("2024-12",'CPI Data'!$B:$B,0))/INDEX('CPI Data'!$E:$E,MATCH("2023-12",'CPI Data'!$B:$B,0))-1,"") | I19: =IFERROR(INDEX('CPI Data'!$E:$E,MATCH("2025-12",'CPI Data'!$B:$B,0))/INDEX('CPI Data'!$E:$E,MATCH("2024-12",'CPI Data'!$B:$B,0))-1,"") | J19: =IFERROR(INDEX('CPI Data'!$E:$E,MATCH("2026-08",'CPI Data'!$B:$B,0))/INDEX('CPI Data'!$E:$E,MATCH("2025-12",'CPI Data'!$B:$B,0))-1,"")
B20: Avg month | C20: =IFERROR(AVERAGE(C6:C17),"") | D20: =IFERROR(AVERAGE(D6:D17),"") | E20: =IFERROR(AVERAGE(E6:E17),"") | F20: =IFERROR(AVERAGE(F6:F17),"") | G20: =IFERROR(AVERAGE(G6:G17),"") | H20: =IFERROR(AVERAGE(H6:H17),"") | I20: =IFERROR(AVERAGE(I6:I17),"") | J20: =IFERROR(AVERAGE(J6:J17),"")
B21: * the 2026 column is year-to-date through 2026-08, not a full year.

Sheet Seasonality Core
B2: Seasonality — IPC Nucleo (core): month-on-month % by calendar year
B3: Core strips out regulated tariffs and seasonal items — the cleanest read on underlying momentum.
B5: Month | C5: 2019 | D5: 2020 | E5: 2021 | F5: 2022 | G5: 2023 | H5: 2024 | I5: 2025 | J5: 2026
B6: Jan | C6: =IF(COUNTIFS('CPI Data'!$C$6:$C$114,C$5,'CPI Data'!$D$6:$D$114,1,'CPI Data'!$F$6:$F$114,">0")=0,"",SUMIFS('CPI Data'!$J$6:$J$114,'CPI Data'!$C$6:$C$114,C$5,'CPI Data'!$D$6:$D$114,1)) | D6: =IF(COUNTIFS('CPI Data'!$C$6:$C$114,D$5,'CPI Data'!$D$6:$D$114,1,'CPI Data'!$F$6:$F$114,">0")=0,"",SUMIFS('CPI Data'!$J$6:$J$114,'CPI Data'!$C$6:$C$114,D$5,'CPI Data'!$D$6:$D$114,1)) | E6: =IF(COUNTIFS('CPI Data'!$C$6:$C$114,E$5,'CPI Data'!$D$6:$D$114,1,'CPI Data'!$F$6:$F$114,">0")=0,"",SUMIFS('CPI Data'!$J$6:$J$114,'CPI Data'!$C$6:$C$114,E$5,'CPI Data'!$D$6:$D$114,1)) | F6: =IF(COUNTIFS('CPI Data'!$C$6:$C$114,F$5,'CPI Data'!$D$6:$D$114,1,'CPI Data'!$F$6:$F$114,">0")=0,"",SUMIFS('CPI Data'!$J$6:$J$114,'CPI Data'!$C$6:$C$114,F$5,'CPI Data'!$D$6:$D$114,1)) | G6: =IF(COUNTIFS('CPI Data'!$C$6:$C$114,G$5,'CPI Data'!$D$6:$D$114,1,'CPI Data'!$F$6:$F$114,">0")=0,"",SUMIFS('CPI Data'!$J$6:$J$114,'CPI Data'!$C$6:$C$114,G$5,'CPI Data'!$D$6:$D$114,1)) | H6: =IF(COUNTIFS('CPI Data'!$C$6:$C$114,H$5,'CPI Data'!$D$6:$D$114,1,'CPI Data'!$F$6:$F$114,">0")=0,"",SUMIFS('CPI Data'!$J$6:$J$114,'CPI Data'!$C$6:$C$114,H$5,'CPI Data'!$D$6:$D$114,1)) | I6: =IF(COUNTIFS('CPI Data'!$C$6:$C$114,I$5,'CPI Data'!$D$6:$D$114,1,'CPI Data'!$F$6:$F$114,">0")=0,"",SUMIFS('CPI Data'!$J$6:$J$114,'CPI Data'!$C$6:$C$114,I$5,'CPI Data'!$D$6:$D$114,1)) | J6: =IF(COUNTIFS('CPI Data'!$C$6:$C$114,J$5,'CPI Data'!$D$6:$D$114,1,'CPI Data'!$F$6:$F$114,">0")=0,"",SUMIFS('CPI Data'!$J$6:$J$114,'CPI Data'!$C$6:$C$114,J$5,'CPI Data'!$D$6:$D$114,1))
B7: Feb | C7: =IF(COUNTIFS('CPI Data'!$C$6:$C$114,C$5,'CPI Data'!$D$6:$D$114,2,'CPI Data'!$F$6:$F$114,">0")=0,"",SUMIFS('CPI Data'!$J$6:$J$114,'CPI Data'!$C$6:$C$114,C$5,'CPI Data'!$D$6:$D$114,2)) | D7: =IF(COUNTIFS('CPI Data'!$C$6:$C$114,D$5,'CPI Data'!$D$6:$D$114,2,'CPI Data'!$F$6:$F$114,">0")=0,"",SUMIFS('CPI Data'!$J$6:$J$114,'CPI Data'!$C$6:$C$114,D$5,'CPI Data'!$D$6:$D$114,2)) | E7: =IF(COUNTIFS('CPI Data'!$C$6:$C$114,E$5,'CPI Data'!$D$6:$D$114,2,'CPI Data'!$F$6:$F$114,">0")=0,"",SUMIFS('CPI Data'!$J$6:$J$114,'CPI Data'!$C$6:$C$114,E$5,'CPI Data'!$D$6:$D$114,2)) | F7: =IF(COUNTIFS('CPI Data'!$C$6:$C$114,F$5,'CPI Data'!$D$6:$D$114,2,'CPI Data'!$F$6:$F$114,">0")=0,"",SUMIFS('CPI Data'!$J$6:$J$114,'CPI Data'!$C$6:$C$114,F$5,'CPI Data'!$D$6:$D$114,2)) | G7: =IF(COUNTIFS('CPI Data'!$C$6:$C$114,G$5,'CPI Data'!$D$6:$D$114,2,'CPI Data'!$F$6:$F$114,">0")=0,"",SUMIFS('CPI Data'!$J$6:$J$114,'CPI Data'!$C$6:$C$114,G$5,'CPI Data'!$D$6:$D$114,2)) | H7: =IF(COUNTIFS('CPI Data'!$C$6:$C$114,H$5,'CPI Data'!$D$6:$D$114,2,'CPI Data'!$F$6:$F$114,">0")=0,"",SUMIFS('CPI Data'!$J$6:$J$114,'CPI Data'!$C$6:$C$114,H$5,'CPI Data'!$D$6:$D$114,2)) | I7: =IF(COUNTIFS('CPI Data'!$C$6:$C$114,I$5,'CPI Data'!$D$6:$D$114,2,'CPI Data'!$F$6:$F$114,">0")=0,"",SUMIFS('CPI Data'!$J$6:$J$114,'CPI Data'!$C$6:$C$114,I$5,'CPI Data'!$D$6:$D$114,2)) | J7: =IF(COUNTIFS('CPI Data'!$C$6:$C$114,J$5,'CPI Data'!$D$6:$D$114,2,'CPI Data'!$F$6:$F$114,">0")=0,"",SUMIFS('CPI Data'!$J$6:$J$114,'CPI Data'!$C$6:$C$114,J$5,'CPI Data'!$D$6:$D$114,2))
B8: Mar | C8: =IF(COUNTIFS('CPI Data'!$C$6:$C$114,C$5,'CPI Data'!$D$6:$D$114,3,'CPI Data'!$F$6:$F$114,">0")=0,"",SUMIFS('CPI Data'!$J$6:$J$114,'CPI Data'!$C$6:$C$114,C$5,'CPI Data'!$D$6:$D$114,3)) | D8: =IF(COUNTIFS('CPI Data'!$C$6:$C$114,D$5,'CPI Data'!$D$6:$D$114,3,'CPI Data'!$F$6:$F$114,">0")=0,"",SUMIFS('CPI Data'!$J$6:$J$114,'CPI Data'!$C$6:$C$114,D$5,'CPI Data'!$D$6:$D$114,3)) | E8: =IF(COUNTIFS('CPI Data'!$C$6:$C$114,E$5,'CPI Data'!$D$6:$D$114,3,'CPI Data'!$F$6:$F$114,">0")=0,"",SUMIFS('CPI Data'!$J$6:$J$114,'CPI Data'!$C$6:$C$114,E$5,'CPI Data'!$D$6:$D$114,3)) | F8: =IF(COUNTIFS('CPI Data'!$C$6:$C$114,F$5,'CPI Data'!$D$6:$D$114,3,'CPI Data'!$F$6:$F$114,">0")=0,"",SUMIFS('CPI Data'!$J$6:$J$114,'CPI Data'!$C$6:$C$114,F$5,'CPI Data'!$D$6:$D$114,3)) | G8: =IF(COUNTIFS('CPI Data'!$C$6:$C$114,G$5,'CPI Data'!$D$6:$D$114,3,'CPI Data'!$F$6:$F$114,">0")=0,"",SUMIFS('CPI Data'!$J$6:$J$114,'CPI Data'!$C$6:$C$114,G$5,'CPI Data'!$D$6:$D$114,3)) | H8: =IF(COUNTIFS('CPI Data'!$C$6:$C$114,H$5,'CPI Data'!$D$6:$D$114,3,'CPI Data'!$F$6:$F$114,">0")=0,"",SUMIFS('CPI Data'!$J$6:$J$114,'CPI Data'!$C$6:$C$114,H$5,'CPI Data'!$D$6:$D$114,3)) | I8: =IF(COUNTIFS('CPI Data'!$C$6:$C$114,I$5,'CPI Data'!$D$6:$D$114,3,'CPI Data'!$F$6:$F$114,">0")=0,"",SUMIFS('CPI Data'!$J$6:$J$114,'CPI Data'!$C$6:$C$114,I$5,'CPI Data'!$D$6:$D$114,3)) | J8: =IF(COUNTIFS('CPI Data'!$C$6:$C$114,J$5,'CPI Data'!$D$6:$D$114,3,'CPI Data'!$F$6:$F$114,">0")=0,"",SUMIFS('CPI Data'!$J$6:$J$114,'CPI Data'!$C$6:$C$114,J$5,'CPI Data'!$D$6:$D$114,3))
B9: Apr | C9: =IF(COUNTIFS('CPI Data'!$C$6:$C$114,C$5,'CPI Data'!$D$6:$D$114,4,'CPI Data'!$F$6:$F$114,">0")=0,"",SUMIFS('CPI Data'!$J$6:$J$114,'CPI Data'!$C$6:$C$114,C$5,'CPI Data'!$D$6:$D$114,4)) | D9: =IF(COUNTIFS('CPI Data'!$C$6:$C$114,D$5,'CPI Data'!$D$6:$D$114,4,'CPI Data'!$F$6:$F$114,">0")=0,"",SUMIFS('CPI Data'!$J$6:$J$114,'CPI Data'!$C$6:$C$114,D$5,'CPI Data'!$D$6:$D$114,4)) | E9: =IF(COUNTIFS('CPI Data'!$C$6:$C$114,E$5,'CPI Data'!$D$6:$D$114,4,'CPI Data'!$F$6:$F$114,">0")=0,"",SUMIFS('CPI Data'!$J$6:$J$114,'CPI Data'!$C$6:$C$114,E$5,'CPI Data'!$D$6:$D$114,4)) | F9: =IF(COUNTIFS('CPI Data'!$C$6:$C$114,F$5,'CPI Data'!$D$6:$D$114,4,'CPI Data'!$F$6:$F$114,">0")=0,"",SUMIFS('CPI Data'!$J$6:$J$114,'CPI Data'!$C$6:$C$114,F$5,'CPI Data'!$D$6:$D$114,4)) | G9: =IF(COUNTIFS('CPI Data'!$C$6:$C$114,G$5,'CPI Data'!$D$6:$D$114,4,'CPI Data'!$F$6:$F$114,">0")=0,"",SUMIFS('CPI Data'!$J$6:$J$114,'CPI Data'!$C$6:$C$114,G$5,'CPI Data'!$D$6:$D$114,4)) | H9: =IF(COUNTIFS('CPI Data'!$C$6:$C$114,H$5,'CPI Data'!$D$6:$D$114,4,'CPI Data'!$F$6:$F$114,">0")=0,"",SUMIFS('CPI Data'!$J$6:$J$114,'CPI Data'!$C$6:$C$114,H$5,'CPI Data'!$D$6:$D$114,4)) | I9: =IF(COUNTIFS('CPI Data'!$C$6:$C$114,I$5,'CPI Data'!$D$6:$D$114,4,'CPI Data'!$F$6:$F$114,">0")=0,"",SUMIFS('CPI Data'!$J$6:$J$114,'CPI Data'!$C$6:$C$114,I$5,'CPI Data'!$D$6:$D$114,4)) | J9: =IF(COUNTIFS('CPI Data'!$C$6:$C$114,J$5,'CPI Data'!$D$6:$D$114,4,'CPI Data'!$F$6:$F$114,">0")=0,"",SUMIFS('CPI Data'!$J$6:$J$114,'CPI Data'!$C$6:$C$114,J$5,'CPI Data'!$D$6:$D$114,4))
B10: May | C10: =IF(COUNTIFS('CPI Data'!$C$6:$C$114,C$5,'CPI Data'!$D$6:$D$114,5,'CPI Data'!$F$6:$F$114,">0")=0,"",SUMIFS('CPI Data'!$J$6:$J$114,'CPI Data'!$C$6:$C$114,C$5,'CPI Data'!$D$6:$D$114,5)) | D10: =IF(COUNTIFS('CPI Data'!$C$6:$C$114,D$5,'CPI Data'!$D$6:$D$114,5,'CPI Data'!$F$6:$F$114,">0")=0,"",SUMIFS('CPI Data'!$J$6:$J$114,'CPI Data'!$C$6:$C$114,D$5,'CPI Data'!$D$6:$D$114,5)) | E10: =IF(COUNTIFS('CPI Data'!$C$6:$C$114,E$5,'CPI Data'!$D$6:$D$114,5,'CPI Data'!$F$6:$F$114,">0")=0,"",SUMIFS('CPI Data'!$J$6:$J$114,'CPI Data'!$C$6:$C$114,E$5,'CPI Data'!$D$6:$D$114,5)) | F10: =IF(COUNTIFS('CPI Data'!$C$6:$C$114,F$5,'CPI Data'!$D$6:$D$114,5,'CPI Data'!$F$6:$F$114,">0")=0,"",SUMIFS('CPI Data'!$J$6:$J$114,'CPI Data'!$C$6:$C$114,F$5,'CPI Data'!$D$6:$D$114,5)) | G10: =IF(COUNTIFS('CPI Data'!$C$6:$C$114,G$5,'CPI Data'!$D$6:$D$114,5,'CPI Data'!$F$6:$F$114,">0")=0,"",SUMIFS('CPI Data'!$J$6:$J$114,'CPI Data'!$C$6:$C$114,G$5,'CPI Data'!$D$6:$D$114,5)) | H10: =IF(COUNTIFS('CPI Data'!$C$6:$C$114,H$5,'CPI Data'!$D$6:$D$114,5,'CPI Data'!$F$6:$F$114,">0")=0,"",SUMIFS('CPI Data'!$J$6:$J$114,'CPI Data'!$C$6:$C$114,H$5,'CPI Data'!$D$6:$D$114,5)) | I10: =IF(COUNTIFS('CPI Data'!$C$6:$C$114,I$5,'CPI Data'!$D$6:$D$114,5,'CPI Data'!$F$6:$F$114,">0")=0,"",SUMIFS('CPI Data'!$J$6:$J$114,'CPI Data'!$C$6:$C$114,I$5,'CPI Data'!$D$6:$D$114,5)) | J10: =IF(COUNTIFS('CPI Data'!$C$6:$C$114,J$5,'CPI Data'!$D$6:$D$114,5,'CPI Data'!$F$6:$F$114,">0")=0,"",SUMIFS('CPI Data'!$J$6:$J$114,'CPI Data'!$C$6:$C$114,J$5,'CPI Data'!$D$6:$D$114,5))
B11: Jun | C11: =IF(COUNTIFS('CPI Data'!$C$6:$C$114,C$5,'CPI Data'!$D$6:$D$114,6,'CPI Data'!$F$6:$F$114,">0")=0,"",SUMIFS('CPI Data'!$J$6:$J$114,'CPI Data'!$C$6:$C$114,C$5,'CPI Data'!$D$6:$D$114,6)) | D11: =IF(COUNTIFS('CPI Data'!$C$6:$C$114,D$5,'CPI Data'!$D$6:$D$114,6,'CPI Data'!$F$6:$F$114,">0")=0,"",SUMIFS('CPI Data'!$J$6:$J$114,'CPI Data'!$C$6:$C$114,D$5,'CPI Data'!$D$6:$D$114,6)) | E11: =IF(COUNTIFS('CPI Data'!$C$6:$C$114,E$5,'CPI Data'!$D$6:$D$114,6,'CPI Data'!$F$6:$F$114,">0")=0,"",SUMIFS('CPI Data'!$J$6:$J$114,'CPI Data'!$C$6:$C$114,E$5,'CPI Data'!$D$6:$D$114,6)) | F11: =IF(COUNTIFS('CPI Data'!$C$6:$C$114,F$5,'CPI Data'!$D$6:$D$114,6,'CPI Data'!$F$6:$F$114,">0")=0,"",SUMIFS('CPI Data'!$J$6:$J$114,'CPI Data'!$C$6:$C$114,F$5,'CPI Data'!$D$6:$D$114,6)) | G11: =IF(COUNTIFS('CPI Data'!$C$6:$C$114,G$5,'CPI Data'!$D$6:$D$114,6,'CPI Data'!$F$6:$F$114,">0")=0,"",SUMIFS('CPI Data'!$J$6:$J$114,'CPI Data'!$C$6:$C$114,G$5,'CPI Data'!$D$6:$D$114,6)) | H11: =IF(COUNTIFS('CPI Data'!$C$6:$C$114,H$5,'CPI Data'!$D$6:$D$114,6,'CPI Data'!$F$6:$F$114,">0")=0,"",SUMIFS('CPI Data'!$J$6:$J$114,'CPI Data'!$C$6:$C$114,H$5,'CPI Data'!$D$6:$D$114,6)) | I11: =IF(COUNTIFS('CPI Data'!$C$6:$C$114,I$5,'CPI Data'!$D$6:$D$114,6,'CPI Data'!$F$6:$F$114,">0")=0,"",SUMIFS('CPI Data'!$J$6:$J$114,'CPI Data'!$C$6:$C$114,I$5,'CPI Data'!$D$6:$D$114,6)) | J11: =IF(COUNTIFS('CPI Data'!$C$6:$C$114,J$5,'CPI Data'!$D$6:$D$114,6,'CPI Data'!$F$6:$F$114,">0")=0,"",SUMIFS('CPI Data'!$J$6:$J$114,'CPI Data'!$C$6:$C$114,J$5,'CPI Data'!$D$6:$D$114,6))
B12: Jul | C12: =IF(COUNTIFS('CPI Data'!$C$6:$C$114,C$5,'CPI Data'!$D$6:$D$114,7,'CPI Data'!$F$6:$F$114,">0")=0,"",SUMIFS('CPI Data'!$J$6:$J$114,'CPI Data'!$C$6:$C$114,C$5,'CPI Data'!$D$6:$D$114,7)) | D12: =IF(COUNTIFS('CPI Data'!$C$6:$C$114,D$5,'CPI Data'!$D$6:$D$114,7,'CPI Data'!$F$6:$F$114,">0")=0,"",SUMIFS('CPI Data'!$J$6:$J$114,'CPI Data'!$C$6:$C$114,D$5,'CPI Data'!$D$6:$D$114,7)) | E12: =IF(COUNTIFS('CPI Data'!$C$6:$C$114,E$5,'CPI Data'!$D$6:$D$114,7,'CPI Data'!$F$6:$F$114,">0")=0,"",SUMIFS('CPI Data'!$J$6:$J$114,'CPI Data'!$C$6:$C$114,E$5,'CPI Data'!$D$6:$D$114,7)) | F12: =IF(COUNTIFS('CPI Data'!$C$6:$C$114,F$5,'CPI Data'!$D$6:$D$114,7,'CPI Data'!$F$6:$F$114,">0")=0,"",SUMIFS('CPI Data'!$J$6:$J$114,'CPI Data'!$C$6:$C$114,F$5,'CPI Data'!$D$6:$D$114,7)) | G12: =IF(COUNTIFS('CPI Data'!$C$6:$C$114,G$5,'CPI Data'!$D$6:$D$114,7,'CPI Data'!$F$6:$F$114,">0")=0,"",SUMIFS('CPI Data'!$J$6:$J$114,'CPI Data'!$C$6:$C$114,G$5,'CPI Data'!$D$6:$D$114,7)) | H12: =IF(COUNTIFS('CPI Data'!$C$6:$C$114,H$5,'CPI Data'!$D$6:$D$114,7,'CPI Data'!$F$6:$F$114,">0")=0,"",SUMIFS('CPI Data'!$J$6:$J$114,'CPI Data'!$C$6:$C$114,H$5,'CPI Data'!$D$6:$D$114,7)) | I12: =IF(COUNTIFS('CPI Data'!$C$6:$C$114,I$5,'CPI Data'!$D$6:$D$114,7,'CPI Data'!$F$6:$F$114,">0")=0,"",SUMIFS('CPI Data'!$J$6:$J$114,'CPI Data'!$C$6:$C$114,I$5,'CPI Data'!$D$6:$D$114,7)) | J12: =IF(COUNTIFS('CPI Data'!$C$6:$C$114,J$5,'CPI Data'!$D$6:$D$114,7,'CPI Data'!$F$6:$F$114,">0")=0,"",SUMIFS('CPI Data'!$J$6:$J$114,'CPI Data'!$C$6:$C$114,J$5,'CPI Data'!$D$6:$D$114,7))
B13: Aug | C13: =IF(COUNTIFS('CPI Data'!$C$6:$C$114,C$5,'CPI Data'!$D$6:$D$114,8,'CPI Data'!$F$6:$F$114,">0")=0,"",SUMIFS('CPI Data'!$J$6:$J$114,'CPI Data'!$C$6:$C$114,C$5,'CPI Data'!$D$6:$D$114,8)) | D13: =IF(COUNTIFS('CPI Data'!$C$6:$C$114,D$5,'CPI Data'!$D$6:$D$114,8,'CPI Data'!$F$6:$F$114,">0")=0,"",SUMIFS('CPI Data'!$J$6:$J$114,'CPI Data'!$C$6:$C$114,D$5,'CPI Data'!$D$6:$D$114,8)) | E13: =IF(COUNTIFS('CPI Data'!$C$6:$C$114,E$5,'CPI Data'!$D$6:$D$114,8,'CPI Data'!$F$6:$F$114,">0")=0,"",SUMIFS('CPI Data'!$J$6:$J$114,'CPI Data'!$C$6:$C$114,E$5,'CPI Data'!$D$6:$D$114,8)) | F13: =IF(COUNTIFS('CPI Data'!$C$6:$C$114,F$5,'CPI Data'!$D$6:$D$114,8,'CPI Data'!$F$6:$F$114,">0")=0,"",SUMIFS('CPI Data'!$J$6:$J$114,'CPI Data'!$C$6:$C$114,F$5,'CPI Data'!$D$6:$D$114,8)) | G13: =IF(COUNTIFS('CPI Data'!$C$6:$C$114,G$5,'CPI Data'!$D$6:$D$114,8,'CPI Data'!$F$6:$F$114,">0")=0,"",SUMIFS('CPI Data'!$J$6:$J$114,'CPI Data'!$C$6:$C$114,G$5,'CPI Data'!$D$6:$D$114,8)) | H13: =IF(COUNTIFS('CPI Data'!$C$6:$C$114,H$5,'CPI Data'!$D$6:$D$114,8,'CPI Data'!$F$6:$F$114,">0")=0,"",SUMIFS('CPI Data'!$J$6:$J$114,'CPI Data'!$C$6:$C$114,H$5,'CPI Data'!$D$6:$D$114,8)) | I13: =IF(COUNTIFS('CPI Data'!$C$6:$C$114,I$5,'CPI Data'!$D$6:$D$114,8,'CPI Data'!$F$6:$F$114,">0")=0,"",SUMIFS('CPI Data'!$J$6:$J$114,'CPI Data'!$C$6:$C$114,I$5,'CPI Data'!$D$6:$D$114,8)) | J13: =IF(COUNTIFS('CPI Data'!$C$6:$C$114,J$5,'CPI Data'!$D$6:$D$114,8,'CPI Data'!$F$6:$F$114,">0")=0,"",SUMIFS('CPI Data'!$J$6:$J$114,'CPI Data'!$C$6:$C$114,J$5,'CPI Data'!$D$6:$D$114,8))
B14: Sep | C14: =IF(COUNTIFS('CPI Data'!$C$6:$C$114,C$5,'CPI Data'!$D$6:$D$114,9,'CPI Data'!$F$6:$F$114,">0")=0,"",SUMIFS('CPI Data'!$J$6:$J$114,'CPI Data'!$C$6:$C$114,C$5,'CPI Data'!$D$6:$D$114,9)) | D14: =IF(COUNTIFS('CPI Data'!$C$6:$C$114,D$5,'CPI Data'!$D$6:$D$114,9,'CPI Data'!$F$6:$F$114,">0")=0,"",SUMIFS('CPI Data'!$J$6:$J$114,'CPI Data'!$C$6:$C$114,D$5,'CPI Data'!$D$6:$D$114,9)) | E14: =IF(COUNTIFS('CPI Data'!$C$6:$C$114,E$5,'CPI Data'!$D$6:$D$114,9,'CPI Data'!$F$6:$F$114,">0")=0,"",SUMIFS('CPI Data'!$J$6:$J$114,'CPI Data'!$C$6:$C$114,E$5,'CPI Data'!$D$6:$D$114,9)) | F14: =IF(COUNTIFS('CPI Data'!$C$6:$C$114,F$5,'CPI Data'!$D$6:$D$114,9,'CPI Data'!$F$6:$F$114,">0")=0,"",SUMIFS('CPI Data'!$J$6:$J$114,'CPI Data'!$C$6:$C$114,F$5,'CPI Data'!$D$6:$D$114,9)) | G14: =IF(COUNTIFS('CPI Data'!$C$6:$C$114,G$5,'CPI Data'!$D$6:$D$114,9,'CPI Data'!$F$6:$F$114,">0")=0,"",SUMIFS('CPI Data'!$J$6:$J$114,'CPI Data'!$C$6:$C$114,G$5,'CPI Data'!$D$6:$D$114,9)) | H14: =IF(COUNTIFS('CPI Data'!$C$6:$C$114,H$5,'CPI Data'!$D$6:$D$114,9,'CPI Data'!$F$6:$F$114,">0")=0,"",SUMIFS('CPI Data'!$J$6:$J$114,'CPI Data'!$C$6:$C$114,H$5,'CPI Data'!$D$6:$D$114,9)) | I14: =IF(COUNTIFS('CPI Data'!$C$6:$C$114,I$5,'CPI Data'!$D$6:$D$114,9,'CPI Data'!$F$6:$F$114,">0")=0,"",SUMIFS('CPI Data'!$J$6:$J$114,'CPI Data'!$C$6:$C$114,I$5,'CPI Data'!$D$6:$D$114,9)) | J14: =IF(COUNTIFS('CPI Data'!$C$6:$C$114,J$5,'CPI Data'!$D$6:$D$114,9,'CPI Data'!$F$6:$F$114,">0")=0,"",SUMIFS('CPI Data'!$J$6:$J$114,'CPI Data'!$C$6:$C$114,J$5,'CPI Data'!$D$6:$D$114,9))
B15: Oct | C15: =IF(COUNTIFS('CPI Data'!$C$6:$C$114,C$5,'CPI Data'!$D$6:$D$114,10,'CPI Data'!$F$6:$F$114,">0")=0,"",SUMIFS('CPI Data'!$J$6:$J$114,'CPI Data'!$C$6:$C$114,C$5,'CPI Data'!$D$6:$D$114,10)) | D15: =IF(COUNTIFS('CPI Data'!$C$6:$C$114,D$5,'CPI Data'!$D$6:$D$114,10,'CPI Data'!$F$6:$F$114,">0")=0,"",SUMIFS('CPI Data'!$J$6:$J$114,'CPI Data'!$C$6:$C$114,D$5,'CPI Data'!$D$6:$D$114,10)) | E15: =IF(COUNTIFS('CPI Data'!$C$6:$C$114,E$5,'CPI Data'!$D$6:$D$114,10,'CPI Data'!$F$6:$F$114,">0")=0,"",SUMIFS('CPI Data'!$J$6:$J$114,'CPI Data'!$C$6:$C$114,E$5,'CPI Data'!$D$6:$D$114,10)) | F15: =IF(COUNTIFS('CPI Data'!$C$6:$C$114,F$5,'CPI Data'!$D$6:$D$114,10,'CPI Data'!$F$6:$F$114,">0")=0,"",SUMIFS('CPI Data'!$J$6:$J$114,'CPI Data'!$C$6:$C$114,F$5,'CPI Data'!$D$6:$D$114,10)) | G15: =IF(COUNTIFS('CPI Data'!$C$6:$C$114,G$5,'CPI Data'!$D$6:$D$114,10,'CPI Data'!$F$6:$F$114,">0")=0,"",SUMIFS('CPI Data'!$J$6:$J$114,'CPI Data'!$C$6:$C$114,G$5,'CPI Data'!$D$6:$D$114,10)) | H15: =IF(COUNTIFS('CPI Data'!$C$6:$C$114,H$5,'CPI Data'!$D$6:$D$114,10,'CPI Data'!$F$6:$F$114,">0")=0,"",SUMIFS('CPI Data'!$J$6:$J$114,'CPI Data'!$C$6:$C$114,H$5,'CPI Data'!$D$6:$D$114,10)) | I15: =IF(COUNTIFS('CPI Data'!$C$6:$C$114,I$5,'CPI Data'!$D$6:$D$114,10,'CPI Data'!$F$6:$F$114,">0")=0,"",SUMIFS('CPI Data'!$J$6:$J$114,'CPI Data'!$C$6:$C$114,I$5,'CPI Data'!$D$6:$D$114,10)) | J15: =IF(COUNTIFS('CPI Data'!$C$6:$C$114,J$5,'CPI Data'!$D$6:$D$114,10,'CPI Data'!$F$6:$F$114,">0")=0,"",SUMIFS('CPI Data'!$J$6:$J$114,'CPI Data'!$C$6:$C$114,J$5,'CPI Data'!$D$6:$D$114,10))
B16: Nov | C16: =IF(COUNTIFS('CPI Data'!$C$6:$C$114,C$5,'CPI Data'!$D$6:$D$114,11,'CPI Data'!$F$6:$F$114,">0")=0,"",SUMIFS('CPI Data'!$J$6:$J$114,'CPI Data'!$C$6:$C$114,C$5,'CPI Data'!$D$6:$D$114,11)) | D16: =IF(COUNTIFS('CPI Data'!$C$6:$C$114,D$5,'CPI Data'!$D$6:$D$114,11,'CPI Data'!$F$6:$F$114,">0")=0,"",SUMIFS('CPI Data'!$J$6:$J$114,'CPI Data'!$C$6:$C$114,D$5,'CPI Data'!$D$6:$D$114,11)) | E16: =IF(COUNTIFS('CPI Data'!$C$6:$C$114,E$5,'CPI Data'!$D$6:$D$114,11,'CPI Data'!$F$6:$F$114,">0")=0,"",SUMIFS('CPI Data'!$J$6:$J$114,'CPI Data'!$C$6:$C$114,E$5,'CPI Data'!$D$6:$D$114,11)) | F16: =IF(COUNTIFS('CPI Data'!$C$6:$C$114,F$5,'CPI Data'!$D$6:$D$114,11,'CPI Data'!$F$6:$F$114,">0")=0,"",SUMIFS('CPI Data'!$J$6:$J$114,'CPI Data'!$C$6:$C$114,F$5,'CPI Data'!$D$6:$D$114,11)) | G16: =IF(COUNTIFS('CPI Data'!$C$6:$C$114,G$5,'CPI Data'!$D$6:$D$114,11,'CPI Data'!$F$6:$F$114,">0")=0,"",SUMIFS('CPI Data'!$J$6:$J$114,'CPI Data'!$C$6:$C$114,G$5,'CPI Data'!$D$6:$D$114,11)) | H16: =IF(COUNTIFS('CPI Data'!$C$6:$C$114,H$5,'CPI Data'!$D$6:$D$114,11,'CPI Data'!$F$6:$F$114,">0")=0,"",SUMIFS('CPI Data'!$J$6:$J$114,'CPI Data'!$C$6:$C$114,H$5,'CPI Data'!$D$6:$D$114,11)) | I16: =IF(COUNTIFS('CPI Data'!$C$6:$C$114,I$5,'CPI Data'!$D$6:$D$114,11,'CPI Data'!$F$6:$F$114,">0")=0,"",SUMIFS('CPI Data'!$J$6:$J$114,'CPI Data'!$C$6:$C$114,I$5,'CPI Data'!$D$6:$D$114,11)) | J16: =IF(COUNTIFS('CPI Data'!$C$6:$C$114,J$5,'CPI Data'!$D$6:$D$114,11,'CPI Data'!$F$6:$F$114,">0")=0,"",SUMIFS('CPI Data'!$J$6:$J$114,'CPI Data'!$C$6:$C$114,J$5,'CPI Data'!$D$6:$D$114,11))
B17: Dec | C17: =IF(COUNTIFS('CPI Data'!$C$6:$C$114,C$5,'CPI Data'!$D$6:$D$114,12,'CPI Data'!$F$6:$F$114,">0")=0,"",SUMIFS('CPI Data'!$J$6:$J$114,'CPI Data'!$C$6:$C$114,C$5,'CPI Data'!$D$6:$D$114,12)) | D17: =IF(COUNTIFS('CPI Data'!$C$6:$C$114,D$5,'CPI Data'!$D$6:$D$114,12,'CPI Data'!$F$6:$F$114,">0")=0,"",SUMIFS('CPI Data'!$J$6:$J$114,'CPI Data'!$C$6:$C$114,D$5,'CPI Data'!$D$6:$D$114,12)) | E17: =IF(COUNTIFS('CPI Data'!$C$6:$C$114,E$5,'CPI Data'!$D$6:$D$114,12,'CPI Data'!$F$6:$F$114,">0")=0,"",SUMIFS('CPI Data'!$J$6:$J$114,'CPI Data'!$C$6:$C$114,E$5,'CPI Data'!$D$6:$D$114,12)) | F17: =IF(COUNTIFS('CPI Data'!$C$6:$C$114,F$5,'CPI Data'!$D$6:$D$114,12,'CPI Data'!$F$6:$F$114,">0")=0,"",SUMIFS('CPI Data'!$J$6:$J$114,'CPI Data'!$C$6:$C$114,F$5,'CPI Data'!$D$6:$D$114,12)) | G17: =IF(COUNTIFS('CPI Data'!$C$6:$C$114,G$5,'CPI Data'!$D$6:$D$114,12,'CPI Data'!$F$6:$F$114,">0")=0,"",SUMIFS('CPI Data'!$J$6:$J$114,'CPI Data'!$C$6:$C$114,G$5,'CPI Data'!$D$6:$D$114,12)) | H17: =IF(COUNTIFS('CPI Data'!$C$6:$C$114,H$5,'CPI Data'!$D$6:$D$114,12,'CPI Data'!$F$6:$F$114,">0")=0,"",SUMIFS('CPI Data'!$J$6:$J$114,'CPI Data'!$C$6:$C$114,H$5,'CPI Data'!$D$6:$D$114,12)) | I17: =IF(COUNTIFS('CPI Data'!$C$6:$C$114,I$5,'CPI Data'!$D$6:$D$114,12,'CPI Data'!$F$6:$F$114,">0")=0,"",SUMIFS('CPI Data'!$J$6:$J$114,'CPI Data'!$C$6:$C$114,I$5,'CPI Data'!$D$6:$D$114,12)) | J17: =IF(COUNTIFS('CPI Data'!$C$6:$C$114,J$5,'CPI Data'!$D$6:$D$114,12,'CPI Data'!$F$6:$F$114,">0")=0,"",SUMIFS('CPI Data'!$J$6:$J$114,'CPI Data'!$C$6:$C$114,J$5,'CPI Data'!$D$6:$D$114,12))
B19: Dec/Dec* | C19: =IFERROR(INDEX('CPI Data'!$F:$F,MATCH("2019-12",'CPI Data'!$B:$B,0))/INDEX('CPI Data'!$F:$F,MATCH("2018-12",'CPI Data'!$B:$B,0))-1,"") | D19: =IFERROR(INDEX('CPI Data'!$F:$F,MATCH("2020-12",'CPI Data'!$B:$B,0))/INDEX('CPI Data'!$F:$F,MATCH("2019-12",'CPI Data'!$B:$B,0))-1,"") | E19: =IFERROR(INDEX('CPI Data'!$F:$F,MATCH("2021-12",'CPI Data'!$B:$B,0))/INDEX('CPI Data'!$F:$F,MATCH("2020-12",'CPI Data'!$B:$B,0))-1,"") | F19: =IFERROR(INDEX('CPI Data'!$F:$F,MATCH("2022-12",'CPI Data'!$B:$B,0))/INDEX('CPI Data'!$F:$F,MATCH("2021-12",'CPI Data'!$B:$B,0))-1,"") | G19: =IFERROR(INDEX('CPI Data'!$F:$F,MATCH("2023-12",'CPI Data'!$B:$B,0))/INDEX('CPI Data'!$F:$F,MATCH("2022-12",'CPI Data'!$B:$B,0))-1,"") | H19: =IFERROR(INDEX('CPI Data'!$F:$F,MATCH("2024-12",'CPI Data'!$B:$B,0))/INDEX('CPI Data'!$F:$F,MATCH("2023-12",'CPI Data'!$B:$B,0))-1,"") | I19: =IFERROR(INDEX('CPI Data'!$F:$F,MATCH("2025-12",'CPI Data'!$B:$B,0))/INDEX('CPI Data'!$F:$F,MATCH("2024-12",'CPI Data'!$B:$B,0))-1,"") | J19: =IFERROR(INDEX('CPI Data'!$F:$F,MATCH("2026-08",'CPI Data'!$B:$B,0))/INDEX('CPI Data'!$F:$F,MATCH("2025-12",'CPI Data'!$B:$B,0))-1,"")
B20: Avg month | C20: =IFERROR(AVERAGE(C6:C17),"") | D20: =IFERROR(AVERAGE(D6:D17),"") | E20: =IFERROR(AVERAGE(E6:E17),"") | F20: =IFERROR(AVERAGE(F6:F17),"") | G20: =IFERROR(AVERAGE(G6:G17),"") | H20: =IFERROR(AVERAGE(H6:H17),"") | I20: =IFERROR(AVERAGE(I6:I17),"") | J20: =IFERROR(AVERAGE(J6:J17),"")
B21: * the 2026 column is year-to-date through 2026-08, not a full year.

Sheet Seasonal Factors
B2: Seasonal factors — each month against its own year's average month
B3: Scale-free, so 2023 (211%) and 2025 (31%) are directly comparable. 1.20x = 20% hotter than a typical month that year.
B5: Month | C5: 2019 | D5: 2020 | E5: 2021 | F5: 2022 | G5: 2023 | H5: 2024 | I5: 2025 | J5: Average | K5: Median | L5: ex-2020
B6: Jan | C6: =IFERROR('Seasonality Headline'!C6/'Seasonality Headline'!C$20,"") | D6: =IFERROR('Seasonality Headline'!D6/'Seasonality Headline'!D$20,"") | E6: =IFERROR('Seasonality Headline'!E6/'Seasonality Headline'!E$20,"") | F6: =IFERROR('Seasonality Headline'!F6/'Seasonality Headline'!F$20,"") | G6: =IFERROR('Seasonality Headline'!G6/'Seasonality Headline'!G$20,"") | H6: =IFERROR('Seasonality Headline'!H6/'Seasonality Headline'!H$20,"") | I6: =IFERROR('Seasonality Headline'!I6/'Seasonality Headline'!I$20,"") | J6: =IFERROR(AVERAGE(C6:I6),"") | K6: =IFERROR(MEDIAN(C6:I6),"") | L6: =IFERROR((SUM(C6:I6)-D6)/(7-1),"")
B7: Feb | C7: =IFERROR('Seasonality Headline'!C7/'Seasonality Headline'!C$20,"") | D7: =IFERROR('Seasonality Headline'!D7/'Seasonality Headline'!D$20,"") | E7: =IFERROR('Seasonality Headline'!E7/'Seasonality Headline'!E$20,"") | F7: =IFERROR('Seasonality Headline'!F7/'Seasonality Headline'!F$20,"") | G7: =IFERROR('Seasonality Headline'!G7/'Seasonality Headline'!G$20,"") | H7: =IFERROR('Seasonality Headline'!H7/'Seasonality Headline'!H$20,"") | I7: =IFERROR('Seasonality Headline'!I7/'Seasonality Headline'!I$20,"") | J7: =IFERROR(AVERAGE(C7:I7),"") | K7: =IFERROR(MEDIAN(C7:I7),"") | L7: =IFERROR((SUM(C7:I7)-D7)/(7-1),"")
B8: Mar | C8: =IFERROR('Seasonality Headline'!C8/'Seasonality Headline'!C$20,"") | D8: =IFERROR('Seasonality Headline'!D8/'Seasonality Headline'!D$20,"") | E8: =IFERROR('Seasonality Headline'!E8/'Seasonality Headline'!E$20,"") | F8: =IFERROR('Seasonality Headline'!F8/'Seasonality Headline'!F$20,"") | G8: =IFERROR('Seasonality Headline'!G8/'Seasonality Headline'!G$20,"") | H8: =IFERROR('Seasonality Headline'!H8/'Seasonality Headline'!H$20,"") | I8: =IFERROR('Seasonality Headline'!I8/'Seasonality Headline'!I$20,"") | J8: =IFERROR(AVERAGE(C8:I8),"") | K8: =IFERROR(MEDIAN(C8:I8),"") | L8: =IFERROR((SUM(C8:I8)-D8)/(7-1),"")
B9: Apr | C9: =IFERROR('Seasonality Headline'!C9/'Seasonality Headline'!C$20,"") | D9: =IFERROR('Seasonality Headline'!D9/'Seasonality Headline'!D$20,"") | E9: =IFERROR('Seasonality Headline'!E9/'Seasonality Headline'!E$20,"") | F9: =IFERROR('Seasonality Headline'!F9/'Seasonality Headline'!F$20,"") | G9: =IFERROR('Seasonality Headline'!G9/'Seasonality Headline'!G$20,"") | H9: =IFERROR('Seasonality Headline'!H9/'Seasonality Headline'!H$20,"") | I9: =IFERROR('Seasonality Headline'!I9/'Seasonality Headline'!I$20,"") | J9: =IFERROR(AVERAGE(C9:I9),"") | K9: =IFERROR(MEDIAN(C9:I9),"") | L9: =IFERROR((SUM(C9:I9)-D9)/(7-1),"")
B10: May | C10: =IFERROR('Seasonality Headline'!C10/'Seasonality Headline'!C$20,"") | D10: =IFERROR('Seasonality Headline'!D10/'Seasonality Headline'!D$20,"") | E10: =IFERROR('Seasonality Headline'!E10/'Seasonality Headline'!E$20,"") | F10: =IFERROR('Seasonality Headline'!F10/'Seasonality Headline'!F$20,"") | G10: =IFERROR('Seasonality Headline'!G10/'Seasonality Headline'!G$20,"") | H10: =IFERROR('Seasonality Headline'!H10/'Seasonality Headline'!H$20,"") | I10: =IFERROR('Seasonality Headline'!I10/'Seasonality Headline'!I$20,"") | J10: =IFERROR(AVERAGE(C10:I10),"") | K10: =IFERROR(MEDIAN(C10:I10),"") | L10: =IFERROR((SUM(C10:I10)-D10)/(7-1),"")
B11: Jun | C11: =IFERROR('Seasonality Headline'!C11/'Seasonality Headline'!C$20,"") | D11: =IFERROR('Seasonality Headline'!D11/'Seasonality Headline'!D$20,"") | E11: =IFERROR('Seasonality Headline'!E11/'Seasonality Headline'!E$20,"") | F11: =IFERROR('Seasonality Headline'!F11/'Seasonality Headline'!F$20,"") | G11: =IFERROR('Seasonality Headline'!G11/'Seasonality Headline'!G$20,"") | H11: =IFERROR('Seasonality Headline'!H11/'Seasonality Headline'!H$20,"") | I11: =IFERROR('Seasonality Headline'!I11/'Seasonality Headline'!I$20,"") | J11: =IFERROR(AVERAGE(C11:I11),"") | K11: =IFERROR(MEDIAN(C11:I11),"") | L11: =IFERROR((SUM(C11:I11)-D11)/(7-1),"")
B12: Jul | C12: =IFERROR('Seasonality Headline'!C12/'Seasonality Headline'!C$20,"") | D12: =IFERROR('Seasonality Headline'!D12/'Seasonality Headline'!D$20,"") | E12: =IFERROR('Seasonality Headline'!E12/'Seasonality Headline'!E$20,"") | F12: =IFERROR('Seasonality Headline'!F12/'Seasonality Headline'!F$20,"") | G12: =IFERROR('Seasonality Headline'!G12/'Seasonality Headline'!G$20,"") | H12: =IFERROR('Seasonality Headline'!H12/'Seasonality Headline'!H$20,"") | I12: =IFERROR('Seasonality Headline'!I12/'Seasonality Headline'!I$20,"") | J12: =IFERROR(AVERAGE(C12:I12),"") | K12: =IFERROR(MEDIAN(C12:I12),"") | L12: =IFERROR((SUM(C12:I12)-D12)/(7-1),"")
B13: Aug | C13: =IFERROR('Seasonality Headline'!C13/'Seasonality Headline'!C$20,"") | D13: =IFERROR('Seasonality Headline'!D13/'Seasonality Headline'!D$20,"") | E13: =IFERROR('Seasonality Headline'!E13/'Seasonality Headline'!E$20,"") | F13: =IFERROR('Seasonality Headline'!F13/'Seasonality Headline'!F$20,"") | G13: =IFERROR('Seasonality Headline'!G13/'Seasonality Headline'!G$20,"") | H13: =IFERROR('Seasonality Headline'!H13/'Seasonality Headline'!H$20,"") | I13: =IFERROR('Seasonality Headline'!I13/'Seasonality Headline'!I$20,"") | J13: =IFERROR(AVERAGE(C13:I13),"") | K13: =IFERROR(MEDIAN(C13:I13),"") | L13: =IFERROR((SUM(C13:I13)-D13)/(7-1),"")
B14: Sep | C14: =IFERROR('Seasonality Headline'!C14/'Seasonality Headline'!C$20,"") | D14: =IFERROR('Seasonality Headline'!D14/'Seasonality Headline'!D$20,"") | E14: =IFERROR('Seasonality Headline'!E14/'Seasonality Headline'!E$20,"") | F14: =IFERROR('Seasonality Headline'!F14/'Seasonality Headline'!F$20,"") | G14: =IFERROR('Seasonality Headline'!G14/'Seasonality Headline'!G$20,"") | H14: =IFERROR('Seasonality Headline'!H14/'Seasonality Headline'!H$20,"") | I14: =IFERROR('Seasonality Headline'!I14/'Seasonality Headline'!I$20,"") | J14: =IFERROR(AVERAGE(C14:I14),"") | K14: =IFERROR(MEDIAN(C14:I14),"") | L14: =IFERROR((SUM(C14:I14)-D14)/(7-1),"")
B15: Oct | C15: =IFERROR('Seasonality Headline'!C15/'Seasonality Headline'!C$20,"") | D15: =IFERROR('Seasonality Headline'!D15/'Seasonality Headline'!D$20,"") | E15: =IFERROR('Seasonality Headline'!E15/'Seasonality Headline'!E$20,"") | F15: =IFERROR('Seasonality Headline'!F15/'Seasonality Headline'!F$20,"") | G15: =IFERROR('Seasonality Headline'!G15/'Seasonality Headline'!G$20,"") | H15: =IFERROR('Seasonality Headline'!H15/'Seasonality Headline'!H$20,"") | I15: =IFERROR('Seasonality Headline'!I15/'Seasonality Headline'!I$20,"") | J15: =IFERROR(AVERAGE(C15:I15),"") | K15: =IFERROR(MEDIAN(C15:I15),"") | L15: =IFERROR((SUM(C15:I15)-D15)/(7-1),"")
B16: Nov | C16: =IFERROR('Seasonality Headline'!C16/'Seasonality Headline'!C$20,"") | D16: =IFERROR('Seasonality Headline'!D16/'Seasonality Headline'!D$20,"") | E16: =IFERROR('Seasonality Headline'!E16/'Seasonality Headline'!E$20,"") | F16: =IFERROR('Seasonality Headline'!F16/'Seasonality Headline'!F$20,"") | G16: =IFERROR('Seasonality Headline'!G16/'Seasonality Headline'!G$20,"") | H16: =IFERROR('Seasonality Headline'!H16/'Seasonality Headline'!H$20,"") | I16: =IFERROR('Seasonality Headline'!I16/'Seasonality Headline'!I$20,"") | J16: =IFERROR(AVERAGE(C16:I16),"") | K16: =IFERROR(MEDIAN(C16:I16),"") | L16: =IFERROR((SUM(C16:I16)-D16)/(7-1),"")
B17: Dec | C17: =IFERROR('Seasonality Headline'!C17/'Seasonality Headline'!C$20,"") | D17: =IFERROR('Seasonality Headline'!D17/'Seasonality Headline'!D$20,"") | E17: =IFERROR('Seasonality Headline'!E17/'Seasonality Headline'!E$20,"") | F17: =IFERROR('Seasonality Headline'!F17/'Seasonality Headline'!F$20,"") | G17: =IFERROR('Seasonality Headline'!G17/'Seasonality Headline'!G$20,"") | H17: =IFERROR('Seasonality Headline'!H17/'Seasonality Headline'!H$20,"") | I17: =IFERROR('Seasonality Headline'!I17/'Seasonality Headline'!I$20,"") | J17: =IFERROR(AVERAGE(C17:I17),"") | K17: =IFERROR(MEDIAN(C17:I17),"") | L17: =IFERROR((SUM(C17:I17)-D17)/(7-1),"")
B19: A factor above 1.00x means the month runs systematically hotter than that year's average month. The Apr-Jul window that matters for 2027 is visible here.

Sheet Momentum
B2: Momentum — 3m and 6m annualised against year-on-year
B3: The annualised measures turn roughly nine months before the y/y does. Where they sit below the y/y, the y/y is still falling mechanically.
B63: Current readings
B64: Measure | C64: Headline | D64: Core | E64: Read
B65: Latest m/m | C65: ='CPI Data'!I98 | D65: ='CPI Data'!J98 | E65: August 2026. Lowest August in the series (2025 1.9%, 2024 4.2%, 2021 2.5%).
B66: 3m annualised | C66: ='CPI Data'!P98 | D66: ='CPI Data'!Q98 | E66: Falling, but the core 3m has barely moved in two months — that is the flattening showing up in the trend measure.
B67: 6m annualised | C67: ='CPI Data'!R98 | E67: The slower measure still sits above the 3m, so the disinflation trend is intact on a half-year view.
B68: y/y | C68: ='CPI Data'!M98 | D68: ='CPI Data'!N98 | E68: Still elevated because the base months of late 2025 were themselves low.
B69: YTD (Jan-Aug) | C69: ='CPI Data'!S98 | E69: Headline 21.3% in 2026 against 19.5% in 2025 — running HOTTER. Core 19.8% against 20.8% — running COOLER. The entire difference is regulados.
B71: The seasonal caution — and it matters for 2027
B72: Month | C72: Printed m/m | D72: Seasonal factor | E72: Deseasonalised m/m | F72: Annualised
B73: Jun-2026 | C73: ='CPI Data'!I96 | D73: ='Seasonal Factors'!$L$11 | E73: =C73/D73 | F73: =(1+E73)^12-1
B74: Jul-2026 | C74: ='CPI Data'!I97 | D74: ='Seasonal Factors'!$L$12 | E74: =C74/D74 | F74: =(1+E74)^12-1
B75: Aug-2026 | C75: ='CPI Data'!I98 | D75: ='Seasonal Factors'!$L$13 | E75: =C75/D75 | F75: =(1+E75)^12-1
B76: Mean | E76: =AVERAGE(E73:E75) | F76: =(1+E76)^12-1
B78: Read: the trailing 3m annualised of 25.1% understates the underlying run rate. June and July fell in the two coolest months of the Argentine calendar (factors 0.76x and 0.80x). Deseasonalised, the last three months run near 2.3%/month — around 31% annualised. August is the genuinely soft print of the three: it deseasonalises to 1.8%.
B79: This cuts the other way for the election window. April to July 2027 — the 3-to-6 months before the vote — carries an average seasonal factor of 0.86x. The window voters see is systematically the flattering part of the year.

Sheet Components
B2: Where the pressure sits — nucleo, regulados, estacionales
B3: The tariff catch-up is what keeps headline above core. It is a relative-price correction, not monetary inflation.
B32: 1. Full calendar year — cumulative from December of the prior year
B33: Component | C33: 2023 | D33: 2024 | E33: 2025 | F33: 2026 YTD
B34: Nivel General | C34: =IFERROR(INDEX('CPI Data'!$E:$E,MATCH("2023-12",'CPI Data'!$B:$B,0))/INDEX('CPI Data'!$E:$E,MATCH("2022-12",'CPI Data'!$B:$B,0))-1,"") | D34: =IFERROR(INDEX('CPI Data'!$E:$E,MATCH("2024-12",'CPI Data'!$B:$B,0))/INDEX('CPI Data'!$E:$E,MATCH("2023-12",'CPI Data'!$B:$B,0))-1,"") | E34: =IFERROR(INDEX('CPI Data'!$E:$E,MATCH("2025-12",'CPI Data'!$B:$B,0))/INDEX('CPI Data'!$E:$E,MATCH("2024-12",'CPI Data'!$B:$B,0))-1,"") | F34: =IFERROR(INDEX('CPI Data'!$E:$E,MATCH("2026-08",'CPI Data'!$B:$B,0))/INDEX('CPI Data'!$E:$E,MATCH("2025-12",'CPI Data'!$B:$B,0))-1,"")
B35: Nucleo | C35: =IFERROR(INDEX('CPI Data'!$F:$F,MATCH("2023-12",'CPI Data'!$B:$B,0))/INDEX('CPI Data'!$F:$F,MATCH("2022-12",'CPI Data'!$B:$B,0))-1,"") | D35: =IFERROR(INDEX('CPI Data'!$F:$F,MATCH("2024-12",'CPI Data'!$B:$B,0))/INDEX('CPI Data'!$F:$F,MATCH("2023-12",'CPI Data'!$B:$B,0))-1,"") | E35: =IFERROR(INDEX('CPI Data'!$F:$F,MATCH("2025-12",'CPI Data'!$B:$B,0))/INDEX('CPI Data'!$F:$F,MATCH("2024-12",'CPI Data'!$B:$B,0))-1,"") | F35: =IFERROR(INDEX('CPI Data'!$F:$F,MATCH("2026-08",'CPI Data'!$B:$B,0))/INDEX('CPI Data'!$F:$F,MATCH("2025-12",'CPI Data'!$B:$B,0))-1,"")
B36: Regulados | C36: =IFERROR(INDEX('CPI Data'!$G:$G,MATCH("2023-12",'CPI Data'!$B:$B,0))/INDEX('CPI Data'!$G:$G,MATCH("2022-12",'CPI Data'!$B:$B,0))-1,"") | D36: =IFERROR(INDEX('CPI Data'!$G:$G,MATCH("2024-12",'CPI Data'!$B:$B,0))/INDEX('CPI Data'!$G:$G,MATCH("2023-12",'CPI Data'!$B:$B,0))-1,"") | E36: =IFERROR(INDEX('CPI Data'!$G:$G,MATCH("2025-12",'CPI Data'!$B:$B,0))/INDEX('CPI Data'!$G:$G,MATCH("2024-12",'CPI Data'!$B:$B,0))-1,"") | F36: =IFERROR(INDEX('CPI Data'!$G:$G,MATCH("2026-08",'CPI Data'!$B:$B,0))/INDEX('CPI Data'!$G:$G,MATCH("2025-12",'CPI Data'!$B:$B,0))-1,"")
B37: Estacionales | C37: =IFERROR(INDEX('CPI Data'!$H:$H,MATCH("2023-12",'CPI Data'!$B:$B,0))/INDEX('CPI Data'!$H:$H,MATCH("2022-12",'CPI Data'!$B:$B,0))-1,"") | D37: =IFERROR(INDEX('CPI Data'!$H:$H,MATCH("2024-12",'CPI Data'!$B:$B,0))/INDEX('CPI Data'!$H:$H,MATCH("2023-12",'CPI Data'!$B:$B,0))-1,"") | E37: =IFERROR(INDEX('CPI Data'!$H:$H,MATCH("2025-12",'CPI Data'!$B:$B,0))/INDEX('CPI Data'!$H:$H,MATCH("2024-12",'CPI Data'!$B:$B,0))-1,"") | F37: =IFERROR(INDEX('CPI Data'!$H:$H,MATCH("2026-08",'CPI Data'!$B:$B,0))/INDEX('CPI Data'!$H:$H,MATCH("2025-12",'CPI Data'!$B:$B,0))-1,"")
B38: The 2026 bar covers only Jan-Aug, so it is NOT comparable with the full years beside it. Use block 2 for that.
B41: 2. Like-for-like — January to Aug of each year
B42: Component | C42: 2023 | D42: 2024 | E42: 2025 | F42: 2026
B43: Nivel General | C43: =IFERROR(INDEX('CPI Data'!$E:$E,MATCH("2023-08",'CPI Data'!$B:$B,0))/INDEX('CPI Data'!$E:$E,MATCH("2022-12",'CPI Data'!$B:$B,0))-1,"") | D43: =IFERROR(INDEX('CPI Data'!$E:$E,MATCH("2024-08",'CPI Data'!$B:$B,0))/INDEX('CPI Data'!$E:$E,MATCH("2023-12",'CPI Data'!$B:$B,0))-1,"") | E43: =IFERROR(INDEX('CPI Data'!$E:$E,MATCH("2025-08",'CPI Data'!$B:$B,0))/INDEX('CPI Data'!$E:$E,MATCH("2024-12",'CPI Data'!$B:$B,0))-1,"") | F43: =IFERROR(INDEX('CPI Data'!$E:$E,MATCH("2026-08",'CPI Data'!$B:$B,0))/INDEX('CPI Data'!$E:$E,MATCH("2025-12",'CPI Data'!$B:$B,0))-1,"")
B44: Nucleo | C44: =IFERROR(INDEX('CPI Data'!$F:$F,MATCH("2023-08",'CPI Data'!$B:$B,0))/INDEX('CPI Data'!$F:$F,MATCH("2022-12",'CPI Data'!$B:$B,0))-1,"") | D44: =IFERROR(INDEX('CPI Data'!$F:$F,MATCH("2024-08",'CPI Data'!$B:$B,0))/INDEX('CPI Data'!$F:$F,MATCH("2023-12",'CPI Data'!$B:$B,0))-1,"") | E44: =IFERROR(INDEX('CPI Data'!$F:$F,MATCH("2025-08",'CPI Data'!$B:$B,0))/INDEX('CPI Data'!$F:$F,MATCH("2024-12",'CPI Data'!$B:$B,0))-1,"") | F44: =IFERROR(INDEX('CPI Data'!$F:$F,MATCH("2026-08",'CPI Data'!$B:$B,0))/INDEX('CPI Data'!$F:$F,MATCH("2025-12",'CPI Data'!$B:$B,0))-1,"")
B45: Regulados | C45: =IFERROR(INDEX('CPI Data'!$G:$G,MATCH("2023-08",'CPI Data'!$B:$B,0))/INDEX('CPI Data'!$G:$G,MATCH("2022-12",'CPI Data'!$B:$B,0))-1,"") | D45: =IFERROR(INDEX('CPI Data'!$G:$G,MATCH("2024-08",'CPI Data'!$B:$B,0))/INDEX('CPI Data'!$G:$G,MATCH("2023-12",'CPI Data'!$B:$B,0))-1,"") | E45: =IFERROR(INDEX('CPI Data'!$G:$G,MATCH("2025-08",'CPI Data'!$B:$B,0))/INDEX('CPI Data'!$G:$G,MATCH("2024-12",'CPI Data'!$B:$B,0))-1,"") | F45: =IFERROR(INDEX('CPI Data'!$G:$G,MATCH("2026-08",'CPI Data'!$B:$B,0))/INDEX('CPI Data'!$G:$G,MATCH("2025-12",'CPI Data'!$B:$B,0))-1,"")
B46: Estacionales | C46: =IFERROR(INDEX('CPI Data'!$H:$H,MATCH("2023-08",'CPI Data'!$B:$B,0))/INDEX('CPI Data'!$H:$H,MATCH("2022-12",'CPI Data'!$B:$B,0))-1,"") | D46: =IFERROR(INDEX('CPI Data'!$H:$H,MATCH("2024-08",'CPI Data'!$B:$B,0))/INDEX('CPI Data'!$H:$H,MATCH("2023-12",'CPI Data'!$B:$B,0))-1,"") | E46: =IFERROR(INDEX('CPI Data'!$H:$H,MATCH("2025-08",'CPI Data'!$B:$B,0))/INDEX('CPI Data'!$H:$H,MATCH("2024-12",'CPI Data'!$B:$B,0))-1,"") | F46: =IFERROR(INDEX('CPI Data'!$H:$H,MATCH("2026-08",'CPI Data'!$B:$B,0))/INDEX('CPI Data'!$H:$H,MATCH("2025-12",'CPI Data'!$B:$B,0))-1,"")
B47: The same 8-month window in every year, so these bars ARE directly comparable. This is the scoreboard.
B52: 3. The relative price shift — regulated against core, Dec-2023 = 100
B53: Date | C53: Regulados index | D53: Nucleo index | E53: Regulados relative to core | F53: Read
B54: 2024-12 | C54: =INDEX('CPI Data'!$G:$G,MATCH("2024-12",'CPI Data'!$B:$B,0))/INDEX('CPI Data'!$G:$G,MATCH("2023-12",'CPI Data'!$B:$B,0))*100 | D54: =INDEX('CPI Data'!$F:$F,MATCH("2024-12",'CPI Data'!$B:$B,0))/INDEX('CPI Data'!$F:$F,MATCH("2023-12",'CPI Data'!$B:$B,0))*100 | E54: =C54/D54-1 | F54: End of the year that did the bulk of the correction
B55: 2025-12 | C55: =INDEX('CPI Data'!$G:$G,MATCH("2025-12",'CPI Data'!$B:$B,0))/INDEX('CPI Data'!$G:$G,MATCH("2023-12",'CPI Data'!$B:$B,0))*100 | D55: =INDEX('CPI Data'!$F:$F,MATCH("2025-12",'CPI Data'!$B:$B,0))/INDEX('CPI Data'!$F:$F,MATCH("2023-12",'CPI Data'!$B:$B,0))*100 | E55: =C55/D55-1 | F55: The gap widened only 1.3pp over the whole of 2025
B56: 2026-08 | C56: =INDEX('CPI Data'!$G:$G,MATCH("2026-08",'CPI Data'!$B:$B,0))/INDEX('CPI Data'!$G:$G,MATCH("2023-12",'CPI Data'!$B:$B,0))*100 | D56: =INDEX('CPI Data'!$F:$F,MATCH("2026-08",'CPI Data'!$B:$B,0))/INDEX('CPI Data'!$F:$F,MATCH("2023-12",'CPI Data'!$B:$B,0))*100 | E56: =C56/D56-1 | F56: 2026 is the year it is widening fastest — and it is not finished
B58: Regulated prices have risen 61% RELATIVE to core since Dec-2023. Two-thirds of that happened in 2024, but the gap has widened a further 11pp since. Energy subsidies went 1.5% of GDP (2023) to 0.6% (2025), with the 2027 Budget planning 0.53% including transport — so the correction has further to run and will keep headline above core into the election year.

Sheet Inheritance
B2: The inheritance — how the deficit was financed with central bank money, 2019-2023
B3: Blue = published. Black = calculated. Series that could not be sourced are left empty, not estimated.
B5: 1. Direct monetary financing of the Treasury
B6: The 2012 reform of the Carta Organica (Ley 26.739) is what made this legal. Art.20 caps advances at 12% of the monetary base plus 10% of the prior year's cash resources; Art.38 governs profit transfers and carries NO quantitative ceiling at all. Accounting profits generated by revaluing FX assets after a devaluation become transferable pesos. That is the channel that does the heavy lifting in 2020.
B7: Series | C7: 2019 | D7: 2020 | E7: 2021 | F7: 2022 | G7: 2023 | H7: Source / note
B8: Adelantos transitorios + transferencia de utilidades (ARS mn) | C8: 430945 | D8: 2066163 | E8: 1379099 | F8: 1013351 | G8: 1698000 | H8: BCRA, Informe Monetario Mensual, December editions — factores de variacion de la base monetaria. Published as a single combined line; the two channels cannot be separated.
B9: Direct financing, % of GDP | C9: n/s | D9: 7.4 | E9: 3.7 | F9: n/s | G9: 0.7 | H9: MIXED DEFINITION. 2020-21 IMF CR 25/3 (includes transfers of valuation gains on FX-denominated non-tradable Treasury securities); 2023 BCRA (adelantos + utilidades only). NEVER plot as one line.
B10: Indirect emission linked to the Treasury, % of GDP | C10: n/s | D10: n/s | E10: n/s | F10: n/s | G10: 2.7 | H10: BCRA Informe al Congreso 2023 p.15. Secondary-market purchases of Treasury paper plus exercised puts — the BCRA's own words: 'dos fuentes indirectas de emision monetaria derivada del desorden fiscal'.
B11: IMF measure: secondary-market purchases, % of GDP | C11: n/s | D11: n/s | E11: n/s | F11: 2.3 | G11: 4.2 | H11: IMF CR 25/3 EPE para.31. NOT reconcilable with the BCRA line above — different coverage (gross vs net, and whether sterilisation and exercised puts are netted). Present both, attributed; do not blend.
B12: Total Treasury-linked emission, % of GDP | C12: =IF(AND(ISNUMBER(C9),ISNUMBER(C10)),C9+C10,"") | D12: =IF(AND(ISNUMBER(D9),ISNUMBER(D10)),D9+D10,"") | E12: =IF(AND(ISNUMBER(E9),ISNUMBER(E10)),E9+E10,"") | F12: =IF(AND(ISNUMBER(F9),ISNUMBER(F10)),F9+F10,"") | G12: =IF(AND(ISNUMBER(G9),ISNUMBER(G10)),G9+G10,"") | H12: Calculated: direct plus the BCRA's own indirect measure. Only 2023 is complete.
B15: 2. The BCRA balance sheet — the remunerated-liability snowball
B17: Series | C17: 2019 | D17: 2020 | E17: 2021 | F17: 2022 | G17: 2023 | H17: Source / note
B18: LELIQ stock, end-December (ARS mn) | C18: 738850 | D18: 1653328 | E18: 2140026 | F18: 6831822 | G18: 3660794 | H18: BCRA IMM, December editions.
B19: Pases pasivos, end-December (ARS mn) | C19: 432590 | D19: 1040553 | E19: 2367419 | F19: 2004090 | G19: 20468572 | H19: BCRA IMM. The 2023 collapse in LELIQ against the pases explosion is a MATURITY SHORTENING — 28-day paper migrating to overnight. A liquidity-risk deterioration, not a reduction.
B20: Total remunerated liabilities (ARS mn) | C20: =IF(AND(ISNUMBER(C18),ISNUMBER(C19)),C18+C19,"") | D20: =IF(AND(ISNUMBER(D18),ISNUMBER(D19)),D18+D19,"") | E20: =IF(AND(ISNUMBER(E18),ISNUMBER(E19)),E18+E19,"") | F20: =IF(AND(ISNUMBER(F18),ISNUMBER(F19)),F18+F19,"") | G20: =IF(AND(ISNUMBER(G18),ISNUMBER(G19)),G18+G19,"") | H20: Calculated.
B21: Base monetaria, December average (ARS mn) | C21: 1734073 | D21: 2425025 | E21: 3394480 | F21: 4781929 | G21: 9209583 | H21: BCRA IMM.
B22: Remunerated liabilities / base money (x) | C22: =IF(AND(ISNUMBER(C20),ISNUMBER(C21)),C20/C21,"") | D22: =IF(AND(ISNUMBER(D20),ISNUMBER(D21)),D20/D21,"") | E22: =IF(AND(ISNUMBER(E20),ISNUMBER(E21)),E20/E21,"") | F22: =IF(AND(ISNUMBER(F20),ISNUMBER(F21)),F20/F21,"") | G22: =IF(AND(ISNUMBER(G20),ISNUMBER(G21)),G20/G21,"") | H22: Calculated from two published BCRA series. Peak was November 2023 at 3.18x — see below.
B23: Base money, % of GDP | C23: n/s | D23: 7.4 | E23: 6.2 | F23: 4.4 | G23: 3.1 | H23: BCRA IMM. The denominator problem: the same nominal overhang sits against a collapsing real money base.
B24: Base money, y/y nominal (%) | C24: 29.7 | D24: 39.8 | E24: 40 | F24: 40.9 | G24: 92.6 | H24: BCRA IMM.
B25: Base money, y/y real s.a. (%) | C25: n/s | D25: n/s | E25: -9.3 | F25: -25.6 | G25: -42 | H25: BCRA IMM. Dec-2023 real base money stood at its December-2001 level.
B26: M2 total, y/y nominal (%) | C26: 34.9 | D26: 84.2 | E26: 54.3 | F26: 66.6 | G26: 142.3 | H26: BCRA IMM.
B27: M3 total, y/y nominal (%) | C27: 40.7 | D27: 83.4 | E27: 54.9 | F27: 82.6 | G27: 112.4 | H27: BCRA IMM.
B28: Quasi-fiscal deficit, % of GDP | C28: n/s | D28: n/s | E28: 3.3 | F28: 5.2 | G28: 10.5 | H28: IMF CR 25/3 EPE para.31 p.33.
B29: Gross international reserves, end-Dec (USD mn) | C29: 44353 | D29: 39410 | E29: 39582 | F29: 44597 | G29: 23073 | H29: BCRA IMM, December editions.
B32: 3. The endogenous dynamic, the stocks at handover, and the repressed inflation
B33: Marker | C33: Value | D33: Unit | E33: Source and why it matters
B34: Peak remunerated liabilities, Nov-2023 | C34: 24758559 | D34: ARS mn | E34: BCRA IMM Nov-2023. The Informe al Congreso p.17 mistypes this by a factor of ten — cite the IMM.
B35: Base money, Nov-2023 | C35: 7797578 | D35: ARS mn | E35: BCRA IMM Nov-2023.
B36: PEAK remunerated / base money | C36: =C34/C35 | D36: x | E36: Calculated. The highest the ratio ever reached.
B37: Remunerated liabilities, % of GDP, Dec-2023 | C37: 9.5 | D37: % | E37: BCRA Informe al Congreso 2023 p.17.
B38: Interest on remunerated liabilities vs base money growth | C38: 3.5 | D38: x | E38: BCRA Informe al Congreso 2023 p.17, verbatim: interest paid was equivalent to three and a half times the growth of the monetary base. Interest is paid in new pesos which must then be reabsorbed by issuing more remunerated liabilities — the snowball is self-feeding.
B39: BCRA net credit to the government, end-2023 | C39: 24.6 | D39: % GDP | E39: IMF CR 25/3 EPE para.31. The cleanest single summary of cumulative fiscal dominance.
B40: Net international reserves, 11-Dec-2023 | C40: -11200 | D40: USD mn | E40: BCRA Informe al Congreso 2023 p.1. Negative since May 2023.
B41: Letras intransferibles, face value, 23-Dec-2023 | C41: 67361 | D41: USD mn | E41: BCRA balance sheet, read by Romano Group via Infobae 5-Jan-2024. Booked at valor tecnico, not market, under Art.62 of Ley 27.541.
B42: Letras intransferibles, estimated recoverable value | C42: 23000 | D42: USD mn | E42: PRIVATE ESTIMATE (Libertad y Progreso). The instrument is non-tradable so no true market price exists — this is a modelled recoverable value by construction. Direction robust, precision not.
B43: Implied writedown on the letras | C43: =1-C42/C41 | D43: % | E43: Calculated from the two rows above. Treat as indicative.
B44: Registered import arrears, 13-Dec-2023 | C44: 42600 | D44: USD mn | E44: BCRA registry, cut-off two days after the handover, via Infobae 25-Mar-2024. A deferred FX claim that had to be resolved before the cepo could go — hence BOPREAL.
B45: Alternative arrears estimate | C45: 57800 | D45: USD mn | E45: Fundacion Capital — a balance-of-payments residual, a different definition from the BCRA registry. Footnote, do not merge.
B47: 4. The FX gap — where Argentina DID reach 1989 levels
B48: Date | C48: Official | D48: Parallel | E48: Gap | F48: Note
B49: 2023-10-23 | C49: 349.95 | D49: 1100 | E49: =D49/C49-1 | F49: peak; widest since 31-Mar-1989 (214.8%)
B50: 2023-12-29 | C50: 808.45 | D50: 1025 | E50: =D50/C50-1 | F50: post-devaluation
B51: 2026-09-22 | C51: 1514 | D51: 1555 | E51: =D51/C51-1 | F51: cepo unwound
B53: The October 2023 gap of 214% was the widest since 31 March 1989, when it reached 214.8%. Unlike the CPI, the FX gap DID reach hyperinflation-era levels. By 22-Sep-2026 the gap is 2.7% — effectively closed. That is the single cleanest evidence that the cepo unwind worked.
B55: 5. Energy subsidies — the repressed price level, and its unwinding
B56: Year | C56: 2019 | D56: 2020 | E56: 2021 | F56: 2022 | G56: 2023 | H56: 2024 | I56: 2025
B57: % of GDP | C57: 1 | D57: 1.8 | E57: 2.3 | F57: 2 | G57: 1.5 | H57: 1.1 | I57: 0.6
B58: Source | C58: Hacienda via Infobae | D58: Hacienda via Infobae | E58: Hacienda via Infobae | F58: CIPPEC | G58: Hacienda via Infobae | H58: IMF review via El Cronista | I58: IMF review via El Cronista
B60: TWO SOURCES SPLICED, flagged: 2019-21 and 2023 are Hacienda estimates, 2022 is CIPPEC, 2024-25 are from the IMF review. Coverage differs. At handover two of every three households paid 9% or less of electricity generation cost — implying roughly a fifteen-fold increase to reach full cost recovery. That, not the CPI, is the measure of how much inflation was sitting in the pipeline.
B61: No single number for 'inflation in the pipeline' is offered here, and the note should not offer one either: a credible estimate needs the CPI weight of regulated items, the required adjustment per item, the pass-through coefficient and the FX pass-through on the arrears stock. Only the second is sourced. The five figures above make the argument without a fabricated aggregate.

Sheet Hyperinflation
B2: How close was Argentina to hyperinflation?
B3: Answer: not close on prices, dangerously close on the balance sheet. Every figure below is calculated from the blue inputs.
B5: 1. The benchmark
B6: 50 | C6: Cagan's threshold. Hyperinflation begins in the month inflation first exceeds 50% per month. Source: Cagan via Fischer, Sahay & Vegh, 'Modern Hyper- and High Inflations', NBER WP 8930, p.2.
B8: 2. Where Argentina actually was
B9: Month | C9: m/m | D9: Annualised (compounded 12x) | E9: Doubling time (months) | F9: % of the Cagan threshold
B10: Dec-2023 (handover) | C10: ='CPI Data'!I66 | D10: =(1+C10)^12-1 | E10: =LN(2)/LN(1+C10) | F10: =C10/($B$6/100)
B11: Nov-2023 | C11: ='CPI Data'!I65 | D11: =(1+C11)^12-1 | E11: =LN(2)/LN(1+C11) | F11: =C11/($B$6/100)
B12: Oct-2023 | C12: ='CPI Data'!I64 | D12: =(1+C12)^12-1 | E12: =LN(2)/LN(1+C12) | F12: =C12/($B$6/100)
B13: Peak 3m annualised to Dec-2023 | C13: =(1+'CPI Data'!P66)^(1/12)-1 | D13: =(1+C13)^12-1 | E13: =LN(2)/LN(1+C13) | F13: =C13/($B$6/100)
B14: Cagan threshold | C14: =$B$6/100 | D14: =(1+C14)^12-1 | E14: =LN(2)/LN(1+C14) | F14: =C14/($B$6/100)
B15: Latest print (2026-08) | C15: ='CPI Data'!I98 | D15: =(1+C15)^12-1 | E15: =LN(2)/LN(1+C15) | F15: =C15/($B$6/100)
B17: Read the December-2023 row across. 25.5% m/m is 51% of the Cagan threshold. It annualises to about 1,427% against the 12,875% the threshold implies — roughly one ninth. Prices doubled every 3.0 months, against 1.7 months at the threshold.
B18: Milei's inaugural warning of 15,000% a year sits ABOVE the Cagan threshold. It was explicitly a FORECAST of hyperinflation, not a description of one. Caputo's 'si seguimos asi, habra hiperinflacion' on 12-Dec-2023 is likewise conditional. The IMF's ex-post evaluation does not use the word at all; it calls late 2023 a full-blown economic crisis. State this plainly in the note — it is the honest finding and it is more persuasive than the rhetoric it corrects.
B20: 3. Comparators — the real hyperinflations
B21: Episode | C21: Period | D21: Peak month | E21: Peak m/m | F21: Annualised | G21: Doubling time (months) | H21: Argentina Dec-2023 as a multiple
B22: Argentina | C22: May 1989 - Mar 1990 | D22: Jul 1989 | E22: 1.97 | F22: =(1+E22)^12-1 | G22: =LN(2)/LN(1+E22) | H22: =$C$10/E22
B23: Bolivia | C23: Apr 1984 - Sep 1985 | D23: Feb 1985 | E23: 1.83 | F23: =(1+E23)^12-1 | G23: =LN(2)/LN(1+E23) | H23: =$C$10/E23
B24: Peru | C24: Jul 1990 - Aug 1990 | D24: Aug 1990 | E24: 3.97 | F24: =(1+E24)^12-1 | G24: =LN(2)/LN(1+E24) | H24: =$C$10/E24
B25: Peru (earlier) | C25: Sep 1988 | D25: Sep 1988 | E25: 1.14 | F25: =(1+E25)^12-1 | G25: =LN(2)/LN(1+E25) | H25: =$C$10/E25
B26: Source: Hanke & Krus, 'The Hyperinflation Table', Cato Institute. Venezuela's 2016-19 episode is absent from the version retrieved and is NOT filled in here. The 1989 Argentine peak of 197% m/m is 7.7 times the December-2023 print: Argentina in 2023 was not in the same regime as Argentina in 1989.
B28: 4. Where the risk actually sat — the balance-sheet markers
B29: Marker | C29: Value at handover | D29: What it means
B30: Base money / GDP | C30: =Inheritance!G28 | D30: Down from 7.4% in 2020. Real base money at its December-2001 level.
B31: Remunerated liabilities / base money | C31: =Inheritance!G26 | D31: Peak 3.18x in November. The overhang: if holders convert that stock into transactional money against a real money demand at 2001 lows, the base multiplies several-fold.
B32: Quasi-fiscal deficit | C32: =Inheritance!G33 | D32: From 3.3% in 2021. Triple what the IMF programme's baseline envisaged.
B33: BCRA net credit to government | C33: =Inheritance!$C$39 | D33: The cumulative stock measure of fiscal dominance.
B34: Net international reserves | C34: =Inheritance!$C$40 | D34: Negative since May 2023.
B35: Interest vs base money growth | C35: =Inheritance!$C$38 | D35: The snowball is self-feeding: interest is paid in new pesos that must be reabsorbed by issuing more remunerated liabilities.
B36: FX gap, peak | C36: =Inheritance!$E$49 | D36: Widest since 31 March 1989.
B38: This is the argument. On prices Argentina was far from Cagan. On the balance sheet it was in the danger zone, and the channel by which 25% monthly could have become 50% monthly was the monetary overhang, not the observed rate. Frame it as a conditional risk, not a realised outcome.

Sheet Real Rates
B2: Real interest rates — ex-post and ex-ante
B3: TEM = (1+TNA/365)^30-1, daily compounding. Real = (1+TEM)/(1+inflation)-1. Both calculated in-sheet.
B5: There is NO continuous policy rate for Dec-2023 to Sep-2026. The instrument was abolished.
B6: Regime I: BCRA policy rate (pases pasivos), administered, Dec-2023 to 9-Jun-2025. Regime II: Jul-2025, LEFI eliminated 10-Jul-2025, no anchor, rates market-determined and violently so (1-day cauciones ranged 26% to 150% intraday on 20-Aug-2025). Regime III: monetary-aggregates targeting from Jul-2025, TAMAR the de facto reference. Jul/Aug/Sep-2025 are LEFT BLANK BY DESIGN — an instrument-transition artefact, not monetary policy. Do not interpolate.
B9: Month | C9: Regime | D9: Nominal % TNA | E9: TEM (derived) | F9: Realised CPI m/m | G9: REAL EX-POST m/m | H9: Real ex-post annualised | I9: REM expected CPI m/m | J9: REAL EX-ANTE m/m | K9: Real ex-ante annualised | L9: Forecast error (pp)
B10: 2023-12 | C10: policy | D10: 100 | E10: =IF(D10="","",(1+D10/100/365)^30-1) | F10: =IFERROR(INDEX('CPI Data'!$I:$I,MATCH($B10,'CPI Data'!$B:$B,0)),"") | G10: =IF(OR(E10="",F10=""),"",(1+E10)/(1+F10)-1) | H10: =IF(G10="","",(1+G10)^12-1) | J10: =IF(OR(E10="",I10=""),"",(1+E10)/(1+I10)-1) | K10: =IF(J10="","",(1+J10)^12-1) | L10: =IF(OR(F10="",I10=""),"",(F10-I10)*100)
B11: 2024-01 | C11: policy | D11: 100 | E11: =IF(D11="","",(1+D11/100/365)^30-1) | F11: =IFERROR(INDEX('CPI Data'!$I:$I,MATCH($B11,'CPI Data'!$B:$B,0)),"") | G11: =IF(OR(E11="",F11=""),"",(1+E11)/(1+F11)-1) | H11: =IF(G11="","",(1+G11)^12-1) | J11: =IF(OR(E11="",I11=""),"",(1+E11)/(1+I11)-1) | K11: =IF(J11="","",(1+J11)^12-1) | L11: =IF(OR(F11="",I11=""),"",(F11-I11)*100)
B12: 2024-02 | C12: policy | D12: 100 | E12: =IF(D12="","",(1+D12/100/365)^30-1) | F12: =IFERROR(INDEX('CPI Data'!$I:$I,MATCH($B12,'CPI Data'!$B:$B,0)),"") | G12: =IF(OR(E12="",F12=""),"",(1+E12)/(1+F12)-1) | H12: =IF(G12="","",(1+G12)^12-1) | J12: =IF(OR(E12="",I12=""),"",(1+E12)/(1+I12)-1) | K12: =IF(J12="","",(1+J12)^12-1) | L12: =IF(OR(F12="",I12=""),"",(F12-I12)*100)
B13: 2024-03 | C13: policy | D13: 80 | E13: =IF(D13="","",(1+D13/100/365)^30-1) | F13: =IFERROR(INDEX('CPI Data'!$I:$I,MATCH($B13,'CPI Data'!$B:$B,0)),"") | G13: =IF(OR(E13="",F13=""),"",(1+E13)/(1+F13)-1) | H13: =IF(G13="","",(1+G13)^12-1) | J13: =IF(OR(E13="",I13=""),"",(1+E13)/(1+I13)-1) | K13: =IF(J13="","",(1+J13)^12-1) | L13: =IF(OR(F13="",I13=""),"",(F13-I13)*100)
B14: 2024-04 | C14: policy | D14: 60 | E14: =IF(D14="","",(1+D14/100/365)^30-1) | F14: =IFERROR(INDEX('CPI Data'!$I:$I,MATCH($B14,'CPI Data'!$B:$B,0)),"") | G14: =IF(OR(E14="",F14=""),"",(1+E14)/(1+F14)-1) | H14: =IF(G14="","",(1+G14)^12-1) | J14: =IF(OR(E14="",I14=""),"",(1+E14)/(1+I14)-1) | K14: =IF(J14="","",(1+J14)^12-1) | L14: =IF(OR(F14="",I14=""),"",(F14-I14)*100)
B15: 2024-05 | C15: policy | D15: 40 | E15: =IF(D15="","",(1+D15/100/365)^30-1) | F15: =IFERROR(INDEX('CPI Data'!$I:$I,MATCH($B15,'CPI Data'!$B:$B,0)),"") | G15: =IF(OR(E15="",F15=""),"",(1+E15)/(1+F15)-1) | H15: =IF(G15="","",(1+G15)^12-1) | J15: =IF(OR(E15="",I15=""),"",(1+E15)/(1+I15)-1) | K15: =IF(J15="","",(1+J15)^12-1) | L15: =IF(OR(F15="",I15=""),"",(F15-I15)*100)
B16: 2024-06 | C16: policy | D16: 40 | E16: =IF(D16="","",(1+D16/100/365)^30-1) | F16: =IFERROR(INDEX('CPI Data'!$I:$I,MATCH($B16,'CPI Data'!$B:$B,0)),"") | G16: =IF(OR(E16="",F16=""),"",(1+E16)/(1+F16)-1) | H16: =IF(G16="","",(1+G16)^12-1) | J16: =IF(OR(E16="",I16=""),"",(1+E16)/(1+I16)-1) | K16: =IF(J16="","",(1+J16)^12-1) | L16: =IF(OR(F16="",I16=""),"",(F16-I16)*100)
B17: 2024-07 | C17: policy | D17: 40 | E17: =IF(D17="","",(1+D17/100/365)^30-1) | F17: =IFERROR(INDEX('CPI Data'!$I:$I,MATCH($B17,'CPI Data'!$B:$B,0)),"") | G17: =IF(OR(E17="",F17=""),"",(1+E17)/(1+F17)-1) | H17: =IF(G17="","",(1+G17)^12-1) | J17: =IF(OR(E17="",I17=""),"",(1+E17)/(1+I17)-1) | K17: =IF(J17="","",(1+J17)^12-1) | L17: =IF(OR(F17="",I17=""),"",(F17-I17)*100)
B18: 2024-08 | C18: policy | D18: 40 | E18: =IF(D18="","",(1+D18/100/365)^30-1) | F18: =IFERROR(INDEX('CPI Data'!$I:$I,MATCH($B18,'CPI Data'!$B:$B,0)),"") | G18: =IF(OR(E18="",F18=""),"",(1+E18)/(1+F18)-1) | H18: =IF(G18="","",(1+G18)^12-1) | J18: =IF(OR(E18="",I18=""),"",(1+E18)/(1+I18)-1) | K18: =IF(J18="","",(1+J18)^12-1) | L18: =IF(OR(F18="",I18=""),"",(F18-I18)*100)
B19: 2024-09 | C19: policy | D19: 40 | E19: =IF(D19="","",(1+D19/100/365)^30-1) | F19: =IFERROR(INDEX('CPI Data'!$I:$I,MATCH($B19,'CPI Data'!$B:$B,0)),"") | G19: =IF(OR(E19="",F19=""),"",(1+E19)/(1+F19)-1) | H19: =IF(G19="","",(1+G19)^12-1) | J19: =IF(OR(E19="",I19=""),"",(1+E19)/(1+I19)-1) | K19: =IF(J19="","",(1+J19)^12-1) | L19: =IF(OR(F19="",I19=""),"",(F19-I19)*100)
B20: 2024-10 | C20: policy | D20: 35 | E20: =IF(D20="","",(1+D20/100/365)^30-1) | F20: =IFERROR(INDEX('CPI Data'!$I:$I,MATCH($B20,'CPI Data'!$B:$B,0)),"") | G20: =IF(OR(E20="",F20=""),"",(1+E20)/(1+F20)-1) | H20: =IF(G20="","",(1+G20)^12-1) | J20: =IF(OR(E20="",I20=""),"",(1+E20)/(1+I20)-1) | K20: =IF(J20="","",(1+J20)^12-1) | L20: =IF(OR(F20="",I20=""),"",(F20-I20)*100)
B21: 2024-11 | C21: policy | D21: 35 | E21: =IF(D21="","",(1+D21/100/365)^30-1) | F21: =IFERROR(INDEX('CPI Data'!$I:$I,MATCH($B21,'CPI Data'!$B:$B,0)),"") | G21: =IF(OR(E21="",F21=""),"",(1+E21)/(1+F21)-1) | H21: =IF(G21="","",(1+G21)^12-1) | J21: =IF(OR(E21="",I21=""),"",(1+E21)/(1+I21)-1) | K21: =IF(J21="","",(1+J21)^12-1) | L21: =IF(OR(F21="",I21=""),"",(F21-I21)*100)
... B28: 2025-06 | C28: policy | D28: 29 | E28: =IF(D28="","",(1+D28/100/365)^30-1) | F28: =IFERROR(INDEX('CPI Data'!$I:$I,MATCH($B28,'CPI Data'!$B:$B,0)),"") | G28: =IF(OR(E28="",F28=""),"",(1+E28)/(1+F28)-1) | H28: =IF(G28="","",(1+G28)^12-1) | J28: =IF(OR(E28="",I28=""),"",(1+E28)/(1+I28)-1) | K28: =IF(J28="","",(1+J28)^12-1) | L28: =IF(OR(F28="",I28=""),"",(F28-I28)*100)
B29: 2025-07 | C29: LEFI transition | E29: =IF(D29="","",(1+D29/100/365)^30-1) | F29: =IFERROR(INDEX('CPI Data'!$I:$I,MATCH($B29,'CPI Data'!$B:$B,0)),"") | G29: =IF(OR(E29="",F29=""),"",(1+E29)/(1+F29)-1) | H29: =IF(G29="","",(1+G29)^12-1) | J29: =IF(OR(E29="",I29=""),"",(1+E29)/(1+I29)-1) | K29: =IF(J29="","",(1+J29)^12-1) | L29: =IF(OR(F29="",I29=""),"",(F29-I29)*100)
B30: 2025-08 | C30: LEFI transition | E30: =IF(D30="","",(1+D30/100/365)^30-1) | F30: =IFERROR(INDEX('CPI Data'!$I:$I,MATCH($B30,'CPI Data'!$B:$B,0)),"") | G30: =IF(OR(E30="",F30=""),"",(1+E30)/(1+F30)-1) | H30: =IF(G30="","",(1+G30)^12-1) | J30: =IF(OR(E30="",I30=""),"",(1+E30)/(1+I30)-1) | K30: =IF(J30="","",(1+J30)^12-1) | L30: =IF(OR(F30="",I30=""),"",(F30-I30)*100)
B31: 2025-09 | C31: LEFI transition | E31: =IF(D31="","",(1+D31/100/365)^30-1) | F31: =IFERROR(INDEX('CPI Data'!$I:$I,MATCH($B31,'CPI Data'!$B:$B,0)),"") | G31: =IF(OR(E31="",F31=""),"",(1+E31)/(1+F31)-1) | H31: =IF(G31="","",(1+G31)^12-1) | J31: =IF(OR(E31="",I31=""),"",(1+E31)/(1+I31)-1) | K31: =IF(J31="","",(1+J31)^12-1) | L31: =IF(OR(F31="",I31=""),"",(F31-I31)*100)
B32: 2025-10 | C32: TAMAR | D32: 38.31 | E32: =IF(D32="","",(1+D32/100/365)^30-1) | F32: =IFERROR(INDEX('CPI Data'!$I:$I,MATCH($B32,'CPI Data'!$B:$B,0)),"") | G32: =IF(OR(E32="",F32=""),"",(1+E32)/(1+F32)-1) | H32: =IF(G32="","",(1+G32)^12-1) | J32: =IF(OR(E32="",I32=""),"",(1+E32)/(1+I32)-1) | K32: =IF(J32="","",(1+J32)^12-1) | L32: =IF(OR(F32="",I32=""),"",(F32-I32)*100)
B33: 2025-11 | C33: TAMAR | D33: 31.44 | E33: =IF(D33="","",(1+D33/100/365)^30-1) | F33: =IFERROR(INDEX('CPI Data'!$I:$I,MATCH($B33,'CPI Data'!$B:$B,0)),"") | G33: =IF(OR(E33="",F33=""),"",(1+E33)/(1+F33)-1) | H33: =IF(G33="","",(1+G33)^12-1) | J33: =IF(OR(E33="",I33=""),"",(1+E33)/(1+I33)-1) | K33: =IF(J33="","",(1+J33)^12-1) | L33: =IF(OR(F33="",I33=""),"",(F33-I33)*100)
B34: 2025-12 | C34: TAMAR | D34: 28.88 | E34: =IF(D34="","",(1+D34/100/365)^30-1) | F34: =IFERROR(INDEX('CPI Data'!$I:$I,MATCH($B34,'CPI Data'!$B:$B,0)),"") | G34: =IF(OR(E34="",F34=""),"",(1+E34)/(1+F34)-1) | H34: =IF(G34="","",(1+G34)^12-1) | J34: =IF(OR(E34="",I34=""),"",(1+E34)/(1+I34)-1) | K34: =IF(J34="","",(1+J34)^12-1) | L34: =IF(OR(F34="",I34=""),"",(F34-I34)*100)
B35: 2026-01 | C35: TAMAR | D35: 32.94 | E35: =IF(D35="","",(1+D35/100/365)^30-1) | F35: =IFERROR(INDEX('CPI Data'!$I:$I,MATCH($B35,'CPI Data'!$B:$B,0)),"") | G35: =IF(OR(E35="",F35=""),"",(1+E35)/(1+F35)-1) | H35: =IF(G35="","",(1+G35)^12-1) | J35: =IF(OR(E35="",I35=""),"",(1+E35)/(1+I35)-1) | K35: =IF(J35="","",(1+J35)^12-1) | L35: =IF(OR(F35="",I35=""),"",(F35-I35)*100)
B36: 2026-02 | C36: TAMAR | D36: 31.06 | E36: =IF(D36="","",(1+D36/100/365)^30-1) | F36: =IFERROR(INDEX('CPI Data'!$I:$I,MATCH($B36,'CPI Data'!$B:$B,0)),"") | G36: =IF(OR(E36="",F36=""),"",(1+E36)/(1+F36)-1) | H36: =IF(G36="","",(1+G36)^12-1) | J36: =IF(OR(E36="",I36=""),"",(1+E36)/(1+I36)-1) | K36: =IF(J36="","",(1+J36)^12-1) | L36: =IF(OR(F36="",I36=""),"",(F36-I36)*100)
B37: 2026-03 | C37: TAMAR | D37: 26.31 | E37: =IF(D37="","",(1+D37/100/365)^30-1) | F37: =IFERROR(INDEX('CPI Data'!$I:$I,MATCH($B37,'CPI Data'!$B:$B,0)),"") | G37: =IF(OR(E37="",F37=""),"",(1+E37)/(1+F37)-1) | H37: =IF(G37="","",(1+G37)^12-1) | I37: 0.03 | J37: =IF(OR(E37="",I37=""),"",(1+E37)/(1+I37)-1) | K37: =IF(J37="","",(1+J37)^12-1) | L37: =IF(OR(F37="",I37=""),"",(F37-I37)*100)
B38: 2026-04 | C38: TAMAR | D38: 23.13 | E38: =IF(D38="","",(1+D38/100/365)^30-1) | F38: =IFERROR(INDEX('CPI Data'!$I:$I,MATCH($B38,'CPI Data'!$B:$B,0)),"") | G38: =IF(OR(E38="",F38=""),"",(1+E38)/(1+F38)-1) | H38: =IF(G38="","",(1+G38)^12-1) | I38: 0.026 | J38: =IF(OR(E38="",I38=""),"",(1+E38)/(1+I38)-1) | K38: =IF(J38="","",(1+J38)^12-1) | L38: =IF(OR(F38="",I38=""),"",(F38-I38)*100)
B39: 2026-05 | C39: TAMAR | D39: 22.25 | E39: =IF(D39="","",(1+D39/100/365)^30-1) | F39: =IFERROR(INDEX('CPI Data'!$I:$I,MATCH($B39,'CPI Data'!$B:$B,0)),"") | G39: =IF(OR(E39="",F39=""),"",(1+E39)/(1+F39)-1) | H39: =IF(G39="","",(1+G39)^12-1) | I39: 0.023 | J39: =IF(OR(E39="",I39=""),"",(1+E39)/(1+I39)-1) | K39: =IF(J39="","",(1+J39)^12-1) | L39: =IF(OR(F39="",I39=""),"",(F39-I39)*100)
B40: 2026-06 | C40: TAMAR | D40: 22.69 | E40: =IF(D40="","",(1+D40/100/365)^30-1) | F40: =IFERROR(INDEX('CPI Data'!$I:$I,MATCH($B40,'CPI Data'!$B:$B,0)),"") | G40: =IF(OR(E40="",F40=""),"",(1+E40)/(1+F40)-1) | H40: =IF(G40="","",(1+G40)^12-1) | I40: 0.02 | J40: =IF(OR(E40="",I40=""),"",(1+E40)/(1+I40)-1) | K40: =IF(J40="","",(1+J40)^12-1) | L40: =IF(OR(F40="",I40=""),"",(F40-I40)*100)
B41: 2026-07 | C41: TAMAR | D41: 23.31 | E41: =IF(D41="","",(1+D41/100/365)^30-1) | F41: =IFERROR(INDEX('CPI Data'!$I:$I,MATCH($B41,'CPI Data'!$B:$B,0)),"") | G41: =IF(OR(E41="",F41=""),"",(1+E41)/(1+F41)-1) | H41: =IF(G41="","",(1+G41)^12-1) | I41: 0.02 | J41: =IF(OR(E41="",I41=""),"",(1+E41)/(1+I41)-1) | K41: =IF(J41="","",(1+J41)^12-1) | L41: =IF(OR(F41="",I41=""),"",(F41-I41)*100)
B42: 2026-08 | C42: TAMAR | D42: 24.69 | E42: =IF(D42="","",(1+D42/100/365)^30-1) | F42: =IFERROR(INDEX('CPI Data'!$I:$I,MATCH($B42,'CPI Data'!$B:$B,0)),"") | G42: =IF(OR(E42="",F42=""),"",(1+E42)/(1+F42)-1) | H42: =IF(G42="","",(1+G42)^12-1) | I42: 0.018 | J42: =IF(OR(E42="",I42=""),"",(1+E42)/(1+I42)-1) | K42: =IF(J42="","",(1+J42)^12-1) | L42: =IF(OR(F42="",I42=""),"",(F42-I42)*100)
B43: 2026-09 | C43: TAMAR | D43: 23.44 | E43: =IF(D43="","",(1+D43/100/365)^30-1) | F43: =IFERROR(INDEX('CPI Data'!$I:$I,MATCH($B43,'CPI Data'!$B:$B,0)),"") | G43: =IF(OR(E43="",F43=""),"",(1+E43)/(1+F43)-1) | H43: =IF(G43="","",(1+G43)^12-1) | I43: 0.018 | J43: =IF(OR(E43="",I43=""),"",(1+E43)/(1+I43)-1) | K43: =IF(J43="","",(1+J43)^12-1) | L43: =IF(OR(F43="",I43=""),"",(F43-I43)*100)
B44: 2026-10 | E44: =IF(D44="","",(1+D44/100/365)^30-1) | F44: =IFERROR(INDEX('CPI Data'!$I:$I,MATCH($B44,'CPI Data'!$B:$B,0)),"") | G44: =IF(OR(E44="",F44=""),"",(1+E44)/(1+F44)-1) | H44: =IF(G44="","",(1+G44)^12-1) | I44: 0.017 | J44: =IF(OR(E44="",I44=""),"",(1+E44)/(1+I44)-1) | K44: =IF(J44="","",(1+J44)^12-1) | L44: =IF(OR(F44="",I44=""),"",(F44-I44)*100)
B45: 2026-11 | E45: =IF(D45="","",(1+D45/100/365)^30-1) | F45: =IFERROR(INDEX('CPI Data'!$I:$I,MATCH($B45,'CPI Data'!$B:$B,0)),"") | G45: =IF(OR(E45="",F45=""),"",(1+E45)/(1+F45)-1) | H45: =IF(G45="","",(1+G45)^12-1) | I45: 0.016 | J45: =IF(OR(E45="",I45=""),"",(1+E45)/(1+I45)-1) | K45: =IF(J45="","",(1+J45)^12-1) | L45: =IF(OR(F45="",I45=""),"",(F45-I45)*100)
B46: 2026-12 | E46: =IF(D46="","",(1+D46/100/365)^30-1) | F46: =IFERROR(INDEX('CPI Data'!$I:$I,MATCH($B46,'CPI Data'!$B:$B,0)),"") | G46: =IF(OR(E46="",F46=""),"",(1+E46)/(1+F46)-1) | H46: =IF(G46="","",(1+G46)^12-1) | I46: 0.018 | J46: =IF(OR(E46="",I46=""),"",(1+E46)/(1+I46)-1) | K46: =IF(J46="","",(1+J46)^12-1) | L46: =IF(OR(F46="",I46=""),"",(F46-I46)*100)
B48: The regime story, and the two crossovers
B49: 2024 — deliberate deep negative rates | D49: January 2024 real ex-post was minus 10.0% PER MONTH, minus 71.7% annualised: the most negative point in the series. The BCRA held 40% TNA from May to September 2024 while CPI ran 3.5-4.6% a month, keeping real rates negative for nine consecutive months by construction. Abolishing the minimum guaranteed plazo fijo rate on 12-Mar-2024 was the enabling act — it let deposit rates fall below inflation without the BCRA having to mandate it. This is how the LELIQ stock was liquefied: not repaid, inflated away.
B50: Crossover 1 — October 2024 | D50: Ex-post real turns positive at +0.22% a month. For historical scale: only 38 of the 271 months from January 2003 to July 2025 had positive real passive rates. Positive real rates are the Argentine anomaly, not the norm.
B51: The 2026 relapse — the live story | D51: Real rates went negative AGAIN from December 2025 and stayed negative for eight of the nine months to August 2026, with the trough at minus 1.16% a month in March 2026. The ex-ante column shows this was not a forecast error but intent: at minus 0.81% ex-ante in March, the BCRA was running negative real rates against its own survey's expectations.
B52: Crossover 2 — August 2026 | D52: Ex-post turns positive at +0.37% a month. But note HOW: the crossover came from CPI falling to 1.67%, not from the BCRA tightening. TAMAR in August was barely above its June trough.
B53: Ex-post against ex-ante | D53: The forecast-error column is the point. March 2026: ex-post minus 1.16% against ex-ante minus 0.81% — the realised real rate was MORE negative than intended. August 2026 is the mirror: the undershoot delivered a TIGHTER real rate than intended. Ex-post flatters policy when inflation is falling and indicts it when inflation is rising. Ex-ante is the better read on intent; both belong in the chart.
B55: GAP: the real ex-ante series begins in March 2026. Earlier rounds need the REM's next-month expected CPI, and the REM summary tables would not machine-read in any round attempted. TAMAR and BADLAR before October 2025 are likewise unsourced. Both are flagged on the Sources tab.

Sheet Expectations
B2: Expectations — the professionals, the households and the market
B3: The ordering for 2027 is government 18.0% < REM 20.0% < market ~24.6%. The government is the most optimistic forecaster of its own inflation.
B5: 1. REM drift — how the forecast has been revised, round by round
B6: Round | C6: Published | D6: Particip. | E6: Year A | F6: Dec/Dec A | G6: Top-10 A | H6: Year B | I6: Dec/Dec B | J6: FX ref | K6: ARS/USD | L6: Source
B7: 2023-12 | C7: 2024-01-11 | D7: 37 | E7: 2024 | F7: 2.13 | J7: Dec-24 | K7: 1700 | L7: PDF
B8: 2024-12 | C8: 2025-01-07 | D8: 42 | E8: 2025 | F8: 0.259 | G8: 0.224 | H8: 2026 | I8: 0.153 | J8: Dec-25 | K8: 1205 | L8: PDF
B9: 2025-06 | C9: 2025-07-04 | D9: 41 | J9: Dec-25 | K9: 1324 | L9: PDF
B10: 2025-10 | C10: 2025-11-07 | D10: 42 | J10: Dec-25 | K10: 1500 | L10: PDF
B11: 2025-12 | C11: 2026-01-07 | D11: 44 | E11: 2026 | F11: 0.289 | H11: 2027 | I11: 0.15 | J11: Dec-26 | K11: 1753 | L11: PDF - SUSPECT
B12: 2026-02 | C12: 2026-03-06 | E12: 2026 | F12: 0.261 | G12: 0.278 | L12: press
B13: 2026-03 | C13: 2026-04-09 | E13: 2026 | F13: 0.291 | J13: Dec-26 | K13: 1700 | L13: press
B14: 2026-04 | C14: 2026-05-07 | D14: 45 | J14: Dec-26 | K14: 1676 | L14: BCRA web
B15: 2026-07 | C15: 2026-08-06 | D15: 45 | E15: 2026 | F15: 0.298 | H15: 2027 | I15: 0.2 | J15: Dec-26 | K15: 1652 | L15: PDF + tracker
B16: 2026-08 | C16: 2026-09-04 | D16: 47 | E16: 2026 | F16: 0.3 | G16: 0.299 | H16: 2027 | J16: Dec-26 | K16: 1630 | L16: PDF + press
B18: The 2026 Dec/Dec forecast has been revised from 15.3% (Dec-2024 round) to 30.0% (Aug-2026 round) — roughly a DOUBLING in twenty months. The steepest leg is Jan to Apr 2026, which coincides exactly with the negative-real-rate episode and the 3.38% March print. Since April the drift has FLATTENED at about 30%: expectations have stabilised, they have not re-anchored lower.
B19: The mirror image runs the other way. Dec-2026 ARS/USD expectations have been revised DOWN from 1,753 to 1,630, about 7%, over the same period that inflation expectations were revised UP about 4pp. The consensus is underwriting MORE inflation and LESS depreciation — that is, continued real appreciation into an election year. That combination is the position to challenge.
B20: GAP: the 2027 median in the August-2026 round is not obtainable — not in the PDF's readable text and absent from all press coverage found. The July round's 20.0% is carried forward and labelled as such.
B22: 2. The 2027 forecaster ladder
B23: Forecaster | C23: 2027 Dec/Dec | D23: Basis and note
B24: Budget 2027 bill (tabled 15-Sep-2026) | C24: 0.18 | D24: Dec/Dec; 21.1% average; ARS 1,847.6/USD Dec-27
B25: BCRA REM, Jul-2026 round | C25: 0.2 | D25: Aug round's 2027 median not obtainable
B26: Market breakeven (derived) | C26: 0.246 | D26: annualised from 1.85%/m Nov-26 to May-27
B27: IMF Art.IV May-2026 | C27: 0.125 | D27: eop; now stale - IMF's 2026 figure of 25.0% already exceeded
B28: UBS base case (Forecast tab) | C28: =Forecast_Base27 | D28: Linked live from the Forecast tab. Between the Budget at 18.0% and the REM at 20.0% the base case has no contrarian content left; the edge, if there is one, is the bear tail.
B30: 3. The peso curve — what the market pays to disagree
B31: Ticker | C31: Maturity | D31: Days | E31: Price | F31: TEM | G31: TEA (recomputed) | H31: Implied annual
B32: S30S6L | C32: 2026-09-30 | D32: 1 | E32: 1.1747 | F32: 0.0179 | G32: =(1+F32)^12-1 | H32: =G32
B33: S16O6L | C33: 2026-10-16 | D33: 17 | E33: 1.0415 | F33: 0.0191 | G33: =(1+F33)^12-1 | H33: =G33
B34: TO26B | C34: 2026-10-19 | D34: 20 | E34: 1.064 | F34: 0.0191 | G34: =(1+F34)^12-1 | H34: =G34
B35: S30O6L | C35: 2026-10-30 | D35: 31 | E35: 1.328 | F35: 0.018 | G35: =(1+F35)^12-1 | H35: =G35
B36: S13N6L | C36: 2026-11-13 | D36: 45 | E36: 1.065 | F36: 0.0196 | G36: =(1+F36)^12-1 | H36: =G36
B37: S30N6L | C37: 2026-11-30 | D37: 62 | E37: 1.247 | F37: 0.0199 | G37: =(1+F37)^12-1 | H37: =G37
B38: T15E7B | C38: 2027-01-15 | D38: 108 | E38: 1.4965 | F38: 0.0207 | G38: =(1+F38)^12-1 | H38: =G38
B39: S29E7L | C39: 2027-01-29 | D39: 122 | E39: 1.0262 | F39: 0.021 | G39: =(1+F39)^12-1 | H39: =G39
B40: T30A7B | C40: 2027-04-30 | D40: 213 | E40: 1.347 | F40: 0.0221 | G40: =(1+F40)^12-1 | H40: =G40
B41: T31Y7B | C41: 2027-05-31 | D41: 244 | E41: 1.267 | F41: 0.0228 | G41: =(1+F41)^12-1 | H41: =G41
B42: T30J7B | C42: 2027-06-30 | D42: 274 | E42: 1.281 | F42: 0.0218 | G42: =(1+F42)^12-1 | H42: =G42
B43: Source: comparatasas.ar, 29-Sep-2026. TTD26B excluded — its quote implies minus 2.40% TEM, stale or mispriced. The curve slopes UP in TEM, from about 1.8-2.0% at the front to 2.21% (30-Apr-27) and 2.28% (31-May-27). THE STEEPEST POINT ON THE PESO CURVE IS THE MAY-2027 MATURITY — precisely the 3-to-6 month window before the vote. That slope IS the market's statement that disinflation stalls into the election year.
B45: 4. Breakevens — fixed-rate against CER
B46: Period | C46: REM expected m/m | D46: Market breakeven m/m | E46: Spread (bp) | F46: Breakeven annualised
B47: 2026-09 | C47: 0.018 | D47: 0.019 | E47: =(D47-C47)*10000 | F47: =(1+D47)^12-1
B48: 2026-10 | C48: 0.017 | D48: 0.019 | E48: =(D48-C48)*10000 | F48: =(1+D48)^12-1
B49: 2026-11 | C49: 0.016 | D49: 0.01825 | E49: =(D49-C49)*10000 | F49: =(1+D49)^12-1
B50: 2026-12 | C50: 0.018 | D50: 0.019 | E50: =(D50-C50)*10000 | F50: =(1+D50)^12-1
B51: Nov-26 to May-27 | D51: 0.0185 | F51: =(1+D51)^12-1 | G51: The longest-dated breakeven that could be sourced. It spans the pre-election window.
B53: The market prices inflation 10-25bp a month ABOVE the REM through year-end, and about 24.6% annualised over November 2026 to May 2027 — against a REM 2027 median of 20.0% and a Budget assumption of 18.0%. Investors also demand about 5% real to hold peso paper to May-2027 against roughly zero at the front end. That term premium, not the level, is the electoral risk priced in pesos.
B54: The dollar curve says the same thing more bluntly: on 30-Sep-2026 AO27, maturing before the election, yielded 4.4% while AO28, maturing after it, yielded 11.6% — a 720bp cliff across the election date.
B56: 5. Households — anchored far above the professionals
B57: Measure | C57: Value | D57: Note
B58: UTDT expected inflation, 12m ahead, Sep-2026 (mean) | C58: 0.298 | D58: Median 30.0%. Down 5.9pp from August — the largest single-month fall in the recent series, and the first sub-30 reading of the episode.
B59: UTDT expected inflation, 12m ahead, Aug-2026 | C59: 0.357
B60: UTDT expected inflation, 30 days ahead, Sep-2026 (mean) | C60: 0.0349 | D60: Median 3.00%. HOUSEHOLDS EXPECT 3.0% NEXT MONTH against a REM of 1.8% and an actual August print of 1.67% — a gap of about 120bp. Household expectations are anchored far above both the market's and the professionals'.
B61: Peak, January 2024 | C61: 2.3 | D61: Above 230%. The fall since is real; the level still is not anchored.
B63: Treat the UTDT level as ordinal, not cardinal — the 12-month mean now sits below the 30-day median annualised, which is internally inconsistent and normal for household surveys. GAP: the monthly UTDT history could not be retrieved; utdt.edu is blocked by the egress proxy.

Sheet Forecast
B2: Forecast — bull / base / bear monthly paths to December 2027
B3: Monthly paths are judgement inputs (blue). Every Dec/Dec figure is a formula. Benchmarked to the REM and the Budget. | M3: Scenario probabilities
M4: Bull | N4: 0.2
B5: Month | C5: Actual | D5: Bull | E5: Base | F5: Bear | G5: Prob-weighted | H5: Bull index | I5: Base index | J5: Bear index | K5: PW index | M5: Base | N5: 0.55
B6: 2025-01 | C6: =IFERROR(IF(INDEX('CPI Data'!$I:$I,MATCH($B6,'CPI Data'!$B:$B,0))="","",INDEX('CPI Data'!$I:$I,MATCH($B6,'CPI Data'!$B:$B,0))),"") | G6: =IF(D6="","",D6*$N$4+E6*$N$5+F6*$N$6) | H6: =IFERROR(INDEX('CPI Data'!$E:$E,MATCH($B6,'CPI Data'!$B:$B,0)),"") | I6: =IFERROR(INDEX('CPI Data'!$E:$E,MATCH($B6,'CPI Data'!$B:$B,0)),"") | J6: =IFERROR(INDEX('CPI Data'!$E:$E,MATCH($B6,'CPI Data'!$B:$B,0)),"") | K6: =IFERROR(INDEX('CPI Data'!$E:$E,MATCH($B6,'CPI Data'!$B:$B,0)),"") | M6: Bear | N6: 0.25
B7: 2025-02 | C7: =IFERROR(IF(INDEX('CPI Data'!$I:$I,MATCH($B7,'CPI Data'!$B:$B,0))="","",INDEX('CPI Data'!$I:$I,MATCH($B7,'CPI Data'!$B:$B,0))),"") | G7: =IF(D7="","",D7*$N$4+E7*$N$5+F7*$N$6) | H7: =IFERROR(INDEX('CPI Data'!$E:$E,MATCH($B7,'CPI Data'!$B:$B,0)),"") | I7: =IFERROR(INDEX('CPI Data'!$E:$E,MATCH($B7,'CPI Data'!$B:$B,0)),"") | J7: =IFERROR(INDEX('CPI Data'!$E:$E,MATCH($B7,'CPI Data'!$B:$B,0)),"") | K7: =IFERROR(INDEX('CPI Data'!$E:$E,MATCH($B7,'CPI Data'!$B:$B,0)),"") | M7: Sum | N7: =SUM(N4:N6)
B8: 2025-03 | C8: =IFERROR(IF(INDEX('CPI Data'!$I:$I,MATCH($B8,'CPI Data'!$B:$B,0))="","",INDEX('CPI Data'!$I:$I,MATCH($B8,'CPI Data'!$B:$B,0))),"") | G8: =IF(D8="","",D8*$N$4+E8*$N$5+F8*$N$6) | H8: =IFERROR(INDEX('CPI Data'!$E:$E,MATCH($B8,'CPI Data'!$B:$B,0)),"") | I8: =IFERROR(INDEX('CPI Data'!$E:$E,MATCH($B8,'CPI Data'!$B:$B,0)),"") | J8: =IFERROR(INDEX('CPI Data'!$E:$E,MATCH($B8,'CPI Data'!$B:$B,0)),"") | K8: =IFERROR(INDEX('CPI Data'!$E:$E,MATCH($B8,'CPI Data'!$B:$B,0)),"")
B9: 2025-04 | C9: =IFERROR(IF(INDEX('CPI Data'!$I:$I,MATCH($B9,'CPI Data'!$B:$B,0))="","",INDEX('CPI Data'!$I:$I,MATCH($B9,'CPI Data'!$B:$B,0))),"") | G9: =IF(D9="","",D9*$N$4+E9*$N$5+F9*$N$6) | H9: =IFERROR(INDEX('CPI Data'!$E:$E,MATCH($B9,'CPI Data'!$B:$B,0)),"") | I9: =IFERROR(INDEX('CPI Data'!$E:$E,MATCH($B9,'CPI Data'!$B:$B,0)),"") | J9: =IFERROR(INDEX('CPI Data'!$E:$E,MATCH($B9,'CPI Data'!$B:$B,0)),"") | K9: =IFERROR(INDEX('CPI Data'!$E:$E,MATCH($B9,'CPI Data'!$B:$B,0)),"")
B10: 2025-05 | C10: =IFERROR(IF(INDEX('CPI Data'!$I:$I,MATCH($B10,'CPI Data'!$B:$B,0))="","",INDEX('CPI Data'!$I:$I,MATCH($B10,'CPI Data'!$B:$B,0))),"") | G10: =IF(D10="","",D10*$N$4+E10*$N$5+F10*$N$6) | H10: =IFERROR(INDEX('CPI Data'!$E:$E,MATCH($B10,'CPI Data'!$B:$B,0)),"") | I10: =IFERROR(INDEX('CPI Data'!$E:$E,MATCH($B10,'CPI Data'!$B:$B,0)),"") | J10: =IFERROR(INDEX('CPI Data'!$E:$E,MATCH($B10,'CPI Data'!$B:$B,0)),"") | K10: =IFERROR(INDEX('CPI Data'!$E:$E,MATCH($B10,'CPI Data'!$B:$B,0)),"")
B11: 2025-06 | C11: =IFERROR(IF(INDEX('CPI Data'!$I:$I,MATCH($B11,'CPI Data'!$B:$B,0))="","",INDEX('CPI Data'!$I:$I,MATCH($B11,'CPI Data'!$B:$B,0))),"") | G11: =IF(D11="","",D11*$N$4+E11*$N$5+F11*$N$6) | H11: =IFERROR(INDEX('CPI Data'!$E:$E,MATCH($B11,'CPI Data'!$B:$B,0)),"") | I11: =IFERROR(INDEX('CPI Data'!$E:$E,MATCH($B11,'CPI Data'!$B:$B,0)),"") | J11: =IFERROR(INDEX('CPI Data'!$E:$E,MATCH($B11,'CPI Data'!$B:$B,0)),"") | K11: =IFERROR(INDEX('CPI Data'!$E:$E,MATCH($B11,'CPI Data'!$B:$B,0)),"")
B12: 2025-07 | C12: =IFERROR(IF(INDEX('CPI Data'!$I:$I,MATCH($B12,'CPI Data'!$B:$B,0))="","",INDEX('CPI Data'!$I:$I,MATCH($B12,'CPI Data'!$B:$B,0))),"") | G12: =IF(D12="","",D12*$N$4+E12*$N$5+F12*$N$6) | H12: =IFERROR(INDEX('CPI Data'!$E:$E,MATCH($B12,'CPI Data'!$B:$B,0)),"") | I12: =IFERROR(INDEX('CPI Data'!$E:$E,MATCH($B12,'CPI Data'!$B:$B,0)),"") | J12: =IFERROR(INDEX('CPI Data'!$E:$E,MATCH($B12,'CPI Data'!$B:$B,0)),"") | K12: =IFERROR(INDEX('CPI Data'!$E:$E,MATCH($B12,'CPI Data'!$B:$B,0)),"")
B13: 2025-08 | C13: =IFERROR(IF(INDEX('CPI Data'!$I:$I,MATCH($B13,'CPI Data'!$B:$B,0))="","",INDEX('CPI Data'!$I:$I,MATCH($B13,'CPI Data'!$B:$B,0))),"") | G13: =IF(D13="","",D13*$N$4+E13*$N$5+F13*$N$6) | H13: =IFERROR(INDEX('CPI Data'!$E:$E,MATCH($B13,'CPI Data'!$B:$B,0)),"") | I13: =IFERROR(INDEX('CPI Data'!$E:$E,MATCH($B13,'CPI Data'!$B:$B,0)),"") | J13: =IFERROR(INDEX('CPI Data'!$E:$E,MATCH($B13,'CPI Data'!$B:$B,0)),"") | K13: =IFERROR(INDEX('CPI Data'!$E:$E,MATCH($B13,'CPI Data'!$B:$B,0)),"")
B14: 2025-09 | C14: =IFERROR(IF(INDEX('CPI Data'!$I:$I,MATCH($B14,'CPI Data'!$B:$B,0))="","",INDEX('CPI Data'!$I:$I,MATCH($B14,'CPI Data'!$B:$B,0))),"") | G14: =IF(D14="","",D14*$N$4+E14*$N$5+F14*$N$6) | H14: =IFERROR(INDEX('CPI Data'!$E:$E,MATCH($B14,'CPI Data'!$B:$B,0)),"") | I14: =IFERROR(INDEX('CPI Data'!$E:$E,MATCH($B14,'CPI Data'!$B:$B,0)),"") | J14: =IFERROR(INDEX('CPI Data'!$E:$E,MATCH($B14,'CPI Data'!$B:$B,0)),"") | K14: =IFERROR(INDEX('CPI Data'!$E:$E,MATCH($B14,'CPI Data'!$B:$B,0)),"")
B15: 2025-10 | C15: =IFERROR(IF(INDEX('CPI Data'!$I:$I,MATCH($B15,'CPI Data'!$B:$B,0))="","",INDEX('CPI Data'!$I:$I,MATCH($B15,'CPI Data'!$B:$B,0))),"") | G15: =IF(D15="","",D15*$N$4+E15*$N$5+F15*$N$6) | H15: =IFERROR(INDEX('CPI Data'!$E:$E,MATCH($B15,'CPI Data'!$B:$B,0)),"") | I15: =IFERROR(INDEX('CPI Data'!$E:$E,MATCH($B15,'CPI Data'!$B:$B,0)),"") | J15: =IFERROR(INDEX('CPI Data'!$E:$E,MATCH($B15,'CPI Data'!$B:$B,0)),"") | K15: =IFERROR(INDEX('CPI Data'!$E:$E,MATCH($B15,'CPI Data'!$B:$B,0)),"")
B16: 2025-11 | C16: =IFERROR(IF(INDEX('CPI Data'!$I:$I,MATCH($B16,'CPI Data'!$B:$B,0))="","",INDEX('CPI Data'!$I:$I,MATCH($B16,'CPI Data'!$B:$B,0))),"") | G16: =IF(D16="","",D16*$N$4+E16*$N$5+F16*$N$6) | H16: =IFERROR(INDEX('CPI Data'!$E:$E,MATCH($B16,'CPI Data'!$B:$B,0)),"") | I16: =IFERROR(INDEX('CPI Data'!$E:$E,MATCH($B16,'CPI Data'!$B:$B,0)),"") | J16: =IFERROR(INDEX('CPI Data'!$E:$E,MATCH($B16,'CPI Data'!$B:$B,0)),"") | K16: =IFERROR(INDEX('CPI Data'!$E:$E,MATCH($B16,'CPI Data'!$B:$B,0)),"")
B17: 2025-12 | C17: =IFERROR(IF(INDEX('CPI Data'!$I:$I,MATCH($B17,'CPI Data'!$B:$B,0))="","",INDEX('CPI Data'!$I:$I,MATCH($B17,'CPI Data'!$B:$B,0))),"") | G17: =IF(D17="","",D17*$N$4+E17*$N$5+F17*$N$6) | H17: =IFERROR(INDEX('CPI Data'!$E:$E,MATCH($B17,'CPI Data'!$B:$B,0)),"") | I17: =IFERROR(INDEX('CPI Data'!$E:$E,MATCH($B17,'CPI Data'!$B:$B,0)),"") | J17: =IFERROR(INDEX('CPI Data'!$E:$E,MATCH($B17,'CPI Data'!$B:$B,0)),"") | K17: =IFERROR(INDEX('CPI Data'!$E:$E,MATCH($B17,'CPI Data'!$B:$B,0)),"")
B18: 2026-01 | C18: =IFERROR(IF(INDEX('CPI Data'!$I:$I,MATCH($B18,'CPI Data'!$B:$B,0))="","",INDEX('CPI Data'!$I:$I,MATCH($B18,'CPI Data'!$B:$B,0))),"") | G18: =IF(D18="","",D18*$N$4+E18*$N$5+F18*$N$6) | H18: =IFERROR(INDEX('CPI Data'!$E:$E,MATCH($B18,'CPI Data'!$B:$B,0)),"") | I18: =IFERROR(INDEX('CPI Data'!$E:$E,MATCH($B18,'CPI Data'!$B:$B,0)),"") | J18: =IFERROR(INDEX('CPI Data'!$E:$E,MATCH($B18,'CPI Data'!$B:$B,0)),"") | K18: =IFERROR(INDEX('CPI Data'!$E:$E,MATCH($B18,'CPI Data'!$B:$B,0)),"")
B19: 2026-02 | C19: =IFERROR(IF(INDEX('CPI Data'!$I:$I,MATCH($B19,'CPI Data'!$B:$B,0))="","",INDEX('CPI Data'!$I:$I,MATCH($B19,'CPI Data'!$B:$B,0))),"") | G19: =IF(D19="","",D19*$N$4+E19*$N$5+F19*$N$6) | H19: =IFERROR(INDEX('CPI Data'!$E:$E,MATCH($B19,'CPI Data'!$B:$B,0)),"") | I19: =IFERROR(INDEX('CPI Data'!$E:$E,MATCH($B19,'CPI Data'!$B:$B,0)),"") | J19: =IFERROR(INDEX('CPI Data'!$E:$E,MATCH($B19,'CPI Data'!$B:$B,0)),"") | K19: =IFERROR(INDEX('CPI Data'!$E:$E,MATCH($B19,'CPI Data'!$B:$B,0)),"")
... B24: 2026-07 | C24: =IFERROR(IF(INDEX('CPI Data'!$I:$I,MATCH($B24,'CPI Data'!$B:$B,0))="","",INDEX('CPI Data'!$I:$I,MATCH($B24,'CPI Data'!$B:$B,0))),"") | G24: =IF(D24="","",D24*$N$4+E24*$N$5+F24*$N$6) | H24: =IFERROR(INDEX('CPI Data'!$E:$E,MATCH($B24,'CPI Data'!$B:$B,0)),"") | I24: =IFERROR(INDEX('CPI Data'!$E:$E,MATCH($B24,'CPI Data'!$B:$B,0)),"") | J24: =IFERROR(INDEX('CPI Data'!$E:$E,MATCH($B24,'CPI Data'!$B:$B,0)),"") | K24: =IFERROR(INDEX('CPI Data'!$E:$E,MATCH($B24,'CPI Data'!$B:$B,0)),"")
B25: 2026-08 | C25: =IFERROR(IF(INDEX('CPI Data'!$I:$I,MATCH($B25,'CPI Data'!$B:$B,0))="","",INDEX('CPI Data'!$I:$I,MATCH($B25,'CPI Data'!$B:$B,0))),"") | D25: =$C25 | E25: =$C25 | F25: =$C25 | G25: =IF(D25="","",D25*$N$4+E25*$N$5+F25*$N$6) | H25: =IFERROR(INDEX('CPI Data'!$E:$E,MATCH($B25,'CPI Data'!$B:$B,0)),"") | I25: =IFERROR(INDEX('CPI Data'!$E:$E,MATCH($B25,'CPI Data'!$B:$B,0)),"") | J25: =IFERROR(INDEX('CPI Data'!$E:$E,MATCH($B25,'CPI Data'!$B:$B,0)),"") | K25: =IFERROR(INDEX('CPI Data'!$E:$E,MATCH($B25,'CPI Data'!$B:$B,0)),"")
B26: 2026-09 | C26: =IFERROR(IF(INDEX('CPI Data'!$I:$I,MATCH($B26,'CPI Data'!$B:$B,0))="","",INDEX('CPI Data'!$I:$I,MATCH($B26,'CPI Data'!$B:$B,0))),"") | D26: 0.015 | E26: 0.018 | F26: 0.025 | G26: =IF(D26="","",D26*$N$4+E26*$N$5+F26*$N$6) | H26: =H25*(1+D26) | I26: =I25*(1+E26) | J26: =J25*(1+F26) | K26: =K25*(1+G26)
B27: 2026-10 | C27: =IFERROR(IF(INDEX('CPI Data'!$I:$I,MATCH($B27,'CPI Data'!$B:$B,0))="","",INDEX('CPI Data'!$I:$I,MATCH($B27,'CPI Data'!$B:$B,0))),"") | D27: 0.015 | E27: 0.019 | F27: 0.027 | G27: =IF(D27="","",D27*$N$4+E27*$N$5+F27*$N$6) | H27: =H26*(1+D27) | I27: =I26*(1+E27) | J27: =J26*(1+F27) | K27: =K26*(1+G27)
B28: 2026-11 | C28: =IFERROR(IF(INDEX('CPI Data'!$I:$I,MATCH($B28,'CPI Data'!$B:$B,0))="","",INDEX('CPI Data'!$I:$I,MATCH($B28,'CPI Data'!$B:$B,0))),"") | D28: 0.014 | E28: 0.019 | F28: 0.026 | G28: =IF(D28="","",D28*$N$4+E28*$N$5+F28*$N$6) | H28: =H27*(1+D28) | I28: =I27*(1+E28) | J28: =J27*(1+F28) | K28: =K27*(1+G28)
B29: 2026-12 | C29: =IFERROR(IF(INDEX('CPI Data'!$I:$I,MATCH($B29,'CPI Data'!$B:$B,0))="","",INDEX('CPI Data'!$I:$I,MATCH($B29,'CPI Data'!$B:$B,0))),"") | D29: 0.016 | E29: 0.021 | F29: 0.028 | G29: =IF(D29="","",D29*$N$4+E29*$N$5+F29*$N$6) | H29: =H28*(1+D29) | I29: =I28*(1+E29) | J29: =J28*(1+F29) | K29: =K28*(1+G29)
B30: 2027-01 | C30: =IFERROR(IF(INDEX('CPI Data'!$I:$I,MATCH($B30,'CPI Data'!$B:$B,0))="","",INDEX('CPI Data'!$I:$I,MATCH($B30,'CPI Data'!$B:$B,0))),"") | D30: 0.015 | E30: 0.02 | F30: 0.028 | G30: =IF(D30="","",D30*$N$4+E30*$N$5+F30*$N$6) | H30: =H29*(1+D30) | I30: =I29*(1+E30) | J30: =J29*(1+F30) | K30: =K29*(1+G30)
B31: 2027-02 | C31: =IFERROR(IF(INDEX('CPI Data'!$I:$I,MATCH($B31,'CPI Data'!$B:$B,0))="","",INDEX('CPI Data'!$I:$I,MATCH($B31,'CPI Data'!$B:$B,0))),"") | D31: 0.013 | E31: 0.018 | F31: 0.026 | G31: =IF(D31="","",D31*$N$4+E31*$N$5+F31*$N$6) | H31: =H30*(1+D31) | I31: =I30*(1+E31) | J31: =J30*(1+F31) | K31: =K30*(1+G31)
B32: 2027-03 | C32: =IFERROR(IF(INDEX('CPI Data'!$I:$I,MATCH($B32,'CPI Data'!$B:$B,0))="","",INDEX('CPI Data'!$I:$I,MATCH($B32,'CPI Data'!$B:$B,0))),"") | D32: 0.013 | E32: 0.017 | F32: 0.025 | G32: =IF(D32="","",D32*$N$4+E32*$N$5+F32*$N$6) | H32: =H31*(1+D32) | I32: =I31*(1+E32) | J32: =J31*(1+F32) | K32: =K31*(1+G32)
B33: 2027-04 | C33: =IFERROR(IF(INDEX('CPI Data'!$I:$I,MATCH($B33,'CPI Data'!$B:$B,0))="","",INDEX('CPI Data'!$I:$I,MATCH($B33,'CPI Data'!$B:$B,0))),"") | D33: 0.011 | E33: 0.016 | F33: 0.023 | G33: =IF(D33="","",D33*$N$4+E33*$N$5+F33*$N$6) | H33: =H32*(1+D33) | I33: =I32*(1+E33) | J33: =J32*(1+F33) | K33: =K32*(1+G33)
B34: 2027-05 | C34: =IFERROR(IF(INDEX('CPI Data'!$I:$I,MATCH($B34,'CPI Data'!$B:$B,0))="","",INDEX('CPI Data'!$I:$I,MATCH($B34,'CPI Data'!$B:$B,0))),"") | D34: 0.01 | E34: 0.014 | F34: 0.021 | G34: =IF(D34="","",D34*$N$4+E34*$N$5+F34*$N$6) | H34: =H33*(1+D34) | I34: =I33*(1+E34) | J34: =J33*(1+F34) | K34: =K33*(1+G34)
B35: 2027-06 | C35: =IFERROR(IF(INDEX('CPI Data'!$I:$I,MATCH($B35,'CPI Data'!$B:$B,0))="","",INDEX('CPI Data'!$I:$I,MATCH($B35,'CPI Data'!$B:$B,0))),"") | D35: 0.009 | E35: 0.013 | F35: 0.02 | G35: =IF(D35="","",D35*$N$4+E35*$N$5+F35*$N$6) | H35: =H34*(1+D35) | I35: =I34*(1+E35) | J35: =J34*(1+F35) | K35: =K34*(1+G35)
B36: 2027-07 | C36: =IFERROR(IF(INDEX('CPI Data'!$I:$I,MATCH($B36,'CPI Data'!$B:$B,0))="","",INDEX('CPI Data'!$I:$I,MATCH($B36,'CPI Data'!$B:$B,0))),"") | D36: 0.009 | E36: 0.013 | F36: 0.019 | G36: =IF(D36="","",D36*$N$4+E36*$N$5+F36*$N$6) | H36: =H35*(1+D36) | I36: =I35*(1+E36) | J36: =J35*(1+F36) | K36: =K35*(1+G36)
B37: 2027-08 | C37: =IFERROR(IF(INDEX('CPI Data'!$I:$I,MATCH($B37,'CPI Data'!$B:$B,0))="","",INDEX('CPI Data'!$I:$I,MATCH($B37,'CPI Data'!$B:$B,0))),"") | D37: 0.008 | E37: 0.012 | F37: 0.019 | G37: =IF(D37="","",D37*$N$4+E37*$N$5+F37*$N$6) | H37: =H36*(1+D37) | I37: =I36*(1+E37) | J37: =J36*(1+F37) | K37: =K36*(1+G37)
... B41: 2027-12 | C41: =IFERROR(IF(INDEX('CPI Data'!$I:$I,MATCH($B41,'CPI Data'!$B:$B,0))="","",INDEX('CPI Data'!$I:$I,MATCH($B41,'CPI Data'!$B:$B,0))),"") | D41: 0.01 | E41: 0.014 | F41: 0.02 | G41: =IF(D41="","",D41*$N$4+E41*$N$5+F41*$N$6) | H41: =H40*(1+D41) | I41: =I40*(1+E41) | J41: =J40*(1+F41) | K41: =K40*(1+G41)
B43: Dec/Dec outcome
C44: Bull | D44: Base | E44: Bear | F44: Prob-weighted | G44: BCRA REM | H44: Budget bill | I44: Note
B45: 2026 (Dec/Dec) | C45: =H$29/INDEX('CPI Data'!$E:$E,MATCH("2025-12",'CPI Data'!$B:$B,0))-1 | D45: =I$29/INDEX('CPI Data'!$E:$E,MATCH("2025-12",'CPI Data'!$B:$B,0))-1 | E45: =J$29/INDEX('CPI Data'!$E:$E,MATCH("2025-12",'CPI Data'!$B:$B,0))-1 | F45: =K$29/INDEX('CPI Data'!$E:$E,MATCH("2025-12",'CPI Data'!$B:$B,0))-1 | G45: 0.3 | I45: REM: the August-2026 round (published 4-Sep-2026, 47 participants) confirms 30.0% median / 29.9% top-10 for 2026.
B46: 2027 (Dec/Dec) | C46: =H$41/H$29-1 | D46: =I$41/I$29-1 | E46: =J$41/J$29-1 | F46: =K$41/K$29-1 | G46: 0.2 | H46: 0.18 | I46: REM 2027 is the JULY round's 20.0% — the August round's 2027 median could not be obtained. Budget 2027 bill (tabled 15-Sep-2026): 18.0% Dec/Dec, 21.1% average, ARS 1,847.6/USD at Dec-2027. Between those two the base case has no contrarian content; the edge is the bear tail.
B49: Scenario assumptions
B50: Driver | C50: Bull | D50: Base | E50: Bear
B51: FX - official, Dec-26 | C51: ARS 1,600 - spot drifts up less than the band crawl; real appreciation resumes | D51: ARS 1,690 - spot tracks the band's CPI-indexed crawl, roughly 2.2%/m | E51: ARS 1,950 - band ceiling tested; a step devaluation of 12-15% in Q4
B52: FX pass-through | C52: 0.10 within a quarter - import competition holds, margins absorb | D52: 0.15 within two quarters - the 2024-25 realised range | E52: 0.30 - a discrete jump reprices tradables fast
B53: Regulated tariffs | C53: Catch-up essentially complete; regulated converges toward core by Q4-26 | D53: Regulated keeps running ~50-80bp/m above core through mid-27, then converges | E53: Subsidy removal re-accelerates; regulated stays 150bp/m above core
B54: Wages / indexation | C54: Paritarias settle at or below expected inflation; backward indexation breaks | D54: Paritarias track trailing CPI - inertia keeps a floor near 1.2-1.4%/m | E54: Real wage recovery demands re-open; formal wages index to trailing 12m
B55: Fiscal / monetary | C55: Primary surplus above 1.5% GDP, no monetary financing, orderly remonetisation | D55: Primary surplus around 1.0-1.5% GDP; peso demand grows with activity | E55: Surplus slips ahead of the 2027 electoral cycle; peso demand stalls
B56: Key risk to this view | C56: Disinflation faster than any Argentine episode since convertibility - historically rare | D56: The band's CPI indexation removes the nominal anchor that drove 2024-25; inflation converges TO the crawl, not below it | E56: A band break is the single event that resets the path - watch reserve accumulation, not the CPI

Sheet Models
B2: Six models — where is CPI in the three to six months before the vote?
B3: Independent approaches, one comparison table. Blue = assumption you can change. Red = parameter estimated from the data. Black = calculated.
B4: Election calendar
B5: General election | D5: 2027-10-24 | E5: Fourth Sunday of October. Runoff within 30 days if no candidate clears 45%, or 40% with a 10pp margin.
B6: PASO primary, if held | D6: 2027-08-08 | E6: Law 26.571. Suspended by statute for 2025 and 2026 ONLY — the suspension does NOT reach 2027, so the legal default is that primaries happen. Abolition needs 37 senators; LLA has roughly 21.
B7: Window start (6 months before) | D7: 2027-04-24 | E7: The start of the period the question asks about.
B8: Window end (3 months before) | D8: 2027-07-24 | E8: The end of it. Monthly prints in the window: April, May, June, July 2027.
B9: Last CPI print published before the vote | D9: 2027-09 | E9: September-2027, released around 14 October. This is the number voters actually have.
B11: Model parameters
B12: MODEL 2 — Inertia / mean reversion
B13: Starting monthly rate | D13: =(1+'CPI Data'!P98)^(1/12)-1 | E13: The trailing 3-month annualised rate at the last print, expressed monthly. Calculated, not assumed.
B14: Terminal monthly rate | D14: 0.011 | E14: Where inflation settles. 1.10%/month compounds to about 14% a year. This is the single most important assumption in the model — stress it.
B15: Monthly decay rho | D15: 0.93 | E15: Share of the gap to the terminal rate that survives each month. 0.93 implies a half-life of about ten months.
B16: Implied half-life (months) | D16: =LN(2)/-LN($D$15) | E16: Calculated from rho.
B18: MODEL 3 — Bottom-up, with the FX band indexation loop
B19: CPI weight, nucleo | D19: 0.7105
B20: CPI weight, regulados | D20: 0.1683
B21: CPI weight, estacionales | D21: 0.1211
B22: Autonomous core, kappa | D22: 0.01309
B23: Indexation coefficient, lambda | D23: 0.4087
B24: FIXED POINT of the loop (monthly) | D24: =$D$22/(1-$D$23) | E24: kappa / (1 - lambda). The rate the indexation loop settles at on its own.
B25: FIXED POINT, annualised | D25: =(1+$D$24)^12-1 | E25: THE HEADLINE RESULT OF THIS MODEL. The mechanical fixed point of a CPI-indexed FX band is close to where inflation already is. Reaching the Budget's 18% requires BREAKING the loop, not letting it run.
B26: Regulated premium over core now (pp/month) | D26: =AVERAGE('CPI Data'!T96:T98)/100 | E26: Three-month average of regulados less nucleo. Calculated from the data, not assumed.
B27: Premium decay per month | D27: 0.94 | E27: How fast the tariff catch-up converges to zero. At 0.94 the premium roughly halves each year. The 2027 Budget plans further subsidy withdrawal to 0.53% of GDP, so a slower decay is the bear case.
B29: MODEL 4 — Seasonal carry-forward
B30: Deseasonalised trend now (monthly) | D30: =Momentum!$E$76 | E30: Mean of the last three months' m/m divided by each month's own seasonal factor. Calculated on the Momentum tab. Note it runs ABOVE the trailing 3m annualised: June and July 2026 fell in the two coolest months of the calendar.
B31: Terminal deseasonalised trend | D31: 0.0125 | E31: Where the seasonally adjusted trend settles.
B32: Monthly decay | D32: 0.93 | E32: Same functional form as Model 2, applied to the seasonally adjusted trend, then the month's seasonal factor is re-imposed.
B34: MODEL 5 — Market-implied
B35: Breakeven, Sep-Oct 2026 (m/m) | D35: 0.019 | E35: Sourced: El Cronista, 25/26-Sep-2026, fixed-rate against CER.
B36: Breakeven, Nov-2026 to May-2027 (m/m) | D36: 0.0185 | E36: Sourced. The longest-dated breakeven obtainable. It spans the pre-election window — which is what makes this model worth having.
B37: Monthly drift beyond May-2027 (pp) | D37: 0 | E37: EXTRAPOLATION, NOT SOURCED. Zero holds the breakeven flat past the last sourced point. Discrete 2027-28 breakevens need a live BYMA/MAE or Bloomberg curve.
B39: MODEL 6 — Consensus
B40: REM Dec/Dec 2026 | D40: 0.3 | E40: August-2026 round, 47 participants. The residual months of 2026 are solved so the path hits this exactly.
B41: REM Dec/Dec 2027 | D41: 0.2 | E41: July-2026 round — the August round's 2027 median could not be obtained. Set this to 18.0% to see the Budget's path instead.
B43: Monthly paths
B44: Month | C44: M# | D44: Actual | E44: M1 Bull | F44: M1 Base | G44: M1 Bear | H44: M2 Inertia | I44: M3 Bottom-up | J44: M4 Seasonal | K44: M5 Market | L44: M6 Consensus | M44: M3 core | N44: M3 premium | O44: Seas. factor | P44: idx Bull | Q44: idx Base | R44: idx Bear | S44: idx Inertia | T44: idx Bottom-up | U44: idx Seasonal | V44: idx Market | W44: idx Consensus
B45: 2026-01 | C45: 1 | D45: =IFERROR(IF(INDEX('CPI Data'!$I:$I,MATCH($B45,'CPI Data'!$B:$B,0))="","",INDEX('CPI Data'!$I:$I,MATCH($B45,'CPI Data'!$B:$B,0))),"") | E45: =IFERROR(INDEX(Forecast!$D:$D,MATCH($B45,Forecast!$B:$B,0)),"") | F45: =IFERROR(INDEX(Forecast!$E:$E,MATCH($B45,Forecast!$B:$B,0)),"") | G45: =IFERROR(INDEX(Forecast!$F:$F,MATCH($B45,Forecast!$B:$B,0)),"") | H45: =$D45 | I45: =$D45 | J45: =$D45 | K45: =$D45 | M45: =IFERROR(INDEX('CPI Data'!$J:$J,MATCH($B45,'CPI Data'!$B:$B,0)),"") | N45: =IFERROR(INDEX('CPI Data'!$T:$T,MATCH($B45,'CPI Data'!$B:$B,0))/100,"") | O45: ='Seasonal Factors'!$L$6 | P45: =IFERROR(INDEX('CPI Data'!$E:$E,MATCH($B45,'CPI Data'!$B:$B,0)),"") | Q45: =IFERROR(INDEX('CPI Data'!$E:$E,MATCH($B45,'CPI Data'!$B:$B,0)),"") | R45: =IFERROR(INDEX('CPI Data'!$E:$E,MATCH($B45,'CPI Data'!$B:$B,0)),"") | S45: =IFERROR(INDEX('CPI Data'!$E:$E,MATCH($B45,'CPI Data'!$B:$B,0)),"") | T45: =IFERROR(INDEX('CPI Data'!$E:$E,MATCH($B45,'CPI Data'!$B:$B,0)),"") | U45: =IFERROR(INDEX('CPI Data'!$E:$E,MATCH($B45,'CPI Data'!$B:$B,0)),"") | V45: =IFERROR(INDEX('CPI Data'!$E:$E,MATCH($B45,'CPI Data'!$B:$B,0)),"") | W45: =IFERROR(INDEX('CPI Data'!$E:$E,MATCH($B45,'CPI Data'!$B:$B,0)),"")
B46: 2026-02 | C46: 2 | D46: =IFERROR(IF(INDEX('CPI Data'!$I:$I,MATCH($B46,'CPI Data'!$B:$B,0))="","",INDEX('CPI Data'!$I:$I,MATCH($B46,'CPI Data'!$B:$B,0))),"") | E46: =IFERROR(INDEX(Forecast!$D:$D,MATCH($B46,Forecast!$B:$B,0)),"") | F46: =IFERROR(INDEX(Forecast!$E:$E,MATCH($B46,Forecast!$B:$B,0)),"") | G46: =IFERROR(INDEX(Forecast!$F:$F,MATCH($B46,Forecast!$B:$B,0)),"") | H46: =$D46 | I46: =$D46 | J46: =$D46 | K46: =$D46 | M46: =IFERROR(INDEX('CPI Data'!$J:$J,MATCH($B46,'CPI Data'!$B:$B,0)),"") | N46: =IFERROR(INDEX('CPI Data'!$T:$T,MATCH($B46,'CPI Data'!$B:$B,0))/100,"") | O46: ='Seasonal Factors'!$L$7 | P46: =IFERROR(INDEX('CPI Data'!$E:$E,MATCH($B46,'CPI Data'!$B:$B,0)),"") | Q46: =IFERROR(INDEX('CPI Data'!$E:$E,MATCH($B46,'CPI Data'!$B:$B,0)),"") | R46: =IFERROR(INDEX('CPI Data'!$E:$E,MATCH($B46,'CPI Data'!$B:$B,0)),"") | S46: =IFERROR(INDEX('CPI Data'!$E:$E,MATCH($B46,'CPI Data'!$B:$B,0)),"") | T46: =IFERROR(INDEX('CPI Data'!$E:$E,MATCH($B46,'CPI Data'!$B:$B,0)),"") | U46: =IFERROR(INDEX('CPI Data'!$E:$E,MATCH($B46,'CPI Data'!$B:$B,0)),"") | V46: =IFERROR(INDEX('CPI Data'!$E:$E,MATCH($B46,'CPI Data'!$B:$B,0)),"") | W46: =IFERROR(INDEX('CPI Data'!$E:$E,MATCH($B46,'CPI Data'!$B:$B,0)),"")
B47: 2026-03 | C47: 3 | D47: =IFERROR(IF(INDEX('CPI Data'!$I:$I,MATCH($B47,'CPI Data'!$B:$B,0))="","",INDEX('CPI Data'!$I:$I,MATCH($B47,'CPI Data'!$B:$B,0))),"") | E47: =IFERROR(INDEX(Forecast!$D:$D,MATCH($B47,Forecast!$B:$B,0)),"") | F47: =IFERROR(INDEX(Forecast!$E:$E,MATCH($B47,Forecast!$B:$B,0)),"") | G47: =IFERROR(INDEX(Forecast!$F:$F,MATCH($B47,Forecast!$B:$B,0)),"") | H47: =$D47 | I47: =$D47 | J47: =$D47 | K47: =$D47 | M47: =IFERROR(INDEX('CPI Data'!$J:$J,MATCH($B47,'CPI Data'!$B:$B,0)),"") | N47: =IFERROR(INDEX('CPI Data'!$T:$T,MATCH($B47,'CPI Data'!$B:$B,0))/100,"") | O47: ='Seasonal Factors'!$L$8 | P47: =IFERROR(INDEX('CPI Data'!$E:$E,MATCH($B47,'CPI Data'!$B:$B,0)),"") | Q47: =IFERROR(INDEX('CPI Data'!$E:$E,MATCH($B47,'CPI Data'!$B:$B,0)),"") | R47: =IFERROR(INDEX('CPI Data'!$E:$E,MATCH($B47,'CPI Data'!$B:$B,0)),"") | S47: =IFERROR(INDEX('CPI Data'!$E:$E,MATCH($B47,'CPI Data'!$B:$B,0)),"") | T47: =IFERROR(INDEX('CPI Data'!$E:$E,MATCH($B47,'CPI Data'!$B:$B,0)),"") | U47: =IFERROR(INDEX('CPI Data'!$E:$E,MATCH($B47,'CPI Data'!$B:$B,0)),"") | V47: =IFERROR(INDEX('CPI Data'!$E:$E,MATCH($B47,'CPI Data'!$B:$B,0)),"") | W47: =IFERROR(INDEX('CPI Data'!$E:$E,MATCH($B47,'CPI Data'!$B:$B,0)),"")
B48: 2026-04 | C48: 4 | D48: =IFERROR(IF(INDEX('CPI Data'!$I:$I,MATCH($B48,'CPI Data'!$B:$B,0))="","",INDEX('CPI Data'!$I:$I,MATCH($B48,'CPI Data'!$B:$B,0))),"") | E48: =IFERROR(INDEX(Forecast!$D:$D,MATCH($B48,Forecast!$B:$B,0)),"") | F48: =IFERROR(INDEX(Forecast!$E:$E,MATCH($B48,Forecast!$B:$B,0)),"") | G48: =IFERROR(INDEX(Forecast!$F:$F,MATCH($B48,Forecast!$B:$B,0)),"") | H48: =$D48 | I48: =$D48 | J48: =$D48 | K48: =$D48 | M48: =IFERROR(INDEX('CPI Data'!$J:$J,MATCH($B48,'CPI Data'!$B:$B,0)),"") | N48: =IFERROR(INDEX('CPI Data'!$T:$T,MATCH($B48,'CPI Data'!$B:$B,0))/100,"") | O48: ='Seasonal Factors'!$L$9 | P48: =IFERROR(INDEX('CPI Data'!$E:$E,MATCH($B48,'CPI Data'!$B:$B,0)),"") | Q48: =IFERROR(INDEX('CPI Data'!$E:$E,MATCH($B48,'CPI Data'!$B:$B,0)),"") | R48: =IFERROR(INDEX('CPI Data'!$E:$E,MATCH($B48,'CPI Data'!$B:$B,0)),"") | S48: =IFERROR(INDEX('CPI Data'!$E:$E,MATCH($B48,'CPI Data'!$B:$B,0)),"") | T48: =IFERROR(INDEX('CPI Data'!$E:$E,MATCH($B48,'CPI Data'!$B:$B,0)),"") | U48: =IFERROR(INDEX('CPI Data'!$E:$E,MATCH($B48,'CPI Data'!$B:$B,0)),"") | V48: =IFERROR(INDEX('CPI Data'!$E:$E,MATCH($B48,'CPI Data'!$B:$B,0)),"") | W48: =IFERROR(INDEX('CPI Data'!$E:$E,MATCH($B48,'CPI Data'!$B:$B,0)),"")
B49: 2026-05 | C49: 5 | D49: =IFERROR(IF(INDEX('CPI Data'!$I:$I,MATCH($B49,'CPI Data'!$B:$B,0))="","",INDEX('CPI Data'!$I:$I,MATCH($B49,'CPI Data'!$B:$B,0))),"") | E49: =IFERROR(INDEX(Forecast!$D:$D,MATCH($B49,Forecast!$B:$B,0)),"") | F49: =IFERROR(INDEX(Forecast!$E:$E,MATCH($B49,Forecast!$B:$B,0)),"") | G49: =IFERROR(INDEX(Forecast!$F:$F,MATCH($B49,Forecast!$B:$B,0)),"") | H49: =$D49 | I49: =$D49 | J49: =$D49 | K49: =$D49 | M49: =IFERROR(INDEX('CPI Data'!$J:$J,MATCH($B49,'CPI Data'!$B:$B,0)),"") | N49: =IFERROR(INDEX('CPI Data'!$T:$T,MATCH($B49,'CPI Data'!$B:$B,0))/100,"") | O49: ='Seasonal Factors'!$L$10 | P49: =IFERROR(INDEX('CPI Data'!$E:$E,MATCH($B49,'CPI Data'!$B:$B,0)),"") | Q49: =IFERROR(INDEX('CPI Data'!$E:$E,MATCH($B49,'CPI Data'!$B:$B,0)),"") | R49: =IFERROR(INDEX('CPI Data'!$E:$E,MATCH($B49,'CPI Data'!$B:$B,0)),"") | S49: =IFERROR(INDEX('CPI Data'!$E:$E,MATCH($B49,'CPI Data'!$B:$B,0)),"") | T49: =IFERROR(INDEX('CPI Data'!$E:$E,MATCH($B49,'CPI Data'!$B:$B,0)),"") | U49: =IFERROR(INDEX('CPI Data'!$E:$E,MATCH($B49,'CPI Data'!$B:$B,0)),"") | V49: =IFERROR(INDEX('CPI Data'!$E:$E,MATCH($B49,'CPI Data'!$B:$B,0)),"") | W49: =IFERROR(INDEX('CPI Data'!$E:$E,MATCH($B49,'CPI Data'!$B:$B,0)),"")
B50: 2026-06 | C50: 6 | D50: =IFERROR(IF(INDEX('CPI Data'!$I:$I,MATCH($B50,'CPI Data'!$B:$B,0))="","",INDEX('CPI Data'!$I:$I,MATCH($B50,'CPI Data'!$B:$B,0))),"") | E50: =IFERROR(INDEX(Forecast!$D:$D,MATCH($B50,Forecast!$B:$B,0)),"") | F50: =IFERROR(INDEX(Forecast!$E:$E,MATCH($B50,Forecast!$B:$B,0)),"") | G50: =IFERROR(INDEX(Forecast!$F:$F,MATCH($B50,Forecast!$B:$B,0)),"") | H50: =$D50 | I50: =$D50 | J50: =$D50 | K50: =$D50 | M50: =IFERROR(INDEX('CPI Data'!$J:$J,MATCH($B50,'CPI Data'!$B:$B,0)),"") | N50: =IFERROR(INDEX('CPI Data'!$T:$T,MATCH($B50,'CPI Data'!$B:$B,0))/100,"") | O50: ='Seasonal Factors'!$L$11 | P50: =IFERROR(INDEX('CPI Data'!$E:$E,MATCH($B50,'CPI Data'!$B:$B,0)),"") | Q50: =IFERROR(INDEX('CPI Data'!$E:$E,MATCH($B50,'CPI Data'!$B:$B,0)),"") | R50: =IFERROR(INDEX('CPI Data'!$E:$E,MATCH($B50,'CPI Data'!$B:$B,0)),"") | S50: =IFERROR(INDEX('CPI Data'!$E:$E,MATCH($B50,'CPI Data'!$B:$B,0)),"") | T50: =IFERROR(INDEX('CPI Data'!$E:$E,MATCH($B50,'CPI Data'!$B:$B,0)),"") | U50: =IFERROR(INDEX('CPI Data'!$E:$E,MATCH($B50,'CPI Data'!$B:$B,0)),"") | V50: =IFERROR(INDEX('CPI Data'!$E:$E,MATCH($B50,'CPI Data'!$B:$B,0)),"") | W50: =IFERROR(INDEX('CPI Data'!$E:$E,MATCH($B50,'CPI Data'!$B:$B,0)),"")
B51: 2026-07 | C51: 7 | D51: =IFERROR(IF(INDEX('CPI Data'!$I:$I,MATCH($B51,'CPI Data'!$B:$B,0))="","",INDEX('CPI Data'!$I:$I,MATCH($B51,'CPI Data'!$B:$B,0))),"") | E51: =IFERROR(INDEX(Forecast!$D:$D,MATCH($B51,Forecast!$B:$B,0)),"") | F51: =IFERROR(INDEX(Forecast!$E:$E,MATCH($B51,Forecast!$B:$B,0)),"") | G51: =IFERROR(INDEX(Forecast!$F:$F,MATCH($B51,Forecast!$B:$B,0)),"") | H51: =$D51 | I51: =$D51 | J51: =$D51 | K51: =$D51 | M51: =IFERROR(INDEX('CPI Data'!$J:$J,MATCH($B51,'CPI Data'!$B:$B,0)),"") | N51: =IFERROR(INDEX('CPI Data'!$T:$T,MATCH($B51,'CPI Data'!$B:$B,0))/100,"") | O51: ='Seasonal Factors'!$L$12 | P51: =IFERROR(INDEX('CPI Data'!$E:$E,MATCH($B51,'CPI Data'!$B:$B,0)),"") | Q51: =IFERROR(INDEX('CPI Data'!$E:$E,MATCH($B51,'CPI Data'!$B:$B,0)),"") | R51: =IFERROR(INDEX('CPI Data'!$E:$E,MATCH($B51,'CPI Data'!$B:$B,0)),"") | S51: =IFERROR(INDEX('CPI Data'!$E:$E,MATCH($B51,'CPI Data'!$B:$B,0)),"") | T51: =IFERROR(INDEX('CPI Data'!$E:$E,MATCH($B51,'CPI Data'!$B:$B,0)),"") | U51: =IFERROR(INDEX('CPI Data'!$E:$E,MATCH($B51,'CPI Data'!$B:$B,0)),"") | V51: =IFERROR(INDEX('CPI Data'!$E:$E,MATCH($B51,'CPI Data'!$B:$B,0)),"") | W51: =IFERROR(INDEX('CPI Data'!$E:$E,MATCH($B51,'CPI Data'!$B:$B,0)),"")
B52: 2026-08 | C52: 8 | D52: =IFERROR(IF(INDEX('CPI Data'!$I:$I,MATCH($B52,'CPI Data'!$B:$B,0))="","",INDEX('CPI Data'!$I:$I,MATCH($B52,'CPI Data'!$B:$B,0))),"") | E52: =IFERROR(INDEX(Forecast!$D:$D,MATCH($B52,Forecast!$B:$B,0)),"") | F52: =IFERROR(INDEX(Forecast!$E:$E,MATCH($B52,Forecast!$B:$B,0)),"") | G52: =IFERROR(INDEX(Forecast!$F:$F,MATCH($B52,Forecast!$B:$B,0)),"") | H52: =$D52 | I52: =$D52 | J52: =$D52 | K52: =$D52 | M52: =IFERROR(INDEX('CPI Data'!$J:$J,MATCH($B52,'CPI Data'!$B:$B,0)),"") | N52: =IFERROR(INDEX('CPI Data'!$T:$T,MATCH($B52,'CPI Data'!$B:$B,0))/100,"") | O52: ='Seasonal Factors'!$L$13 | P52: =IFERROR(INDEX('CPI Data'!$E:$E,MATCH($B52,'CPI Data'!$B:$B,0)),"") | Q52: =IFERROR(INDEX('CPI Data'!$E:$E,MATCH($B52,'CPI Data'!$B:$B,0)),"") | R52: =IFERROR(INDEX('CPI Data'!$E:$E,MATCH($B52,'CPI Data'!$B:$B,0)),"") | S52: =IFERROR(INDEX('CPI Data'!$E:$E,MATCH($B52,'CPI Data'!$B:$B,0)),"") | T52: =IFERROR(INDEX('CPI Data'!$E:$E,MATCH($B52,'CPI Data'!$B:$B,0)),"") | U52: =IFERROR(INDEX('CPI Data'!$E:$E,MATCH($B52,'CPI Data'!$B:$B,0)),"") | V52: =IFERROR(INDEX('CPI Data'!$E:$E,MATCH($B52,'CPI Data'!$B:$B,0)),"") | W52: =IFERROR(INDEX('CPI Data'!$E:$E,MATCH($B52,'CPI Data'!$B:$B,0)),"")
B53: 2026-09 | C53: 9 | D53: =IFERROR(IF(INDEX('CPI Data'!$I:$I,MATCH($B53,'CPI Data'!$B:$B,0))="","",INDEX('CPI Data'!$I:$I,MATCH($B53,'CPI Data'!$B:$B,0))),"") | E53: =IFERROR(INDEX(Forecast!$D:$D,MATCH($B53,Forecast!$B:$B,0)),"") | F53: =IFERROR(INDEX(Forecast!$E:$E,MATCH($B53,Forecast!$B:$B,0)),"") | G53: =IFERROR(INDEX(Forecast!$F:$F,MATCH($B53,Forecast!$B:$B,0)),"") | H53: =$D$14+($D$13-$D$14)*$D$15^(ROW()-52) | I53: =(M53+$D$20*N53)*O53 | J53: =($D$31+($D$30-$D$31)*$D$32^(ROW()-52))*O53 | K53: =IF($B53<="2026-10",$D$35,IF($B53<="2027-05",$D$36,$D$36+$D$37*(ROW()-61))) | L53: =((1+$D$40)*INDEX('CPI Data'!$E:$E,MATCH("2025-12",'CPI Data'!$B:$B,0))/INDEX('CPI Data'!$E:$E,MATCH("2026-08",'CPI Data'!$B:$B,0)))^(1/4)-1 | M53: =$D$22+$D$23*I51 | N53: =$D$26*$D$27^(ROW()-52) | O53: ='Seasonal Factors'!$L$14 | P53: =P52*(1+E53) | Q53: =Q52*(1+F53) | R53: =R52*(1+G53) | S53: =S52*(1+H53) | T53: =T52*(1+I53) | U53: =U52*(1+J53) | V53: =V52*(1+K53) | W53: =W52*(1+L53)
B54: 2026-10 | C54: 10 | D54: =IFERROR(IF(INDEX('CPI Data'!$I:$I,MATCH($B54,'CPI Data'!$B:$B,0))="","",INDEX('CPI Data'!$I:$I,MATCH($B54,'CPI Data'!$B:$B,0))),"") | E54: =IFERROR(INDEX(Forecast!$D:$D,MATCH($B54,Forecast!$B:$B,0)),"") | F54: =IFERROR(INDEX(Forecast!$E:$E,MATCH($B54,Forecast!$B:$B,0)),"") | G54: =IFERROR(INDEX(Forecast!$F:$F,MATCH($B54,Forecast!$B:$B,0)),"") | H54: =$D$14+($D$13-$D$14)*$D$15^(ROW()-52) | I54: =(M54+$D$20*N54)*O54 | J54: =($D$31+($D$30-$D$31)*$D$32^(ROW()-52))*O54 | K54: =IF($B54<="2026-10",$D$35,IF($B54<="2027-05",$D$36,$D$36+$D$37*(ROW()-61))) | L54: =((1+$D$40)*INDEX('CPI Data'!$E:$E,MATCH("2025-12",'CPI Data'!$B:$B,0))/INDEX('CPI Data'!$E:$E,MATCH("2026-08",'CPI Data'!$B:$B,0)))^(1/4)-1 | M54: =$D$22+$D$23*I52 | N54: =$D$26*$D$27^(ROW()-52) | O54: ='Seasonal Factors'!$L$15 | P54: =P53*(1+E54) | Q54: =Q53*(1+F54) | R54: =R53*(1+G54) | S54: =S53*(1+H54) | T54: =T53*(1+I54) | U54: =U53*(1+J54) | V54: =V53*(1+K54) | W54: =W53*(1+L54)
B55: 2026-11 | C55: 11 | D55: =IFERROR(IF(INDEX('CPI Data'!$I:$I,MATCH($B55,'CPI Data'!$B:$B,0))="","",INDEX('CPI Data'!$I:$I,MATCH($B55,'CPI Data'!$B:$B,0))),"") | E55: =IFERROR(INDEX(Forecast!$D:$D,MATCH($B55,Forecast!$B:$B,0)),"") | F55: =IFERROR(INDEX(Forecast!$E:$E,MATCH($B55,Forecast!$B:$B,0)),"") | G55: =IFERROR(INDEX(Forecast!$F:$F,MATCH($B55,Forecast!$B:$B,0)),"") | H55: =$D$14+($D$13-$D$14)*$D$15^(ROW()-52) | I55: =(M55+$D$20*N55)*O55 | J55: =($D$31+($D$30-$D$31)*$D$32^(ROW()-52))*O55 | K55: =IF($B55<="2026-10",$D$35,IF($B55<="2027-05",$D$36,$D$36+$D$37*(ROW()-61))) | L55: =((1+$D$40)*INDEX('CPI Data'!$E:$E,MATCH("2025-12",'CPI Data'!$B:$B,0))/INDEX('CPI Data'!$E:$E,MATCH("2026-08",'CPI Data'!$B:$B,0)))^(1/4)-1 | M55: =$D$22+$D$23*I53 | N55: =$D$26*$D$27^(ROW()-52) | O55: ='Seasonal Factors'!$L$16 | P55: =P54*(1+E55) | Q55: =Q54*(1+F55) | R55: =R54*(1+G55) | S55: =S54*(1+H55) | T55: =T54*(1+I55) | U55: =U54*(1+J55) | V55: =V54*(1+K55) | W55: =W54*(1+L55)
B56: 2026-12 | C56: 12 | D56: =IFERROR(IF(INDEX('CPI Data'!$I:$I,MATCH($B56,'CPI Data'!$B:$B,0))="","",INDEX('CPI Data'!$I:$I,MATCH($B56,'CPI Data'!$B:$B,0))),"") | E56: =IFERROR(INDEX(Forecast!$D:$D,MATCH($B56,Forecast!$B:$B,0)),"") | F56: =IFERROR(INDEX(Forecast!$E:$E,MATCH($B56,Forecast!$B:$B,0)),"") | G56: =IFERROR(INDEX(Forecast!$F:$F,MATCH($B56,Forecast!$B:$B,0)),"") | H56: =$D$14+($D$13-$D$14)*$D$15^(ROW()-52) | I56: =(M56+$D$20*N56)*O56 | J56: =($D$31+($D$30-$D$31)*$D$32^(ROW()-52))*O56 | K56: =IF($B56<="2026-10",$D$35,IF($B56<="2027-05",$D$36,$D$36+$D$37*(ROW()-61))) | L56: =((1+$D$40)*INDEX('CPI Data'!$E:$E,MATCH("2025-12",'CPI Data'!$B:$B,0))/INDEX('CPI Data'!$E:$E,MATCH("2026-08",'CPI Data'!$B:$B,0)))^(1/4)-1 | M56: =$D$22+$D$23*I54 | N56: =$D$26*$D$27^(ROW()-52) | O56: ='Seasonal Factors'!$L$17 | P56: =P55*(1+E56) | Q56: =Q55*(1+F56) | R56: =R55*(1+G56) | S56: =S55*(1+H56) | T56: =T55*(1+I56) | U56: =U55*(1+J56) | V56: =V55*(1+K56) | W56: =W55*(1+L56)
B57: 2027-01 | C57: 1 | D57: =IFERROR(IF(INDEX('CPI Data'!$I:$I,MATCH($B57,'CPI Data'!$B:$B,0))="","",INDEX('CPI Data'!$I:$I,MATCH($B57,'CPI Data'!$B:$B,0))),"") | E57: =IFERROR(INDEX(Forecast!$D:$D,MATCH($B57,Forecast!$B:$B,0)),"") | F57: =IFERROR(INDEX(Forecast!$E:$E,MATCH($B57,Forecast!$B:$B,0)),"") | G57: =IFERROR(INDEX(Forecast!$F:$F,MATCH($B57,Forecast!$B:$B,0)),"") | H57: =$D$14+($D$13-$D$14)*$D$15^(ROW()-52) | I57: =(M57+$D$20*N57)*O57 | J57: =($D$31+($D$30-$D$31)*$D$32^(ROW()-52))*O57 | K57: =IF($B57<="2026-10",$D$35,IF($B57<="2027-05",$D$36,$D$36+$D$37*(ROW()-61))) | L57: =(1+$D$41)^(1/12)-1 | M57: =$D$22+$D$23*I55 | N57: =$D$26*$D$27^(ROW()-52) | O57: ='Seasonal Factors'!$L$6 | P57: =P56*(1+E57) | Q57: =Q56*(1+F57) | R57: =R56*(1+G57) | S57: =S56*(1+H57) | T57: =T56*(1+I57) | U57: =U56*(1+J57) | V57: =V56*(1+K57) | W57: =W56*(1+L57)
B58: 2027-02 | C58: 2 | D58: =IFERROR(IF(INDEX('CPI Data'!$I:$I,MATCH($B58,'CPI Data'!$B:$B,0))="","",INDEX('CPI Data'!$I:$I,MATCH($B58,'CPI Data'!$B:$B,0))),"") | E58: =IFERROR(INDEX(Forecast!$D:$D,MATCH($B58,Forecast!$B:$B,0)),"") | F58: =IFERROR(INDEX(Forecast!$E:$E,MATCH($B58,Forecast!$B:$B,0)),"") | G58: =IFERROR(INDEX(Forecast!$F:$F,MATCH($B58,Forecast!$B:$B,0)),"") | H58: =$D$14+($D$13-$D$14)*$D$15^(ROW()-52) | I58: =(M58+$D$20*N58)*O58 | J58: =($D$31+($D$30-$D$31)*$D$32^(ROW()-52))*O58 | K58: =IF($B58<="2026-10",$D$35,IF($B58<="2027-05",$D$36,$D$36+$D$37*(ROW()-61))) | L58: =(1+$D$41)^(1/12)-1 | M58: =$D$22+$D$23*I56 | N58: =$D$26*$D$27^(ROW()-52) | O58: ='Seasonal Factors'!$L$7 | P58: =P57*(1+E58) | Q58: =Q57*(1+F58) | R58: =R57*(1+G58) | S58: =S57*(1+H58) | T58: =T57*(1+I58) | U58: =U57*(1+J58) | V58: =V57*(1+K58) | W58: =W57*(1+L58)
B59: 2027-03 | C59: 3 | D59: =IFERROR(IF(INDEX('CPI Data'!$I:$I,MATCH($B59,'CPI Data'!$B:$B,0))="","",INDEX('CPI Data'!$I:$I,MATCH($B59,'CPI Data'!$B:$B,0))),"") | E59: =IFERROR(INDEX(Forecast!$D:$D,MATCH($B59,Forecast!$B:$B,0)),"") | F59: =IFERROR(INDEX(Forecast!$E:$E,MATCH($B59,Forecast!$B:$B,0)),"") | G59: =IFERROR(INDEX(Forecast!$F:$F,MATCH($B59,Forecast!$B:$B,0)),"") | H59: =$D$14+($D$13-$D$14)*$D$15^(ROW()-52) | I59: =(M59+$D$20*N59)*O59 | J59: =($D$31+($D$30-$D$31)*$D$32^(ROW()-52))*O59 | K59: =IF($B59<="2026-10",$D$35,IF($B59<="2027-05",$D$36,$D$36+$D$37*(ROW()-61))) | L59: =(1+$D$41)^(1/12)-1 | M59: =$D$22+$D$23*I57 | N59: =$D$26*$D$27^(ROW()-52) | O59: ='Seasonal Factors'!$L$8 | P59: =P58*(1+E59) | Q59: =Q58*(1+F59) | R59: =R58*(1+G59) | S59: =S58*(1+H59) | T59: =T58*(1+I59) | U59: =U58*(1+J59) | V59: =V58*(1+K59) | W59: =W58*(1+L59)
B60: 2027-04 | C60: 4 | D60: =IFERROR(IF(INDEX('CPI Data'!$I:$I,MATCH($B60,'CPI Data'!$B:$B,0))="","",INDEX('CPI Data'!$I:$I,MATCH($B60,'CPI Data'!$B:$B,0))),"") | E60: =IFERROR(INDEX(Forecast!$D:$D,MATCH($B60,Forecast!$B:$B,0)),"") | F60: =IFERROR(INDEX(Forecast!$E:$E,MATCH($B60,Forecast!$B:$B,0)),"") | G60: =IFERROR(INDEX(Forecast!$F:$F,MATCH($B60,Forecast!$B:$B,0)),"") | H60: =$D$14+($D$13-$D$14)*$D$15^(ROW()-52) | I60: =(M60+$D$20*N60)*O60 | J60: =($D$31+($D$30-$D$31)*$D$32^(ROW()-52))*O60 | K60: =IF($B60<="2026-10",$D$35,IF($B60<="2027-05",$D$36,$D$36+$D$37*(ROW()-61))) | L60: =(1+$D$41)^(1/12)-1 | M60: =$D$22+$D$23*I58 | N60: =$D$26*$D$27^(ROW()-52) | O60: ='Seasonal Factors'!$L$9 | P60: =P59*(1+E60) | Q60: =Q59*(1+F60) | R60: =R59*(1+G60) | S60: =S59*(1+H60) | T60: =T59*(1+I60) | U60: =U59*(1+J60) | V60: =V59*(1+K60) | W60: =W59*(1+L60)
B61: 2027-05 | C61: 5 | D61: =IFERROR(IF(INDEX('CPI Data'!$I:$I,MATCH($B61,'CPI Data'!$B:$B,0))="","",INDEX('CPI Data'!$I:$I,MATCH($B61,'CPI Data'!$B:$B,0))),"") | E61: =IFERROR(INDEX(Forecast!$D:$D,MATCH($B61,Forecast!$B:$B,0)),"") | F61: =IFERROR(INDEX(Forecast!$E:$E,MATCH($B61,Forecast!$B:$B,0)),"") | G61: =IFERROR(INDEX(Forecast!$F:$F,MATCH($B61,Forecast!$B:$B,0)),"") | H61: =$D$14+($D$13-$D$14)*$D$15^(ROW()-52) | I61: =(M61+$D$20*N61)*O61 | J61: =($D$31+($D$30-$D$31)*$D$32^(ROW()-52))*O61 | K61: =IF($B61<="2026-10",$D$35,IF($B61<="2027-05",$D$36,$D$36+$D$37*(ROW()-61))) | L61: =(1+$D$41)^(1/12)-1 | M61: =$D$22+$D$23*I59 | N61: =$D$26*$D$27^(ROW()-52) | O61: ='Seasonal Factors'!$L$10 | P61: =P60*(1+E61) | Q61: =Q60*(1+F61) | R61: =R60*(1+G61) | S61: =S60*(1+H61) | T61: =T60*(1+I61) | U61: =U60*(1+J61) | V61: =V60*(1+K61) | W61: =W60*(1+L61)
B62: 2027-06 | C62: 6 | D62: =IFERROR(IF(INDEX('CPI Data'!$I:$I,MATCH($B62,'CPI Data'!$B:$B,0))="","",INDEX('CPI Data'!$I:$I,MATCH($B62,'CPI Data'!$B:$B,0))),"") | E62: =IFERROR(INDEX(Forecast!$D:$D,MATCH($B62,Forecast!$B:$B,0)),"") | F62: =IFERROR(INDEX(Forecast!$E:$E,MATCH($B62,Forecast!$B:$B,0)),"") | G62: =IFERROR(INDEX(Forecast!$F:$F,MATCH($B62,Forecast!$B:$B,0)),"") | H62: =$D$14+($D$13-$D$14)*$D$15^(ROW()-52) | I62: =(M62+$D$20*N62)*O62 | J62: =($D$31+($D$30-$D$31)*$D$32^(ROW()-52))*O62 | K62: =IF($B62<="2026-10",$D$35,IF($B62<="2027-05",$D$36,$D$36+$D$37*(ROW()-61))) | L62: =(1+$D$41)^(1/12)-1 | M62: =$D$22+$D$23*I60 | N62: =$D$26*$D$27^(ROW()-52) | O62: ='Seasonal Factors'!$L$11 | P62: =P61*(1+E62) | Q62: =Q61*(1+F62) | R62: =R61*(1+G62) | S62: =S61*(1+H62) | T62: =T61*(1+I62) | U62: =U61*(1+J62) | V62: =V61*(1+K62) | W62: =W61*(1+L62)
B63: 2027-07 | C63: 7 | D63: =IFERROR(IF(INDEX('CPI Data'!$I:$I,MATCH($B63,'CPI Data'!$B:$B,0))="","",INDEX('CPI Data'!$I:$I,MATCH($B63,'CPI Data'!$B:$B,0))),"") | E63: =IFERROR(INDEX(Forecast!$D:$D,MATCH($B63,Forecast!$B:$B,0)),"") | F63: =IFERROR(INDEX(Forecast!$E:$E,MATCH($B63,Forecast!$B:$B,0)),"") | G63: =IFERROR(INDEX(Forecast!$F:$F,MATCH($B63,Forecast!$B:$B,0)),"") | H63: =$D$14+($D$13-$D$14)*$D$15^(ROW()-52) | I63: =(M63+$D$20*N63)*O63 | J63: =($D$31+($D$30-$D$31)*$D$32^(ROW()-52))*O63 | K63: =IF($B63<="2026-10",$D$35,IF($B63<="2027-05",$D$36,$D$36+$D$37*(ROW()-61))) | L63: =(1+$D$41)^(1/12)-1 | M63: =$D$22+$D$23*I61 | N63: =$D$26*$D$27^(ROW()-52) | O63: ='Seasonal Factors'!$L$12 | P63: =P62*(1+E63) | Q63: =Q62*(1+F63) | R63: =R62*(1+G63) | S63: =S62*(1+H63) | T63: =T62*(1+I63) | U63: =U62*(1+J63) | V63: =V62*(1+K63) | W63: =W62*(1+L63)
B64: 2027-08 | C64: 8 | D64: =IFERROR(IF(INDEX('CPI Data'!$I:$I,MATCH($B64,'CPI Data'!$B:$B,0))="","",INDEX('CPI Data'!$I:$I,MATCH($B64,'CPI Data'!$B:$B,0))),"") | E64: =IFERROR(INDEX(Forecast!$D:$D,MATCH($B64,Forecast!$B:$B,0)),"") | F64: =IFERROR(INDEX(Forecast!$E:$E,MATCH($B64,Forecast!$B:$B,0)),"") | G64: =IFERROR(INDEX(Forecast!$F:$F,MATCH($B64,Forecast!$B:$B,0)),"") | H64: =$D$14+($D$13-$D$14)*$D$15^(ROW()-52) | I64: =(M64+$D$20*N64)*O64 | J64: =($D$31+($D$30-$D$31)*$D$32^(ROW()-52))*O64 | K64: =IF($B64<="2026-10",$D$35,IF($B64<="2027-05",$D$36,$D$36+$D$37*(ROW()-61))) | L64: =(1+$D$41)^(1/12)-1 | M64: =$D$22+$D$23*I62 | N64: =$D$26*$D$27^(ROW()-52) | O64: ='Seasonal Factors'!$L$13 | P64: =P63*(1+E64) | Q64: =Q63*(1+F64) | R64: =R63*(1+G64) | S64: =S63*(1+H64) | T64: =T63*(1+I64) | U64: =U63*(1+J64) | V64: =V63*(1+K64) | W64: =W63*(1+L64)
B65: 2027-09 | C65: 9 | D65: =IFERROR(IF(INDEX('CPI Data'!$I:$I,MATCH($B65,'CPI Data'!$B:$B,0))="","",INDEX('CPI Data'!$I:$I,MATCH($B65,'CPI Data'!$B:$B,0))),"") | E65: =IFERROR(INDEX(Forecast!$D:$D,MATCH($B65,Forecast!$B:$B,0)),"") | F65: =IFERROR(INDEX(Forecast!$E:$E,MATCH($B65,Forecast!$B:$B,0)),"") | G65: =IFERROR(INDEX(Forecast!$F:$F,MATCH($B65,Forecast!$B:$B,0)),"") | H65: =$D$14+($D$13-$D$14)*$D$15^(ROW()-52) | I65: =(M65+$D$20*N65)*O65 | J65: =($D$31+($D$30-$D$31)*$D$32^(ROW()-52))*O65 | K65: =IF($B65<="2026-10",$D$35,IF($B65<="2027-05",$D$36,$D$36+$D$37*(ROW()-61))) | L65: =(1+$D$41)^(1/12)-1 | M65: =$D$22+$D$23*I63 | N65: =$D$26*$D$27^(ROW()-52) | O65: ='Seasonal Factors'!$L$14 | P65: =P64*(1+E65) | Q65: =Q64*(1+F65) | R65: =R64*(1+G65) | S65: =S64*(1+H65) | T65: =T64*(1+I65) | U65: =U64*(1+J65) | V65: =V64*(1+K65) | W65: =W64*(1+L65)
B66: 2027-10 | C66: 10 | D66: =IFERROR(IF(INDEX('CPI Data'!$I:$I,MATCH($B66,'CPI Data'!$B:$B,0))="","",INDEX('CPI Data'!$I:$I,MATCH($B66,'CPI Data'!$B:$B,0))),"") | E66: =IFERROR(INDEX(Forecast!$D:$D,MATCH($B66,Forecast!$B:$B,0)),"") | F66: =IFERROR(INDEX(Forecast!$E:$E,MATCH($B66,Forecast!$B:$B,0)),"") | G66: =IFERROR(INDEX(Forecast!$F:$F,MATCH($B66,Forecast!$B:$B,0)),"") | H66: =$D$14+($D$13-$D$14)*$D$15^(ROW()-52) | I66: =(M66+$D$20*N66)*O66 | J66: =($D$31+($D$30-$D$31)*$D$32^(ROW()-52))*O66 | K66: =IF($B66<="2026-10",$D$35,IF($B66<="2027-05",$D$36,$D$36+$D$37*(ROW()-61))) | L66: =(1+$D$41)^(1/12)-1 | M66: =$D$22+$D$23*I64 | N66: =$D$26*$D$27^(ROW()-52) | O66: ='Seasonal Factors'!$L$15 | P66: =P65*(1+E66) | Q66: =Q65*(1+F66) | R66: =R65*(1+G66) | S66: =S65*(1+H66) | T66: =T65*(1+I66) | U66: =U65*(1+J66) | V66: =V65*(1+K66) | W66: =W65*(1+L66)
B67: 2027-11 | C67: 11 | D67: =IFERROR(IF(INDEX('CPI Data'!$I:$I,MATCH($B67,'CPI Data'!$B:$B,0))="","",INDEX('CPI Data'!$I:$I,MATCH($B67,'CPI Data'!$B:$B,0))),"") | E67: =IFERROR(INDEX(Forecast!$D:$D,MATCH($B67,Forecast!$B:$B,0)),"") | F67: =IFERROR(INDEX(Forecast!$E:$E,MATCH($B67,Forecast!$B:$B,0)),"") | G67: =IFERROR(INDEX(Forecast!$F:$F,MATCH($B67,Forecast!$B:$B,0)),"") | H67: =$D$14+($D$13-$D$14)*$D$15^(ROW()-52) | I67: =(M67+$D$20*N67)*O67 | J67: =($D$31+($D$30-$D$31)*$D$32^(ROW()-52))*O67 | K67: =IF($B67<="2026-10",$D$35,IF($B67<="2027-05",$D$36,$D$36+$D$37*(ROW()-61))) | L67: =(1+$D$41)^(1/12)-1 | M67: =$D$22+$D$23*I65 | N67: =$D$26*$D$27^(ROW()-52) | O67: ='Seasonal Factors'!$L$16 | P67: =P66*(1+E67) | Q67: =Q66*(1+F67) | R67: =R66*(1+G67) | S67: =S66*(1+H67) | T67: =T66*(1+I67) | U67: =U66*(1+J67) | V67: =V66*(1+K67) | W67: =W66*(1+L67)
B68: 2027-12 | C68: 12 | D68: =IFERROR(IF(INDEX('CPI Data'!$I:$I,MATCH($B68,'CPI Data'!$B:$B,0))="","",INDEX('CPI Data'!$I:$I,MATCH($B68,'CPI Data'!$B:$B,0))),"") | E68: =IFERROR(INDEX(Forecast!$D:$D,MATCH($B68,Forecast!$B:$B,0)),"") | F68: =IFERROR(INDEX(Forecast!$E:$E,MATCH($B68,Forecast!$B:$B,0)),"") | G68: =IFERROR(INDEX(Forecast!$F:$F,MATCH($B68,Forecast!$B:$B,0)),"") | H68: =$D$14+($D$13-$D$14)*$D$15^(ROW()-52) | I68: =(M68+$D$20*N68)*O68 | J68: =($D$31+($D$30-$D$31)*$D$32^(ROW()-52))*O68 | K68: =IF($B68<="2026-10",$D$35,IF($B68<="2027-05",$D$36,$D$36+$D$37*(ROW()-61))) | L68: =(1+$D$41)^(1/12)-1 | M68: =$D$22+$D$23*I66 | N68: =$D$26*$D$27^(ROW()-52) | O68: ='Seasonal Factors'!$L$17 | P68: =P67*(1+E68) | Q68: =Q67*(1+F68) | R68: =R67*(1+G68) | S68: =S67*(1+H68) | T68: =T67*(1+I68) | U68: =U67*(1+J68) | V68: =V67*(1+K68) | W68: =W67*(1+L68)
B70: THE ANSWER — where each model puts inflation in the election window
B71: Model | C71: Avg m/m Apr-Jul 2027 | D71: Window annualised | E71: y/y at Jul-2027 | F71: y/y at Sep-2027 (last print before the vote) | G71: Dec/Dec 2027 | H71: What it assumes
B72: M1 Bull scenario | C72: =AVERAGE(E60:E63) | D72: =(P63/P59)^3-1 | E72: =P63/P51-1 | F72: =P65/P53-1 | G72: =P68/P56-1 | H72: Disinflation faster than any Argentine episode since convertibility.
B73: M1 Base scenario | C73: =AVERAGE(F60:F63) | D73: =(Q63/Q59)^3-1 | E73: =Q63/Q51-1 | F73: =Q65/Q53-1 | G73: =Q68/Q56-1 | H73: Inflation converges to the crawl, not below it. Regulated runs 50-80bp above core to mid-2027.
B74: M1 Bear scenario | C74: =AVERAGE(G60:G63) | D74: =(R63/R59)^3-1 | E74: =R63/R51-1 | F74: =R65/R53-1 | G74: =R68/R56-1 | H74: The band ceiling is tested; pass-through 0.30; subsidy removal re-accelerates.
B75: M2 Inertia / mean reversion | C75: =AVERAGE(H60:H63) | D75: =(S63/S59)^3-1 | E75: =S63/S51-1 | F75: =S65/S53-1 | G75: =S68/S56-1 | H75: Pure time-series: the gap to a terminal rate decays at a constant monthly rate. No economics, which is the point — it is the null.
B76: M3 Bottom-up with band indexation | C76: =AVERAGE(I60:I63) | D76: =(T63/T59)^3-1 | E76: =T63/T51-1 | F76: =T65/T53-1 | G76: =T68/T56-1 | H76: The band indexes to CPI at t-2, FX passes into core, regulated carries a decaying premium, and the month's seasonal factor is re-imposed.
B77: M4 Seasonal carry-forward | C77: =AVERAGE(J60:J63) | D77: =(U63/U59)^3-1 | E77: =U63/U51-1 | F77: =U65/U53-1 | G77: =U68/U56-1 | H77: Takes today's DESEASONALISED trend and re-imposes the calendar. The window is seasonally soft — factor 0.86x.
B78: M5 Market-implied | C78: =AVERAGE(K60:K63) | D78: =(V63/V59)^3-1 | E78: =V63/V51-1 | F78: =V65/V53-1 | G78: =V68/V56-1 | H78: The CER breakeven the market actually trades. Sourced to May-2027, flat thereafter.
B79: M6 Consensus (REM) | C79: =AVERAGE(L60:L63) | D79: =(W63/W59)^3-1 | E79: =W63/W51-1 | F79: =W65/W53-1 | G79: =W68/W56-1 | H79: The REM's own Dec/Dec targets, distributed smoothly.
B80: Mean of the six independent models (M2-M6 plus M1 Base) | C80: =AVERAGE(C73,C75:C79) | D80: =AVERAGE(D73,D75:D79) | E80: =AVERAGE(E73,E75:E79) | F80: =AVERAGE(F73,F75:F79) | G80: =AVERAGE(G73,G75:G79) | H80: Excludes the bull and bear tails, which are scenario bounds rather than central estimates.
B82: Budget 2027 bill | G82: 0.18 | H82: Tabled 15-Sep-2026. 18.0% Dec/Dec, 21.1% average, ARS 1,847.6/USD at Dec-2027.
B83: BCRA REM 2027 (Jul round) | G83: 0.2 | H83: The August round's 2027 median could not be obtained.
B84: Market breakeven, annualised | G84: 0.246 | H84: Derived from 1.85%/month over Nov-2026 to May-2027 — the window that matters.
B85: IMF Article IV, May-2026 | G85: 0.125 | H85: Already stale: the IMF's 2026 figure of 25.0% has been exceeded by August's 21.3% YTD.
B86: M3 fixed point of the indexation loop | G86: =$D$25 | H86: What a CPI-indexed band settles at mechanically. This is the number to argue from.
B88: How to read this
B89: The window flatters the government | D89: April to July 2027 carries an average seasonal factor of 0.86x — the coolest stretch of the Argentine calendar. Whatever the trend, the monthly prints voters see in the three-to-six months before the vote will be the best-looking of the year. Every model shows it, because the seasonality is in the data, not the assumptions.
B90: The models disagree about the level, not the direction | D90: All six have inflation lower in mid-2027 than today. The spread is in how much lower, and it maps almost exactly onto one question: does the CPI-indexed band get broken, or does it run?
B91: Model 3 is the one with a mechanism | D91: It is also the one with the weakest statistical fit — R-squared 0.156 on fourteen observations — and it must be presented that way. What survives the weak fit is the fixed point: three different estimation windows all put it between 30% and 33% a year. A CPI-indexed band does not deliver 18%; it delivers roughly what you already have.
B92: The market is the outlier on the hawkish side | D92: At about 24.6% annualised over the pre-election window against a REM of 20.0% and a Budget of 18.0%, investors are paying real money to disagree with the official path. The steepest point on the entire peso curve is the May-2027 maturity.
B93: What would change the answer | D93: A break in the band mechanism. Nothing else in these models moves the 2027 number much, because every channel that matters — wages, regulated prices, the FX crawl — now indexes to trailing CPI. That is the single point of leverage, and it is a policy choice, not a forecast.

Sheet Approval Model
B2: Does inflation decide the election? A transparent scoring device
B3: NINE observations, three parameters. This organises priors. It is not a forecast, and it must not be sold as one.
B5: Health warning — read before using any number on this tab
B6: Nine usable observations against three fitted parameters. No standard errors are reportable. The specification was chosen after seeing the data.
B7: THERE IS NO PRESIDENTIAL OBSERVATION IN THE 20-40% INFLATION BAND. Every Argentine presidential election has been fought either below 20% or above 40%. 2027 will almost certainly be fought between 13% and 29%. Every number this model produces for 2027 is extrapolation, not inference.
B8: The residual is scandal and candidate quality, and it is the same order of magnitude as the macro term: the August-2025 audio scandal moved the confidence index 13.6% in a single month, more than inflation did over the same period.
B9: The coding of 2003 is a judgement call — Duhalde was an unelected caretaker who did not stand, and Kirchner won as a Peronist. On strict party continuity the incumbent party retained. Coding it as a loss, as here, is defensible but it moves the headline base rate by 11pp on its own.
B11: 1. The specification
B12: x = wL x [ ln(1+pi/100) - ln(1.20) ] + wD x D + wW x (-W)
B13: P(incumbent coalition wins) = 1 / ( 1 + exp( k x x ) )
B14: Inflation enters in LOGS. A linear level term cannot span 3.4% and 3,610% — read literally, a linear coefficient would have implied an approval fall of sixteen thousand points in 1989. ln(1.20) centres the level term at 20% y/y, the empirical break in the record.
B16: 2. Inputs and the live calculation
B17: Input | C17: Value | D17: Note
B18: pi — y/y CPI at the last print before the vote (%) | C18: 18.7 | D18: Default is the base-case Dec/Dec 2027 from the Forecast tab.
B19: D — direction of inflation | C19: -1 | D19: +1 rising, 0 flat, -1 falling, over the prior three to six months.
B20: W — direction of real wages | C20: -1 | D20: +1 rising, 0 flat, -1 falling, over the prior twelve months. Currently minus 3.0% y/y and down three months running.
B21: wL — weight on the inflation level | C21: 0.8 | D21: Fitted. Use 1.7 for the true-inflation variant.
B22: wD — weight on inflation direction | C22: 0 | D22: FITTED TO EXACTLY ZERO in both variants. Retained so the term can be stressed, not because it earns its place.
B23: wW — weight on real wages | C23: 0.7 | D23: Fitted. 0.6 in the true-inflation variant — barely moves, which is why this is the robust channel.
B24: k — slope | C24: 2.5 | D24: 3.0 in the true-inflation variant.
B26: x (the score) | C26: =$C$21*(LN(1+$C$18/100)-LN(1.2))+$C$22*$C$19+$C$23*(-$C$20)
B27: P(incumbent coalition wins) | C27: =1/(1+EXP($C$24*$C$26))
B28: Unconditional base rate | C28: =3/9 | D28: Argentine incumbents retained the presidency in 3 of the 9 elections from 1989 to 2023. This is the benchmark any model output should be compared against.
B30: 3. Fit against the historical record
B31: Election | C31: pi (y/y, %) | D31: D | E31: W | F31: P(win) | G31: Actual | H31: Hit?
B32: 1989 | C32: 3610 | D32: 1 | E32: -1 | F32: =1/(1+EXP($C$24*($C$21*(LN(1+C32/100)-LN(1.2))+$C$22*D32+$C$23*(-E32)))) | G32: 0 | H32: =IF((F32>0.5)=(G32=1),"hit","MISS")
B33: 1995 | C33: 3.4 | D33: -1 | E33: 1 | F33: =1/(1+EXP($C$24*($C$21*(LN(1+C33/100)-LN(1.2))+$C$22*D33+$C$23*(-E33)))) | G33: 1 | H33: =IF((F33>0.5)=(G33=1),"hit","MISS")
B34: 1999 | C34: -1.8 | D34: -1 | E34: -1 | F34: =1/(1+EXP($C$24*($C$21*(LN(1+C34/100)-LN(1.2))+$C$22*D34+$C$23*(-E34)))) | G34: 0 | H34: =IF((F34>0.5)=(G34=1),"hit","MISS")
B35: 2003 | C35: 13.4 | D35: -1 | E35: -1 | F35: =1/(1+EXP($C$24*($C$21*(LN(1+C35/100)-LN(1.2))+$C$22*D35+$C$23*(-E35)))) | G35: 0 | H35: =IF((F35>0.5)=(G35=1),"hit","MISS")
B36: 2007 | C36: 8.6 | D36: 1 | E36: 1 | F36: =1/(1+EXP($C$24*($C$21*(LN(1+C36/100)-LN(1.2))+$C$22*D36+$C$23*(-E36)))) | G36: 1 | H36: =IF((F36>0.5)=(G36=1),"hit","MISS")
B37: 2011 | C37: 9.9 | D37: 0 | E37: 1 | F37: =1/(1+EXP($C$24*($C$21*(LN(1+C37/100)-LN(1.2))+$C$22*D37+$C$23*(-E37)))) | G37: 1 | H37: =IF((F37>0.5)=(G37=1),"hit","MISS")
B38: 2015 | C38: 14.3 | D38: 0 | E38: 1 | F38: =1/(1+EXP($C$24*($C$21*(LN(1+C38/100)-LN(1.2))+$C$22*D38+$C$23*(-E38)))) | G38: 0 | H38: =IF((F38>0.5)=(G38=1),"hit","MISS")
B39: 2019 | C39: 53.5 | D39: 1 | E39: -1 | F39: =1/(1+EXP($C$24*($C$21*(LN(1+C39/100)-LN(1.2))+$C$22*D39+$C$23*(-E39)))) | G39: 0 | H39: =IF((F39>0.5)=(G39=1),"hit","MISS")
B40: 2023 | C40: 138.3 | D40: 1 | E40: -1 | F40: =1/(1+EXP($C$24*($C$21*(LN(1+C40/100)-LN(1.2))+$C$22*D40+$C$23*(-E40)))) | G40: 0 | H40: =IF((F40>0.5)=(G40=1),"hit","MISS")
B41: Hit rate | F41: =COUNTIF(H32:H40,"hit")&" / "&9
B42: 1983 is excluded: there was no civilian incumbent on the ballot, so it is not an economic-voting observation. Including it would inflate the 'high inflation beats the incumbent' count with a case that had nothing to do with inflation.
B43: The model misses 2015, and it misses it the same way in every specification — it predicts an incumbent win at 0.86 and CFK's coalition lost. That miss IS the model's signature: it has no term for term limits, candidate quality or twelve years of incumbency fatigue. Say so in the note rather than fudging it.
B44: 1999 is the case that kills the simple inflation story. De la Rua won against an incumbent Peronist administration running DEFLATION of minus 1.8%. Inflation was as low and as falling as it has ever been in Argentine democratic history, and the incumbent lost anyway, because real wages and employment were collapsing into the convertibility endgame.
B45: 2011 is the measured-versus-perceived caveat. CFK was re-elected with 54.11% on an official print of 9.9% when Cavallo (2013, JME 60(2)) measured true inflation near 20%. Two readings: voters were fooled, or voters voted their wallets and real wages were rising. The second is the better reading, because the first cannot explain 2015 — same official inflation, same rising real wages, and the incumbent lost.
B47: 4. Single-variable benchmarks — the most defensible result on this tab
B48: Rule | C48: Correct | D48: of | E48: Hit rate
B49: Incumbent wins iff real wages rose over the prior 12m | C49: 8 | D49: 9 | E49: =C49/D49
B50: Incumbent wins iff y/y inflation < 20% | C50: 6 | D50: 9 | E50: =C50/D50
B51: Incumbent wins iff inflation is not rising | C51: 5 | D51: 9 | E51: =C51/D51
B52: The one-variable real-wage rule matches the three-parameter model's hit rate with ZERO fitted parameters. If the note carries one number from this tab, it should be this one, not the logistic coefficients.
B54: 5. Base rates by inflation band
B55: Condition | C55: Won | D55: of | E55: Rate | F55: Note
B56: Incumbent retained the presidency | C56: 3 | D56: 9 | E56: =C56/D56 | F56: unconditional prior
B57: Won with y/y inflation >= 40% | C57: 0 | D57: 3 | E57: =C57/D57 | F57: no incumbent has ever survived 40%+
B58: Won with y/y inflation 20-40% | C58: 0 | D58: 0 | E58: n/a | F58: NO PRESIDENTIAL OBSERVATION IN THIS BAND
B59: Won with y/y inflation < 20% | C59: 3 | D59: 6 | E59: =C59/D59 | F59: a coin flip
B60: Won with real wages rising | C60: 3 | D60: 4 | E60: =C60/D60
B61: Won with real wages falling | C61: 0 | D61: 5 | E61: =C61/D61
B62: Inflation is a good VETO variable and a poor SELECTION variable. Above 40% it is close to dispositive — no Argentine incumbent has ever survived it. Below 20% it carries almost no information: the incumbent wins half the time, and the outcome is decided by real income, candidate and scandal.
B64: 6. Sensitivity — the grid that makes the argument
B65: Rows: y/y inflation at the last print before the vote. Columns: the direction of real wages over the prior twelve months. Every cell is the live formula.
B66: pi (y/y, %) | C66: Real wages FALLING | D66: Real wages FLAT | E66: Real wages RISING
B67: W = | C67: -1 | D67: 0 | E67: 1
B68: 10 | C68: =1/(1+EXP($C$24*($C$21*(LN(1+$B68/100)-LN(1.2))+$C$22*$C$19+$C$23*(-C$67)))) | D68: =1/(1+EXP($C$24*($C$21*(LN(1+$B68/100)-LN(1.2))+$C$22*$C$19+$C$23*(-D$67)))) | E68: =1/(1+EXP($C$24*($C$21*(LN(1+$B68/100)-LN(1.2))+$C$22*$C$19+$C$23*(-E$67))))
B69: 13 | C69: =1/(1+EXP($C$24*($C$21*(LN(1+$B69/100)-LN(1.2))+$C$22*$C$19+$C$23*(-C$67)))) | D69: =1/(1+EXP($C$24*($C$21*(LN(1+$B69/100)-LN(1.2))+$C$22*$C$19+$C$23*(-D$67)))) | E69: =1/(1+EXP($C$24*($C$21*(LN(1+$B69/100)-LN(1.2))+$C$22*$C$19+$C$23*(-E$67))))
