Workbook

Sheet 1 Bond inputs
A1: Argentina hard-currency curve — inputs
A2: EVERY BLUE CELL IS AN INPUT: overwrite from Bloomberg. Black cells are formulas and should not be typed over. The numbers below are ILLUSTRATIVE PLACEHOLDERS chosen only to make the arithmetic visible — they are not market levels and must be replaced before use.
A3: Holding period (years) | B3: 0.5 | C3: <- drives tabs 2 and 3
A5: Bond | B5: Maturity | C5: Coupon (%, current step) | D5: Price (clean) | E5: YTM (%) | F5: Mod. duration (years) | G5: Convexity (years squared)
A6: GD29 | B6: 2029 | C6: 1 | D6: 88 | E6: 8.5 | F6: 1.8 | G6: 4
A7: GD30 | B7: 2030 | C7: 1.75 | D7: 82 | E7: 8.2 | F7: 2.6 | G7: 9
A8: GD35 | B8: 2035 | C8: 4.125 | D8: 72 | E8: 7.9 | F8: 5.4 | G8: 36
A9: GD38 | B9: 2038 | C9: 4.25 | D9: 79 | E9: 7.6 | F9: 5 | G9: 31
A10: GD41 | B10: 2041 | C10: 3.5 | D10: 68 | E10: 7.7 | F10: 6.1 | G10: 45
A11: GD46 | B11: 2046 | C11: 4.125 | D11: 70 | E11: 7.3 | F11: 6.3 | G11: 48
A13: UNITS — read this once. All rates and returns are in PERCENT UNITS: 8.50 means 8.5%, not 0.085. All yield moves are in BASIS POINTS. Mixing the two is the only way to get this workbook wrong.
A14: Bloomberg fields: coupon CPN, clean price PX_LAST, yield YLD_YTM_MID, modified duration DUR_ADJ_MID (use OAD if you prefer), convexity CVX_MID. CONVEXITY SCALE MATTERS: this model wants years squared, so the price effect is 0.5 x CVX x (dy in decimals)^2 — roughly 36 for a 5.4-year bond. Bloomberg quotes CVX_MID divided by 100, so MULTIPLY THE BLOOMBERG NUMBER BY 100 before pasting. Getting this wrong silently kills the convexity benefit and you will not see an error.
A15: The globals amortise, so modified duration — not maturity — is the right risk measure, and it is why GD29 and GD46 behave completely differently on near-identical yields.
A16: Coupon = the step currently in effect, not the weighted average over the bond's life. The step-up schedule is why the cash half of carry grows over time on the long bonds.

Sheet 2 Carry cushion
A1: Carry cushion — how far yields can widen before you lose money
A2: The headline 'you accrue ~4% in six months' is only interesting relative to what it protects against. Carry divided by duration converts it into basis points of widening, which is the unit the market actually moves in.
A5: Bond | B5: Holding period (yrs) | C5: Carry if yields unchanged (%) | D5: of which: cash coupon (%) | E5: of which: pull-to-par (%) | F5: Mod. duration (years) | G5: Breakeven widening — duration only (bp) | H5: Breakeven widening — with convexity (bp) | I5: Breakeven end price
A6: ='1 Bond inputs'!A6 -> GD29 | B6: ='1 Bond inputs'!$B$3 -> 0.5 | C6: ='1 Bond inputs'!E6*$B6 -> 4.25 | D6: ='1 Bond inputs'!C6*$B6/'1 Bond inputs'!D6*100 -> 0.56818182 | E6: =C6-D6 -> 3.6818182 | F6: ='1 Bond inputs'!F6 -> 1.8 | G6: =C6/100/F6*10000 -> 236.11111 | H6: =(F6-SQRT(F6^2-2*'1 Bond inputs'!G6*C6/100))/'1 Bond inputs'!G6*10000 -> 242.65341 | I6: ='1 Bond inputs'!D6-'1 Bond inputs'!C6*$B6 -> 87.5
A7: ='1 Bond inputs'!A7 -> GD30 | B7: ='1 Bond inputs'!$B$3 -> 0.5 | C7: ='1 Bond inputs'!E7*$B7 -> 4.1 | D7: ='1 Bond inputs'!C7*$B7/'1 Bond inputs'!D7*100 -> 1.0670732 | E7: =C7-D7 -> 3.0329268 | F7: ='1 Bond inputs'!F7 -> 2.6 | G7: =C7/100/F7*10000 -> 157.69231 | H7: =(F7-SQRT(F7^2-2*'1 Bond inputs'!G7*C7/100))/'1 Bond inputs'!G7*10000 -> 162.24848 | I7: ='1 Bond inputs'!D7-'1 Bond inputs'!C7*$B7 -> 81.125
A8: ='1 Bond inputs'!A8 -> GD35 | B8: ='1 Bond inputs'!$B$3 -> 0.5 | C8: ='1 Bond inputs'!E8*$B8 -> 3.95 | D8: ='1 Bond inputs'!C8*$B8/'1 Bond inputs'!D8*100 -> 2.8645833 | E8: =C8-D8 -> 1.0854167 | F8: ='1 Bond inputs'!F8 -> 5.4 | G8: =C8/100/F8*10000 -> 73.148148 | H8: =(F8-SQRT(F8^2-2*'1 Bond inputs'!G8*C8/100))/'1 Bond inputs'!G8*10000 -> 75.024367 | I8: ='1 Bond inputs'!D8-'1 Bond inputs'!C8*$B8 -> 69.9375
A9: ='1 Bond inputs'!A9 -> GD38 | B9: ='1 Bond inputs'!$B$3 -> 0.5 | C9: ='1 Bond inputs'!E9*$B9 -> 3.8 | D9: ='1 Bond inputs'!C9*$B9/'1 Bond inputs'!D9*100 -> 2.6898734 | E9: =C9-D9 -> 1.1101266 | F9: ='1 Bond inputs'!F9 -> 5 | G9: =C9/100/F9*10000 -> 76 | H9: =(F9-SQRT(F9^2-2*'1 Bond inputs'!G9*C9/100))/'1 Bond inputs'!G9*10000 -> 77.880254 | I9: ='1 Bond inputs'!D9-'1 Bond inputs'!C9*$B9 -> 76.875
A10: ='1 Bond inputs'!A10 -> GD41 | B10: ='1 Bond inputs'!$B$3 -> 0.5 | C10: ='1 Bond inputs'!E10*$B10 -> 3.85 | D10: ='1 Bond inputs'!C10*$B10/'1 Bond inputs'!D10*100 -> 2.5735294 | E10: =C10-D10 -> 1.2764706 | F10: ='1 Bond inputs'!F10 -> 6.1 | G10: =C10/100/F10*10000 -> 63.114754 | H10: =(F10-SQRT(F10^2-2*'1 Bond inputs'!G10*C10/100))/'1 Bond inputs'!G10*10000 -> 64.65674 | I10: ='1 Bond inputs'!D10-'1 Bond inputs'!C10*$B10 -> 66.25
A11: ='1 Bond inputs'!A11 -> GD46 | B11: ='1 Bond inputs'!$B$3 -> 0.5 | C11: ='1 Bond inputs'!E11*$B11 -> 3.65 | D11: ='1 Bond inputs'!C11*$B11/'1 Bond inputs'!D11*100 -> 2.9464286 | E11: =C11-D11 -> 0.70357143 | F11: ='1 Bond inputs'!F11 -> 6.3 | G11: =C11/100/F11*10000 -> 57.936508 | H11: =(F11-SQRT(F11^2-2*'1 Bond inputs'!G11*C11/100))/'1 Bond inputs'!G11*10000 -> 59.274994 | I11: ='1 Bond inputs'!D11-'1 Bond inputs'!C11*$B11 -> 67.9375
A13: READ THE CHART THIS WAY: same yield, same 4% headline, and the front end absorbs roughly twice the widening the long end does. That gap is the entire point — it is invisible on a yield screen and it is what actually determines whether the trade works.
A14: The stacked chart splits the carry into the part you bank and the part you only book if the market cooperates. On a deep-discount bond the second bar is the larger one, which is why 'I'm getting paid 8% to wait' overstates what is genuinely being banked.
A15: Breakeven end price = price - coupon x horizon: the level the bond can fall to and still leave you flat. It sits below today's price because a discount bond would otherwise have accreted upward over the period.
A16: Duration/convexity approximation, not full cashflow repricing. It is accurate to a few bp for moves inside roughly +/-200bp and understates the cushion for very large moves. For a hard number on a big shock, reprice the schedule.

Sheet 3 Total return grid
A1: Total return over the holding period vs. parallel yield shift
A2: The sensitivity table. Read down a column to find where each bond flips from positive to negative — that crossing point is the cushion in tab 2, and the chart shows it as the line crossing zero.
A5: Yield change (bp) | B5: ='2 Carry cushion'!A6 -> GD29 | C5: ='2 Carry cushion'!A7 -> GD30 | D5: ='2 Carry cushion'!A8 -> GD35 | E5: ='2 Carry cushion'!A9 -> GD38 | F5: ='2 Carry cushion'!A10 -> GD41 | G5: ='2 Carry cushion'!A11 -> GD46
A6: -300 | B6: ='2 Carry cushion'!$C$6-'2 Carry cushion'!$F$6*($A6/10000)*100+0.5*'1 Bond inputs'!$G$6*($A6/10000)^2*100 -> 9.83 | C6: ='2 Carry cushion'!$C$7-'2 Carry cushion'!$F$7*($A6/10000)*100+0.5*'1 Bond inputs'!$G$7*($A6/10000)^2*100 -> 12.305 | D6: ='2 Carry cushion'!$C$8-'2 Carry cushion'!$F$8*($A6/10000)*100+0.5*'1 Bond inputs'!$G$8*($A6/10000)^2*100 -> 21.77 | E6: ='2 Carry cushion'!$C$9-'2 Carry cushion'!$F$9*($A6/10000)*100+0.5*'1 Bond inputs'!$G$9*($A6/10000)^2*100 -> 20.195 | F6: ='2 Carry cushion'!$C$10-'2 Carry cushion'!$F$10*($A6/10000)*100+0.5*'1 Bond inputs'!$G$10*($A6/10000)^2*100 -> 24.175 | G6: ='2 Carry cushion'!$C$11-'2 Carry cushion'!$F$11*($A6/10000)*100+0.5*'1 Bond inputs'!$G$11*($A6/10000)^2*100 -> 24.71
A7: -250 | B7: ='2 Carry cushion'!$C$6-'2 Carry cushion'!$F$6*($A7/10000)*100+0.5*'1 Bond inputs'!$G$6*($A7/10000)^2*100 -> 8.875 | C7: ='2 Carry cushion'!$C$7-'2 Carry cushion'!$F$7*($A7/10000)*100+0.5*'1 Bond inputs'!$G$7*($A7/10000)^2*100 -> 10.88125 | D7: ='2 Carry cushion'!$C$8-'2 Carry cushion'!$F$8*($A7/10000)*100+0.5*'1 Bond inputs'!$G$8*($A7/10000)^2*100 -> 18.575 | E7: ='2 Carry cushion'!$C$9-'2 Carry cushion'!$F$9*($A7/10000)*100+0.5*'1 Bond inputs'!$G$9*($A7/10000)^2*100 -> 17.26875 | F7: ='2 Carry cushion'!$C$10-'2 Carry cushion'!$F$10*($A7/10000)*100+0.5*'1 Bond inputs'!$G$10*($A7/10000)^2*100 -> 20.50625 | G7: ='2 Carry cushion'!$C$11-'2 Carry cushion'!$F$11*($A7/10000)*100+0.5*'1 Bond inputs'!$G$11*($A7/10000)^2*100 -> 20.9
A8: -200 | B8: ='2 Carry cushion'!$C$6-'2 Carry cushion'!$F$6*($A8/10000)*100+0.5*'1 Bond inputs'!$G$6*($A8/10000)^2*100 -> 7.93 | C8: ='2 Carry cushion'!$C$7-'2 Carry cushion'!$F$7*($A8/10000)*100+0.5*'1 Bond inputs'!$G$7*($A8/10000)^2*100 -> 9.48 | D8: ='2 Carry cushion'!$C$8-'2 Carry cushion'!$F$8*($A8/10000)*100+0.5*'1 Bond inputs'!$G$8*($A8/10000)^2*100 -> 15.47 | E8: ='2 Carry cushion'!$C$9-'2 Carry cushion'!$F$9*($A8/10000)*100+0.5*'1 Bond inputs'!$G$9*($A8/10000)^2*100 -> 14.42 | F8: ='2 Carry cushion'!$C$10-'2 Carry cushion'!$F$10*($A8/10000)*100+0.5*'1 Bond inputs'!$G$10*($A8/10000)^2*100 -> 16.95 | G8: ='2 Carry cushion'!$C$11-'2 Carry cushion'!$F$11*($A8/10000)*100+0.5*'1 Bond inputs'!$G$11*($A8/10000)^2*100 -> 17.21
A9: -150 | B9: ='2 Carry cushion'!$C$6-'2 Carry cushion'!$F$6*($A9/10000)*100+0.5*'1 Bond inputs'!$G$6*($A9/10000)^2*100 -> 6.995 | C9: ='2 Carry cushion'!$C$7-'2 Carry cushion'!$F$7*($A9/10000)*100+0.5*'1 Bond inputs'!$G$7*($A9/10000)^2*100 -> 8.10125 | D9: ='2 Carry cushion'!$C$8-'2 Carry cushion'!$F$8*($A9/10000)*100+0.5*'1 Bond inputs'!$G$8*($A9/10000)^2*100 -> 12.455 | E9: ='2 Carry cushion'!$C$9-'2 Carry cushion'!$F$9*($A9/10000)*100+0.5*'1 Bond inputs'!$G$9*($A9/10000)^2*100 -> 11.64875 | F9: ='2 Carry cushion'!$C$10-'2 Carry cushion'!$F$10*($A9/10000)*100+0.5*'1 Bond inputs'!$G$10*($A9/10000)^2*100 -> 13.50625 | G9: ='2 Carry cushion'!$C$11-'2 Carry cushion'!$F$11*($A9/10000)*100+0.5*'1 Bond inputs'!$G$11*($A9/10000)^2*100 -> 13.64
A10: -100 | B10: ='2 Carry cushion'!$C$6-'2 Carry cushion'!$F$6*($A10/10000)*100+0.5*'1 Bond inputs'!$G$6*($A10/10000)^2*100 -> 6.07 | C10: ='2 Carry cushion'!$C$7-'2 Carry cushion'!$F$7*($A10/10000)*100+0.5*'1 Bond inputs'!$G$7*($A10/10000)^2*100 -> 6.745 | D10: ='2 Carry cushion'!$C$8-'2 Carry cushion'!$F$8*($A10/10000)*100+0.5*'1 Bond inputs'!$G$8*($A10/10000)^2*100 -> 9.53 | E10: ='2 Carry cushion'!$C$9-'2 Carry cushion'!$F$9*($A10/10000)*100+0.5*'1 Bond inputs'!$G$9*($A10/10000)^2*100 -> 8.955 | F10: ='2 Carry cushion'!$C$10-'2 Carry cushion'!$F$10*($A10/10000)*100+0.5*'1 Bond inputs'!$G$10*($A10/10000)^2*100 -> 10.175 | G10: ='2 Carry cushion'!$C$11-'2 Carry cushion'!$F$11*($A10/10000)*100+0.5*'1 Bond inputs'!$G$11*($A10/10000)^2*100 -> 10.19
A11: -50 | B11: ='2 Carry cushion'!$C$6-'2 Carry cushion'!$F$6*($A11/10000)*100+0.5*'1 Bond inputs'!$G$6*($A11/10000)^2*100 -> 5.155 | C11: ='2 Carry cushion'!$C$7-'2 Carry cushion'!$F$7*($A11/10000)*100+0.5*'1 Bond inputs'!$G$7*($A11/10000)^2*100 -> 5.41125 | D11: ='2 Carry cushion'!$C$8-'2 Carry cushion'!$F$8*($A11/10000)*100+0.5*'1 Bond inputs'!$G$8*($A11/10000)^2*100 -> 6.695 | E11: ='2 Carry cushion'!$C$9-'2 Carry cushion'!$F$9*($A11/10000)*100+0.5*'1 Bond inputs'!$G$9*($A11/10000)^2*100 -> 6.33875 | F11: ='2 Carry cushion'!$C$10-'2 Carry cushion'!$F$10*($A11/10000)*100+0.5*'1 Bond inputs'!$G$10*($A11/10000)^2*100 -> 6.95625 | G11: ='2 Carry cushion'!$C$11-'2 Carry cushion'!$F$11*($A11/10000)*100+0.5*'1 Bond inputs'!$G$11*($A11/10000)^2*100 -> 6.86
A12: 0 | B12: ='2 Carry cushion'!$C$6-'2 Carry cushion'!$F$6*($A12/10000)*100+0.5*'1 Bond inputs'!$G$6*($A12/10000)^2*100 -> 4.25 | C12: ='2 Carry cushion'!$C$7-'2 Carry cushion'!$F$7*($A12/10000)*100+0.5*'1 Bond inputs'!$G$7*($A12/10000)^2*100 -> 4.1 | D12: ='2 Carry cushion'!$C$8-'2 Carry cushion'!$F$8*($A12/10000)*100+0.5*'1 Bond inputs'!$G$8*($A12/10000)^2*100 -> 3.95 | E12: ='2 Carry cushion'!$C$9-'2 Carry cushion'!$F$9*($A12/10000)*100+0.5*'1 Bond inputs'!$G$9*($A12/10000)^2*100 -> 3.8 | F12: ='2 Carry cushion'!$C$10-'2 Carry cushion'!$F$10*($A12/10000)*100+0.5*'1 Bond inputs'!$G$10*($A12/10000)^2*100 -> 3.85 | G12: ='2 Carry cushion'!$C$11-'2 Carry cushion'!$F$11*($A12/10000)*100+0.5*'1 Bond inputs'!$G$11*($A12/10000)^2*100 -> 3.65
A13: 50 | B13: ='2 Carry cushion'!$C$6-'2 Carry cushion'!$F$6*($A13/10000)*100+0.5*'1 Bond inputs'!$G$6*($A13/10000)^2*100 -> 3.355 | C13: ='2 Carry cushion'!$C$7-'2 Carry cushion'!$F$7*($A13/10000)*100+0.5*'1 Bond inputs'!$G$7*($A13/10000)^2*100 -> 2.81125 | D13: ='2 Carry cushion'!$C$8-'2 Carry cushion'!$F$8*($A13/10000)*100+0.5*'1 Bond inputs'!$G$8*($A13/10000)^2*100 -> 1.295 | E13: ='2 Carry cushion'!$C$9-'2 Carry cushion'!$F$9*($A13/10000)*100+0.5*'1 Bond inputs'!$G$9*($A13/10000)^2*100 -> 1.33875 | F13: ='2 Carry cushion'!$C$10-'2 Carry cushion'!$F$10*($A13/10000)*100+0.5*'1 Bond inputs'!$G$10*($A13/10000)^2*100 -> 0.85625 | G13: ='2 Carry cushion'!$C$11-'2 Carry cushion'!$F$11*($A13/10000)*100+0.5*'1 Bond inputs'!$G$11*($A13/10000)^2*100 -> 0.56
A14: 100 | B14: ='2 Carry cushion'!$C$6-'2 Carry cushion'!$F$6*($A14/10000)*100+0.5*'1 Bond inputs'!$G$6*($A14/10000)^2*100 -> 2.47 | C14: ='2 Carry cushion'!$C$7-'2 Carry cushion'!$F$7*($A14/10000)*100+0.5*'1 Bond inputs'!$G$7*($A14/10000)^2*100 -> 1.545 | D14: ='2 Carry cushion'!$C$8-'2 Carry cushion'!$F$8*($A14/10000)*100+0.5*'1 Bond inputs'!$G$8*($A14/10000)^2*100 -> -1.27 | E14: ='2 Carry cushion'!$C$9-'2 Carry cushion'!$F$9*($A14/10000)*100+0.5*'1 Bond inputs'!$G$9*($A14/10000)^2*100 -> -1.045 | F14: ='2 Carry cushion'!$C$10-'2 Carry cushion'!$F$10*($A14/10000)*100+0.5*'1 Bond inputs'!$G$10*($A14/10000)^2*100 -> -2.025 | G14: ='2 Carry cushion'!$C$11-'2 Carry cushion'!$F$11*($A14/10000)*100+0.5*'1 Bond inputs'!$G$11*($A14/10000)^2*100 -> -2.41
A15: 150 | B15: ='2 Carry cushion'!$C$6-'2 Carry cushion'!$F$6*($A15/10000)*100+0.5*'1 Bond inputs'!$G$6*($A15/10000)^2*100 -> 1.595 | C15: ='2 Carry cushion'!$C$7-'2 Carry cushion'!$F$7*($A15/10000)*100+0.5*'1 Bond inputs'!$G$7*($A15/10000)^2*100 -> 0.30125 | D15: ='2 Carry cushion'!$C$8-'2 Carry cushion'!$F$8*($A15/10000)*100+0.5*'1 Bond inputs'!$G$8*($A15/10000)^2*100 -> -3.745 | E15: ='2 Carry cushion'!$C$9-'2 Carry cushion'!$F$9*($A15/10000)*100+0.5*'1 Bond inputs'!$G$9*($A15/10000)^2*100 -> -3.35125 | F15: ='2 Carry cushion'!$C$10-'2 Carry cushion'!$F$10*($A15/10000)*100+0.5*'1 Bond inputs'!$G$10*($A15/10000)^2*100 -> -4.79375 | G15: ='2 Carry cushion'!$C$11-'2 Carry cushion'!$F$11*($A15/10000)*100+0.5*'1 Bond inputs'!$G$11*($A15/10000)^2*100 -> -5.26
A16: 200 | B16: ='2 Carry cushion'!$C$6-'2 Carry cushion'!$F$6*($A16/10000)*100+0.5*'1 Bond inputs'!$G$6*($A16/10000)^2*100 -> 0.73 | C16: ='2 Carry cushion'!$C$7-'2 Carry cushion'!$F$7*($A16/10000)*100+0.5*'1 Bond inputs'!$G$7*($A16/10000)^2*100 -> -0.92 | D16: ='2 Carry cushion'!$C$8-'2 Carry cushion'!$F$8*($A16/10000)*100+0.5*'1 Bond inputs'!$G$8*($A16/10000)^2*100 -> -6.13 | E16: ='2 Carry cushion'!$C$9-'2 Carry cushion'!$F$9*($A16/10000)*100+0.5*'1 Bond inputs'!$G$9*($A16/10000)^2*100 -> -5.58 | F16: ='2 Carry cushion'!$C$10-'2 Carry cushion'!$F$10*($A16/10000)*100+0.5*'1 Bond inputs'!$G$10*($A16/10000)^2*100 -> -7.45 | G16: ='2 Carry cushion'!$C$11-'2 Carry cushion'!$F$11*($A16/10000)*100+0.5*'1 Bond inputs'!$G$11*($A16/10000)^2*100 -> -7.99
A17: 250 | B17: ='2 Carry cushion'!$C$6-'2 Carry cushion'!$F$6*($A17/10000)*100+0.5*'1 Bond inputs'!$G$6*($A17/10000)^2*100 -> -0.125 | C17: ='2 Carry cushion'!$C$7-'2 Carry cushion'!$F$7*($A17/10000)*100+0.5*'1 Bond inputs'!$G$7*($A17/10000)^2*100 -> -2.11875 | D17: ='2 Carry cushion'!$C$8-'2 Carry cushion'!$F$8*($A17/10000)*100+0.5*'1 Bond inputs'!$G$8*($A17/10000)^2*100 -> -8.425 | E17: ='2 Carry cushion'!$C$9-'2 Carry cushion'!$F$9*($A17/10000)*100+0.5*'1 Bond inputs'!$G$9*($A17/10000)^2*100 -> -7.73125 | F17: ='2 Carry cushion'!$C$10-'2 Carry cushion'!$F$10*($A17/10000)*100+0.5*'1 Bond inputs'!$G$10*($A17/10000)^2*100 -> -9.99375 | G17: ='2 Carry cushion'!$C$11-'2 Carry cushion'!$F$11*($A17/10000)*100+0.5*'1 Bond inputs'!$G$11*($A17/10000)^2*100 -> -10.6
... A22: 500 | B22: ='2 Carry cushion'!$C$6-'2 Carry cushion'!$F$6*($A22/10000)*100+0.5*'1 Bond inputs'!$G$6*($A22/10000)^2*100 -> -4.25 | C22: ='2 Carry cushion'!$C$7-'2 Carry cushion'!$F$7*($A22/10000)*100+0.5*'1 Bond inputs'!$G$7*($A22/10000)^2*100 -> -7.775 | D22: ='2 Carry cushion'!$C$8-'2 Carry cushion'!$F$8*($A22/10000)*100+0.5*'1 Bond inputs'!$G$8*($A22/10000)^2*100 -> -18.55 | E22: ='2 Carry cushion'!$C$9-'2 Carry cushion'!$F$9*($A22/10000)*100+0.5*'1 Bond inputs'!$G$9*($A22/10000)^2*100 -> -17.325 | F22: ='2 Carry cushion'!$C$10-'2 Carry cushion'!$F$10*($A22/10000)*100+0.5*'1 Bond inputs'!$G$10*($A22/10000)^2*100 -> -21.025 | G22: ='2 Carry cushion'!$C$11-'2 Carry cushion'!$F$11*($A22/10000)*100+0.5*'1 Bond inputs'!$G$11*($A22/10000)^2*100 -> -21.85
A24: Left column is an input in the sense that you can change the range — the row labels drive the calculation, so overwrite them to zoom in on the region you care about.
A25: Every column crosses zero at a different place despite the yields sitting in a 120bp band. That dispersion is duration, and it is the whole trade.

Sheet 4 Cushion by horizon
A1: The cushion builds with time
A2: Breakeven widening in basis points, by holding period. Carry accrues linearly while duration barely moves, so protection grows roughly in a straight line the longer you are prepared to sit.
A5: Holding period (months) | B5: ='2 Carry cushion'!A6 -> GD29 | C5: ='2 Carry cushion'!A7 -> GD30 | D5: ='2 Carry cushion'!A8 -> GD35 | E5: ='2 Carry cushion'!A9 -> GD38 | F5: ='2 Carry cushion'!A10 -> GD41 | G5: ='2 Carry cushion'!A11 -> GD46
A6: 1 | B6: ='1 Bond inputs'!$E$6/100*($A6/12)/'1 Bond inputs'!$F$6*10000 -> 39.351852 | C6: ='1 Bond inputs'!$E$7/100*($A6/12)/'1 Bond inputs'!$F$7*10000 -> 26.282051 | D6: ='1 Bond inputs'!$E$8/100*($A6/12)/'1 Bond inputs'!$F$8*10000 -> 12.191358 | E6: ='1 Bond inputs'!$E$9/100*($A6/12)/'1 Bond inputs'!$F$9*10000 -> 12.666667 | F6: ='1 Bond inputs'!$E$10/100*($A6/12)/'1 Bond inputs'!$F$10*10000 -> 10.519126 | G6: ='1 Bond inputs'!$E$11/100*($A6/12)/'1 Bond inputs'!$F$11*10000 -> 9.6560847
A7: 2 | B7: ='1 Bond inputs'!$E$6/100*($A7/12)/'1 Bond inputs'!$F$6*10000 -> 78.703704 | C7: ='1 Bond inputs'!$E$7/100*($A7/12)/'1 Bond inputs'!$F$7*10000 -> 52.564103 | D7: ='1 Bond inputs'!$E$8/100*($A7/12)/'1 Bond inputs'!$F$8*10000 -> 24.382716 | E7: ='1 Bond inputs'!$E$9/100*($A7/12)/'1 Bond inputs'!$F$9*10000 -> 25.333333 | F7: ='1 Bond inputs'!$E$10/100*($A7/12)/'1 Bond inputs'!$F$10*10000 -> 21.038251 | G7: ='1 Bond inputs'!$E$11/100*($A7/12)/'1 Bond inputs'!$F$11*10000 -> 19.312169
A8: 3 | B8: ='1 Bond inputs'!$E$6/100*($A8/12)/'1 Bond inputs'!$F$6*10000 -> 118.05556 | C8: ='1 Bond inputs'!$E$7/100*($A8/12)/'1 Bond inputs'!$F$7*10000 -> 78.846154 | D8: ='1 Bond inputs'!$E$8/100*($A8/12)/'1 Bond inputs'!$F$8*10000 -> 36.574074 | E8: ='1 Bond inputs'!$E$9/100*($A8/12)/'1 Bond inputs'!$F$9*10000 -> 38 | F8: ='1 Bond inputs'!$E$10/100*($A8/12)/'1 Bond inputs'!$F$10*10000 -> 31.557377 | G8: ='1 Bond inputs'!$E$11/100*($A8/12)/'1 Bond inputs'!$F$11*10000 -> 28.968254
A9: 4 | B9: ='1 Bond inputs'!$E$6/100*($A9/12)/'1 Bond inputs'!$F$6*10000 -> 157.40741 | C9: ='1 Bond inputs'!$E$7/100*($A9/12)/'1 Bond inputs'!$F$7*10000 -> 105.12821 | D9: ='1 Bond inputs'!$E$8/100*($A9/12)/'1 Bond inputs'!$F$8*10000 -> 48.765432 | E9: ='1 Bond inputs'!$E$9/100*($A9/12)/'1 Bond inputs'!$F$9*10000 -> 50.666667 | F9: ='1 Bond inputs'!$E$10/100*($A9/12)/'1 Bond inputs'!$F$10*10000 -> 42.076503 | G9: ='1 Bond inputs'!$E$11/100*($A9/12)/'1 Bond inputs'!$F$11*10000 -> 38.624339
A10: 6 | B10: ='1 Bond inputs'!$E$6/100*($A10/12)/'1 Bond inputs'!$F$6*10000 -> 236.11111 | C10: ='1 Bond inputs'!$E$7/100*($A10/12)/'1 Bond inputs'!$F$7*10000 -> 157.69231 | D10: ='1 Bond inputs'!$E$8/100*($A10/12)/'1 Bond inputs'!$F$8*10000 -> 73.148148 | E10: ='1 Bond inputs'!$E$9/100*($A10/12)/'1 Bond inputs'!$F$9*10000 -> 76 | F10: ='1 Bond inputs'!$E$10/100*($A10/12)/'1 Bond inputs'!$F$10*10000 -> 63.114754 | G10: ='1 Bond inputs'!$E$11/100*($A10/12)/'1 Bond inputs'!$F$11*10000 -> 57.936508
A11: 9 | B11: ='1 Bond inputs'!$E$6/100*($A11/12)/'1 Bond inputs'!$F$6*10000 -> 354.16667 | C11: ='1 Bond inputs'!$E$7/100*($A11/12)/'1 Bond inputs'!$F$7*10000 -> 236.53846 | D11: ='1 Bond inputs'!$E$8/100*($A11/12)/'1 Bond inputs'!$F$8*10000 -> 109.72222 | E11: ='1 Bond inputs'!$E$9/100*($A11/12)/'1 Bond inputs'!$F$9*10000 -> 114 | F11: ='1 Bond inputs'!$E$10/100*($A11/12)/'1 Bond inputs'!$F$10*10000 -> 94.672131 | G11: ='1 Bond inputs'!$E$11/100*($A11/12)/'1 Bond inputs'!$F$11*10000 -> 86.904762
A12: 12 | B12: ='1 Bond inputs'!$E$6/100*($A12/12)/'1 Bond inputs'!$F$6*10000 -> 472.22222 | C12: ='1 Bond inputs'!$E$7/100*($A12/12)/'1 Bond inputs'!$F$7*10000 -> 315.38462 | D12: ='1 Bond inputs'!$E$8/100*($A12/12)/'1 Bond inputs'!$F$8*10000 -> 146.2963 | E12: ='1 Bond inputs'!$E$9/100*($A12/12)/'1 Bond inputs'!$F$9*10000 -> 152 | F12: ='1 Bond inputs'!$E$10/100*($A12/12)/'1 Bond inputs'!$F$10*10000 -> 126.22951 | G12: ='1 Bond inputs'!$E$11/100*($A12/12)/'1 Bond inputs'!$F$11*10000 -> 115.87302
A13: 18 | B13: ='1 Bond inputs'!$E$6/100*($A13/12)/'1 Bond inputs'!$F$6*10000 -> 708.33333 | C13: ='1 Bond inputs'!$E$7/100*($A13/12)/'1 Bond inputs'!$F$7*10000 -> 473.07692 | D13: ='1 Bond inputs'!$E$8/100*($A13/12)/'1 Bond inputs'!$F$8*10000 -> 219.44444 | E13: ='1 Bond inputs'!$E$9/100*($A13/12)/'1 Bond inputs'!$F$9*10000 -> 228 | F13: ='1 Bond inputs'!$E$10/100*($A13/12)/'1 Bond inputs'!$F$10*10000 -> 189.34426 | G13: ='1 Bond inputs'!$E$11/100*($A13/12)/'1 Bond inputs'!$F$11*10000 -> 173.80952
A14: 24 | B14: ='1 Bond inputs'!$E$6/100*($A14/12)/'1 Bond inputs'!$F$6*10000 -> 944.44444 | C14: ='1 Bond inputs'!$E$7/100*($A14/12)/'1 Bond inputs'!$F$7*10000 -> 630.76923 | D14: ='1 Bond inputs'!$E$8/100*($A14/12)/'1 Bond inputs'!$F$8*10000 -> 292.59259 | E14: ='1 Bond inputs'!$E$9/100*($A14/12)/'1 Bond inputs'!$F$9*10000 -> 304 | F14: ='1 Bond inputs'!$E$10/100*($A14/12)/'1 Bond inputs'!$F$10*10000 -> 252.45902 | G14: ='1 Bond inputs'!$E$11/100*($A14/12)/'1 Bond inputs'!$F$11*10000 -> 231.74603
A15: 36 | B15: ='1 Bond inputs'!$E$6/100*($A15/12)/'1 Bond inputs'!$F$6*10000 -> 1416.6667 | C15: ='1 Bond inputs'!$E$7/100*($A15/12)/'1 Bond inputs'!$F$7*10000 -> 946.15385 | D15: ='1 Bond inputs'!$E$8/100*($A15/12)/'1 Bond inputs'!$F$8*10000 -> 438.88889 | E15: ='1 Bond inputs'!$E$9/100*($A15/12)/'1 Bond inputs'!$F$9*10000 -> 456 | F15: ='1 Bond inputs'!$E$10/100*($A15/12)/'1 Bond inputs'!$F$10*10000 -> 378.68852 | G15: ='1 Bond inputs'!$E$11/100*($A15/12)/'1 Bond inputs'!$F$11*10000 -> 347.61905
A17: Duration-only breakeven, so it is the conservative version of tab 2 column H. It also ignores roll-down, which on a steep curve is a second source of cushion.
A18: This tab is independent of the holding-period input on tab 1 — it sweeps the horizon deliberately. Tab 1's cell fixes the single horizon used everywhere else.

Sheet 5 Spread move check
A1: Is the cushion big relative to how this market actually moves?
A2: A cushion only means something next to the realised distribution of moves. Paste a real spread history over column B and this tab answers the only question that matters: how often has a six-month move been larger than the protection you are being paid?
A3: Periods ahead (rows) | B3: 6 | C3: <- 6 with monthly data; set to 126 and paste daily data if you prefer
A5: Month | B5: Spread (bp) | C5: Spread 6m later (bp) | D5: Change (bp) | E5: Absolute change (bp) | G5: Distribution of six-month absolute moves
A6: Sep-2022 | B6: 2450 | C6: =INDEX($B$6:$B$53,ROW()-5+$B$3) -> 2350 | D6: =C6-B6 -> -100 | E6: =ABS(D6) -> 100 | G6: Median (bp) | H6: =MEDIAN($E$6:$E$47) -> 200
A7: Oct-2022 | B7: 2600 | C7: =INDEX($B$6:$B$53,ROW()-5+$B$3) -> 2600 | D7: =C7-B7 -> 0 | E7: =ABS(D7) -> 0 | G7: 75th percentile (bp) | H7: =PERCENTILE($E$6:$E$47,0.75) -> 350
A8: Nov-2022 | B8: 2350 | C8: =INDEX($B$6:$B$53,ROW()-5+$B$3) -> 2450 | D8: =C8-B8 -> 100 | E8: =ABS(D8) -> 100 | G8: 90th percentile (bp) | H8: =PERCENTILE($E$6:$E$47,0.9) -> 745
A9: Dec-2022 | B9: 2200 | C9: =INDEX($B$6:$B$53,ROW()-5+$B$3) -> 2200 | D9: =C9-B9 -> 0 | E9: =ABS(D9) -> 0 | G9: Largest in sample (bp) | H9: =MAX($E$6:$E$47) -> 1350
A10: Jan-2023 | B10: 1900 | C10: =INDEX($B$6:$B$53,ROW()-5+$B$3) -> 2050 | D10: =C10-B10 -> 150 | E10: =ABS(D10) -> 150 | G10: Cushion on GD35 (bp) | H10: ='2 Carry cushion'!H8 -> 75.024367
A11: Feb-2023 | B11: 2100 | C11: =INDEX($B$6:$B$53,ROW()-5+$B$3) -> 2350 | D11: =C11-B11 -> 250 | E11: =ABS(D11) -> 250 | G11: Share of windows breaching | H11: =COUNTIF($E$6:$E$47,">"&$H$10)/COUNT($E$6:$E$47) -> 0.69047619
A12: Mar-2023 | B12: 2350 | C12: =INDEX($B$6:$B$53,ROW()-5+$B$3) -> 2400 | D12: =C12-B12 -> 50 | E12: =ABS(D12) -> 50
A13: Apr-2023 | B13: 2600 | C13: =INDEX($B$6:$B$53,ROW()-5+$B$3) -> 2600 | D13: =C13-B13 -> 0 | E13: =ABS(D13) -> 0
A14: May-2023 | B14: 2450 | C14: =INDEX($B$6:$B$53,ROW()-5+$B$3) -> 2100 | D14: =C14-B14 -> -350 | E14: =ABS(D14) -> 350
A15: Jun-2023 | B15: 2200 | C15: =INDEX($B$6:$B$53,ROW()-5+$B$3) -> 1900 | D15: =C15-B15 -> -300 | E15: =ABS(D15) -> 300
A16: Jul-2023 | B16: 2050 | C16: =INDEX($B$6:$B$53,ROW()-5+$B$3) -> 1950 | D16: =C16-B16 -> -100 | E16: =ABS(D16) -> 100
A17: Aug-2023 | B17: 2350 | C17: =INDEX($B$6:$B$53,ROW()-5+$B$3) -> 1750 | D17: =C17-B17 -> -600 | E17: =ABS(D17) -> 600
A18: Sep-2023 | B18: 2400 | C18: =INDEX($B$6:$B$53,ROW()-5+$B$3) -> 1600 | D18: =C18-B18 -> -800 | E18: =ABS(D18) -> 800
A19: Oct-2023 | B19: 2600 | C19: =INDEX($B$6:$B$53,ROW()-5+$B$3) -> 1250 | D19: =C19-B19 -> -1350 | E19: =ABS(D19) -> 1350
A20: Nov-2023 | B20: 2100 | C20: =INDEX($B$6:$B$53,ROW()-5+$B$3) -> 1400 | D20: =C20-B20 -> -700 | E20: =ABS(D20) -> 700
A21: Dec-2023 | B21: 1900 | C21: =INDEX($B$6:$B$53,ROW()-5+$B$3) -> 1550 | D21: =C21-B21 -> -350 | E21: =ABS(D21) -> 350
A22: Jan-2024 | B22: 1950 | C22: =INDEX($B$6:$B$53,ROW()-5+$B$3) -> 1600 | D22: =C22-B22 -> -350 | E22: =ABS(D22) -> 350
A23: Feb-2024 | B23: 1750 | C23: =INDEX($B$6:$B$53,ROW()-5+$B$3) -> 1450 | D23: =C23-B23 -> -300 | E23: =ABS(D23) -> 300
... A47: Feb-2026 | B47: 560 | C47: =INDEX($B$6:$B$53,ROW()-5+$B$3) -> 520 | D47: =C47-B47 -> -40 | E47: =ABS(D47) -> 40
A48: Mar-2026 | B48: 600
A49: Apr-2026 | B49: 640
A50: May-2026 | B50: 590
A51: Jun-2026 | B51: 560
A52: Jul-2026 | B52: 540
A53: Aug-2026 | B53: 520
A55: THE SPREAD HISTORY IN COLUMN B IS ILLUSTRATIVE — it is shaped like Argentina's recent path but the values are invented. Paste the real series before quoting a single number off this tab.
A56: The bottom-right cell is the honest version of the pitch. If a large share of historical six-month windows moved more than the cushion, then the carry is compensation for volatility rather than a free lunch, and the trade is a view on the distribution narrowing — not on the coupon.
A57: Overlapping windows, so these are not independent observations and the percentiles are noisier than the sample size suggests. Fine for scaling the cushion; not a probability estimate.
A58: Formulas stop six rows early on purpose: the last six months have no six-month-forward observation yet. Extend both the data and the formulas together as new months print.

Sheet 6 Bloomberg refresh
A1: Refreshing this model from Bloomberg — do it yourself
A2: Every formula below is written WITHOUT its leading equals sign, so this tab stays inert outside the terminal. Type an = in front when you paste it into a live sheet. Replace the ISIN with the bond you want.
A5: Tab 1 cell | B5: What it is | C5: Type this (prefix with =) | D5: Bloomberg field | E5: What goes wrong
A6: STEP 1 — one row per bond, pulled live
A7: A6 | B7: Bond name | C7: BDP("US040114HS26 Corp","SECURITY_NAME") | D7: SECURITY_NAME | E7: Identify by ISIN, not by the ARGENT ticker string. The globals and the local-law Bonares have near-identical descriptions and mixing GD35 with AL35 is the classic error.
A8: B6 | B8: Maturity | C8: BDP("US040114HS26 Corp","MATURITY") | D8: MATURITY | E8: Format the cell as a date or it shows as a five-digit serial.
A9: C6 | B9: Coupon in effect | C9: BDP("US040114HS26 Corp","CPN") | D9: CPN | E9: Returns the CURRENT step, which is what this model wants. For the whole step schedule use BDS("US040114HS26 Corp","MULTI_CPN_SCHEDULE") — it spills down, so leave room.
A10: D6 | B10: Clean price | C10: BDP("US040114HS26 Corp","PX_LAST") | D10: PX_LAST | E10: PX_LAST is clean. Use PX_BID if you are sizing a real buy — the bid/ask on these is wide enough to move the cushion by several bp.
A11: E6 | B11: Yield to maturity | C11: BDP("US040114HS26 Corp","YLD_YTM_MID") | D11: YLD_YTM_MID | E11: Comes back as 7.9 (percent units), which is what this model wants. Add an override to price off your own level: BDP(...,"YLD_YTM_MID","PX_BID=72.5").
A12: F6 | B12: Modified duration | C12: BDP("US040114HS26 Corp","DUR_ADJ_MID") | D12: DUR_ADJ_MID | E12: Duration to workout. For these bullets/amortisers it equals DUR_ADJ_MTY_MID; if the two ever differ, take the maturity one, since the cushion logic assumes you hold.
A13: G6 | B13: Convexity | C13: BDP("US040114HS26 Corp","CVX_MID")*100 | D13: CVX_MID | E13: THE x100 IS NOT OPTIONAL. Bloomberg quotes convexity divided by 100; this model wants years squared (~36 for a 5.4-year bond). Omit it and the convexity column silently does nothing.
A14: STEP 2 — spread history for tab 5
A15: Tab 5 A:B | B15: Monthly spread history | C15: BDH("US040114HS26 Corp","Z_SPRD_MID","1/1/2023","8/11/2026","Per=M","Dir=V","Fill=P") | D15: Z_SPRD_MID | E15: Pull the spread off the BOND rather than hunting for an EMBI index ticker — it is the spread your position actually carries, and it definitely exists. BDH is an array that spills down and will overwrite anything below it.
B16: Alternative: yield history | C16: BDH("US040114HS26 Corp","YLD_YTM_MID","1/1/2023","8/11/2026","Per=M","Dir=V") | D16: YLD_YTM_MID | E16: Use yield rather than spread if you want the move measured in the same units as the cushion. Strictly more correct: the cushion is a YIELD breakeven, not a spread breakeven.
A17: STEP 3 — check my field names rather than trusting them
B18: Field finder | C18: Terminal: US040114HS26 Corp FLDS <GO> | D18: — | E18: Searches every field available on that specific security and shows the live value. This is how you verify anything on this tab in ten seconds. Field coverage differs by security, so a name that works on one bond can be blank on another.
B19: Yield and spread screen | C19: Terminal: US040114HS26 Corp YAS <GO> | D19: — | E19: Cross-check price, yield, duration and convexity against the numbers your BDP calls return before you trust the model. If YAS and your sheet disagree it is almost always a settlement date difference.
B20: Formula builder | C20: Excel ribbon: Bloomberg tab -> Spreadsheet Builder | D20: — | E20: Builds BDP/BDH calls through a wizard and writes the syntax for you. Faster than remembering override names, and it shows you the argument order.
A22: SETTLEMENT DATE is the quiet one. BDP prices analytics to the default settlement convention, so yield, duration and convexity all shift if you change it. Force it explicitly when it matters: BDP(...,"YLD_YTM_MID","SETTLE_DT=20260813").
A23: CLEAN vs DIRTY PRICE is a real refinement once you are on live data. This model divides the coupon by the CLEAN price, but you actually pay clean + accrued. Pull accrued with BDP(...,"INT_ACC") and use clean + accrued as the denominator in column D of tab 2 for a true return on capital employed. It moves the cash-coupon number by a few basis points, never enough to change a decision, but it is the correct version.
A24: BDP is a snapshot that refreshes with the sheet; BDH is a historical array that spills. Never point BDH at a range that has anything below it. A cell reading 'Requesting Data' has not returned yet — that is not an error, just wait.
A25: The ISIN above is a placeholder and may not be the bond you think it is. Confirm each one on the terminal before wiring it in.

Sheet Notes
A1: Method, conventions and what to overwrite
A4: HOW TO USE THIS
A5: 1. Overwrite every blue cell on tab 1 with live Bloomberg data. Nothing else needs touching.
A6: 2. Set the holding period in cell B3 of tab 1. Everything downstream recalculates.
A7: 3. Paste a real spread history into columns A and B of tab 5, then extend the formulas in C:E.
A8: 4. Blue = type here. Black = formula. Green = pulled from another tab.
A10: THE ARITHMETIC
A11: Total return over horizon h = y*h - D*dy + 0.5*C*dy^2
A12: y = yield to maturity D = modified duration
A13: h = holding period in years C = convexity
A14: dy = parallel yield shift in decimals
A15: Setting total return to zero and solving for dy gives the breakeven widening — the cushion.
... A40: positions or gridline settings - so there is nothing to undo when reformatting by hand.
