Workbook

Sheet README
A1: Macro Tracker — Argentina
A2: Pure-Excel workbook driven by Haver DLX. Edit codes on the Codes tab, hit DLX > Refresh / Calculate, every tab and chart updates.
A4: How to use
A5: 1. | B5: Make sure the Haver DLX add-in is loaded (Excel > File > Options > Add-ins).
A6: 2. | B6: Open the Codes tab and review the Haver codes. Yellow cells are inputs.
A7: 3. | B7: Hit DLX > Refresh (or just press F9) to pull data.
A8: 4. | B8: Open any category tab (GDP, Inflation, …). Each indicator has a quarterly block, an annual block, and a chart.
A9: 5. | B9: The Dashboard tab summarises the latest read and 2-year forecast for every indicator.
A11: Forecasts
A12: Linear (TREND) | B12: Excel's TREND() extends the levels linearly over the next 8 quarters. Robust to zero / negative values.
A13: Holt-Winters (ETS) | B13: Excel's FORECAST.ETS() is exponential triple smoothing with auto seasonality. Pair with FORECAST.ETS.CONFINT() for 95% bands.
A15: Notes on Argentina
A16: Inflation regime breaks | B16: INDEC suspended/restated CPI 2007-15. Forecasts on the full history will look strange — consider trimming the date range used in the formula or relying on Holt-Winters which damps.
A17: Currency revaluations | B17: Pesos series may have notch jumps. Inspect the chart before quoting a forecast.
A19: Files
A20: Argentina_Tracker.xlsx | B20: This workbook. Open this every day.
A21: build_argentina.py | B21: Regenerates the workbook layout. Only run if you want to add/remove categories or rebuild from scratch.

Sheet Codes
A1: Codes — Single Source of Truth (Argentina)
A2: Edit the yellow cells. Quarterly Code is required; Annual Code is optional (the workbook aggregates from Q if blank). Aggregation: avg | sum | last.
A4: Section | B4: Indicator | C4: Frequency hint | D4: Quarterly Code | E4: Annual Code | F4: Units | G4: Aggregation | H4: Notes
A5: GDP | B5: Real GDP (SA) | C5: Q | D5: S213NGPC@LATAM | E5: S213NGPCA@LATAM | F5: Mn 2004 ARS | G5: avg | H5: [VERIFY] AR is country code 213 in IFS-style mnemonics.
A6: GDP | B6: Nominal GDP | C6: Q | D6: S213NGDP@LATAM | E6: S213NGDPA@LATAM | F6: Mn ARS | G6: avg | H6: [VERIFY]
A7: GDP | B7: EMAE Activity Index | C7: Q | D7: EMAE@ARGEN | E7: EMAEA@ARGEN | F7: Index 2004=100 | G7: avg | H7: INDEC monthly activity proxy. [VERIFY] code on your subscription.
A8: Inflation | B8: CPI National (IPC nacional) | C8: Q | D8: IPCNAC@ARGEN | E8: IPCNACA@ARGEN | F8: Index Dec-16=100 | G8: avg | H8: INDEC. Pre-2017 series has structural breaks (INDEC reform).
A9: Inflation | B9: Core CPI | C9: Q | D9: IPCCORE@ARGEN | E9: IPCCOREA@ARGEN | F9: Index | G9: avg | H9: [VERIFY]
A10: Inflation | B10: Wholesale Price Index (IPIM) | C10: Q | D10: IPIM@ARGEN | E10: IPIMA@ARGEN | F10: Index | G10: avg | H10: [VERIFY]
A11: Fiscal | B11: Primary Fiscal Balance | C11: Q | D11: SPNFBAL@ARGEN | E11: SPNFBALA@ARGEN | F11: Mn ARS | G11: sum | H11: Sector Publico Nacional No Financiero. [VERIFY]
A12: Fiscal | B12: Federal Tax Revenue | C12: Q | D12: RECNAC@ARGEN | E12: RECNACA@ARGEN | F12: Mn ARS | G12: sum | H12: [VERIFY]
A13: Fiscal | B13: Public Debt | C13: Q | D13: DEUDPUB@ARGEN | E13: DEUDPUBA@ARGEN | F13: USD Mn | G13: last | H13: End-period stock. [VERIFY]
A14: BoP | B14: Current Account Balance | C14: Q | D14: S213NCABA@LATAM | E14: S213NCABAA@LATAM | F14: USD Mn | G14: sum | H14: INDEC / BCRA. [VERIFY]
A15: BoP | B15: Trade Balance | C15: Q | D15: EXPMP@ARGEN | E15: EXPMPA@ARGEN | F15: USD Mn | G15: sum | H15: Exports - imports. [VERIFY]
... A18: Reserves | B18: Net International Reserves | C18: Q | D18: RESNET@ARGEN | E18: RESNETA@ARGEN | F18: USD Mn | G18: last | H18: BCRA NIR. [VERIFY]

Sheet GDP
A1: GDP — Argentina
A2: Each block: live HaverData pulls (col B) → growth metrics → TREND + FORECAST.ETS forecasts → chart.
A4: =Codes!$B$5&" ["&Codes!$D$5&"] "&Codes!$F$5 -> Real GDP (SA) [S213NGPC@LATAM] Mn 2004 ARS
A5: Aggregation: | B5: =Codes!$G$5 -> avg | D5: Notes: | E5: =Codes!$H$5 -> [VERIFY] AR is country code 213 in IFS-style mnemonics.
A6: Quarterly | J6: Annual
A7: Date | B7: Level | C7: QoQ % | D7: YoY % | E7: Linear Fcst | F7: ETS Fcst | G7: ETS Low 95% | H7: ETS High 95% | J7: Year | K7: Level | L7: YoY % | M7: Forecast
A8: 39448 | B8: =IFERROR(haverdata(Codes!$D$5,$A8),"") | E8: =IFERROR(IF(B8="",IFERROR(GROWTH($B$8:$B$95,$A$8:$A$95,$A8),TREND($B$8:$B$95,$A$8:$A$95,$A8)),""),"") | F8: =IFERROR(forecast.ets($A8,$B$8:$B$95,$A$8:$A$95,4,1,1),"") | G8: =IFERROR(F8-forecast.ets.confint($A8,$B$8:$B$95,$A$8:$A$95,0.95,4,1,1),"") | H8: =IFERROR(F8+forecast.ets.confint($A8,$B$8:$B$95,$A$8:$A$95,0.95,4,1,1),"") | J8: 2008 | K8: =IFERROR(AVERAGEIFS($B$8:$B$95,$A$8:$A$95,">="&DATE(J8,1,1),$A$8:$A$95,"<="&DATE(J8,12,31)),"") | M8: =IFERROR(AVERAGEIFS($F$8:$F$95,$A$8:$A$95,">="&DATE(J8,1,1),$A$8:$A$95,"<="&DATE(J8,12,31)),"")
A9: 39539 | B9: =IFERROR(haverdata(Codes!$D$5,$A9),"") | C9: =IFERROR(B9/B8-1,"") | E9: =IFERROR(IF(B9="",IFERROR(GROWTH($B$8:$B$95,$A$8:$A$95,$A9),TREND($B$8:$B$95,$A$8:$A$95,$A9)),""),"") | F9: =IFERROR(forecast.ets($A9,$B$8:$B$95,$A$8:$A$95,4,1,1),"") | G9: =IFERROR(F9-forecast.ets.confint($A9,$B$8:$B$95,$A$8:$A$95,0.95,4,1,1),"") | H9: =IFERROR(F9+forecast.ets.confint($A9,$B$8:$B$95,$A$8:$A$95,0.95,4,1,1),"") | J9: 2009 | K9: =IFERROR(AVERAGEIFS($B$8:$B$95,$A$8:$A$95,">="&DATE(J9,1,1),$A$8:$A$95,"<="&DATE(J9,12,31)),"") | L9: =IFERROR(K9/K8-1,"") | M9: =IFERROR(AVERAGEIFS($F$8:$F$95,$A$8:$A$95,">="&DATE(J9,1,1),$A$8:$A$95,"<="&DATE(J9,12,31)),"")
A10: 39630 | B10: =IFERROR(haverdata(Codes!$D$5,$A10),"") | C10: =IFERROR(B10/B9-1,"") | E10: =IFERROR(IF(B10="",IFERROR(GROWTH($B$8:$B$95,$A$8:$A$95,$A10),TREND($B$8:$B$95,$A$8:$A$95,$A10)),""),"") | F10: =IFERROR(forecast.ets($A10,$B$8:$B$95,$A$8:$A$95,4,1,1),"") | G10: =IFERROR(F10-forecast.ets.confint($A10,$B$8:$B$95,$A$8:$A$95,0.95,4,1,1),"") | H10: =IFERROR(F10+forecast.ets.confint($A10,$B$8:$B$95,$A$8:$A$95,0.95,4,1,1),"") | J10: 2010 | K10: =IFERROR(AVERAGEIFS($B$8:$B$95,$A$8:$A$95,">="&DATE(J10,1,1),$A$8:$A$95,"<="&DATE(J10,12,31)),"") | L10: =IFERROR(K10/K9-1,"") | M10: =IFERROR(AVERAGEIFS($F$8:$F$95,$A$8:$A$95,">="&DATE(J10,1,1),$A$8:$A$95,"<="&DATE(J10,12,31)),"")
A11: 39722 | B11: =IFERROR(haverdata(Codes!$D$5,$A11),"") | C11: =IFERROR(B11/B10-1,"") | E11: =IFERROR(IF(B11="",IFERROR(GROWTH($B$8:$B$95,$A$8:$A$95,$A11),TREND($B$8:$B$95,$A$8:$A$95,$A11)),""),"") | F11: =IFERROR(forecast.ets($A11,$B$8:$B$95,$A$8:$A$95,4,1,1),"") | G11: =IFERROR(F11-forecast.ets.confint($A11,$B$8:$B$95,$A$8:$A$95,0.95,4,1,1),"") | H11: =IFERROR(F11+forecast.ets.confint($A11,$B$8:$B$95,$A$8:$A$95,0.95,4,1,1),"") | J11: 2011 | K11: =IFERROR(AVERAGEIFS($B$8:$B$95,$A$8:$A$95,">="&DATE(J11,1,1),$A$8:$A$95,"<="&DATE(J11,12,31)),"") | L11: =IFERROR(K11/K10-1,"") | M11: =IFERROR(AVERAGEIFS($F$8:$F$95,$A$8:$A$95,">="&DATE(J11,1,1),$A$8:$A$95,"<="&DATE(J11,12,31)),"")
A12: 39814 | B12: =IFERROR(haverdata(Codes!$D$5,$A12),"") | C12: =IFERROR(B12/B11-1,"") | D12: =IFERROR(B12/B8-1,"") | E12: =IFERROR(IF(B12="",IFERROR(GROWTH($B$8:$B$95,$A$8:$A$95,$A12),TREND($B$8:$B$95,$A$8:$A$95,$A12)),""),"") | F12: =IFERROR(forecast.ets($A12,$B$8:$B$95,$A$8:$A$95,4,1,1),"") | G12: =IFERROR(F12-forecast.ets.confint($A12,$B$8:$B$95,$A$8:$A$95,0.95,4,1,1),"") | H12: =IFERROR(F12+forecast.ets.confint($A12,$B$8:$B$95,$A$8:$A$95,0.95,4,1,1),"") | J12: 2012 | K12: =IFERROR(AVERAGEIFS($B$8:$B$95,$A$8:$A$95,">="&DATE(J12,1,1),$A$8:$A$95,"<="&DATE(J12,12,31)),"") | L12: =IFERROR(K12/K11-1,"") | M12: =IFERROR(AVERAGEIFS($F$8:$F$95,$A$8:$A$95,">="&DATE(J12,1,1),$A$8:$A$95,"<="&DATE(J12,12,31)),"")
A13: 39904 | B13: =IFERROR(haverdata(Codes!$D$5,$A13),"") | C13: =IFERROR(B13/B12-1,"") | D13: =IFERROR(B13/B9-1,"") | E13: =IFERROR(IF(B13="",IFERROR(GROWTH($B$8:$B$95,$A$8:$A$95,$A13),TREND($B$8:$B$95,$A$8:$A$95,$A13)),""),"") | F13: =IFERROR(forecast.ets($A13,$B$8:$B$95,$A$8:$A$95,4,1,1),"") | G13: =IFERROR(F13-forecast.ets.confint($A13,$B$8:$B$95,$A$8:$A$95,0.95,4,1,1),"") | H13: =IFERROR(F13+forecast.ets.confint($A13,$B$8:$B$95,$A$8:$A$95,0.95,4,1,1),"") | J13: 2013 | K13: =IFERROR(AVERAGEIFS($B$8:$B$95,$A$8:$A$95,">="&DATE(J13,1,1),$A$8:$A$95,"<="&DATE(J13,12,31)),"") | L13: =IFERROR(K13/K12-1,"") | M13: =IFERROR(AVERAGEIFS($F$8:$F$95,$A$8:$A$95,">="&DATE(J13,1,1),$A$8:$A$95,"<="&DATE(J13,12,31)),"")
A14: 39995 | B14: =IFERROR(haverdata(Codes!$D$5,$A14),"") | C14: =IFERROR(B14/B13-1,"") | D14: =IFERROR(B14/B10-1,"") | E14: =IFERROR(IF(B14="",IFERROR(GROWTH($B$8:$B$95,$A$8:$A$95,$A14),TREND($B$8:$B$95,$A$8:$A$95,$A14)),""),"") | F14: =IFERROR(forecast.ets($A14,$B$8:$B$95,$A$8:$A$95,4,1,1),"") | G14: =IFERROR(F14-forecast.ets.confint($A14,$B$8:$B$95,$A$8:$A$95,0.95,4,1,1),"") | H14: =IFERROR(F14+forecast.ets.confint($A14,$B$8:$B$95,$A$8:$A$95,0.95,4,1,1),"") | J14: 2014 | K14: =IFERROR(AVERAGEIFS($B$8:$B$95,$A$8:$A$95,">="&DATE(J14,1,1),$A$8:$A$95,"<="&DATE(J14,12,31)),"") | L14: =IFERROR(K14/K13-1,"") | M14: =IFERROR(AVERAGEIFS($F$8:$F$95,$A$8:$A$95,">="&DATE(J14,1,1),$A$8:$A$95,"<="&DATE(J14,12,31)),"")
A15: 40087 | B15: =IFERROR(haverdata(Codes!$D$5,$A15),"") | C15: =IFERROR(B15/B14-1,"") | D15: =IFERROR(B15/B11-1,"") | E15: =IFERROR(IF(B15="",IFERROR(GROWTH($B$8:$B$95,$A$8:$A$95,$A15),TREND($B$8:$B$95,$A$8:$A$95,$A15)),""),"") | F15: =IFERROR(forecast.ets($A15,$B$8:$B$95,$A$8:$A$95,4,1,1),"") | G15: =IFERROR(F15-forecast.ets.confint($A15,$B$8:$B$95,$A$8:$A$95,0.95,4,1,1),"") | H15: =IFERROR(F15+forecast.ets.confint($A15,$B$8:$B$95,$A$8:$A$95,0.95,4,1,1),"") | J15: 2015 | K15: =IFERROR(AVERAGEIFS($B$8:$B$95,$A$8:$A$95,">="&DATE(J15,1,1),$A$8:$A$95,"<="&DATE(J15,12,31)),"") | L15: =IFERROR(K15/K14-1,"") | M15: =IFERROR(AVERAGEIFS($F$8:$F$95,$A$8:$A$95,">="&DATE(J15,1,1),$A$8:$A$95,"<="&DATE(J15,12,31)),"")
A16: 40179 | B16: =IFERROR(haverdata(Codes!$D$5,$A16),"") | C16: =IFERROR(B16/B15-1,"") | D16: =IFERROR(B16/B12-1,"") | E16: =IFERROR(IF(B16="",IFERROR(GROWTH($B$8:$B$95,$A$8:$A$95,$A16),TREND($B$8:$B$95,$A$8:$A$95,$A16)),""),"") | F16: =IFERROR(forecast.ets($A16,$B$8:$B$95,$A$8:$A$95,4,1,1),"") | G16: =IFERROR(F16-forecast.ets.confint($A16,$B$8:$B$95,$A$8:$A$95,0.95,4,1,1),"") | H16: =IFERROR(F16+forecast.ets.confint($A16,$B$8:$B$95,$A$8:$A$95,0.95,4,1,1),"") | J16: 2016 | K16: =IFERROR(AVERAGEIFS($B$8:$B$95,$A$8:$A$95,">="&DATE(J16,1,1),$A$8:$A$95,"<="&DATE(J16,12,31)),"") | L16: =IFERROR(K16/K15-1,"") | M16: =IFERROR(AVERAGEIFS($F$8:$F$95,$A$8:$A$95,">="&DATE(J16,1,1),$A$8:$A$95,"<="&DATE(J16,12,31)),"")
A17: 40269 | B17: =IFERROR(haverdata(Codes!$D$5,$A17),"") | C17: =IFERROR(B17/B16-1,"") | D17: =IFERROR(B17/B13-1,"") | E17: =IFERROR(IF(B17="",IFERROR(GROWTH($B$8:$B$95,$A$8:$A$95,$A17),TREND($B$8:$B$95,$A$8:$A$95,$A17)),""),"") | F17: =IFERROR(forecast.ets($A17,$B$8:$B$95,$A$8:$A$95,4,1,1),"") | G17: =IFERROR(F17-forecast.ets.confint($A17,$B$8:$B$95,$A$8:$A$95,0.95,4,1,1),"") | H17: =IFERROR(F17+forecast.ets.confint($A17,$B$8:$B$95,$A$8:$A$95,0.95,4,1,1),"") | J17: 2017 | K17: =IFERROR(AVERAGEIFS($B$8:$B$95,$A$8:$A$95,">="&DATE(J17,1,1),$A$8:$A$95,"<="&DATE(J17,12,31)),"") | L17: =IFERROR(K17/K16-1,"") | M17: =IFERROR(AVERAGEIFS($F$8:$F$95,$A$8:$A$95,">="&DATE(J17,1,1),$A$8:$A$95,"<="&DATE(J17,12,31)),"")
A18: 40360 | B18: =IFERROR(haverdata(Codes!$D$5,$A18),"") | C18: =IFERROR(B18/B17-1,"") | D18: =IFERROR(B18/B14-1,"") | E18: =IFERROR(IF(B18="",IFERROR(GROWTH($B$8:$B$95,$A$8:$A$95,$A18),TREND($B$8:$B$95,$A$8:$A$95,$A18)),""),"") | F18: =IFERROR(forecast.ets($A18,$B$8:$B$95,$A$8:$A$95,4,1,1),"") | G18: =IFERROR(F18-forecast.ets.confint($A18,$B$8:$B$95,$A$8:$A$95,0.95,4,1,1),"") | H18: =IFERROR(F18+forecast.ets.confint($A18,$B$8:$B$95,$A$8:$A$95,0.95,4,1,1),"") | J18: 2018 | K18: =IFERROR(AVERAGEIFS($B$8:$B$95,$A$8:$A$95,">="&DATE(J18,1,1),$A$8:$A$95,"<="&DATE(J18,12,31)),"") | L18: =IFERROR(K18/K17-1,"") | M18: =IFERROR(AVERAGEIFS($F$8:$F$95,$A$8:$A$95,">="&DATE(J18,1,1),$A$8:$A$95,"<="&DATE(J18,12,31)),"")
A19: 40452 | B19: =IFERROR(haverdata(Codes!$D$5,$A19),"") | C19: =IFERROR(B19/B18-1,"") | D19: =IFERROR(B19/B15-1,"") | E19: =IFERROR(IF(B19="",IFERROR(GROWTH($B$8:$B$95,$A$8:$A$95,$A19),TREND($B$8:$B$95,$A$8:$A$95,$A19)),""),"") | F19: =IFERROR(forecast.ets($A19,$B$8:$B$95,$A$8:$A$95,4,1,1),"") | G19: =IFERROR(F19-forecast.ets.confint($A19,$B$8:$B$95,$A$8:$A$95,0.95,4,1,1),"") | H19: =IFERROR(F19+forecast.ets.confint($A19,$B$8:$B$95,$A$8:$A$95,0.95,4,1,1),"") | J19: 2019 | K19: =IFERROR(AVERAGEIFS($B$8:$B$95,$A$8:$A$95,">="&DATE(J19,1,1),$A$8:$A$95,"<="&DATE(J19,12,31)),"") | L19: =IFERROR(K19/K18-1,"") | M19: =IFERROR(AVERAGEIFS($F$8:$F$95,$A$8:$A$95,">="&DATE(J19,1,1),$A$8:$A$95,"<="&DATE(J19,12,31)),"")
A20: 40544 | B20: =IFERROR(haverdata(Codes!$D$5,$A20),"") | C20: =IFERROR(B20/B19-1,"") | D20: =IFERROR(B20/B16-1,"") | E20: =IFERROR(IF(B20="",IFERROR(GROWTH($B$8:$B$95,$A$8:$A$95,$A20),TREND($B$8:$B$95,$A$8:$A$95,$A20)),""),"") | F20: =IFERROR(forecast.ets($A20,$B$8:$B$95,$A$8:$A$95,4,1,1),"") | G20: =IFERROR(F20-forecast.ets.confint($A20,$B$8:$B$95,$A$8:$A$95,0.95,4,1,1),"") | H20: =IFERROR(F20+forecast.ets.confint($A20,$B$8:$B$95,$A$8:$A$95,0.95,4,1,1),"") | J20: 2020 | K20: =IFERROR(AVERAGEIFS($B$8:$B$95,$A$8:$A$95,">="&DATE(J20,1,1),$A$8:$A$95,"<="&DATE(J20,12,31)),"") | L20: =IFERROR(K20/K19-1,"") | M20: =IFERROR(AVERAGEIFS($F$8:$F$95,$A$8:$A$95,">="&DATE(J20,1,1),$A$8:$A$95,"<="&DATE(J20,12,31)),"")
A21: 40634 | B21: =IFERROR(haverdata(Codes!$D$5,$A21),"") | C21: =IFERROR(B21/B20-1,"") | D21: =IFERROR(B21/B17-1,"") | E21: =IFERROR(IF(B21="",IFERROR(GROWTH($B$8:$B$95,$A$8:$A$95,$A21),TREND($B$8:$B$95,$A$8:$A$95,$A21)),""),"") | F21: =IFERROR(forecast.ets($A21,$B$8:$B$95,$A$8:$A$95,4,1,1),"") | G21: =IFERROR(F21-forecast.ets.confint($A21,$B$8:$B$95,$A$8:$A$95,0.95,4,1,1),"") | H21: =IFERROR(F21+forecast.ets.confint($A21,$B$8:$B$95,$A$8:$A$95,0.95,4,1,1),"") | J21: 2021 | K21: =IFERROR(AVERAGEIFS($B$8:$B$95,$A$8:$A$95,">="&DATE(J21,1,1),$A$8:$A$95,"<="&DATE(J21,12,31)),"") | L21: =IFERROR(K21/K20-1,"") | M21: =IFERROR(AVERAGEIFS($F$8:$F$95,$A$8:$A$95,">="&DATE(J21,1,1),$A$8:$A$95,"<="&DATE(J21,12,31)),"")
A22: 40725 | B22: =IFERROR(haverdata(Codes!$D$5,$A22),"") | C22: =IFERROR(B22/B21-1,"") | D22: =IFERROR(B22/B18-1,"") | E22: =IFERROR(IF(B22="",IFERROR(GROWTH($B$8:$B$95,$A$8:$A$95,$A22),TREND($B$8:$B$95,$A$8:$A$95,$A22)),""),"") | F22: =IFERROR(forecast.ets($A22,$B$8:$B$95,$A$8:$A$95,4,1,1),"") | G22: =IFERROR(F22-forecast.ets.confint($A22,$B$8:$B$95,$A$8:$A$95,0.95,4,1,1),"") | H22: =IFERROR(F22+forecast.ets.confint($A22,$B$8:$B$95,$A$8:$A$95,0.95,4,1,1),"") | J22: 2022 | K22: =IFERROR(AVERAGEIFS($B$8:$B$95,$A$8:$A$95,">="&DATE(J22,1,1),$A$8:$A$95,"<="&DATE(J22,12,31)),"") | L22: =IFERROR(K22/K21-1,"") | M22: =IFERROR(AVERAGEIFS($F$8:$F$95,$A$8:$A$95,">="&DATE(J22,1,1),$A$8:$A$95,"<="&DATE(J22,12,31)),"")
A23: 40817 | B23: =IFERROR(haverdata(Codes!$D$5,$A23),"") | C23: =IFERROR(B23/B22-1,"") | D23: =IFERROR(B23/B19-1,"") | E23: =IFERROR(IF(B23="",IFERROR(GROWTH($B$8:$B$95,$A$8:$A$95,$A23),TREND($B$8:$B$95,$A$8:$A$95,$A23)),""),"") | F23: =IFERROR(forecast.ets($A23,$B$8:$B$95,$A$8:$A$95,4,1,1),"") | G23: =IFERROR(F23-forecast.ets.confint($A23,$B$8:$B$95,$A$8:$A$95,0.95,4,1,1),"") | H23: =IFERROR(F23+forecast.ets.confint($A23,$B$8:$B$95,$A$8:$A$95,0.95,4,1,1),"") | J23: 2023 | K23: =IFERROR(AVERAGEIFS($B$8:$B$95,$A$8:$A$95,">="&DATE(J23,1,1),$A$8:$A$95,"<="&DATE(J23,12,31)),"") | L23: =IFERROR(K23/K22-1,"") | M23: =IFERROR(AVERAGEIFS($F$8:$F$95,$A$8:$A$95,">="&DATE(J23,1,1),$A$8:$A$95,"<="&DATE(J23,12,31)),"")
... A29: 41365 | B29: =IFERROR(haverdata(Codes!$D$5,$A29),"") | C29: =IFERROR(B29/B28-1,"") | D29: =IFERROR(B29/B25-1,"") | E29: =IFERROR(IF(B29="",IFERROR(GROWTH($B$8:$B$95,$A$8:$A$95,$A29),TREND($B$8:$B$95,$A$8:$A$95,$A29)),""),"") | F29: =IFERROR(forecast.ets($A29,$B$8:$B$95,$A$8:$A$95,4,1,1),"") | G29: =IFERROR(F29-forecast.ets.confint($A29,$B$8:$B$95,$A$8:$A$95,0.95,4,1,1),"") | H29: =IFERROR(F29+forecast.ets.confint($A29,$B$8:$B$95,$A$8:$A$95,0.95,4,1,1),"") | J29: 2029 | K29: =IFERROR(AVERAGEIFS($B$8:$B$95,$A$8:$A$95,">="&DATE(J29,1,1),$A$8:$A$95,"<="&DATE(J29,12,31)),"") | L29: =IFERROR(K29/K28-1,"") | M29: =IFERROR(AVERAGEIFS($F$8:$F$95,$A$8:$A$95,">="&DATE(J29,1,1),$A$8:$A$95,"<="&DATE(J29,12,31)),"")
A30: 41456 | B30: =IFERROR(haverdata(Codes!$D$5,$A30),"") | C30: =IFERROR(B30/B29-1,"") | D30: =IFERROR(B30/B26-1,"") | E30: =IFERROR(IF(B30="",IFERROR(GROWTH($B$8:$B$95,$A$8:$A$95,$A30),TREND($B$8:$B$95,$A$8:$A$95,$A30)),""),"") | F30: =IFERROR(forecast.ets($A30,$B$8:$B$95,$A$8:$A$95,4,1,1),"") | G30: =IFERROR(F30-forecast.ets.confint($A30,$B$8:$B$95,$A$8:$A$95,0.95,4,1,1),"") | H30: =IFERROR(F30+forecast.ets.confint($A30,$B$8:$B$95,$A$8:$A$95,0.95,4,1,1),"")
A31: 41548 | B31: =IFERROR(haverdata(Codes!$D$5,$A31),"") | C31: =IFERROR(B31/B30-1,"") | D31: =IFERROR(B31/B27-1,"") | E31: =IFERROR(IF(B31="",IFERROR(GROWTH($B$8:$B$95,$A$8:$A$95,$A31),TREND($B$8:$B$95,$A$8:$A$95,$A31)),""),"") | F31: =IFERROR(forecast.ets($A31,$B$8:$B$95,$A$8:$A$95,4,1,1),"") | G31: =IFERROR(F31-forecast.ets.confint($A31,$B$8:$B$95,$A$8:$A$95,0.95,4,1,1),"") | H31: =IFERROR(F31+forecast.ets.confint($A31,$B$8:$B$95,$A$8:$A$95,0.95,4,1,1),"")
A32: 41640 | B32: =IFERROR(haverdata(Codes!$D$5,$A32),"") | C32: =IFERROR(B32/B31-1,"") | D32: =IFERROR(B32/B28-1,"") | E32: =IFERROR(IF(B32="",IFERROR(GROWTH($B$8:$B$95,$A$8:$A$95,$A32),TREND($B$8:$B$95,$A$8:$A$95,$A32)),""),"") | F32: =IFERROR(forecast.ets($A32,$B$8:$B$95,$A$8:$A$95,4,1,1),"") | G32: =IFERROR(F32-forecast.ets.confint($A32,$B$8:$B$95,$A$8:$A$95,0.95,4,1,1),"") | H32: =IFERROR(F32+forecast.ets.confint($A32,$B$8:$B$95,$A$8:$A$95,0.95,4,1,1),"")
A33: 41730 | B33: =IFERROR(haverdata(Codes!$D$5,$A33),"") | C33: =IFERROR(B33/B32-1,"") | D33: =IFERROR(B33/B29-1,"") | E33: =IFERROR(IF(B33="",IFERROR(GROWTH($B$8:$B$95,$A$8:$A$95,$A33),TREND($B$8:$B$95,$A$8:$A$95,$A33)),""),"") | F33: =IFERROR(forecast.ets($A33,$B$8:$B$95,$A$8:$A$95,4,1,1),"") | G33: =IFERROR(F33-forecast.ets.confint($A33,$B$8:$B$95,$A$8:$A$95,0.95,4,1,1),"") | H33: =IFERROR(F33+forecast.ets.confint($A33,$B$8:$B$95,$A$8:$A$95,0.95,4,1,1),"")
A34: 41821 | B34: =IFERROR(haverdata(Codes!$D$5,$A34),"") | C34: =IFERROR(B34/B33-1,"") | D34: =IFERROR(B34/B30-1,"") | E34: =IFERROR(IF(B34="",IFERROR(GROWTH($B$8:$B$95,$A$8:$A$95,$A34),TREND($B$8:$B$95,$A$8:$A$95,$A34)),""),"") | F34: =IFERROR(forecast.ets($A34,$B$8:$B$95,$A$8:$A$95,4,1,1),"") | G34: =IFERROR(F34-forecast.ets.confint($A34,$B$8:$B$95,$A$8:$A$95,0.95,4,1,1),"") | H34: =IFERROR(F34+forecast.ets.confint($A34,$B$8:$B$95,$A$8:$A$95,0.95,4,1,1),"")
A35: 41913 | B35: =IFERROR(haverdata(Codes!$D$5,$A35),"") | C35: =IFERROR(B35/B34-1,"") | D35: =IFERROR(B35/B31-1,"") | E35: =IFERROR(IF(B35="",IFERROR(GROWTH($B$8:$B$95,$A$8:$A$95,$A35),TREND($B$8:$B$95,$A$8:$A$95,$A35)),""),"") | F35: =IFERROR(forecast.ets($A35,$B$8:$B$95,$A$8:$A$95,4,1,1),"") | G35: =IFERROR(F35-forecast.ets.confint($A35,$B$8:$B$95,$A$8:$A$95,0.95,4,1,1),"") | H35: =IFERROR(F35+forecast.ets.confint($A35,$B$8:$B$95,$A$8:$A$95,0.95,4,1,1),"")
A36: 42005 | B36: =IFERROR(haverdata(Codes!$D$5,$A36),"") | C36: =IFERROR(B36/B35-1,"") | D36: =IFERROR(B36/B32-1,"") | E36: =IFERROR(IF(B36="",IFERROR(GROWTH($B$8:$B$95,$A$8:$A$95,$A36),TREND($B$8:$B$95,$A$8:$A$95,$A36)),""),"") | F36: =IFERROR(forecast.ets($A36,$B$8:$B$95,$A$8:$A$95,4,1,1),"") | G36: =IFERROR(F36-forecast.ets.confint($A36,$B$8:$B$95,$A$8:$A$95,0.95,4,1,1),"") | H36: =IFERROR(F36+forecast.ets.confint($A36,$B$8:$B$95,$A$8:$A$95,0.95,4,1,1),"")
A37: 42095 | B37: =IFERROR(haverdata(Codes!$D$5,$A37),"") | C37: =IFERROR(B37/B36-1,"") | D37: =IFERROR(B37/B33-1,"") | E37: =IFERROR(IF(B37="",IFERROR(GROWTH($B$8:$B$95,$A$8:$A$95,$A37),TREND($B$8:$B$95,$A$8:$A$95,$A37)),""),"") | F37: =IFERROR(forecast.ets($A37,$B$8:$B$95,$A$8:$A$95,4,1,1),"") | G37: =IFERROR(F37-forecast.ets.confint($A37,$B$8:$B$95,$A$8:$A$95,0.95,4,1,1),"") | H37: =IFERROR(F37+forecast.ets.confint($A37,$B$8:$B$95,$A$8:$A$95,0.95,4,1,1),"")
A38: 42186 | B38: =IFERROR(haverdata(Codes!$D$5,$A38),"") | C38: =IFERROR(B38/B37-1,"") | D38: =IFERROR(B38/B34-1,"") | E38: =IFERROR(IF(B38="",IFERROR(GROWTH($B$8:$B$95,$A$8:$A$95,$A38),TREND($B$8:$B$95,$A$8:$A$95,$A38)),""),"") | F38: =IFERROR(forecast.ets($A38,$B$8:$B$95,$A$8:$A$95,4,1,1),"") | G38: =IFERROR(F38-forecast.ets.confint($A38,$B$8:$B$95,$A$8:$A$95,0.95,4,1,1),"") | H38: =IFERROR(F38+forecast.ets.confint($A38,$B$8:$B$95,$A$8:$A$95,0.95,4,1,1),"")
A39: 42278 | B39: =IFERROR(haverdata(Codes!$D$5,$A39),"") | C39: =IFERROR(B39/B38-1,"") | D39: =IFERROR(B39/B35-1,"") | E39: =IFERROR(IF(B39="",IFERROR(GROWTH($B$8:$B$95,$A$8:$A$95,$A39),TREND($B$8:$B$95,$A$8:$A$95,$A39)),""),"") | F39: =IFERROR(forecast.ets($A39,$B$8:$B$95,$A$8:$A$95,4,1,1),"") | G39: =IFERROR(F39-forecast.ets.confint($A39,$B$8:$B$95,$A$8:$A$95,0.95,4,1,1),"") | H39: =IFERROR(F39+forecast.ets.confint($A39,$B$8:$B$95,$A$8:$A$95,0.95,4,1,1),"")
A40: 42370 | B40: =IFERROR(haverdata(Codes!$D$5,$A40),"") | C40: =IFERROR(B40/B39-1,"") | D40: =IFERROR(B40/B36-1,"") | E40: =IFERROR(IF(B40="",IFERROR(GROWTH($B$8:$B$95,$A$8:$A$95,$A40),TREND($B$8:$B$95,$A$8:$A$95,$A40)),""),"") | F40: =IFERROR(forecast.ets($A40,$B$8:$B$95,$A$8:$A$95,4,1,1),"") | G40: =IFERROR(F40-forecast.ets.confint($A40,$B$8:$B$95,$A$8:$A$95,0.95,4,1,1),"") | H40: =IFERROR(F40+forecast.ets.confint($A40,$B$8:$B$95,$A$8:$A$95,0.95,4,1,1),"")
A41: 42461 | B41: =IFERROR(haverdata(Codes!$D$5,$A41),"") | C41: =IFERROR(B41/B40-1,"") | D41: =IFERROR(B41/B37-1,"") | E41: =IFERROR(IF(B41="",IFERROR(GROWTH($B$8:$B$95,$A$8:$A$95,$A41),TREND($B$8:$B$95,$A$8:$A$95,$A41)),""),"") | F41: =IFERROR(forecast.ets($A41,$B$8:$B$95,$A$8:$A$95,4,1,1),"") | G41: =IFERROR(F41-forecast.ets.confint($A41,$B$8:$B$95,$A$8:$A$95,0.95,4,1,1),"") | H41: =IFERROR(F41+forecast.ets.confint($A41,$B$8:$B$95,$A$8:$A$95,0.95,4,1,1),"")
... A95: 47392 | B95: =IFERROR(haverdata(Codes!$D$5,$A95),"") | C95: =IFERROR(B95/B94-1,"") | D95: =IFERROR(B95/B91-1,"") | E95: =IFERROR(IF(B95="",IFERROR(GROWTH($B$8:$B$95,$A$8:$A$95,$A95),TREND($B$8:$B$95,$A$8:$A$95,$A95)),""),"") | F95: =IFERROR(forecast.ets($A95,$B$8:$B$95,$A$8:$A$95,4,1,1),"") | G95: =IFERROR(F95-forecast.ets.confint($A95,$B$8:$B$95,$A$8:$A$95,0.95,4,1,1),"") | H95: =IFERROR(F95+forecast.ets.confint($A95,$B$8:$B$95,$A$8:$A$95,0.95,4,1,1),"")
A100: =Codes!$B$6&" ["&Codes!$D$6&"] "&Codes!$F$6 -> Nominal GDP [S213NGDP@LATAM] Mn ARS
A101: Aggregation: | B101: =Codes!$G$6 -> avg | D101: Notes: | E101: =Codes!$H$6 -> [VERIFY]
A102: Quarterly | J102: Annual
A103: Date | B103: Level | C103: QoQ % | D103: YoY % | E103: Linear Fcst | F103: ETS Fcst | G103: ETS Low 95% | H103: ETS High 95% | J103: Year | K103: Level | L103: YoY % | M103: Forecast
A104: 39448 | B104: =IFERROR(haverdata(Codes!$D$6,$A104),"") | E104: =IFERROR(IF(B104="",IFERROR(GROWTH($B$104:$B$191,$A$104:$A$191,$A104),TREND($B$104:$B$191,$A$104:$A$191,$A104)),""),"") | F104: =IFERROR(forecast.ets($A104,$B$104:$B$191,$A$104:$A$191,4,1,1),"") | G104: =IFERROR(F104-forecast.ets.confint($A104,$B$104:$B$191,$A$104:$A$191,0.95,4,1,1),"") | H104: =IFERROR(F104+forecast.ets.confint($A104,$B$104:$B$191,$A$104:$A$191,0.95,4,1,1),"") | J104: 2008 | K104: =IFERROR(AVERAGEIFS($B$104:$B$191,$A$104:$A$191,">="&DATE(J104,1,1),$A$104:$A$191,"<="&DATE(J104,12,31)),"") | M104: =IFERROR(AVERAGEIFS($F$104:$F$191,$A$104:$A$191,">="&DATE(J104,1,1),$A$104:$A$191,"<="&DATE(J104,12,31)),"")
A105: 39539 | B105: =IFERROR(haverdata(Codes!$D$6,$A105),"") | C105: =IFERROR(B105/B104-1,"") | E105: =IFERROR(IF(B105="",IFERROR(GROWTH($B$104:$B$191,$A$104:$A$191,$A105),TREND($B$104:$B$191,$A$104:$A$191,$A105)),""),"") | F105: =IFERROR(forecast.ets($A105,$B$104:$B$191,$A$104:$A$191,4,1,1),"") | G105: =IFERROR(F105-forecast.ets.confint($A105,$B$104:$B$191,$A$104:$A$191,0.95,4,1,1),"") | H105: =IFERROR(F105+forecast.ets.confint($A105,$B$104:$B$191,$A$104:$A$191,0.95,4,1,1),"") | J105: 2009 | K105: =IFERROR(AVERAGEIFS($B$104:$B$191,$A$104:$A$191,">="&DATE(J105,1,1),$A$104:$A$191,"<="&DATE(J105,12,31)),"") | L105: =IFERROR(K105/K104-1,"") | M105: =IFERROR(AVERAGEIFS($F$104:$F$191,$A$104:$A$191,">="&DATE(J105,1,1),$A$104:$A$191,"<="&DATE(J105,12,31)),"")
A106: 39630 | B106: =IFERROR(haverdata(Codes!$D$6,$A106),"") | C106: =IFERROR(B106/B105-1,"") | E106: =IFERROR(IF(B106="",IFERROR(GROWTH($B$104:$B$191,$A$104:$A$191,$A106),TREND($B$104:$B$191,$A$104:$A$191,$A106)),""),"") | F106: =IFERROR(forecast.ets($A106,$B$104:$B$191,$A$104:$A$191,4,1,1),"") | G106: =IFERROR(F106-forecast.ets.confint($A106,$B$104:$B$191,$A$104:$A$191,0.95,4,1,1),"") | H106: =IFERROR(F106+forecast.ets.confint($A106,$B$104:$B$191,$A$104:$A$191,0.95,4,1,1),"") | J106: 2010 | K106: =IFERROR(AVERAGEIFS($B$104:$B$191,$A$104:$A$191,">="&DATE(J106,1,1),$A$104:$A$191,"<="&DATE(J106,12,31)),"") | L106: =IFERROR(K106/K105-1,"") | M106: =IFERROR(AVERAGEIFS($F$104:$F$191,$A$104:$A$191,">="&DATE(J106,1,1),$A$104:$A$191,"<="&DATE(J106,12,31)),"")
A107: 39722 | B107: =IFERROR(haverdata(Codes!$D$6,$A107),"") | C107: =IFERROR(B107/B106-1,"") | E107: =IFERROR(IF(B107="",IFERROR(GROWTH($B$104:$B$191,$A$104:$A$191,$A107),TREND($B$104:$B$191,$A$104:$A$191,$A107)),""),"") | F107: =IFERROR(forecast.ets($A107,$B$104:$B$191,$A$104:$A$191,4,1,1),"") | G107: =IFERROR(F107-forecast.ets.confint($A107,$B$104:$B$191,$A$104:$A$191,0.95,4,1,1),"") | H107: =IFERROR(F107+forecast.ets.confint($A107,$B$104:$B$191,$A$104:$A$191,0.95,4,1,1),"") | J107: 2011 | K107: =IFERROR(AVERAGEIFS($B$104:$B$191,$A$104:$A$191,">="&DATE(J107,1,1),$A$104:$A$191,"<="&DATE(J107,12,31)),"") | L107: =IFERROR(K107/K106-1,"") | M107: =IFERROR(AVERAGEIFS($F$104:$F$191,$A$104:$A$191,">="&DATE(J107,1,1),$A$104:$A$191,"<="&DATE(J107,12,31)),"")
A108: 39814 | B108: =IFERROR(haverdata(Codes!$D$6,$A108),"") | C108: =IFERROR(B108/B107-1,"") | D108: =IFERROR(B108/B104-1,"") | E108: =IFERROR(IF(B108="",IFERROR(GROWTH($B$104:$B$191,$A$104:$A$191,$A108),TREND($B$104:$B$191,$A$104:$A$191,$A108)),""),"") | F108: =IFERROR(forecast.ets($A108,$B$104:$B$191,$A$104:$A$191,4,1,1),"") | G108: =IFERROR(F108-forecast.ets.confint($A108,$B$104:$B$191,$A$104:$A$191,0.95,4,1,1),"") | H108: =IFERROR(F108+forecast.ets.confint($A108,$B$104:$B$191,$A$104:$A$191,0.95,4,1,1),"") | J108: 2012 | K108: =IFERROR(AVERAGEIFS($B$104:$B$191,$A$104:$A$191,">="&DATE(J108,1,1),$A$104:$A$191,"<="&DATE(J108,12,31)),"") | L108: =IFERROR(K108/K107-1,"") | M108: =IFERROR(AVERAGEIFS($F$104:$F$191,$A$104:$A$191,">="&DATE(J108,1,1),$A$104:$A$191,"<="&DATE(J108,12,31)),"")
A109: 39904 | B109: =IFERROR(haverdata(Codes!$D$6,$A109),"") | C109: =IFERROR(B109/B108-1,"") | D109: =IFERROR(B109/B105-1,"") | E109: =IFERROR(IF(B109="",IFERROR(GROWTH($B$104:$B$191,$A$104:$A$191,$A109),TREND($B$104:$B$191,$A$104:$A$191,$A109)),""),"") | F109: =IFERROR(forecast.ets($A109,$B$104:$B$191,$A$104:$A$191,4,1,1),"") | G109: =IFERROR(F109-forecast.ets.confint($A109,$B$104:$B$191,$A$104:$A$191,0.95,4,1,1),"") | H109: =IFERROR(F109+forecast.ets.confint($A109,$B$104:$B$191,$A$104:$A$191,0.95,4,1,1),"") | J109: 2013 | K109: =IFERROR(AVERAGEIFS($B$104:$B$191,$A$104:$A$191,">="&DATE(J109,1,1),$A$104:$A$191,"<="&DATE(J109,12,31)),"") | L109: =IFERROR(K109/K108-1,"") | M109: =IFERROR(AVERAGEIFS($F$104:$F$191,$A$104:$A$191,">="&DATE(J109,1,1),$A$104:$A$191,"<="&DATE(J109,12,31)),"")
A110: 39995 | B110: =IFERROR(haverdata(Codes!$D$6,$A110),"") | C110: =IFERROR(B110/B109-1,"") | D110: =IFERROR(B110/B106-1,"") | E110: =IFERROR(IF(B110="",IFERROR(GROWTH($B$104:$B$191,$A$104:$A$191,$A110),TREND($B$104:$B$191,$A$104:$A$191,$A110)),""),"") | F110: =IFERROR(forecast.ets($A110,$B$104:$B$191,$A$104:$A$191,4,1,1),"") | G110: =IFERROR(F110-forecast.ets.confint($A110,$B$104:$B$191,$A$104:$A$191,0.95,4,1,1),"") | H110: =IFERROR(F110+forecast.ets.confint($A110,$B$104:$B$191,$A$104:$A$191,0.95,4,1,1),"") | J110: 2014 | K110: =IFERROR(AVERAGEIFS($B$104:$B$191,$A$104:$A$191,">="&DATE(J110,1,1),$A$104:$A$191,"<="&DATE(J110,12,31)),"") | L110: =IFERROR(K110/K109-1,"") | M110: =IFERROR(AVERAGEIFS($F$104:$F$191,$A$104:$A$191,">="&DATE(J110,1,1),$A$104:$A$191,"<="&DATE(J110,12,31)),"")
A111: 40087 | B111: =IFERROR(haverdata(Codes!$D$6,$A111),"") | C111: =IFERROR(B111/B110-1,"") | D111: =IFERROR(B111/B107-1,"") | E111: =IFERROR(IF(B111="",IFERROR(GROWTH($B$104:$B$191,$A$104:$A$191,$A111),TREND($B$104:$B$191,$A$104:$A$191,$A111)),""),"") | F111: =IFERROR(forecast.ets($A111,$B$104:$B$191,$A$104:$A$191,4,1,1),"") | G111: =IFERROR(F111-forecast.ets.confint($A111,$B$104:$B$191,$A$104:$A$191,0.95,4,1,1),"") | H111: =IFERROR(F111+forecast.ets.confint($A111,$B$104:$B$191,$A$104:$A$191,0.95,4,1,1),"") | J111: 2015 | K111: =IFERROR(AVERAGEIFS($B$104:$B$191,$A$104:$A$191,">="&DATE(J111,1,1),$A$104:$A$191,"<="&DATE(J111,12,31)),"") | L111: =IFERROR(K111/K110-1,"") | M111: =IFERROR(AVERAGEIFS($F$104:$F$191,$A$104:$A$191,">="&DATE(J111,1,1),$A$104:$A$191,"<="&DATE(J111,12,31)),"")
A112: 40179 | B112: =IFERROR(haverdata(Codes!$D$6,$A112),"") | C112: =IFERROR(B112/B111-1,"") | D112: =IFERROR(B112/B108-1,"") | E112: =IFERROR(IF(B112="",IFERROR(GROWTH($B$104:$B$191,$A$104:$A$191,$A112),TREND($B$104:$B$191,$A$104:$A$191,$A112)),""),"") | F112: =IFERROR(forecast.ets($A112,$B$104:$B$191,$A$104:$A$191,4,1,1),"") | G112: =IFERROR(F112-forecast.ets.confint($A112,$B$104:$B$191,$A$104:$A$191,0.95,4,1,1),"") | H112: =IFERROR(F112+forecast.ets.confint($A112,$B$104:$B$191,$A$104:$A$191,0.95,4,1,1),"") | J112: 2016 | K112: =IFERROR(AVERAGEIFS($B$104:$B$191,$A$104:$A$191,">="&DATE(J112,1,1),$A$104:$A$191,"<="&DATE(J112,12,31)),"") | L112: =IFERROR(K112/K111-1,"") | M112: =IFERROR(AVERAGEIFS($F$104:$F$191,$A$104:$A$191,">="&DATE(J112,1,1),$A$104:$A$191,"<="&DATE(J112,12,31)),"")
A113: 40269 | B113: =IFERROR(haverdata(Codes!$D$6,$A113),"") | C113: =IFERROR(B113/B112-1,"") | D113: =IFERROR(B113/B109-1,"") | E113: =IFERROR(IF(B113="",IFERROR(GROWTH($B$104:$B$191,$A$104:$A$191,$A113),TREND($B$104:$B$191,$A$104:$A$191,$A113)),""),"") | F113: =IFERROR(forecast.ets($A113,$B$104:$B$191,$A$104:$A$191,4,1,1),"") | G113: =IFERROR(F113-forecast.ets.confint($A113,$B$104:$B$191,$A$104:$A$191,0.95,4,1,1),"") | H113: =IFERROR(F113+forecast.ets.confint($A113,$B$104:$B$191,$A$104:$A$191,0.95,4,1,1),"") | J113: 2017 | K113: =IFERROR(AVERAGEIFS($B$104:$B$191,$A$104:$A$191,">="&DATE(J113,1,1),$A$104:$A$191,"<="&DATE(J113,12,31)),"") | L113: =IFERROR(K113/K112-1,"") | M113: =IFERROR(AVERAGEIFS($F$104:$F$191,$A$104:$A$191,">="&DATE(J113,1,1),$A$104:$A$191,"<="&DATE(J113,12,31)),"")
A114: 40360 | B114: =IFERROR(haverdata(Codes!$D$6,$A114),"") | C114: =IFERROR(B114/B113-1,"") | D114: =IFERROR(B114/B110-1,"") | E114: =IFERROR(IF(B114="",IFERROR(GROWTH($B$104:$B$191,$A$104:$A$191,$A114),TREND($B$104:$B$191,$A$104:$A$191,$A114)),""),"") | F114: =IFERROR(forecast.ets($A114,$B$104:$B$191,$A$104:$A$191,4,1,1),"") | G114: =IFERROR(F114-forecast.ets.confint($A114,$B$104:$B$191,$A$104:$A$191,0.95,4,1,1),"") | H114: =IFERROR(F114+forecast.ets.confint($A114,$B$104:$B$191,$A$104:$A$191,0.95,4,1,1),"") | J114: 2018 | K114: =IFERROR(AVERAGEIFS($B$104:$B$191,$A$104:$A$191,">="&DATE(J114,1,1),$A$104:$A$191,"<="&DATE(J114,12,31)),"") | L114: =IFERROR(K114/K113-1,"") | M114: =IFERROR(AVERAGEIFS($F$104:$F$191,$A$104:$A$191,">="&DATE(J114,1,1),$A$104:$A$191,"<="&DATE(J114,12,31)),"")
A115: 40452 | B115: =IFERROR(haverdata(Codes!$D$6,$A115),"") | C115: =IFERROR(B115/B114-1,"") | D115: =IFERROR(B115/B111-1,"") | E115: =IFERROR(IF(B115="",IFERROR(GROWTH($B$104:$B$191,$A$104:$A$191,$A115),TREND($B$104:$B$191,$A$104:$A$191,$A115)),""),"") | F115: =IFERROR(forecast.ets($A115,$B$104:$B$191,$A$104:$A$191,4,1,1),"") | G115: =IFERROR(F115-forecast.ets.confint($A115,$B$104:$B$191,$A$104:$A$191,0.95,4,1,1),"") | H115: =IFERROR(F115+forecast.ets.confint($A115,$B$104:$B$191,$A$104:$A$191,0.95,4,1,1),"") | J115: 2019 | K115: =IFERROR(AVERAGEIFS($B$104:$B$191,$A$104:$A$191,">="&DATE(J115,1,1),$A$104:$A$191,"<="&DATE(J115,12,31)),"") | L115: =IFERROR(K115/K114-1,"") | M115: =IFERROR(AVERAGEIFS($F$104:$F$191,$A$104:$A$191,">="&DATE(J115,1,1),$A$104:$A$191,"<="&DATE(J115,12,31)),"")
A116: 40544 | B116: =IFERROR(haverdata(Codes!$D$6,$A116),"") | C116: =IFERROR(B116/B115-1,"") | D116: =IFERROR(B116/B112-1,"") | E116: =IFERROR(IF(B116="",IFERROR(GROWTH($B$104:$B$191,$A$104:$A$191,$A116),TREND($B$104:$B$191,$A$104:$A$191,$A116)),""),"") | F116: =IFERROR(forecast.ets($A116,$B$104:$B$191,$A$104:$A$191,4,1,1),"") | G116: =IFERROR(F116-forecast.ets.confint($A116,$B$104:$B$191,$A$104:$A$191,0.95,4,1,1),"") | H116: =IFERROR(F116+forecast.ets.confint($A116,$B$104:$B$191,$A$104:$A$191,0.95,4,1,1),"") | J116: 2020 | K116: =IFERROR(AVERAGEIFS($B$104:$B$191,$A$104:$A$191,">="&DATE(J116,1,1),$A$104:$A$191,"<="&DATE(J116,12,31)),"") | L116: =IFERROR(K116/K115-1,"") | M116: =IFERROR(AVERAGEIFS($F$104:$F$191,$A$104:$A$191,">="&DATE(J116,1,1),$A$104:$A$191,"<="&DATE(J116,12,31)),"")
A117: 40634 | B117: =IFERROR(haverdata(Codes!$D$6,$A117),"") | C117: =IFERROR(B117/B116-1,"") | D117: =IFERROR(B117/B113-1,"") | E117: =IFERROR(IF(B117="",IFERROR(GROWTH($B$104:$B$191,$A$104:$A$191,$A117),TREND($B$104:$B$191,$A$104:$A$191,$A117)),""),"") | F117: =IFERROR(forecast.ets($A117,$B$104:$B$191,$A$104:$A$191,4,1,1),"") | G117: =IFERROR(F117-forecast.ets.confint($A117,$B$104:$B$191,$A$104:$A$191,0.95,4,1,1),"") | H117: =IFERROR(F117+forecast.ets.confint($A117,$B$104:$B$191,$A$104:$A$191,0.95,4,1,1),"") | J117: 2021 | K117: =IFERROR(AVERAGEIFS($B$104:$B$191,$A$104:$A$191,">="&DATE(J117,1,1),$A$104:$A$191,"<="&DATE(J117,12,31)),"") | L117: =IFERROR(K117/K116-1,"") | M117: =IFERROR(AVERAGEIFS($F$104:$F$191,$A$104:$A$191,">="&DATE(J117,1,1),$A$104:$A$191,"<="&DATE(J117,12,31)),"")
A118: 40725 | B118: =IFERROR(haverdata(Codes!$D$6,$A118),"") | C118: =IFERROR(B118/B117-1,"") | D118: =IFERROR(B118/B114-1,"") | E118: =IFERROR(IF(B118="",IFERROR(GROWTH($B$104:$B$191,$A$104:$A$191,$A118),TREND($B$104:$B$191,$A$104:$A$191,$A118)),""),"") | F118: =IFERROR(forecast.ets($A118,$B$104:$B$191,$A$104:$A$191,4,1,1),"") | G118: =IFERROR(F118-forecast.ets.confint($A118,$B$104:$B$191,$A$104:$A$191,0.95,4,1,1),"") | H118: =IFERROR(F118+forecast.ets.confint($A118,$B$104:$B$191,$A$104:$A$191,0.95,4,1,1),"") | J118: 2022 | K118: =IFERROR(AVERAGEIFS($B$104:$B$191,$A$104:$A$191,">="&DATE(J118,1,1),$A$104:$A$191,"<="&DATE(J118,12,31)),"") | L118: =IFERROR(K118/K117-1,"") | M118: =IFERROR(AVERAGEIFS($F$104:$F$191,$A$104:$A$191,">="&DATE(J118,1,1),$A$104:$A$191,"<="&DATE(J118,12,31)),"")
A119: 40817 | B119: =IFERROR(haverdata(Codes!$D$6,$A119),"") | C119: =IFERROR(B119/B118-1,"") | D119: =IFERROR(B119/B115-1,"") | E119: =IFERROR(IF(B119="",IFERROR(GROWTH($B$104:$B$191,$A$104:$A$191,$A119),TREND($B$104:$B$191,$A$104:$A$191,$A119)),""),"") | F119: =IFERROR(forecast.ets($A119,$B$104:$B$191,$A$104:$A$191,4,1,1),"") | G119: =IFERROR(F119-forecast.ets.confint($A119,$B$104:$B$191,$A$104:$A$191,0.95,4,1,1),"") | H119: =IFERROR(F119+forecast.ets.confint($A119,$B$104:$B$191,$A$104:$A$191,0.95,4,1,1),"") | J119: 2023 | K119: =IFERROR(AVERAGEIFS($B$104:$B$191,$A$104:$A$191,">="&DATE(J119,1,1),$A$104:$A$191,"<="&DATE(J119,12,31)),"") | L119: =IFERROR(K119/K118-1,"") | M119: =IFERROR(AVERAGEIFS($F$104:$F$191,$A$104:$A$191,">="&DATE(J119,1,1),$A$104:$A$191,"<="&DATE(J119,12,31)),"")
... A125: 41365 | B125: =IFERROR(haverdata(Codes!$D$6,$A125),"") | C125: =IFERROR(B125/B124-1,"") | D125: =IFERROR(B125/B121-1,"") | E125: =IFERROR(IF(B125="",IFERROR(GROWTH($B$104:$B$191,$A$104:$A$191,$A125),TREND($B$104:$B$191,$A$104:$A$191,$A125)),""),"") | F125: =IFERROR(forecast.ets($A125,$B$104:$B$191,$A$104:$A$191,4,1,1),"") | G125: =IFERROR(F125-forecast.ets.confint($A125,$B$104:$B$191,$A$104:$A$191,0.95,4,1,1),"") | H125: =IFERROR(F125+forecast.ets.confint($A125,$B$104:$B$191,$A$104:$A$191,0.95,4,1,1),"") | J125: 2029 | K125: =IFERROR(AVERAGEIFS($B$104:$B$191,$A$104:$A$191,">="&DATE(J125,1,1),$A$104:$A$191,"<="&DATE(J125,12,31)),"") | L125: =IFERROR(K125/K124-1,"") | M125: =IFERROR(AVERAGEIFS($F$104:$F$191,$A$104:$A$191,">="&DATE(J125,1,1),$A$104:$A$191,"<="&DATE(J125,12,31)),"")
A126: 41456 | B126: =IFERROR(haverdata(Codes!$D$6,$A126),"") | C126: =IFERROR(B126/B125-1,"") | D126: =IFERROR(B126/B122-1,"") | E126: =IFERROR(IF(B126="",IFERROR(GROWTH($B$104:$B$191,$A$104:$A$191,$A126),TREND($B$104:$B$191,$A$104:$A$191,$A126)),""),"") | F126: =IFERROR(forecast.ets($A126,$B$104:$B$191,$A$104:$A$191,4,1,1),"") | G126: =IFERROR(F126-forecast.ets.confint($A126,$B$104:$B$191,$A$104:$A$191,0.95,4,1,1),"") | H126: =IFERROR(F126+forecast.ets.confint($A126,$B$104:$B$191,$A$104:$A$191,0.95,4,1,1),"")
A127: 41548 | B127: =IFERROR(haverdata(Codes!$D$6,$A127),"") | C127: =IFERROR(B127/B126-1,"") | D127: =IFERROR(B127/B123-1,"") | E127: =IFERROR(IF(B127="",IFERROR(GROWTH($B$104:$B$191,$A$104:$A$191,$A127),TREND($B$104:$B$191,$A$104:$A$191,$A127)),""),"") | F127: =IFERROR(forecast.ets($A127,$B$104:$B$191,$A$104:$A$191,4,1,1),"") | G127: =IFERROR(F127-forecast.ets.confint($A127,$B$104:$B$191,$A$104:$A$191,0.95,4,1,1),"") | H127: =IFERROR(F127+forecast.ets.confint($A127,$B$104:$B$191,$A$104:$A$191,0.95,4,1,1),"")
A128: 41640 | B128: =IFERROR(haverdata(Codes!$D$6,$A128),"") | C128: =IFERROR(B128/B127-1,"") | D128: =IFERROR(B128/B124-1,"") | E128: =IFERROR(IF(B128="",IFERROR(GROWTH($B$104:$B$191,$A$104:$A$191,$A128),TREND($B$104:$B$191,$A$104:$A$191,$A128)),""),"") | F128: =IFERROR(forecast.ets($A128,$B$104:$B$191,$A$104:$A$191,4,1,1),"") | G128: =IFERROR(F128-forecast.ets.confint($A128,$B$104:$B$191,$A$104:$A$191,0.95,4,1,1),"") | H128: =IFERROR(F128+forecast.ets.confint($A128,$B$104:$B$191,$A$104:$A$191,0.95,4,1,1),"")
A129: 41730 | B129: =IFERROR(haverdata(Codes!$D$6,$A129),"") | C129: =IFERROR(B129/B128-1,"") | D129: =IFERROR(B129/B125-1,"") | E129: =IFERROR(IF(B129="",IFERROR(GROWTH($B$104:$B$191,$A$104:$A$191,$A129),TREND($B$104:$B$191,$A$104:$A$191,$A129)),""),"") | F129: =IFERROR(forecast.ets($A129,$B$104:$B$191,$A$104:$A$191,4,1,1),"") | G129: =IFERROR(F129-forecast.ets.confint($A129,$B$104:$B$191,$A$104:$A$191,0.95,4,1,1),"") | H129: =IFERROR(F129+forecast.ets.confint($A129,$B$104:$B$191,$A$104:$A$191,0.95,4,1,1),"")
A130: 41821 | B130: =IFERROR(haverdata(Codes!$D$6,$A130),"") | C130: =IFERROR(B130/B129-1,"") | D130: =IFERROR(B130/B126-1,"") | E130: =IFERROR(IF(B130="",IFERROR(GROWTH($B$104:$B$191,$A$104:$A$191,$A130),TREND($B$104:$B$191,$A$104:$A$191,$A130)),""),"") | F130: =IFERROR(forecast.ets($A130,$B$104:$B$191,$A$104:$A$191,4,1,1),"") | G130: =IFERROR(F130-forecast.ets.confint($A130,$B$104:$B$191,$A$104:$A$191,0.95,4,1,1),"") | H130: =IFERROR(F130+forecast.ets.confint($A130,$B$104:$B$191,$A$104:$A$191,0.95,4,1,1),"")
A131: 41913 | B131: =IFERROR(haverdata(Codes!$D$6,$A131),"") | C131: =IFERROR(B131/B130-1,"") | D131: =IFERROR(B131/B127-1,"") | E131: =IFERROR(IF(B131="",IFERROR(GROWTH($B$104:$B$191,$A$104:$A$191,$A131),TREND($B$104:$B$191,$A$104:$A$191,$A131)),""),"") | F131: =IFERROR(forecast.ets($A131,$B$104:$B$191,$A$104:$A$191,4,1,1),"") | G131: =IFERROR(F131-forecast.ets.confint($A131,$B$104:$B$191,$A$104:$A$191,0.95,4,1,1),"") | H131: =IFERROR(F131+forecast.ets.confint($A131,$B$104:$B$191,$A$104:$A$191,0.95,4,1,1),"")
A132: 42005 | B132: =IFERROR(haverdata(Codes!$D$6,$A132),"") | C132: =IFERROR(B132/B131-1,"") | D132: =IFERROR(B132/B128-1,"") | E132: =IFERROR(IF(B132="",IFERROR(GROWTH($B$104:$B$191,$A$104:$A$191,$A132),TREND($B$104:$B$191,$A$104:$A$191,$A132)),""),"") | F132: =IFERROR(forecast.ets($A132,$B$104:$B$191,$A$104:$A$191,4,1,1),"") | G132: =IFERROR(F132-forecast.ets.confint($A132,$B$104:$B$191,$A$104:$A$191,0.95,4,1,1),"") | H132: =IFERROR(F132+forecast.ets.confint($A132,$B$104:$B$191,$A$104:$A$191,0.95,4,1,1),"")
A133: 42095 | B133: =IFERROR(haverdata(Codes!$D$6,$A133),"") | C133: =IFERROR(B133/B132-1,"") | D133: =IFERROR(B133/B129-1,"") | E133: =IFERROR(IF(B133="",IFERROR(GROWTH($B$104:$B$191,$A$104:$A$191,$A133),TREND($B$104:$B$191,$A$104:$A$191,$A133)),""),"") | F133: =IFERROR(forecast.ets($A133,$B$104:$B$191,$A$104:$A$191,4,1,1),"") | G133: =IFERROR(F133-forecast.ets.confint($A133,$B$104:$B$191,$A$104:$A$191,0.95,4,1,1),"") | H133: =IFERROR(F133+forecast.ets.confint($A133,$B$104:$B$191,$A$104:$A$191,0.95,4,1,1),"")
A134: 42186 | B134: =IFERROR(haverdata(Codes!$D$6,$A134),"") | C134: =IFERROR(B134/B133-1,"") | D134: =IFERROR(B134/B130-1,"") | E134: =IFERROR(IF(B134="",IFERROR(GROWTH($B$104:$B$191,$A$104:$A$191,$A134),TREND($B$104:$B$191,$A$104:$A$191,$A134)),""),"") | F134: =IFERROR(forecast.ets($A134,$B$104:$B$191,$A$104:$A$191,4,1,1),"") | G134: =IFERROR(F134-forecast.ets.confint($A134,$B$104:$B$191,$A$104:$A$191,0.95,4,1,1),"") | H134: =IFERROR(F134+forecast.ets.confint($A134,$B$104:$B$191,$A$104:$A$191,0.95,4,1,1),"")
A135: 42278 | B135: =IFERROR(haverdata(Codes!$D$6,$A135),"") | C135: =IFERROR(B135/B134-1,"") | D135: =IFERROR(B135/B131-1,"") | E135: =IFERROR(IF(B135="",IFERROR(GROWTH($B$104:$B$191,$A$104:$A$191,$A135),TREND($B$104:$B$191,$A$104:$A$191,$A135)),""),"") | F135: =IFERROR(forecast.ets($A135,$B$104:$B$191,$A$104:$A$191,4,1,1),"") | G135: =IFERROR(F135-forecast.ets.confint($A135,$B$104:$B$191,$A$104:$A$191,0.95,4,1,1),"") | H135: =IFERROR(F135+forecast.ets.confint($A135,$B$104:$B$191,$A$104:$A$191,0.95,4,1,1),"")
A136: 42370 | B136: =IFERROR(haverdata(Codes!$D$6,$A136),"") | C136: =IFERROR(B136/B135-1,"") | D136: =IFERROR(B136/B132-1,"") | E136: =IFERROR(IF(B136="",IFERROR(GROWTH($B$104:$B$191,$A$104:$A$191,$A136),TREND($B$104:$B$191,$A$104:$A$191,$A136)),""),"") | F136: =IFERROR(forecast.ets($A136,$B$104:$B$191,$A$104:$A$191,4,1,1),"") | G136: =IFERROR(F136-forecast.ets.confint($A136,$B$104:$B$191,$A$104:$A$191,0.95,4,1,1),"") | H136: =IFERROR(F136+forecast.ets.confint($A136,$B$104:$B$191,$A$104:$A$191,0.95,4,1,1),"")
A137: 42461 | B137: =IFERROR(haverdata(Codes!$D$6,$A137),"") | C137: =IFERROR(B137/B136-1,"") | D137: =IFERROR(B137/B133-1,"") | E137: =IFERROR(IF(B137="",IFERROR(GROWTH($B$104:$B$191,$A$104:$A$191,$A137),TREND($B$104:$B$191,$A$104:$A$191,$A137)),""),"") | F137: =IFERROR(forecast.ets($A137,$B$104:$B$191,$A$104:$A$191,4,1,1),"") | G137: =IFERROR(F137-forecast.ets.confint($A137,$B$104:$B$191,$A$104:$A$191,0.95,4,1,1),"") | H137: =IFERROR(F137+forecast.ets.confint($A137,$B$104:$B$191,$A$104:$A$191,0.95,4,1,1),"")
... A191: 47392 | B191: =IFERROR(haverdata(Codes!$D$6,$A191),"") | C191: =IFERROR(B191/B190-1,"") | D191: =IFERROR(B191/B187-1,"") | E191: =IFERROR(IF(B191="",IFERROR(GROWTH($B$104:$B$191,$A$104:$A$191,$A191),TREND($B$104:$B$191,$A$104:$A$191,$A191)),""),"") | F191: =IFERROR(forecast.ets($A191,$B$104:$B$191,$A$104:$A$191,4,1,1),"") | G191: =IFERROR(F191-forecast.ets.confint($A191,$B$104:$B$191,$A$104:$A$191,0.95,4,1,1),"") | H191: =IFERROR(F191+forecast.ets.confint($A191,$B$104:$B$191,$A$104:$A$191,0.95,4,1,1),"")
A196: =Codes!$B$7&" ["&Codes!$D$7&"] "&Codes!$F$7 -> EMAE Activity Index [EMAE@ARGEN] Index 2004=100
A197: Aggregation: | B197: =Codes!$G$7 -> avg | D197: Notes: | E197: =Codes!$H$7 -> INDEC monthly activity proxy. [VERIFY] code on your subscription.
A198: Quarterly | J198: Annual
A199: Date | B199: Level | C199: QoQ % | D199: YoY % | E199: Linear Fcst | F199: ETS Fcst | G199: ETS Low 95% | H199: ETS High 95% | J199: Year | K199: Level | L199: YoY % | M199: Forecast
A200: 39448 | B200: =IFERROR(haverdata(Codes!$D$7,$A200),"") | E200: =IFERROR(IF(B200="",IFERROR(GROWTH($B$200:$B$287,$A$200:$A$287,$A200),TREND($B$200:$B$287,$A$200:$A$287,$A200)),""),"") | F200: =IFERROR(forecast.ets($A200,$B$200:$B$287,$A$200:$A$287,4,1,1),"") | G200: =IFERROR(F200-forecast.ets.confint($A200,$B$200:$B$287,$A$200:$A$287,0.95,4,1,1),"") | H200: =IFERROR(F200+forecast.ets.confint($A200,$B$200:$B$287,$A$200:$A$287,0.95,4,1,1),"") | J200: 2008 | K200: =IFERROR(AVERAGEIFS($B$200:$B$287,$A$200:$A$287,">="&DATE(J200,1,1),$A$200:$A$287,"<="&DATE(J200,12,31)),"") | M200: =IFERROR(AVERAGEIFS($F$200:$F$287,$A$200:$A$287,">="&DATE(J200,1,1),$A$200:$A$287,"<="&DATE(J200,12,31)),"")
A201: 39539 | B201: =IFERROR(haverdata(Codes!$D$7,$A201),"") | C201: =IFERROR(B201/B200-1,"") | E201: =IFERROR(IF(B201="",IFERROR(GROWTH($B$200:$B$287,$A$200:$A$287,$A201),TREND($B$200:$B$287,$A$200:$A$287,$A201)),""),"") | F201: =IFERROR(forecast.ets($A201,$B$200:$B$287,$A$200:$A$287,4,1,1),"") | G201: =IFERROR(F201-forecast.ets.confint($A201,$B$200:$B$287,$A$200:$A$287,0.95,4,1,1),"") | H201: =IFERROR(F201+forecast.ets.confint($A201,$B$200:$B$287,$A$200:$A$287,0.95,4,1,1),"") | J201: 2009 | K201: =IFERROR(AVERAGEIFS($B$200:$B$287,$A$200:$A$287,">="&DATE(J201,1,1),$A$200:$A$287,"<="&DATE(J201,12,31)),"") | L201: =IFERROR(K201/K200-1,"") | M201: =IFERROR(AVERAGEIFS($F$200:$F$287,$A$200:$A$287,">="&DATE(J201,1,1),$A$200:$A$287,"<="&DATE(J201,12,31)),"")
A202: 39630 | B202: =IFERROR(haverdata(Codes!$D$7,$A202),"") | C202: =IFERROR(B202/B201-1,"") | E202: =IFERROR(IF(B202="",IFERROR(GROWTH($B$200:$B$287,$A$200:$A$287,$A202),TREND($B$200:$B$287,$A$200:$A$287,$A202)),""),"") | F202: =IFERROR(forecast.ets($A202,$B$200:$B$287,$A$200:$A$287,4,1,1),"") | G202: =IFERROR(F202-forecast.ets.confint($A202,$B$200:$B$287,$A$200:$A$287,0.95,4,1,1),"") | H202: =IFERROR(F202+forecast.ets.confint($A202,$B$200:$B$287,$A$200:$A$287,0.95,4,1,1),"") | J202: 2010 | K202: =IFERROR(AVERAGEIFS($B$200:$B$287,$A$200:$A$287,">="&DATE(J202,1,1),$A$200:$A$287,"<="&DATE(J202,12,31)),"") | L202: =IFERROR(K202/K201-1,"") | M202: =IFERROR(AVERAGEIFS($F$200:$F$287,$A$200:$A$287,">="&DATE(J202,1,1),$A$200:$A$287,"<="&DATE(J202,12,31)),"")
A203: 39722 | B203: =IFERROR(haverdata(Codes!$D$7,$A203),"") | C203: =IFERROR(B203/B202-1,"") | E203: =IFERROR(IF(B203="",IFERROR(GROWTH($B$200:$B$287,$A$200:$A$287,$A203),TREND($B$200:$B$287,$A$200:$A$287,$A203)),""),"") | F203: =IFERROR(forecast.ets($A203,$B$200:$B$287,$A$200:$A$287,4,1,1),"") | G203: =IFERROR(F203-forecast.ets.confint($A203,$B$200:$B$287,$A$200:$A$287,0.95,4,1,1),"") | H203: =IFERROR(F203+forecast.ets.confint($A203,$B$200:$B$287,$A$200:$A$287,0.95,4,1,1),"") | J203: 2011 | K203: =IFERROR(AVERAGEIFS($B$200:$B$287,$A$200:$A$287,">="&DATE(J203,1,1),$A$200:$A$287,"<="&DATE(J203,12,31)),"") | L203: =IFERROR(K203/K202-1,"") | M203: =IFERROR(AVERAGEIFS($F$200:$F$287,$A$200:$A$287,">="&DATE(J203,1,1),$A$200:$A$287,"<="&DATE(J203,12,31)),"")
A204: 39814 | B204: =IFERROR(haverdata(Codes!$D$7,$A204),"") | C204: =IFERROR(B204/B203-1,"") | D204: =IFERROR(B204/B200-1,"") | E204: =IFERROR(IF(B204="",IFERROR(GROWTH($B$200:$B$287,$A$200:$A$287,$A204),TREND($B$200:$B$287,$A$200:$A$287,$A204)),""),"") | F204: =IFERROR(forecast.ets($A204,$B$200:$B$287,$A$200:$A$287,4,1,1),"") | G204: =IFERROR(F204-forecast.ets.confint($A204,$B$200:$B$287,$A$200:$A$287,0.95,4,1,1),"") | H204: =IFERROR(F204+forecast.ets.confint($A204,$B$200:$B$287,$A$200:$A$287,0.95,4,1,1),"") | J204: 2012 | K204: =IFERROR(AVERAGEIFS($B$200:$B$287,$A$200:$A$287,">="&DATE(J204,1,1),$A$200:$A$287,"<="&DATE(J204,12,31)),"") | L204: =IFERROR(K204/K203-1,"") | M204: =IFERROR(AVERAGEIFS($F$200:$F$287,$A$200:$A$287,">="&DATE(J204,1,1),$A$200:$A$287,"<="&DATE(J204,12,31)),"")
A205: 39904 | B205: =IFERROR(haverdata(Codes!$D$7,$A205),"") | C205: =IFERROR(B205/B204-1,"") | D205: =IFERROR(B205/B201-1,"") | E205: =IFERROR(IF(B205="",IFERROR(GROWTH($B$200:$B$287,$A$200:$A$287,$A205),TREND($B$200:$B$287,$A$200:$A$287,$A205)),""),"") | F205: =IFERROR(forecast.ets($A205,$B$200:$B$287,$A$200:$A$287,4,1,1),"") | G205: =IFERROR(F205-forecast.ets.confint($A205,$B$200:$B$287,$A$200:$A$287,0.95,4,1,1),"") | H205: =IFERROR(F205+forecast.ets.confint($A205,$B$200:$B$287,$A$200:$A$287,0.95,4,1,1),"") | J205: 2013 | K205: =IFERROR(AVERAGEIFS($B$200:$B$287,$A$200:$A$287,">="&DATE(J205,1,1),$A$200:$A$287,"<="&DATE(J205,12,31)),"") | L205: =IFERROR(K205/K204-1,"") | M205: =IFERROR(AVERAGEIFS($F$200:$F$287,$A$200:$A$287,">="&DATE(J205,1,1),$A$200:$A$287,"<="&DATE(J205,12,31)),"")
A206: 39995 | B206: =IFERROR(haverdata(Codes!$D$7,$A206),"") | C206: =IFERROR(B206/B205-1,"") | D206: =IFERROR(B206/B202-1,"") | E206: =IFERROR(IF(B206="",IFERROR(GROWTH($B$200:$B$287,$A$200:$A$287,$A206),TREND($B$200:$B$287,$A$200:$A$287,$A206)),""),"") | F206: =IFERROR(forecast.ets($A206,$B$200:$B$287,$A$200:$A$287,4,1,1),"") | G206: =IFERROR(F206-forecast.ets.confint($A206,$B$200:$B$287,$A$200:$A$287,0.95,4,1,1),"") | H206: =IFERROR(F206+forecast.ets.confint($A206,$B$200:$B$287,$A$200:$A$287,0.95,4,1,1),"") | J206: 2014 | K206: =IFERROR(AVERAGEIFS($B$200:$B$287,$A$200:$A$287,">="&DATE(J206,1,1),$A$200:$A$287,"<="&DATE(J206,12,31)),"") | L206: =IFERROR(K206/K205-1,"") | M206: =IFERROR(AVERAGEIFS($F$200:$F$287,$A$200:$A$287,">="&DATE(J206,1,1),$A$200:$A$287,"<="&DATE(J206,12,31)),"")
A207: 40087 | B207: =IFERROR(haverdata(Codes!$D$7,$A207),"") | C207: =IFERROR(B207/B206-1,"") | D207: =IFERROR(B207/B203-1,"") | E207: =IFERROR(IF(B207="",IFERROR(GROWTH($B$200:$B$287,$A$200:$A$287,$A207),TREND($B$200:$B$287,$A$200:$A$287,$A207)),""),"") | F207: =IFERROR(forecast.ets($A207,$B$200:$B$287,$A$200:$A$287,4,1,1),"") | G207: =IFERROR(F207-forecast.ets.confint($A207,$B$200:$B$287,$A$200:$A$287,0.95,4,1,1),"") | H207: =IFERROR(F207+forecast.ets.confint($A207,$B$200:$B$287,$A$200:$A$287,0.95,4,1,1),"") | J207: 2015 | K207: =IFERROR(AVERAGEIFS($B$200:$B$287,$A$200:$A$287,">="&DATE(J207,1,1),$A$200:$A$287,"<="&DATE(J207,12,31)),"") | L207: =IFERROR(K207/K206-1,"") | M207: =IFERROR(AVERAGEIFS($F$200:$F$287,$A$200:$A$287,">="&DATE(J207,1,1),$A$200:$A$287,"<="&DATE(J207,12,31)),"")
A208: 40179 | B208: =IFERROR(haverdata(Codes!$D$7,$A208),"") | C208: =IFERROR(B208/B207-1,"") | D208: =IFERROR(B208/B204-1,"") | E208: =IFERROR(IF(B208="",IFERROR(GROWTH($B$200:$B$287,$A$200:$A$287,$A208),TREND($B$200:$B$287,$A$200:$A$287,$A208)),""),"") | F208: =IFERROR(forecast.ets($A208,$B$200:$B$287,$A$200:$A$287,4,1,1),"") | G208: =IFERROR(F208-forecast.ets.confint($A208,$B$200:$B$287,$A$200:$A$287,0.95,4,1,1),"") | H208: =IFERROR(F208+forecast.ets.confint($A208,$B$200:$B$287,$A$200:$A$287,0.95,4,1,1),"") | J208: 2016 | K208: =IFERROR(AVERAGEIFS($B$200:$B$287,$A$200:$A$287,">="&DATE(J208,1,1),$A$200:$A$287,"<="&DATE(J208,12,31)),"") | L208: =IFERROR(K208/K207-1,"") | M208: =IFERROR(AVERAGEIFS($F$200:$F$287,$A$200:$A$287,">="&DATE(J208,1,1),$A$200:$A$287,"<="&DATE(J208,12,31)),"")
A209: 40269 | B209: =IFERROR(haverdata(Codes!$D$7,$A209),"") | C209: =IFERROR(B209/B208-1,"") | D209: =IFERROR(B209/B205-1,"") | E209: =IFERROR(IF(B209="",IFERROR(GROWTH($B$200:$B$287,$A$200:$A$287,$A209),TREND($B$200:$B$287,$A$200:$A$287,$A209)),""),"") | F209: =IFERROR(forecast.ets($A209,$B$200:$B$287,$A$200:$A$287,4,1,1),"") | G209: =IFERROR(F209-forecast.ets.confint($A209,$B$200:$B$287,$A$200:$A$287,0.95,4,1,1),"") | H209: =IFERROR(F209+forecast.ets.confint($A209,$B$200:$B$287,$A$200:$A$287,0.95,4,1,1),"") | J209: 2017 | K209: =IFERROR(AVERAGEIFS($B$200:$B$287,$A$200:$A$287,">="&DATE(J209,1,1),$A$200:$A$287,"<="&DATE(J209,12,31)),"") | L209: =IFERROR(K209/K208-1,"") | M209: =IFERROR(AVERAGEIFS($F$200:$F$287,$A$200:$A$287,">="&DATE(J209,1,1),$A$200:$A$287,"<="&DATE(J209,12,31)),"")
A210: 40360 | B210: =IFERROR(haverdata(Codes!$D$7,$A210),"") | C210: =IFERROR(B210/B209-1,"") | D210: =IFERROR(B210/B206-1,"") | E210: =IFERROR(IF(B210="",IFERROR(GROWTH($B$200:$B$287,$A$200:$A$287,$A210),TREND($B$200:$B$287,$A$200:$A$287,$A210)),""),"") | F210: =IFERROR(forecast.ets($A210,$B$200:$B$287,$A$200:$A$287,4,1,1),"") | G210: =IFERROR(F210-forecast.ets.confint($A210,$B$200:$B$287,$A$200:$A$287,0.95,4,1,1),"") | H210: =IFERROR(F210+forecast.ets.confint($A210,$B$200:$B$287,$A$200:$A$287,0.95,4,1,1),"") | J210: 2018 | K210: =IFERROR(AVERAGEIFS($B$200:$B$287,$A$200:$A$287,">="&DATE(J210,1,1),$A$200:$A$287,"<="&DATE(J210,12,31)),"") | L210: =IFERROR(K210/K209-1,"") | M210: =IFERROR(AVERAGEIFS($F$200:$F$287,$A$200:$A$287,">="&DATE(J210,1,1),$A$200:$A$287,"<="&DATE(J210,12,31)),"")
A211: 40452 | B211: =IFERROR(haverdata(Codes!$D$7,$A211),"") | C211: =IFERROR(B211/B210-1,"") | D211: =IFERROR(B211/B207-1,"") | E211: =IFERROR(IF(B211="",IFERROR(GROWTH($B$200:$B$287,$A$200:$A$287,$A211),TREND($B$200:$B$287,$A$200:$A$287,$A211)),""),"") | F211: =IFERROR(forecast.ets($A211,$B$200:$B$287,$A$200:$A$287,4,1,1),"") | G211: =IFERROR(F211-forecast.ets.confint($A211,$B$200:$B$287,$A$200:$A$287,0.95,4,1,1),"") | H211: =IFERROR(F211+forecast.ets.confint($A211,$B$200:$B$287,$A$200:$A$287,0.95,4,1,1),"") | J211: 2019 | K211: =IFERROR(AVERAGEIFS($B$200:$B$287,$A$200:$A$287,">="&DATE(J211,1,1),$A$200:$A$287,"<="&DATE(J211,12,31)),"") | L211: =IFERROR(K211/K210-1,"") | M211: =IFERROR(AVERAGEIFS($F$200:$F$287,$A$200:$A$287,">="&DATE(J211,1,1),$A$200:$A$287,"<="&DATE(J211,12,31)),"")
A212: 40544 | B212: =IFERROR(haverdata(Codes!$D$7,$A212),"") | C212: =IFERROR(B212/B211-1,"") | D212: =IFERROR(B212/B208-1,"") | E212: =IFERROR(IF(B212="",IFERROR(GROWTH($B$200:$B$287,$A$200:$A$287,$A212),TREND($B$200:$B$287,$A$200:$A$287,$A212)),""),"") | F212: =IFERROR(forecast.ets($A212,$B$200:$B$287,$A$200:$A$287,4,1,1),"") | G212: =IFERROR(F212-forecast.ets.confint($A212,$B$200:$B$287,$A$200:$A$287,0.95,4,1,1),"") | H212: =IFERROR(F212+forecast.ets.confint($A212,$B$200:$B$287,$A$200:$A$287,0.95,4,1,1),"") | J212: 2020 | K212: =IFERROR(AVERAGEIFS($B$200:$B$287,$A$200:$A$287,">="&DATE(J212,1,1),$A$200:$A$287,"<="&DATE(J212,12,31)),"") | L212: =IFERROR(K212/K211-1,"") | M212: =IFERROR(AVERAGEIFS($F$200:$F$287,$A$200:$A$287,">="&DATE(J212,1,1),$A$200:$A$287,"<="&DATE(J212,12,31)),"")
A213: 40634 | B213: =IFERROR(haverdata(Codes!$D$7,$A213),"") | C213: =IFERROR(B213/B212-1,"") | D213: =IFERROR(B213/B209-1,"") | E213: =IFERROR(IF(B213="",IFERROR(GROWTH($B$200:$B$287,$A$200:$A$287,$A213),TREND($B$200:$B$287,$A$200:$A$287,$A213)),""),"") | F213: =IFERROR(forecast.ets($A213,$B$200:$B$287,$A$200:$A$287,4,1,1),"") | G213: =IFERROR(F213-forecast.ets.confint($A213,$B$200:$B$287,$A$200:$A$287,0.95,4,1,1),"") | H213: =IFERROR(F213+forecast.ets.confint($A213,$B$200:$B$287,$A$200:$A$287,0.95,4,1,1),"") | J213: 2021 | K213: =IFERROR(AVERAGEIFS($B$200:$B$287,$A$200:$A$287,">="&DATE(J213,1,1),$A$200:$A$287,"<="&DATE(J213,12,31)),"") | L213: =IFERROR(K213/K212-1,"") | M213: =IFERROR(AVERAGEIFS($F$200:$F$287,$A$200:$A$287,">="&DATE(J213,1,1),$A$200:$A$287,"<="&DATE(J213,12,31)),"")
A214: 40725 | B214: =IFERROR(haverdata(Codes!$D$7,$A214),"") | C214: =IFERROR(B214/B213-1,"") | D214: =IFERROR(B214/B210-1,"") | E214: =IFERROR(IF(B214="",IFERROR(GROWTH($B$200:$B$287,$A$200:$A$287,$A214),TREND($B$200:$B$287,$A$200:$A$287,$A214)),""),"") | F214: =IFERROR(forecast.ets($A214,$B$200:$B$287,$A$200:$A$287,4,1,1),"") | G214: =IFERROR(F214-forecast.ets.confint($A214,$B$200:$B$287,$A$200:$A$287,0.95,4,1,1),"") | H214: =IFERROR(F214+forecast.ets.confint($A214,$B$200:$B$287,$A$200:$A$287,0.95,4,1,1),"") | J214: 2022 | K214: =IFERROR(AVERAGEIFS($B$200:$B$287,$A$200:$A$287,">="&DATE(J214,1,1),$A$200:$A$287,"<="&DATE(J214,12,31)),"") | L214: =IFERROR(K214/K213-1,"") | M214: =IFERROR(AVERAGEIFS($F$200:$F$287,$A$200:$A$287,">="&DATE(J214,1,1),$A$200:$A$287,"<="&DATE(J214,12,31)),"")
A215: 40817 | B215: =IFERROR(haverdata(Codes!$D$7,$A215),"") | C215: =IFERROR(B215/B214-1,"") | D215: =IFERROR(B215/B211-1,"") | E215: =IFERROR(IF(B215="",IFERROR(GROWTH($B$200:$B$287,$A$200:$A$287,$A215),TREND($B$200:$B$287,$A$200:$A$287,$A215)),""),"") | F215: =IFERROR(forecast.ets($A215,$B$200:$B$287,$A$200:$A$287,4,1,1),"") | G215: =IFERROR(F215-forecast.ets.confint($A215,$B$200:$B$287,$A$200:$A$287,0.95,4,1,1),"") | H215: =IFERROR(F215+forecast.ets.confint($A215,$B$200:$B$287,$A$200:$A$287,0.95,4,1,1),"") | J215: 2023 | K215: =IFERROR(AVERAGEIFS($B$200:$B$287,$A$200:$A$287,">="&DATE(J215,1,1),$A$200:$A$287,"<="&DATE(J215,12,31)),"") | L215: =IFERROR(K215/K214-1,"") | M215: =IFERROR(AVERAGEIFS($F$200:$F$287,$A$200:$A$287,">="&DATE(J215,1,1),$A$200:$A$287,"<="&DATE(J215,12,31)),"")
... A221: 41365 | B221: =IFERROR(haverdata(Codes!$D$7,$A221),"") | C221: =IFERROR(B221/B220-1,"") | D221: =IFERROR(B221/B217-1,"") | E221: =IFERROR(IF(B221="",IFERROR(GROWTH($B$200:$B$287,$A$200:$A$287,$A221),TREND($B$200:$B$287,$A$200:$A$287,$A221)),""),"") | F221: =IFERROR(forecast.ets($A221,$B$200:$B$287,$A$200:$A$287,4,1,1),"") | G221: =IFERROR(F221-forecast.ets.confint($A221,$B$200:$B$287,$A$200:$A$287,0.95,4,1,1),"") | H221: =IFERROR(F221+forecast.ets.confint($A221,$B$200:$B$287,$A$200:$A$287,0.95,4,1,1),"") | J221: 2029 | K221: =IFERROR(AVERAGEIFS($B$200:$B$287,$A$200:$A$287,">="&DATE(J221,1,1),$A$200:$A$287,"<="&DATE(J221,12,31)),"") | L221: =IFERROR(K221/K220-1,"") | M221: =IFERROR(AVERAGEIFS($F$200:$F$287,$A$200:$A$287,">="&DATE(J221,1,1),$A$200:$A$287,"<="&DATE(J221,12,31)),"")
A222: 41456 | B222: =IFERROR(haverdata(Codes!$D$7,$A222),"") | C222: =IFERROR(B222/B221-1,"") | D222: =IFERROR(B222/B218-1,"") | E222: =IFERROR(IF(B222="",IFERROR(GROWTH($B$200:$B$287,$A$200:$A$287,$A222),TREND($B$200:$B$287,$A$200:$A$287,$A222)),""),"") | F222: =IFERROR(forecast.ets($A222,$B$200:$B$287,$A$200:$A$287,4,1,1),"") | G222: =IFERROR(F222-forecast.ets.confint($A222,$B$200:$B$287,$A$200:$A$287,0.95,4,1,1),"") | H222: =IFERROR(F222+forecast.ets.confint($A222,$B$200:$B$287,$A$200:$A$287,0.95,4,1,1),"")
A223: 41548 | B223: =IFERROR(haverdata(Codes!$D$7,$A223),"") | C223: =IFERROR(B223/B222-1,"") | D223: =IFERROR(B223/B219-1,"") | E223: =IFERROR(IF(B223="",IFERROR(GROWTH($B$200:$B$287,$A$200:$A$287,$A223),TREND($B$200:$B$287,$A$200:$A$287,$A223)),""),"") | F223: =IFERROR(forecast.ets($A223,$B$200:$B$287,$A$200:$A$287,4,1,1),"") | G223: =IFERROR(F223-forecast.ets.confint($A223,$B$200:$B$287,$A$200:$A$287,0.95,4,1,1),"") | H223: =IFERROR(F223+forecast.ets.confint($A223,$B$200:$B$287,$A$200:$A$287,0.95,4,1,1),"")
A224: 41640 | B224: =IFERROR(haverdata(Codes!$D$7,$A224),"") | C224: =IFERROR(B224/B223-1,"") | D224: =IFERROR(B224/B220-1,"") | E224: =IFERROR(IF(B224="",IFERROR(GROWTH($B$200:$B$287,$A$200:$A$287,$A224),TREND($B$200:$B$287,$A$200:$A$287,$A224)),""),"") | F224: =IFERROR(forecast.ets($A224,$B$200:$B$287,$A$200:$A$287,4,1,1),"") | G224: =IFERROR(F224-forecast.ets.confint($A224,$B$200:$B$287,$A$200:$A$287,0.95,4,1,1),"") | H224: =IFERROR(F224+forecast.ets.confint($A224,$B$200:$B$287,$A$200:$A$287,0.95,4,1,1),"")
A225: 41730 | B225: =IFERROR(haverdata(Codes!$D$7,$A225),"") | C225: =IFERROR(B225/B224-1,"") | D225: =IFERROR(B225/B221-1,"") | E225: =IFERROR(IF(B225="",IFERROR(GROWTH($B$200:$B$287,$A$200:$A$287,$A225),TREND($B$200:$B$287,$A$200:$A$287,$A225)),""),"") | F225: =IFERROR(forecast.ets($A225,$B$200:$B$287,$A$200:$A$287,4,1,1),"") | G225: =IFERROR(F225-forecast.ets.confint($A225,$B$200:$B$287,$A$200:$A$287,0.95,4,1,1),"") | H225: =IFERROR(F225+forecast.ets.confint($A225,$B$200:$B$287,$A$200:$A$287,0.95,4,1,1),"")
A226: 41821 | B226: =IFERROR(haverdata(Codes!$D$7,$A226),"") | C226: =IFERROR(B226/B225-1,"") | D226: =IFERROR(B226/B222-1,"") | E226: =IFERROR(IF(B226="",IFERROR(GROWTH($B$200:$B$287,$A$200:$A$287,$A226),TREND($B$200:$B$287,$A$200:$A$287,$A226)),""),"") | F226: =IFERROR(forecast.ets($A226,$B$200:$B$287,$A$200:$A$287,4,1,1),"") | G226: =IFERROR(F226-forecast.ets.confint($A226,$B$200:$B$287,$A$200:$A$287,0.95,4,1,1),"") | H226: =IFERROR(F226+forecast.ets.confint($A226,$B$200:$B$287,$A$200:$A$287,0.95,4,1,1),"")
A227: 41913 | B227: =IFERROR(haverdata(Codes!$D$7,$A227),"") | C227: =IFERROR(B227/B226-1,"") | D227: =IFERROR(B227/B223-1,"") | E227: =IFERROR(IF(B227="",IFERROR(GROWTH($B$200:$B$287,$A$200:$A$287,$A227),TREND($B$200:$B$287,$A$200:$A$287,$A227)),""),"") | F227: =IFERROR(forecast.ets($A227,$B$200:$B$287,$A$200:$A$287,4,1,1),"") | G227: =IFERROR(F227-forecast.ets.confint($A227,$B$200:$B$287,$A$200:$A$287,0.95,4,1,1),"") | H227: =IFERROR(F227+forecast.ets.confint($A227,$B$200:$B$287,$A$200:$A$287,0.95,4,1,1),"")
A228: 42005 | B228: =IFERROR(haverdata(Codes!$D$7,$A228),"") | C228: =IFERROR(B228/B227-1,"") | D228: =IFERROR(B228/B224-1,"") | E228: =IFERROR(IF(B228="",IFERROR(GROWTH($B$200:$B$287,$A$200:$A$287,$A228),TREND($B$200:$B$287,$A$200:$A$287,$A228)),""),"") | F228: =IFERROR(forecast.ets($A228,$B$200:$B$287,$A$200:$A$287,4,1,1),"") | G228: =IFERROR(F228-forecast.ets.confint($A228,$B$200:$B$287,$A$200:$A$287,0.95,4,1,1),"") | H228: =IFERROR(F228+forecast.ets.confint($A228,$B$200:$B$287,$A$200:$A$287,0.95,4,1,1),"")
A229: 42095 | B229: =IFERROR(haverdata(Codes!$D$7,$A229),"") | C229: =IFERROR(B229/B228-1,"") | D229: =IFERROR(B229/B225-1,"") | E229: =IFERROR(IF(B229="",IFERROR(GROWTH($B$200:$B$287,$A$200:$A$287,$A229),TREND($B$200:$B$287,$A$200:$A$287,$A229)),""),"") | F229: =IFERROR(forecast.ets($A229,$B$200:$B$287,$A$200:$A$287,4,1,1),"") | G229: =IFERROR(F229-forecast.ets.confint($A229,$B$200:$B$287,$A$200:$A$287,0.95,4,1,1),"") | H229: =IFERROR(F229+forecast.ets.confint($A229,$B$200:$B$287,$A$200:$A$287,0.95,4,1,1),"")
A230: 42186 | B230: =IFERROR(haverdata(Codes!$D$7,$A230),"") | C230: =IFERROR(B230/B229-1,"") | D230: =IFERROR(B230/B226-1,"") | E230: =IFERROR(IF(B230="",IFERROR(GROWTH($B$200:$B$287,$A$200:$A$287,$A230),TREND($B$200:$B$287,$A$200:$A$287,$A230)),""),"") | F230: =IFERROR(forecast.ets($A230,$B$200:$B$287,$A$200:$A$287,4,1,1),"") | G230: =IFERROR(F230-forecast.ets.confint($A230,$B$200:$B$287,$A$200:$A$287,0.95,4,1,1),"") | H230: =IFERROR(F230+forecast.ets.confint($A230,$B$200:$B$287,$A$200:$A$287,0.95,4,1,1),"")
...

Sheet Inflation
A1: Inflation — Argentina
A2: Each block: live HaverData pulls (col B) → growth metrics → TREND + FORECAST.ETS forecasts → chart.
A4: =Codes!$B$8&" ["&Codes!$D$8&"] "&Codes!$F$8 -> CPI National (IPC nacional) [IPCNAC@ARGEN] Index Dec-16=100
A5: Aggregation: | B5: =Codes!$G$8 -> avg | D5: Notes: | E5: =Codes!$H$8 -> INDEC. Pre-2017 series has structural breaks (INDEC reform).
A6: Quarterly | J6: Annual
A7: Date | B7: Level | C7: QoQ % | D7: YoY % | E7: Linear Fcst | F7: ETS Fcst | G7: ETS Low 95% | H7: ETS High 95% | J7: Year | K7: Level | L7: YoY % | M7: Forecast
A8: 39448 | B8: =IFERROR(haverdata(Codes!$D$8,$A8),"") | E8: =IFERROR(IF(B8="",IFERROR(GROWTH($B$8:$B$95,$A$8:$A$95,$A8),TREND($B$8:$B$95,$A$8:$A$95,$A8)),""),"") | F8: =IFERROR(forecast.ets($A8,$B$8:$B$95,$A$8:$A$95,4,1,1),"") | G8: =IFERROR(F8-forecast.ets.confint($A8,$B$8:$B$95,$A$8:$A$95,0.95,4,1,1),"") | H8: =IFERROR(F8+forecast.ets.confint($A8,$B$8:$B$95,$A$8:$A$95,0.95,4,1,1),"") | J8: 2008 | K8: =IFERROR(AVERAGEIFS($B$8:$B$95,$A$8:$A$95,">="&DATE(J8,1,1),$A$8:$A$95,"<="&DATE(J8,12,31)),"") | M8: =IFERROR(AVERAGEIFS($F$8:$F$95,$A$8:$A$95,">="&DATE(J8,1,1),$A$8:$A$95,"<="&DATE(J8,12,31)),"")
A9: 39539 | B9: =IFERROR(haverdata(Codes!$D$8,$A9),"") | C9: =IFERROR(B9/B8-1,"") | E9: =IFERROR(IF(B9="",IFERROR(GROWTH($B$8:$B$95,$A$8:$A$95,$A9),TREND($B$8:$B$95,$A$8:$A$95,$A9)),""),"") | F9: =IFERROR(forecast.ets($A9,$B$8:$B$95,$A$8:$A$95,4,1,1),"") | G9: =IFERROR(F9-forecast.ets.confint($A9,$B$8:$B$95,$A$8:$A$95,0.95,4,1,1),"") | H9: =IFERROR(F9+forecast.ets.confint($A9,$B$8:$B$95,$A$8:$A$95,0.95,4,1,1),"") | J9: 2009 | K9: =IFERROR(AVERAGEIFS($B$8:$B$95,$A$8:$A$95,">="&DATE(J9,1,1),$A$8:$A$95,"<="&DATE(J9,12,31)),"") | L9: =IFERROR(K9/K8-1,"") | M9: =IFERROR(AVERAGEIFS($F$8:$F$95,$A$8:$A$95,">="&DATE(J9,1,1),$A$8:$A$95,"<="&DATE(J9,12,31)),"")
A10: 39630 | B10: =IFERROR(haverdata(Codes!$D$8,$A10),"") | C10: =IFERROR(B10/B9-1,"") | E10: =IFERROR(IF(B10="",IFERROR(GROWTH($B$8:$B$95,$A$8:$A$95,$A10),TREND($B$8:$B$95,$A$8:$A$95,$A10)),""),"") | F10: =IFERROR(forecast.ets($A10,$B$8:$B$95,$A$8:$A$95,4,1,1),"") | G10: =IFERROR(F10-forecast.ets.confint($A10,$B$8:$B$95,$A$8:$A$95,0.95,4,1,1),"") | H10: =IFERROR(F10+forecast.ets.confint($A10,$B$8:$B$95,$A$8:$A$95,0.95,4,1,1),"") | J10: 2010 | K10: =IFERROR(AVERAGEIFS($B$8:$B$95,$A$8:$A$95,">="&DATE(J10,1,1),$A$8:$A$95,"<="&DATE(J10,12,31)),"") | L10: =IFERROR(K10/K9-1,"") | M10: =IFERROR(AVERAGEIFS($F$8:$F$95,$A$8:$A$95,">="&DATE(J10,1,1),$A$8:$A$95,"<="&DATE(J10,12,31)),"")
A11: 39722 | B11: =IFERROR(haverdata(Codes!$D$8,$A11),"") | C11: =IFERROR(B11/B10-1,"") | E11: =IFERROR(IF(B11="",IFERROR(GROWTH($B$8:$B$95,$A$8:$A$95,$A11),TREND($B$8:$B$95,$A$8:$A$95,$A11)),""),"") | F11: =IFERROR(forecast.ets($A11,$B$8:$B$95,$A$8:$A$95,4,1,1),"") | G11: =IFERROR(F11-forecast.ets.confint($A11,$B$8:$B$95,$A$8:$A$95,0.95,4,1,1),"") | H11: =IFERROR(F11+forecast.ets.confint($A11,$B$8:$B$95,$A$8:$A$95,0.95,4,1,1),"") | J11: 2011 | K11: =IFERROR(AVERAGEIFS($B$8:$B$95,$A$8:$A$95,">="&DATE(J11,1,1),$A$8:$A$95,"<="&DATE(J11,12,31)),"") | L11: =IFERROR(K11/K10-1,"") | M11: =IFERROR(AVERAGEIFS($F$8:$F$95,$A$8:$A$95,">="&DATE(J11,1,1),$A$8:$A$95,"<="&DATE(J11,12,31)),"")
A12: 39814 | B12: =IFERROR(haverdata(Codes!$D$8,$A12),"") | C12: =IFERROR(B12/B11-1,"") | D12: =IFERROR(B12/B8-1,"") | E12: =IFERROR(IF(B12="",IFERROR(GROWTH($B$8:$B$95,$A$8:$A$95,$A12),TREND($B$8:$B$95,$A$8:$A$95,$A12)),""),"") | F12: =IFERROR(forecast.ets($A12,$B$8:$B$95,$A$8:$A$95,4,1,1),"") | G12: =IFERROR(F12-forecast.ets.confint($A12,$B$8:$B$95,$A$8:$A$95,0.95,4,1,1),"") | H12: =IFERROR(F12+forecast.ets.confint($A12,$B$8:$B$95,$A$8:$A$95,0.95,4,1,1),"") | J12: 2012 | K12: =IFERROR(AVERAGEIFS($B$8:$B$95,$A$8:$A$95,">="&DATE(J12,1,1),$A$8:$A$95,"<="&DATE(J12,12,31)),"") | L12: =IFERROR(K12/K11-1,"") | M12: =IFERROR(AVERAGEIFS($F$8:$F$95,$A$8:$A$95,">="&DATE(J12,1,1),$A$8:$A$95,"<="&DATE(J12,12,31)),"")
A13: 39904 | B13: =IFERROR(haverdata(Codes!$D$8,$A13),"") | C13: =IFERROR(B13/B12-1,"") | D13: =IFERROR(B13/B9-1,"") | E13: =IFERROR(IF(B13="",IFERROR(GROWTH($B$8:$B$95,$A$8:$A$95,$A13),TREND($B$8:$B$95,$A$8:$A$95,$A13)),""),"") | F13: =IFERROR(forecast.ets($A13,$B$8:$B$95,$A$8:$A$95,4,1,1),"") | G13: =IFERROR(F13-forecast.ets.confint($A13,$B$8:$B$95,$A$8:$A$95,0.95,4,1,1),"") | H13: =IFERROR(F13+forecast.ets.confint($A13,$B$8:$B$95,$A$8:$A$95,0.95,4,1,1),"") | J13: 2013 | K13: =IFERROR(AVERAGEIFS($B$8:$B$95,$A$8:$A$95,">="&DATE(J13,1,1),$A$8:$A$95,"<="&DATE(J13,12,31)),"") | L13: =IFERROR(K13/K12-1,"") | M13: =IFERROR(AVERAGEIFS($F$8:$F$95,$A$8:$A$95,">="&DATE(J13,1,1),$A$8:$A$95,"<="&DATE(J13,12,31)),"")
A14: 39995 | B14: =IFERROR(haverdata(Codes!$D$8,$A14),"") | C14: =IFERROR(B14/B13-1,"") | D14: =IFERROR(B14/B10-1,"") | E14: =IFERROR(IF(B14="",IFERROR(GROWTH($B$8:$B$95,$A$8:$A$95,$A14),TREND($B$8:$B$95,$A$8:$A$95,$A14)),""),"") | F14: =IFERROR(forecast.ets($A14,$B$8:$B$95,$A$8:$A$95,4,1,1),"") | G14: =IFERROR(F14-forecast.ets.confint($A14,$B$8:$B$95,$A$8:$A$95,0.95,4,1,1),"") | H14: =IFERROR(F14+forecast.ets.confint($A14,$B$8:$B$95,$A$8:$A$95,0.95,4,1,1),"") | J14: 2014 | K14: =IFERROR(AVERAGEIFS($B$8:$B$95,$A$8:$A$95,">="&DATE(J14,1,1),$A$8:$A$95,"<="&DATE(J14,12,31)),"") | L14: =IFERROR(K14/K13-1,"") | M14: =IFERROR(AVERAGEIFS($F$8:$F$95,$A$8:$A$95,">="&DATE(J14,1,1),$A$8:$A$95,"<="&DATE(J14,12,31)),"")
A15: 40087 | B15: =IFERROR(haverdata(Codes!$D$8,$A15),"") | C15: =IFERROR(B15/B14-1,"") | D15: =IFERROR(B15/B11-1,"") | E15: =IFERROR(IF(B15="",IFERROR(GROWTH($B$8:$B$95,$A$8:$A$95,$A15),TREND($B$8:$B$95,$A$8:$A$95,$A15)),""),"") | F15: =IFERROR(forecast.ets($A15,$B$8:$B$95,$A$8:$A$95,4,1,1),"") | G15: =IFERROR(F15-forecast.ets.confint($A15,$B$8:$B$95,$A$8:$A$95,0.95,4,1,1),"") | H15: =IFERROR(F15+forecast.ets.confint($A15,$B$8:$B$95,$A$8:$A$95,0.95,4,1,1),"") | J15: 2015 | K15: =IFERROR(AVERAGEIFS($B$8:$B$95,$A$8:$A$95,">="&DATE(J15,1,1),$A$8:$A$95,"<="&DATE(J15,12,31)),"") | L15: =IFERROR(K15/K14-1,"") | M15: =IFERROR(AVERAGEIFS($F$8:$F$95,$A$8:$A$95,">="&DATE(J15,1,1),$A$8:$A$95,"<="&DATE(J15,12,31)),"")
A16: 40179 | B16: =IFERROR(haverdata(Codes!$D$8,$A16),"") | C16: =IFERROR(B16/B15-1,"") | D16: =IFERROR(B16/B12-1,"") | E16: =IFERROR(IF(B16="",IFERROR(GROWTH($B$8:$B$95,$A$8:$A$95,$A16),TREND($B$8:$B$95,$A$8:$A$95,$A16)),""),"") | F16: =IFERROR(forecast.ets($A16,$B$8:$B$95,$A$8:$A$95,4,1,1),"") | G16: =IFERROR(F16-forecast.ets.confint($A16,$B$8:$B$95,$A$8:$A$95,0.95,4,1,1),"") | H16: =IFERROR(F16+forecast.ets.confint($A16,$B$8:$B$95,$A$8:$A$95,0.95,4,1,1),"") | J16: 2016 | K16: =IFERROR(AVERAGEIFS($B$8:$B$95,$A$8:$A$95,">="&DATE(J16,1,1),$A$8:$A$95,"<="&DATE(J16,12,31)),"") | L16: =IFERROR(K16/K15-1,"") | M16: =IFERROR(AVERAGEIFS($F$8:$F$95,$A$8:$A$95,">="&DATE(J16,1,1),$A$8:$A$95,"<="&DATE(J16,12,31)),"")
A17: 40269 | B17: =IFERROR(haverdata(Codes!$D$8,$A17),"") | C17: =IFERROR(B17/B16-1,"") | D17: =IFERROR(B17/B13-1,"") | E17: =IFERROR(IF(B17="",IFERROR(GROWTH($B$8:$B$95,$A$8:$A$95,$A17),TREND($B$8:$B$95,$A$8:$A$95,$A17)),""),"") | F17: =IFERROR(forecast.ets($A17,$B$8:$B$95,$A$8:$A$95,4,1,1),"") | G17: =IFERROR(F17-forecast.ets.confint($A17,$B$8:$B$95,$A$8:$A$95,0.95,4,1,1),"") | H17: =IFERROR(F17+forecast.ets.confint($A17,$B$8:$B$95,$A$8:$A$95,0.95,4,1,1),"") | J17: 2017 | K17: =IFERROR(AVERAGEIFS($B$8:$B$95,$A$8:$A$95,">="&DATE(J17,1,1),$A$8:$A$95,"<="&DATE(J17,12,31)),"") | L17: =IFERROR(K17/K16-1,"") | M17: =IFERROR(AVERAGEIFS($F$8:$F$95,$A$8:$A$95,">="&DATE(J17,1,1),$A$8:$A$95,"<="&DATE(J17,12,31)),"")
A18: 40360 | B18: =IFERROR(haverdata(Codes!$D$8,$A18),"") | C18: =IFERROR(B18/B17-1,"") | D18: =IFERROR(B18/B14-1,"") | E18: =IFERROR(IF(B18="",IFERROR(GROWTH($B$8:$B$95,$A$8:$A$95,$A18),TREND($B$8:$B$95,$A$8:$A$95,$A18)),""),"") | F18: =IFERROR(forecast.ets($A18,$B$8:$B$95,$A$8:$A$95,4,1,1),"") | G18: =IFERROR(F18-forecast.ets.confint($A18,$B$8:$B$95,$A$8:$A$95,0.95,4,1,1),"") | H18: =IFERROR(F18+forecast.ets.confint($A18,$B$8:$B$95,$A$8:$A$95,0.95,4,1,1),"") | J18: 2018 | K18: =IFERROR(AVERAGEIFS($B$8:$B$95,$A$8:$A$95,">="&DATE(J18,1,1),$A$8:$A$95,"<="&DATE(J18,12,31)),"") | L18: =IFERROR(K18/K17-1,"") | M18: =IFERROR(AVERAGEIFS($F$8:$F$95,$A$8:$A$95,">="&DATE(J18,1,1),$A$8:$A$95,"<="&DATE(J18,12,31)),"")
A19: 40452 | B19: =IFERROR(haverdata(Codes!$D$8,$A19),"") | C19: =IFERROR(B19/B18-1,"") | D19: =IFERROR(B19/B15-1,"") | E19: =IFERROR(IF(B19="",IFERROR(GROWTH($B$8:$B$95,$A$8:$A$95,$A19),TREND($B$8:$B$95,$A$8:$A$95,$A19)),""),"") | F19: =IFERROR(forecast.ets($A19,$B$8:$B$95,$A$8:$A$95,4,1,1),"") | G19: =IFERROR(F19-forecast.ets.confint($A19,$B$8:$B$95,$A$8:$A$95,0.95,4,1,1),"") | H19: =IFERROR(F19+forecast.ets.confint($A19,$B$8:$B$95,$A$8:$A$95,0.95,4,1,1),"") | J19: 2019 | K19: =IFERROR(AVERAGEIFS($B$8:$B$95,$A$8:$A$95,">="&DATE(J19,1,1),$A$8:$A$95,"<="&DATE(J19,12,31)),"") | L19: =IFERROR(K19/K18-1,"") | M19: =IFERROR(AVERAGEIFS($F$8:$F$95,$A$8:$A$95,">="&DATE(J19,1,1),$A$8:$A$95,"<="&DATE(J19,12,31)),"")
A20: 40544 | B20: =IFERROR(haverdata(Codes!$D$8,$A20),"") | C20: =IFERROR(B20/B19-1,"") | D20: =IFERROR(B20/B16-1,"") | E20: =IFERROR(IF(B20="",IFERROR(GROWTH($B$8:$B$95,$A$8:$A$95,$A20),TREND($B$8:$B$95,$A$8:$A$95,$A20)),""),"") | F20: =IFERROR(forecast.ets($A20,$B$8:$B$95,$A$8:$A$95,4,1,1),"") | G20: =IFERROR(F20-forecast.ets.confint($A20,$B$8:$B$95,$A$8:$A$95,0.95,4,1,1),"") | H20: =IFERROR(F20+forecast.ets.confint($A20,$B$8:$B$95,$A$8:$A$95,0.95,4,1,1),"") | J20: 2020 | K20: =IFERROR(AVERAGEIFS($B$8:$B$95,$A$8:$A$95,">="&DATE(J20,1,1),$A$8:$A$95,"<="&DATE(J20,12,31)),"") | L20: =IFERROR(K20/K19-1,"") | M20: =IFERROR(AVERAGEIFS($F$8:$F$95,$A$8:$A$95,">="&DATE(J20,1,1),$A$8:$A$95,"<="&DATE(J20,12,31)),"")
A21: 40634 | B21: =IFERROR(haverdata(Codes!$D$8,$A21),"") | C21: =IFERROR(B21/B20-1,"") | D21: =IFERROR(B21/B17-1,"") | E21: =IFERROR(IF(B21="",IFERROR(GROWTH($B$8:$B$95,$A$8:$A$95,$A21),TREND($B$8:$B$95,$A$8:$A$95,$A21)),""),"") | F21: =IFERROR(forecast.ets($A21,$B$8:$B$95,$A$8:$A$95,4,1,1),"") | G21: =IFERROR(F21-forecast.ets.confint($A21,$B$8:$B$95,$A$8:$A$95,0.95,4,1,1),"") | H21: =IFERROR(F21+forecast.ets.confint($A21,$B$8:$B$95,$A$8:$A$95,0.95,4,1,1),"") | J21: 2021 | K21: =IFERROR(AVERAGEIFS($B$8:$B$95,$A$8:$A$95,">="&DATE(J21,1,1),$A$8:$A$95,"<="&DATE(J21,12,31)),"") | L21: =IFERROR(K21/K20-1,"") | M21: =IFERROR(AVERAGEIFS($F$8:$F$95,$A$8:$A$95,">="&DATE(J21,1,1),$A$8:$A$95,"<="&DATE(J21,12,31)),"")
A22: 40725 | B22: =IFERROR(haverdata(Codes!$D$8,$A22),"") | C22: =IFERROR(B22/B21-1,"") | D22: =IFERROR(B22/B18-1,"") | E22: =IFERROR(IF(B22="",IFERROR(GROWTH($B$8:$B$95,$A$8:$A$95,$A22),TREND($B$8:$B$95,$A$8:$A$95,$A22)),""),"") | F22: =IFERROR(forecast.ets($A22,$B$8:$B$95,$A$8:$A$95,4,1,1),"") | G22: =IFERROR(F22-forecast.ets.confint($A22,$B$8:$B$95,$A$8:$A$95,0.95,4,1,1),"") | H22: =IFERROR(F22+forecast.ets.confint($A22,$B$8:$B$95,$A$8:$A$95,0.95,4,1,1),"") | J22: 2022 | K22: =IFERROR(AVERAGEIFS($B$8:$B$95,$A$8:$A$95,">="&DATE(J22,1,1),$A$8:$A$95,"<="&DATE(J22,12,31)),"") | L22: =IFERROR(K22/K21-1,"") | M22: =IFERROR(AVERAGEIFS($F$8:$F$95,$A$8:$A$95,">="&DATE(J22,1,1),$A$8:$A$95,"<="&DATE(J22,12,31)),"")
A23: 40817 | B23: =IFERROR(haverdata(Codes!$D$8,$A23),"") | C23: =IFERROR(B23/B22-1,"") | D23: =IFERROR(B23/B19-1,"") | E23: =IFERROR(IF(B23="",IFERROR(GROWTH($B$8:$B$95,$A$8:$A$95,$A23),TREND($B$8:$B$95,$A$8:$A$95,$A23)),""),"") | F23: =IFERROR(forecast.ets($A23,$B$8:$B$95,$A$8:$A$95,4,1,1),"") | G23: =IFERROR(F23-forecast.ets.confint($A23,$B$8:$B$95,$A$8:$A$95,0.95,4,1,1),"") | H23: =IFERROR(F23+forecast.ets.confint($A23,$B$8:$B$95,$A$8:$A$95,0.95,4,1,1),"") | J23: 2023 | K23: =IFERROR(AVERAGEIFS($B$8:$B$95,$A$8:$A$95,">="&DATE(J23,1,1),$A$8:$A$95,"<="&DATE(J23,12,31)),"") | L23: =IFERROR(K23/K22-1,"") | M23: =IFERROR(AVERAGEIFS($F$8:$F$95,$A$8:$A$95,">="&DATE(J23,1,1),$A$8:$A$95,"<="&DATE(J23,12,31)),"")
... A29: 41365 | B29: =IFERROR(haverdata(Codes!$D$8,$A29),"") | C29: =IFERROR(B29/B28-1,"") | D29: =IFERROR(B29/B25-1,"") | E29: =IFERROR(IF(B29="",IFERROR(GROWTH($B$8:$B$95,$A$8:$A$95,$A29),TREND($B$8:$B$95,$A$8:$A$95,$A29)),""),"") | F29: =IFERROR(forecast.ets($A29,$B$8:$B$95,$A$8:$A$95,4,1,1),"") | G29: =IFERROR(F29-forecast.ets.confint($A29,$B$8:$B$95,$A$8:$A$95,0.95,4,1,1),"") | H29: =IFERROR(F29+forecast.ets.confint($A29,$B$8:$B$95,$A$8:$A$95,0.95,4,1,1),"") | J29: 2029 | K29: =IFERROR(AVERAGEIFS($B$8:$B$95,$A$8:$A$95,">="&DATE(J29,1,1),$A$8:$A$95,"<="&DATE(J29,12,31)),"") | L29: =IFERROR(K29/K28-1,"") | M29: =IFERROR(AVERAGEIFS($F$8:$F$95,$A$8:$A$95,">="&DATE(J29,1,1),$A$8:$A$95,"<="&DATE(J29,12,31)),"")
A30: 41456 | B30: =IFERROR(haverdata(Codes!$D$8,$A30),"") | C30: =IFERROR(B30/B29-1,"") | D30: =IFERROR(B30/B26-1,"") | E30: =IFERROR(IF(B30="",IFERROR(GROWTH($B$8:$B$95,$A$8:$A$95,$A30),TREND($B$8:$B$95,$A$8:$A$95,$A30)),""),"") | F30: =IFERROR(forecast.ets($A30,$B$8:$B$95,$A$8:$A$95,4,1,1),"") | G30: =IFERROR(F30-forecast.ets.confint($A30,$B$8:$B$95,$A$8:$A$95,0.95,4,1,1),"") | H30: =IFERROR(F30+forecast.ets.confint($A30,$B$8:$B$95,$A$8:$A$95,0.95,4,1,1),"")
A31: 41548 | B31: =IFERROR(haverdata(Codes!$D$8,$A31),"") | C31: =IFERROR(B31/B30-1,"") | D31: =IFERROR(B31/B27-1,"") | E31: =IFERROR(IF(B31="",IFERROR(GROWTH($B$8:$B$95,$A$8:$A$95,$A31),TREND($B$8:$B$95,$A$8:$A$95,$A31)),""),"") | F31: =IFERROR(forecast.ets($A31,$B$8:$B$95,$A$8:$A$95,4,1,1),"") | G31: =IFERROR(F31-forecast.ets.confint($A31,$B$8:$B$95,$A$8:$A$95,0.95,4,1,1),"") | H31: =IFERROR(F31+forecast.ets.confint($A31,$B$8:$B$95,$A$8:$A$95,0.95,4,1,1),"")
A32: 41640 | B32: =IFERROR(haverdata(Codes!$D$8,$A32),"") | C32: =IFERROR(B32/B31-1,"") | D32: =IFERROR(B32/B28-1,"") | E32: =IFERROR(IF(B32="",IFERROR(GROWTH($B$8:$B$95,$A$8:$A$95,$A32),TREND($B$8:$B$95,$A$8:$A$95,$A32)),""),"") | F32: =IFERROR(forecast.ets($A32,$B$8:$B$95,$A$8:$A$95,4,1,1),"") | G32: =IFERROR(F32-forecast.ets.confint($A32,$B$8:$B$95,$A$8:$A$95,0.95,4,1,1),"") | H32: =IFERROR(F32+forecast.ets.confint($A32,$B$8:$B$95,$A$8:$A$95,0.95,4,1,1),"")
A33: 41730 | B33: =IFERROR(haverdata(Codes!$D$8,$A33),"") | C33: =IFERROR(B33/B32-1,"") | D33: =IFERROR(B33/B29-1,"") | E33: =IFERROR(IF(B33="",IFERROR(GROWTH($B$8:$B$95,$A$8:$A$95,$A33),TREND($B$8:$B$95,$A$8:$A$95,$A33)),""),"") | F33: =IFERROR(forecast.ets($A33,$B$8:$B$95,$A$8:$A$95,4,1,1),"") | G33: =IFERROR(F33-forecast.ets.confint($A33,$B$8:$B$95,$A$8:$A$95,0.95,4,1,1),"") | H33: =IFERROR(F33+forecast.ets.confint($A33,$B$8:$B$95,$A$8:$A$95,0.95,4,1,1),"")
A34: 41821 | B34: =IFERROR(haverdata(Codes!$D$8,$A34),"") | C34: =IFERROR(B34/B33-1,"") | D34: =IFERROR(B34/B30-1,"") | E34: =IFERROR(IF(B34="",IFERROR(GROWTH($B$8:$B$95,$A$8:$A$95,$A34),TREND($B$8:$B$95,$A$8:$A$95,$A34)),""),"") | F34: =IFERROR(forecast.ets($A34,$B$8:$B$95,$A$8:$A$95,4,1,1),"") | G34: =IFERROR(F34-forecast.ets.confint($A34,$B$8:$B$95,$A$8:$A$95,0.95,4,1,1),"") | H34: =IFERROR(F34+forecast.ets.confint($A34,$B$8:$B$95,$A$8:$A$95,0.95,4,1,1),"")
A35: 41913 | B35: =IFERROR(haverdata(Codes!$D$8,$A35),"") | C35: =IFERROR(B35/B34-1,"") | D35: =IFERROR(B35/B31-1,"") | E35: =IFERROR(IF(B35="",IFERROR(GROWTH($B$8:$B$95,$A$8:$A$95,$A35),TREND($B$8:$B$95,$A$8:$A$95,$A35)),""),"") | F35: =IFERROR(forecast.ets($A35,$B$8:$B$95,$A$8:$A$95,4,1,1),"") | G35: =IFERROR(F35-forecast.ets.confint($A35,$B$8:$B$95,$A$8:$A$95,0.95,4,1,1),"") | H35: =IFERROR(F35+forecast.ets.confint($A35,$B$8:$B$95,$A$8:$A$95,0.95,4,1,1),"")
A36: 42005 | B36: =IFERROR(haverdata(Codes!$D$8,$A36),"") | C36: =IFERROR(B36/B35-1,"") | D36: =IFERROR(B36/B32-1,"") | E36: =IFERROR(IF(B36="",IFERROR(GROWTH($B$8:$B$95,$A$8:$A$95,$A36),TREND($B$8:$B$95,$A$8:$A$95,$A36)),""),"") | F36: =IFERROR(forecast.ets($A36,$B$8:$B$95,$A$8:$A$95,4,1,1),"") | G36: =IFERROR(F36-forecast.ets.confint($A36,$B$8:$B$95,$A$8:$A$95,0.95,4,1,1),"") | H36: =IFERROR(F36+forecast.ets.confint($A36,$B$8:$B$95,$A$8:$A$95,0.95,4,1,1),"")
A37: 42095 | B37: =IFERROR(haverdata(Codes!$D$8,$A37),"") | C37: =IFERROR(B37/B36-1,"") | D37: =IFERROR(B37/B33-1,"") | E37: =IFERROR(IF(B37="",IFERROR(GROWTH($B$8:$B$95,$A$8:$A$95,$A37),TREND($B$8:$B$95,$A$8:$A$95,$A37)),""),"") | F37: =IFERROR(forecast.ets($A37,$B$8:$B$95,$A$8:$A$95,4,1,1),"") | G37: =IFERROR(F37-forecast.ets.confint($A37,$B$8:$B$95,$A$8:$A$95,0.95,4,1,1),"") | H37: =IFERROR(F37+forecast.ets.confint($A37,$B$8:$B$95,$A$8:$A$95,0.95,4,1,1),"")
A38: 42186 | B38: =IFERROR(haverdata(Codes!$D$8,$A38),"") | C38: =IFERROR(B38/B37-1,"") | D38: =IFERROR(B38/B34-1,"") | E38: =IFERROR(IF(B38="",IFERROR(GROWTH($B$8:$B$95,$A$8:$A$95,$A38),TREND($B$8:$B$95,$A$8:$A$95,$A38)),""),"") | F38: =IFERROR(forecast.ets($A38,$B$8:$B$95,$A$8:$A$95,4,1,1),"") | G38: =IFERROR(F38-forecast.ets.confint($A38,$B$8:$B$95,$A$8:$A$95,0.95,4,1,1),"") | H38: =IFERROR(F38+forecast.ets.confint($A38,$B$8:$B$95,$A$8:$A$95,0.95,4,1,1),"")
A39: 42278 | B39: =IFERROR(haverdata(Codes!$D$8,$A39),"") | C39: =IFERROR(B39/B38-1,"") | D39: =IFERROR(B39/B35-1,"") | E39: =IFERROR(IF(B39="",IFERROR(GROWTH($B$8:$B$95,$A$8:$A$95,$A39),TREND($B$8:$B$95,$A$8:$A$95,$A39)),""),"") | F39: =IFERROR(forecast.ets($A39,$B$8:$B$95,$A$8:$A$95,4,1,1),"") | G39: =IFERROR(F39-forecast.ets.confint($A39,$B$8:$B$95,$A$8:$A$95,0.95,4,1,1),"") | H39: =IFERROR(F39+forecast.ets.confint($A39,$B$8:$B$95,$A$8:$A$95,0.95,4,1,1),"")
A40: 42370 | B40: =IFERROR(haverdata(Codes!$D$8,$A40),"") | C40: =IFERROR(B40/B39-1,"") | D40: =IFERROR(B40/B36-1,"") | E40: =IFERROR(IF(B40="",IFERROR(GROWTH($B$8:$B$95,$A$8:$A$95,$A40),TREND($B$8:$B$95,$A$8:$A$95,$A40)),""),"") | F40: =IFERROR(forecast.ets($A40,$B$8:$B$95,$A$8:$A$95,4,1,1),"") | G40: =IFERROR(F40-forecast.ets.confint($A40,$B$8:$B$95,$A$8:$A$95,0.95,4,1,1),"") | H40: =IFERROR(F40+forecast.ets.confint($A40,$B$8:$B$95,$A$8:$A$95,0.95,4,1,1),"")
A41: 42461 | B41: =IFERROR(haverdata(Codes!$D$8,$A41),"") | C41: =IFERROR(B41/B40-1,"") | D41: =IFERROR(B41/B37-1,"") | E41: =IFERROR(IF(B41="",IFERROR(GROWTH($B$8:$B$95,$A$8:$A$95,$A41),TREND($B$8:$B$95,$A$8:$A$95,$A41)),""),"") | F41: =IFERROR(forecast.ets($A41,$B$8:$B$95,$A$8:$A$95,4,1,1),"") | G41: =IFERROR(F41-forecast.ets.confint($A41,$B$8:$B$95,$A$8:$A$95,0.95,4,1,1),"") | H41: =IFERROR(F41+forecast.ets.confint($A41,$B$8:$B$95,$A$8:$A$95,0.95,4,1,1),"")
... A95: 47392 | B95: =IFERROR(haverdata(Codes!$D$8,$A95),"") | C95: =IFERROR(B95/B94-1,"") | D95: =IFERROR(B95/B91-1,"") | E95: =IFERROR(IF(B95="",IFERROR(GROWTH($B$8:$B$95,$A$8:$A$95,$A95),TREND($B$8:$B$95,$A$8:$A$95,$A95)),""),"") | F95: =IFERROR(forecast.ets($A95,$B$8:$B$95,$A$8:$A$95,4,1,1),"") | G95: =IFERROR(F95-forecast.ets.confint($A95,$B$8:$B$95,$A$8:$A$95,0.95,4,1,1),"") | H95: =IFERROR(F95+forecast.ets.confint($A95,$B$8:$B$95,$A$8:$A$95,0.95,4,1,1),"")
A100: =Codes!$B$9&" ["&Codes!$D$9&"] "&Codes!$F$9 -> Core CPI [IPCCORE@ARGEN] Index
A101: Aggregation: | B101: =Codes!$G$9 -> avg | D101: Notes: | E101: =Codes!$H$9 -> [VERIFY]
A102: Quarterly | J102: Annual
A103: Date | B103: Level | C103: QoQ % | D103: YoY % | E103: Linear Fcst | F103: ETS Fcst | G103: ETS Low 95% | H103: ETS High 95% | J103: Year | K103: Level | L103: YoY % | M103: Forecast
A104: 39448 | B104: =IFERROR(haverdata(Codes!$D$9,$A104),"") | E104: =IFERROR(IF(B104="",IFERROR(GROWTH($B$104:$B$191,$A$104:$A$191,$A104),TREND($B$104:$B$191,$A$104:$A$191,$A104)),""),"") | F104: =IFERROR(forecast.ets($A104,$B$104:$B$191,$A$104:$A$191,4,1,1),"") | G104: =IFERROR(F104-forecast.ets.confint($A104,$B$104:$B$191,$A$104:$A$191,0.95,4,1,1),"") | H104: =IFERROR(F104+forecast.ets.confint($A104,$B$104:$B$191,$A$104:$A$191,0.95,4,1,1),"") | J104: 2008 | K104: =IFERROR(AVERAGEIFS($B$104:$B$191,$A$104:$A$191,">="&DATE(J104,1,1),$A$104:$A$191,"<="&DATE(J104,12,31)),"") | M104: =IFERROR(AVERAGEIFS($F$104:$F$191,$A$104:$A$191,">="&DATE(J104,1,1),$A$104:$A$191,"<="&DATE(J104,12,31)),"")
A105: 39539 | B105: =IFERROR(haverdata(Codes!$D$9,$A105),"") | C105: =IFERROR(B105/B104-1,"") | E105: =IFERROR(IF(B105="",IFERROR(GROWTH($B$104:$B$191,$A$104:$A$191,$A105),TREND($B$104:$B$191,$A$104:$A$191,$A105)),""),"") | F105: =IFERROR(forecast.ets($A105,$B$104:$B$191,$A$104:$A$191,4,1,1),"") | G105: =IFERROR(F105-forecast.ets.confint($A105,$B$104:$B$191,$A$104:$A$191,0.95,4,1,1),"") | H105: =IFERROR(F105+forecast.ets.confint($A105,$B$104:$B$191,$A$104:$A$191,0.95,4,1,1),"") | J105: 2009 | K105: =IFERROR(AVERAGEIFS($B$104:$B$191,$A$104:$A$191,">="&DATE(J105,1,1),$A$104:$A$191,"<="&DATE(J105,12,31)),"") | L105: =IFERROR(K105/K104-1,"") | M105: =IFERROR(AVERAGEIFS($F$104:$F$191,$A$104:$A$191,">="&DATE(J105,1,1),$A$104:$A$191,"<="&DATE(J105,12,31)),"")
A106: 39630 | B106: =IFERROR(haverdata(Codes!$D$9,$A106),"") | C106: =IFERROR(B106/B105-1,"") | E106: =IFERROR(IF(B106="",IFERROR(GROWTH($B$104:$B$191,$A$104:$A$191,$A106),TREND($B$104:$B$191,$A$104:$A$191,$A106)),""),"") | F106: =IFERROR(forecast.ets($A106,$B$104:$B$191,$A$104:$A$191,4,1,1),"") | G106: =IFERROR(F106-forecast.ets.confint($A106,$B$104:$B$191,$A$104:$A$191,0.95,4,1,1),"") | H106: =IFERROR(F106+forecast.ets.confint($A106,$B$104:$B$191,$A$104:$A$191,0.95,4,1,1),"") | J106: 2010 | K106: =IFERROR(AVERAGEIFS($B$104:$B$191,$A$104:$A$191,">="&DATE(J106,1,1),$A$104:$A$191,"<="&DATE(J106,12,31)),"") | L106: =IFERROR(K106/K105-1,"") | M106: =IFERROR(AVERAGEIFS($F$104:$F$191,$A$104:$A$191,">="&DATE(J106,1,1),$A$104:$A$191,"<="&DATE(J106,12,31)),"")
A107: 39722 | B107: =IFERROR(haverdata(Codes!$D$9,$A107),"") | C107: =IFERROR(B107/B106-1,"") | E107: =IFERROR(IF(B107="",IFERROR(GROWTH($B$104:$B$191,$A$104:$A$191,$A107),TREND($B$104:$B$191,$A$104:$A$191,$A107)),""),"") | F107: =IFERROR(forecast.ets($A107,$B$104:$B$191,$A$104:$A$191,4,1,1),"") | G107: =IFERROR(F107-forecast.ets.confint($A107,$B$104:$B$191,$A$104:$A$191,0.95,4,1,1),"") | H107: =IFERROR(F107+forecast.ets.confint($A107,$B$104:$B$191,$A$104:$A$191,0.95,4,1,1),"") | J107: 2011 | K107: =IFERROR(AVERAGEIFS($B$104:$B$191,$A$104:$A$191,">="&DATE(J107,1,1),$A$104:$A$191,"<="&DATE(J107,12,31)),"") | L107: =IFERROR(K107/K106-1,"") | M107: =IFERROR(AVERAGEIFS($F$104:$F$191,$A$104:$A$191,">="&DATE(J107,1,1),$A$104:$A$191,"<="&DATE(J107,12,31)),"")
A108: 39814 | B108: =IFERROR(haverdata(Codes!$D$9,$A108),"") | C108: =IFERROR(B108/B107-1,"") | D108: =IFERROR(B108/B104-1,"") | E108: =IFERROR(IF(B108="",IFERROR(GROWTH($B$104:$B$191,$A$104:$A$191,$A108),TREND($B$104:$B$191,$A$104:$A$191,$A108)),""),"") | F108: =IFERROR(forecast.ets($A108,$B$104:$B$191,$A$104:$A$191,4,1,1),"") | G108: =IFERROR(F108-forecast.ets.confint($A108,$B$104:$B$191,$A$104:$A$191,0.95,4,1,1),"") | H108: =IFERROR(F108+forecast.ets.confint($A108,$B$104:$B$191,$A$104:$A$191,0.95,4,1,1),"") | J108: 2012 | K108: =IFERROR(AVERAGEIFS($B$104:$B$191,$A$104:$A$191,">="&DATE(J108,1,1),$A$104:$A$191,"<="&DATE(J108,12,31)),"") | L108: =IFERROR(K108/K107-1,"") | M108: =IFERROR(AVERAGEIFS($F$104:$F$191,$A$104:$A$191,">="&DATE(J108,1,1),$A$104:$A$191,"<="&DATE(J108,12,31)),"")
A109: 39904 | B109: =IFERROR(haverdata(Codes!$D$9,$A109),"") | C109: =IFERROR(B109/B108-1,"") | D109: =IFERROR(B109/B105-1,"") | E109: =IFERROR(IF(B109="",IFERROR(GROWTH($B$104:$B$191,$A$104:$A$191,$A109),TREND($B$104:$B$191,$A$104:$A$191,$A109)),""),"") | F109: =IFERROR(forecast.ets($A109,$B$104:$B$191,$A$104:$A$191,4,1,1),"") | G109: =IFERROR(F109-forecast.ets.confint($A109,$B$104:$B$191,$A$104:$A$191,0.95,4,1,1),"") | H109: =IFERROR(F109+forecast.ets.confint($A109,$B$104:$B$191,$A$104:$A$191,0.95,4,1,1),"") | J109: 2013 | K109: =IFERROR(AVERAGEIFS($B$104:$B$191,$A$104:$A$191,">="&DATE(J109,1,1),$A$104:$A$191,"<="&DATE(J109,12,31)),"") | L109: =IFERROR(K109/K108-1,"") | M109: =IFERROR(AVERAGEIFS($F$104:$F$191,$A$104:$A$191,">="&DATE(J109,1,1),$A$104:$A$191,"<="&DATE(J109,12,31)),"")
A110: 39995 | B110: =IFERROR(haverdata(Codes!$D$9,$A110),"") | C110: =IFERROR(B110/B109-1,"") | D110: =IFERROR(B110/B106-1,"") | E110: =IFERROR(IF(B110="",IFERROR(GROWTH($B$104:$B$191,$A$104:$A$191,$A110),TREND($B$104:$B$191,$A$104:$A$191,$A110)),""),"") | F110: =IFERROR(forecast.ets($A110,$B$104:$B$191,$A$104:$A$191,4,1,1),"") | G110: =IFERROR(F110-forecast.ets.confint($A110,$B$104:$B$191,$A$104:$A$191,0.95,4,1,1),"") | H110: =IFERROR(F110+forecast.ets.confint($A110,$B$104:$B$191,$A$104:$A$191,0.95,4,1,1),"") | J110: 2014 | K110: =IFERROR(AVERAGEIFS($B$104:$B$191,$A$104:$A$191,">="&DATE(J110,1,1),$A$104:$A$191,"<="&DATE(J110,12,31)),"") | L110: =IFERROR(K110/K109-1,"") | M110: =IFERROR(AVERAGEIFS($F$104:$F$191,$A$104:$A$191,">="&DATE(J110,1,1),$A$104:$A$191,"<="&DATE(J110,12,31)),"")
A111: 40087 | B111: =IFERROR(haverdata(Codes!$D$9,$A111),"") | C111: =IFERROR(B111/B110-1,"") | D111: =IFERROR(B111/B107-1,"") | E111: =IFERROR(IF(B111="",IFERROR(GROWTH($B$104:$B$191,$A$104:$A$191,$A111),TREND($B$104:$B$191,$A$104:$A$191,$A111)),""),"") | F111: =IFERROR(forecast.ets($A111,$B$104:$B$191,$A$104:$A$191,4,1,1),"") | G111: =IFERROR(F111-forecast.ets.confint($A111,$B$104:$B$191,$A$104:$A$191,0.95,4,1,1),"") | H111: =IFERROR(F111+forecast.ets.confint($A111,$B$104:$B$191,$A$104:$A$191,0.95,4,1,1),"") | J111: 2015 | K111: =IFERROR(AVERAGEIFS($B$104:$B$191,$A$104:$A$191,">="&DATE(J111,1,1),$A$104:$A$191,"<="&DATE(J111,12,31)),"") | L111: =IFERROR(K111/K110-1,"") | M111: =IFERROR(AVERAGEIFS($F$104:$F$191,$A$104:$A$191,">="&DATE(J111,1,1),$A$104:$A$191,"<="&DATE(J111,12,31)),"")
A112: 40179 | B112: =IFERROR(haverdata(Codes!$D$9,$A112),"") | C112: =IFERROR(B112/B111-1,"") | D112: =IFERROR(B112/B108-1,"") | E112: =IFERROR(IF(B112="",IFERROR(GROWTH($B$104:$B$191,$A$104:$A$191,$A112),TREND($B$104:$B$191,$A$104:$A$191,$A112)),""),"") | F112: =IFERROR(forecast.ets($A112,$B$104:$B$191,$A$104:$A$191,4,1,1),"") | G112: =IFERROR(F112-forecast.ets.confint($A112,$B$104:$B$191,$A$104:$A$191,0.95,4,1,1),"") | H112: =IFERROR(F112+forecast.ets.confint($A112,$B$104:$B$191,$A$104:$A$191,0.95,4,1,1),"") | J112: 2016 | K112: =IFERROR(AVERAGEIFS($B$104:$B$191,$A$104:$A$191,">="&DATE(J112,1,1),$A$104:$A$191,"<="&DATE(J112,12,31)),"") | L112: =IFERROR(K112/K111-1,"") | M112: =IFERROR(AVERAGEIFS($F$104:$F$191,$A$104:$A$191,">="&DATE(J112,1,1),$A$104:$A$191,"<="&DATE(J112,12,31)),"")
A113: 40269 | B113: =IFERROR(haverdata(Codes!$D$9,$A113),"") | C113: =IFERROR(B113/B112-1,"") | D113: =IFERROR(B113/B109-1,"") | E113: =IFERROR(IF(B113="",IFERROR(GROWTH($B$104:$B$191,$A$104:$A$191,$A113),TREND($B$104:$B$191,$A$104:$A$191,$A113)),""),"") | F113: =IFERROR(forecast.ets($A113,$B$104:$B$191,$A$104:$A$191,4,1,1),"") | G113: =IFERROR(F113-forecast.ets.confint($A113,$B$104:$B$191,$A$104:$A$191,0.95,4,1,1),"") | H113: =IFERROR(F113+forecast.ets.confint($A113,$B$104:$B$191,$A$104:$A$191,0.95,4,1,1),"") | J113: 2017 | K113: =IFERROR(AVERAGEIFS($B$104:$B$191,$A$104:$A$191,">="&DATE(J113,1,1),$A$104:$A$191,"<="&DATE(J113,12,31)),"") | L113: =IFERROR(K113/K112-1,"") | M113: =IFERROR(AVERAGEIFS($F$104:$F$191,$A$104:$A$191,">="&DATE(J113,1,1),$A$104:$A$191,"<="&DATE(J113,12,31)),"")
A114: 40360 | B114: =IFERROR(haverdata(Codes!$D$9,$A114),"") | C114: =IFERROR(B114/B113-1,"") | D114: =IFERROR(B114/B110-1,"") | E114: =IFERROR(IF(B114="",IFERROR(GROWTH($B$104:$B$191,$A$104:$A$191,$A114),TREND($B$104:$B$191,$A$104:$A$191,$A114)),""),"") | F114: =IFERROR(forecast.ets($A114,$B$104:$B$191,$A$104:$A$191,4,1,1),"") | G114: =IFERROR(F114-forecast.ets.confint($A114,$B$104:$B$191,$A$104:$A$191,0.95,4,1,1),"") | H114: =IFERROR(F114+forecast.ets.confint($A114,$B$104:$B$191,$A$104:$A$191,0.95,4,1,1),"") | J114: 2018 | K114: =IFERROR(AVERAGEIFS($B$104:$B$191,$A$104:$A$191,">="&DATE(J114,1,1),$A$104:$A$191,"<="&DATE(J114,12,31)),"") | L114: =IFERROR(K114/K113-1,"") | M114: =IFERROR(AVERAGEIFS($F$104:$F$191,$A$104:$A$191,">="&DATE(J114,1,1),$A$104:$A$191,"<="&DATE(J114,12,31)),"")
A115: 40452 | B115: =IFERROR(haverdata(Codes!$D$9,$A115),"") | C115: =IFERROR(B115/B114-1,"") | D115: =IFERROR(B115/B111-1,"") | E115: =IFERROR(IF(B115="",IFERROR(GROWTH($B$104:$B$191,$A$104:$A$191,$A115),TREND($B$104:$B$191,$A$104:$A$191,$A115)),""),"") | F115: =IFERROR(forecast.ets($A115,$B$104:$B$191,$A$104:$A$191,4,1,1),"") | G115: =IFERROR(F115-forecast.ets.confint($A115,$B$104:$B$191,$A$104:$A$191,0.95,4,1,1),"") | H115: =IFERROR(F115+forecast.ets.confint($A115,$B$104:$B$191,$A$104:$A$191,0.95,4,1,1),"") | J115: 2019 | K115: =IFERROR(AVERAGEIFS($B$104:$B$191,$A$104:$A$191,">="&DATE(J115,1,1),$A$104:$A$191,"<="&DATE(J115,12,31)),"") | L115: =IFERROR(K115/K114-1,"") | M115: =IFERROR(AVERAGEIFS($F$104:$F$191,$A$104:$A$191,">="&DATE(J115,1,1),$A$104:$A$191,"<="&DATE(J115,12,31)),"")
A116: 40544 | B116: =IFERROR(haverdata(Codes!$D$9,$A116),"") | C116: =IFERROR(B116/B115-1,"") | D116: =IFERROR(B116/B112-1,"") | E116: =IFERROR(IF(B116="",IFERROR(GROWTH($B$104:$B$191,$A$104:$A$191,$A116),TREND($B$104:$B$191,$A$104:$A$191,$A116)),""),"") | F116: =IFERROR(forecast.ets($A116,$B$104:$B$191,$A$104:$A$191,4,1,1),"") | G116: =IFERROR(F116-forecast.ets.confint($A116,$B$104:$B$191,$A$104:$A$191,0.95,4,1,1),"") | H116: =IFERROR(F116+forecast.ets.confint($A116,$B$104:$B$191,$A$104:$A$191,0.95,4,1,1),"") | J116: 2020 | K116: =IFERROR(AVERAGEIFS($B$104:$B$191,$A$104:$A$191,">="&DATE(J116,1,1),$A$104:$A$191,"<="&DATE(J116,12,31)),"") | L116: =IFERROR(K116/K115-1,"") | M116: =IFERROR(AVERAGEIFS($F$104:$F$191,$A$104:$A$191,">="&DATE(J116,1,1),$A$104:$A$191,"<="&DATE(J116,12,31)),"")
A117: 40634 | B117: =IFERROR(haverdata(Codes!$D$9,$A117),"") | C117: =IFERROR(B117/B116-1,"") | D117: =IFERROR(B117/B113-1,"") | E117: =IFERROR(IF(B117="",IFERROR(GROWTH($B$104:$B$191,$A$104:$A$191,$A117),TREND($B$104:$B$191,$A$104:$A$191,$A117)),""),"") | F117: =IFERROR(forecast.ets($A117,$B$104:$B$191,$A$104:$A$191,4,1,1),"") | G117: =IFERROR(F117-forecast.ets.confint($A117,$B$104:$B$191,$A$104:$A$191,0.95,4,1,1),"") | H117: =IFERROR(F117+forecast.ets.confint($A117,$B$104:$B$191,$A$104:$A$191,0.95,4,1,1),"") | J117: 2021 | K117: =IFERROR(AVERAGEIFS($B$104:$B$191,$A$104:$A$191,">="&DATE(J117,1,1),$A$104:$A$191,"<="&DATE(J117,12,31)),"") | L117: =IFERROR(K117/K116-1,"") | M117: =IFERROR(AVERAGEIFS($F$104:$F$191,$A$104:$A$191,">="&DATE(J117,1,1),$A$104:$A$191,"<="&DATE(J117,12,31)),"")
A118: 40725 | B118: =IFERROR(haverdata(Codes!$D$9,$A118),"") | C118: =IFERROR(B118/B117-1,"") | D118: =IFERROR(B118/B114-1,"") | E118: =IFERROR(IF(B118="",IFERROR(GROWTH($B$104:$B$191,$A$104:$A$191,$A118),TREND($B$104:$B$191,$A$104:$A$191,$A118)),""),"") | F118: =IFERROR(forecast.ets($A118,$B$104:$B$191,$A$104:$A$191,4,1,1),"") | G118: =IFERROR(F118-forecast.ets.confint($A118,$B$104:$B$191,$A$104:$A$191,0.95,4,1,1),"") | H118: =IFERROR(F118+forecast.ets.confint($A118,$B$104:$B$191,$A$104:$A$191,0.95,4,1,1),"") | J118: 2022 | K118: =IFERROR(AVERAGEIFS($B$104:$B$191,$A$104:$A$191,">="&DATE(J118,1,1),$A$104:$A$191,"<="&DATE(J118,12,31)),"") | L118: =IFERROR(K118/K117-1,"") | M118: =IFERROR(AVERAGEIFS($F$104:$F$191,$A$104:$A$191,">="&DATE(J118,1,1),$A$104:$A$191,"<="&DATE(J118,12,31)),"")
A119: 40817 | B119: =IFERROR(haverdata(Codes!$D$9,$A119),"") | C119: =IFERROR(B119/B118-1,"") | D119: =IFERROR(B119/B115-1,"") | E119: =IFERROR(IF(B119="",IFERROR(GROWTH($B$104:$B$191,$A$104:$A$191,$A119),TREND($B$104:$B$191,$A$104:$A$191,$A119)),""),"") | F119: =IFERROR(forecast.ets($A119,$B$104:$B$191,$A$104:$A$191,4,1,1),"") | G119: =IFERROR(F119-forecast.ets.confint($A119,$B$104:$B$191,$A$104:$A$191,0.95,4,1,1),"") | H119: =IFERROR(F119+forecast.ets.confint($A119,$B$104:$B$191,$A$104:$A$191,0.95,4,1,1),"") | J119: 2023 | K119: =IFERROR(AVERAGEIFS($B$104:$B$191,$A$104:$A$191,">="&DATE(J119,1,1),$A$104:$A$191,"<="&DATE(J119,12,31)),"") | L119: =IFERROR(K119/K118-1,"") | M119: =IFERROR(AVERAGEIFS($F$104:$F$191,$A$104:$A$191,">="&DATE(J119,1,1),$A$104:$A$191,"<="&DATE(J119,12,31)),"")
... A125: 41365 | B125: =IFERROR(haverdata(Codes!$D$9,$A125),"") | C125: =IFERROR(B125/B124-1,"") | D125: =IFERROR(B125/B121-1,"") | E125: =IFERROR(IF(B125="",IFERROR(GROWTH($B$104:$B$191,$A$104:$A$191,$A125),TREND($B$104:$B$191,$A$104:$A$191,$A125)),""),"") | F125: =IFERROR(forecast.ets($A125,$B$104:$B$191,$A$104:$A$191,4,1,1),"") | G125: =IFERROR(F125-forecast.ets.confint($A125,$B$104:$B$191,$A$104:$A$191,0.95,4,1,1),"") | H125: =IFERROR(F125+forecast.ets.confint($A125,$B$104:$B$191,$A$104:$A$191,0.95,4,1,1),"") | J125: 2029 | K125: =IFERROR(AVERAGEIFS($B$104:$B$191,$A$104:$A$191,">="&DATE(J125,1,1),$A$104:$A$191,"<="&DATE(J125,12,31)),"") | L125: =IFERROR(K125/K124-1,"") | M125: =IFERROR(AVERAGEIFS($F$104:$F$191,$A$104:$A$191,">="&DATE(J125,1,1),$A$104:$A$191,"<="&DATE(J125,12,31)),"")
A126: 41456 | B126: =IFERROR(haverdata(Codes!$D$9,$A126),"") | C126: =IFERROR(B126/B125-1,"") | D126: =IFERROR(B126/B122-1,"") | E126: =IFERROR(IF(B126="",IFERROR(GROWTH($B$104:$B$191,$A$104:$A$191,$A126),TREND($B$104:$B$191,$A$104:$A$191,$A126)),""),"") | F126: =IFERROR(forecast.ets($A126,$B$104:$B$191,$A$104:$A$191,4,1,1),"") | G126: =IFERROR(F126-forecast.ets.confint($A126,$B$104:$B$191,$A$104:$A$191,0.95,4,1,1),"") | H126: =IFERROR(F126+forecast.ets.confint($A126,$B$104:$B$191,$A$104:$A$191,0.95,4,1,1),"")
A127: 41548 | B127: =IFERROR(haverdata(Codes!$D$9,$A127),"") | C127: =IFERROR(B127/B126-1,"") | D127: =IFERROR(B127/B123-1,"") | E127: =IFERROR(IF(B127="",IFERROR(GROWTH($B$104:$B$191,$A$104:$A$191,$A127),TREND($B$104:$B$191,$A$104:$A$191,$A127)),""),"") | F127: =IFERROR(forecast.ets($A127,$B$104:$B$191,$A$104:$A$191,4,1,1),"") | G127: =IFERROR(F127-forecast.ets.confint($A127,$B$104:$B$191,$A$104:$A$191,0.95,4,1,1),"") | H127: =IFERROR(F127+forecast.ets.confint($A127,$B$104:$B$191,$A$104:$A$191,0.95,4,1,1),"")
A128: 41640 | B128: =IFERROR(haverdata(Codes!$D$9,$A128),"") | C128: =IFERROR(B128/B127-1,"") | D128: =IFERROR(B128/B124-1,"") | E128: =IFERROR(IF(B128="",IFERROR(GROWTH($B$104:$B$191,$A$104:$A$191,$A128),TREND($B$104:$B$191,$A$104:$A$191,$A128)),""),"") | F128: =IFERROR(forecast.ets($A128,$B$104:$B$191,$A$104:$A$191,4,1,1),"") | G128: =IFERROR(F128-forecast.ets.confint($A128,$B$104:$B$191,$A$104:$A$191,0.95,4,1,1),"") | H128: =IFERROR(F128+forecast.ets.confint($A128,$B$104:$B$191,$A$104:$A$191,0.95,4,1,1),"")
A129: 41730 | B129: =IFERROR(haverdata(Codes!$D$9,$A129),"") | C129: =IFERROR(B129/B128-1,"") | D129: =IFERROR(B129/B125-1,"") | E129: =IFERROR(IF(B129="",IFERROR(GROWTH($B$104:$B$191,$A$104:$A$191,$A129),TREND($B$104:$B$191,$A$104:$A$191,$A129)),""),"") | F129: =IFERROR(forecast.ets($A129,$B$104:$B$191,$A$104:$A$191,4,1,1),"") | G129: =IFERROR(F129-forecast.ets.confint($A129,$B$104:$B$191,$A$104:$A$191,0.95,4,1,1),"") | H129: =IFERROR(F129+forecast.ets.confint($A129,$B$104:$B$191,$A$104:$A$191,0.95,4,1,1),"")
A130: 41821 | B130: =IFERROR(haverdata(Codes!$D$9,$A130),"") | C130: =IFERROR(B130/B129-1,"") | D130: =IFERROR(B130/B126-1,"") | E130: =IFERROR(IF(B130="",IFERROR(GROWTH($B$104:$B$191,$A$104:$A$191,$A130),TREND($B$104:$B$191,$A$104:$A$191,$A130)),""),"") | F130: =IFERROR(forecast.ets($A130,$B$104:$B$191,$A$104:$A$191,4,1,1),"") | G130: =IFERROR(F130-forecast.ets.confint($A130,$B$104:$B$191,$A$104:$A$191,0.95,4,1,1),"") | H130: =IFERROR(F130+forecast.ets.confint($A130,$B$104:$B$191,$A$104:$A$191,0.95,4,1,1),"")
A131: 41913 | B131: =IFERROR(haverdata(Codes!$D$9,$A131),"") | C131: =IFERROR(B131/B130-1,"") | D131: =IFERROR(B131/B127-1,"") | E131: =IFERROR(IF(B131="",IFERROR(GROWTH($B$104:$B$191,$A$104:$A$191,$A131),TREND($B$104:$B$191,$A$104:$A$191,$A131)),""),"") | F131: =IFERROR(forecast.ets($A131,$B$104:$B$191,$A$104:$A$191,4,1,1),"") | G131: =IFERROR(F131-forecast.ets.confint($A131,$B$104:$B$191,$A$104:$A$191,0.95,4,1,1),"") | H131: =IFERROR(F131+forecast.ets.confint($A131,$B$104:$B$191,$A$104:$A$191,0.95,4,1,1),"")
A132: 42005 | B132: =IFERROR(haverdata(Codes!$D$9,$A132),"") | C132: =IFERROR(B132/B131-1,"") | D132: =IFERROR(B132/B128-1,"") | E132: =IFERROR(IF(B132="",IFERROR(GROWTH($B$104:$B$191,$A$104:$A$191,$A132),TREND($B$104:$B$191,$A$104:$A$191,$A132)),""),"") | F132: =IFERROR(forecast.ets($A132,$B$104:$B$191,$A$104:$A$191,4,1,1),"") | G132: =IFERROR(F132-forecast.ets.confint($A132,$B$104:$B$191,$A$104:$A$191,0.95,4,1,1),"") | H132: =IFERROR(F132+forecast.ets.confint($A132,$B$104:$B$191,$A$104:$A$191,0.95,4,1,1),"")
A133: 42095 | B133: =IFERROR(haverdata(Codes!$D$9,$A133),"") | C133: =IFERROR(B133/B132-1,"") | D133: =IFERROR(B133/B129-1,"") | E133: =IFERROR(IF(B133="",IFERROR(GROWTH($B$104:$B$191,$A$104:$A$191,$A133),TREND($B$104:$B$191,$A$104:$A$191,$A133)),""),"") | F133: =IFERROR(forecast.ets($A133,$B$104:$B$191,$A$104:$A$191,4,1,1),"") | G133: =IFERROR(F133-forecast.ets.confint($A133,$B$104:$B$191,$A$104:$A$191,0.95,4,1,1),"") | H133: =IFERROR(F133+forecast.ets.confint($A133,$B$104:$B$191,$A$104:$A$191,0.95,4,1,1),"")
A134: 42186 | B134: =IFERROR(haverdata(Codes!$D$9,$A134),"") | C134: =IFERROR(B134/B133-1,"") | D134: =IFERROR(B134/B130-1,"") | E134: =IFERROR(IF(B134="",IFERROR(GROWTH($B$104:$B$191,$A$104:$A$191,$A134),TREND($B$104:$B$191,$A$104:$A$191,$A134)),""),"") | F134: =IFERROR(forecast.ets($A134,$B$104:$B$191,$A$104:$A$191,4,1,1),"") | G134: =IFERROR(F134-forecast.ets.confint($A134,$B$104:$B$191,$A$104:$A$191,0.95,4,1,1),"") | H134: =IFERROR(F134+forecast.ets.confint($A134,$B$104:$B$191,$A$104:$A$191,0.95,4,1,1),"")
A135: 42278 | B135: =IFERROR(haverdata(Codes!$D$9,$A135),"") | C135: =IFERROR(B135/B134-1,"") | D135: =IFERROR(B135/B131-1,"") | E135: =IFERROR(IF(B135="",IFERROR(GROWTH($B$104:$B$191,$A$104:$A$191,$A135),TREND($B$104:$B$191,$A$104:$A$191,$A135)),""),"") | F135: =IFERROR(forecast.ets($A135,$B$104:$B$191,$A$104:$A$191,4,1,1),"") | G135: =IFERROR(F135-forecast.ets.confint($A135,$B$104:$B$191,$A$104:$A$191,0.95,4,1,1),"") | H135: =IFERROR(F135+forecast.ets.confint($A135,$B$104:$B$191,$A$104:$A$191,0.95,4,1,1),"")
A136: 42370 | B136: =IFERROR(haverdata(Codes!$D$9,$A136),"") | C136: =IFERROR(B136/B135-1,"") | D136: =IFERROR(B136/B132-1,"") | E136: =IFERROR(IF(B136="",IFERROR(GROWTH($B$104:$B$191,$A$104:$A$191,$A136),TREND($B$104:$B$191,$A$104:$A$191,$A136)),""),"") | F136: =IFERROR(forecast.ets($A136,$B$104:$B$191,$A$104:$A$191,4,1,1),"") | G136: =IFERROR(F136-forecast.ets.confint($A136,$B$104:$B$191,$A$104:$A$191,0.95,4,1,1),"") | H136: =IFERROR(F136+forecast.ets.confint($A136,$B$104:$B$191,$A$104:$A$191,0.95,4,1,1),"")
A137: 42461 | B137: =IFERROR(haverdata(Codes!$D$9,$A137),"") | C137: =IFERROR(B137/B136-1,"") | D137: =IFERROR(B137/B133-1,"") | E137: =IFERROR(IF(B137="",IFERROR(GROWTH($B$104:$B$191,$A$104:$A$191,$A137),TREND($B$104:$B$191,$A$104:$A$191,$A137)),""),"") | F137: =IFERROR(forecast.ets($A137,$B$104:$B$191,$A$104:$A$191,4,1,1),"") | G137: =IFERROR(F137-forecast.ets.confint($A137,$B$104:$B$191,$A$104:$A$191,0.95,4,1,1),"") | H137: =IFERROR(F137+forecast.ets.confint($A137,$B$104:$B$191,$A$104:$A$191,0.95,4,1,1),"")
... A191: 47392 | B191: =IFERROR(haverdata(Codes!$D$9,$A191),"") | C191: =IFERROR(B191/B190-1,"") | D191: =IFERROR(B191/B187-1,"") | E191: =IFERROR(IF(B191="",IFERROR(GROWTH($B$104:$B$191,$A$104:$A$191,$A191),TREND($B$104:$B$191,$A$104:$A$191,$A191)),""),"") | F191: =IFERROR(forecast.ets($A191,$B$104:$B$191,$A$104:$A$191,4,1,1),"") | G191: =IFERROR(F191-forecast.ets.confint($A191,$B$104:$B$191,$A$104:$A$191,0.95,4,1,1),"") | H191: =IFERROR(F191+forecast.ets.confint($A191,$B$104:$B$191,$A$104:$A$191,0.95,4,1,1),"")
A196: =Codes!$B$10&" ["&Codes!$D$10&"] "&Codes!$F$10 -> Wholesale Price Index (IPIM) [IPIM@ARGEN] Index
A197: Aggregation: | B197: =Codes!$G$10 -> avg | D197: Notes: | E197: =Codes!$H$10 -> [VERIFY]
A198: Quarterly | J198: Annual
A199: Date | B199: Level | C199: QoQ % | D199: YoY % | E199: Linear Fcst | F199: ETS Fcst | G199: ETS Low 95% | H199: ETS High 95% | J199: Year | K199: Level | L199: YoY % | M199: Forecast
A200: 39448 | B200: =IFERROR(haverdata(Codes!$D$10,$A200),"") | E200: =IFERROR(IF(B200="",IFERROR(GROWTH($B$200:$B$287,$A$200:$A$287,$A200),TREND($B$200:$B$287,$A$200:$A$287,$A200)),""),"") | F200: =IFERROR(forecast.ets($A200,$B$200:$B$287,$A$200:$A$287,4,1,1),"") | G200: =IFERROR(F200-forecast.ets.confint($A200,$B$200:$B$287,$A$200:$A$287,0.95,4,1,1),"") | H200: =IFERROR(F200+forecast.ets.confint($A200,$B$200:$B$287,$A$200:$A$287,0.95,4,1,1),"") | J200: 2008 | K200: =IFERROR(AVERAGEIFS($B$200:$B$287,$A$200:$A$287,">="&DATE(J200,1,1),$A$200:$A$287,"<="&DATE(J200,12,31)),"") | M200: =IFERROR(AVERAGEIFS($F$200:$F$287,$A$200:$A$287,">="&DATE(J200,1,1),$A$200:$A$287,"<="&DATE(J200,12,31)),"")
A201: 39539 | B201: =IFERROR(haverdata(Codes!$D$10,$A201),"") | C201: =IFERROR(B201/B200-1,"") | E201: =IFERROR(IF(B201="",IFERROR(GROWTH($B$200:$B$287,$A$200:$A$287,$A201),TREND($B$200:$B$287,$A$200:$A$287,$A201)),""),"") | F201: =IFERROR(forecast.ets($A201,$B$200:$B$287,$A$200:$A$287,4,1,1),"") | G201: =IFERROR(F201-forecast.ets.confint($A201,$B$200:$B$287,$A$200:$A$287,0.95,4,1,1),"") | H201: =IFERROR(F201+forecast.ets.confint($A201,$B$200:$B$287,$A$200:$A$287,0.95,4,1,1),"") | J201: 2009 | K201: =IFERROR(AVERAGEIFS($B$200:$B$287,$A$200:$A$287,">="&DATE(J201,1,1),$A$200:$A$287,"<="&DATE(J201,12,31)),"") | L201: =IFERROR(K201/K200-1,"") | M201: =IFERROR(AVERAGEIFS($F$200:$F$287,$A$200:$A$287,">="&DATE(J201,1,1),$A$200:$A$287,"<="&DATE(J201,12,31)),"")
A202: 39630 | B202: =IFERROR(haverdata(Codes!$D$10,$A202),"") | C202: =IFERROR(B202/B201-1,"") | E202: =IFERROR(IF(B202="",IFERROR(GROWTH($B$200:$B$287,$A$200:$A$287,$A202),TREND($B$200:$B$287,$A$200:$A$287,$A202)),""),"") | F202: =IFERROR(forecast.ets($A202,$B$200:$B$287,$A$200:$A$287,4,1,1),"") | G202: =IFERROR(F202-forecast.ets.confint($A202,$B$200:$B$287,$A$200:$A$287,0.95,4,1,1),"") | H202: =IFERROR(F202+forecast.ets.confint($A202,$B$200:$B$287,$A$200:$A$287,0.95,4,1,1),"") | J202: 2010 | K202: =IFERROR(AVERAGEIFS($B$200:$B$287,$A$200:$A$287,">="&DATE(J202,1,1),$A$200:$A$287,"<="&DATE(J202,12,31)),"") | L202: =IFERROR(K202/K201-1,"") | M202: =IFERROR(AVERAGEIFS($F$200:$F$287,$A$200:$A$287,">="&DATE(J202,1,1),$A$200:$A$287,"<="&DATE(J202,12,31)),"")
A203: 39722 | B203: =IFERROR(haverdata(Codes!$D$10,$A203),"") | C203: =IFERROR(B203/B202-1,"") | E203: =IFERROR(IF(B203="",IFERROR(GROWTH($B$200:$B$287,$A$200:$A$287,$A203),TREND($B$200:$B$287,$A$200:$A$287,$A203)),""),"") | F203: =IFERROR(forecast.ets($A203,$B$200:$B$287,$A$200:$A$287,4,1,1),"") | G203: =IFERROR(F203-forecast.ets.confint($A203,$B$200:$B$287,$A$200:$A$287,0.95,4,1,1),"") | H203: =IFERROR(F203+forecast.ets.confint($A203,$B$200:$B$287,$A$200:$A$287,0.95,4,1,1),"") | J203: 2011 | K203: =IFERROR(AVERAGEIFS($B$200:$B$287,$A$200:$A$287,">="&DATE(J203,1,1),$A$200:$A$287,"<="&DATE(J203,12,31)),"") | L203: =IFERROR(K203/K202-1,"") | M203: =IFERROR(AVERAGEIFS($F$200:$F$287,$A$200:$A$287,">="&DATE(J203,1,1),$A$200:$A$287,"<="&DATE(J203,12,31)),"")
A204: 39814 | B204: =IFERROR(haverdata(Codes!$D$10,$A204),"") | C204: =IFERROR(B204/B203-1,"") | D204: =IFERROR(B204/B200-1,"") | E204: =IFERROR(IF(B204="",IFERROR(GROWTH($B$200:$B$287,$A$200:$A$287,$A204),TREND($B$200:$B$287,$A$200:$A$287,$A204)),""),"") | F204: =IFERROR(forecast.ets($A204,$B$200:$B$287,$A$200:$A$287,4,1,1),"") | G204: =IFERROR(F204-forecast.ets.confint($A204,$B$200:$B$287,$A$200:$A$287,0.95,4,1,1),"") | H204: =IFERROR(F204+forecast.ets.confint($A204,$B$200:$B$287,$A$200:$A$287,0.95,4,1,1),"") | J204: 2012 | K204: =IFERROR(AVERAGEIFS($B$200:$B$287,$A$200:$A$287,">="&DATE(J204,1,1),$A$200:$A$287,"<="&DATE(J204,12,31)),"") | L204: =IFERROR(K204/K203-1,"") | M204: =IFERROR(AVERAGEIFS($F$200:$F$287,$A$200:$A$287,">="&DATE(J204,1,1),$A$200:$A$287,"<="&DATE(J204,12,31)),"")
A205: 39904 | B205: =IFERROR(haverdata(Codes!$D$10,$A205),"") | C205: =IFERROR(B205/B204-1,"") | D205: =IFERROR(B205/B201-1,"") | E205: =IFERROR(IF(B205="",IFERROR(GROWTH($B$200:$B$287,$A$200:$A$287,$A205),TREND($B$200:$B$287,$A$200:$A$287,$A205)),""),"") | F205: =IFERROR(forecast.ets($A205,$B$200:$B$287,$A$200:$A$287,4,1,1),"") | G205: =IFERROR(F205-forecast.ets.confint($A205,$B$200:$B$287,$A$200:$A$287,0.95,4,1,1),"") | H205: =IFERROR(F205+forecast.ets.confint($A205,$B$200:$B$287,$A$200:$A$287,0.95,4,1,1),"") | J205: 2013 | K205: =IFERROR(AVERAGEIFS($B$200:$B$287,$A$200:$A$287,">="&DATE(J205,1,1),$A$200:$A$287,"<="&DATE(J205,12,31)),"") | L205: =IFERROR(K205/K204-1,"") | M205: =IFERROR(AVERAGEIFS($F$200:$F$287,$A$200:$A$287,">="&DATE(J205,1,1),$A$200:$A$287,"<="&DATE(J205,12,31)),"")
A206: 39995 | B206: =IFERROR(haverdata(Codes!$D$10,$A206),"") | C206: =IFERROR(B206/B205-1,"") | D206: =IFERROR(B206/B202-1,"") | E206: =IFERROR(IF(B206="",IFERROR(GROWTH($B$200:$B$287,$A$200:$A$287,$A206),TREND($B$200:$B$287,$A$200:$A$287,$A206)),""),"") | F206: =IFERROR(forecast.ets($A206,$B$200:$B$287,$A$200:$A$287,4,1,1),"") | G206: =IFERROR(F206-forecast.ets.confint($A206,$B$200:$B$287,$A$200:$A$287,0.95,4,1,1),"") | H206: =IFERROR(F206+forecast.ets.confint($A206,$B$200:$B$287,$A$200:$A$287,0.95,4,1,1),"") | J206: 2014 | K206: =IFERROR(AVERAGEIFS($B$200:$B$287,$A$200:$A$287,">="&DATE(J206,1,1),$A$200:$A$287,"<="&DATE(J206,12,31)),"") | L206: =IFERROR(K206/K205-1,"") | M206: =IFERROR(AVERAGEIFS($F$200:$F$287,$A$200:$A$287,">="&DATE(J206,1,1),$A$200:$A$287,"<="&DATE(J206,12,31)),"")
A207: 40087 | B207: =IFERROR(haverdata(Codes!$D$10,$A207),"") | C207: =IFERROR(B207/B206-1,"") | D207: =IFERROR(B207/B203-1,"") | E207: =IFERROR(IF(B207="",IFERROR(GROWTH($B$200:$B$287,$A$200:$A$287,$A207),TREND($B$200:$B$287,$A$200:$A$287,$A207)),""),"") | F207: =IFERROR(forecast.ets($A207,$B$200:$B$287,$A$200:$A$287,4,1,1),"") | G207: =IFERROR(F207-forecast.ets.confint($A207,$B$200:$B$287,$A$200:$A$287,0.95,4,1,1),"") | H207: =IFERROR(F207+forecast.ets.confint($A207,$B$200:$B$287,$A$200:$A$287,0.95,4,1,1),"") | J207: 2015 | K207: =IFERROR(AVERAGEIFS($B$200:$B$287,$A$200:$A$287,">="&DATE(J207,1,1),$A$200:$A$287,"<="&DATE(J207,12,31)),"") | L207: =IFERROR(K207/K206-1,"") | M207: =IFERROR(AVERAGEIFS($F$200:$F$287,$A$200:$A$287,">="&DATE(J207,1,1),$A$200:$A$287,"<="&DATE(J207,12,31)),"")
A208: 40179 | B208: =IFERROR(haverdata(Codes!$D$10,$A208),"") | C208: =IFERROR(B208/B207-1,"") | D208: =IFERROR(B208/B204-1,"") | E208: =IFERROR(IF(B208="",IFERROR(GROWTH($B$200:$B$287,$A$200:$A$287,$A208),TREND($B$200:$B$287,$A$200:$A$287,$A208)),""),"") | F208: =IFERROR(forecast.ets($A208,$B$200:$B$287,$A$200:$A$287,4,1,1),"") | G208: =IFERROR(F208-forecast.ets.confint($A208,$B$200:$B$287,$A$200:$A$287,0.95,4,1,1),"") | H208: =IFERROR(F208+forecast.ets.confint($A208,$B$200:$B$287,$A$200:$A$287,0.95,4,1,1),"") | J208: 2016 | K208: =IFERROR(AVERAGEIFS($B$200:$B$287,$A$200:$A$287,">="&DATE(J208,1,1),$A$200:$A$287,"<="&DATE(J208,12,31)),"") | L208: =IFERROR(K208/K207-1,"") | M208: =IFERROR(AVERAGEIFS($F$200:$F$287,$A$200:$A$287,">="&DATE(J208,1,1),$A$200:$A$287,"<="&DATE(J208,12,31)),"")
A209: 40269 | B209: =IFERROR(haverdata(Codes!$D$10,$A209),"") | C209: =IFERROR(B209/B208-1,"") | D209: =IFERROR(B209/B205-1,"") | E209: =IFERROR(IF(B209="",IFERROR(GROWTH($B$200:$B$287,$A$200:$A$287,$A209),TREND($B$200:$B$287,$A$200:$A$287,$A209)),""),"") | F209: =IFERROR(forecast.ets($A209,$B$200:$B$287,$A$200:$A$287,4,1,1),"") | G209: =IFERROR(F209-forecast.ets.confint($A209,$B$200:$B$287,$A$200:$A$287,0.95,4,1,1),"") | H209: =IFERROR(F209+forecast.ets.confint($A209,$B$200:$B$287,$A$200:$A$287,0.95,4,1,1),"") | J209: 2017 | K209: =IFERROR(AVERAGEIFS($B$200:$B$287,$A$200:$A$287,">="&DATE(J209,1,1),$A$200:$A$287,"<="&DATE(J209,12,31)),"") | L209: =IFERROR(K209/K208-1,"") | M209: =IFERROR(AVERAGEIFS($F$200:$F$287,$A$200:$A$287,">="&DATE(J209,1,1),$A$200:$A$287,"<="&DATE(J209,12,31)),"")
A210: 40360 | B210: =IFERROR(haverdata(Codes!$D$10,$A210),"") | C210: =IFERROR(B210/B209-1,"") | D210: =IFERROR(B210/B206-1,"") | E210: =IFERROR(IF(B210="",IFERROR(GROWTH($B$200:$B$287,$A$200:$A$287,$A210),TREND($B$200:$B$287,$A$200:$A$287,$A210)),""),"") | F210: =IFERROR(forecast.ets($A210,$B$200:$B$287,$A$200:$A$287,4,1,1),"") | G210: =IFERROR(F210-forecast.ets.confint($A210,$B$200:$B$287,$A$200:$A$287,0.95,4,1,1),"") | H210: =IFERROR(F210+forecast.ets.confint($A210,$B$200:$B$287,$A$200:$A$287,0.95,4,1,1),"") | J210: 2018 | K210: =IFERROR(AVERAGEIFS($B$200:$B$287,$A$200:$A$287,">="&DATE(J210,1,1),$A$200:$A$287,"<="&DATE(J210,12,31)),"") | L210: =IFERROR(K210/K209-1,"") | M210: =IFERROR(AVERAGEIFS($F$200:$F$287,$A$200:$A$287,">="&DATE(J210,1,1),$A$200:$A$287,"<="&DATE(J210,12,31)),"")
A211: 40452 | B211: =IFERROR(haverdata(Codes!$D$10,$A211),"") | C211: =IFERROR(B211/B210-1,"") | D211: =IFERROR(B211/B207-1,"") | E211: =IFERROR(IF(B211="",IFERROR(GROWTH($B$200:$B$287,$A$200:$A$287,$A211),TREND($B$200:$B$287,$A$200:$A$287,$A211)),""),"") | F211: =IFERROR(forecast.ets($A211,$B$200:$B$287,$A$200:$A$287,4,1,1),"") | G211: =IFERROR(F211-forecast.ets.confint($A211,$B$200:$B$287,$A$200:$A$287,0.95,4,1,1),"") | H211: =IFERROR(F211+forecast.ets.confint($A211,$B$200:$B$287,$A$200:$A$287,0.95,4,1,1),"") | J211: 2019 | K211: =IFERROR(AVERAGEIFS($B$200:$B$287,$A$200:$A$287,">="&DATE(J211,1,1),$A$200:$A$287,"<="&DATE(J211,12,31)),"") | L211: =IFERROR(K211/K210-1,"") | M211: =IFERROR(AVERAGEIFS($F$200:$F$287,$A$200:$A$287,">="&DATE(J211,1,1),$A$200:$A$287,"<="&DATE(J211,12,31)),"")
A212: 40544 | B212: =IFERROR(haverdata(Codes!$D$10,$A212),"") | C212: =IFERROR(B212/B211-1,"") | D212: =IFERROR(B212/B208-1,"") | E212: =IFERROR(IF(B212="",IFERROR(GROWTH($B$200:$B$287,$A$200:$A$287,$A212),TREND($B$200:$B$287,$A$200:$A$287,$A212)),""),"") | F212: =IFERROR(forecast.ets($A212,$B$200:$B$287,$A$200:$A$287,4,1,1),"") | G212: =IFERROR(F212-forecast.ets.confint($A212,$B$200:$B$287,$A$200:$A$287,0.95,4,1,1),"") | H212: =IFERROR(F212+forecast.ets.confint($A212,$B$200:$B$287,$A$200:$A$287,0.95,4,1,1),"") | J212: 2020 | K212: =IFERROR(AVERAGEIFS($B$200:$B$287,$A$200:$A$287,">="&DATE(J212,1,1),$A$200:$A$287,"<="&DATE(J212,12,31)),"") | L212: =IFERROR(K212/K211-1,"") | M212: =IFERROR(AVERAGEIFS($F$200:$F$287,$A$200:$A$287,">="&DATE(J212,1,1),$A$200:$A$287,"<="&DATE(J212,12,31)),"")
A213: 40634 | B213: =IFERROR(haverdata(Codes!$D$10,$A213),"") | C213: =IFERROR(B213/B212-1,"") | D213: =IFERROR(B213/B209-1,"") | E213: =IFERROR(IF(B213="",IFERROR(GROWTH($B$200:$B$287,$A$200:$A$287,$A213),TREND($B$200:$B$287,$A$200:$A$287,$A213)),""),"") | F213: =IFERROR(forecast.ets($A213,$B$200:$B$287,$A$200:$A$287,4,1,1),"") | G213: =IFERROR(F213-forecast.ets.confint($A213,$B$200:$B$287,$A$200:$A$287,0.95,4,1,1),"") | H213: =IFERROR(F213+forecast.ets.confint($A213,$B$200:$B$287,$A$200:$A$287,0.95,4,1,1),"") | J213: 2021 | K213: =IFERROR(AVERAGEIFS($B$200:$B$287,$A$200:$A$287,">="&DATE(J213,1,1),$A$200:$A$287,"<="&DATE(J213,12,31)),"") | L213: =IFERROR(K213/K212-1,"") | M213: =IFERROR(AVERAGEIFS($F$200:$F$287,$A$200:$A$287,">="&DATE(J213,1,1),$A$200:$A$287,"<="&DATE(J213,12,31)),"")
A214: 40725 | B214: =IFERROR(haverdata(Codes!$D$10,$A214),"") | C214: =IFERROR(B214/B213-1,"") | D214: =IFERROR(B214/B210-1,"") | E214: =IFERROR(IF(B214="",IFERROR(GROWTH($B$200:$B$287,$A$200:$A$287,$A214),TREND($B$200:$B$287,$A$200:$A$287,$A214)),""),"") | F214: =IFERROR(forecast.ets($A214,$B$200:$B$287,$A$200:$A$287,4,1,1),"") | G214: =IFERROR(F214-forecast.ets.confint($A214,$B$200:$B$287,$A$200:$A$287,0.95,4,1,1),"") | H214: =IFERROR(F214+forecast.ets.confint($A214,$B$200:$B$287,$A$200:$A$287,0.95,4,1,1),"") | J214: 2022 | K214: =IFERROR(AVERAGEIFS($B$200:$B$287,$A$200:$A$287,">="&DATE(J214,1,1),$A$200:$A$287,"<="&DATE(J214,12,31)),"") | L214: =IFERROR(K214/K213-1,"") | M214: =IFERROR(AVERAGEIFS($F$200:$F$287,$A$200:$A$287,">="&DATE(J214,1,1),$A$200:$A$287,"<="&DATE(J214,12,31)),"")
A215: 40817 | B215: =IFERROR(haverdata(Codes!$D$10,$A215),"") | C215: =IFERROR(B215/B214-1,"") | D215: =IFERROR(B215/B211-1,"") | E215: =IFERROR(IF(B215="",IFERROR(GROWTH($B$200:$B$287,$A$200:$A$287,$A215),TREND($B$200:$B$287,$A$200:$A$287,$A215)),""),"") | F215: =IFERROR(forecast.ets($A215,$B$200:$B$287,$A$200:$A$287,4,1,1),"") | G215: =IFERROR(F215-forecast.ets.confint($A215,$B$200:$B$287,$A$200:$A$287,0.95,4,1,1),"") | H215: =IFERROR(F215+forecast.ets.confint($A215,$B$200:$B$287,$A$200:$A$287,0.95,4,1,1),"") | J215: 2023 | K215: =IFERROR(AVERAGEIFS($B$200:$B$287,$A$200:$A$287,">="&DATE(J215,1,1),$A$200:$A$287,"<="&DATE(J215,12,31)),"") | L215: =IFERROR(K215/K214-1,"") | M215: =IFERROR(AVERAGEIFS($F$200:$F$287,$A$200:$A$287,">="&DATE(J215,1,1),$A$200:$A$287,"<="&DATE(J215,12,31)),"")
... A221: 41365 | B221: =IFERROR(haverdata(Codes!$D$10,$A221),"") | C221: =IFERROR(B221/B220-1,"") | D221: =IFERROR(B221/B217-1,"") | E221: =IFERROR(IF(B221="",IFERROR(GROWTH($B$200:$B$287,$A$200:$A$287,$A221),TREND($B$200:$B$287,$A$200:$A$287,$A221)),""),"") | F221: =IFERROR(forecast.ets($A221,$B$200:$B$287,$A$200:$A$287,4,1,1),"") | G221: =IFERROR(F221-forecast.ets.confint($A221,$B$200:$B$287,$A$200:$A$287,0.95,4,1,1),"") | H221: =IFERROR(F221+forecast.ets.confint($A221,$B$200:$B$287,$A$200:$A$287,0.95,4,1,1),"") | J221: 2029 | K221: =IFERROR(AVERAGEIFS($B$200:$B$287,$A$200:$A$287,">="&DATE(J221,1,1),$A$200:$A$287,"<="&DATE(J221,12,31)),"") | L221: =IFERROR(K221/K220-1,"") | M221: =IFERROR(AVERAGEIFS($F$200:$F$287,$A$200:$A$287,">="&DATE(J221,1,1),$A$200:$A$287,"<="&DATE(J221,12,31)),"")
A222: 41456 | B222: =IFERROR(haverdata(Codes!$D$10,$A222),"") | C222: =IFERROR(B222/B221-1,"") | D222: =IFERROR(B222/B218-1,"") | E222: =IFERROR(IF(B222="",IFERROR(GROWTH($B$200:$B$287,$A$200:$A$287,$A222),TREND($B$200:$B$287,$A$200:$A$287,$A222)),""),"") | F222: =IFERROR(forecast.ets($A222,$B$200:$B$287,$A$200:$A$287,4,1,1),"") | G222: =IFERROR(F222-forecast.ets.confint($A222,$B$200:$B$287,$A$200:$A$287,0.95,4,1,1),"") | H222: =IFERROR(F222+forecast.ets.confint($A222,$B$200:$B$287,$A$200:$A$287,0.95,4,1,1),"")
A223: 41548 | B223: =IFERROR(haverdata(Codes!$D$10,$A223),"") | C223: =IFERROR(B223/B222-1,"") | D223: =IFERROR(B223/B219-1,"") | E223: =IFERROR(IF(B223="",IFERROR(GROWTH($B$200:$B$287,$A$200:$A$287,$A223),TREND($B$200:$B$287,$A$200:$A$287,$A223)),""),"") | F223: =IFERROR(forecast.ets($A223,$B$200:$B$287,$A$200:$A$287,4,1,1),"") | G223: =IFERROR(F223-forecast.ets.confint($A223,$B$200:$B$287,$A$200:$A$287,0.95,4,1,1),"") | H223: =IFERROR(F223+forecast.ets.confint($A223,$B$200:$B$287,$A$200:$A$287,0.95,4,1,1),"")
A224: 41640 | B224: =IFERROR(haverdata(Codes!$D$10,$A224),"") | C224: =IFERROR(B224/B223-1,"") | D224: =IFERROR(B224/B220-1,"") | E224: =IFERROR(IF(B224="",IFERROR(GROWTH($B$200:$B$287,$A$200:$A$287,$A224),TREND($B$200:$B$287,$A$200:$A$287,$A224)),""),"") | F224: =IFERROR(forecast.ets($A224,$B$200:$B$287,$A$200:$A$287,4,1,1),"") | G224: =IFERROR(F224-forecast.ets.confint($A224,$B$200:$B$287,$A$200:$A$287,0.95,4,1,1),"") | H224: =IFERROR(F224+forecast.ets.confint($A224,$B$200:$B$287,$A$200:$A$287,0.95,4,1,1),"")
A225: 41730 | B225: =IFERROR(haverdata(Codes!$D$10,$A225),"") | C225: =IFERROR(B225/B224-1,"") | D225: =IFERROR(B225/B221-1,"") | E225: =IFERROR(IF(B225="",IFERROR(GROWTH($B$200:$B$287,$A$200:$A$287,$A225),TREND($B$200:$B$287,$A$200:$A$287,$A225)),""),"") | F225: =IFERROR(forecast.ets($A225,$B$200:$B$287,$A$200:$A$287,4,1,1),"") | G225: =IFERROR(F225-forecast.ets.confint($A225,$B$200:$B$287,$A$200:$A$287,0.95,4,1,1),"") | H225: =IFERROR(F225+forecast.ets.confint($A225,$B$200:$B$287,$A$200:$A$287,0.95,4,1,1),"")
A226: 41821 | B226: =IFERROR(haverdata(Codes!$D$10,$A226),"") | C226: =IFERROR(B226/B225-1,"") | D226: =IFERROR(B226/B222-1,"") | E226: =IFERROR(IF(B226="",IFERROR(GROWTH($B$200:$B$287,$A$200:$A$287,$A226),TREND($B$200:$B$287,$A$200:$A$287,$A226)),""),"") | F226: =IFERROR(forecast.ets($A226,$B$200:$B$287,$A$200:$A$287,4,1,1),"") | G226: =IFERROR(F226-forecast.ets.confint($A226,$B$200:$B$287,$A$200:$A$287,0.95,4,1,1),"") | H226: =IFERROR(F226+forecast.ets.confint($A226,$B$200:$B$287,$A$200:$A$287,0.95,4,1,1),"")
A227: 41913 | B227: =IFERROR(haverdata(Codes!$D$10,$A227),"") | C227: =IFERROR(B227/B226-1,"") | D227: =IFERROR(B227/B223-1,"") | E227: =IFERROR(IF(B227="",IFERROR(GROWTH($B$200:$B$287,$A$200:$A$287,$A227),TREND($B$200:$B$287,$A$200:$A$287,$A227)),""),"") | F227: =IFERROR(forecast.ets($A227,$B$200:$B$287,$A$200:$A$287,4,1,1),"") | G227: =IFERROR(F227-forecast.ets.confint($A227,$B$200:$B$287,$A$200:$A$287,0.95,4,1,1),"") | H227: =IFERROR(F227+forecast.ets.confint($A227,$B$200:$B$287,$A$200:$A$287,0.95,4,1,1),"")
A228: 42005 | B228: =IFERROR(haverdata(Codes!$D$10,$A228),"") | C228: =IFERROR(B228/B227-1,"") | D228: =IFERROR(B228/B224-1,"") | E228: =IFERROR(IF(B228="",IFERROR(GROWTH($B$200:$B$287,$A$200:$A$287,$A228),TREND($B$200:$B$287,$A$200:$A$287,$A228)),""),"") | F228: =IFERROR(forecast.ets($A228,$B$200:$B$287,$A$200:$A$287,4,1,1),"") | G228: =IFERROR(F228-forecast.ets.confint($A228,$B$200:$B$287,$A$200:$A$287,0.95,4,1,1),"") | H228: =IFERROR(F228+forecast.ets.confint($A228,$B$200:$B$287,$A$200:$A$287,0.95,4,1,1),"")
A229: 42095 | B229: =IFERROR(haverdata(Codes!$D$10,$A229),"") | C229: =IFERROR(B229/B228-1,"") | D229: =IFERROR(B229/B225-1,"") | E229: =IFERROR(IF(B229="",IFERROR(GROWTH($B$200:$B$287,$A$200:$A$287,$A229),TREND($B$200:$B$287,$A$200:$A$287,$A229)),""),"") | F229: =IFERROR(forecast.ets($A229,$B$200:$B$287,$A$200:$A$287,4,1,1),"") | G229: =IFERROR(F229-forecast.ets.confint($A229,$B$200:$B$287,$A$200:$A$287,0.95,4,1,1),"") | H229: =IFERROR(F229+forecast.ets.confint($A229,$B$200:$B$287,$A$200:$A$287,0.95,4,1,1),"")
A230: 42186 | B230: =IFERROR(haverdata(Codes!$D$10,$A230),"") | C230: =IFERROR(B230/B229-1,"") | D230: =IFERROR(B230/B226-1,"") | E230: =IFERROR(IF(B230="",IFERROR(GROWTH($B$200:$B$287,$A$200:$A$287,$A230),TREND($B$200:$B$287,$A$200:$A$287,$A230)),""),"") | F230: =IFERROR(forecast.ets($A230,$B$200:$B$287,$A$200:$A$287,4,1,1),"") | G230: =IFERROR(F230-forecast.ets.confint($A230,$B$200:$B$287,$A$200:$A$287,0.95,4,1,1),"") | H230: =IFERROR(F230+forecast.ets.confint($A230,$B$200:$B$287,$A$200:$A$287,0.95,4,1,1),"")
...

Sheet Fiscal
A1: Fiscal — Argentina
A2: Each block: live HaverData pulls (col B) → growth metrics → TREND + FORECAST.ETS forecasts → chart.
A4: =Codes!$B$11&" ["&Codes!$D$11&"] "&Codes!$F$11 -> Primary Fiscal Balance [SPNFBAL@ARGEN] Mn ARS
A5: Aggregation: | B5: =Codes!$G$11 -> sum | D5: Notes: | E5: =Codes!$H$11 -> Sector Publico Nacional No Financiero. [VERIFY]
A6: Quarterly | J6: Annual
A7: Date | B7: Level | C7: QoQ % | D7: YoY % | E7: Linear Fcst | F7: ETS Fcst | G7: ETS Low 95% | H7: ETS High 95% | J7: Year | K7: Level | L7: YoY % | M7: Forecast
A8: 39448 | B8: =IFERROR(haverdata(Codes!$D$11,$A8),"") | E8: =IFERROR(IF(B8="",IFERROR(GROWTH($B$8:$B$95,$A$8:$A$95,$A8),TREND($B$8:$B$95,$A$8:$A$95,$A8)),""),"") | F8: =IFERROR(forecast.ets($A8,$B$8:$B$95,$A$8:$A$95,4,1,1),"") | G8: =IFERROR(F8-forecast.ets.confint($A8,$B$8:$B$95,$A$8:$A$95,0.95,4,1,1),"") | H8: =IFERROR(F8+forecast.ets.confint($A8,$B$8:$B$95,$A$8:$A$95,0.95,4,1,1),"") | J8: 2008 | K8: =IFERROR(SUMIFS($B$8:$B$95,$A$8:$A$95,">="&DATE(J8,1,1),$A$8:$A$95,"<="&DATE(J8,12,31)),"") -> 0 | M8: =IFERROR(SUMIFS($F$8:$F$95,$A$8:$A$95,">="&DATE(J8,1,1),$A$8:$A$95,"<="&DATE(J8,12,31)),"") -> 0
A9: 39539 | B9: =IFERROR(haverdata(Codes!$D$11,$A9),"") | C9: =IFERROR(B9/B8-1,"") | E9: =IFERROR(IF(B9="",IFERROR(GROWTH($B$8:$B$95,$A$8:$A$95,$A9),TREND($B$8:$B$95,$A$8:$A$95,$A9)),""),"") | F9: =IFERROR(forecast.ets($A9,$B$8:$B$95,$A$8:$A$95,4,1,1),"") | G9: =IFERROR(F9-forecast.ets.confint($A9,$B$8:$B$95,$A$8:$A$95,0.95,4,1,1),"") | H9: =IFERROR(F9+forecast.ets.confint($A9,$B$8:$B$95,$A$8:$A$95,0.95,4,1,1),"") | J9: 2009 | K9: =IFERROR(SUMIFS($B$8:$B$95,$A$8:$A$95,">="&DATE(J9,1,1),$A$8:$A$95,"<="&DATE(J9,12,31)),"") -> 0 | L9: =IFERROR(K9/K8-1,"") | M9: =IFERROR(SUMIFS($F$8:$F$95,$A$8:$A$95,">="&DATE(J9,1,1),$A$8:$A$95,"<="&DATE(J9,12,31)),"") -> 0
A10: 39630 | B10: =IFERROR(haverdata(Codes!$D$11,$A10),"") | C10: =IFERROR(B10/B9-1,"") | E10: =IFERROR(IF(B10="",IFERROR(GROWTH($B$8:$B$95,$A$8:$A$95,$A10),TREND($B$8:$B$95,$A$8:$A$95,$A10)),""),"") | F10: =IFERROR(forecast.ets($A10,$B$8:$B$95,$A$8:$A$95,4,1,1),"") | G10: =IFERROR(F10-forecast.ets.confint($A10,$B$8:$B$95,$A$8:$A$95,0.95,4,1,1),"") | H10: =IFERROR(F10+forecast.ets.confint($A10,$B$8:$B$95,$A$8:$A$95,0.95,4,1,1),"") | J10: 2010 | K10: =IFERROR(SUMIFS($B$8:$B$95,$A$8:$A$95,">="&DATE(J10,1,1),$A$8:$A$95,"<="&DATE(J10,12,31)),"") -> 0 | L10: =IFERROR(K10/K9-1,"") | M10: =IFERROR(SUMIFS($F$8:$F$95,$A$8:$A$95,">="&DATE(J10,1,1),$A$8:$A$95,"<="&DATE(J10,12,31)),"") -> 0
A11: 39722 | B11: =IFERROR(haverdata(Codes!$D$11,$A11),"") | C11: =IFERROR(B11/B10-1,"") | E11: =IFERROR(IF(B11="",IFERROR(GROWTH($B$8:$B$95,$A$8:$A$95,$A11),TREND($B$8:$B$95,$A$8:$A$95,$A11)),""),"") | F11: =IFERROR(forecast.ets($A11,$B$8:$B$95,$A$8:$A$95,4,1,1),"") | G11: =IFERROR(F11-forecast.ets.confint($A11,$B$8:$B$95,$A$8:$A$95,0.95,4,1,1),"") | H11: =IFERROR(F11+forecast.ets.confint($A11,$B$8:$B$95,$A$8:$A$95,0.95,4,1,1),"") | J11: 2011 | K11: =IFERROR(SUMIFS($B$8:$B$95,$A$8:$A$95,">="&DATE(J11,1,1),$A$8:$A$95,"<="&DATE(J11,12,31)),"") -> 0 | L11: =IFERROR(K11/K10-1,"") | M11: =IFERROR(SUMIFS($F$8:$F$95,$A$8:$A$95,">="&DATE(J11,1,1),$A$8:$A$95,"<="&DATE(J11,12,31)),"") -> 0
A12: 39814 | B12: =IFERROR(haverdata(Codes!$D$11,$A12),"") | C12: =IFERROR(B12/B11-1,"") | D12: =IFERROR(B12/B8-1,"") | E12: =IFERROR(IF(B12="",IFERROR(GROWTH($B$8:$B$95,$A$8:$A$95,$A12),TREND($B$8:$B$95,$A$8:$A$95,$A12)),""),"") | F12: =IFERROR(forecast.ets($A12,$B$8:$B$95,$A$8:$A$95,4,1,1),"") | G12: =IFERROR(F12-forecast.ets.confint($A12,$B$8:$B$95,$A$8:$A$95,0.95,4,1,1),"") | H12: =IFERROR(F12+forecast.ets.confint($A12,$B$8:$B$95,$A$8:$A$95,0.95,4,1,1),"") | J12: 2012 | K12: =IFERROR(SUMIFS($B$8:$B$95,$A$8:$A$95,">="&DATE(J12,1,1),$A$8:$A$95,"<="&DATE(J12,12,31)),"") -> 0 | L12: =IFERROR(K12/K11-1,"") | M12: =IFERROR(SUMIFS($F$8:$F$95,$A$8:$A$95,">="&DATE(J12,1,1),$A$8:$A$95,"<="&DATE(J12,12,31)),"") -> 0
A13: 39904 | B13: =IFERROR(haverdata(Codes!$D$11,$A13),"") | C13: =IFERROR(B13/B12-1,"") | D13: =IFERROR(B13/B9-1,"") | E13: =IFERROR(IF(B13="",IFERROR(GROWTH($B$8:$B$95,$A$8:$A$95,$A13),TREND($B$8:$B$95,$A$8:$A$95,$A13)),""),"") | F13: =IFERROR(forecast.ets($A13,$B$8:$B$95,$A$8:$A$95,4,1,1),"") | G13: =IFERROR(F13-forecast.ets.confint($A13,$B$8:$B$95,$A$8:$A$95,0.95,4,1,1),"") | H13: =IFERROR(F13+forecast.ets.confint($A13,$B$8:$B$95,$A$8:$A$95,0.95,4,1,1),"") | J13: 2013 | K13: =IFERROR(SUMIFS($B$8:$B$95,$A$8:$A$95,">="&DATE(J13,1,1),$A$8:$A$95,"<="&DATE(J13,12,31)),"") -> 0 | L13: =IFERROR(K13/K12-1,"") | M13: =IFERROR(SUMIFS($F$8:$F$95,$A$8:$A$95,">="&DATE(J13,1,1),$A$8:$A$95,"<="&DATE(J13,12,31)),"") -> 0
A14: 39995 | B14: =IFERROR(haverdata(Codes!$D$11,$A14),"") | C14: =IFERROR(B14/B13-1,"") | D14: =IFERROR(B14/B10-1,"") | E14: =IFERROR(IF(B14="",IFERROR(GROWTH($B$8:$B$95,$A$8:$A$95,$A14),TREND($B$8:$B$95,$A$8:$A$95,$A14)),""),"") | F14: =IFERROR(forecast.ets($A14,$B$8:$B$95,$A$8:$A$95,4,1,1),"") | G14: =IFERROR(F14-forecast.ets.confint($A14,$B$8:$B$95,$A$8:$A$95,0.95,4,1,1),"") | H14: =IFERROR(F14+forecast.ets.confint($A14,$B$8:$B$95,$A$8:$A$95,0.95,4,1,1),"") | J14: 2014 | K14: =IFERROR(SUMIFS($B$8:$B$95,$A$8:$A$95,">="&DATE(J14,1,1),$A$8:$A$95,"<="&DATE(J14,12,31)),"") -> 0 | L14: =IFERROR(K14/K13-1,"") | M14: =IFERROR(SUMIFS($F$8:$F$95,$A$8:$A$95,">="&DATE(J14,1,1),$A$8:$A$95,"<="&DATE(J14,12,31)),"") -> 0
A15: 40087 | B15: =IFERROR(haverdata(Codes!$D$11,$A15),"") | C15: =IFERROR(B15/B14-1,"") | D15: =IFERROR(B15/B11-1,"") | E15: =IFERROR(IF(B15="",IFERROR(GROWTH($B$8:$B$95,$A$8:$A$95,$A15),TREND($B$8:$B$95,$A$8:$A$95,$A15)),""),"") | F15: =IFERROR(forecast.ets($A15,$B$8:$B$95,$A$8:$A$95,4,1,1),"") | G15: =IFERROR(F15-forecast.ets.confint($A15,$B$8:$B$95,$A$8:$A$95,0.95,4,1,1),"") | H15: =IFERROR(F15+forecast.ets.confint($A15,$B$8:$B$95,$A$8:$A$95,0.95,4,1,1),"") | J15: 2015 | K15: =IFERROR(SUMIFS($B$8:$B$95,$A$8:$A$95,">="&DATE(J15,1,1),$A$8:$A$95,"<="&DATE(J15,12,31)),"") -> 0 | L15: =IFERROR(K15/K14-1,"") | M15: =IFERROR(SUMIFS($F$8:$F$95,$A$8:$A$95,">="&DATE(J15,1,1),$A$8:$A$95,"<="&DATE(J15,12,31)),"") -> 0
A16: 40179 | B16: =IFERROR(haverdata(Codes!$D$11,$A16),"") | C16: =IFERROR(B16/B15-1,"") | D16: =IFERROR(B16/B12-1,"") | E16: =IFERROR(IF(B16="",IFERROR(GROWTH($B$8:$B$95,$A$8:$A$95,$A16),TREND($B$8:$B$95,$A$8:$A$95,$A16)),""),"") | F16: =IFERROR(forecast.ets($A16,$B$8:$B$95,$A$8:$A$95,4,1,1),"") | G16: =IFERROR(F16-forecast.ets.confint($A16,$B$8:$B$95,$A$8:$A$95,0.95,4,1,1),"") | H16: =IFERROR(F16+forecast.ets.confint($A16,$B$8:$B$95,$A$8:$A$95,0.95,4,1,1),"") | J16: 2016 | K16: =IFERROR(SUMIFS($B$8:$B$95,$A$8:$A$95,">="&DATE(J16,1,1),$A$8:$A$95,"<="&DATE(J16,12,31)),"") -> 0 | L16: =IFERROR(K16/K15-1,"") | M16: =IFERROR(SUMIFS($F$8:$F$95,$A$8:$A$95,">="&DATE(J16,1,1),$A$8:$A$95,"<="&DATE(J16,12,31)),"") -> 0
A17: 40269 | B17: =IFERROR(haverdata(Codes!$D$11,$A17),"") | C17: =IFERROR(B17/B16-1,"") | D17: =IFERROR(B17/B13-1,"") | E17: =IFERROR(IF(B17="",IFERROR(GROWTH($B$8:$B$95,$A$8:$A$95,$A17),TREND($B$8:$B$95,$A$8:$A$95,$A17)),""),"") | F17: =IFERROR(forecast.ets($A17,$B$8:$B$95,$A$8:$A$95,4,1,1),"") | G17: =IFERROR(F17-forecast.ets.confint($A17,$B$8:$B$95,$A$8:$A$95,0.95,4,1,1),"") | H17: =IFERROR(F17+forecast.ets.confint($A17,$B$8:$B$95,$A$8:$A$95,0.95,4,1,1),"") | J17: 2017 | K17: =IFERROR(SUMIFS($B$8:$B$95,$A$8:$A$95,">="&DATE(J17,1,1),$A$8:$A$95,"<="&DATE(J17,12,31)),"") -> 0 | L17: =IFERROR(K17/K16-1,"") | M17: =IFERROR(SUMIFS($F$8:$F$95,$A$8:$A$95,">="&DATE(J17,1,1),$A$8:$A$95,"<="&DATE(J17,12,31)),"") -> 0
A18: 40360 | B18: =IFERROR(haverdata(Codes!$D$11,$A18),"") | C18: =IFERROR(B18/B17-1,"") | D18: =IFERROR(B18/B14-1,"") | E18: =IFERROR(IF(B18="",IFERROR(GROWTH($B$8:$B$95,$A$8:$A$95,$A18),TREND($B$8:$B$95,$A$8:$A$95,$A18)),""),"") | F18: =IFERROR(forecast.ets($A18,$B$8:$B$95,$A$8:$A$95,4,1,1),"") | G18: =IFERROR(F18-forecast.ets.confint($A18,$B$8:$B$95,$A$8:$A$95,0.95,4,1,1),"") | H18: =IFERROR(F18+forecast.ets.confint($A18,$B$8:$B$95,$A$8:$A$95,0.95,4,1,1),"") | J18: 2018 | K18: =IFERROR(SUMIFS($B$8:$B$95,$A$8:$A$95,">="&DATE(J18,1,1),$A$8:$A$95,"<="&DATE(J18,12,31)),"") -> 0 | L18: =IFERROR(K18/K17-1,"") | M18: =IFERROR(SUMIFS($F$8:$F$95,$A$8:$A$95,">="&DATE(J18,1,1),$A$8:$A$95,"<="&DATE(J18,12,31)),"") -> 0
A19: 40452 | B19: =IFERROR(haverdata(Codes!$D$11,$A19),"") | C19: =IFERROR(B19/B18-1,"") | D19: =IFERROR(B19/B15-1,"") | E19: =IFERROR(IF(B19="",IFERROR(GROWTH($B$8:$B$95,$A$8:$A$95,$A19),TREND($B$8:$B$95,$A$8:$A$95,$A19)),""),"") | F19: =IFERROR(forecast.ets($A19,$B$8:$B$95,$A$8:$A$95,4,1,1),"") | G19: =IFERROR(F19-forecast.ets.confint($A19,$B$8:$B$95,$A$8:$A$95,0.95,4,1,1),"") | H19: =IFERROR(F19+forecast.ets.confint($A19,$B$8:$B$95,$A$8:$A$95,0.95,4,1,1),"") | J19: 2019 | K19: =IFERROR(SUMIFS($B$8:$B$95,$A$8:$A$95,">="&DATE(J19,1,1),$A$8:$A$95,"<="&DATE(J19,12,31)),"") -> 0 | L19: =IFERROR(K19/K18-1,"") | M19: =IFERROR(SUMIFS($F$8:$F$95,$A$8:$A$95,">="&DATE(J19,1,1),$A$8:$A$95,"<="&DATE(J19,12,31)),"") -> 0
A20: 40544 | B20: =IFERROR(haverdata(Codes!$D$11,$A20),"") | C20: =IFERROR(B20/B19-1,"") | D20: =IFERROR(B20/B16-1,"") | E20: =IFERROR(IF(B20="",IFERROR(GROWTH($B$8:$B$95,$A$8:$A$95,$A20),TREND($B$8:$B$95,$A$8:$A$95,$A20)),""),"") | F20: =IFERROR(forecast.ets($A20,$B$8:$B$95,$A$8:$A$95,4,1,1),"") | G20: =IFERROR(F20-forecast.ets.confint($A20,$B$8:$B$95,$A$8:$A$95,0.95,4,1,1),"") | H20: =IFERROR(F20+forecast.ets.confint($A20,$B$8:$B$95,$A$8:$A$95,0.95,4,1,1),"") | J20: 2020 | K20: =IFERROR(SUMIFS($B$8:$B$95,$A$8:$A$95,">="&DATE(J20,1,1),$A$8:$A$95,"<="&DATE(J20,12,31)),"") -> 0 | L20: =IFERROR(K20/K19-1,"") | M20: =IFERROR(SUMIFS($F$8:$F$95,$A$8:$A$95,">="&DATE(J20,1,1),$A$8:$A$95,"<="&DATE(J20,12,31)),"") -> 0
A21: 40634 | B21: =IFERROR(haverdata(Codes!$D$11,$A21),"") | C21: =IFERROR(B21/B20-1,"") | D21: =IFERROR(B21/B17-1,"") | E21: =IFERROR(IF(B21="",IFERROR(GROWTH($B$8:$B$95,$A$8:$A$95,$A21),TREND($B$8:$B$95,$A$8:$A$95,$A21)),""),"") | F21: =IFERROR(forecast.ets($A21,$B$8:$B$95,$A$8:$A$95,4,1,1),"") | G21: =IFERROR(F21-forecast.ets.confint($A21,$B$8:$B$95,$A$8:$A$95,0.95,4,1,1),"") | H21: =IFERROR(F21+forecast.ets.confint($A21,$B$8:$B$95,$A$8:$A$95,0.95,4,1,1),"") | J21: 2021 | K21: =IFERROR(SUMIFS($B$8:$B$95,$A$8:$A$95,">="&DATE(J21,1,1),$A$8:$A$95,"<="&DATE(J21,12,31)),"") -> 0 | L21: =IFERROR(K21/K20-1,"") | M21: =IFERROR(SUMIFS($F$8:$F$95,$A$8:$A$95,">="&DATE(J21,1,1),$A$8:$A$95,"<="&DATE(J21,12,31)),"") -> 0
A22: 40725 | B22: =IFERROR(haverdata(Codes!$D$11,$A22),"") | C22: =IFERROR(B22/B21-1,"") | D22: =IFERROR(B22/B18-1,"") | E22: =IFERROR(IF(B22="",IFERROR(GROWTH($B$8:$B$95,$A$8:$A$95,$A22),TREND($B$8:$B$95,$A$8:$A$95,$A22)),""),"") | F22: =IFERROR(forecast.ets($A22,$B$8:$B$95,$A$8:$A$95,4,1,1),"") | G22: =IFERROR(F22-forecast.ets.confint($A22,$B$8:$B$95,$A$8:$A$95,0.95,4,1,1),"") | H22: =IFERROR(F22+forecast.ets.confint($A22,$B$8:$B$95,$A$8:$A$95,0.95,4,1,1),"") | J22: 2022 | K22: =IFERROR(SUMIFS($B$8:$B$95,$A$8:$A$95,">="&DATE(J22,1,1),$A$8:$A$95,"<="&DATE(J22,12,31)),"") -> 0 | L22: =IFERROR(K22/K21-1,"") | M22: =IFERROR(SUMIFS($F$8:$F$95,$A$8:$A$95,">="&DATE(J22,1,1),$A$8:$A$95,"<="&DATE(J22,12,31)),"") -> 0
A23: 40817 | B23: =IFERROR(haverdata(Codes!$D$11,$A23),"") | C23: =IFERROR(B23/B22-1,"") | D23: =IFERROR(B23/B19-1,"") | E23: =IFERROR(IF(B23="",IFERROR(GROWTH($B$8:$B$95,$A$8:$A$95,$A23),TREND($B$8:$B$95,$A$8:$A$95,$A23)),""),"") | F23: =IFERROR(forecast.ets($A23,$B$8:$B$95,$A$8:$A$95,4,1,1),"") | G23: =IFERROR(F23-forecast.ets.confint($A23,$B$8:$B$95,$A$8:$A$95,0.95,4,1,1),"") | H23: =IFERROR(F23+forecast.ets.confint($A23,$B$8:$B$95,$A$8:$A$95,0.95,4,1,1),"") | J23: 2023 | K23: =IFERROR(SUMIFS($B$8:$B$95,$A$8:$A$95,">="&DATE(J23,1,1),$A$8:$A$95,"<="&DATE(J23,12,31)),"") -> 0 | L23: =IFERROR(K23/K22-1,"") | M23: =IFERROR(SUMIFS($F$8:$F$95,$A$8:$A$95,">="&DATE(J23,1,1),$A$8:$A$95,"<="&DATE(J23,12,31)),"") -> 0
... A29: 41365 | B29: =IFERROR(haverdata(Codes!$D$11,$A29),"") | C29: =IFERROR(B29/B28-1,"") | D29: =IFERROR(B29/B25-1,"") | E29: =IFERROR(IF(B29="",IFERROR(GROWTH($B$8:$B$95,$A$8:$A$95,$A29),TREND($B$8:$B$95,$A$8:$A$95,$A29)),""),"") | F29: =IFERROR(forecast.ets($A29,$B$8:$B$95,$A$8:$A$95,4,1,1),"") | G29: =IFERROR(F29-forecast.ets.confint($A29,$B$8:$B$95,$A$8:$A$95,0.95,4,1,1),"") | H29: =IFERROR(F29+forecast.ets.confint($A29,$B$8:$B$95,$A$8:$A$95,0.95,4,1,1),"") | J29: 2029 | K29: =IFERROR(SUMIFS($B$8:$B$95,$A$8:$A$95,">="&DATE(J29,1,1),$A$8:$A$95,"<="&DATE(J29,12,31)),"") -> 0 | L29: =IFERROR(K29/K28-1,"") | M29: =IFERROR(SUMIFS($F$8:$F$95,$A$8:$A$95,">="&DATE(J29,1,1),$A$8:$A$95,"<="&DATE(J29,12,31)),"") -> 0
A30: 41456 | B30: =IFERROR(haverdata(Codes!$D$11,$A30),"") | C30: =IFERROR(B30/B29-1,"") | D30: =IFERROR(B30/B26-1,"") | E30: =IFERROR(IF(B30="",IFERROR(GROWTH($B$8:$B$95,$A$8:$A$95,$A30),TREND($B$8:$B$95,$A$8:$A$95,$A30)),""),"") | F30: =IFERROR(forecast.ets($A30,$B$8:$B$95,$A$8:$A$95,4,1,1),"") | G30: =IFERROR(F30-forecast.ets.confint($A30,$B$8:$B$95,$A$8:$A$95,0.95,4,1,1),"") | H30: =IFERROR(F30+forecast.ets.confint($A30,$B$8:$B$95,$A$8:$A$95,0.95,4,1,1),"")
A31: 41548 | B31: =IFERROR(haverdata(Codes!$D$11,$A31),"") | C31: =IFERROR(B31/B30-1,"") | D31: =IFERROR(B31/B27-1,"") | E31: =IFERROR(IF(B31="",IFERROR(GROWTH($B$8:$B$95,$A$8:$A$95,$A31),TREND($B$8:$B$95,$A$8:$A$95,$A31)),""),"") | F31: =IFERROR(forecast.ets($A31,$B$8:$B$95,$A$8:$A$95,4,1,1),"") | G31: =IFERROR(F31-forecast.ets.confint($A31,$B$8:$B$95,$A$8:$A$95,0.95,4,1,1),"") | H31: =IFERROR(F31+forecast.ets.confint($A31,$B$8:$B$95,$A$8:$A$95,0.95,4,1,1),"")
A32: 41640 | B32: =IFERROR(haverdata(Codes!$D$11,$A32),"") | C32: =IFERROR(B32/B31-1,"") | D32: =IFERROR(B32/B28-1,"") | E32: =IFERROR(IF(B32="",IFERROR(GROWTH($B$8:$B$95,$A$8:$A$95,$A32),TREND($B$8:$B$95,$A$8:$A$95,$A32)),""),"") | F32: =IFERROR(forecast.ets($A32,$B$8:$B$95,$A$8:$A$95,4,1,1),"") | G32: =IFERROR(F32-forecast.ets.confint($A32,$B$8:$B$95,$A$8:$A$95,0.95,4,1,1),"") | H32: =IFERROR(F32+forecast.ets.confint($A32,$B$8:$B$95,$A$8:$A$95,0.95,4,1,1),"")
A33: 41730 | B33: =IFERROR(haverdata(Codes!$D$11,$A33),"") | C33: =IFERROR(B33/B32-1,"") | D33: =IFERROR(B33/B29-1,"") | E33: =IFERROR(IF(B33="",IFERROR(GROWTH($B$8:$B$95,$A$8:$A$95,$A33),TREND($B$8:$B$95,$A$8:$A$95,$A33)),""),"") | F33: =IFERROR(forecast.ets($A33,$B$8:$B$95,$A$8:$A$95,4,1,1),"") | G33: =IFERROR(F33-forecast.ets.confint($A33,$B$8:$B$95,$A$8:$A$95,0.95,4,1,1),"") | H33: =IFERROR(F33+forecast.ets.confint($A33,$B$8:$B$95,$A$8:$A$95,0.95,4,1,1),"")
A34: 41821 | B34: =IFERROR(haverdata(Codes!$D$11,$A34),"") | C34: =IFERROR(B34/B33-1,"") | D34: =IFERROR(B34/B30-1,"") | E34: =IFERROR(IF(B34="",IFERROR(GROWTH($B$8:$B$95,$A$8:$A$95,$A34),TREND($B$8:$B$95,$A$8:$A$95,$A34)),""),"") | F34: =IFERROR(forecast.ets($A34,$B$8:$B$95,$A$8:$A$95,4,1,1),"") | G34: =IFERROR(F34-forecast.ets.confint($A34,$B$8:$B$95,$A$8:$A$95,0.95,4,1,1),"") | H34: =IFERROR(F34+forecast.ets.confint($A34,$B$8:$B$95,$A$8:$A$95,0.95,4,1,1),"")
A35: 41913 | B35: =IFERROR(haverdata(Codes!$D$11,$A35),"") | C35: =IFERROR(B35/B34-1,"") | D35: =IFERROR(B35/B31-1,"") | E35: =IFERROR(IF(B35="",IFERROR(GROWTH($B$8:$B$95,$A$8:$A$95,$A35),TREND($B$8:$B$95,$A$8:$A$95,$A35)),""),"") | F35: =IFERROR(forecast.ets($A35,$B$8:$B$95,$A$8:$A$95,4,1,1),"") | G35: =IFERROR(F35-forecast.ets.confint($A35,$B$8:$B$95,$A$8:$A$95,0.95,4,1,1),"") | H35: =IFERROR(F35+forecast.ets.confint($A35,$B$8:$B$95,$A$8:$A$95,0.95,4,1,1),"")
A36: 42005 | B36: =IFERROR(haverdata(Codes!$D$11,$A36),"") | C36: =IFERROR(B36/B35-1,"") | D36: =IFERROR(B36/B32-1,"") | E36: =IFERROR(IF(B36="",IFERROR(GROWTH($B$8:$B$95,$A$8:$A$95,$A36),TREND($B$8:$B$95,$A$8:$A$95,$A36)),""),"") | F36: =IFERROR(forecast.ets($A36,$B$8:$B$95,$A$8:$A$95,4,1,1),"") | G36: =IFERROR(F36-forecast.ets.confint($A36,$B$8:$B$95,$A$8:$A$95,0.95,4,1,1),"") | H36: =IFERROR(F36+forecast.ets.confint($A36,$B$8:$B$95,$A$8:$A$95,0.95,4,1,1),"")
A37: 42095 | B37: =IFERROR(haverdata(Codes!$D$11,$A37),"") | C37: =IFERROR(B37/B36-1,"") | D37: =IFERROR(B37/B33-1,"") | E37: =IFERROR(IF(B37="",IFERROR(GROWTH($B$8:$B$95,$A$8:$A$95,$A37),TREND($B$8:$B$95,$A$8:$A$95,$A37)),""),"") | F37: =IFERROR(forecast.ets($A37,$B$8:$B$95,$A$8:$A$95,4,1,1),"") | G37: =IFERROR(F37-forecast.ets.confint($A37,$B$8:$B$95,$A$8:$A$95,0.95,4,1,1),"") | H37: =IFERROR(F37+forecast.ets.confint($A37,$B$8:$B$95,$A$8:$A$95,0.95,4,1,1),"")
A38: 42186 | B38: =IFERROR(haverdata(Codes!$D$11,$A38),"") | C38: =IFERROR(B38/B37-1,"") | D38: =IFERROR(B38/B34-1,"") | E38: =IFERROR(IF(B38="",IFERROR(GROWTH($B$8:$B$95,$A$8:$A$95,$A38),TREND($B$8:$B$95,$A$8:$A$95,$A38)),""),"") | F38: =IFERROR(forecast.ets($A38,$B$8:$B$95,$A$8:$A$95,4,1,1),"") | G38: =IFERROR(F38-forecast.ets.confint($A38,$B$8:$B$95,$A$8:$A$95,0.95,4,1,1),"") | H38: =IFERROR(F38+forecast.ets.confint($A38,$B$8:$B$95,$A$8:$A$95,0.95,4,1,1),"")
A39: 42278 | B39: =IFERROR(haverdata(Codes!$D$11,$A39),"") | C39: =IFERROR(B39/B38-1,"") | D39: =IFERROR(B39/B35-1,"") | E39: =IFERROR(IF(B39="",IFERROR(GROWTH($B$8:$B$95,$A$8:$A$95,$A39),TREND($B$8:$B$95,$A$8:$A$95,$A39)),""),"") | F39: =IFERROR(forecast.ets($A39,$B$8:$B$95,$A$8:$A$95,4,1,1),"") | G39: =IFERROR(F39-forecast.ets.confint($A39,$B$8:$B$95,$A$8:$A$95,0.95,4,1,1),"") | H39: =IFERROR(F39+forecast.ets.confint($A39,$B$8:$B$95,$A$8:$A$95,0.95,4,1,1),"")
A40: 42370 | B40: =IFERROR(haverdata(Codes!$D$11,$A40),"") | C40: =IFERROR(B40/B39-1,"") | D40: =IFERROR(B40/B36-1,"") | E40: =IFERROR(IF(B40="",IFERROR(GROWTH($B$8:$B$95,$A$8:$A$95,$A40),TREND($B$8:$B$95,$A$8:$A$95,$A40)),""),"") | F40: =IFERROR(forecast.ets($A40,$B$8:$B$95,$A$8:$A$95,4,1,1),"") | G40: =IFERROR(F40-forecast.ets.confint($A40,$B$8:$B$95,$A$8:$A$95,0.95,4,1,1),"") | H40: =IFERROR(F40+forecast.ets.confint($A40,$B$8:$B$95,$A$8:$A$95,0.95,4,1,1),"")
A41: 42461 | B41: =IFERROR(haverdata(Codes!$D$11,$A41),"") | C41: =IFERROR(B41/B40-1,"") | D41: =IFERROR(B41/B37-1,"") | E41: =IFERROR(IF(B41="",IFERROR(GROWTH($B$8:$B$95,$A$8:$A$95,$A41),TREND($B$8:$B$95,$A$8:$A$95,$A41)),""),"") | F41: =IFERROR(forecast.ets($A41,$B$8:$B$95,$A$8:$A$95,4,1,1),"") | G41: =IFERROR(F41-forecast.ets.confint($A41,$B$8:$B$95,$A$8:$A$95,0.95,4,1,1),"") | H41: =IFERROR(F41+forecast.ets.confint($A41,$B$8:$B$95,$A$8:$A$95,0.95,4,1,1),"")
... A95: 47392 | B95: =IFERROR(haverdata(Codes!$D$11,$A95),"") | C95: =IFERROR(B95/B94-1,"") | D95: =IFERROR(B95/B91-1,"") | E95: =IFERROR(IF(B95="",IFERROR(GROWTH($B$8:$B$95,$A$8:$A$95,$A95),TREND($B$8:$B$95,$A$8:$A$95,$A95)),""),"") | F95: =IFERROR(forecast.ets($A95,$B$8:$B$95,$A$8:$A$95,4,1,1),"") | G95: =IFERROR(F95-forecast.ets.confint($A95,$B$8:$B$95,$A$8:$A$95,0.95,4,1,1),"") | H95: =IFERROR(F95+forecast.ets.confint($A95,$B$8:$B$95,$A$8:$A$95,0.95,4,1,1),"")
A100: =Codes!$B$12&" ["&Codes!$D$12&"] "&Codes!$F$12 -> Federal Tax Revenue [RECNAC@ARGEN] Mn ARS
A101: Aggregation: | B101: =Codes!$G$12 -> sum | D101: Notes: | E101: =Codes!$H$12 -> [VERIFY]
A102: Quarterly | J102: Annual
A103: Date | B103: Level | C103: QoQ % | D103: YoY % | E103: Linear Fcst | F103: ETS Fcst | G103: ETS Low 95% | H103: ETS High 95% | J103: Year | K103: Level | L103: YoY % | M103: Forecast
A104: 39448 | B104: =IFERROR(haverdata(Codes!$D$12,$A104),"") | E104: =IFERROR(IF(B104="",IFERROR(GROWTH($B$104:$B$191,$A$104:$A$191,$A104),TREND($B$104:$B$191,$A$104:$A$191,$A104)),""),"") | F104: =IFERROR(forecast.ets($A104,$B$104:$B$191,$A$104:$A$191,4,1,1),"") | G104: =IFERROR(F104-forecast.ets.confint($A104,$B$104:$B$191,$A$104:$A$191,0.95,4,1,1),"") | H104: =IFERROR(F104+forecast.ets.confint($A104,$B$104:$B$191,$A$104:$A$191,0.95,4,1,1),"") | J104: 2008 | K104: =IFERROR(SUMIFS($B$104:$B$191,$A$104:$A$191,">="&DATE(J104,1,1),$A$104:$A$191,"<="&DATE(J104,12,31)),"") -> 0 | M104: =IFERROR(SUMIFS($F$104:$F$191,$A$104:$A$191,">="&DATE(J104,1,1),$A$104:$A$191,"<="&DATE(J104,12,31)),"") -> 0
A105: 39539 | B105: =IFERROR(haverdata(Codes!$D$12,$A105),"") | C105: =IFERROR(B105/B104-1,"") | E105: =IFERROR(IF(B105="",IFERROR(GROWTH($B$104:$B$191,$A$104:$A$191,$A105),TREND($B$104:$B$191,$A$104:$A$191,$A105)),""),"") | F105: =IFERROR(forecast.ets($A105,$B$104:$B$191,$A$104:$A$191,4,1,1),"") | G105: =IFERROR(F105-forecast.ets.confint($A105,$B$104:$B$191,$A$104:$A$191,0.95,4,1,1),"") | H105: =IFERROR(F105+forecast.ets.confint($A105,$B$104:$B$191,$A$104:$A$191,0.95,4,1,1),"") | J105: 2009 | K105: =IFERROR(SUMIFS($B$104:$B$191,$A$104:$A$191,">="&DATE(J105,1,1),$A$104:$A$191,"<="&DATE(J105,12,31)),"") -> 0 | L105: =IFERROR(K105/K104-1,"") | M105: =IFERROR(SUMIFS($F$104:$F$191,$A$104:$A$191,">="&DATE(J105,1,1),$A$104:$A$191,"<="&DATE(J105,12,31)),"") -> 0
A106: 39630 | B106: =IFERROR(haverdata(Codes!$D$12,$A106),"") | C106: =IFERROR(B106/B105-1,"") | E106: =IFERROR(IF(B106="",IFERROR(GROWTH($B$104:$B$191,$A$104:$A$191,$A106),TREND($B$104:$B$191,$A$104:$A$191,$A106)),""),"") | F106: =IFERROR(forecast.ets($A106,$B$104:$B$191,$A$104:$A$191,4,1,1),"") | G106: =IFERROR(F106-forecast.ets.confint($A106,$B$104:$B$191,$A$104:$A$191,0.95,4,1,1),"") | H106: =IFERROR(F106+forecast.ets.confint($A106,$B$104:$B$191,$A$104:$A$191,0.95,4,1,1),"") | J106: 2010 | K106: =IFERROR(SUMIFS($B$104:$B$191,$A$104:$A$191,">="&DATE(J106,1,1),$A$104:$A$191,"<="&DATE(J106,12,31)),"") -> 0 | L106: =IFERROR(K106/K105-1,"") | M106: =IFERROR(SUMIFS($F$104:$F$191,$A$104:$A$191,">="&DATE(J106,1,1),$A$104:$A$191,"<="&DATE(J106,12,31)),"") -> 0
A107: 39722 | B107: =IFERROR(haverdata(Codes!$D$12,$A107),"") | C107: =IFERROR(B107/B106-1,"") | E107: =IFERROR(IF(B107="",IFERROR(GROWTH($B$104:$B$191,$A$104:$A$191,$A107),TREND($B$104:$B$191,$A$104:$A$191,$A107)),""),"") | F107: =IFERROR(forecast.ets($A107,$B$104:$B$191,$A$104:$A$191,4,1,1),"") | G107: =IFERROR(F107-forecast.ets.confint($A107,$B$104:$B$191,$A$104:$A$191,0.95,4,1,1),"") | H107: =IFERROR(F107+forecast.ets.confint($A107,$B$104:$B$191,$A$104:$A$191,0.95,4,1,1),"") | J107: 2011 | K107: =IFERROR(SUMIFS($B$104:$B$191,$A$104:$A$191,">="&DATE(J107,1,1),$A$104:$A$191,"<="&DATE(J107,12,31)),"") -> 0 | L107: =IFERROR(K107/K106-1,"") | M107: =IFERROR(SUMIFS($F$104:$F$191,$A$104:$A$191,">="&DATE(J107,1,1),$A$104:$A$191,"<="&DATE(J107,12,31)),"") -> 0
A108: 39814 | B108: =IFERROR(haverdata(Codes!$D$12,$A108),"") | C108: =IFERROR(B108/B107-1,"") | D108: =IFERROR(B108/B104-1,"") | E108: =IFERROR(IF(B108="",IFERROR(GROWTH($B$104:$B$191,$A$104:$A$191,$A108),TREND($B$104:$B$191,$A$104:$A$191,$A108)),""),"") | F108: =IFERROR(forecast.ets($A108,$B$104:$B$191,$A$104:$A$191,4,1,1),"") | G108: =IFERROR(F108-forecast.ets.confint($A108,$B$104:$B$191,$A$104:$A$191,0.95,4,1,1),"") | H108: =IFERROR(F108+forecast.ets.confint($A108,$B$104:$B$191,$A$104:$A$191,0.95,4,1,1),"") | J108: 2012 | K108: =IFERROR(SUMIFS($B$104:$B$191,$A$104:$A$191,">="&DATE(J108,1,1),$A$104:$A$191,"<="&DATE(J108,12,31)),"") -> 0 | L108: =IFERROR(K108/K107-1,"") | M108: =IFERROR(SUMIFS($F$104:$F$191,$A$104:$A$191,">="&DATE(J108,1,1),$A$104:$A$191,"<="&DATE(J108,12,31)),"") -> 0
A109: 39904 | B109: =IFERROR(haverdata(Codes!$D$12,$A109),"") | C109: =IFERROR(B109/B108-1,"") | D109: =IFERROR(B109/B105-1,"") | E109: =IFERROR(IF(B109="",IFERROR(GROWTH($B$104:$B$191,$A$104:$A$191,$A109),TREND($B$104:$B$191,$A$104:$A$191,$A109)),""),"") | F109: =IFERROR(forecast.ets($A109,$B$104:$B$191,$A$104:$A$191,4,1,1),"") | G109: =IFERROR(F109-forecast.ets.confint($A109,$B$104:$B$191,$A$104:$A$191,0.95,4,1,1),"") | H109: =IFERROR(F109+forecast.ets.confint($A109,$B$104:$B$191,$A$104:$A$191,0.95,4,1,1),"") | J109: 2013 | K109: =IFERROR(SUMIFS($B$104:$B$191,$A$104:$A$191,">="&DATE(J109,1,1),$A$104:$A$191,"<="&DATE(J109,12,31)),"") -> 0 | L109: =IFERROR(K109/K108-1,"") | M109: =IFERROR(SUMIFS($F$104:$F$191,$A$104:$A$191,">="&DATE(J109,1,1),$A$104:$A$191,"<="&DATE(J109,12,31)),"") -> 0
A110: 39995 | B110: =IFERROR(haverdata(Codes!$D$12,$A110),"") | C110: =IFERROR(B110/B109-1,"") | D110: =IFERROR(B110/B106-1,"") | E110: =IFERROR(IF(B110="",IFERROR(GROWTH($B$104:$B$191,$A$104:$A$191,$A110),TREND($B$104:$B$191,$A$104:$A$191,$A110)),""),"") | F110: =IFERROR(forecast.ets($A110,$B$104:$B$191,$A$104:$A$191,4,1,1),"") | G110: =IFERROR(F110-forecast.ets.confint($A110,$B$104:$B$191,$A$104:$A$191,0.95,4,1,1),"") | H110: =IFERROR(F110+forecast.ets.confint($A110,$B$104:$B$191,$A$104:$A$191,0.95,4,1,1),"") | J110: 2014 | K110: =IFERROR(SUMIFS($B$104:$B$191,$A$104:$A$191,">="&DATE(J110,1,1),$A$104:$A$191,"<="&DATE(J110,12,31)),"") -> 0 | L110: =IFERROR(K110/K109-1,"") | M110: =IFERROR(SUMIFS($F$104:$F$191,$A$104:$A$191,">="&DATE(J110,1,1),$A$104:$A$191,"<="&DATE(J110,12,31)),"") -> 0
A111: 40087 | B111: =IFERROR(haverdata(Codes!$D$12,$A111),"") | C111: =IFERROR(B111/B110-1,"") | D111: =IFERROR(B111/B107-1,"") | E111: =IFERROR(IF(B111="",IFERROR(GROWTH($B$104:$B$191,$A$104:$A$191,$A111),TREND($B$104:$B$191,$A$104:$A$191,$A111)),""),"") | F111: =IFERROR(forecast.ets($A111,$B$104:$B$191,$A$104:$A$191,4,1,1),"") | G111: =IFERROR(F111-forecast.ets.confint($A111,$B$104:$B$191,$A$104:$A$191,0.95,4,1,1),"") | H111: =IFERROR(F111+forecast.ets.confint($A111,$B$104:$B$191,$A$104:$A$191,0.95,4,1,1),"") | J111: 2015 | K111: =IFERROR(SUMIFS($B$104:$B$191,$A$104:$A$191,">="&DATE(J111,1,1),$A$104:$A$191,"<="&DATE(J111,12,31)),"") -> 0 | L111: =IFERROR(K111/K110-1,"") | M111: =IFERROR(SUMIFS($F$104:$F$191,$A$104:$A$191,">="&DATE(J111,1,1),$A$104:$A$191,"<="&DATE(J111,12,31)),"") -> 0
A112: 40179 | B112: =IFERROR(haverdata(Codes!$D$12,$A112),"") | C112: =IFERROR(B112/B111-1,"") | D112: =IFERROR(B112/B108-1,"") | E112: =IFERROR(IF(B112="",IFERROR(GROWTH($B$104:$B$191,$A$104:$A$191,$A112),TREND($B$104:$B$191,$A$104:$A$191,$A112)),""),"") | F112: =IFERROR(forecast.ets($A112,$B$104:$B$191,$A$104:$A$191,4,1,1),"") | G112: =IFERROR(F112-forecast.ets.confint($A112,$B$104:$B$191,$A$104:$A$191,0.95,4,1,1),"") | H112: =IFERROR(F112+forecast.ets.confint($A112,$B$104:$B$191,$A$104:$A$191,0.95,4,1,1),"") | J112: 2016 | K112: =IFERROR(SUMIFS($B$104:$B$191,$A$104:$A$191,">="&DATE(J112,1,1),$A$104:$A$191,"<="&DATE(J112,12,31)),"") -> 0 | L112: =IFERROR(K112/K111-1,"") | M112: =IFERROR(SUMIFS($F$104:$F$191,$A$104:$A$191,">="&DATE(J112,1,1),$A$104:$A$191,"<="&DATE(J112,12,31)),"") -> 0
A113: 40269 | B113: =IFERROR(haverdata(Codes!$D$12,$A113),"") | C113: =IFERROR(B113/B112-1,"") | D113: =IFERROR(B113/B109-1,"") | E113: =IFERROR(IF(B113="",IFERROR(GROWTH($B$104:$B$191,$A$104:$A$191,$A113),TREND($B$104:$B$191,$A$104:$A$191,$A113)),""),"") | F113: =IFERROR(forecast.ets($A113,$B$104:$B$191,$A$104:$A$191,4,1,1),"") | G113: =IFERROR(F113-forecast.ets.confint($A113,$B$104:$B$191,$A$104:$A$191,0.95,4,1,1),"") | H113: =IFERROR(F113+forecast.ets.confint($A113,$B$104:$B$191,$A$104:$A$191,0.95,4,1,1),"") | J113: 2017 | K113: =IFERROR(SUMIFS($B$104:$B$191,$A$104:$A$191,">="&DATE(J113,1,1),$A$104:$A$191,"<="&DATE(J113,12,31)),"") -> 0 | L113: =IFERROR(K113/K112-1,"") | M113: =IFERROR(SUMIFS($F$104:$F$191,$A$104:$A$191,">="&DATE(J113,1,1),$A$104:$A$191,"<="&DATE(J113,12,31)),"") -> 0
A114: 40360 | B114: =IFERROR(haverdata(Codes!$D$12,$A114),"") | C114: =IFERROR(B114/B113-1,"") | D114: =IFERROR(B114/B110-1,"") | E114: =IFERROR(IF(B114="",IFERROR(GROWTH($B$104:$B$191,$A$104:$A$191,$A114),TREND($B$104:$B$191,$A$104:$A$191,$A114)),""),"") | F114: =IFERROR(forecast.ets($A114,$B$104:$B$191,$A$104:$A$191,4,1,1),"") | G114: =IFERROR(F114-forecast.ets.confint($A114,$B$104:$B$191,$A$104:$A$191,0.95,4,1,1),"") | H114: =IFERROR(F114+forecast.ets.confint($A114,$B$104:$B$191,$A$104:$A$191,0.95,4,1,1),"") | J114: 2018 | K114: =IFERROR(SUMIFS($B$104:$B$191,$A$104:$A$191,">="&DATE(J114,1,1),$A$104:$A$191,"<="&DATE(J114,12,31)),"") -> 0 | L114: =IFERROR(K114/K113-1,"") | M114: =IFERROR(SUMIFS($F$104:$F$191,$A$104:$A$191,">="&DATE(J114,1,1),$A$104:$A$191,"<="&DATE(J114,12,31)),"") -> 0
A115: 40452 | B115: =IFERROR(haverdata(Codes!$D$12,$A115),"") | C115: =IFERROR(B115/B114-1,"") | D115: =IFERROR(B115/B111-1,"") | E115: =IFERROR(IF(B115="",IFERROR(GROWTH($B$104:$B$191,$A$104:$A$191,$A115),TREND($B$104:$B$191,$A$104:$A$191,$A115)),""),"") | F115: =IFERROR(forecast.ets($A115,$B$104:$B$191,$A$104:$A$191,4,1,1),"") | G115: =IFERROR(F115-forecast.ets.confint($A115,$B$104:$B$191,$A$104:$A$191,0.95,4,1,1),"") | H115: =IFERROR(F115+forecast.ets.confint($A115,$B$104:$B$191,$A$104:$A$191,0.95,4,1,1),"") | J115: 2019 | K115: =IFERROR(SUMIFS($B$104:$B$191,$A$104:$A$191,">="&DATE(J115,1,1),$A$104:$A$191,"<="&DATE(J115,12,31)),"") -> 0 | L115: =IFERROR(K115/K114-1,"") | M115: =IFERROR(SUMIFS($F$104:$F$191,$A$104:$A$191,">="&DATE(J115,1,1),$A$104:$A$191,"<="&DATE(J115,12,31)),"") -> 0
A116: 40544 | B116: =IFERROR(haverdata(Codes!$D$12,$A116),"") | C116: =IFERROR(B116/B115-1,"") | D116: =IFERROR(B116/B112-1,"") | E116: =IFERROR(IF(B116="",IFERROR(GROWTH($B$104:$B$191,$A$104:$A$191,$A116),TREND($B$104:$B$191,$A$104:$A$191,$A116)),""),"") | F116: =IFERROR(forecast.ets($A116,$B$104:$B$191,$A$104:$A$191,4,1,1),"") | G116: =IFERROR(F116-forecast.ets.confint($A116,$B$104:$B$191,$A$104:$A$191,0.95,4,1,1),"") | H116: =IFERROR(F116+forecast.ets.confint($A116,$B$104:$B$191,$A$104:$A$191,0.95,4,1,1),"") | J116: 2020 | K116: =IFERROR(SUMIFS($B$104:$B$191,$A$104:$A$191,">="&DATE(J116,1,1),$A$104:$A$191,"<="&DATE(J116,12,31)),"") -> 0 | L116: =IFERROR(K116/K115-1,"") | M116: =IFERROR(SUMIFS($F$104:$F$191,$A$104:$A$191,">="&DATE(J116,1,1),$A$104:$A$191,"<="&DATE(J116,12,31)),"") -> 0
A117: 40634 | B117: =IFERROR(haverdata(Codes!$D$12,$A117),"") | C117: =IFERROR(B117/B116-1,"") | D117: =IFERROR(B117/B113-1,"") | E117: =IFERROR(IF(B117="",IFERROR(GROWTH($B$104:$B$191,$A$104:$A$191,$A117),TREND($B$104:$B$191,$A$104:$A$191,$A117)),""),"") | F117: =IFERROR(forecast.ets($A117,$B$104:$B$191,$A$104:$A$191,4,1,1),"") | G117: =IFERROR(F117-forecast.ets.confint($A117,$B$104:$B$191,$A$104:$A$191,0.95,4,1,1),"") | H117: =IFERROR(F117+forecast.ets.confint($A117,$B$104:$B$191,$A$104:$A$191,0.95,4,1,1),"") | J117: 2021 | K117: =IFERROR(SUMIFS($B$104:$B$191,$A$104:$A$191,">="&DATE(J117,1,1),$A$104:$A$191,"<="&DATE(J117,12,31)),"") -> 0 | L117: =IFERROR(K117/K116-1,"") | M117: =IFERROR(SUMIFS($F$104:$F$191,$A$104:$A$191,">="&DATE(J117,1,1),$A$104:$A$191,"<="&DATE(J117,12,31)),"") -> 0
A118: 40725 | B118: =IFERROR(haverdata(Codes!$D$12,$A118),"") | C118: =IFERROR(B118/B117-1,"") | D118: =IFERROR(B118/B114-1,"") | E118: =IFERROR(IF(B118="",IFERROR(GROWTH($B$104:$B$191,$A$104:$A$191,$A118),TREND($B$104:$B$191,$A$104:$A$191,$A118)),""),"") | F118: =IFERROR(forecast.ets($A118,$B$104:$B$191,$A$104:$A$191,4,1,1),"") | G118: =IFERROR(F118-forecast.ets.confint($A118,$B$104:$B$191,$A$104:$A$191,0.95,4,1,1),"") | H118: =IFERROR(F118+forecast.ets.confint($A118,$B$104:$B$191,$A$104:$A$191,0.95,4,1,1),"") | J118: 2022 | K118: =IFERROR(SUMIFS($B$104:$B$191,$A$104:$A$191,">="&DATE(J118,1,1),$A$104:$A$191,"<="&DATE(J118,12,31)),"") -> 0 | L118: =IFERROR(K118/K117-1,"") | M118: =IFERROR(SUMIFS($F$104:$F$191,$A$104:$A$191,">="&DATE(J118,1,1),$A$104:$A$191,"<="&DATE(J118,12,31)),"") -> 0
A119: 40817 | B119: =IFERROR(haverdata(Codes!$D$12,$A119),"") | C119: =IFERROR(B119/B118-1,"") | D119: =IFERROR(B119/B115-1,"") | E119: =IFERROR(IF(B119="",IFERROR(GROWTH($B$104:$B$191,$A$104:$A$191,$A119),TREND($B$104:$B$191,$A$104:$A$191,$A119)),""),"") | F119: =IFERROR(forecast.ets($A119,$B$104:$B$191,$A$104:$A$191,4,1,1),"") | G119: =IFERROR(F119-forecast.ets.confint($A119,$B$104:$B$191,$A$104:$A$191,0.95,4,1,1),"") | H119: =IFERROR(F119+forecast.ets.confint($A119,$B$104:$B$191,$A$104:$A$191,0.95,4,1,1),"") | J119: 2023 | K119: =IFERROR(SUMIFS($B$104:$B$191,$A$104:$A$191,">="&DATE(J119,1,1),$A$104:$A$191,"<="&DATE(J119,12,31)),"") -> 0 | L119: =IFERROR(K119/K118-1,"") | M119: =IFERROR(SUMIFS($F$104:$F$191,$A$104:$A$191,">="&DATE(J119,1,1),$A$104:$A$191,"<="&DATE(J119,12,31)),"") -> 0
... A125: 41365 | B125: =IFERROR(haverdata(Codes!$D$12,$A125),"") | C125: =IFERROR(B125/B124-1,"") | D125: =IFERROR(B125/B121-1,"") | E125: =IFERROR(IF(B125="",IFERROR(GROWTH($B$104:$B$191,$A$104:$A$191,$A125),TREND($B$104:$B$191,$A$104:$A$191,$A125)),""),"") | F125: =IFERROR(forecast.ets($A125,$B$104:$B$191,$A$104:$A$191,4,1,1),"") | G125: =IFERROR(F125-forecast.ets.confint($A125,$B$104:$B$191,$A$104:$A$191,0.95,4,1,1),"") | H125: =IFERROR(F125+forecast.ets.confint($A125,$B$104:$B$191,$A$104:$A$191,0.95,4,1,1),"") | J125: 2029 | K125: =IFERROR(SUMIFS($B$104:$B$191,$A$104:$A$191,">="&DATE(J125,1,1),$A$104:$A$191,"<="&DATE(J125,12,31)),"") -> 0 | L125: =IFERROR(K125/K124-1,"") | M125: =IFERROR(SUMIFS($F$104:$F$191,$A$104:$A$191,">="&DATE(J125,1,1),$A$104:$A$191,"<="&DATE(J125,12,31)),"") -> 0
A126: 41456 | B126: =IFERROR(haverdata(Codes!$D$12,$A126),"") | C126: =IFERROR(B126/B125-1,"") | D126: =IFERROR(B126/B122-1,"") | E126: =IFERROR(IF(B126="",IFERROR(GROWTH($B$104:$B$191,$A$104:$A$191,$A126),TREND($B$104:$B$191,$A$104:$A$191,$A126)),""),"") | F126: =IFERROR(forecast.ets($A126,$B$104:$B$191,$A$104:$A$191,4,1,1),"") | G126: =IFERROR(F126-forecast.ets.confint($A126,$B$104:$B$191,$A$104:$A$191,0.95,4,1,1),"") | H126: =IFERROR(F126+forecast.ets.confint($A126,$B$104:$B$191,$A$104:$A$191,0.95,4,1,1),"")
A127: 41548 | B127: =IFERROR(haverdata(Codes!$D$12,$A127),"") | C127: =IFERROR(B127/B126-1,"") | D127: =IFERROR(B127/B123-1,"") | E127: =IFERROR(IF(B127="",IFERROR(GROWTH($B$104:$B$191,$A$104:$A$191,$A127),TREND($B$104:$B$191,$A$104:$A$191,$A127)),""),"") | F127: =IFERROR(forecast.ets($A127,$B$104:$B$191,$A$104:$A$191,4,1,1),"") | G127: =IFERROR(F127-forecast.ets.confint($A127,$B$104:$B$191,$A$104:$A$191,0.95,4,1,1),"") | H127: =IFERROR(F127+forecast.ets.confint($A127,$B$104:$B$191,$A$104:$A$191,0.95,4,1,1),"")
A128: 41640 | B128: =IFERROR(haverdata(Codes!$D$12,$A128),"") | C128: =IFERROR(B128/B127-1,"") | D128: =IFERROR(B128/B124-1,"") | E128: =IFERROR(IF(B128="",IFERROR(GROWTH($B$104:$B$191,$A$104:$A$191,$A128),TREND($B$104:$B$191,$A$104:$A$191,$A128)),""),"") | F128: =IFERROR(forecast.ets($A128,$B$104:$B$191,$A$104:$A$191,4,1,1),"") | G128: =IFERROR(F128-forecast.ets.confint($A128,$B$104:$B$191,$A$104:$A$191,0.95,4,1,1),"") | H128: =IFERROR(F128+forecast.ets.confint($A128,$B$104:$B$191,$A$104:$A$191,0.95,4,1,1),"")
A129: 41730 | B129: =IFERROR(haverdata(Codes!$D$12,$A129),"") | C129: =IFERROR(B129/B128-1,"") | D129: =IFERROR(B129/B125-1,"") | E129: =IFERROR(IF(B129="",IFERROR(GROWTH($B$104:$B$191,$A$104:$A$191,$A129),TREND($B$104:$B$191,$A$104:$A$191,$A129)),""),"") | F129: =IFERROR(forecast.ets($A129,$B$104:$B$191,$A$104:$A$191,4,1,1),"") | G129: =IFERROR(F129-forecast.ets.confint($A129,$B$104:$B$191,$A$104:$A$191,0.95,4,1,1),"") | H129: =IFERROR(F129+forecast.ets.confint($A129,$B$104:$B$191,$A$104:$A$191,0.95,4,1,1),"")
A130: 41821 | B130: =IFERROR(haverdata(Codes!$D$12,$A130),"") | C130: =IFERROR(B130/B129-1,"") | D130: =IFERROR(B130/B126-1,"") | E130: =IFERROR(IF(B130="",IFERROR(GROWTH($B$104:$B$191,$A$104:$A$191,$A130),TREND($B$104:$B$191,$A$104:$A$191,$A130)),""),"") | F130: =IFERROR(forecast.ets($A130,$B$104:$B$191,$A$104:$A$191,4,1,1),"") | G130: =IFERROR(F130-forecast.ets.confint($A130,$B$104:$B$191,$A$104:$A$191,0.95,4,1,1),"") | H130: =IFERROR(F130+forecast.ets.confint($A130,$B$104:$B$191,$A$104:$A$191,0.95,4,1,1),"")
A131: 41913 | B131: =IFERROR(haverdata(Codes!$D$12,$A131),"") | C131: =IFERROR(B131/B130-1,"") | D131: =IFERROR(B131/B127-1,"") | E131: =IFERROR(IF(B131="",IFERROR(GROWTH($B$104:$B$191,$A$104:$A$191,$A131),TREND($B$104:$B$191,$A$104:$A$191,$A131)),""),"") | F131: =IFERROR(forecast.ets($A131,$B$104:$B$191,$A$104:$A$191,4,1,1),"") | G131: =IFERROR(F131-forecast.ets.confint($A131,$B$104:$B$191,$A$104:$A$191,0.95,4,1,1),"") | H131: =IFERROR(F131+forecast.ets.confint($A131,$B$104:$B$191,$A$104:$A$191,0.95,4,1,1),"")
A132: 42005 | B132: =IFERROR(haverdata(Codes!$D$12,$A132),"") | C132: =IFERROR(B132/B131-1,"") | D132: =IFERROR(B132/B128-1,"") | E132: =IFERROR(IF(B132="",IFERROR(GROWTH($B$104:$B$191,$A$104:$A$191,$A132),TREND($B$104:$B$191,$A$104:$A$191,$A132)),""),"") | F132: =IFERROR(forecast.ets($A132,$B$104:$B$191,$A$104:$A$191,4,1,1),"") | G132: =IFERROR(F132-forecast.ets.confint($A132,$B$104:$B$191,$A$104:$A$191,0.95,4,1,1),"") | H132: =IFERROR(F132+forecast.ets.confint($A132,$B$104:$B$191,$A$104:$A$191,0.95,4,1,1),"")
A133: 42095 | B133: =IFERROR(haverdata(Codes!$D$12,$A133),"") | C133: =IFERROR(B133/B132-1,"") | D133: =IFERROR(B133/B129-1,"") | E133: =IFERROR(IF(B133="",IFERROR(GROWTH($B$104:$B$191,$A$104:$A$191,$A133),TREND($B$104:$B$191,$A$104:$A$191,$A133)),""),"") | F133: =IFERROR(forecast.ets($A133,$B$104:$B$191,$A$104:$A$191,4,1,1),"") | G133: =IFERROR(F133-forecast.ets.confint($A133,$B$104:$B$191,$A$104:$A$191,0.95,4,1,1),"") | H133: =IFERROR(F133+forecast.ets.confint($A133,$B$104:$B$191,$A$104:$A$191,0.95,4,1,1),"")
A134: 42186 | B134: =IFERROR(haverdata(Codes!$D$12,$A134),"") | C134: =IFERROR(B134/B133-1,"") | D134: =IFERROR(B134/B130-1,"") | E134: =IFERROR(IF(B134="",IFERROR(GROWTH($B$104:$B$191,$A$104:$A$191,$A134),TREND($B$104:$B$191,$A$104:$A$191,$A134)),""),"") | F134: =IFERROR(forecast.ets($A134,$B$104:$B$191,$A$104:$A$191,4,1,1),"") | G134: =IFERROR(F134-forecast.ets.confint($A134,$B$104:$B$191,$A$104:$A$191,0.95,4,1,1),"") | H134: =IFERROR(F134+forecast.ets.confint($A134,$B$104:$B$191,$A$104:$A$191,0.95,4,1,1),"")
A135: 42278 | B135: =IFERROR(haverdata(Codes!$D$12,$A135),"") | C135: =IFERROR(B135/B134-1,"") | D135: =IFERROR(B135/B131-1,"") | E135: =IFERROR(IF(B135="",IFERROR(GROWTH($B$104:$B$191,$A$104:$A$191,$A135),TREND($B$104:$B$191,$A$104:$A$191,$A135)),""),"") | F135: =IFERROR(forecast.ets($A135,$B$104:$B$191,$A$104:$A$191,4,1,1),"") | G135: =IFERROR(F135-forecast.ets.confint($A135,$B$104:$B$191,$A$104:$A$191,0.95,4,1,1),"") | H135: =IFERROR(F135+forecast.ets.confint($A135,$B$104:$B$191,$A$104:$A$191,0.95,4,1,1),"")
A136: 42370 | B136: =IFERROR(haverdata(Codes!$D$12,$A136),"") | C136: =IFERROR(B136/B135-1,"") | D136: =IFERROR(B136/B132-1,"") | E136: =IFERROR(IF(B136="",IFERROR(GROWTH($B$104:$B$191,$A$104:$A$191,$A136),TREND($B$104:$B$191,$A$104:$A$191,$A136)),""),"") | F136: =IFERROR(forecast.ets($A136,$B$104:$B$191,$A$104:$A$191,4,1,1),"") | G136: =IFERROR(F136-forecast.ets.confint($A136,$B$104:$B$191,$A$104:$A$191,0.95,4,1,1),"") | H136: =IFERROR(F136+forecast.ets.confint($A136,$B$104:$B$191,$A$104:$A$191,0.95,4,1,1),"")
A137: 42461 | B137: =IFERROR(haverdata(Codes!$D$12,$A137),"") | C137: =IFERROR(B137/B136-1,"") | D137: =IFERROR(B137/B133-1,"") | E137: =IFERROR(IF(B137="",IFERROR(GROWTH($B$104:$B$191,$A$104:$A$191,$A137),TREND($B$104:$B$191,$A$104:$A$191,$A137)),""),"") | F137: =IFERROR(forecast.ets($A137,$B$104:$B$191,$A$104:$A$191,4,1,1),"") | G137: =IFERROR(F137-forecast.ets.confint($A137,$B$104:$B$191,$A$104:$A$191,0.95,4,1,1),"") | H137: =IFERROR(F137+forecast.ets.confint($A137,$B$104:$B$191,$A$104:$A$191,0.95,4,1,1),"")
... A191: 47392 | B191: =IFERROR(haverdata(Codes!$D$12,$A191),"") | C191: =IFERROR(B191/B190-1,"") | D191: =IFERROR(B191/B187-1,"") | E191: =IFERROR(IF(B191="",IFERROR(GROWTH($B$104:$B$191,$A$104:$A$191,$A191),TREND($B$104:$B$191,$A$104:$A$191,$A191)),""),"") | F191: =IFERROR(forecast.ets($A191,$B$104:$B$191,$A$104:$A$191,4,1,1),"") | G191: =IFERROR(F191-forecast.ets.confint($A191,$B$104:$B$191,$A$104:$A$191,0.95,4,1,1),"") | H191: =IFERROR(F191+forecast.ets.confint($A191,$B$104:$B$191,$A$104:$A$191,0.95,4,1,1),"")
A196: =Codes!$B$13&" ["&Codes!$D$13&"] "&Codes!$F$13 -> Public Debt [DEUDPUB@ARGEN] USD Mn
A197: Aggregation: | B197: =Codes!$G$13 -> last | D197: Notes: | E197: =Codes!$H$13 -> End-period stock. [VERIFY]
A198: Quarterly | J198: Annual
A199: Date | B199: Level | C199: QoQ % | D199: YoY % | E199: Linear Fcst | F199: ETS Fcst | G199: ETS Low 95% | H199: ETS High 95% | J199: Year | K199: Level | L199: YoY % | M199: Forecast
A200: 39448 | B200: =IFERROR(haverdata(Codes!$D$13,$A200),"") | E200: =IFERROR(IF(B200="",IFERROR(GROWTH($B$200:$B$287,$A$200:$A$287,$A200),TREND($B$200:$B$287,$A$200:$A$287,$A200)),""),"") | F200: =IFERROR(forecast.ets($A200,$B$200:$B$287,$A$200:$A$287,4,1,1),"") | G200: =IFERROR(F200-forecast.ets.confint($A200,$B$200:$B$287,$A$200:$A$287,0.95,4,1,1),"") | H200: =IFERROR(F200+forecast.ets.confint($A200,$B$200:$B$287,$A$200:$A$287,0.95,4,1,1),"") | J200: 2008 | K200: =IFERROR(INDEX($B$200:$B$287,MATCH(DATE(J200,10,1),$A$200:$A$287,0)),"") | M200: =IFERROR(INDEX($F$200:$F$287,MATCH(DATE(J200,10,1),$A$200:$A$287,0)),"")
A201: 39539 | B201: =IFERROR(haverdata(Codes!$D$13,$A201),"") | C201: =IFERROR(B201/B200-1,"") | E201: =IFERROR(IF(B201="",IFERROR(GROWTH($B$200:$B$287,$A$200:$A$287,$A201),TREND($B$200:$B$287,$A$200:$A$287,$A201)),""),"") | F201: =IFERROR(forecast.ets($A201,$B$200:$B$287,$A$200:$A$287,4,1,1),"") | G201: =IFERROR(F201-forecast.ets.confint($A201,$B$200:$B$287,$A$200:$A$287,0.95,4,1,1),"") | H201: =IFERROR(F201+forecast.ets.confint($A201,$B$200:$B$287,$A$200:$A$287,0.95,4,1,1),"") | J201: 2009 | K201: =IFERROR(INDEX($B$200:$B$287,MATCH(DATE(J201,10,1),$A$200:$A$287,0)),"") | L201: =IFERROR(K201/K200-1,"") | M201: =IFERROR(INDEX($F$200:$F$287,MATCH(DATE(J201,10,1),$A$200:$A$287,0)),"")
A202: 39630 | B202: =IFERROR(haverdata(Codes!$D$13,$A202),"") | C202: =IFERROR(B202/B201-1,"") | E202: =IFERROR(IF(B202="",IFERROR(GROWTH($B$200:$B$287,$A$200:$A$287,$A202),TREND($B$200:$B$287,$A$200:$A$287,$A202)),""),"") | F202: =IFERROR(forecast.ets($A202,$B$200:$B$287,$A$200:$A$287,4,1,1),"") | G202: =IFERROR(F202-forecast.ets.confint($A202,$B$200:$B$287,$A$200:$A$287,0.95,4,1,1),"") | H202: =IFERROR(F202+forecast.ets.confint($A202,$B$200:$B$287,$A$200:$A$287,0.95,4,1,1),"") | J202: 2010 | K202: =IFERROR(INDEX($B$200:$B$287,MATCH(DATE(J202,10,1),$A$200:$A$287,0)),"") | L202: =IFERROR(K202/K201-1,"") | M202: =IFERROR(INDEX($F$200:$F$287,MATCH(DATE(J202,10,1),$A$200:$A$287,0)),"")
A203: 39722 | B203: =IFERROR(haverdata(Codes!$D$13,$A203),"") | C203: =IFERROR(B203/B202-1,"") | E203: =IFERROR(IF(B203="",IFERROR(GROWTH($B$200:$B$287,$A$200:$A$287,$A203),TREND($B$200:$B$287,$A$200:$A$287,$A203)),""),"") | F203: =IFERROR(forecast.ets($A203,$B$200:$B$287,$A$200:$A$287,4,1,1),"") | G203: =IFERROR(F203-forecast.ets.confint($A203,$B$200:$B$287,$A$200:$A$287,0.95,4,1,1),"") | H203: =IFERROR(F203+forecast.ets.confint($A203,$B$200:$B$287,$A$200:$A$287,0.95,4,1,1),"") | J203: 2011 | K203: =IFERROR(INDEX($B$200:$B$287,MATCH(DATE(J203,10,1),$A$200:$A$287,0)),"") | L203: =IFERROR(K203/K202-1,"") | M203: =IFERROR(INDEX($F$200:$F$287,MATCH(DATE(J203,10,1),$A$200:$A$287,0)),"")
A204: 39814 | B204: =IFERROR(haverdata(Codes!$D$13,$A204),"") | C204: =IFERROR(B204/B203-1,"") | D204: =IFERROR(B204/B200-1,"") | E204: =IFERROR(IF(B204="",IFERROR(GROWTH($B$200:$B$287,$A$200:$A$287,$A204),TREND($B$200:$B$287,$A$200:$A$287,$A204)),""),"") | F204: =IFERROR(forecast.ets($A204,$B$200:$B$287,$A$200:$A$287,4,1,1),"") | G204: =IFERROR(F204-forecast.ets.confint($A204,$B$200:$B$287,$A$200:$A$287,0.95,4,1,1),"") | H204: =IFERROR(F204+forecast.ets.confint($A204,$B$200:$B$287,$A$200:$A$287,0.95,4,1,1),"") | J204: 2012 | K204: =IFERROR(INDEX($B$200:$B$287,MATCH(DATE(J204,10,1),$A$200:$A$287,0)),"") | L204: =IFERROR(K204/K203-1,"") | M204: =IFERROR(INDEX($F$200:$F$287,MATCH(DATE(J204,10,1),$A$200:$A$287,0)),"")
A205: 39904 | B205: =IFERROR(haverdata(Codes!$D$13,$A205),"") | C205: =IFERROR(B205/B204-1,"") | D205: =IFERROR(B205/B201-1,"") | E205: =IFERROR(IF(B205="",IFERROR(GROWTH($B$200:$B$287,$A$200:$A$287,$A205),TREND($B$200:$B$287,$A$200:$A$287,$A205)),""),"") | F205: =IFERROR(forecast.ets($A205,$B$200:$B$287,$A$200:$A$287,4,1,1),"") | G205: =IFERROR(F205-forecast.ets.confint($A205,$B$200:$B$287,$A$200:$A$287,0.95,4,1,1),"") | H205: =IFERROR(F205+forecast.ets.confint($A205,$B$200:$B$287,$A$200:$A$287,0.95,4,1,1),"") | J205: 2013 | K205: =IFERROR(INDEX($B$200:$B$287,MATCH(DATE(J205,10,1),$A$200:$A$287,0)),"") | L205: =IFERROR(K205/K204-1,"") | M205: =IFERROR(INDEX($F$200:$F$287,MATCH(DATE(J205,10,1),$A$200:$A$287,0)),"")
A206: 39995 | B206: =IFERROR(haverdata(Codes!$D$13,$A206),"") | C206: =IFERROR(B206/B205-1,"") | D206: =IFERROR(B206/B202-1,"") | E206: =IFERROR(IF(B206="",IFERROR(GROWTH($B$200:$B$287,$A$200:$A$287,$A206),TREND($B$200:$B$287,$A$200:$A$287,$A206)),""),"") | F206: =IFERROR(forecast.ets($A206,$B$200:$B$287,$A$200:$A$287,4,1,1),"") | G206: =IFERROR(F206-forecast.ets.confint($A206,$B$200:$B$287,$A$200:$A$287,0.95,4,1,1),"") | H206: =IFERROR(F206+forecast.ets.confint($A206,$B$200:$B$287,$A$200:$A$287,0.95,4,1,1),"") | J206: 2014 | K206: =IFERROR(INDEX($B$200:$B$287,MATCH(DATE(J206,10,1),$A$200:$A$287,0)),"") | L206: =IFERROR(K206/K205-1,"") | M206: =IFERROR(INDEX($F$200:$F$287,MATCH(DATE(J206,10,1),$A$200:$A$287,0)),"")
A207: 40087 | B207: =IFERROR(haverdata(Codes!$D$13,$A207),"") | C207: =IFERROR(B207/B206-1,"") | D207: =IFERROR(B207/B203-1,"") | E207: =IFERROR(IF(B207="",IFERROR(GROWTH($B$200:$B$287,$A$200:$A$287,$A207),TREND($B$200:$B$287,$A$200:$A$287,$A207)),""),"") | F207: =IFERROR(forecast.ets($A207,$B$200:$B$287,$A$200:$A$287,4,1,1),"") | G207: =IFERROR(F207-forecast.ets.confint($A207,$B$200:$B$287,$A$200:$A$287,0.95,4,1,1),"") | H207: =IFERROR(F207+forecast.ets.confint($A207,$B$200:$B$287,$A$200:$A$287,0.95,4,1,1),"") | J207: 2015 | K207: =IFERROR(INDEX($B$200:$B$287,MATCH(DATE(J207,10,1),$A$200:$A$287,0)),"") | L207: =IFERROR(K207/K206-1,"") | M207: =IFERROR(INDEX($F$200:$F$287,MATCH(DATE(J207,10,1),$A$200:$A$287,0)),"")
A208: 40179 | B208: =IFERROR(haverdata(Codes!$D$13,$A208),"") | C208: =IFERROR(B208/B207-1,"") | D208: =IFERROR(B208/B204-1,"") | E208: =IFERROR(IF(B208="",IFERROR(GROWTH($B$200:$B$287,$A$200:$A$287,$A208),TREND($B$200:$B$287,$A$200:$A$287,$A208)),""),"") | F208: =IFERROR(forecast.ets($A208,$B$200:$B$287,$A$200:$A$287,4,1,1),"") | G208: =IFERROR(F208-forecast.ets.confint($A208,$B$200:$B$287,$A$200:$A$287,0.95,4,1,1),"") | H208: =IFERROR(F208+forecast.ets.confint($A208,$B$200:$B$287,$A$200:$A$287,0.95,4,1,1),"") | J208: 2016 | K208: =IFERROR(INDEX($B$200:$B$287,MATCH(DATE(J208,10,1),$A$200:$A$287,0)),"") | L208: =IFERROR(K208/K207-1,"") | M208: =IFERROR(INDEX($F$200:$F$287,MATCH(DATE(J208,10,1),$A$200:$A$287,0)),"")
A209: 40269 | B209: =IFERROR(haverdata(Codes!$D$13,$A209),"") | C209: =IFERROR(B209/B208-1,"") | D209: =IFERROR(B209/B205-1,"") | E209: =IFERROR(IF(B209="",IFERROR(GROWTH($B$200:$B$287,$A$200:$A$287,$A209),TREND($B$200:$B$287,$A$200:$A$287,$A209)),""),"") | F209: =IFERROR(forecast.ets($A209,$B$200:$B$287,$A$200:$A$287,4,1,1),"") | G209: =IFERROR(F209-forecast.ets.confint($A209,$B$200:$B$287,$A$200:$A$287,0.95,4,1,1),"") | H209: =IFERROR(F209+forecast.ets.confint($A209,$B$200:$B$287,$A$200:$A$287,0.95,4,1,1),"") | J209: 2017 | K209: =IFERROR(INDEX($B$200:$B$287,MATCH(DATE(J209,10,1),$A$200:$A$287,0)),"") | L209: =IFERROR(K209/K208-1,"") | M209: =IFERROR(INDEX($F$200:$F$287,MATCH(DATE(J209,10,1),$A$200:$A$287,0)),"")
A210: 40360 | B210: =IFERROR(haverdata(Codes!$D$13,$A210),"") | C210: =IFERROR(B210/B209-1,"") | D210: =IFERROR(B210/B206-1,"") | E210: =IFERROR(IF(B210="",IFERROR(GROWTH($B$200:$B$287,$A$200:$A$287,$A210),TREND($B$200:$B$287,$A$200:$A$287,$A210)),""),"") | F210: =IFERROR(forecast.ets($A210,$B$200:$B$287,$A$200:$A$287,4,1,1),"") | G210: =IFERROR(F210-forecast.ets.confint($A210,$B$200:$B$287,$A$200:$A$287,0.95,4,1,1),"") | H210: =IFERROR(F210+forecast.ets.confint($A210,$B$200:$B$287,$A$200:$A$287,0.95,4,1,1),"") | J210: 2018 | K210: =IFERROR(INDEX($B$200:$B$287,MATCH(DATE(J210,10,1),$A$200:$A$287,0)),"") | L210: =IFERROR(K210/K209-1,"") | M210: =IFERROR(INDEX($F$200:$F$287,MATCH(DATE(J210,10,1),$A$200:$A$287,0)),"")
A211: 40452 | B211: =IFERROR(haverdata(Codes!$D$13,$A211),"") | C211: =IFERROR(B211/B210-1,"") | D211: =IFERROR(B211/B207-1,"") | E211: =IFERROR(IF(B211="",IFERROR(GROWTH($B$200:$B$287,$A$200:$A$287,$A211),TREND($B$200:$B$287,$A$200:$A$287,$A211)),""),"") | F211: =IFERROR(forecast.ets($A211,$B$200:$B$287,$A$200:$A$287,4,1,1),"") | G211: =IFERROR(F211-forecast.ets.confint($A211,$B$200:$B$287,$A$200:$A$287,0.95,4,1,1),"") | H211: =IFERROR(F211+forecast.ets.confint($A211,$B$200:$B$287,$A$200:$A$287,0.95,4,1,1),"") | J211: 2019 | K211: =IFERROR(INDEX($B$200:$B$287,MATCH(DATE(J211,10,1),$A$200:$A$287,0)),"") | L211: =IFERROR(K211/K210-1,"") | M211: =IFERROR(INDEX($F$200:$F$287,MATCH(DATE(J211,10,1),$A$200:$A$287,0)),"")
A212: 40544 | B212: =IFERROR(haverdata(Codes!$D$13,$A212),"") | C212: =IFERROR(B212/B211-1,"") | D212: =IFERROR(B212/B208-1,"") | E212: =IFERROR(IF(B212="",IFERROR(GROWTH($B$200:$B$287,$A$200:$A$287,$A212),TREND($B$200:$B$287,$A$200:$A$287,$A212)),""),"") | F212: =IFERROR(forecast.ets($A212,$B$200:$B$287,$A$200:$A$287,4,1,1),"") | G212: =IFERROR(F212-forecast.ets.confint($A212,$B$200:$B$287,$A$200:$A$287,0.95,4,1,1),"") | H212: =IFERROR(F212+forecast.ets.confint($A212,$B$200:$B$287,$A$200:$A$287,0.95,4,1,1),"") | J212: 2020 | K212: =IFERROR(INDEX($B$200:$B$287,MATCH(DATE(J212,10,1),$A$200:$A$287,0)),"") | L212: =IFERROR(K212/K211-1,"") | M212: =IFERROR(INDEX($F$200:$F$287,MATCH(DATE(J212,10,1),$A$200:$A$287,0)),"")
A213: 40634 | B213: =IFERROR(haverdata(Codes!$D$13,$A213),"") | C213: =IFERROR(B213/B212-1,"") | D213: =IFERROR(B213/B209-1,"") | E213: =IFERROR(IF(B213="",IFERROR(GROWTH($B$200:$B$287,$A$200:$A$287,$A213),TREND($B$200:$B$287,$A$200:$A$287,$A213)),""),"") | F213: =IFERROR(forecast.ets($A213,$B$200:$B$287,$A$200:$A$287,4,1,1),"") | G213: =IFERROR(F213-forecast.ets.confint($A213,$B$200:$B$287,$A$200:$A$287,0.95,4,1,1),"") | H213: =IFERROR(F213+forecast.ets.confint($A213,$B$200:$B$287,$A$200:$A$287,0.95,4,1,1),"") | J213: 2021 | K213: =IFERROR(INDEX($B$200:$B$287,MATCH(DATE(J213,10,1),$A$200:$A$287,0)),"") | L213: =IFERROR(K213/K212-1,"") | M213: =IFERROR(INDEX($F$200:$F$287,MATCH(DATE(J213,10,1),$A$200:$A$287,0)),"")
A214: 40725 | B214: =IFERROR(haverdata(Codes!$D$13,$A214),"") | C214: =IFERROR(B214/B213-1,"") | D214: =IFERROR(B214/B210-1,"") | E214: =IFERROR(IF(B214="",IFERROR(GROWTH($B$200:$B$287,$A$200:$A$287,$A214),TREND($B$200:$B$287,$A$200:$A$287,$A214)),""),"") | F214: =IFERROR(forecast.ets($A214,$B$200:$B$287,$A$200:$A$287,4,1,1),"") | G214: =IFERROR(F214-forecast.ets.confint($A214,$B$200:$B$287,$A$200:$A$287,0.95,4,1,1),"") | H214: =IFERROR(F214+forecast.ets.confint($A214,$B$200:$B$287,$A$200:$A$287,0.95,4,1,1),"") | J214: 2022 | K214: =IFERROR(INDEX($B$200:$B$287,MATCH(DATE(J214,10,1),$A$200:$A$287,0)),"") | L214: =IFERROR(K214/K213-1,"") | M214: =IFERROR(INDEX($F$200:$F$287,MATCH(DATE(J214,10,1),$A$200:$A$287,0)),"")
A215: 40817 | B215: =IFERROR(haverdata(Codes!$D$13,$A215),"") | C215: =IFERROR(B215/B214-1,"") | D215: =IFERROR(B215/B211-1,"") | E215: =IFERROR(IF(B215="",IFERROR(GROWTH($B$200:$B$287,$A$200:$A$287,$A215),TREND($B$200:$B$287,$A$200:$A$287,$A215)),""),"") | F215: =IFERROR(forecast.ets($A215,$B$200:$B$287,$A$200:$A$287,4,1,1),"") | G215: =IFERROR(F215-forecast.ets.confint($A215,$B$200:$B$287,$A$200:$A$287,0.95,4,1,1),"") | H215: =IFERROR(F215+forecast.ets.confint($A215,$B$200:$B$287,$A$200:$A$287,0.95,4,1,1),"") | J215: 2023 | K215: =IFERROR(INDEX($B$200:$B$287,MATCH(DATE(J215,10,1),$A$200:$A$287,0)),"") | L215: =IFERROR(K215/K214-1,"") | M215: =IFERROR(INDEX($F$200:$F$287,MATCH(DATE(J215,10,1),$A$200:$A$287,0)),"")
... A221: 41365 | B221: =IFERROR(haverdata(Codes!$D$13,$A221),"") | C221: =IFERROR(B221/B220-1,"") | D221: =IFERROR(B221/B217-1,"") | E221: =IFERROR(IF(B221="",IFERROR(GROWTH($B$200:$B$287,$A$200:$A$287,$A221),TREND($B$200:$B$287,$A$200:$A$287,$A221)),""),"") | F221: =IFERROR(forecast.ets($A221,$B$200:$B$287,$A$200:$A$287,4,1,1),"") | G221: =IFERROR(F221-forecast.ets.confint($A221,$B$200:$B$287,$A$200:$A$287,0.95,4,1,1),"") | H221: =IFERROR(F221+forecast.ets.confint($A221,$B$200:$B$287,$A$200:$A$287,0.95,4,1,1),"") | J221: 2029 | K221: =IFERROR(INDEX($B$200:$B$287,MATCH(DATE(J221,10,1),$A$200:$A$287,0)),"") | L221: =IFERROR(K221/K220-1,"") | M221: =IFERROR(INDEX($F$200:$F$287,MATCH(DATE(J221,10,1),$A$200:$A$287,0)),"")
A222: 41456 | B222: =IFERROR(haverdata(Codes!$D$13,$A222),"") | C222: =IFERROR(B222/B221-1,"") | D222: =IFERROR(B222/B218-1,"") | E222: =IFERROR(IF(B222="",IFERROR(GROWTH($B$200:$B$287,$A$200:$A$287,$A222),TREND($B$200:$B$287,$A$200:$A$287,$A222)),""),"") | F222: =IFERROR(forecast.ets($A222,$B$200:$B$287,$A$200:$A$287,4,1,1),"") | G222: =IFERROR(F222-forecast.ets.confint($A222,$B$200:$B$287,$A$200:$A$287,0.95,4,1,1),"") | H222: =IFERROR(F222+forecast.ets.confint($A222,$B$200:$B$287,$A$200:$A$287,0.95,4,1,1),"")
A223: 41548 | B223: =IFERROR(haverdata(Codes!$D$13,$A223),"") | C223: =IFERROR(B223/B222-1,"") | D223: =IFERROR(B223/B219-1,"") | E223: =IFERROR(IF(B223="",IFERROR(GROWTH($B$200:$B$287,$A$200:$A$287,$A223),TREND($B$200:$B$287,$A$200:$A$287,$A223)),""),"") | F223: =IFERROR(forecast.ets($A223,$B$200:$B$287,$A$200:$A$287,4,1,1),"") | G223: =IFERROR(F223-forecast.ets.confint($A223,$B$200:$B$287,$A$200:$A$287,0.95,4,1,1),"") | H223: =IFERROR(F223+forecast.ets.confint($A223,$B$200:$B$287,$A$200:$A$287,0.95,4,1,1),"")
A224: 41640 | B224: =IFERROR(haverdata(Codes!$D$13,$A224),"") | C224: =IFERROR(B224/B223-1,"") | D224: =IFERROR(B224/B220-1,"") | E224: =IFERROR(IF(B224="",IFERROR(GROWTH($B$200:$B$287,$A$200:$A$287,$A224),TREND($B$200:$B$287,$A$200:$A$287,$A224)),""),"") | F224: =IFERROR(forecast.ets($A224,$B$200:$B$287,$A$200:$A$287,4,1,1),"") | G224: =IFERROR(F224-forecast.ets.confint($A224,$B$200:$B$287,$A$200:$A$287,0.95,4,1,1),"") | H224: =IFERROR(F224+forecast.ets.confint($A224,$B$200:$B$287,$A$200:$A$287,0.95,4,1,1),"")
A225: 41730 | B225: =IFERROR(haverdata(Codes!$D$13,$A225),"") | C225: =IFERROR(B225/B224-1,"") | D225: =IFERROR(B225/B221-1,"") | E225: =IFERROR(IF(B225="",IFERROR(GROWTH($B$200:$B$287,$A$200:$A$287,$A225),TREND($B$200:$B$287,$A$200:$A$287,$A225)),""),"") | F225: =IFERROR(forecast.ets($A225,$B$200:$B$287,$A$200:$A$287,4,1,1),"") | G225: =IFERROR(F225-forecast.ets.confint($A225,$B$200:$B$287,$A$200:$A$287,0.95,4,1,1),"") | H225: =IFERROR(F225+forecast.ets.confint($A225,$B$200:$B$287,$A$200:$A$287,0.95,4,1,1),"")
A226: 41821 | B226: =IFERROR(haverdata(Codes!$D$13,$A226),"") | C226: =IFERROR(B226/B225-1,"") | D226: =IFERROR(B226/B222-1,"") | E226: =IFERROR(IF(B226="",IFERROR(GROWTH($B$200:$B$287,$A$200:$A$287,$A226),TREND($B$200:$B$287,$A$200:$A$287,$A226)),""),"") | F226: =IFERROR(forecast.ets($A226,$B$200:$B$287,$A$200:$A$287,4,1,1),"") | G226: =IFERROR(F226-forecast.ets.confint($A226,$B$200:$B$287,$A$200:$A$287,0.95,4,1,1),"") | H226: =IFERROR(F226+forecast.ets.confint($A226,$B$200:$B$287,$A$200:$A$287,0.95,4,1,1),"")
A227: 41913 | B227: =IFERROR(haverdata(Codes!$D$13,$A227),"") | C227: =IFERROR(B227/B226-1,"") | D227: =IFERROR(B227/B223-1,"") | E227: =IFERROR(IF(B227="",IFERROR(GROWTH($B$200:$B$287,$A$200:$A$287,$A227),TREND($B$200:$B$287,$A$200:$A$287,$A227)),""),"") | F227: =IFERROR(forecast.ets($A227,$B$200:$B$287,$A$200:$A$287,4,1,1),"") | G227: =IFERROR(F227-forecast.ets.confint($A227,$B$200:$B$287,$A$200:$A$287,0.95,4,1,1),"") | H227: =IFERROR(F227+forecast.ets.confint($A227,$B$200:$B$287,$A$200:$A$287,0.95,4,1,1),"")
A228: 42005 | B228: =IFERROR(haverdata(Codes!$D$13,$A228),"") | C228: =IFERROR(B228/B227-1,"") | D228: =IFERROR(B228/B224-1,"") | E228: =IFERROR(IF(B228="",IFERROR(GROWTH($B$200:$B$287,$A$200:$A$287,$A228),TREND($B$200:$B$287,$A$200:$A$287,$A228)),""),"") | F228: =IFERROR(forecast.ets($A228,$B$200:$B$287,$A$200:$A$287,4,1,1),"") | G228: =IFERROR(F228-forecast.ets.confint($A228,$B$200:$B$287,$A$200:$A$287,0.95,4,1,1),"") | H228: =IFERROR(F228+forecast.ets.confint($A228,$B$200:$B$287,$A$200:$A$287,0.95,4,1,1),"")
A229: 42095 | B229: =IFERROR(haverdata(Codes!$D$13,$A229),"") | C229: =IFERROR(B229/B228-1,"") | D229: =IFERROR(B229/B225-1,"") | E229: =IFERROR(IF(B229="",IFERROR(GROWTH($B$200:$B$287,$A$200:$A$287,$A229),TREND($B$200:$B$287,$A$200:$A$287,$A229)),""),"") | F229: =IFERROR(forecast.ets($A229,$B$200:$B$287,$A$200:$A$287,4,1,1),"") | G229: =IFERROR(F229-forecast.ets.confint($A229,$B$200:$B$287,$A$200:$A$287,0.95,4,1,1),"") | H229: =IFERROR(F229+forecast.ets.confint($A229,$B$200:$B$287,$A$200:$A$287,0.95,4,1,1),"")
A230: 42186 | B230: =IFERROR(haverdata(Codes!$D$13,$A230),"") | C230: =IFERROR(B230/B229-1,"") | D230: =IFERROR(B230/B226-1,"") | E230: =IFERROR(IF(B230="",IFERROR(GROWTH($B$200:$B$287,$A$200:$A$287,$A230),TREND($B$200:$B$287,$A$200:$A$287,$A230)),""),"") | F230: =IFERROR(forecast.ets($A230,$B$200:$B$287,$A$200:$A$287,4,1,1),"") | G230: =IFERROR(F230-forecast.ets.confint($A230,$B$200:$B$287,$A$200:$A$287,0.95,4,1,1),"") | H230: =IFERROR(F230+forecast.ets.confint($A230,$B$200:$B$287,$A$200:$A$287,0.95,4,1,1),"")
...

Sheet BoP
A1: BoP — Argentina
A2: Each block: live HaverData pulls (col B) → growth metrics → TREND + FORECAST.ETS forecasts → chart.
A4: =Codes!$B$14&" ["&Codes!$D$14&"] "&Codes!$F$14 -> Current Account Balance [S213NCABA@LATAM] USD Mn
A5: Aggregation: | B5: =Codes!$G$14 -> sum | D5: Notes: | E5: =Codes!$H$14 -> INDEC / BCRA. [VERIFY]
A6: Quarterly | J6: Annual
A7: Date | B7: Level | C7: QoQ % | D7: YoY % | E7: Linear Fcst | F7: ETS Fcst | G7: ETS Low 95% | H7: ETS High 95% | J7: Year | K7: Level | L7: YoY % | M7: Forecast
A8: 39448 | B8: =IFERROR(haverdata(Codes!$D$14,$A8),"") | E8: =IFERROR(IF(B8="",IFERROR(GROWTH($B$8:$B$95,$A$8:$A$95,$A8),TREND($B$8:$B$95,$A$8:$A$95,$A8)),""),"") | F8: =IFERROR(forecast.ets($A8,$B$8:$B$95,$A$8:$A$95,4,1,1),"") | G8: =IFERROR(F8-forecast.ets.confint($A8,$B$8:$B$95,$A$8:$A$95,0.95,4,1,1),"") | H8: =IFERROR(F8+forecast.ets.confint($A8,$B$8:$B$95,$A$8:$A$95,0.95,4,1,1),"") | J8: 2008 | K8: =IFERROR(SUMIFS($B$8:$B$95,$A$8:$A$95,">="&DATE(J8,1,1),$A$8:$A$95,"<="&DATE(J8,12,31)),"") -> 0 | M8: =IFERROR(SUMIFS($F$8:$F$95,$A$8:$A$95,">="&DATE(J8,1,1),$A$8:$A$95,"<="&DATE(J8,12,31)),"") -> 0
A9: 39539 | B9: =IFERROR(haverdata(Codes!$D$14,$A9),"") | C9: =IFERROR(B9/B8-1,"") | E9: =IFERROR(IF(B9="",IFERROR(GROWTH($B$8:$B$95,$A$8:$A$95,$A9),TREND($B$8:$B$95,$A$8:$A$95,$A9)),""),"") | F9: =IFERROR(forecast.ets($A9,$B$8:$B$95,$A$8:$A$95,4,1,1),"") | G9: =IFERROR(F9-forecast.ets.confint($A9,$B$8:$B$95,$A$8:$A$95,0.95,4,1,1),"") | H9: =IFERROR(F9+forecast.ets.confint($A9,$B$8:$B$95,$A$8:$A$95,0.95,4,1,1),"") | J9: 2009 | K9: =IFERROR(SUMIFS($B$8:$B$95,$A$8:$A$95,">="&DATE(J9,1,1),$A$8:$A$95,"<="&DATE(J9,12,31)),"") -> 0 | L9: =IFERROR(K9/K8-1,"") | M9: =IFERROR(SUMIFS($F$8:$F$95,$A$8:$A$95,">="&DATE(J9,1,1),$A$8:$A$95,"<="&DATE(J9,12,31)),"") -> 0
A10: 39630 | B10: =IFERROR(haverdata(Codes!$D$14,$A10),"") | C10: =IFERROR(B10/B9-1,"") | E10: =IFERROR(IF(B10="",IFERROR(GROWTH($B$8:$B$95,$A$8:$A$95,$A10),TREND($B$8:$B$95,$A$8:$A$95,$A10)),""),"") | F10: =IFERROR(forecast.ets($A10,$B$8:$B$95,$A$8:$A$95,4,1,1),"") | G10: =IFERROR(F10-forecast.ets.confint($A10,$B$8:$B$95,$A$8:$A$95,0.95,4,1,1),"") | H10: =IFERROR(F10+forecast.ets.confint($A10,$B$8:$B$95,$A$8:$A$95,0.95,4,1,1),"") | J10: 2010 | K10: =IFERROR(SUMIFS($B$8:$B$95,$A$8:$A$95,">="&DATE(J10,1,1),$A$8:$A$95,"<="&DATE(J10,12,31)),"") -> 0 | L10: =IFERROR(K10/K9-1,"") | M10: =IFERROR(SUMIFS($F$8:$F$95,$A$8:$A$95,">="&DATE(J10,1,1),$A$8:$A$95,"<="&DATE(J10,12,31)),"") -> 0
A11: 39722 | B11: =IFERROR(haverdata(Codes!$D$14,$A11),"") | C11: =IFERROR(B11/B10-1,"") | E11: =IFERROR(IF(B11="",IFERROR(GROWTH($B$8:$B$95,$A$8:$A$95,$A11),TREND($B$8:$B$95,$A$8:$A$95,$A11)),""),"") | F11: =IFERROR(forecast.ets($A11,$B$8:$B$95,$A$8:$A$95,4,1,1),"") | G11: =IFERROR(F11-forecast.ets.confint($A11,$B$8:$B$95,$A$8:$A$95,0.95,4,1,1),"") | H11: =IFERROR(F11+forecast.ets.confint($A11,$B$8:$B$95,$A$8:$A$95,0.95,4,1,1),"") | J11: 2011 | K11: =IFERROR(SUMIFS($B$8:$B$95,$A$8:$A$95,">="&DATE(J11,1,1),$A$8:$A$95,"<="&DATE(J11,12,31)),"") -> 0 | L11: =IFERROR(K11/K10-1,"") | M11: =IFERROR(SUMIFS($F$8:$F$95,$A$8:$A$95,">="&DATE(J11,1,1),$A$8:$A$95,"<="&DATE(J11,12,31)),"") -> 0
A12: 39814 | B12: =IFERROR(haverdata(Codes!$D$14,$A12),"") | C12: =IFERROR(B12/B11-1,"") | D12: =IFERROR(B12/B8-1,"") | E12: =IFERROR(IF(B12="",IFERROR(GROWTH($B$8:$B$95,$A$8:$A$95,$A12),TREND($B$8:$B$95,$A$8:$A$95,$A12)),""),"") | F12: =IFERROR(forecast.ets($A12,$B$8:$B$95,$A$8:$A$95,4,1,1),"") | G12: =IFERROR(F12-forecast.ets.confint($A12,$B$8:$B$95,$A$8:$A$95,0.95,4,1,1),"") | H12: =IFERROR(F12+forecast.ets.confint($A12,$B$8:$B$95,$A$8:$A$95,0.95,4,1,1),"") | J12: 2012 | K12: =IFERROR(SUMIFS($B$8:$B$95,$A$8:$A$95,">="&DATE(J12,1,1),$A$8:$A$95,"<="&DATE(J12,12,31)),"") -> 0 | L12: =IFERROR(K12/K11-1,"") | M12: =IFERROR(SUMIFS($F$8:$F$95,$A$8:$A$95,">="&DATE(J12,1,1),$A$8:$A$95,"<="&DATE(J12,12,31)),"") -> 0
A13: 39904 | B13: =IFERROR(haverdata(Codes!$D$14,$A13),"") | C13: =IFERROR(B13/B12-1,"") | D13: =IFERROR(B13/B9-1,"") | E13: =IFERROR(IF(B13="",IFERROR(GROWTH($B$8:$B$95,$A$8:$A$95,$A13),TREND($B$8:$B$95,$A$8:$A$95,$A13)),""),"") | F13: =IFERROR(forecast.ets($A13,$B$8:$B$95,$A$8:$A$95,4,1,1),"") | G13: =IFERROR(F13-forecast.ets.confint($A13,$B$8:$B$95,$A$8:$A$95,0.95,4,1,1),"") | H13: =IFERROR(F13+forecast.ets.confint($A13,$B$8:$B$95,$A$8:$A$95,0.95,4,1,1),"") | J13: 2013 | K13: =IFERROR(SUMIFS($B$8:$B$95,$A$8:$A$95,">="&DATE(J13,1,1),$A$8:$A$95,"<="&DATE(J13,12,31)),"") -> 0 | L13: =IFERROR(K13/K12-1,"") | M13: =IFERROR(SUMIFS($F$8:$F$95,$A$8:$A$95,">="&DATE(J13,1,1),$A$8:$A$95,"<="&DATE(J13,12,31)),"") -> 0
A14: 39995 | B14: =IFERROR(haverdata(Codes!$D$14,$A14),"") | C14: =IFERROR(B14/B13-1,"") | D14: =IFERROR(B14/B10-1,"") | E14: =IFERROR(IF(B14="",IFERROR(GROWTH($B$8:$B$95,$A$8:$A$95,$A14),TREND($B$8:$B$95,$A$8:$A$95,$A14)),""),"") | F14: =IFERROR(forecast.ets($A14,$B$8:$B$95,$A$8:$A$95,4,1,1),"") | G14: =IFERROR(F14-forecast.ets.confint($A14,$B$8:$B$95,$A$8:$A$95,0.95,4,1,1),"") | H14: =IFERROR(F14+forecast.ets.confint($A14,$B$8:$B$95,$A$8:$A$95,0.95,4,1,1),"") | J14: 2014 | K14: =IFERROR(SUMIFS($B$8:$B$95,$A$8:$A$95,">="&DATE(J14,1,1),$A$8:$A$95,"<="&DATE(J14,12,31)),"") -> 0 | L14: =IFERROR(K14/K13-1,"") | M14: =IFERROR(SUMIFS($F$8:$F$95,$A$8:$A$95,">="&DATE(J14,1,1),$A$8:$A$95,"<="&DATE(J14,12,31)),"") -> 0
A15: 40087 | B15: =IFERROR(haverdata(Codes!$D$14,$A15),"") | C15: =IFERROR(B15/B14-1,"") | D15: =IFERROR(B15/B11-1,"") | E15: =IFERROR(IF(B15="",IFERROR(GROWTH($B$8:$B$95,$A$8:$A$95,$A15),TREND($B$8:$B$95,$A$8:$A$95,$A15)),""),"") | F15: =IFERROR(forecast.ets($A15,$B$8:$B$95,$A$8:$A$95,4,1,1),"") | G15: =IFERROR(F15-forecast.ets.confint($A15,$B$8:$B$95,$A$8:$A$95,0.95,4,1,1),"") | H15: =IFERROR(F15+forecast.ets.confint($A15,$B$8:$B$95,$A$8:$A$95,0.95,4,1,1),"") | J15: 2015 | K15: =IFERROR(SUMIFS($B$8:$B$95,$A$8:$A$95,">="&DATE(J15,1,1),$A$8:$A$95,"<="&DATE(J15,12,31)),"") -> 0 | L15: =IFERROR(K15/K14-1,"") | M15: =IFERROR(SUMIFS($F$8:$F$95,$A$8:$A$95,">="&DATE(J15,1,1),$A$8:$A$95,"<="&DATE(J15,12,31)),"") -> 0
A16: 40179 | B16: =IFERROR(haverdata(Codes!$D$14,$A16),"") | C16: =IFERROR(B16/B15-1,"") | D16: =IFERROR(B16/B12-1,"") | E16: =IFERROR(IF(B16="",IFERROR(GROWTH($B$8:$B$95,$A$8:$A$95,$A16),TREND($B$8:$B$95,$A$8:$A$95,$A16)),""),"") | F16: =IFERROR(forecast.ets($A16,$B$8:$B$95,$A$8:$A$95,4,1,1),"") | G16: =IFERROR(F16-forecast.ets.confint($A16,$B$8:$B$95,$A$8:$A$95,0.95,4,1,1),"") | H16: =IFERROR(F16+forecast.ets.confint($A16,$B$8:$B$95,$A$8:$A$95,0.95,4,1,1),"") | J16: 2016 | K16: =IFERROR(SUMIFS($B$8:$B$95,$A$8:$A$95,">="&DATE(J16,1,1),$A$8:$A$95,"<="&DATE(J16,12,31)),"") -> 0 | L16: =IFERROR(K16/K15-1,"") | M16: =IFERROR(SUMIFS($F$8:$F$95,$A$8:$A$95,">="&DATE(J16,1,1),$A$8:$A$95,"<="&DATE(J16,12,31)),"") -> 0
A17: 40269 | B17: =IFERROR(haverdata(Codes!$D$14,$A17),"") | C17: =IFERROR(B17/B16-1,"") | D17: =IFERROR(B17/B13-1,"") | E17: =IFERROR(IF(B17="",IFERROR(GROWTH($B$8:$B$95,$A$8:$A$95,$A17),TREND($B$8:$B$95,$A$8:$A$95,$A17)),""),"") | F17: =IFERROR(forecast.ets($A17,$B$8:$B$95,$A$8:$A$95,4,1,1),"") | G17: =IFERROR(F17-forecast.ets.confint($A17,$B$8:$B$95,$A$8:$A$95,0.95,4,1,1),"") | H17: =IFERROR(F17+forecast.ets.confint($A17,$B$8:$B$95,$A$8:$A$95,0.95,4,1,1),"") | J17: 2017 | K17: =IFERROR(SUMIFS($B$8:$B$95,$A$8:$A$95,">="&DATE(J17,1,1),$A$8:$A$95,"<="&DATE(J17,12,31)),"") -> 0 | L17: =IFERROR(K17/K16-1,"") | M17: =IFERROR(SUMIFS($F$8:$F$95,$A$8:$A$95,">="&DATE(J17,1,1),$A$8:$A$95,"<="&DATE(J17,12,31)),"") -> 0
A18: 40360 | B18: =IFERROR(haverdata(Codes!$D$14,$A18),"") | C18: =IFERROR(B18/B17-1,"") | D18: =IFERROR(B18/B14-1,"") | E18: =IFERROR(IF(B18="",IFERROR(GROWTH($B$8:$B$95,$A$8:$A$95,$A18),TREND($B$8:$B$95,$A$8:$A$95,$A18)),""),"") | F18: =IFERROR(forecast.ets($A18,$B$8:$B$95,$A$8:$A$95,4,1,1),"") | G18: =IFERROR(F18-forecast.ets.confint($A18,$B$8:$B$95,$A$8:$A$95,0.95,4,1,1),"") | H18: =IFERROR(F18+forecast.ets.confint($A18,$B$8:$B$95,$A$8:$A$95,0.95,4,1,1),"") | J18: 2018 | K18: =IFERROR(SUMIFS($B$8:$B$95,$A$8:$A$95,">="&DATE(J18,1,1),$A$8:$A$95,"<="&DATE(J18,12,31)),"") -> 0 | L18: =IFERROR(K18/K17-1,"") | M18: =IFERROR(SUMIFS($F$8:$F$95,$A$8:$A$95,">="&DATE(J18,1,1),$A$8:$A$95,"<="&DATE(J18,12,31)),"") -> 0
A19: 40452 | B19: =IFERROR(haverdata(Codes!$D$14,$A19),"") | C19: =IFERROR(B19/B18-1,"") | D19: =IFERROR(B19/B15-1,"") | E19: =IFERROR(IF(B19="",IFERROR(GROWTH($B$8:$B$95,$A$8:$A$95,$A19),TREND($B$8:$B$95,$A$8:$A$95,$A19)),""),"") | F19: =IFERROR(forecast.ets($A19,$B$8:$B$95,$A$8:$A$95,4,1,1),"") | G19: =IFERROR(F19-forecast.ets.confint($A19,$B$8:$B$95,$A$8:$A$95,0.95,4,1,1),"") | H19: =IFERROR(F19+forecast.ets.confint($A19,$B$8:$B$95,$A$8:$A$95,0.95,4,1,1),"") | J19: 2019 | K19: =IFERROR(SUMIFS($B$8:$B$95,$A$8:$A$95,">="&DATE(J19,1,1),$A$8:$A$95,"<="&DATE(J19,12,31)),"") -> 0 | L19: =IFERROR(K19/K18-1,"") | M19: =IFERROR(SUMIFS($F$8:$F$95,$A$8:$A$95,">="&DATE(J19,1,1),$A$8:$A$95,"<="&DATE(J19,12,31)),"") -> 0
A20: 40544 | B20: =IFERROR(haverdata(Codes!$D$14,$A20),"") | C20: =IFERROR(B20/B19-1,"") | D20: =IFERROR(B20/B16-1,"") | E20: =IFERROR(IF(B20="",IFERROR(GROWTH($B$8:$B$95,$A$8:$A$95,$A20),TREND($B$8:$B$95,$A$8:$A$95,$A20)),""),"") | F20: =IFERROR(forecast.ets($A20,$B$8:$B$95,$A$8:$A$95,4,1,1),"") | G20: =IFERROR(F20-forecast.ets.confint($A20,$B$8:$B$95,$A$8:$A$95,0.95,4,1,1),"") | H20: =IFERROR(F20+forecast.ets.confint($A20,$B$8:$B$95,$A$8:$A$95,0.95,4,1,1),"") | J20: 2020 | K20: =IFERROR(SUMIFS($B$8:$B$95,$A$8:$A$95,">="&DATE(J20,1,1),$A$8:$A$95,"<="&DATE(J20,12,31)),"") -> 0 | L20: =IFERROR(K20/K19-1,"") | M20: =IFERROR(SUMIFS($F$8:$F$95,$A$8:$A$95,">="&DATE(J20,1,1),$A$8:$A$95,"<="&DATE(J20,12,31)),"") -> 0
A21: 40634 | B21: =IFERROR(haverdata(Codes!$D$14,$A21),"") | C21: =IFERROR(B21/B20-1,"") | D21: =IFERROR(B21/B17-1,"") | E21: =IFERROR(IF(B21="",IFERROR(GROWTH($B$8:$B$95,$A$8:$A$95,$A21),TREND($B$8:$B$95,$A$8:$A$95,$A21)),""),"") | F21: =IFERROR(forecast.ets($A21,$B$8:$B$95,$A$8:$A$95,4,1,1),"") | G21: =IFERROR(F21-forecast.ets.confint($A21,$B$8:$B$95,$A$8:$A$95,0.95,4,1,1),"") | H21: =IFERROR(F21+forecast.ets.confint($A21,$B$8:$B$95,$A$8:$A$95,0.95,4,1,1),"") | J21: 2021 | K21: =IFERROR(SUMIFS($B$8:$B$95,$A$8:$A$95,">="&DATE(J21,1,1),$A$8:$A$95,"<="&DATE(J21,12,31)),"") -> 0 | L21: =IFERROR(K21/K20-1,"") | M21: =IFERROR(SUMIFS($F$8:$F$95,$A$8:$A$95,">="&DATE(J21,1,1),$A$8:$A$95,"<="&DATE(J21,12,31)),"") -> 0
A22: 40725 | B22: =IFERROR(haverdata(Codes!$D$14,$A22),"") | C22: =IFERROR(B22/B21-1,"") | D22: =IFERROR(B22/B18-1,"") | E22: =IFERROR(IF(B22="",IFERROR(GROWTH($B$8:$B$95,$A$8:$A$95,$A22),TREND($B$8:$B$95,$A$8:$A$95,$A22)),""),"") | F22: =IFERROR(forecast.ets($A22,$B$8:$B$95,$A$8:$A$95,4,1,1),"") | G22: =IFERROR(F22-forecast.ets.confint($A22,$B$8:$B$95,$A$8:$A$95,0.95,4,1,1),"") | H22: =IFERROR(F22+forecast.ets.confint($A22,$B$8:$B$95,$A$8:$A$95,0.95,4,1,1),"") | J22: 2022 | K22: =IFERROR(SUMIFS($B$8:$B$95,$A$8:$A$95,">="&DATE(J22,1,1),$A$8:$A$95,"<="&DATE(J22,12,31)),"") -> 0 | L22: =IFERROR(K22/K21-1,"") | M22: =IFERROR(SUMIFS($F$8:$F$95,$A$8:$A$95,">="&DATE(J22,1,1),$A$8:$A$95,"<="&DATE(J22,12,31)),"") -> 0
A23: 40817 | B23: =IFERROR(haverdata(Codes!$D$14,$A23),"") | C23: =IFERROR(B23/B22-1,"") | D23: =IFERROR(B23/B19-1,"") | E23: =IFERROR(IF(B23="",IFERROR(GROWTH($B$8:$B$95,$A$8:$A$95,$A23),TREND($B$8:$B$95,$A$8:$A$95,$A23)),""),"") | F23: =IFERROR(forecast.ets($A23,$B$8:$B$95,$A$8:$A$95,4,1,1),"") | G23: =IFERROR(F23-forecast.ets.confint($A23,$B$8:$B$95,$A$8:$A$95,0.95,4,1,1),"") | H23: =IFERROR(F23+forecast.ets.confint($A23,$B$8:$B$95,$A$8:$A$95,0.95,4,1,1),"") | J23: 2023 | K23: =IFERROR(SUMIFS($B$8:$B$95,$A$8:$A$95,">="&DATE(J23,1,1),$A$8:$A$95,"<="&DATE(J23,12,31)),"") -> 0 | L23: =IFERROR(K23/K22-1,"") | M23: =IFERROR(SUMIFS($F$8:$F$95,$A$8:$A$95,">="&DATE(J23,1,1),$A$8:$A$95,"<="&DATE(J23,12,31)),"") -> 0
... A29: 41365 | B29: =IFERROR(haverdata(Codes!$D$14,$A29),"") | C29: =IFERROR(B29/B28-1,"") | D29: =IFERROR(B29/B25-1,"") | E29: =IFERROR(IF(B29="",IFERROR(GROWTH($B$8:$B$95,$A$8:$A$95,$A29),TREND($B$8:$B$95,$A$8:$A$95,$A29)),""),"") | F29: =IFERROR(forecast.ets($A29,$B$8:$B$95,$A$8:$A$95,4,1,1),"") | G29: =IFERROR(F29-forecast.ets.confint($A29,$B$8:$B$95,$A$8:$A$95,0.95,4,1,1),"") | H29: =IFERROR(F29+forecast.ets.confint($A29,$B$8:$B$95,$A$8:$A$95,0.95,4,1,1),"") | J29: 2029 | K29: =IFERROR(SUMIFS($B$8:$B$95,$A$8:$A$95,">="&DATE(J29,1,1),$A$8:$A$95,"<="&DATE(J29,12,31)),"") -> 0 | L29: =IFERROR(K29/K28-1,"") | M29: =IFERROR(SUMIFS($F$8:$F$95,$A$8:$A$95,">="&DATE(J29,1,1),$A$8:$A$95,"<="&DATE(J29,12,31)),"") -> 0
A30: 41456 | B30: =IFERROR(haverdata(Codes!$D$14,$A30),"") | C30: =IFERROR(B30/B29-1,"") | D30: =IFERROR(B30/B26-1,"") | E30: =IFERROR(IF(B30="",IFERROR(GROWTH($B$8:$B$95,$A$8:$A$95,$A30),TREND($B$8:$B$95,$A$8:$A$95,$A30)),""),"") | F30: =IFERROR(forecast.ets($A30,$B$8:$B$95,$A$8:$A$95,4,1,1),"") | G30: =IFERROR(F30-forecast.ets.confint($A30,$B$8:$B$95,$A$8:$A$95,0.95,4,1,1),"") | H30: =IFERROR(F30+forecast.ets.confint($A30,$B$8:$B$95,$A$8:$A$95,0.95,4,1,1),"")
A31: 41548 | B31: =IFERROR(haverdata(Codes!$D$14,$A31),"") | C31: =IFERROR(B31/B30-1,"") | D31: =IFERROR(B31/B27-1,"") | E31: =IFERROR(IF(B31="",IFERROR(GROWTH($B$8:$B$95,$A$8:$A$95,$A31),TREND($B$8:$B$95,$A$8:$A$95,$A31)),""),"") | F31: =IFERROR(forecast.ets($A31,$B$8:$B$95,$A$8:$A$95,4,1,1),"") | G31: =IFERROR(F31-forecast.ets.confint($A31,$B$8:$B$95,$A$8:$A$95,0.95,4,1,1),"") | H31: =IFERROR(F31+forecast.ets.confint($A31,$B$8:$B$95,$A$8:$A$95,0.95,4,1,1),"")
A32: 41640 | B32: =IFERROR(haverdata(Codes!$D$14,$A32),"") | C32: =IFERROR(B32/B31-1,"") | D32: =IFERROR(B32/B28-1,"") | E32: =IFERROR(IF(B32="",IFERROR(GROWTH($B$8:$B$95,$A$8:$A$95,$A32),TREND($B$8:$B$95,$A$8:$A$95,$A32)),""),"") | F32: =IFERROR(forecast.ets($A32,$B$8:$B$95,$A$8:$A$95,4,1,1),"") | G32: =IFERROR(F32-forecast.ets.confint($A32,$B$8:$B$95,$A$8:$A$95,0.95,4,1,1),"") | H32: =IFERROR(F32+forecast.ets.confint($A32,$B$8:$B$95,$A$8:$A$95,0.95,4,1,1),"")
A33: 41730 | B33: =IFERROR(haverdata(Codes!$D$14,$A33),"") | C33: =IFERROR(B33/B32-1,"") | D33: =IFERROR(B33/B29-1,"") | E33: =IFERROR(IF(B33="",IFERROR(GROWTH($B$8:$B$95,$A$8:$A$95,$A33),TREND($B$8:$B$95,$A$8:$A$95,$A33)),""),"") | F33: =IFERROR(forecast.ets($A33,$B$8:$B$95,$A$8:$A$95,4,1,1),"") | G33: =IFERROR(F33-forecast.ets.confint($A33,$B$8:$B$95,$A$8:$A$95,0.95,4,1,1),"") | H33: =IFERROR(F33+forecast.ets.confint($A33,$B$8:$B$95,$A$8:$A$95,0.95,4,1,1),"")
A34: 41821 | B34: =IFERROR(haverdata(Codes!$D$14,$A34),"") | C34: =IFERROR(B34/B33-1,"") | D34: =IFERROR(B34/B30-1,"") | E34: =IFERROR(IF(B34="",IFERROR(GROWTH($B$8:$B$95,$A$8:$A$95,$A34),TREND($B$8:$B$95,$A$8:$A$95,$A34)),""),"") | F34: =IFERROR(forecast.ets($A34,$B$8:$B$95,$A$8:$A$95,4,1,1),"") | G34: =IFERROR(F34-forecast.ets.confint($A34,$B$8:$B$95,$A$8:$A$95,0.95,4,1,1),"") | H34: =IFERROR(F34+forecast.ets.confint($A34,$B$8:$B$95,$A$8:$A$95,0.95,4,1,1),"")
A35: 41913 | B35: =IFERROR(haverdata(Codes!$D$14,$A35),"") | C35: =IFERROR(B35/B34-1,"") | D35: =IFERROR(B35/B31-1,"") | E35: =IFERROR(IF(B35="",IFERROR(GROWTH($B$8:$B$95,$A$8:$A$95,$A35),TREND($B$8:$B$95,$A$8:$A$95,$A35)),""),"") | F35: =IFERROR(forecast.ets($A35,$B$8:$B$95,$A$8:$A$95,4,1,1),"") | G35: =IFERROR(F35-forecast.ets.confint($A35,$B$8:$B$95,$A$8:$A$95,0.95,4,1,1),"") | H35: =IFERROR(F35+forecast.ets.confint($A35,$B$8:$B$95,$A$8:$A$95,0.95,4,1,1),"")
A36: 42005 | B36: =IFERROR(haverdata(Codes!$D$14,$A36),"") | C36: =IFERROR(B36/B35-1,"") | D36: =IFERROR(B36/B32-1,"") | E36: =IFERROR(IF(B36="",IFERROR(GROWTH($B$8:$B$95,$A$8:$A$95,$A36),TREND($B$8:$B$95,$A$8:$A$95,$A36)),""),"") | F36: =IFERROR(forecast.ets($A36,$B$8:$B$95,$A$8:$A$95,4,1,1),"") | G36: =IFERROR(F36-forecast.ets.confint($A36,$B$8:$B$95,$A$8:$A$95,0.95,4,1,1),"") | H36: =IFERROR(F36+forecast.ets.confint($A36,$B$8:$B$95,$A$8:$A$95,0.95,4,1,1),"")
A37: 42095 | B37: =IFERROR(haverdata(Codes!$D$14,$A37),"") | C37: =IFERROR(B37/B36-1,"") | D37: =IFERROR(B37/B33-1,"") | E37: =IFERROR(IF(B37="",IFERROR(GROWTH($B$8:$B$95,$A$8:$A$95,$A37),TREND($B$8:$B$95,$A$8:$A$95,$A37)),""),"") | F37: =IFERROR(forecast.ets($A37,$B$8:$B$95,$A$8:$A$95,4,1,1),"") | G37: =IFERROR(F37-forecast.ets.confint($A37,$B$8:$B$95,$A$8:$A$95,0.95,4,1,1),"") | H37: =IFERROR(F37+forecast.ets.confint($A37,$B$8:$B$95,$A$8:$A$95,0.95,4,1,1),"")
A38: 42186 | B38: =IFERROR(haverdata(Codes!$D$14,$A38),"") | C38: =IFERROR(B38/B37-1,"") | D38: =IFERROR(B38/B34-1,"") | E38: =IFERROR(IF(B38="",IFERROR(GROWTH($B$8:$B$95,$A$8:$A$95,$A38),TREND($B$8:$B$95,$A$8:$A$95,$A38)),""),"") | F38: =IFERROR(forecast.ets($A38,$B$8:$B$95,$A$8:$A$95,4,1,1),"") | G38: =IFERROR(F38-forecast.ets.confint($A38,$B$8:$B$95,$A$8:$A$95,0.95,4,1,1),"") | H38: =IFERROR(F38+forecast.ets.confint($A38,$B$8:$B$95,$A$8:$A$95,0.95,4,1,1),"")
A39: 42278 | B39: =IFERROR(haverdata(Codes!$D$14,$A39),"") | C39: =IFERROR(B39/B38-1,"") | D39: =IFERROR(B39/B35-1,"") | E39: =IFERROR(IF(B39="",IFERROR(GROWTH($B$8:$B$95,$A$8:$A$95,$A39),TREND($B$8:$B$95,$A$8:$A$95,$A39)),""),"") | F39: =IFERROR(forecast.ets($A39,$B$8:$B$95,$A$8:$A$95,4,1,1),"") | G39: =IFERROR(F39-forecast.ets.confint($A39,$B$8:$B$95,$A$8:$A$95,0.95,4,1,1),"") | H39: =IFERROR(F39+forecast.ets.confint($A39,$B$8:$B$95,$A$8:$A$95,0.95,4,1,1),"")
A40: 42370 | B40: =IFERROR(haverdata(Codes!$D$14,$A40),"") | C40: =IFERROR(B40/B39-1,"") | D40: =IFERROR(B40/B36-1,"") | E40: =IFERROR(IF(B40="",IFERROR(GROWTH($B$8:$B$95,$A$8:$A$95,$A40),TREND($B$8:$B$95,$A$8:$A$95,$A40)),""),"") | F40: =IFERROR(forecast.ets($A40,$B$8:$B$95,$A$8:$A$95,4,1,1),"") | G40: =IFERROR(F40-forecast.ets.confint($A40,$B$8:$B$95,$A$8:$A$95,0.95,4,1,1),"") | H40: =IFERROR(F40+forecast.ets.confint($A40,$B$8:$B$95,$A$8:$A$95,0.95,4,1,1),"")
A41: 42461 | B41: =IFERROR(haverdata(Codes!$D$14,$A41),"") | C41: =IFERROR(B41/B40-1,"") | D41: =IFERROR(B41/B37-1,"") | E41: =IFERROR(IF(B41="",IFERROR(GROWTH($B$8:$B$95,$A$8:$A$95,$A41),TREND($B$8:$B$95,$A$8:$A$95,$A41)),""),"") | F41: =IFERROR(forecast.ets($A41,$B$8:$B$95,$A$8:$A$95,4,1,1),"") | G41: =IFERROR(F41-forecast.ets.confint($A41,$B$8:$B$95,$A$8:$A$95,0.95,4,1,1),"") | H41: =IFERROR(F41+forecast.ets.confint($A41,$B$8:$B$95,$A$8:$A$95,0.95,4,1,1),"")
... A95: 47392 | B95: =IFERROR(haverdata(Codes!$D$14,$A95),"") | C95: =IFERROR(B95/B94-1,"") | D95: =IFERROR(B95/B91-1,"") | E95: =IFERROR(IF(B95="",IFERROR(GROWTH($B$8:$B$95,$A$8:$A$95,$A95),TREND($B$8:$B$95,$A$8:$A$95,$A95)),""),"") | F95: =IFERROR(forecast.ets($A95,$B$8:$B$95,$A$8:$A$95,4,1,1),"") | G95: =IFERROR(F95-forecast.ets.confint($A95,$B$8:$B$95,$A$8:$A$95,0.95,4,1,1),"") | H95: =IFERROR(F95+forecast.ets.confint($A95,$B$8:$B$95,$A$8:$A$95,0.95,4,1,1),"")
A100: =Codes!$B$15&" ["&Codes!$D$15&"] "&Codes!$F$15 -> Trade Balance [EXPMP@ARGEN] USD Mn
A101: Aggregation: | B101: =Codes!$G$15 -> sum | D101: Notes: | E101: =Codes!$H$15 -> Exports - imports. [VERIFY]
A102: Quarterly | J102: Annual
A103: Date | B103: Level | C103: QoQ % | D103: YoY % | E103: Linear Fcst | F103: ETS Fcst | G103: ETS Low 95% | H103: ETS High 95% | J103: Year | K103: Level | L103: YoY % | M103: Forecast
A104: 39448 | B104: =IFERROR(haverdata(Codes!$D$15,$A104),"") | E104: =IFERROR(IF(B104="",IFERROR(GROWTH($B$104:$B$191,$A$104:$A$191,$A104),TREND($B$104:$B$191,$A$104:$A$191,$A104)),""),"") | F104: =IFERROR(forecast.ets($A104,$B$104:$B$191,$A$104:$A$191,4,1,1),"") | G104: =IFERROR(F104-forecast.ets.confint($A104,$B$104:$B$191,$A$104:$A$191,0.95,4,1,1),"") | H104: =IFERROR(F104+forecast.ets.confint($A104,$B$104:$B$191,$A$104:$A$191,0.95,4,1,1),"") | J104: 2008 | K104: =IFERROR(SUMIFS($B$104:$B$191,$A$104:$A$191,">="&DATE(J104,1,1),$A$104:$A$191,"<="&DATE(J104,12,31)),"") -> 0 | M104: =IFERROR(SUMIFS($F$104:$F$191,$A$104:$A$191,">="&DATE(J104,1,1),$A$104:$A$191,"<="&DATE(J104,12,31)),"") -> 0
A105: 39539 | B105: =IFERROR(haverdata(Codes!$D$15,$A105),"") | C105: =IFERROR(B105/B104-1,"") | E105: =IFERROR(IF(B105="",IFERROR(GROWTH($B$104:$B$191,$A$104:$A$191,$A105),TREND($B$104:$B$191,$A$104:$A$191,$A105)),""),"") | F105: =IFERROR(forecast.ets($A105,$B$104:$B$191,$A$104:$A$191,4,1,1),"") | G105: =IFERROR(F105-forecast.ets.confint($A105,$B$104:$B$191,$A$104:$A$191,0.95,4,1,1),"") | H105: =IFERROR(F105+forecast.ets.confint($A105,$B$104:$B$191,$A$104:$A$191,0.95,4,1,1),"") | J105: 2009 | K105: =IFERROR(SUMIFS($B$104:$B$191,$A$104:$A$191,">="&DATE(J105,1,1),$A$104:$A$191,"<="&DATE(J105,12,31)),"") -> 0 | L105: =IFERROR(K105/K104-1,"") | M105: =IFERROR(SUMIFS($F$104:$F$191,$A$104:$A$191,">="&DATE(J105,1,1),$A$104:$A$191,"<="&DATE(J105,12,31)),"") -> 0
A106: 39630 | B106: =IFERROR(haverdata(Codes!$D$15,$A106),"") | C106: =IFERROR(B106/B105-1,"") | E106: =IFERROR(IF(B106="",IFERROR(GROWTH($B$104:$B$191,$A$104:$A$191,$A106),TREND($B$104:$B$191,$A$104:$A$191,$A106)),""),"") | F106: =IFERROR(forecast.ets($A106,$B$104:$B$191,$A$104:$A$191,4,1,1),"") | G106: =IFERROR(F106-forecast.ets.confint($A106,$B$104:$B$191,$A$104:$A$191,0.95,4,1,1),"") | H106: =IFERROR(F106+forecast.ets.confint($A106,$B$104:$B$191,$A$104:$A$191,0.95,4,1,1),"") | J106: 2010 | K106: =IFERROR(SUMIFS($B$104:$B$191,$A$104:$A$191,">="&DATE(J106,1,1),$A$104:$A$191,"<="&DATE(J106,12,31)),"") -> 0 | L106: =IFERROR(K106/K105-1,"") | M106: =IFERROR(SUMIFS($F$104:$F$191,$A$104:$A$191,">="&DATE(J106,1,1),$A$104:$A$191,"<="&DATE(J106,12,31)),"") -> 0
A107: 39722 | B107: =IFERROR(haverdata(Codes!$D$15,$A107),"") | C107: =IFERROR(B107/B106-1,"") | E107: =IFERROR(IF(B107="",IFERROR(GROWTH($B$104:$B$191,$A$104:$A$191,$A107),TREND($B$104:$B$191,$A$104:$A$191,$A107)),""),"") | F107: =IFERROR(forecast.ets($A107,$B$104:$B$191,$A$104:$A$191,4,1,1),"") | G107: =IFERROR(F107-forecast.ets.confint($A107,$B$104:$B$191,$A$104:$A$191,0.95,4,1,1),"") | H107: =IFERROR(F107+forecast.ets.confint($A107,$B$104:$B$191,$A$104:$A$191,0.95,4,1,1),"") | J107: 2011 | K107: =IFERROR(SUMIFS($B$104:$B$191,$A$104:$A$191,">="&DATE(J107,1,1),$A$104:$A$191,"<="&DATE(J107,12,31)),"") -> 0 | L107: =IFERROR(K107/K106-1,"") | M107: =IFERROR(SUMIFS($F$104:$F$191,$A$104:$A$191,">="&DATE(J107,1,1),$A$104:$A$191,"<="&DATE(J107,12,31)),"") -> 0
A108: 39814 | B108: =IFERROR(haverdata(Codes!$D$15,$A108),"") | C108: =IFERROR(B108/B107-1,"") | D108: =IFERROR(B108/B104-1,"") | E108: =IFERROR(IF(B108="",IFERROR(GROWTH($B$104:$B$191,$A$104:$A$191,$A108),TREND($B$104:$B$191,$A$104:$A$191,$A108)),""),"") | F108: =IFERROR(forecast.ets($A108,$B$104:$B$191,$A$104:$A$191,4,1,1),"") | G108: =IFERROR(F108-forecast.ets.confint($A108,$B$104:$B$191,$A$104:$A$191,0.95,4,1,1),"") | H108: =IFERROR(F108+forecast.ets.confint($A108,$B$104:$B$191,$A$104:$A$191,0.95,4,1,1),"") | J108: 2012 | K108: =IFERROR(SUMIFS($B$104:$B$191,$A$104:$A$191,">="&DATE(J108,1,1),$A$104:$A$191,"<="&DATE(J108,12,31)),"") -> 0 | L108: =IFERROR(K108/K107-1,"") | M108: =IFERROR(SUMIFS($F$104:$F$191,$A$104:$A$191,">="&DATE(J108,1,1),$A$104:$A$191,"<="&DATE(J108,12,31)),"") -> 0
A109: 39904 | B109: =IFERROR(haverdata(Codes!$D$15,$A109),"") | C109: =IFERROR(B109/B108-1,"") | D109: =IFERROR(B109/B105-1,"") | E109: =IFERROR(IF(B109="",IFERROR(GROWTH($B$104:$B$191,$A$104:$A$191,$A109),TREND($B$104:$B$191,$A$104:$A$191,$A109)),""),"") | F109: =IFERROR(forecast.ets($A109,$B$104:$B$191,$A$104:$A$191,4,1,1),"") | G109: =IFERROR(F109-forecast.ets.confint($A109,$B$104:$B$191,$A$104:$A$191,0.95,4,1,1),"") | H109: =IFERROR(F109+forecast.ets.confint($A109,$B$104:$B$191,$A$104:$A$191,0.95,4,1,1),"") | J109: 2013 | K109: =IFERROR(SUMIFS($B$104:$B$191,$A$104:$A$191,">="&DATE(J109,1,1),$A$104:$A$191,"<="&DATE(J109,12,31)),"") -> 0 | L109: =IFERROR(K109/K108-1,"") | M109: =IFERROR(SUMIFS($F$104:$F$191,$A$104:$A$191,">="&DATE(J109,1,1),$A$104:$A$191,"<="&DATE(J109,12,31)),"") -> 0
A110: 39995 | B110: =IFERROR(haverdata(Codes!$D$15,$A110),"") | C110: =IFERROR(B110/B109-1,"") | D110: =IFERROR(B110/B106-1,"") | E110: =IFERROR(IF(B110="",IFERROR(GROWTH($B$104:$B$191,$A$104:$A$191,$A110),TREND($B$104:$B$191,$A$104:$A$191,$A110)),""),"") | F110: =IFERROR(forecast.ets($A110,$B$104:$B$191,$A$104:$A$191,4,1,1),"") | G110: =IFERROR(F110-forecast.ets.confint($A110,$B$104:$B$191,$A$104:$A$191,0.95,4,1,1),"") | H110: =IFERROR(F110+forecast.ets.confint($A110,$B$104:$B$191,$A$104:$A$191,0.95,4,1,1),"") | J110: 2014 | K110: =IFERROR(SUMIFS($B$104:$B$191,$A$104:$A$191,">="&DATE(J110,1,1),$A$104:$A$191,"<="&DATE(J110,12,31)),"") -> 0 | L110: =IFERROR(K110/K109-1,"") | M110: =IFERROR(SUMIFS($F$104:$F$191,$A$104:$A$191,">="&DATE(J110,1,1),$A$104:$A$191,"<="&DATE(J110,12,31)),"") -> 0
