Workbook

Sheet Read me
B2: Argentina — balance of payments and external funding
B3: INDEC balanza de pagos, BPM6 basis, millions of US dollars. Data through 2026-Q1.
B5: What's in here
B6: Data BoP | C6: All 33 published BPM6 lines, quarterly from 2006. Blue = INDEC source. The identity and build-up check columns must read zero — they are how you know nothing has been mistyped or mis-signed.
B7: Current Account | C7: Every current-account line in three frames: quarterly, four-quarter rolling, and annual. The rolling frame is the one to read — quarterly Argentine BoP is violently seasonal (the harvest lands in Q2) and the annual frame is too slow to trade on.
B8: Financial Account | C8: The same three frames for the financial account, split into direct, portfolio, derivatives, other investment and reserve assets, each further split into what residents did with assets and what non-residents did with liabilities.
B9: Funding | C9: How the current account is actually funded. Reads down from the current account to the change in reserves, showing every source of financing in between. This is the tab that answers what builds and what dents reserves.
B10: % of GDP | C10: The four-quarter rolling frame divided by four-quarter rolling USD GDP. Scale-free, so 2006 and 2026 are comparable.
B11: Reserves | C11: The reserve-asset line on its own: quarterly, rolling, annual, and cumulated since 2006.
B12: Forecast | C12: Bull / base / bear current-account paths for 2026 and 2027, built up from the components, with the assumptions behind each and the IMF projection as a benchmark.
B14: Sign conventions — read this before using any number
B15: Financial account | C15: BPM6 net lending(+) / net borrowing(-). The financial account equals net acquisition of financial assets MINUS net incurrence of liabilities, and reserve assets sit inside it. So a NEGATIVE financial account is a net capital INFLOW. This trips people up constantly; the Funding tab restates everything in inflow-positive terms so you never have to hold it in your head.
B16: Reserve assets | C16: POSITIVE = reserves BUILT. Verified against the known years: 2019 -21,375 and 2023 -21,675 (the two big loss years), 2024 +6,093, 2025 +7,221.
B17: The identity | C17: Current account + capital account - financial account + errors and omissions = 0. It holds to machine precision in 77 of 81 quarters; the four 2016 quarters carry a residual of up to 2.1 that is internal to INDEC's own vintage.
B18: A trap in the source data | C18: The other-investment liabilities series is stored with its sign FLIPPED from Q1-2017 onward, but in natural sign before that. Column AL of the Data tab corrects for it with an explicit date test, and everything downstream uses the corrected column. If you pull this series yourself and assume one sign convention, you will silently corrupt 2006-2016.
B20: Two gaps in what INDEC publishes
B21: Investment income | C21: Investment income does not decompose into direct + portfolio + other. A fourth component — income earned ON reserve assets — is in the total but not published separately. It averages about +88mn a quarter and is always a credit. Column AN backs it out as the residual so the decomposition closes.
B22: Sector detail | C22: INDEC's API does not carry other investment split by sector (central bank, government, banks, other) or by instrument (currency and deposits, loans, trade credit). That detail exists only in the informe tecnico spreadsheets. If you need to see which sector borrowed, that is the source, not this.
B24: Source | C24: INDEC, Balanza de pagos, posicion de inversion internacional y deuda externa, MBP6, quarterly, retrieved from the official series API at apis.datos.gob.ar, dataset 160 (quarterly family 160.2). USD GDP for the ratio tab is INDEC current-price GDP converted at the BCRA Comunicacion "A" 3500 wholesale rate, period average — the same series used in the companion GDP pack.
B25: Validation | C25: Annual current account reproduces INDEC's published figures for 2023 (-22,355), 2024 (+5,891) and 2025 (-7,788), and every quarterly print from Q1-2025 to Q1-2026, to within rounding. Reserve assets reproduce 2019, 2023, 2024 and 2025 exactly. One benchmark did NOT reproduce: 2021 computes to 6,624.8 against a published 6,645 — INDEC has since revised 2021 down by 20.2, so the live series is right and the old print is stale.
B26: Provisional data | C26: INDEC marks everything from 2022 onward as provisional and has revised it more than once. Do not treat the last four years as settled.

Sheet Data BoP
B2: INDEC balance of payments, BPM6 — quarterly source data
B3: Millions of US dollars. Blue = INDEC source value. Black = formula. Check columns must read zero.
B5: Quarter | C5: Year | D5: Q | E5: CURRENT ACCOUNT | F5: Goods & services | G5: Goods balance | H5: Goods exports FOB | I5: Goods imports FOB | J5: Services balance | K5: Services credits | L5: Services debits | M5: Primary income | N5: of which: compensation | O5: Investment income | P5: Income on direct inv. | Q5: Income on portfolio | R5: Income on other inv. | S5: Secondary income | T5: CAPITAL ACCOUNT | U5: FINANCIAL ACCOUNT | V5: Direct inv. total | W5: DI assets equity | X5: DI assets debt | Y5: DI liab. equity | Z5: DI liab. debt | AA5: Portfolio total | AB5: PI assets equity | AC5: PI assets debt | AD5: PI liab. equity | AE5: PI liab. debt | AF5: Financial derivatives | AG5: Other inv. total | AH5: OI assets | AI5: OI liab. (as published) | AJ5: RESERVE ASSETS | AK5: Errors & omissions | AL5: OI liab., sign corrected | AM5: Identity check | AN5: Fin. acct build check | AO5: Income on reserves (resid.) | AP5: Nominal GDP (USD mn, qtr) | AQ5: 4q rolling GDP (USD mn)
B6: 2006-Q1 | C6: 2006 | D6: 1 | E6: 703.26687 | F6: 2691.0759 | G6: 2906.3 | H6: 9945.6 | I6: 7039.3 | J6: -215.22406 | K6: 1945.1375 | L6: 2160.3616 | M6: -2177.7489 | N6: -13.484736 | O6: -2164.2641 | P6: -1542.4722 | Q6: -715.4277 | R6: -85.475302 | S6: 189.93979 | T6: 10.4 | U6: 781.03661 | V6: -1375.7522 | W6: 377.20756 | X6: 0 | Y6: 1469.9598 | Z6: 283 | AA6: -2253.0962 | AB6: 205.538 | AC6: 541.692 | AD6: 247.06557 | AE6: 2753.2606 | AF6: -15.956819 | AG6: 11059.782 | AH6: 587.04922 | AI6: -10472.733 | AJ6: -6633.94 | AK6: 67.369736 | AL6: =IF($C6<2017,AI6,-AI6) -> -10472.733 | AM6: =E6+T6-U6+AK6 -> 0 | AN6: =V6+AA6+AF6+AG6+AJ6-U6 -> 6.3664629e-12 | AO6: =O6-P6-Q6-R6 -> 179.11111 | AP6: 52522.526
B7: 2006-Q2 | C7: 2006 | D7: 2 | E7: 1916.5945 | F7: 3803.208 | G7: 4123.5 | H7: 11980.3 | I7: 7856.8 | J7: -320.29197 | K7: 1712.9188 | L7: 2033.2108 | M7: -2159.0401 | N7: -18.373753 | O7: -2140.6663 | P7: -1514.785 | Q7: -803.74297 | R7: -51.674519 | S7: 272.42649 | T7: 39.9 | U7: 1980.8828 | V7: -672.39111 | W7: 1090.9457 | X7: 0 | Y7: 612.3368 | Z7: 1151 | AA7: -1970.5648 | AB7: -54.226 | AC7: 104.85 | AD7: 110.72396 | AE7: 1910.4648 | AF7: -32.365185 | AG7: 813.19386 | AH7: 224.66308 | AI7: -588.53078 | AJ7: 3843.01 | AK7: 24.388326 | AL7: =IF($C7<2017,AI7,-AI7) -> -588.53078 | AM7: =E7+T7-U7+AK7 -> 4.5119464e-13 | AN7: =V7+AA7+AF7+AG7+AJ7-U7 -> 0 | AO7: =O7-P7-Q7-R7 -> 229.53616 | AP7: 59326.411
B8: 2006-Q3 | C8: 2006 | D8: 3 | E8: 1516.8665 | F8: 2986.876 | G8: 3255.5 | H8: 12126.8 | I8: 8871.3 | J8: -268.62401 | K8: 1898.8544 | L8: 2167.4784 | M8: -1690.7436 | N8: -15.609485 | O8: -1675.1341 | P8: -1220.3751 | Q8: -700.76873 | R8: -27.196085 | S8: 220.73404 | T8: 45.430412 | U8: 1232.3861 | V8: -1116.8668 | W8: 424.95187 | X8: 0 | Y8: 1653.8187 | Z8: -112 | AA8: -802.52817 | AB8: 122.74 | AC8: 59.778 | AD8: 132.1497 | AE8: 852.89648 | AF8: -37.995426 | AG8: 659.8165 | AH8: 421.67896 | AI8: -238.13754 | AJ8: 2529.96 | AK8: -329.91081 | AL8: =IF($C8<2017,AI8,-AI8) -> -238.13754 | AM8: =E8+T8-U8+AK8 -> 0 | AN8: =V8+AA8+AF8+AG8+AJ8-U8 -> 0 | AO8: =O8-P8-Q8-R8 -> 273.20583 | AP8: 59067.254
B9: 2006-Q4 | C9: 2006 | D9: 4 | E9: 2362.0747 | F9: 3785.4826 | G9: 3744.3 | H9: 12564.8 | I9: 8820.5 | J9: 41.182608 | K9: 2354.1044 | L9: 2312.9218 | M9: -1695.0775 | N9: -13.631065 | O9: -1681.4464 | P9: -1199.1867 | Q9: -772.49442 | R9: -17.558833 | S9: 271.66961 | T9: 1.8939157 | U9: 3486.1254 | V9: 66.383086 | W9: 545.61561 | X9: 0 | Y9: 1538.2325 | Z9: -1059 | AA9: -2213.2076 | AB9: 127.706 | AC9: 152.9156 | AD9: 216.7165 | AE9: 2277.1127 | AF9: 212.96197 | AG9: 1629.188 | AH9: 2007.1773 | AI9: 377.98928 | AJ9: 3790.8 | AK9: 1122.1568 | AL9: =IF($C9<2017,AI9,-AI9) -> 377.98928 | AM9: =E9+T9-U9+AK9 -> 0 | AN9: =V9+AA9+AF9+AG9+AJ9-U9 -> 0 | AO9: =O9-P9-Q9-R9 -> 307.79351 | AP9: 61950.301 | AQ9: =SUM(AP6:AP9) -> 232866.49
B10: 2007-Q1 | C10: 2007 | D10: 1 | E10: 601.80209 | F10: 2327.7692 | G10: 2424.5 | H10: 11178.1 | I10: 8753.6 | J10: -96.730777 | K10: 2600.1297 | L10: 2696.8605 | M10: -1957.6619 | N10: -17.718326 | O10: -1939.9436 | P10: -1443.2163 | Q10: -829.19126 | R10: -29.5053 | S10: 231.69475 | T10: 11.5 | U10: 1476.2968 | V10: -717.42879 | W10: 409.62905 | X10: 0 | Y10: 425.75946 | Z10: 701.29838 | AA10: -2299.2615 | AB10: 257.825 | AC10: 14.9075 | AD10: 549.90636 | AE10: 2022.0877 | AF10: 7.8881731 | AG10: -174.59106 | AH10: 398.64055 | AI10: 573.23161 | AJ10: 4659.69 | AK10: 862.99469 | AL10: =IF($C10<2017,AI10,-AI10) -> 573.23161 | AM10: =E10+T10-U10+AK10 -> 0 | AN10: =V10+AA10+AF10+AG10+AJ10-U10 -> 0 | AO10: =O10-P10-Q10-R10 -> 361.96932 | AP10: 62530.88 | AQ10: =SUM(AP7:AP10) -> 242874.85
B11: 2007-Q2 | C11: 2007 | D11: 2 | E11: 2026.1906 | F11: 3622.2503 | G11: 3984.2 | H11: 13693.2 | I11: 9709 | J11: -361.94967 | K11: 2154.1852 | L11: 2516.1349 | M11: -1881.3289 | N11: -15.892115 | O11: -1865.4368 | P11: -1416.4047 | Q11: -857.36352 | R11: -42.155252 | S11: 285.26918 | T11: 6.6831964 | U11: 961.59229 | V11: -702.35407 | W11: 397.46312 | X11: 0 | Y11: 502.60256 | Z11: 597.21464 | AA11: -5662.7037 | AB11: 398.552 | AC11: -192.7557 | AD11: 594.93145 | AE11: 5273.5686 | AF11: 26.852836 | AG11: 960.15724 | AH11: 1776.4563 | AI11: 816.29904 | AJ11: 6339.64 | AK11: -1071.2815 | AL11: =IF($C11<2017,AI11,-AI11) -> 816.29904 | AM11: =E11+T11-U11+AK11 -> 0 | AN11: =V11+AA11+AF11+AG11+AJ11-U11 -> 0 | AO11: =O11-P11-Q11-R11 -> 450.48669 | AP11: 73317.957 | AQ11: =SUM(AP8:AP11) -> 256866.39
B12: 2007-Q3 | C12: 2007 | D12: 3 | E12: 449.26483 | F12: 1863.7897 | G12: 2346.262 | H12: 14388.562 | I12: 12042.3 | J12: -482.47226 | K12: 2321.4119 | L12: 2803.8841 | M12: -1665.6199 | N12: -19.473336 | O12: -1646.1466 | P12: -1294.3058 | Q12: -823.4659 | R12: -25.805467 | S12: 251.09502 | T12: 102.21072 | U12: 696.76192 | V12: -1530.032 | W12: 361.66316 | X12: 0 | Y12: 1460.4957 | Z12: 431.19949 | AA12: 1488.8172 | AB12: 245.997 | AC12: -31.229 | AD12: 228.47213 | AE12: -1502.5213 | AF12: -17.9536 | AG12: 1597.6804 | AH12: 4161.8946 | AI12: 2564.2142 | AJ12: -841.75 | AK12: 145.28638 | AL12: =IF($C12<2017,AI12,-AI12) -> 2564.2142 | AM12: =E12+T12-U12+AK12 -> 0 | AN12: =V12+AA12+AF12+AG12+AJ12-U12 -> 0 | AO12: =O12-P12-Q12-R12 -> 497.43057 | AP12: 72852.009 | AQ12: =SUM(AP9:AP12) -> 270651.15
B13: 2007-Q4 | C13: 2007 | D13: 4 | E13: 2971.2804 | F13: 4756.7707 | G13: 4797.1 | H13: 16816.7 | I13: 12019.6 | J13: -40.329315 | K13: 2970.0097 | L13: 3010.3391 | M13: -2090.045 | N13: -19.383139 | O13: -2070.6619 | P13: -1643.9381 | Q13: -768.97376 | R13: -147.08146 | S13: 304.55473 | T13: 0.751977 | U13: 2764.7959 | V13: -2019.1099 | W13: 335.47763 | X13: 0 | Y13: 2238.6632 | Z13: 115.92433 | AA13: -994.81481 | AB13: 486.984 | AC13: -6.732 | AD13: 411.62508 | AE13: 1063.4417 | AF13: 547.8 | AG13: 2298.7806 | AH13: 4219.682 | AI13: 1920.9014 | AJ13: 2932.14 | AK13: -207.23652 | AL13: =IF($C13<2017,AI13,-AI13) -> 1920.9014 | AM13: =E13+T13-U13+AK13 -> 0 | AN13: =V13+AA13+AF13+AG13+AJ13-U13 -> 0 | AO13: =O13-P13-Q13-R13 -> 489.33151 | AP13: 79085.289 | AQ13: =SUM(AP10:AP13) -> 287786.14
B14: 2008-Q1 | C14: 2008 | D14: 1 | E14: 1323.2146 | F14: 3303.6277 | G14: 3860.4 | H14: 16067.5 | I14: 12207.1 | J14: -556.77226 | K14: 2943.9976 | L14: 3500.7698 | M14: -2254.5385 | N14: -12.769577 | O14: -2241.7689 | P14: -1770.1325 | Q14: -797.86913 | R14: -121.01397 | S14: 274.1253 | T14: 43.631 | U14: 2610.9358 | V14: -3137.0014 | W14: 346.00328 | X14: 0 | Y14: 1537.4968 | Z14: 1945.5079 | AA14: 1033.6156 | AB14: 130.501 | AC14: 583.686 | AD14: -92.909673 | AE14: -226.51895 | AF14: -12.4 | AG14: 1192.5116 | AH14: 2617.8398 | AI14: 1425.3282 | AJ14: 3534.21 | AK14: 1244.0903 | AL14: =IF($C14<2017,AI14,-AI14) -> 1425.3282 | AM14: =E14+T14-U14+AK14 -> 0 | AN14: =V14+AA14+AF14+AG14+AJ14-U14 -> 0 | AO14: =O14-P14-Q14-R14 -> 447.24671 | AP14: 81874.729 | AQ14: =SUM(AP11:AP14) -> 307129.98
B15: 2008-Q2 | C15: 2008 | D15: 2 | E15: 319.25979 | F15: 2235.4626 | G15: 2942.3 | H15: 17526.3 | I15: 14584 | J15: -706.83744 | K15: 2579.4281 | L15: 3286.2656 | M15: -2229.8294 | N15: -15.403454 | O15: -2214.426 | P15: -1575.9096 | Q15: -866.31909 | R15: -160.93806 | S15: 313.62666 | T15: 14.751145 | U15: -667.96176 | V15: -1946.1919 | W15: 318.61091 | X15: 0 | Y15: 329.71942 | Z15: 1935.0834 | AA15: 2143.6934 | AB15: 669.137 | AC15: 18.489 | AD15: -202.87302 | AE15: -1253.1944 | AF15: 59.9 | AG15: 1695.5768 | AH15: 5196.4462 | AI15: 3500.8695 | AJ15: -2620.94 | AK15: -1001.9727 | AL15: =IF($C15<2017,AI15,-AI15) -> 3500.8695 | AM15: =E15+T15-U15+AK15 -> 0 | AN15: =V15+AA15+AF15+AG15+AJ15-U15 -> 0 | AO15: =O15-P15-Q15-R15 -> 388.74082 | AP15: 97237.603 | AQ15: =SUM(AP12:AP15) -> 331049.63
B16: 2008-Q3 | C16: 2008 | D16: 3 | E16: 2991.9188 | F16: 4958.9146 | G16: 5658.472 | H16: 21338.372 | I16: 15679.9 | J16: -699.55743 | K16: 2838.161 | L16: 3537.7185 | M16: -2226.4907 | N16: -17.448658 | O16: -2209.042 | P16: -1641.9865 | Q16: -740.69902 | R16: -132.02734 | S16: 259.49491 | T16: 123.8 | U16: 4535.4996 | V16: -1854.0751 | W16: 498.52132 | X16: 0 | Y16: 1906.2467 | Z16: 446.3498 | AA16: 4012.0782 | AB16: 97.261 | AC16: 1679.4657 | AD16: -58.179793 | AE16: -2177.1717 | AF16: 11.8 | AG16: 2415.1265 | AH16: 4809.1173 | AI16: 2393.9908 | AJ16: -49.43 | AK16: 1419.7808 | AL16: =IF($C16<2017,AI16,-AI16) -> 2393.9908 | AM16: =E16+T16-U16+AK16 -> 0 | AN16: =V16+AA16+AF16+AG16+AJ16-U16 -> 0 | AO16: =O16-P16-Q16-R16 -> 305.67088 | AP16: 97142.793 | AQ16: =SUM(AP13:AP16) -> 355340.41
B17: 2008-Q4 | C17: 2008 | D17: 4 | E17: 786.81315 | F17: 2842.9321 | G17: 3102.1 | H17: 15227.3 | I17: 12125.2 | J17: -259.16789 | K17: 3062.5623 | L17: 3321.7302 | M17: -2323.3321 | N17: -6.0199771 | O17: -2317.3122 | P17: -1591.5095 | Q17: -678.93522 | R17: -276.4716 | S17: 267.21319 | T17: 2.8778719 | U17: 75.48052 | V17: -1397.3501 | W17: 227.79908 | X17: 0 | Y17: 1175.4658 | Z17: 449.68337 | AA17: 689.20184 | AB17: -370.519 | AC17: -652.45685 | AD17: -176.65929 | AE17: -1535.5184 | AF17: 875.4 | AG17: 754.68881 | AH17: -382.88831 | AI17: -1137.5771 | AJ17: -846.46 | AK17: -714.2105 | AL17: =IF($C17<2017,AI17,-AI17) -> -1137.5771 | AM17: =E17+T17-U17+AK17 -> 0 | AN17: =V17+AA17+AF17+AG17+AJ17-U17 -> 0 | AO17: =O17-P17-Q17-R17 -> 229.60419 | AP17: 87623.248 | AQ17: =SUM(AP14:AP17) -> 363878.37
B18: 2009-Q1 | C18: 2009 | D18: 1 | E18: 1190.6916 | F18: 3367.8917 | G18: 3998.7 | H18: 11954.2 | I18: 7955.5 | J18: -630.80834 | K18: 2755.1961 | L18: 3386.0045 | M18: -2372.6826 | N18: -9.9565829 | O18: -2362.7261 | P18: -1760.2154 | Q18: -478.92568 | R18: -239.12318 | S18: 195.48254 | T18: 22.068297 | U18: 1063.5869 | V18: -1329.3758 | W18: 341.10497 | X18: 0 | Y18: 1974 | Z18: -303.51926 | AA18: 826.39481 | AB18: 109 | AC18: 740.44186 | AD18: -73.100388 | AE18: 96.147442 | AF18: -0.9 | AG18: 1300.3479 | AH18: 1731.6305 | AI18: 431.28262 | AJ18: 267.12 | AK18: -149.17293 | AL18: =IF($C18<2017,AI18,-AI18) -> 431.28262 | AM18: =E18+T18-U18+AK18 -> 0 | AN18: =V18+AA18+AF18+AG18+AJ18-U18 -> 0 | AO18: =O18-P18-Q18-R18 -> 115.53817 | AP18: 78497.112 | AQ18: =SUM(AP15:AP18) -> 360500.76
B19: 2009-Q2 | C19: 2009 | D19: 2 | E19: 4297.8251 | F19: 6449.4047 | G19: 6799.439 | H19: 15499.383 | I19: 8699.944 | J19: -350.03432 | K19: 2346.0162 | L19: 2696.0505 | M19: -2419.5556 | N19: -15.197304 | O19: -2404.3583 | P19: -1590.0895 | Q19: -667.8151 | R19: -248.42321 | S19: 267.97598 | T19: 0.6 | U19: 3073.7654 | V19: -581.00071 | W19: -235.17713 | X19: 0 | Y19: 533 | Z19: -187.17642 | AA19: -29.596546 | AB19: 165 | AC19: -480.54175 | AD19: 10.404173 | AE19: -296.34937 | AF19: 3.1 | AG19: 4379.9826 | AH19: 4536.052 | AI19: 156.06941 | AJ19: -698.72 | AK19: -1224.6597 | AL19: =IF($C19<2017,AI19,-AI19) -> 156.06941 | AM19: =E19+T19-U19+AK19 -> 0 | AN19: =V19+AA19+AF19+AG19+AJ19-U19 -> 0 | AO19: =O19-P19-Q19-R19 -> 101.96953 | AP19: 83898.257 | AQ19: =SUM(AP16:AP19) -> 347161.41
B20: 2009-Q3 | C20: 2009 | D20: 3 | E20: 704.7219 | F20: 3041.6864 | G20: 3764.488 | H20: 13837.668 | I20: 10073.18 | J20: -722.80164 | K20: 2313.6869 | L20: 3036.4885 | M20: -2528.8122 | N20: -21.413775 | O20: -2507.3984 | P20: -1663.9376 | Q20: -668.77588 | R20: -255.42397 | S20: 191.84776 | T20: 54.716732 | U20: 556.71391 | V20: -330.6616 | W20: 354.193 | X20: 0 | Y20: 1381 | Z20: -696.1454 | AA20: 817.14725 | AB20: 304 | AC20: -168.6982 | AD20: -54.286803 | AE20: -627.55864 | AF20: 20.4 | AG20: -1761.2617 | AH20: 367.69448 | AI20: 2128.9562 | AJ20: 1811.09 | AK20: -202.72472 | AL20: =IF($C20<2017,AI20,-AI20) -> 2128.9562 | AM20: =E20+T20-U20+AK20 -> 0 | AN20: =V20+AA20+AF20+AG20+AJ20-U20 -> 0 | AO20: =O20-P20-Q20-R20 -> 80.739055 | AP20: 82875.044 | AQ20: =SUM(AP17:AP20) -> 332893.66
... B86: 2026-Q1 | C86: 2026 | D86: 1 | E86: -1650.5258 | F86: 2311.3867 | G86: 6339.4596 | H86: 21916.049 | I86: 15576.589 | J86: -4028.0729 | K86: 5208.8695 | L86: 9236.9424 | M86: -4675.8332 | N86: -25.140044 | O86: -4650.6931 | P86: -2781.2949 | Q86: -799.5285 | R86: -1202.8977 | S86: 713.92067 | T86: 63.375631 | U86: -2398.2541 | V86: -1290.6768 | W86: 503.0621 | X86: 0 | Y86: 1913.9839 | Z86: -120.245 | AA86: 656.59172 | AB86: 397.43909 | AC86: 1046.3974 | AD86: -352.59237 | AE86: 1139.8371 | AF86: -10.350472 | AG86: -1764.4027 | AH86: -575.69209 | AI86: -1188.7106 | AJ86: 10.584206 | AK86: -811.10384 | AL86: =IF($C86<2017,AI86,-AI86) -> 1188.7106 | AM86: =E86+T86-U86+AK86 -> 0 | AN86: =V86+AA86+AF86+AG86+AJ86-U86 -> 0 | AO86: =O86-P86-Q86-R86 -> 133.02798 | AP86: 171682.28 | AQ86: =SUM(AP83:AP86) -> 684502
B88: Identity check = current account + capital account - financial account + errors and omissions. Zero except the four 2016 quarters (residual up to 2.1), which is internal to INDEC's vintage.
B89: Other-investment liabilities are published in natural sign to Q4-2016 and sign-flipped from Q1-2017. Column AL corrects for that; use AL, never AI, in any calculation. In AL a POSITIVE value is a net incurrence of liabilities, i.e. an inflow.
B90: Income on reserve assets is not published separately; it is the residual that makes investment income close. Always a credit, averaging about +88mn a quarter.
B91: Nominal GDP in USD: INDEC current-price GDP (published at annual rates, so divided by four for a true quarterly flow) converted at the period-average Com. "A" 3500 wholesale rate. Same construction as the companion GDP pack.

Sheet Current Account
B2: Current account — quarterly, four-quarter rolling and annual
B3: Millions of US dollars. Positive = credit / surplus. The rolling frame is the one to read: Argentine quarterly BoP is dominated by the Q2 harvest.
B4: Quarterly | T4: Four-quarter rolling
B5: Quarter | C5: CURRENT ACCOUNT | D5: Goods balance | E5: Exports FOB | F5: Imports FOB | G5: Services balance | H5: Services credits | I5: Services debits | J5: Primary income | K5: Compensation | L5: Investment income | M5: on direct inv. | N5: on portfolio | O5: on other inv. | P5: on reserves | Q5: Secondary income | R5: Capital account | T5: Quarter | U5: CURRENT ACCOUNT | V5: Goods balance | W5: Exports FOB | X5: Imports FOB | Y5: Services balance | Z5: Services credits | AA5: Services debits | AB5: Primary income | AC5: Compensation | AD5: Investment income | AE5: on direct inv. | AF5: on portfolio | AG5: on other inv. | AH5: on reserves | AI5: Secondary income | AJ5: Capital account
B6: ='Data BoP'!B6 -> 2006-Q1 | C6: ='Data BoP'!E6 -> 703.26687 | D6: ='Data BoP'!G6 -> 2906.3 | E6: ='Data BoP'!H6 -> 9945.6 | F6: ='Data BoP'!I6 -> 7039.3 | G6: ='Data BoP'!J6 -> -215.22406 | H6: ='Data BoP'!K6 -> 1945.1375 | I6: ='Data BoP'!L6 -> 2160.3616 | J6: ='Data BoP'!M6 -> -2177.7489 | K6: ='Data BoP'!N6 -> -13.484736 | ... O6: ='Data BoP'!R6 -> -85.475302 | P6: ='Data BoP'!AO6 -> 179.11111 | Q6: ='Data BoP'!S6 -> 189.93979 | R6: ='Data BoP'!T6 -> 10.4 | T6: ='Data BoP'!B6 -> 2006-Q1
B7: ='Data BoP'!B7 -> 2006-Q2 | C7: ='Data BoP'!E7 -> 1916.5945 | D7: ='Data BoP'!G7 -> 4123.5 | E7: ='Data BoP'!H7 -> 11980.3 | F7: ='Data BoP'!I7 -> 7856.8 | G7: ='Data BoP'!J7 -> -320.29197 | H7: ='Data BoP'!K7 -> 1712.9188 | I7: ='Data BoP'!L7 -> 2033.2108 | J7: ='Data BoP'!M7 -> -2159.0401 | K7: ='Data BoP'!N7 -> -18.373753 | ... O7: ='Data BoP'!R7 -> -51.674519 | P7: ='Data BoP'!AO7 -> 229.53616 | Q7: ='Data BoP'!S7 -> 272.42649 | R7: ='Data BoP'!T7 -> 39.9 | T7: ='Data BoP'!B7 -> 2006-Q2
B8: ='Data BoP'!B8 -> 2006-Q3 | C8: ='Data BoP'!E8 -> 1516.8665 | D8: ='Data BoP'!G8 -> 3255.5 | E8: ='Data BoP'!H8 -> 12126.8 | F8: ='Data BoP'!I8 -> 8871.3 | G8: ='Data BoP'!J8 -> -268.62401 | H8: ='Data BoP'!K8 -> 1898.8544 | I8: ='Data BoP'!L8 -> 2167.4784 | J8: ='Data BoP'!M8 -> -1690.7436 | K8: ='Data BoP'!N8 -> -15.609485 | ... O8: ='Data BoP'!R8 -> -27.196085 | P8: ='Data BoP'!AO8 -> 273.20583 | Q8: ='Data BoP'!S8 -> 220.73404 | R8: ='Data BoP'!T8 -> 45.430412 | T8: ='Data BoP'!B8 -> 2006-Q3
B9: ='Data BoP'!B9 -> 2006-Q4 | C9: ='Data BoP'!E9 -> 2362.0747 | D9: ='Data BoP'!G9 -> 3744.3 | E9: ='Data BoP'!H9 -> 12564.8 | F9: ='Data BoP'!I9 -> 8820.5 | G9: ='Data BoP'!J9 -> 41.182608 | H9: ='Data BoP'!K9 -> 2354.1044 | I9: ='Data BoP'!L9 -> 2312.9218 | J9: ='Data BoP'!M9 -> -1695.0775 | K9: ='Data BoP'!N9 -> -13.631065 | ... O9: ='Data BoP'!R9 -> -17.558833 | P9: ='Data BoP'!AO9 -> 307.79351 | Q9: ='Data BoP'!S9 -> 271.66961 | R9: ='Data BoP'!T9 -> 1.8939157 | T9: ='Data BoP'!B9 -> 2006-Q4 | U9: =('Data BoP'!E6)+('Data BoP'!E7)+('Data BoP'!E8)+('Data BoP'!E9) -> 6498.8025 | V9: =('Data BoP'!G6)+('Data BoP'!G7)+('Data BoP'!G8)+('Data BoP'!G9) -> 14029.6 | W9: =('Data BoP'!H6)+('Data BoP'!H7)+('Data BoP'!H8)+('Data BoP'!H9) -> 46617.5 | X9: =('Data BoP'!I6)+('Data BoP'!I7)+('Data BoP'!I8)+('Data BoP'!I9) -> 32587.9 | Y9: =('Data BoP'!J6)+('Data BoP'!J7)+('Data BoP'!J8)+('Data BoP'!J9) -> -762.95743 | Z9: =('Data BoP'!K6)+('Data BoP'!K7)+('Data BoP'!K8)+('Data BoP'!K9) -> 7911.0151 | AA9: =('Data BoP'!L6)+('Data BoP'!L7)+('Data BoP'!L8)+('Data BoP'!L9) -> 8673.9725 | AB9: =('Data BoP'!M6)+('Data BoP'!M7)+('Data BoP'!M8)+('Data BoP'!M9) -> -7722.61 | AC9: =('Data BoP'!N6)+('Data BoP'!N7)+('Data BoP'!N8)+('Data BoP'!N9) -> -61.099038 | ... AG9: =('Data BoP'!R6)+('Data BoP'!R7)+('Data BoP'!R8)+('Data BoP'!R9) -> -181.90474 | AH9: =('Data BoP'!AO6)+('Data BoP'!AO7)+('Data BoP'!AO8)+('Data BoP'!AO9) -> 989.6466 | AI9: =('Data BoP'!S6)+('Data BoP'!S7)+('Data BoP'!S8)+('Data BoP'!S9) -> 954.76993 | AJ9: =('Data BoP'!T6)+('Data BoP'!T7)+('Data BoP'!T8)+('Data BoP'!T9) -> 97.624328
B10: ='Data BoP'!B10 -> 2007-Q1 | C10: ='Data BoP'!E10 -> 601.80209 | D10: ='Data BoP'!G10 -> 2424.5 | E10: ='Data BoP'!H10 -> 11178.1 | F10: ='Data BoP'!I10 -> 8753.6 | G10: ='Data BoP'!J10 -> -96.730777 | H10: ='Data BoP'!K10 -> 2600.1297 | I10: ='Data BoP'!L10 -> 2696.8605 | J10: ='Data BoP'!M10 -> -1957.6619 | K10: ='Data BoP'!N10 -> -17.718326 | ... O10: ='Data BoP'!R10 -> -29.5053 | P10: ='Data BoP'!AO10 -> 361.96932 | Q10: ='Data BoP'!S10 -> 231.69475 | R10: ='Data BoP'!T10 -> 11.5 | T10: ='Data BoP'!B10 -> 2007-Q1 | U10: =('Data BoP'!E7)+('Data BoP'!E8)+('Data BoP'!E9)+('Data BoP'!E10) -> 6397.3377 | V10: =('Data BoP'!G7)+('Data BoP'!G8)+('Data BoP'!G9)+('Data BoP'!G10) -> 13547.8 | W10: =('Data BoP'!H7)+('Data BoP'!H8)+('Data BoP'!H9)+('Data BoP'!H10) -> 47850 | X10: =('Data BoP'!I7)+('Data BoP'!I8)+('Data BoP'!I9)+('Data BoP'!I10) -> 34302.2 | Y10: =('Data BoP'!J7)+('Data BoP'!J8)+('Data BoP'!J9)+('Data BoP'!J10) -> -644.46415 | Z10: =('Data BoP'!K7)+('Data BoP'!K8)+('Data BoP'!K9)+('Data BoP'!K10) -> 8566.0073 | AA10: =('Data BoP'!L7)+('Data BoP'!L8)+('Data BoP'!L9)+('Data BoP'!L10) -> 9210.4714 | AB10: =('Data BoP'!M7)+('Data BoP'!M8)+('Data BoP'!M9)+('Data BoP'!M10) -> -7502.523 | AC10: =('Data BoP'!N7)+('Data BoP'!N8)+('Data BoP'!N9)+('Data BoP'!N10) -> -65.332629 | ... AG10: =('Data BoP'!R7)+('Data BoP'!R8)+('Data BoP'!R9)+('Data BoP'!R10) -> -125.93474 | AH10: =('Data BoP'!AO7)+('Data BoP'!AO8)+('Data BoP'!AO9)+('Data BoP'!AO10) -> 1172.5048 | AI10: =('Data BoP'!S7)+('Data BoP'!S8)+('Data BoP'!S9)+('Data BoP'!S10) -> 996.52489 | AJ10: =('Data BoP'!T7)+('Data BoP'!T8)+('Data BoP'!T9)+('Data BoP'!T10) -> 98.724328
B11: ='Data BoP'!B11 -> 2007-Q2 | C11: ='Data BoP'!E11 -> 2026.1906 | D11: ='Data BoP'!G11 -> 3984.2 | E11: ='Data BoP'!H11 -> 13693.2 | F11: ='Data BoP'!I11 -> 9709 | G11: ='Data BoP'!J11 -> -361.94967 | H11: ='Data BoP'!K11 -> 2154.1852 | I11: ='Data BoP'!L11 -> 2516.1349 | J11: ='Data BoP'!M11 -> -1881.3289 | K11: ='Data BoP'!N11 -> -15.892115 | ... O11: ='Data BoP'!R11 -> -42.155252 | P11: ='Data BoP'!AO11 -> 450.48669 | Q11: ='Data BoP'!S11 -> 285.26918 | R11: ='Data BoP'!T11 -> 6.6831964 | T11: ='Data BoP'!B11 -> 2007-Q2 | U11: =('Data BoP'!E8)+('Data BoP'!E9)+('Data BoP'!E10)+('Data BoP'!E11) -> 6506.9338 | V11: =('Data BoP'!G8)+('Data BoP'!G9)+('Data BoP'!G10)+('Data BoP'!G11) -> 13408.5 | W11: =('Data BoP'!H8)+('Data BoP'!H9)+('Data BoP'!H10)+('Data BoP'!H11) -> 49562.9 | X11: =('Data BoP'!I8)+('Data BoP'!I9)+('Data BoP'!I10)+('Data BoP'!I11) -> 36154.4 | Y11: =('Data BoP'!J8)+('Data BoP'!J9)+('Data BoP'!J10)+('Data BoP'!J11) -> -686.12185 | Z11: =('Data BoP'!K8)+('Data BoP'!K9)+('Data BoP'!K10)+('Data BoP'!K11) -> 9007.2736 | AA11: =('Data BoP'!L8)+('Data BoP'!L9)+('Data BoP'!L10)+('Data BoP'!L11) -> 9693.3955 | AB11: =('Data BoP'!M8)+('Data BoP'!M9)+('Data BoP'!M10)+('Data BoP'!M11) -> -7224.8119 | AC11: =('Data BoP'!N8)+('Data BoP'!N9)+('Data BoP'!N10)+('Data BoP'!N11) -> -62.850991 | ... AG11: =('Data BoP'!R8)+('Data BoP'!R9)+('Data BoP'!R10)+('Data BoP'!R11) -> -116.41547 | AH11: =('Data BoP'!AO8)+('Data BoP'!AO9)+('Data BoP'!AO10)+('Data BoP'!AO11) -> 1393.4553 | AI11: =('Data BoP'!S8)+('Data BoP'!S9)+('Data BoP'!S10)+('Data BoP'!S11) -> 1009.3676 | AJ11: =('Data BoP'!T8)+('Data BoP'!T9)+('Data BoP'!T10)+('Data BoP'!T11) -> 65.507524
B12: ='Data BoP'!B12 -> 2007-Q3 | C12: ='Data BoP'!E12 -> 449.26483 | D12: ='Data BoP'!G12 -> 2346.262 | E12: ='Data BoP'!H12 -> 14388.562 | F12: ='Data BoP'!I12 -> 12042.3 | G12: ='Data BoP'!J12 -> -482.47226 | H12: ='Data BoP'!K12 -> 2321.4119 | I12: ='Data BoP'!L12 -> 2803.8841 | J12: ='Data BoP'!M12 -> -1665.6199 | K12: ='Data BoP'!N12 -> -19.473336 | ... O12: ='Data BoP'!R12 -> -25.805467 | P12: ='Data BoP'!AO12 -> 497.43057 | Q12: ='Data BoP'!S12 -> 251.09502 | R12: ='Data BoP'!T12 -> 102.21072 | T12: ='Data BoP'!B12 -> 2007-Q3 | U12: =('Data BoP'!E9)+('Data BoP'!E10)+('Data BoP'!E11)+('Data BoP'!E12) -> 5439.3322 | V12: =('Data BoP'!G9)+('Data BoP'!G10)+('Data BoP'!G11)+('Data BoP'!G12) -> 12499.262 | W12: =('Data BoP'!H9)+('Data BoP'!H10)+('Data BoP'!H11)+('Data BoP'!H12) -> 51824.662 | X12: =('Data BoP'!I9)+('Data BoP'!I10)+('Data BoP'!I11)+('Data BoP'!I12) -> 39325.4 | Y12: =('Data BoP'!J9)+('Data BoP'!J10)+('Data BoP'!J11)+('Data BoP'!J12) -> -899.9701 | Z12: =('Data BoP'!K9)+('Data BoP'!K10)+('Data BoP'!K11)+('Data BoP'!K12) -> 9429.8311 | AA12: =('Data BoP'!L9)+('Data BoP'!L10)+('Data BoP'!L11)+('Data BoP'!L12) -> 10329.801 | AB12: =('Data BoP'!M9)+('Data BoP'!M10)+('Data BoP'!M11)+('Data BoP'!M12) -> -7199.6883 | AC12: =('Data BoP'!N9)+('Data BoP'!N10)+('Data BoP'!N11)+('Data BoP'!N12) -> -66.714842 | ... AG12: =('Data BoP'!R9)+('Data BoP'!R10)+('Data BoP'!R11)+('Data BoP'!R12) -> -115.02485 | AH12: =('Data BoP'!AO9)+('Data BoP'!AO10)+('Data BoP'!AO11)+('Data BoP'!AO12) -> 1617.6801 | AI12: =('Data BoP'!S9)+('Data BoP'!S10)+('Data BoP'!S11)+('Data BoP'!S12) -> 1039.7286 | AJ12: =('Data BoP'!T9)+('Data BoP'!T10)+('Data BoP'!T11)+('Data BoP'!T12) -> 122.28783
B13: ='Data BoP'!B13 -> 2007-Q4 | C13: ='Data BoP'!E13 -> 2971.2804 | D13: ='Data BoP'!G13 -> 4797.1 | E13: ='Data BoP'!H13 -> 16816.7 | F13: ='Data BoP'!I13 -> 12019.6 | G13: ='Data BoP'!J13 -> -40.329315 | H13: ='Data BoP'!K13 -> 2970.0097 | I13: ='Data BoP'!L13 -> 3010.3391 | J13: ='Data BoP'!M13 -> -2090.045 | K13: ='Data BoP'!N13 -> -19.383139 | ... O13: ='Data BoP'!R13 -> -147.08146 | P13: ='Data BoP'!AO13 -> 489.33151 | Q13: ='Data BoP'!S13 -> 304.55473 | R13: ='Data BoP'!T13 -> 0.751977 | T13: ='Data BoP'!B13 -> 2007-Q4 | U13: =('Data BoP'!E10)+('Data BoP'!E11)+('Data BoP'!E12)+('Data BoP'!E13) -> 6048.5379 | V13: =('Data BoP'!G10)+('Data BoP'!G11)+('Data BoP'!G12)+('Data BoP'!G13) -> 13552.062 | W13: =('Data BoP'!H10)+('Data BoP'!H11)+('Data BoP'!H12)+('Data BoP'!H13) -> 56076.562 | X13: =('Data BoP'!I10)+('Data BoP'!I11)+('Data BoP'!I12)+('Data BoP'!I13) -> 42524.5 | Y13: =('Data BoP'!J10)+('Data BoP'!J11)+('Data BoP'!J12)+('Data BoP'!J13) -> -981.48202 | Z13: =('Data BoP'!K10)+('Data BoP'!K11)+('Data BoP'!K12)+('Data BoP'!K13) -> 10045.736 | AA13: =('Data BoP'!L10)+('Data BoP'!L11)+('Data BoP'!L12)+('Data BoP'!L13) -> 11027.219 | AB13: =('Data BoP'!M10)+('Data BoP'!M11)+('Data BoP'!M12)+('Data BoP'!M13) -> -7594.6558 | AC13: =('Data BoP'!N10)+('Data BoP'!N11)+('Data BoP'!N12)+('Data BoP'!N13) -> -72.466917 | ... AG13: =('Data BoP'!R10)+('Data BoP'!R11)+('Data BoP'!R12)+('Data BoP'!R13) -> -244.54748 | AH13: =('Data BoP'!AO10)+('Data BoP'!AO11)+('Data BoP'!AO12)+('Data BoP'!AO13) -> 1799.2181 | AI13: =('Data BoP'!S10)+('Data BoP'!S11)+('Data BoP'!S12)+('Data BoP'!S13) -> 1072.6137 | AJ13: =('Data BoP'!T10)+('Data BoP'!T11)+('Data BoP'!T12)+('Data BoP'!T13) -> 121.14589
B14: ='Data BoP'!B14 -> 2008-Q1 | C14: ='Data BoP'!E14 -> 1323.2146 | D14: ='Data BoP'!G14 -> 3860.4 | E14: ='Data BoP'!H14 -> 16067.5 | F14: ='Data BoP'!I14 -> 12207.1 | G14: ='Data BoP'!J14 -> -556.77226 | H14: ='Data BoP'!K14 -> 2943.9976 | I14: ='Data BoP'!L14 -> 3500.7698 | J14: ='Data BoP'!M14 -> -2254.5385 | K14: ='Data BoP'!N14 -> -12.769577 | ... O14: ='Data BoP'!R14 -> -121.01397 | P14: ='Data BoP'!AO14 -> 447.24671 | Q14: ='Data BoP'!S14 -> 274.1253 | R14: ='Data BoP'!T14 -> 43.631 | T14: ='Data BoP'!B14 -> 2008-Q1 | U14: =('Data BoP'!E11)+('Data BoP'!E12)+('Data BoP'!E13)+('Data BoP'!E14) -> 6769.9504 | V14: =('Data BoP'!G11)+('Data BoP'!G12)+('Data BoP'!G13)+('Data BoP'!G14) -> 14987.962 | W14: =('Data BoP'!H11)+('Data BoP'!H12)+('Data BoP'!H13)+('Data BoP'!H14) -> 60965.962 | X14: =('Data BoP'!I11)+('Data BoP'!I12)+('Data BoP'!I13)+('Data BoP'!I14) -> 45978 | Y14: =('Data BoP'!J11)+('Data BoP'!J12)+('Data BoP'!J13)+('Data BoP'!J14) -> -1441.5235 | Z14: =('Data BoP'!K11)+('Data BoP'!K12)+('Data BoP'!K13)+('Data BoP'!K14) -> 10389.604 | AA14: =('Data BoP'!L11)+('Data BoP'!L12)+('Data BoP'!L13)+('Data BoP'!L14) -> 11831.128 | AB14: =('Data BoP'!M11)+('Data BoP'!M12)+('Data BoP'!M13)+('Data BoP'!M14) -> -7891.5323 | AC14: =('Data BoP'!N11)+('Data BoP'!N12)+('Data BoP'!N13)+('Data BoP'!N14) -> -67.518168 | ... AG14: =('Data BoP'!R11)+('Data BoP'!R12)+('Data BoP'!R13)+('Data BoP'!R14) -> -336.05615 | AH14: =('Data BoP'!AO11)+('Data BoP'!AO12)+('Data BoP'!AO13)+('Data BoP'!AO14) -> 1884.4955 | AI14: =('Data BoP'!S11)+('Data BoP'!S12)+('Data BoP'!S13)+('Data BoP'!S14) -> 1115.0442 | AJ14: =('Data BoP'!T11)+('Data BoP'!T12)+('Data BoP'!T13)+('Data BoP'!T14) -> 153.27689
B15: ='Data BoP'!B15 -> 2008-Q2 | C15: ='Data BoP'!E15 -> 319.25979 | D15: ='Data BoP'!G15 -> 2942.3 | E15: ='Data BoP'!H15 -> 17526.3 | F15: ='Data BoP'!I15 -> 14584 | G15: ='Data BoP'!J15 -> -706.83744 | H15: ='Data BoP'!K15 -> 2579.4281 | I15: ='Data BoP'!L15 -> 3286.2656 | J15: ='Data BoP'!M15 -> -2229.8294 | K15: ='Data BoP'!N15 -> -15.403454 | ... O15: ='Data BoP'!R15 -> -160.93806 | P15: ='Data BoP'!AO15 -> 388.74082 | Q15: ='Data BoP'!S15 -> 313.62666 | R15: ='Data BoP'!T15 -> 14.751145 | T15: ='Data BoP'!B15 -> 2008-Q2 | U15: =('Data BoP'!E12)+('Data BoP'!E13)+('Data BoP'!E14)+('Data BoP'!E15) -> 5063.0196 | V15: =('Data BoP'!G12)+('Data BoP'!G13)+('Data BoP'!G14)+('Data BoP'!G15) -> 13946.062 | W15: =('Data BoP'!H12)+('Data BoP'!H13)+('Data BoP'!H14)+('Data BoP'!H15) -> 64799.062 | X15: =('Data BoP'!I12)+('Data BoP'!I13)+('Data BoP'!I14)+('Data BoP'!I15) -> 50853 | Y15: =('Data BoP'!J12)+('Data BoP'!J13)+('Data BoP'!J14)+('Data BoP'!J15) -> -1786.4113 | Z15: =('Data BoP'!K12)+('Data BoP'!K13)+('Data BoP'!K14)+('Data BoP'!K15) -> 10814.847 | AA15: =('Data BoP'!L12)+('Data BoP'!L13)+('Data BoP'!L14)+('Data BoP'!L15) -> 12601.259 | AB15: =('Data BoP'!M12)+('Data BoP'!M13)+('Data BoP'!M14)+('Data BoP'!M15) -> -8240.0328 | AC15: =('Data BoP'!N12)+('Data BoP'!N13)+('Data BoP'!N14)+('Data BoP'!N15) -> -67.029506 | ... AG15: =('Data BoP'!R12)+('Data BoP'!R13)+('Data BoP'!R14)+('Data BoP'!R15) -> -454.83896 | AH15: =('Data BoP'!AO12)+('Data BoP'!AO13)+('Data BoP'!AO14)+('Data BoP'!AO15) -> 1822.7496 | AI15: =('Data BoP'!S12)+('Data BoP'!S13)+('Data BoP'!S14)+('Data BoP'!S15) -> 1143.4017 | AJ15: =('Data BoP'!T12)+('Data BoP'!T13)+('Data BoP'!T14)+('Data BoP'!T15) -> 161.34484
B16: ='Data BoP'!B16 -> 2008-Q3 | C16: ='Data BoP'!E16 -> 2991.9188 | D16: ='Data BoP'!G16 -> 5658.472 | E16: ='Data BoP'!H16 -> 21338.372 | F16: ='Data BoP'!I16 -> 15679.9 | G16: ='Data BoP'!J16 -> -699.55743 | H16: ='Data BoP'!K16 -> 2838.161 | I16: ='Data BoP'!L16 -> 3537.7185 | J16: ='Data BoP'!M16 -> -2226.4907 | K16: ='Data BoP'!N16 -> -17.448658 | ... O16: ='Data BoP'!R16 -> -132.02734 | P16: ='Data BoP'!AO16 -> 305.67088 | Q16: ='Data BoP'!S16 -> 259.49491 | R16: ='Data BoP'!T16 -> 123.8 | T16: ='Data BoP'!B16 -> 2008-Q3 | U16: =('Data BoP'!E13)+('Data BoP'!E14)+('Data BoP'!E15)+('Data BoP'!E16) -> 7605.6736 | V16: =('Data BoP'!G13)+('Data BoP'!G14)+('Data BoP'!G15)+('Data BoP'!G16) -> 17258.272 | W16: =('Data BoP'!H13)+('Data BoP'!H14)+('Data BoP'!H15)+('Data BoP'!H16) -> 71748.872 | X16: =('Data BoP'!I13)+('Data BoP'!I14)+('Data BoP'!I15)+('Data BoP'!I16) -> 54490.6 | Y16: =('Data BoP'!J13)+('Data BoP'!J14)+('Data BoP'!J15)+('Data BoP'!J16) -> -2003.4964 | Z16: =('Data BoP'!K13)+('Data BoP'!K14)+('Data BoP'!K15)+('Data BoP'!K16) -> 11331.596 | AA16: =('Data BoP'!L13)+('Data BoP'!L14)+('Data BoP'!L15)+('Data BoP'!L16) -> 13335.093 | AB16: =('Data BoP'!M13)+('Data BoP'!M14)+('Data BoP'!M15)+('Data BoP'!M16) -> -8800.9035 | AC16: =('Data BoP'!N13)+('Data BoP'!N14)+('Data BoP'!N15)+('Data BoP'!N16) -> -65.004828 | ... AG16: =('Data BoP'!R13)+('Data BoP'!R14)+('Data BoP'!R15)+('Data BoP'!R16) -> -561.06083 | AH16: =('Data BoP'!AO13)+('Data BoP'!AO14)+('Data BoP'!AO15)+('Data BoP'!AO16) -> 1630.9899 | AI16: =('Data BoP'!S13)+('Data BoP'!S14)+('Data BoP'!S15)+('Data BoP'!S16) -> 1151.8016 | AJ16: =('Data BoP'!T13)+('Data BoP'!T14)+('Data BoP'!T15)+('Data BoP'!T16) -> 182.93412
B17: ='Data BoP'!B17 -> 2008-Q4 | C17: ='Data BoP'!E17 -> 786.81315 | D17: ='Data BoP'!G17 -> 3102.1 | E17: ='Data BoP'!H17 -> 15227.3 | F17: ='Data BoP'!I17 -> 12125.2 | G17: ='Data BoP'!J17 -> -259.16789 | H17: ='Data BoP'!K17 -> 3062.5623 | I17: ='Data BoP'!L17 -> 3321.7302 | J17: ='Data BoP'!M17 -> -2323.3321 | K17: ='Data BoP'!N17 -> -6.0199771 | ... O17: ='Data BoP'!R17 -> -276.4716 | P17: ='Data BoP'!AO17 -> 229.60419 | Q17: ='Data BoP'!S17 -> 267.21319 | R17: ='Data BoP'!T17 -> 2.8778719 | T17: ='Data BoP'!B17 -> 2008-Q4 | U17: =('Data BoP'!E14)+('Data BoP'!E15)+('Data BoP'!E16)+('Data BoP'!E17) -> 5421.2063 | V17: =('Data BoP'!G14)+('Data BoP'!G15)+('Data BoP'!G16)+('Data BoP'!G17) -> 15563.272 | W17: =('Data BoP'!H14)+('Data BoP'!H15)+('Data BoP'!H16)+('Data BoP'!H17) -> 70159.472 | X17: =('Data BoP'!I14)+('Data BoP'!I15)+('Data BoP'!I16)+('Data BoP'!I17) -> 54596.2 | Y17: =('Data BoP'!J14)+('Data BoP'!J15)+('Data BoP'!J16)+('Data BoP'!J17) -> -2222.335 | Z17: =('Data BoP'!K14)+('Data BoP'!K15)+('Data BoP'!K16)+('Data BoP'!K17) -> 11424.149 | AA17: =('Data BoP'!L14)+('Data BoP'!L15)+('Data BoP'!L16)+('Data BoP'!L17) -> 13646.484 | AB17: =('Data BoP'!M14)+('Data BoP'!M15)+('Data BoP'!M16)+('Data BoP'!M17) -> -9034.1907 | AC17: =('Data BoP'!N14)+('Data BoP'!N15)+('Data BoP'!N16)+('Data BoP'!N17) -> -51.641666 | ... AG17: =('Data BoP'!R14)+('Data BoP'!R15)+('Data BoP'!R16)+('Data BoP'!R17) -> -690.45097 | AH17: =('Data BoP'!AO14)+('Data BoP'!AO15)+('Data BoP'!AO16)+('Data BoP'!AO17) -> 1371.2626 | AI17: =('Data BoP'!S14)+('Data BoP'!S15)+('Data BoP'!S16)+('Data BoP'!S17) -> 1114.4601 | AJ17: =('Data BoP'!T14)+('Data BoP'!T15)+('Data BoP'!T16)+('Data BoP'!T17) -> 185.06002
B18: ='Data BoP'!B18 -> 2009-Q1 | C18: ='Data BoP'!E18 -> 1190.6916 | D18: ='Data BoP'!G18 -> 3998.7 | E18: ='Data BoP'!H18 -> 11954.2 | F18: ='Data BoP'!I18 -> 7955.5 | G18: ='Data BoP'!J18 -> -630.80834 | H18: ='Data BoP'!K18 -> 2755.1961 | I18: ='Data BoP'!L18 -> 3386.0045 | J18: ='Data BoP'!M18 -> -2372.6826 | K18: ='Data BoP'!N18 -> -9.9565829 | ... O18: ='Data BoP'!R18 -> -239.12318 | P18: ='Data BoP'!AO18 -> 115.53817 | Q18: ='Data BoP'!S18 -> 195.48254 | R18: ='Data BoP'!T18 -> 22.068297 | T18: ='Data BoP'!B18 -> 2009-Q1 | U18: =('Data BoP'!E15)+('Data BoP'!E16)+('Data BoP'!E17)+('Data BoP'!E18) -> 5288.6833 | V18: =('Data BoP'!G15)+('Data BoP'!G16)+('Data BoP'!G17)+('Data BoP'!G18) -> 15701.572 | W18: =('Data BoP'!H15)+('Data BoP'!H16)+('Data BoP'!H17)+('Data BoP'!H18) -> 66046.172 | X18: =('Data BoP'!I15)+('Data BoP'!I16)+('Data BoP'!I17)+('Data BoP'!I18) -> 50344.6 | Y18: =('Data BoP'!J15)+('Data BoP'!J16)+('Data BoP'!J17)+('Data BoP'!J18) -> -2296.3711 | Z18: =('Data BoP'!K15)+('Data BoP'!K16)+('Data BoP'!K17)+('Data BoP'!K18) -> 11235.348 | AA18: =('Data BoP'!L15)+('Data BoP'!L16)+('Data BoP'!L17)+('Data BoP'!L18) -> 13531.719 | AB18: =('Data BoP'!M15)+('Data BoP'!M16)+('Data BoP'!M17)+('Data BoP'!M18) -> -9152.3349 | AC18: =('Data BoP'!N15)+('Data BoP'!N16)+('Data BoP'!N17)+('Data BoP'!N18) -> -48.828671 | ... AG18: =('Data BoP'!R15)+('Data BoP'!R16)+('Data BoP'!R17)+('Data BoP'!R18) -> -808.56017 | AH18: =('Data BoP'!AO15)+('Data BoP'!AO16)+('Data BoP'!AO17)+('Data BoP'!AO18) -> 1039.5541 | AI18: =('Data BoP'!S15)+('Data BoP'!S16)+('Data BoP'!S17)+('Data BoP'!S18) -> 1035.8173 | AJ18: =('Data BoP'!T15)+('Data BoP'!T16)+('Data BoP'!T17)+('Data BoP'!T18) -> 163.49731
B19: ='Data BoP'!B19 -> 2009-Q2 | C19: ='Data BoP'!E19 -> 4297.8251 | D19: ='Data BoP'!G19 -> 6799.439 | E19: ='Data BoP'!H19 -> 15499.383 | F19: ='Data BoP'!I19 -> 8699.944 | G19: ='Data BoP'!J19 -> -350.03432 | H19: ='Data BoP'!K19 -> 2346.0162 | I19: ='Data BoP'!L19 -> 2696.0505 | J19: ='Data BoP'!M19 -> -2419.5556 | K19: ='Data BoP'!N19 -> -15.197304 | ... O19: ='Data BoP'!R19 -> -248.42321 | P19: ='Data BoP'!AO19 -> 101.96953 | Q19: ='Data BoP'!S19 -> 267.97598 | R19: ='Data BoP'!T19 -> 0.6 | T19: ='Data BoP'!B19 -> 2009-Q2 | U19: =('Data BoP'!E16)+('Data BoP'!E17)+('Data BoP'!E18)+('Data BoP'!E19) -> 9267.2486 | V19: =('Data BoP'!G16)+('Data BoP'!G17)+('Data BoP'!G18)+('Data BoP'!G19) -> 19558.711 | W19: =('Data BoP'!H16)+('Data BoP'!H17)+('Data BoP'!H18)+('Data BoP'!H19) -> 64019.255 | X19: =('Data BoP'!I16)+('Data BoP'!I17)+('Data BoP'!I18)+('Data BoP'!I19) -> 44460.544 | Y19: =('Data BoP'!J16)+('Data BoP'!J17)+('Data BoP'!J18)+('Data BoP'!J19) -> -1939.568 | Z19: =('Data BoP'!K16)+('Data BoP'!K17)+('Data BoP'!K18)+('Data BoP'!K19) -> 11001.936 | AA19: =('Data BoP'!L16)+('Data BoP'!L17)+('Data BoP'!L18)+('Data BoP'!L19) -> 12941.504 | AB19: =('Data BoP'!M16)+('Data BoP'!M17)+('Data BoP'!M18)+('Data BoP'!M19) -> -9342.061 | AC19: =('Data BoP'!N16)+('Data BoP'!N17)+('Data BoP'!N18)+('Data BoP'!N19) -> -48.622522 | ... AG19: =('Data BoP'!R16)+('Data BoP'!R17)+('Data BoP'!R18)+('Data BoP'!R19) -> -896.04533 | AH19: =('Data BoP'!AO16)+('Data BoP'!AO17)+('Data BoP'!AO18)+('Data BoP'!AO19) -> 752.78277 | AI19: =('Data BoP'!S16)+('Data BoP'!S17)+('Data BoP'!S18)+('Data BoP'!S19) -> 990.16662 | AJ19: =('Data BoP'!T16)+('Data BoP'!T17)+('Data BoP'!T18)+('Data BoP'!T19) -> 149.34617
B20: ='Data BoP'!B20 -> 2009-Q3 | C20: ='Data BoP'!E20 -> 704.7219 | D20: ='Data BoP'!G20 -> 3764.488 | E20: ='Data BoP'!H20 -> 13837.668 | F20: ='Data BoP'!I20 -> 10073.18 | G20: ='Data BoP'!J20 -> -722.80164 | H20: ='Data BoP'!K20 -> 2313.6869 | I20: ='Data BoP'!L20 -> 3036.4885 | J20: ='Data BoP'!M20 -> -2528.8122 | K20: ='Data BoP'!N20 -> -21.413775 | ... O20: ='Data BoP'!R20 -> -255.42397 | P20: ='Data BoP'!AO20 -> 80.739055 | Q20: ='Data BoP'!S20 -> 191.84776 | R20: ='Data BoP'!T20 -> 54.716732 | T20: ='Data BoP'!B20 -> 2009-Q3 | U20: =('Data BoP'!E17)+('Data BoP'!E18)+('Data BoP'!E19)+('Data BoP'!E20) -> 6980.0517 | V20: =('Data BoP'!G17)+('Data BoP'!G18)+('Data BoP'!G19)+('Data BoP'!G20) -> 17664.727 | W20: =('Data BoP'!H17)+('Data BoP'!H18)+('Data BoP'!H19)+('Data BoP'!H20) -> 56518.551 | X20: =('Data BoP'!I17)+('Data BoP'!I18)+('Data BoP'!I19)+('Data BoP'!I20) -> 38853.824 | Y20: =('Data BoP'!J17)+('Data BoP'!J18)+('Data BoP'!J19)+('Data BoP'!J20) -> -1962.8122 | Z20: =('Data BoP'!K17)+('Data BoP'!K18)+('Data BoP'!K19)+('Data BoP'!K20) -> 10477.462 | AA20: =('Data BoP'!L17)+('Data BoP'!L18)+('Data BoP'!L19)+('Data BoP'!L20) -> 12440.274 | AB20: =('Data BoP'!M17)+('Data BoP'!M18)+('Data BoP'!M19)+('Data BoP'!M20) -> -9644.3826 | AC20: =('Data BoP'!N17)+('Data BoP'!N18)+('Data BoP'!N19)+('Data BoP'!N20) -> -52.587638 | ... AG20: =('Data BoP'!R17)+('Data BoP'!R18)+('Data BoP'!R19)+('Data BoP'!R20) -> -1019.442 | AH20: =('Data BoP'!AO17)+('Data BoP'!AO18)+('Data BoP'!AO19)+('Data BoP'!AO20) -> 527.85094 | AI20: =('Data BoP'!S17)+('Data BoP'!S18)+('Data BoP'!S19)+('Data BoP'!S20) -> 922.51947 | AJ20: =('Data BoP'!T17)+('Data BoP'!T18)+('Data BoP'!T19)+('Data BoP'!T20) -> 80.262901
... B86: ='Data BoP'!B86 -> 2026-Q1 | C86: ='Data BoP'!E86 -> -1650.5258 | D86: ='Data BoP'!G86 -> 6339.4596 | E86: ='Data BoP'!H86 -> 21916.049 | F86: ='Data BoP'!I86 -> 15576.589 | G86: ='Data BoP'!J86 -> -4028.0729 | H86: ='Data BoP'!K86 -> 5208.8695 | I86: ='Data BoP'!L86 -> 9236.9424 | J86: ='Data BoP'!M86 -> -4675.8332 | K86: ='Data BoP'!N86 -> -25.140044 | ... O86: ='Data BoP'!R86 -> -1202.8977 | P86: ='Data BoP'!AO86 -> 133.02798 | Q86: ='Data BoP'!S86 -> 713.92067 | R86: ='Data BoP'!T86 -> 63.375631 | T86: ='Data BoP'!B86 -> 2026-Q1 | U86: =('Data BoP'!E83)+('Data BoP'!E84)+('Data BoP'!E85)+('Data BoP'!E86) -> -4281.0987 | V86: =('Data BoP'!G83)+('Data BoP'!G84)+('Data BoP'!G85)+('Data BoP'!G86) -> 19638.654 | W86: =('Data BoP'!H83)+('Data BoP'!H84)+('Data BoP'!H85)+('Data BoP'!H86) -> 90365.617 | X86: =('Data BoP'!I83)+('Data BoP'!I84)+('Data BoP'!I85)+('Data BoP'!I86) -> 70726.963 | Y86: =('Data BoP'!J83)+('Data BoP'!J84)+('Data BoP'!J85)+('Data BoP'!J86) -> -11069.201 | Z86: =('Data BoP'!K83)+('Data BoP'!K84)+('Data BoP'!K85)+('Data BoP'!K86) -> 18898.494 | AA86: =('Data BoP'!L83)+('Data BoP'!L84)+('Data BoP'!L85)+('Data BoP'!L86) -> 29967.695 | AB86: =('Data BoP'!M83)+('Data BoP'!M84)+('Data BoP'!M85)+('Data BoP'!M86) -> -15737.007 | AC86: =('Data BoP'!N83)+('Data BoP'!N84)+('Data BoP'!N85)+('Data BoP'!N86) -> -99.457177 | ... AG86: =('Data BoP'!R83)+('Data BoP'!R84)+('Data BoP'!R85)+('Data BoP'!R86) -> -4631.2247 | AH86: =('Data BoP'!AO83)+('Data BoP'!AO84)+('Data BoP'!AO85)+('Data BoP'!AO86) -> 417.21132 | AI86: =('Data BoP'!S83)+('Data BoP'!S84)+('Data BoP'!S85)+('Data BoP'!S86) -> 2886.4562 | AJ86: =('Data BoP'!T83)+('Data BoP'!T84)+('Data BoP'!T85)+('Data BoP'!T86) -> 458.3965
B89: Annual
B90: Year | C90: CURRENT ACCOUNT | D90: Goods balance | E90: Exports FOB | F90: Imports FOB | G90: Services balance | H90: Services credits | I90: Services debits | J90: Primary income | K90: Compensation | L90: Investment income | M90: on direct inv. | N90: on portfolio | O90: on other inv. | P90: on reserves | Q90: Secondary income | R90: Capital account
B91: 2006 | C91: =SUMIFS('Data BoP'!$E$6:$E$86,'Data BoP'!$C$6:$C$86,$B91) -> 6498.8025 | D91: =SUMIFS('Data BoP'!$G$6:$G$86,'Data BoP'!$C$6:$C$86,$B91) -> 14029.6 | E91: =SUMIFS('Data BoP'!$H$6:$H$86,'Data BoP'!$C$6:$C$86,$B91) -> 46617.5 | F91: =SUMIFS('Data BoP'!$I$6:$I$86,'Data BoP'!$C$6:$C$86,$B91) -> 32587.9 | G91: =SUMIFS('Data BoP'!$J$6:$J$86,'Data BoP'!$C$6:$C$86,$B91) -> -762.95743 | H91: =SUMIFS('Data BoP'!$K$6:$K$86,'Data BoP'!$C$6:$C$86,$B91) -> 7911.0151 | I91: =SUMIFS('Data BoP'!$L$6:$L$86,'Data BoP'!$C$6:$C$86,$B91) -> 8673.9725 | J91: =SUMIFS('Data BoP'!$M$6:$M$86,'Data BoP'!$C$6:$C$86,$B91) -> -7722.61 | K91: =SUMIFS('Data BoP'!$N$6:$N$86,'Data BoP'!$C$6:$C$86,$B91) -> -61.099038 | L91: =SUMIFS('Data BoP'!$O$6:$O$86,'Data BoP'!$C$6:$C$86,$B91) -> -7661.5109 | M91: =SUMIFS('Data BoP'!$P$6:$P$86,'Data BoP'!$C$6:$C$86,$B91) -> -5476.819 | N91: =SUMIFS('Data BoP'!$Q$6:$Q$86,'Data BoP'!$C$6:$C$86,$B91) -> -2992.4338 | O91: =SUMIFS('Data BoP'!$R$6:$R$86,'Data BoP'!$C$6:$C$86,$B91) -> -181.90474 | P91: =SUMIFS('Data BoP'!$AO$6:$AO$86,'Data BoP'!$C$6:$C$86,$B91) -> 989.6466 | Q91: =SUMIFS('Data BoP'!$S$6:$S$86,'Data BoP'!$C$6:$C$86,$B91) -> 954.76993 | R91: =SUMIFS('Data BoP'!$T$6:$T$86,'Data BoP'!$C$6:$C$86,$B91) -> 97.624328
B92: 2007 | C92: =SUMIFS('Data BoP'!$E$6:$E$86,'Data BoP'!$C$6:$C$86,$B92) -> 6048.5379 | D92: =SUMIFS('Data BoP'!$G$6:$G$86,'Data BoP'!$C$6:$C$86,$B92) -> 13552.062 | E92: =SUMIFS('Data BoP'!$H$6:$H$86,'Data BoP'!$C$6:$C$86,$B92) -> 56076.562 | F92: =SUMIFS('Data BoP'!$I$6:$I$86,'Data BoP'!$C$6:$C$86,$B92) -> 42524.5 | G92: =SUMIFS('Data BoP'!$J$6:$J$86,'Data BoP'!$C$6:$C$86,$B92) -> -981.48202 | H92: =SUMIFS('Data BoP'!$K$6:$K$86,'Data BoP'!$C$6:$C$86,$B92) -> 10045.736 | I92: =SUMIFS('Data BoP'!$L$6:$L$86,'Data BoP'!$C$6:$C$86,$B92) -> 11027.219 | J92: =SUMIFS('Data BoP'!$M$6:$M$86,'Data BoP'!$C$6:$C$86,$B92) -> -7594.6558 | K92: =SUMIFS('Data BoP'!$N$6:$N$86,'Data BoP'!$C$6:$C$86,$B92) -> -72.466917 | L92: =SUMIFS('Data BoP'!$O$6:$O$86,'Data BoP'!$C$6:$C$86,$B92) -> -7522.1888 | M92: =SUMIFS('Data BoP'!$P$6:$P$86,'Data BoP'!$C$6:$C$86,$B92) -> -5797.865 | N92: =SUMIFS('Data BoP'!$Q$6:$Q$86,'Data BoP'!$C$6:$C$86,$B92) -> -3278.9944 | O92: =SUMIFS('Data BoP'!$R$6:$R$86,'Data BoP'!$C$6:$C$86,$B92) -> -244.54748 | P92: =SUMIFS('Data BoP'!$AO$6:$AO$86,'Data BoP'!$C$6:$C$86,$B92) -> 1799.2181 | Q92: =SUMIFS('Data BoP'!$S$6:$S$86,'Data BoP'!$C$6:$C$86,$B92) -> 1072.6137 | R92: =SUMIFS('Data BoP'!$T$6:$T$86,'Data BoP'!$C$6:$C$86,$B92) -> 121.14589
B93: 2008 | C93: =SUMIFS('Data BoP'!$E$6:$E$86,'Data BoP'!$C$6:$C$86,$B93) -> 5421.2063 | D93: =SUMIFS('Data BoP'!$G$6:$G$86,'Data BoP'!$C$6:$C$86,$B93) -> 15563.272 | E93: =SUMIFS('Data BoP'!$H$6:$H$86,'Data BoP'!$C$6:$C$86,$B93) -> 70159.472 | F93: =SUMIFS('Data BoP'!$I$6:$I$86,'Data BoP'!$C$6:$C$86,$B93) -> 54596.2 | G93: =SUMIFS('Data BoP'!$J$6:$J$86,'Data BoP'!$C$6:$C$86,$B93) -> -2222.335 | H93: =SUMIFS('Data BoP'!$K$6:$K$86,'Data BoP'!$C$6:$C$86,$B93) -> 11424.149 | I93: =SUMIFS('Data BoP'!$L$6:$L$86,'Data BoP'!$C$6:$C$86,$B93) -> 13646.484 | J93: =SUMIFS('Data BoP'!$M$6:$M$86,'Data BoP'!$C$6:$C$86,$B93) -> -9034.1907 | K93: =SUMIFS('Data BoP'!$N$6:$N$86,'Data BoP'!$C$6:$C$86,$B93) -> -51.641666 | L93: =SUMIFS('Data BoP'!$O$6:$O$86,'Data BoP'!$C$6:$C$86,$B93) -> -8982.549 | M93: =SUMIFS('Data BoP'!$P$6:$P$86,'Data BoP'!$C$6:$C$86,$B93) -> -6579.5382 | N93: =SUMIFS('Data BoP'!$Q$6:$Q$86,'Data BoP'!$C$6:$C$86,$B93) -> -3083.8225 | O93: =SUMIFS('Data BoP'!$R$6:$R$86,'Data BoP'!$C$6:$C$86,$B93) -> -690.45097 | P93: =SUMIFS('Data BoP'!$AO$6:$AO$86,'Data BoP'!$C$6:$C$86,$B93) -> 1371.2626 | Q93: =SUMIFS('Data BoP'!$S$6:$S$86,'Data BoP'!$C$6:$C$86,$B93) -> 1114.4601 | R93: =SUMIFS('Data BoP'!$T$6:$T$86,'Data BoP'!$C$6:$C$86,$B93) -> 185.06002
B94: 2009 | C94: =SUMIFS('Data BoP'!$E$6:$E$86,'Data BoP'!$C$6:$C$86,$B94) -> 7254.1157 | D94: =SUMIFS('Data BoP'!$G$6:$G$86,'Data BoP'!$C$6:$C$86,$B94) -> 18644.85 | E94: =SUMIFS('Data BoP'!$H$6:$H$86,'Data BoP'!$C$6:$C$86,$B94) -> 55790.984 | F94: =SUMIFS('Data BoP'!$I$6:$I$86,'Data BoP'!$C$6:$C$86,$B94) -> 37146.134 | G94: =SUMIFS('Data BoP'!$J$6:$J$86,'Data BoP'!$C$6:$C$86,$B94) -> -1992.0315 | H94: =SUMIFS('Data BoP'!$K$6:$K$86,'Data BoP'!$C$6:$C$86,$B94) -> 10544.621 | I94: =SUMIFS('Data BoP'!$L$6:$L$86,'Data BoP'!$C$6:$C$86,$B94) -> 12536.653 | J94: =SUMIFS('Data BoP'!$M$6:$M$86,'Data BoP'!$C$6:$C$86,$B94) -> -10318.875 | K94: =SUMIFS('Data BoP'!$N$6:$N$86,'Data BoP'!$C$6:$C$86,$B94) -> -59.357787 | L94: =SUMIFS('Data BoP'!$O$6:$O$86,'Data BoP'!$C$6:$C$86,$B94) -> -10259.517 | M94: =SUMIFS('Data BoP'!$P$6:$P$86,'Data BoP'!$C$6:$C$86,$B94) -> -7069.7925 | N94: =SUMIFS('Data BoP'!$Q$6:$Q$86,'Data BoP'!$C$6:$C$86,$B94) -> -2548.7037 | O94: =SUMIFS('Data BoP'!$R$6:$R$86,'Data BoP'!$C$6:$C$86,$B94) -> -998.42778 | P94: =SUMIFS('Data BoP'!$AO$6:$AO$86,'Data BoP'!$C$6:$C$86,$B94) -> 357.40675 | Q94: =SUMIFS('Data BoP'!$S$6:$S$86,'Data BoP'!$C$6:$C$86,$B94) -> 920.17218 | R94: =SUMIFS('Data BoP'!$T$6:$T$86,'Data BoP'!$C$6:$C$86,$B94) -> 79.984228
B95: 2010 | C95: =SUMIFS('Data BoP'!$E$6:$E$86,'Data BoP'!$C$6:$C$86,$B95) -> -1622.9959 | D95: =SUMIFS('Data BoP'!$G$6:$G$86,'Data BoP'!$C$6:$C$86,$B95) -> 14147.109 | E95: =SUMIFS('Data BoP'!$H$6:$H$86,'Data BoP'!$C$6:$C$86,$B95) -> 68305.873 | F95: =SUMIFS('Data BoP'!$I$6:$I$86,'Data BoP'!$C$6:$C$86,$B95) -> 54158.764 | G95: =SUMIFS('Data BoP'!$J$6:$J$86,'Data BoP'!$C$6:$C$86,$B95) -> -1803.5886 | H95: =SUMIFS('Data BoP'!$K$6:$K$86,'Data BoP'!$C$6:$C$86,$B95) -> 12817.143 | I95: =SUMIFS('Data BoP'!$L$6:$L$86,'Data BoP'!$C$6:$C$86,$B95) -> 14620.732 | J95: =SUMIFS('Data BoP'!$M$6:$M$86,'Data BoP'!$C$6:$C$86,$B95) -> -14547.533 | K95: =SUMIFS('Data BoP'!$N$6:$N$86,'Data BoP'!$C$6:$C$86,$B95) -> -54.723346 | L95: =SUMIFS('Data BoP'!$O$6:$O$86,'Data BoP'!$C$6:$C$86,$B95) -> -14492.81 | M95: =SUMIFS('Data BoP'!$P$6:$P$86,'Data BoP'!$C$6:$C$86,$B95) -> -11161.705 | N95: =SUMIFS('Data BoP'!$Q$6:$Q$86,'Data BoP'!$C$6:$C$86,$B95) -> -2413.1417 | O95: =SUMIFS('Data BoP'!$R$6:$R$86,'Data BoP'!$C$6:$C$86,$B95) -> -1066.902 | P95: =SUMIFS('Data BoP'!$AO$6:$AO$86,'Data BoP'!$C$6:$C$86,$B95) -> 148.93835 | Q95: =SUMIFS('Data BoP'!$S$6:$S$86,'Data BoP'!$C$6:$C$86,$B95) -> 581.01668 | R95: =SUMIFS('Data BoP'!$T$6:$T$86,'Data BoP'!$C$6:$C$86,$B95) -> 78.477885
B96: 2011 | C96: =SUMIFS('Data BoP'!$E$6:$E$86,'Data BoP'!$C$6:$C$86,$B96) -> -5340.1812 | D96: =SUMIFS('Data BoP'!$G$6:$G$86,'Data BoP'!$C$6:$C$86,$B96) -> 12350.931 | E96: =SUMIFS('Data BoP'!$H$6:$H$86,'Data BoP'!$C$6:$C$86,$B96) -> 83119.709 | F96: =SUMIFS('Data BoP'!$I$6:$I$86,'Data BoP'!$C$6:$C$86,$B96) -> 70768.778 | G96: =SUMIFS('Data BoP'!$J$6:$J$86,'Data BoP'!$C$6:$C$86,$B96) -> -3152.488 | H96: =SUMIFS('Data BoP'!$K$6:$K$86,'Data BoP'!$C$6:$C$86,$B96) -> 14496.981 | I96: =SUMIFS('Data BoP'!$L$6:$L$86,'Data BoP'!$C$6:$C$86,$B96) -> 17649.469 | J96: =SUMIFS('Data BoP'!$M$6:$M$86,'Data BoP'!$C$6:$C$86,$B96) -> -15073.067 | K96: =SUMIFS('Data BoP'!$N$6:$N$86,'Data BoP'!$C$6:$C$86,$B96) -> -45.897878 | L96: =SUMIFS('Data BoP'!$O$6:$O$86,'Data BoP'!$C$6:$C$86,$B96) -> -15027.169 | M96: =SUMIFS('Data BoP'!$P$6:$P$86,'Data BoP'!$C$6:$C$86,$B96) -> -11136.355 | N96: =SUMIFS('Data BoP'!$Q$6:$Q$86,'Data BoP'!$C$6:$C$86,$B96) -> -2744.6919 | O96: =SUMIFS('Data BoP'!$R$6:$R$86,'Data BoP'!$C$6:$C$86,$B96) -> -1227.8537 | P96: =SUMIFS('Data BoP'!$AO$6:$AO$86,'Data BoP'!$C$6:$C$86,$B96) -> 81.731558 | Q96: =SUMIFS('Data BoP'!$S$6:$S$86,'Data BoP'!$C$6:$C$86,$B96) -> 534.44286 | R96: =SUMIFS('Data BoP'!$T$6:$T$86,'Data BoP'!$C$6:$C$86,$B96) -> 62.723846
B97: 2012 | C97: =SUMIFS('Data BoP'!$E$6:$E$86,'Data BoP'!$C$6:$C$86,$B97) -> -2138.0404 | D97: =SUMIFS('Data BoP'!$G$6:$G$86,'Data BoP'!$C$6:$C$86,$B97) -> 15040.913 | E97: =SUMIFS('Data BoP'!$H$6:$H$86,'Data BoP'!$C$6:$C$86,$B97) -> 80083.655 | F97: =SUMIFS('Data BoP'!$I$6:$I$86,'Data BoP'!$C$6:$C$86,$B97) -> 65042.742 | G97: =SUMIFS('Data BoP'!$J$6:$J$86,'Data BoP'!$C$6:$C$86,$B97) -> -4097.2247 | H97: =SUMIFS('Data BoP'!$K$6:$K$86,'Data BoP'!$C$6:$C$86,$B97) -> 14247.101 | I97: =SUMIFS('Data BoP'!$L$6:$L$86,'Data BoP'!$C$6:$C$86,$B97) -> 18344.325 | J97: =SUMIFS('Data BoP'!$M$6:$M$86,'Data BoP'!$C$6:$C$86,$B97) -> -13753.841 | K97: =SUMIFS('Data BoP'!$N$6:$N$86,'Data BoP'!$C$6:$C$86,$B97) -> -62.771927 | L97: =SUMIFS('Data BoP'!$O$6:$O$86,'Data BoP'!$C$6:$C$86,$B97) -> -13691.069 | M97: =SUMIFS('Data BoP'!$P$6:$P$86,'Data BoP'!$C$6:$C$86,$B97) -> -9616.2488 | N97: =SUMIFS('Data BoP'!$Q$6:$Q$86,'Data BoP'!$C$6:$C$86,$B97) -> -2658.5003 | O97: =SUMIFS('Data BoP'!$R$6:$R$86,'Data BoP'!$C$6:$C$86,$B97) -> -1470.1735 | P97: =SUMIFS('Data BoP'!$AO$6:$AO$86,'Data BoP'!$C$6:$C$86,$B97) -> 53.85394 | Q97: =SUMIFS('Data BoP'!$S$6:$S$86,'Data BoP'!$C$6:$C$86,$B97) -> 672.1122 | R97: =SUMIFS('Data BoP'!$T$6:$T$86,'Data BoP'!$C$6:$C$86,$B97) -> 47.884045
B98: 2013 | C98: =SUMIFS('Data BoP'!$E$6:$E$86,'Data BoP'!$C$6:$C$86,$B98) -> -13124.374 | D98: =SUMIFS('Data BoP'!$G$6:$G$86,'Data BoP'!$C$6:$C$86,$B98) -> 4635.2352 | E98: =SUMIFS('Data BoP'!$H$6:$H$86,'Data BoP'!$C$6:$C$86,$B98) -> 75928.228 | F98: =SUMIFS('Data BoP'!$I$6:$I$86,'Data BoP'!$C$6:$C$86,$B98) -> 71292.993 | G98: =SUMIFS('Data BoP'!$J$6:$J$86,'Data BoP'!$C$6:$C$86,$B98) -> -5328.9161 | H98: =SUMIFS('Data BoP'!$K$6:$K$86,'Data BoP'!$C$6:$C$86,$B98) -> 13679.892 | I98: =SUMIFS('Data BoP'!$L$6:$L$86,'Data BoP'!$C$6:$C$86,$B98) -> 19008.808 | J98: =SUMIFS('Data BoP'!$M$6:$M$86,'Data BoP'!$C$6:$C$86,$B98) -> -13164.828 | K98: =SUMIFS('Data BoP'!$N$6:$N$86,'Data BoP'!$C$6:$C$86,$B98) -> -65.409421 | L98: =SUMIFS('Data BoP'!$O$6:$O$86,'Data BoP'!$C$6:$C$86,$B98) -> -13099.418 | M98: =SUMIFS('Data BoP'!$P$6:$P$86,'Data BoP'!$C$6:$C$86,$B98) -> -8978.5668 | N98: =SUMIFS('Data BoP'!$Q$6:$Q$86,'Data BoP'!$C$6:$C$86,$B98) -> -2773.2992 | O98: =SUMIFS('Data BoP'!$R$6:$R$86,'Data BoP'!$C$6:$C$86,$B98) -> -1384.8637 | P98: =SUMIFS('Data BoP'!$AO$6:$AO$86,'Data BoP'!$C$6:$C$86,$B98) -> 37.311542 | Q98: =SUMIFS('Data BoP'!$S$6:$S$86,'Data BoP'!$C$6:$C$86,$B98) -> 734.13466 | R98: =SUMIFS('Data BoP'!$T$6:$T$86,'Data BoP'!$C$6:$C$86,$B98) -> 33.412874
B99: 2014 | C99: =SUMIFS('Data BoP'!$E$6:$E$86,'Data BoP'!$C$6:$C$86,$B99) -> -9179.0263 | D99: =SUMIFS('Data BoP'!$G$6:$G$86,'Data BoP'!$C$6:$C$86,$B99) -> 5541.4698 | E99: =SUMIFS('Data BoP'!$H$6:$H$86,'Data BoP'!$C$6:$C$86,$B99) -> 68440.436 | F99: =SUMIFS('Data BoP'!$I$6:$I$86,'Data BoP'!$C$6:$C$86,$B99) -> 62898.966 | G99: =SUMIFS('Data BoP'!$J$6:$J$86,'Data BoP'!$C$6:$C$86,$B99) -> -4641.2922 | H99: =SUMIFS('Data BoP'!$K$6:$K$86,'Data BoP'!$C$6:$C$86,$B99) -> 13396.372 | I99: =SUMIFS('Data BoP'!$L$6:$L$86,'Data BoP'!$C$6:$C$86,$B99) -> 18037.664 | J99: =SUMIFS('Data BoP'!$M$6:$M$86,'Data BoP'!$C$6:$C$86,$B99) -> -11613.847 | K99: =SUMIFS('Data BoP'!$N$6:$N$86,'Data BoP'!$C$6:$C$86,$B99) -> -34.191273 | L99: =SUMIFS('Data BoP'!$O$6:$O$86,'Data BoP'!$C$6:$C$86,$B99) -> -11579.656 | M99: =SUMIFS('Data BoP'!$P$6:$P$86,'Data BoP'!$C$6:$C$86,$B99) -> -7299.5735 | N99: =SUMIFS('Data BoP'!$Q$6:$Q$86,'Data BoP'!$C$6:$C$86,$B99) -> -2938.6885 | O99: =SUMIFS('Data BoP'!$R$6:$R$86,'Data BoP'!$C$6:$C$86,$B99) -> -1358.8475 | P99: =SUMIFS('Data BoP'!$AO$6:$AO$86,'Data BoP'!$C$6:$C$86,$B99) -> 17.453245 | Q99: =SUMIFS('Data BoP'!$S$6:$S$86,'Data BoP'!$C$6:$C$86,$B99) -> 1534.6436 | R99: =SUMIFS('Data BoP'!$T$6:$T$86,'Data BoP'!$C$6:$C$86,$B99) -> 56.797105
B100: 2015 | C100: =SUMIFS('Data BoP'!$E$6:$E$86,'Data BoP'!$C$6:$C$86,$B100) -> -17621.985 | D100: =SUMIFS('Data BoP'!$G$6:$G$86,'Data BoP'!$C$6:$C$86,$B100) -> -785.17639 | E100: =SUMIFS('Data BoP'!$H$6:$H$86,'Data BoP'!$C$6:$C$86,$B100) -> 56809.053 | F100: =SUMIFS('Data BoP'!$I$6:$I$86,'Data BoP'!$C$6:$C$86,$B100) -> 57594.23 | G100: =SUMIFS('Data BoP'!$J$6:$J$86,'Data BoP'!$C$6:$C$86,$B100) -> -5815.0447 | H100: =SUMIFS('Data BoP'!$K$6:$K$86,'Data BoP'!$C$6:$C$86,$B100) -> 13213.512 | I100: =SUMIFS('Data BoP'!$L$6:$L$86,'Data BoP'!$C$6:$C$86,$B100) -> 19028.557 | J100: =SUMIFS('Data BoP'!$M$6:$M$86,'Data BoP'!$C$6:$C$86,$B100) -> -12104.599 | K100: =SUMIFS('Data BoP'!$N$6:$N$86,'Data BoP'!$C$6:$C$86,$B100) -> 25.812828 | L100: =SUMIFS('Data BoP'!$O$6:$O$86,'Data BoP'!$C$6:$C$86,$B100) -> -12130.411 | M100: =SUMIFS('Data BoP'!$P$6:$P$86,'Data BoP'!$C$6:$C$86,$B100) -> -8145.1451 | N100: =SUMIFS('Data BoP'!$Q$6:$Q$86,'Data BoP'!$C$6:$C$86,$B100) -> -2687.2444 | O100: =SUMIFS('Data BoP'!$R$6:$R$86,'Data BoP'!$C$6:$C$86,$B100) -> -1322.4984 | P100: =SUMIFS('Data BoP'!$AO$6:$AO$86,'Data BoP'!$C$6:$C$86,$B100) -> 24.476529 | Q100: =SUMIFS('Data BoP'!$S$6:$S$86,'Data BoP'!$C$6:$C$86,$B100) -> 1082.8345 | R100: =SUMIFS('Data BoP'!$T$6:$T$86,'Data BoP'!$C$6:$C$86,$B100) -> 51.9292
B101: 2016 | C101: =SUMIFS('Data BoP'!$E$6:$E$86,'Data BoP'!$C$6:$C$86,$B101) -> -15104.787 | D101: =SUMIFS('Data BoP'!$G$6:$G$86,'Data BoP'!$C$6:$C$86,$B101) -> 4416.1569 | E101: =SUMIFS('Data BoP'!$H$6:$H$86,'Data BoP'!$C$6:$C$86,$B101) -> 57959.934 | F101: =SUMIFS('Data BoP'!$I$6:$I$86,'Data BoP'!$C$6:$C$86,$B101) -> 53543.777 | G101: =SUMIFS('Data BoP'!$J$6:$J$86,'Data BoP'!$C$6:$C$86,$B101) -> -8451.6552 | H101: =SUMIFS('Data BoP'!$K$6:$K$86,'Data BoP'!$C$6:$C$86,$B101) -> 13424.707 | I101: =SUMIFS('Data BoP'!$L$6:$L$86,'Data BoP'!$C$6:$C$86,$B101) -> 21876.362 | J101: =SUMIFS('Data BoP'!$M$6:$M$86,'Data BoP'!$C$6:$C$86,$B101) -> -12192.211 | K101: =SUMIFS('Data BoP'!$N$6:$N$86,'Data BoP'!$C$6:$C$86,$B101) -> -93.937831 | L101: =SUMIFS('Data BoP'!$O$6:$O$86,'Data BoP'!$C$6:$C$86,$B101) -> -12098.273 | M101: =SUMIFS('Data BoP'!$P$6:$P$86,'Data BoP'!$C$6:$C$86,$B101) -> -7166.2554 | N101: =SUMIFS('Data BoP'!$Q$6:$Q$86,'Data BoP'!$C$6:$C$86,$B101) -> -3505.4293 | O101: =SUMIFS('Data BoP'!$R$6:$R$86,'Data BoP'!$C$6:$C$86,$B101) -> -1487.1405 | P101: =SUMIFS('Data BoP'!$AO$6:$AO$86,'Data BoP'!$C$6:$C$86,$B101) -> 60.552378 | Q101: =SUMIFS('Data BoP'!$S$6:$S$86,'Data BoP'!$C$6:$C$86,$B101) -> 1122.9225 | R101: =SUMIFS('Data BoP'!$T$6:$T$86,'Data BoP'!$C$6:$C$86,$B101) -> 370.80455
B102: 2017 | C102: =SUMIFS('Data BoP'!$E$6:$E$86,'Data BoP'!$C$6:$C$86,$B102) -> -31151.352 | D102: =SUMIFS('Data BoP'!$G$6:$G$86,'Data BoP'!$C$6:$C$86,$B102) -> -5447.0631 | E102: =SUMIFS('Data BoP'!$H$6:$H$86,'Data BoP'!$C$6:$C$86,$B102) -> 58661.874 | F102: =SUMIFS('Data BoP'!$I$6:$I$86,'Data BoP'!$C$6:$C$86,$B102) -> 64108.937 | G102: =SUMIFS('Data BoP'!$J$6:$J$86,'Data BoP'!$C$6:$C$86,$B102) -> -9695.4386 | H102: =SUMIFS('Data BoP'!$K$6:$K$86,'Data BoP'!$C$6:$C$86,$B102) -> 15506.202 | I102: =SUMIFS('Data BoP'!$L$6:$L$86,'Data BoP'!$C$6:$C$86,$B102) -> 25201.641 | J102: =SUMIFS('Data BoP'!$M$6:$M$86,'Data BoP'!$C$6:$C$86,$B102) -> -16380.284 | K102: =SUMIFS('Data BoP'!$N$6:$N$86,'Data BoP'!$C$6:$C$86,$B102) -> -80.803522 | L102: =SUMIFS('Data BoP'!$O$6:$O$86,'Data BoP'!$C$6:$C$86,$B102) -> -16299.48 | M102: =SUMIFS('Data BoP'!$P$6:$P$86,'Data BoP'!$C$6:$C$86,$B102) -> -8681.6453 | N102: =SUMIFS('Data BoP'!$Q$6:$Q$86,'Data BoP'!$C$6:$C$86,$B102) -> -5980.8424 | O102: =SUMIFS('Data BoP'!$R$6:$R$86,'Data BoP'!$C$6:$C$86,$B102) -> -1767.3448 | P102: =SUMIFS('Data BoP'!$AO$6:$AO$86,'Data BoP'!$C$6:$C$86,$B102) -> 130.35228 | Q102: =SUMIFS('Data BoP'!$S$6:$S$86,'Data BoP'!$C$6:$C$86,$B102) -> 371.43365 | R102: =SUMIFS('Data BoP'!$T$6:$T$86,'Data BoP'!$C$6:$C$86,$B102) -> 173.49547
... B110: 2025 | C110: =SUMIFS('Data BoP'!$E$6:$E$86,'Data BoP'!$C$6:$C$86,$B110) -> -7788.1256 | D110: =SUMIFS('Data BoP'!$G$6:$G$86,'Data BoP'!$C$6:$C$86,$B110) -> 15359.035 | E110: =SUMIFS('Data BoP'!$H$6:$H$86,'Data BoP'!$C$6:$C$86,$B110) -> 87151.683 | F110: =SUMIFS('Data BoP'!$I$6:$I$86,'Data BoP'!$C$6:$C$86,$B110) -> 71792.648 | G110: =SUMIFS('Data BoP'!$J$6:$J$86,'Data BoP'!$C$6:$C$86,$B110) -> -11600.938 | H110: =SUMIFS('Data BoP'!$K$6:$K$86,'Data BoP'!$C$6:$C$86,$B110) -> 18340.857 | I110: =SUMIFS('Data BoP'!$L$6:$L$86,'Data BoP'!$C$6:$C$86,$B110) -> 29941.795 | J110: =SUMIFS('Data BoP'!$M$6:$M$86,'Data BoP'!$C$6:$C$86,$B110) -> -14078.683 | K110: =SUMIFS('Data BoP'!$N$6:$N$86,'Data BoP'!$C$6:$C$86,$B110) -> -97.65516 | L110: =SUMIFS('Data BoP'!$O$6:$O$86,'Data BoP'!$C$6:$C$86,$B110) -> -13981.028 | M110: =SUMIFS('Data BoP'!$P$6:$P$86,'Data BoP'!$C$6:$C$86,$B110) -> -7244.531 | N110: =SUMIFS('Data BoP'!$Q$6:$Q$86,'Data BoP'!$C$6:$C$86,$B110) -> -2668.575 | O110: =SUMIFS('Data BoP'!$R$6:$R$86,'Data BoP'!$C$6:$C$86,$B110) -> -4399.9252 | P110: =SUMIFS('Data BoP'!$AO$6:$AO$86,'Data BoP'!$C$6:$C$86,$B110) -> 332.00343 | Q110: =SUMIFS('Data BoP'!$S$6:$S$86,'Data BoP'!$C$6:$C$86,$B110) -> 2532.4599 | R110: =SUMIFS('Data BoP'!$T$6:$T$86,'Data BoP'!$C$6:$C$86,$B110) -> 454.14014

Sheet Financial Account
B2: Financial account — quarterly, four-quarter rolling and annual
B3: Millions of US dollars, BPM6 net lending(+) / net borrowing(-). A NEGATIVE total is a net capital INFLOW. Liabilities are shown in natural sign: positive = non-residents put money in.
B4: Quarterly | U4: Four-quarter rolling
B5: Quarter | C5: FINANCIAL ACCOUNT | D5: Direct investment, net | E5: DI assets (equity) | F5: DI assets (debt) | G5: DI liabilities (equity) | H5: DI liabilities (debt) | I5: Portfolio investment, net | J5: PI assets (equity) | K5: PI assets (debt) | L5: PI liabilities (equity) | M5: PI liabilities (debt) | N5: Financial derivatives | O5: Other investment, net | P5: OI assets | Q5: OI liabilities (corrected) | R5: RESERVE ASSETS | S5: Errors & omissions | U5: Quarter | V5: FINANCIAL ACCOUNT | W5: Direct investment, net | X5: DI assets (equity) | Y5: DI assets (debt) | Z5: DI liabilities (equity) | AA5: DI liabilities (debt) | AB5: Portfolio investment, net | AC5: PI assets (equity) | AD5: PI assets (debt) | AE5: PI liabilities (equity) | AF5: PI liabilities (debt) | AG5: Financial derivatives | AH5: Other investment, net | AI5: OI assets | AJ5: OI liabilities (corrected) | AK5: RESERVE ASSETS | AL5: Errors & omissions
B6: ='Data BoP'!B6 -> 2006-Q1 | C6: ='Data BoP'!U6 -> 781.03661 | D6: ='Data BoP'!V6 -> -1375.7522 | E6: ='Data BoP'!W6 -> 377.20756 | F6: ='Data BoP'!X6 -> 0 | G6: ='Data BoP'!Y6 -> 1469.9598 | H6: ='Data BoP'!Z6 -> 283 | I6: ='Data BoP'!AA6 -> -2253.0962 | J6: ='Data BoP'!AB6 -> 205.538 | ... P6: ='Data BoP'!AH6 -> 587.04922 | Q6: ='Data BoP'!AL6 -> -10472.733 | R6: ='Data BoP'!AJ6 -> -6633.94 | S6: ='Data BoP'!AK6 -> 67.369736 | U6: ='Data BoP'!B6 -> 2006-Q1
B7: ='Data BoP'!B7 -> 2006-Q2 | C7: ='Data BoP'!U7 -> 1980.8828 | D7: ='Data BoP'!V7 -> -672.39111 | E7: ='Data BoP'!W7 -> 1090.9457 | F7: ='Data BoP'!X7 -> 0 | G7: ='Data BoP'!Y7 -> 612.3368 | H7: ='Data BoP'!Z7 -> 1151 | I7: ='Data BoP'!AA7 -> -1970.5648 | J7: ='Data BoP'!AB7 -> -54.226 | ... P7: ='Data BoP'!AH7 -> 224.66308 | Q7: ='Data BoP'!AL7 -> -588.53078 | R7: ='Data BoP'!AJ7 -> 3843.01 | S7: ='Data BoP'!AK7 -> 24.388326 | U7: ='Data BoP'!B7 -> 2006-Q2
B8: ='Data BoP'!B8 -> 2006-Q3 | C8: ='Data BoP'!U8 -> 1232.3861 | D8: ='Data BoP'!V8 -> -1116.8668 | E8: ='Data BoP'!W8 -> 424.95187 | F8: ='Data BoP'!X8 -> 0 | G8: ='Data BoP'!Y8 -> 1653.8187 | H8: ='Data BoP'!Z8 -> -112 | I8: ='Data BoP'!AA8 -> -802.52817 | J8: ='Data BoP'!AB8 -> 122.74 | ... P8: ='Data BoP'!AH8 -> 421.67896 | Q8: ='Data BoP'!AL8 -> -238.13754 | R8: ='Data BoP'!AJ8 -> 2529.96 | S8: ='Data BoP'!AK8 -> -329.91081 | U8: ='Data BoP'!B8 -> 2006-Q3
B9: ='Data BoP'!B9 -> 2006-Q4 | C9: ='Data BoP'!U9 -> 3486.1254 | D9: ='Data BoP'!V9 -> 66.383086 | E9: ='Data BoP'!W9 -> 545.61561 | F9: ='Data BoP'!X9 -> 0 | G9: ='Data BoP'!Y9 -> 1538.2325 | H9: ='Data BoP'!Z9 -> -1059 | I9: ='Data BoP'!AA9 -> -2213.2076 | J9: ='Data BoP'!AB9 -> 127.706 | ... P9: ='Data BoP'!AH9 -> 2007.1773 | Q9: ='Data BoP'!AL9 -> 377.98928 | R9: ='Data BoP'!AJ9 -> 3790.8 | S9: ='Data BoP'!AK9 -> 1122.1568 | U9: ='Data BoP'!B9 -> 2006-Q4 | V9: =('Data BoP'!U6)+('Data BoP'!U7)+('Data BoP'!U8)+('Data BoP'!U9) -> 7480.4309 | W9: =('Data BoP'!V6)+('Data BoP'!V7)+('Data BoP'!V8)+('Data BoP'!V9) -> -3098.6271 | X9: =('Data BoP'!W6)+('Data BoP'!W7)+('Data BoP'!W8)+('Data BoP'!W9) -> 2438.7207 | Y9: =('Data BoP'!X6)+('Data BoP'!X7)+('Data BoP'!X8)+('Data BoP'!X9) -> 0 | Z9: =('Data BoP'!Y6)+('Data BoP'!Y7)+('Data BoP'!Y8)+('Data BoP'!Y9) -> 5274.3478 | AA9: =('Data BoP'!Z6)+('Data BoP'!Z7)+('Data BoP'!Z8)+('Data BoP'!Z9) -> 263 | AB9: =('Data BoP'!AA6)+('Data BoP'!AA7)+('Data BoP'!AA8)+('Data BoP'!AA9) -> -7239.3968 | AC9: =('Data BoP'!AB6)+('Data BoP'!AB7)+('Data BoP'!AB8)+('Data BoP'!AB9) -> 401.758 | ... AI9: =('Data BoP'!AH6)+('Data BoP'!AH7)+('Data BoP'!AH8)+('Data BoP'!AH9) -> 3240.5685 | AJ9: =('Data BoP'!AL6)+('Data BoP'!AL7)+('Data BoP'!AL8)+('Data BoP'!AL9) -> -10921.412 | AK9: =('Data BoP'!AJ6)+('Data BoP'!AJ7)+('Data BoP'!AJ8)+('Data BoP'!AJ9) -> 3529.83 | AL9: =('Data BoP'!AK6)+('Data BoP'!AK7)+('Data BoP'!AK8)+('Data BoP'!AK9) -> 884.00404
B10: ='Data BoP'!B10 -> 2007-Q1 | C10: ='Data BoP'!U10 -> 1476.2968 | D10: ='Data BoP'!V10 -> -717.42879 | E10: ='Data BoP'!W10 -> 409.62905 | F10: ='Data BoP'!X10 -> 0 | G10: ='Data BoP'!Y10 -> 425.75946 | H10: ='Data BoP'!Z10 -> 701.29838 | I10: ='Data BoP'!AA10 -> -2299.2615 | J10: ='Data BoP'!AB10 -> 257.825 | ... P10: ='Data BoP'!AH10 -> 398.64055 | Q10: ='Data BoP'!AL10 -> 573.23161 | R10: ='Data BoP'!AJ10 -> 4659.69 | S10: ='Data BoP'!AK10 -> 862.99469 | U10: ='Data BoP'!B10 -> 2007-Q1 | V10: =('Data BoP'!U7)+('Data BoP'!U8)+('Data BoP'!U9)+('Data BoP'!U10) -> 8175.6911 | W10: =('Data BoP'!V7)+('Data BoP'!V8)+('Data BoP'!V9)+('Data BoP'!V10) -> -2440.3036 | X10: =('Data BoP'!W7)+('Data BoP'!W8)+('Data BoP'!W9)+('Data BoP'!W10) -> 2471.1422 | Y10: =('Data BoP'!X7)+('Data BoP'!X8)+('Data BoP'!X9)+('Data BoP'!X10) -> 0 | Z10: =('Data BoP'!Y7)+('Data BoP'!Y8)+('Data BoP'!Y9)+('Data BoP'!Y10) -> 4230.1475 | AA10: =('Data BoP'!Z7)+('Data BoP'!Z8)+('Data BoP'!Z9)+('Data BoP'!Z10) -> 681.29838 | AB10: =('Data BoP'!AA7)+('Data BoP'!AA8)+('Data BoP'!AA9)+('Data BoP'!AA10) -> -7285.5621 | AC10: =('Data BoP'!AB7)+('Data BoP'!AB8)+('Data BoP'!AB9)+('Data BoP'!AB10) -> 454.045 | ... AI10: =('Data BoP'!AH7)+('Data BoP'!AH8)+('Data BoP'!AH9)+('Data BoP'!AH10) -> 3052.1599 | AJ10: =('Data BoP'!AL7)+('Data BoP'!AL8)+('Data BoP'!AL9)+('Data BoP'!AL10) -> 124.55257 | AK10: =('Data BoP'!AJ7)+('Data BoP'!AJ8)+('Data BoP'!AJ9)+('Data BoP'!AJ10) -> 14823.46 | AL10: =('Data BoP'!AK7)+('Data BoP'!AK8)+('Data BoP'!AK9)+('Data BoP'!AK10) -> 1679.629
B11: ='Data BoP'!B11 -> 2007-Q2 | C11: ='Data BoP'!U11 -> 961.59229 | D11: ='Data BoP'!V11 -> -702.35407 | E11: ='Data BoP'!W11 -> 397.46312 | F11: ='Data BoP'!X11 -> 0 | G11: ='Data BoP'!Y11 -> 502.60256 | H11: ='Data BoP'!Z11 -> 597.21464 | I11: ='Data BoP'!AA11 -> -5662.7037 | J11: ='Data BoP'!AB11 -> 398.552 | ... P11: ='Data BoP'!AH11 -> 1776.4563 | Q11: ='Data BoP'!AL11 -> 816.29904 | R11: ='Data BoP'!AJ11 -> 6339.64 | S11: ='Data BoP'!AK11 -> -1071.2815 | U11: ='Data BoP'!B11 -> 2007-Q2 | V11: =('Data BoP'!U8)+('Data BoP'!U9)+('Data BoP'!U10)+('Data BoP'!U11) -> 7156.4006 | W11: =('Data BoP'!V8)+('Data BoP'!V9)+('Data BoP'!V10)+('Data BoP'!V11) -> -2470.2666 | X11: =('Data BoP'!W8)+('Data BoP'!W9)+('Data BoP'!W10)+('Data BoP'!W11) -> 1777.6596 | Y11: =('Data BoP'!X8)+('Data BoP'!X9)+('Data BoP'!X10)+('Data BoP'!X11) -> 0 | Z11: =('Data BoP'!Y8)+('Data BoP'!Y9)+('Data BoP'!Y10)+('Data BoP'!Y11) -> 4120.4132 | AA11: =('Data BoP'!Z8)+('Data BoP'!Z9)+('Data BoP'!Z10)+('Data BoP'!Z11) -> 127.51301 | AB11: =('Data BoP'!AA8)+('Data BoP'!AA9)+('Data BoP'!AA10)+('Data BoP'!AA11) -> -10977.701 | AC11: =('Data BoP'!AB8)+('Data BoP'!AB9)+('Data BoP'!AB10)+('Data BoP'!AB11) -> 906.823 | ... AI11: =('Data BoP'!AH8)+('Data BoP'!AH9)+('Data BoP'!AH10)+('Data BoP'!AH11) -> 4603.9531 | AJ11: =('Data BoP'!AL8)+('Data BoP'!AL9)+('Data BoP'!AL10)+('Data BoP'!AL11) -> 1529.3824 | AK11: =('Data BoP'!AJ8)+('Data BoP'!AJ9)+('Data BoP'!AJ10)+('Data BoP'!AJ11) -> 17320.09 | AL11: =('Data BoP'!AK8)+('Data BoP'!AK9)+('Data BoP'!AK10)+('Data BoP'!AK11) -> 583.95921
B12: ='Data BoP'!B12 -> 2007-Q3 | C12: ='Data BoP'!U12 -> 696.76192 | D12: ='Data BoP'!V12 -> -1530.032 | E12: ='Data BoP'!W12 -> 361.66316 | F12: ='Data BoP'!X12 -> 0 | G12: ='Data BoP'!Y12 -> 1460.4957 | H12: ='Data BoP'!Z12 -> 431.19949 | I12: ='Data BoP'!AA12 -> 1488.8172 | J12: ='Data BoP'!AB12 -> 245.997 | ... P12: ='Data BoP'!AH12 -> 4161.8946 | Q12: ='Data BoP'!AL12 -> 2564.2142 | R12: ='Data BoP'!AJ12 -> -841.75 | S12: ='Data BoP'!AK12 -> 145.28638 | U12: ='Data BoP'!B12 -> 2007-Q3 | V12: =('Data BoP'!U9)+('Data BoP'!U10)+('Data BoP'!U11)+('Data BoP'!U12) -> 6620.7764 | W12: =('Data BoP'!V9)+('Data BoP'!V10)+('Data BoP'!V11)+('Data BoP'!V12) -> -2883.4318 | X12: =('Data BoP'!W9)+('Data BoP'!W10)+('Data BoP'!W11)+('Data BoP'!W12) -> 1714.3709 | Y12: =('Data BoP'!X9)+('Data BoP'!X10)+('Data BoP'!X11)+('Data BoP'!X12) -> 0 | Z12: =('Data BoP'!Y9)+('Data BoP'!Y10)+('Data BoP'!Y11)+('Data BoP'!Y12) -> 3927.0903 | AA12: =('Data BoP'!Z9)+('Data BoP'!Z10)+('Data BoP'!Z11)+('Data BoP'!Z12) -> 670.7125 | AB12: =('Data BoP'!AA9)+('Data BoP'!AA10)+('Data BoP'!AA11)+('Data BoP'!AA12) -> -8686.3557 | AC12: =('Data BoP'!AB9)+('Data BoP'!AB10)+('Data BoP'!AB11)+('Data BoP'!AB12) -> 1030.08 | ... AI12: =('Data BoP'!AH9)+('Data BoP'!AH10)+('Data BoP'!AH11)+('Data BoP'!AH12) -> 8344.1687 | AJ12: =('Data BoP'!AL9)+('Data BoP'!AL10)+('Data BoP'!AL11)+('Data BoP'!AL12) -> 4331.7341 | AK12: =('Data BoP'!AJ9)+('Data BoP'!AJ10)+('Data BoP'!AJ11)+('Data BoP'!AJ12) -> 13948.38 | AL12: =('Data BoP'!AK9)+('Data BoP'!AK10)+('Data BoP'!AK11)+('Data BoP'!AK12) -> 1059.1564
B13: ='Data BoP'!B13 -> 2007-Q4 | C13: ='Data BoP'!U13 -> 2764.7959 | D13: ='Data BoP'!V13 -> -2019.1099 | E13: ='Data BoP'!W13 -> 335.47763 | F13: ='Data BoP'!X13 -> 0 | G13: ='Data BoP'!Y13 -> 2238.6632 | H13: ='Data BoP'!Z13 -> 115.92433 | I13: ='Data BoP'!AA13 -> -994.81481 | J13: ='Data BoP'!AB13 -> 486.984 | ... P13: ='Data BoP'!AH13 -> 4219.682 | Q13: ='Data BoP'!AL13 -> 1920.9014 | R13: ='Data BoP'!AJ13 -> 2932.14 | S13: ='Data BoP'!AK13 -> -207.23652 | U13: ='Data BoP'!B13 -> 2007-Q4 | V13: =('Data BoP'!U10)+('Data BoP'!U11)+('Data BoP'!U12)+('Data BoP'!U13) -> 5899.4469 | W13: =('Data BoP'!V10)+('Data BoP'!V11)+('Data BoP'!V12)+('Data BoP'!V13) -> -4968.9248 | X13: =('Data BoP'!W10)+('Data BoP'!W11)+('Data BoP'!W12)+('Data BoP'!W13) -> 1504.233 | Y13: =('Data BoP'!X10)+('Data BoP'!X11)+('Data BoP'!X12)+('Data BoP'!X13) -> 0 | Z13: =('Data BoP'!Y10)+('Data BoP'!Y11)+('Data BoP'!Y12)+('Data BoP'!Y13) -> 4627.5209 | AA13: =('Data BoP'!Z10)+('Data BoP'!Z11)+('Data BoP'!Z12)+('Data BoP'!Z13) -> 1845.6368 | AB13: =('Data BoP'!AA10)+('Data BoP'!AA11)+('Data BoP'!AA12)+('Data BoP'!AA13) -> -7467.9629 | AC13: =('Data BoP'!AB10)+('Data BoP'!AB11)+('Data BoP'!AB12)+('Data BoP'!AB13) -> 1389.358 | ... AI13: =('Data BoP'!AH10)+('Data BoP'!AH11)+('Data BoP'!AH12)+('Data BoP'!AH13) -> 10556.673 | AJ13: =('Data BoP'!AL10)+('Data BoP'!AL11)+('Data BoP'!AL12)+('Data BoP'!AL13) -> 5874.6463 | AK13: =('Data BoP'!AJ10)+('Data BoP'!AJ11)+('Data BoP'!AJ12)+('Data BoP'!AJ13) -> 13089.72 | AL13: =('Data BoP'!AK10)+('Data BoP'!AK11)+('Data BoP'!AK12)+('Data BoP'!AK13) -> -270.2369
B14: ='Data BoP'!B14 -> 2008-Q1 | C14: ='Data BoP'!U14 -> 2610.9358 | D14: ='Data BoP'!V14 -> -3137.0014 | E14: ='Data BoP'!W14 -> 346.00328 | F14: ='Data BoP'!X14 -> 0 | G14: ='Data BoP'!Y14 -> 1537.4968 | H14: ='Data BoP'!Z14 -> 1945.5079 | I14: ='Data BoP'!AA14 -> 1033.6156 | J14: ='Data BoP'!AB14 -> 130.501 | ... P14: ='Data BoP'!AH14 -> 2617.8398 | Q14: ='Data BoP'!AL14 -> 1425.3282 | R14: ='Data BoP'!AJ14 -> 3534.21 | S14: ='Data BoP'!AK14 -> 1244.0903 | U14: ='Data BoP'!B14 -> 2008-Q1 | V14: =('Data BoP'!U11)+('Data BoP'!U12)+('Data BoP'!U13)+('Data BoP'!U14) -> 7034.0859 | W14: =('Data BoP'!V11)+('Data BoP'!V12)+('Data BoP'!V13)+('Data BoP'!V14) -> -7388.4974 | X14: =('Data BoP'!W11)+('Data BoP'!W12)+('Data BoP'!W13)+('Data BoP'!W14) -> 1440.6072 | Y14: =('Data BoP'!X11)+('Data BoP'!X12)+('Data BoP'!X13)+('Data BoP'!X14) -> 0 | Z14: =('Data BoP'!Y11)+('Data BoP'!Y12)+('Data BoP'!Y13)+('Data BoP'!Y14) -> 5739.2582 | AA14: =('Data BoP'!Z11)+('Data BoP'!Z12)+('Data BoP'!Z13)+('Data BoP'!Z14) -> 3089.8463 | AB14: =('Data BoP'!AA11)+('Data BoP'!AA12)+('Data BoP'!AA13)+('Data BoP'!AA14) -> -4135.0857 | AC14: =('Data BoP'!AB11)+('Data BoP'!AB12)+('Data BoP'!AB13)+('Data BoP'!AB14) -> 1262.034 | ... AI14: =('Data BoP'!AH11)+('Data BoP'!AH12)+('Data BoP'!AH13)+('Data BoP'!AH14) -> 12775.873 | AJ14: =('Data BoP'!AL11)+('Data BoP'!AL12)+('Data BoP'!AL13)+('Data BoP'!AL14) -> 6726.7429 | AK14: =('Data BoP'!AJ11)+('Data BoP'!AJ12)+('Data BoP'!AJ13)+('Data BoP'!AJ14) -> 11964.24 | AL14: =('Data BoP'!AK11)+('Data BoP'!AK12)+('Data BoP'!AK13)+('Data BoP'!AK14) -> 110.85868
B15: ='Data BoP'!B15 -> 2008-Q2 | C15: ='Data BoP'!U15 -> -667.96176 | D15: ='Data BoP'!V15 -> -1946.1919 | E15: ='Data BoP'!W15 -> 318.61091 | F15: ='Data BoP'!X15 -> 0 | G15: ='Data BoP'!Y15 -> 329.71942 | H15: ='Data BoP'!Z15 -> 1935.0834 | I15: ='Data BoP'!AA15 -> 2143.6934 | J15: ='Data BoP'!AB15 -> 669.137 | ... P15: ='Data BoP'!AH15 -> 5196.4462 | Q15: ='Data BoP'!AL15 -> 3500.8695 | R15: ='Data BoP'!AJ15 -> -2620.94 | S15: ='Data BoP'!AK15 -> -1001.9727 | U15: ='Data BoP'!B15 -> 2008-Q2 | V15: =('Data BoP'!U12)+('Data BoP'!U13)+('Data BoP'!U14)+('Data BoP'!U15) -> 5404.5319 | W15: =('Data BoP'!V12)+('Data BoP'!V13)+('Data BoP'!V14)+('Data BoP'!V15) -> -8632.3352 | X15: =('Data BoP'!W12)+('Data BoP'!W13)+('Data BoP'!W14)+('Data BoP'!W15) -> 1361.755 | Y15: =('Data BoP'!X12)+('Data BoP'!X13)+('Data BoP'!X14)+('Data BoP'!X15) -> 0 | Z15: =('Data BoP'!Y12)+('Data BoP'!Y13)+('Data BoP'!Y14)+('Data BoP'!Y15) -> 5566.3751 | AA15: =('Data BoP'!Z12)+('Data BoP'!Z13)+('Data BoP'!Z14)+('Data BoP'!Z15) -> 4427.7151 | AB15: =('Data BoP'!AA12)+('Data BoP'!AA13)+('Data BoP'!AA14)+('Data BoP'!AA15) -> 3671.3114 | AC15: =('Data BoP'!AB12)+('Data BoP'!AB13)+('Data BoP'!AB14)+('Data BoP'!AB15) -> 1532.619 | ... AI15: =('Data BoP'!AH12)+('Data BoP'!AH13)+('Data BoP'!AH14)+('Data BoP'!AH15) -> 16195.863 | AJ15: =('Data BoP'!AL12)+('Data BoP'!AL13)+('Data BoP'!AL14)+('Data BoP'!AL15) -> 9411.3133 | AK15: =('Data BoP'!AJ12)+('Data BoP'!AJ13)+('Data BoP'!AJ14)+('Data BoP'!AJ15) -> 3003.66 | AL15: =('Data BoP'!AK12)+('Data BoP'!AK13)+('Data BoP'!AK14)+('Data BoP'!AK15) -> 180.16743
B16: ='Data BoP'!B16 -> 2008-Q3 | C16: ='Data BoP'!U16 -> 4535.4996 | D16: ='Data BoP'!V16 -> -1854.0751 | E16: ='Data BoP'!W16 -> 498.52132 | F16: ='Data BoP'!X16 -> 0 | G16: ='Data BoP'!Y16 -> 1906.2467 | H16: ='Data BoP'!Z16 -> 446.3498 | I16: ='Data BoP'!AA16 -> 4012.0782 | J16: ='Data BoP'!AB16 -> 97.261 | ... P16: ='Data BoP'!AH16 -> 4809.1173 | Q16: ='Data BoP'!AL16 -> 2393.9908 | R16: ='Data BoP'!AJ16 -> -49.43 | S16: ='Data BoP'!AK16 -> 1419.7808 | U16: ='Data BoP'!B16 -> 2008-Q3 | V16: =('Data BoP'!U13)+('Data BoP'!U14)+('Data BoP'!U15)+('Data BoP'!U16) -> 9243.2695 | W16: =('Data BoP'!V13)+('Data BoP'!V14)+('Data BoP'!V15)+('Data BoP'!V16) -> -8956.3783 | X16: =('Data BoP'!W13)+('Data BoP'!W14)+('Data BoP'!W15)+('Data BoP'!W16) -> 1498.6131 | Y16: =('Data BoP'!X13)+('Data BoP'!X14)+('Data BoP'!X15)+('Data BoP'!X16) -> 0 | Z16: =('Data BoP'!Y13)+('Data BoP'!Y14)+('Data BoP'!Y15)+('Data BoP'!Y16) -> 6012.126 | AA16: =('Data BoP'!Z13)+('Data BoP'!Z14)+('Data BoP'!Z15)+('Data BoP'!Z16) -> 4442.8654 | AB16: =('Data BoP'!AA13)+('Data BoP'!AA14)+('Data BoP'!AA15)+('Data BoP'!AA16) -> 6194.5724 | AC16: =('Data BoP'!AB13)+('Data BoP'!AB14)+('Data BoP'!AB15)+('Data BoP'!AB16) -> 1383.883 | ... AI16: =('Data BoP'!AH13)+('Data BoP'!AH14)+('Data BoP'!AH15)+('Data BoP'!AH16) -> 16843.085 | AJ16: =('Data BoP'!AL13)+('Data BoP'!AL14)+('Data BoP'!AL15)+('Data BoP'!AL16) -> 9241.0899 | AK16: =('Data BoP'!AJ13)+('Data BoP'!AJ14)+('Data BoP'!AJ15)+('Data BoP'!AJ16) -> 3795.98 | AL16: =('Data BoP'!AK13)+('Data BoP'!AK14)+('Data BoP'!AK15)+('Data BoP'!AK16) -> 1454.6618
B17: ='Data BoP'!B17 -> 2008-Q4 | C17: ='Data BoP'!U17 -> 75.48052 | D17: ='Data BoP'!V17 -> -1397.3501 | E17: ='Data BoP'!W17 -> 227.79908 | F17: ='Data BoP'!X17 -> 0 | G17: ='Data BoP'!Y17 -> 1175.4658 | H17: ='Data BoP'!Z17 -> 449.68337 | I17: ='Data BoP'!AA17 -> 689.20184 | J17: ='Data BoP'!AB17 -> -370.519 | ... P17: ='Data BoP'!AH17 -> -382.88831 | Q17: ='Data BoP'!AL17 -> -1137.5771 | R17: ='Data BoP'!AJ17 -> -846.46 | S17: ='Data BoP'!AK17 -> -714.2105 | U17: ='Data BoP'!B17 -> 2008-Q4 | V17: =('Data BoP'!U14)+('Data BoP'!U15)+('Data BoP'!U16)+('Data BoP'!U17) -> 6553.9542 | W17: =('Data BoP'!V14)+('Data BoP'!V15)+('Data BoP'!V16)+('Data BoP'!V17) -> -8334.6185 | X17: =('Data BoP'!W14)+('Data BoP'!W15)+('Data BoP'!W16)+('Data BoP'!W17) -> 1390.9346 | Y17: =('Data BoP'!X14)+('Data BoP'!X15)+('Data BoP'!X16)+('Data BoP'!X17) -> 0 | Z17: =('Data BoP'!Y14)+('Data BoP'!Y15)+('Data BoP'!Y16)+('Data BoP'!Y17) -> 4948.9287 | AA17: =('Data BoP'!Z14)+('Data BoP'!Z15)+('Data BoP'!Z16)+('Data BoP'!Z17) -> 4776.6244 | AB17: =('Data BoP'!AA14)+('Data BoP'!AA15)+('Data BoP'!AA16)+('Data BoP'!AA17) -> 7878.5891 | AC17: =('Data BoP'!AB14)+('Data BoP'!AB15)+('Data BoP'!AB16)+('Data BoP'!AB17) -> 526.38 | ... AI17: =('Data BoP'!AH14)+('Data BoP'!AH15)+('Data BoP'!AH16)+('Data BoP'!AH17) -> 12240.515 | AJ17: =('Data BoP'!AL14)+('Data BoP'!AL15)+('Data BoP'!AL16)+('Data BoP'!AL17) -> 6182.6114 | AK17: =('Data BoP'!AJ14)+('Data BoP'!AJ15)+('Data BoP'!AJ16)+('Data BoP'!AJ17) -> 17.38 | AL17: =('Data BoP'!AK14)+('Data BoP'!AK15)+('Data BoP'!AK16)+('Data BoP'!AK17) -> 947.68784
B18: ='Data BoP'!B18 -> 2009-Q1 | C18: ='Data BoP'!U18 -> 1063.5869 | D18: ='Data BoP'!V18 -> -1329.3758 | E18: ='Data BoP'!W18 -> 341.10497 | F18: ='Data BoP'!X18 -> 0 | G18: ='Data BoP'!Y18 -> 1974 | H18: ='Data BoP'!Z18 -> -303.51926 | I18: ='Data BoP'!AA18 -> 826.39481 | J18: ='Data BoP'!AB18 -> 109 | ... P18: ='Data BoP'!AH18 -> 1731.6305 | Q18: ='Data BoP'!AL18 -> 431.28262 | R18: ='Data BoP'!AJ18 -> 267.12 | S18: ='Data BoP'!AK18 -> -149.17293 | U18: ='Data BoP'!B18 -> 2009-Q1 | V18: =('Data BoP'!U15)+('Data BoP'!U16)+('Data BoP'!U17)+('Data BoP'!U18) -> 5006.6053 | W18: =('Data BoP'!V15)+('Data BoP'!V16)+('Data BoP'!V17)+('Data BoP'!V18) -> -6526.9929 | X18: =('Data BoP'!W15)+('Data BoP'!W16)+('Data BoP'!W17)+('Data BoP'!W18) -> 1386.0363 | Y18: =('Data BoP'!X15)+('Data BoP'!X16)+('Data BoP'!X17)+('Data BoP'!X18) -> 0 | Z18: =('Data BoP'!Y15)+('Data BoP'!Y16)+('Data BoP'!Y17)+('Data BoP'!Y18) -> 5385.4319 | AA18: =('Data BoP'!Z15)+('Data BoP'!Z16)+('Data BoP'!Z17)+('Data BoP'!Z18) -> 2527.5973 | AB18: =('Data BoP'!AA15)+('Data BoP'!AA16)+('Data BoP'!AA17)+('Data BoP'!AA18) -> 7671.3682 | AC18: =('Data BoP'!AB15)+('Data BoP'!AB16)+('Data BoP'!AB17)+('Data BoP'!AB18) -> 504.879 | ... AI18: =('Data BoP'!AH15)+('Data BoP'!AH16)+('Data BoP'!AH17)+('Data BoP'!AH18) -> 11354.306 | AJ18: =('Data BoP'!AL15)+('Data BoP'!AL16)+('Data BoP'!AL17)+('Data BoP'!AL18) -> 5188.5658 | AK18: =('Data BoP'!AJ15)+('Data BoP'!AJ16)+('Data BoP'!AJ17)+('Data BoP'!AJ18) -> -3249.71 | AL18: =('Data BoP'!AK15)+('Data BoP'!AK16)+('Data BoP'!AK17)+('Data BoP'!AK18) -> -445.57536
B19: ='Data BoP'!B19 -> 2009-Q2 | C19: ='Data BoP'!U19 -> 3073.7654 | D19: ='Data BoP'!V19 -> -581.00071 | E19: ='Data BoP'!W19 -> -235.17713 | F19: ='Data BoP'!X19 -> 0 | G19: ='Data BoP'!Y19 -> 533 | H19: ='Data BoP'!Z19 -> -187.17642 | I19: ='Data BoP'!AA19 -> -29.596546 | J19: ='Data BoP'!AB19 -> 165 | ... P19: ='Data BoP'!AH19 -> 4536.052 | Q19: ='Data BoP'!AL19 -> 156.06941 | R19: ='Data BoP'!AJ19 -> -698.72 | S19: ='Data BoP'!AK19 -> -1224.6597 | U19: ='Data BoP'!B19 -> 2009-Q2 | V19: =('Data BoP'!U16)+('Data BoP'!U17)+('Data BoP'!U18)+('Data BoP'!U19) -> 8748.3324 | W19: =('Data BoP'!V16)+('Data BoP'!V17)+('Data BoP'!V18)+('Data BoP'!V19) -> -5161.8018 | X19: =('Data BoP'!W16)+('Data BoP'!W17)+('Data BoP'!W18)+('Data BoP'!W19) -> 832.24824 | Y19: =('Data BoP'!X16)+('Data BoP'!X17)+('Data BoP'!X18)+('Data BoP'!X19) -> 0 | Z19: =('Data BoP'!Y16)+('Data BoP'!Y17)+('Data BoP'!Y18)+('Data BoP'!Y19) -> 5588.7125 | AA19: =('Data BoP'!Z16)+('Data BoP'!Z17)+('Data BoP'!Z18)+('Data BoP'!Z19) -> 405.33749 | AB19: =('Data BoP'!AA16)+('Data BoP'!AA17)+('Data BoP'!AA18)+('Data BoP'!AA19) -> 5498.0783 | AC19: =('Data BoP'!AB16)+('Data BoP'!AB17)+('Data BoP'!AB18)+('Data BoP'!AB19) -> 0.742 | ... AI19: =('Data BoP'!AH16)+('Data BoP'!AH17)+('Data BoP'!AH18)+('Data BoP'!AH19) -> 10693.912 | AJ19: =('Data BoP'!AL16)+('Data BoP'!AL17)+('Data BoP'!AL18)+('Data BoP'!AL19) -> 1843.7657 | AK19: =('Data BoP'!AJ16)+('Data BoP'!AJ17)+('Data BoP'!AJ18)+('Data BoP'!AJ19) -> -1327.49 | AL19: =('Data BoP'!AK16)+('Data BoP'!AK17)+('Data BoP'!AK18)+('Data BoP'!AK19) -> -668.26239
B20: ='Data BoP'!B20 -> 2009-Q3 | C20: ='Data BoP'!U20 -> 556.71391 | D20: ='Data BoP'!V20 -> -330.6616 | E20: ='Data BoP'!W20 -> 354.193 | F20: ='Data BoP'!X20 -> 0 | G20: ='Data BoP'!Y20 -> 1381 | H20: ='Data BoP'!Z20 -> -696.1454 | I20: ='Data BoP'!AA20 -> 817.14725 | J20: ='Data BoP'!AB20 -> 304 | ... P20: ='Data BoP'!AH20 -> 367.69448 | Q20: ='Data BoP'!AL20 -> 2128.9562 | R20: ='Data BoP'!AJ20 -> 1811.09 | S20: ='Data BoP'!AK20 -> -202.72472 | U20: ='Data BoP'!B20 -> 2009-Q3 | V20: =('Data BoP'!U17)+('Data BoP'!U18)+('Data BoP'!U19)+('Data BoP'!U20) -> 4769.5467 | W20: =('Data BoP'!V17)+('Data BoP'!V18)+('Data BoP'!V19)+('Data BoP'!V20) -> -3638.3882 | X20: =('Data BoP'!W17)+('Data BoP'!W18)+('Data BoP'!W19)+('Data BoP'!W20) -> 687.91992 | Y20: =('Data BoP'!X17)+('Data BoP'!X18)+('Data BoP'!X19)+('Data BoP'!X20) -> 0 | Z20: =('Data BoP'!Y17)+('Data BoP'!Y18)+('Data BoP'!Y19)+('Data BoP'!Y20) -> 5063.4658 | AA20: =('Data BoP'!Z17)+('Data BoP'!Z18)+('Data BoP'!Z19)+('Data BoP'!Z20) -> -737.15771 | AB20: =('Data BoP'!AA17)+('Data BoP'!AA18)+('Data BoP'!AA19)+('Data BoP'!AA20) -> 2303.1474 | AC20: =('Data BoP'!AB17)+('Data BoP'!AB18)+('Data BoP'!AB19)+('Data BoP'!AB20) -> 207.481 | ... AI20: =('Data BoP'!AH17)+('Data BoP'!AH18)+('Data BoP'!AH19)+('Data BoP'!AH20) -> 6252.4887 | AJ20: =('Data BoP'!AL17)+('Data BoP'!AL18)+('Data BoP'!AL19)+('Data BoP'!AL20) -> 1578.7311 | AK20: =('Data BoP'!AJ17)+('Data BoP'!AJ18)+('Data BoP'!AJ19)+('Data BoP'!AJ20) -> 533.03 | AL20: =('Data BoP'!AK17)+('Data BoP'!AK18)+('Data BoP'!AK19)+('Data BoP'!AK20) -> -2290.7679
... B86: ='Data BoP'!B86 -> 2026-Q1 | C86: ='Data BoP'!U86 -> -2398.2541 | D86: ='Data BoP'!V86 -> -1290.6768 | E86: ='Data BoP'!W86 -> 503.0621 | F86: ='Data BoP'!X86 -> 0 | G86: ='Data BoP'!Y86 -> 1913.9839 | H86: ='Data BoP'!Z86 -> -120.245 | I86: ='Data BoP'!AA86 -> 656.59172 | J86: ='Data BoP'!AB86 -> 397.43909 | ... P86: ='Data BoP'!AH86 -> -575.69209 | Q86: ='Data BoP'!AL86 -> 1188.7106 | R86: ='Data BoP'!AJ86 -> 10.584206 | S86: ='Data BoP'!AK86 -> -811.10384 | U86: ='Data BoP'!B86 -> 2026-Q1 | V86: =('Data BoP'!U83)+('Data BoP'!U84)+('Data BoP'!U85)+('Data BoP'!U86) -> -7212.243 | W86: =('Data BoP'!V83)+('Data BoP'!V84)+('Data BoP'!V85)+('Data BoP'!V86) -> -2596.103 | X86: =('Data BoP'!W83)+('Data BoP'!W84)+('Data BoP'!W85)+('Data BoP'!W86) -> 2694.4886 | Y86: =('Data BoP'!X83)+('Data BoP'!X84)+('Data BoP'!X85)+('Data BoP'!X86) -> 0 | Z86: =('Data BoP'!Y83)+('Data BoP'!Y84)+('Data BoP'!Y85)+('Data BoP'!Y86) -> 5038.1567 | AA86: =('Data BoP'!Z83)+('Data BoP'!Z84)+('Data BoP'!Z85)+('Data BoP'!Z86) -> 252.435 | AB86: =('Data BoP'!AA83)+('Data BoP'!AA84)+('Data BoP'!AA85)+('Data BoP'!AA86) -> -2316.0948 | AC86: =('Data BoP'!AB83)+('Data BoP'!AB84)+('Data BoP'!AB85)+('Data BoP'!AB86) -> 2007.8701 | ... AI86: =('Data BoP'!AH83)+('Data BoP'!AH84)+('Data BoP'!AH85)+('Data BoP'!AH86) -> 12601.479 | AJ86: =('Data BoP'!AL83)+('Data BoP'!AL84)+('Data BoP'!AL85)+('Data BoP'!AL86) -> 27762.178 | AK86: =('Data BoP'!AJ83)+('Data BoP'!AJ84)+('Data BoP'!AJ85)+('Data BoP'!AJ86) -> 12859.159 | AL86: =('Data BoP'!AK83)+('Data BoP'!AK84)+('Data BoP'!AK85)+('Data BoP'!AK86) -> -3389.5408
B89: Annual
B90: Year | C90: FINANCIAL ACCOUNT | D90: Direct investment, net | E90: DI assets (equity) | F90: DI assets (debt) | G90: DI liabilities (equity) | H90: DI liabilities (debt) | I90: Portfolio investment, net | J90: PI assets (equity) | K90: PI assets (debt) | L90: PI liabilities (equity) | M90: PI liabilities (debt) | N90: Financial derivatives | O90: Other investment, net | P90: OI assets | Q90: OI liabilities (corrected) | R90: RESERVE ASSETS | S90: Errors & omissions
B91: 2006 | C91: =SUMIFS('Data BoP'!$U$6:$U$86,'Data BoP'!$C$6:$C$86,$B91) -> 7480.4309 | D91: =SUMIFS('Data BoP'!$V$6:$V$86,'Data BoP'!$C$6:$C$86,$B91) -> -3098.6271 | E91: =SUMIFS('Data BoP'!$W$6:$W$86,'Data BoP'!$C$6:$C$86,$B91) -> 2438.7207 | F91: =SUMIFS('Data BoP'!$X$6:$X$86,'Data BoP'!$C$6:$C$86,$B91) -> 0 | G91: =SUMIFS('Data BoP'!$Y$6:$Y$86,'Data BoP'!$C$6:$C$86,$B91) -> 5274.3478 | H91: =SUMIFS('Data BoP'!$Z$6:$Z$86,'Data BoP'!$C$6:$C$86,$B91) -> 263 | I91: =SUMIFS('Data BoP'!$AA$6:$AA$86,'Data BoP'!$C$6:$C$86,$B91) -> -7239.3968 | J91: =SUMIFS('Data BoP'!$AB$6:$AB$86,'Data BoP'!$C$6:$C$86,$B91) -> 401.758 | K91: =SUMIFS('Data BoP'!$AC$6:$AC$86,'Data BoP'!$C$6:$C$86,$B91) -> 859.2356 | L91: =SUMIFS('Data BoP'!$AD$6:$AD$86,'Data BoP'!$C$6:$C$86,$B91) -> 706.65573 | M91: =SUMIFS('Data BoP'!$AE$6:$AE$86,'Data BoP'!$C$6:$C$86,$B91) -> 7793.7347 | N91: =SUMIFS('Data BoP'!$AF$6:$AF$86,'Data BoP'!$C$6:$C$86,$B91) -> 126.64454 | O91: =SUMIFS('Data BoP'!$AG$6:$AG$86,'Data BoP'!$C$6:$C$86,$B91) -> 14161.98 | P91: =SUMIFS('Data BoP'!$AH$6:$AH$86,'Data BoP'!$C$6:$C$86,$B91) -> 3240.5685 | Q91: =SUMIFS('Data BoP'!$AL$6:$AL$86,'Data BoP'!$C$6:$C$86,$B91) -> -10921.412 | R91: =SUMIFS('Data BoP'!$AJ$6:$AJ$86,'Data BoP'!$C$6:$C$86,$B91) -> 3529.83 | S91: =SUMIFS('Data BoP'!$AK$6:$AK$86,'Data BoP'!$C$6:$C$86,$B91) -> 884.00404
B92: 2007 | C92: =SUMIFS('Data BoP'!$U$6:$U$86,'Data BoP'!$C$6:$C$86,$B92) -> 5899.4469 | D92: =SUMIFS('Data BoP'!$V$6:$V$86,'Data BoP'!$C$6:$C$86,$B92) -> -4968.9248 | E92: =SUMIFS('Data BoP'!$W$6:$W$86,'Data BoP'!$C$6:$C$86,$B92) -> 1504.233 | F92: =SUMIFS('Data BoP'!$X$6:$X$86,'Data BoP'!$C$6:$C$86,$B92) -> 0 | G92: =SUMIFS('Data BoP'!$Y$6:$Y$86,'Data BoP'!$C$6:$C$86,$B92) -> 4627.5209 | H92: =SUMIFS('Data BoP'!$Z$6:$Z$86,'Data BoP'!$C$6:$C$86,$B92) -> 1845.6368 | I92: =SUMIFS('Data BoP'!$AA$6:$AA$86,'Data BoP'!$C$6:$C$86,$B92) -> -7467.9629 | J92: =SUMIFS('Data BoP'!$AB$6:$AB$86,'Data BoP'!$C$6:$C$86,$B92) -> 1389.358 | K92: =SUMIFS('Data BoP'!$AC$6:$AC$86,'Data BoP'!$C$6:$C$86,$B92) -> -215.8092 | L92: =SUMIFS('Data BoP'!$AD$6:$AD$86,'Data BoP'!$C$6:$C$86,$B92) -> 1784.935 | M92: =SUMIFS('Data BoP'!$AE$6:$AE$86,'Data BoP'!$C$6:$C$86,$B92) -> 6856.5767 | N92: =SUMIFS('Data BoP'!$AF$6:$AF$86,'Data BoP'!$C$6:$C$86,$B92) -> 564.58741 | O92: =SUMIFS('Data BoP'!$AG$6:$AG$86,'Data BoP'!$C$6:$C$86,$B92) -> 4682.0272 | P92: =SUMIFS('Data BoP'!$AH$6:$AH$86,'Data BoP'!$C$6:$C$86,$B92) -> 10556.673 | Q92: =SUMIFS('Data BoP'!$AL$6:$AL$86,'Data BoP'!$C$6:$C$86,$B92) -> 5874.6463 | R92: =SUMIFS('Data BoP'!$AJ$6:$AJ$86,'Data BoP'!$C$6:$C$86,$B92) -> 13089.72 | S92: =SUMIFS('Data BoP'!$AK$6:$AK$86,'Data BoP'!$C$6:$C$86,$B92) -> -270.2369
B93: 2008 | C93: =SUMIFS('Data BoP'!$U$6:$U$86,'Data BoP'!$C$6:$C$86,$B93) -> 6553.9542 | D93: =SUMIFS('Data BoP'!$V$6:$V$86,'Data BoP'!$C$6:$C$86,$B93) -> -8334.6185 | E93: =SUMIFS('Data BoP'!$W$6:$W$86,'Data BoP'!$C$6:$C$86,$B93) -> 1390.9346 | F93: =SUMIFS('Data BoP'!$X$6:$X$86,'Data BoP'!$C$6:$C$86,$B93) -> 0 | G93: =SUMIFS('Data BoP'!$Y$6:$Y$86,'Data BoP'!$C$6:$C$86,$B93) -> 4948.9287 | H93: =SUMIFS('Data BoP'!$Z$6:$Z$86,'Data BoP'!$C$6:$C$86,$B93) -> 4776.6244 | I93: =SUMIFS('Data BoP'!$AA$6:$AA$86,'Data BoP'!$C$6:$C$86,$B93) -> 7878.5891 | J93: =SUMIFS('Data BoP'!$AB$6:$AB$86,'Data BoP'!$C$6:$C$86,$B93) -> 526.38 | K93: =SUMIFS('Data BoP'!$AC$6:$AC$86,'Data BoP'!$C$6:$C$86,$B93) -> 1629.1838 | L93: =SUMIFS('Data BoP'!$AD$6:$AD$86,'Data BoP'!$C$6:$C$86,$B93) -> -530.62178 | M93: =SUMIFS('Data BoP'!$AE$6:$AE$86,'Data BoP'!$C$6:$C$86,$B93) -> -5192.4034 | N93: =SUMIFS('Data BoP'!$AF$6:$AF$86,'Data BoP'!$C$6:$C$86,$B93) -> 934.7 | O93: =SUMIFS('Data BoP'!$AG$6:$AG$86,'Data BoP'!$C$6:$C$86,$B93) -> 6057.9037 | P93: =SUMIFS('Data BoP'!$AH$6:$AH$86,'Data BoP'!$C$6:$C$86,$B93) -> 12240.515 | Q93: =SUMIFS('Data BoP'!$AL$6:$AL$86,'Data BoP'!$C$6:$C$86,$B93) -> 6182.6114 | R93: =SUMIFS('Data BoP'!$AJ$6:$AJ$86,'Data BoP'!$C$6:$C$86,$B93) -> 17.38 | S93: =SUMIFS('Data BoP'!$AK$6:$AK$86,'Data BoP'!$C$6:$C$86,$B93) -> 947.68784
B94: 2009 | C94: =SUMIFS('Data BoP'!$U$6:$U$86,'Data BoP'!$C$6:$C$86,$B94) -> 6712.7826 | D94: =SUMIFS('Data BoP'!$V$6:$V$86,'Data BoP'!$C$6:$C$86,$B94) -> -3305.6125 | E94: =SUMIFS('Data BoP'!$W$6:$W$86,'Data BoP'!$C$6:$C$86,$B94) -> 711.5464 | F94: =SUMIFS('Data BoP'!$X$6:$X$86,'Data BoP'!$C$6:$C$86,$B94) -> 0 | G94: =SUMIFS('Data BoP'!$Y$6:$Y$86,'Data BoP'!$C$6:$C$86,$B94) -> 5027 | H94: =SUMIFS('Data BoP'!$Z$6:$Z$86,'Data BoP'!$C$6:$C$86,$B94) -> -1009.8411 | I94: =SUMIFS('Data BoP'!$AA$6:$AA$86,'Data BoP'!$C$6:$C$86,$B94) -> 2153.1431 | J94: =SUMIFS('Data BoP'!$AB$6:$AB$86,'Data BoP'!$C$6:$C$86,$B94) -> 983 | K94: =SUMIFS('Data BoP'!$AC$6:$AC$86,'Data BoP'!$C$6:$C$86,$B94) -> -337.46609 | L94: =SUMIFS('Data BoP'!$AD$6:$AD$86,'Data BoP'!$C$6:$C$86,$B94) -> -211.91786 | M94: =SUMIFS('Data BoP'!$AE$6:$AE$86,'Data BoP'!$C$6:$C$86,$B94) -> -1295.6914 | N94: =SUMIFS('Data BoP'!$AF$6:$AF$86,'Data BoP'!$C$6:$C$86,$B94) -> 1248.3 | O94: =SUMIFS('Data BoP'!$AG$6:$AG$86,'Data BoP'!$C$6:$C$86,$B94) -> 5270.742 | P94: =SUMIFS('Data BoP'!$AH$6:$AH$86,'Data BoP'!$C$6:$C$86,$B94) -> 6179.3211 | Q94: =SUMIFS('Data BoP'!$AL$6:$AL$86,'Data BoP'!$C$6:$C$86,$B94) -> 908.57907 | R94: =SUMIFS('Data BoP'!$AJ$6:$AJ$86,'Data BoP'!$C$6:$C$86,$B94) -> 1346.21 | S94: =SUMIFS('Data BoP'!$AK$6:$AK$86,'Data BoP'!$C$6:$C$86,$B94) -> -621.31729
B95: 2010 | C95: =SUMIFS('Data BoP'!$U$6:$U$86,'Data BoP'!$C$6:$C$86,$B95) -> -3802.1033 | D95: =SUMIFS('Data BoP'!$V$6:$V$86,'Data BoP'!$C$6:$C$86,$B95) -> -10367.958 | E95: =SUMIFS('Data BoP'!$W$6:$W$86,'Data BoP'!$C$6:$C$86,$B95) -> 964.76068 | F95: =SUMIFS('Data BoP'!$X$6:$X$86,'Data BoP'!$C$6:$C$86,$B95) -> 0 | G95: =SUMIFS('Data BoP'!$Y$6:$Y$86,'Data BoP'!$C$6:$C$86,$B95) -> 7826.037 | H95: =SUMIFS('Data BoP'!$Z$6:$Z$86,'Data BoP'!$C$6:$C$86,$B95) -> 3506.6816 | I95: =SUMIFS('Data BoP'!$AA$6:$AA$86,'Data BoP'!$C$6:$C$86,$B95) -> -3262.1936 | J95: =SUMIFS('Data BoP'!$AB$6:$AB$86,'Data BoP'!$C$6:$C$86,$B95) -> 640 | K95: =SUMIFS('Data BoP'!$AC$6:$AC$86,'Data BoP'!$C$6:$C$86,$B95) -> -1226.4127 | L95: =SUMIFS('Data BoP'!$AD$6:$AD$86,'Data BoP'!$C$6:$C$86,$B95) -> -71.016322 | M95: =SUMIFS('Data BoP'!$AE$6:$AE$86,'Data BoP'!$C$6:$C$86,$B95) -> 2746.7972 | N95: =SUMIFS('Data BoP'!$AF$6:$AF$86,'Data BoP'!$C$6:$C$86,$B95) -> -712.25797 | O95: =SUMIFS('Data BoP'!$AG$6:$AG$86,'Data BoP'!$C$6:$C$86,$B95) -> 6382.9562 | P95: =SUMIFS('Data BoP'!$AH$6:$AH$86,'Data BoP'!$C$6:$C$86,$B95) -> 8717.0328 | Q95: =SUMIFS('Data BoP'!$AL$6:$AL$86,'Data BoP'!$C$6:$C$86,$B95) -> 2334.0766 | R95: =SUMIFS('Data BoP'!$AJ$6:$AJ$86,'Data BoP'!$C$6:$C$86,$B95) -> 4157.35 | S95: =SUMIFS('Data BoP'!$AK$6:$AK$86,'Data BoP'!$C$6:$C$86,$B95) -> -2257.5853
B96: 2011 | C96: =SUMIFS('Data BoP'!$U$6:$U$86,'Data BoP'!$C$6:$C$86,$B96) -> -5252.203 | D96: =SUMIFS('Data BoP'!$V$6:$V$86,'Data BoP'!$C$6:$C$86,$B96) -> -9351.9309 | E96: =SUMIFS('Data BoP'!$W$6:$W$86,'Data BoP'!$C$6:$C$86,$B96) -> 1488 | F96: =SUMIFS('Data BoP'!$X$6:$X$86,'Data BoP'!$C$6:$C$86,$B96) -> 0 | G96: =SUMIFS('Data BoP'!$Y$6:$Y$86,'Data BoP'!$C$6:$C$86,$B96) -> 8240.3606 | H96: =SUMIFS('Data BoP'!$Z$6:$Z$86,'Data BoP'!$C$6:$C$86,$B96) -> 2599.5704 | I96: =SUMIFS('Data BoP'!$AA$6:$AA$86,'Data BoP'!$C$6:$C$86,$B96) -> -143.23416 | J96: =SUMIFS('Data BoP'!$AB$6:$AB$86,'Data BoP'!$C$6:$C$86,$B96) -> -197 | K96: =SUMIFS('Data BoP'!$AC$6:$AC$86,'Data BoP'!$C$6:$C$86,$B96) -> -194.61992 | L96: =SUMIFS('Data BoP'!$AD$6:$AD$86,'Data BoP'!$C$6:$C$86,$B96) -> -208.19566 | M96: =SUMIFS('Data BoP'!$AE$6:$AE$86,'Data BoP'!$C$6:$C$86,$B96) -> -40.190098 | N96: =SUMIFS('Data BoP'!$AF$6:$AF$86,'Data BoP'!$C$6:$C$86,$B96) -> 2356.1814 | O96: =SUMIFS('Data BoP'!$AG$6:$AG$86,'Data BoP'!$C$6:$C$86,$B96) -> 7994.6907 | P96: =SUMIFS('Data BoP'!$AH$6:$AH$86,'Data BoP'!$C$6:$C$86,$B96) -> 19013.445 | Q96: =SUMIFS('Data BoP'!$AL$6:$AL$86,'Data BoP'!$C$6:$C$86,$B96) -> 11018.755 | R96: =SUMIFS('Data BoP'!$AJ$6:$AJ$86,'Data BoP'!$C$6:$C$86,$B96) -> -6107.91 | S96: =SUMIFS('Data BoP'!$AK$6:$AK$86,'Data BoP'!$C$6:$C$86,$B96) -> 25.254371
B97: 2012 | C97: =SUMIFS('Data BoP'!$U$6:$U$86,'Data BoP'!$C$6:$C$86,$B97) -> -2788.1356 | D97: =SUMIFS('Data BoP'!$V$6:$V$86,'Data BoP'!$C$6:$C$86,$B97) -> -14269.084 | E97: =SUMIFS('Data BoP'!$W$6:$W$86,'Data BoP'!$C$6:$C$86,$B97) -> 1054.8496 | F97: =SUMIFS('Data BoP'!$X$6:$X$86,'Data BoP'!$C$6:$C$86,$B97) -> 0 | G97: =SUMIFS('Data BoP'!$Y$6:$Y$86,'Data BoP'!$C$6:$C$86,$B97) -> 12203.816 | H97: =SUMIFS('Data BoP'!$Z$6:$Z$86,'Data BoP'!$C$6:$C$86,$B97) -> 3120.1176 | I97: =SUMIFS('Data BoP'!$AA$6:$AA$86,'Data BoP'!$C$6:$C$86,$B97) -> 149.91833 | J97: =SUMIFS('Data BoP'!$AB$6:$AB$86,'Data BoP'!$C$6:$C$86,$B97) -> 131 | K97: =SUMIFS('Data BoP'!$AC$6:$AC$86,'Data BoP'!$C$6:$C$86,$B97) -> 133.92492 | L97: =SUMIFS('Data BoP'!$AD$6:$AD$86,'Data BoP'!$C$6:$C$86,$B97) -> -134.90772 | M97: =SUMIFS('Data BoP'!$AE$6:$AE$86,'Data BoP'!$C$6:$C$86,$B97) -> 249.91431 | N97: =SUMIFS('Data BoP'!$AF$6:$AF$86,'Data BoP'!$C$6:$C$86,$B97) -> 2908.1815 | O97: =SUMIFS('Data BoP'!$AG$6:$AG$86,'Data BoP'!$C$6:$C$86,$B97) -> 11727.569 | P97: =SUMIFS('Data BoP'!$AH$6:$AH$86,'Data BoP'!$C$6:$C$86,$B97) -> 9722.0574 | Q97: =SUMIFS('Data BoP'!$AL$6:$AL$86,'Data BoP'!$C$6:$C$86,$B97) -> -2005.5115 | R97: =SUMIFS('Data BoP'!$AJ$6:$AJ$86,'Data BoP'!$C$6:$C$86,$B97) -> -3304.72 | S97: =SUMIFS('Data BoP'!$AK$6:$AK$86,'Data BoP'!$C$6:$C$86,$B97) -> -697.9793
B98: 2013 | C98: =SUMIFS('Data BoP'!$U$6:$U$86,'Data BoP'!$C$6:$C$86,$B98) -> -16164.896 | D98: =SUMIFS('Data BoP'!$V$6:$V$86,'Data BoP'!$C$6:$C$86,$B98) -> -8931.689 | E98: =SUMIFS('Data BoP'!$W$6:$W$86,'Data BoP'!$C$6:$C$86,$B98) -> 889.97286 | F98: =SUMIFS('Data BoP'!$X$6:$X$86,'Data BoP'!$C$6:$C$86,$B98) -> 0 | G98: =SUMIFS('Data BoP'!$Y$6:$Y$86,'Data BoP'!$C$6:$C$86,$B98) -> 10604.662 | H98: =SUMIFS('Data BoP'!$Z$6:$Z$86,'Data BoP'!$C$6:$C$86,$B98) -> -783 | I98: =SUMIFS('Data BoP'!$AA$6:$AA$86,'Data BoP'!$C$6:$C$86,$B98) -> -432.58592 | J98: =SUMIFS('Data BoP'!$AB$6:$AB$86,'Data BoP'!$C$6:$C$86,$B98) -> 116.48223 | K98: =SUMIFS('Data BoP'!$AC$6:$AC$86,'Data BoP'!$C$6:$C$86,$B98) -> 380.07661 | L98: =SUMIFS('Data BoP'!$AD$6:$AD$86,'Data BoP'!$C$6:$C$86,$B98) -> 341.87778 | M98: =SUMIFS('Data BoP'!$AE$6:$AE$86,'Data BoP'!$C$6:$C$86,$B98) -> 587.26697 | N98: =SUMIFS('Data BoP'!$AF$6:$AF$86,'Data BoP'!$C$6:$C$86,$B98) -> -32.376672 | O98: =SUMIFS('Data BoP'!$AG$6:$AG$86,'Data BoP'!$C$6:$C$86,$B98) -> 5055.5151 | P98: =SUMIFS('Data BoP'!$AH$6:$AH$86,'Data BoP'!$C$6:$C$86,$B98) -> 3892.6512 | Q98: =SUMIFS('Data BoP'!$AL$6:$AL$86,'Data BoP'!$C$6:$C$86,$B98) -> -1162.8639 | R98: =SUMIFS('Data BoP'!$AJ$6:$AJ$86,'Data BoP'!$C$6:$C$86,$B98) -> -11823.76 | S98: =SUMIFS('Data BoP'!$AK$6:$AK$86,'Data BoP'!$C$6:$C$86,$B98) -> -3073.9356
B99: 2014 | C99: =SUMIFS('Data BoP'!$U$6:$U$86,'Data BoP'!$C$6:$C$86,$B99) -> -9320.6723 | D99: =SUMIFS('Data BoP'!$V$6:$V$86,'Data BoP'!$C$6:$C$86,$B99) -> -3144.7941 | E99: =SUMIFS('Data BoP'!$W$6:$W$86,'Data BoP'!$C$6:$C$86,$B99) -> 1920.5414 | F99: =SUMIFS('Data BoP'!$X$6:$X$86,'Data BoP'!$C$6:$C$86,$B99) -> 0 | G99: =SUMIFS('Data BoP'!$Y$6:$Y$86,'Data BoP'!$C$6:$C$86,$B99) -> 6009.8602 | H99: =SUMIFS('Data BoP'!$Z$6:$Z$86,'Data BoP'!$C$6:$C$86,$B99) -> -944.52461 | I99: =SUMIFS('Data BoP'!$AA$6:$AA$86,'Data BoP'!$C$6:$C$86,$B99) -> 2339.4304 | J99: =SUMIFS('Data BoP'!$AB$6:$AB$86,'Data BoP'!$C$6:$C$86,$B99) -> -184.67743 | K99: =SUMIFS('Data BoP'!$AC$6:$AC$86,'Data BoP'!$C$6:$C$86,$B99) -> 159.46524 | L99: =SUMIFS('Data BoP'!$AD$6:$AD$86,'Data BoP'!$C$6:$C$86,$B99) -> 217.8996 | M99: =SUMIFS('Data BoP'!$AE$6:$AE$86,'Data BoP'!$C$6:$C$86,$B99) -> -2582.5422 | N99: =SUMIFS('Data BoP'!$AF$6:$AF$86,'Data BoP'!$C$6:$C$86,$B99) -> -168.2069 | O99: =SUMIFS('Data BoP'!$AG$6:$AG$86,'Data BoP'!$C$6:$C$86,$B99) -> -9542.2117 | P99: =SUMIFS('Data BoP'!$AH$6:$AH$86,'Data BoP'!$C$6:$C$86,$B99) -> 1422.0058 | Q99: =SUMIFS('Data BoP'!$AL$6:$AL$86,'Data BoP'!$C$6:$C$86,$B99) -> 10964.218 | R99: =SUMIFS('Data BoP'!$AJ$6:$AJ$86,'Data BoP'!$C$6:$C$86,$B99) -> 1195.11 | S99: =SUMIFS('Data BoP'!$AK$6:$AK$86,'Data BoP'!$C$6:$C$86,$B99) -> -198.44314
B100: 2015 | C100: =SUMIFS('Data BoP'!$U$6:$U$86,'Data BoP'!$C$6:$C$86,$B100) -> -18497.849 | D100: =SUMIFS('Data BoP'!$V$6:$V$86,'Data BoP'!$C$6:$C$86,$B100) -> -10883.761 | E100: =SUMIFS('Data BoP'!$W$6:$W$86,'Data BoP'!$C$6:$C$86,$B100) -> 875.23323 | F100: =SUMIFS('Data BoP'!$X$6:$X$86,'Data BoP'!$C$6:$C$86,$B100) -> 0 | G100: =SUMIFS('Data BoP'!$Y$6:$Y$86,'Data BoP'!$C$6:$C$86,$B100) -> 9376.5157 | H100: =SUMIFS('Data BoP'!$Z$6:$Z$86,'Data BoP'!$C$6:$C$86,$B100) -> 2382.4784 | I100: =SUMIFS('Data BoP'!$AA$6:$AA$86,'Data BoP'!$C$6:$C$86,$B100) -> -437.23881 | J100: =SUMIFS('Data BoP'!$AB$6:$AB$86,'Data BoP'!$C$6:$C$86,$B100) -> -176.39004 | K100: =SUMIFS('Data BoP'!$AC$6:$AC$86,'Data BoP'!$C$6:$C$86,$B100) -> 269.07263 | L100: =SUMIFS('Data BoP'!$AD$6:$AD$86,'Data BoP'!$C$6:$C$86,$B100) -> 239.11155 | M100: =SUMIFS('Data BoP'!$AE$6:$AE$86,'Data BoP'!$C$6:$C$86,$B100) -> 290.80985 | N100: =SUMIFS('Data BoP'!$AF$6:$AF$86,'Data BoP'!$C$6:$C$86,$B100) -> -24.991331 | O100: =SUMIFS('Data BoP'!$AG$6:$AG$86,'Data BoP'!$C$6:$C$86,$B100) -> -2245.8883 | P100: =SUMIFS('Data BoP'!$AH$6:$AH$86,'Data BoP'!$C$6:$C$86,$B100) -> 8813.6526 | Q100: =SUMIFS('Data BoP'!$AL$6:$AL$86,'Data BoP'!$C$6:$C$86,$B100) -> 11059.541 | R100: =SUMIFS('Data BoP'!$AJ$6:$AJ$86,'Data BoP'!$C$6:$C$86,$B100) -> -4905.97 | S100: =SUMIFS('Data BoP'!$AK$6:$AK$86,'Data BoP'!$C$6:$C$86,$B100) -> -927.79325
B101: 2016 | C101: =SUMIFS('Data BoP'!$U$6:$U$86,'Data BoP'!$C$6:$C$86,$B101) -> -13964.056 | D101: =SUMIFS('Data BoP'!$V$6:$V$86,'Data BoP'!$C$6:$C$86,$B101) -> -1473.6334 | E101: =SUMIFS('Data BoP'!$W$6:$W$86,'Data BoP'!$C$6:$C$86,$B101) -> 1786.5309 | F101: =SUMIFS('Data BoP'!$X$6:$X$86,'Data BoP'!$C$6:$C$86,$B101) -> 0 | G101: =SUMIFS('Data BoP'!$Y$6:$Y$86,'Data BoP'!$C$6:$C$86,$B101) -> 7991.847 | H101: =SUMIFS('Data BoP'!$Z$6:$Z$86,'Data BoP'!$C$6:$C$86,$B101) -> -4731.6827 | I101: =SUMIFS('Data BoP'!$AA$6:$AA$86,'Data BoP'!$C$6:$C$86,$B101) -> -35255.294 | J101: =SUMIFS('Data BoP'!$AB$6:$AB$86,'Data BoP'!$C$6:$C$86,$B101) -> -978.25588 | K101: =SUMIFS('Data BoP'!$AC$6:$AC$86,'Data BoP'!$C$6:$C$86,$B101) -> 1776.0954 | L101: =SUMIFS('Data BoP'!$AD$6:$AD$86,'Data BoP'!$C$6:$C$86,$B101) -> 985.21667 | M101: =SUMIFS('Data BoP'!$AE$6:$AE$86,'Data BoP'!$C$6:$C$86,$B101) -> 35067.917 | N101: =SUMIFS('Data BoP'!$AF$6:$AF$86,'Data BoP'!$C$6:$C$86,$B101) -> 222.04504 | O101: =SUMIFS('Data BoP'!$AG$6:$AG$86,'Data BoP'!$C$6:$C$86,$B101) -> 8231.5905 | P101: =SUMIFS('Data BoP'!$AH$6:$AH$86,'Data BoP'!$C$6:$C$86,$B101) -> 2689.3872 | Q101: =SUMIFS('Data BoP'!$AL$6:$AL$86,'Data BoP'!$C$6:$C$86,$B101) -> -5542.2034 | R101: =SUMIFS('Data BoP'!$AJ$6:$AJ$86,'Data BoP'!$C$6:$C$86,$B101) -> 14311.235 | S101: =SUMIFS('Data BoP'!$AK$6:$AK$86,'Data BoP'!$C$6:$C$86,$B101) -> 774.91576
B102: 2017 | C102: =SUMIFS('Data BoP'!$U$6:$U$86,'Data BoP'!$C$6:$C$86,$B102) -> -31273.188 | D102: =SUMIFS('Data BoP'!$V$6:$V$86,'Data BoP'!$C$6:$C$86,$B102) -> -10361.231 | E102: =SUMIFS('Data BoP'!$W$6:$W$86,'Data BoP'!$C$6:$C$86,$B102) -> 1155.6302 | F102: =SUMIFS('Data BoP'!$X$6:$X$86,'Data BoP'!$C$6:$C$86,$B102) -> 0 | G102: =SUMIFS('Data BoP'!$Y$6:$Y$86,'Data BoP'!$C$6:$C$86,$B102) -> 9094.8013 | H102: =SUMIFS('Data BoP'!$Z$6:$Z$86,'Data BoP'!$C$6:$C$86,$B102) -> 2422.0602 | I102: =SUMIFS('Data BoP'!$AA$6:$AA$86,'Data BoP'!$C$6:$C$86,$B102) -> -35921.739 | J102: =SUMIFS('Data BoP'!$AB$6:$AB$86,'Data BoP'!$C$6:$C$86,$B102) -> 307.80044 | K102: =SUMIFS('Data BoP'!$AC$6:$AC$86,'Data BoP'!$C$6:$C$86,$B102) -> 5194.5378 | L102: =SUMIFS('Data BoP'!$AD$6:$AD$86,'Data BoP'!$C$6:$C$86,$B102) -> 3013.3 | M102: =SUMIFS('Data BoP'!$AE$6:$AE$86,'Data BoP'!$C$6:$C$86,$B102) -> 38410.778 | N102: =SUMIFS('Data BoP'!$AF$6:$AF$86,'Data BoP'!$C$6:$C$86,$B102) -> -96.2256 | O102: =SUMIFS('Data BoP'!$AG$6:$AG$86,'Data BoP'!$C$6:$C$86,$B102) -> 550.30288 | P102: =SUMIFS('Data BoP'!$AH$6:$AH$86,'Data BoP'!$C$6:$C$86,$B102) -> 12506.083 | Q102: =SUMIFS('Data BoP'!$AL$6:$AL$86,'Data BoP'!$C$6:$C$86,$B102) -> 11955.78 | R102: =SUMIFS('Data BoP'!$AJ$6:$AJ$86,'Data BoP'!$C$6:$C$86,$B102) -> 14555.706 | S102: =SUMIFS('Data BoP'!$AK$6:$AK$86,'Data BoP'!$C$6:$C$86,$B102) -> -295.33165
... B110: 2025 | C110: =SUMIFS('Data BoP'!$U$6:$U$86,'Data BoP'!$C$6:$C$86,$B110) -> -12003.104 | D110: =SUMIFS('Data BoP'!$V$6:$V$86,'Data BoP'!$C$6:$C$86,$B110) -> -1618.3973 | E110: =SUMIFS('Data BoP'!$W$6:$W$86,'Data BoP'!$C$6:$C$86,$B110) -> 2743.3313 | F110: =SUMIFS('Data BoP'!$X$6:$X$86,'Data BoP'!$C$6:$C$86,$B110) -> 0 | G110: =SUMIFS('Data BoP'!$Y$6:$Y$86,'Data BoP'!$C$6:$C$86,$B110) -> 3629.5496 | H110: =SUMIFS('Data BoP'!$Z$6:$Z$86,'Data BoP'!$C$6:$C$86,$B110) -> 732.179 | I110: =SUMIFS('Data BoP'!$AA$6:$AA$86,'Data BoP'!$C$6:$C$86,$B110) -> 278.16234 | J110: =SUMIFS('Data BoP'!$AB$6:$AB$86,'Data BoP'!$C$6:$C$86,$B110) -> 2356.2561 | K110: =SUMIFS('Data BoP'!$AC$6:$AC$86,'Data BoP'!$C$6:$C$86,$B110) -> 3642.6408 | L110: =SUMIFS('Data BoP'!$AD$6:$AD$86,'Data BoP'!$C$6:$C$86,$B110) -> -1418.0092 | M110: =SUMIFS('Data BoP'!$AE$6:$AE$86,'Data BoP'!$C$6:$C$86,$B110) -> 7138.7438 | N110: =SUMIFS('Data BoP'!$AF$6:$AF$86,'Data BoP'!$C$6:$C$86,$B110) -> 2.7203365 | O110: =SUMIFS('Data BoP'!$AG$6:$AG$86,'Data BoP'!$C$6:$C$86,$B110) -> -17886.663 | P110: =SUMIFS('Data BoP'!$AH$6:$AH$86,'Data BoP'!$C$6:$C$86,$B110) -> 10075.25 | Q110: =SUMIFS('Data BoP'!$AL$6:$AL$86,'Data BoP'!$C$6:$C$86,$B110) -> 27961.913 | R110: =SUMIFS('Data BoP'!$AJ$6:$AJ$86,'Data BoP'!$C$6:$C$86,$B110) -> 7221.074 | S110: =SUMIFS('Data BoP'!$AK$6:$AK$86,'Data BoP'!$C$6:$C$86,$B110) -> -4669.1182

Sheet Funding
B2: How the current account is funded — and what that leaves for reserves
B3: Four-quarter rolling, millions of US dollars. Everything is restated INFLOW-POSITIVE: a positive number adds to Argentina's dollars, a negative number takes them away.
B4: Read it down. The current account plus the capital account is the external balance. Non-residents putting money in adds to it; residents taking money out subtracts. Errors and omissions is unrecorded flow — in Argentina it is large and usually a leak. What is left is the change in reserve assets, which is the bottom line and ties exactly to INDEC's published reserve-asset figure.
B6: Quarter | C6: Current account | D6: Capital account | E6: Total: external balance | F6: FDI into Argentina | G6: Portfolio into Argentina | H6: Other inv. borrowing | I6: Total: gross inflows (liabilities) | J6: Residents' FDI abroad | K6: Residents' portfolio abroad | L6: Residents' other assets | M6: Total: gross outflows (assets) | N6: Financial derivatives | O6: Total: net capital inflow | P6: Errors & omissions | Q6: CHANGE IN RESERVES
B7: ='Data BoP'!B6 -> 2006-Q1
B8: ='Data BoP'!B7 -> 2006-Q2
B9: ='Data BoP'!B8 -> 2006-Q3
B10: ='Data BoP'!B9 -> 2006-Q4 | C10: =('Data BoP'!E6)+('Data BoP'!E7)+('Data BoP'!E8)+('Data BoP'!E9) -> 6498.8025 | D10: =('Data BoP'!T6)+('Data BoP'!T7)+('Data BoP'!T8)+('Data BoP'!T9) -> 97.624328 | E10: =('Data BoP'!E6+'Data BoP'!T6)+('Data BoP'!E7+'Data BoP'!T7)+('Data BoP'!E8+'Data BoP'!T8)+('Data BoP'!E9+'Data BoP'!T9) -> 6596.4268 | F10: =('Data BoP'!Y6+'Data BoP'!Z6)+('Data BoP'!Y7+'Data BoP'!Z7)+('Data BoP'!Y8+'Data BoP'!Z8)+('Data BoP'!Y9+'Data BoP'!Z9) -> 5537.3478 | G10: =('Data BoP'!AD6+'Data BoP'!AE6)+('Data BoP'!AD7+'Data BoP'!AE7)+('Data BoP'!AD8+'Data BoP'!AE8)+('Data BoP'!AD9+'Data BoP'!AE9) -> 8500.3904 | H10: =('Data BoP'!AL6)+('Data BoP'!AL7)+('Data BoP'!AL8)+('Data BoP'!AL9) -> -10921.412 | I10: =('Data BoP'!Y6+'Data BoP'!Z6+'Data BoP'!AD6+'Data BoP'!AE6+'Data BoP'!AL6)+('Data BoP'!Y7+'Data BoP'!Z7+'Data BoP'!AD7+'Data BoP'!AE7+'Data BoP'!AL7)+('Data BoP'!Y8+'Data BoP'!Z8+'Data BoP'!AD8+'Data BoP'!AE8+'Data BoP'!AL8)+('Data BoP'!Y9+'Data BoP'!Z9+'Data BoP'!AD9+'Data BoP'!AE9+'Data BoP'!AL9) -> 3116.3265 | J10: =(-('Data BoP'!W6+'Data BoP'!X6))+(-('Data BoP'!W7+'Data BoP'!X7))+(-('Data BoP'!W8+'Data BoP'!X8))+(-('Data BoP'!W9+'Data BoP'!X9)) -> -2438.7207 | K10: =(-('Data BoP'!AB6+'Data BoP'!AC6))+(-('Data BoP'!AB7+'Data BoP'!AC7))+(-('Data BoP'!AB8+'Data BoP'!AC8))+(-('Data BoP'!AB9+'Data BoP'!AC9)) -> -1260.9936 | L10: =(-'Data BoP'!AH6)+(-'Data BoP'!AH7)+(-'Data BoP'!AH8)+(-'Data BoP'!AH9) -> -3240.5685 | M10: =(-('Data BoP'!W6+'Data BoP'!X6+'Data BoP'!AB6+'Data BoP'!AC6+'Data BoP'!AH6))+(-('Data BoP'!W7+'Data BoP'!X7+'Data BoP'!AB7+'Data BoP'!AC7+'Data BoP'!AH7))+(-('Data BoP'!W8+'Data BoP'!X8+'Data BoP'!AB8+'Data BoP'!AC8+'Data BoP'!AH8))+(-('Data BoP'!W9+'Data BoP'!X9+'Data BoP'!AB9+'Data BoP'!AC9+'Data BoP'!AH9)) -> -6940.2829 | N10: =(-'Data BoP'!AF6)+(-'Data BoP'!AF7)+(-'Data BoP'!AF8)+(-'Data BoP'!AF9) -> -126.64454 | O10: =(-('Data BoP'!U6-'Data BoP'!AJ6))+(-('Data BoP'!U7-'Data BoP'!AJ7))+(-('Data BoP'!U8-'Data BoP'!AJ8))+(-('Data BoP'!U9-'Data BoP'!AJ9)) -> -3950.6009 | P10: =('Data BoP'!AK6)+('Data BoP'!AK7)+('Data BoP'!AK8)+('Data BoP'!AK9) -> 884.00404 | Q10: =('Data BoP'!AJ6)+('Data BoP'!AJ7)+('Data BoP'!AJ8)+('Data BoP'!AJ9) -> 3529.83
B11: ='Data BoP'!B10 -> 2007-Q1 | C11: =('Data BoP'!E7)+('Data BoP'!E8)+('Data BoP'!E9)+('Data BoP'!E10) -> 6397.3377 | D11: =('Data BoP'!T7)+('Data BoP'!T8)+('Data BoP'!T9)+('Data BoP'!T10) -> 98.724328 | E11: =('Data BoP'!E7+'Data BoP'!T7)+('Data BoP'!E8+'Data BoP'!T8)+('Data BoP'!E9+'Data BoP'!T9)+('Data BoP'!E10+'Data BoP'!T10) -> 6496.0621 | F11: =('Data BoP'!Y7+'Data BoP'!Z7)+('Data BoP'!Y8+'Data BoP'!Z8)+('Data BoP'!Y9+'Data BoP'!Z9)+('Data BoP'!Y10+'Data BoP'!Z10) -> 4911.4459 | G11: =('Data BoP'!AD7+'Data BoP'!AE7)+('Data BoP'!AD8+'Data BoP'!AE8)+('Data BoP'!AD9+'Data BoP'!AE9)+('Data BoP'!AD10+'Data BoP'!AE10) -> 8072.0582 | H11: =('Data BoP'!AL7)+('Data BoP'!AL8)+('Data BoP'!AL9)+('Data BoP'!AL10) -> 124.55257 | I11: =('Data BoP'!Y7+'Data BoP'!Z7+'Data BoP'!AD7+'Data BoP'!AE7+'Data BoP'!AL7)+('Data BoP'!Y8+'Data BoP'!Z8+'Data BoP'!AD8+'Data BoP'!AE8+'Data BoP'!AL8)+('Data BoP'!Y9+'Data BoP'!Z9+'Data BoP'!AD9+'Data BoP'!AE9+'Data BoP'!AL9)+('Data BoP'!Y10+'Data BoP'!Z10+'Data BoP'!AD10+'Data BoP'!AE10+'Data BoP'!AL10) -> 13108.057 | J11: =(-('Data BoP'!W7+'Data BoP'!X7))+(-('Data BoP'!W8+'Data BoP'!X8))+(-('Data BoP'!W9+'Data BoP'!X9))+(-('Data BoP'!W10+'Data BoP'!X10)) -> -2471.1422 | K11: =(-('Data BoP'!AB7+'Data BoP'!AC7))+(-('Data BoP'!AB8+'Data BoP'!AC8))+(-('Data BoP'!AB9+'Data BoP'!AC9))+(-('Data BoP'!AB10+'Data BoP'!AC10)) -> -786.4961 | L11: =(-'Data BoP'!AH7)+(-'Data BoP'!AH8)+(-'Data BoP'!AH9)+(-'Data BoP'!AH10) -> -3052.1599 | M11: =(-('Data BoP'!W7+'Data BoP'!X7+'Data BoP'!AB7+'Data BoP'!AC7+'Data BoP'!AH7))+(-('Data BoP'!W8+'Data BoP'!X8+'Data BoP'!AB8+'Data BoP'!AC8+'Data BoP'!AH8))+(-('Data BoP'!W9+'Data BoP'!X9+'Data BoP'!AB9+'Data BoP'!AC9+'Data BoP'!AH9))+(-('Data BoP'!W10+'Data BoP'!X10+'Data BoP'!AB10+'Data BoP'!AC10+'Data BoP'!AH10)) -> -6309.7982 | N11: =(-'Data BoP'!AF7)+(-'Data BoP'!AF8)+(-'Data BoP'!AF9)+(-'Data BoP'!AF10) -> -150.48953 | O11: =(-('Data BoP'!U7-'Data BoP'!AJ7))+(-('Data BoP'!U8-'Data BoP'!AJ8))+(-('Data BoP'!U9-'Data BoP'!AJ9))+(-('Data BoP'!U10-'Data BoP'!AJ10)) -> 6647.7689 | P11: =('Data BoP'!AK7)+('Data BoP'!AK8)+('Data BoP'!AK9)+('Data BoP'!AK10) -> 1679.629 | Q11: =('Data BoP'!AJ7)+('Data BoP'!AJ8)+('Data BoP'!AJ9)+('Data BoP'!AJ10) -> 14823.46
B12: ='Data BoP'!B11 -> 2007-Q2 | C12: =('Data BoP'!E8)+('Data BoP'!E9)+('Data BoP'!E10)+('Data BoP'!E11) -> 6506.9338 | D12: =('Data BoP'!T8)+('Data BoP'!T9)+('Data BoP'!T10)+('Data BoP'!T11) -> 65.507524 | E12: =('Data BoP'!E8+'Data BoP'!T8)+('Data BoP'!E9+'Data BoP'!T9)+('Data BoP'!E10+'Data BoP'!T10)+('Data BoP'!E11+'Data BoP'!T11) -> 6572.4414 | F12: =('Data BoP'!Y8+'Data BoP'!Z8)+('Data BoP'!Y9+'Data BoP'!Z9)+('Data BoP'!Y10+'Data BoP'!Z10)+('Data BoP'!Y11+'Data BoP'!Z11) -> 4247.9262 | G12: =('Data BoP'!AD8+'Data BoP'!AE8)+('Data BoP'!AD9+'Data BoP'!AE9)+('Data BoP'!AD10+'Data BoP'!AE10)+('Data BoP'!AD11+'Data BoP'!AE11) -> 11919.369 | H12: =('Data BoP'!AL8)+('Data BoP'!AL9)+('Data BoP'!AL10)+('Data BoP'!AL11) -> 1529.3824 | I12: =('Data BoP'!Y8+'Data BoP'!Z8+'Data BoP'!AD8+'Data BoP'!AE8+'Data BoP'!AL8)+('Data BoP'!Y9+'Data BoP'!Z9+'Data BoP'!AD9+'Data BoP'!AE9+'Data BoP'!AL9)+('Data BoP'!Y10+'Data BoP'!Z10+'Data BoP'!AD10+'Data BoP'!AE10+'Data BoP'!AL10)+('Data BoP'!Y11+'Data BoP'!Z11+'Data BoP'!AD11+'Data BoP'!AE11+'Data BoP'!AL11) -> 17696.678 | J12: =(-('Data BoP'!W8+'Data BoP'!X8))+(-('Data BoP'!W9+'Data BoP'!X9))+(-('Data BoP'!W10+'Data BoP'!X10))+(-('Data BoP'!W11+'Data BoP'!X11)) -> -1777.6596 | K12: =(-('Data BoP'!AB8+'Data BoP'!AC8))+(-('Data BoP'!AB9+'Data BoP'!AC9))+(-('Data BoP'!AB10+'Data BoP'!AC10))+(-('Data BoP'!AB11+'Data BoP'!AC11)) -> -941.6684 | L12: =(-'Data BoP'!AH8)+(-'Data BoP'!AH9)+(-'Data BoP'!AH10)+(-'Data BoP'!AH11) -> -4603.9531 | M12: =(-('Data BoP'!W8+'Data BoP'!X8+'Data BoP'!AB8+'Data BoP'!AC8+'Data BoP'!AH8))+(-('Data BoP'!W9+'Data BoP'!X9+'Data BoP'!AB9+'Data BoP'!AC9+'Data BoP'!AH9))+(-('Data BoP'!W10+'Data BoP'!X10+'Data BoP'!AB10+'Data BoP'!AC10+'Data BoP'!AH10))+(-('Data BoP'!W11+'Data BoP'!X11+'Data BoP'!AB11+'Data BoP'!AC11+'Data BoP'!AH11)) -> -7323.2811 | N12: =(-'Data BoP'!AF8)+(-'Data BoP'!AF9)+(-'Data BoP'!AF10)+(-'Data BoP'!AF11) -> -209.70755 | O12: =(-('Data BoP'!U8-'Data BoP'!AJ8))+(-('Data BoP'!U9-'Data BoP'!AJ9))+(-('Data BoP'!U10-'Data BoP'!AJ10))+(-('Data BoP'!U11-'Data BoP'!AJ11)) -> 10163.689 | P12: =('Data BoP'!AK8)+('Data BoP'!AK9)+('Data BoP'!AK10)+('Data BoP'!AK11) -> 583.95921 | Q12: =('Data BoP'!AJ8)+('Data BoP'!AJ9)+('Data BoP'!AJ10)+('Data BoP'!AJ11) -> 17320.09
B13: ='Data BoP'!B12 -> 2007-Q3 | C13: =('Data BoP'!E9)+('Data BoP'!E10)+('Data BoP'!E11)+('Data BoP'!E12) -> 5439.3322 | D13: =('Data BoP'!T9)+('Data BoP'!T10)+('Data BoP'!T11)+('Data BoP'!T12) -> 122.28783 | E13: =('Data BoP'!E9+'Data BoP'!T9)+('Data BoP'!E10+'Data BoP'!T10)+('Data BoP'!E11+'Data BoP'!T11)+('Data BoP'!E12+'Data BoP'!T12) -> 5561.62 | F13: =('Data BoP'!Y9+'Data BoP'!Z9)+('Data BoP'!Y10+'Data BoP'!Z10)+('Data BoP'!Y11+'Data BoP'!Z11)+('Data BoP'!Y12+'Data BoP'!Z12) -> 4597.8028 | G13: =('Data BoP'!AD9+'Data BoP'!AE9)+('Data BoP'!AD10+'Data BoP'!AE10)+('Data BoP'!AD11+'Data BoP'!AE11)+('Data BoP'!AD12+'Data BoP'!AE12) -> 9660.2741 | H13: =('Data BoP'!AL9)+('Data BoP'!AL10)+('Data BoP'!AL11)+('Data BoP'!AL12) -> 4331.7341 | I13: =('Data BoP'!Y9+'Data BoP'!Z9+'Data BoP'!AD9+'Data BoP'!AE9+'Data BoP'!AL9)+('Data BoP'!Y10+'Data BoP'!Z10+'Data BoP'!AD10+'Data BoP'!AE10+'Data BoP'!AL10)+('Data BoP'!Y11+'Data BoP'!Z11+'Data BoP'!AD11+'Data BoP'!AE11+'Data BoP'!AL11)+('Data BoP'!Y12+'Data BoP'!Z12+'Data BoP'!AD12+'Data BoP'!AE12+'Data BoP'!AL12) -> 18589.811 | J13: =(-('Data BoP'!W9+'Data BoP'!X9))+(-('Data BoP'!W10+'Data BoP'!X10))+(-('Data BoP'!W11+'Data BoP'!X11))+(-('Data BoP'!W12+'Data BoP'!X12)) -> -1714.3709 | K13: =(-('Data BoP'!AB9+'Data BoP'!AC9))+(-('Data BoP'!AB10+'Data BoP'!AC10))+(-('Data BoP'!AB11+'Data BoP'!AC11))+(-('Data BoP'!AB12+'Data BoP'!AC12)) -> -973.9184 | L13: =(-'Data BoP'!AH9)+(-'Data BoP'!AH10)+(-'Data BoP'!AH11)+(-'Data BoP'!AH12) -> -8344.1687 | M13: =(-('Data BoP'!W9+'Data BoP'!X9+'Data BoP'!AB9+'Data BoP'!AC9+'Data BoP'!AH9))+(-('Data BoP'!W10+'Data BoP'!X10+'Data BoP'!AB10+'Data BoP'!AC10+'Data BoP'!AH10))+(-('Data BoP'!W11+'Data BoP'!X11+'Data BoP'!AB11+'Data BoP'!AC11+'Data BoP'!AH11))+(-('Data BoP'!W12+'Data BoP'!X12+'Data BoP'!AB12+'Data BoP'!AC12+'Data BoP'!AH12)) -> -11032.458 | N13: =(-'Data BoP'!AF9)+(-'Data BoP'!AF10)+(-'Data BoP'!AF11)+(-'Data BoP'!AF12) -> -229.74937 | O13: =(-('Data BoP'!U9-'Data BoP'!AJ9))+(-('Data BoP'!U10-'Data BoP'!AJ10))+(-('Data BoP'!U11-'Data BoP'!AJ11))+(-('Data BoP'!U12-'Data BoP'!AJ12)) -> 7327.6036 | P13: =('Data BoP'!AK9)+('Data BoP'!AK10)+('Data BoP'!AK11)+('Data BoP'!AK12) -> 1059.1564 | Q13: =('Data BoP'!AJ9)+('Data BoP'!AJ10)+('Data BoP'!AJ11)+('Data BoP'!AJ12) -> 13948.38
B14: ='Data BoP'!B13 -> 2007-Q4 | C14: =('Data BoP'!E10)+('Data BoP'!E11)+('Data BoP'!E12)+('Data BoP'!E13) -> 6048.5379 | D14: =('Data BoP'!T10)+('Data BoP'!T11)+('Data BoP'!T12)+('Data BoP'!T13) -> 121.14589 | E14: =('Data BoP'!E10+'Data BoP'!T10)+('Data BoP'!E11+'Data BoP'!T11)+('Data BoP'!E12+'Data BoP'!T12)+('Data BoP'!E13+'Data BoP'!T13) -> 6169.6838 | F14: =('Data BoP'!Y10+'Data BoP'!Z10)+('Data BoP'!Y11+'Data BoP'!Z11)+('Data BoP'!Y12+'Data BoP'!Z12)+('Data BoP'!Y13+'Data BoP'!Z13) -> 6473.1578 | G14: =('Data BoP'!AD10+'Data BoP'!AE10)+('Data BoP'!AD11+'Data BoP'!AE11)+('Data BoP'!AD12+'Data BoP'!AE12)+('Data BoP'!AD13+'Data BoP'!AE13) -> 8641.5117 | H14: =('Data BoP'!AL10)+('Data BoP'!AL11)+('Data BoP'!AL12)+('Data BoP'!AL13) -> 5874.6463 | I14: =('Data BoP'!Y10+'Data BoP'!Z10+'Data BoP'!AD10+'Data BoP'!AE10+'Data BoP'!AL10)+('Data BoP'!Y11+'Data BoP'!Z11+'Data BoP'!AD11+'Data BoP'!AE11+'Data BoP'!AL11)+('Data BoP'!Y12+'Data BoP'!Z12+'Data BoP'!AD12+'Data BoP'!AE12+'Data BoP'!AL12)+('Data BoP'!Y13+'Data BoP'!Z13+'Data BoP'!AD13+'Data BoP'!AE13+'Data BoP'!AL13) -> 20989.316 | J14: =(-('Data BoP'!W10+'Data BoP'!X10))+(-('Data BoP'!W11+'Data BoP'!X11))+(-('Data BoP'!W12+'Data BoP'!X12))+(-('Data BoP'!W13+'Data BoP'!X13)) -> -1504.233 | K14: =(-('Data BoP'!AB10+'Data BoP'!AC10))+(-('Data BoP'!AB11+'Data BoP'!AC11))+(-('Data BoP'!AB12+'Data BoP'!AC12))+(-('Data BoP'!AB13+'Data BoP'!AC13)) -> -1173.5488 | L14: =(-'Data BoP'!AH10)+(-'Data BoP'!AH11)+(-'Data BoP'!AH12)+(-'Data BoP'!AH13) -> -10556.673 | M14: =(-('Data BoP'!W10+'Data BoP'!X10+'Data BoP'!AB10+'Data BoP'!AC10+'Data BoP'!AH10))+(-('Data BoP'!W11+'Data BoP'!X11+'Data BoP'!AB11+'Data BoP'!AC11+'Data BoP'!AH11))+(-('Data BoP'!W12+'Data BoP'!X12+'Data BoP'!AB12+'Data BoP'!AC12+'Data BoP'!AH12))+(-('Data BoP'!W13+'Data BoP'!X13+'Data BoP'!AB13+'Data BoP'!AC13+'Data BoP'!AH13)) -> -13234.455 | N14: =(-'Data BoP'!AF10)+(-'Data BoP'!AF11)+(-'Data BoP'!AF12)+(-'Data BoP'!AF13) -> -564.58741 | O14: =(-('Data BoP'!U10-'Data BoP'!AJ10))+(-('Data BoP'!U11-'Data BoP'!AJ11))+(-('Data BoP'!U12-'Data BoP'!AJ12))+(-('Data BoP'!U13-'Data BoP'!AJ13)) -> 7190.2731 | P14: =('Data BoP'!AK10)+('Data BoP'!AK11)+('Data BoP'!AK12)+('Data BoP'!AK13) -> -270.2369 | Q14: =('Data BoP'!AJ10)+('Data BoP'!AJ11)+('Data BoP'!AJ12)+('Data BoP'!AJ13) -> 13089.72
B15: ='Data BoP'!B14 -> 2008-Q1 | C15: =('Data BoP'!E11)+('Data BoP'!E12)+('Data BoP'!E13)+('Data BoP'!E14) -> 6769.9504 | D15: =('Data BoP'!T11)+('Data BoP'!T12)+('Data BoP'!T13)+('Data BoP'!T14) -> 153.27689 | E15: =('Data BoP'!E11+'Data BoP'!T11)+('Data BoP'!E12+'Data BoP'!T12)+('Data BoP'!E13+'Data BoP'!T13)+('Data BoP'!E14+'Data BoP'!T14) -> 6923.2273 | F15: =('Data BoP'!Y11+'Data BoP'!Z11)+('Data BoP'!Y12+'Data BoP'!Z12)+('Data BoP'!Y13+'Data BoP'!Z13)+('Data BoP'!Y14+'Data BoP'!Z14) -> 8829.1046 | G15: =('Data BoP'!AD11+'Data BoP'!AE11)+('Data BoP'!AD12+'Data BoP'!AE12)+('Data BoP'!AD13+'Data BoP'!AE13)+('Data BoP'!AD14+'Data BoP'!AE14) -> 5750.089 | H15: =('Data BoP'!AL11)+('Data BoP'!AL12)+('Data BoP'!AL13)+('Data BoP'!AL14) -> 6726.7429 | I15: =('Data BoP'!Y11+'Data BoP'!Z11+'Data BoP'!AD11+'Data BoP'!AE11+'Data BoP'!AL11)+('Data BoP'!Y12+'Data BoP'!Z12+'Data BoP'!AD12+'Data BoP'!AE12+'Data BoP'!AL12)+('Data BoP'!Y13+'Data BoP'!Z13+'Data BoP'!AD13+'Data BoP'!AE13+'Data BoP'!AL13)+('Data BoP'!Y14+'Data BoP'!Z14+'Data BoP'!AD14+'Data BoP'!AE14+'Data BoP'!AL14) -> 21305.936 | J15: =(-('Data BoP'!W11+'Data BoP'!X11))+(-('Data BoP'!W12+'Data BoP'!X12))+(-('Data BoP'!W13+'Data BoP'!X13))+(-('Data BoP'!W14+'Data BoP'!X14)) -> -1440.6072 | K15: =(-('Data BoP'!AB11+'Data BoP'!AC11))+(-('Data BoP'!AB12+'Data BoP'!AC12))+(-('Data BoP'!AB13+'Data BoP'!AC13))+(-('Data BoP'!AB14+'Data BoP'!AC14)) -> -1615.0033 | L15: =(-'Data BoP'!AH11)+(-'Data BoP'!AH12)+(-'Data BoP'!AH13)+(-'Data BoP'!AH14) -> -12775.873 | M15: =(-('Data BoP'!W11+'Data BoP'!X11+'Data BoP'!AB11+'Data BoP'!AC11+'Data BoP'!AH11))+(-('Data BoP'!W12+'Data BoP'!X12+'Data BoP'!AB12+'Data BoP'!AC12+'Data BoP'!AH12))+(-('Data BoP'!W13+'Data BoP'!X13+'Data BoP'!AB13+'Data BoP'!AC13+'Data BoP'!AH13))+(-('Data BoP'!W14+'Data BoP'!X14+'Data BoP'!AB14+'Data BoP'!AC14+'Data BoP'!AH14)) -> -15831.483 | N15: =(-'Data BoP'!AF11)+(-'Data BoP'!AF12)+(-'Data BoP'!AF13)+(-'Data BoP'!AF14) -> -544.29924 | O15: =(-('Data BoP'!U11-'Data BoP'!AJ11))+(-('Data BoP'!U12-'Data BoP'!AJ12))+(-('Data BoP'!U13-'Data BoP'!AJ13))+(-('Data BoP'!U14-'Data BoP'!AJ14)) -> 4930.1541 | P15: =('Data BoP'!AK11)+('Data BoP'!AK12)+('Data BoP'!AK13)+('Data BoP'!AK14) -> 110.85868 | Q15: =('Data BoP'!AJ11)+('Data BoP'!AJ12)+('Data BoP'!AJ13)+('Data BoP'!AJ14) -> 11964.24
B16: ='Data BoP'!B15 -> 2008-Q2 | C16: =('Data BoP'!E12)+('Data BoP'!E13)+('Data BoP'!E14)+('Data BoP'!E15) -> 5063.0196 | D16: =('Data BoP'!T12)+('Data BoP'!T13)+('Data BoP'!T14)+('Data BoP'!T15) -> 161.34484 | E16: =('Data BoP'!E12+'Data BoP'!T12)+('Data BoP'!E13+'Data BoP'!T13)+('Data BoP'!E14+'Data BoP'!T14)+('Data BoP'!E15+'Data BoP'!T15) -> 5224.3644 | F16: =('Data BoP'!Y12+'Data BoP'!Z12)+('Data BoP'!Y13+'Data BoP'!Z13)+('Data BoP'!Y14+'Data BoP'!Z14)+('Data BoP'!Y15+'Data BoP'!Z15) -> 9994.0902 | G16: =('Data BoP'!AD12+'Data BoP'!AE12)+('Data BoP'!AD13+'Data BoP'!AE13)+('Data BoP'!AD14+'Data BoP'!AE14)+('Data BoP'!AD15+'Data BoP'!AE15) -> -1574.4784 | H16: =('Data BoP'!AL12)+('Data BoP'!AL13)+('Data BoP'!AL14)+('Data BoP'!AL15) -> 9411.3133 | I16: =('Data BoP'!Y12+'Data BoP'!Z12+'Data BoP'!AD12+'Data BoP'!AE12+'Data BoP'!AL12)+('Data BoP'!Y13+'Data BoP'!Z13+'Data BoP'!AD13+'Data BoP'!AE13+'Data BoP'!AL13)+('Data BoP'!Y14+'Data BoP'!Z14+'Data BoP'!AD14+'Data BoP'!AE14+'Data BoP'!AL14)+('Data BoP'!Y15+'Data BoP'!Z15+'Data BoP'!AD15+'Data BoP'!AE15+'Data BoP'!AL15) -> 17830.925 | J16: =(-('Data BoP'!W12+'Data BoP'!X12))+(-('Data BoP'!W13+'Data BoP'!X13))+(-('Data BoP'!W14+'Data BoP'!X14))+(-('Data BoP'!W15+'Data BoP'!X15)) -> -1361.755 | K16: =(-('Data BoP'!AB12+'Data BoP'!AC12))+(-('Data BoP'!AB13+'Data BoP'!AC13))+(-('Data BoP'!AB14+'Data BoP'!AC14))+(-('Data BoP'!AB15+'Data BoP'!AC15)) -> -2096.833 | L16: =(-'Data BoP'!AH12)+(-'Data BoP'!AH13)+(-'Data BoP'!AH14)+(-'Data BoP'!AH15) -> -16195.863 | M16: =(-('Data BoP'!W12+'Data BoP'!X12+'Data BoP'!AB12+'Data BoP'!AC12+'Data BoP'!AH12))+(-('Data BoP'!W13+'Data BoP'!X13+'Data BoP'!AB13+'Data BoP'!AC13+'Data BoP'!AH13))+(-('Data BoP'!W14+'Data BoP'!X14+'Data BoP'!AB14+'Data BoP'!AC14+'Data BoP'!AH14))+(-('Data BoP'!W15+'Data BoP'!X15+'Data BoP'!AB15+'Data BoP'!AC15+'Data BoP'!AH15)) -> -19654.451 | N16: =(-'Data BoP'!AF12)+(-'Data BoP'!AF13)+(-'Data BoP'!AF14)+(-'Data BoP'!AF15) -> -577.3464 | O16: =(-('Data BoP'!U12-'Data BoP'!AJ12))+(-('Data BoP'!U13-'Data BoP'!AJ13))+(-('Data BoP'!U14-'Data BoP'!AJ14))+(-('Data BoP'!U15-'Data BoP'!AJ15)) -> -2400.8719 | P16: =('Data BoP'!AK12)+('Data BoP'!AK13)+('Data BoP'!AK14)+('Data BoP'!AK15) -> 180.16743 | Q16: =('Data BoP'!AJ12)+('Data BoP'!AJ13)+('Data BoP'!AJ14)+('Data BoP'!AJ15) -> 3003.66
B17: ='Data BoP'!B16 -> 2008-Q3 | C17: =('Data BoP'!E13)+('Data BoP'!E14)+('Data BoP'!E15)+('Data BoP'!E16) -> 7605.6736 | D17: =('Data BoP'!T13)+('Data BoP'!T14)+('Data BoP'!T15)+('Data BoP'!T16) -> 182.93412 | E17: =('Data BoP'!E13+'Data BoP'!T13)+('Data BoP'!E14+'Data BoP'!T14)+('Data BoP'!E15+'Data BoP'!T15)+('Data BoP'!E16+'Data BoP'!T16) -> 7788.6077 | F17: =('Data BoP'!Y13+'Data BoP'!Z13)+('Data BoP'!Y14+'Data BoP'!Z14)+('Data BoP'!Y15+'Data BoP'!Z15)+('Data BoP'!Y16+'Data BoP'!Z16) -> 10454.991 | G17: =('Data BoP'!AD13+'Data BoP'!AE13)+('Data BoP'!AD14+'Data BoP'!AE14)+('Data BoP'!AD15+'Data BoP'!AE15)+('Data BoP'!AD16+'Data BoP'!AE16) -> -2535.7807 | H17: =('Data BoP'!AL13)+('Data BoP'!AL14)+('Data BoP'!AL15)+('Data BoP'!AL16) -> 9241.0899 | I17: =('Data BoP'!Y13+'Data BoP'!Z13+'Data BoP'!AD13+'Data BoP'!AE13+'Data BoP'!AL13)+('Data BoP'!Y14+'Data BoP'!Z14+'Data BoP'!AD14+'Data BoP'!AE14+'Data BoP'!AL14)+('Data BoP'!Y15+'Data BoP'!Z15+'Data BoP'!AD15+'Data BoP'!AE15+'Data BoP'!AL15)+('Data BoP'!Y16+'Data BoP'!Z16+'Data BoP'!AD16+'Data BoP'!AE16+'Data BoP'!AL16) -> 17160.301 | J17: =(-('Data BoP'!W13+'Data BoP'!X13))+(-('Data BoP'!W14+'Data BoP'!X14))+(-('Data BoP'!W15+'Data BoP'!X15))+(-('Data BoP'!W16+'Data BoP'!X16)) -> -1498.6131 | K17: =(-('Data BoP'!AB13+'Data BoP'!AC13))+(-('Data BoP'!AB14+'Data BoP'!AC14))+(-('Data BoP'!AB15+'Data BoP'!AC15))+(-('Data BoP'!AB16+'Data BoP'!AC16)) -> -3658.7917 | L17: =(-'Data BoP'!AH13)+(-'Data BoP'!AH14)+(-'Data BoP'!AH15)+(-'Data BoP'!AH16) -> -16843.085 | M17: =(-('Data BoP'!W13+'Data BoP'!X13+'Data BoP'!AB13+'Data BoP'!AC13+'Data BoP'!AH13))+(-('Data BoP'!W14+'Data BoP'!X14+'Data BoP'!AB14+'Data BoP'!AC14+'Data BoP'!AH14))+(-('Data BoP'!W15+'Data BoP'!X15+'Data BoP'!AB15+'Data BoP'!AC15+'Data BoP'!AH15))+(-('Data BoP'!W16+'Data BoP'!X16+'Data BoP'!AB16+'Data BoP'!AC16+'Data BoP'!AH16)) -> -22000.49 | N17: =(-'Data BoP'!AF13)+(-'Data BoP'!AF14)+(-'Data BoP'!AF15)+(-'Data BoP'!AF16) -> -607.1 | O17: =(-('Data BoP'!U13-'Data BoP'!AJ13))+(-('Data BoP'!U14-'Data BoP'!AJ14))+(-('Data BoP'!U15-'Data BoP'!AJ15))+(-('Data BoP'!U16-'Data BoP'!AJ16)) -> -5447.2895 | P17: =('Data BoP'!AK13)+('Data BoP'!AK14)+('Data BoP'!AK15)+('Data BoP'!AK16) -> 1454.6618 | Q17: =('Data BoP'!AJ13)+('Data BoP'!AJ14)+('Data BoP'!AJ15)+('Data BoP'!AJ16) -> 3795.98
B18: ='Data BoP'!B17 -> 2008-Q4 | C18: =('Data BoP'!E14)+('Data BoP'!E15)+('Data BoP'!E16)+('Data BoP'!E17) -> 5421.2063 | D18: =('Data BoP'!T14)+('Data BoP'!T15)+('Data BoP'!T16)+('Data BoP'!T17) -> 185.06002 | E18: =('Data BoP'!E14+'Data BoP'!T14)+('Data BoP'!E15+'Data BoP'!T15)+('Data BoP'!E16+'Data BoP'!T16)+('Data BoP'!E17+'Data BoP'!T17) -> 5606.2663 | F18: =('Data BoP'!Y14+'Data BoP'!Z14)+('Data BoP'!Y15+'Data BoP'!Z15)+('Data BoP'!Y16+'Data BoP'!Z16)+('Data BoP'!Y17+'Data BoP'!Z17) -> 9725.5531 | G18: =('Data BoP'!AD14+'Data BoP'!AE14)+('Data BoP'!AD15+'Data BoP'!AE15)+('Data BoP'!AD16+'Data BoP'!AE16)+('Data BoP'!AD17+'Data BoP'!AE17) -> -5723.0252 | H18: =('Data BoP'!AL14)+('Data BoP'!AL15)+('Data BoP'!AL16)+('Data BoP'!AL17) -> 6182.6114 | I18: =('Data BoP'!Y14+'Data BoP'!Z14+'Data BoP'!AD14+'Data BoP'!AE14+'Data BoP'!AL14)+('Data BoP'!Y15+'Data BoP'!Z15+'Data BoP'!AD15+'Data BoP'!AE15+'Data BoP'!AL15)+('Data BoP'!Y16+'Data BoP'!Z16+'Data BoP'!AD16+'Data BoP'!AE16+'Data BoP'!AL16)+('Data BoP'!Y17+'Data BoP'!Z17+'Data BoP'!AD17+'Data BoP'!AE17+'Data BoP'!AL17) -> 10185.139 | J18: =(-('Data BoP'!W14+'Data BoP'!X14))+(-('Data BoP'!W15+'Data BoP'!X15))+(-('Data BoP'!W16+'Data BoP'!X16))+(-('Data BoP'!W17+'Data BoP'!X17)) -> -1390.9346 | K18: =(-('Data BoP'!AB14+'Data BoP'!AC14))+(-('Data BoP'!AB15+'Data BoP'!AC15))+(-('Data BoP'!AB16+'Data BoP'!AC16))+(-('Data BoP'!AB17+'Data BoP'!AC17)) -> -2155.5638 | L18: =(-'Data BoP'!AH14)+(-'Data BoP'!AH15)+(-'Data BoP'!AH16)+(-'Data BoP'!AH17) -> -12240.515 | M18: =(-('Data BoP'!W14+'Data BoP'!X14+'Data BoP'!AB14+'Data BoP'!AC14+'Data BoP'!AH14))+(-('Data BoP'!W15+'Data BoP'!X15+'Data BoP'!AB15+'Data BoP'!AC15+'Data BoP'!AH15))+(-('Data BoP'!W16+'Data BoP'!X16+'Data BoP'!AB16+'Data BoP'!AC16+'Data BoP'!AH16))+(-('Data BoP'!W17+'Data BoP'!X17+'Data BoP'!AB17+'Data BoP'!AC17+'Data BoP'!AH17)) -> -15787.013 | N18: =(-'Data BoP'!AF14)+(-'Data BoP'!AF15)+(-'Data BoP'!AF16)+(-'Data BoP'!AF17) -> -934.7 | O18: =(-('Data BoP'!U14-'Data BoP'!AJ14))+(-('Data BoP'!U15-'Data BoP'!AJ15))+(-('Data BoP'!U16-'Data BoP'!AJ16))+(-('Data BoP'!U17-'Data BoP'!AJ17)) -> -6536.5742 | P18: =('Data BoP'!AK14)+('Data BoP'!AK15)+('Data BoP'!AK16)+('Data BoP'!AK17) -> 947.68784 | Q18: =('Data BoP'!AJ14)+('Data BoP'!AJ15)+('Data BoP'!AJ16)+('Data BoP'!AJ17) -> 17.38
B19: ='Data BoP'!B18 -> 2009-Q1 | C19: =('Data BoP'!E15)+('Data BoP'!E16)+('Data BoP'!E17)+('Data BoP'!E18) -> 5288.6833 | D19: =('Data BoP'!T15)+('Data BoP'!T16)+('Data BoP'!T17)+('Data BoP'!T18) -> 163.49731 | E19: =('Data BoP'!E15+'Data BoP'!T15)+('Data BoP'!E16+'Data BoP'!T16)+('Data BoP'!E17+'Data BoP'!T17)+('Data BoP'!E18+'Data BoP'!T18) -> 5452.1806 | F19: =('Data BoP'!Y15+'Data BoP'!Z15)+('Data BoP'!Y16+'Data BoP'!Z16)+('Data BoP'!Y17+'Data BoP'!Z17)+('Data BoP'!Y18+'Data BoP'!Z18) -> 7913.0292 | G19: =('Data BoP'!AD15+'Data BoP'!AE15)+('Data BoP'!AD16+'Data BoP'!AE16)+('Data BoP'!AD17+'Data BoP'!AE17)+('Data BoP'!AD18+'Data BoP'!AE18) -> -5380.5495 | H19: =('Data BoP'!AL15)+('Data BoP'!AL16)+('Data BoP'!AL17)+('Data BoP'!AL18) -> 5188.5658 | I19: =('Data BoP'!Y15+'Data BoP'!Z15+'Data BoP'!AD15+'Data BoP'!AE15+'Data BoP'!AL15)+('Data BoP'!Y16+'Data BoP'!Z16+'Data BoP'!AD16+'Data BoP'!AE16+'Data BoP'!AL16)+('Data BoP'!Y17+'Data BoP'!Z17+'Data BoP'!AD17+'Data BoP'!AE17+'Data BoP'!AL17)+('Data BoP'!Y18+'Data BoP'!Z18+'Data BoP'!AD18+'Data BoP'!AE18+'Data BoP'!AL18) -> 7721.0455 | J19: =(-('Data BoP'!W15+'Data BoP'!X15))+(-('Data BoP'!W16+'Data BoP'!X16))+(-('Data BoP'!W17+'Data BoP'!X17))+(-('Data BoP'!W18+'Data BoP'!X18)) -> -1386.0363 | K19: =(-('Data BoP'!AB15+'Data BoP'!AC15))+(-('Data BoP'!AB16+'Data BoP'!AC16))+(-('Data BoP'!AB17+'Data BoP'!AC17))+(-('Data BoP'!AB18+'Data BoP'!AC18)) -> -2290.8187 | L19: =(-'Data BoP'!AH15)+(-'Data BoP'!AH16)+(-'Data BoP'!AH17)+(-'Data BoP'!AH18) -> -11354.306 | M19: =(-('Data BoP'!W15+'Data BoP'!X15+'Data BoP'!AB15+'Data BoP'!AC15+'Data BoP'!AH15))+(-('Data BoP'!W16+'Data BoP'!X16+'Data BoP'!AB16+'Data BoP'!AC16+'Data BoP'!AH16))+(-('Data BoP'!W17+'Data BoP'!X17+'Data BoP'!AB17+'Data BoP'!AC17+'Data BoP'!AH17))+(-('Data BoP'!W18+'Data BoP'!X18+'Data BoP'!AB18+'Data BoP'!AC18+'Data BoP'!AH18)) -> -15031.161 | N19: =(-'Data BoP'!AF15)+(-'Data BoP'!AF16)+(-'Data BoP'!AF17)+(-'Data BoP'!AF18) -> -946.2 | O19: =(-('Data BoP'!U15-'Data BoP'!AJ15))+(-('Data BoP'!U16-'Data BoP'!AJ16))+(-('Data BoP'!U17-'Data BoP'!AJ17))+(-('Data BoP'!U18-'Data BoP'!AJ18)) -> -8256.3153 | P19: =('Data BoP'!AK15)+('Data BoP'!AK16)+('Data BoP'!AK17)+('Data BoP'!AK18) -> -445.57536 | Q19: =('Data BoP'!AJ15)+('Data BoP'!AJ16)+('Data BoP'!AJ17)+('Data BoP'!AJ18) -> -3249.71
B20: ='Data BoP'!B19 -> 2009-Q2 | C20: =('Data BoP'!E16)+('Data BoP'!E17)+('Data BoP'!E18)+('Data BoP'!E19) -> 9267.2486 | D20: =('Data BoP'!T16)+('Data BoP'!T17)+('Data BoP'!T18)+('Data BoP'!T19) -> 149.34617 | E20: =('Data BoP'!E16+'Data BoP'!T16)+('Data BoP'!E17+'Data BoP'!T17)+('Data BoP'!E18+'Data BoP'!T18)+('Data BoP'!E19+'Data BoP'!T19) -> 9416.5948 | F20: =('Data BoP'!Y16+'Data BoP'!Z16)+('Data BoP'!Y17+'Data BoP'!Z17)+('Data BoP'!Y18+'Data BoP'!Z18)+('Data BoP'!Y19+'Data BoP'!Z19) -> 5994.05 | G20: =('Data BoP'!AD16+'Data BoP'!AE16)+('Data BoP'!AD17+'Data BoP'!AE17)+('Data BoP'!AD18+'Data BoP'!AE18)+('Data BoP'!AD19+'Data BoP'!AE19) -> -4210.4274 | H20: =('Data BoP'!AL16)+('Data BoP'!AL17)+('Data BoP'!AL18)+('Data BoP'!AL19) -> 1843.7657 | I20: =('Data BoP'!Y16+'Data BoP'!Z16+'Data BoP'!AD16+'Data BoP'!AE16+'Data BoP'!AL16)+('Data BoP'!Y17+'Data BoP'!Z17+'Data BoP'!AD17+'Data BoP'!AE17+'Data BoP'!AL17)+('Data BoP'!Y18+'Data BoP'!Z18+'Data BoP'!AD18+'Data BoP'!AE18+'Data BoP'!AL18)+('Data BoP'!Y19+'Data BoP'!Z19+'Data BoP'!AD19+'Data BoP'!AE19+'Data BoP'!AL19) -> 3627.3884 | J20: =(-('Data BoP'!W16+'Data BoP'!X16))+(-('Data BoP'!W17+'Data BoP'!X17))+(-('Data BoP'!W18+'Data BoP'!X18))+(-('Data BoP'!W19+'Data BoP'!X19)) -> -832.24824 | K20: =(-('Data BoP'!AB16+'Data BoP'!AC16))+(-('Data BoP'!AB17+'Data BoP'!AC17))+(-('Data BoP'!AB18+'Data BoP'!AC18))+(-('Data BoP'!AB19+'Data BoP'!AC19)) -> -1287.651 | L20: =(-'Data BoP'!AH16)+(-'Data BoP'!AH17)+(-'Data BoP'!AH18)+(-'Data BoP'!AH19) -> -10693.912 | M20: =(-('Data BoP'!W16+'Data BoP'!X16+'Data BoP'!AB16+'Data BoP'!AC16+'Data BoP'!AH16))+(-('Data BoP'!W17+'Data BoP'!X17+'Data BoP'!AB17+'Data BoP'!AC17+'Data BoP'!AH17))+(-('Data BoP'!W18+'Data BoP'!X18+'Data BoP'!AB18+'Data BoP'!AC18+'Data BoP'!AH18))+(-('Data BoP'!W19+'Data BoP'!X19+'Data BoP'!AB19+'Data BoP'!AC19+'Data BoP'!AH19)) -> -12813.811 | N20: =(-'Data BoP'!AF16)+(-'Data BoP'!AF17)+(-'Data BoP'!AF18)+(-'Data BoP'!AF19) -> -889.4 | O20: =(-('Data BoP'!U16-'Data BoP'!AJ16))+(-('Data BoP'!U17-'Data BoP'!AJ17))+(-('Data BoP'!U18-'Data BoP'!AJ18))+(-('Data BoP'!U19-'Data BoP'!AJ19)) -> -10075.822 | P20: =('Data BoP'!AK16)+('Data BoP'!AK17)+('Data BoP'!AK18)+('Data BoP'!AK19) -> -668.26239 | Q20: =('Data BoP'!AJ16)+('Data BoP'!AJ17)+('Data BoP'!AJ18)+('Data BoP'!AJ19) -> -1327.49
B21: ='Data BoP'!B20 -> 2009-Q3 | C21: =('Data BoP'!E17)+('Data BoP'!E18)+('Data BoP'!E19)+('Data BoP'!E20) -> 6980.0517 | D21: =('Data BoP'!T17)+('Data BoP'!T18)+('Data BoP'!T19)+('Data BoP'!T20) -> 80.262901 | E21: =('Data BoP'!E17+'Data BoP'!T17)+('Data BoP'!E18+'Data BoP'!T18)+('Data BoP'!E19+'Data BoP'!T19)+('Data BoP'!E20+'Data BoP'!T20) -> 7060.3146 | F21: =('Data BoP'!Y17+'Data BoP'!Z17)+('Data BoP'!Y18+'Data BoP'!Z18)+('Data BoP'!Y19+'Data BoP'!Z19)+('Data BoP'!Y20+'Data BoP'!Z20) -> 4326.3081 | G21: =('Data BoP'!AD17+'Data BoP'!AE17)+('Data BoP'!AD18+'Data BoP'!AE18)+('Data BoP'!AD19+'Data BoP'!AE19)+('Data BoP'!AD20+'Data BoP'!AE20) -> -2656.9213 | H21: =('Data BoP'!AL17)+('Data BoP'!AL18)+('Data BoP'!AL19)+('Data BoP'!AL20) -> 1578.7311 | I21: =('Data BoP'!Y17+'Data BoP'!Z17+'Data BoP'!AD17+'Data BoP'!AE17+'Data BoP'!AL17)+('Data BoP'!Y18+'Data BoP'!Z18+'Data BoP'!AD18+'Data BoP'!AE18+'Data BoP'!AL18)+('Data BoP'!Y19+'Data BoP'!Z19+'Data BoP'!AD19+'Data BoP'!AE19+'Data BoP'!AL19)+('Data BoP'!Y20+'Data BoP'!Z20+'Data BoP'!AD20+'Data BoP'!AE20+'Data BoP'!AL20) -> 3248.118 | J21: =(-('Data BoP'!W17+'Data BoP'!X17))+(-('Data BoP'!W18+'Data BoP'!X18))+(-('Data BoP'!W19+'Data BoP'!X19))+(-('Data BoP'!W20+'Data BoP'!X20)) -> -687.91992 | K21: =(-('Data BoP'!AB17+'Data BoP'!AC17))+(-('Data BoP'!AB18+'Data BoP'!AC18))+(-('Data BoP'!AB19+'Data BoP'!AC19))+(-('Data BoP'!AB20+'Data BoP'!AC20)) -> 353.77394 | L21: =(-'Data BoP'!AH17)+(-'Data BoP'!AH18)+(-'Data BoP'!AH19)+(-'Data BoP'!AH20) -> -6252.4887 | M21: =(-('Data BoP'!W17+'Data BoP'!X17+'Data BoP'!AB17+'Data BoP'!AC17+'Data BoP'!AH17))+(-('Data BoP'!W18+'Data BoP'!X18+'Data BoP'!AB18+'Data BoP'!AC18+'Data BoP'!AH18))+(-('Data BoP'!W19+'Data BoP'!X19+'Data BoP'!AB19+'Data BoP'!AC19+'Data BoP'!AH19))+(-('Data BoP'!W20+'Data BoP'!X20+'Data BoP'!AB20+'Data BoP'!AC20+'Data BoP'!AH20)) -> -6586.6347 | N21: =(-'Data BoP'!AF17)+(-'Data BoP'!AF18)+(-'Data BoP'!AF19)+(-'Data BoP'!AF20) -> -898 | O21: =(-('Data BoP'!U17-'Data BoP'!AJ17))+(-('Data BoP'!U18-'Data BoP'!AJ18))+(-('Data BoP'!U19-'Data BoP'!AJ19))+(-('Data BoP'!U20-'Data BoP'!AJ20)) -> -4236.5167 | P21: =('Data BoP'!AK17)+('Data BoP'!AK18)+('Data BoP'!AK19)+('Data BoP'!AK20) -> -2290.7679 | Q21: =('Data BoP'!AJ17)+('Data BoP'!AJ18)+('Data BoP'!AJ19)+('Data BoP'!AJ20) -> 533.03
... B87: ='Data BoP'!B86 -> 2026-Q1 | C87: =('Data BoP'!E83)+('Data BoP'!E84)+('Data BoP'!E85)+('Data BoP'!E86) -> -4281.0987 | D87: =('Data BoP'!T83)+('Data BoP'!T84)+('Data BoP'!T85)+('Data BoP'!T86) -> 458.3965 | E87: =('Data BoP'!E83+'Data BoP'!T83)+('Data BoP'!E84+'Data BoP'!T84)+('Data BoP'!E85+'Data BoP'!T85)+('Data BoP'!E86+'Data BoP'!T86) -> -3822.7022 | F87: =('Data BoP'!Y83+'Data BoP'!Z83)+('Data BoP'!Y84+'Data BoP'!Z84)+('Data BoP'!Y85+'Data BoP'!Z85)+('Data BoP'!Y86+'Data BoP'!Z86) -> 5290.5917 | G87: =('Data BoP'!AD83+'Data BoP'!AE83)+('Data BoP'!AD84+'Data BoP'!AE84)+('Data BoP'!AD85+'Data BoP'!AE85)+('Data BoP'!AD86+'Data BoP'!AE86) -> 7137.6697 | H87: =('Data BoP'!AL83)+('Data BoP'!AL84)+('Data BoP'!AL85)+('Data BoP'!AL86) -> 27762.178 | I87: =('Data BoP'!Y83+'Data BoP'!Z83+'Data BoP'!AD83+'Data BoP'!AE83+'Data BoP'!AL83)+('Data BoP'!Y84+'Data BoP'!Z84+'Data BoP'!AD84+'Data BoP'!AE84+'Data BoP'!AL84)+('Data BoP'!Y85+'Data BoP'!Z85+'Data BoP'!AD85+'Data BoP'!AE85+'Data BoP'!AL85)+('Data BoP'!Y86+'Data BoP'!Z86+'Data BoP'!AD86+'Data BoP'!AE86+'Data BoP'!AL86) -> 40190.44 | J87: =(-('Data BoP'!W83+'Data BoP'!X83))+(-('Data BoP'!W84+'Data BoP'!X84))+(-('Data BoP'!W85+'Data BoP'!X85))+(-('Data BoP'!W86+'Data BoP'!X86)) -> -2694.4886 | K87: =(-('Data BoP'!AB83+'Data BoP'!AC83))+(-('Data BoP'!AB84+'Data BoP'!AC84))+(-('Data BoP'!AB85+'Data BoP'!AC85))+(-('Data BoP'!AB86+'Data BoP'!AC86)) -> -4821.5749 | L87: =(-'Data BoP'!AH83)+(-'Data BoP'!AH84)+(-'Data BoP'!AH85)+(-'Data BoP'!AH86) -> -12601.479 | M87: =(-('Data BoP'!W83+'Data BoP'!X83+'Data BoP'!AB83+'Data BoP'!AC83+'Data BoP'!AH83))+(-('Data BoP'!W84+'Data BoP'!X84+'Data BoP'!AB84+'Data BoP'!AC84+'Data BoP'!AH84))+(-('Data BoP'!W85+'Data BoP'!X85+'Data BoP'!AB85+'Data BoP'!AC85+'Data BoP'!AH85))+(-('Data BoP'!W86+'Data BoP'!X86+'Data BoP'!AB86+'Data BoP'!AC86+'Data BoP'!AH86)) -> -20117.543 | N87: =(-'Data BoP'!AF83)+(-'Data BoP'!AF84)+(-'Data BoP'!AF85)+(-'Data BoP'!AF86) -> -1.494248 | O87: =(-('Data BoP'!U83-'Data BoP'!AJ83))+(-('Data BoP'!U84-'Data BoP'!AJ84))+(-('Data BoP'!U85-'Data BoP'!AJ85))+(-('Data BoP'!U86-'Data BoP'!AJ86)) -> 20071.402 | P87: =('Data BoP'!AK83)+('Data BoP'!AK84)+('Data BoP'!AK85)+('Data BoP'!AK86) -> -3389.5408 | Q87: =('Data BoP'!AJ83)+('Data BoP'!AJ84)+('Data BoP'!AJ85)+('Data BoP'!AJ86) -> 12859.159
B89: Check: external balance + net capital inflow + errors and omissions = change in reserves. This is the BPM6 identity rearranged, so it holds by construction — if it ever does not, a source cell has been edited.
B90: 'Other investment borrowing' is where IMF disbursements land. The April-2025 EFF disbursement is the single largest positive entry in that column in the whole history.
B91: Errors and omissions in Argentina is not noise to be ignored. It is persistently negative and large, and is conventionally read as unrecorded capital flight. Treat it as a funding line, which is why it sits here rather than in a footnote.

Sheet % of GDP
B2: Four-quarter rolling, as a share of GDP
B3: Rolling four-quarter flows divided by rolling four-quarter nominal GDP in US dollars. Scale-free, so any two eras are directly comparable.
B6: Quarter | C6: Current account | D6: Goods balance | E6: Services balance | F6: Primary income | G6: Secondary income | H6: Financial account | I6: FDI liabilities | J6: Portfolio liabilities | K6: Other inv. liabilities | L6: Resident asset accumulation | M6: Errors & omissions | N6: Change in reserves | O6: memo: 4q GDP (USD mn)
B7: ='Data BoP'!B6 -> 2006-Q1
B8: ='Data BoP'!B7 -> 2006-Q2
B9: ='Data BoP'!B8 -> 2006-Q3
B10: ='Data BoP'!B9 -> 2006-Q4 | C10: =IF('Data BoP'!$AQ9=0,"",(('Data BoP'!E6)+('Data BoP'!E7)+('Data BoP'!E8)+('Data BoP'!E9))/'Data BoP'!$AQ9) -> 0.027907847 | D10: =IF('Data BoP'!$AQ9=0,"",(('Data BoP'!G6)+('Data BoP'!G7)+('Data BoP'!G8)+('Data BoP'!G9))/'Data BoP'!$AQ9) -> 0.060247397 | E10: =IF('Data BoP'!$AQ9=0,"",(('Data BoP'!J6)+('Data BoP'!J7)+('Data BoP'!J8)+('Data BoP'!J9))/'Data BoP'!$AQ9) -> -0.0032763727 | F10: =IF('Data BoP'!$AQ9=0,"",(('Data BoP'!M6)+('Data BoP'!M7)+('Data BoP'!M8)+('Data BoP'!M9))/'Data BoP'!$AQ9) -> -0.033163251 | G10: =IF('Data BoP'!$AQ9=0,"",(('Data BoP'!S6)+('Data BoP'!S7)+('Data BoP'!S8)+('Data BoP'!S9))/'Data BoP'!$AQ9) -> 0.0041000743 | H10: =IF('Data BoP'!$AQ9=0,"",(('Data BoP'!U6)+('Data BoP'!U7)+('Data BoP'!U8)+('Data BoP'!U9))/'Data BoP'!$AQ9) -> 0.03212326 | I10: =IF('Data BoP'!$AQ9=0,"",(('Data BoP'!Y6+'Data BoP'!Z6)+('Data BoP'!Y7+'Data BoP'!Z7)+('Data BoP'!Y8+'Data BoP'!Z8)+('Data BoP'!Y9+'Data BoP'!Z9))/'Data BoP'!$AQ9) -> 0.023779066 | J10: =IF('Data BoP'!$AQ9=0,"",(('Data BoP'!AD6+'Data BoP'!AE6)+('Data BoP'!AD7+'Data BoP'!AE7)+('Data BoP'!AD8+'Data BoP'!AE8)+('Data BoP'!AD9+'Data BoP'!AE9))/'Data BoP'!$AQ9) -> 0.036503278 | K10: =IF('Data BoP'!$AQ9=0,"",(('Data BoP'!AL6)+('Data BoP'!AL7)+('Data BoP'!AL8)+('Data BoP'!AL9))/'Data BoP'!$AQ9) -> -0.046899885 | L10: =IF('Data BoP'!$AQ9=0,"",(('Data BoP'!W6+'Data BoP'!X6+'Data BoP'!AB6+'Data BoP'!AC6+'Data BoP'!AH6)+('Data BoP'!W7+'Data BoP'!X7+'Data BoP'!AB7+'Data BoP'!AC7+'Data BoP'!AH7)+('Data BoP'!W8+'Data BoP'!X8+'Data BoP'!AB8+'Data BoP'!AC8+'Data BoP'!AH8)+('Data BoP'!W9+'Data BoP'!X9+'Data BoP'!AB9+'Data BoP'!AC9+'Data BoP'!AH9))/'Data BoP'!$AQ9) -> 0.029803699 | M10: =IF('Data BoP'!$AQ9=0,"",(('Data BoP'!AK6)+('Data BoP'!AK7)+('Data BoP'!AK8)+('Data BoP'!AK9))/'Data BoP'!$AQ9) -> 0.0037961839 | N10: =IF('Data BoP'!$AQ9=0,"",(('Data BoP'!AJ6)+('Data BoP'!AJ7)+('Data BoP'!AJ8)+('Data BoP'!AJ9))/'Data BoP'!$AQ9) -> 0.015158171 | O10: ='Data BoP'!$AQ9 -> 232866.49
B11: ='Data BoP'!B10 -> 2007-Q1 | C11: =IF('Data BoP'!$AQ10=0,"",(('Data BoP'!E7)+('Data BoP'!E8)+('Data BoP'!E9)+('Data BoP'!E10))/'Data BoP'!$AQ10) -> 0.026340059 | D11: =IF('Data BoP'!$AQ10=0,"",(('Data BoP'!G7)+('Data BoP'!G8)+('Data BoP'!G9)+('Data BoP'!G10))/'Data BoP'!$AQ10) -> 0.055780993 | E11: =IF('Data BoP'!$AQ10=0,"",(('Data BoP'!J7)+('Data BoP'!J8)+('Data BoP'!J9)+('Data BoP'!J10))/'Data BoP'!$AQ10) -> -0.0026534825 | F11: =IF('Data BoP'!$AQ10=0,"",(('Data BoP'!M7)+('Data BoP'!M8)+('Data BoP'!M9)+('Data BoP'!M10))/'Data BoP'!$AQ10) -> -0.03089049 | G11: =IF('Data BoP'!$AQ10=0,"",(('Data BoP'!S7)+('Data BoP'!S8)+('Data BoP'!S9)+('Data BoP'!S10))/'Data BoP'!$AQ10) -> 0.0041030387 | H11: =IF('Data BoP'!$AQ10=0,"",(('Data BoP'!U7)+('Data BoP'!U8)+('Data BoP'!U9)+('Data BoP'!U10))/'Data BoP'!$AQ10) -> 0.033662156 | I11: =IF('Data BoP'!$AQ10=0,"",(('Data BoP'!Y7+'Data BoP'!Z7)+('Data BoP'!Y8+'Data BoP'!Z8)+('Data BoP'!Y9+'Data BoP'!Z9)+('Data BoP'!Y10+'Data BoP'!Z10))/'Data BoP'!$AQ10) -> 0.020222126 | J11: =IF('Data BoP'!$AQ10=0,"",(('Data BoP'!AD7+'Data BoP'!AE7)+('Data BoP'!AD8+'Data BoP'!AE8)+('Data BoP'!AD9+'Data BoP'!AE9)+('Data BoP'!AD10+'Data BoP'!AE10))/'Data BoP'!$AQ10) -> 0.033235464 | K11: =IF('Data BoP'!$AQ10=0,"",(('Data BoP'!AL7)+('Data BoP'!AL8)+('Data BoP'!AL9)+('Data BoP'!AL10))/'Data BoP'!$AQ10) -> 0.00051282614 | L11: =IF('Data BoP'!$AQ10=0,"",(('Data BoP'!W7+'Data BoP'!X7+'Data BoP'!AB7+'Data BoP'!AC7+'Data BoP'!AH7)+('Data BoP'!W8+'Data BoP'!X8+'Data BoP'!AB8+'Data BoP'!AC8+'Data BoP'!AH8)+('Data BoP'!W9+'Data BoP'!X9+'Data BoP'!AB9+'Data BoP'!AC9+'Data BoP'!AH9)+('Data BoP'!W10+'Data BoP'!X10+'Data BoP'!AB10+'Data BoP'!AC10+'Data BoP'!AH10))/'Data BoP'!$AQ10) -> 0.025979628 | M11: =IF('Data BoP'!$AQ10=0,"",(('Data BoP'!AK7)+('Data BoP'!AK8)+('Data BoP'!AK9)+('Data BoP'!AK10))/'Data BoP'!$AQ10) -> 0.0069156153 | N11: =IF('Data BoP'!$AQ10=0,"",(('Data BoP'!AJ7)+('Data BoP'!AJ8)+('Data BoP'!AJ9)+('Data BoP'!AJ10))/'Data BoP'!$AQ10) -> 0.061033327 | O11: ='Data BoP'!$AQ10 -> 242874.85
B12: ='Data BoP'!B11 -> 2007-Q2 | C12: =IF('Data BoP'!$AQ11=0,"",(('Data BoP'!E8)+('Data BoP'!E9)+('Data BoP'!E10)+('Data BoP'!E11))/'Data BoP'!$AQ11) -> 0.025331978 | D12: =IF('Data BoP'!$AQ11=0,"",(('Data BoP'!G8)+('Data BoP'!G9)+('Data BoP'!G10)+('Data BoP'!G11))/'Data BoP'!$AQ11) -> 0.052200289 | E12: =IF('Data BoP'!$AQ11=0,"",(('Data BoP'!J8)+('Data BoP'!J9)+('Data BoP'!J10)+('Data BoP'!J11))/'Data BoP'!$AQ11) -> -0.0026711235 | F12: =IF('Data BoP'!$AQ11=0,"",(('Data BoP'!M8)+('Data BoP'!M9)+('Data BoP'!M10)+('Data BoP'!M11))/'Data BoP'!$AQ11) -> -0.028126731 | G12: =IF('Data BoP'!$AQ11=0,"",(('Data BoP'!S8)+('Data BoP'!S9)+('Data BoP'!S10)+('Data BoP'!S11))/'Data BoP'!$AQ11) -> 0.0039295432 | H12: =IF('Data BoP'!$AQ11=0,"",(('Data BoP'!U8)+('Data BoP'!U9)+('Data BoP'!U10)+('Data BoP'!U11))/'Data BoP'!$AQ11) -> 0.027860401 | I12: =IF('Data BoP'!$AQ11=0,"",(('Data BoP'!Y8+'Data BoP'!Z8)+('Data BoP'!Y9+'Data BoP'!Z9)+('Data BoP'!Y10+'Data BoP'!Z10)+('Data BoP'!Y11+'Data BoP'!Z11))/'Data BoP'!$AQ11) -> 0.016537493 | J12: =IF('Data BoP'!$AQ11=0,"",(('Data BoP'!AD8+'Data BoP'!AE8)+('Data BoP'!AD9+'Data BoP'!AE9)+('Data BoP'!AD10+'Data BoP'!AE10)+('Data BoP'!AD11+'Data BoP'!AE11))/'Data BoP'!$AQ11) -> 0.046402993 | K12: =IF('Data BoP'!$AQ11=0,"",(('Data BoP'!AL8)+('Data BoP'!AL9)+('Data BoP'!AL10)+('Data BoP'!AL11))/'Data BoP'!$AQ11) -> 0.0059539996 | L12: =IF('Data BoP'!$AQ11=0,"",(('Data BoP'!W8+'Data BoP'!X8+'Data BoP'!AB8+'Data BoP'!AC8+'Data BoP'!AH8)+('Data BoP'!W9+'Data BoP'!X9+'Data BoP'!AB9+'Data BoP'!AC9+'Data BoP'!AH9)+('Data BoP'!W10+'Data BoP'!X10+'Data BoP'!AB10+'Data BoP'!AC10+'Data BoP'!AH10)+('Data BoP'!W11+'Data BoP'!X11+'Data BoP'!AB11+'Data BoP'!AC11+'Data BoP'!AH11))/'Data BoP'!$AQ11) -> 0.028510079 | M12: =IF('Data BoP'!$AQ11=0,"",(('Data BoP'!AK8)+('Data BoP'!AK9)+('Data BoP'!AK10)+('Data BoP'!AK11))/'Data BoP'!$AQ11) -> 0.0022733967 | N12: =IF('Data BoP'!$AQ11=0,"",(('Data BoP'!AJ8)+('Data BoP'!AJ9)+('Data BoP'!AJ10)+('Data BoP'!AJ11))/'Data BoP'!$AQ11) -> 0.067428401 | O12: ='Data BoP'!$AQ11 -> 256866.39
B13: ='Data BoP'!B12 -> 2007-Q3 | C13: =IF('Data BoP'!$AQ12=0,"",(('Data BoP'!E9)+('Data BoP'!E10)+('Data BoP'!E11)+('Data BoP'!E12))/'Data BoP'!$AQ12) -> 0.020097207 | D13: =IF('Data BoP'!$AQ12=0,"",(('Data BoP'!G9)+('Data BoP'!G10)+('Data BoP'!G11)+('Data BoP'!G12))/'Data BoP'!$AQ12) -> 0.046182187 | E13: =IF('Data BoP'!$AQ12=0,"",(('Data BoP'!J9)+('Data BoP'!J10)+('Data BoP'!J11)+('Data BoP'!J12))/'Data BoP'!$AQ12) -> -0.0033252033 | F13: =IF('Data BoP'!$AQ12=0,"",(('Data BoP'!M9)+('Data BoP'!M10)+('Data BoP'!M11)+('Data BoP'!M12))/'Data BoP'!$AQ12) -> -0.026601359 | G13: =IF('Data BoP'!$AQ12=0,"",(('Data BoP'!S9)+('Data BoP'!S10)+('Data BoP'!S11)+('Data BoP'!S12))/'Data BoP'!$AQ12) -> 0.0038415819 | H13: =IF('Data BoP'!$AQ12=0,"",(('Data BoP'!U9)+('Data BoP'!U10)+('Data BoP'!U11)+('Data BoP'!U12))/'Data BoP'!$AQ12) -> 0.024462399 | I13: =IF('Data BoP'!$AQ12=0,"",(('Data BoP'!Y9+'Data BoP'!Z9)+('Data BoP'!Y10+'Data BoP'!Z10)+('Data BoP'!Y11+'Data BoP'!Z11)+('Data BoP'!Y12+'Data BoP'!Z12))/'Data BoP'!$AQ12) -> 0.01698793 | J13: =IF('Data BoP'!$AQ12=0,"",(('Data BoP'!AD9+'Data BoP'!AE9)+('Data BoP'!AD10+'Data BoP'!AE10)+('Data BoP'!AD11+'Data BoP'!AE11)+('Data BoP'!AD12+'Data BoP'!AE12))/'Data BoP'!$AQ12) -> 0.035692714 | K13: =IF('Data BoP'!$AQ12=0,"",(('Data BoP'!AL9)+('Data BoP'!AL10)+('Data BoP'!AL11)+('Data BoP'!AL12))/'Data BoP'!$AQ12) -> 0.016004862 | L13: =IF('Data BoP'!$AQ12=0,"",(('Data BoP'!W9+'Data BoP'!X9+'Data BoP'!AB9+'Data BoP'!AC9+'Data BoP'!AH9)+('Data BoP'!W10+'Data BoP'!X10+'Data BoP'!AB10+'Data BoP'!AC10+'Data BoP'!AH10)+('Data BoP'!W11+'Data BoP'!X11+'Data BoP'!AB11+'Data BoP'!AC11+'Data BoP'!AH11)+('Data BoP'!W12+'Data BoP'!X12+'Data BoP'!AB12+'Data BoP'!AC12+'Data BoP'!AH12))/'Data BoP'!$AQ12) -> 0.04076265 | M13: =IF('Data BoP'!$AQ12=0,"",(('Data BoP'!AK9)+('Data BoP'!AK10)+('Data BoP'!AK11)+('Data BoP'!AK12))/'Data BoP'!$AQ12) -> 0.0039133638 | N13: =IF('Data BoP'!$AQ12=0,"",(('Data BoP'!AJ9)+('Data BoP'!AJ10)+('Data BoP'!AJ11)+('Data BoP'!AJ12))/'Data BoP'!$AQ12) -> 0.051536379 | O13: ='Data BoP'!$AQ12 -> 270651.15
B14: ='Data BoP'!B13 -> 2007-Q4 | C14: =IF('Data BoP'!$AQ13=0,"",(('Data BoP'!E10)+('Data BoP'!E11)+('Data BoP'!E12)+('Data BoP'!E13))/'Data BoP'!$AQ13) -> 0.021017475 | D14: =IF('Data BoP'!$AQ13=0,"",(('Data BoP'!G10)+('Data BoP'!G11)+('Data BoP'!G12)+('Data BoP'!G13))/'Data BoP'!$AQ13) -> 0.04709074 | E14: =IF('Data BoP'!$AQ13=0,"",(('Data BoP'!J10)+('Data BoP'!J11)+('Data BoP'!J12)+('Data BoP'!J13))/'Data BoP'!$AQ13) -> -0.0034104563 | F14: =IF('Data BoP'!$AQ13=0,"",(('Data BoP'!M10)+('Data BoP'!M11)+('Data BoP'!M12)+('Data BoP'!M13))/'Data BoP'!$AQ13) -> -0.026389929 | G14: =IF('Data BoP'!$AQ13=0,"",(('Data BoP'!S10)+('Data BoP'!S11)+('Data BoP'!S12)+('Data BoP'!S13))/'Data BoP'!$AQ13) -> 0.0037271208 | H14: =IF('Data BoP'!$AQ13=0,"",(('Data BoP'!U10)+('Data BoP'!U11)+('Data BoP'!U12)+('Data BoP'!U13))/'Data BoP'!$AQ13) -> 0.020499413 | I14: =IF('Data BoP'!$AQ13=0,"",(('Data BoP'!Y10+'Data BoP'!Z10)+('Data BoP'!Y11+'Data BoP'!Z11)+('Data BoP'!Y12+'Data BoP'!Z12)+('Data BoP'!Y13+'Data BoP'!Z13))/'Data BoP'!$AQ13) -> 0.022492945 | J14: =IF('Data BoP'!$AQ13=0,"",(('Data BoP'!AD10+'Data BoP'!AE10)+('Data BoP'!AD11+'Data BoP'!AE11)+('Data BoP'!AD12+'Data BoP'!AE12)+('Data BoP'!AD13+'Data BoP'!AE13))/'Data BoP'!$AQ13) -> 0.030027547 | K14: =IF('Data BoP'!$AQ13=0,"",(('Data BoP'!AL10)+('Data BoP'!AL11)+('Data BoP'!AL12)+('Data BoP'!AL13))/'Data BoP'!$AQ13) -> 0.020413236 | L14: =IF('Data BoP'!$AQ13=0,"",(('Data BoP'!W10+'Data BoP'!X10+'Data BoP'!AB10+'Data BoP'!AC10+'Data BoP'!AH10)+('Data BoP'!W11+'Data BoP'!X11+'Data BoP'!AB11+'Data BoP'!AC11+'Data BoP'!AH11)+('Data BoP'!W12+'Data BoP'!X12+'Data BoP'!AB12+'Data BoP'!AC12+'Data BoP'!AH12)+('Data BoP'!W13+'Data BoP'!X13+'Data BoP'!AB13+'Data BoP'!AC13+'Data BoP'!AH13))/'Data BoP'!$AQ13) -> 0.045987119 | M14: =IF('Data BoP'!$AQ13=0,"",(('Data BoP'!AK10)+('Data BoP'!AK11)+('Data BoP'!AK12)+('Data BoP'!AK13))/'Data BoP'!$AQ13) -> -0.00093901988 | N14: =IF('Data BoP'!$AQ13=0,"",(('Data BoP'!AJ10)+('Data BoP'!AJ11)+('Data BoP'!AJ12)+('Data BoP'!AJ13))/'Data BoP'!$AQ13) -> 0.045484193 | O14: ='Data BoP'!$AQ13 -> 287786.14
B15: ='Data BoP'!B14 -> 2008-Q1 | C15: =IF('Data BoP'!$AQ14=0,"",(('Data BoP'!E11)+('Data BoP'!E12)+('Data BoP'!E13)+('Data BoP'!E14))/'Data BoP'!$AQ14) -> 0.022042623 | D15: =IF('Data BoP'!$AQ14=0,"",(('Data BoP'!G11)+('Data BoP'!G12)+('Data BoP'!G13)+('Data BoP'!G14))/'Data BoP'!$AQ14) -> 0.048800061 | E15: =IF('Data BoP'!$AQ14=0,"",(('Data BoP'!J11)+('Data BoP'!J12)+('Data BoP'!J13)+('Data BoP'!J14))/'Data BoP'!$AQ14) -> -0.0046935291 | F15: =IF('Data BoP'!$AQ14=0,"",(('Data BoP'!M11)+('Data BoP'!M12)+('Data BoP'!M13)+('Data BoP'!M14))/'Data BoP'!$AQ14) -> -0.025694438 | G15: =IF('Data BoP'!$AQ14=0,"",(('Data BoP'!S11)+('Data BoP'!S12)+('Data BoP'!S13)+('Data BoP'!S14))/'Data BoP'!$AQ14) -> 0.0036305287 | H15: =IF('Data BoP'!$AQ14=0,"",(('Data BoP'!U11)+('Data BoP'!U12)+('Data BoP'!U13)+('Data BoP'!U14))/'Data BoP'!$AQ14) -> 0.022902635 | I15: =IF('Data BoP'!$AQ14=0,"",(('Data BoP'!Y11+'Data BoP'!Z11)+('Data BoP'!Y12+'Data BoP'!Z12)+('Data BoP'!Y13+'Data BoP'!Z13)+('Data BoP'!Y14+'Data BoP'!Z14))/'Data BoP'!$AQ14) -> 0.028747127 | J15: =IF('Data BoP'!$AQ14=0,"",(('Data BoP'!AD11+'Data BoP'!AE11)+('Data BoP'!AD12+'Data BoP'!AE12)+('Data BoP'!AD13+'Data BoP'!AE13)+('Data BoP'!AD14+'Data BoP'!AE14))/'Data BoP'!$AQ14) -> 0.018722005 | K15: =IF('Data BoP'!$AQ14=0,"",(('Data BoP'!AL11)+('Data BoP'!AL12)+('Data BoP'!AL13)+('Data BoP'!AL14))/'Data BoP'!$AQ14) -> 0.021901941 | L15: =IF('Data BoP'!$AQ14=0,"",(('Data BoP'!W11+'Data BoP'!X11+'Data BoP'!AB11+'Data BoP'!AC11+'Data BoP'!AH11)+('Data BoP'!W12+'Data BoP'!X12+'Data BoP'!AB12+'Data BoP'!AC12+'Data BoP'!AH12)+('Data BoP'!W13+'Data BoP'!X13+'Data BoP'!AB13+'Data BoP'!AC13+'Data BoP'!AH13)+('Data BoP'!W14+'Data BoP'!X14+'Data BoP'!AB14+'Data BoP'!AC14+'Data BoP'!AH14))/'Data BoP'!$AQ14) -> 0.051546524 | M15: =IF('Data BoP'!$AQ14=0,"",(('Data BoP'!AK11)+('Data BoP'!AK12)+('Data BoP'!AK13)+('Data BoP'!AK14))/'Data BoP'!$AQ14) -> 0.00036095036 | N15: =IF('Data BoP'!$AQ14=0,"",(('Data BoP'!AJ11)+('Data BoP'!AJ12)+('Data BoP'!AJ13)+('Data BoP'!AJ14))/'Data BoP'!$AQ14) -> 0.038954972 | O15: ='Data BoP'!$AQ14 -> 307129.98
B16: ='Data BoP'!B15 -> 2008-Q2 | C16: =IF('Data BoP'!$AQ15=0,"",(('Data BoP'!E12)+('Data BoP'!E13)+('Data BoP'!E14)+('Data BoP'!E15))/'Data BoP'!$AQ15) -> 0.015293839 | D16: =IF('Data BoP'!$AQ15=0,"",(('Data BoP'!G12)+('Data BoP'!G13)+('Data BoP'!G14)+('Data BoP'!G15))/'Data BoP'!$AQ15) -> 0.042126801 | E16: =IF('Data BoP'!$AQ15=0,"",(('Data BoP'!J12)+('Data BoP'!J13)+('Data BoP'!J14)+('Data BoP'!J15))/'Data BoP'!$AQ15) -> -0.0053962038 | F16: =IF('Data BoP'!$AQ15=0,"",(('Data BoP'!M12)+('Data BoP'!M13)+('Data BoP'!M14)+('Data BoP'!M15))/'Data BoP'!$AQ15) -> -0.024890627 | G16: =IF('Data BoP'!$AQ15=0,"",(('Data BoP'!S12)+('Data BoP'!S13)+('Data BoP'!S14)+('Data BoP'!S15))/'Data BoP'!$AQ15) -> 0.003453868 | H16: =IF('Data BoP'!$AQ15=0,"",(('Data BoP'!U12)+('Data BoP'!U13)+('Data BoP'!U14)+('Data BoP'!U15))/'Data BoP'!$AQ15) -> 0.016325443 | I16: =IF('Data BoP'!$AQ15=0,"",(('Data BoP'!Y12+'Data BoP'!Z12)+('Data BoP'!Y13+'Data BoP'!Z13)+('Data BoP'!Y14+'Data BoP'!Z14)+('Data BoP'!Y15+'Data BoP'!Z15))/'Data BoP'!$AQ15) -> 0.030189099 | J16: =IF('Data BoP'!$AQ15=0,"",(('Data BoP'!AD12+'Data BoP'!AE12)+('Data BoP'!AD13+'Data BoP'!AE13)+('Data BoP'!AD14+'Data BoP'!AE14)+('Data BoP'!AD15+'Data BoP'!AE15))/'Data BoP'!$AQ15) -> -0.0047560191 | K16: =IF('Data BoP'!$AQ15=0,"",(('Data BoP'!AL12)+('Data BoP'!AL13)+('Data BoP'!AL14)+('Data BoP'!AL15))/'Data BoP'!$AQ15) -> 0.028428708 | L16: =IF('Data BoP'!$AQ15=0,"",(('Data BoP'!W12+'Data BoP'!X12+'Data BoP'!AB12+'Data BoP'!AC12+'Data BoP'!AH12)+('Data BoP'!W13+'Data BoP'!X13+'Data BoP'!AB13+'Data BoP'!AC13+'Data BoP'!AH13)+('Data BoP'!W14+'Data BoP'!X14+'Data BoP'!AB14+'Data BoP'!AC14+'Data BoP'!AH14)+('Data BoP'!W15+'Data BoP'!X15+'Data BoP'!AB15+'Data BoP'!AC15+'Data BoP'!AH15))/'Data BoP'!$AQ15) -> 0.059370103 | M16: =IF('Data BoP'!$AQ15=0,"",(('Data BoP'!AK12)+('Data BoP'!AK13)+('Data BoP'!AK14)+('Data BoP'!AK15))/'Data BoP'!$AQ15) -> 0.00054423089 | N16: =IF('Data BoP'!$AQ15=0,"",(('Data BoP'!AJ12)+('Data BoP'!AJ13)+('Data BoP'!AJ14)+('Data BoP'!AJ15))/'Data BoP'!$AQ15) -> 0.0090731411 | O16: ='Data BoP'!$AQ15 -> 331049.63
B17: ='Data BoP'!B16 -> 2008-Q3 | C17: =IF('Data BoP'!$AQ16=0,"",(('Data BoP'!E13)+('Data BoP'!E14)+('Data BoP'!E15)+('Data BoP'!E16))/'Data BoP'!$AQ16) -> 0.021403908 | D17: =IF('Data BoP'!$AQ16=0,"",(('Data BoP'!G13)+('Data BoP'!G14)+('Data BoP'!G15)+('Data BoP'!G16))/'Data BoP'!$AQ16) -> 0.048568278 | E17: =IF('Data BoP'!$AQ16=0,"",(('Data BoP'!J13)+('Data BoP'!J14)+('Data BoP'!J15)+('Data BoP'!J16))/'Data BoP'!$AQ16) -> -0.0056382454 | F17: =IF('Data BoP'!$AQ16=0,"",(('Data BoP'!M13)+('Data BoP'!M14)+('Data BoP'!M15)+('Data BoP'!M16))/'Data BoP'!$AQ16) -> -0.024767528 | G17: =IF('Data BoP'!$AQ16=0,"",(('Data BoP'!S13)+('Data BoP'!S14)+('Data BoP'!S15)+('Data BoP'!S16))/'Data BoP'!$AQ16) -> 0.0032414033 | H17: =IF('Data BoP'!$AQ16=0,"",(('Data BoP'!U13)+('Data BoP'!U14)+('Data BoP'!U15)+('Data BoP'!U16))/'Data BoP'!$AQ16) -> 0.026012435 | I17: =IF('Data BoP'!$AQ16=0,"",(('Data BoP'!Y13+'Data BoP'!Z13)+('Data BoP'!Y14+'Data BoP'!Z14)+('Data BoP'!Y15+'Data BoP'!Z15)+('Data BoP'!Y16+'Data BoP'!Z16))/'Data BoP'!$AQ16) -> 0.029422467 | J17: =IF('Data BoP'!$AQ16=0,"",(('Data BoP'!AD13+'Data BoP'!AE13)+('Data BoP'!AD14+'Data BoP'!AE14)+('Data BoP'!AD15+'Data BoP'!AE15)+('Data BoP'!AD16+'Data BoP'!AE16))/'Data BoP'!$AQ16) -> -0.0071362013 | K17: =IF('Data BoP'!$AQ16=0,"",(('Data BoP'!AL13)+('Data BoP'!AL14)+('Data BoP'!AL15)+('Data BoP'!AL16))/'Data BoP'!$AQ16) -> 0.026006301 | L17: =IF('Data BoP'!$AQ16=0,"",(('Data BoP'!W13+'Data BoP'!X13+'Data BoP'!AB13+'Data BoP'!AC13+'Data BoP'!AH13)+('Data BoP'!W14+'Data BoP'!X14+'Data BoP'!AB14+'Data BoP'!AC14+'Data BoP'!AH14)+('Data BoP'!W15+'Data BoP'!X15+'Data BoP'!AB15+'Data BoP'!AC15+'Data BoP'!AH15)+('Data BoP'!W16+'Data BoP'!X16+'Data BoP'!AB16+'Data BoP'!AC16+'Data BoP'!AH16))/'Data BoP'!$AQ16) -> 0.061913842 | M17: =IF('Data BoP'!$AQ16=0,"",(('Data BoP'!AK13)+('Data BoP'!AK14)+('Data BoP'!AK15)+('Data BoP'!AK16))/'Data BoP'!$AQ16) -> 0.0040937134 | N17: =IF('Data BoP'!$AQ16=0,"",(('Data BoP'!AJ13)+('Data BoP'!AJ14)+('Data BoP'!AJ15)+('Data BoP'!AJ16))/'Data BoP'!$AQ16) -> 0.010682658 | O17: ='Data BoP'!$AQ16 -> 355340.41
B18: ='Data BoP'!B17 -> 2008-Q4 | C18: =IF('Data BoP'!$AQ17=0,"",(('Data BoP'!E14)+('Data BoP'!E15)+('Data BoP'!E16)+('Data BoP'!E17))/'Data BoP'!$AQ17) -> 0.014898402 | D18: =IF('Data BoP'!$AQ17=0,"",(('Data BoP'!G14)+('Data BoP'!G15)+('Data BoP'!G16)+('Data BoP'!G17))/'Data BoP'!$AQ17) -> 0.042770533 | E18: =IF('Data BoP'!$AQ17=0,"",(('Data BoP'!J14)+('Data BoP'!J15)+('Data BoP'!J16)+('Data BoP'!J17))/'Data BoP'!$AQ17) -> -0.0061073567 | F18: =IF('Data BoP'!$AQ17=0,"",(('Data BoP'!M14)+('Data BoP'!M15)+('Data BoP'!M16)+('Data BoP'!M17))/'Data BoP'!$AQ17) -> -0.024827501 | G18: =IF('Data BoP'!$AQ17=0,"",(('Data BoP'!S14)+('Data BoP'!S15)+('Data BoP'!S16)+('Data BoP'!S17))/'Data BoP'!$AQ17) -> 0.0030627268 | H18: =IF('Data BoP'!$AQ17=0,"",(('Data BoP'!U14)+('Data BoP'!U15)+('Data BoP'!U16)+('Data BoP'!U17))/'Data BoP'!$AQ17) -> 0.018011387 | I18: =IF('Data BoP'!$AQ17=0,"",(('Data BoP'!Y14+'Data BoP'!Z14)+('Data BoP'!Y15+'Data BoP'!Z15)+('Data BoP'!Y16+'Data BoP'!Z16)+('Data BoP'!Y17+'Data BoP'!Z17))/'Data BoP'!$AQ17) -> 0.026727483 | J18: =IF('Data BoP'!$AQ17=0,"",(('Data BoP'!AD14+'Data BoP'!AE14)+('Data BoP'!AD15+'Data BoP'!AE15)+('Data BoP'!AD16+'Data BoP'!AE16)+('Data BoP'!AD17+'Data BoP'!AE17))/'Data BoP'!$AQ17) -> -0.015727852 | K18: =IF('Data BoP'!$AQ17=0,"",(('Data BoP'!AL14)+('Data BoP'!AL15)+('Data BoP'!AL16)+('Data BoP'!AL17))/'Data BoP'!$AQ17) -> 0.016990873 | L18: =IF('Data BoP'!$AQ17=0,"",(('Data BoP'!W14+'Data BoP'!X14+'Data BoP'!AB14+'Data BoP'!AC14+'Data BoP'!AH14)+('Data BoP'!W15+'Data BoP'!X15+'Data BoP'!AB15+'Data BoP'!AC15+'Data BoP'!AH15)+('Data BoP'!W16+'Data BoP'!X16+'Data BoP'!AB16+'Data BoP'!AC16+'Data BoP'!AH16)+('Data BoP'!W17+'Data BoP'!X17+'Data BoP'!AB17+'Data BoP'!AC17+'Data BoP'!AH17))/'Data BoP'!$AQ17) -> 0.043385413 | M18: =IF('Data BoP'!$AQ17=0,"",(('Data BoP'!AK14)+('Data BoP'!AK15)+('Data BoP'!AK16)+('Data BoP'!AK17))/'Data BoP'!$AQ17) -> 0.0026044083 | N18: =IF('Data BoP'!$AQ17=0,"",(('Data BoP'!AJ14)+('Data BoP'!AJ15)+('Data BoP'!AJ16)+('Data BoP'!AJ17))/'Data BoP'!$AQ17) -> 4.7763212e-05 | O18: ='Data BoP'!$AQ17 -> 363878.37
B19: ='Data BoP'!B18 -> 2009-Q1 | C19: =IF('Data BoP'!$AQ18=0,"",(('Data BoP'!E15)+('Data BoP'!E16)+('Data BoP'!E17)+('Data BoP'!E18))/'Data BoP'!$AQ18) -> 0.014670381 | D19: =IF('Data BoP'!$AQ18=0,"",(('Data BoP'!G15)+('Data BoP'!G16)+('Data BoP'!G17)+('Data BoP'!G18))/'Data BoP'!$AQ18) -> 0.043554893 | E19: =IF('Data BoP'!$AQ18=0,"",(('Data BoP'!J15)+('Data BoP'!J16)+('Data BoP'!J17)+('Data BoP'!J18))/'Data BoP'!$AQ18) -> -0.0063699481 | F19: =IF('Data BoP'!$AQ18=0,"",(('Data BoP'!M15)+('Data BoP'!M16)+('Data BoP'!M17)+('Data BoP'!M18))/'Data BoP'!$AQ18) -> -0.025387838 | G19: =IF('Data BoP'!$AQ18=0,"",(('Data BoP'!S15)+('Data BoP'!S16)+('Data BoP'!S17)+('Data BoP'!S18))/'Data BoP'!$AQ18) -> 0.0028732736 | H19: =IF('Data BoP'!$AQ18=0,"",(('Data BoP'!U15)+('Data BoP'!U16)+('Data BoP'!U17)+('Data BoP'!U18))/'Data BoP'!$AQ18) -> 0.013887919 | I19: =IF('Data BoP'!$AQ18=0,"",(('Data BoP'!Y15+'Data BoP'!Z15)+('Data BoP'!Y16+'Data BoP'!Z16)+('Data BoP'!Y17+'Data BoP'!Z17)+('Data BoP'!Y18+'Data BoP'!Z18))/'Data BoP'!$AQ18) -> 0.021950104 | J19: =IF('Data BoP'!$AQ18=0,"",(('Data BoP'!AD15+'Data BoP'!AE15)+('Data BoP'!AD16+'Data BoP'!AE16)+('Data BoP'!AD17+'Data BoP'!AE17)+('Data BoP'!AD18+'Data BoP'!AE18))/'Data BoP'!$AQ18) -> -0.01492521 | K19: =IF('Data BoP'!$AQ18=0,"",(('Data BoP'!AL15)+('Data BoP'!AL16)+('Data BoP'!AL17)+('Data BoP'!AL18))/'Data BoP'!$AQ18) -> 0.014392663 | L19: =IF('Data BoP'!$AQ18=0,"",(('Data BoP'!W15+'Data BoP'!X15+'Data BoP'!AB15+'Data BoP'!AC15+'Data BoP'!AH15)+('Data BoP'!W16+'Data BoP'!X16+'Data BoP'!AB16+'Data BoP'!AC16+'Data BoP'!AH16)+('Data BoP'!W17+'Data BoP'!X17+'Data BoP'!AB17+'Data BoP'!AC17+'Data BoP'!AH17)+('Data BoP'!W18+'Data BoP'!X18+'Data BoP'!AB18+'Data BoP'!AC18+'Data BoP'!AH18))/'Data BoP'!$AQ18) -> 0.041695227 | M19: =IF('Data BoP'!$AQ18=0,"",(('Data BoP'!AK15)+('Data BoP'!AK16)+('Data BoP'!AK17)+('Data BoP'!AK18))/'Data BoP'!$AQ18) -> -0.0012359901 | N19: =IF('Data BoP'!$AQ18=0,"",(('Data BoP'!AJ15)+('Data BoP'!AJ16)+('Data BoP'!AJ17)+('Data BoP'!AJ18))/'Data BoP'!$AQ18) -> -0.0090144333 | O19: ='Data BoP'!$AQ18 -> 360500.76
B20: ='Data BoP'!B19 -> 2009-Q2 | C20: =IF('Data BoP'!$AQ19=0,"",(('Data BoP'!E16)+('Data BoP'!E17)+('Data BoP'!E18)+('Data BoP'!E19))/'Data BoP'!$AQ19) -> 0.026694351 | D20: =IF('Data BoP'!$AQ19=0,"",(('Data BoP'!G16)+('Data BoP'!G17)+('Data BoP'!G18)+('Data BoP'!G19))/'Data BoP'!$AQ19) -> 0.056338955 | E20: =IF('Data BoP'!$AQ19=0,"",(('Data BoP'!J16)+('Data BoP'!J17)+('Data BoP'!J18)+('Data BoP'!J19))/'Data BoP'!$AQ19) -> -0.0055869343 | F20: =IF('Data BoP'!$AQ19=0,"",(('Data BoP'!M16)+('Data BoP'!M17)+('Data BoP'!M18)+('Data BoP'!M19))/'Data BoP'!$AQ19) -> -0.026909849 | G20: =IF('Data BoP'!$AQ19=0,"",(('Data BoP'!S16)+('Data BoP'!S17)+('Data BoP'!S18)+('Data BoP'!S19))/'Data BoP'!$AQ19) -> 0.0028521794 | H20: =IF('Data BoP'!$AQ19=0,"",(('Data BoP'!U16)+('Data BoP'!U17)+('Data BoP'!U18)+('Data BoP'!U19))/'Data BoP'!$AQ19) -> 0.025199611 | I20: =IF('Data BoP'!$AQ19=0,"",(('Data BoP'!Y16+'Data BoP'!Z16)+('Data BoP'!Y17+'Data BoP'!Z17)+('Data BoP'!Y18+'Data BoP'!Z18)+('Data BoP'!Y19+'Data BoP'!Z19))/'Data BoP'!$AQ19) -> 0.017265888 | J20: =IF('Data BoP'!$AQ19=0,"",(('Data BoP'!AD16+'Data BoP'!AE16)+('Data BoP'!AD17+'Data BoP'!AE17)+('Data BoP'!AD18+'Data BoP'!AE18)+('Data BoP'!AD19+'Data BoP'!AE19))/'Data BoP'!$AQ19) -> -0.012128155 | K20: =IF('Data BoP'!$AQ19=0,"",(('Data BoP'!AL16)+('Data BoP'!AL17)+('Data BoP'!AL18)+('Data BoP'!AL19))/'Data BoP'!$AQ19) -> 0.0053109755 | L20: =IF('Data BoP'!$AQ19=0,"",(('Data BoP'!W16+'Data BoP'!X16+'Data BoP'!AB16+'Data BoP'!AC16+'Data BoP'!AH16)+('Data BoP'!W17+'Data BoP'!X17+'Data BoP'!AB17+'Data BoP'!AC17+'Data BoP'!AH17)+('Data BoP'!W18+'Data BoP'!X18+'Data BoP'!AB18+'Data BoP'!AC18+'Data BoP'!AH18)+('Data BoP'!W19+'Data BoP'!X19+'Data BoP'!AB19+'Data BoP'!AC19+'Data BoP'!AH19))/'Data BoP'!$AQ19) -> 0.03691024 | M20: =IF('Data BoP'!$AQ19=0,"",(('Data BoP'!AK16)+('Data BoP'!AK17)+('Data BoP'!AK18)+('Data BoP'!AK19))/'Data BoP'!$AQ19) -> -0.0019249328 | N20: =IF('Data BoP'!$AQ19=0,"",(('Data BoP'!AJ16)+('Data BoP'!AJ17)+('Data BoP'!AJ18)+('Data BoP'!AJ19))/'Data BoP'!$AQ19) -> -0.0038238409 | O20: ='Data BoP'!$AQ19 -> 347161.41
B21: ='Data BoP'!B20 -> 2009-Q3 | C21: =IF('Data BoP'!$AQ20=0,"",(('Data BoP'!E17)+('Data BoP'!E18)+('Data BoP'!E19)+('Data BoP'!E20))/'Data BoP'!$AQ20) -> 0.020967812 | D21: =IF('Data BoP'!$AQ20=0,"",(('Data BoP'!G17)+('Data BoP'!G18)+('Data BoP'!G19)+('Data BoP'!G20))/'Data BoP'!$AQ20) -> 0.053064174 | E21: =IF('Data BoP'!$AQ20=0,"",(('Data BoP'!J17)+('Data BoP'!J18)+('Data BoP'!J19)+('Data BoP'!J20))/'Data BoP'!$AQ20) -> -0.0058962138 | F21: =IF('Data BoP'!$AQ20=0,"",(('Data BoP'!M17)+('Data BoP'!M18)+('Data BoP'!M19)+('Data BoP'!M20))/'Data BoP'!$AQ20) -> -0.028971362 | G21: =IF('Data BoP'!$AQ20=0,"",(('Data BoP'!S17)+('Data BoP'!S18)+('Data BoP'!S19)+('Data BoP'!S20))/'Data BoP'!$AQ20) -> 0.0027712137 | H21: =IF('Data BoP'!$AQ20=0,"",(('Data BoP'!U17)+('Data BoP'!U18)+('Data BoP'!U19)+('Data BoP'!U20))/'Data BoP'!$AQ20) -> 0.014327538 | I21: =IF('Data BoP'!$AQ20=0,"",(('Data BoP'!Y17+'Data BoP'!Z17)+('Data BoP'!Y18+'Data BoP'!Z18)+('Data BoP'!Y19+'Data BoP'!Z19)+('Data BoP'!Y20+'Data BoP'!Z20))/'Data BoP'!$AQ20) -> 0.012996066 | J21: =IF('Data BoP'!$AQ20=0,"",(('Data BoP'!AD17+'Data BoP'!AE17)+('Data BoP'!AD18+'Data BoP'!AE18)+('Data BoP'!AD19+'Data BoP'!AE19)+('Data BoP'!AD20+'Data BoP'!AE20))/'Data BoP'!$AQ20) -> -0.0079812913 | K21: =IF('Data BoP'!$AQ20=0,"",(('Data BoP'!AL17)+('Data BoP'!AL18)+('Data BoP'!AL19)+('Data BoP'!AL20))/'Data BoP'!$AQ20) -> 0.0047424488 | L21: =IF('Data BoP'!$AQ20=0,"",(('Data BoP'!W17+'Data BoP'!X17+'Data BoP'!AB17+'Data BoP'!AC17+'Data BoP'!AH17)+('Data BoP'!W18+'Data BoP'!X18+'Data BoP'!AB18+'Data BoP'!AC18+'Data BoP'!AH18)+('Data BoP'!W19+'Data BoP'!X19+'Data BoP'!AB19+'Data BoP'!AC19+'Data BoP'!AH19)+('Data BoP'!W20+'Data BoP'!X20+'Data BoP'!AB20+'Data BoP'!AC20+'Data BoP'!AH20))/'Data BoP'!$AQ20) -> 0.019786002 | M21: =IF('Data BoP'!$AQ20=0,"",(('Data BoP'!AK17)+('Data BoP'!AK18)+('Data BoP'!AK19)+('Data BoP'!AK20))/'Data BoP'!$AQ20) -> -0.0068813803 | N21: =IF('Data BoP'!$AQ20=0,"",(('Data BoP'!AJ17)+('Data BoP'!AJ18)+('Data BoP'!AJ19)+('Data BoP'!AJ20))/'Data BoP'!$AQ20) -> 0.001601202 | O21: ='Data BoP'!$AQ20 -> 332893.66
... B87: ='Data BoP'!B86 -> 2026-Q1 | C87: =IF('Data BoP'!$AQ86=0,"",(('Data BoP'!E83)+('Data BoP'!E84)+('Data BoP'!E85)+('Data BoP'!E86))/'Data BoP'!$AQ86) -> -0.0062543262 | D87: =IF('Data BoP'!$AQ86=0,"",(('Data BoP'!G83)+('Data BoP'!G84)+('Data BoP'!G85)+('Data BoP'!G86))/'Data BoP'!$AQ86) -> 0.028690426 | E87: =IF('Data BoP'!$AQ86=0,"",(('Data BoP'!J83)+('Data BoP'!J84)+('Data BoP'!J85)+('Data BoP'!J86))/'Data BoP'!$AQ86) -> -0.016171175 | F87: =IF('Data BoP'!$AQ86=0,"",(('Data BoP'!M83)+('Data BoP'!M84)+('Data BoP'!M85)+('Data BoP'!M86))/'Data BoP'!$AQ86) -> -0.022990448 | G87: =IF('Data BoP'!$AQ86=0,"",(('Data BoP'!S83)+('Data BoP'!S84)+('Data BoP'!S85)+('Data BoP'!S86))/'Data BoP'!$AQ86) -> 0.0042168704 | H87: =IF('Data BoP'!$AQ86=0,"",(('Data BoP'!U83)+('Data BoP'!U84)+('Data BoP'!U85)+('Data BoP'!U86))/'Data BoP'!$AQ86) -> -0.010536482 | I87: =IF('Data BoP'!$AQ86=0,"",(('Data BoP'!Y83+'Data BoP'!Z83)+('Data BoP'!Y84+'Data BoP'!Z84)+('Data BoP'!Y85+'Data BoP'!Z85)+('Data BoP'!Y86+'Data BoP'!Z86))/'Data BoP'!$AQ86) -> 0.0077291107 | J87: =IF('Data BoP'!$AQ86=0,"",(('Data BoP'!AD83+'Data BoP'!AE83)+('Data BoP'!AD84+'Data BoP'!AE84)+('Data BoP'!AD85+'Data BoP'!AE85)+('Data BoP'!AD86+'Data BoP'!AE86))/'Data BoP'!$AQ86) -> 0.010427537 | K87: =IF('Data BoP'!$AQ86=0,"",(('Data BoP'!AL83)+('Data BoP'!AL84)+('Data BoP'!AL85)+('Data BoP'!AL86))/'Data BoP'!$AQ86) -> 0.040558214 | L87: =IF('Data BoP'!$AQ86=0,"",(('Data BoP'!W83+'Data BoP'!X83+'Data BoP'!AB83+'Data BoP'!AC83+'Data BoP'!AH83)+('Data BoP'!W84+'Data BoP'!X84+'Data BoP'!AB84+'Data BoP'!AC84+'Data BoP'!AH84)+('Data BoP'!W85+'Data BoP'!X85+'Data BoP'!AB85+'Data BoP'!AC85+'Data BoP'!AH85)+('Data BoP'!W86+'Data BoP'!X86+'Data BoP'!AB86+'Data BoP'!AC86+'Data BoP'!AH86))/'Data BoP'!$AQ86) -> 0.029390043 | M87: =IF('Data BoP'!$AQ86=0,"",(('Data BoP'!AK83)+('Data BoP'!AK84)+('Data BoP'!AK85)+('Data BoP'!AK86))/'Data BoP'!$AQ86) -> -0.0049518348 | N87: =IF('Data BoP'!$AQ86=0,"",(('Data BoP'!AJ83)+('Data BoP'!AJ84)+('Data BoP'!AJ85)+('Data BoP'!AJ86))/'Data BoP'!$AQ86) -> 0.018786153 | O87: ='Data BoP'!$AQ86 -> 684502
B89: Denominator is nominal GDP converted at the official Com. "A" 3500 rate. Under a managed band that rate is not a market-clearing one, so the USD GDP level — and therefore every ratio here — moves with the regime as well as with the economy. In periods with a wide parallel gap (2012-2015, 2020-2023) these ratios understate the true burden.

Sheet Reserves
B2: Reserve assets — the BPM6 transaction line
B3: This is the change in reserves attributable to transactions, which is what the balance of payments explains. It is not the change in the headline stock: valuation, gold price and cross-rate moves are excluded.
B6: Quarter | C6: Quarterly | D6: 4q rolling | E6: Cumulative since 2006 | F6: % of GDP (4q rolling)
B7: ='Data BoP'!B6 -> 2006-Q1 | C7: ='Data BoP'!AJ6 -> -6633.94 | E7: =SUM('Data BoP'!$AJ$6:$AJ6) -> -6633.94
B8: ='Data BoP'!B7 -> 2006-Q2 | C8: ='Data BoP'!AJ7 -> 3843.01 | E8: =SUM('Data BoP'!$AJ$6:$AJ7) -> -2790.93
B9: ='Data BoP'!B8 -> 2006-Q3 | C9: ='Data BoP'!AJ8 -> 2529.96 | E9: =SUM('Data BoP'!$AJ$6:$AJ8) -> -260.97
B10: ='Data BoP'!B9 -> 2006-Q4 | C10: ='Data BoP'!AJ9 -> 3790.8 | D10: =SUM('Data BoP'!AJ6:AJ9) -> 3529.83 | E10: =SUM('Data BoP'!$AJ$6:$AJ9) -> 3529.83 | F10: =IF('Data BoP'!$AQ9=0,"",D10/'Data BoP'!$AQ9) -> 0.015158171
B11: ='Data BoP'!B10 -> 2007-Q1 | C11: ='Data BoP'!AJ10 -> 4659.69 | D11: =SUM('Data BoP'!AJ7:AJ10) -> 14823.46 | E11: =SUM('Data BoP'!$AJ$6:$AJ10) -> 8189.52 | F11: =IF('Data BoP'!$AQ10=0,"",D11/'Data BoP'!$AQ10) -> 0.061033327
B12: ='Data BoP'!B11 -> 2007-Q2 | C12: ='Data BoP'!AJ11 -> 6339.64 | D12: =SUM('Data BoP'!AJ8:AJ11) -> 17320.09 | E12: =SUM('Data BoP'!$AJ$6:$AJ11) -> 14529.16 | F12: =IF('Data BoP'!$AQ11=0,"",D12/'Data BoP'!$AQ11) -> 0.067428401
B13: ='Data BoP'!B12 -> 2007-Q3 | C13: ='Data BoP'!AJ12 -> -841.75 | D13: =SUM('Data BoP'!AJ9:AJ12) -> 13948.38 | E13: =SUM('Data BoP'!$AJ$6:$AJ12) -> 13687.41 | F13: =IF('Data BoP'!$AQ12=0,"",D13/'Data BoP'!$AQ12) -> 0.051536379
B14: ='Data BoP'!B13 -> 2007-Q4 | C14: ='Data BoP'!AJ13 -> 2932.14 | D14: =SUM('Data BoP'!AJ10:AJ13) -> 13089.72 | E14: =SUM('Data BoP'!$AJ$6:$AJ13) -> 16619.55 | F14: =IF('Data BoP'!$AQ13=0,"",D14/'Data BoP'!$AQ13) -> 0.045484193
B15: ='Data BoP'!B14 -> 2008-Q1 | C15: ='Data BoP'!AJ14 -> 3534.21 | D15: =SUM('Data BoP'!AJ11:AJ14) -> 11964.24 | E15: =SUM('Data BoP'!$AJ$6:$AJ14) -> 20153.76 | F15: =IF('Data BoP'!$AQ14=0,"",D15/'Data BoP'!$AQ14) -> 0.038954972
B16: ='Data BoP'!B15 -> 2008-Q2 | C16: ='Data BoP'!AJ15 -> -2620.94 | D16: =SUM('Data BoP'!AJ12:AJ15) -> 3003.66 | E16: =SUM('Data BoP'!$AJ$6:$AJ15) -> 17532.82 | F16: =IF('Data BoP'!$AQ15=0,"",D16/'Data BoP'!$AQ15) -> 0.0090731411
B17: ='Data BoP'!B16 -> 2008-Q3 | C17: ='Data BoP'!AJ16 -> -49.43 | D17: =SUM('Data BoP'!AJ13:AJ16) -> 3795.98 | E17: =SUM('Data BoP'!$AJ$6:$AJ16) -> 17483.39 | F17: =IF('Data BoP'!$AQ16=0,"",D17/'Data BoP'!$AQ16) -> 0.010682658
B18: ='Data BoP'!B17 -> 2008-Q4 | C18: ='Data BoP'!AJ17 -> -846.46 | D18: =SUM('Data BoP'!AJ14:AJ17) -> 17.38 | E18: =SUM('Data BoP'!$AJ$6:$AJ17) -> 16636.93 | F18: =IF('Data BoP'!$AQ17=0,"",D18/'Data BoP'!$AQ17) -> 4.7763212e-05
B19: ='Data BoP'!B18 -> 2009-Q1 | C19: ='Data BoP'!AJ18 -> 267.12 | D19: =SUM('Data BoP'!AJ15:AJ18) -> -3249.71 | E19: =SUM('Data BoP'!$AJ$6:$AJ18) -> 16904.05 | F19: =IF('Data BoP'!$AQ18=0,"",D19/'Data BoP'!$AQ18) -> -0.0090144333
B20: ='Data BoP'!B19 -> 2009-Q2 | C20: ='Data BoP'!AJ19 -> -698.72 | D20: =SUM('Data BoP'!AJ16:AJ19) -> -1327.49 | E20: =SUM('Data BoP'!$AJ$6:$AJ19) -> 16205.33 | F20: =IF('Data BoP'!$AQ19=0,"",D20/'Data BoP'!$AQ19) -> -0.0038238409
B21: ='Data BoP'!B20 -> 2009-Q3 | C21: ='Data BoP'!AJ20 -> 1811.09 | D21: =SUM('Data BoP'!AJ17:AJ20) -> 533.03 | E21: =SUM('Data BoP'!$AJ$6:$AJ20) -> 18016.42 | F21: =IF('Data BoP'!$AQ20=0,"",D21/'Data BoP'!$AQ20) -> 0.001601202
... B87: ='Data BoP'!B86 -> 2026-Q1 | C87: ='Data BoP'!AJ86 -> 10.584206 | D87: =SUM('Data BoP'!AJ83:AJ86) -> 12859.159 | E87: =SUM('Data BoP'!$AJ$6:$AJ86) -> 6699.252 | F87: =IF('Data BoP'!$AQ86=0,"",D87/'Data BoP'!$AQ86) -> 0.018786153
B90: Annual
B91: Year | C91: Reserve assets (USD mn) | D91: % of GDP | E91: Current account (USD mn) | F91: Net capital inflow (USD mn) | G91: Errors & omissions (USD mn)
B92: 2006 | C92: =SUMIFS('Data BoP'!$AJ$6:$AJ$86,'Data BoP'!$C$6:$C$86,$B92) -> 3529.83 | D92: =C92/SUMIFS('Data BoP'!$AP$6:$AP$86,'Data BoP'!$C$6:$C$86,$B92) -> 0.015158171 | E92: =SUMIFS('Data BoP'!$E$6:$E$86,'Data BoP'!$C$6:$C$86,$B92) -> 6498.8025 | F92: =-(SUMIFS('Data BoP'!$U$6:$U$86,'Data BoP'!$C$6:$C$86,$B92)-C92) -> -3950.6009 | G92: =SUMIFS('Data BoP'!$AK$6:$AK$86,'Data BoP'!$C$6:$C$86,$B92) -> 884.00404
B93: 2007 | C93: =SUMIFS('Data BoP'!$AJ$6:$AJ$86,'Data BoP'!$C$6:$C$86,$B93) -> 13089.72 | D93: =C93/SUMIFS('Data BoP'!$AP$6:$AP$86,'Data BoP'!$C$6:$C$86,$B93) -> 0.045484193 | E93: =SUMIFS('Data BoP'!$E$6:$E$86,'Data BoP'!$C$6:$C$86,$B93) -> 6048.5379 | F93: =-(SUMIFS('Data BoP'!$U$6:$U$86,'Data BoP'!$C$6:$C$86,$B93)-C93) -> 7190.2731 | G93: =SUMIFS('Data BoP'!$AK$6:$AK$86,'Data BoP'!$C$6:$C$86,$B93) -> -270.2369
B94: 2008 | C94: =SUMIFS('Data BoP'!$AJ$6:$AJ$86,'Data BoP'!$C$6:$C$86,$B94) -> 17.38 | D94: =C94/SUMIFS('Data BoP'!$AP$6:$AP$86,'Data BoP'!$C$6:$C$86,$B94) -> 4.7763212e-05 | E94: =SUMIFS('Data BoP'!$E$6:$E$86,'Data BoP'!$C$6:$C$86,$B94) -> 5421.2063 | F94: =-(SUMIFS('Data BoP'!$U$6:$U$86,'Data BoP'!$C$6:$C$86,$B94)-C94) -> -6536.5742 | G94: =SUMIFS('Data BoP'!$AK$6:$AK$86,'Data BoP'!$C$6:$C$86,$B94) -> 947.68784
B95: 2009 | C95: =SUMIFS('Data BoP'!$AJ$6:$AJ$86,'Data BoP'!$C$6:$C$86,$B95) -> 1346.21 | D95: =C95/SUMIFS('Data BoP'!$AP$6:$AP$86,'Data BoP'!$C$6:$C$86,$B95) -> 0.0040271718 | E95: =SUMIFS('Data BoP'!$E$6:$E$86,'Data BoP'!$C$6:$C$86,$B95) -> 7254.1157 | F95: =-(SUMIFS('Data BoP'!$U$6:$U$86,'Data BoP'!$C$6:$C$86,$B95)-C95) -> -5366.5726 | G95: =SUMIFS('Data BoP'!$AK$6:$AK$86,'Data BoP'!$C$6:$C$86,$B95) -> -621.31729
B96: 2010 | C96: =SUMIFS('Data BoP'!$AJ$6:$AJ$86,'Data BoP'!$C$6:$C$86,$B96) -> 4157.35 | D96: =C96/SUMIFS('Data BoP'!$AP$6:$AP$86,'Data BoP'!$C$6:$C$86,$B96) -> 0.0097971037 | E96: =SUMIFS('Data BoP'!$E$6:$E$86,'Data BoP'!$C$6:$C$86,$B96) -> -1622.9959 | F96: =-(SUMIFS('Data BoP'!$U$6:$U$86,'Data BoP'!$C$6:$C$86,$B96)-C96) -> 7959.4533 | G96: =SUMIFS('Data BoP'!$AK$6:$AK$86,'Data BoP'!$C$6:$C$86,$B96) -> -2257.5853
B97: 2011 | C97: =SUMIFS('Data BoP'!$AJ$6:$AJ$86,'Data BoP'!$C$6:$C$86,$B97) -> -6107.91 | D97: =C97/SUMIFS('Data BoP'!$AP$6:$AP$86,'Data BoP'!$C$6:$C$86,$B97) -> -0.01158744 | E97: =SUMIFS('Data BoP'!$E$6:$E$86,'Data BoP'!$C$6:$C$86,$B97) -> -5340.1812 | F97: =-(SUMIFS('Data BoP'!$U$6:$U$86,'Data BoP'!$C$6:$C$86,$B97)-C97) -> -855.70702 | G97: =SUMIFS('Data BoP'!$AK$6:$AK$86,'Data BoP'!$C$6:$C$86,$B97) -> 25.254371
B98: 2012 | C98: =SUMIFS('Data BoP'!$AJ$6:$AJ$86,'Data BoP'!$C$6:$C$86,$B98) -> -3304.72 | D98: =C98/SUMIFS('Data BoP'!$AP$6:$AP$86,'Data BoP'!$C$6:$C$86,$B98) -> -0.0057068291 | E98: =SUMIFS('Data BoP'!$E$6:$E$86,'Data BoP'!$C$6:$C$86,$B98) -> -2138.0404 | F98: =-(SUMIFS('Data BoP'!$U$6:$U$86,'Data BoP'!$C$6:$C$86,$B98)-C98) -> -516.58439 | G98: =SUMIFS('Data BoP'!$AK$6:$AK$86,'Data BoP'!$C$6:$C$86,$B98) -> -697.9793
B99: 2013 | C99: =SUMIFS('Data BoP'!$AJ$6:$AJ$86,'Data BoP'!$C$6:$C$86,$B99) -> -11823.76 | D99: =C99/SUMIFS('Data BoP'!$AP$6:$AP$86,'Data BoP'!$C$6:$C$86,$B99) -> -0.019346813 | E99: =SUMIFS('Data BoP'!$E$6:$E$86,'Data BoP'!$C$6:$C$86,$B99) -> -13124.374 | F99: =-(SUMIFS('Data BoP'!$U$6:$U$86,'Data BoP'!$C$6:$C$86,$B99)-C99) -> 4341.1365 | G99: =SUMIFS('Data BoP'!$AK$6:$AK$86,'Data BoP'!$C$6:$C$86,$B99) -> -3073.9356
B100: 2014 | C100: =SUMIFS('Data BoP'!$AJ$6:$AJ$86,'Data BoP'!$C$6:$C$86,$B100) -> 1195.11 | D100: =C100/SUMIFS('Data BoP'!$AP$6:$AP$86,'Data BoP'!$C$6:$C$86,$B100) -> 0.002123332 | E100: =SUMIFS('Data BoP'!$E$6:$E$86,'Data BoP'!$C$6:$C$86,$B100) -> -9179.0263 | F100: =-(SUMIFS('Data BoP'!$U$6:$U$86,'Data BoP'!$C$6:$C$86,$B100)-C100) -> 10515.782 | G100: =SUMIFS('Data BoP'!$AK$6:$AK$86,'Data BoP'!$C$6:$C$86,$B100) -> -198.44314
B101: 2015 | C101: =SUMIFS('Data BoP'!$AJ$6:$AJ$86,'Data BoP'!$C$6:$C$86,$B101) -> -4905.97 | D101: =C101/SUMIFS('Data BoP'!$AP$6:$AP$86,'Data BoP'!$C$6:$C$86,$B101) -> -0.0076409829 | E101: =SUMIFS('Data BoP'!$E$6:$E$86,'Data BoP'!$C$6:$C$86,$B101) -> -17621.985 | F101: =-(SUMIFS('Data BoP'!$U$6:$U$86,'Data BoP'!$C$6:$C$86,$B101)-C101) -> 13591.879 | G101: =SUMIFS('Data BoP'!$AK$6:$AK$86,'Data BoP'!$C$6:$C$86,$B101) -> -927.79325
B102: 2016 | C102: =SUMIFS('Data BoP'!$AJ$6:$AJ$86,'Data BoP'!$C$6:$C$86,$B102) -> 14311.235 | D102: =C102/SUMIFS('Data BoP'!$AP$6:$AP$86,'Data BoP'!$C$6:$C$86,$B102) -> 0.02570047 | E102: =SUMIFS('Data BoP'!$E$6:$E$86,'Data BoP'!$C$6:$C$86,$B102) -> -15104.787 | F102: =-(SUMIFS('Data BoP'!$U$6:$U$86,'Data BoP'!$C$6:$C$86,$B102)-C102) -> 28275.292 | G102: =SUMIFS('Data BoP'!$AK$6:$AK$86,'Data BoP'!$C$6:$C$86,$B102) -> 774.91576
B103: 2017 | C103: =SUMIFS('Data BoP'!$AJ$6:$AJ$86,'Data BoP'!$C$6:$C$86,$B103) -> 14555.706 | D103: =C103/SUMIFS('Data BoP'!$AP$6:$AP$86,'Data BoP'!$C$6:$C$86,$B103) -> 0.022623678 | E103: =SUMIFS('Data BoP'!$E$6:$E$86,'Data BoP'!$C$6:$C$86,$B103) -> -31151.352 | F103: =-(SUMIFS('Data BoP'!$U$6:$U$86,'Data BoP'!$C$6:$C$86,$B103)-C103) -> 45828.893 | G103: =SUMIFS('Data BoP'!$AK$6:$AK$86,'Data BoP'!$C$6:$C$86,$B103) -> -295.33165
... B111: 2025 | C111: =SUMIFS('Data BoP'!$AJ$6:$AJ$86,'Data BoP'!$C$6:$C$86,$B111) -> 7221.074 | D111: =C111/SUMIFS('Data BoP'!$AP$6:$AP$86,'Data BoP'!$C$6:$C$86,$B111) -> 0.01053433 | E111: =SUMIFS('Data BoP'!$E$6:$E$86,'Data BoP'!$C$6:$C$86,$B111) -> -7788.1256 | F111: =-(SUMIFS('Data BoP'!$U$6:$U$86,'Data BoP'!$C$6:$C$86,$B111)-C111) -> 19224.178 | G111: =SUMIFS('Data BoP'!$AK$6:$AK$86,'Data BoP'!$C$6:$C$86,$B111) -> -4669.1182
B113: Reserve assets here are transaction flows on the BPM6 definition. The BCRA's published gross reserve stock moves for other reasons too — valuation, the gold price, cross rates, and swap lines that are on the balance sheet but not freely usable. Reconciling this line to the headline stock needs BCRA's balance cambiario, which is not in this pack.
B114: Validated against INDEC's published annual figures: 2019 -21,375; 2023 -21,675; 2024 +6,093; 2025 +7,221.

Sheet Forecast
B2: Current account forecast — bull / base / bear, 2026 and 2027
B3: Built up from the components in millions of US dollars. Blue = judgement input. Black = formula. 'Bull' means a stronger external position, i.e. a better current account.
B4: 2025 and the first quarter of 2026 are actuals pulled from the Data tab. The scenario columns are full-year figures, so the 2026 columns already contain the realised Q1 — check the memo row at the bottom, which shows what the remaining three quarters have to deliver for each scenario to land.
B7: US$ mn | C7: 2025 actual | D7: 2026 Q1 actual | E7: 2026 Bull | F7: 2026 Base | G7: 2026 Bear | H7: 2027 Bull | I7: 2027 Base | J7: 2027 Bear
B8: Goods exports FOB | C8: =SUMIFS('Data BoP'!$H$6:$H$86,'Data BoP'!$C$6:$C$86,2025) -> 87151.683 | D8: ='Data BoP'!H86 -> 21916.049 | E8: 103000 | F8: 98000 | G8: 94500 | H8: 118000 | I8: 109000 | J8: 101000
B9: Goods imports FOB | C9: =SUMIFS('Data BoP'!$I$6:$I$86,'Data BoP'!$C$6:$C$86,2025) -> 71792.648 | D9: ='Data BoP'!I86 -> 15576.589 | E9: 76000 | F9: 79000 | G9: 81000 | H9: 84000 | I9: 89000 | J9: 89000
B10: Services credits | C10: =SUMIFS('Data BoP'!$K$6:$K$86,'Data BoP'!$C$6:$C$86,2025) -> 18340.857 | D10: ='Data BoP'!K86 -> 5208.8695 | E10: 21500 | F10: 21000 | G10: 20500 | H10: 23500 | I10: 22500 | J10: 21500
B11: Services debits | C11: =SUMIFS('Data BoP'!$L$6:$L$86,'Data BoP'!$C$6:$C$86,2025) -> 29941.795 | D11: ='Data BoP'!L86 -> 9236.9424 | E11: 32000 | F11: 34500 | G11: 35500 | H11: 33500 | I11: 36500 | J11: 38000
B12: Primary income | C12: =SUMIFS('Data BoP'!$M$6:$M$86,'Data BoP'!$C$6:$C$86,2025) -> -14078.683 | D12: ='Data BoP'!M86 -> -4675.8332 | E12: -15500 | F12: -17000 | G12: -18500 | H12: -16500 | I12: -18500 | J12: -20000
B13: Secondary income | C13: =SUMIFS('Data BoP'!$S$6:$S$86,'Data BoP'!$C$6:$C$86,2025) -> 2532.4599 | D13: ='Data BoP'!S86 -> 713.92067 | E13: 2900 | F13: 2800 | G13: 2700 | H13: 3000 | I13: 2900 | J13: 2800
B14: Goods balance | C14: =C8-C9 -> 15359.035 | D14: =D8-D9 -> 6339.4596 | E14: =E8-E9 -> 27000 | F14: =F8-F9 -> 19000 | G14: =G8-G9 -> 13500 | H14: =H8-H9 -> 34000 | I14: =I8-I9 -> 20000 | J14: =J8-J9 -> 12000
B15: Services balance | C15: =C10-C11 -> -11600.938 | D15: =D10-D11 -> -4028.0729 | E15: =E10-E11 -> -10500 | F15: =F10-F11 -> -13500 | G15: =G10-G11 -> -15000 | H15: =H10-H11 -> -10000 | I15: =I10-I11 -> -14000 | J15: =J10-J11 -> -16500
B16: CURRENT ACCOUNT | C16: =C14+C15+C12+C13 -> -7788.1256 | D16: =D14+D15+D12+D13 -> -1650.5258 | E16: =E14+E15+E12+E13 -> 3900 | F16: =F14+F15+F12+F13 -> -8700 | G16: =G14+G15+G12+G13 -> -17300 | H16: =H14+H15+H12+H13 -> 10500 | I16: =I14+I15+I12+I13 -> -9600 | J16: =J14+J15+J12+J13 -> -21700
B17: % of GDP | C17: =IF(C18=0,"",C16/(C18*1000)) -> -0.011361563 | D17: =IF(D18=0,"",D16/(D18*1000)) -> -0.0096138395 | E17: =IF(E18=0,"",E16/(E18*1000)) -> 0.0053424658 | F17: =IF(F18=0,"",F16/(F18*1000)) -> -0.012253521 | G17: =IF(G18=0,"",G16/(G18*1000)) -> -0.026015038 | H17: =IF(H18=0,"",H16/(H18*1000)) -> 0.013461538 | I17: =IF(I18=0,"",I16/(I18*1000)) -> -0.0128 | J17: =IF(J18=0,"",J16/(J18*1000)) -> -0.031449275
B18: Nominal GDP (USD bn) | C18: =SUMIFS('Data BoP'!$AP$6:$AP$86,'Data BoP'!$C$6:$C$86,2025)/1000 -> 685.48012 | D18: ='Data BoP'!AP86/1000 -> 171.68228 | E18: 730 | F18: 710 | G18: 665 | H18: 780 | I18: 750 | J18: 690
B20: Memo
B21: Implied Q2-Q4 2026 current account | E21: =E16-$D$16 -> 5550.5258 | F21: =F16-$D$16 -> -7049.4742 | G21: =G16-$D$16 -> -15649.474
B22: IMF projection (Apr-2026 WEO / Art. IV) | F22: -5435 | I22: -4070
B23: IMF World Economic Outlook of April 2026 and the 2026 Article IV / Second Review of the Extended Arrangement, which both carry a current account of -US$5.4bn for 2026 (-0.8% of GDP) and -US$4.1bn for 2027 (-0.6%). The BCRA REM does not survey the current account, so there is no market consensus line to show; the REM's June-2026 trade balance median of +US$23.6bn on a customs basis is the nearest thing, and it is not directly comparable with the BoP goods balance.
B26: Scenario assumptions
B27: Driver | C27: Bull (stronger external) | D27: Base | E27: Bear (weaker external)
B28: Energy and mining exports | C28: Vaca Muerta liquids and the pipeline build push net energy exports past US$12bn by 2027; Rio Tinto / lithium volumes add on top | D28: Net energy exports build steadily toward US$9-10bn by 2027 — the volume is real but infrastructure paces it | E28: Pipeline and export-terminal slippage caps energy at current levels; a soft global oil price does the rest
B29: Agriculture | C29: Two good harvests and no export-tax reversal; farmer selling stays current | D29: Normal harvest, no drought, retenciones broadly where they are | E29: A La Nina drought year — the 2018 and 2023 template, worth US$15-20bn of exports when it lands
B30: Imports | C30: Import growth lags activity as the real exchange rate normalises | D30: Imports grow roughly with domestic demand; no new restrictions and none needed | E30: A strong real exchange rate plus recovering activity pulls imports up faster than exports
B31: Services | C31: The tourism deficit narrows as the real exchange rate corrects; knowledge-based exports keep growing | D31: Tourism stays a large and persistent deficit — Argentines travelling out is the single biggest services line and it responds to a strong peso | E31: An overvalued peso keeps outbound tourism at record levels; the services deficit widens further
B32: Primary income | C32: Falling country risk cuts the interest bill; profit remittances stay modest | D32: Interest on the restructured stock plus IMF charges keeps primary income deeply negative; remittances resume gradually as FX access normalises | E32: Renewed profit and dividend remittance after years of pent-up stock, on top of the interest bill
B33: What would change my mind | C33: Monthly trade prints running above US$2.5bn with imports flat — that is the bull case showing up early | D33: The base sits close to the IMF on 2026 but is more cautious on 2027, because the import response to a recovering economy at a strong real exchange rate is the thing that historically closes these windows | E33: Watch the services line, not the goods line. Goods surpluses in Argentina have repeatedly been eaten by tourism and profit remittances rather than by imports
