Workbook

Sheet Read me
B2: Argentina — the fiscal balance, the interest bill and the debt burden
B3: Companion to the fiscal pack. Everything is live: change an input and every path moves.
B5: READ THIS FIRST
B6: The debt stock is the weak input | C6: Argentina's official sources disagree about WHAT to count. Gross Administracion Central debt, that same figure net of intra-public-sector holdings, and a measure including BCRA remunerated liabilities differ by more than twenty points of GDP. The stock series here is gross Administracion Central. Two anchors are solid — USD 466,921mn at Dec-2024 and USD 455,067mn at Dec-2025, both from the Secretaria de Finanzas monthly bulletin — and Dec-2019 at USD 323,177mn comes from the BCRA. The earlier years are indicative and you should overwrite them from the Secretaria de Finanzas series or Bloomberg.
B7: So is the exchange rate | C7: Debt is converted at the end-of-period Com. "A" 3500 rate, which is the official convention. Those cells are blue inputs. End-2025 in particular should be checked.
B8: What is NOT uncertain | C8: The primary balance, the interest bill and nominal GDP all come from the fiscal pack and reconcile to Hacienda and INDEC to the peso. The debt DYNAMICS engine — the decomposition and the stabilising primary balance — is arithmetic, not estimation.
B10: What's here
B11: Data | C11: Annual fiscal aggregates, GDP, FX and the debt stock. Blue = input you can overwrite.
B12: Dynamics | C12: The change in debt/GDP each year decomposed into what caused it: the primary balance, the interest bill, real growth, inflation eroding the domestic-currency stock, exchange-rate revaluation of the FX-denominated stock, and a residual. The residual is the honest measure of what the identity does not explain — below-the-line operations, valuation effects, and any mismatch in the debt measure.
B13: Stabilising PB | C13: The core question. For any combination of interest cost, growth, inflation and depreciation, the primary balance that holds debt/GDP flat — and how far today's actual balance sits from it.
B14: Scenarios | C14: A five-year projection with six editable assumptions. Includes the threshold test: at what primary balance does debt start rising, and what shock makes it accelerate.
B16: The identity | C16: d(t) - d(t-1) = [ (i - pi - g - alpha*eps*(1+pi)) / ((1+g)(1+pi)) ] * d(t-1) - pb + residual, where d is debt/GDP, i the effective nominal interest rate, pi the GDP deflator, g real growth, alpha the FX-denominated share and eps nominal depreciation. Everything is expressed in domestic currency, which is why depreciation raises the ratio.
B17: Interest is CASH | C17: The interest line is cash paid, as reported in base caja. Capitalising instruments accrue interest that does not appear until paid, so the EFFECTIVE interest rate computed here understates the accrual cost. This matters: it flatters the stabilising primary balance.

Sheet Data
B2: Annual inputs
B3: Blue = input. Green = linked from the fiscal pack construction. Black = formula.
B7: Year | C7: Nominal GDP (mn pesos) | D7: Primary balance (mn pesos) | E7: Interest paid (mn pesos) | F7: Overall balance (mn pesos) | G7: FX eop (Com. A3500) | H7: Gross debt (USD mn) | I7: Source of debt figure | J7: Debt (mn pesos) | K7: Debt / GDP | L7: EMAE avg (real proxy) | M7: CPI avg | N7: FX share of debt | O7: FX average (period avg) | P7: GDP (USD mn) | Q7: Debt / GDP (both in USD)
B8: 2016 | C8: 8228159.6 | D8: -343524 | E8: 131259 | F8: -474785 | G8: 15.85 | H8: 275446 | I8: indicative — verify | J8: =G8*H8 -> 4365819.1 | K8: =J8/C8 -> 0.53059485 | L8: 147.37062 | M8: 90.529476 | N8: 0.7 | O8: 14.78 | P8: =C8/O8 -> 556709.04 | Q8: =H8/P8 -> 0.49477551
B9: 2017 | C9: 10660228 | D9: -404143 | E9: 224908 | F9: -629050 | G9: 18.65 | H9: 320935 | I9: indicative — verify | J9: =G9*H9 -> 5985437.8 | K9: =J9/C9 -> 0.56147368 | L9: 151.47296 | M9: 112.88711 | N9: 0.7 | O9: 16.58 | P9: =C9/O9 -> 642957.09 | Q9: =H9/P9 -> 0.49915462
B10: 2018 | C10: 14744811 | D10: -338987 | E10: 388940 | F10: -727927 | G10: 37.7 | H10: 332192 | I10: indicative — verify | J10: =G10*H10 -> 12523638 | K10: =J10/C10 -> 0.84935905 | L10: 148.12287 | M10: 151.58167 | N10: 0.7 | O10: 28.11 | P10: =C10/O10 -> 524539.69 | Q10: =H10/P10 -> 0.63330193
B11: 2019 | C11: 21558444 | D11: -95120 | E11: 724285 | F11: -819406 | G11: 59.89 | H11: 323177 | I11: BCRA IPOM | J11: =G11*H11 -> 19355071 | K11: =J11/C11 -> 0.89779533 | L11: 145.52888 | M11: 232.74342 | N11: 0.7 | O11: 48.24 | P11: =C11/O11 -> 446899.75 | Q11: =H11/P11 -> 0.72315323
B12: 2020 | C12: 27209814 | D12: -1749958 | E12: 542875 | F12: -2292829 | G12: 84.15 | H12: 335473 | I12: indicative — verify | J12: =G12*H12 -> 28230053 | K12: =J12/C12 -> 1.0374953 | L12: 129.50722 | M12: 330.54168 | N12: 0.45 | O12: 70.58 | P12: =C12/O12 -> 385517.34 | Q12: =H12/P12 -> 0.87018912
B13: 2021 | C13: 46219084 | D13: -980240 | E13: 684241 | F13: -1664482 | G13: 102.72 | H13: 360664 | I13: indicative — verify | J13: =G13*H13 -> 37047406 | K13: =J13/C13 -> 0.80156081 | L13: 143.20515 | M13: 490.55486 | N13: 0.45 | O13: 95.1 | P13: =C13/O13 -> 486005.08 | Q13: =H13/P13 -> 0.74209923
B14: 2022 | C14: 82810045 | D14: -1659747 | E14: 1493010 | F14: -3152757 | G14: 177.16 | H14: 394593 | I14: indicative — verify | J14: =G14*H14 -> 69906096 | K14: =J14/C14 -> 0.8441741 | L14: 150.64691 | M14: 845.86746 | N14: 0.45 | O14: 130.68 | P14: =C14/O14 -> 633685.69 | Q14: =H14/P14 -> 0.62269514
B15: 2023 | C15: 1.9394618e+08 | D15: -5164636 | E15: 3253831 | F15: -8418468 | G15: 808.45 | H15: 370674 | I15: widely reported | J15: =G15*H15 -> 2.996714e+08 | K15: =J15/C15 -> 1.5451266 | L15: 148.84942 | M15: 1975.0069 | N15: 0.45 | O15: 296.3 | P15: =C15/O15 -> 654560.17 | Q15: =H15/P15 -> 0.56629477
B16: 2024 | C16: 5.8437701e+08 | D16: 10405811 | E16: 8641024 | F16: 1764786 | G16: 1032.5 | H16: 466921 | I16: Sec. Finanzas bulletin | J16: =G16*H16 -> 4.8209593e+08 | K16: =J16/C16 -> 0.82497416 | L16: 146.29155 | M16: 6317.7399 | N16: 0.45 | O16: 916.9 | P16: =C16/O16 -> 637339.96 | Q16: =H16/P16 -> 0.73260901
B17: 2025 | C17: 8.502398e+08 | D17: 11769217 | E17: 10315401 | F17: 1453819 | G17: 1420 | H17: 455067 | I17: Sec. Finanzas bulletin | J17: =G17*H17 -> 646195140 | K17: =J17/C17 -> 0.76001516 | L17: 151.87093 | M17: 8966.1665 | N17: 0.45 | O17: 1247.6 | P17: =C17/O17 -> 681500.32 | Q17: =H17/P17 -> 0.6677429
B19: The FX share is the portion of the debt stock denominated in or linked to foreign currency. It drives how much a devaluation raises the ratio. Roughly 45% since the 2020 restructuring; set it precisely from the Secretaria de Finanzas currency breakdown.
B20: Rows shown in red in the source column are indicative levels, not verified prints. Overwrite column H before using the level (as opposed to the dynamics) in a note.

Sheet Dynamics
B2: What moved the debt ratio each year
B3: Percentage points of GDP. A positive contribution pushed the ratio UP.
B7: Year | C7: Debt/GDP (end) | D7: Change (pp) | E7: Effective interest rate i | F7: Real growth g | G7: GDP deflator pi | H7: Depreciation eps | I7: Primary balance | J7: (a) Interest cost | K7: (b) Real growth | L7: (c) Inflation erosion | M7: (d) FX revaluation | N7: (e) Primary balance | O7: Explained (a..e) | P7: Residual (SFA)
B8: 2016 | C8: =Data!K8 -> 0.53059485
B9: 2017 | C9: =Data!K9 -> 0.56147368 | D9: =(C9-C8)*100 -> 3.0878831 | E9: =Data!E9/Data!J8 -> 0.051515648 | F9: =Data!L9/Data!L8-1 -> 0.027836907 | G9: =(Data!C9/Data!C8)/(Data!L9/Data!L8)-1 -> 0.26049057 | H9: =Data!G9/Data!G8-1 -> 0.17665615 | I9: =Data!D9/Data!C9 -> -0.037911289 | J9: =E9*C8/((1+F9)*(1+G9))*100 -> 2.1097859 | K9: =-F9*C8/((1+F9)*(1+G9))*100 -> -1.1400403 | L9: =-G9*C8/((1+F9)*(1+G9))*100 -> -10.668202 | M9: =Data!N9*H9*(1+G9)*C8/((1+F9)*(1+G9))*100 -> 6.3835994 | N9: =-I9*100 -> 3.7911289 | O9: =SUM(J9:N9) -> 0.476272 | P9: =D9-O9 -> 2.6116111
B10: 2018 | C10: =Data!K10 -> 0.84935905 | D10: =(C10-C9)*100 -> 28.788537 | E10: =Data!E10/Data!J9 -> 0.064981045 | F10: =Data!L10/Data!L9-1 -> -0.022116753 | G10: =(Data!C10/Data!C9)/(Data!L10/Data!L9)-1 -> 0.41444375 | H10: =Data!G10/Data!G9-1 -> 1.0214477 | I10: =Data!D10/Data!C10 -> -0.022990258 | J10: =E10*C9/((1+F10)*(1+G10))*100 -> 2.6378094 | K10: =-F10*C9/((1+F10)*(1+G10))*100 -> 0.89779688 | L10: =-G10*C9/((1+F10)*(1+G10))*100 -> -16.823731 | M10: =Data!N10*H10*(1+G10)*C9/((1+F10)*(1+G10))*100 -> 41.054104 | N10: =-I10*100 -> 2.2990258 | O10: =SUM(J10:N10) -> 30.065006 | P10: =D10-O10 -> -1.2764688
B11: 2019 | C11: =Data!K11 -> 0.89779533 | D11: =(C11-C10)*100 -> 4.8436282 | E11: =Data!E11/Data!J10 -> 0.057833433 | F11: =Data!L11/Data!L10-1 -> -0.017512443 | G11: =(Data!C11/Data!C10)/(Data!L11/Data!L10)-1 -> 0.48816524 | H11: =Data!G11/Data!G10-1 -> 0.58859416 | I11: =Data!D11/Data!C11 -> -0.0044121922 | J11: =E11*C10/((1+F11)*(1+G11))*100 -> 3.3596348 | K11: =-F11*C10/((1+F11)*(1+G11))*100 -> 1.0173253 | L11: =-G11*C10/((1+F11)*(1+G11))*100 -> -28.358285 | M11: =Data!N11*H11*(1+G11)*C10/((1+F11)*(1+G11))*100 -> 35.618715 | N11: =-I11*100 -> 0.44121922 | O11: =SUM(J11:N11) -> 12.07861 | P11: =D11-O11 -> -7.2349821
B12: 2020 | C12: =Data!K12 -> 1.0374953 | D12: =(C12-C11)*100 -> 13.969992 | E12: =Data!E12/Data!J11 -> 0.028048206 | F12: =Data!L12/Data!L11-1 -> -0.11009262 | G12: =(Data!C12/Data!C11)/(Data!L12/Data!L11)-1 -> 0.41828449 | H12: =Data!G12/Data!G11-1 -> 0.40507597 | I12: =Data!D12/Data!C12 -> -0.064313486 | J12: =E12*C11/((1+F12)*(1+G12))*100 -> 1.9951441 | K12: =-F12*C11/((1+F12)*(1+G12))*100 -> 7.8311834 | L12: =-G12*C11/((1+F12)*(1+G12))*100 -> -29.753697 | M12: =Data!N12*H12*(1+G12)*C11/((1+F12)*(1+G12))*100 -> 18.389992 | N12: =-I12*100 -> 6.4313486 | O12: =SUM(J12:N12) -> 4.8939705 | P12: =D12-O12 -> 9.0760214
B13: 2021 | C13: =Data!K13 -> 0.80156081 | D13: =(C13-C12)*100 -> -23.593444 | E13: =Data!E13/Data!J12 -> 0.024238035 | F13: =Data!L13/Data!L12-1 -> 0.10576955 | G13: =(Data!C13/Data!C12)/(Data!L13/Data!L12)-1 -> 0.53614116 | H13: =Data!G13/Data!G12-1 -> 0.22067736 | I13: =Data!D13/Data!C13 -> -0.021208556 | J13: =E13*C12/((1+F13)*(1+G13))*100 -> 1.4804296 | K13: =-F13*C12/((1+F13)*(1+G13))*100 -> -6.4602755 | L13: =-G13*C12/((1+F13)*(1+G13))*100 -> -32.746849 | M13: =Data!N13*H13*(1+G13)*C12/((1+F13)*(1+G13))*100 -> 9.3173366 | N13: =-I13*100 -> 2.1208556 | O13: =SUM(J13:N13) -> -26.288502 | P13: =D13-O13 -> 2.6950584
B14: 2022 | C14: =Data!K14 -> 0.8441741 | D14: =(C14-C13)*100 -> 4.2613292 | E14: =Data!E14/Data!J13 -> 0.040299987 | F14: =Data!L14/Data!L13-1 -> 0.051965767 | G14: =(Data!C14/Data!C13)/(Data!L14/Data!L13)-1 -> 0.70317819 | H14: =Data!G14/Data!G13-1 -> 0.72468847 | I14: =Data!D14/Data!C14 -> -0.020042822 | J14: =E14*C13/((1+F14)*(1+G14))*100 -> 1.8029334 | K14: =-F14*C13/((1+F14)*(1+G14))*100 -> -2.3248349 | L14: =-G14*C13/((1+F14)*(1+G14))*100 -> -31.458657 | M14: =Data!N14*H14*(1+G14)*C13/((1+F14)*(1+G14))*100 -> 24.848418 | N14: =-I14*100 -> 2.0042822 | O14: =SUM(J14:N14) -> -5.1278584 | P14: =D14-O14 -> 9.3891875
B15: 2023 | C15: =Data!K15 -> 1.5451266 | D15: =(C15-C14)*100 -> 70.095247 | E15: =Data!E15/Data!J14 -> 0.046545741 | F15: =Data!L15/Data!L14-1 -> -0.01193181 | G15: =(Data!C15/Data!C14)/(Data!L15/Data!L14)-1 -> 1.3703435 | H15: =Data!G15/Data!G14-1 -> 3.563389 | I15: =Data!D15/Data!C15 -> -0.026629223 | J15: =E15*C14/((1+F15)*(1+G15))*100 -> 1.6776979 | K15: =-F15*C14/((1+F15)*(1+G15))*100 -> 0.43007098 | L15: =-G15*C14/((1+F15)*(1+G15))*100 -> -49.392757 | M15: =Data!N15*H15*(1+G15)*C14/((1+F15)*(1+G15))*100 -> 137.00009 | N15: =-I15*100 -> 2.6629223 | O15: =SUM(J15:N15) -> 92.378027 | P15: =D15-O15 -> -22.282779
B16: 2024 | C16: =Data!K16 -> 0.82497416 | D16: =(C16-C15)*100 -> -72.015242 | E16: =Data!E16/Data!J15 -> 0.028834998 | F16: =Data!L16/Data!L15-1 -> -0.017184298 | G16: =(Data!C16/Data!C15)/(Data!L16/Data!L15)-1 -> 2.0657717 | H16: =Data!G16/Data!G15-1 -> 0.27713526 | I16: =Data!D16/Data!C16 -> 0.017806674 | J16: =E16*C15/((1+F16)*(1+G16))*100 -> 1.4786728 | K16: =-F16*C15/((1+F16)*(1+G16))*100 -> 0.88121921 | L16: =-G16*C15/((1+F16)*(1+G16))*100 -> -105.93378 | M16: =Data!N16*H16*(1+G16)*C15/((1+F16)*(1+G16))*100 -> 19.606328 | N16: =-I16*100 -> -1.7806674 | O16: =SUM(J16:N16) -> -85.748232 | P16: =D16-O16 -> 13.73299
B17: 2025 | C17: =Data!K17 -> 0.76001516 | D17: =(C17-C16)*100 -> -6.4958993 | E17: =Data!E17/Data!J16 -> 0.021396988 | F17: =Data!L17/Data!L16-1 -> 0.038138792 | G17: =(Data!C17/Data!C16)/(Data!L17/Data!L16)-1 -> 0.40149931 | H17: =Data!G17/Data!G16-1 -> 0.37530266 | I17: =Data!D17/Data!C17 -> 0.013842233 | J17: =E17*C16/((1+F17)*(1+G17))*100 -> 1.2132343 | K17: =-F17*C16/((1+F17)*(1+G17))*100 -> -2.1625142 | L17: =-G17*C16/((1+F17)*(1+G17))*100 -> -22.765481 | M17: =Data!N17*H17*(1+G17)*C16/((1+F17)*(1+G17))*100 -> 13.420821 | N17: =-I17*100 -> -1.3842233 | O17: =SUM(J17:N17) -> -11.678163 | P17: =D17-O17 -> 5.1822641
B19: The effective interest rate is cash interest paid over the previous year's debt stock. Because base caja excludes accrued-but-unpaid interest on capitalising instruments, this understates the true cost of carry.
B20: A large residual means the identity is not capturing the debt move: below-the-line operations, valuation changes, debt assumed or restructured, or a mismatch between the debt measure and the fiscal coverage. In Argentina it is routinely large. Do not hide it.

Sheet Stabilising PB
B2: The primary balance that holds debt/GDP flat
B3: Argentine debt is multi-currency. A single-currency (i - pi - g) formula is wrong here: inflation erodes plain peso debt, but NOT the FX-denominated stock and NOT the CER-indexed stock.
B4: Debt stock grows in pesos at: alpha x (eps + i$) + beta x (pi + iCER) + gamma x iPeso
B5: Nominal GDP grows at: (1+g)(1+pi). Debt/GDP is flat when the primary balance covers the gap.
B7: Inputs
B8: Debt / GDP, d | E8: =Data!K17 -> 0.76001516
B9: FX-denominated share, alpha | E9: 0.45
B10: CER-indexed share, beta | E10: 0.35
B11: Plain peso share, gamma | E11: =1-E9-E10 -> 0.2
B12: Interest on FX debt, i$ | E12: 0.05
B13: Interest on CER debt, iCER | E13: 0.05
B14: Interest on peso debt, iPeso | E14: 0.3
B15: Nominal depreciation, eps | E15: 0.25
B16: GDP deflator, pi | E16: 0.25
B17: Real growth, g | E17: 0.03
B18: Actual primary balance | E18: =Data!D17/Data!C17 -> 0.013842233
B20: Result
B21: Debt stock nominal growth | E21: =($E$9*($E$15+$E$12)+$E$10*($E$16+$E$13)+$E$11*$E$14) -> 0.3
B22: Nominal GDP growth | E22: =(1+$E$17)*(1+$E$16)-1 -> 0.2875
B23: DEBT-STABILISING PRIMARY BALANCE | E23: =$E$8*((1+($E$9*($E$15+$E$12)+$E$10*($E$16+$E$13)+$E$11*$E$14))/((1+$E$17)*(1+$E$16))-1) -> 0.007378788
B24: Actual primary balance | E24: =$E$18 -> 0.013842233
B25: GAP — actual less required (pp of GDP) | E25: =(E24-E23)*100 -> 0.64634445
B26: Implied change in debt/GDP (pp) | E26: =-(E24-E23)*100 -> -0.64634445
B28: A POSITIVE gap means the actual primary surplus more than covers the carry and debt/GDP falls. Negative means debt rises even with a primary surplus.
B31: The threshold table: required primary balance (% of GDP) by depreciation and real growth
B32: Everything else held at the inputs above. This is the answer to 'what makes it shoot up'.
B34: eps \ g | C34: -0.03 | D34: 0 | E34: 0.02 | F34: 0.04 | G34: 0.06
B35: 0 | C35: =$E$8*((1+($E$9*($B35+$E$12)+$E$10*($E$16+$E$13)+$E$11*$E$14))/((1+C$34)*(1+$E$16))-1) -> -0.015670416 | D35: =$E$8*((1+($E$9*($B35+$E$12)+$E$10*($E$16+$E$13)+$E$11*$E$14))/((1+D$34)*(1+$E$16))-1) -> -0.038000758 | E35: =$E$8*((1+($E$9*($B35+$E$12)+$E$10*($E$16+$E$13)+$E$11*$E$14))/((1+E$34)*(1+$E$16))-1) -> -0.052157903 | F35: =$E$8*((1+($E$9*($B35+$E$12)+$E$10*($E$16+$E$13)+$E$11*$E$14))/((1+F$34)*(1+$E$16))-1) -> -0.065770543 | G35: =$E$8*((1+($E$9*($B35+$E$12)+$E$10*($E$16+$E$13)+$E$11*$E$14))/((1+G$34)*(1+$E$16))-1) -> -0.078869498
B36: 0.15 | C36: =$E$8*((1+($E$9*($B36+$E$12)+$E$10*($E$16+$E$13)+$E$11*$E$14))/((1+C$34)*(1+$E$16))-1) -> 0.026639707 | D36: =$E$8*((1+($E$9*($B36+$E$12)+$E$10*($E$16+$E$13)+$E$11*$E$14))/((1+D$34)*(1+$E$16))-1) -> 0.0030400607 | E36: =$E$8*((1+($E$9*($B36+$E$12)+$E$10*($E$16+$E$13)+$E$11*$E$14))/((1+E$34)*(1+$E$16))-1) -> -0.011921806 | F36: =$E$8*((1+($E$9*($B36+$E$12)+$E$10*($E$16+$E$13)+$E$11*$E$14))/((1+F$34)*(1+$E$16))-1) -> -0.026308217 | G36: =$E$8*((1+($E$9*($B36+$E$12)+$E$10*($E$16+$E$13)+$E$11*$E$14))/((1+G$34)*(1+$E$16))-1) -> -0.040151745
B37: 0.25 | C37: =$E$8*((1+($E$9*($B37+$E$12)+$E$10*($E$16+$E$13)+$E$11*$E$14))/((1+C$34)*(1+$E$16))-1) -> 0.054846455 | D37: =$E$8*((1+($E$9*($B37+$E$12)+$E$10*($E$16+$E$13)+$E$11*$E$14))/((1+D$34)*(1+$E$16))-1) -> 0.030400607 | E37: =$E$8*((1+($E$9*($B37+$E$12)+$E$10*($E$16+$E$13)+$E$11*$E$14))/((1+E$34)*(1+$E$16))-1) -> 0.014902258 | F37: =$E$8*((1+($E$9*($B37+$E$12)+$E$10*($E$16+$E$13)+$E$11*$E$14))/((1+F$34)*(1+$E$16))-1) -> 0 | G37: =$E$8*((1+($E$9*($B37+$E$12)+$E$10*($E$16+$E$13)+$E$11*$E$14))/((1+G$34)*(1+$E$16))-1) -> -0.014339909
B38: 0.4 | C38: =$E$8*((1+($E$9*($B38+$E$12)+$E$10*($E$16+$E$13)+$E$11*$E$14))/((1+C$34)*(1+$E$16))-1) -> 0.097156578 | D38: =$E$8*((1+($E$9*($B38+$E$12)+$E$10*($E$16+$E$13)+$E$11*$E$14))/((1+D$34)*(1+$E$16))-1) -> 0.071441425 | E38: =$E$8*((1+($E$9*($B38+$E$12)+$E$10*($E$16+$E$13)+$E$11*$E$14))/((1+E$34)*(1+$E$16))-1) -> 0.055138355 | F38: =$E$8*((1+($E$9*($B38+$E$12)+$E$10*($E$16+$E$13)+$E$11*$E$14))/((1+F$34)*(1+$E$16))-1) -> 0.039462326 | G38: =$E$8*((1+($E$9*($B38+$E$12)+$E$10*($E$16+$E$13)+$E$11*$E$14))/((1+G$34)*(1+$E$16))-1) -> 0.024377845
B39: 0.6 | C39: =$E$8*((1+($E$9*($B39+$E$12)+$E$10*($E$16+$E$13)+$E$11*$E$14))/((1+C$34)*(1+$E$16))-1) -> 0.15357007 | D39: =$E$8*((1+($E$9*($B39+$E$12)+$E$10*($E$16+$E$13)+$E$11*$E$14))/((1+D$34)*(1+$E$16))-1) -> 0.12616252 | E39: =$E$8*((1+($E$9*($B39+$E$12)+$E$10*($E$16+$E$13)+$E$11*$E$14))/((1+E$34)*(1+$E$16))-1) -> 0.10878648 | F39: =$E$8*((1+($E$9*($B39+$E$12)+$E$10*($E$16+$E$13)+$E$11*$E$14))/((1+F$34)*(1+$E$16))-1) -> 0.09207876 | G39: =$E$8*((1+($E$9*($B39+$E$12)+$E$10*($E$16+$E$13)+$E$11*$E$14))/((1+G$34)*(1+$E$16))-1) -> 0.076001516
B40: 0.8 | C40: =$E$8*((1+($E$9*($B40+$E$12)+$E$10*($E$16+$E$13)+$E$11*$E$14))/((1+C$34)*(1+$E$16))-1) -> 0.20998357 | D40: =$E$8*((1+($E$9*($B40+$E$12)+$E$10*($E$16+$E$13)+$E$11*$E$14))/((1+D$34)*(1+$E$16))-1) -> 0.18088361 | E40: =$E$8*((1+($E$9*($B40+$E$12)+$E$10*($E$16+$E$13)+$E$11*$E$14))/((1+E$34)*(1+$E$16))-1) -> 0.16243461 | F40: =$E$8*((1+($E$9*($B40+$E$12)+$E$10*($E$16+$E$13)+$E$11*$E$14))/((1+F$34)*(1+$E$16))-1) -> 0.14469519 | G40: =$E$8*((1+($E$9*($B40+$E$12)+$E$10*($E$16+$E$13)+$E$11*$E$14))/((1+G$34)*(1+$E$16))-1) -> 0.12762519
B42: Compare every cell against the actual primary balance in E24. Anything above it is a combination where the current fiscal stance is not enough and the ratio rises.
B43: Note how flat the table is across growth and how steep it is across depreciation. Growth helps at the margin; the exchange rate dominates. With 45% of the stock in foreign currency, roughly 0.45pp of extra primary surplus is needed for every 1pp of real depreciation.

Sheet Scenarios
B2: Seven-year debt path
B3: Same multi-currency engine. Change any yellow input and the path moves.
B5: FX-denominated share, alpha | E5: 0.45
B6: CER-indexed share, beta | E6: 0.35
B7: Interest on FX debt, i$ | E7: 0.05
B8: Interest on CER debt, iCER | E8: 0.05
B9: Interest on peso debt, iPeso | E9: 0.3
B10: Nominal depreciation, eps | E10: 0.25
B11: GDP deflator, pi | E11: 0.25
B12: Real growth, g | E12: 0.03
B13: Primary balance, pb | E13: 0.015
B14: Plain peso share, gamma | E14: =1-E5-E6 -> 0.2
B15: Starting debt / GDP | E15: =Data!K17 -> 0.76001516
B18: Year | C18: Debt / GDP | D18: Change (pp) | E18: Carry (pp) | F18: Primary balance (pp)
B19: =2025 -> 2025 | C19: =$E$15 -> 0.76001516
B20: =B19+1 -> 2026 | C20: =C19+D20/100 -> 0.75239395 | D20: =E20+F20 -> -0.7621212 | E20: =C19*((1+($E$5*($E$10+$E$7)+$E$6*($E$11+$E$8)+$E$14*$E$9))/((1+$E$12)*(1+$E$11))-1)*100 -> 0.7378788 | F20: =-$E$13*100 -> -1.5
B21: =B20+1 -> 2027 | C21: =C20+D21/100 -> 0.74469875 | D21: =E21+F21 -> -0.76952043 | E21: =C20*((1+($E$5*($E$10+$E$7)+$E$6*($E$11+$E$8)+$E$14*$E$9))/((1+$E$12)*(1+$E$11))-1)*100 -> 0.73047957 | F21: =-$E$13*100 -> -1.5
B22: =B21+1 -> 2028 | C22: =C21+D22/100 -> 0.73692883 | D22: =E22+F22 -> -0.77699151 | E22: =C21*((1+($E$5*($E$10+$E$7)+$E$6*($E$11+$E$8)+$E$14*$E$9))/((1+$E$12)*(1+$E$11))-1)*100 -> 0.72300849 | F22: =-$E$13*100 -> -1.5
B23: =B22+1 -> 2029 | C23: =C22+D23/100 -> 0.72908348 | D23: =E23+F23 -> -0.78453511 | E23: =C22*((1+($E$5*($E$10+$E$7)+$E$6*($E$11+$E$8)+$E$14*$E$9))/((1+$E$12)*(1+$E$11))-1)*100 -> 0.71546489 | F23: =-$E$13*100 -> -1.5
B24: =B23+1 -> 2030 | C24: =C23+D24/100 -> 0.72116196 | D24: =E24+F24 -> -0.79215196 | E24: =C23*((1+($E$5*($E$10+$E$7)+$E$6*($E$11+$E$8)+$E$14*$E$9))/((1+$E$12)*(1+$E$11))-1)*100 -> 0.70784804 | F24: =-$E$13*100 -> -1.5
B25: =B24+1 -> 2031 | C25: =C24+D25/100 -> 0.71316353 | D25: =E25+F25 -> -0.79984276 | E25: =C24*((1+($E$5*($E$10+$E$7)+$E$6*($E$11+$E$8)+$E$14*$E$9))/((1+$E$12)*(1+$E$11))-1)*100 -> 0.70015724 | F25: =-$E$13*100 -> -1.5
B26: =B25+1 -> 2032 | C26: =C25+D26/100 -> 0.70508745 | D26: =E26+F26 -> -0.80760822 | E26: =C25*((1+($E$5*($E$10+$E$7)+$E$6*($E$11+$E$8)+$E$14*$E$9))/((1+$E$12)*(1+$E$11))-1)*100 -> 0.69239178 | F26: =-$E$13*100 -> -1.5
B28: Defaults are a plausible steady state, not a forecast: a stable real exchange rate (25% depreciation against a 25% deflator), 3% real growth and a 1.5% primary surplus.
B29: Set depreciation to 60% and watch what happens. That is the Argentine debt problem in one line: solvency is an exchange-rate question at least as much as a fiscal one, and no plausible primary surplus offsets a large real devaluation in the year it lands.

Sheet Charts
B2: Charts
