Workbook

Sheet Read me
B2: Argentina inflation — INDEC IPC seasonality pack
B3: Data through 2026-06. Built automatically from INDEC national CPI.
B5: What's in here
B6: Data | C6: Every INDEC national CPI series used here, as index levels (blue = hardcoded from source) with month-on-month, year-on-year, 3m annualised and year-to-date calculated by formula.
B7: Seasonality Headline | C7: The chart you asked for: x-axis Jan-Dec, one line per year 2019 onwards, values = monthly headline m/m.
B8: Seasonality Core | C8: Same, for IPC Núcleo (core).
B9: Heatmap | C9: Year x month grid, colour-scaled — the fastest way to see which months run hot in a given regime.
B10: Momentum | C10: 3-month annualised vs year-on-year, headline and core. Shows turning points ~9 months before the y/y does.
B11: Components | C11: Núcleo vs Regulados vs Estacionales — where the 2026 pressure actually sits.
B12: Seasonal Factors | C12: Each month's m/m divided by that year's average month. Scale-free, so 2023 (211%) and 2025 (31%) are comparable. 1.20x = that month runs 20% hotter than a typical month of the same year.
B13: Forecast | C13: Bull / base / bear monthly paths to Dec-2027 with the FX and tariff assumptions behind each, benchmarked to the BCRA REM.
B15: Source | C15: INDEC, Índice de precios al consumidor nacional (base dic-2016 = 100), retrieved from the official series API at apis.datos.gob.ar (series 148.3_INIVELNAL_DICI_M_26, 148.3_INUCLEONAL_DICI_M_19, 148.3_IREGULANAL_DICI_M_22, 148.3_IESTACINAL_DICI_M_25).
B16: Validation | C16: Compounded monthly rates reproduce INDEC's published Dec/Dec prints exactly: 2019 53.8%, 2020 36.1%, 2021 50.9%, 2022 94.8%, 2023 211.4%, 2024 117.8%, 2025 31.5%. June-2026 y/y 33.5% and YTD 16.8% also match the official release.
B18: How to update
B19: Option 1 — automatic | C19: A scheduled task re-runs this build every month on the 16th (INDEC publishes around the 13th-15th) and sends you the refreshed workbook. Nothing to do.
B20: Option 2 — by hand | C20: On the Data tab, find the first empty yellow row and paste the new index levels into columns E-H. Every m/m, y/y, matrix and heatmap cell updates by formula. Chart series ranges cover the full calendar year, so a part-year line will read zero for months you have not filled — the automatic rebuild handles that for you.
B21: Caution | C21: INDEC occasionally revises the seasonal and regulated sub-indices. The automatic rebuild re-pulls the whole history each month, so revisions flow through; a manual paste-in does not restate history.

Sheet Data
B2: INDEC IPC nacional — index levels and derived rates
B3: Blue = hardcoded index level from INDEC. Black = formula. Paste new prints into the yellow rows.
B5: Month | C5: Year | D5: M# | E5: Nivel General (index) | F5: Núcleo (index) | G5: Regulados (index) | H5: Estacionales (index) | I5: m/m Nivel Gen. | J5: m/m Núcleo | K5: m/m Regulados | L5: m/m Estacion. | M5: y/y Nivel Gen. | N5: y/y Núcleo | O5: 3m ann. Nivel Gen. | P5: 3m ann. Núcleo | Q5: YTD Nivel Gen.
B6: 2018-12 | C6: 2018 | D6: 12 | E6: 184.2552 | F6: 178.9326
B7: 2019-01 | C7: 2019 | D7: 1 | E7: 189.6101 | F7: 184.3056 | I7: =IF(OR(E7="",E6=""),"",E7/E6-1) -> 0.029062409 | J7: =IF(OR(F7="",F6=""),"",F7/F6-1) -> 0.030028066 | K7: =IF(OR(G7="",G6=""),"",G7/G6-1) | L7: =IF(OR(H7="",H6=""),"",H7/H6-1) | Q7: =IF(E7="","",IFERROR(E7/INDEX($E:$E,MATCH(C7-1&"-12",$B:$B,0))-1,"")) -> 0.029062409
B8: 2019-02 | C8: 2019 | D8: 2 | E8: 196.7501 | F8: 191.4115 | I8: =IF(OR(E8="",E7=""),"",E8/E7-1) -> 0.037656222 | J8: =IF(OR(F8="",F7=""),"",F8/F7-1) -> 0.038554987 | K8: =IF(OR(G8="",G7=""),"",G8/G7-1) | L8: =IF(OR(H8="",H7=""),"",H8/H7-1) | Q8: =IF(E8="","",IFERROR(E8/INDEX($E:$E,MATCH(C8-1&"-12",$B:$B,0))-1,"")) -> 0.067813012
B9: 2019-03 | C9: 2019 | D9: 3 | E9: 205.9571 | F9: 200.1771 | I9: =IF(OR(E9="",E8=""),"",E9/E8-1) -> 0.046795402 | J9: =IF(OR(F9="",F8=""),"",F9/F8-1) -> 0.045794532 | K9: =IF(OR(G9="",G8=""),"",G9/G8-1) | L9: =IF(OR(H9="",H8=""),"",H9/H8-1) | O9: =IF(OR(E9="",E6=""),"",(E9/E6)^4-1) -> 0.56109042 | P9: =IF(OR(F9="",F6=""),"",(F9/F6)^4-1) -> 0.56638921 | Q9: =IF(E9="","",IFERROR(E9/INDEX($E:$E,MATCH(C9-1&"-12",$B:$B,0))-1,"")) -> 0.11778175
B10: 2019-04 | C10: 2019 | D10: 4 | E10: 212.95964 | F10: 207.7179 | I10: =IF(OR(E10="",E9=""),"",E10/E9-1) -> 0.034 | J10: =IF(OR(F10="",F9=""),"",F10/F9-1) -> 0.037670643 | K10: =IF(OR(G10="",G9=""),"",G10/G9-1) | L10: =IF(OR(H10="",H9=""),"",H10/H9-1) | O10: =IF(OR(E10="",E7=""),"",(E10/E7)^4-1) -> 0.59126811 | P10: =IF(OR(F10="",F7=""),"",(F10/F7)^4-1) -> 0.6133982 | Q10: =IF(E10="","",IFERROR(E10/INDEX($E:$E,MATCH(C10-1&"-12",$B:$B,0))-1,"")) -> 0.15578633
B11: 2019-05 | C11: 2019 | D11: 5 | E11: 219.5691 | F11: 214.3182 | I11: =IF(OR(E11="",E10=""),"",E11/E10-1) -> 0.031036203 | J11: =IF(OR(F11="",F10=""),"",F11/F10-1) -> 0.031775307 | K11: =IF(OR(G11="",G10=""),"",G11/G10-1) | L11: =IF(OR(H11="",H10=""),"",H11/H10-1) | O11: =IF(OR(E11="",E8=""),"",(E11/E8)^4-1) -> 0.55104729 | P11: =IF(OR(F11="",F8=""),"",(F11/F8)^4-1) -> 0.57167992 | Q11: =IF(E11="","",IFERROR(E11/INDEX($E:$E,MATCH(C11-1&"-12",$B:$B,0))-1,"")) -> 0.19165755
B12: 2019-06 | C12: 2019 | D12: 6 | E12: 225.537 | F12: 220.1725 | I12: =IF(OR(E12="",E11=""),"",E12/E11-1) -> 0.027180054 | J12: =IF(OR(F12="",F11=""),"",F12/F11-1) -> 0.027315926 | K12: =IF(OR(G12="",G11=""),"",G12/G11-1) | L12: =IF(OR(H12="",H11=""),"",H12/H11-1) | O12: =IF(OR(E12="",E9=""),"",(E12/E9)^4-1) -> 0.43801735 | P12: =IF(OR(F12="",F9=""),"",(F12/F9)^4-1) -> 0.46350672 | Q12: =IF(E12="","",IFERROR(E12/INDEX($E:$E,MATCH(C12-1&"-12",$B:$B,0))-1,"")) -> 0.22404687
B13: 2019-07 | C13: 2019 | D13: 7 | E13: 230.494 | F13: 224.9011 | I13: =IF(OR(E13="",E12=""),"",E13/E12-1) -> 0.021978655 | J13: =IF(OR(F13="",F12=""),"",F13/F12-1) -> 0.021476797 | K13: =IF(OR(G13="",G12=""),"",G13/G12-1) | L13: =IF(OR(H13="",H12=""),"",H13/H12-1) | O13: =IF(OR(E13="",E10=""),"",(E13/E10)^4-1) -> 0.37230066 | P13: =IF(OR(F13="",F10=""),"",(F13/F10)^4-1) -> 0.37426544 | Q13: =IF(E13="","",IFERROR(E13/INDEX($E:$E,MATCH(C13-1&"-12",$B:$B,0))-1,"")) -> 0.25094977
B14: 2019-08 | C14: 2019 | D14: 8 | E14: 239.6077 | F14: 235.3317 | I14: =IF(OR(E14="",E13=""),"",E14/E13-1) -> 0.039539858 | J14: =IF(OR(F14="",F13=""),"",F14/F13-1) -> 0.046378608 | K14: =IF(OR(G14="",G13=""),"",G14/G13-1) | L14: =IF(OR(H14="",H13=""),"",H14/H13-1) | O14: =IF(OR(E14="",E11=""),"",(E14/E11)^4-1) -> 0.41813702 | P14: =IF(OR(F14="",F11=""),"",(F14/F11)^4-1) -> 0.4537359 | Q14: =IF(E14="","",IFERROR(E14/INDEX($E:$E,MATCH(C14-1&"-12",$B:$B,0))-1,"")) -> 0.30041215
B15: 2019-09 | C15: 2019 | D15: 9 | E15: 253.7102 | F15: 250.4818 | I15: =IF(OR(E15="",E14=""),"",E15/E14-1) -> 0.058856623 | J15: =IF(OR(F15="",F14=""),"",F15/F14-1) -> 0.064377642 | K15: =IF(OR(G15="",G14=""),"",G15/G14-1) | L15: =IF(OR(H15="",H14=""),"",H15/H14-1) | O15: =IF(OR(E15="",E12=""),"",(E15/E12)^4-1) -> 0.6013288 | P15: =IF(OR(F15="",F12=""),"",(F15/F12)^4-1) -> 0.67514501 | Q15: =IF(E15="","",IFERROR(E15/INDEX($E:$E,MATCH(C15-1&"-12",$B:$B,0))-1,"")) -> 0.37695001
B16: 2019-10 | C16: 2019 | D16: 10 | E16: 262.0661 | F16: 260.0118 | I16: =IF(OR(E16="",E15=""),"",E16/E15-1) -> 0.032934821 | J16: =IF(OR(F16="",F15=""),"",F16/F15-1) -> 0.038046676 | K16: =IF(OR(G16="",G15=""),"",G16/G15-1) | L16: =IF(OR(H16="",H15=""),"",H16/H15-1) | O16: =IF(OR(E16="",E13=""),"",(E16/E13)^4-1) -> 0.67110941 | P16: =IF(OR(F16="",F13=""),"",(F16/F13)^4-1) -> 0.7865119 | Q16: =IF(E16="","",IFERROR(E16/INDEX($E:$E,MATCH(C16-1&"-12",$B:$B,0))-1,"")) -> 0.42229961
B17: 2019-11 | C17: 2019 | D17: 11 | E17: 273.2158 | F17: 270.3554 | I17: =IF(OR(E17="",E16=""),"",E17/E16-1) -> 0.042545373 | J17: =IF(OR(F17="",F16=""),"",F17/F16-1) -> 0.039781271 | K17: =IF(OR(G17="",G16=""),"",G17/G16-1) | L17: =IF(OR(H17="",H16=""),"",H17/H16-1) | O17: =IF(OR(E17="",E14=""),"",(E17/E14)^4-1) -> 0.69051941 | P17: =IF(OR(F17="",F14=""),"",(F17/F14)^4-1) -> 0.74188093 | Q17: =IF(E17="","",IFERROR(E17/INDEX($E:$E,MATCH(C17-1&"-12",$B:$B,0))-1,"")) -> 0.48281188
B18: 2019-12 | C18: 2019 | D18: 12 | E18: 283.4442 | F18: 280.3107 | I18: =IF(OR(E18="",E17=""),"",E18/E17-1) -> 0.037437074 | J18: =IF(OR(F18="",F17=""),"",F18/F17-1) -> 0.036823011 | K18: =IF(OR(G18="",G17=""),"",G18/G17-1) | L18: =IF(OR(H18="",H17=""),"",H18/H17-1) | M18: =IF(OR(E18="",E6=""),"",E18/E6-1) -> 0.53832402 | N18: =IF(OR(F18="",F6=""),"",F18/F6-1) -> 0.56657144 | O18: =IF(OR(E18="",E15=""),"",(E18/E15)^4-1) -> 0.55782471 | P18: =IF(OR(F18="",F15=""),"",(F18/F15)^4-1) -> 0.56838977 | Q18: =IF(E18="","",IFERROR(E18/INDEX($E:$E,MATCH(C18-1&"-12",$B:$B,0))-1,"")) -> 0.53832402
B19: 2020-01 | C19: 2020 | D19: 1 | E19: 289.8299 | F19: 287.1529 | I19: =IF(OR(E19="",E18=""),"",E19/E18-1) -> 0.022528949 | J19: =IF(OR(F19="",F18=""),"",F19/F18-1) -> 0.024409343 | K19: =IF(OR(G19="",G18=""),"",G19/G18-1) | L19: =IF(OR(H19="",H18=""),"",H19/H18-1) | M19: =IF(OR(E19="",E7=""),"",E19/E7-1) -> 0.52855729 | N19: =IF(OR(F19="",F7=""),"",F19/F7-1) -> 0.55802591 | O19: =IF(OR(E19="",E16=""),"",(E19/E16)^4-1) -> 0.49599232 | P19: =IF(OR(F19="",F16=""),"",(F19/F16)^4-1) -> 0.48758091 | Q19: =IF(E19="","",IFERROR(E19/INDEX($E:$E,MATCH(C19-1&"-12",$B:$B,0))-1,"")) -> 0.022528949
B20: 2020-02 | C20: 2020 | D20: 2 | E20: 295.666 | F20: 293.9922 | I20: =IF(OR(E20="",E19=""),"",E20/E19-1) -> 0.020136294 | J20: =IF(OR(F20="",F19=""),"",F20/F19-1) -> 0.023817625 | K20: =IF(OR(G20="",G19=""),"",G20/G19-1) | L20: =IF(OR(H20="",H19=""),"",H20/H19-1) | M20: =IF(OR(E20="",E8=""),"",E20/E8-1) -> 0.50274892 | N20: =IF(OR(F20="",F8=""),"",F20/F8-1) -> 0.53591712 | O20: =IF(OR(E20="",E17=""),"",(E20/E17)^4-1) -> 0.37145733 | P20: =IF(OR(F20="",F17=""),"",(F20/F17)^4-1) -> 0.39830863 | Q20: =IF(E20="","",IFERROR(E20/INDEX($E:$E,MATCH(C20-1&"-12",$B:$B,0))-1,"")) -> 0.043118893
B21: 2020-03 | C21: 2020 | D21: 3 | E21: 305.5515 | F21: 303.1665 | I21: =IF(OR(E21="",E20=""),"",E21/E20-1) -> 0.033434686 | J21: =IF(OR(F21="",F20=""),"",F21/F20-1) -> 0.03120593 | K21: =IF(OR(G21="",G20=""),"",G21/G20-1) | L21: =IF(OR(H21="",H20=""),"",H21/H20-1) | M21: =IF(OR(E21="",E9=""),"",E21/E9-1) -> 0.48356867 | N21: =IF(OR(F21="",F9=""),"",F21/F9-1) -> 0.51449142 | O21: =IF(OR(E21="",E18=""),"",(E21/E18)^4-1) -> 0.3504154 | P21: =IF(OR(F21="",F18=""),"",(F21/F18)^4-1) -> 0.36825214 | Q21: =IF(E21="","",IFERROR(E21/INDEX($E:$E,MATCH(C21-1&"-12",$B:$B,0))-1,"")) -> 0.077995246
B22: 2020-04 | C22: 2020 | D22: 4 | E22: 310.1243 | F22: 308.3681 | I22: =IF(OR(E22="",E21=""),"",E22/E21-1) -> 0.014965726 | J22: =IF(OR(F22="",F21=""),"",F22/F21-1) -> 0.017157569 | K22: =IF(OR(G22="",G21=""),"",G22/G21-1) | L22: =IF(OR(H22="",H21=""),"",H22/H21-1) | M22: =IF(OR(E22="",E10=""),"",E22/E10-1) -> 0.45625856 | N22: =IF(OR(F22="",F10=""),"",F22/F10-1) -> 0.48455237 | O22: =IF(OR(E22="",E19=""),"",(E22/E19)^4-1) -> 0.31090265 | P22: =IF(OR(F22="",F19=""),"",(F22/F19)^4-1) -> 0.32991827 | Q22: =IF(E22="","",IFERROR(E22/INDEX($E:$E,MATCH(C22-1&"-12",$B:$B,0))-1,"")) -> 0.094128227
B23: 2020-05 | C23: 2020 | D23: 5 | E23: 314.9087 | F23: 313.3195 | I23: =IF(OR(E23="",E22=""),"",E23/E22-1) -> 0.015427363 | J23: =IF(OR(F23="",F22=""),"",F23/F22-1) -> 0.016056784 | K23: =IF(OR(G23="",G22=""),"",G23/G22-1) | L23: =IF(OR(H23="",H22=""),"",H23/H22-1) | M23: =IF(OR(E23="",E11=""),"",E23/E11-1) -> 0.43421228 | N23: =IF(OR(F23="",F11=""),"",F23/F11-1) -> 0.46193604 | O23: =IF(OR(E23="",E20=""),"",(E23/E20)^4-1) -> 0.28686531 | P23: =IF(OR(F23="",F20=""),"",(F23/F20)^4-1) -> 0.29004977 | Q23: =IF(E23="","",IFERROR(E23/INDEX($E:$E,MATCH(C23-1&"-12",$B:$B,0))-1,"")) -> 0.11100774
B24: 2020-06 | C24: 2020 | D24: 6 | E24: 321.9738 | F24: 320.5733 | I24: =IF(OR(E24="",E23=""),"",E24/E23-1) -> 0.022435392 | J24: =IF(OR(F24="",F23=""),"",F24/F23-1) -> 0.023151448 | K24: =IF(OR(G24="",G23=""),"",G24/G23-1) | L24: =IF(OR(H24="",H23=""),"",H24/H23-1) | M24: =IF(OR(E24="",E12=""),"",E24/E12-1) -> 0.42758749 | N24: =IF(OR(F24="",F12=""),"",F24/F12-1) -> 0.45600972 | O24: =IF(OR(E24="",E21=""),"",(E24/E21)^4-1) -> 0.23294713 | P24: =IF(OR(F24="",F21=""),"",(F24/F21)^4-1) -> 0.25021456 | Q24: =IF(E24="","",IFERROR(E24/INDEX($E:$E,MATCH(C24-1&"-12",$B:$B,0))-1,"")) -> 0.13593363
B25: 2020-07 | C25: 2020 | D25: 7 | E25: 328.2014 | F25: 328.6943 | I25: =IF(OR(E25="",E24=""),"",E25/E24-1) -> 0.019341946 | J25: =IF(OR(F25="",F24=""),"",F25/F24-1) -> 0.02533274 | K25: =IF(OR(G25="",G24=""),"",G25/G24-1) | L25: =IF(OR(H25="",H24=""),"",H25/H24-1) | M25: =IF(OR(E25="",E13=""),"",E25/E13-1) -> 0.42390431 | N25: =IF(OR(F25="",F13=""),"",F25/F13-1) -> 0.46150597 | O25: =IF(OR(E25="",E22=""),"",(E25/E22)^4-1) -> 0.25434941 | P25: =IF(OR(F25="",F22=""),"",(F25/F22)^4-1) -> 0.29089498 | Q25: =IF(E25="","",IFERROR(E25/INDEX($E:$E,MATCH(C25-1&"-12",$B:$B,0))-1,"")) -> 0.1579048
B26: 2020-08 | C26: 2020 | D26: 8 | E26: 337.0632 | F26: 338.6645 | I26: =IF(OR(E26="",E25=""),"",E26/E25-1) -> 0.027001104 | J26: =IF(OR(F26="",F25=""),"",F26/F25-1) -> 0.030332744 | K26: =IF(OR(G26="",G25=""),"",G26/G25-1) | L26: =IF(OR(H26="",H25=""),"",H26/H25-1) | M26: =IF(OR(E26="",E14=""),"",E26/E14-1) -> 0.40672942 | N26: =IF(OR(F26="",F14=""),"",F26/F14-1) -> 0.43909427 | O26: =IF(OR(E26="",E23=""),"",(E26/E23)^4-1) -> 0.31252239 | P26: =IF(OR(F26="",F23=""),"",(F26/F23)^4-1) -> 0.36498852 | Q26: =IF(E26="","",IFERROR(E26/INDEX($E:$E,MATCH(C26-1&"-12",$B:$B,0))-1,"")) -> 0.18916951
B27: 2020-09 | C27: 2020 | D27: 9 | E27: 346.6207 | F27: 346.511 | I27: =IF(OR(E27="",E26=""),"",E27/E26-1) -> 0.028355216 | J27: =IF(OR(F27="",F26=""),"",F27/F26-1) -> 0.023168947 | K27: =IF(OR(G27="",G26=""),"",G27/G26-1) | L27: =IF(OR(H27="",H26=""),"",H27/H26-1) | M27: =IF(OR(E27="",E15=""),"",E27/E15-1) -> 0.36620719 | N27: =IF(OR(F27="",F15=""),"",F27/F15-1) -> 0.38337795 | O27: =IF(OR(E27="",E24=""),"",(E27/E24)^4-1) -> 0.34318504 | P27: =IF(OR(F27="",F24=""),"",(F27/F24)^4-1) -> 0.36508191 | Q27: =IF(E27="","",IFERROR(E27/INDEX($E:$E,MATCH(C27-1&"-12",$B:$B,0))-1,"")) -> 0.22288867
B28: 2020-10 | C28: 2020 | D28: 10 | E28: 359.657 | F28: 358.4989 | I28: =IF(OR(E28="",E27=""),"",E28/E27-1) -> 0.037609698 | J28: =IF(OR(F28="",F27=""),"",F28/F27-1) -> 0.034596016 | K28: =IF(OR(G28="",G27=""),"",G28/G27-1) | L28: =IF(OR(H28="",H27=""),"",H28/H27-1) | M28: =IF(OR(E28="",E16=""),"",E28/E16-1) -> 0.3723904 | N28: =IF(OR(F28="",F16=""),"",F28/F16-1) -> 0.37877935 | O28: =IF(OR(E28="",E25=""),"",(E28/E25)^4-1) -> 0.44208996 | P28: =IF(OR(F28="",F25=""),"",(F28/F25)^4-1) -> 0.4150853 | Q28: =IF(E28="","",IFERROR(E28/INDEX($E:$E,MATCH(C28-1&"-12",$B:$B,0))-1,"")) -> 0.26888114
B29: 2020-11 | C29: 2020 | D29: 11 | E29: 371.0211 | F29: 372.6154 | I29: =IF(OR(E29="",E28=""),"",E29/E28-1) -> 0.031597049 | J29: =IF(OR(F29="",F28=""),"",F29/F28-1) -> 0.03937669 | K29: =IF(OR(G29="",G28=""),"",G29/G28-1) | L29: =IF(OR(H29="",H28=""),"",H29/H28-1) | M29: =IF(OR(E29="",E17=""),"",E29/E17-1) -> 0.3579782 | N29: =IF(OR(F29="",F17=""),"",F29/F17-1) -> 0.37824286 | O29: =IF(OR(E29="",E26=""),"",(E29/E26)^4-1) -> 0.46807782 | P29: =IF(OR(F29="",F26=""),"",(F29/F26)^4-1) -> 0.46542805 | Q29: =IF(E29="","",IFERROR(E29/INDEX($E:$E,MATCH(C29-1&"-12",$B:$B,0))-1,"")) -> 0.30897404
... B42: 2021-12 | C42: 2021 | D42: 12 | E42: 582.4575 | F42: 605.1759 | I42: =IF(OR(E42="",E41=""),"",E42/E41-1) -> 0.038399703 | J42: =IF(OR(F42="",F41=""),"",F42/F41-1) -> 0.044232388 | K42: =IF(OR(G42="",G41=""),"",G42/G41-1) | L42: =IF(OR(H42="",H41=""),"",H42/H41-1) | M42: =IF(OR(E42="",E30=""),"",E42/E30-1) -> 0.50941634 | N42: =IF(OR(F42="",F30=""),"",F42/F30-1) -> 0.54869327 | O42: =IF(OR(E42="",E39=""),"",(E42/E39)^4-1) -> 0.47532438 | P42: =IF(OR(F42="",F39=""),"",(F42/F39)^4-1) -> 0.53295975 | Q42: =IF(E42="","",IFERROR(E42/INDEX($E:$E,MATCH(C42-1&"-12",$B:$B,0))-1,"")) -> 0.50941634
B43: 2022-01 | C43: 2022 | D43: 1 | E43: 605.0317 | F43: 625.1594 | G43: 512.3766 | H43: 658.2543 | I43: =IF(OR(E43="",E42=""),"",E43/E42-1) -> 0.038756819 | J43: =IF(OR(F43="",F42=""),"",F43/F42-1) -> 0.033020978 | K43: =IF(OR(G43="",G42=""),"",G43/G42-1) | L43: =IF(OR(H43="",H42=""),"",H43/H42-1) | M43: =IF(OR(E43="",E31=""),"",E43/E31-1) -> 0.50690162 | N43: =IF(OR(F43="",F31=""),"",F43/F31-1) -> 0.5395459 | O43: =IF(OR(E43="",E40=""),"",(E43/E40)^4-1) -> 0.49592056 | P43: =IF(OR(F43="",F40=""),"",(F43/F40)^4-1) -> 0.53897472 | Q43: =IF(E43="","",IFERROR(E43/INDEX($E:$E,MATCH(C43-1&"-12",$B:$B,0))-1,"")) -> 0.038756819
B44: 2022-02 | C44: 2022 | D44: 2 | E44: 633.4341 | F44: 652.9838 | G44: 528.2683 | H44: 713.7013 | I44: =IF(OR(E44="",E43=""),"",E44/E43-1) -> 0.046943656 | J44: =IF(OR(F44="",F43=""),"",F44/F43-1) -> 0.044507689 | K44: =IF(OR(G44="",G43=""),"",G44/G43-1) -> 0.031015663 | L44: =IF(OR(H44="",H43=""),"",H44/H43-1) -> 0.084233403 | M44: =IF(OR(E44="",E32=""),"",E44/E32-1) -> 0.52319257 | N44: =IF(OR(F44="",F32=""),"",F44/F32-1) -> 0.54518293 | O44: =IF(OR(E44="",E41=""),"",(E44/E41)^4-1) -> 0.62632377 | P44: =IF(OR(F44="",F41=""),"",(F44/F41)^4-1) -> 0.61165383 | Q44: =IF(E44="","",IFERROR(E44/INDEX($E:$E,MATCH(C44-1&"-12",$B:$B,0))-1,"")) -> 0.087519862
B45: 2022-03 | C45: 2022 | D45: 3 | E45: 676.0566 | F45: 694.7515 | G45: 572.7992 | H45: 757.8963 | I45: =IF(OR(E45="",E44=""),"",E45/E44-1) -> 0.067287978 | J45: =IF(OR(F45="",F44=""),"",F45/F44-1) -> 0.063964374 | K45: =IF(OR(G45="",G44=""),"",G45/G44-1) -> 0.084295991 | L45: =IF(OR(H45="",H44=""),"",H45/H44-1) -> 0.061923665 | M45: =IF(OR(E45="",E33=""),"",E45/E33-1) -> 0.5510663 | N45: =IF(OR(F45="",F33=""),"",F45/F33-1) -> 0.57283234 | O45: =IF(OR(E45="",E42=""),"",(E45/E42)^4-1) -> 0.81499428 | P45: =IF(OR(F45="",F42=""),"",(F45/F42)^4-1) -> 0.73696662 | Q45: =IF(E45="","",IFERROR(E45/INDEX($E:$E,MATCH(C45-1&"-12",$B:$B,0))-1,"")) -> 0.16069687
B46: 2022-04 | C46: 2022 | D46: 4 | E46: 716.9399 | F46: 741.3622 | G46: 595.2223 | H46: 799.0308 | I46: =IF(OR(E46="",E45=""),"",E46/E45-1) -> 0.060473191 | J46: =IF(OR(F46="",F45=""),"",F46/F45-1) -> 0.067089744 | K46: =IF(OR(G46="",G45=""),"",G46/G45-1) -> 0.039146528 | L46: =IF(OR(H46="",H45=""),"",H46/H45-1) -> 0.054274576 | M46: =IF(OR(E46="",E34=""),"",E46/E34-1) -> 0.58038009 | N46: =IF(OR(F46="",F34=""),"",F46/F34-1) -> 0.60517415 | O46: =IF(OR(E46="",E43=""),"",(E46/E43)^4-1) -> 0.97159853 | P46: =IF(OR(F46="",F43=""),"",(F46/F43)^4-1) -> 0.97769216 | Q46: =IF(E46="","",IFERROR(E46/INDEX($E:$E,MATCH(C46-1&"-12",$B:$B,0))-1,"")) -> 0.23088792
B47: 2022-05 | C47: 2022 | D47: 5 | E47: 753.147 | F47: 779.9267 | G47: 629.0029 | H47: 825.8088 | I47: =IF(OR(E47="",E46=""),"",E47/E46-1) -> 0.050502281 | J47: =IF(OR(F47="",F46=""),"",F47/F46-1) -> 0.052018433 | K47: =IF(OR(G47="",G46=""),"",G47/G46-1) -> 0.056752914 | L47: =IF(OR(H47="",H46=""),"",H47/H46-1) -> 0.033513101 | M47: =IF(OR(E47="",E35=""),"",E47/E35-1) -> 0.6067993 | N47: =IF(OR(F47="",F35=""),"",F47/F35-1) -> 0.63188718 | O47: =IF(OR(E47="",E44=""),"",(E47/E44)^4-1) -> 0.99854184 | P47: =IF(OR(F47="",F44=""),"",(F47/F44)^4-1) -> 1.0351926 | Q47: =IF(E47="","",IFERROR(E47/INDEX($E:$E,MATCH(C47-1&"-12",$B:$B,0))-1,"")) -> 0.29305057
B48: 2022-06 | C48: 2022 | D48: 6 | E48: 793.0278 | F48: 819.5734 | G48: 662.0938 | H48: 880.3186 | I48: =IF(OR(E48="",E47=""),"",E48/E47-1) -> 0.052952213 | J48: =IF(OR(F48="",F47=""),"",F48/F47-1) -> 0.05083388 | K48: =IF(OR(G48="",G47=""),"",G48/G47-1) -> 0.052608501 | L48: =IF(OR(H48="",H47=""),"",H48/H47-1) -> 0.066007773 | M48: =IF(OR(E48="",E36=""),"",E48/E36-1) -> 0.63982582 | N48: =IF(OR(F48="",F36=""),"",F48/F36-1) -> 0.65509897 | O48: =IF(OR(E48="",E45=""),"",(E48/E45)^4-1) -> 0.89330866 | P48: =IF(OR(F48="",F45=""),"",(F48/F45)^4-1) -> 0.9365711 | Q48: =IF(E48="","",IFERROR(E48/INDEX($E:$E,MATCH(C48-1&"-12",$B:$B,0))-1,"")) -> 0.36152045
B49: 2022-07 | C49: 2022 | D49: 7 | E49: 851.761 | F49: 879.6383 | G49: 694.6115 | H49: 979.7957 | I49: =IF(OR(E49="",E48=""),"",E49/E48-1) -> 0.074061969 | J49: =IF(OR(F49="",F48=""),"",F49/F48-1) -> 0.073288006 | K49: =IF(OR(G49="",G48=""),"",G49/G48-1) -> 0.049113434 | L49: =IF(OR(H49="",H48=""),"",H49/H48-1) -> 0.11300125 | M49: =IF(OR(E49="",E37=""),"",E49/E37-1) -> 0.71002454 | N49: =IF(OR(F49="",F37=""),"",F49/F37-1) -> 0.72242565 | O49: =IF(OR(E49="",E46=""),"",(E49/E46)^4-1) -> 0.99223241 | P49: =IF(OR(F49="",F46=""),"",(F49/F46)^4-1) -> 0.98195946 | Q49: =IF(E49="","",IFERROR(E49/INDEX($E:$E,MATCH(C49-1&"-12",$B:$B,0))-1,"")) -> 0.46235734
B50: 2022-08 | C50: 2022 | D50: 8 | E50: 911.1316 | F50: 939.4677 | G50: 738.3105 | H50: 1064.731 | I50: =IF(OR(E50="",E49=""),"",E50/E49-1) -> 0.069703356 | J50: =IF(OR(F50="",F49=""),"",F50/F49-1) -> 0.068015911 | K50: =IF(OR(G50="",G49=""),"",G50/G49-1) -> 0.062911426 | L50: =IF(OR(H50="",H49=""),"",H50/H49-1) -> 0.086686745 | M50: =IF(OR(E50="",E38=""),"",E50/E38-1) -> 0.78515273 | N50: =IF(OR(F50="",F38=""),"",F50/F38-1) -> 0.78370889 | O50: =IF(OR(E50="",E47=""),"",(E50/E47)^4-1) -> 1.1419308 | P50: =IF(OR(F50="",F47=""),"",(F50/F47)^4-1) -> 1.1052916 | Q50: =IF(E50="","",IFERROR(E50/INDEX($E:$E,MATCH(C50-1&"-12",$B:$B,0))-1,"")) -> 0.56428855
B51: 2022-09 | C51: 2022 | D51: 9 | E51: 967.3076 | F51: 991.2585 | G51: 771.8891 | H51: 1189.6609 | I51: =IF(OR(E51="",E50=""),"",E51/E50-1) -> 0.061655199 | J51: =IF(OR(F51="",F50=""),"",F51/F50-1) -> 0.055127813 | K51: =IF(OR(G51="",G50=""),"",G51/G50-1) -> 0.045480323 | L51: =IF(OR(H51="",H50=""),"",H51/H50-1) -> 0.11733471 | M51: =IF(OR(E51="",E39=""),"",E51/E39-1) -> 0.83029982 | N51: =IF(OR(F51="",F39=""),"",F51/F39-1) -> 0.82258582 | O51: =IF(OR(E51="",E48=""),"",(E51/E48)^4-1) -> 1.2136286 | P51: =IF(OR(F51="",F48=""),"",(F51/F48)^4-1) -> 1.1399138 | Q51: =IF(E51="","",IFERROR(E51/INDEX($E:$E,MATCH(C51-1&"-12",$B:$B,0))-1,"")) -> 0.66073508
B52: 2022-10 | C52: 2022 | D52: 10 | E52: 1028.706 | F52: 1046.265 | G52: 829.1011 | H52: 1297.2889 | I52: =IF(OR(E52="",E51=""),"",E52/E51-1) -> 0.063473501 | J52: =IF(OR(F52="",F51=""),"",F52/F51-1) -> 0.05549158 | K52: =IF(OR(G52="",G51=""),"",G52/G51-1) -> 0.074119456 | L52: =IF(OR(H52="",H51=""),"",H52/H51-1) -> 0.090469477 | M52: =IF(OR(E52="",E40=""),"",E52/E40-1) -> 0.88035685 | N52: =IF(OR(F52="",F40=""),"",F52/F40-1) -> 0.86405535 | O52: =IF(OR(E52="",E49=""),"",(E52/E49)^4-1) -> 1.1276201 | P52: =IF(OR(F52="",F49=""),"",(F52/F49)^4-1) -> 1.0014754 | Q52: =IF(E52="","",IFERROR(E52/INDEX($E:$E,MATCH(C52-1&"-12",$B:$B,0))-1,"")) -> 0.76614774
B53: 2022-11 | C53: 2022 | D53: 11 | E53: 1079.2787 | F53: 1096.024 | G53: 880.7676 | H53: 1350.5167 | I53: =IF(OR(E53="",E52=""),"",E53/E52-1) -> 0.049161471 | J53: =IF(OR(F53="",F52=""),"",F53/F52-1) -> 0.047558697 | K53: =IF(OR(G53="",G52=""),"",G53/G52-1) -> 0.062316284 | L53: =IF(OR(H53="",H52=""),"",H53/H52-1) -> 0.041030028 | M53: =IF(OR(E53="",E41=""),"",E53/E41-1) -> 0.92412782 | N53: =IF(OR(F53="",F41=""),"",F53/F41-1) -> 0.8911919 | O53: =IF(OR(E53="",E50=""),"",(E53/E50)^4-1) -> 0.96883802 | P53: =IF(OR(F53="",F50=""),"",(F53/F50)^4-1) -> 0.85247708 | Q53: =IF(E53="","",IFERROR(E53/INDEX($E:$E,MATCH(C53-1&"-12",$B:$B,0))-1,"")) -> 0.85297417
B54: 2022-12 | C54: 2022 | D54: 12 | E54: 1134.5875 | F54: 1153.5771 | G54: 925.7853 | H54: 1413.2059 | I54: =IF(OR(E54="",E53=""),"",E54/E53-1) -> 0.051246078 | J54: =IF(OR(F54="",F53=""),"",F54/F53-1) -> 0.052510803 | K54: =IF(OR(G54="",G53=""),"",G54/G53-1) -> 0.051111894 | L54: =IF(OR(H54="",H53=""),"",H54/H53-1) -> 0.046418678 | M54: =IF(OR(E54="",E42=""),"",E54/E42-1) -> 0.94793182 | N54: =IF(OR(F54="",F42=""),"",F54/F42-1) -> 0.9061848 | O54: =IF(OR(E54="",E51=""),"",(E54/E51)^4-1) -> 0.89275141 | P54: =IF(OR(F54="",F51=""),"",(F54/F51)^4-1) -> 0.83416671 | Q54: =IF(E54="","",IFERROR(E54/INDEX($E:$E,MATCH(C54-1&"-12",$B:$B,0))-1,"")) -> 0.94793182
... B96: 2026-06 | C96: 2026 | D96: 6 | E96: 11826.41 | F96: 12010.32 | G96: 12389.434 | H96: 9738.5609 | I96: =IF(OR(E96="",E95=""),"",E96/E95-1) -> 0.018868715 | J96: =IF(OR(F96="",F95=""),"",F96/F95-1) -> 0.015695812 | K96: =IF(OR(G96="",G95=""),"",G96/G95-1) -> 0.022951919 | L96: =IF(OR(H96="",H95=""),"",H96/H95-1) -> 0.033758882 | M96: =IF(OR(E96="",E84=""),"",E96/E84-1) -> 0.33547731 | N96: =IF(OR(F96="",F84=""),"",F96/F84-1) -> 0.31817794 | O96: =IF(OR(E96="",E93=""),"",(E96/E93)^4-1) -> 0.29931248 | P96: =IF(OR(F96="",F93=""),"",(F96/F93)^4-1) -> 0.2562715 | Q96: =IF(E96="","",IFERROR(E96/INDEX($E:$E,MATCH(C96-1&"-12",$B:$B,0))-1,"")) -> 0.16845926
B97: 2026-07 | C97: 2026 | D97: 7 | I97: =IF(OR(E97="",E96=""),"",E97/E96-1) | J97: =IF(OR(F97="",F96=""),"",F97/F96-1) | K97: =IF(OR(G97="",G96=""),"",G97/G96-1) | L97: =IF(OR(H97="",H96=""),"",H97/H96-1) | M97: =IF(OR(E97="",E85=""),"",E97/E85-1) | N97: =IF(OR(F97="",F85=""),"",F97/F85-1) | O97: =IF(OR(E97="",E94=""),"",(E97/E94)^4-1) | P97: =IF(OR(F97="",F94=""),"",(F97/F94)^4-1) | Q97: =IF(E97="","",IFERROR(E97/INDEX($E:$E,MATCH(C97-1&"-12",$B:$B,0))-1,""))
B98: 2026-08 | C98: 2026 | D98: 8 | I98: =IF(OR(E98="",E97=""),"",E98/E97-1) | J98: =IF(OR(F98="",F97=""),"",F98/F97-1) | K98: =IF(OR(G98="",G97=""),"",G98/G97-1) | L98: =IF(OR(H98="",H97=""),"",H98/H97-1) | M98: =IF(OR(E98="",E86=""),"",E98/E86-1) | N98: =IF(OR(F98="",F86=""),"",F98/F86-1) | O98: =IF(OR(E98="",E95=""),"",(E98/E95)^4-1) | P98: =IF(OR(F98="",F95=""),"",(F98/F95)^4-1) | Q98: =IF(E98="","",IFERROR(E98/INDEX($E:$E,MATCH(C98-1&"-12",$B:$B,0))-1,""))
B99: 2026-09 | C99: 2026 | D99: 9 | I99: =IF(OR(E99="",E98=""),"",E99/E98-1) | J99: =IF(OR(F99="",F98=""),"",F99/F98-1) | K99: =IF(OR(G99="",G98=""),"",G99/G98-1) | L99: =IF(OR(H99="",H98=""),"",H99/H98-1) | M99: =IF(OR(E99="",E87=""),"",E99/E87-1) | N99: =IF(OR(F99="",F87=""),"",F99/F87-1) | O99: =IF(OR(E99="",E96=""),"",(E99/E96)^4-1) | P99: =IF(OR(F99="",F96=""),"",(F99/F96)^4-1) | Q99: =IF(E99="","",IFERROR(E99/INDEX($E:$E,MATCH(C99-1&"-12",$B:$B,0))-1,""))
B100: 2026-10 | C100: 2026 | D100: 10 | I100: =IF(OR(E100="",E99=""),"",E100/E99-1) | J100: =IF(OR(F100="",F99=""),"",F100/F99-1) | K100: =IF(OR(G100="",G99=""),"",G100/G99-1) | L100: =IF(OR(H100="",H99=""),"",H100/H99-1) | M100: =IF(OR(E100="",E88=""),"",E100/E88-1) | N100: =IF(OR(F100="",F88=""),"",F100/F88-1) | O100: =IF(OR(E100="",E97=""),"",(E100/E97)^4-1) | P100: =IF(OR(F100="",F97=""),"",(F100/F97)^4-1) | Q100: =IF(E100="","",IFERROR(E100/INDEX($E:$E,MATCH(C100-1&"-12",$B:$B,0))-1,""))
B101: 2026-11 | C101: 2026 | D101: 11 | I101: =IF(OR(E101="",E100=""),"",E101/E100-1) | J101: =IF(OR(F101="",F100=""),"",F101/F100-1) | K101: =IF(OR(G101="",G100=""),"",G101/G100-1) | L101: =IF(OR(H101="",H100=""),"",H101/H100-1) | M101: =IF(OR(E101="",E89=""),"",E101/E89-1) | N101: =IF(OR(F101="",F89=""),"",F101/F89-1) | O101: =IF(OR(E101="",E98=""),"",(E101/E98)^4-1) | P101: =IF(OR(F101="",F98=""),"",(F101/F98)^4-1) | Q101: =IF(E101="","",IFERROR(E101/INDEX($E:$E,MATCH(C101-1&"-12",$B:$B,0))-1,""))
B102: 2026-12 | C102: 2026 | D102: 12 | I102: =IF(OR(E102="",E101=""),"",E102/E101-1) | J102: =IF(OR(F102="",F101=""),"",F102/F101-1) | K102: =IF(OR(G102="",G101=""),"",G102/G101-1) | L102: =IF(OR(H102="",H101=""),"",H102/H101-1) | M102: =IF(OR(E102="",E90=""),"",E102/E90-1) | N102: =IF(OR(F102="",F90=""),"",F102/F90-1) | O102: =IF(OR(E102="",E99=""),"",(E102/E99)^4-1) | P102: =IF(OR(F102="",F99=""),"",(F102/F99)^4-1) | Q102: =IF(E102="","",IFERROR(E102/INDEX($E:$E,MATCH(C102-1&"-12",$B:$B,0))-1,""))
B103: 2027-01 | C103: 2027 | D103: 1 | I103: =IF(OR(E103="",E102=""),"",E103/E102-1) | J103: =IF(OR(F103="",F102=""),"",F103/F102-1) | K103: =IF(OR(G103="",G102=""),"",G103/G102-1) | L103: =IF(OR(H103="",H102=""),"",H103/H102-1) | M103: =IF(OR(E103="",E91=""),"",E103/E91-1) | N103: =IF(OR(F103="",F91=""),"",F103/F91-1) | O103: =IF(OR(E103="",E100=""),"",(E103/E100)^4-1) | P103: =IF(OR(F103="",F100=""),"",(F103/F100)^4-1) | Q103: =IF(E103="","",IFERROR(E103/INDEX($E:$E,MATCH(C103-1&"-12",$B:$B,0))-1,""))
B104: 2027-02 | C104: 2027 | D104: 2 | I104: =IF(OR(E104="",E103=""),"",E104/E103-1) | J104: =IF(OR(F104="",F103=""),"",F104/F103-1) | K104: =IF(OR(G104="",G103=""),"",G104/G103-1) | L104: =IF(OR(H104="",H103=""),"",H104/H103-1) | M104: =IF(OR(E104="",E92=""),"",E104/E92-1) | N104: =IF(OR(F104="",F92=""),"",F104/F92-1) | O104: =IF(OR(E104="",E101=""),"",(E104/E101)^4-1) | P104: =IF(OR(F104="",F101=""),"",(F104/F101)^4-1) | Q104: =IF(E104="","",IFERROR(E104/INDEX($E:$E,MATCH(C104-1&"-12",$B:$B,0))-1,""))
B105: 2027-03 | C105: 2027 | D105: 3 | I105: =IF(OR(E105="",E104=""),"",E105/E104-1) | J105: =IF(OR(F105="",F104=""),"",F105/F104-1) | K105: =IF(OR(G105="",G104=""),"",G105/G104-1) | L105: =IF(OR(H105="",H104=""),"",H105/H104-1) | M105: =IF(OR(E105="",E93=""),"",E105/E93-1) | N105: =IF(OR(F105="",F93=""),"",F105/F93-1) | O105: =IF(OR(E105="",E102=""),"",(E105/E102)^4-1) | P105: =IF(OR(F105="",F102=""),"",(F105/F102)^4-1) | Q105: =IF(E105="","",IFERROR(E105/INDEX($E:$E,MATCH(C105-1&"-12",$B:$B,0))-1,""))
B106: 2027-04 | C106: 2027 | D106: 4 | I106: =IF(OR(E106="",E105=""),"",E106/E105-1) | J106: =IF(OR(F106="",F105=""),"",F106/F105-1) | K106: =IF(OR(G106="",G105=""),"",G106/G105-1) | L106: =IF(OR(H106="",H105=""),"",H106/H105-1) | M106: =IF(OR(E106="",E94=""),"",E106/E94-1) | N106: =IF(OR(F106="",F94=""),"",F106/F94-1) | O106: =IF(OR(E106="",E103=""),"",(E106/E103)^4-1) | P106: =IF(OR(F106="",F103=""),"",(F106/F103)^4-1) | Q106: =IF(E106="","",IFERROR(E106/INDEX($E:$E,MATCH(C106-1&"-12",$B:$B,0))-1,""))
B107: 2027-05 | C107: 2027 | D107: 5 | I107: =IF(OR(E107="",E106=""),"",E107/E106-1) | J107: =IF(OR(F107="",F106=""),"",F107/F106-1) | K107: =IF(OR(G107="",G106=""),"",G107/G106-1) | L107: =IF(OR(H107="",H106=""),"",H107/H106-1) | M107: =IF(OR(E107="",E95=""),"",E107/E95-1) | N107: =IF(OR(F107="",F95=""),"",F107/F95-1) | O107: =IF(OR(E107="",E104=""),"",(E107/E104)^4-1) | P107: =IF(OR(F107="",F104=""),"",(F107/F104)^4-1) | Q107: =IF(E107="","",IFERROR(E107/INDEX($E:$E,MATCH(C107-1&"-12",$B:$B,0))-1,""))
B108: 2027-06 | C108: 2027 | D108: 6 | I108: =IF(OR(E108="",E107=""),"",E108/E107-1) | J108: =IF(OR(F108="",F107=""),"",F108/F107-1) | K108: =IF(OR(G108="",G107=""),"",G108/G107-1) | L108: =IF(OR(H108="",H107=""),"",H108/H107-1) | M108: =IF(OR(E108="",E96=""),"",E108/E96-1) | N108: =IF(OR(F108="",F96=""),"",F108/F96-1) | O108: =IF(OR(E108="",E105=""),"",(E108/E105)^4-1) | P108: =IF(OR(F108="",F105=""),"",(F108/F105)^4-1) | Q108: =IF(E108="","",IFERROR(E108/INDEX($E:$E,MATCH(C108-1&"-12",$B:$B,0))-1,""))
... B114: 2027-12 | C114: 2027 | D114: 12 | I114: =IF(OR(E114="",E113=""),"",E114/E113-1) | J114: =IF(OR(F114="",F113=""),"",F114/F113-1) | K114: =IF(OR(G114="",G113=""),"",G114/G113-1) | L114: =IF(OR(H114="",H113=""),"",H114/H113-1) | M114: =IF(OR(E114="",E102=""),"",E114/E102-1) | N114: =IF(OR(F114="",F102=""),"",F114/F102-1) | O114: =IF(OR(E114="",E111=""),"",(E114/E111)^4-1) | P114: =IF(OR(F114="",F111=""),"",(F114/F111)^4-1) | Q114: =IF(E114="","",IFERROR(E114/INDEX($E:$E,MATCH(C114-1&"-12",$B:$B,0))-1,""))

Sheet Seasonality Headline
B2: Seasonality — IPC Nivel General (headline): month-on-month % by calendar year
B3: One line per calendar year, Jan-Dec on the x-axis. Recent years are drawn darker; 2026 in red.
B5: Month | C5: 2019 | D5: 2020 | E5: 2021 | F5: 2022 | G5: 2023 | H5: 2024 | I5: 2025 | J5: 2026
B6: Jan | C6: =IF(COUNTIFS(Data!$C$6:$C$114,C$5,Data!$D$6:$D$114,1,Data!$E$6:$E$114,">0")=0,"",SUMIFS(Data!$I$6:$I$114,Data!$C$6:$C$114,C$5,Data!$D$6:$D$114,1)) -> 0.029062409 | D6: =IF(COUNTIFS(Data!$C$6:$C$114,D$5,Data!$D$6:$D$114,1,Data!$E$6:$E$114,">0")=0,"",SUMIFS(Data!$I$6:$I$114,Data!$C$6:$C$114,D$5,Data!$D$6:$D$114,1)) -> 0.022528949 | E6: =IF(COUNTIFS(Data!$C$6:$C$114,E$5,Data!$D$6:$D$114,1,Data!$E$6:$E$114,">0")=0,"",SUMIFS(Data!$I$6:$I$114,Data!$C$6:$C$114,E$5,Data!$D$6:$D$114,1)) -> 0.040490294 | F6: =IF(COUNTIFS(Data!$C$6:$C$114,F$5,Data!$D$6:$D$114,1,Data!$E$6:$E$114,">0")=0,"",SUMIFS(Data!$I$6:$I$114,Data!$C$6:$C$114,F$5,Data!$D$6:$D$114,1)) -> 0.038756819 | G6: =IF(COUNTIFS(Data!$C$6:$C$114,G$5,Data!$D$6:$D$114,1,Data!$E$6:$E$114,">0")=0,"",SUMIFS(Data!$I$6:$I$114,Data!$C$6:$C$114,G$5,Data!$D$6:$D$114,1)) -> 0.060278736 | H6: =IF(COUNTIFS(Data!$C$6:$C$114,H$5,Data!$D$6:$D$114,1,Data!$E$6:$E$114,">0")=0,"",SUMIFS(Data!$I$6:$I$114,Data!$C$6:$C$114,H$5,Data!$D$6:$D$114,1)) -> 0.20614225 | I6: =IF(COUNTIFS(Data!$C$6:$C$114,I$5,Data!$D$6:$D$114,1,Data!$E$6:$E$114,">0")=0,"",SUMIFS(Data!$I$6:$I$114,Data!$C$6:$C$114,I$5,Data!$D$6:$D$114,1)) -> 0.02211048 | J6: =IF(COUNTIFS(Data!$C$6:$C$114,J$5,Data!$D$6:$D$114,1,Data!$E$6:$E$114,">0")=0,"",SUMIFS(Data!$I$6:$I$114,Data!$C$6:$C$114,J$5,Data!$D$6:$D$114,1)) -> 0.028816194
B7: Feb | C7: =IF(COUNTIFS(Data!$C$6:$C$114,C$5,Data!$D$6:$D$114,2,Data!$E$6:$E$114,">0")=0,"",SUMIFS(Data!$I$6:$I$114,Data!$C$6:$C$114,C$5,Data!$D$6:$D$114,2)) -> 0.037656222 | D7: =IF(COUNTIFS(Data!$C$6:$C$114,D$5,Data!$D$6:$D$114,2,Data!$E$6:$E$114,">0")=0,"",SUMIFS(Data!$I$6:$I$114,Data!$C$6:$C$114,D$5,Data!$D$6:$D$114,2)) -> 0.020136294 | E7: =IF(COUNTIFS(Data!$C$6:$C$114,E$5,Data!$D$6:$D$114,2,Data!$E$6:$E$114,">0")=0,"",SUMIFS(Data!$I$6:$I$114,Data!$C$6:$C$114,E$5,Data!$D$6:$D$114,2)) -> 0.035746317 | F7: =IF(COUNTIFS(Data!$C$6:$C$114,F$5,Data!$D$6:$D$114,2,Data!$E$6:$E$114,">0")=0,"",SUMIFS(Data!$I$6:$I$114,Data!$C$6:$C$114,F$5,Data!$D$6:$D$114,2)) -> 0.046943656 | G7: =IF(COUNTIFS(Data!$C$6:$C$114,G$5,Data!$D$6:$D$114,2,Data!$E$6:$E$114,">0")=0,"",SUMIFS(Data!$I$6:$I$114,Data!$C$6:$C$114,G$5,Data!$D$6:$D$114,2)) -> 0.066277217 | H7: =IF(COUNTIFS(Data!$C$6:$C$114,H$5,Data!$D$6:$D$114,2,Data!$E$6:$E$114,">0")=0,"",SUMIFS(Data!$I$6:$I$114,Data!$C$6:$C$114,H$5,Data!$D$6:$D$114,2)) -> 0.13240676 | I7: =IF(COUNTIFS(Data!$C$6:$C$114,I$5,Data!$D$6:$D$114,2,Data!$E$6:$E$114,">0")=0,"",SUMIFS(Data!$I$6:$I$114,Data!$C$6:$C$114,I$5,Data!$D$6:$D$114,2)) -> 0.024016274 | J7: =IF(COUNTIFS(Data!$C$6:$C$114,J$5,Data!$D$6:$D$114,2,Data!$E$6:$E$114,">0")=0,"",SUMIFS(Data!$I$6:$I$114,Data!$C$6:$C$114,J$5,Data!$D$6:$D$114,2)) -> 0.028963191
B8: Mar | C8: =IF(COUNTIFS(Data!$C$6:$C$114,C$5,Data!$D$6:$D$114,3,Data!$E$6:$E$114,">0")=0,"",SUMIFS(Data!$I$6:$I$114,Data!$C$6:$C$114,C$5,Data!$D$6:$D$114,3)) -> 0.046795402 | D8: =IF(COUNTIFS(Data!$C$6:$C$114,D$5,Data!$D$6:$D$114,3,Data!$E$6:$E$114,">0")=0,"",SUMIFS(Data!$I$6:$I$114,Data!$C$6:$C$114,D$5,Data!$D$6:$D$114,3)) -> 0.033434686 | E8: =IF(COUNTIFS(Data!$C$6:$C$114,E$5,Data!$D$6:$D$114,3,Data!$E$6:$E$114,">0")=0,"",SUMIFS(Data!$I$6:$I$114,Data!$C$6:$C$114,E$5,Data!$D$6:$D$114,3)) -> 0.048108075 | F8: =IF(COUNTIFS(Data!$C$6:$C$114,F$5,Data!$D$6:$D$114,3,Data!$E$6:$E$114,">0")=0,"",SUMIFS(Data!$I$6:$I$114,Data!$C$6:$C$114,F$5,Data!$D$6:$D$114,3)) -> 0.067287978 | G8: =IF(COUNTIFS(Data!$C$6:$C$114,G$5,Data!$D$6:$D$114,3,Data!$E$6:$E$114,">0")=0,"",SUMIFS(Data!$I$6:$I$114,Data!$C$6:$C$114,G$5,Data!$D$6:$D$114,3)) -> 0.076752398 | H8: =IF(COUNTIFS(Data!$C$6:$C$114,H$5,Data!$D$6:$D$114,3,Data!$E$6:$E$114,">0")=0,"",SUMIFS(Data!$I$6:$I$114,Data!$C$6:$C$114,H$5,Data!$D$6:$D$114,3)) -> 0.110097 | I8: =IF(COUNTIFS(Data!$C$6:$C$114,I$5,Data!$D$6:$D$114,3,Data!$E$6:$E$114,">0")=0,"",SUMIFS(Data!$I$6:$I$114,Data!$C$6:$C$114,I$5,Data!$D$6:$D$114,3)) -> 0.037293353 | J8: =IF(COUNTIFS(Data!$C$6:$C$114,J$5,Data!$D$6:$D$114,3,Data!$E$6:$E$114,">0")=0,"",SUMIFS(Data!$I$6:$I$114,Data!$C$6:$C$114,J$5,Data!$D$6:$D$114,3)) -> 0.033826222
B9: Apr | C9: =IF(COUNTIFS(Data!$C$6:$C$114,C$5,Data!$D$6:$D$114,4,Data!$E$6:$E$114,">0")=0,"",SUMIFS(Data!$I$6:$I$114,Data!$C$6:$C$114,C$5,Data!$D$6:$D$114,4)) -> 0.034 | D9: =IF(COUNTIFS(Data!$C$6:$C$114,D$5,Data!$D$6:$D$114,4,Data!$E$6:$E$114,">0")=0,"",SUMIFS(Data!$I$6:$I$114,Data!$C$6:$C$114,D$5,Data!$D$6:$D$114,4)) -> 0.014965726 | E9: =IF(COUNTIFS(Data!$C$6:$C$114,E$5,Data!$D$6:$D$114,4,Data!$E$6:$E$114,">0")=0,"",SUMIFS(Data!$I$6:$I$114,Data!$C$6:$C$114,E$5,Data!$D$6:$D$114,4)) -> 0.040802935 | F9: =IF(COUNTIFS(Data!$C$6:$C$114,F$5,Data!$D$6:$D$114,4,Data!$E$6:$E$114,">0")=0,"",SUMIFS(Data!$I$6:$I$114,Data!$C$6:$C$114,F$5,Data!$D$6:$D$114,4)) -> 0.060473191 | G9: =IF(COUNTIFS(Data!$C$6:$C$114,G$5,Data!$D$6:$D$114,4,Data!$E$6:$E$114,">0")=0,"",SUMIFS(Data!$I$6:$I$114,Data!$C$6:$C$114,G$5,Data!$D$6:$D$114,4)) -> 0.084026899 | H9: =IF(COUNTIFS(Data!$C$6:$C$114,H$5,Data!$D$6:$D$114,4,Data!$E$6:$E$114,">0")=0,"",SUMIFS(Data!$I$6:$I$114,Data!$C$6:$C$114,H$5,Data!$D$6:$D$114,4)) -> 0.088319208 | I9: =IF(COUNTIFS(Data!$C$6:$C$114,I$5,Data!$D$6:$D$114,4,Data!$E$6:$E$114,">0")=0,"",SUMIFS(Data!$I$6:$I$114,Data!$C$6:$C$114,I$5,Data!$D$6:$D$114,4)) -> 0.027808358 | J9: =IF(COUNTIFS(Data!$C$6:$C$114,J$5,Data!$D$6:$D$114,4,Data!$E$6:$E$114,">0")=0,"",SUMIFS(Data!$I$6:$I$114,Data!$C$6:$C$114,J$5,Data!$D$6:$D$114,4)) -> 0.025821796
B10: May | C10: =IF(COUNTIFS(Data!$C$6:$C$114,C$5,Data!$D$6:$D$114,5,Data!$E$6:$E$114,">0")=0,"",SUMIFS(Data!$I$6:$I$114,Data!$C$6:$C$114,C$5,Data!$D$6:$D$114,5)) -> 0.031036203 | D10: =IF(COUNTIFS(Data!$C$6:$C$114,D$5,Data!$D$6:$D$114,5,Data!$E$6:$E$114,">0")=0,"",SUMIFS(Data!$I$6:$I$114,Data!$C$6:$C$114,D$5,Data!$D$6:$D$114,5)) -> 0.015427363 | E10: =IF(COUNTIFS(Data!$C$6:$C$114,E$5,Data!$D$6:$D$114,5,Data!$E$6:$E$114,">0")=0,"",SUMIFS(Data!$I$6:$I$114,Data!$C$6:$C$114,E$5,Data!$D$6:$D$114,5)) -> 0.033229781 | F10: =IF(COUNTIFS(Data!$C$6:$C$114,F$5,Data!$D$6:$D$114,5,Data!$E$6:$E$114,">0")=0,"",SUMIFS(Data!$I$6:$I$114,Data!$C$6:$C$114,F$5,Data!$D$6:$D$114,5)) -> 0.050502281 | G10: =IF(COUNTIFS(Data!$C$6:$C$114,G$5,Data!$D$6:$D$114,5,Data!$E$6:$E$114,">0")=0,"",SUMIFS(Data!$I$6:$I$114,Data!$C$6:$C$114,G$5,Data!$D$6:$D$114,5)) -> 0.07772753 | H10: =IF(COUNTIFS(Data!$C$6:$C$114,H$5,Data!$D$6:$D$114,5,Data!$E$6:$E$114,">0")=0,"",SUMIFS(Data!$I$6:$I$114,Data!$C$6:$C$114,H$5,Data!$D$6:$D$114,5)) -> 0.041760449 | I10: =IF(COUNTIFS(Data!$C$6:$C$114,I$5,Data!$D$6:$D$114,5,Data!$E$6:$E$114,">0")=0,"",SUMIFS(Data!$I$6:$I$114,Data!$C$6:$C$114,I$5,Data!$D$6:$D$114,5)) -> 0.015011086 | J10: =IF(COUNTIFS(Data!$C$6:$C$114,J$5,Data!$D$6:$D$114,5,Data!$E$6:$E$114,">0")=0,"",SUMIFS(Data!$I$6:$I$114,Data!$C$6:$C$114,J$5,Data!$D$6:$D$114,5)) -> 0.021499723
B11: Jun | C11: =IF(COUNTIFS(Data!$C$6:$C$114,C$5,Data!$D$6:$D$114,6,Data!$E$6:$E$114,">0")=0,"",SUMIFS(Data!$I$6:$I$114,Data!$C$6:$C$114,C$5,Data!$D$6:$D$114,6)) -> 0.027180054 | D11: =IF(COUNTIFS(Data!$C$6:$C$114,D$5,Data!$D$6:$D$114,6,Data!$E$6:$E$114,">0")=0,"",SUMIFS(Data!$I$6:$I$114,Data!$C$6:$C$114,D$5,Data!$D$6:$D$114,6)) -> 0.022435392 | E11: =IF(COUNTIFS(Data!$C$6:$C$114,E$5,Data!$D$6:$D$114,6,Data!$E$6:$E$114,">0")=0,"",SUMIFS(Data!$I$6:$I$114,Data!$C$6:$C$114,E$5,Data!$D$6:$D$114,6)) -> 0.03174548 | F11: =IF(COUNTIFS(Data!$C$6:$C$114,F$5,Data!$D$6:$D$114,6,Data!$E$6:$E$114,">0")=0,"",SUMIFS(Data!$I$6:$I$114,Data!$C$6:$C$114,F$5,Data!$D$6:$D$114,6)) -> 0.052952213 | G11: =IF(COUNTIFS(Data!$C$6:$C$114,G$5,Data!$D$6:$D$114,6,Data!$E$6:$E$114,">0")=0,"",SUMIFS(Data!$I$6:$I$114,Data!$C$6:$C$114,G$5,Data!$D$6:$D$114,6)) -> 0.05950832 | H11: =IF(COUNTIFS(Data!$C$6:$C$114,H$5,Data!$D$6:$D$114,6,Data!$E$6:$E$114,">0")=0,"",SUMIFS(Data!$I$6:$I$114,Data!$C$6:$C$114,H$5,Data!$D$6:$D$114,6)) -> 0.045773499 | I11: =IF(COUNTIFS(Data!$C$6:$C$114,I$5,Data!$D$6:$D$114,6,Data!$E$6:$E$114,">0")=0,"",SUMIFS(Data!$I$6:$I$114,Data!$C$6:$C$114,I$5,Data!$D$6:$D$114,6)) -> 0.016189249 | J11: =IF(COUNTIFS(Data!$C$6:$C$114,J$5,Data!$D$6:$D$114,6,Data!$E$6:$E$114,">0")=0,"",SUMIFS(Data!$I$6:$I$114,Data!$C$6:$C$114,J$5,Data!$D$6:$D$114,6)) -> 0.018868715
B12: Jul | C12: =IF(COUNTIFS(Data!$C$6:$C$114,C$5,Data!$D$6:$D$114,7,Data!$E$6:$E$114,">0")=0,"",SUMIFS(Data!$I$6:$I$114,Data!$C$6:$C$114,C$5,Data!$D$6:$D$114,7)) -> 0.021978655 | D12: =IF(COUNTIFS(Data!$C$6:$C$114,D$5,Data!$D$6:$D$114,7,Data!$E$6:$E$114,">0")=0,"",SUMIFS(Data!$I$6:$I$114,Data!$C$6:$C$114,D$5,Data!$D$6:$D$114,7)) -> 0.019341946 | E12: =IF(COUNTIFS(Data!$C$6:$C$114,E$5,Data!$D$6:$D$114,7,Data!$E$6:$E$114,">0")=0,"",SUMIFS(Data!$I$6:$I$114,Data!$C$6:$C$114,E$5,Data!$D$6:$D$114,7)) -> 0.029970333 | F12: =IF(COUNTIFS(Data!$C$6:$C$114,F$5,Data!$D$6:$D$114,7,Data!$E$6:$E$114,">0")=0,"",SUMIFS(Data!$I$6:$I$114,Data!$C$6:$C$114,F$5,Data!$D$6:$D$114,7)) -> 0.074061969 | G12: =IF(COUNTIFS(Data!$C$6:$C$114,G$5,Data!$D$6:$D$114,7,Data!$E$6:$E$114,">0")=0,"",SUMIFS(Data!$I$6:$I$114,Data!$C$6:$C$114,G$5,Data!$D$6:$D$114,7)) -> 0.063448509 | H12: =IF(COUNTIFS(Data!$C$6:$C$114,H$5,Data!$D$6:$D$114,7,Data!$E$6:$E$114,">0")=0,"",SUMIFS(Data!$I$6:$I$114,Data!$C$6:$C$114,H$5,Data!$D$6:$D$114,7)) -> 0.040309337 | I12: =IF(COUNTIFS(Data!$C$6:$C$114,I$5,Data!$D$6:$D$114,7,Data!$E$6:$E$114,">0")=0,"",SUMIFS(Data!$I$6:$I$114,Data!$C$6:$C$114,I$5,Data!$D$6:$D$114,7)) -> 0.019016838 | J12: =IF(COUNTIFS(Data!$C$6:$C$114,J$5,Data!$D$6:$D$114,7,Data!$E$6:$E$114,">0")=0,"",SUMIFS(Data!$I$6:$I$114,Data!$C$6:$C$114,J$5,Data!$D$6:$D$114,7))
B13: Aug | C13: =IF(COUNTIFS(Data!$C$6:$C$114,C$5,Data!$D$6:$D$114,8,Data!$E$6:$E$114,">0")=0,"",SUMIFS(Data!$I$6:$I$114,Data!$C$6:$C$114,C$5,Data!$D$6:$D$114,8)) -> 0.039539858 | D13: =IF(COUNTIFS(Data!$C$6:$C$114,D$5,Data!$D$6:$D$114,8,Data!$E$6:$E$114,">0")=0,"",SUMIFS(Data!$I$6:$I$114,Data!$C$6:$C$114,D$5,Data!$D$6:$D$114,8)) -> 0.027001104 | E13: =IF(COUNTIFS(Data!$C$6:$C$114,E$5,Data!$D$6:$D$114,8,Data!$E$6:$E$114,">0")=0,"",SUMIFS(Data!$I$6:$I$114,Data!$C$6:$C$114,E$5,Data!$D$6:$D$114,8)) -> 0.024684867 | F13: =IF(COUNTIFS(Data!$C$6:$C$114,F$5,Data!$D$6:$D$114,8,Data!$E$6:$E$114,">0")=0,"",SUMIFS(Data!$I$6:$I$114,Data!$C$6:$C$114,F$5,Data!$D$6:$D$114,8)) -> 0.069703356 | G13: =IF(COUNTIFS(Data!$C$6:$C$114,G$5,Data!$D$6:$D$114,8,Data!$E$6:$E$114,">0")=0,"",SUMIFS(Data!$I$6:$I$114,Data!$C$6:$C$114,G$5,Data!$D$6:$D$114,8)) -> 0.12441638 | H13: =IF(COUNTIFS(Data!$C$6:$C$114,H$5,Data!$D$6:$D$114,8,Data!$E$6:$E$114,">0")=0,"",SUMIFS(Data!$I$6:$I$114,Data!$C$6:$C$114,H$5,Data!$D$6:$D$114,8)) -> 0.041722733 | I13: =IF(COUNTIFS(Data!$C$6:$C$114,I$5,Data!$D$6:$D$114,8,Data!$E$6:$E$114,">0")=0,"",SUMIFS(Data!$I$6:$I$114,Data!$C$6:$C$114,I$5,Data!$D$6:$D$114,8)) -> 0.018757935 | J13: =IF(COUNTIFS(Data!$C$6:$C$114,J$5,Data!$D$6:$D$114,8,Data!$E$6:$E$114,">0")=0,"",SUMIFS(Data!$I$6:$I$114,Data!$C$6:$C$114,J$5,Data!$D$6:$D$114,8))
B14: Sep | C14: =IF(COUNTIFS(Data!$C$6:$C$114,C$5,Data!$D$6:$D$114,9,Data!$E$6:$E$114,">0")=0,"",SUMIFS(Data!$I$6:$I$114,Data!$C$6:$C$114,C$5,Data!$D$6:$D$114,9)) -> 0.058856623 | D14: =IF(COUNTIFS(Data!$C$6:$C$114,D$5,Data!$D$6:$D$114,9,Data!$E$6:$E$114,">0")=0,"",SUMIFS(Data!$I$6:$I$114,Data!$C$6:$C$114,D$5,Data!$D$6:$D$114,9)) -> 0.028355216 | E14: =IF(COUNTIFS(Data!$C$6:$C$114,E$5,Data!$D$6:$D$114,9,Data!$E$6:$E$114,">0")=0,"",SUMIFS(Data!$I$6:$I$114,Data!$C$6:$C$114,E$5,Data!$D$6:$D$114,9)) -> 0.03546788 | F14: =IF(COUNTIFS(Data!$C$6:$C$114,F$5,Data!$D$6:$D$114,9,Data!$E$6:$E$114,">0")=0,"",SUMIFS(Data!$I$6:$I$114,Data!$C$6:$C$114,F$5,Data!$D$6:$D$114,9)) -> 0.061655199 | G14: =IF(COUNTIFS(Data!$C$6:$C$114,G$5,Data!$D$6:$D$114,9,Data!$E$6:$E$114,">0")=0,"",SUMIFS(Data!$I$6:$I$114,Data!$C$6:$C$114,G$5,Data!$D$6:$D$114,9)) -> 0.1274975 | H14: =IF(COUNTIFS(Data!$C$6:$C$114,H$5,Data!$D$6:$D$114,9,Data!$E$6:$E$114,">0")=0,"",SUMIFS(Data!$I$6:$I$114,Data!$C$6:$C$114,H$5,Data!$D$6:$D$114,9)) -> 0.034692081 | I14: =IF(COUNTIFS(Data!$C$6:$C$114,I$5,Data!$D$6:$D$114,9,Data!$E$6:$E$114,">0")=0,"",SUMIFS(Data!$I$6:$I$114,Data!$C$6:$C$114,I$5,Data!$D$6:$D$114,9)) -> 0.020759603 | J14: =IF(COUNTIFS(Data!$C$6:$C$114,J$5,Data!$D$6:$D$114,9,Data!$E$6:$E$114,">0")=0,"",SUMIFS(Data!$I$6:$I$114,Data!$C$6:$C$114,J$5,Data!$D$6:$D$114,9))
B15: Oct | C15: =IF(COUNTIFS(Data!$C$6:$C$114,C$5,Data!$D$6:$D$114,10,Data!$E$6:$E$114,">0")=0,"",SUMIFS(Data!$I$6:$I$114,Data!$C$6:$C$114,C$5,Data!$D$6:$D$114,10)) -> 0.032934821 | D15: =IF(COUNTIFS(Data!$C$6:$C$114,D$5,Data!$D$6:$D$114,10,Data!$E$6:$E$114,">0")=0,"",SUMIFS(Data!$I$6:$I$114,Data!$C$6:$C$114,D$5,Data!$D$6:$D$114,10)) -> 0.037609698 | E15: =IF(COUNTIFS(Data!$C$6:$C$114,E$5,Data!$D$6:$D$114,10,Data!$E$6:$E$114,">0")=0,"",SUMIFS(Data!$I$6:$I$114,Data!$C$6:$C$114,E$5,Data!$D$6:$D$114,10)) -> 0.035162748 | F15: =IF(COUNTIFS(Data!$C$6:$C$114,F$5,Data!$D$6:$D$114,10,Data!$E$6:$E$114,">0")=0,"",SUMIFS(Data!$I$6:$I$114,Data!$C$6:$C$114,F$5,Data!$D$6:$D$114,10)) -> 0.063473501 | G15: =IF(COUNTIFS(Data!$C$6:$C$114,G$5,Data!$D$6:$D$114,10,Data!$E$6:$E$114,">0")=0,"",SUMIFS(Data!$I$6:$I$114,Data!$C$6:$C$114,G$5,Data!$D$6:$D$114,10)) -> 0.083017394 | H15: =IF(COUNTIFS(Data!$C$6:$C$114,H$5,Data!$D$6:$D$114,10,Data!$E$6:$E$114,">0")=0,"",SUMIFS(Data!$I$6:$I$114,Data!$C$6:$C$114,H$5,Data!$D$6:$D$114,10)) -> 0.02691738 | I15: =IF(COUNTIFS(Data!$C$6:$C$114,I$5,Data!$D$6:$D$114,10,Data!$E$6:$E$114,">0")=0,"",SUMIFS(Data!$I$6:$I$114,Data!$C$6:$C$114,I$5,Data!$D$6:$D$114,10)) -> 0.023419431 | J15: =IF(COUNTIFS(Data!$C$6:$C$114,J$5,Data!$D$6:$D$114,10,Data!$E$6:$E$114,">0")=0,"",SUMIFS(Data!$I$6:$I$114,Data!$C$6:$C$114,J$5,Data!$D$6:$D$114,10))
B16: Nov | C16: =IF(COUNTIFS(Data!$C$6:$C$114,C$5,Data!$D$6:$D$114,11,Data!$E$6:$E$114,">0")=0,"",SUMIFS(Data!$I$6:$I$114,Data!$C$6:$C$114,C$5,Data!$D$6:$D$114,11)) -> 0.042545373 | D16: =IF(COUNTIFS(Data!$C$6:$C$114,D$5,Data!$D$6:$D$114,11,Data!$E$6:$E$114,">0")=0,"",SUMIFS(Data!$I$6:$I$114,Data!$C$6:$C$114,D$5,Data!$D$6:$D$114,11)) -> 0.031597049 | E16: =IF(COUNTIFS(Data!$C$6:$C$114,E$5,Data!$D$6:$D$114,11,Data!$E$6:$E$114,">0")=0,"",SUMIFS(Data!$I$6:$I$114,Data!$C$6:$C$114,E$5,Data!$D$6:$D$114,11)) -> 0.025294646 | F16: =IF(COUNTIFS(Data!$C$6:$C$114,F$5,Data!$D$6:$D$114,11,Data!$E$6:$E$114,">0")=0,"",SUMIFS(Data!$I$6:$I$114,Data!$C$6:$C$114,F$5,Data!$D$6:$D$114,11)) -> 0.049161471 | G16: =IF(COUNTIFS(Data!$C$6:$C$114,G$5,Data!$D$6:$D$114,11,Data!$E$6:$E$114,">0")=0,"",SUMIFS(Data!$I$6:$I$114,Data!$C$6:$C$114,G$5,Data!$D$6:$D$114,11)) -> 0.1281069 | H16: =IF(COUNTIFS(Data!$C$6:$C$114,H$5,Data!$D$6:$D$114,11,Data!$E$6:$E$114,">0")=0,"",SUMIFS(Data!$I$6:$I$114,Data!$C$6:$C$114,H$5,Data!$D$6:$D$114,11)) -> 0.024265561 | I16: =IF(COUNTIFS(Data!$C$6:$C$114,I$5,Data!$D$6:$D$114,11,Data!$E$6:$E$114,">0")=0,"",SUMIFS(Data!$I$6:$I$114,Data!$C$6:$C$114,I$5,Data!$D$6:$D$114,11)) -> 0.024729197 | J16: =IF(COUNTIFS(Data!$C$6:$C$114,J$5,Data!$D$6:$D$114,11,Data!$E$6:$E$114,">0")=0,"",SUMIFS(Data!$I$6:$I$114,Data!$C$6:$C$114,J$5,Data!$D$6:$D$114,11))
B17: Dec | C17: =IF(COUNTIFS(Data!$C$6:$C$114,C$5,Data!$D$6:$D$114,12,Data!$E$6:$E$114,">0")=0,"",SUMIFS(Data!$I$6:$I$114,Data!$C$6:$C$114,C$5,Data!$D$6:$D$114,12)) -> 0.037437074 | D17: =IF(COUNTIFS(Data!$C$6:$C$114,D$5,Data!$D$6:$D$114,12,Data!$E$6:$E$114,">0")=0,"",SUMIFS(Data!$I$6:$I$114,Data!$C$6:$C$114,D$5,Data!$D$6:$D$114,12)) -> 0.040055673 | E17: =IF(COUNTIFS(Data!$C$6:$C$114,E$5,Data!$D$6:$D$114,12,Data!$E$6:$E$114,">0")=0,"",SUMIFS(Data!$I$6:$I$114,Data!$C$6:$C$114,E$5,Data!$D$6:$D$114,12)) -> 0.038399703 | F17: =IF(COUNTIFS(Data!$C$6:$C$114,F$5,Data!$D$6:$D$114,12,Data!$E$6:$E$114,">0")=0,"",SUMIFS(Data!$I$6:$I$114,Data!$C$6:$C$114,F$5,Data!$D$6:$D$114,12)) -> 0.051246078 | G17: =IF(COUNTIFS(Data!$C$6:$C$114,G$5,Data!$D$6:$D$114,12,Data!$E$6:$E$114,">0")=0,"",SUMIFS(Data!$I$6:$I$114,Data!$C$6:$C$114,G$5,Data!$D$6:$D$114,12)) -> 0.25465675 | H17: =IF(COUNTIFS(Data!$C$6:$C$114,H$5,Data!$D$6:$D$114,12,Data!$E$6:$E$114,">0")=0,"",SUMIFS(Data!$I$6:$I$114,Data!$C$6:$C$114,H$5,Data!$D$6:$D$114,12)) -> 0.027041041 | I17: =IF(COUNTIFS(Data!$C$6:$C$114,I$5,Data!$D$6:$D$114,12,Data!$E$6:$E$114,">0")=0,"",SUMIFS(Data!$I$6:$I$114,Data!$C$6:$C$114,I$5,Data!$D$6:$D$114,12)) -> 0.028452719 | J17: =IF(COUNTIFS(Data!$C$6:$C$114,J$5,Data!$D$6:$D$114,12,Data!$E$6:$E$114,">0")=0,"",SUMIFS(Data!$I$6:$I$114,Data!$C$6:$C$114,J$5,Data!$D$6:$D$114,12))
B19: Dec/Dec* | C19: =IFERROR(INDEX(Data!$E:$E,MATCH("2019-12",Data!$B:$B,0))/INDEX(Data!$E:$E,MATCH("2018-12",Data!$B:$B,0))-1,"") -> 0.53832402 | D19: =IFERROR(INDEX(Data!$E:$E,MATCH("2020-12",Data!$B:$B,0))/INDEX(Data!$E:$E,MATCH("2019-12",Data!$B:$B,0))-1,"") -> 0.36140588 | E19: =IFERROR(INDEX(Data!$E:$E,MATCH("2021-12",Data!$B:$B,0))/INDEX(Data!$E:$E,MATCH("2020-12",Data!$B:$B,0))-1,"") -> 0.50941634 | F19: =IFERROR(INDEX(Data!$E:$E,MATCH("2022-12",Data!$B:$B,0))/INDEX(Data!$E:$E,MATCH("2021-12",Data!$B:$B,0))-1,"") -> 0.94793182 | G19: =IFERROR(INDEX(Data!$E:$E,MATCH("2023-12",Data!$B:$B,0))/INDEX(Data!$E:$E,MATCH("2022-12",Data!$B:$B,0))-1,"") -> 2.1140764 | H19: =IFERROR(INDEX(Data!$E:$E,MATCH("2024-12",Data!$B:$B,0))/INDEX(Data!$E:$E,MATCH("2023-12",Data!$B:$B,0))-1,"") -> 1.1776363 | I19: =IFERROR(INDEX(Data!$E:$E,MATCH("2025-12",Data!$B:$B,0))/INDEX(Data!$E:$E,MATCH("2024-12",Data!$B:$B,0))-1,"") -> 0.31548761 | J19: =IFERROR(INDEX(Data!$E:$E,MATCH("2026-06",Data!$B:$B,0))/INDEX(Data!$E:$E,MATCH("2025-12",Data!$B:$B,0))-1,"") -> 0.16845926
B20: Avg month | C20: =IFERROR(AVERAGE(C6:C17),"") -> 0.036585224 | D20: =IFERROR(AVERAGE(D6:D17),"") -> 0.026074091 | E20: =IFERROR(AVERAGE(E6:E17),"") -> 0.034925255 | F20: =IFERROR(AVERAGE(F6:F17),"") -> 0.057184809 | G20: =IFERROR(AVERAGE(G6:G17),"") -> 0.10047621 | H20: =IFERROR(AVERAGE(H6:H17),"") -> 0.068287275 | I20: =IFERROR(AVERAGE(I6:I17),"") -> 0.023130377 | J20: =IFERROR(AVERAGE(J6:J17),"") -> 0.026299307
B21: * 2026 column is year-to-date through 2026-06, not a full year.

Sheet Seasonality Core
B2: Seasonality — IPC Núcleo (core): month-on-month % by calendar year
B3: Core strips out regulated tariffs and seasonal items — the cleanest read on underlying momentum.
B5: Month | C5: 2019 | D5: 2020 | E5: 2021 | F5: 2022 | G5: 2023 | H5: 2024 | I5: 2025 | J5: 2026
B6: Jan | C6: =IF(COUNTIFS(Data!$C$6:$C$114,C$5,Data!$D$6:$D$114,1,Data!$F$6:$F$114,">0")=0,"",SUMIFS(Data!$J$6:$J$114,Data!$C$6:$C$114,C$5,Data!$D$6:$D$114,1)) -> 0.030028066 | D6: =IF(COUNTIFS(Data!$C$6:$C$114,D$5,Data!$D$6:$D$114,1,Data!$F$6:$F$114,">0")=0,"",SUMIFS(Data!$J$6:$J$114,Data!$C$6:$C$114,D$5,Data!$D$6:$D$114,1)) -> 0.024409343 | E6: =IF(COUNTIFS(Data!$C$6:$C$114,E$5,Data!$D$6:$D$114,1,Data!$F$6:$F$114,">0")=0,"",SUMIFS(Data!$J$6:$J$114,Data!$C$6:$C$114,E$5,Data!$D$6:$D$114,1)) -> 0.039158779 | F6: =IF(COUNTIFS(Data!$C$6:$C$114,F$5,Data!$D$6:$D$114,1,Data!$F$6:$F$114,">0")=0,"",SUMIFS(Data!$J$6:$J$114,Data!$C$6:$C$114,F$5,Data!$D$6:$D$114,1)) -> 0.033020978 | G6: =IF(COUNTIFS(Data!$C$6:$C$114,G$5,Data!$D$6:$D$114,1,Data!$F$6:$F$114,">0")=0,"",SUMIFS(Data!$J$6:$J$114,Data!$C$6:$C$114,G$5,Data!$D$6:$D$114,1)) -> 0.053521433 | H6: =IF(COUNTIFS(Data!$C$6:$C$114,H$5,Data!$D$6:$D$114,1,Data!$F$6:$F$114,">0")=0,"",SUMIFS(Data!$J$6:$J$114,Data!$C$6:$C$114,H$5,Data!$D$6:$D$114,1)) -> 0.20216489 | I6: =IF(COUNTIFS(Data!$C$6:$C$114,I$5,Data!$D$6:$D$114,1,Data!$F$6:$F$114,">0")=0,"",SUMIFS(Data!$J$6:$J$114,Data!$C$6:$C$114,I$5,Data!$D$6:$D$114,1)) -> 0.023976894 | J6: =IF(COUNTIFS(Data!$C$6:$C$114,J$5,Data!$D$6:$D$114,1,Data!$F$6:$F$114,">0")=0,"",SUMIFS(Data!$J$6:$J$114,Data!$C$6:$C$114,J$5,Data!$D$6:$D$114,1)) -> 0.026303691
B7: Feb | C7: =IF(COUNTIFS(Data!$C$6:$C$114,C$5,Data!$D$6:$D$114,2,Data!$F$6:$F$114,">0")=0,"",SUMIFS(Data!$J$6:$J$114,Data!$C$6:$C$114,C$5,Data!$D$6:$D$114,2)) -> 0.038554987 | D7: =IF(COUNTIFS(Data!$C$6:$C$114,D$5,Data!$D$6:$D$114,2,Data!$F$6:$F$114,">0")=0,"",SUMIFS(Data!$J$6:$J$114,Data!$C$6:$C$114,D$5,Data!$D$6:$D$114,2)) -> 0.023817625 | E7: =IF(COUNTIFS(Data!$C$6:$C$114,E$5,Data!$D$6:$D$114,2,Data!$F$6:$F$114,">0")=0,"",SUMIFS(Data!$J$6:$J$114,Data!$C$6:$C$114,E$5,Data!$D$6:$D$114,2)) -> 0.040697185 | F7: =IF(COUNTIFS(Data!$C$6:$C$114,F$5,Data!$D$6:$D$114,2,Data!$F$6:$F$114,">0")=0,"",SUMIFS(Data!$J$6:$J$114,Data!$C$6:$C$114,F$5,Data!$D$6:$D$114,2)) -> 0.044507689 | G7: =IF(COUNTIFS(Data!$C$6:$C$114,G$5,Data!$D$6:$D$114,2,Data!$F$6:$F$114,">0")=0,"",SUMIFS(Data!$J$6:$J$114,Data!$C$6:$C$114,G$5,Data!$D$6:$D$114,2)) -> 0.076902164 | H7: =IF(COUNTIFS(Data!$C$6:$C$114,H$5,Data!$D$6:$D$114,2,Data!$F$6:$F$114,">0")=0,"",SUMIFS(Data!$J$6:$J$114,Data!$C$6:$C$114,H$5,Data!$D$6:$D$114,2)) -> 0.12290141 | I7: =IF(COUNTIFS(Data!$C$6:$C$114,I$5,Data!$D$6:$D$114,2,Data!$F$6:$F$114,">0")=0,"",SUMIFS(Data!$J$6:$J$114,Data!$C$6:$C$114,I$5,Data!$D$6:$D$114,2)) -> 0.029203528 | J7: =IF(COUNTIFS(Data!$C$6:$C$114,J$5,Data!$D$6:$D$114,2,Data!$F$6:$F$114,">0")=0,"",SUMIFS(Data!$J$6:$J$114,Data!$C$6:$C$114,J$5,Data!$D$6:$D$114,2)) -> 0.030753752
B8: Mar | C8: =IF(COUNTIFS(Data!$C$6:$C$114,C$5,Data!$D$6:$D$114,3,Data!$F$6:$F$114,">0")=0,"",SUMIFS(Data!$J$6:$J$114,Data!$C$6:$C$114,C$5,Data!$D$6:$D$114,3)) -> 0.045794532 | D8: =IF(COUNTIFS(Data!$C$6:$C$114,D$5,Data!$D$6:$D$114,3,Data!$F$6:$F$114,">0")=0,"",SUMIFS(Data!$J$6:$J$114,Data!$C$6:$C$114,D$5,Data!$D$6:$D$114,3)) -> 0.03120593 | E8: =IF(COUNTIFS(Data!$C$6:$C$114,E$5,Data!$D$6:$D$114,3,Data!$F$6:$F$114,">0")=0,"",SUMIFS(Data!$J$6:$J$114,Data!$C$6:$C$114,E$5,Data!$D$6:$D$114,3)) -> 0.045260548 | F8: =IF(COUNTIFS(Data!$C$6:$C$114,F$5,Data!$D$6:$D$114,3,Data!$F$6:$F$114,">0")=0,"",SUMIFS(Data!$J$6:$J$114,Data!$C$6:$C$114,F$5,Data!$D$6:$D$114,3)) -> 0.063964374 | G8: =IF(COUNTIFS(Data!$C$6:$C$114,G$5,Data!$D$6:$D$114,3,Data!$F$6:$F$114,">0")=0,"",SUMIFS(Data!$J$6:$J$114,Data!$C$6:$C$114,G$5,Data!$D$6:$D$114,3)) -> 0.07210126 | H8: =IF(COUNTIFS(Data!$C$6:$C$114,H$5,Data!$D$6:$D$114,3,Data!$F$6:$F$114,">0")=0,"",SUMIFS(Data!$J$6:$J$114,Data!$C$6:$C$114,H$5,Data!$D$6:$D$114,3)) -> 0.09412048 | I8: =IF(COUNTIFS(Data!$C$6:$C$114,I$5,Data!$D$6:$D$114,3,Data!$F$6:$F$114,">0")=0,"",SUMIFS(Data!$J$6:$J$114,Data!$C$6:$C$114,I$5,Data!$D$6:$D$114,3)) -> 0.031927902 | J8: =IF(COUNTIFS(Data!$C$6:$C$114,J$5,Data!$D$6:$D$114,3,Data!$F$6:$F$114,">0")=0,"",SUMIFS(Data!$J$6:$J$114,Data!$C$6:$C$114,J$5,Data!$D$6:$D$114,3)) -> 0.031889458
B9: Apr | C9: =IF(COUNTIFS(Data!$C$6:$C$114,C$5,Data!$D$6:$D$114,4,Data!$F$6:$F$114,">0")=0,"",SUMIFS(Data!$J$6:$J$114,Data!$C$6:$C$114,C$5,Data!$D$6:$D$114,4)) -> 0.037670643 | D9: =IF(COUNTIFS(Data!$C$6:$C$114,D$5,Data!$D$6:$D$114,4,Data!$F$6:$F$114,">0")=0,"",SUMIFS(Data!$J$6:$J$114,Data!$C$6:$C$114,D$5,Data!$D$6:$D$114,4)) -> 0.017157569 | E9: =IF(COUNTIFS(Data!$C$6:$C$114,E$5,Data!$D$6:$D$114,4,Data!$F$6:$F$114,">0")=0,"",SUMIFS(Data!$J$6:$J$114,Data!$C$6:$C$114,E$5,Data!$D$6:$D$114,4)) -> 0.045589514 | F9: =IF(COUNTIFS(Data!$C$6:$C$114,F$5,Data!$D$6:$D$114,4,Data!$F$6:$F$114,">0")=0,"",SUMIFS(Data!$J$6:$J$114,Data!$C$6:$C$114,F$5,Data!$D$6:$D$114,4)) -> 0.067089744 | G9: =IF(COUNTIFS(Data!$C$6:$C$114,G$5,Data!$D$6:$D$114,4,Data!$F$6:$F$114,">0")=0,"",SUMIFS(Data!$J$6:$J$114,Data!$C$6:$C$114,G$5,Data!$D$6:$D$114,4)) -> 0.08400631 | H9: =IF(COUNTIFS(Data!$C$6:$C$114,H$5,Data!$D$6:$D$114,4,Data!$F$6:$F$114,">0")=0,"",SUMIFS(Data!$J$6:$J$114,Data!$C$6:$C$114,H$5,Data!$D$6:$D$114,4)) -> 0.062984384 | I9: =IF(COUNTIFS(Data!$C$6:$C$114,I$5,Data!$D$6:$D$114,4,Data!$F$6:$F$114,">0")=0,"",SUMIFS(Data!$J$6:$J$114,Data!$C$6:$C$114,I$5,Data!$D$6:$D$114,4)) -> 0.03214716 | J9: =IF(COUNTIFS(Data!$C$6:$C$114,J$5,Data!$D$6:$D$114,4,Data!$F$6:$F$114,">0")=0,"",SUMIFS(Data!$J$6:$J$114,Data!$C$6:$C$114,J$5,Data!$D$6:$D$114,4)) -> 0.022864744
B10: May | C10: =IF(COUNTIFS(Data!$C$6:$C$114,C$5,Data!$D$6:$D$114,5,Data!$F$6:$F$114,">0")=0,"",SUMIFS(Data!$J$6:$J$114,Data!$C$6:$C$114,C$5,Data!$D$6:$D$114,5)) -> 0.031775307 | D10: =IF(COUNTIFS(Data!$C$6:$C$114,D$5,Data!$D$6:$D$114,5,Data!$F$6:$F$114,">0")=0,"",SUMIFS(Data!$J$6:$J$114,Data!$C$6:$C$114,D$5,Data!$D$6:$D$114,5)) -> 0.016056784 | E10: =IF(COUNTIFS(Data!$C$6:$C$114,E$5,Data!$D$6:$D$114,5,Data!$F$6:$F$114,">0")=0,"",SUMIFS(Data!$J$6:$J$114,Data!$C$6:$C$114,E$5,Data!$D$6:$D$114,5)) -> 0.034797507 | F10: =IF(COUNTIFS(Data!$C$6:$C$114,F$5,Data!$D$6:$D$114,5,Data!$F$6:$F$114,">0")=0,"",SUMIFS(Data!$J$6:$J$114,Data!$C$6:$C$114,F$5,Data!$D$6:$D$114,5)) -> 0.052018433 | G10: =IF(COUNTIFS(Data!$C$6:$C$114,G$5,Data!$D$6:$D$114,5,Data!$F$6:$F$114,">0")=0,"",SUMIFS(Data!$J$6:$J$114,Data!$C$6:$C$114,G$5,Data!$D$6:$D$114,5)) -> 0.078417897 | H10: =IF(COUNTIFS(Data!$C$6:$C$114,H$5,Data!$D$6:$D$114,5,Data!$F$6:$F$114,">0")=0,"",SUMIFS(Data!$J$6:$J$114,Data!$C$6:$C$114,H$5,Data!$D$6:$D$114,5)) -> 0.037346867 | I10: =IF(COUNTIFS(Data!$C$6:$C$114,I$5,Data!$D$6:$D$114,5,Data!$F$6:$F$114,">0")=0,"",SUMIFS(Data!$J$6:$J$114,Data!$C$6:$C$114,I$5,Data!$D$6:$D$114,5)) -> 0.02197265 | J10: =IF(COUNTIFS(Data!$C$6:$C$114,J$5,Data!$D$6:$D$114,5,Data!$F$6:$F$114,">0")=0,"",SUMIFS(Data!$J$6:$J$114,Data!$C$6:$C$114,J$5,Data!$D$6:$D$114,5)) -> 0.019034777
B11: Jun | C11: =IF(COUNTIFS(Data!$C$6:$C$114,C$5,Data!$D$6:$D$114,6,Data!$F$6:$F$114,">0")=0,"",SUMIFS(Data!$J$6:$J$114,Data!$C$6:$C$114,C$5,Data!$D$6:$D$114,6)) -> 0.027315926 | D11: =IF(COUNTIFS(Data!$C$6:$C$114,D$5,Data!$D$6:$D$114,6,Data!$F$6:$F$114,">0")=0,"",SUMIFS(Data!$J$6:$J$114,Data!$C$6:$C$114,D$5,Data!$D$6:$D$114,6)) -> 0.023151448 | E11: =IF(COUNTIFS(Data!$C$6:$C$114,E$5,Data!$D$6:$D$114,6,Data!$F$6:$F$114,">0")=0,"",SUMIFS(Data!$J$6:$J$114,Data!$C$6:$C$114,E$5,Data!$D$6:$D$114,6)) -> 0.036096552 | F11: =IF(COUNTIFS(Data!$C$6:$C$114,F$5,Data!$D$6:$D$114,6,Data!$F$6:$F$114,">0")=0,"",SUMIFS(Data!$J$6:$J$114,Data!$C$6:$C$114,F$5,Data!$D$6:$D$114,6)) -> 0.05083388 | G11: =IF(COUNTIFS(Data!$C$6:$C$114,G$5,Data!$D$6:$D$114,6,Data!$F$6:$F$114,">0")=0,"",SUMIFS(Data!$J$6:$J$114,Data!$C$6:$C$114,G$5,Data!$D$6:$D$114,6)) -> 0.064922131 | H11: =IF(COUNTIFS(Data!$C$6:$C$114,H$5,Data!$D$6:$D$114,6,Data!$F$6:$F$114,">0")=0,"",SUMIFS(Data!$J$6:$J$114,Data!$C$6:$C$114,H$5,Data!$D$6:$D$114,6)) -> 0.036511303 | I11: =IF(COUNTIFS(Data!$C$6:$C$114,I$5,Data!$D$6:$D$114,6,Data!$F$6:$F$114,">0")=0,"",SUMIFS(Data!$J$6:$J$114,Data!$C$6:$C$114,I$5,Data!$D$6:$D$114,6)) -> 0.01713735 | J11: =IF(COUNTIFS(Data!$C$6:$C$114,J$5,Data!$D$6:$D$114,6,Data!$F$6:$F$114,">0")=0,"",SUMIFS(Data!$J$6:$J$114,Data!$C$6:$C$114,J$5,Data!$D$6:$D$114,6)) -> 0.015695812
B12: Jul | C12: =IF(COUNTIFS(Data!$C$6:$C$114,C$5,Data!$D$6:$D$114,7,Data!$F$6:$F$114,">0")=0,"",SUMIFS(Data!$J$6:$J$114,Data!$C$6:$C$114,C$5,Data!$D$6:$D$114,7)) -> 0.021476797 | D12: =IF(COUNTIFS(Data!$C$6:$C$114,D$5,Data!$D$6:$D$114,7,Data!$F$6:$F$114,">0")=0,"",SUMIFS(Data!$J$6:$J$114,Data!$C$6:$C$114,D$5,Data!$D$6:$D$114,7)) -> 0.02533274 | E12: =IF(COUNTIFS(Data!$C$6:$C$114,E$5,Data!$D$6:$D$114,7,Data!$F$6:$F$114,">0")=0,"",SUMIFS(Data!$J$6:$J$114,Data!$C$6:$C$114,E$5,Data!$D$6:$D$114,7)) -> 0.031335013 | F12: =IF(COUNTIFS(Data!$C$6:$C$114,F$5,Data!$D$6:$D$114,7,Data!$F$6:$F$114,">0")=0,"",SUMIFS(Data!$J$6:$J$114,Data!$C$6:$C$114,F$5,Data!$D$6:$D$114,7)) -> 0.073288006 | G12: =IF(COUNTIFS(Data!$C$6:$C$114,G$5,Data!$D$6:$D$114,7,Data!$F$6:$F$114,">0")=0,"",SUMIFS(Data!$J$6:$J$114,Data!$C$6:$C$114,G$5,Data!$D$6:$D$114,7)) -> 0.064975294 | H12: =IF(COUNTIFS(Data!$C$6:$C$114,H$5,Data!$D$6:$D$114,7,Data!$F$6:$F$114,">0")=0,"",SUMIFS(Data!$J$6:$J$114,Data!$C$6:$C$114,H$5,Data!$D$6:$D$114,7)) -> 0.037855879 | I12: =IF(COUNTIFS(Data!$C$6:$C$114,I$5,Data!$D$6:$D$114,7,Data!$F$6:$F$114,">0")=0,"",SUMIFS(Data!$J$6:$J$114,Data!$C$6:$C$114,I$5,Data!$D$6:$D$114,7)) -> 0.014791483 | J12: =IF(COUNTIFS(Data!$C$6:$C$114,J$5,Data!$D$6:$D$114,7,Data!$F$6:$F$114,">0")=0,"",SUMIFS(Data!$J$6:$J$114,Data!$C$6:$C$114,J$5,Data!$D$6:$D$114,7))
B13: Aug | C13: =IF(COUNTIFS(Data!$C$6:$C$114,C$5,Data!$D$6:$D$114,8,Data!$F$6:$F$114,">0")=0,"",SUMIFS(Data!$J$6:$J$114,Data!$C$6:$C$114,C$5,Data!$D$6:$D$114,8)) -> 0.046378608 | D13: =IF(COUNTIFS(Data!$C$6:$C$114,D$5,Data!$D$6:$D$114,8,Data!$F$6:$F$114,">0")=0,"",SUMIFS(Data!$J$6:$J$114,Data!$C$6:$C$114,D$5,Data!$D$6:$D$114,8)) -> 0.030332744 | E13: =IF(COUNTIFS(Data!$C$6:$C$114,E$5,Data!$D$6:$D$114,8,Data!$F$6:$F$114,">0")=0,"",SUMIFS(Data!$J$6:$J$114,Data!$C$6:$C$114,E$5,Data!$D$6:$D$114,8)) -> 0.031321875 | F13: =IF(COUNTIFS(Data!$C$6:$C$114,F$5,Data!$D$6:$D$114,8,Data!$F$6:$F$114,">0")=0,"",SUMIFS(Data!$J$6:$J$114,Data!$C$6:$C$114,F$5,Data!$D$6:$D$114,8)) -> 0.068015911 | G13: =IF(COUNTIFS(Data!$C$6:$C$114,G$5,Data!$D$6:$D$114,8,Data!$F$6:$F$114,">0")=0,"",SUMIFS(Data!$J$6:$J$114,Data!$C$6:$C$114,G$5,Data!$D$6:$D$114,8)) -> 0.13786682 | H13: =IF(COUNTIFS(Data!$C$6:$C$114,H$5,Data!$D$6:$D$114,8,Data!$F$6:$F$114,">0")=0,"",SUMIFS(Data!$J$6:$J$114,Data!$C$6:$C$114,H$5,Data!$D$6:$D$114,8)) -> 0.041202856 | I13: =IF(COUNTIFS(Data!$C$6:$C$114,I$5,Data!$D$6:$D$114,8,Data!$F$6:$F$114,">0")=0,"",SUMIFS(Data!$J$6:$J$114,Data!$C$6:$C$114,I$5,Data!$D$6:$D$114,8)) -> 0.020449004 | J13: =IF(COUNTIFS(Data!$C$6:$C$114,J$5,Data!$D$6:$D$114,8,Data!$F$6:$F$114,">0")=0,"",SUMIFS(Data!$J$6:$J$114,Data!$C$6:$C$114,J$5,Data!$D$6:$D$114,8))
B14: Sep | C14: =IF(COUNTIFS(Data!$C$6:$C$114,C$5,Data!$D$6:$D$114,9,Data!$F$6:$F$114,">0")=0,"",SUMIFS(Data!$J$6:$J$114,Data!$C$6:$C$114,C$5,Data!$D$6:$D$114,9)) -> 0.064377642 | D14: =IF(COUNTIFS(Data!$C$6:$C$114,D$5,Data!$D$6:$D$114,9,Data!$F$6:$F$114,">0")=0,"",SUMIFS(Data!$J$6:$J$114,Data!$C$6:$C$114,D$5,Data!$D$6:$D$114,9)) -> 0.023168947 | E14: =IF(COUNTIFS(Data!$C$6:$C$114,E$5,Data!$D$6:$D$114,9,Data!$F$6:$F$114,">0")=0,"",SUMIFS(Data!$J$6:$J$114,Data!$C$6:$C$114,E$5,Data!$D$6:$D$114,9)) -> 0.032621256 | F14: =IF(COUNTIFS(Data!$C$6:$C$114,F$5,Data!$D$6:$D$114,9,Data!$F$6:$F$114,">0")=0,"",SUMIFS(Data!$J$6:$J$114,Data!$C$6:$C$114,F$5,Data!$D$6:$D$114,9)) -> 0.055127813 | G14: =IF(COUNTIFS(Data!$C$6:$C$114,G$5,Data!$D$6:$D$114,9,Data!$F$6:$F$114,">0")=0,"",SUMIFS(Data!$J$6:$J$114,Data!$C$6:$C$114,G$5,Data!$D$6:$D$114,9)) -> 0.13428211 | H14: =IF(COUNTIFS(Data!$C$6:$C$114,H$5,Data!$D$6:$D$114,9,Data!$F$6:$F$114,">0")=0,"",SUMIFS(Data!$J$6:$J$114,Data!$C$6:$C$114,H$5,Data!$D$6:$D$114,9)) -> 0.032622058 | I14: =IF(COUNTIFS(Data!$C$6:$C$114,I$5,Data!$D$6:$D$114,9,Data!$F$6:$F$114,">0")=0,"",SUMIFS(Data!$J$6:$J$114,Data!$C$6:$C$114,I$5,Data!$D$6:$D$114,9)) -> 0.018958762 | J14: =IF(COUNTIFS(Data!$C$6:$C$114,J$5,Data!$D$6:$D$114,9,Data!$F$6:$F$114,">0")=0,"",SUMIFS(Data!$J$6:$J$114,Data!$C$6:$C$114,J$5,Data!$D$6:$D$114,9))
B15: Oct | C15: =IF(COUNTIFS(Data!$C$6:$C$114,C$5,Data!$D$6:$D$114,10,Data!$F$6:$F$114,">0")=0,"",SUMIFS(Data!$J$6:$J$114,Data!$C$6:$C$114,C$5,Data!$D$6:$D$114,10)) -> 0.038046676 | D15: =IF(COUNTIFS(Data!$C$6:$C$114,D$5,Data!$D$6:$D$114,10,Data!$F$6:$F$114,">0")=0,"",SUMIFS(Data!$J$6:$J$114,Data!$C$6:$C$114,D$5,Data!$D$6:$D$114,10)) -> 0.034596016 | E15: =IF(COUNTIFS(Data!$C$6:$C$114,E$5,Data!$D$6:$D$114,10,Data!$F$6:$F$114,">0")=0,"",SUMIFS(Data!$J$6:$J$114,Data!$C$6:$C$114,E$5,Data!$D$6:$D$114,10)) -> 0.032010124 | F15: =IF(COUNTIFS(Data!$C$6:$C$114,F$5,Data!$D$6:$D$114,10,Data!$F$6:$F$114,">0")=0,"",SUMIFS(Data!$J$6:$J$114,Data!$C$6:$C$114,F$5,Data!$D$6:$D$114,10)) -> 0.05549158 | G15: =IF(COUNTIFS(Data!$C$6:$C$114,G$5,Data!$D$6:$D$114,10,Data!$F$6:$F$114,">0")=0,"",SUMIFS(Data!$J$6:$J$114,Data!$C$6:$C$114,G$5,Data!$D$6:$D$114,10)) -> 0.088110343 | H15: =IF(COUNTIFS(Data!$C$6:$C$114,H$5,Data!$D$6:$D$114,10,Data!$F$6:$F$114,">0")=0,"",SUMIFS(Data!$J$6:$J$114,Data!$C$6:$C$114,H$5,Data!$D$6:$D$114,10)) -> 0.029178168 | I15: =IF(COUNTIFS(Data!$C$6:$C$114,I$5,Data!$D$6:$D$114,10,Data!$F$6:$F$114,">0")=0,"",SUMIFS(Data!$J$6:$J$114,Data!$C$6:$C$114,I$5,Data!$D$6:$D$114,10)) -> 0.022167187 | J15: =IF(COUNTIFS(Data!$C$6:$C$114,J$5,Data!$D$6:$D$114,10,Data!$F$6:$F$114,">0")=0,"",SUMIFS(Data!$J$6:$J$114,Data!$C$6:$C$114,J$5,Data!$D$6:$D$114,10))
B16: Nov | C16: =IF(COUNTIFS(Data!$C$6:$C$114,C$5,Data!$D$6:$D$114,11,Data!$F$6:$F$114,">0")=0,"",SUMIFS(Data!$J$6:$J$114,Data!$C$6:$C$114,C$5,Data!$D$6:$D$114,11)) -> 0.039781271 | D16: =IF(COUNTIFS(Data!$C$6:$C$114,D$5,Data!$D$6:$D$114,11,Data!$F$6:$F$114,">0")=0,"",SUMIFS(Data!$J$6:$J$114,Data!$C$6:$C$114,D$5,Data!$D$6:$D$114,11)) -> 0.03937669 | E16: =IF(COUNTIFS(Data!$C$6:$C$114,E$5,Data!$D$6:$D$114,11,Data!$F$6:$F$114,">0")=0,"",SUMIFS(Data!$J$6:$J$114,Data!$C$6:$C$114,E$5,Data!$D$6:$D$114,11)) -> 0.032527366 | F16: =IF(COUNTIFS(Data!$C$6:$C$114,F$5,Data!$D$6:$D$114,11,Data!$F$6:$F$114,">0")=0,"",SUMIFS(Data!$J$6:$J$114,Data!$C$6:$C$114,F$5,Data!$D$6:$D$114,11)) -> 0.047558697 | G16: =IF(COUNTIFS(Data!$C$6:$C$114,G$5,Data!$D$6:$D$114,11,Data!$F$6:$F$114,">0")=0,"",SUMIFS(Data!$J$6:$J$114,Data!$C$6:$C$114,G$5,Data!$D$6:$D$114,11)) -> 0.13403616 | H16: =IF(COUNTIFS(Data!$C$6:$C$114,H$5,Data!$D$6:$D$114,11,Data!$F$6:$F$114,">0")=0,"",SUMIFS(Data!$J$6:$J$114,Data!$C$6:$C$114,H$5,Data!$D$6:$D$114,11)) -> 0.027148339 | I16: =IF(COUNTIFS(Data!$C$6:$C$114,I$5,Data!$D$6:$D$114,11,Data!$F$6:$F$114,">0")=0,"",SUMIFS(Data!$J$6:$J$114,Data!$C$6:$C$114,I$5,Data!$D$6:$D$114,11)) -> 0.026389974 | J16: =IF(COUNTIFS(Data!$C$6:$C$114,J$5,Data!$D$6:$D$114,11,Data!$F$6:$F$114,">0")=0,"",SUMIFS(Data!$J$6:$J$114,Data!$C$6:$C$114,J$5,Data!$D$6:$D$114,11))
B17: Dec | C17: =IF(COUNTIFS(Data!$C$6:$C$114,C$5,Data!$D$6:$D$114,12,Data!$F$6:$F$114,">0")=0,"",SUMIFS(Data!$J$6:$J$114,Data!$C$6:$C$114,C$5,Data!$D$6:$D$114,12)) -> 0.036823011 | D17: =IF(COUNTIFS(Data!$C$6:$C$114,D$5,Data!$D$6:$D$114,12,Data!$F$6:$F$114,">0")=0,"",SUMIFS(Data!$J$6:$J$114,Data!$C$6:$C$114,D$5,Data!$D$6:$D$114,12)) -> 0.04871001 | E17: =IF(COUNTIFS(Data!$C$6:$C$114,E$5,Data!$D$6:$D$114,12,Data!$F$6:$F$114,">0")=0,"",SUMIFS(Data!$J$6:$J$114,Data!$C$6:$C$114,E$5,Data!$D$6:$D$114,12)) -> 0.044232388 | F17: =IF(COUNTIFS(Data!$C$6:$C$114,F$5,Data!$D$6:$D$114,12,Data!$F$6:$F$114,">0")=0,"",SUMIFS(Data!$J$6:$J$114,Data!$C$6:$C$114,F$5,Data!$D$6:$D$114,12)) -> 0.052510803 | G17: =IF(COUNTIFS(Data!$C$6:$C$114,G$5,Data!$D$6:$D$114,12,Data!$F$6:$F$114,">0")=0,"",SUMIFS(Data!$J$6:$J$114,Data!$C$6:$C$114,G$5,Data!$D$6:$D$114,12)) -> 0.2825876 | H17: =IF(COUNTIFS(Data!$C$6:$C$114,H$5,Data!$D$6:$D$114,12,Data!$F$6:$F$114,">0")=0,"",SUMIFS(Data!$J$6:$J$114,Data!$C$6:$C$114,H$5,Data!$D$6:$D$114,12)) -> 0.031972815 | I17: =IF(COUNTIFS(Data!$C$6:$C$114,I$5,Data!$D$6:$D$114,12,Data!$F$6:$F$114,">0")=0,"",SUMIFS(Data!$J$6:$J$114,Data!$C$6:$C$114,I$5,Data!$D$6:$D$114,12)) -> 0.030338921 | J17: =IF(COUNTIFS(Data!$C$6:$C$114,J$5,Data!$D$6:$D$114,12,Data!$F$6:$F$114,">0")=0,"",SUMIFS(Data!$J$6:$J$114,Data!$C$6:$C$114,J$5,Data!$D$6:$D$114,12))
B19: Dec/Dec* | C19: =IFERROR(INDEX(Data!$F:$F,MATCH("2019-12",Data!$B:$B,0))/INDEX(Data!$F:$F,MATCH("2018-12",Data!$B:$B,0))-1,"") -> 0.56657144 | D19: =IFERROR(INDEX(Data!$F:$F,MATCH("2020-12",Data!$B:$B,0))/INDEX(Data!$F:$F,MATCH("2019-12",Data!$B:$B,0))-1,"") -> 0.39404418 | E19: =IFERROR(INDEX(Data!$F:$F,MATCH("2021-12",Data!$B:$B,0))/INDEX(Data!$F:$F,MATCH("2020-12",Data!$B:$B,0))-1,"") -> 0.54869327 | F19: =IFERROR(INDEX(Data!$F:$F,MATCH("2022-12",Data!$B:$B,0))/INDEX(Data!$F:$F,MATCH("2021-12",Data!$B:$B,0))-1,"") -> 0.9061848 | G19: =IFERROR(INDEX(Data!$F:$F,MATCH("2023-12",Data!$B:$B,0))/INDEX(Data!$F:$F,MATCH("2022-12",Data!$B:$B,0))-1,"") -> 2.294057 | H19: =IFERROR(INDEX(Data!$F:$F,MATCH("2024-12",Data!$B:$B,0))/INDEX(Data!$F:$F,MATCH("2023-12",Data!$B:$B,0))-1,"") -> 1.0549513 | I19: =IFERROR(INDEX(Data!$F:$F,MATCH("2025-12",Data!$B:$B,0))/INDEX(Data!$F:$F,MATCH("2024-12",Data!$B:$B,0))-1,"") -> 0.33088474 | J19: =IFERROR(INDEX(Data!$F:$F,MATCH("2026-06",Data!$B:$B,0))/INDEX(Data!$F:$F,MATCH("2025-12",Data!$B:$B,0))-1,"") -> 0.15567274
B20: Avg month | C20: =IFERROR(AVERAGE(C6:C17),"") -> 0.038168622 | D20: =IFERROR(AVERAGE(D6:D17),"") -> 0.028109654 | E20: =IFERROR(AVERAGE(E6:E17),"") -> 0.037137342 | F20: =IFERROR(AVERAGE(F6:F17),"") -> 0.055285659 | G20: =IFERROR(AVERAGE(G6:G17),"") -> 0.10597746 | H20: =IFERROR(AVERAGE(H6:H17),"") -> 0.063000787 | I20: =IFERROR(AVERAGE(I6:I17),"") -> 0.024121735 | J20: =IFERROR(AVERAGE(J6:J17),"") -> 0.024423706
B21: * 2026 column is year-to-date through 2026-06, not a full year.

Sheet Heatmap
B2: Monthly inflation heatmap — year x month
B3: Green = cool, red = hot, scaled within each block. Headline on top, core below.
B5: Headline (IPC Nivel General)
B6: Year | C6: Jan | D6: Feb | E6: Mar | F6: Apr | G6: May | H6: Jun | I6: Jul | J6: Aug | K6: Sep | L6: Oct | M6: Nov | N6: Dec | O6: Dec/Dec
B7: 2019 | C7: ='Seasonality Headline'!C6 -> 0.029062409 | D7: ='Seasonality Headline'!C7 -> 0.037656222 | E7: ='Seasonality Headline'!C8 -> 0.046795402 | F7: ='Seasonality Headline'!C9 -> 0.034 | G7: ='Seasonality Headline'!C10 -> 0.031036203 | H7: ='Seasonality Headline'!C11 -> 0.027180054 | I7: ='Seasonality Headline'!C12 -> 0.021978655 | J7: ='Seasonality Headline'!C13 -> 0.039539858 | K7: ='Seasonality Headline'!C14 -> 0.058856623 | L7: ='Seasonality Headline'!C15 -> 0.032934821 | M7: ='Seasonality Headline'!C16 -> 0.042545373 | N7: ='Seasonality Headline'!C17 -> 0.037437074 | O7: ='Seasonality Headline'!C19 -> 0.53832402
B8: 2020 | C8: ='Seasonality Headline'!D6 -> 0.022528949 | D8: ='Seasonality Headline'!D7 -> 0.020136294 | E8: ='Seasonality Headline'!D8 -> 0.033434686 | F8: ='Seasonality Headline'!D9 -> 0.014965726 | G8: ='Seasonality Headline'!D10 -> 0.015427363 | H8: ='Seasonality Headline'!D11 -> 0.022435392 | I8: ='Seasonality Headline'!D12 -> 0.019341946 | J8: ='Seasonality Headline'!D13 -> 0.027001104 | K8: ='Seasonality Headline'!D14 -> 0.028355216 | L8: ='Seasonality Headline'!D15 -> 0.037609698 | M8: ='Seasonality Headline'!D16 -> 0.031597049 | N8: ='Seasonality Headline'!D17 -> 0.040055673 | O8: ='Seasonality Headline'!D19 -> 0.36140588
B9: 2021 | C9: ='Seasonality Headline'!E6 -> 0.040490294 | D9: ='Seasonality Headline'!E7 -> 0.035746317 | E9: ='Seasonality Headline'!E8 -> 0.048108075 | F9: ='Seasonality Headline'!E9 -> 0.040802935 | G9: ='Seasonality Headline'!E10 -> 0.033229781 | H9: ='Seasonality Headline'!E11 -> 0.03174548 | I9: ='Seasonality Headline'!E12 -> 0.029970333 | J9: ='Seasonality Headline'!E13 -> 0.024684867 | K9: ='Seasonality Headline'!E14 -> 0.03546788 | L9: ='Seasonality Headline'!E15 -> 0.035162748 | M9: ='Seasonality Headline'!E16 -> 0.025294646 | N9: ='Seasonality Headline'!E17 -> 0.038399703 | O9: ='Seasonality Headline'!E19 -> 0.50941634
B10: 2022 | C10: ='Seasonality Headline'!F6 -> 0.038756819 | D10: ='Seasonality Headline'!F7 -> 0.046943656 | E10: ='Seasonality Headline'!F8 -> 0.067287978 | F10: ='Seasonality Headline'!F9 -> 0.060473191 | G10: ='Seasonality Headline'!F10 -> 0.050502281 | H10: ='Seasonality Headline'!F11 -> 0.052952213 | I10: ='Seasonality Headline'!F12 -> 0.074061969 | J10: ='Seasonality Headline'!F13 -> 0.069703356 | K10: ='Seasonality Headline'!F14 -> 0.061655199 | L10: ='Seasonality Headline'!F15 -> 0.063473501 | M10: ='Seasonality Headline'!F16 -> 0.049161471 | N10: ='Seasonality Headline'!F17 -> 0.051246078 | O10: ='Seasonality Headline'!F19 -> 0.94793182
B11: 2023 | C11: ='Seasonality Headline'!G6 -> 0.060278736 | D11: ='Seasonality Headline'!G7 -> 0.066277217 | E11: ='Seasonality Headline'!G8 -> 0.076752398 | F11: ='Seasonality Headline'!G9 -> 0.084026899 | G11: ='Seasonality Headline'!G10 -> 0.07772753 | H11: ='Seasonality Headline'!G11 -> 0.05950832 | I11: ='Seasonality Headline'!G12 -> 0.063448509 | J11: ='Seasonality Headline'!G13 -> 0.12441638 | K11: ='Seasonality Headline'!G14 -> 0.1274975 | L11: ='Seasonality Headline'!G15 -> 0.083017394 | M11: ='Seasonality Headline'!G16 -> 0.1281069 | N11: ='Seasonality Headline'!G17 -> 0.25465675 | O11: ='Seasonality Headline'!G19 -> 2.1140764
B12: 2024 | C12: ='Seasonality Headline'!H6 -> 0.20614225 | D12: ='Seasonality Headline'!H7 -> 0.13240676 | E12: ='Seasonality Headline'!H8 -> 0.110097 | F12: ='Seasonality Headline'!H9 -> 0.088319208 | G12: ='Seasonality Headline'!H10 -> 0.041760449 | H12: ='Seasonality Headline'!H11 -> 0.045773499 | I12: ='Seasonality Headline'!H12 -> 0.040309337 | J12: ='Seasonality Headline'!H13 -> 0.041722733 | K12: ='Seasonality Headline'!H14 -> 0.034692081 | L12: ='Seasonality Headline'!H15 -> 0.02691738 | M12: ='Seasonality Headline'!H16 -> 0.024265561 | N12: ='Seasonality Headline'!H17 -> 0.027041041 | O12: ='Seasonality Headline'!H19 -> 1.1776363
B13: 2025 | C13: ='Seasonality Headline'!I6 -> 0.02211048 | D13: ='Seasonality Headline'!I7 -> 0.024016274 | E13: ='Seasonality Headline'!I8 -> 0.037293353 | F13: ='Seasonality Headline'!I9 -> 0.027808358 | G13: ='Seasonality Headline'!I10 -> 0.015011086 | H13: ='Seasonality Headline'!I11 -> 0.016189249 | I13: ='Seasonality Headline'!I12 -> 0.019016838 | J13: ='Seasonality Headline'!I13 -> 0.018757935 | K13: ='Seasonality Headline'!I14 -> 0.020759603 | L13: ='Seasonality Headline'!I15 -> 0.023419431 | M13: ='Seasonality Headline'!I16 -> 0.024729197 | N13: ='Seasonality Headline'!I17 -> 0.028452719 | O13: ='Seasonality Headline'!I19 -> 0.31548761
B14: 2026 | C14: ='Seasonality Headline'!J6 -> 0.028816194 | D14: ='Seasonality Headline'!J7 -> 0.028963191 | E14: ='Seasonality Headline'!J8 -> 0.033826222 | F14: ='Seasonality Headline'!J9 -> 0.025821796 | G14: ='Seasonality Headline'!J10 -> 0.021499723 | H14: ='Seasonality Headline'!J11 -> 0.018868715 | I14: ='Seasonality Headline'!J12 | J14: ='Seasonality Headline'!J13 | K14: ='Seasonality Headline'!J14 | L14: ='Seasonality Headline'!J15 | M14: ='Seasonality Headline'!J16 | N14: ='Seasonality Headline'!J17 | O14: ='Seasonality Headline'!J19 -> 0.16845926
B17: Core (IPC Núcleo)
B18: Year | C18: Jan | D18: Feb | E18: Mar | F18: Apr | G18: May | H18: Jun | I18: Jul | J18: Aug | K18: Sep | L18: Oct | M18: Nov | N18: Dec | O18: Dec/Dec
B19: 2019 | C19: ='Seasonality Core'!C6 -> 0.030028066 | D19: ='Seasonality Core'!C7 -> 0.038554987 | E19: ='Seasonality Core'!C8 -> 0.045794532 | F19: ='Seasonality Core'!C9 -> 0.037670643 | G19: ='Seasonality Core'!C10 -> 0.031775307 | H19: ='Seasonality Core'!C11 -> 0.027315926 | I19: ='Seasonality Core'!C12 -> 0.021476797 | J19: ='Seasonality Core'!C13 -> 0.046378608 | K19: ='Seasonality Core'!C14 -> 0.064377642 | L19: ='Seasonality Core'!C15 -> 0.038046676 | M19: ='Seasonality Core'!C16 -> 0.039781271 | N19: ='Seasonality Core'!C17 -> 0.036823011 | O19: ='Seasonality Core'!C19 -> 0.56657144
B20: 2020 | C20: ='Seasonality Core'!D6 -> 0.024409343 | D20: ='Seasonality Core'!D7 -> 0.023817625 | E20: ='Seasonality Core'!D8 -> 0.03120593 | F20: ='Seasonality Core'!D9 -> 0.017157569 | G20: ='Seasonality Core'!D10 -> 0.016056784 | H20: ='Seasonality Core'!D11 -> 0.023151448 | I20: ='Seasonality Core'!D12 -> 0.02533274 | J20: ='Seasonality Core'!D13 -> 0.030332744 | K20: ='Seasonality Core'!D14 -> 0.023168947 | L20: ='Seasonality Core'!D15 -> 0.034596016 | M20: ='Seasonality Core'!D16 -> 0.03937669 | N20: ='Seasonality Core'!D17 -> 0.04871001 | O20: ='Seasonality Core'!D19 -> 0.39404418
B21: 2021 | C21: ='Seasonality Core'!E6 -> 0.039158779 | D21: ='Seasonality Core'!E7 -> 0.040697185 | E21: ='Seasonality Core'!E8 -> 0.045260548 | F21: ='Seasonality Core'!E9 -> 0.045589514 | G21: ='Seasonality Core'!E10 -> 0.034797507 | H21: ='Seasonality Core'!E11 -> 0.036096552 | I21: ='Seasonality Core'!E12 -> 0.031335013 | J21: ='Seasonality Core'!E13 -> 0.031321875 | K21: ='Seasonality Core'!E14 -> 0.032621256 | L21: ='Seasonality Core'!E15 -> 0.032010124 | M21: ='Seasonality Core'!E16 -> 0.032527366 | N21: ='Seasonality Core'!E17 -> 0.044232388 | O21: ='Seasonality Core'!E19 -> 0.54869327
B22: 2022 | C22: ='Seasonality Core'!F6 -> 0.033020978 | D22: ='Seasonality Core'!F7 -> 0.044507689 | E22: ='Seasonality Core'!F8 -> 0.063964374 | F22: ='Seasonality Core'!F9 -> 0.067089744 | G22: ='Seasonality Core'!F10 -> 0.052018433 | H22: ='Seasonality Core'!F11 -> 0.05083388 | I22: ='Seasonality Core'!F12 -> 0.073288006 | J22: ='Seasonality Core'!F13 -> 0.068015911 | K22: ='Seasonality Core'!F14 -> 0.055127813 | L22: ='Seasonality Core'!F15 -> 0.05549158 | M22: ='Seasonality Core'!F16 -> 0.047558697 | N22: ='Seasonality Core'!F17 -> 0.052510803 | O22: ='Seasonality Core'!F19 -> 0.9061848
B23: 2023 | C23: ='Seasonality Core'!G6 -> 0.053521433 | D23: ='Seasonality Core'!G7 -> 0.076902164 | E23: ='Seasonality Core'!G8 -> 0.07210126 | F23: ='Seasonality Core'!G9 -> 0.08400631 | G23: ='Seasonality Core'!G10 -> 0.078417897 | H23: ='Seasonality Core'!G11 -> 0.064922131 | I23: ='Seasonality Core'!G12 -> 0.064975294 | J23: ='Seasonality Core'!G13 -> 0.13786682 | K23: ='Seasonality Core'!G14 -> 0.13428211 | L23: ='Seasonality Core'!G15 -> 0.088110343 | M23: ='Seasonality Core'!G16 -> 0.13403616 | N23: ='Seasonality Core'!G17 -> 0.2825876 | O23: ='Seasonality Core'!G19 -> 2.294057
B24: 2024 | C24: ='Seasonality Core'!H6 -> 0.20216489 | D24: ='Seasonality Core'!H7 -> 0.12290141 | E24: ='Seasonality Core'!H8 -> 0.09412048 | F24: ='Seasonality Core'!H9 -> 0.062984384 | G24: ='Seasonality Core'!H10 -> 0.037346867 | H24: ='Seasonality Core'!H11 -> 0.036511303 | I24: ='Seasonality Core'!H12 -> 0.037855879 | J24: ='Seasonality Core'!H13 -> 0.041202856 | K24: ='Seasonality Core'!H14 -> 0.032622058 | L24: ='Seasonality Core'!H15 -> 0.029178168 | M24: ='Seasonality Core'!H16 -> 0.027148339 | N24: ='Seasonality Core'!H17 -> 0.031972815 | O24: ='Seasonality Core'!H19 -> 1.0549513
B25: 2025 | C25: ='Seasonality Core'!I6 -> 0.023976894 | D25: ='Seasonality Core'!I7 -> 0.029203528 | E25: ='Seasonality Core'!I8 -> 0.031927902 | F25: ='Seasonality Core'!I9 -> 0.03214716 | G25: ='Seasonality Core'!I10 -> 0.02197265 | H25: ='Seasonality Core'!I11 -> 0.01713735 | I25: ='Seasonality Core'!I12 -> 0.014791483 | J25: ='Seasonality Core'!I13 -> 0.020449004 | K25: ='Seasonality Core'!I14 -> 0.018958762 | L25: ='Seasonality Core'!I15 -> 0.022167187 | M25: ='Seasonality Core'!I16 -> 0.026389974 | N25: ='Seasonality Core'!I17 -> 0.030338921 | O25: ='Seasonality Core'!I19 -> 0.33088474
B26: 2026 | C26: ='Seasonality Core'!J6 -> 0.026303691 | D26: ='Seasonality Core'!J7 -> 0.030753752 | E26: ='Seasonality Core'!J8 -> 0.031889458 | F26: ='Seasonality Core'!J9 -> 0.022864744 | G26: ='Seasonality Core'!J10 -> 0.019034777 | H26: ='Seasonality Core'!J11 -> 0.015695812 | I26: ='Seasonality Core'!J12 | J26: ='Seasonality Core'!J13 | K26: ='Seasonality Core'!J14 | L26: ='Seasonality Core'!J15 | M26: ='Seasonality Core'!J16 | N26: ='Seasonality Core'!J17 | O26: ='Seasonality Core'!J19 -> 0.15567274
B30: Colour scale is relative to the whole block, so 2023-24 dominates the red end. For a like-for-like read across regimes use the Seasonal Factors tab.

Sheet Momentum
B2: Momentum — 3-month annualised vs year-on-year
B3: 3m annualised turns first. Where it sits below y/y, the y/y is still falling mechanically.

Sheet Components
B2: Where the pressure sits — núcleo vs regulados vs estacionales
B3: Regulated prices (tariffs, transport, fuel, health plans) are the 2026 story.
B32: 1. Full calendar year — cumulative from December of the prior year
B33: Component | C33: 2023 | D33: 2024 | E33: 2025 | F33: 2026 YTD
B34: Nivel General | C34: =IFERROR(INDEX(Data!$E:$E,MATCH("2023-12",Data!$B:$B,0))/INDEX(Data!$E:$E,MATCH("2022-12",Data!$B:$B,0))-1,"") -> 2.1140764 | D34: =IFERROR(INDEX(Data!$E:$E,MATCH("2024-12",Data!$B:$B,0))/INDEX(Data!$E:$E,MATCH("2023-12",Data!$B:$B,0))-1,"") -> 1.1776363 | E34: =IFERROR(INDEX(Data!$E:$E,MATCH("2025-12",Data!$B:$B,0))/INDEX(Data!$E:$E,MATCH("2024-12",Data!$B:$B,0))-1,"") -> 0.31548761 | F34: =IFERROR(INDEX(Data!$E:$E,MATCH("2026-06",Data!$B:$B,0))/INDEX(Data!$E:$E,MATCH("2025-12",Data!$B:$B,0))-1,"") -> 0.16845926
B35: Núcleo | C35: =IFERROR(INDEX(Data!$F:$F,MATCH("2023-12",Data!$B:$B,0))/INDEX(Data!$F:$F,MATCH("2022-12",Data!$B:$B,0))-1,"") -> 2.294057 | D35: =IFERROR(INDEX(Data!$F:$F,MATCH("2024-12",Data!$B:$B,0))/INDEX(Data!$F:$F,MATCH("2023-12",Data!$B:$B,0))-1,"") -> 1.0549513 | E35: =IFERROR(INDEX(Data!$F:$F,MATCH("2025-12",Data!$B:$B,0))/INDEX(Data!$F:$F,MATCH("2024-12",Data!$B:$B,0))-1,"") -> 0.33088474 | F35: =IFERROR(INDEX(Data!$F:$F,MATCH("2026-06",Data!$B:$B,0))/INDEX(Data!$F:$F,MATCH("2025-12",Data!$B:$B,0))-1,"") -> 0.15567274
B36: Regulados | C36: =IFERROR(INDEX(Data!$G:$G,MATCH("2023-12",Data!$B:$B,0))/INDEX(Data!$G:$G,MATCH("2022-12",Data!$B:$B,0))-1,"") -> 1.6494095 | D36: =IFERROR(INDEX(Data!$G:$G,MATCH("2024-12",Data!$B:$B,0))/INDEX(Data!$G:$G,MATCH("2023-12",Data!$B:$B,0))-1,"") -> 2.0587838 | E36: =IFERROR(INDEX(Data!$G:$G,MATCH("2025-12",Data!$B:$B,0))/INDEX(Data!$G:$G,MATCH("2024-12",Data!$B:$B,0))-1,"") -> 0.34209244 | F36: =IFERROR(INDEX(Data!$G:$G,MATCH("2026-06",Data!$B:$B,0))/INDEX(Data!$G:$G,MATCH("2025-12",Data!$B:$B,0))-1,"") -> 0.23044126
B37: Estacionales | C37: =IFERROR(INDEX(Data!$H:$H,MATCH("2023-12",Data!$B:$B,0))/INDEX(Data!$H:$H,MATCH("2022-12",Data!$B:$B,0))-1,"") -> 1.7897805 | D37: =IFERROR(INDEX(Data!$H:$H,MATCH("2024-12",Data!$B:$B,0))/INDEX(Data!$H:$H,MATCH("2023-12",Data!$B:$B,0))-1,"") -> 0.87321703 | E37: =IFERROR(INDEX(Data!$H:$H,MATCH("2025-12",Data!$B:$B,0))/INDEX(Data!$H:$H,MATCH("2024-12",Data!$B:$B,0))-1,"") -> 0.1695119 | F37: =IFERROR(INDEX(Data!$H:$H,MATCH("2026-06",Data!$B:$B,0))/INDEX(Data!$H:$H,MATCH("2025-12",Data!$B:$B,0))-1,"") -> 0.12752599
B38: Each bar compounds that year's monthly rates off a Dec = 100 base. The 2026 bar covers only Jan-Jun (6 of 12 months), so it is NOT comparable with the full years beside it. Use block 2 for that.
B41: 2. Like-for-like — January to Jun of each year
B42: Component | C42: 2023 | D42: 2024 | E42: 2025 | F42: 2026
B43: Nivel General | C43: =IFERROR(INDEX(Data!$E:$E,MATCH("2023-06",Data!$B:$B,0))/INDEX(Data!$E:$E,MATCH("2022-12",Data!$B:$B,0))-1,"") -> 0.50681327 | D43: =IFERROR(INDEX(Data!$E:$E,MATCH("2024-06",Data!$B:$B,0))/INDEX(Data!$E:$E,MATCH("2023-12",Data!$B:$B,0))-1,"") -> 0.79772685 | E43: =IFERROR(INDEX(Data!$E:$E,MATCH("2025-06",Data!$B:$B,0))/INDEX(Data!$E:$E,MATCH("2024-12",Data!$B:$B,0))-1,"") -> 0.15096952 | F43: =IFERROR(INDEX(Data!$E:$E,MATCH("2026-06",Data!$B:$B,0))/INDEX(Data!$E:$E,MATCH("2025-12",Data!$B:$B,0))-1,"") -> 0.16845926
B44: Núcleo | C44: =IFERROR(INDEX(Data!$F:$F,MATCH("2023-06",Data!$B:$B,0))/INDEX(Data!$F:$F,MATCH("2022-12",Data!$B:$B,0))-1,"") -> 0.51423117 | D44: =IFERROR(INDEX(Data!$F:$F,MATCH("2024-06",Data!$B:$B,0))/INDEX(Data!$F:$F,MATCH("2023-12",Data!$B:$B,0))-1,"") -> 0.68809055 | E44: =IFERROR(INDEX(Data!$F:$F,MATCH("2025-06",Data!$B:$B,0))/INDEX(Data!$F:$F,MATCH("2024-12",Data!$B:$B,0))-1,"") -> 0.16681305 | F44: =IFERROR(INDEX(Data!$F:$F,MATCH("2026-06",Data!$B:$B,0))/INDEX(Data!$F:$F,MATCH("2025-12",Data!$B:$B,0))-1,"") -> 0.15567274
B45: Regulados | C45: =IFERROR(INDEX(Data!$G:$G,MATCH("2023-06",Data!$B:$B,0))/INDEX(Data!$G:$G,MATCH("2022-12",Data!$B:$B,0))-1,"") -> 0.4947995 | D45: =IFERROR(INDEX(Data!$G:$G,MATCH("2024-06",Data!$B:$B,0))/INDEX(Data!$G:$G,MATCH("2023-12",Data!$B:$B,0))-1,"") -> 1.4095693 | E45: =IFERROR(INDEX(Data!$G:$G,MATCH("2025-06",Data!$B:$B,0))/INDEX(Data!$G:$G,MATCH("2024-12",Data!$B:$B,0))-1,"") -> 0.14215553 | F45: =IFERROR(INDEX(Data!$G:$G,MATCH("2026-06",Data!$B:$B,0))/INDEX(Data!$G:$G,MATCH("2025-12",Data!$B:$B,0))-1,"") -> 0.23044126
B46: Estacionales | C46: =IFERROR(INDEX(Data!$H:$H,MATCH("2023-06",Data!$B:$B,0))/INDEX(Data!$H:$H,MATCH("2022-12",Data!$B:$B,0))-1,"") -> 0.48224148 | D46: =IFERROR(INDEX(Data!$H:$H,MATCH("2024-06",Data!$B:$B,0))/INDEX(Data!$H:$H,MATCH("2023-12",Data!$B:$B,0))-1,"") -> 0.72760034 | E46: =IFERROR(INDEX(Data!$H:$H,MATCH("2025-06",Data!$B:$B,0))/INDEX(Data!$H:$H,MATCH("2024-12",Data!$B:$B,0))-1,"") -> 0.067342359 | F46: =IFERROR(INDEX(Data!$H:$H,MATCH("2026-06",Data!$B:$B,0))/INDEX(Data!$H:$H,MATCH("2025-12",Data!$B:$B,0))-1,"") -> 0.12752599
B47: The same 6-month window in every year, so these bars ARE directly comparable. Read this one to judge whether 2026 is running hotter or cooler than 2025.

Sheet Seasonal Factors
B2: Seasonal factors — each month vs its own year's average month
B3: Scale-free ratio, so 2023 (211% inflation) and 2025 (31%) are directly comparable. 1.20x = 20% hotter than a typical month that year.
B5: Month | C5: 2019 | D5: 2020 | E5: 2021 | F5: 2022 | G5: 2023 | H5: 2024 | I5: 2025 | J5: Average | K5: Median | L5: ex-2020
B6: Jan | C6: =IFERROR('Seasonality Headline'!C6/'Seasonality Headline'!C$20,"") -> 0.79437559 | D6: =IFERROR('Seasonality Headline'!D6/'Seasonality Headline'!D$20,"") -> 0.86403583 | E6: =IFERROR('Seasonality Headline'!E6/'Seasonality Headline'!E$20,"") -> 1.1593414 | F6: =IFERROR('Seasonality Headline'!F6/'Seasonality Headline'!F$20,"") -> 0.67774676 | G6: =IFERROR('Seasonality Headline'!G6/'Seasonality Headline'!G$20,"") -> 0.59993042 | H6: =IFERROR('Seasonality Headline'!H6/'Seasonality Headline'!H$20,"") -> 3.0187506 | I6: =IFERROR('Seasonality Headline'!I6/'Seasonality Headline'!I$20,"") -> 0.9559066 | J6: =IFERROR(AVERAGE(C6:I6),"") -> 1.1528696 | K6: =IFERROR(MEDIAN(C6:I6),"") -> 0.86403583 | L6: =IFERROR((SUM(C6:I6)-D6)/(7-1),"") -> 1.2010086
B7: Feb | C7: =IFERROR('Seasonality Headline'!C7/'Seasonality Headline'!C$20,"") -> 1.029274 | D7: =IFERROR('Seasonality Headline'!D7/'Seasonality Headline'!D$20,"") -> 0.77227211 | E7: =IFERROR('Seasonality Headline'!E7/'Seasonality Headline'!E$20,"") -> 1.0235091 | F7: =IFERROR('Seasonality Headline'!F7/'Seasonality Headline'!F$20,"") -> 0.8209113 | G7: =IFERROR('Seasonality Headline'!G7/'Seasonality Headline'!G$20,"") -> 0.65963093 | H7: =IFERROR('Seasonality Headline'!H7/'Seasonality Headline'!H$20,"") -> 1.9389668 | I7: =IFERROR('Seasonality Headline'!I7/'Seasonality Headline'!I$20,"") -> 1.0383002 | J7: =IFERROR(AVERAGE(C7:I7),"") -> 1.0404092 | K7: =IFERROR(MEDIAN(C7:I7),"") -> 1.0235091 | L7: =IFERROR((SUM(C7:I7)-D7)/(7-1),"") -> 1.0850987
B8: Mar | C8: =IFERROR('Seasonality Headline'!C8/'Seasonality Headline'!C$20,"") -> 1.2790793 | D8: =IFERROR('Seasonality Headline'!D8/'Seasonality Headline'!D$20,"") -> 1.2822954 | E8: =IFERROR('Seasonality Headline'!E8/'Seasonality Headline'!E$20,"") -> 1.3774581 | F8: =IFERROR('Seasonality Headline'!F8/'Seasonality Headline'!F$20,"") -> 1.1766758 | G8: =IFERROR('Seasonality Headline'!G8/'Seasonality Headline'!G$20,"") -> 0.76388627 | H8: =IFERROR('Seasonality Headline'!H8/'Seasonality Headline'!H$20,"") -> 1.6122623 | I8: =IFERROR('Seasonality Headline'!I8/'Seasonality Headline'!I$20,"") -> 1.6123106 | J8: =IFERROR(AVERAGE(C8:I8),"") -> 1.3005668 | K8: =IFERROR(MEDIAN(C8:I8),"") -> 1.2822954 | L8: =IFERROR((SUM(C8:I8)-D8)/(7-1),"") -> 1.3036121
B9: Apr | C9: =IFERROR('Seasonality Headline'!C9/'Seasonality Headline'!C$20,"") -> 0.92933693 | D9: =IFERROR('Seasonality Headline'!D9/'Seasonality Headline'!D$20,"") -> 0.57396922 | E9: =IFERROR('Seasonality Headline'!E9/'Seasonality Headline'!E$20,"") -> 1.1682931 | F9: =IFERROR('Seasonality Headline'!F9/'Seasonality Headline'!F$20,"") -> 1.0575045 | G9: =IFERROR('Seasonality Headline'!G9/'Seasonality Headline'!G$20,"") -> 0.8362865 | H9: =IFERROR('Seasonality Headline'!H9/'Seasonality Headline'!H$20,"") -> 1.293348 | I9: =IFERROR('Seasonality Headline'!I9/'Seasonality Headline'!I$20,"") -> 1.2022441 | J9: =IFERROR(AVERAGE(C9:I9),"") -> 1.0087118 | K9: =IFERROR(MEDIAN(C9:I9),"") -> 1.0575045 | L9: =IFERROR((SUM(C9:I9)-D9)/(7-1),"") -> 1.0811688
B10: May | C10: =IFERROR('Seasonality Headline'!C10/'Seasonality Headline'!C$20,"") -> 0.84832615 | D10: =IFERROR('Seasonality Headline'!D10/'Seasonality Headline'!D$20,"") -> 0.59167402 | E10: =IFERROR('Seasonality Headline'!E10/'Seasonality Headline'!E$20,"") -> 0.95145421 | F10: =IFERROR('Seasonality Headline'!F10/'Seasonality Headline'!F$20,"") -> 0.88314154 | G10: =IFERROR('Seasonality Headline'!G10/'Seasonality Headline'!G$20,"") -> 0.77359137 | H10: =IFERROR('Seasonality Headline'!H10/'Seasonality Headline'!H$20,"") -> 0.61154071 | I10: =IFERROR('Seasonality Headline'!I10/'Seasonality Headline'!I$20,"") -> 0.64897716 | J10: =IFERROR(AVERAGE(C10:I10),"") -> 0.75838645 | K10: =IFERROR(MEDIAN(C10:I10),"") -> 0.77359137 | L10: =IFERROR((SUM(C10:I10)-D10)/(7-1),"") -> 0.78617186
B11: Jun | C11: =IFERROR('Seasonality Headline'!C11/'Seasonality Headline'!C$20,"") -> 0.74292435 | D11: =IFERROR('Seasonality Headline'!D11/'Seasonality Headline'!D$20,"") -> 0.86044768 | E11: =IFERROR('Seasonality Headline'!E11/'Seasonality Headline'!E$20,"") -> 0.90895485 | F11: =IFERROR('Seasonality Headline'!F11/'Seasonality Headline'!F$20,"") -> 0.9259839 | G11: =IFERROR('Seasonality Headline'!G11/'Seasonality Headline'!G$20,"") -> 0.59226278 | H11: =IFERROR('Seasonality Headline'!H11/'Seasonality Headline'!H$20,"") -> 0.67030788 | I11: =IFERROR('Seasonality Headline'!I11/'Seasonality Headline'!I$20,"") -> 0.69991288 | J11: =IFERROR(AVERAGE(C11:I11),"") -> 0.77154205 | K11: =IFERROR(MEDIAN(C11:I11),"") -> 0.74292435 | L11: =IFERROR((SUM(C11:I11)-D11)/(7-1),"") -> 0.75672444
B12: Jul | C12: =IFERROR('Seasonality Headline'!C12/'Seasonality Headline'!C$20,"") -> 0.60075224 | D12: =IFERROR('Seasonality Headline'!D12/'Seasonality Headline'!D$20,"") -> 0.74180711 | E12: =IFERROR('Seasonality Headline'!E12/'Seasonality Headline'!E$20,"") -> 0.85812783 | F12: =IFERROR('Seasonality Headline'!F12/'Seasonality Headline'!F$20,"") -> 1.2951336 | G12: =IFERROR('Seasonality Headline'!G12/'Seasonality Headline'!G$20,"") -> 0.63147792 | H12: =IFERROR('Seasonality Headline'!H12/'Seasonality Headline'!H$20,"") -> 0.5902906 | I12: =IFERROR('Seasonality Headline'!I12/'Seasonality Headline'!I$20,"") -> 0.82215856 | J12: =IFERROR(AVERAGE(C12:I12),"") -> 0.79139255 | K12: =IFERROR(MEDIAN(C12:I12),"") -> 0.74180711 | L12: =IFERROR((SUM(C12:I12)-D12)/(7-1),"") -> 0.79965679
B13: Aug | C13: =IFERROR('Seasonality Headline'!C13/'Seasonality Headline'!C$20,"") -> 1.0807603 | D13: =IFERROR('Seasonality Headline'!D13/'Seasonality Headline'!D$20,"") -> 1.035553 | E13: =IFERROR('Seasonality Headline'!E13/'Seasonality Headline'!E$20,"") -> 0.70679131 | F13: =IFERROR('Seasonality Headline'!F13/'Seasonality Headline'!F$20,"") -> 1.2189138 | G13: =IFERROR('Seasonality Headline'!G13/'Seasonality Headline'!G$20,"") -> 1.238267 | H13: =IFERROR('Seasonality Headline'!H13/'Seasonality Headline'!H$20,"") -> 0.6109884 | I13: =IFERROR('Seasonality Headline'!I13/'Seasonality Headline'!I$20,"") -> 0.81096539 | J13: =IFERROR(AVERAGE(C13:I13),"") -> 0.95746275 | K13: =IFERROR(MEDIAN(C13:I13),"") -> 1.035553 | L13: =IFERROR((SUM(C13:I13)-D13)/(7-1),"") -> 0.94444771
B14: Sep | C14: =IFERROR('Seasonality Headline'!C14/'Seasonality Headline'!C$20,"") -> 1.6087539 | D14: =IFERROR('Seasonality Headline'!D14/'Seasonality Headline'!D$20,"") -> 1.0874863 | E14: =IFERROR('Seasonality Headline'!E14/'Seasonality Headline'!E$20,"") -> 1.0155367 | F14: =IFERROR('Seasonality Headline'!F14/'Seasonality Headline'!F$20,"") -> 1.0781744 | G14: =IFERROR('Seasonality Headline'!G14/'Seasonality Headline'!G$20,"") -> 1.2689322 | H14: =IFERROR('Seasonality Headline'!H14/'Seasonality Headline'!H$20,"") -> 0.50803141 | I14: =IFERROR('Seasonality Headline'!I14/'Seasonality Headline'!I$20,"") -> 0.89750389 | J14: =IFERROR(AVERAGE(C14:I14),"") -> 1.0663456 | K14: =IFERROR(MEDIAN(C14:I14),"") -> 1.0781744 | L14: =IFERROR((SUM(C14:I14)-D14)/(7-1),"") -> 1.0628221
B15: Oct | C15: =IFERROR('Seasonality Headline'!C15/'Seasonality Headline'!C$20,"") -> 0.90022192 | D15: =IFERROR('Seasonality Headline'!D15/'Seasonality Headline'!D$20,"") -> 1.4424165 | E15: =IFERROR('Seasonality Headline'!E15/'Seasonality Headline'!E$20,"") -> 1.0068001 | F15: =IFERROR('Seasonality Headline'!F15/'Seasonality Headline'!F$20,"") -> 1.1099714 | G15: =IFERROR('Seasonality Headline'!G15/'Seasonality Headline'!G$20,"") -> 0.8262393 | H15: =IFERROR('Seasonality Headline'!H15/'Seasonality Headline'!H$20,"") -> 0.39417857 | I15: =IFERROR('Seasonality Headline'!I15/'Seasonality Headline'!I$20,"") -> 1.0124967 | J15: =IFERROR(AVERAGE(C15:I15),"") -> 0.95604634 | K15: =IFERROR(MEDIAN(C15:I15),"") -> 1.0068001 | L15: =IFERROR((SUM(C15:I15)-D15)/(7-1),"") -> 0.87498466
B16: Nov | C16: =IFERROR('Seasonality Headline'!C16/'Seasonality Headline'!C$20,"") -> 1.1629114 | D16: =IFERROR('Seasonality Headline'!D16/'Seasonality Headline'!D$20,"") -> 1.2118178 | E16: =IFERROR('Seasonality Headline'!E16/'Seasonality Headline'!E$20,"") -> 0.72425086 | F16: =IFERROR('Seasonality Headline'!F16/'Seasonality Headline'!F$20,"") -> 0.85969458 | G16: =IFERROR('Seasonality Headline'!G16/'Seasonality Headline'!G$20,"") -> 1.2749973 | H16: =IFERROR('Seasonality Headline'!H16/'Seasonality Headline'!H$20,"") -> 0.35534528 | I16: =IFERROR('Seasonality Headline'!I16/'Seasonality Headline'!I$20,"") -> 1.0691221 | J16: =IFERROR(AVERAGE(C16:I16),"") -> 0.95116276 | K16: =IFERROR(MEDIAN(C16:I16),"") -> 1.0691221 | L16: =IFERROR((SUM(C16:I16)-D16)/(7-1),"") -> 0.90772025
B17: Dec | C17: =IFERROR('Seasonality Headline'!C17/'Seasonality Headline'!C$20,"") -> 1.023284 | D17: =IFERROR('Seasonality Headline'!D17/'Seasonality Headline'!D$20,"") -> 1.5362251 | E17: =IFERROR('Seasonality Headline'!E17/'Seasonality Headline'!E$20,"") -> 1.0994824 | F17: =IFERROR('Seasonality Headline'!F17/'Seasonality Headline'!F$20,"") -> 0.89614844 | G17: =IFERROR('Seasonality Headline'!G17/'Seasonality Headline'!G$20,"") -> 2.5344979 | H17: =IFERROR('Seasonality Headline'!H17/'Seasonality Headline'!H$20,"") -> 0.39598945 | I17: =IFERROR('Seasonality Headline'!I17/'Seasonality Headline'!I$20,"") -> 1.2301018 | J17: =IFERROR(AVERAGE(C17:I17),"") -> 1.2451042 | K17: =IFERROR(MEDIAN(C17:I17),"") -> 1.0994824 | L17: =IFERROR((SUM(C17:I17)-D17)/(7-1),"") -> 1.196584
B19: Read: a factor above 1.00x means the month is systematically hotter than the year's average month. Denominator is that year's own average monthly rate (Seasonality tab, row 20).

Sheet Forecast
B2: Forecast — Argentina CPI, bull / base / bear to Dec-2027
B3: Monthly paths are judgement inputs (blue). Dec/Dec figures are formulas. Benchmarked to the BCRA REM of June-2026.
B5: Month | C5: Actual | D5: Bull | E5: Base | F5: Bear | G5: Bull index | H5: Base index | I5: Bear index
B6: 2025-01 | C6: =IFERROR(IF(INDEX(Data!$I:$I,MATCH($B6,Data!$B:$B,0))="","",INDEX(Data!$I:$I,MATCH($B6,Data!$B:$B,0))),"") -> 0.02211048 | G6: =IFERROR(INDEX(Data!$E:$E,MATCH($B6,Data!$B:$B,0)),"") -> 7864.1257 | H6: =IFERROR(INDEX(Data!$E:$E,MATCH($B6,Data!$B:$B,0)),"") -> 7864.1257 | I6: =IFERROR(INDEX(Data!$E:$E,MATCH($B6,Data!$B:$B,0)),"") -> 7864.1257
B7: 2025-02 | C7: =IFERROR(IF(INDEX(Data!$I:$I,MATCH($B7,Data!$B:$B,0))="","",INDEX(Data!$I:$I,MATCH($B7,Data!$B:$B,0))),"") -> 0.024016274 | G7: =IFERROR(INDEX(Data!$E:$E,MATCH($B7,Data!$B:$B,0)),"") -> 8052.9927 | H7: =IFERROR(INDEX(Data!$E:$E,MATCH($B7,Data!$B:$B,0)),"") -> 8052.9927 | I7: =IFERROR(INDEX(Data!$E:$E,MATCH($B7,Data!$B:$B,0)),"") -> 8052.9927
B8: 2025-03 | C8: =IFERROR(IF(INDEX(Data!$I:$I,MATCH($B8,Data!$B:$B,0))="","",INDEX(Data!$I:$I,MATCH($B8,Data!$B:$B,0))),"") -> 0.037293353 | G8: =IFERROR(INDEX(Data!$E:$E,MATCH($B8,Data!$B:$B,0)),"") -> 8353.3158 | H8: =IFERROR(INDEX(Data!$E:$E,MATCH($B8,Data!$B:$B,0)),"") -> 8353.3158 | I8: =IFERROR(INDEX(Data!$E:$E,MATCH($B8,Data!$B:$B,0)),"") -> 8353.3158
B9: 2025-04 | C9: =IFERROR(IF(INDEX(Data!$I:$I,MATCH($B9,Data!$B:$B,0))="","",INDEX(Data!$I:$I,MATCH($B9,Data!$B:$B,0))),"") -> 0.027808358 | G9: =IFERROR(INDEX(Data!$E:$E,MATCH($B9,Data!$B:$B,0)),"") -> 8585.6078 | H9: =IFERROR(INDEX(Data!$E:$E,MATCH($B9,Data!$B:$B,0)),"") -> 8585.6078 | I9: =IFERROR(INDEX(Data!$E:$E,MATCH($B9,Data!$B:$B,0)),"") -> 8585.6078
B10: 2025-05 | C10: =IFERROR(IF(INDEX(Data!$I:$I,MATCH($B10,Data!$B:$B,0))="","",INDEX(Data!$I:$I,MATCH($B10,Data!$B:$B,0))),"") -> 0.015011086 | G10: =IFERROR(INDEX(Data!$E:$E,MATCH($B10,Data!$B:$B,0)),"") -> 8714.4871 | H10: =IFERROR(INDEX(Data!$E:$E,MATCH($B10,Data!$B:$B,0)),"") -> 8714.4871 | I10: =IFERROR(INDEX(Data!$E:$E,MATCH($B10,Data!$B:$B,0)),"") -> 8714.4871
B11: 2025-06 | C11: =IFERROR(IF(INDEX(Data!$I:$I,MATCH($B11,Data!$B:$B,0))="","",INDEX(Data!$I:$I,MATCH($B11,Data!$B:$B,0))),"") -> 0.016189249 | G11: =IFERROR(INDEX(Data!$E:$E,MATCH($B11,Data!$B:$B,0)),"") -> 8855.5681 | H11: =IFERROR(INDEX(Data!$E:$E,MATCH($B11,Data!$B:$B,0)),"") -> 8855.5681 | I11: =IFERROR(INDEX(Data!$E:$E,MATCH($B11,Data!$B:$B,0)),"") -> 8855.5681
B12: 2025-07 | C12: =IFERROR(IF(INDEX(Data!$I:$I,MATCH($B12,Data!$B:$B,0))="","",INDEX(Data!$I:$I,MATCH($B12,Data!$B:$B,0))),"") -> 0.019016838 | G12: =IFERROR(INDEX(Data!$E:$E,MATCH($B12,Data!$B:$B,0)),"") -> 9023.973 | H12: =IFERROR(INDEX(Data!$E:$E,MATCH($B12,Data!$B:$B,0)),"") -> 9023.973 | I12: =IFERROR(INDEX(Data!$E:$E,MATCH($B12,Data!$B:$B,0)),"") -> 9023.973
B13: 2025-08 | C13: =IFERROR(IF(INDEX(Data!$I:$I,MATCH($B13,Data!$B:$B,0))="","",INDEX(Data!$I:$I,MATCH($B13,Data!$B:$B,0))),"") -> 0.018757935 | G13: =IFERROR(INDEX(Data!$E:$E,MATCH($B13,Data!$B:$B,0)),"") -> 9193.2441 | H13: =IFERROR(INDEX(Data!$E:$E,MATCH($B13,Data!$B:$B,0)),"") -> 9193.2441 | I13: =IFERROR(INDEX(Data!$E:$E,MATCH($B13,Data!$B:$B,0)),"") -> 9193.2441
B14: 2025-09 | C14: =IFERROR(IF(INDEX(Data!$I:$I,MATCH($B14,Data!$B:$B,0))="","",INDEX(Data!$I:$I,MATCH($B14,Data!$B:$B,0))),"") -> 0.020759603 | G14: =IFERROR(INDEX(Data!$E:$E,MATCH($B14,Data!$B:$B,0)),"") -> 9384.0922 | H14: =IFERROR(INDEX(Data!$E:$E,MATCH($B14,Data!$B:$B,0)),"") -> 9384.0922 | I14: =IFERROR(INDEX(Data!$E:$E,MATCH($B14,Data!$B:$B,0)),"") -> 9384.0922
B15: 2025-10 | C15: =IFERROR(IF(INDEX(Data!$I:$I,MATCH($B15,Data!$B:$B,0))="","",INDEX(Data!$I:$I,MATCH($B15,Data!$B:$B,0))),"") -> 0.023419431 | G15: =IFERROR(INDEX(Data!$E:$E,MATCH($B15,Data!$B:$B,0)),"") -> 9603.8623 | H15: =IFERROR(INDEX(Data!$E:$E,MATCH($B15,Data!$B:$B,0)),"") -> 9603.8623 | I15: =IFERROR(INDEX(Data!$E:$E,MATCH($B15,Data!$B:$B,0)),"") -> 9603.8623
B16: 2025-11 | C16: =IFERROR(IF(INDEX(Data!$I:$I,MATCH($B16,Data!$B:$B,0))="","",INDEX(Data!$I:$I,MATCH($B16,Data!$B:$B,0))),"") -> 0.024729197 | G16: =IFERROR(INDEX(Data!$E:$E,MATCH($B16,Data!$B:$B,0)),"") -> 9841.3581 | H16: =IFERROR(INDEX(Data!$E:$E,MATCH($B16,Data!$B:$B,0)),"") -> 9841.3581 | I16: =IFERROR(INDEX(Data!$E:$E,MATCH($B16,Data!$B:$B,0)),"") -> 9841.3581
B17: 2025-12 | C17: =IFERROR(IF(INDEX(Data!$I:$I,MATCH($B17,Data!$B:$B,0))="","",INDEX(Data!$I:$I,MATCH($B17,Data!$B:$B,0))),"") -> 0.028452719 | G17: =IFERROR(INDEX(Data!$E:$E,MATCH($B17,Data!$B:$B,0)),"") -> 10121.371 | H17: =IFERROR(INDEX(Data!$E:$E,MATCH($B17,Data!$B:$B,0)),"") -> 10121.371 | I17: =IFERROR(INDEX(Data!$E:$E,MATCH($B17,Data!$B:$B,0)),"") -> 10121.371
... B22: 2026-05 | C22: =IFERROR(IF(INDEX(Data!$I:$I,MATCH($B22,Data!$B:$B,0))="","",INDEX(Data!$I:$I,MATCH($B22,Data!$B:$B,0))),"") -> 0.021499723 | G22: =IFERROR(INDEX(Data!$E:$E,MATCH($B22,Data!$B:$B,0)),"") -> 11607.394 | H22: =IFERROR(INDEX(Data!$E:$E,MATCH($B22,Data!$B:$B,0)),"") -> 11607.394 | I22: =IFERROR(INDEX(Data!$E:$E,MATCH($B22,Data!$B:$B,0)),"") -> 11607.394
B23: 2026-06 | C23: =IFERROR(IF(INDEX(Data!$I:$I,MATCH($B23,Data!$B:$B,0))="","",INDEX(Data!$I:$I,MATCH($B23,Data!$B:$B,0))),"") -> 0.018868715 | D23: =$C23 -> 0.018868715 | E23: =$C23 -> 0.018868715 | F23: =$C23 -> 0.018868715 | G23: =IFERROR(INDEX(Data!$E:$E,MATCH($B23,Data!$B:$B,0)),"") -> 11826.41 | H23: =IFERROR(INDEX(Data!$E:$E,MATCH($B23,Data!$B:$B,0)),"") -> 11826.41 | I23: =IFERROR(INDEX(Data!$E:$E,MATCH($B23,Data!$B:$B,0)),"") -> 11826.41
B24: 2026-07 | C24: =IFERROR(IF(INDEX(Data!$I:$I,MATCH($B24,Data!$B:$B,0))="","",INDEX(Data!$I:$I,MATCH($B24,Data!$B:$B,0))),"") | D24: 0.017 | E24: 0.019 | F24: 0.022 | G24: =G23*(1+D24) -> 12027.459 | H24: =H23*(1+E24) -> 12051.112 | I24: =I23*(1+F24) -> 12086.591
B25: 2026-08 | C25: =IFERROR(IF(INDEX(Data!$I:$I,MATCH($B25,Data!$B:$B,0))="","",INDEX(Data!$I:$I,MATCH($B25,Data!$B:$B,0))),"") | D25: 0.016 | E25: 0.018 | F25: 0.024 | G25: =G24*(1+D25) -> 12219.899 | H25: =H24*(1+E25) -> 12268.032 | I25: =I24*(1+F25) -> 12376.67
B26: 2026-09 | C26: =IFERROR(IF(INDEX(Data!$I:$I,MATCH($B26,Data!$B:$B,0))="","",INDEX(Data!$I:$I,MATCH($B26,Data!$B:$B,0))),"") | D26: 0.015 | E26: 0.018 | F26: 0.025 | G26: =G25*(1+D26) -> 12403.197 | H26: =H25*(1+E26) -> 12488.857 | I26: =I25*(1+F26) -> 12686.086
B27: 2026-10 | C27: =IFERROR(IF(INDEX(Data!$I:$I,MATCH($B27,Data!$B:$B,0))="","",INDEX(Data!$I:$I,MATCH($B27,Data!$B:$B,0))),"") | D27: 0.015 | E27: 0.019 | F27: 0.027 | G27: =G26*(1+D27) -> 12589.245 | H27: =H26*(1+E27) -> 12726.145 | I27: =I26*(1+F27) -> 13028.611
B28: 2026-11 | C28: =IFERROR(IF(INDEX(Data!$I:$I,MATCH($B28,Data!$B:$B,0))="","",INDEX(Data!$I:$I,MATCH($B28,Data!$B:$B,0))),"") | D28: 0.014 | E28: 0.019 | F28: 0.026 | G28: =G27*(1+D28) -> 12765.494 | H28: =H27*(1+E28) -> 12967.942 | I28: =I27*(1+F28) -> 13367.354
B29: 2026-12 | C29: =IFERROR(IF(INDEX(Data!$I:$I,MATCH($B29,Data!$B:$B,0))="","",INDEX(Data!$I:$I,MATCH($B29,Data!$B:$B,0))),"") | D29: 0.016 | E29: 0.021 | F29: 0.028 | G29: =G28*(1+D29) -> 12969.742 | H29: =H28*(1+E29) -> 13240.268 | I29: =I28*(1+F29) -> 13741.64
B30: 2027-01 | C30: =IFERROR(IF(INDEX(Data!$I:$I,MATCH($B30,Data!$B:$B,0))="","",INDEX(Data!$I:$I,MATCH($B30,Data!$B:$B,0))),"") | D30: 0.015 | E30: 0.02 | F30: 0.028 | G30: =G29*(1+D30) -> 13164.289 | H30: =H29*(1+E30) -> 13505.074 | I30: =I29*(1+F30) -> 14126.406
B31: 2027-02 | C31: =IFERROR(IF(INDEX(Data!$I:$I,MATCH($B31,Data!$B:$B,0))="","",INDEX(Data!$I:$I,MATCH($B31,Data!$B:$B,0))),"") | D31: 0.013 | E31: 0.018 | F31: 0.026 | G31: =G30*(1+D31) -> 13335.424 | H31: =H30*(1+E31) -> 13748.165 | I31: =I30*(1+F31) -> 14493.693
B32: 2027-03 | C32: =IFERROR(IF(INDEX(Data!$I:$I,MATCH($B32,Data!$B:$B,0))="","",INDEX(Data!$I:$I,MATCH($B32,Data!$B:$B,0))),"") | D32: 0.013 | E32: 0.017 | F32: 0.025 | G32: =G31*(1+D32) -> 13508.785 | H32: =H31*(1+E32) -> 13981.884 | I32: =I31*(1+F32) -> 14856.035
B33: 2027-04 | C33: =IFERROR(IF(INDEX(Data!$I:$I,MATCH($B33,Data!$B:$B,0))="","",INDEX(Data!$I:$I,MATCH($B33,Data!$B:$B,0))),"") | D33: 0.011 | E33: 0.016 | F33: 0.023 | G33: =G32*(1+D33) -> 13657.381 | H33: =H32*(1+E33) -> 14205.594 | I33: =I32*(1+F33) -> 15197.724
B34: 2027-05 | C34: =IFERROR(IF(INDEX(Data!$I:$I,MATCH($B34,Data!$B:$B,0))="","",INDEX(Data!$I:$I,MATCH($B34,Data!$B:$B,0))),"") | D34: 0.01 | E34: 0.014 | F34: 0.021 | G34: =G33*(1+D34) -> 13793.955 | H34: =H33*(1+E34) -> 14404.472 | I34: =I33*(1+F34) -> 15516.876
B35: 2027-06 | C35: =IFERROR(IF(INDEX(Data!$I:$I,MATCH($B35,Data!$B:$B,0))="","",INDEX(Data!$I:$I,MATCH($B35,Data!$B:$B,0))),"") | D35: 0.009 | E35: 0.013 | F35: 0.02 | G35: =G34*(1+D35) -> 13918.101 | H35: =H34*(1+E35) -> 14591.731 | I35: =I34*(1+F35) -> 15827.214
... B41: 2027-12 | C41: =IFERROR(IF(INDEX(Data!$I:$I,MATCH($B41,Data!$B:$B,0))="","",INDEX(Data!$I:$I,MATCH($B41,Data!$B:$B,0))),"") | D41: 0.01 | E41: 0.014 | F41: 0.02 | G41: =G40*(1+D41) -> 14643.155 | H41: =H40*(1+E41) -> 15720.858 | I41: =I40*(1+F41) -> 17684.645
B43: Dec/Dec outcome
D44: Bull | E44: Base | F44: Bear | G44: BCRA REM (Jun-26 survey)
B45: 2026 (Dec/Dec) | D45: =G$29/INDEX(Data!$E:$E,MATCH("2025-12",Data!$B:$B,0))-1 -> 0.28142144 | E45: =H$29/INDEX(Data!$E:$E,MATCH("2025-12",Data!$B:$B,0))-1 -> 0.30814964 | F45: =I$29/INDEX(Data!$E:$E,MATCH("2025-12",Data!$B:$B,0))-1 -> 0.3576856 | G45: 0.3
B46: 2027 (Dec/Dec) | D46: =G$41/G$29-1 -> 0.12902432 | E46: =H$41/H$29-1 -> 0.18735193 | F46: =I$41/I$29-1 -> 0.28693841 | G46: 0.118
B47: REM = BCRA Relevamiento de Expectativas de Mercado, June-2026 round (44 participants, published 6-Jul-2026): 30% for 2026; the 2027 median is the last published reading. 2026 formula splices realised months with the scenario path.
B50: Scenario assumptions
B51: Driver | C51: Bull | D51: Base | E51: Bear
B52: FX — official, Dec-26 | C52: ARS 1,600 — spot drifts up less than the band crawl; real appreciation resumes | D52: ARS 1,690 — spot tracks the band's CPI-indexed crawl, roughly 2.2%/m from ARS 1,470 | E52: ARS 1,950 — band ceiling tested; a step devaluation of 12-15% in Q4
B53: FX pass-through | C53: 0.10 within a quarter — import competition holds, margins absorb | D53: 0.15 within two quarters — the 2024-25 realised range | E53: 0.30 — a discrete jump reprices tradables fast
B54: Regulated tariffs | C54: Catch-up essentially complete; regulated converges toward core by Q4-26 | D54: Regulated keeps running ~50-80bp/m above core through mid-27, then converges | E54: Energy and transport subsidy removal re-accelerates; regulated stays 150bp/m above core
B55: Wages / indexation | C55: Paritarias settle at or below expected inflation; backward-looking indexation breaks | D55: Paritarias track trailing CPI — inertia keeps a floor near 1.2-1.4%/m | E55: Real wage recovery demands re-open; formal wages index to trailing 12m
B56: Fiscal / monetary | C56: Primary surplus above 1.5% GDP, no monetary financing, remonetisation orderly | D56: Primary surplus around 1.0-1.5% GDP maintained; peso demand grows with activity | E56: Surplus slips ahead of the 2027 electoral cycle; peso demand stalls
B57: Key risk to this view | C57: Disinflation faster than any Argentine episode since convertibility — historically rare | D57: The band's CPI indexation removes the nominal anchor that drove 2024-25; inflation converges to the crawl, not below it | E57: A band break is the single event that resets the whole path — watch reserve accumulation, not the CPI
