Workbook
Name _DLX1: Employment!$B$3:$V$7
Name _DLX1: 'Inflation expectations'!$B$3:$I$7
Name _DLX1.USE: #REF!
Name _DLX1.USE: 'Current account'!$D$3:$I$24
Name _DLX10.USE: 'Net reserves'!$B$20:$G$37
Name _DLX13.USE: #REF!
Name _DLX2: 'Trade balance'!$B$2:$L$6
Name _DLX2.USE: #REF!
Name _DLX3: '12 month rolling fiscal'!#REF!
Name _DLX4: '12 month rolling fiscal'!$B$2:$G$6
Name _DLX5: '12 month rolling fiscal'!$I$2:$P$6
Name _DLX6: 'GDP contributions (HAVER)'!$B$3:$Z$7
Name _DLX7.USE: '[3]Monetary analysis'!#REF!
Name _DLX8: 'CPI MoM'!$B$2:$H$6
Name año2003: #REF!
Name dbBacktables: [4]dbBacktables!$A$2:$A$43
Name dbIndicators: [4]dbIndicators!$A$2:$A$230
Name dbSources: [4]dbSources!$A$2:$A$93
Name PRINT_TITLES_MI: #REF!
Name YesNo: [4]YesNo!$A$2:$A$3

Sheet Inflation expectations
C2: 12mo inflation expectations | D2: 24mo inflation expectations | E2: 30% annual mark
B3: 11606 !M | C3: N213VC1M@EMERGELA | D3: N213VC2M@EMERGELA
B4: .DESC | C4: Argentina: Median National CPI Inflation Expectations, 12 months (%) | D4: Argentina: Median National CPI Inflation Expectations, 24 months (%)
B5: .SOURCE | C5: BCRA | D5: BCRA
B6: .DATA_TYPE | C6: % | D6: %
B7: .MAG | C7: 0 | D7: 0
A8: 42522 | B8: 1606 | C8: 21.5 | D8: 15.9 | E8: 30
A9: 42552 | B9: 1607 | C9: 21.7 | D9: 16 | E9: 30
A10: 42583 | B10: 1608 | C10: 21.9 | D10: 16 | E10: 30
A11: 42614 | B11: 1609 | C11: 21.1 | D11: 15.4 | E11: 30
A12: 42644 | B12: 1610 | C12: 19.4 | D12: 14.9 | E12: 30
A13: 42675 | B13: 1611 | C13: 20 | D13: 15.4 | E13: 30
A14: 42705 | B14: 1612 | C14: 19.6 | D14: 14 | E14: 30
A15: 42736 | B15: 1701 | C15: 19.7 | D15: 14 | E15: 30
A16: 42767 | B16: 1702 | C16: 19.5 | D16: 13.1 | E16: 30
A17: 42795 | B17: 1703 | C17: 18.4 | D17: 13 | E17: 30
A18: 42826 | B18: 1704 | C18: 17.5 | D18: 13 | E18: 30
A19: 42856 | B19: 1705 | C19: 17 | D19: 13.1 | E19: 30
... A67: 44317 | B67: 2105 | C67: 43.3 | D67: 37.9 | E67: 30
A68: 44348 | B68: 2106 | C68: 43.1 | D68: #N/A | E68: 30
A69: 44378 | B69: 2107 | C69: 43.2 | D69: 38.5 | E69: 30
A70: 44409 | B70: 2108 | C70: 43.7 | D70: 38.5 | E70: 30
A71: 44440 | B71: 2109 | C71: 45.6 | D71: 38.6 | E71: 30
A72: 44470 | B72: 2110 | C72: 48.6 | D72: 40.1 | E72: 30
A73: 44501 | B73: 2111 | C73: 52.3 | D73: 41.1 | E73: 30
A74: 44531 | B74: 2112 | C74: 54.8 | D74: 43.4 | E74: 30
A75: 44562 | B75: 2201 | C75: 53.9 | D75: 44.3 | E75: 30
A76: 44593 | B76: 2202 | C76: 52.9 | D76: 44.6 | E76: 30
A77: 44621 | B77: 2203 | C77: 55.4 | D77: 45.8 | E77: 30
A78: 44652 | B78: 2204 | C78: 56.1 | D78: 50 | E78: 30
A79: 44682 | B79: 2205 | C79: 60.1 | D79: 55.2 | E79: 30
A80: 44713 | B80: 2206 | C80: 68.8 | D80: 60 | E80: 30
... A129: 46204 | B129: 2607 | C129: 21.8 | D129: 16.6 | E129: 30

Sheet Trade balance
C1: Trade balance | E1: Exports of energy | F1: Imports of energy
B2: 10501 !M | C2: N213IBD@EMERGELA | E2: N213IXFN@EMERGELA | F2: N213IMF@EMERGELA
B3: .DESC | C3: Argentina: Goods Trade Balance (NSA, Mil.US$) | E3: Argentina: Exports of Fuels & Energy (NSA, Mil.US$) | F3: Argentina: Imports: Manufacture Fuels and Lubricants (NSA, Mil.US$)
B4: .SOURCE | C4: INDEC | E4: INDEC | F4: INDEC
B5: .DATA_TYPE | C5: US$ | E5: US$ | F5: US$
B6: .MAG | C6: 6 | E6: 6 | F6: 6
B7: 0501 | C7: 880.1 | D7: =E7-F7 -> 455.8 | E7: 542 | F7: 86.2
B8: 0502 | C8: 739 | D8: =E8-F8 -> 350 | E8: 436 | F8: 86
B9: 0503 | C9: 856.9 | D9: =E9-F9 -> 430.9 | E9: 510 | F9: 79.1
B10: 0504 | C10: 1180.9 | D10: =E10-F10 -> 389.7 | E10: 574 | F10: 184.3
B11: 0505 | C11: 1219.3 | D11: =E11-F11 -> 354.6 | E11: 547 | F11: 192.4
B12: 0506 | C12: 726.6 | D12: =E12-F12 -> 397.7 | E12: 599 | F12: 201.3
B13: 0507 | C13: 1252 | D13: =E13-F13 -> 431.2 | E13: 585 | F13: 153.8
B14: 0508 | C14: 1211.7 | D14: =E14-F14 -> 574.9 | E14: 703 | F14: 128.1
B15: 0509 | C15: 1014.8 | D15: =E15-F15 -> 602.6 | E15: 713 | F15: 110.4
B16: 0510 | C16: 896.2 | D16: =E16-F16 -> 555.7 | E16: 654 | F16: 98.3
B17: 0511 | C17: 572.8 | D17: =E17-F17 -> 519 | E17: 617 | F17: 98 | G17: Full trade balance | H17: Energy trade balance | I17: Non-energy
A18: 38687 | B18: 0512 | C18: 1149.6 | D18: =E18-F18 -> 542.6 | E18: 670 | F18: 127.4 | G18: =SUM(C7:C18) -> 11699.9 | H18: =SUM(D7:D18) -> 5604.7 | I18: =G18-H18 -> 6095.2
A19: 38718 | B19: 0601 | C19: 863.9 | D19: =E19-F19 -> 549.4 | E19: 649 | F19: 99.6 | G19: =SUM(C8:C19) -> 11683.7 | H19: =SUM(D8:D19) -> 5698.3 | I19: =G19-H19 -> 5985.4
A20: 38749 | B20: 0602 | C20: 763.9 | D20: =E20-F20 -> 487.2 | E20: 587 | F20: 99.8 | G20: =SUM(C9:C20) -> 11708.6 | H20: =SUM(D9:D20) -> 5835.5 | I20: =G20-H20 -> 5873.1
A21: 38777 | B21: 0603 | C21: 925.9 | D21: =E21-F21 -> 474.3 | E21: 599 | F21: 124.7 | G21: =SUM(C10:C21) -> 11777.6 | H21: =SUM(D10:D21) -> 5878.9 | I21: =G21-H21 -> 5898.7
A22: 38808 | B22: 0604 | C22: 1379.9 | D22: =E22-F22 -> 577.5 | E22: 710 | F22: 132.5 | G22: =SUM(C11:C22) -> 11976.6 | H22: =SUM(D11:D22) -> 6066.7 | I22: =G22-H22 -> 5909.9
A23: 38838 | B23: 0605 | C23: 1355.4 | D23: =E23-F23 -> 467.7 | E23: 600 | F23: 132.3 | G23: =SUM(C12:C23) -> 12112.7 | H23: =SUM(D12:D23) -> 6179.8 | I23: =G23-H23 -> 5932.9
A24: 38869 | B24: 0606 | C24: 988.6 | D24: =E24-F24 -> 498.7 | E24: 716 | F24: 217.3 | G24: =SUM(C13:C24) -> 12374.7 | H24: =SUM(D13:D24) -> 6280.8 | I24: =G24-H24 -> 6093.9
A25: 38899 | B25: 0607 | C25: 964.5 | D25: =E25-F25 -> 477.5 | E25: 657 | F25: 179.5 | G25: =SUM(C14:C25) -> 12087.2 | H25: =SUM(D14:D25) -> 6327.1 | I25: =G25-H25 -> 5760.1
A26: 38930 | B26: 0608 | C26: 965.4 | D26: =E26-F26 -> 423.5 | E26: 646 | F26: 222.5 | G26: =SUM(C15:C26) -> 11840.9 | H26: =SUM(D15:D26) -> 6175.7 | I26: =G26-H26 -> 5665.2
A27: 38961 | B27: 0609 | C27: 878.7 | D27: =E27-F27 -> 455.7 | E27: 640 | F27: 184.3 | G27: =SUM(C16:C27) -> 11704.8 | H27: =SUM(D16:D27) -> 6028.8 | I27: =G27-H27 -> 5676
A28: 38991 | B28: 0610 | C28: 948.6 | D28: =E28-F28 -> 576.9 | E28: 717 | F28: 140.1 | G28: =SUM(C17:C28) -> 11757.2 | H28: =SUM(D17:D28) -> 6050 | I28: =G28-H28 -> 5707.2
A29: 39022 | B29: 0611 | C29: 872.9 | D29: =E29-F29 -> 502.5 | E29: 622 | F29: 119.5 | G29: =SUM(C18:C29) -> 12057.3 | H29: =SUM(D18:D29) -> 6033.5 | I29: =G29-H29 -> 6023.8
... A264: 46174 | B264: 2606 | C264: 2193.8 | D264: =E264-F264 -> 611.5 | E264: 1406 | F264: 794.5 | G264: =SUM(C253:C264) -> 22481.1 | H264: =SUM(D253:D264) -> 9951.3 | I264: =G264-H264 -> 12529.8

Sheet Current account
BI1: 4Q 2022 | BJ1: 1Q 2023 | BK1: 2Q 2023 | BL1: 3Q 2023 | BM1: 4Q 2023 | BN1: 1Q 2024 | BO1: 2Q 2024 | BP1: 3Q 2024 | BQ1: 4Q 2024 | BR1: 1Q 2025 | BS1: 2Q 2025 | BT1: 3Q 2025 | BU1: 4Q 2025 | BV1: 1Q 2026
J2: 40238 | K2: 40330 | L2: 40422 | M2: 40513 | N2: 40603 | O2: 40695 | P2: 40787 | Q2: 40878 | R2: 40969 | S2: 41061 | T2: 41153 | U2: 41244 | V2: 41334 | W2: 41426 | X2: 41518 | Y2: 41609 | Z2: 41699 | AA2: 41791 | AB2: 41883 | AC2: 41974 | AD2: 42064 | AE2: 42156 | AF2: 42248 | AG2: 42339 | AH2: 42430 | AI2: 42522 | AJ2: 42614 | AK2: 42705 | AL2: 42795 | AM2: 42887 | AN2: 42979 | AO2: 43070 | AP2: 43160 | AQ2: 43252 | AR2: 43344 | AS2: 43435 | AT2: 43525 | AU2: 43617 | AV2: 43709 | AW2: 43800 | AX2: 43891 | AY2: 43983 | AZ2: 44075 | BA2: 44166 | BB2: 44256 | BC2: 44348 | BD2: 44440 | BE2: 44531 | BF2: 44621 | BG2: 44713 | BH2: 44805 | BI2: 44896 | BJ2: 44986 | BK2: 45078 | BL2: 45170 | BM2: 45261 | BN2: 45352 | BO2: 45444 | BP2: 45536 | BQ2: 45627 | BR2: 45717 | BS2: 45809 | BT2: 45901 | BU2: 45992 | BV2: 46082
D3: 1101 !Q NA_ | E3: .DESC | F3: .T1 | G3: .SOURCE | H3: .AGG | I3: .DATA_TYPE | J3: 101 | K3: 102 | L3: 103 | M3: 104 | N3: 111 | O3: 112 | P3: 113 | Q3: 114 | R3: 121 | S3: 122 | T3: 123 | U3: 124 | V3: 131 | W3: 132 | X3: 133 | Y3: 134 | Z3: 141 | AA3: 142 | AB3: 143 | AC3: 144 | AD3: 151 | AE3: 152 | AF3: 153 | AG3: 154 | AH3: 161 | AI3: 162 | AJ3: 163 | AK3: 164 | AL3: 171 | AM3: 172 | AN3: 173 | AO3: 174 | AP3: 181 | AQ3: 182 | AR3: 183 | AS3: 184 | AT3: 191 | AU3: 192 | AV3: 193 | AW3: 194 | AX3: 201 | AY3: 202 | AZ3: 203 | BA3: 204 | BB3: 211 | BC3: 212 | BD3: 213 | BE3: 214 | BF3: 221 | BG3: 222 | BH3: 223 | BI3: 224 | BJ3: 231 | BK3: 232 | BL3: 233 | BM3: 234 | BN3: 241 | BO3: 242 | BP3: 243 | BQ3: 244 | BR3: 251 | BS3: 252 | BT3: 253 | BU3: 254 | BV3: 261
C4: CAB | D4: N213AC@EMERGELA | E4: Argentina: Balance of Payments: Current Account Balance (NSA, Mil.US$) | F4: Q1-1992 | G4: INDEC | H4: Sum | I4: US$ | J4: -1633 | K4: 2101 | L4: -529 | M4: -1563 | N4: -2242 | O4: 509 | P4: -1516 | Q4: -2091 | R4: -1782 | S4: 499 | T4: 66 | U4: -921 | V4: -3886 | W4: -326 | X4: -3022 | Y4: -5891 | Z4: -6048 | AA4: 646 | AB4: -1840 | AC4: -1938 | AD4: -5544 | AE4: -2469 | AF4: -4508 | AG4: -5101 | AH4: -4897 | AI4: -2931 | AJ4: -2967 | AK4: -4311 | AL4: -7235 | AM4: -6605 | AN4: -8149 | AO4: -9163 | AP4: -9396 | AQ4: -8434 | AR4: -7359 | AS4: -1894 | AT4: -3434 | AU4: -1812 | AV4: -808 | AW4: 2561 | AX4: 117 | AY4: 2863 | AZ4: 1150 | BA4: -1442 | BB4: 395 | BC4: 2547 | BD4: 3349 | BE4: 334 | BF4: -1243 | BG4: -953 | BH4: -3606 | BI4: 1837 | BJ4: -5874 | BK4: -6820 | BL4: -6401 | BM4: -3259 | BN4: 58 | BO4: 3503 | BP4: 625 | BQ4: 1705 | BR4: -5158 | BS4: -2452 | BT4: -2100 | BU4: 1922 | BV4: -1651
C5: Merchandise | D5: N213ACG@EMERGELA | E5: Argentina: Balance of Payments: Goods (NSA, Mil.US$) | F5: Q1-1986 | G5: INDEC | H5: Sum | I5: US$ | J5: 2521 | K5: 5937 | L5: 3532 | M5: 2157 | N5: 2083 | O5: 4900 | P5: 2810 | Q5: 2559 | R5: 3047 | S5: 4601 | T5: 4245 | U5: 3147 | V5: 1012 | W5: 3780 | X5: 1363 | Y5: -1519 | Z5: -2017 | AA5: 4303 | AB5: 1850 | AC5: 1406 | AD5: -866 | AE5: 1463 | AF5: -281 | AG5: -1101 | AH5: 176 | AI5: 1677 | AJ5: 1826 | AK5: 736 | AL5: -620 | AM5: -712 | AN5: -1679 | AO5: -2435 | AP5: -1665 | AQ5: -1696 | AR5: -746 | AS5: 3364 | AT5: 2550 | AU5: 4223 | AV5: 4471 | AW5: 6990 | AX5: 3926 | AY5: 5341 | AZ5: 4069 | BA5: 1295 | BB5: 3241 | BC5: 5168 | BD5: 6659 | BE5: 3627 | BF5: 2778 | BG5: 3214 | BH5: 925 | BI5: 5500 | BJ5: -312 | BK5: -2099 | BL5: -1284 | BM5: 937 | BN5: 5070 | BO5: 7109 | BP5: 5306 | BQ5: 4919 | BR5: 2060 | BS5: 2668 | BT5: 4348 | BU5: 6283 | BV5: 6339
C6: Services | D6: N213ACS@EMERGELA | E6: Argentina: Balance of Payments: Services (NSA, Mil.US$) | F6: Q1-1992 | G6: INDEC | H6: Sum | I6: US$ | J6: -571 | K6: -564 | L6: -534 | M6: -135 | N6: -852 | O6: -782 | P6: -883 | Q6: -636 | R6: -1223 | S6: -1029 | T6: -1016 | U6: -829 | V6: -1730 | W6: -1277 | X6: -1354 | Y6: -968 | Z6: -1551 | AA6: -1195 | AB6: -1121 | AC6: -775 | AD6: -1536 | AE6: -1247 | AF6: -1544 | AG6: -1489 | AH6: -2498 | AI6: -1927 | AJ6: -2225 | AK6: -1801 | AL6: -3061 | AM6: -2069 | AN6: -2549 | AO6: -2017 | AP6: -3397 | AQ6: -2537 | AR6: -1953 | AS6: -1049 | AT6: -1710 | AU6: -1291 | AV6: -1285 | AW6: -557 | AX6: -986 | AY6: -295 | AZ6: -602 | BA6: -654 | BB6: -659 | BC6: -641 | BD6: -1028 | BE6: -1373 | BF6: -1898 | BG6: -1781 | BH6: -1988 | BI6: -1108 | BJ6: -2317 | BK6: -1546 | BL6: -1638 | BM6: -875 | BN6: -1368 | BO6: -1054 | BP6: -1545 | BQ6: -971 | BR6: -4560 | BS6: -2433 | BT6: -2679 | BU6: -1930 | BV6: -4028
C7: Income | D7: N213ACY@EMERGELA | E7: Argentina: Balance of Payments: Primary Income (NSA, Mil.US$) | F7: Q1-1994 | G7: INDEC | H7: Sum | I7: US$ | J7: -3723 | K7: -3486 | L7: -3650 | M7: -3689 | N7: -3498 | O7: -3766 | P7: -3655 | Q7: -4154 | R7: -3756 | S7: -3271 | T7: -3329 | U7: -3397 | V7: -3343 | W7: -3281 | X7: -3263 | Y7: -3279 | Z7: -2783 | AA7: -2985 | AB7: -2992 | AC7: -2855 | AD7: -3223 | AE7: -3088 | AF7: -2886 | AG7: -2907 | AH7: -2895 | AI7: -2987 | AJ7: -2863 | AK7: -3448 | AL7: -3778 | AM7: -4033 | AN7: -3843 | AO7: -4726 | AP7: -4490 | AQ7: -4654 | AR7: -4898 | AS7: -4608 | AT7: -4558 | AU7: -4840 | AV7: -4219 | AW7: -4115 | AX7: -3088 | AY7: -2574 | AZ7: -2592 | BA7: -2251 | BB7: -2503 | BC7: -2414 | BD7: -2607 | BE7: -2249 | BF7: -2571 | BG7: -2972 | BH7: -2969 | BI7: -3065 | BJ7: -3719 | BK7: -3808 | BL7: -3967 | BM7: -3808 | BN7: -4140 | BO7: -3329 | BP7: -3503 | BQ7: -2848 | BR7: -3018 | BS7: -3566 | BT7: -4276 | BU7: -3219 | BV7: -4676
C8: Transfers | D8: N213ACT@EMERGELA | E8: Argentina: Balance of Payments: Secondary Income (NSA, Mil.US$) | F8: Q1-1994 | G8: INDEC | H8: Sum | I8: US$ | J8: 140 | K8: 215 | L8: 122 | M8: 104 | N8: 25 | O8: 158 | P8: 211 | Q8: 141 | R8: 150 | S8: 198 | T8: 167 | U8: 157 | V8: 176 | W8: 452 | X8: 231 | Y8: -125 | Z8: 303 | AA8: 523 | AB8: 423 | AC8: 286 | AD8: 81 | AE8: 403 | AF8: 203 | AG8: 396 | AH8: 321 | AI8: 306 | AJ8: 294 | AK8: 203 | AL8: 224 | AM8: 209 | AN8: -77 | AO8: 15 | AP8: 156 | AQ8: 452 | AR8: 238 | AS8: 399 | AT8: 285 | AU8: 96 | AV8: 224 | AW8: 244 | AX8: 265 | AY8: 392 | AZ8: 275 | BA8: 167 | BB8: 316 | BC8: 433 | BD8: 324 | BE8: 328 | BF8: 448 | BG8: 587 | BH8: 426 | BI8: 510 | BJ8: 473 | BK8: 633 | BL8: 488 | BM8: 486 | BN8: 496 | BO8: 776 | BP8: 367 | BQ8: 606 | BR8: 360 | BS8: 878 | BT8: 506 | BU8: 788 | BV8: 714
BD10: =BD11-BD12 -> -1145
C11: K account | D11: N213AK@EMERGELA | E11: Argentina: Balance of Payments: Capital Account (NSA, Mil.US$) | F11: Q1-2006 | G11: INDEC | H11: Sum | I11: US$ | J11: 17 | K11: 4 | L11: 55 | M11: 3 | N11: 16 | O11: 1 | P11: 45 | Q11: 1 | R11: 1 | S11: 22 | T11: 28 | U11: -4 | V11: 1 | W11: 0 | X11: 33 | Y11: -1 | Z11: 2 | AA11: 16 | AB11: 40 | AC11: -1 | AD11: 10 | AE11: 3 | AF11: 39 | AG11: 1 | AH11: 83 | AI11: 32 | AJ11: 109 | AK11: 141 | AL11: 45 | AM11: 44 | AN11: 79 | AO11: 6 | AP11: 24 | AQ11: 21 | AR11: 47 | AS11: 19 | AT11: 37 | AU11: 139 | AV11: 80 | AW11: 27 | AX11: 42 | AY11: 32 | AZ11: 40 | BA11: 50 | BB11: 46 | BC11: 94 | BD11: 70 | BE11: 43 | BF11: 34 | BG11: 27 | BH11: 81 | BI11: 49 | BJ11: 27 | BK11: 49 | BL11: 38 | BM11: 77 | BN11: 95 | BO11: 57 | BP11: 45 | BQ11: 81 | BR11: 59 | BS11: 172 | BT11: 137 | BU11: 86 | BV11: 63
C12: F. account | D12: N213AF@EMERGELA | E12: Argentina: Balance of Payments: Financial Account (NSA, Mil.US$) | F12: Q1-2006 | G12: INDEC | H12: Sum | I12: US$ | J12: -1661 | K12: 937 | L12: -817 | M12: -2262 | N12: -1876 | O12: 168 | P12: -3477 | Q12: -67 | R12: -2005 | S12: 259 | T12: -519 | U12: -523 | V12: -4668 | W12: -734 | X12: -4239 | Y12: -6524 | Z12: -4503 | AA12: 432 | AB12: -2167 | AC12: -3083 | AD12: -5612 | AE12: -2498 | AF12: -5404 | AG12: -4984 | AH12: -4731 | AI12: -3104 | AJ12: -4656 | AK12: -1473 | AL12: -6224 | AM12: -6971 | AN12: -8878 | AO12: -9200 | AP12: -9547 | AQ12: -9002 | AR12: -7853 | AS12: -1635 | AT12: -3639 | AU12: -2373 | AV12: -1538 | AW12: 2431 | AX12: -512 | AY12: 3825 | AZ12: -376 | BA12: -1576 | BB12: 1410 | BC12: 1305 | BD12: 1215 | BE12: 572 | BF12: -1739 | BG12: -3118 | BH12: -3456 | BI12: 876 | BJ12: -7538 | BK12: -7003 | BL12: -7307 | BM12: -4066 | BN12: -833 | BO12: 2578 | BP12: -814 | BQ12: 1388 | BR12: -7189 | BS12: -3348 | BT12: -3658 | BU12: 2193 | BV12: -2398
C13: Net FDI | D13: N213AFI@EMERGELA | E13: Argentina: BOP: Fin Acct, Total Direct Investment (NSA, Mil.US$) | F13: Q1-2006 | G13: INDEC | H13: Sum | I13: US$ | J13: -3159 | K13: -1899 | L13: -2906 | M13: -2404 | N13: -3214 | O13: -632 | P13: -1390 | Q13: -4116 | R13: -4154 | S13: -3612 | T13: -3106 | U13: -3397 | V13: -1941 | W13: -2920 | X13: -2513 | Y13: -1557 | Z13: -39 | AA13: 1744 | AB13: -2055 | AC13: -2795 | AD13: -3273 | AE13: -3175 | AF13: -2450 | AG13: -1985 | AH13: -1852 | AI13: 407 | AJ13: -703 | AK13: 674 | AL13: -3174 | AM13: -2021 | AN13: -3043 | AO13: -2124 | AP13: -2471 | AQ13: -2211 | AR13: -2656 | AS13: -2654 | AT13: -1969 | AU13: -381 | AV13: -1231 | AW13: -1546 | AX13: -1594 | AY13: 387 | AZ13: -1250 | BA13: -1250 | BB13: -2214 | BC13: -1583 | BD13: -339 | BE13: -979 | BF13: -3055 | BG13: -4290 | BH13: -5421 | BI13: -349 | BJ13: -4006 | BK13: -5631 | BL13: -6798 | BM13: -6809 | BN13: -5022 | BO13: -1670 | BP13: -3117 | BQ13: 218 | BR13: -313 | BS13: -1984 | BT13: -4302 | BU13: 4981 | BV13: -1291
C14: P. flows | D14: N213AFP@EMERGELA | E14: Argentina: BOP: Fin Accnt: Portfolio Investment (NSA, Mil.US$) | F14: Q1-2006 | G14: INDEC | H14: Sum | I14: US$ | J14: -211 | K14: -1083 | L14: -309 | M14: -1659 | N14: -695 | O14: -85 | P14: -143 | Q14: 780 | R14: -1906 | S14: 426 | T14: 1401 | U14: 229 | V14: -278 | W14: 945 | X14: 190 | Y14: -1289 | Z14: -1164 | AA14: 4127 | AB14: -445 | AC14: -179 | AD14: -1185 | AE14: -1308 | AF14: -414 | AG14: 2470 | AH14: -4678 | AI14: -10691 | AJ14: -7707 | AK14: -12178 | AL14: -14043 | AM14: -3760 | AN14: -7208 | AO14: -10910 | AP14: -12953 | AQ14: 1874 | AR14: 1902 | AS14: 2253 | AT14: 362 | AU14: 6026 | AV14: -111 | AW14: 831 | AX14: -676 | AY14: 1259 | AZ14: 2268 | BA14: -1281 | BB14: 1892 | BC14: 1246 | BD14: 986 | BE14: 818 | BF14: 2333 | BG14: 1854 | BH14: 2057 | BI14: 1219 | BJ14: 3001 | BK14: 966 | BL14: 2422 | BM14: 520 | BN14: -2755 | BO14: -583 | BP14: 4136 | BQ14: 3331 | BR14: 3251 | BS14: -1976 | BT14: 3471 | BU14: -4468 | BV14: 657
C15: F. derivatives | D15: N213AFV@EMERGELA | E15: Argentina: BOP: Fin Accnt: Financial Derivatives (NSA, Mil.US$) | F15: Q1-2006 | G15: INDEC | H15: Sum | I15: US$ | J15: 23 | K15: 84 | L15: -799 | M15: -21 | N15: 36 | O15: 161 | P15: 33 | Q15: 2126 | R15: 9 | S15: 1 | T15: 26 | U15: 2873 | V15: -12 | W15: -14 | X15: 2 | Y15: -7 | Z15: 36 | AA15: -163 | AB15: -34 | AC15: -6 | AD15: -12 | AE15: -5 | AF15: -1 | AG15: -7 | AH15: 32 | AI15: 366 | AJ15: -32 | AK15: -144 | AL15: -140 | AM15: 7 | AN15: 11 | AO15: 26 | AP15: -27 | AQ15: -4 | AR15: 30 | AS15: -32 | AT15: -24 | AU15: -45 | AV15: 33 | AW15: 11 | AX15: 0 | AY15: 3 | AZ15: -1 | BA15: 7 | BB15: -3 | BC15: 0 | BD15: 0 | BE15: -13 | BF15: 1 | BG15: 2 | BH15: -5 | BI15: 6 | BJ15: 3 | BK15: -2 | BL15: -2 | BM15: 10 | BN15: 1 | BO15: -6 | BP15: 18 | BQ15: 6 | BR15: -9 | BS15: -6 | BT15: -21 | BU15: 39 | BV15: -10
C16: O. investments | D16: N213AFO@EMERGELA | E16: Argentina: BOP: Financial Account, Other Investments (NSA, Mil.US$) | F16: Q1-2006 | G16: INDEC | H16: Sum | I16: US$ | J16: 1990 | K16: 1730 | L16: 1919 | M16: 744 | N16: 3156 | O16: 498 | P16: 1177 | Q16: 3164 | R16: 3376 | S16: 4143 | T16: 2886 | U16: 1322 | V16: 148 | W16: 3966 | X16: 668 | Y16: 274 | Z16: 397 | AA16: -7460 | AB16: 1350 | AC16: -3829 | AD16: -1481 | AE16: -309 | AF16: -2313 | AG16: 1856 | AH16: -1778 | AI16: 5741 | AJ16: 4356 | AK16: -87 | AL16: 194 | AM16: 1607 | AN16: -523 | AO16: -728 | AP16: -250 | AQ16: -9402 | AR16: 5157 | AS16: -17872 | AT16: -1964 | AU16: -6200 | AV16: 14594 | AW16: 7868 | AX16: 2847 | AY16: 2968 | AZ16: 1643 | BA16: 3758 | BB16: 1055 | BC16: -760 | BD16: 116 | BE16: 4386 | BF16: -4210 | BG16: -1967 | BH16: 3438 | BI16: -5968 | BJ16: -532 | BK16: 7721 | BL16: -2041 | BM16: 6937 | BN16: 2864 | BO16: 3143 | BP16: 1119 | BQ16: -5459 | BR16: -4490 | BS16: -13655 | BT16: -2351 | BU16: 2609 | BV16: -1764
C17: Change reserves | D17: N213AFRA@EMERGELA | E17: Argentina: Balance of Payments: Change in Intl Reserves (NSA, Mil.US$) | F17: Q1-2006 | G17: INDEC | H17: Sum | I17: US$ | J17: -304 | K17: 2104 | L17: 1279 | M17: 1078 | N17: -1159 | O17: 226 | P17: -3154 | Q17: -2021 | R17: 670 | S17: -699 | T17: -1726 | U17: -1549 | V17: -2583 | W17: -2711 | X17: -2585 | Y17: -3945 | Z17: -3733 | AA17: 2184 | AB17: -983 | AC17: 3727 | AD17: 339 | AE17: 2300 | AF17: -227 | AG17: -7318 | AH17: 3545 | AI17: 1074 | AJ17: -569 | AK17: 10262 | AL17: 10938 | AM17: -2804 | AN17: 1885 | AO17: 4537 | AP17: 6153 | AQ17: 741 | AR17: -12287 | AS17: 16670 | AT17: -45 | AU17: -1773 | AV17: -14823 | AW17: -4733 | AX17: -1089 | AY17: -793 | AZ17: -3036 | BA17: -2809 | BB17: 680 | BC17: 2403 | BD17: 452 | BE17: -3640 | BF17: 3192 | BG17: 1283 | BH17: -3525 | BI17: 5969 | BJ17: -6004 | BK17: -10058 | BL17: -889 | BM17: -4724 | BN17: 4078 | BO17: 1694 | BP17: -2971 | BQ17: 3292 | BR17: -5628 | BS17: 14271 | BT17: -454 | BU17: -968 | BV17: 11
C19: Errors and omission | D19: N213AERR@EMERGELA | E19: Argentina: Balance of Payments: Errors and Omissions (NSA, Mil.US$) | F19: Q1-2006 | G19: INDEC | H19: Sum | I19: US$ | J19: -46 | K19: -1168 | L19: -342 | M19: -702 | N19: 349 | O19: -342 | P19: -2006 | Q19: 2023 | R19: -223 | S19: -262 | T19: -614 | U19: 402 | V19: -783 | W19: -409 | X19: -1249 | Y19: -633 | Z19: 1543 | AA19: -231 | AB19: -367 | AC19: -1144 | AD19: -77 | AE19: -32 | AF19: -935 | AG19: 116 | AH19: 82 | AI19: -205 | AJ19: -1798 | AK19: 2697 | AL19: 965 | AM19: -409 | AN19: -809 | AO19: -42 | AP19: -175 | AQ19: -588 | AR19: -541 | AS19: 241 | AT19: -243 | AU19: -700 | AV19: -810 | AW19: -158 | AX19: -671 | AY19: 930 | AZ19: -1566 | BA19: -184 | BB19: 968 | BC19: -1336 | BD19: -2204 | BE19: 195 | BF19: -531 | BG19: -2193 | BH19: 68 | BI19: -1010 | BJ19: -1690 | BK19: -232 | BL19: -944 | BM19: -885 | BN19: -986 | BO19: -981 | BP19: -1485 | BQ19: -398 | BR19: -2091 | BS19: -1068 | BT19: -1694 | BU19: 184 | BV19: -811
C21: GDP | D21: N213NGPD@EMERGELA | E21: Argentina: GDP at Current Prices & Exchange Rates(NSA, Bil.US$) | F21: Q1-1993 | G21: INDEC/H | H21: Sum | I21: US$ | J21: 92.498 | K21: 108.599 | L21: 109.191 | M21: 115.847 | N21: 118.227 | O21: 137.686 | P21: 135.671 | Q21: 138.032 | R21: 135.5 | S21: 149.417 | T21: 147.097 | U21: 148.837 | V21: 144.477 | W21: 162.05 | X21: 154.289 | Y21: 152.224 | Z21: 129.177 | AA21: 146.844 | AB21: 141.936 | AC21: 148.064 | AD21: 147.289 | AE21: 166.789 | AF21: 168.968 | AG21: 161.183 | AH21: 121.31 | AI21: 147.808 | AJ21: 142.667 | AK21: 145.35 | AL21: 147.4 | AM21: 167.762 | AN21: 160.762 | AO21: 166.965 | AP21: 157.004 | AQ21: 153.567 | AR21: 119.255 | AS21: 113.529 | AT21: 112.069 | AU21: 121.039 | AV21: 110.536 | AW21: 106.315 | AX21: 101.797 | AY21: 88.88 | AZ21: 94.01 | BA21: 100.925 | BB21: 103.954 | BC21: 123.279 | BD21: 122.148 | BE21: 135.204 | BF21: 141.679 | BG21: 166.899 | BH21: 161.877 | BI21: 160.607 | BJ21: 158.949 | BK21: 172.575 | BL21: 166.808 | BM21: 158.881 | BN21: 129.61 | BO21: 158.098 | BP21: 169.36 | BQ21: 177.162 | BR21: 172.832 | BS21: 182.106 | BT21: 167.101 | BU21: 165.419 | BV21: 172.274
C23: CAB | M23: =SUM(J4:M4) -> -1624 | N23: =SUM(K4:N4) -> -2233 | O23: =SUM(L4:O4) -> -3825 | P23: =SUM(M4:P4) -> -4812 | Q23: =SUM(N4:Q4) -> -5340 | R23: =SUM(O4:R4) -> -4880 | S23: =SUM(P4:S4) -> -4890 | T23: =SUM(Q4:T4) -> -3308 | ... BV23: =SUM(BS4:BV4) -> -4281
C24: Merchandise | M24: =SUM(J5:M5) -> 14147 | N24: =SUM(K5:N5) -> 13709 | O24: =SUM(L5:O5) -> 12672 | P24: =SUM(M5:P5) -> 11950 | Q24: =SUM(N5:Q5) -> 12352 | R24: =SUM(O5:R5) -> 13316 | S24: =SUM(P5:S5) -> 13017 | T24: =SUM(Q5:T5) -> 14452 | ... BV24: =SUM(BS5:BV5) -> 19638
C25: Services | M25: =SUM(J6:M6) -> -1804 | N25: =SUM(K6:N6) -> -2085 | O25: =SUM(L6:O6) -> -2303 | P25: =SUM(M6:P6) -> -2652 | Q25: =SUM(N6:Q6) -> -3153 | R25: =SUM(O6:R6) -> -3524 | S25: =SUM(P6:S6) -> -3771 | T25: =SUM(Q6:T6) -> -3904 | ... BV25: =SUM(BS6:BV6) -> -11070
C26: Income | M26: =SUM(J7:M7) -> -14548 | N26: =SUM(K7:N7) -> -14323 | O26: =SUM(L7:O7) -> -14603 | P26: =SUM(M7:P7) -> -14608 | Q26: =SUM(N7:Q7) -> -15073 | R26: =SUM(O7:R7) -> -15331 | S26: =SUM(P7:S7) -> -14836 | T26: =SUM(Q7:T7) -> -14510 | ... BV26: =SUM(BS7:BV7) -> -15737
C27: Transfers | M27: =SUM(J8:M8) -> 581 | N27: =SUM(K8:N8) -> 466 | O27: =SUM(L8:O8) -> 409 | P27: =SUM(M8:P8) -> 498 | Q27: =SUM(N8:Q8) -> 535 | R27: =SUM(O8:R8) -> 660 | S27: =SUM(P8:S8) -> 700 | T27: =SUM(Q8:T8) -> 656 | ... BV27: =SUM(BS8:BV8) -> 2886
C30: K account | M30: =SUM(J11:M11) -> 79 | N30: =SUM(K11:N11) -> 78 | O30: =SUM(L11:O11) -> 75 | P30: =SUM(M11:P11) -> 65 | Q30: =SUM(N11:Q11) -> 63 | R30: =SUM(O11:R11) -> 48 | S30: =SUM(P11:S11) -> 69 | T30: =SUM(Q11:T11) -> 52 | ... BV30: =SUM(BS11:BV11) -> 458
C31: F. account | M31: =-SUM(J12:M12) -> 3803 | N31: =-SUM(K12:N12) -> 4018 | O31: =-SUM(L12:O12) -> 4787 | P31: =-SUM(M12:P12) -> 7447 | Q31: =-SUM(N12:Q12) -> 5252 | R31: =-SUM(O12:R12) -> 5381 | S31: =-SUM(P12:S12) -> 5290 | T31: =-SUM(Q12:T12) -> 2332 | ... BV31: =-SUM(BS12:BV12) -> 7211
C32: Net FDI | M32: =-SUM(J13:M13) -> 10368 | N32: =-SUM(K13:N13) -> 10423 | O32: =-SUM(L13:O13) -> 9156 | P32: =-SUM(M13:P13) -> 7640 | Q32: =-SUM(N13:Q13) -> 9352 | R32: =-SUM(O13:R13) -> 10292 | S32: =-SUM(P13:S13) -> 13272 | T32: =-SUM(Q13:T13) -> 14988 | ... BV32: =-SUM(BS13:BV13) -> 2596
C33: P. flows | M33: =-SUM(J14:M14) -> 3262 | N33: =-SUM(K14:N14) -> 3746 | O33: =-SUM(L14:O14) -> 2748 | P33: =-SUM(M14:P14) -> 2582 | Q33: =-SUM(N14:Q14) -> 143 | R33: =-SUM(O14:R14) -> 1354 | S33: =-SUM(P14:S14) -> 843 | T33: =-SUM(Q14:T14) -> -701 | ... BV33: =-SUM(BS14:BV14) -> 2316
C34: F. derivatives | M34: =-SUM(J15:M15) -> 713 | N34: =-SUM(K15:N15) -> 700 | O34: =-SUM(L15:O15) -> 623 | P34: =-SUM(M15:P15) -> -209 | Q34: =-SUM(N15:Q15) -> -2356 | R34: =-SUM(O15:R15) -> -2329 | S34: =-SUM(P15:S15) -> -2169 | T34: =-SUM(Q15:T15) -> -2162 | ... BV34: =-SUM(BS15:BV15) -> -2
C35: O. investments | M35: =-SUM(J16:M16) -> -6383 | N35: =-SUM(K16:N16) -> -7549 | O35: =-SUM(L16:O16) -> -6317 | P35: =-SUM(M16:P16) -> -5575 | Q35: =-SUM(N16:Q16) -> -7995 | R35: =-SUM(O16:R16) -> -8215 | S35: =-SUM(P16:S16) -> -11860 | T35: =-SUM(Q16:T16) -> -13569 | ... BV35: =-SUM(BS16:BV16) -> 15161
C36: Change reserves | M36: =-SUM(J17:M17) -> -4157 | N36: =-SUM(K17:N17) -> -3302 | O36: =-SUM(L17:O17) -> -1424 | P36: =-SUM(M17:P17) -> 3009 | Q36: =-SUM(N17:Q17) -> 6108 | R36: =-SUM(O17:R17) -> 4279 | S36: =-SUM(P17:S17) -> 5204 | T36: =-SUM(Q17:T17) -> 3776 | ... BV36: =-SUM(BS17:BV17) -> -12860
C38: Errors and omission | M38: =SUM(J19:M19) -> -2258 | N38: =SUM(K19:N19) -> -1863 | O38: =SUM(L19:O19) -> -1037 | P38: =SUM(M19:P19) -> -2701 | Q38: =SUM(N19:Q19) -> 24 | R38: =SUM(O19:R19) -> -548 | S38: =SUM(P19:S19) -> -468 | T38: =SUM(Q19:T19) -> 924 | ... BV38: =SUM(BS19:BV19) -> -3389
C40: GDP | M40: =SUM(J21:M21) -> 426.135 | N40: =SUM(K21:N21) -> 451.864 | O40: =SUM(L21:O21) -> 480.951 | P40: =SUM(M21:P21) -> 507.431 | Q40: =SUM(N21:Q21) -> 529.616 | R40: =SUM(O21:R21) -> 546.889 | S40: =SUM(P21:S21) -> 558.62 | T40: =SUM(Q21:T21) -> 570.046 | ... BV40: =SUM(BS21:BV21) -> 686.9
C43: % of GDP
C44: CAB | M44: =(M23/1000)/M$40*100 -> -0.38109989 | N44: =(N23/1000)/N$40*100 -> -0.49417524 | O44: =(O23/1000)/O$40*100 -> -0.79529931 | P44: =(P23/1000)/P$40*100 -> -0.94830627 | Q44: =(Q23/1000)/Q$40*100 -> -1.0082777 | R44: =(R23/1000)/R$40*100 -> -0.89232001 | S44: =(S23/1000)/S$40*100 -> -0.87537145 | T44: =(T23/1000)/T$40*100 -> -0.58030405 | ... BV44: =(BV23/1000)/BV$40*100 -> -0.62323482
C45: Merchandise | M45: =(M24/1000)/M$40*100 -> 3.31984 | N45: =(N24/1000)/N$40*100 -> 3.0338774 | O45: =(O24/1000)/O$40*100 -> 2.6347798 | P45: =(P24/1000)/P$40*100 -> 2.355 | Q45: =(Q24/1000)/Q$40*100 -> 2.3322558 | R45: =(R24/1000)/R$40*100 -> 2.4348634 | S45: =(S24/1000)/S$40*100 -> 2.3302066 | T45: =(T24/1000)/T$40*100 -> 2.535234 | ... BV45: =(BV24/1000)/BV$40*100 -> 2.8589314
C46: Services | M46: =(M25/1000)/M$40*100 -> -0.42334002 | N46: =(N25/1000)/N$40*100 -> -0.46142202 | O46: =(O25/1000)/O$40*100 -> -0.47884296 | P46: =(P25/1000)/P$40*100 -> -0.52263263 | Q46: =(Q25/1000)/Q$40*100 -> -0.595337 | R46: =(R25/1000)/R$40*100 -> -0.64437208 | S46: =(S25/1000)/S$40*100 -> -0.67505639 | T46: =(T25/1000)/T$40*100 -> -0.68485701 | ... BV46: =(BV25/1000)/BV$40*100 -> -1.6115883
C47: Income | M47: =(M26/1000)/M$40*100 -> -3.4139416 | N47: =(N26/1000)/N$40*100 -> -3.169759 | O47: =(O26/1000)/O$40*100 -> -3.036276 | P47: =(P26/1000)/P$40*100 -> -2.8788151 | Q47: =(Q26/1000)/Q$40*100 -> -2.8460243 | R47: =(R26/1000)/R$40*100 -> -2.8033111 | S47: =(S26/1000)/S$40*100 -> -2.6558304 | T47: =(T26/1000)/T$40*100 -> -2.5454086 | ... BV47: =(BV26/1000)/BV$40*100 -> -2.2910176
C48: Transfers | M48: =(M27/1000)/M$40*100 -> 0.13634177 | N48: =(N27/1000)/N$40*100 -> 0.10312837 | O48: =(O27/1000)/O$40*100 -> 0.085039848 | P48: =(P27/1000)/P$40*100 -> 0.098141422 | Q48: =(Q27/1000)/Q$40*100 -> 0.10101659 | R48: =(R27/1000)/R$40*100 -> 0.12068262 | S48: =(S27/1000)/S$40*100 -> 0.1253088 | T48: =(T27/1000)/T$40*100 -> 0.11507843 | ... BV48: =(BV27/1000)/BV$40*100 -> 0.42014849
C51: K account | M51: =(M30/1000)/M$40*100 -> 0.018538726 | N51: =(N30/1000)/N$40*100 -> 0.017261831 | O51: =(O30/1000)/O$40*100 -> 0.015594104 | P51: =(P30/1000)/P$40*100 -> 0.012809623 | Q51: =(Q30/1000)/Q$40*100 -> 0.011895411 | R51: =(R30/1000)/R$40*100 -> 0.0087769182 | S51: =(S30/1000)/S$40*100 -> 0.012351867 | T51: =(T30/1000)/T$40*100 -> 0.0091220709 | ... BV51: =(BV30/1000)/BV$40*100 -> 0.066676372
C52: F. account | M52: =-(M31/1000)/M$40*100 -> -0.89244019 | N52: =-(N31/1000)/N$40*100 -> -0.8892056 | O52: =-(O31/1000)/O$40*100 -> -0.99531969 | P52: =-(P31/1000)/P$40*100 -> -1.4675887 | Q52: =-(Q31/1000)/Q$40*100 -> -0.99166188 | R52: =-(R31/1000)/R$40*100 -> -0.9839291 | S52: =-(S31/1000)/S$40*100 -> -0.94697648 | T52: =-(T31/1000)/T$40*100 -> -0.40908979 | ... AH52: =-(AH31/1000)/AH$40*100 -> -2.8494945 | AI52: =(AI31/1000)/AI$40*100 -> 3.0408715 | AJ52: =(AJ31/1000)/AJ$40*100 -> 3.0499085 | AK52: =(AK31/1000)/AK$40*100 -> 2.5063943 | AL52: =(AL31/1000)/AL$40*100 -> 2.6502636 | AM52: =(AM31/1000)/AM$40*100 -> 3.2036924 | AN52: =(AN31/1000)/AN$40*100 -> 3.7899542 | AO52: =(AO31/1000)/AO$40*100 -> 4.8644478 | AP52: =(AP31/1000)/AP$40*100 -> 5.3021258 | ... BV52: =(BV31/1000)/BV$40*100 -> 1.0497889
C53: Net FDI | M53: =-(M32/1000)/M$40*100 -> -2.4330318 | N53: =-(N32/1000)/N$40*100 -> -2.3066675 | O53: =-(O32/1000)/O$40*100 -> -1.9037282 | P53: =-(P32/1000)/P$40*100 -> -1.5056234 | Q53: =-(Q32/1000)/Q$40*100 -> -1.7658077 | R53: =-(R32/1000)/R$40*100 -> -1.8819175 | S53: =-(S32/1000)/S$40*100 -> -2.3758548 | T53: =-(T32/1000)/T$40*100 -> -2.6292615 | ... AH53: =-(AH32/1000)/AH$40*100 -> -1.5304488 | AI53: =(AI32/1000)/AI$40*100 -> 0.98119542 | AJ53: =(AJ32/1000)/AJ$40*100 -> 0.72133173 | AK53: =(AK32/1000)/AK$40*100 -> 0.26456783 | AL53: =(AL32/1000)/AL$40*100 -> 0.47940332 | AM53: =(AM32/1000)/AM$40*100 -> 0.8660779 | AN53: =(AN32/1000)/AN$40*100 -> 1.2174982 | AO53: =(AO32/1000)/AO$40*100 -> 1.6117868 | AP53: =(AP32/1000)/AP$40*100 -> 1.4803224 | ... BV53: =(BV32/1000)/BV$40*100 -> 0.37792983
C54: P. flows | M54: =-(M33/1000)/M$40*100 -> -0.76548512 | N54: =-(N33/1000)/N$40*100 -> -0.8290105 | O54: =-(O33/1000)/O$40*100 -> -0.57136798 | P54: =-(P33/1000)/P$40*100 -> -0.50883765 | Q54: =-(Q33/1000)/Q$40*100 -> -0.027000695 | R54: =-(R33/1000)/R$40*100 -> -0.24758223 | S54: =-(S33/1000)/S$40*100 -> -0.15090759 | T54: =-(T33/1000)/T$40*100 -> 0.12297253 | ... AH54: =-(AH33/1000)/AH$40*100 -> -0.63566518 | AI54: =(AI33/1000)/AI$40*100 -> 2.2215399 | AJ54: =(AJ33/1000)/AJ$40*100 -> 3.5963614 | AK54: =(AK33/1000)/AK$40*100 -> 6.3277303 | AL54: =(AL33/1000)/AL$40*100 -> 7.6503922 | AM54: =(AM33/1000)/AM$40*100 -> 6.2482281 | AN54: =(AN33/1000)/AN$40*100 -> 5.9859257 | AO54: =(AO33/1000)/AO$40*100 -> 5.5874342 | AP54: =(AP33/1000)/AP$40*100 -> 5.3381416 | ... BV54: =(BV33/1000)/BV$40*100 -> 0.33716698
C55: F. derivatives | M55: =-(M34/1000)/M$40*100 -> -0.16731787 | N55: =-(N34/1000)/N$40*100 -> -0.15491387 | O55: =-(O34/1000)/O$40*100 -> -0.12953503 | P55: =-(P34/1000)/P$40*100 -> 0.041187866 | Q55: =-(Q34/1000)/Q$40*100 -> 0.44485061 | R55: =-(R34/1000)/R$40*100 -> 0.42586338 | S55: =-(S34/1000)/S$40*100 -> 0.38827826 | T55: =-(T34/1000)/T$40*100 -> 0.37926764 | ... AH55: =-(AH34/1000)/AH$40*100 -> 0.0030731905 | AI55: =(AI34/1000)/AI$40*100 -> -0.065079288 | AJ55: =(AJ34/1000)/AJ$40*100 -> -0.062656204 | AK55: =(AK34/1000)/AK$40*100 -> -0.039846716 | AL55: =(AL34/1000)/AL$40*100 -> -0.0085730207 | AM55: =(AM34/1000)/AM$40*100 -> 0.051228574 | AN55: =(AN34/1000)/AN$40*100 -> 0.042815247 | AO55: =(AO34/1000)/AO$40*100 -> 0.014932593 | AP55: =(AP34/1000)/AP$40*100 -> -0.0026053919 | ... BV55: =(BV34/1000)/BV$40*100 -> -0.0002911632
C56: O. investments | M56: =-(M35/1000)/M$40*100 -> 1.4978821 | N56: =-(N35/1000)/N$40*100 -> 1.6706354 | O56: =-(O35/1000)/O$40*100 -> 1.3134394 | P56: =-(P35/1000)/P$40*100 -> 1.0986715 | Q56: =-(Q35/1000)/Q$40*100 -> 1.5095843 | R56: =-(R35/1000)/R$40*100 -> 1.502133 | S56: =-(S35/1000)/S$40*100 -> 2.123089 | T56: =-(T35/1000)/T$40*100 -> 2.3803342 | ... AH56: =-(AH35/1000)/AH$40*100 -> -0.41148403 | AI56: =(AI35/1000)/AI$40*100 -> -0.58504611 | AJ56: =(AJ35/1000)/AJ$40*100 -> -1.7758409 | AK56: =(AK35/1000)/AK$40*100 -> -1.4775593 | AL56: =(AL35/1000)/AL$40*100 -> -1.7495821 | AM56: =(AM35/1000)/AM$40*100 -> -1.0063348 | AN56: =(AN35/1000)/AN$40*100 -> -0.19170286 | AO56: =(AO35/1000)/AO$40*100 -> -0.085551316 | AP56: =(AP35/1000)/AP$40*100 -> -0.016245385 | ... BV56: =(BV35/1000)/BV$40*100 -> 2.2071626
C57: Change reserves | M57: =-(M36/1000)/M$40*100 -> 0.97551245 | N57: =-(N36/1000)/N$40*100 -> 0.73075085 | O57: =-(O36/1000)/O$40*100 -> 0.29608006 | P57: =-(P36/1000)/P$40*100 -> -0.59298703 | Q57: =-(Q36/1000)/Q$40*100 -> -1.1532884 | R57: =-(R36/1000)/R$40*100 -> -0.78242568 | S57: =-(S36/1000)/S$40*100 -> -0.9315814 | T57: =-(T36/1000)/T$40*100 -> -0.66240268 | ... AH57: =-(AH36/1000)/AH$40*100 -> -0.27496967 | AI57: =(AI36/1000)/AI$40*100 -> 0.48826153 | AJ57: =(AJ36/1000)/AJ$40*100 -> 0.57036344 | AK57: =(AK36/1000)/AK$40*100 -> -2.5688567 | AL57: =(AL36/1000)/AL$40*100 -> -3.7215483 | AM57: =(AM36/1000)/AM$40*100 -> -2.9555074 | AN57: =(AN36/1000)/AN$40*100 -> -3.2644212 | AO57: =(AO36/1000)/AO$40*100 -> -2.2641545 | AP57: =(AP36/1000)/AP$40*100 -> -1.4974873 | ... BV57: =(BV36/1000)/BV$40*100 -> -1.8721794
C59: Errors and omission
C61: GDP
AO65: 2100000 | AP65: =AO65/12*1.333 -> 233275
AO66: 600000
AO69: 2350000
AO70: =AO69/20.5 -> 114634.15

Sheet Net reserves
H1: 2012 | I1: 2013 | J1: 2014 | K1: 2015 | L1: 2016 | M1: 2017 | N1: 2018 | O1: 2019 | P1: 2020 | Q1: 2021 | R1: 2022 | S1: 2023
A2: Central bank gross FX reserves ($bn) | H2: =OFFSET($S$11,0,12*(H8-1),1,1)/1000 -> 43.29 | I2: =OFFSET($S$11,0,12*(I8-1),1,1)/1000 -> 30.599 | J2: =OFFSET($S$11,0,12*(J8-1),1,1)/1000 -> 31.407 | K2: =OFFSET($S$11,0,12*(K8-1),1,1)/1000 -> 25.563 | L2: =OFFSET($S$11,0,12*(L8-1),1,1)/1000 -> 39.308 | M2: =OFFSET($S$11,0,12*(M8-1),1,1)/1000 -> 55.055 | N2: =OFFSET($S$11,0,12*(N8-1),1,1)/1000 -> 65.786 | O2: =OFFSET($S$11,0,12*(O8-1),1,1)/1000 -> 44.848 | ... S2: =OFFSET($S$11,0,12*(S8-1),1,1)/1000 -> 23.073
A3: Central bank net FX reserves ($bn) | H3: =OFFSET($S$12,0,12*(H8-1),1,1)/1000 -> 33.858245 | I3: =OFFSET($S$12,0,12*(I8-1),1,1)/1000 -> 16.190752 | J3: =OFFSET($S$12,0,12*(J8-1),1,1)/1000 -> 17.017012 | K3: =OFFSET($S$12,0,12*(K8-1),1,1)/1000 -> 0.51824404 | L3: =OFFSET($S$12,0,12*(L8-1),1,1)/1000 -> 10.199107 | M3: =OFFSET($S$12,0,12*(M8-1),1,1)/1000 -> 27.697552 | N3: =OFFSET($S$12,0,12*(N8-1),1,1)/1000 -> 29.260467 | O3: =OFFSET($S$12,0,12*(O8-1),1,1)/1000 -> 13.370597 | ... S3: =OFFSET($S$12,0,12*(S8-1),1,1)/1000 -> -10.458519 | EW3: Word
A4: Central bank gross non-gold FX reserves ($bn) | H4: =OFFSET($S$16,0,12*(H8-1),1,1)/1000 -> 39.963529 | I4: =OFFSET($S$16,0,12*(I8-1),1,1)/1000 -> 28.209528 | J4: =OFFSET($S$16,0,12*(J8-1),1,1)/1000 -> 29.052215 | K4: =OFFSET($S$16,0,12*(K8-1),1,1)/1000 -> 23.456067 | L4: =OFFSET($S$16,0,12*(L8-1),1,1)/1000 -> 37.206251 | M4: =OFFSET($S$16,0,12*(M8-1),1,1)/1000 -> 52.756225 | N4: =OFFSET($S$16,0,12*(N8-1),1,1)/1000 -> 63.530377 | O4: =OFFSET($S$16,0,12*(O8-1),1,1)/1000 -> 42.163534 | ... S4: =OFFSET($S$16,0,12*(S8-1),1,1)/1000 -> 18.977127
A6: Repos | H6: =OFFSET($S$13,0,12*(H8-1),1,1)/1000 -> 0.931857 | I6: =OFFSET($S$13,0,12*(I8-1),1,1)/1000 -> 1.046064 | J6: =OFFSET($S$13,0,12*(J8-1),1,1)/1000 -> 3.539621 | K6: =OFFSET($S$13,0,12*(K8-1),1,1)/1000 -> 11.855968 | L6: =OFFSET($S$13,0,12*(L8-1),1,1)/1000 -> 11.356553 | M6: =OFFSET($S$13,0,12*(M8-1),1,1)/1000 -> 12.032361 | N6: =OFFSET($S$13,0,12*(N8-1),1,1)/1000 -> 19.978878 | O6: =OFFSET($S$13,0,12*(O8-1),1,1)/1000 -> 19.831922 | P6: =OFFSET($S$13,0,12*(P8-1),1,1)/1000 -> 21.676752
A8: Counters | H8: 1 | I8: 2 | J8: 3 | K8: 4 | L8: 5 | M8: 6 | N8: 7 | O8: 8 | P8: 9 | Q8: 10 | R8: 11 | S8: 12 | DT8: 45500
DT9: =DT8-DS11+DS12 -> 8639.3738 | DW9: =DT9-5000 -> 3639.3738
H10: 40909 | I10: 40940 | J10: 40969 | K10: 41000 | L10: 41030 | M10: 41061 | N10: 41091 | O10: 41122 | P10: 41153 | Q10: 41183 | R10: 41214 | S10: 41244 | T10: 41275 | U10: 41306 | V10: 41334 | W10: 41365 | X10: 41395 | Y10: 41426 | Z10: 41456 | AA10: 41487 | AB10: 41518 | AC10: 41548 | AD10: 41579 | AE10: 41609 | AF10: 41640 | AG10: 41671 | AH10: 41699 | AI10: 41730 | AJ10: 41760 | AK10: 41791 | AL10: 41821 | AM10: 41852 | AN10: 41883 | AO10: 41913 | AP10: 41944 | AQ10: 41974 | AR10: 42005 | AS10: 42036 | AT10: 42064 | AU10: 42095 | AV10: 42125 | AW10: 42156 | AX10: 42186 | AY10: 42217 | AZ10: 42248 | BA10: 42278 | BB10: 42309 | BC10: 42339 | BD10: 42370 | BE10: 42401 | BF10: 42430 | BG10: 42461 | BH10: 42491 | BI10: 42522 | BJ10: 42552 | BK10: 42583 | BL10: 42614 | BM10: 42644 | BN10: 42675 | BO10: 42705 | BP10: 42736 | BQ10: 42767 | BR10: 42795 | BS10: 42826 | BT10: 42856 | BU10: 42887 | BV10: 42917 | BW10: 42948 | BX10: 42979 | BY10: 43009 | BZ10: 43040 | CA10: 43070 | CB10: 43101 | CC10: 43132 | CD10: 43160 | CE10: 43191 | CF10: 43221 | CG10: 43252 | CH10: 43282 | CI10: 43313 | CJ10: 43344 | CK10: 43374 | CL10: 43405 | CM10: 43435 | CN10: 43466 | CO10: 43497 | CP10: 43525 | CQ10: 43556 | CR10: 43586 | CS10: 43617 | CT10: 43647 | CU10: 43678 | CV10: 43709 | CW10: 43739 | CX10: 43770 | CY10: 43800 | CZ10: 43831 | DA10: 43862 | DB10: 43891 | DC10: 43922 | DD10: 43952 | DE10: 43983 | DF10: 44013 | DG10: 44044 | DH10: 44075 | DI10: 44105 | DJ10: 44136 | DK10: 44166 | DL10: 44197 | DM10: 44228 | DN10: 44256 | DO10: 44287 | DP10: 44317 | DQ10: 44348 | DR10: 44378 | DS10: 44409 | DT10: 44440 | DU10: 44470 | DV10: 44501 | DW10: 44531 | DX10: 44562 | DY10: 44593 | DZ10: 44621 | EA10: 44652 | EB10: 44682 | EC10: 44713 | ED10: 44743 | EE10: 44774 | EF10: 44805 | EG10: 44835 | EH10: 44866 | EI10: 44896 | EJ10: 44927 | EK10: 44958 | EL10: 44986 | EM10: 45017 | EN10: 45047 | EO10: 45078 | EP10: 45108 | EQ10: 45139 | ER10: 45170 | ES10: 45200 | ET10: 45231 | EU10: 45261 | EV10: 45292 | EW10: 45323 | EX10: 45352 | EY10: 45383 | EZ10: 45413 | FA10: 45444 | FB10: 45474 | FC10: 45505 | FD10: 45536 | FE10: 45566 | FF10: 45597 | FG10: 45627 | FH10: 45658 | FI10: 45689 | FJ10: 45717 | FK10: 45748 | FL10: 45778 | FM10: 45809 | FN10: 45839 | FO10: 45870 | FP10: 45901 | FQ10: 45931 | FR10: 45962 | FS10: 45992 | FT10: 46023 | FU10: 46054 | FV10: 46082 | FW10: 46113 | FX10: 46143 | FY10: 46174 | FZ10: 46204 | GA10: 46235
A11: Gross reserves | H11: =H21 -> 46594 | I11: =I21 -> 46668 | J11: =J21 -> 47291 | K11: =K21 -> 47844 | L11: =L21 -> 46978 | M11: =M21 -> 46348 | N11: =N21 -> 46818 | O11: =O21 -> 45152 | ... FY11: =FY21 -> 44870 | FZ11: 47500 | GA11: 49500
A12: Net reserves | H12: =H21-H13-H14 -> 38906.999 | I12: =I21-I13-I14 -> 39046.498 | J12: =J21-J13-J14 -> 39370.867 | K12: =K21-K13-K14 -> 40023.011 | L12: =L21-L13-L14 -> 39947.099 | M12: =M21-M13-M14 -> 40166.412 | N12: =N21-N13-N14 -> 40038.854 | O12: =O21-O13-O14 -> 37843.969 | ... Z12: =Z21-Z13-Z14 -> 27734.515 | AA12: =AA21-AA13-AA14-AA15 -> 24505.176 | AB12: =AB21-AB13-AB14-AB15 -> 22120.38 | AC12: =AC21-AC13-AC14-AC15 -> 20310.947 | AD12: =AD21-AD13-AD14-AD15 -> 17956.071 | AE12: =AE21-AE13-AE14-AE15 -> 16190.752 | AF12: =AF21-AF13-AF14-AF15 -> 13056.723 | AG12: =AG21-AG13-AG14-AG15 -> 14938.488 | AH12: =AH21-AH13-AH14-AH15 -> 15098.471 | ... GA12: =GA21-GA13-GA14-GA15 -> 1559.1251
A13: Repos | H13: =-H28 -> 946.603 | I13: =-I28 -> 966.99 | J13: =-J28 -> 881.431 | K13: =-K28 -> 860.152 | L13: =-L28 -> 911.31 | M13: =-M28 -> 946.472 | N13: =-N28 -> 957.157 | O13: =-O28 -> 951.102 | ... EH13: =-EH28 -> 20098.579 | EI13: =-EI28-EI29 -> 20624.514 | EJ13: =-EJ28-EJ29 -> 21036.054 | EK13: =-EK28-EK29 -> 20548.803 | EL13: =-EL28-EL29 -> 20743.813 | EM13: =-EM28-EM29 -> 20657.851 | EN13: =-EN28-EN29 -> 20161.339 | EO13: =-EO28-EO29 -> 19815.798 | EP13: =-EP28-EP29 -> 20037.231 | ... FY13: =-FY28-FY29 -> 27542.728 | FZ13: =FY13 -> 27542.728 | GA13: =FZ13 -> 27542.728
A14: Private USD deposits | H14: =H30 -> 6740.3984 | I14: =I30 -> 6654.5121 | J14: =J30 -> 7038.7015 | K14: =K30 -> 6960.8369 | L14: =L30 -> 6119.5911 | M14: =M30 -> 5235.116 | N14: =N30 -> 5821.9891 | O14: =O30 -> 6356.9294 | ... FY14: =FY30 -> 12397.85 | FZ14: =FY14 -> 12397.85 | GA14: =FZ14 -> 12397.85
A15: Gold | H15: =H24 -> 3433.639 | I15: =I24 -> 3419.784 | J15: =J24 -> 3311.107 | K15: =K24 -> 3300.428 | L15: =L24 -> 3096.593 | M15: =M24 -> 3175.038 | N15: =N24 -> 3201.359 | O15: =O24 -> 3346.499 | ... FY15: =FY24 -> 8000.297 | FZ15: =FY15 -> 8000.297 | GA15: =FZ15 -> 8000.297
A16: Non-gold reserves | H16: =H21-H24 -> 43160.361 | I16: =I21-I24 -> 43248.216 | J16: =J21-J24 -> 43979.893 | K16: =K21-K24 -> 44543.572 | L16: =L21-L24 -> 43881.407 | M16: =M21-M24 -> 43172.962 | N16: =N21-N24 -> 43616.641 | O16: =O21-O24 -> 41805.501 | ... FY16: =FY21-FY24 -> 36869.703 | FZ16: =FY16 -> 36869.703 | GA16: =FZ16 -> 36869.703
B20: 11201 !M NA_ | C20: .DESC | D20: .T1 | E20: .SOURCE | F20: .AGG | G20: .DATA_TYPE | H20: 1201 | I20: 1202 | J20: 1203 | K20: 1204 | L20: 1205 | M20: 1206 | N20: 1207 | O20: 1208 | P20: 1209 | Q20: 1210 | R20: 1211 | S20: 1212 | T20: 1301 | U20: 1302 | V20: 1303 | W20: 1304 | X20: 1305 | Y20: 1306 | Z20: 1307 | AA20: 1308 | AB20: 1309 | AC20: 1310 | AD20: 1311 | AE20: 1312 | AF20: 1401 | AG20: 1402 | AH20: 1403 | AI20: 1404 | AJ20: 1405 | AK20: 1406 | AL20: 1407 | AM20: 1408 | AN20: 1409 | AO20: 1410 | AP20: 1411 | AQ20: 1412 | AR20: 1501 | AS20: 1502 | AT20: 1503 | AU20: 1504 | AV20: 1505 | AW20: 1506 | AX20: 1507 | AY20: 1508 | AZ20: 1509 | BA20: 1510 | BB20: 1511 | BC20: 1512 | BD20: 1601 | BE20: 1602 | BF20: 1603 | BG20: 1604 | BH20: 1605 | BI20: 1606 | BJ20: 1607 | BK20: 1608 | BL20: 1609 | BM20: 1610 | BN20: 1611 | BO20: 1612 | BP20: 1701 | BQ20: 1702 | BR20: 1703 | BS20: 1704 | BT20: 1705 | BU20: 1706 | BV20: 1707 | BW20: 1708 | BX20: 1709 | BY20: 1710 | BZ20: 1711 | CA20: 1712 | CB20: 1801 | CC20: 1802 | CD20: 1803 | CE20: 1804 | CF20: 1805 | CG20: 1806 | CH20: 1807 | CI20: 1808 | CJ20: 1809 | CK20: 1810 | CL20: 1811 | CM20: 1812 | CN20: 1901 | CO20: 1902 | CP20: 1903 | CQ20: 1904 | CR20: 1905 | CS20: 1906 | CT20: 1907 | CU20: 1908 | CV20: 1909 | CW20: 1910 | CX20: 1911 | CY20: 1912 | CZ20: 2001 | DA20: 2002 | DB20: 2003 | DC20: 2004 | DD20: 2005 | DE20: 2006 | DF20: 2007 | DG20: 2008 | DH20: 2009 | DI20: 2010 | DJ20: 2011 | DK20: 2012 | DL20: 2101 | DM20: 2102 | DN20: 2103 | DO20: 2104 | DP20: 2105 | DQ20: 2106 | DR20: 2107 | DS20: 2108 | DT20: 2109 | DU20: 2110 | DV20: 2111 | DW20: 2112 | DX20: 2201 | DY20: 2202 | DZ20: 2203 | EA20: 2204 | EB20: 2205 | EC20: 2206 | ED20: 2207 | EE20: 2208 | EF20: 2209 | EG20: 2210 | EH20: 2211 | EI20: 2212 | EJ20: 2301 | EK20: 2302 | EL20: 2303 | EM20: 2304 | EN20: 2305 | EO20: 2306 | EP20: 2307 | EQ20: 2308 | ER20: 2309 | ES20: 2310 | ET20: 2311 | EU20: 2312 | EV20: 2401 | EW20: 2402 | EX20: 2403 | EY20: 2404 | EZ20: 2405 | FA20: 2406 | FB20: 2407 | FC20: 2408 | FD20: 2409 | FE20: 2410 | FF20: 2411 | FG20: 2412 | FH20: 2501 | FI20: 2502 | FJ20: 2503 | FK20: 2504 | FL20: 2505 | FM20: 2506 | FN20: 2507 | FO20: 2508 | FP20: 2509 | FQ20: 2510 | FR20: 2511 | FS20: 2512 | FT20: 2601 | FU20: 2602 | FV20: 2603 | FW20: 2604 | FX20: 2605 | FY20: 2606 | FZ20: 2607
A21: FX reserves | B21: N213LFRG@EMERGELA | C21: Argentina: BCRA International Reserves (EOP, Mil.US$) | D21: Jan-1940 | E21: BCRA | F21: End of Period | G21: US$ | H21: 46594 | I21: 46668 | J21: 47291 | K21: 47844 | L21: 46978 | M21: 46348 | N21: 46818 | O21: 45152 | P21: 45010 | Q21: 45274 | R21: 45238 | S21: 43290 | T21: 42531 | U21: 41609 | V21: 40446 | W21: 39532 | X21: 38551 | Y21: 37005 | Z21: 37049 | AA21: 36678 | AB21: 34741 | AC21: 33232 | AD21: 30799 | AE21: 30599 | AF21: 27748 | AG21: 27546 | AH21: 27007 | AI21: 28220 | AJ21: 28542 | AK21: 29278 | AL21: 29003 | AM21: 28620 | AN21: 27866 | AO21: 28111 | AP21: 28911 | AQ21: 31407 | AR21: 31452 | AS21: 31470 | AT21: 31490 | AU21: 33909 | AV21: 33283 | AW21: 33851 | AX21: 33943 | AY21: 33606 | AZ21: 33257 | BA21: 26970 | BB21: 25615 | BC21: 25563 | BD21: 30074 | BE21: 28399 | BF21: 29572 | BG21: 34380 | BH21: 30171 | BI21: 30507 | BJ21: 32511 | BK21: 31150 | BL21: 29902 | BM21: 37210 | BN21: 37378 | BO21: 39308 | BP21: 46887 | BQ21: 50608 | BR21: 50522 | BS21: 48217 | BT21: 46146 | BU21: 47995 | BV21: 47014 | BW21: 48877 | BX21: 50237 | BY21: 51810 | BZ21: 54563 | CA21: 55055 | CB21: 62024 | CC21: 61509 | CD21: 61726 | CE21: 56623 | CF21: 50098 | CG21: 61881 | CH21: 57996 | CI21: 52658 | CJ21: 49003 | CK21: 53955 | CL21: 51193 | CM21: 65786 | CN21: 66811 | CO21: 68015 | CP21: 66187 | CQ21: 71663 | CR21: 64779 | CS21: 64278 | CT21: 67899 | CU21: 54100 | CV21: 48703 | CW21: 43260 | CX21: 43772 | CY21: 44848 | CZ21: 44917 | DA21: 44791 | DB21: 43561 | DC21: 43568 | DD21: 42589 | DE21: 43242 | DF21: 43386 | DG21: 42842 | DH21: 41379 | DI21: 39856 | DJ21: 38652 | DK21: 39387 | DL21: 39515 | DM21: 39518 | DN21: 39593 | DO21: 40263 | DP21: 41872 | DQ21: 42437 | DR21: 42582 | DS21: 46180 | DT21: 42911 | DU21: 42817 | DV21: 41530 | DW21: 39662 | DX21: 37589 | DY21: 37018 | DZ21: 43137 | EA21: 42007 | EB21: 41561 | EC21: 42787 | ED21: 38232 | EE21: 36734 | EF21: 37625 | EG21: 38676 | EH21: 38009 | EI21: 44598 | EJ21: 41417 | EK21: 38709 | EL21: 39060 | EM21: 35001 | EN21: 33001 | EO21: 27926 | EP21: 24092 | EQ21: 27818 | ER21: 26925 | ES21: 22559 | ET21: 21513 | EU21: 23073 | EV21: 27642 | EW21: 26690 | EX21: 27127 | EY21: 27578 | EZ21: 28664 | FA21: 29022 | FB21: 26402 | FC21: 26719 | FD21: 27172 | FE21: 28618 | FF21: 30214 | FG21: 29640 | FH21: 28310 | FI21: 28117 | FJ21: 24986 | FK21: 38928 | FL21: 36919 | FM21: 39973 | FN21: 38866 | FO21: 39986 | FP21: 40374 | FQ21: 39382 | FR21: 40335 | FS21: 41167 | FT21: 44503 | FU21: 45566 | FV21: 42052 | FW21: 44516 | FX21: 48193 | FY21: 44870 | FZ21: 47599 | GA21: 49500
A22: Official reserve assets | B22: L213NAT@IFS | C22: Argentina: Official Reserve Assets (EOP, Mil.US$) | D22: Sep-2000 | E22: IMF | F22: End of Period | G22: US$ | H22: 46594.275 | I22: 46667.873 | J22: 47290.719 | K22: 47844.169 | L22: 46977.529 | M22: 46347.88 | N22: 46818.403 | O22: 45152.121 | P22: 45010.4 | Q22: 45274.313 | R22: 45237.537 | S22: 43290.268 | T22: 42530.591 | U22: 41609.108 | V22: 40445.772 | W22: 39531.944 | X22: 38551.071 | Y22: 37005.088 | Z22: 37048.577 | AA22: 36678.089 | AB22: 34741.175 | AC22: 33231.819 | AD22: 30798.711 | AE22: 30600.443 | AF22: 27748.151 | AG22: 27545.91 | AH22: 27007.323 | AI22: 28220.006 | AJ22: 28541.775 | AK22: 29278.334 | AL22: 29002.882 | AM22: 28619.651 | AN22: 27865.52 | AO22: 28111.41 | AP22: 28910.8 | AQ22: 31407.549 | AR22: 31451.545 | AS22: 31469.85 | AT22: 31489.55 | AU22: 33908.87 | AV22: 33283.236 | AW22: 33851.344 | AX22: 33942.957 | AY22: 33605.994 | AZ22: 33257.143 | BA22: 26969.611 | BB22: 25614.778 | BC22: 25563.482 | BD22: 30074.001 | BE22: 28398.536 | BF22: 29571.69 | BG22: 34379.757 | BH22: 30171.35 | BI22: 30507.284 | BJ22: 32511.207 | BK22: 31149.636 | BL22: 29901.568 | BM22: 37210.424 | BN22: 37377.698 | BO22: 39308.314 | BP22: 46886.711 | BQ22: 50607.995 | BR22: 50522.329 | BS22: 48216.717 | BT22: 46145.77 | BU22: 47994.546 | BV22: 47014.173 | BW22: 48876.535 | BX22: 50237.025 | BY22: 51809.938 | BZ22: 54563.421 | CA22: 55055.081 | CB22: 62023.844 | CC22: 61508.505 | CD22: 61725.912 | CE22: 56622.97 | CF22: 50098.112 | CG22: 61880.978 | CH22: 57996.156 | CI22: 52657.659 | CJ22: 49003.426 | CK22: 53955.088 | CL22: 51193.236 | CM22: 65785.763 | CN22: 66811.241 | CO22: 68014.865 | CP22: 66187.122 | CQ22: 71662.492 | CR22: 64779.384 | CS22: 64278.004 | CT22: 67899.418 | CU22: 54100.383 | CV22: 48703.345 | CW22: 43260.325 | CX22: 43772.256 | CY22: 44848.343 | CZ22: 44917.098 | DA22: 44790.678 | DB22: 43561.209 | DC22: 43568.382 | DD22: 42588.498 | DE22: 43241.495 | DF22: 43386.263 | DG22: 42842.069 | DH22: 41378.84 | DI22: 39856.341 | DJ22: 38651.953 | DK22: 39387.067 | DL22: 39515.179 | DM22: 39518.126 | DN22: 39593.339 | DO22: 40262.763 | DP22: 41871.81 | DQ22: 42436.914 | DR22: 42581.74 | DS22: 46180.316 | DT22: 42911.183 | DU22: 42817.083 | DV22: 41529.544 | DW22: 39662.442 | DX22: 37588.966 | DY22: 37017.463 | DZ22: 43137.397 | EA22: 42006.594 | EB22: 41561.079 | EC22: 42786.791 | ED22: 38231.739 | EE22: 36734.427 | EF22: 37625.012 | EG22: 38675.902 | EH22: 38008.871 | EI22: 44598.433 | EJ22: 41417.273 | EK22: 38709.357 | EL22: 39060.011 | EM22: 35001.285 | EN22: 33001.348 | EO22: 27925.947 | EP22: 24091.963 | EQ22: 27818.482 | ER22: 26924.696 | ES22: 22558.874 | ET22: 21513.117 | EU22: 23073.165 | EV22: 27641.526 | EW22: 26690.39 | EX22: 27127.076 | EY22: 27578.444 | EZ22: 28663.836 | FA22: 29021.796 | FB22: 26401.661 | FC22: 26718.641 | FD22: 27172.273 | FE22: 28617.946 | FF22: 30214.105 | FG22: 29639.73 | FH22: 28309.765 | FI22: 28117.311 | FJ22: 24986.329 | FK22: 38928.25 | FL22: 36919.129 | FM22: 39972.557 | FN22: 38865.967 | FO22: 39986.148 | FP22: 40373.564 | FQ22: 39381.591 | FR22: 40422.422 | FS22: 41094.284 | FT22: 44503.121 | FU22: 45565.581 | FV22: 42052.054 | FW22: 44515.839 | FX22: 48193.48 | FY22: 44870.205
A23: SDR | B23: L213NAS@IFS | C23: Argentina: Official Reserve Assets: SDRs (EOP, Mil.US$) | D23: Sep-2000 | E23: IMF | F23: End of Period | G23: US$ | H23: 3185.689 | I23: 3194.988 | J23: 3181.137 | K23: 3182.192 | L23: 3100.999 | M23: 3116.277 | N23: 3097.595 | O23: 3124.989 | P23: 3166.61 | Q23: 3167.159 | R23: 3151.26 | S23: 3155.766 | T23: 3163.595 | U23: 3110.275 | V23: 3072.202 | W23: 3098.743 | X23: 3077.25 | Y23: 3088.062 | Z23: 3107.356 | AA23: 3111.185 | AB23: 3149.954 | AC23: 3158.31 | AD23: 3152.151 | AE23: 3162.299 | AF23: 3150.719 | AG23: 3177.239 | AH23: 3173.941 | AI23: 3182.618 | AJ23: 3163.012 | AK23: 3174.372 | AL23: 3144.634 | AM23: 3117.564 | AN23: 3044.19 | AO23: 3035.55 | AP23: 3006.35 | AQ23: 2974.803 | AR23: 2894.831 | AS23: 2889.63 | AT23: 2832.47 | AU23: 2887.833 | AV23: 2854.923 | AW23: 2887.666 | AX23: 2863.785 | AY23: 2882.235 | AZ23: 2882.231 | BA23: 2868.243 | BB23: 2817.296 | BC23: 2845.257 | BD23: 2834.644 | BE23: 2836.077 | BF23: 2892.68 | BG23: 2910.275 | BH23: 2880.26 | BI23: 2872.088 | BJ23: 2860.991 | BK23: 2489.681 | BL23: 2492.408 | BM23: 2453.43 | BN23: 2417.445 | BO23: 2401.113 | BP23: 2427.648 | BQ23: 2419.69 | BR23: 2423.86 | BS23: 2450.108 | BT23: 2472.479 | BU23: 2486.327 | BV23: 2516.868 | BW23: 2524.326 | BX23: 2525.265 | BY23: 2511.183 | BZ23: 2528.04 | CA23: 2545.195 | CB23: 2605.889 | CC23: 2582.379 | CD23: 2604.915 | CE23: 2571.378 | CF23: 2530.279 | CG23: 3809.282 | CH23: 3807.861 | CI23: 3748.943 | CJ23: 3735.568 | CK23: 4174.842 | CL23: 3514.972 | CM23: 4360.37 | CN23: 3566.474 | CO23: 3348.657 | CP23: 3328.365 | CQ23: 3326.344 | CR23: 3034.828 | CS23: 3031.429 | CT23: 3345.915 | CU23: 2962.914 | CV23: 2954.253 | CW23: 2991.088 | CX23: 2584.585 | CY23: 2604.986 | CZ23: 2595.531 | DA23: 2210.386 | DB23: 2206.441 | DC23: 2199.831 | DD23: 1888.438 | DE23: 1864.877 | DF23: 1942.198 | DG23: 1642.988 | DH23: 1629.985 | DI23: 1634.821 | DJ23: 1344.718 | DK23: 1354.4 | DL23: 1354.974 | DM23: 1039.038 | DN23: 1023.156 | DO23: 1036.757 | DP23: 740.771 | DQ23: 853.196 | DR23: 854.638 | DS23: 4855.625 | DT23: 2934.164 | DU23: 2947.848 | DV23: 2532.043 | DW23: 673.096 | DX23: 376.7 | DY23: 10.919 | DZ23: 6781.894 | EA23: 5908.132 | EB23: 5563.303 | EC23: 6777.062 | ED23: 4792.507 | EE23: 4257.873 | EF23: 1614.614 | EG23: 2932.736 | EH23: 2429.315 | EI23: 5763.558 | EJ23: 3188.287 | EK23: 2411.598 | EL23: 5066.81 | EM23: 2423.519 | EN23: 1607.264 | EO23: 10.29 | EP23: 70.829 | EQ23: 2968.929 | ER23: 1860.917 | ES23: 68.15 | ET23: 0.134 | EU23: 0.104 | EV23: 2707.306 | EW23: 893.344 | EX23: 892.558 | EY23: 890.733 | EZ23: 30.194 | FA23: 817.402 | FB23: 854.926 | FC23: 8.591 | FD23: 8.679 | FE23: 845.686 | FF23: 42.847 | FG23: 42.645 | FH23: 708.861 | FI23: 63.117 | FJ23: 64.235 | FK23: 741.032 | FL23: 77.088 | FM23: 78.26 | FN23: 77.345 | FO23: 40.791 | FP23: 40.955 | FQ23: 912.257 | FR23: 67.442 | FS23: 68.139 | FT23: 878.312 | FU23: 40.407 | FV23: 39.961 | FW23: 856.763 | FX23: 48.284 | FY23: 47.955
A24: Gold | B24: L213NAG@IFS | C24: Argentina: Official Reserve Assets: Gold (EOP, Mil.US$) | D24: Sep-2000 | E24: IMF | F24: End of Period | G24: US$ | H24: 3433.639 | I24: 3419.784 | J24: 3311.107 | K24: 3300.428 | L24: 3096.593 | M24: 3175.038 | N24: 3201.359 | O24: 3346.499 | P24: 3514.148 | Q24: 3411.109 | R24: 3399.835 | S24: 3326.471 | T24: 3330.738 | U24: 3137.265 | V24: 3186.968 | W24: 2922.909 | X24: 2763.398 | Y24: 2432.764 | Z24: 2606.626 | AA24: 2769.571 | AB24: 2637.949 | AC24: 2625.523 | AD24: 2481.812 | AE24: 2389.472 | AF24: 2461.744 | AG24: 2623.657 | AH24: 2545.946 | AI24: 2569.587 | AJ24: 2470.041 | AK24: 2633.641 | AL24: 2542.234 | AM24: 2552.06 | AN24: 2399.34 | AO24: 2324.52 | AP24: 2316.17 | AQ24: 2354.785 | AR24: 2529.55 | AS24: 2406.96 | AT24: 2345.58 | AU24: 2348.343 | AV24: 2361.821 | AW24: 2325.933 | AX24: 2178.014 | AY24: 2249.096 | AZ24: 2214.398 | BA24: 2263.348 | BB24: 2110.625 | BC24: 2106.933 | BD24: 2215.272 | BE24: 2444.197 | BF24: 2444.44 | BG24: 2559.801 | BH24: 2413.03 | BI24: 2617.265 | BJ24: 2681.558 | BK24: 2594.438 | BL24: 2607.757 | BM24: 2322.99 | BN24: 2141.825 | BO24: 2101.749 | BP24: 2400.569 | BQ24: 2291.49 | BR24: 2202.13 | BS24: 2514.149 | BT24: 2522.781 | BU24: 2386.584 | BV24: 2514.067 | BW24: 2614.705 | BX24: 2545.529 | BY24: 2435.019 | BZ24: 2293.122 | CA24: 2298.775 | CB24: 2657.883 | CC24: 2616.789 | CD24: 2337.695 | CE24: 2623.718 | CF24: 2579.034 | CG24: 2486.436 | CH24: 2429.229 | CI24: 2383.834 | CJ24: 2296.958 | CK24: 2406.924 | CL24: 2435.609 | CM24: 2255.623 | CN24: 2622.26 | CO24: 2608.201 | CP24: 2280.853 | CQ24: 2547.164 | CR24: 2588.214 | CS24: 2486.031 | CT24: 2818.441 | CU24: 3011.884 | CV24: 2914.148 | CW24: 2999.439 | CX24: 2904.26 | CY24: 2684.466 | CZ24: 3140.234 | DA24: 3139.756 | DB24: 2940.878 | DC24: 3341.13 | DD24: 3440.716 | DE24: 3533.096 | DF24: 3910.815 | DG24: 3913.236 | DH24: 3753.824 | DI24: 3728.992 | DJ24: 3527.459 | DK24: 3758.25 | DL24: 3673.155 | DM24: 3424.241 | DN24: 3392.997 | DO24: 3510.864 | DP24: 3783.082 | DQ24: 3509.634 | DR24: 3600.406 | DS24: 3599.83 | DT24: 3483.452 | DU24: 3536.153 | DV24: 3521.762 | DW24: 3213.763 | DX24: 3564.319 | DY24: 3744.514 | DZ24: 3859.206 | EA24: 3789.156 | EB24: 3655.429 | EC24: 3587.94 | ED24: 3502.289 | EE24: 3398.376 | EF24: 3299.545 | EG24: 3243.926 | EH24: 3476.683 | EI24: 3617.973 | EJ24: 3827.942 | EK24: 3629.287 | EL24: 3905.435 | EM24: 3949.105 | EN24: 3900.89 | EO24: 3806.882 | EP24: 3468.944 | EQ24: 3849.896 | ER24: 3669.542 | ES24: 3936.798 | ET24: 4042.934 | EU24: 4095.873 | EV24: 4064.59 | EW24: 4058.258 | EX24: 4344.767 | EY24: 4554.201 | EZ24: 4614.008 | FA24: 4616.965 | FB24: 4806.688 | FC24: 4960.642 | FD24: 5234.802 | FE24: 5436.811 | FF24: 5277.643 | FG24: 5206.145 | FH24: 5572.628 | FI24: 5646.35 | FJ24: 6187.312 | FK24: 6560.286 | FL24: 6532.298 | FM24: 6535.891 | FN24: 6539.126 | FO24: 6835.005 | FP24: 7629.01 | FQ24: 7934.396 | FR24: 8368.309 | FS24: 8585.662 | FT24: 9644.6 | FU24: 10388.584 | FV24: 9236.571 | FW24: 9172.834 | FX24: 9037.023 | FY24: 8000.297
A25: FX loans, securities, deposits | B25: L213NC@IFS | C25: Argentina: Predetermined ST Drains: Fgn Curr Loans/Secur/Deposits (EOP, Mil.US$) | D25: Dec-2005 | E25: IMF | F25: End of Period | G25: US$ | H25: -20015.944 | I25: -19309.446 | J25: -19476.872 | K25: -21067.088 | L25: -18893.439 | M25: -17731.619 | N25: -22032.333 | O25: -17835.49 | P25: -19717.789 | Q25: -22539.909 | R25: -22008.06 | S25: -20150.833 | T25: -19642.446 | U25: -19152.599 | V25: -18849.108 | W25: -17695.106 | X25: -16746.723 | Y25: -16727.432 | Z25: -16963.437 | AA25: -26275.169 | AB25: -20886.119 | AC25: -20810.219 | AD25: -19032.784 | AE25: -19413.281 | AF25: -19072.719 | AG25: -17319.552 | AH25: -16672.677 | AI25: -15956.771 | AJ25: -15664.113 | AK25: -15509.167 | AL25: -15043.088 | AM25: -15326.908 | AN25: -15594.41 | AO25: -22271.57 | AP25: -22959.3 | AQ25: -26229.612 | AR25: -34688.225 | AS25: -25955.44 | AT25: -25142.006 | AU25: -25873.351 | AV25: -25593.512 | AW25: -24274.714 | AX25: -25122.496 | AY25: -24641.627 | AZ25: -31565.986 | BA25: -21635.803 | BB25: -23545.315 | BC25: -25563.839 | BD25: -25285.521 | BE25: -23942.231 | BF25: -26574.16 | BG25: -39075.137 | BH25: -34169.28 | BI25: -35658.4 | BJ25: -41045.769 | BK25: -39108.57 | BL25: -39014.807 | BM25: -44065.778 | BN25: -41472.422 | BO25: -45449.086 | BP25: -53678.348 | BQ25: -56049.031 | BR25: -58666.121 | BS25: -46755.531 | BT25: -43943.287 | BU25: -44797.758 | BV25: -43713.23 | BW25: -46079.733 | BX25: -44462.887 | BY25: -44228.012 | BZ25: -49684.071 | CA25: -52448.878 | CB25: -56862.578 | CC25: -53332.961 | CD25: -57401.04 | CE25: -61056.794 | CF25: -59684.202 | CG25: -74290.199 | CH25: -69539.078 | CI25: -67208.555 | CJ25: -66783.591 | CK25: -72263.547 | CL25: -62911.744 | CM25: -68172.982 | CN25: -67141.958 | CO25: -67479.617 | CP25: -65290.128 | CQ25: -72181.117 | CR25: -60511.331 | CS25: -61285.543 | CT25: -65026.97 | CU25: -52143.555 | CV25: -45679.43 | CW25: -48633.65 | CX25: -48041.503 | CY25: -52864.38 | CZ25: -53539.944 | DA25: -53911.126 | DB25: -55336.19 | DC25: -59180.286 | DD25: -58539.459 | DE25: -59861.602 | DF25: -56674.517 | DG25: -32447.842 | DH25: -34725.912 | DI25: -34525.579 | DJ25: -34341.277 | DK25: -36473.052 | DL25: -30289.272 | DM25: -30647.549 | DN25: -30600.607 | DO25: -36391.445 | DP25: -33617.058 | DQ25: -39488.294 | DR25: -44591.276 | DS25: -44501.213 | DT25: -45704.512 | DU25: -48716.447 | DV25: -48677.089 | DW25: -50031.822 | DX25: -59609.506 | DY25: -58630.526 | DZ25: -64633.161 | EA25: -60859.179 | EB25: -56218.581 | EC25: -54414.768 | ED25: -54211.083 | EE25: -55804.29 | EF25: -51776.124 | EG25: -55076.014 | EH25: -54844.282 | EI25: -56986.965 | EJ25: -55818.766 | EK25: -54407.533 | EL25: -54855.139 | EM25: -50892.591 | EN25: -49698.046 | EO25: -46689.11 | EP25: -49575.812 | EQ25: -51956.225 | ER25: -51811.865 | ES25: -48454.216 | ET25: -44553.209 | EU25: -44276.465 | EV25: -40896.343 | EW25: -38703.069 | EX25: -36926.052 | EY25: -34467.344 | EZ25: -33574.341 | FA25: -45157.868 | FB25: -45004.737 | FC25: -41487.95 | FD25: -43148.62 | FE25: -44421.491 | FF25: -48510.802 | FG25: -48903.526 | FH25: -46432.444 | FI25: -46248.428 | FJ25: -44295.399 | FK25: -60912.296 | FL25: -36781.099 | FM25: -37614.767 | FN25: -36624.925 | FO25: -35018.14 | FP25: -36588.889 | FQ25: -35942.571 | FR25: -37941.9 | FS25: -41129.766 | FT25: -41848.498 | FU25: -41188.218 | FV25: -38503.89 | FW25: -41494.125 | FX25: -42971.934 | FY25: -40884.988
A26: Outflow - principal | B26: L213NCOP@IFS | C26: Argentina: Predtrm ST Drain: Fgn Curr Loans/Sec/Dep: Princ Outflow (EOP,Mil.US$) | D26: Sep-2000 | E26: IMF | F26: End of Period | G26: US$ | H26: -16913.568 | I26: -16213.373 | J26: -16384.105 | K26: -17972.44 | L26: -15819.209 | M26: -14478.509 | N26: -18777.41 | O26: -14591.905 | P26: -16481.502 | Q26: -19141.324 | R26: -18628.905 | S26: -16777.982 | T26: -16272.218 | U26: -15787.326 | V26: -15559.297 | W26: -14417.262 | X26: -13482.018 | Y26: -13050.35 | Z26: -13288.056 | AA26: -22606.022 | AB26: -17302.35 | AC26: -16996.851 | AD26: -15223.051 | AE26: -15617.468 | AF26: -15278.113 | AG26: -13528.494 | AH26: -12856.307 | AI26: -12158.474 | AJ26: -11869.035 | AK26: -11728.291 | AL26: -11264.671 | AM26: -11467.136 | AN26: -11742.97 | AO26: -18428.91 | AP26: -19121.19 | AQ26: -21556.363 | AR26: -30017.78 | AS26: -30821.58 | AT26: -30013.286 | AU26: -30969.922 | AV26: -30736.014 | AW26: -29433.054 | AX26: -30282.621 | AY26: -29809.17 | AZ26: -36740.262 | BA26: -27017.631 | BB26: -28609.079 | BC26: -20037.48 | BD26: -19767.884 | BE26: -18436.27 | BF26: -20830.222 | BG26: -32179.647 | BH26: -27364.91 | BI26: -28770.666 | BJ26: -33486.816 | BK26: -32148.572 | BL26: -31850.27 | BM26: -37026.378 | BN26: -34434.575 | BO26: -38381.478 | BP26: -46022.604 | BQ26: -48392.273 | BR26: -51011.422 | BS26: -39230.45 | BT26: -36359.115 | BU26: -36836.727 | BV26: -35702.359 | BW26: -37589.356 | BX26: -35590.607 | BY26: -35026.997 | BZ26: -40373.044 | CA26: -43029.194 | CB26: -46769.917 | CC26: -43224.517 | CD26: -47312.347 | CE26: -50550.645 | CF26: -50805.294 | CG26: -64823.692 | CH26: -60230.45 | CI26: -57703.181 | CJ26: -57249.039 | CK26: -62748.827 | CL26: -52300.773 | CM26: -57423.273 | CN26: -57001.198 | CO26: -57168.853 | CP26: -54493.408 | CQ26: -61415.833 | CR26: -50374.157 | CS26: -50288.102 | CT26: -54139.988 | CU26: -41431.319 | CV26: -34996.502 | CW26: -36862.802 | CX26: -35926.966 | CY26: -40917.052 | CZ26: -43205.4 | DA26: -43752.817 | DB26: -45162.073 | DC26: -48861.046 | DD26: -48036.995 | DE26: -47896.775 | DF26: -44360.888 | DG26: -29775.373 | DH26: -32117.451 | DI26: -31966.453 | DJ26: -31678.984 | DK26: -33785.013 | DL26: -27110.263 | DM26: -27441.182 | DN26: -27484.27 | DO26: -33238.212 | DP26: -30661.041 | DQ26: -36562.54 | DR26: -40776.353 | DS26: -40761.095 | DT26: -41990.816 | DU26: -44987.809 | DV26: -45106.628 | DW26: -46467.256 | DX26: -55690.151 | DY26: -54882.957 | DZ26: -60845.802 | EA26: -56400.27 | EB26: -51838.957 | EC26: -50109.365 | ED26: -48747.551 | EE26: -50465.066 | EF26: -46144.61 | EG26: -49815.556 | EH26: -49677.494 | EI26: -51082.122 | EJ26: -48836.179 | EK26: -47725.222 | EL26: -47551.67 | EM26: -42924.308 | EN26: -41964.725 | EO26: -38891.782 | EP26: -41144.282 | EQ26: -43506.736 | ER26: -43211.496 | ES26: -39865.816 | ET26: -35985.763 | EU26: -35692.093 | EV26: -31916.718 | EW26: -30084.185 | EX26: -28153.368 | EY26: -25584.575 | EZ26: -24705.055 | FA26: -36205.455 | FB26: -35878.3 | FC26: -32292.573 | FD26: -34075.268 | FE26: -35473.225 | FF26: -39706.967 | FG26: -40625.068 | FH26: -38101.519 | FI26: -37963.249 | FJ26: -35997.838 | FK26: -51981.122 | FL26: -27966.708 | FM26: -28679.439 | FN26: -27777.176 | FO26: -26376.742 | FP26: -27970.367 | FQ26: -27206.377 | FR26: -29253.033 | FS26: -32037.933 | FT26: -32854.318 | FU26: -32215.309 | FV26: -29029.221 | FW26: -31915.205 | FX26: -33597.388 | FY26: -31254.812
A27: Outflows - interests | B27: L213NCOI@IFS | C27: Argentina: Predtrm ST Drains: Fgn Curr Loans/Sec/Dep: Int Outflow (EOP, Mil.US$) | D27: May-2001 | E27: IMF | F27: End of Period | G27: US$ | H27: -3102.37 | I27: -3096.053 | J27: -3092.758 | K27: -3094.648 | L27: -3074.23 | M27: -3253.11 | N27: -3254.923 | O27: -3243.585 | P27: -3236.287 | Q27: -3398.595 | R27: -3379.155 | S27: -3372.851 | T27: -3370.218 | U27: -3365.274 | V27: -3289.812 | W27: -3277.844 | X27: -3264.705 | Y27: -3677.072 | Z27: -3675.371 | AA27: -3669.137 | AB27: -3583.779 | AC27: -3813.367 | AD27: -3809.733 | AE27: -3795.813 | AF27: -3794.606 | AG27: -3791.058 | AH27: -3816.369 | AI27: -3798.297 | AJ27: -3795.068 | AK27: -3780.876 | AL27: -3778.418 | AM27: -3859.762 | AN27: -3851.44 | AO27: -3842.67 | AP27: -3838.11 | AQ27: -4673.249 | AR27: -4670.445 | AS27: -4663.97 | AT27: -4658.83 | AU27: -4433.54 | AV27: -4387.608 | AW27: -4371.77 | AX27: -4369.994 | AY27: -4362.567 | AZ27: -4355.834 | BA27: -4148.282 | BB27: -4466.346 | BC27: -5526.358 | BD27: -5517.636 | BE27: -5505.961 | BF27: -5743.938 | BG27: -6895.49 | BH27: -6804.37 | BI27: -6887.734 | BJ27: -7558.953 | BK27: -6959.998 | BL27: -7164.537 | BM27: -7039.399 | BN27: -7037.847 | BO27: -7067.608 | BP27: -7655.744 | BQ27: -7656.758 | BR27: -7654.699 | BS27: -7525.081 | BT27: -7584.172 | BU27: -7961.031 | BV27: -8010.871 | BW27: -8490.377 | BX27: -8872.281 | BY27: -9201.015 | BZ27: -9311.027 | CA27: -9419.684 | CB27: -10092.661 | CC27: -10108.444 | CD27: -10088.692 | CE27: -10506.149 | CF27: -8878.908 | CG27: -9466.507 | CH27: -9308.627 | CI27: -9505.374 | CJ27: -9534.552 | CK27: -9514.72 | CL27: -10610.971 | CM27: -10749.708 | CN27: -10140.76 | CO27: -10310.764 | CP27: -10796.72 | CQ27: -10765.283 | CR27: -10137.174 | CS27: -10997.441 | CT27: -10886.981 | CU27: -10712.236 | CV27: -10682.928 | CW27: -11770.848 | CX27: -12114.537 | CY27: -11947.328 | CZ27: -10334.543 | DA27: -10158.31 | DB27: -10174.116 | DC27: -10319.24 | DD27: -10502.464 | DE27: -11964.827 | DF27: -12313.629 | DG27: -2672.469 | DH27: -2608.461 | DI27: -2559.126 | DJ27: -2662.293 | DK27: -2688.039 | DL27: -3179.009 | DM27: -3206.368 | DN27: -3116.337 | DO27: -3153.233 | DP27: -2956.017 | DQ27: -2925.753 | DR27: -3814.923 | DS27: -3740.119 | DT27: -3713.696 | DU27: -3728.638 | DV27: -3570.461 | DW27: -3564.566 | DX27: -3919.355 | DY27: -3747.568 | DZ27: -3787.359 | EA27: -4458.909 | EB27: -4379.624 | EC27: -4305.404 | ED27: -5463.532 | EE27: -5339.224 | EF27: -5631.515 | EG27: -5260.457 | EH27: -5166.788 | EI27: -5904.843 | EJ27: -6982.587 | EK27: -6682.311 | EL27: -7303.468 | EM27: -7968.283 | EN27: -7733.32 | EO27: -7797.328 | EP27: -8431.53 | EQ27: -8449.489 | ER27: -8600.369 | ES27: -8588.4 | ET27: -8567.446 | EU27: -8584.372 | EV27: -8979.624 | EW27: -8618.884 | EX27: -8772.684 | EY27: -8882.769 | EZ27: -8869.286 | FA27: -8952.413 | FB27: -9126.436 | FC27: -9195.377 | FD27: -9073.352 | FE27: -8948.266 | FF27: -8803.835 | FG27: -8278.458 | FH27: -8330.925 | FI27: -8285.179 | FJ27: -8297.561 | FK27: -8931.174 | FL27: -8814.392 | FM27: -8935.328 | FN27: -8847.75 | FO27: -8641.398 | FP27: -8618.522 | FQ27: -8736.193 | FR27: -8688.867 | FS27: -9091.833 | FT27: -8994.18 | FU27: -8972.909 | FV27: -9474.669 | FW27: -9578.92 | FX27: -9374.546 | FY27: -9630.176
A28: Outflows related to repo | B28: L213NGOO@IFS | C28: Argentina: Predtrm ST Drains: Fgn Curr Outflows Related to Repos (EOP, Mil.US$) | D28: Jul-2007 | E28: IMF | F28: End of Period | G28: US$ | H28: -946.603 | I28: -966.99 | J28: -881.431 | K28: -860.152 | L28: -911.31 | M28: -946.472 | N28: -957.157 | O28: -951.102 | P28: -755.91 | Q28: -931.535 | R28: -915.779 | S28: -931.857 | T28: -789.192 | U28: -1044.201 | V28: -860.128 | W28: -1012.607 | X28: -1037.484 | Y28: -960.818 | Z28: -983.054 | AA28: -997.768 | AB28: -1001.026 | AC28: -997.55 | AD28: -946.985 | AE28: -1046.064 | AF28: -977.454 | AG28: -1016.703 | AH28: -1015.023 | AI28: -995.936 | AJ28: -1010.849 | AK28: -1066.272 | AL28: -1074.087 | AM28: -947.585 | AN28: -966.4 | AO28: -1806.8 | AP28: -2534.77 | AQ28: -3539.621 | AR28: -4384.686 | AS28: -4605.12 | AT28: -6323.88 | AU28: -7387.587 | AV28: -8032.65 | AW28: -9029.152 | AX28: -9051.399 | AY28: -11073.554 | AZ28: -12119.123 | BA28: -12167.887 | BB28: -12024.418 | BC28: -11855.968 | BD28: -16647.13 | BE28: -16749.713 | BF28: -16923.01 | BG28: -16793.02 | BH28: -16627.52 | BI28: -16627.709 | BJ28: -12587.683 | BK28: -12515.293 | BL28: -12609.707 | BM28: -12448.271 | BN28: -12381.31 | BO28: -11356.553 | BP28: -11446.908 | BQ28: -11468.631 | BR28: -11449.512 | BS28: -11431.428 | BT28: -11542.815 | BU28: -11598.343 | BV28: -11685.476 | BW28: -11888.378 | BX28: -11824.723 | BY28: -11825.583 | BZ28: -11865.606 | CA28: -12032.361 | CB28: -12402.424 | CC28: -12170.543 | CD28: -12228.329 | CE28: -12167.77 | CF28: -12007.274 | CG28: -11661.585 | CH28: -11352.554 | CI28: -11325.163 | CJ28: -11268.816 | CK28: -11111.709 | CL28: -11161.65 | CM28: -19978.878 | CN28: -20481.653 | CO28: -20499.167 | CP28: -20446.78 | CQ28: -20381.35 | CR28: -19909.363 | CS28: -20017.776 | CT28: -19971.69 | CU28: -19256.612 | CV28: -19279.75 | CW28: -19566.44 | CX28: -19590.718 | CY28: -19831.922 | CZ28: -20030.637 | DA28: -20093.461 | DB28: -19914.538 | DC28: -19745.506 | DD28: -19828.905 | DE28: -20057.482 | DF28: -20295.344 | DG28: -20741.072 | DH28: -20902.346 | DI28: -21187.189 | DJ28: -21519.96 | DK28: -21676.752 | DL28: -21983.676 | DM28: -21842.288 | DN28: -21599.797 | DO28: -21838.749 | DP28: -22168.658 | DQ28: -21894.092 | DR28: -21880.974 | DS28: -21883.883 | DT28: -21934.265 | DU28: -22056.956 | DV28: -22187.703 | DW28: -22214.169 | DX28: -22197.311 | DY28: -22337.167 | DZ28: -22263.093 | EA28: -21429.756 | EB28: -21244.647 | EC28: -21162.987 | ED28: -21036.291 | EE28: -20630.434 | EF28: -20035.155 | EG28: -19562.865 | EH28: -20098.579 | EI28: -1776.514 | EJ28: -1782.054 | EK28: -1788.803 | EL28: -1797.813 | EM28: -1803.851 | EN28: -1808.339 | EO28: -1814.798 | EP28: -1824.231 | EQ28: -1832.272 | ER28: -1840.003 | ES28: -1848.37 | ET28: -1858.53 | EU28: -1869.095 | EV28: -1876.566 | EW28: -1885.964 | EX28: -1893.249 | EY28: -1900.733 | EZ28: -1909.802 | FA28: -1917.633 | FB28: -1932.144 | FC28: -1943.026 | FD28: -1953.332 | FE28: -1958.311 | FF28: -1965.345 | FG28: -1973.674 | FH28: -2072.886 | FI28: -2079.817 | FJ28: -2093.931 | FK28: -2101.174 | FL28: -2105.882 | FM28: -2267.298 | FN28: -2278.042 | FO28: -2286.655 | FP28: -2290.036 | FQ28: -3293.831 | FR28: -3287.7 | FS28: -3290.429 | FT28: -7503.463 | FU28: -7497.827 | FV28: -7495.468 | FW28: -8400.845 | FX28: -8384.838 | FY28: -8389.728
A29: Short term shorts | B29: L213NGS@IFS | C29: Argentina: Predtrm ST Drains: Aggregate Short in Curr Fwrd/Futures (EOP,Mil.US$) | D29: Feb-2001 | E29: IMF | F29: End of Period | G29: US$ | EI29: -18848 | EJ29: -19254 | EK29: -18760 | EL29: -18946 | EM29: -18854 | EN29: -18353 | EO29: -18001 | EP29: -18213 | EQ29: -17944 | ER29: -17869 | ES29: -17846 | ET29: -18321 | EU29: -18432 | EV29: -18280 | EW29: -18251 | EX29: -18176 | EY29: -18162 | EZ29: -18183 | FA29: -17993 | FB29: -18013 | FC29: -18358 | FD29: -18562 | FE29: -18340 | FF29: -18011 | FG29: -17869 | FH29: -18002 | FI29: -17924 | FJ29: -17968 | FK29: -17931 | FL29: -18108 | FM29: -18172 | FN29: -18088 | FO29: -18263 | FP29: -18285 | FQ29: -20795 | FR29: -20908 | FS29: -18624 | FT29: -18706 | FU29: -18954 | FV29: -18868 | FW29: -19042 | FX29: -19216 | FY29: -19153
A30: Private sector FX deposits | B30: FX(C213MAN@EMERGELA) | C30: Argentina: BCRA: Absorptn Src: Dep by Fin Inst in Fgn Curr(EOP, Mil.US$) | D30: Jan-1994 | E30: BCRA | F30: End of Period | G30: US$ <- LocCur | H30: 6740.3984 | I30: 6654.5121 | J30: 7038.7015 | K30: 6960.8369 | L30: 6119.5911 | M30: 5235.116 | N30: 5821.9891 | O30: 6356.9294 | P30: 6678.6402 | Q30: 7747.598 | R30: 8073.5884 | S30: 8499.8979 | T30: 8102.1551 | U30: 7700.0398 | V30: 7599.2356 | W30: 7987.343 | X30: 7977.4316 | Y30: 7962.5302 | Z30: 8331.4312 | AA30: 8405.4848 | AB30: 8981.645 | AC30: 9297.9803 | AD30: 9414.1317 | AE30: 10972.712 | AF30: 11252.079 | AG30: 8967.1524 | AH30: 8347.5604 | AI30: 7320.8249 | AJ30: 7401.5318 | AK30: 7790.3996 | AL30: 7461.8972 | AM30: 7534.918 | AN30: 7401.6468 | AO30: 7799.325 | AP30: 7898.1486 | AQ30: 8495.5817 | AR30: 8617.708 | AS30: 9385.4493 | AT30: 8463.9567 | AU30: 8032.7991 | AV30: 7748.161 | AW30: 7723.8053 | AX30: 8271.2192 | AY30: 7884.8865 | AZ30: 8030.4213 | BA30: 9340.1473 | BB30: 9605.0285 | BC30: 11081.855 | BD30: 9488.447 | BE30: 7285.7707 | BF30: 9003.7671 | BG30: 8666.3147 | BH30: 11041.793 | BI30: 11213.48 | BJ30: 11695.827 | BK30: 10395.094 | BL30: 10034.974 | BM30: 17250.125 | BN30: 13780.239 | BO30: 15650.591 | BP30: 21985.465 | BQ30: 22287.258 | BR30: 24245.786 | BS30: 18781 | BT30: 15601.466 | BU30: 13056.018 | BV30: 15268.907 | BW30: 16070.89 | BX30: 14471.723 | BY30: 12755.133 | BZ30: 14343.913 | CA30: 13026.312 | CB30: 16222.449 | CC30: 12130.284 | CD30: 12443.621 | CE30: 12608.409 | CF30: 11362.995 | CG30: 13911.399 | CH30: 13780.673 | CI30: 13825.986 | CJ30: 13027.803 | CK30: 13109.983 | CL30: 13355.758 | CM30: 14291.032 | CN30: 14008.105 | CO30: 13715.47 | CP30: 15487.88 | CQ30: 16017.049 | CR30: 16679.559 | CS30: 15694.053 | CT30: 15996.868 | CU30: 11121.991 | CV30: 8784.159 | CW30: 8030.5439 | CX30: 8171.8316 | CY30: 8961.0152 | CZ30: 9972.1743 | DA30: 10643.296 | DB30: 10330.712 | DC30: 10883.962 | DD30: 11236.189 | DE30: 10529.861 | DF30: 10726.518 | DG30: 11418.921 | DH30: 12010.191 | DI30: 11518.897 | DJ30: 11191.703 | DK30: 10928.736 | DL30: 11455.215 | DM30: 11859.844 | DN30: 11229.519 | DO30: 10547.885 | DP30: 10108.956 | DQ30: 10702.138 | DR30: 11220.209 | DS30: 11376.913 | DT30: 11874.408 | DU30: 11922.366 | DV30: 11453.951 | DW30: 12128.163 | DX30: 12043.709 | DY30: 12196.541 | DZ30: 11574.987 | EA30: 12291.686 | EB30: 12106.127 | EC30: 11529.24 | ED30: 11484.45 | EE30: 11547.997 | EF30: 11049.124 | EG30: 11228.827 | EH30: 11530.368 | EI30: 12092.346 | EJ30: 12888.554 | EK30: 12961.672 | EL30: 12149.791 | EM30: 11245.165 | EN30: 11019.171 | EO30: 10307.574 | EP30: 9839.0925 | EQ30: 9385.2572 | ER30: 9584.0604 | ES30: 8896.1722 | ET30: 8863.6897 | EU30: 9134.5515 | EV30: 9813.5929 | EW30: 9333.236 | EX30: 8907.3644 | EY30: 8401.9637 | EZ30: 8129.5685 | FA30: 8333.7057 | FB30: 9609.8772 | FC30: 9495.1028 | FD30: 10675.391 | FE30: 12570.273 | FF30: 13586.966 | FG30: 12280.564 | FH30: 12863.616 | FI30: 12436.271 | FJ30: 11428.23 | FK30: 13775.617 | FL30: 12046.725 | FM30: 11443.553 | FN30: 12352.79 | FO30: 12202.101 | FP30: 12698.184 | FQ30: 14073.245 | FR30: 16026.693 | FS30: 15158.656 | FT30: 17330.113 | FU30: 17181.975 | FV30: 14366.487 | FW30: 14051.529 | FX30: 14753.086 | FY30: 12397.85
A33: Deposits other than Repos | H33: =(-H25)-H34 -> 20015.944 | I33: =(-I25)-I34 -> 19309.446 | J33: =(-J25)-J34 -> 19476.872 | K33: =(-K25)-K34 -> 21067.088 | L33: =(-L25)-L34 -> 18893.439 | M33: =(-M25)-M34 -> 17731.619 | N33: =(-N25)-N34 -> 22032.333 | O33: =(-O25)-O34 -> 17835.49 | ... DR33: =(-DR25)-DR34 -> 44591.276
A34: Repos | H34: =-H31 -> 0 | I34: =-I31 -> 0 | J34: =-J31 -> 0 | K34: =-K31 -> 0 | L34: =-L31 -> 0 | M34: =-M31 -> 0 | N34: =-N31 -> 0 | O34: =-O31 -> 0 | ... DR34: =-DR31 -> 0
A35: Net FX reserves | H35: =H21-H34-H33 -> 26578.056 | I35: =I21-I34-I33 -> 27358.554 | J35: =J21-J34-J33 -> 27814.128 | K35: =K21-K34-K33 -> 26776.912 | L35: =L21-L34-L33 -> 28084.561 | M35: =M21-M34-M33 -> 28616.381 | N35: =N21-N34-N33 -> 24785.667 | O35: =O21-O34-O33 -> 27316.51 | ... DP35: =DP21-DP34-DP33 -> 8254.942
A36: FX reserves - non gold | H36: =H21-H24 -> 43160.361 | I36: =I21-I24 -> 43248.216 | J36: =J21-J24 -> 43979.893 | K36: =K21-K24 -> 44543.572 | L36: =L21-L24 -> 43881.407 | M36: =M21-M24 -> 43172.962 | N36: =N21-N24 -> 43616.641 | O36: =O21-O24 -> 41805.501 | ... DP36: =DP21-DP24 -> 38088.918
DY37: Aug 2020\
DY38: 18.5 | DZ38: 3.5
DY39: 6.9
DY40: =DY39*DY38 -> 127.65 | DZ40: =DY40/6.3 -> 20.261905
DT47: =18*7 -> 126
DT48: =DT47/6.4 -> 19.6875

Sheet GDP demand contributions
B2: Demand-side contributions to GDP growth
B3: Percentage points. Contributions sum exactly to GDP growth — which requires carrying the statistical discrepancy explicitly. Imports enter with a negative sign.
B4: Contribution of component i = (level_i this period - level_i a year earlier) / GDP a year earlier. The inventories line is inventories PLUS statistical discrepancy, because INDEC only split them out in 2024 and a split series would break the y/y comparison in that year.
B6: 1. Quarterly, year-on-year (original series)
B7: Quarter | C7: GDP y/y | D7: Private consumption | E7: Public consumption | F7: GFCF | G7: Inventories + discrepancy | H7: Exports | I7: Imports | J7: Sum of contributions | K7: Check (sum - GDP) | L7: memo: discrep. alone | N7: Real GDP | O7: Domestic demand | P7: Inventories + discrepancy | Q7: External sector
B8: ='[8]Data Constant'!B10 -> 1Q 2005 | C8: =('[8]Data Constant'!F10/'[8]Data Constant'!F6-1)*100 -> 7.2187868 | D8: =('[8]Data Constant'!G10-'[8]Data Constant'!G6)/'[8]Data Constant'!$F6*100 -> 3.1632397 | E8: =('[8]Data Constant'!H10-'[8]Data Constant'!H6)/'[8]Data Constant'!$F6*100 -> 0.97574097 | F8: =('[8]Data Constant'!I10-'[8]Data Constant'!I6)/'[8]Data Constant'!$F6*100 -> 1.9284514 | G8: =('[8]Data Constant'!N10-'[8]Data Constant'!N6)/'[8]Data Constant'!$F6*100 -> 0.15618046 | H8: =('[8]Data Constant'!L10-'[8]Data Constant'!L6)/'[8]Data Constant'!$F6*100 -> 3.5651202 | I8: =-('[8]Data Constant'!M10-'[8]Data Constant'!M6)/'[8]Data Constant'!$F6*100 -> -2.569967 | J8: =SUM(D8:I8) -> 7.2187658 | K8: =J8-C8 -> -2.0993133e-05 | L8: =IF(OR('[8]Data Constant'!K10="",'[8]Data Constant'!K6=""),"",('[8]Data Constant'!K10-'[8]Data Constant'!K6)/'[8]Data Constant'!$F6*100)
B9: ='[8]Data Constant'!B11 -> 2Q 2005 | C9: =('[8]Data Constant'!F11/'[8]Data Constant'!F7-1)*100 -> 13.077981 | D9: =('[8]Data Constant'!G11-'[8]Data Constant'!G7)/'[8]Data Constant'!$F7*100 -> 9.132672 | E9: =('[8]Data Constant'!H11-'[8]Data Constant'!H7)/'[8]Data Constant'!$F7*100 -> 1.1936131 | F9: =('[8]Data Constant'!I11-'[8]Data Constant'!I7)/'[8]Data Constant'!$F7*100 -> 2.4325395 | G9: =('[8]Data Constant'!N11-'[8]Data Constant'!N7)/'[8]Data Constant'!$F7*100 -> 0.032731467 | H9: =('[8]Data Constant'!L11-'[8]Data Constant'!L7)/'[8]Data Constant'!$F7*100 -> 3.6460785 | I9: =-('[8]Data Constant'!M11-'[8]Data Constant'!M7)/'[8]Data Constant'!$F7*100 -> -3.3596503 | J9: =SUM(D9:I9) -> 13.077984 | K9: =J9-C9 -> 3.5951988e-06 | L9: =IF(OR('[8]Data Constant'!K11="",'[8]Data Constant'!K7=""),"",('[8]Data Constant'!K11-'[8]Data Constant'!K7)/'[8]Data Constant'!$F7*100)
B10: ='[8]Data Constant'!B12 -> 3Q 2005 | C10: =('[8]Data Constant'!F12/'[8]Data Constant'!F8-1)*100 -> 6.9719779 | D10: =('[8]Data Constant'!G12-'[8]Data Constant'!G8)/'[8]Data Constant'!$F8*100 -> 2.783069 | E10: =('[8]Data Constant'!H12-'[8]Data Constant'!H8)/'[8]Data Constant'!$F8*100 -> 1.092591 | F10: =('[8]Data Constant'!I12-'[8]Data Constant'!I8)/'[8]Data Constant'!$F8*100 -> 2.2226429 | G10: =('[8]Data Constant'!N12-'[8]Data Constant'!N8)/'[8]Data Constant'!$F8*100 -> -0.037611895 | H10: =('[8]Data Constant'!L12-'[8]Data Constant'!L8)/'[8]Data Constant'!$F8*100 -> 3.286596 | I10: =-('[8]Data Constant'!M12-'[8]Data Constant'!M8)/'[8]Data Constant'!$F8*100 -> -2.3753036 | J10: =SUM(D10:I10) -> 6.9719833 | K10: =J10-C10 -> 5.4687576e-06 | L10: =IF(OR('[8]Data Constant'!K12="",'[8]Data Constant'!K8=""),"",('[8]Data Constant'!K12-'[8]Data Constant'!K8)/'[8]Data Constant'!$F8*100)
B11: ='[8]Data Constant'!B13 -> 4Q 2005 | C11: =('[8]Data Constant'!F13/'[8]Data Constant'!F9-1)*100 -> 7.7828945 | D11: =('[8]Data Constant'!G13-'[8]Data Constant'!G9)/'[8]Data Constant'!$F9*100 -> 3.5811304 | E11: =('[8]Data Constant'!H13-'[8]Data Constant'!H9)/'[8]Data Constant'!$F9*100 -> 1.1075977 | F11: =('[8]Data Constant'!I13-'[8]Data Constant'!I9)/'[8]Data Constant'!$F9*100 -> 3.4530515 | G11: =('[8]Data Constant'!N13-'[8]Data Constant'!N9)/'[8]Data Constant'!$F9*100 -> 0.17946061 | H11: =('[8]Data Constant'!L13-'[8]Data Constant'!L9)/'[8]Data Constant'!$F9*100 -> 1.7857561 | I11: =-('[8]Data Constant'!M13-'[8]Data Constant'!M9)/'[8]Data Constant'!$F9*100 -> -2.3240911 | J11: =SUM(D11:I11) -> 7.7829052 | K11: =J11-C11 -> 1.0698599e-05 | L11: =IF(OR('[8]Data Constant'!K13="",'[8]Data Constant'!K9=""),"",('[8]Data Constant'!K13-'[8]Data Constant'!K9)/'[8]Data Constant'!$F9*100) | N11: =SUM(O11:Q11) -> 7.7829052 | O11: =D11+E11+F11 -> 8.1417796 | P11: =+G11 -> 0.17946061 | Q11: =+H11+I11 -> -0.53833497
B12: ='[8]Data Constant'!B14 -> 1Q 2006 | C12: =('[8]Data Constant'!F14/'[8]Data Constant'!F10-1)*100 -> 7.8495711 | D12: =('[8]Data Constant'!G14-'[8]Data Constant'!G10)/'[8]Data Constant'!$F10*100 -> 7.1086259 | E12: =('[8]Data Constant'!H14-'[8]Data Constant'!H10)/'[8]Data Constant'!$F10*100 -> 0.54690241 | F12: =('[8]Data Constant'!I14-'[8]Data Constant'!I10)/'[8]Data Constant'!$F10*100 -> 2.6669512 | G12: =('[8]Data Constant'!N14-'[8]Data Constant'!N10)/'[8]Data Constant'!$F10*100 -> -1.4408436 | H12: =('[8]Data Constant'!L14-'[8]Data Constant'!L10)/'[8]Data Constant'!$F10*100 -> 1.3401098 | I12: =-('[8]Data Constant'!M14-'[8]Data Constant'!M10)/'[8]Data Constant'!$F10*100 -> -2.3721747 | J12: =SUM(D12:I12) -> 7.8495711 | K12: =J12-C12 -> -1.4299673e-13 | L12: =IF(OR('[8]Data Constant'!K14="",'[8]Data Constant'!K10=""),"",('[8]Data Constant'!K14-'[8]Data Constant'!K10)/'[8]Data Constant'!$F10*100) | N12: =SUM(O12:Q12) -> 7.8495711 | O12: =D12+E12+F12 -> 10.322479 | P12: =+G12 -> -1.4408436 | Q12: =+H12+I12 -> -1.0320648
B13: ='[8]Data Constant'!B15 -> 2Q 2006 | C13: =('[8]Data Constant'!F15/'[8]Data Constant'!F11-1)*100 -> 5.5715853 | D13: =('[8]Data Constant'!G15-'[8]Data Constant'!G11)/'[8]Data Constant'!$F11*100 -> 4.6481125 | E13: =('[8]Data Constant'!H15-'[8]Data Constant'!H11)/'[8]Data Constant'!$F11*100 -> 0.30787147 | F13: =('[8]Data Constant'!I15-'[8]Data Constant'!I11)/'[8]Data Constant'!$F11*100 -> 1.8648868 | G13: =('[8]Data Constant'!N15-'[8]Data Constant'!N11)/'[8]Data Constant'!$F11*100 -> -1.0357941 | H13: =('[8]Data Constant'!L15-'[8]Data Constant'!L11)/'[8]Data Constant'!$F11*100 -> 0.55252231 | I13: =-('[8]Data Constant'!M15-'[8]Data Constant'!M11)/'[8]Data Constant'!$F11*100 -> -0.76601369 | J13: =SUM(D13:I13) -> 5.5715853 | K13: =J13-C13 -> -4.1744386e-14 | L13: =IF(OR('[8]Data Constant'!K15="",'[8]Data Constant'!K11=""),"",('[8]Data Constant'!K15-'[8]Data Constant'!K11)/'[8]Data Constant'!$F11*100) | N13: =SUM(O13:Q13) -> 5.5715853 | O13: =D13+E13+F13 -> 6.8208707 | P13: =+G13 -> -1.0357941 | Q13: =+H13+I13 -> -0.21349138
B14: ='[8]Data Constant'!B16 -> 3Q 2006 | C14: =('[8]Data Constant'!F16/'[8]Data Constant'!F12-1)*100 -> 9.3804903 | D14: =('[8]Data Constant'!G16-'[8]Data Constant'!G12)/'[8]Data Constant'!$F12*100 -> 9.5515716 | E14: =('[8]Data Constant'!H16-'[8]Data Constant'!H12)/'[8]Data Constant'!$F12*100 -> 0.36181468 | F14: =('[8]Data Constant'!I16-'[8]Data Constant'!I12)/'[8]Data Constant'!$F12*100 -> 3.1630208 | G14: =('[8]Data Constant'!N16-'[8]Data Constant'!N12)/'[8]Data Constant'!$F12*100 -> -1.9167531 | H14: =('[8]Data Constant'!L16-'[8]Data Constant'!L12)/'[8]Data Constant'!$F12*100 -> 0.74652874 | I14: =-('[8]Data Constant'!M16-'[8]Data Constant'!M12)/'[8]Data Constant'!$F12*100 -> -2.5256925 | J14: =SUM(D14:I14) -> 9.3804903 | K14: =J14-C14 -> -7.1054274e-14 | L14: =IF(OR('[8]Data Constant'!K16="",'[8]Data Constant'!K12=""),"",('[8]Data Constant'!K16-'[8]Data Constant'!K12)/'[8]Data Constant'!$F12*100) | N14: =SUM(O14:Q14) -> 9.3804903 | O14: =D14+E14+F14 -> 13.076407 | P14: =+G14 -> -1.9167531 | Q14: =+H14+I14 -> -1.7791638
B15: ='[8]Data Constant'!B17 -> 4Q 2006 | C15: =('[8]Data Constant'!F17/'[8]Data Constant'!F13-1)*100 -> 9.6770404 | D15: =('[8]Data Constant'!G17-'[8]Data Constant'!G13)/'[8]Data Constant'!$F13*100 -> 6.8154072 | E15: =('[8]Data Constant'!H17-'[8]Data Constant'!H13)/'[8]Data Constant'!$F13*100 -> 0.47242029 | F15: =('[8]Data Constant'!I17-'[8]Data Constant'!I13)/'[8]Data Constant'!$F13*100 -> 2.1846725 | G15: =('[8]Data Constant'!N17-'[8]Data Constant'!N13)/'[8]Data Constant'!$F13*100 -> -0.35478561 | H15: =('[8]Data Constant'!L17-'[8]Data Constant'!L13)/'[8]Data Constant'!$F13*100 -> 2.9449257 | I15: =-('[8]Data Constant'!M17-'[8]Data Constant'!M13)/'[8]Data Constant'!$F13*100 -> -2.3855997 | J15: =SUM(D15:I15) -> 9.6770404 | K15: =J15-C15 -> 3.5527137e-14 | L15: =IF(OR('[8]Data Constant'!K17="",'[8]Data Constant'!K13=""),"",('[8]Data Constant'!K17-'[8]Data Constant'!K13)/'[8]Data Constant'!$F13*100) | N15: =SUM(O15:Q15) -> 9.6770404 | O15: =D15+E15+F15 -> 9.4724999 | P15: =+G15 -> -0.35478561 | Q15: =+H15+I15 -> 0.55932604
B16: ='[8]Data Constant'!B18 -> 1Q 2007 | C16: =('[8]Data Constant'!F18/'[8]Data Constant'!F14-1)*100 -> 8.3589411 | D16: =('[8]Data Constant'!G18-'[8]Data Constant'!G14)/'[8]Data Constant'!$F14*100 -> 7.449786 | E16: =('[8]Data Constant'!H18-'[8]Data Constant'!H14)/'[8]Data Constant'!$F14*100 -> 0.81625617 | F16: =('[8]Data Constant'!I18-'[8]Data Constant'!I14)/'[8]Data Constant'!$F14*100 -> 3.3104135 | G16: =('[8]Data Constant'!N18-'[8]Data Constant'!N14)/'[8]Data Constant'!$F14*100 -> -1.063079 | H16: =('[8]Data Constant'!L18-'[8]Data Constant'!L14)/'[8]Data Constant'!$F14*100 -> 0.78755783 | I16: =-('[8]Data Constant'!M18-'[8]Data Constant'!M14)/'[8]Data Constant'!$F14*100 -> -2.9419933 | J16: =SUM(D16:I16) -> 8.3589411 | K16: =J16-C16 -> 1.4210855e-13 | L16: =IF(OR('[8]Data Constant'!K18="",'[8]Data Constant'!K14=""),"",('[8]Data Constant'!K18-'[8]Data Constant'!K14)/'[8]Data Constant'!$F14*100) | N16: =SUM(O16:Q16) -> 8.3589411 | O16: =D16+E16+F16 -> 11.576456 | P16: =+G16 -> -1.063079 | Q16: =+H16+I16 -> -2.1544355
B17: ='[8]Data Constant'!B19 -> 2Q 2007 | C17: =('[8]Data Constant'!F19/'[8]Data Constant'!F15-1)*100 -> 9.8593874 | D17: =('[8]Data Constant'!G19-'[8]Data Constant'!G15)/'[8]Data Constant'!$F15*100 -> 5.0859218 | E17: =('[8]Data Constant'!H19-'[8]Data Constant'!H15)/'[8]Data Constant'!$F15*100 -> 0.85606634 | F17: =('[8]Data Constant'!I19-'[8]Data Constant'!I15)/'[8]Data Constant'!$F15*100 -> 3.259732 | G17: =('[8]Data Constant'!N19-'[8]Data Constant'!N15)/'[8]Data Constant'!$F15*100 -> 1.5553316 | H17: =('[8]Data Constant'!L19-'[8]Data Constant'!L15)/'[8]Data Constant'!$F15*100 -> 1.6970396 | I17: =-('[8]Data Constant'!M19-'[8]Data Constant'!M15)/'[8]Data Constant'!$F15*100 -> -2.594704 | J17: =SUM(D17:I17) -> 9.8593874 | K17: =J17-C17 -> 3.5171865e-13 | L17: =IF(OR('[8]Data Constant'!K19="",'[8]Data Constant'!K15=""),"",('[8]Data Constant'!K19-'[8]Data Constant'!K15)/'[8]Data Constant'!$F15*100) | N17: =SUM(O17:Q17) -> 9.8593874 | O17: =D17+E17+F17 -> 9.2017201 | P17: =+G17 -> 1.5553316 | Q17: =+H17+I17 -> -0.89766435
B18: ='[8]Data Constant'!B20 -> 3Q 2007 | C18: =('[8]Data Constant'!F20/'[8]Data Constant'!F16-1)*100 -> 8.4277977 | D18: =('[8]Data Constant'!G20-'[8]Data Constant'!G16)/'[8]Data Constant'!$F16*100 -> 5.3625351 | E18: =('[8]Data Constant'!H20-'[8]Data Constant'!H16)/'[8]Data Constant'!$F16*100 -> 0.81201468 | F18: =('[8]Data Constant'!I20-'[8]Data Constant'!I16)/'[8]Data Constant'!$F16*100 -> 4.0259232 | G18: =('[8]Data Constant'!N20-'[8]Data Constant'!N16)/'[8]Data Constant'!$F16*100 -> 0.29828216 | H18: =('[8]Data Constant'!L20-'[8]Data Constant'!L16)/'[8]Data Constant'!$F16*100 -> 2.6084335 | I18: =-('[8]Data Constant'!M20-'[8]Data Constant'!M16)/'[8]Data Constant'!$F16*100 -> -4.6793909 | J18: =SUM(D18:I18) -> 8.4277977 | K18: =J18-C18 -> -2.2737368e-13 | L18: =IF(OR('[8]Data Constant'!K20="",'[8]Data Constant'!K16=""),"",('[8]Data Constant'!K20-'[8]Data Constant'!K16)/'[8]Data Constant'!$F16*100) | N18: =SUM(O18:Q18) -> 8.4277977 | O18: =D18+E18+F18 -> 10.200473 | P18: =+G18 -> 0.29828216 | Q18: =+H18+I18 -> -2.0709574
B19: ='[8]Data Constant'!B21 -> 4Q 2007 | C19: =('[8]Data Constant'!F21/'[8]Data Constant'!F17-1)*100 -> 9.2673486 | D19: =('[8]Data Constant'!G21-'[8]Data Constant'!G17)/'[8]Data Constant'!$F17*100 -> 6.6052232 | E19: =('[8]Data Constant'!H21-'[8]Data Constant'!H17)/'[8]Data Constant'!$F17*100 -> 0.88479207 | F19: =('[8]Data Constant'!I21-'[8]Data Constant'!I17)/'[8]Data Constant'!$F17*100 -> 4.0737349 | G19: =('[8]Data Constant'!N21-'[8]Data Constant'!N17)/'[8]Data Constant'!$F17*100 -> -0.74519655 | H19: =('[8]Data Constant'!L21-'[8]Data Constant'!L17)/'[8]Data Constant'!$F17*100 -> 2.7450309 | I19: =-('[8]Data Constant'!M21-'[8]Data Constant'!M17)/'[8]Data Constant'!$F17*100 -> -4.2962359 | J19: =SUM(D19:I19) -> 9.2673486 | K19: =J19-C19 -> -1.7941204e-13 | L19: =IF(OR('[8]Data Constant'!K21="",'[8]Data Constant'!K17=""),"",('[8]Data Constant'!K21-'[8]Data Constant'!K17)/'[8]Data Constant'!$F17*100) | N19: =SUM(O19:Q19) -> 9.2673486 | O19: =D19+E19+F19 -> 11.56375 | P19: =+G19 -> -0.74519655 | Q19: =+H19+I19 -> -1.551205
B20: ='[8]Data Constant'!B22 -> 1Q 2008 | C20: =('[8]Data Constant'!F22/'[8]Data Constant'!F18-1)*100 -> 6.9123146 | D20: =('[8]Data Constant'!G22-'[8]Data Constant'!G18)/'[8]Data Constant'!$F18*100 -> 6.9619858 | E20: =('[8]Data Constant'!H22-'[8]Data Constant'!H18)/'[8]Data Constant'!$F18*100 -> 0.40112646 | F20: =('[8]Data Constant'!I22-'[8]Data Constant'!I18)/'[8]Data Constant'!$F18*100 -> 3.3642853 | G20: =('[8]Data Constant'!N22-'[8]Data Constant'!N18)/'[8]Data Constant'!$F18*100 -> -0.67243016 | H20: =('[8]Data Constant'!L22-'[8]Data Constant'!L18)/'[8]Data Constant'!$F18*100 -> 1.4234907 | I20: =-('[8]Data Constant'!M22-'[8]Data Constant'!M18)/'[8]Data Constant'!$F18*100 -> -4.5661435 | J20: =SUM(D20:I20) -> 6.9123146 | K20: =J20-C20 -> 6.6613381e-14 | L20: =IF(OR('[8]Data Constant'!K22="",'[8]Data Constant'!K18=""),"",('[8]Data Constant'!K22-'[8]Data Constant'!K18)/'[8]Data Constant'!$F18*100) | N20: =SUM(O20:Q20) -> 6.9123146 | O20: =D20+E20+F20 -> 10.727398 | P20: =+G20 -> -0.67243016 | Q20: =+H20+I20 -> -3.1426528
B21: ='[8]Data Constant'!B23 -> 2Q 2008 | C21: =('[8]Data Constant'!F23/'[8]Data Constant'!F19-1)*100 -> 5.4526855 | D21: =('[8]Data Constant'!G23-'[8]Data Constant'!G19)/'[8]Data Constant'!$F19*100 -> 6.1564011 | E21: =('[8]Data Constant'!H23-'[8]Data Constant'!H19)/'[8]Data Constant'!$F19*100 -> 0.57640039 | F21: =('[8]Data Constant'!I23-'[8]Data Constant'!I19)/'[8]Data Constant'!$F19*100 -> 3.2017331 | G21: =('[8]Data Constant'!N23-'[8]Data Constant'!N19)/'[8]Data Constant'!$F19*100 -> 0.4763707 | H21: =('[8]Data Constant'!L23-'[8]Data Constant'!L19)/'[8]Data Constant'!$F19*100 -> -0.60522278 | I21: =-('[8]Data Constant'!M23-'[8]Data Constant'!M19)/'[8]Data Constant'!$F19*100 -> -4.3529971 | J21: =SUM(D21:I21) -> 5.4526855 | K21: =J21-C21 -> -2.016165e-13 | L21: =IF(OR('[8]Data Constant'!K23="",'[8]Data Constant'!K19=""),"",('[8]Data Constant'!K23-'[8]Data Constant'!K19)/'[8]Data Constant'!$F19*100) | N21: =SUM(O21:Q21) -> 5.4526855 | O21: =D21+E21+F21 -> 9.9345346 | P21: =+G21 -> 0.4763707 | Q21: =+H21+I21 -> -4.9582198
B22: ='[8]Data Constant'!B24 -> 3Q 2008 | C22: =('[8]Data Constant'!F24/'[8]Data Constant'!F20-1)*100 -> 6.0060161 | D22: =('[8]Data Constant'!G24-'[8]Data Constant'!G20)/'[8]Data Constant'!$F20*100 -> 3.6252908 | E22: =('[8]Data Constant'!H24-'[8]Data Constant'!H20)/'[8]Data Constant'!$F20*100 -> 0.68989005 | F22: =('[8]Data Constant'!I24-'[8]Data Constant'!I20)/'[8]Data Constant'!$F20*100 -> 1.5657572 | G22: =('[8]Data Constant'!N24-'[8]Data Constant'!N20)/'[8]Data Constant'!$F20*100 -> 0.3883294 | H22: =('[8]Data Constant'!L24-'[8]Data Constant'!L20)/'[8]Data Constant'!$F20*100 -> 2.5001043 | I22: =-('[8]Data Constant'!M24-'[8]Data Constant'!M20)/'[8]Data Constant'!$F20*100 -> -2.7633556 | J22: =SUM(D22:I22) -> 6.0060161 | K22: =J22-C22 -> 2.0516921e-13 | L22: =IF(OR('[8]Data Constant'!K24="",'[8]Data Constant'!K20=""),"",('[8]Data Constant'!K24-'[8]Data Constant'!K20)/'[8]Data Constant'!$F20*100) | N22: =SUM(O22:Q22) -> 6.0060161 | O22: =D22+E22+F22 -> 5.880938 | P22: =+G22 -> 0.3883294 | Q22: =+H22+I22 -> -0.26325124
... B92: ='[8]Data Constant'!B94 -> 1Q 2026 | C92: =('[8]Data Constant'!F94/'[8]Data Constant'!F90-1)*100 -> 2.3276313 | D92: =('[8]Data Constant'!G94-'[8]Data Constant'!G90)/'[8]Data Constant'!$F90*100 -> 2.1949153 | E92: =('[8]Data Constant'!H94-'[8]Data Constant'!H90)/'[8]Data Constant'!$F90*100 -> -0.11715373 | F92: =('[8]Data Constant'!I94-'[8]Data Constant'!I90)/'[8]Data Constant'!$F90*100 -> -2.3248095 | G92: =('[8]Data Constant'!N94-'[8]Data Constant'!N90)/'[8]Data Constant'!$F90*100 -> -2.0200721 | H92: =('[8]Data Constant'!L94-'[8]Data Constant'!L90)/'[8]Data Constant'!$F90*100 -> 2.1753871 | I92: =-('[8]Data Constant'!M94-'[8]Data Constant'!M90)/'[8]Data Constant'!$F90*100 -> 2.4193642 | J92: =SUM(D92:I92) -> 2.3276313 | K92: =J92-C92 -> -1.5543122e-14 | L92: =IF(OR('[8]Data Constant'!K94="",'[8]Data Constant'!K90=""),"",('[8]Data Constant'!K94-'[8]Data Constant'!K90)/'[8]Data Constant'!$F90*100) -> -0.22184522 | N92: =SUM(O92:Q92) -> 2.3276313 | O92: =D92+E92+F92 -> -0.24704796 | P92: =+G92 -> -2.0200721 | Q92: =+H92+I92 -> 4.5947513
B94: The check column is zero everywhere except Q3/Q4 2019 and their y/y counterparts in 2020, where INDEC's own components do not sum to GDP. The memo column is blank before 2024 because the discrepancy series does not exist there — it is inside the inventories line, where the contribution calculation already counts it.
B97: 2. Annual
B98: Year | C98: GDP y/y | D98: Private consumption | E98: Public consumption | F98: GFCF | G98: Inventories + discrepancy | H98: Exports | I98: Imports | J98: Sum of contributions | K98: Check (sum - GDP)
B99: =[8]Annual!B7 -> 2005 | C99: =[8]Annual!J7*100 -> 8.8516599 | D99: =([8]Annual!D7-[8]Annual!D6)/[8]Annual!$C6*100 -> 4.7557566 | E99: =([8]Annual!E7-[8]Annual!E6)/[8]Annual!$C6*100 -> 1.0953957 | F99: =([8]Annual!F7-[8]Annual!F6)/[8]Annual!$C6*100 -> 2.5157278 | G99: =([8]Annual!G7-[8]Annual!G6)/[8]Annual!$C6*100 -> 0.081216329 | H99: =([8]Annual!H7-[8]Annual!H6)/[8]Annual!$C6*100 -> 3.0732023 | I99: =-([8]Annual!I7-[8]Annual!I6)/[8]Annual!$C6*100 -> -2.6696389 | J99: =SUM(D99:I99) -> 8.8516599 | K99: =J99-C99 -> 1.0125234e-13
B100: =[8]Annual!B8 -> 2006 | C100: =[8]Annual!J8*100 -> 8.0471515 | D100: =([8]Annual!D8-[8]Annual!D7)/[8]Annual!$C7*100 -> 6.9538323 | E100: =([8]Annual!E8-[8]Annual!E7)/[8]Annual!$C7*100 -> 0.41756023 | F100: =([8]Annual!F8-[8]Annual!F7)/[8]Annual!$C7*100 -> 2.4477121 | G100: =([8]Annual!G8-[8]Annual!G7)/[8]Annual!$C7*100 -> -1.176736 | H100: =([8]Annual!H8-[8]Annual!H7)/[8]Annual!$C7*100 -> 1.3753778 | I100: =-([8]Annual!I8-[8]Annual!I7)/[8]Annual!$C7*100 -> -1.9705949 | J100: =SUM(D100:I100) -> 8.0471515 | K100: =J100-C100 -> -5.5067062e-14
B101: =[8]Annual!B9 -> 2007 | C101: =[8]Annual!J9*100 -> 9.0076509 | D101: =([8]Annual!D9-[8]Annual!D8)/[8]Annual!$C8*100 -> 6.086875 | E101: =([8]Annual!E9-[8]Annual!E8)/[8]Annual!$C8*100 -> 0.84312307 | F101: =([8]Annual!F9-[8]Annual!F8)/[8]Annual!$C8*100 -> 3.6648616 | G101: =([8]Annual!G9-[8]Annual!G8)/[8]Annual!$C8*100 -> 0.05707071 | H101: =([8]Annual!H9-[8]Annual!H8)/[8]Annual!$C8*100 -> 1.9727466 | I101: =-([8]Annual!I9-[8]Annual!I8)/[8]Annual!$C8*100 -> -3.6170261 | J101: =SUM(D101:I101) -> 9.0076509 | K101: =J101-C101 -> 0
B102: =[8]Annual!B10 -> 2008 | C102: =[8]Annual!J10*100 -> 4.0572331 | D102: =([8]Annual!D10-[8]Annual!D9)/[8]Annual!$C9*100 -> 4.7362664 | E102: =([8]Annual!E10-[8]Annual!E9)/[8]Annual!$C9*100 -> 0.5341964 | F102: =([8]Annual!F10-[8]Annual!F9)/[8]Annual!$C9*100 -> 1.7216663 | G102: =([8]Annual!G10-[8]Annual!G9)/[8]Annual!$C9*100 -> -0.37100223 | H102: =([8]Annual!H10-[8]Annual!H9)/[8]Annual!$C9*100 -> 0.17739031 | I102: =-([8]Annual!I10-[8]Annual!I9)/[8]Annual!$C9*100 -> -2.7412842 | J102: =SUM(D102:I102) -> 4.0572331 | K102: =J102-C102 -> 6.9277917e-14
B103: =[8]Annual!B11 -> 2009 | C103: =[8]Annual!J11*100 -> -5.9185251 | D103: =([8]Annual!D11-[8]Annual!D10)/[8]Annual!$C10*100 -> -3.6368636 | E103: =([8]Annual!E11-[8]Annual!E10)/[8]Annual!$C10*100 -> 0.60567416 | F103: =([8]Annual!F11-[8]Annual!F10)/[8]Annual!$C10*100 -> -4.6685624 | G103: =([8]Annual!G11-[8]Annual!G10)/[8]Annual!$C10*100 -> -0.11166296 | H103: =([8]Annual!H11-[8]Annual!H10)/[8]Annual!$C10*100 -> -2.1695924 | I103: =-([8]Annual!I11-[8]Annual!I10)/[8]Annual!$C10*100 -> 4.0624822 | J103: =SUM(D103:I103) -> -5.9185251 | K103: =J103-C103 -> -8.2600593e-14
B104: =[8]Annual!B12 -> 2010 | C104: =[8]Annual!J12*100 -> 10.125398 | D104: =([8]Annual!D12-[8]Annual!D11)/[8]Annual!$C11*100 -> 7.5801847 | E104: =([8]Annual!E12-[8]Annual!E11)/[8]Annual!$C11*100 -> 0.65807153 | F104: =([8]Annual!F12-[8]Annual!F11)/[8]Annual!$C11*100 -> 4.4688009 | G104: =([8]Annual!G12-[8]Annual!G11)/[8]Annual!$C11*100 -> 1.0443576 | H104: =([8]Annual!H12-[8]Annual!H11)/[8]Annual!$C11*100 -> 3.1081136 | I104: =-([8]Annual!I12-[8]Annual!I11)/[8]Annual!$C11*100 -> -6.7341301 | J104: =SUM(D104:I104) -> 10.125398 | K104: =J104-C104 -> 0
B105: =[8]Annual!B13 -> 2011 | C105: =[8]Annual!J13*100 -> 6.0039517 | D105: =([8]Annual!D13-[8]Annual!D12)/[8]Annual!$C12*100 -> 6.4087203 | E105: =([8]Annual!E13-[8]Annual!E12)/[8]Annual!$C12*100 -> 0.52759843 | F105: =([8]Annual!F13-[8]Annual!F12)/[8]Annual!$C12*100 -> 3.3911296 | G105: =([8]Annual!G13-[8]Annual!G12)/[8]Annual!$C12*100 -> -0.10979105 | H105: =([8]Annual!H13-[8]Annual!H12)/[8]Annual!$C12*100 -> 0.95968131 | I105: =-([8]Annual!I13-[8]Annual!I12)/[8]Annual!$C12*100 -> -5.1733869 | J105: =SUM(D105:I105) -> 6.0039517 | K105: =J105-C105 -> -2.3980817e-14
B106: =[8]Annual!B14 -> 2012 | C106: =[8]Annual!J14*100 -> -1.0264205 | D106: =([8]Annual!D14-[8]Annual!D13)/[8]Annual!$C13*100 -> 0.78360175 | E106: =([8]Annual!E14-[8]Annual!E13)/[8]Annual!$C13*100 -> 0.34308374 | F106: =([8]Annual!F14-[8]Annual!F13)/[8]Annual!$C13*100 -> -1.5287935 | G106: =([8]Annual!G14-[8]Annual!G13)/[8]Annual!$C13*100 -> -0.96892011 | H106: =([8]Annual!H14-[8]Annual!H13)/[8]Annual!$C13*100 -> -0.9336812 | I106: =-([8]Annual!I14-[8]Annual!I13)/[8]Annual!$C13*100 -> 1.2782889 | J106: =SUM(D106:I106) -> -1.0264205 | K106: =J106-C106 -> -3.9745984e-14
B107: =[8]Annual!B15 -> 2013 | C107: =[8]Annual!J15*100 -> 2.4053238 | D107: =([8]Annual!D15-[8]Annual!D14)/[8]Annual!$C14*100 -> 2.6237455 | E107: =([8]Annual!E15-[8]Annual!E14)/[8]Annual!$C14*100 -> 0.63156081 | F107: =([8]Annual!F15-[8]Annual!F14)/[8]Annual!$C14*100 -> 0.47461725 | G107: =([8]Annual!G15-[8]Annual!G14)/[8]Annual!$C14*100 -> 0.46099739 | H107: =([8]Annual!H15-[8]Annual!H14)/[8]Annual!$C14*100 -> -0.77512058 | I107: =-([8]Annual!I15-[8]Annual!I14)/[8]Annual!$C14*100 -> -1.0104766 | J107: =SUM(D107:I107) -> 2.4053238 | K107: =J107-C107 -> 1.0036416e-13
B108: =[8]Annual!B16 -> 2014 | C108: =[8]Annual!J16*100 -> -2.5126153 | D108: =([8]Annual!D16-[8]Annual!D15)/[8]Annual!$C15*100 -> -3.1801596 | E108: =([8]Annual!E16-[8]Annual!E15)/[8]Annual!$C15*100 -> 0.35940254 | F108: =([8]Annual!F16-[8]Annual!F15)/[8]Annual!$C15*100 -> -1.3696312 | G108: =([8]Annual!G16-[8]Annual!G15)/[8]Annual!$C15*100 -> 0.094945196 | H108: =([8]Annual!H16-[8]Annual!H15)/[8]Annual!$C15*100 -> -1.4478189 | I108: =-([8]Annual!I16-[8]Annual!I15)/[8]Annual!$C15*100 -> 3.0306467 | J108: =SUM(D108:I108) -> -2.5126153 | K108: =J108-C108 -> -8.1712415e-14
B109: =[8]Annual!B17 -> 2015 | C109: =[8]Annual!J17*100 -> 2.7311598 | D109: =([8]Annual!D17-[8]Annual!D16)/[8]Annual!$C16*100 -> 2.6173851 | E109: =([8]Annual!E17-[8]Annual!E16)/[8]Annual!$C16*100 -> 0.89512459 | F109: =([8]Annual!F17-[8]Annual!F16)/[8]Annual!$C16*100 -> 0.67144133 | G109: =([8]Annual!G17-[8]Annual!G16)/[8]Annual!$C16*100 -> 0.22632468 | H109: =([8]Annual!H17-[8]Annual!H16)/[8]Annual!$C16*100 -> -0.54976442 | I109: =-([8]Annual!I17-[8]Annual!I16)/[8]Annual!$C16*100 -> -1.1293515 | J109: =SUM(D109:I109) -> 2.7311598 | K109: =J109-C109 -> 1.3411494e-13
B110: =[8]Annual!B18 -> 2016 | C110: =[8]Annual!J18*100 -> -2.0803278 | D110: =([8]Annual!D18-[8]Annual!D17)/[8]Annual!$C17*100 -> -0.56360696 | E110: =([8]Annual!E18-[8]Annual!E17)/[8]Annual!$C17*100 -> -0.070348246 | F110: =([8]Annual!F18-[8]Annual!F17)/[8]Annual!$C17*100 -> -1.1285253 | G110: =([8]Annual!G18-[8]Annual!G17)/[8]Annual!$C17*100 -> 0.10907399 | H110: =([8]Annual!H18-[8]Annual!H17)/[8]Annual!$C17*100 -> 0.99610055 | I110: =-([8]Annual!I18-[8]Annual!I17)/[8]Annual!$C17*100 -> -1.4230219 | J110: =SUM(D110:I110) -> -2.0803278 | K110: =J110-C110 -> -1.6431301e-13
... B119: =[8]Annual!B27 -> 2025 | C119: =[8]Annual!J27*100 -> 4.4832446 | D119: =([8]Annual!D27-[8]Annual!D26)/[8]Annual!$C26*100 -> 6.1738342 | E119: =([8]Annual!E27-[8]Annual!E26)/[8]Annual!$C26*100 -> 0.051670444 | F119: =([8]Annual!F27-[8]Annual!F26)/[8]Annual!$C26*100 -> 2.8260448 | G119: =([8]Annual!G27-[8]Annual!G26)/[8]Annual!$C26*100 -> 0.54704652 | H119: =([8]Annual!H27-[8]Annual!H26)/[8]Annual!$C26*100 -> 1.8835432 | I119: =-([8]Annual!I27-[8]Annual!I26)/[8]Annual!$C26*100 -> -6.9988946 | J119: =SUM(D119:I119) -> 4.4832446 | K119: =J119-C119 -> -5.6843419e-14

Sheet 12 month rolling fiscal
B2: 1161 !Q | C2: N213NGDP@EMERGELA | I2: 11601 !M | J2: movt(N213FGB@EMERGELA,12) | K2: movt(N213FGPB@EMERGELA,12) | L2: movt(N213FECD@EMERGELA,12) | M2: GDP nominal
B3: .DESC | C3: Argentina: Gross Domestic Product at Market Prices (NSAAR, Bil.Pesos) | I3: .DESC | J3: Argentina: Public Sector: Budget Balance (NSA, Mil.Pesos) 12-month MovingTotal | K3: Argentina: Public Sector: Primary Budget Balance (NSA, Mil.Pesos) 12-month MovingTotal | L3: Argentina: Public Sector: Interest Payments (NSA, Mil.Pesos) 12-month MovingTotal
B4: .SOURCE | C4: INDEC | I4: .SOURCE | J4: MH | K4: MH | L4: MH
B5: .DATA_TYPE | C5: LocCur | I5: .DATA_TYPE | J5: LocCur | K5: LocCur | L5: LocCur
B6: .MAG | C6: 9 | I6: .MAG | J6: 6 | K6: 6 | L6: 6
A7: 1Q 2016 | B7: 161 | C7: 7006.65 | H7: 42370 | I7: 1601 | J7: -214370.9 | K7: #N/A | L7: #N/A
A8: 2Q 2016 | B8: 162 | C8: 8414.56 | H8: 42401 | I8: 1602 | J8: -218514.9 | K8: #N/A | L8: #N/A
A9: 3Q 2016 | B9: 163 | C9: 8527.63 | H9: 42430 | I9: 1603 | J9: -232452.4 | K9: #N/A | L9: #N/A
A10: 4Q 2016 | B10: 164 | C10: 8963.81 | D10: =AVERAGE(C7:C10) -> 8228.1625 | H10: 42461 | I10: 1604 | J10: -225423.9 | K10: #N/A | L10: #N/A
A11: 1Q 2017 | B11: 171 | C11: 9240.88 | D11: =AVERAGE(C8:C11) -> 8786.72 | H11: 42491 | I11: 1605 | J11: -244117 | K11: #N/A | L11: #N/A
A12: 2Q 2017 | B12: 172 | C12: 10558.21 | D12: =AVERAGE(C9:C12) -> 9322.6325 | H12: 42522 | I12: 1606 | J12: -296722.8 | K12: #N/A | L12: #N/A
A13: 3Q 2017 | B13: 173 | C13: 11116.42 | D13: =AVERAGE(C10:C13) -> 9969.83 | H13: 42552 | I13: 1607 | J13: -323270.6 | K13: #N/A | L13: #N/A
A14: 4Q 2017 | B14: 174 | C14: 11725.41 | D14: =AVERAGE(C11:C14) -> 10660.23 | E14: =D14/D10-1 -> 0.29557845 | H14: 42583 | I14: 1608 | J14: -350743.9 | K14: #N/A | L14: #N/A
A15: 1Q 2018 | B15: 181 | C15: 12457.79 | D15: =AVERAGE(C12:C15) -> 11464.457 | E15: =D15/D11-1 -> 0.30474825 | H15: 42614 | I15: 1609 | J15: -379662.9 | K15: #N/A | L15: #N/A
A16: 2Q 2018 | B16: 182 | C16: 14431.39 | D16: =AVERAGE(C13:C16) -> 12432.753 | E16: =D16/D12-1 -> 0.33360963 | H16: 42644 | I16: 1610 | J16: -439401.3 | K16: #N/A | L16: #N/A
A17: 3Q 2018 | B17: 183 | C17: 15276.28 | D17: =AVERAGE(C14:C17) -> 13472.717 | E17: =D17/D13-1 -> 0.35134877 | H17: 42675 | I17: 1611 | J17: -450044.6 | K17: #N/A | L17: #N/A
A18: 4Q 2018 | B18: 184 | C18: 16813.78 | D18: =AVERAGE(C15:C18) -> 14744.81 | E18: =D18/D14-1 -> 0.38316059 | H18: 42705 | I18: 1612 | J18: -474785.5 | K18: -343525.5 | L18: 131260 | N18: Fiscal balance (% of GDP) | O18: Primary balance (% of GDP)
A19: 1Q 2019 | B19: 191 | C19: 17484.11 | D19: =AVERAGE(C16:C19) -> 16001.39 | E19: =D19/D15-1 -> 0.39573896 | G19: 1Q 2017 | H19: 42736 | I19: 1701 | J19: -478144.3 | K19: -340679 | L19: 137465.3 | M19: =VLOOKUP(G19,$A$11:$D$47,4,FALSE) -> 8786.72 | N19: =J19/M19/10 -> -5.4416699 | O19: =K19/M19/10 -> -3.8772033
A20: 2Q 2019 | B20: 192 | C20: 21233.56 | D20: =AVERAGE(C17:C20) -> 17701.932 | E20: =D20/D16-1 -> 0.42381444 | G20: 1Q 2017 | H20: 42767 | I20: 1702 | J20: -487607.4 | K20: -350783.4 | L20: 136824 | M20: =VLOOKUP(G20,$A$11:$D$47,4,FALSE) -> 8786.72 | N20: =J20/M20/10 -> -5.5493677 | O20: =K20/M20/10 -> -3.9921996
A21: 3Q 2019 | B21: 193 | C21: 22303.88 | D21: =AVERAGE(C18:C21) -> 19458.833 | E21: =D21/D17-1 -> 0.44431385 | G21: 1Q 2017 | H21: 42795 | I21: 1703 | J21: -480856.7 | K21: -338955.5 | L21: 141901.2 | M21: =VLOOKUP(G21,$A$11:$D$47,4,FALSE) -> 8786.72 | N21: =J21/M21/10 -> -5.4725392 | O21: =K21/M21/10 -> -3.8575885
A22: 4Q 2019 | B22: 194 | C22: 25212.23 | D22: =AVERAGE(C19:C22) -> 21558.445 | E22: =D22/D18-1 -> 0.46210395 | G22: 2Q 2017 | H22: 42826 | I22: 1704 | J22: -512793.7 | K22: -346725.6 | L22: 166068.1 | M22: =VLOOKUP(G22,$A$11:$D$47,4,FALSE) -> 9322.6325 | N22: =J22/M22/10 -> -5.5005247 | O22: =K22/M22/10 -> -3.7191813
A23: 1Q 2020 | B23: 201 | C23: 24999.99 | D23: =AVERAGE(C20:C23) -> 23437.415 | E23: =D23/D19-1 -> 0.46471119 | G23: 2Q 2017 | H23: 42856 | I23: 1705 | J23: -532845.3 | K23: -361990.8 | L23: 170854.5 | M23: =VLOOKUP(G23,$A$11:$D$47,4,FALSE) -> 9322.6325 | N23: =J23/M23/10 -> -5.7156098 | O23: =K23/M23/10 -> -3.8829247
A24: 2Q 2020 | B24: 202 | C24: 24025.36 | D24: =AVERAGE(C21:C24) -> 24135.365 | E24: =D24/D20-1 -> 0.36343108 | G24: 2Q 2017 | H24: 42887 | I24: 1706 | J24: -552110.2 | K24: -375021.6 | L24: 177088.6 | M24: =VLOOKUP(G24,$A$11:$D$47,4,FALSE) -> 9322.6325 | N24: =J24/M24/10 -> -5.9222564 | O24: =K24/M24/10 -> -4.0227007
A25: 3Q 2020 | B25: 203 | C25: 27536.38 | D25: =AVERAGE(C22:C25) -> 25443.49 | E25: =D25/D21-1 -> 0.30755481 | G25: 3Q 2017 | H25: 42917 | I25: 1707 | J25: -557246.9 | K25: -372744.9 | L25: 184502 | M25: =VLOOKUP(G25,$A$11:$D$47,4,FALSE) -> 9969.83 | N25: =J25/M25/10 -> -5.589332 | O25: =K25/M25/10 -> -3.7387287
A26: 4Q 2020 | B26: 204 | C26: 32277.53 | D26: =AVERAGE(C23:C26) -> 27209.815 | E26: =D26/D22-1 -> 0.26214182 | G26: 3Q 2017 | H26: 42948 | I26: 1708 | J26: -550016.7 | K26: -361980 | L26: 188036.7 | M26: =VLOOKUP(G26,$A$11:$D$47,4,FALSE) -> 9969.83 | N26: =J26/M26/10 -> -5.5168112 | O26: =K26/M26/10 -> -3.630754
A27: 1Q 2021 | B27: 211 | C27: 36785.11 | D27: =AVERAGE(C24:C27) -> 30156.095 | E27: =D27/D23-1 -> 0.28666472 | G27: 3Q 2017 | H27: 42979 | I27: 1709 | J27: -552197.5 | K27: -356315.8 | L27: 195881.7 | M27: =VLOOKUP(G27,$A$11:$D$47,4,FALSE) -> 9969.83 | N27: =J27/M27/10 -> -5.5386852 | O27: =K27/M27/10 -> -3.5739406
A28: 2Q 2021 | B28: 212 | C28: 46340.28 | D28: =AVERAGE(C25:C28) -> 35734.825 | E28: =D28/D24-1 -> 0.48060015 | G28: 4Q 2017 | H28: 43009 | I28: 1710 | J28: -536628.7 | K28: -326942.3 | L28: 209686.4 | M28: =VLOOKUP(G28,$A$11:$D$47,4,FALSE) -> 10660.23 | N28: =J28/M28/10 -> -5.0339317 | O28: =K28/M28/10 -> -3.0669348
A29: 3Q 2021 | B29: 213 | C29: 47462.53 | D29: =AVERAGE(C26:C29) -> 40716.363 | E29: =D29/D25-1 -> 0.60026641 | G29: 4Q 2017 | H29: 43040 | I29: 1711 | J29: -562791.6 | K29: -343304.1 | L29: 219487.5 | M29: =VLOOKUP(G29,$A$11:$D$47,4,FALSE) -> 10660.23 | N29: =J29/M29/10 -> -5.279357 | O29: =K29/M29/10 -> -3.2204193
A30: 4Q 2021 | B30: 214 | C30: 54288.41 | D30: =AVERAGE(C27:C30) -> 46219.083 | E30: =D30/D26-1 -> 0.69861804 | G30: 4Q 2017 | H30: 43070 | I30: 1712 | J30: -629049.5 | K30: -404142.3 | L30: 224907.2 | M30: =VLOOKUP(G30,$A$11:$D$47,4,FALSE) -> 10660.23 | N30: =J30/M30/10 -> -5.9008999 | O30: =K30/M30/10 -> -3.7911218
... A47: 1Q 2026 | B47: 261 | C47: 973875.78 | D47: =AVERAGE(C44:C47) -> 911284.19 | E47: =D47/D43-1 -> 0.38316186 | G47: 2Q 2019 | H47: 43586 | I47: 1905 | J47: -785095.3 | K47: -253006.9 | L47: 532088.4 | M47: =VLOOKUP(G47,$A$11:$D$47,4,FALSE) -> 17701.932 | N47: =J47/M47/10 -> -4.4350824 | O47: =K47/M47/10 -> -1.4292615
G48: 2Q 2019 | H48: 43617 | I48: 1906 | J48: -763941.9 | K48: -202941.5 | L48: 561000.4 | M48: =VLOOKUP(G48,$A$11:$D$47,4,FALSE) -> 17701.932 | N48: =J48/M48/10 -> -4.3155848 | O48: =K48/M48/10 -> -1.146437
G49: 3Q 2019 | H49: 43647 | I49: 1907 | J49: -779429.1 | K49: -184369.1 | L49: 595060 | M49: =VLOOKUP(G49,$A$11:$D$47,4,FALSE) -> 19458.833 | N49: =J49/M49/10 -> -4.0055286 | O49: =K49/M49/10 -> -0.94748285
G50: 3Q 2019 | H50: 43678 | I50: 1908 | J50: -779709.8 | K50: -160266.6 | L50: 619443.2 | M50: =VLOOKUP(G50,$A$11:$D$47,4,FALSE) -> 19458.833 | N50: =J50/M50/10 -> -4.0069711 | O50: =K50/M50/10 -> -0.82361879
G51: 3Q 2019 | H51: 43709 | I51: 1909 | J51: -800075.7 | K51: -162780.6 | L51: 637295.1 | M51: =VLOOKUP(G51,$A$11:$D$47,4,FALSE) -> 19458.833 | N51: =J51/M51/10 -> -4.1116326 | O51: =K51/M51/10 -> -0.83653837
G52: 4Q 2019 | H52: 43739 | I52: 1910 | J52: -785996.3 | K52: -137667.8 | L52: 648328.5 | M52: =VLOOKUP(G52,$A$11:$D$47,4,FALSE) -> 21558.445 | N52: =J52/M52/10 -> -3.6458859 | O52: =K52/M52/10 -> -0.63857945
G53: 4Q 2019 | H53: 43770 | I53: 1911 | J53: -786778.3 | K53: -110294.6 | L53: 676483.7 | M53: =VLOOKUP(G53,$A$11:$D$47,4,FALSE) -> 21558.445 | N53: =J53/M53/10 -> -3.6495132 | O53: =K53/M53/10 -> -0.5116074
G54: 4Q 2019 | H54: 43800 | I54: 1912 | J54: -819406.8 | K54: -95121.5 | L54: 724285.3 | M54: =VLOOKUP(G54,$A$11:$D$47,4,FALSE) -> 21558.445 | N54: =J54/M54/10 -> -3.8008623 | O54: =K54/M54/10 -> -0.44122616
G55: 1Q 2020 | H55: 43831 | I55: 2001 | J55: -850186.9 | K55: -115545.1 | L55: 734641.8 | M55: =VLOOKUP(G55,$A$11:$D$47,4,FALSE) -> 23437.415 | N55: =J55/M55/10 -> -3.6274773 | O55: =K55/M55/10 -> -0.49299421
G56: 1Q 2020 | H56: 43862 | I56: 2002 | J56: -912858.7 | K56: -149768.6 | L56: 763090.1 | M56: =VLOOKUP(G56,$A$11:$D$47,4,FALSE) -> 23437.415 | N56: =J56/M56/10 -> -3.8948779 | O56: =K56/M56/10 -> -0.63901501
G57: 1Q 2020 | H57: 43891 | I57: 2003 | J57: -1029325.3 | K57: -261459.3 | L57: 767866 | M57: =VLOOKUP(G57,$A$11:$D$47,4,FALSE) -> 23437.415 | N57: =J57/M57/10 -> -4.3918039 | O57: =K57/M57/10 -> -1.1155637
G58: 2Q 2020 | H58: 43922 | I58: 2004 | J58: -1229301.9 | K58: -490779.4 | L58: 738522.5 | M58: =VLOOKUP(G58,$A$11:$D$47,4,FALSE) -> 24135.365 | N58: =J58/M58/10 -> -5.0933636 | O58: =K58/M58/10 -> -2.0334451
G59: 2Q 2020 | H59: 43952 | I59: 2005 | J59: -1498886.8 | K59: -768040.2 | L59: 730846.6 | M59: =VLOOKUP(G59,$A$11:$D$47,4,FALSE) -> 24135.365 | N59: =J59/M59/10 -> -6.2103341 | O59: =K59/M59/10 -> -3.1822191
... G129: 1Q 2026 | H129: 46082 | I129: 2603 | J129: 1878799.8 | K129: 12878760 | L129: 10999960 | M129: =VLOOKUP(G129,$A$11:$D$47,4,FALSE) -> 911284.19 | N129: =J129/M129/10 -> 0.20617057 | O129: =K129/M129/10 -> 1.4132539
G130: 2Q 2026 | H130: 46113 | I130: 2604 | J130: 1574561.7 | K130: 12665655 | L130: 11091093 | M130: =M118*1.35 -> 982556.08 | N130: =J130/M130/10 -> 0.16025159 | O130: =K130/M130/10 -> 1.2890516
G131: 2Q 2026 | H131: 46143 | I131: 2605 | J131: 1391052 | K131: 12893104 | L131: 11502052 | M131: =M119*1.35 -> 982556.08 | N131: =J131/M131/10 -> 0.14157482 | O131: =K131/M131/10 -> 1.3122003
G132: 2Q 2026 | H132: 46174 | I132: 2606 | J132: -185073.6 | K132: 11405728 | L132: 11590802 | M132: =M120*1.35 -> 982556.08 | N132: =J132/M132/10 -> -0.018835933 | O132: =K132/M132/10 -> 1.1608221
H133: 46204
H134: 46235
H135: 46266
H136: 46296
H137: 46327
H138: 46357 | N138: 0.3 | O138: 1.5

Sheet Stabilising primary balance
B2: The primary balance that holds debt/GDP flat
B3: Argentine debt is multi-currency. A single-currency (i - pi - g) formula is wrong here: inflation erodes plain peso debt, but NOT the FX-denominated stock and NOT the CER-indexed stock.
B4: Debt stock grows in pesos at: alpha x (eps + i$) + beta x (pi + iCER) + gamma x iPeso
B5: Nominal GDP grows at: (1+g)(1+pi). Debt/GDP is flat when the primary balance covers the gap.
B7: Inputs
B8: Debt / GDP, d | E8: =[5]Data!K17 -> 0.76001516
B9: FX-denominated share, alpha | E9: 0.45
B10: CER-indexed share, beta | E10: 0.35
B11: Plain peso share, gamma | E11: =1-E9-E10 -> 0.2
B12: Interest on FX debt, i$ | E12: 0.05
B13: Interest on CER debt, iCER | E13: 0.05
B14: Interest on peso debt, iPeso | E14: 0.3
B15: Nominal depreciation, eps | E15: 0.25
B16: GDP deflator, pi | E16: 0.25
B17: Real growth, g | E17: 0.03
B18: Actual primary balance | E18: =[5]Data!D17/[5]Data!C17 -> 0.013842233
B20: Result
B21: Debt stock nominal growth | E21: =($E$9*($E$15+$E$12)+$E$10*($E$16+$E$13)+$E$11*$E$14) -> 0.3
B22: Nominal GDP growth | E22: =(1+$E$17)*(1+$E$16)-1 -> 0.2875
B23: DEBT-STABILISING PRIMARY BALANCE | E23: =$E$8*((1+($E$9*($E$15+$E$12)+$E$10*($E$16+$E$13)+$E$11*$E$14))/((1+$E$17)*(1+$E$16))-1) -> 0.007378788
B24: Actual primary balance | E24: =$E$18 -> 0.013842233
B25: GAP — actual less required (pp of GDP) | E25: =(E24-E23)*100 -> 0.64634445
B26: Implied change in debt/GDP (pp) | E26: =-(E24-E23)*100 -> -0.64634445
B28: A POSITIVE gap means the actual primary surplus more than covers the carry and debt/GDP falls. Negative means debt rises even with a primary surplus.
B31: The threshold table: required primary balance (% of GDP) by depreciation and real growth
B32: Everything else held at the inputs above. This is the answer to 'what makes it shoot up'.
B34: Real GDP growth | C34: -0.03 | D34: 0 | E34: 0.02 | F34: 0.04 | G34: 0.06
B35: USD ARS depreciation
B36: 0 | C36: =$E$8*((1+($E$9*($B36+$E$12)+$E$10*($E$16+$E$13)+$E$11*$E$14))/((1+C$34)*(1+$E$16))-1) -> -0.015670416 | D36: =$E$8*((1+($E$9*($B36+$E$12)+$E$10*($E$16+$E$13)+$E$11*$E$14))/((1+D$34)*(1+$E$16))-1) -> -0.038000758 | E36: =$E$8*((1+($E$9*($B36+$E$12)+$E$10*($E$16+$E$13)+$E$11*$E$14))/((1+E$34)*(1+$E$16))-1) -> -0.052157903 | F36: =$E$8*((1+($E$9*($B36+$E$12)+$E$10*($E$16+$E$13)+$E$11*$E$14))/((1+F$34)*(1+$E$16))-1) -> -0.065770543 | G36: =$E$8*((1+($E$9*($B36+$E$12)+$E$10*($E$16+$E$13)+$E$11*$E$14))/((1+G$34)*(1+$E$16))-1) -> -0.078869498
B37: 0.15 | C37: =$E$8*((1+($E$9*($B37+$E$12)+$E$10*($E$16+$E$13)+$E$11*$E$14))/((1+C$34)*(1+$E$16))-1) -> 0.026639707 | D37: =$E$8*((1+($E$9*($B37+$E$12)+$E$10*($E$16+$E$13)+$E$11*$E$14))/((1+D$34)*(1+$E$16))-1) -> 0.0030400607 | E37: =$E$8*((1+($E$9*($B37+$E$12)+$E$10*($E$16+$E$13)+$E$11*$E$14))/((1+E$34)*(1+$E$16))-1) -> -0.011921806 | F37: =$E$8*((1+($E$9*($B37+$E$12)+$E$10*($E$16+$E$13)+$E$11*$E$14))/((1+F$34)*(1+$E$16))-1) -> -0.026308217 | G37: =$E$8*((1+($E$9*($B37+$E$12)+$E$10*($E$16+$E$13)+$E$11*$E$14))/((1+G$34)*(1+$E$16))-1) -> -0.040151745
B38: 0.25 | C38: =$E$8*((1+($E$9*($B38+$E$12)+$E$10*($E$16+$E$13)+$E$11*$E$14))/((1+C$34)*(1+$E$16))-1) -> 0.054846455 | D38: =$E$8*((1+($E$9*($B38+$E$12)+$E$10*($E$16+$E$13)+$E$11*$E$14))/((1+D$34)*(1+$E$16))-1) -> 0.030400607 | E38: =$E$8*((1+($E$9*($B38+$E$12)+$E$10*($E$16+$E$13)+$E$11*$E$14))/((1+E$34)*(1+$E$16))-1) -> 0.014902258 | F38: =$E$8*((1+($E$9*($B38+$E$12)+$E$10*($E$16+$E$13)+$E$11*$E$14))/((1+F$34)*(1+$E$16))-1) -> 0 | G38: =$E$8*((1+($E$9*($B38+$E$12)+$E$10*($E$16+$E$13)+$E$11*$E$14))/((1+G$34)*(1+$E$16))-1) -> -0.014339909
B39: 0.4 | C39: =$E$8*((1+($E$9*($B39+$E$12)+$E$10*($E$16+$E$13)+$E$11*$E$14))/((1+C$34)*(1+$E$16))-1) -> 0.097156578 | D39: =$E$8*((1+($E$9*($B39+$E$12)+$E$10*($E$16+$E$13)+$E$11*$E$14))/((1+D$34)*(1+$E$16))-1) -> 0.071441425 | E39: =$E$8*((1+($E$9*($B39+$E$12)+$E$10*($E$16+$E$13)+$E$11*$E$14))/((1+E$34)*(1+$E$16))-1) -> 0.055138355 | F39: =$E$8*((1+($E$9*($B39+$E$12)+$E$10*($E$16+$E$13)+$E$11*$E$14))/((1+F$34)*(1+$E$16))-1) -> 0.039462326 | G39: =$E$8*((1+($E$9*($B39+$E$12)+$E$10*($E$16+$E$13)+$E$11*$E$14))/((1+G$34)*(1+$E$16))-1) -> 0.024377845
B40: 0.6 | C40: =$E$8*((1+($E$9*($B40+$E$12)+$E$10*($E$16+$E$13)+$E$11*$E$14))/((1+C$34)*(1+$E$16))-1) -> 0.15357007 | D40: =$E$8*((1+($E$9*($B40+$E$12)+$E$10*($E$16+$E$13)+$E$11*$E$14))/((1+D$34)*(1+$E$16))-1) -> 0.12616252 | E40: =$E$8*((1+($E$9*($B40+$E$12)+$E$10*($E$16+$E$13)+$E$11*$E$14))/((1+E$34)*(1+$E$16))-1) -> 0.10878648 | F40: =$E$8*((1+($E$9*($B40+$E$12)+$E$10*($E$16+$E$13)+$E$11*$E$14))/((1+F$34)*(1+$E$16))-1) -> 0.09207876 | G40: =$E$8*((1+($E$9*($B40+$E$12)+$E$10*($E$16+$E$13)+$E$11*$E$14))/((1+G$34)*(1+$E$16))-1) -> 0.076001516
B43: Compare every cell against the actual primary balance in E24. Anything above it is a combination where the current fiscal stance is not enough and the ratio rises.
B44: Note how flat the table is across growth and how steep it is across depreciation. Growth helps at the margin; the exchange rate dominates. With 45% of the stock in foreign currency, roughly 0.45pp of extra primary surplus is needed for every 1pp of real depreciation.

Sheet Buenos Aires polling
B2: Buenos Aires province on its own — May 2026
B3: A quarter of the national electorate, and it behaves nothing like the national average.
B7: Figure | C7: Positive % | D7: Negative % | E7: NET
B8: Axel Kicillof | C8: 51 | D8: 47 | E8: =C8-D8 -> 4
B9: Cristina Kirchner | C9: 47 | D9: 51 | E9: =C9-D9 -> -4
B10: Sergio Massa | C10: 37 | D10: 59 | E10: =C10-D10 -> -22
B11: Javier Milei | C11: 33 | D11: 65 | E11: =C11-D11 -> -32
B12: Mauricio Macri | C12: 28 | D12: 70 | E12: =C12-D12 -> -42
B13: Victoria Villarruel | C13: 25 | D13: 67 | E13: =C13-D13 -> -42
B14: Karina Milei | C14: 17 | D14: 77 | E14: =C14-D14 -> -60
B16: Mood
B17: Say provincial situation is bad or very bad % | E17: 61
B18: Express hope about the future % | E18: 29
B19: Report predominantly negative emotions % | E19: 54
B21: Kicillof is the only figure in the country with a positive net image anywhere, and it is here. Milei is at -32 in the province against roughly -14 to -28 nationally. This is the industrial belt, and it is also where the Di Tella confidence index is falling fastest.
C26: Net Approval | D26: National | E26: PBA
C27: J. Milei | D27: -20 | E27: =E11 -> -32
C28: A. Kicillof | D28: -17 | E28: =E8 -> 4
C29: S. Massa | E29: =E10 -> -22
C30: M. Macri | E30: =E12 -> -42

Sheet Bond data (Bloomberg)
C3: Security_name | D3: CPN | E3: PX_CLEAN_MID | F3: YLD_YTM_MID | G3: DUR_ADJ_MID | H3: Convex | I3: CNVX_MID
B4: US040114HX11 ISIN | C4: {=_xll.BDP($B4,C$3)} -> ARGENT 1 07/09/29 | D4: {=_xll.BDP($B4,D$3)} -> 1 | E4: {=_xll.BDP($B4,E$3)} -> 89.7595 | F4: {=_xll.BDP($B4,F$3)} -> 4.8175962 | G4: {=_xll.BDP($B4,G$3)} -> 1.5337481 | H4: =I4*100 -> 3.0997726 | I4: {=_xll.BDP($B4,I$3)} -> 0.030997726
B5: US040114HS26 ISIN | C5: {=_xll.BDP(B5,C$3)} -> ARGENT 0 3/4 07/09/30 | D5: {=_xll.BDP($B5,D$3)} -> 0.75 | E5: {=_xll.BDP($B5,E$3)} -> 87.624 | F5: {=_xll.BDP($B5,F$3)} -> 5.0232955 | G5: {=_xll.BDP($B5,G$3)} -> 1.9701817 | H5: =I5*100 -> 4.8479371 | I5: {=_xll.BDP($B5,I$3)} -> 0.048479371
B6: US040114HT09 ISIN | C6: {=_xll.BDP(B6,C$3)} -> ARGENT 4 1/8 07/09/35 | D6: {=_xll.BDP($B6,D$3)} -> 4.125 | E6: {=_xll.BDP($B6,E$3)} -> 77.937 | F6: {=_xll.BDP($B6,F$3)} -> 8.3988434 | G6: {=_xll.BDP($B6,G$3)} -> 5.2884463 | H6: =I6*100 -> 33.482619 | I6: {=_xll.BDP($B6,I$3)} -> 0.33482619
B7: US040114HU71 ISIN | C7: {=_xll.BDP(B7,C$3)} -> ARGENT 5 01/09/38 | D7: {=_xll.BDP($B7,D$3)} -> 5 | E7: {=_xll.BDP($B7,E$3)} -> 81.5315 | F7: {=_xll.BDP($B7,F$3)} -> 7.4234425 | G7: {=_xll.BDP($B7,G$3)} -> 4.5566703 | H7: =I7*100 -> 24.918883 | I7: {=_xll.BDP($B7,I$3)} -> 0.24918883
B8: US040114HV54 ISIN | C8: {=_xll.BDP(B8,C$3)} -> ARGENT 3 1/2 07/09/41 | D8: {=_xll.BDP($B8,D$3)} -> 3.5 | E8: {=_xll.BDP($B8,E$3)} -> 72.8825 | F8: {=_xll.BDP($B8,F$3)} -> 7.5249034 | G8: {=_xll.BDP($B8,G$3)} -> 5.7747426 | H8: =I8*100 -> 39.467411 | I8: {=_xll.BDP($B8,I$3)} -> 0.39467411
B9: US040114HW38 ISIN | C9: {=_xll.BDP(B9,C$3)} -> ARGENT 4 1/8 07/09/46 | D9: {=_xll.BDP($B9,D$3)} -> 4.125 | E9: {=_xll.BDP($B9,E$3)} -> 73.3985 | F9: {=_xll.BDP($B9,F$3)} -> 7.4584382 | G9: {=_xll.BDP($B9,G$3)} -> 6.2064604 | H9: =I9*100 -> 46.826511 | I9: {=_xll.BDP($B9,I$3)} -> 0.46826511

Sheet Sources & notes
B2: Sources and field details
B4: Reale Dalla Torre | C4: National survey fielded 24-28 July 2026, n = 1,162. Reported by Perfil and MDZ. The most complete single-house panel available; used for the Main panel tab.
B5: Zentrix | C5: Monitor de Opinion Publica, July 2026. Reported by iProfesional.
B6: Delfos | C6: National survey fielded 15-19 May 2026, n = 2,689, margin of error +/- 1.9%. Reported by El Destape.
B7: Opina Argentina | C7: June 2026, reported by Perfil.
B8: Latam Pulse | C8: AtlasIntel for Bloomberg News, monthly 2026 releases.
B9: Di Tella ICG | C9: Universidad Torcuato Di Tella, Indice de Confianza en el Gobierno, July 2026.
B10: Buenos Aires panel | C10: Provincial survey, May 2026, reported by InfoPlatense.
B11: Poll average | C11: Cited by Filo News, July 2026, as the average negative image across measurements.
B13: Prepared | C13: 4 August 2026. Polling is a snapshot; refresh before using in a dated note.

Sheet 1 Bond inputs
C1: Argentina hard-currency curve — inputs
C2: EVERY BLUE CELL IS AN INPUT: overwrite from Bloomberg. Black cells are formulas and should not be typed over. The numbers below are ILLUSTRATIVE PLACEHOLDERS chosen only to make the arithmetic visible — they are not market levels and must be replaced before use.
C3: Holding period (years) | D3: 0.5 | E3: <- drives tabs 2 and 3
B4: Security_name | E4: CPN | F4: PX_Clean_mid | G4: YLD_YTM_MID | H4: DUR_ADJ_MID | I4: Convex | J4: CNVX_MID
C5: Bond | D5: Maturity | E5: Coupon (%, current step) | F5: Price (clean) | G5: YTM (%) | H5: Mod. duration (years) | I5: Convexity (years squared)
A6: US040114HX11 ISIN | B6: {=_xll.BDP($A6,B$4)} -> ARGENT 1 07/09/29 | C6: GD29 | D6: 2029 | E6: {=_xll.BDP($A6,E$4)} -> 1 | F6: {=_xll.BDP($A6,F$4)} -> 89.765 | G6: {=_xll.BDP($A6,G$4)} -> 4.8175962 | H6: {=_xll.BDP($A6,H$4)} -> 1.5337481 | I6: =J6*100 -> 3.0997726 | J6: {=_xll.BDP($A6,J$4)} -> 0.030997726
A7: US040114HS26 ISIN | B7: {=_xll.BDP($A7,B$4)} -> ARGENT 0 3/4 07/09/30 | C7: GD30 | D7: 2030 | E7: {=_xll.BDP($A7,E$4)} -> 0.75 | F7: {=_xll.BDP($A7,F$4)} -> 87.628 | G7: {=_xll.BDP($A7,G$4)} -> 5.0232955 | H7: {=_xll.BDP($A7,H$4)} -> 1.9701817 | I7: =J7*100 -> 4.8479371 | J7: {=_xll.BDP($A7,J$4)} -> 0.048479371
A8: US040114HT09 ISIN | B8: {=_xll.BDP($A8,B$4)} -> ARGENT 4 1/8 07/09/35 | C8: GD35 | D8: 2035 | E8: {=_xll.BDP($A8,E$4)} -> 4.125 | F8: {=_xll.BDP($A8,F$4)} -> 77.936 | G8: {=_xll.BDP($A8,G$4)} -> 8.3988434 | H8: {=_xll.BDP($A8,H$4)} -> 5.2884463 | I8: =J8*100 -> 33.482619 | J8: {=_xll.BDP($A8,J$4)} -> 0.33482619
A9: US040114HU71 ISIN | B9: {=_xll.BDP($A9,B$4)} -> ARGENT 5 01/09/38 | C9: GD38 | D9: 2038 | E9: {=_xll.BDP($A9,E$4)} -> 5 | F9: {=_xll.BDP($A9,F$4)} -> 81.5335 | G9: {=_xll.BDP($A9,G$4)} -> 7.4234425 | H9: {=_xll.BDP($A9,H$4)} -> 4.5566703 | I9: =J9*100 -> 24.918883 | J9: {=_xll.BDP($A9,J$4)} -> 0.24918883
A10: US040114HV54 ISIN | B10: {=_xll.BDP($A10,B$4)} -> ARGENT 3 1/2 07/09/41 | C10: GD41 | D10: 2041 | E10: {=_xll.BDP($A10,E$4)} -> 3.5 | F10: {=_xll.BDP($A10,F$4)} -> 72.8835 | G10: {=_xll.BDP($A10,G$4)} -> 7.5249034 | H10: {=_xll.BDP($A10,H$4)} -> 5.7747426 | I10: =J10*100 -> 39.467411 | J10: {=_xll.BDP($A10,J$4)} -> 0.39467411
A11: US040114HW38 ISIN | B11: {=_xll.BDP($A11,B$4)} -> ARGENT 4 1/8 07/09/46 | C11: GD46 | D11: 2046 | E11: {=_xll.BDP($A11,E$4)} -> 4.125 | F11: {=_xll.BDP($A11,F$4)} -> 73.4 | G11: {=_xll.BDP($A11,G$4)} -> 7.4584382 | H11: {=_xll.BDP($A11,H$4)} -> 6.2064604 | I11: =J11*100 -> 46.826511 | J11: {=_xll.BDP($A11,J$4)} -> 0.46826511
C13: UNITS — read this once. All rates and returns are in PERCENT UNITS: 8.50 means 8.5%, not 0.085. All yield moves are in BASIS POINTS. Mixing the two is the only way to get this workbook wrong.
C14: Bloomberg fields: coupon CPN, clean price PX_LAST, yield YLD_YTM_MID, modified duration DUR_ADJ_MID (use OAD if you prefer), convexity CVX_MID. CONVEXITY SCALE MATTERS: this model wants years squared, so the price effect is 0.5 x CVX x (dy in decimals)^2 — roughly 36 for a 5.4-year bond. Bloomberg quotes CVX_MID divided by 100, so MULTIPLY THE BLOOMBERG NUMBER BY 100 before pasting. Getting this wrong silently kills the convexity benefit and you will not see an error.
C15: The globals amortise, so modified duration — not maturity — is the right risk measure, and it is why GD29 and GD46 behave completely differently on near-identical yields.
C16: Coupon = the step currently in effect, not the weighted average over the bond's life. The step-up schedule is why the cash half of carry grows over time on the long bonds.
F26: =8/12 -> 0.66666667

Sheet 2 Carry cushion
A1: Carry cushion — how far yields can widen before you lose money
A2: The headline 'you accrue ~4% in six months' is only interesting relative to what it protects against. Carry divided by duration converts it into basis points of widening, which is the unit the market actually moves in.
A5: Bond | B5: Holding period (yrs) | C5: Carry if yields unchanged (%) | D5: of which: cash coupon (%) | E5: of which: pull-to-par (%) | F5: Mod. duration (years) | G5: Breakeven widening — duration only (bp) | H5: Breakeven widening — with convexity (bp) | I5: Breakeven end price
A6: ='1 Bond inputs'!C6 -> GD29 | B6: ='1 Bond inputs'!$D$3 -> 0.5 | C6: ='1 Bond inputs'!G6*$B6 -> 2.4087981 | D6: ='1 Bond inputs'!E6*$B6/'1 Bond inputs'!F6*100 -> 0.55700997 | E6: =C6-D6 -> 1.8517881 | F6: ='1 Bond inputs'!H6 -> 1.5337481 | G6: =C6/100/F6*10000 -> 157.05304 | H6: =(F6-SQRT(F6^2-2*'1 Bond inputs'!I6*C6/100))/'1 Bond inputs'!I6*10000 -> 159.62796 | I6: ='1 Bond inputs'!F6-'1 Bond inputs'!E6*$B6 -> 89.265
A7: ='1 Bond inputs'!C7 -> GD30 | B7: ='1 Bond inputs'!$D$3 -> 0.5 | C7: ='1 Bond inputs'!G7*$B7 -> 2.5116477 | D7: ='1 Bond inputs'!E7*$B7/'1 Bond inputs'!F7*100 -> 0.42794541 | E7: =C7-D7 -> 2.0837023 | F7: ='1 Bond inputs'!H7 -> 1.9701817 | G7: =C7/100/F7*10000 -> 127.48305 | H7: =(F7-SQRT(F7^2-2*'1 Bond inputs'!I7*C7/100))/'1 Bond inputs'!I7*10000 -> 129.54787 | I7: ='1 Bond inputs'!F7-'1 Bond inputs'!E7*$B7 -> 87.253
A8: ='1 Bond inputs'!C8 -> GD35 | B8: ='1 Bond inputs'!$D$3 -> 0.5 | C8: ='1 Bond inputs'!G8*$B8 -> 4.1994217 | D8: ='1 Bond inputs'!E8*$B8/'1 Bond inputs'!F8*100 -> 2.6464022 | E8: =C8-D8 -> 1.5530195 | F8: ='1 Bond inputs'!H8 -> 5.2884463 | G8: =C8/100/F8*10000 -> 79.407476 | H8: =(F8-SQRT(F8^2-2*'1 Bond inputs'!I8*C8/100))/'1 Bond inputs'!I8*10000 -> 81.510726 | I8: ='1 Bond inputs'!F8-'1 Bond inputs'!E8*$B8 -> 75.8735
A9: ='1 Bond inputs'!C9 -> GD38 | B9: ='1 Bond inputs'!$D$3 -> 0.5 | C9: ='1 Bond inputs'!G9*$B9 -> 3.7117213 | D9: ='1 Bond inputs'!E9*$B9/'1 Bond inputs'!F9*100 -> 3.0662243 | E9: =C9-D9 -> 0.64549695 | F9: ='1 Bond inputs'!H9 -> 4.5566703 | G9: =C9/100/F9*10000 -> 81.456876 | H9: =(F9-SQRT(F9^2-2*'1 Bond inputs'!I9*C9/100))/'1 Bond inputs'!I9*10000 -> 83.356785 | I9: ='1 Bond inputs'!F9-'1 Bond inputs'!E9*$B9 -> 79.0335
A10: ='1 Bond inputs'!C10 -> GD41 | B10: ='1 Bond inputs'!$D$3 -> 0.5 | C10: ='1 Bond inputs'!G10*$B10 -> 3.7624517 | D10: ='1 Bond inputs'!E10*$B10/'1 Bond inputs'!F10*100 -> 2.4010922 | E10: =C10-D10 -> 1.3613595 | F10: ='1 Bond inputs'!H10 -> 5.7747426 | G10: =C10/100/F10*10000 -> 65.153583 | H10: =(F10-SQRT(F10^2-2*'1 Bond inputs'!I10*C10/100))/'1 Bond inputs'!I10*10000 -> 66.67263 | I10: ='1 Bond inputs'!F10-'1 Bond inputs'!E10*$B10 -> 71.1335
A11: ='1 Bond inputs'!C11 -> GD46 | B11: ='1 Bond inputs'!$D$3 -> 0.5 | C11: ='1 Bond inputs'!G11*$B11 -> 3.7292191 | D11: ='1 Bond inputs'!E11*$B11/'1 Bond inputs'!F11*100 -> 2.8099455 | E11: =C11-D11 -> 0.91927358 | F11: ='1 Bond inputs'!H11 -> 6.2064604 | G11: =C11/100/F11*10000 -> 60.086086 | H11: =(F11-SQRT(F11^2-2*'1 Bond inputs'!I11*C11/100))/'1 Bond inputs'!I11*10000 -> 61.51353 | I11: ='1 Bond inputs'!F11-'1 Bond inputs'!E11*$B11 -> 71.3375
A13: READ THE CHART THIS WAY: same yield, same 4% headline, and the front end absorbs roughly twice the widening the long end does. That gap is the entire point — it is invisible on a yield screen and it is what actually determines whether the trade works.
A14: The stacked chart splits the carry into the part you bank and the part you only book if the market cooperates. On a deep-discount bond the second bar is the larger one, which is why 'I'm getting paid 8% to wait' overstates what is genuinely being banked.
A15: Breakeven end price = price - coupon x horizon: the level the bond can fall to and still leave you flat. It sits below today's price because a discount bond would otherwise have accreted upward over the period.
A16: Duration/convexity approximation, not full cashflow repricing. It is accurate to a few bp for moves inside roughly +/-200bp and understates the cushion for very large moves. For a hard number on a big shock, reprice the schedule.

Sheet GDP contributions (HAVER)
C2: Real GDP | D2: Consumption | E2: Gvt. Consumption | F2: Investment | G2: Inventories | H2: Statistical discrepancy | I2: Exports | J2: Imports
B3: 1181 !Q | C3: N213NGPC@EMERGELA | D3: N213NCPC@EMERGELA | E3: N213NCGC@EMERGELA | F3: N213NFC@EMERGELA | G3: N213NBC@EMERGELA | H3: N213NSDC@EMERGELA | I3: N213NXC@EMERGELA | J3: N213NMC@EMERGELA
B4: .DESC | C4: Argentina: Gross Domestic Product at Market Prices (NSAAR, Mil.2004.Pesos) | D4: Argentina: GDP: Private Consumption Expenditure (NSAAR, Mil.2004.Pesos) | E4: Argentina: GDP: Govt Consumption Expenditure (NSAAR, Mil.2004.Pesos) | F4: Argentina: GDP: Gross Fixed Capital Formation (NSAAR, Mil.2004.Pesos) | G4: Argentina: GDP: Change in Inventory (NSAAR, Mil.2004.Pesos) | H4: Argentina: GDP: Statistical Discrepancy (NSAAR, Mil.2004.Pesos) | I4: Argentina: GDP: Exports of Goods and Services (NSAAR, Mil.2004.Pesos) | J4: Argentina: GDP: Imports of Goods and Services (NSAAR, Mil.2004.Pesos)
B5: .SOURCE | C5: INDEC | D5: INDEC | E5: INDEC | F5: INDEC | G5: INDEC | H5: INDEC | I5: INDEC | J5: INDEC
B6: .DATA_TYPE | C6: LocCur | D6: LocCur | E6: LocCur | F6: LocCur | G6: LocCur | H6: LocCur | I6: LocCur | J6: LocCur
B7: .MAG | C7: 6 | D7: 6 | E7: 6 | F7: 6 | G7: 6 | H7: 6 | I7: 6 | J7: 6
A8: 1Q 2018 | B8: 181 | C8: 707324.27 | D8: 552912.88 | E8: 92056.194 | F8: 152300.6 | G8: -9443.672 | H8: #N/A | I8: 144939.93 | J8: 225441.67
A9: 2Q 2018 | B9: 182 | C9: 747428.3 | D9: 588455.76 | E9: 97624.181 | F9: 151659.17 | G9: -7901.444 | H9: #N/A | I9: 137726.12 | J9: 220135.48
A10: 3Q 2018 | B10: 183 | C10: 696101.58 | D10: 513316.29 | E10: 96923.533 | F10: 142066.42 | G10: 6049.897 | H10: #N/A | I10: 144474.37 | J10: 206728.93
A11: 4Q 2018 | B11: 184 | C11: 678655.62 | D11: 451265.21 | E11: 101213.66 | F11: 121488.75 | G11: 15485.466 | H11: #N/A | I11: 160897.22 | J11: 171694.68 | L11: Domestic demand | M11: External sector | N11: Inventories + discrepancy | P11: Consumption | Q11: Gvt. Consumption | R11: Investment | S11: Inventories | T11: Statistical discrepancy | U11: Exports | V11: Imports | X11: GDP growth | Y11: GDP | Z11: Consumption | AA11: Gvt. Consumption | AB11: Investment | AC11: Inventories | AD11: Statistical discrepancy | AE11: Exports | AF11: Imports
A12: 1Q 2019 | B12: 191 | C12: 665848.71 | D12: 504391.51 | E12: 87955.885 | F12: 114187.83 | G12: -17798.712 | H12: #N/A | I12: 145979.49 | J12: 168867.28 | L12: =P12+Q12 -> -7.4395407 | M12: =U12-V12 -> 8.1453365 | N12: =S12 -> -1.1812178 | P12: =Z12/$Y12*$X12 -> -6.8598478 | Q12: =AA12/$Y12*$X12 -> -0.57969296 | R12: =AB12/$Y12*$X12 -> -5.3883035 | S12: =AC12/$Y12*$X12 -> -1.1812178 | T12: =AD12/$Y12*$X12 -> #N/A | U12: =AE12/$Y12*$X12 -> 0.14697007 | V12: =AF12/$Y12*$X12 -> -7.9983665 | X12: =(C12/C8-1)*100 -> -5.8637254 | Y12: =C12-C8 -> -41475.553 | Z12: =D12-D8 -> -48521.368 | AA12: =E12-E8 -> -4100.309 | AB12: =F12-F8 -> -38112.778 | AC12: =G12-G8 -> -8355.04 | AD12: =H12-H8 -> #N/A | AE12: =I12-I8 -> 1039.555 | AF12: =J12-J8 -> -56574.387
A13: 2Q 2019 | B13: 192 | C13: 751784.46 | D13: 550677.29 | E13: 93381.864 | F13: 123592.23 | G13: -4122.05 | H13: #N/A | I13: 159369.07 | J13: 171113.94 | P13: =Z13/$Y13*$X13 -> -5.054461 | Q13: =AA13/$Y13*$X13 -> -0.56758849 | R13: =AB13/$Y13*$X13 -> -3.7551348 | S13: =AC13/$Y13*$X13 -> 0.50565305 | T13: =AD13/$Y13*$X13 -> #N/A | U13: =AE13/$Y13*$X13 -> 2.8956561 | V13: =AF13/$Y13*$X13 -> -6.5586949 | X13: =(C13/C9-1)*100 -> 0.58281992 | Y13: =C13-C9 -> 4356.161 | Z13: =D13-D9 -> -37778.472 | AA13: =E13-E9 -> -4242.317 | AB13: =F13-F9 -> -28066.94 | AC13: =G13-G9 -> 3779.394 | AD13: =H13-H9 -> #N/A | AE13: =I13-I9 -> 21642.953 | AF13: =J13-J9 -> -49021.542
A14: 3Q 2019 | B14: 193 | C14: 683900.9 | D14: 480415.61 | E14: 88666.35 | F14: 127742.5 | G14: -2865.411 | H14: #N/A | I14: 166474.09 | J14: 176396.74 | P14: =Z14/$Y14*$X14 -> -4.7264202 | Q14: =AA14/$Y14*$X14 -> -1.1862037 | R14: =AB14/$Y14*$X14 -> -2.0577337 | S14: =AC14/$Y14*$X14 -> -1.2807481 | T14: =AD14/$Y14*$X14 -> #N/A | U14: =AE14/$Y14*$X14 -> 3.1604177 | V14: =AF14/$Y14*$X14 -> -4.3574367 | X14: =(C14/C10-1)*100 -> -1.7527162 | Y14: =C14-C10 -> -12200.685 | Z14: =D14-D10 -> -32900.686 | AA14: =E14-E10 -> -8257.183 | AB14: =F14-F10 -> -14323.917 | AC14: =G14-G10 -> -8915.308 | AD14: =H14-H10 -> #N/A | AE14: =I14-I10 -> 21999.718 | AF14: =J14-J10 -> -30332.186
A15: 4Q 2019 | B15: 194 | C15: 671361.14 | D15: 441436.05 | E15: 92992.646 | F15: 111464.94 | G15: 6361.625 | H15: #N/A | I15: 173554.7 | J15: 153557.48 | P15: =Z15/$Y15*$X15 -> -1.4483279 | Q15: =AA15/$Y15*$X15 -> -1.2113674 | R15: =AB15/$Y15*$X15 -> -1.4770092 | S15: =AC15/$Y15*$X15 -> -1.3443992 | T15: =AD15/$Y15*$X15 -> #N/A | U15: =AE15/$Y15*$X15 -> 1.8650807 | V15: =AF15/$Y15*$X15 -> -2.6725186 | X15: =(C15/C11-1)*100 -> -1.0748426 | Y15: =C15-C11 -> -7294.48 | Z15: =D15-D11 -> -9829.159 | AA15: =E15-E11 -> -8221.013 | AB15: =F15-F11 -> -10023.806 | AC15: =G15-G11 -> -9123.841 | AD15: =H15-H11 -> #N/A | AE15: =I15-I11 -> 12657.475 | AF15: =J15-J11 -> -18137.198
A16: 1Q 2020 | B16: 201 | C16: 632389.35 | D16: 470887.43 | E16: 87736.345 | F16: 93438.799 | G16: -11049.715 | H16: #N/A | I16: 139323.36 | J16: 147946.86 | P16: =Z16/$Y16*$X16 -> -5.0317852 | Q16: =AA16/$Y16*$X16 -> -0.032971454 | R16: =AB16/$Y16*$X16 -> -3.1161774 | S16: =AC16/$Y16*$X16 -> 1.0135932 | T16: =AD16/$Y16*$X16 -> #N/A | U16: =AE16/$Y16*$X16 -> -0.99964629 | V16: =AF16/$Y16*$X16 -> -3.1419175 | X16: =(C16/C12-1)*100 -> -5.0250695 | Y16: =C16-C12 -> -33459.361 | Z16: =D16-D12 -> -33504.077 | AA16: =E16-E12 -> -219.54 | AB16: =F16-F12 -> -20749.027 | AC16: =G16-G12 -> 6748.997 | AD16: =H16-H12 -> #N/A | AE16: =I16-I12 -> -6656.132 | AF16: =J16-J12 -> -20920.417
A17: 2Q 2020 | B17: 202 | C17: 609379.99 | D17: 434291.22 | E17: 87928.545 | F17: 76231.158 | G17: -6832.347 | H17: #N/A | I17: 136593.33 | J17: 118831.92 | P17: =Z17/$Y17*$X17 -> -15.481307 | Q17: =AA17/$Y17*$X17 -> -0.72538331 | R17: =AB17/$Y17*$X17 -> -6.2998203 | S17: =AC17/$Y17*$X17 -> -0.36051517 | T17: =AD17/$Y17*$X17 -> #N/A | U17: =AE17/$Y17*$X17 -> -3.029558 | V17: =AF17/$Y17*$X17 -> -6.9543901 | X17: =(C17/C13-1)*100 -> -18.942194 | Y17: =C17-C13 -> -142404.47 | Z17: =D17-D13 -> -116386.06 | AA17: =E17-E13 -> -5453.319 | AB17: =F17-F13 -> -47361.07 | AC17: =G17-G13 -> -2710.297 | AD17: =H17-H13 -> #N/A | AE17: =I17-I13 -> -22775.746 | AF17: =J17-J13 -> -52282.024
A18: 3Q 2020 | B18: 203 | C18: 614192.48 | D18: 408971.26 | E18: 86984.634 | F18: 116052.7 | G18: 2771.336 | H18: #N/A | I18: 136347.82 | J18: 136935.28 | P18: =Z18/$Y18*$X18 -> -10.446593 | Q18: =AA18/$Y18*$X18 -> -0.24590054 | R18: =AB18/$Y18*$X18 -> -1.7092826 | S18: =AC18/$Y18*$X18 -> 0.82420523 | T18: =AD18/$Y18*$X18 -> #N/A | U18: =AE18/$Y18*$X18 -> -4.4050637 | V18: =AF18/$Y18*$X18 -> -5.7700563 | X18: =(C18/C14-1)*100 -> -10.192766 | Y18: =C18-C14 -> -69708.421 | Z18: =D18-D14 -> -71444.344 | AA18: =E18-E14 -> -1681.716 | AB18: =F18-F14 -> -11689.799 | AC18: =G18-G14 -> 5636.747 | AD18: =H18-H14 -> #N/A | AE18: =I18-I14 -> -30126.27 | AF18: =J18-J14 -> -39461.467
A19: 4Q 2020 | B19: 204 | C19: 642403.32 | D19: 422152.32 | E19: 93008.979 | F19: 128941.85 | G19: 28647.373 | H19: #N/A | I19: 120573.81 | J19: 150921 | P19: =Z19/$Y19*$X19 -> -2.8723338 | Q19: =AA19/$Y19*$X19 -> 0.0024328188 | R19: =AB19/$Y19*$X19 -> 2.6032056 | S19: =AC19/$Y19*$X19 -> 3.3194873 | T19: =AD19/$Y19*$X19 -> #N/A | U19: =AE19/$Y19*$X19 -> -7.8915633 | V19: =AF19/$Y19*$X19 -> -0.39270652 | X19: =(C19/C15-1)*100 -> -4.3132995 | Y19: =C19-C15 -> -28957.817 | Z19: =D19-D15 -> -19283.733 | AA19: =E19-E15 -> 16.333 | AB19: =F19-F15 -> 17476.911 | AC19: =G19-G15 -> 22285.748 | AD19: =H19-H15 -> #N/A | AE19: =I19-I15 -> -52980.889 | AF19: =J19-J15 -> -2636.479
A20: 1Q 2021 | B20: 211 | C20: 652831.98 | D20: 473418.89 | E20: 88352.496 | F20: 129688.33 | G20: -16381.82 | H20: #N/A | I20: 125271.19 | J20: 147517.11 | P20: =Z20/$Y20*$X20 -> 0.40029975 | Q20: =AA20/$Y20*$X20 -> 0.097432222 | R20: =AB20/$Y20*$X20 -> 5.7321545 | S20: =AC20/$Y20*$X20 -> -0.84316805 | T20: =AD20/$Y20*$X20 -> #N/A | U20: =AE20/$Y20*$X20 -> -2.2220746 | V20: =AF20/$Y20*$X20 -> -0.067957026 | X20: =(C20/C16-1)*100 -> 3.2326007 | Y20: =C20-C16 -> 20442.623 | Z20: =D20-D16 -> 2531.453 | AA20: =E20-E16 -> 616.151 | AB20: =F20-F16 -> 36249.535 | AC20: =G20-G16 -> -5332.105 | AD20: =H20-H16 -> #N/A | AE20: =I20-I16 -> -14052.163 | AF20: =J20-J16 -> -429.753
A21: 2Q 2021 | B21: 212 | C21: 723516.62 | D21: 514737.79 | E21: 93809.853 | F21: 136177.7 | G21: -4393.762 | H21: #N/A | I21: 146242.56 | J21: 163057.52 | P21: =Z21/$Y21*$X21 -> 13.201381 | Q21: =AA21/$Y21*$X21 -> 0.96512982 | R21: =AB21/$Y21*$X21 -> 9.8373002 | S21: =AC21/$Y21*$X21 -> 0.40017478 | T21: =AD21/$Y21*$X21 -> #N/A | U21: =AE21/$Y21*$X21 -> 1.5834514 | V21: =AF21/$Y21*$X21 -> 7.2574761 | X21: =(C21/C17-1)*100 -> 18.729961 | Y21: =C21-C17 -> 114136.63 | Z21: =D21-D17 -> 80446.572 | AA21: =E21-E17 -> 5881.308 | AB21: =F21-F17 -> 59946.539 | AC21: =G21-G17 -> 2438.585 | AD21: =H21-H17 -> #N/A | AE21: =I21-I17 -> 9649.236 | AF21: =J21-J17 -> 44225.607
A22: 3Q 2021 | B22: 213 | C22: 686756.47 | D22: 449491.73 | E22: 95108.617 | F22: 141727.55 | G22: 3827.399 | H22: #N/A | I22: 161505.19 | J22: 164904.02 | P22: =Z22/$Y22*$X22 -> 6.5973571 | Q22: =AA22/$Y22*$X22 -> 1.3227096 | R22: =AB22/$Y22*$X22 -> 4.1802612 | S22: =AC22/$Y22*$X22 -> 0.17194333 | T22: =AD22/$Y22*$X22 -> #N/A | U22: =AE22/$Y22*$X22 -> 4.0960069 | V22: =AF22/$Y22*$X22 -> 4.5537425 | X22: =(C22/C18-1)*100 -> 11.814536 | Y22: =C22-C18 -> 72563.99 | Z22: =D22-D18 -> 40520.471 | AA22: =E22-E18 -> 8123.983 | AB22: =F22-F18 -> 25674.85 | AC22: =G22-G18 -> 1056.063 | AD22: =H22-H18 -> #N/A | AE22: =I22-I18 -> 25157.366 | AF22: =J22-J18 -> 27968.744
A23: 4Q 2021 | B23: 214 | C23: 696134.67 | D23: 463015.57 | E23: 103726.73 | F23: 148125.39 | G23: 18495.754 | H23: #N/A | I23: 144860.43 | J23: 182089.2 | P23: =Z23/$Y23*$X23 -> 6.3609962 | Q23: =AA23/$Y23*$X23 -> 1.6683832 | R23: =AB23/$Y23*$X23 -> 2.9862146 | S23: =AC23/$Y23*$X23 -> -1.5802563 | T23: =AD23/$Y23*$X23 -> #N/A | U23: =AE23/$Y23*$X23 -> 3.7805879 | V23: =AF23/$Y23*$X23 -> 4.8518116 | X23: =(C23/C19-1)*100 -> 8.364114 | Y23: =C23-C19 -> 53731.346 | Z23: =D23-D19 -> 40863.251 | AA23: =E23-E19 -> 10717.749 | AB23: =F23-F19 -> 19183.542 | AC23: =G23-G19 -> -10151.619 | AD23: =H23-H19 -> #N/A | AE23: =I23-I19 -> 24286.622 | AF23: =J23-J19 -> 31168.199
A24: 1Q 2022 | B24: 221 | C24: 697625.29 | D24: 516582.48 | E24: 94876.315 | F24: 143683.72 | G24: -10285.127 | H24: 3455.491 | I24: 135342.64 | J24: 182574.75 | P24: =Z24/$Y24*$X24 -> 6.6117461 | Q24: =AA24/$Y24*$X24 -> 0.99931058 | R24: =AB24/$Y24*$X24 -> 2.1437962 | S24: =AC24/$Y24*$X24 -> 0.93388394 | T24: =AD24/$Y24*$X24 -> #N/A | U24: =AE24/$Y24*$X24 -> 1.5427325 | V24: =AF24/$Y24*$X24 -> 5.3700856 | X24: =(C24/C20-1)*100 -> 6.8613839 | Y24: =C24-C20 -> 44793.308 | Z24: =D24-D20 -> 43163.593 | AA24: =E24-E20 -> 6523.819 | AB24: =F24-F20 -> 13995.387 | AC24: =G24-G20 -> 6096.693 | AD24: =H24-H20 -> #N/A | AE24: =I24-I20 -> 10071.451 | AF24: =J24-J20 -> 35057.636
A25: 2Q 2022 | B25: 222 | C25: 782338.63 | D25: 576435.44 | E25: 99651.253 | F25: 160568.55 | G25: -7371 | H25: 2589.835 | I25: 157619.7 | J25: 204565.32 | O25: =SUM(P25:U25)-V25 -> #N/A | P25: =Z25/$Y25*$X25 -> 8.5274675 | Q25: =AA25/$Y25*$X25 -> 0.80736224 | R25: =AB25/$Y25*$X25 -> 3.3711532 | S25: =AC25/$Y25*$X25 -> -0.41149545 | T25: =AD25/$Y25*$X25 -> #N/A | U25: =AE25/$Y25*$X25 -> 1.5724778 | V25: =AF25/$Y25*$X25 -> 5.7369507 | X25: =(C25/C21-1)*100 -> 8.1300146 | Y25: =C25-C21 -> 58822.007 | Z25: =D25-D21 -> 61697.645 | AA25: =E25-E21 -> 5841.4 | AB25: =F25-F21 -> 24390.854 | AC25: =G25-G21 -> -2977.238 | AD25: =H25-H21 -> #N/A | AE25: =I25-I21 -> 11377.138 | AF25: =J25-J21 -> 41507.792
A26: 3Q 2022 | B26: 223 | C26: 732662.16 | D26: 497399.58 | E26: 96128.789 | F26: 160952.87 | G26: 22366.004 | H26: 850.829 | I26: 157115.55 | J26: 201300.63 | O26: =SUM(P26:U26)-V26 -> #N/A | P26: =Z26/$Y26*$X26 -> 6.9759583 | Q26: =AA26/$Y26*$X26 -> 0.14854931 | R26: =AB26/$Y26*$X26 -> 2.7994382 | S26: =AC26/$Y26*$X26 -> 2.6994438 | T26: =AD26/$Y26*$X26 -> #N/A | U26: =AE26/$Y26*$X26 -> -0.63918437 | V26: =AF26/$Y26*$X26 -> 5.2997839 | X26: =(C26/C22-1)*100 -> 6.6844214 | Y26: =C26-C22 -> 45905.696 | Z26: =D26-D22 -> 47907.845 | AA26: =E26-E22 -> 1020.172 | AB26: =F26-F22 -> 19225.323 | AC26: =G26-G22 -> 18538.605 | AD26: =H26-H22 -> #N/A | AE26: =I26-I22 -> -4389.64 | AF26: =J26-J22 -> 36396.609
A27: 4Q 2022 | B27: 224 | C27: 712740.46 | D27: 490167.72 | E27: 100882.29 | F27: 148604.11 | G27: 3388.381 | H27: -13333.556 | I27: 154135.03 | J27: 184437.07 | O27: =SUM(P27:U27)-V27 -> #N/A | P27: =Z27/$Y27*$X27 -> 3.9004166 | Q27: =AA27/$Y27*$X27 -> -0.40860513 | R27: =AB27/$Y27*$X27 -> 0.068767872 | S27: =AC27/$Y27*$X27 -> -2.1701797 | T27: =AD27/$Y27*$X27 -> #N/A | U27: =AE27/$Y27*$X27 -> 1.3323001 | V27: =AF27/$Y27*$X27 -> 0.3372721 | X27: =(C27/C23-1)*100 -> 2.3854277 | Y27: =C27-C23 -> 16605.789 | Z27: =D27-D23 -> 27152.152 | AA27: =E27-E23 -> -2844.442 | AB27: =F27-F23 -> 478.717 | AC27: =G27-G23 -> -15107.373 | AD27: =H27-H23 -> #N/A | AE27: =I27-I23 -> 9274.603 | AF27: =J27-J23 -> 2347.868
A28: 1Q 2023 | B28: 231 | C28: 704009.04 | D28: 535974.73 | E28: 97699.373 | F28: 141756.11 | G28: -8051.105 | H28: 16502.654 | I28: 126446.8 | J28: 189816.87 | O28: =SUM(P28:U28)-V28 -> 2.785294 | P28: =Z28/$Y28*$X28 -> 2.7797512 | Q28: =AA28/$Y28*$X28 -> 0.40466681 | R28: =AB28/$Y28*$X28 -> -0.27631023 | S28: =AC28/$Y28*$X28 -> 0.32023237 | T28: =AD28/$Y28*$X28 -> 1.8702251 | U28: =AE28/$Y28*$X28 -> -1.2751609 | V28: =AF28/$Y28*$X28 -> 1.0381103 | X28: =(C28/C24-1)*100 -> 0.91506861 | Y28: =C28-C24 -> 6383.75 | Z28: =D28-D24 -> 19392.247 | AA28: =E28-E24 -> 2823.058 | AB28: =F28-F24 -> -1927.61 | AC28: =G28-G24 -> 2234.022 | AD28: =H28-H24 -> 13047.163 | AE28: =I28-I24 -> -8895.845 | AF28: =J28-J24 -> 7242.12
A29: 2Q 2023 | B29: 232 | C29: 738128.41 | D29: 588087.03 | E29: 104013.85 | F29: 157587.98 | G29: -36051.054 | H29: -11636.946 | I29: 136912.27 | J29: 212421.67 | O29: =SUM(P29:U29)-V29 -> -7.4695275 | P29: =Z29/$Y29*$X29 -> 1.4893286 | Q29: =AA29/$Y29*$X29 -> 0.55763551 | R29: =AB29/$Y29*$X29 -> -0.38098272 | S29: =AC29/$Y29*$X29 -> -3.6659386 | T29: =AD29/$Y29*$X29 -> -1.818494 | U29: =AE29/$Y29*$X29 -> -2.6468624 | V29: =AF29/$Y29*$X29 -> 1.0042139 | X29: =(C29/C25-1)*100 -> -5.6510335 | Y29: =C29-C25 -> -44210.218 | Z29: =D29-D25 -> 11651.593 | AA29: =E29-E25 -> 4362.598 | AB29: =F29-F25 -> -2980.575 | AC29: =G29-G25 -> -28680.054 | AD29: =H29-H25 -> -14226.781 | AE29: =I29-I25 -> -20707.427 | AF29: =J29-J25 -> 7856.353
A30: 3Q 2023 | B30: 233 | C30: 728542.26 | D30: 496373.77 | E30: 99537.229 | F30: 162177.09 | G30: 31511.919 | H30: 6508.051 | I30: 143916.19 | J30: 204973.94 | O30: =SUM(P30:U30)-V30 -> 0.2098259 | P30: =Z30/$Y30*$X30 -> -0.1400116 | Q30: =AA30/$Y30*$X30 -> 0.46521305 | R30: =AB30/$Y30*$X30 -> 0.16709175 | S30: =AC30/$Y30*$X30 -> 1.2483127 | T30: =AD30/$Y30*$X30 -> 0.77214606 | U30: =AE30/$Y30*$X30 -> -1.8015614 | V30: =AF30/$Y30*$X30 -> 0.50136464 | X30: =(C30/C26-1)*100 -> -0.56232029 | Y30: =C30-C26 -> -4119.908 | Z30: =D30-D26 -> -1025.812 | AA30: =E30-E26 -> 3408.44 | AB30: =F30-F26 -> 1224.218 | AC30: =G30-G26 -> 9145.915 | AD30: =H30-H26 -> 5657.222 | AE30: =I30-I26 -> -13199.359 | AF30: =J30-J26 -> 3673.309
A31: 4Q 2023 | B31: 234 | C31: 700543.2 | D31: 480687.41 | E31: 99272.705 | F31: 137053.08 | G31: 30180.388 | H31: -11924.588 | I31: 136117.33 | J31: 182767.72 | O31: =SUM(P31:U31)-V31 -> -1.5136353 | P31: =Z31/$Y31*$X31 -> -1.3301208 | Q31: =AA31/$Y31*$X31 -> -0.22582989 | R31: =AB31/$Y31*$X31 -> -1.6206495 | S31: =AC31/$Y31*$X31 -> 3.7590131 | T31: =AD31/$Y31*$X31 -> 0.19768318 | U31: =AE31/$Y31*$X31 -> -2.5279464 | V31: =AF31/$Y31*$X31 -> -0.23421513 | X31: =(C31/C27-1)*100 -> -1.7113185 | Y31: =C31-C27 -> -12197.259 | Z31: =D31-D27 -> -9480.309 | AA31: =E31-E27 -> -1609.581 | AB31: =F31-F27 -> -11551.025 | AC31: =G31-G27 -> 26792.007 | AD31: =H31-H27 -> 1408.968 | AE31: =I31-I27 -> -18017.697 | AF31: =J31-J27 -> -1669.346
A32: 1Q 2024 | B32: 241 | C32: 668219.63 | D32: 508286.75 | E32: 93290.784 | F32: 107772.24 | G32: -29378.771 | H32: 4554.47 | I32: 147382.29 | J32: 163688.13 | O32: =SUM(P32:U32)-V32 -> -7.427754 | P32: =Z32/$Y32*$X32 -> -3.9329009 | Q32: =AA32/$Y32*$X32 -> -0.62621199 | R32: =AB32/$Y32*$X32 -> -4.8271922 | S32: =AC32/$Y32*$X32 -> -3.0294591 | T32: =AD32/$Y32*$X32 -> -1.6971634 | U32: =AE32/$Y32*$X32 -> 2.973753 | V32: =AF32/$Y32*$X32 -> -3.7114207 | X32: =(C32/C28-1)*100 -> -5.0836569 | Y32: =C32-C28 -> -35789.404 | Z32: =D32-D28 -> -27687.978 | AA32: =E32-E28 -> -4408.589 | AB32: =F32-F28 -> -33983.869 | AC32: =G32-G28 -> -21327.666 | AD32: =H32-H28 -> -11948.184 | AE32: =I32-I28 -> 20935.49 | AF32: =J32-J28 -> -26128.737
A33: 2Q 2024 | B33: 242 | C33: 729909.37 | D33: 538393.96 | E33: 98261.488 | F33: 111250.68 | G33: -9485.314 | H33: -8671.411 | I33: 164179.76 | J33: 164019.8 | O33: =SUM(P33:U33)-V33 -> 0.46304992 | P33: =Z33/$Y33*$X33 -> -6.7323065 | Q33: =AA33/$Y33*$X33 -> -0.77931738 | R33: =AB33/$Y33*$X33 -> -6.2776746 | S33: =AC33/$Y33*$X33 -> 3.5990675 | T33: =AD33/$Y33*$X33 -> 0.4017641 | U33: =AE33/$Y33*$X33 -> 3.6941388 | V33: =AF33/$Y33*$X33 -> -6.557378 | X33: =(C33/C29-1)*100 -> -1.1134976 | Y33: =C33-C29 -> -8219.042 | Z33: =D33-D29 -> -49693.067 | AA33: =E33-E29 -> -5752.363 | AB33: =F33-F29 -> -46337.3 | AC33: =G33-G29 -> 26565.74 | AD33: =H33-H29 -> 2965.535 | AE33: =I33-I29 -> 27267.488 | AF33: =J33-J29 -> -48401.87
A34: 3Q 2024 | B34: 243 | C34: 714299.22 | D34: 490119.31 | E34: 95614.376 | F34: 134999.68 | G34: 16624.836 | H34: -14763.567 | I34: 172087.52 | J34: 180382.93 | O34: =SUM(P34:U34)-V34 -> -2.8483027 | P34: =Z34/$Y34*$X34 -> -0.85848967 | Q34: =AA34/$Y34*$X34 -> -0.53845236 | R34: =AB34/$Y34*$X34 -> -3.7303825 | S34: =AC34/$Y34*$X34 -> -2.0434069 | T34: =AD34/$Y34*$X34 -> -2.9197508 | U34: =AE34/$Y34*$X34 -> 3.8668076 | V34: =AF34/$Y34*$X34 -> -3.375372 | X34: =(C34/C30-1)*100 -> -1.9550051 | Y34: =C34-C30 -> -14243.038 | Z34: =D34-D30 -> -6254.46 | AA34: =E34-E30 -> -3922.853 | AB34: =F34-F30 -> -27177.413 | AC34: =G34-G30 -> -14887.083 | AD34: =H34-H30 -> -21271.618 | AE34: =I34-I30 -> 28171.327 | AF34: =J34-J30 -> -24591.011
A35: 4Q 2024 | B35: 244 | C35: 719523.32 | D35: 504095.17 | E35: 101219.35 | F35: 139618.48 | G35: 26848.363 | H35: -25287.855 | I35: 172594.56 | J35: 199564.73 | O35: =SUM(P35:U35)-V35 -> 4.4115351 | P35: =Z35/$Y35*$X35 -> 3.3413722 | Q35: =AA35/$Y35*$X35 -> 0.2778758 | R35: =AB35/$Y35*$X35 -> 0.36620011 | S35: =AC35/$Y35*$X35 -> -0.47563448 | T35: =AD35/$Y35*$X35 -> -1.9075579 | U35: =AE35/$Y35*$X35 -> 5.2069911 | V35: =AF35/$Y35*$X35 -> 2.3977118 | X35: =(C35/C31-1)*100 -> 2.7093436 | Y35: =C35-C31 -> 18980.122 | Z35: =D35-D31 -> 23407.756 | AA35: =E35-E31 -> 1946.64 | AB35: =F35-F31 -> 2565.39 | AC35: =G35-G31 -> -3332.025 | AD35: =H35-H31 -> -13363.267 | AE35: =I35-I31 -> 36477.222 | AF35: =J35-J31 -> 16797.007
A36: 1Q 2025 | B36: 251 | C36: 709095.12 | D36: 566590.76 | E36: 91687.793 | F36: 141620.55 | G36: -19277.671 | H36: 1704.755 | I36: 156881.31 | J36: 230112.38 | O36: =SUM(P36:U36)-V36 -> 6.1170746 | P36: =Z36/$Y36*$X36 -> 8.7252763 | Q36: =AA36/$Y36*$X36 -> -0.23988984 | R36: =AB36/$Y36*$X36 -> 5.0654468 | S36: =AC36/$Y36*$X36 -> 1.5116437 | T36: =AD36/$Y36*$X36 -> -0.42646383 | U36: =AE36/$Y36*$X36 -> 1.4215425 | V36: =AF36/$Y36*$X36 -> 9.9404811 | X36: =(C36/C32-1)*100 -> 6.1170747 | Y36: =C36-C32 -> 40875.494 | Z36: =D36-D32 -> 58304.009 | AA36: =E36-E32 -> -1602.991 | AB36: =F36-F32 -> 33848.31 | AC36: =G36-G32 -> 10101.1 | AD36: =H36-H32 -> -2849.715 | AE36: =I36-I32 -> 9499.026 | AF36: =J36-J32 -> 66424.246
... A40: 1Q 2026 | B40: 261 | C40: 725600.24 | D40: 582154.8 | E40: 90857.061 | F40: 125135.44 | G40: -32028.81 | H40: 131.662 | I40: 172306.88 | J40: 212956.78 | O40: =SUM(P40:U40)-V40 -> 2.3276316 | P40: =Z40/$Y40*$X40 -> 2.1949154 | Q40: =AA40/$Y40*$X40 -> -0.11715382 | R40: =AB40/$Y40*$X40 -> -2.3248094 | S40: =AC40/$Y40*$X40 -> -1.7982269 | T40: =AD40/$Y40*$X40 -> -0.22184513 | U40: =AE40/$Y40*$X40 -> 2.1753871 | V40: =AF40/$Y40*$X40 -> -2.4193643 | X40: =(C40/C36-1)*100 -> 2.3276313 | Y40: =C40-C36 -> 16505.12 | Z40: =D40-D36 -> 15564.038 | AA40: =E40-E36 -> -830.732 | AB40: =F40-F36 -> -16485.11 | AC40: =G40-G36 -> -12751.139 | AD40: =H40-H36 -> -1573.093 | AE40: =I40-I36 -> 15425.564 | AF40: =J40-J36 -> -17155.594

Sheet Employment
C2: Mining | D2: Manufacturing | E2: Construction | F2: Formal employment | G2: Mining employment | H2: Manufacturing employment | I2: Construction employment
B3: 1151 !Q | C3: H213GQC@EMERGELA | D3: H213G2MC@EMERGELA | E3: H213GCOC@EMERGELA | F3: S213ELEC@EMERGELA | G3: S213ECN@EMERGELA | H3: S213ECM@EMERGELA | I3: S213ECK@EMERGELA
B4: .DESC | C4: Argentina: GVA: Mining and Quarrying (SAAR, Mil.2004.Pesos) | D4: Argentina: GVA: Manufacturing (SAAR, Mil.2004.Pesos) | E4: Argentina: GVA: Construction (SAAR, Mil.2004.Pesos) | F4: Argentina: Private Reg Salaried Employ: Total (SA, Persons) | G4: Argentina: Private Reg Salaried Employ: Mining & Quarrying (SA, Persons) | H4: Argentina: Private Reg Salaried Employ: Manufacturing Industry (SA, Persons) | I4: Argentina: Private Reg Salaried Employ: Construction (SA, Persons)
B5: .SOURCE | C5: INDEC/H | D5: INDEC/H | E5: INDEC/H | F5: MTEySS | G5: MTEySS | H5: MTEySS | I5: MTEySS
B6: .DATA_TYPE | C6: LocCur | D6: LocCur | E6: LocCur | F6: Units | G6: Units | H6: Units | I6: Units
B7: .MAG | C7: 6 | D7: 6 | E7: 6 | F7: 0 | G7: 0 | H7: 0 | I7: 0 | N7: Oil output | O7: Manufacturing | P7: Construction | Q7: Formal employment | R7: Oil & mining | S7: Manufacturing | T7: Construction
A8: 1Q 2015 | B8: 151 | C8: 23215.973 | D8: 124590.72 | E8: 22044.416 | F8: 6520873 | G8: 91361 | H8: 1281741 | I8: 447480 | K8: =G8/$F8*100 -> 1.4010547 | L8: =H8/$F8*100 -> 19.655972 | N8: =C8/C$8*100 -> 100 | O8: =D8/D$8*100 -> 100 | P8: =E8/E$8*100 -> 100 | Q8: =F8/F$8*100 -> 100 | R8: =G8/G$8*100 -> 100 | S8: =H8/H$8*100 -> 100
A9: 2Q 2015 | B9: 152 | C9: 23409.551 | D9: 126980.24 | E9: 22974.521 | F9: 6587551 | G9: 91025 | H9: 1292445 | I9: 462210 | K9: =G9/$F9*100 -> 1.381773 | L9: =H9/$F9*100 -> 19.619507 | N9: =C9/C$8*100 -> 100.83381 | O9: =D9/D$8*100 -> 101.91789 | P9: =E9/E$8*100 -> 104.21923 | Q9: =F9/F$8*100 -> 101.02253 | R9: =G9/G$8*100 -> 99.632228 | S9: =H9/H$8*100 -> 100.83511
A10: 3Q 2015 | B10: 153 | C10: 23147.52 | D10: 126173.96 | E10: 22898.78 | F10: 6620689 | G10: 90555 | H10: 1298801 | I10: 464593 | K10: =G10/$F10*100 -> 1.3677579 | L10: =H10/$F10*100 -> 19.617309 | N10: =C10/C$8*100 -> 99.705147 | O10: =D10/D$8*100 -> 101.27075 | P10: =E10/E$8*100 -> 103.87565 | Q10: =F10/F$8*100 -> 101.53072 | R10: =G10/G$8*100 -> 99.117785 | S10: =H10/H$8*100 -> 101.331
A11: 4Q 2015 | B11: 154 | C11: 22762.511 | D11: 123206.59 | E11: 22317.528 | F11: 6606981 | G11: 89519 | H11: 1296330 | I11: 448344 | K11: =G11/$F11*100 -> 1.3549154 | L11: =H11/$F11*100 -> 19.62061 | N11: =C11/C$8*100 -> 98.046767 | O11: =D11/D$8*100 -> 98.889059 | P11: =E11/E$8*100 -> 101.23892 | Q11: =F11/F$11*100 -> 100 | R11: =G11/G$11*100 -> 100 | S11: =H11/H$11*100 -> 100 | T11: =I11/I$11*100 -> 100 | U11: 100
A12: 1Q 2016 | B12: 161 | C12: 22347.724 | D12: 120741.64 | E12: 20751.032 | F12: 6574288 | G12: 88239 | H12: 1286951 | I12: 422320 | K12: =G12/$F12*100 -> 1.3421834 | L12: =H12/$F12*100 -> 19.575519 | N12: =C12/C$8*100 -> 96.260122 | O12: =D12/D$8*100 -> 96.910618 | P12: =E12/E$8*100 -> 94.132827 | Q12: =F12/F$11*100 -> 99.505175 | R12: =G12/G$11*100 -> 98.570136 | S12: =H12/H$11*100 -> 99.276496 | T12: =I12/I$11*100 -> 94.195528 | U12: 100
A13: 2Q 2016 | B13: 162 | C13: 21976.417 | D13: 117313.13 | E13: 19423.583 | F13: 6542140 | G13: 85876 | H13: 1274411 | I13: 412404 | K13: =G13/$F13*100 -> 1.3126592 | L13: =H13/$F13*100 -> 19.480033 | N13: =C13/C$8*100 -> 94.660762 | O13: =D13/D$8*100 -> 94.158801 | P13: =E13/E$8*100 -> 88.111125 | Q13: =F13/F$11*100 -> 99.018599 | R13: =G13/G$11*100 -> 95.930473 | S13: =H13/H$11*100 -> 98.30915 | T13: =I13/I$11*100 -> 91.983834 | U13: 100
A14: 3Q 2016 | B14: 163 | C14: 21864.974 | D14: 116958.62 | E14: 19852.245 | F14: 6531958 | G14: 84663 | H14: 1264627 | I14: 413700 | K14: =G14/$F14*100 -> 1.2961351 | L14: =H14/$F14*100 -> 19.360611 | N14: =C14/C$8*100 -> 94.180735 | O14: =D14/D$8*100 -> 93.874261 | P14: =E14/E$8*100 -> 90.055663 | Q14: =F14/F$11*100 -> 98.864489 | R14: =G14/G$11*100 -> 94.575453 | S14: =H14/H$11*100 -> 97.554404 | T14: =I14/I$11*100 -> 92.272898 | U14: 100
A15: 4Q 2016 | B15: 164 | C15: 21268.255 | D15: 118167.83 | E15: 20120.128 | F15: 6549573 | G15: 84066 | H15: 1258466 | I15: 422246 | K15: =G15/$F15*100 -> 1.2835341 | L15: =H15/$F15*100 -> 19.214474 | N15: =C15/C$8*100 -> 91.61044 | O15: =D15/D$8*100 -> 94.844804 | P15: =E15/E$8*100 -> 91.27086 | Q15: =F15/F$11*100 -> 99.131101 | R15: =G15/G$11*100 -> 93.908556 | S15: =H15/H$11*100 -> 97.079139 | T15: =I15/I$11*100 -> 94.179023 | U15: 100
A16: 1Q 2017 | B16: 171 | C16: 21189.88 | D16: 117978.66 | E16: 21105.981 | F16: 6575488 | G16: 82622 | H16: 1252970 | I16: 436764 | K16: =G16/$F16*100 -> 1.2565151 | L16: =H16/$F16*100 -> 19.055164 | N16: =C16/C$8*100 -> 91.272849 | O16: =D16/D$8*100 -> 94.692977 | P16: =E16/E$8*100 -> 95.742981 | Q16: =F16/F$11*100 -> 99.523338 | R16: =G16/G$11*100 -> 92.29549 | S16: =H16/H$11*100 -> 96.655173 | T16: =I16/I$11*100 -> 97.417162 | U16: 100
A17: 2Q 2017 | B17: 172 | C17: 20531.46 | D17: 120705.64 | E17: 21388.952 | F17: 6592079 | G17: 81233 | H17: 1249407 | I17: 447612 | K17: =G17/$F17*100 -> 1.232282 | L17: =H17/$F17*100 -> 18.953156 | N17: =C17/C$8*100 -> 88.436784 | O17: =D17/D$8*100 -> 96.881721 | P17: =E17/E$8*100 -> 97.026621 | Q17: =F17/F$11*100 -> 99.774451 | R17: =G17/G$11*100 -> 90.743864 | S17: =H17/H$11*100 -> 96.38032 | T17: =I17/I$11*100 -> 99.836733 | U17: 100
A18: 3Q 2017 | B18: 173 | C18: 21110.328 | D18: 122677.69 | E18: 22041.381 | F18: 6627129 | G18: 81159 | H18: 1243738 | I18: 460742 | K18: =G18/$F18*100 -> 1.224648 | L18: =H18/$F18*100 -> 18.767373 | N18: =C18/C$8*100 -> 90.930188 | O18: =D18/D$8*100 -> 98.464544 | P18: =E18/E$8*100 -> 99.986232 | Q18: =F18/F$11*100 -> 100.30495 | R18: =G18/G$11*100 -> 90.6612 | S18: =H18/H$11*100 -> 95.943008 | T18: =I18/I$11*100 -> 102.76529 | U18: 100
A19: 4Q 2017 | B19: 174 | C19: 21516.414 | D19: 123220.21 | E19: 22999.851 | F19: 6668757 | G19: 81315 | H19: 1245451 | I19: 472630 | K19: =G19/$F19*100 -> 1.2193427 | L19: =H19/$F19*100 -> 18.675909 | N19: =C19/C$8*100 -> 92.679355 | O19: =D19/D$8*100 -> 98.89999 | P19: =E19/E$8*100 -> 104.33414 | Q19: =F19/F$11*100 -> 100.93501 | R19: =G19/G$11*100 -> 90.835465 | S19: =H19/H$11*100 -> 96.075151 | T19: =I19/I$11*100 -> 105.41682 | U19: 100
A20: 1Q 2018 | B20: 181 | C20: 21453.901 | D20: 122224.64 | E20: 22839.63 | F20: 6682567 | G20: 81638 | H20: 1242180 | I20: 477195 | K20: =G20/$F20*100 -> 1.2216563 | L20: =H20/$F20*100 -> 18.588366 | N20: =C20/C$8*100 -> 92.410088 | O20: =D20/D$8*100 -> 98.100915 | P20: =E20/E$8*100 -> 103.60733 | Q20: =F20/F$11*100 -> 101.14403 | R20: =G20/G$11*100 -> 91.196282 | S20: =H20/H$11*100 -> 95.822823 | T20: =I20/I$11*100 -> 106.43501 | U20: 100
A21: 2Q 2018 | B21: 182 | C21: 21455.314 | D21: 118718.2 | E21: 22593.068 | F21: 6665029 | G21: 84975 | H21: 1229780 | I21: 475880 | K21: =G21/$F21*100 -> 1.2749382 | L21: =H21/$F21*100 -> 18.451233 | N21: =C21/C$8*100 -> 92.416174 | O21: =D21/D$8*100 -> 95.286544 | P21: =E21/E$8*100 -> 102.48885 | Q21: =F21/F$11*100 -> 100.87859 | R21: =G21/G$11*100 -> 94.923983 | S21: =H21/H$11*100 -> 94.866276 | T21: =I21/I$11*100 -> 106.14171 | U21: 100
A22: 3Q 2018 | B22: 183 | C22: 21115.369 | D22: 113588.17 | E22: 21894.816 | F22: 6615816 | G22: 85361 | H22: 1212009 | I22: 467787 | K22: =G22/$F22*100 -> 1.2902566 | L22: =H22/$F22*100 -> 18.319872 | N22: =C22/C$8*100 -> 90.951902 | O22: =D22/D$8*100 -> 91.169042 | P22: =E22/E$8*100 -> 99.32137 | Q22: =F22/F$11*100 -> 100.13372 | R22: =G22/G$11*100 -> 95.355176 | S22: =H22/H$11*100 -> 93.495406 | T22: =I22/I$11*100 -> 104.33663 | U22: 100
... A51: 4Q 2025 | B51: 254 | C51: 30792.209 | D51: 107116.38 | E51: 19435.215 | F51: 6609142 | G51: 91132 | H51: 1208731 | I51: 393120 | K51: =G51/$F51*100 -> 1.3788779 | L51: =H51/$F51*100 -> 18.288773 | N51: =C51/C$8*100 -> 132.63372 | O51: =D51/D$8*100 -> 85.9746 | P51: =E51/E$8*100 -> 88.163891 | Q51: =F51/F$11*100 -> 100.03271 | R51: =G51/G$11*100 -> 101.80185 | S51: =H51/H$11*100 -> 93.242539 | T51: =I51/I$11*100 -> 87.682672 | U51: 100
A52: 1Q 2026 | B52: 261 | C52: 32327.382 | D52: 109532.35 | E52: 19836.069 | N52: =C52/C$8*100 -> 139.24629 | O52: =D52/D$8*100 -> 87.913725 | P52: =E52/E$8*100 -> 89.982284 | T52: =I52/I$11*100 -> 0 | U52: 100

Sheet CPI MoM
C1: Headline | D1: Core
B2: 12201 !M | C2: N213PC@EMERGELA | D2: N213PCXQ@EMERGELA
B3: .DESC | C3: Argentina: Consumer Price Index (NSA, Dec-16=100) | D3: Argentina: CPI Ex Seasonal & Regulated (NSA, Dec-16=100)
B4: .SOURCE | C4: INDEC | D4: INDEC
B5: .DATA_TYPE | C5: INDEX | D5: INDEX
B6: .MAG | C6: 0 | D6: 0
A7: 44562 | B7: 2201 | C7: 605.0317 | D7: 625.1594 | E7: Headline | F7: Core | G7: 2% threshold
A8: 44593 | B8: 2202 | C8: 633.4341 | D8: 652.9838 | E8: =(C8/C7-1)*100 -> 4.6943656 | F8: =(D8/D7-1)*100 -> 4.4507689 | G8: 2
A9: 44621 | B9: 2203 | C9: 676.0566 | D9: 694.7515 | E9: =(C9/C8-1)*100 -> 6.7287978 | F9: =(D9/D8-1)*100 -> 6.3964374 | G9: 2
A10: 44652 | B10: 2204 | C10: 716.9399 | D10: 741.3622 | E10: =(C10/C9-1)*100 -> 6.0473191 | F10: =(D10/D9-1)*100 -> 6.7089744 | G10: 2
A11: 44682 | B11: 2205 | C11: 753.147 | D11: 779.9267 | E11: =(C11/C10-1)*100 -> 5.0502281 | F11: =(D11/D10-1)*100 -> 5.2018433 | G11: 2
A12: 44713 | B12: 2206 | C12: 793.0278 | D12: 819.5734 | E12: =(C12/C11-1)*100 -> 5.2952213 | F12: =(D12/D11-1)*100 -> 5.083388 | G12: 2
A13: 44743 | B13: 2207 | C13: 851.761 | D13: 879.6383 | E13: =(C13/C12-1)*100 -> 7.4061969 | F13: =(D13/D12-1)*100 -> 7.3288006 | G13: 2
A14: 44774 | B14: 2208 | C14: 911.1316 | D14: 939.4677 | E14: =(C14/C13-1)*100 -> 6.9703356 | F14: =(D14/D13-1)*100 -> 6.8015911 | G14: 2
A15: 44805 | B15: 2209 | C15: 967.3076 | D15: 991.2585 | E15: =(C15/C14-1)*100 -> 6.1655199 | F15: =(D15/D14-1)*100 -> 5.5127813 | G15: 2
A16: 44835 | B16: 2210 | C16: 1028.706 | D16: 1046.265 | E16: =(C16/C15-1)*100 -> 6.3473501 | F16: =(D16/D15-1)*100 -> 5.549158 | G16: 2
A17: 44866 | B17: 2211 | C17: 1079.2787 | D17: 1096.024 | E17: =(C17/C16-1)*100 -> 4.9161471 | F17: =(D17/D16-1)*100 -> 4.7558697 | G17: 2
A18: 44896 | B18: 2212 | C18: 1134.5875 | D18: 1153.5771 | E18: =(C18/C17-1)*100 -> 5.1246078 | F18: =(D18/D17-1)*100 -> 5.2510803 | G18: 2
A19: 44927 | B19: 2301 | C19: 1202.979 | D19: 1215.3182 | E19: =(C19/C18-1)*100 -> 6.0278736 | F19: =(D19/D18-1)*100 -> 5.3521433 | G19: 2
... A60: 46174 | B60: 2606 | C60: 11826.41 | D60: 12010.32 | E60: =(C60/C59-1)*100 -> 1.8868715 | F60: =(D60/D59-1)*100 -> 1.5695812 | G60: 2
