Workbook

Sheet README
A1: Simplified Deep Value Strategy — Bloomberg workbook
A2: Implements the mechanics described in Appendix B of "Building a Better Deep Value Portfolio" (Kupersmith, Ross, Thapar, AQR, March 2017).
A4: What this is
A5: A working implementation of the Appendix B engine on two of the fourteen sub-strategies: Emerging Currencies
A6: (signal: real exchange rate) and Interest Rate Futures (signal: adjusted real short rate). The engine is generic —
A7: the Template sheet explains how to add Global Bonds, Developed Currencies, Inflation Breakevens or any other sleeve.
A9: The mechanics, step by step
A10: 1. Each sub-strategy is divided into SUBSETS. For non-stock-selection strategies a subset is a PAIR of assets.
A11: 7 assets gives 21 pairs per sleeve.
A12: 2. Within each subset, assets are sorted on the valuation metric: long the top third, short the bottom third.
A13: In a two-asset subset that reduces to long the cheap one and short the rich one.
A14: 3. The VALUATION SPREAD of the subset is the gap between the long and short legs' valuation. Always positive.
... A53: each data sheet.

Sheet Config
A1: Configuration
A2: Blue = input. Change these and the whole workbook recalculates.
A4: Parameter | B4: Value | C4: Notes
A5: Entry / step-1 z threshold | B5: 2 | C5: Subset is included when the expanding z-score of its valuation spread exceeds this.
A6: Step-2 z threshold | B6: 3 | C6: Position steps up at this z.
A7: Step-3 z threshold | B7: 4 | C7: Position steps up again at this z.
A8: Exit z threshold | B8: 2 | C8: Subset is removed when z falls below this. Appendix B uses 2. Set to 1 for the footnote variant.
A9: Weight at step 1 | B9: 1 | C9: Risk multiplier once included.
A10: Weight at step 2 | B10: 1.5 | C10: Risk multiplier at the step-2 threshold.
A11: Weight at step 3 | B11: 2 | C11: Risk multiplier at the step-3 threshold.
A12: Min obs for z-score | B12: 60 | C12: Months of history required before an expanding z-score is produced.
A13: Vol lookback (months) | B13: 36 | C13: Trailing window for subset and portfolio volatility.
A14: Target vol per subset | B14: 0.02 | C14: Annualised risk target for each included subset before portfolio scaling.
A15: Portfolio vol cap | B15: 0.1 | C15: Annualised. If trailing portfolio vol exceeds this, all subsets scale down proportionally.
A16: Max subset scalar | B16: 5 | C16: Cap on the vol-targeting multiplier, to stop a quiet subset being levered absurdly.
... A18: Sleeves in portfolio | B18: 2 | C18: Used for the equal-risk-contribution split across sleeves.
A20: All thresholds and multipliers above are taken from Appendix B as supplied by the user. Risk-targeting parameters are implementation choices.

Sheet Tickers
A1: Bloomberg pull sheet
A2: Verify every ticker on the terminal before trusting it. Column F is the formula to paste into the matching yellow block.
A4: Start date | B4: 37987
A5: End date | B5: 46295
A6: BDH options | B6: "Per=M","Dts=H","Days=A","Fill=P" | C6: Monthly periodicity, dates hidden so one column comes back, all calendar days, previous value carried.
A8: Sleeve | B8: Series needed | C8: Suggested ticker | D8: Confidence | E8: How to verify on the terminal | F8: BDH formula to paste
A9: EM currencies | B9: BRL spot per USD | C9: USDBRL Curncy | D9: High | E9: Standard spot ticker. Confirm quoting convention is units per USD. | F9: =IF($C9="<verify>","-- fill in the ticker first --","=BDH("""&$C9&""",""PX_LAST"","""&TEXT($B$4,"yyyymmdd")&""","""&TEXT($B$5,"yyyymmdd")&""","&$B$6&")") -> =BDH("USDBRL Curncy","PX_LAST","20040101","20260930","Per=M","Dts=H","Days=A","Fill=P")
A10: EM currencies | B10: MXN spot per USD | C10: USDMXN Curncy | D10: High | E10: Standard spot ticker. Confirm quoting convention is units per USD. | F10: =IF($C10="<verify>","-- fill in the ticker first --","=BDH("""&$C10&""",""PX_LAST"","""&TEXT($B$4,"yyyymmdd")&""","""&TEXT($B$5,"yyyymmdd")&""","&$B$6&")") -> =BDH("USDMXN Curncy","PX_LAST","20040101","20260930","Per=M","Dts=H","Days=A","Fill=P")
A11: EM currencies | B11: CLP spot per USD | C11: USDCLP Curncy | D11: High | E11: Standard spot ticker. Confirm quoting convention is units per USD. | F11: =IF($C11="<verify>","-- fill in the ticker first --","=BDH("""&$C11&""",""PX_LAST"","""&TEXT($B$4,"yyyymmdd")&""","""&TEXT($B$5,"yyyymmdd")&""","&$B$6&")") -> =BDH("USDCLP Curncy","PX_LAST","20040101","20260930","Per=M","Dts=H","Days=A","Fill=P")
A12: EM currencies | B12: COP spot per USD | C12: USDCOP Curncy | D12: High | E12: Standard spot ticker. Confirm quoting convention is units per USD. | F12: =IF($C12="<verify>","-- fill in the ticker first --","=BDH("""&$C12&""",""PX_LAST"","""&TEXT($B$4,"yyyymmdd")&""","""&TEXT($B$5,"yyyymmdd")&""","&$B$6&")") -> =BDH("USDCOP Curncy","PX_LAST","20040101","20260930","Per=M","Dts=H","Days=A","Fill=P")
A13: EM currencies | B13: ZAR spot per USD | C13: USDZAR Curncy | D13: High | E13: Standard spot ticker. Confirm quoting convention is units per USD. | F13: =IF($C13="<verify>","-- fill in the ticker first --","=BDH("""&$C13&""",""PX_LAST"","""&TEXT($B$4,"yyyymmdd")&""","""&TEXT($B$5,"yyyymmdd")&""","&$B$6&")") -> =BDH("USDZAR Curncy","PX_LAST","20040101","20260930","Per=M","Dts=H","Days=A","Fill=P")
A14: EM currencies | B14: TRY spot per USD | C14: USDTRY Curncy | D14: High | E14: Standard spot ticker. Confirm quoting convention is units per USD. | F14: =IF($C14="<verify>","-- fill in the ticker first --","=BDH("""&$C14&""",""PX_LAST"","""&TEXT($B$4,"yyyymmdd")&""","""&TEXT($B$5,"yyyymmdd")&""","&$B$6&")") -> =BDH("USDTRY Curncy","PX_LAST","20040101","20260930","Per=M","Dts=H","Days=A","Fill=P")
A15: EM currencies | B15: PLN spot per USD | C15: USDPLN Curncy | D15: High | E15: Standard spot ticker. Confirm quoting convention is units per USD. | F15: =IF($C15="<verify>","-- fill in the ticker first --","=BDH("""&$C15&""",""PX_LAST"","""&TEXT($B$4,"yyyymmdd")&""","""&TEXT($B$5,"yyyymmdd")&""","&$B$6&")") -> =BDH("USDPLN Curncy","PX_LAST","20040101","20260930","Per=M","Dts=H","Days=A","Fill=P")
A16: EM currencies | B16: BRL country CPI index | C16: <verify> | D16: Find it | E16: ECO <GO> > country > Consumer Price Index > copy the index-level (not YoY) ticker. | F16: =IF($C16="<verify>","-- fill in the ticker first --","=BDH("""&$C16&""",""PX_LAST"","""&TEXT($B$4,"yyyymmdd")&""","""&TEXT($B$5,"yyyymmdd")&""","&$B$6&")") -> -- fill in the ticker first --
A17: EM currencies | B17: MXN country CPI index | C17: <verify> | D17: Find it | E17: ECO <GO> > country > Consumer Price Index > copy the index-level (not YoY) ticker. | F17: =IF($C17="<verify>","-- fill in the ticker first --","=BDH("""&$C17&""",""PX_LAST"","""&TEXT($B$4,"yyyymmdd")&""","""&TEXT($B$5,"yyyymmdd")&""","&$B$6&")") -> -- fill in the ticker first --
A18: EM currencies | B18: CLP country CPI index | C18: <verify> | D18: Find it | E18: ECO <GO> > country > Consumer Price Index > copy the index-level (not YoY) ticker. | F18: =IF($C18="<verify>","-- fill in the ticker first --","=BDH("""&$C18&""",""PX_LAST"","""&TEXT($B$4,"yyyymmdd")&""","""&TEXT($B$5,"yyyymmdd")&""","&$B$6&")") -> -- fill in the ticker first --
A19: EM currencies | B19: COP country CPI index | C19: <verify> | D19: Find it | E19: ECO <GO> > country > Consumer Price Index > copy the index-level (not YoY) ticker. | F19: =IF($C19="<verify>","-- fill in the ticker first --","=BDH("""&$C19&""",""PX_LAST"","""&TEXT($B$4,"yyyymmdd")&""","""&TEXT($B$5,"yyyymmdd")&""","&$B$6&")") -> -- fill in the ticker first --
A20: EM currencies | B20: ZAR country CPI index | C20: <verify> | D20: Find it | E20: ECO <GO> > country > Consumer Price Index > copy the index-level (not YoY) ticker. | F20: =IF($C20="<verify>","-- fill in the ticker first --","=BDH("""&$C20&""",""PX_LAST"","""&TEXT($B$4,"yyyymmdd")&""","""&TEXT($B$5,"yyyymmdd")&""","&$B$6&")") -> -- fill in the ticker first --
... A44: Rate futures | B44: NZ 2-year government yield | C44: <verify> | D44: Find it | E44: Generic 2y sovereign yield. Confirm it is the on-the-run generic, not a specific bond. | F44: =IF($C44="<verify>","-- fill in the ticker first --","=BDH("""&$C44&""",""PX_LAST"","""&TEXT($B$4,"yyyymmdd")&""","""&TEXT($B$5,"yyyymmdd")&""","&$B$6&")") -> -- fill in the ticker first --
A46: Confidence column is mine, not Bloomberg's. "High" means the ticker follows a standard convention I am confident in; "Find it" means look it up rather than trust a guess.

Sheet EMFX_Data
A1: EMFX Data
A2: Signal: real exchange rate. RER = (country CPI / US CPI) / spot, indexed to 100 at the first observation. Cheapness = minus the log deviation of RER from its own EXPANDING mean, so a higher number means cheaper. Yellow = paste BDH here. | B2: Spot, units per USD — INPUT | I2: CPI index — INPUT | Q2: Real exchange rate (100 = first obs) | X2: Valuation: cheapness vs own history | AE2: Monthly return to a long position
A3: Date | B3: BRL | C3: MXN | D3: CLP | E3: COP | F3: ZAR | G3: TRY | H3: PLN | I3: BRL | J3: MXN | K3: CLP | L3: COP | M3: ZAR | N3: TRY | O3: PLN | P3: US | Q3: BRL | R3: MXN | S3: CLP | T3: COP | U3: ZAR | V3: TRY | W3: PLN | X3: BRL | Y3: MXN | Z3: CLP | AA3: COP | AB3: ZAR | AC3: TRY | AD3: PLN | AE3: BRL | AF3: MXN | AG3: CLP | AH3: COP | AI3: ZAR | AJ3: TRY | AK3: PLN
A4: 38017 | B4: 3.0823 | C4: 10.9023 | D4: 652.5266 | E4: 2270.9169 | F4: 6.1991 | G4: 1.3872 | H4: 4.0673 | I4: 100.526 | J4: 100.406 | K4: 100.278 | L4: 100.314 | M4: 100.486 | N4: 100.943 | O4: 100.266 | P4: 100.203 | Q4: =(I4/$P4)/(I$4/$P$4)/(B4/B$4)*100 -> 100 | R4: =(J4/$P4)/(J$4/$P$4)/(C4/C$4)*100 -> 100 | S4: =(K4/$P4)/(K$4/$P$4)/(D4/D$4)*100 -> 100 | T4: =(L4/$P4)/(L$4/$P$4)/(E4/E$4)*100 -> 100 | U4: =(M4/$P4)/(M$4/$P$4)/(F4/F$4)*100 -> 100 | V4: =(N4/$P4)/(N$4/$P$4)/(G4/G$4)*100 -> 100 | W4: =(O4/$P4)/(O$4/$P$4)/(H4/H$4)*100 -> 100 | X4: =-(LN(Q4)-LN(AVERAGE(Q$4:Q4))) -> 0 | Y4: =-(LN(R4)-LN(AVERAGE(R$4:R4))) -> 0 | Z4: =-(LN(S4)-LN(AVERAGE(S$4:S4))) -> 0 | AA4: =-(LN(T4)-LN(AVERAGE(T$4:T4))) -> 0 | AB4: =-(LN(U4)-LN(AVERAGE(U$4:U4))) -> 0 | AC4: =-(LN(V4)-LN(AVERAGE(V$4:V4))) -> 0 | AD4: =-(LN(w4)-LN(AVERAGE(W$4:W4))) -> 3.912023
A5: 38046 | B5: 3.0631 | C5: 10.9988 | D5: 678.2575 | E5: 2265.5455 | F5: 6.4573 | G5: 1.3666 | H5: 3.9147 | I5: 100.984 | J5: 100.864 | K5: 100.418 | L5: 100.397 | M5: 100.812 | N5: 102.036 | O5: 100.354 | P5: 100.54 | Q5: =(I5/$P5)/(I$4/$P$4)/(B5/B$4)*100 -> 100.74645 | R5: =(J5/$P5)/(J$4/$P$4)/(C5/C$4)*100 -> 99.241013 | S5: =(K5/$P5)/(K$4/$P$4)/(D5/D$4)*100 -> 96.017714 | T5: =(L5/$P5)/(L$4/$P$4)/(E5/E$4)*100 -> 99.983764 | U5: =(M5/$P5)/(M$4/$P$4)/(F5/F$4)*100 -> 95.990045 | V5: =(N5/$P5)/(N$4/$P$4)/(G5/G$4)*100 -> 102.26258 | W5: =(O5/$P5)/(O$4/$P$4)/(H5/H$4)*100 -> 103.64075 | X5: =-(LN(Q5)-LN(AVERAGE(Q$4:Q5))) -> -0.0037114641 | Y5: =-(LN(R5)-LN(AVERAGE(R$4:R5))) -> 0.0038166665 | Z5: =-(LN(S5)-LN(AVERAGE(S$4:S5))) -> 0.020525156 | AA5: =-(LN(T5)-LN(AVERAGE(T$4:T5))) -> 8.1187415e-05 | AB5: =-(LN(U5)-LN(AVERAGE(U$4:U5))) -> 0.0206722 | AC5: =-(LN(V5)-LN(AVERAGE(V$4:V5))) -> -0.011124222 | AD5: =-(LN(W5)-LN(AVERAGE(W$4:W5))) -> -0.017720378 | AE5: =LN(B4/B5) -> 0.0062485965 | AF5: =LN(C4/C5) -> -0.0088123998 | AG5: =LN(D4/D5) -> -0.038675105 | AH5: =LN(E4/E5) -> 0.0023681019 | AI5: =LN(F4/F5) -> -0.040807154 | AJ5: =LN(G4/G5) -> 0.014961424 | AK5: =LN(H4/H5) -> 0.03824069
A6: 38077 | B6: 3.012 | C6: 10.8222 | D6: 685.6233 | E6: 2327.7761 | F6: 6.6255 | G6: 1.3612 | H6: 3.8341 | I6: 101.413 | J6: 101.273 | K6: 100.806 | L6: 100.874 | M6: 101.25 | N6: 103.463 | O6: 100.394 | P6: 100.864 | Q6: =(I6/$P6)/(I$4/$P$4)/(B6/B$4)*100 -> 102.5604 | R6: =(J6/$P6)/(J$4/$P$4)/(C6/C$4)*100 -> 100.94414 | S6: =(K6/$P6)/(K$4/$P$4)/(D6/D$4)*100 -> 95.046889 | T6: =(L6/$P6)/(L$4/$P$4)/(E6/E$4)*100 -> 97.459071 | U6: =(M6/$P6)/(M$4/$P$4)/(F6/F$4)*100 -> 93.657809 | V6: =(N6/$P6)/(N$4/$P$4)/(G6/G$4)*100 -> 103.76969 | W6: =(O6/$P6)/(O$4/$P$4)/(H6/H$4)*100 -> 105.5216 | X6: =-(LN(Q6)-LN(AVERAGE(Q$4:Q6))) -> -0.014319188 | Y6: =-(LN(R6)-LN(AVERAGE(R$4:R6))) -> -0.0087801331 | Z6: =-(LN(S6)-LN(AVERAGE(S$4:S6))) -> 0.020562617 | AA6: =-(LN(T6)-LN(AVERAGE(T$4:T6))) -> 0.017177261 | AB6: =-(LN(U6)-LN(AVERAGE(U$4:U6))) -> 0.030405788 | AC6: =-(LN(V6)-LN(AVERAGE(V$4:V6))) -> -0.017095701 | AD6: =-(LN(W6)-LN(AVERAGE(W$4:W6))) -> -0.023661418 | AE6: =LN(B5/B6) -> 0.016823165 | AF6: =LN(C5/C6) -> 0.016186596 | AG6: =LN(D5/D6) -> -0.010801342 | AH6: =LN(E5/E6) -> -0.027097779 | AI6: =LN(F5/F6) -> -0.025714567 | AJ6: =LN(G5/G6) -> 0.0039592397 | AK6: =LN(H5/H6) -> 0.020803971
A7: 38107 | B7: 2.897 | C7: 11.0535 | D7: 691.3283 | E7: 2466.8603 | F7: 6.6192 | G7: 1.3152 | H7: 3.9423 | I7: 101.887 | J7: 101.637 | K7: 101.157 | L7: 101.031 | M7: 101.712 | N7: 104.739 | O7: 100.58 | P7: 101.015 | Q7: =(I7/$P7)/(I$4/$P$4)/(B7/B$4)*100 -> 106.96991 | R7: =(J7/$P7)/(J$4/$P$4)/(C7/C$4)*100 -> 99.038793 | S7: =(K7/$P7)/(K$4/$P$4)/(D7/D$4)*100 -> 94.44936 | T7: =(L7/$P7)/(L$4/$P$4)/(E7/E$4)*100 -> 91.969674 | U7: =(M7/$P7)/(M$4/$P$4)/(F7/F$4)*100 -> 94.033939 | V7: =(N7/$P7)/(N$4/$P$4)/(G7/G$4)*100 -> 108.56113 | W7: =(O7/$P7)/(O$4/$P$4)/(H7/H$4)*100 -> 102.66191 | X7: =-(LN(Q7)-LN(AVERAGE(Q$4:Q7))) -> -0.042010008 | Y7: =-(LN(R7)-LN(AVERAGE(R$4:R7))) -> 0.0077165453 | Z7: =-(LN(S7)-LN(AVERAGE(S$4:S7))) -> 0.020219237 | AA7: =-(LN(T7)-LN(AVERAGE(T$4:T7))) -> 0.056885967 | AB7: =-(LN(U7)-LN(AVERAGE(U$4:U7))) -> 0.019863411 | AC7: =-(LN(V7)-LN(AVERAGE(V$4:V7))) -> -0.0463095 | AD7: =-(LN(W7)-LN(AVERAGE(W$4:W7))) -> 0.0028612053 | AE7: =LN(B6/B7) -> 0.038928591 | AF7: =LN(C6/C7) -> -0.02114754 | AG7: =LN(D6/D7) -> -0.0082864679 | AH7: =LN(E6/E7) -> -0.05803286 | AI7: =LN(F6/F7) -> 0.000951324 | AJ7: =LN(G6/G7) -> 0.034377918 | AK7: =LN(H6/H7) -> -0.027829583
A8: 38138 | B8: 2.878 | C8: 10.9931 | D8: 651.5512 | E8: 2592.9368 | F8: 6.5974 | G8: 1.3482 | H8: 3.9813 | I8: 102.412 | J8: 101.914 | K8: 101.584 | L8: 101.464 | M8: 102.311 | N8: 105.742 | O8: 100.755 | P8: 101.186 | Q8: =(I8/$P8)/(I$4/$P$4)/(B8/B$4)*100 -> 108.04803 | R8: =(J8/$P8)/(J$4/$P$4)/(C8/C$4)*100 -> 99.6856 | S8: =(K8/$P8)/(K$4/$P$4)/(D8/D$4)*100 -> 100.46843 | T8: =(L8/$P8)/(L$4/$P$4)/(E8/E$4)*100 -> 87.724326 | U8: =(M8/$P8)/(M$4/$P$4)/(F8/F$4)*100 -> 94.739894 | V8: =(N8/$P8)/(N$4/$P$4)/(G8/G$4)*100 -> 106.73734 | W8: =(O8/$P8)/(O$4/$P$4)/(H8/H$4)*100 -> 101.66103 | X8: =-(LN(Q8)-LN(AVERAGE(Q$4:Q8))) -> -0.04141172 | Y8: =-(LN(R8)-LN(AVERAGE(R$4:R8))) -> 0.00096566617 | Z8: =-(LN(S8)-LN(AVERAGE(S$4:S8))) -> -0.033109062 | AA8: =-(LN(T8)-LN(AVERAGE(T$4:T8))) -> 0.08416617 | AB8: =-(LN(U8)-LN(AVERAGE(U$4:U8))) -> 0.0099194457 | AC8: =-(LN(V8)-LN(AVERAGE(V$4:V8))) -> -0.023424291 | AD8: =-(LN(W8)-LN(AVERAGE(W$4:W8))) -> 0.010139414 | AE8: =LN(B7/B8) -> 0.0065801103 | AF8: =LN(C7/C8) -> 0.0054793166 | AG8: =LN(D7/D8) -> 0.059258838 | AH8: =LN(E7/E8) -> -0.049844924 | AI8: =LN(F7/F8) -> 0.0032988847 | AJ8: =LN(G7/G8) -> -0.024781624 | AK8: =LN(H7/H8) -> -0.0098440898
A9: 38168 | B9: 2.9946 | C9: 11.4654 | D9: 619.8892 | E9: 2504.1313 | F9: 6.2382 | G9: 1.3051 | H9: 4.0561 | I9: 102.786 | J9: 102.288 | K9: 102.009 | L9: 102.188 | M9: 102.827 | N9: 106.867 | O9: 100.963 | P9: 101.335 | Q9: =(I9/$P9)/(I$4/$P$4)/(B9/B$4)*100 -> 104.06697 | R9: =(J9/$P9)/(J$4/$P$4)/(C9/C$4)*100 -> 95.788901 | S9: =(K9/$P9)/(K$4/$P$4)/(D9/D$4)*100 -> 105.88592 | T9: =(L9/$P9)/(L$4/$P$4)/(E9/E$4)*100 -> 91.34899 | U9: =(M9/$P9)/(M$4/$P$4)/(F9/F$4)*100 -> 100.55235 | V9: =(N9/$P9)/(N$4/$P$4)/(G9/G$4)*100 -> 111.2715 | W9: =(O9/$P9)/(O$4/$P$4)/(H9/H$4)*100 -> 99.845239 | X9: =-(LN(Q9)-LN(AVERAGE(Q$4:Q9))) -> -0.003224353 | Y9: =-(LN(R9)-LN(AVERAGE(R$4:R9))) -> 0.034148176 | Z9: =-(LN(S9)-LN(AVERAGE(S$4:S9))) -> -0.07083762 | AA9: =-(LN(T9)-LN(AVERAGE(T$4:T9))) -> 0.036529685 | AB9: =-(LN(U9)-LN(AVERAGE(U$4:U9))) -> -0.041180287 | AC9: =-(LN(V9)-LN(AVERAGE(V$4:V9))) -> -0.053890805 | AD9: =-(LN(W9)-LN(AVERAGE(W$4:W9))) -> 0.023523152 | AE9: =LN(B8/B9) -> -0.039715058 | AF9: =LN(C8/C9) -> -0.042066001 | AG9: =LN(D8/D9) -> 0.049815229 | AH9: =LN(E8/E9) -> 0.034849245 | AI9: =LN(F8/F9) -> 0.055983953 | AJ9: =LN(G8/G9) -> 0.032490703 | AK9: =LN(H8/H9) -> -0.018613522
A10: 38199 | B10: 2.8438 | C10: 11.0978 | D10: 656.3564 | E10: 2384.2895 | F10: 6.0916 | G10: 1.3179 | H10: 4.0834 | I10: 103.29 | J10: 102.725 | K10: 102.434 | L10: 102.415 | M10: 103.212 | N10: 107.995 | O10: 100.99 | P10: 101.596 | Q10: =(I10/$P10)/(I$4/$P$4)/(B10/B$4)*100 -> 109.83983 | R10: =(J10/$P10)/(J$4/$P$4)/(C10/C$4)*100 -> 99.129253 | S10: =(K10/$P10)/(K$4/$P$4)/(D10/D$4)*100 -> 100.16156 | T10: =(L10/$P10)/(L$4/$P$4)/(E10/E$4)*100 -> 95.906577 | U10: =(M10/$P10)/(M$4/$P$4)/(F10/F$4)*100 -> 103.09225 | V10: =(N10/$P10)/(N$4/$P$4)/(G10/G$4)*100 -> 111.0678 | W10: =(O10/$P10)/(O$4/$P$4)/(H10/H$4)*100 -> 98.949381 | X10: =-(LN(Q10)-LN(AVERAGE(Q$4:Q10))) -> -0.04883651 | Y10: =-(LN(R10)-LN(AVERAGE(R$4:R10))) -> -0.00011107157 | Z10: =-(LN(S10)-LN(AVERAGE(S$4:S10))) -> -0.013065501 | AA10: =-(LN(T10)-LN(AVERAGE(T$4:T10))) -> -0.010411771 | AB10: =-(LN(U10)-LN(AVERAGE(U$4:U10))) -> -0.056407518 | AC10: =-(LN(V10)-LN(AVERAGE(V$4:V10))) -> -0.044453551 | AD10: =-(LN(W10)-LN(AVERAGE(W$4:W10))) -> 0.027952415 | AE10: =LN(B9/B10) -> 0.051669481 | AF10: =LN(C9/C10) -> 0.032586914 | AG10: =LN(D9/D10) -> -0.057163182 | AH10: =LN(E9/E10) -> 0.049040712 | AI10: =LN(F9/F10) -> 0.023780906 | AJ10: =LN(G9/G10) -> -0.0097598945 | AK10: =LN(H9/H10) -> -0.0067080539
A11: 38230 | B11: 2.8835 | C11: 10.9373 | D11: 647.7642 | E11: 2598.7366 | F11: 6.3668 | G11: 1.3334 | H11: 4.2852 | I11: 103.797 | J11: 103.147 | K11: 102.695 | L11: 102.847 | M11: 103.719 | N11: 109.495 | O11: 101.187 | P11: 101.793 | Q11: =(I11/$P11)/(I$4/$P$4)/(B11/B$4)*100 -> 108.64861 | R11: =(J11/$P11)/(J$4/$P$4)/(C11/C$4)*100 -> 100.80168 | S11: =(K11/$P11)/(K$4/$P$4)/(D11/D$4)*100 -> 101.55182 | T11: =(L11/$P11)/(L$4/$P$4)/(E11/E$4)*100 -> 88.192544 | U11: =(M11/$P11)/(M$4/$P$4)/(F11/F$4)*100 -> 98.928861 | V11: =(N11/$P11)/(N$4/$P$4)/(G11/G$4)*100 -> 111.08605 | W11: =(O11/$P11)/(O$4/$P$4)/(H11/H$4)*100 -> 94.29072 | X11: =-(LN(Q11)-LN(AVERAGE(Q$4:Q11))) -> -0.033111229 | Y11: =-(LN(R11)-LN(AVERAGE(R$4:R11))) -> -0.014720702 | Z11: =-(LN(S11)-LN(AVERAGE(S$4:S11))) -> -0.023454286 | AA11: =-(LN(T11)-LN(AVERAGE(T$4:T11))) -> 0.064549912 | AB11: =-(LN(U11)-LN(AVERAGE(U$4:U11))) -> -0.013273624 | AC11: =-(LN(V11)-LN(AVERAGE(V$4:V11))) -> -0.038930505 | AD11: =-(LN(W11)-LN(AVERAGE(W$4:W11))) -> 0.066967163 | AE11: =LN(B10/B11) -> -0.013863648 | AF11: =LN(C10/C11) -> 0.014567925 | AG11: =LN(D10/D11) -> 0.013177193 | AH11: =LN(E10/E11) -> -0.086124227 | AI11: =LN(F10/F11) -> -0.044186216 | AJ11: =LN(G10/G11) -> -0.011692511 | AK11: =LN(H10/H11) -> -0.048237251
A12: 38260 | B12: 2.9407 | C12: 10.0125 | D12: 670.2438 | E12: 2502.9242 | F12: 6.3827 | G12: 1.3634 | H12: 4.2023 | I12: 104.299 | J12: 103.54 | K12: 102.777 | L12: 103.063 | M12: 104.261 | N12: 110.663 | O12: 101.559 | P12: 102.073 | Q12: =(I12/$P12)/(I$4/$P$4)/(B12/B$4)*100 -> 106.75686 | R12: =(J12/$P12)/(J$4/$P$4)/(C12/C$4)*100 -> 110.22851 | S12: =(K12/$P12)/(K$4/$P$4)/(D12/D$4)*100 -> 97.954757 | T12: =(L12/$P12)/(L$4/$P$4)/(E12/E$4)*100 -> 91.509171 | U12: =(M12/$P12)/(M$4/$P$4)/(F12/F$4)*100 -> 98.925985 | V12: =(N12/$P12)/(N$4/$P$4)/(G12/G$4)*100 -> 109.49943 | W12: =(O12/$P12)/(O$4/$P$4)/(H12/H$4)*100 -> 96.239581 | X12: =-(LN(Q12)-LN(AVERAGE(Q$4:Q12))) -> -0.013806876 | Y12: =-(LN(R12)-LN(AVERAGE(R$4:R12))) -> -0.092002256 | Z12: =-(LN(S12)-LN(AVERAGE(S$4:S12))) -> 0.01121604 | AA12: =-(LN(T12)-LN(AVERAGE(T$4:T12))) -> 0.024600226 | AB12: =-(LN(U12)-LN(AVERAGE(U$4:U12))) -> -0.011764245 | AC12: =-(LN(V12)-LN(AVERAGE(V$4:V12))) -> -0.021787618 | AD12: =-(LN(W12)-LN(AVERAGE(W$4:W12))) -> 0.041447065 | AE12: =LN(B11/B12) -> -0.019642814 | AF12: =LN(C11/C12) -> 0.088344653 | AG12: =LN(D11/D12) -> -0.034114786 | AH12: =LN(E11/E12) -> 0.037565676 | AI12: =LN(F11/F12) -> -0.0024942168 | AJ12: =LN(G11/G12) -> -0.022249509 | AK12: =LN(H11/H12) -> 0.019535231
A13: 38291 | B13: 3.0247 | C13: 9.7433 | D13: 696.5507 | E13: 2560.383 | F13: 6.8653 | G13: 1.3729 | H13: 3.808 | I13: 104.802 | J13: 104.146 | K13: 103.052 | L13: 103.424 | M13: 105.036 | N13: 111.918 | O13: 101.823 | P13: 102.089 | Q13: =(I13/$P13)/(I$4/$P$4)/(B13/B$4)*100 -> 104.27628 | R13: =(J13/$P13)/(J$4/$P$4)/(C13/C$4)*100 -> 113.91916 | S13: =(K13/$P13)/(K$4/$P$4)/(D13/D$4)*100 -> 94.492649 | T13: =(L13/$P13)/(L$4/$P$4)/(E13/E$4)*100 -> 89.754837 | U13: =(M13/$P13)/(M$4/$P$4)/(F13/F$4)*100 -> 92.641059 | V13: =(N13/$P13)/(N$4/$P$4)/(G13/G$4)*100 -> 109.95771 | W13: =(O13/$P13)/(O$4/$P$4)/(H13/H$4)*100 -> 106.46411 | X13: =-(LN(Q13)-LN(AVERAGE(Q$4:Q13))) -> 0.0087369671 | Y13: =-(LN(R13)-LN(AVERAGE(R$4:R13))) -> -0.11171592 | Z13: =-(LN(S13)-LN(AVERAGE(S$4:S13))) -> 0.042578739 | AA13: =-(LN(T13)-LN(AVERAGE(T$4:T13))) -> 0.03964769 | AB13: =-(LN(U13)-LN(AVERAGE(U$4:U13))) -> 0.048616476 | AC13: =-(LN(V13)-LN(AVERAGE(V$4:V13))) -> -0.023337127 | AD13: =-(LN(W13)-LN(AVERAGE(W$4:W13))) -> -0.053406187 | AE13: =LN(B12/B13) -> -0.028164265 | AF13: =LN(C12/C13) -> 0.027254443 | AG13: =LN(D12/D13) -> -0.038499056 | AH13: =LN(E12/E13) -> -0.022697128 | AI13: =LN(F12/F13) -> -0.072888533 | AJ13: =LN(G12/G13) -> -0.006943711 | AK13: =LN(H12/H13) -> 0.098527878
A14: 38321 | B14: 3.2031 | C14: 9.7711 | D14: 721.6297 | E14: 2558.9509 | F14: 7.1808 | G14: 1.444 | H14: 3.9158 | I14: 105.441 | J14: 104.543 | K14: 103.229 | L14: 103.821 | M14: 105.481 | N14: 112.911 | O14: 102.097 | P14: 102.453 | Q14: =(I14/$P14)/(I$4/$P$4)/(B14/B$4)*100 -> 98.716913 | R14: =(J14/$P14)/(J$4/$P$4)/(C14/C$4)*100 -> 113.62294 | S14: =(K14/$P14)/(K$4/$P$4)/(D14/D$4)*100 -> 91.04077 | T14: =(L14/$P14)/(L$4/$P$4)/(E14/E$4)*100 -> 89.829502 | U14: =(M14/$P14)/(M$4/$P$4)/(F14/F$4)*100 -> 88.629956 | V14: =(N14/$P14)/(N$4/$P$4)/(G14/G$4)*100 -> 105.09643 | W14: =(O14/$P14)/(O$4/$P$4)/(H14/H$4)*100 -> 103.44298 | X14: =-(LN(Q14)-LN(AVERAGE(Q$4:Q14))) -> 0.057913546 | Y14: =-(LN(R14)-LN(AVERAGE(R$4:R14))) -> -0.098686126 | Z14: =-(LN(S14)-LN(AVERAGE(S$4:S14))) -> 0.072796854 | AA14: =-(LN(T14)-LN(AVERAGE(T$4:T14))) -> 0.035349022 | AB14: =-(LN(U14)-LN(AVERAGE(U$4:U14))) -> 0.084783037 | AC14: =-(LN(V14)-LN(AVERAGE(V$4:V14))) -> 0.019910902 | AD14: =-(LN(W14)-LN(AVERAGE(W$4:W14))) -> -0.022355521 | AE14: =LN(B13/B14) -> -0.057307178 | AF14: =LN(C13/C14) -> -0.00284918 | AG14: =LN(D13/D14) -> -0.035371543 | AH14: =LN(E13/E14) -> 0.00055948687 | AI14: =LN(F13/F14) -> -0.044931059 | AJ14: =LN(G13/G14) -> -0.05049175 | AK14: =LN(H13/H14) -> -0.027915534
A15: 38352 | B15: 3.257 | C15: 9.4961 | D15: 734.8981 | E15: 2522.2839 | F15: 6.9257 | G15: 1.4896 | H15: 3.8287 | I15: 105.716 | J15: 105.121 | K15: 103.59 | L15: 104.374 | M15: 105.747 | N15: 114.123 | O15: 102.366 | P15: 102.648 | Q15: =(I15/$P15)/(I$4/$P$4)/(B15/B$4)*100 -> 97.151542 | R15: =(J15/$P15)/(J$4/$P$4)/(C15/C$4)*100 -> 117.33644 | S15: =(K15/$P15)/(K$4/$P$4)/(D15/D$4)*100 -> 89.539259 | T15: =(L15/$P15)/(L$4/$P$4)/(E15/E$4)*100 -> 91.446752 | U15: =(M15/$P15)/(M$4/$P$4)/(F15/F$4)*100 -> 91.951262 | V15: =(N15/$P15)/(N$4/$P$4)/(G15/G$4)*100 -> 102.77716 | W15: =(O15/$P15)/(O$4/$P$4)/(H15/H$4)*100 -> 105.87347 | X15: =-(LN(Q15)-LN(AVERAGE(Q$4:Q15))) -> 0.067943982 | Y15: =-(LN(R15)-LN(AVERAGE(R$4:R15))) -> -0.11926405 | Z15: =-(LN(S15)-LN(AVERAGE(S$4:S15))) -> 0.082272814 | AA15: =-(LN(T15)-LN(AVERAGE(T$4:T15))) -> 0.016058462 | AB15: =-(LN(U15)-LN(AVERAGE(U$4:U15))) -> 0.044081559 | AC15: =-(LN(V15)-LN(AVERAGE(V$4:V15))) -> 0.038774545 | AD15: =-(LN(W15)-LN(AVERAGE(W$4:W15))) -> -0.04170097 | AE15: =LN(B14/B15) -> -0.016687435 | AF15: =LN(C14/C15) -> 0.028547861 | AG15: =LN(D14/D15) -> -0.018219724 | AH15: =LN(E14/E15) -> 0.014432569 | AI15: =LN(F14/F15) -> 0.036171667 | AJ15: =LN(G14/G15) -> -0.031090587 | AK15: =LN(H14/H15) -> 0.022494331
A16: 38383 | B16: 3.2791 | C16: 9.4543 | D16: 738.3999 | E16: 2523.1447 | F16: 7.0499 | G16: 1.5443 | H16: 3.9762 | I16: 106.144 | J16: 105.535 | K16: 103.852 | L16: 104.893 | M16: 105.933 | N16: 115.24 | O16: 102.607 | P16: 102.923 | Q16: =(I16/$P16)/(I$4/$P$4)/(B16/B$4)*100 -> 96.628576 | R16: =(J16/$P16)/(J$4/$P$4)/(C16/C$4)*100 -> 118.00323 | S16: =(K16/$P16)/(K$4/$P$4)/(D16/D$4)*100 -> 89.101308 | T16: =(L16/$P16)/(L$4/$P$4)/(E16/E$4)*100 -> 91.62465 | U16: =(M16/$P16)/(M$4/$P$4)/(F16/F$4)*100 -> 90.248436 | V16: =(N16/$P16)/(N$4/$P$4)/(G16/G$4)*100 -> 99.839578 | W16: =(O16/$P16)/(O$4/$P$4)/(H16/H$4)*100 -> 101.913 | X16: =-(LN(Q16)-LN(AVERAGE(Q$4:Q16))) -> 0.06788693 | Y16: =-(LN(R16)-LN(AVERAGE(R$4:R16))) -> -0.11474657 | Z16: =-(LN(S16)-LN(AVERAGE(S$4:S16))) -> 0.080733408 | AA16: =-(LN(T16)-LN(AVERAGE(T$4:T16))) -> 0.013036255 | AB16: =-(LN(U16)-LN(AVERAGE(U$4:U16))) -> 0.058082652 | AC16: =-(LN(V16)-LN(AVERAGE(V$4:V16))) -> 0.062719711 | AD16: =-(LN(W16)-LN(AVERAGE(W$4:W16))) -> -0.0033002418 | AE16: =LN(B15/B16) -> -0.0067624682 | AF16: =LN(C15/C16) -> 0.0044115235 | AG16: =LN(D15/D16) -> -0.0047536976 | AH16: =LN(E15/E16) -> -0.00034121978 | AI16: =LN(F15/F16) -> -0.017774302 | AJ16: =LN(G15/G16) -> -0.036063106 | AK16: =LN(H15/H16) -> -0.037801269
... A276: 46295 | B276: 5.6154 | C276: 18.5313 | D276: 616.6608 | E276: 4850.8656 | F276: 11.6312 | G276: 14.7348 | H276: 5.0772 | I276: 335.878 | J276: 258.586 | K276: 204.864 | L276: 297.689 | M276: 325.903 | N276: 1908.363 | O276: 196.186 | P276: 173.73 | Q276: =(I276/$P276)/(I$4/$P$4)/(B276/B$4)*100 -> 105.77993 | R276: =(J276/$P276)/(J$4/$P$4)/(C276/C$4)*100 -> 87.390352 | S276: =(K276/$P276)/(K$4/$P$4)/(D276/D$4)*100 -> 124.68602 | T276: =(L276/$P276)/(L$4/$P$4)/(E276/E$4)*100 -> 80.128893 | U276: =(M276/$P276)/(M$4/$P$4)/(F276/F$4)*100 -> 99.699464 | V276: =(N276/$P276)/(N$4/$P$4)/(G276/G$4)*100 -> 102.65628 | W276: =(O276/$P276)/(O$4/$P$4)/(H276/H$4)*100 -> 90.407022 | X276: =-(LN(Q276)-LN(AVERAGE(Q$4:Q276))) -> 0.039396313 | Y276: =-(LN(R276)-LN(AVERAGE(R$4:R276))) -> 0.12502047 | Z276: =-(LN(S276)-LN(AVERAGE(S$4:S276))) -> -0.099500725 | AA276: =-(LN(T276)-LN(AVERAGE(T$4:T276))) -> 0.15889029 | AB276: =-(LN(U276)-LN(AVERAGE(U$4:U276))) -> 0.01156223 | AC276: =-(LN(V276)-LN(AVERAGE(V$4:V276))) -> -0.020444761 | AD276: =-(LN(W276)-LN(AVERAGE(W$4:W276))) -> 0.18777428 | AE276: =LN(B275/B276) -> -0.034071051 | AF276: =LN(C275/C276) -> 0.061705515 | AG276: =LN(D275/D276) -> 0.053266444 | AH276: =LN(E275/E276) -> -0.0044929689 | AI276: =LN(F275/F276) -> 0.039373804 | AJ276: =LN(G275/G276) -> 0.020035742 | AK276: =LN(H275/H276) -> -0.016262458
A278: Synthetic placeholder data. Replace the yellow blocks with BDH pulls from Tickers. Formula columns update automatically.
A279: Placeholder spot is generated from a mean-reverting real exchange rate, which is the premise the signal rests on. Real data will not be this well behaved.

Sheet Rates_Data
A1: Rates Data
A2: Signal: adjusted real short rate = 3-month rate less expected inflation 12 months ahead, then measured against each market's OWN expanding mean. Higher = cheaper. Return approximated as minus duration times the change in the 2-year yield. Yellow = paste BDH here. | B2: 3-month rate, % — INPUT | I2: Expected inflation 12m ahead, % — INPUT | P2: 2-year government yield, % — INPUT | W2: Real short rate, % | AD2: Valuation: cheapness vs own history | AK2: Monthly return to a long position
A3: Date | B3: US | C3: DE | D3: GB | E3: CA | F3: AU | G3: JP | H3: NZ | I3: US | J3: DE | K3: GB | L3: CA | M3: AU | N3: JP | O3: NZ | P3: US | Q3: DE | R3: GB | S3: CA | T3: AU | U3: JP | V3: NZ | W3: US | X3: DE | Y3: GB | Z3: CA | AA3: AU | AB3: JP | AC3: NZ | AD3: US | AE3: DE | AF3: GB | AG3: CA | AH3: AU | AI3: JP | AJ3: NZ | AK3: US | AL3: DE | AM3: GB | AN3: CA | AO3: AU | AP3: JP | AQ3: NZ
A4: 38017 | B4: 2.48 | C4: 1.673 | D4: 2.773 | E4: 2.018 | F4: 3.365 | G4: 0.297 | H4: 4.049 | I4: 2.035 | J4: 1.699 | K4: 2.134 | L4: 1.834 | M4: 2.5 | N4: 0.297 | O4: 2.173 | P4: 2.69 | Q4: 1.962 | R4: 2.965 | S4: 2.332 | T4: 3.465 | U4: 0.586 | V4: 4.346 | W4: =B4-I4 -> 0.445 | X4: =C4-J4 -> -0.026 | Y4: =D4-K4 -> 0.639 | Z4: =E4-L4 -> 0.184 | AA4: =F4-M4 -> 0.865 | AB4: =G4-N4 -> 0 | AC4: =H4-O4 -> 1.876 | AD4: =w4-AVERAGE(W$4:W4) -> 1.555 | AE4: =X4-AVERAGE(X$4:X4) -> 0 | AF4: =Y4-AVERAGE(Y$4:Y4) -> 0 | AG4: =z4-AVERAGE(Z$4:Z4) -> 3.816 | AH4: =AA4-AVERAGE(AA$4:AA4) -> 0 | AI4: =AB4-AVERAGE(AB$4:AB4) -> 0 | AJ4: =AC4-AVERAGE(AC$4:AC4) -> 0
A5: 38046 | B5: 2.681 | C5: 1.838 | D5: 2.56 | E5: 2.007 | F5: 3.545 | G5: -0.05 | H5: 4.035 | I5: 2.143 | J5: 1.835 | K5: 2.18 | L5: 1.929 | M5: 2.434 | N5: 0.293 | O5: 2.082 | P5: 2.834 | Q5: 2.255 | R5: 2.807 | S5: 2.399 | T5: 3.846 | U5: 0.163 | V5: 4.348 | W5: =B5-I5 -> 0.538 | X5: =C5-J5 -> 0.003 | Y5: =D5-K5 -> 0.38 | Z5: =E5-L5 -> 0.078 | AA5: =F5-M5 -> 1.111 | AB5: =G5-N5 -> -0.343 | AC5: =H5-O5 -> 1.953 | AD5: =W5-AVERAGE(W$4:W5) -> 0.0465 | AE5: =X5-AVERAGE(X$4:X5) -> 0.0145 | AF5: =Y5-AVERAGE(Y$4:Y5) -> -0.1295 | AG5: =Z5-AVERAGE(Z$4:Z5) -> -0.053 | AH5: =AA5-AVERAGE(AA$4:AA5) -> 0.123 | AI5: =AB5-AVERAGE(AB$4:AB5) -> -0.1715 | AJ5: =AC5-AVERAGE(AC$4:AC5) -> 0.0385 | AK5: =-RateDur*(P5-P4)/100 -> -0.002736 | AL5: =-RateDur*(Q5-Q4)/100 -> -0.005567 | AM5: =-RateDur*(R5-R4)/100 -> 0.003002 | AN5: =-RateDur*(S5-S4)/100 -> -0.001273 | AO5: =-RateDur*(T5-T4)/100 -> -0.007239 | AP5: =-RateDur*(U5-U4)/100 -> 0.008037 | AQ5: =-RateDur*(V5-V4)/100 -> -3.8e-05
A6: 38077 | B6: 2.99 | C6: 1.886 | D6: 2.694 | E6: 2.08 | F6: 3.451 | G6: -0.161 | H6: 4.202 | I6: 2.216 | J6: 1.801 | K6: 2.262 | L6: 2.015 | M6: 2.379 | N6: 0.311 | O6: 2.105 | P6: 3.093 | Q6: 2.016 | R6: 3.029 | S6: 2.441 | T6: 4.023 | U6: -0.034 | V6: 4.508 | W6: =B6-I6 -> 0.774 | X6: =C6-J6 -> 0.085 | Y6: =D6-K6 -> 0.432 | Z6: =E6-L6 -> 0.065 | AA6: =F6-M6 -> 1.072 | AB6: =G6-N6 -> -0.472 | AC6: =H6-O6 -> 2.097 | AD6: =W6-AVERAGE(W$4:W6) -> 0.18833333 | AE6: =X6-AVERAGE(X$4:X6) -> 0.064333333 | AF6: =Y6-AVERAGE(Y$4:Y6) -> -0.051666667 | AG6: =Z6-AVERAGE(Z$4:Z6) -> -0.044 | AH6: =AA6-AVERAGE(AA$4:AA6) -> 0.056 | AI6: =AB6-AVERAGE(AB$4:AB6) -> -0.20033333 | AJ6: =AC6-AVERAGE(AC$4:AC6) -> 0.12166667 | AK6: =-RateDur*(P6-P5)/100 -> -0.004921 | AL6: =-RateDur*(Q6-Q5)/100 -> 0.004541 | AM6: =-RateDur*(R6-R5)/100 -> -0.004218 | AN6: =-RateDur*(S6-S5)/100 -> -0.000798 | AO6: =-RateDur*(T6-T5)/100 -> -0.003363 | AP6: =-RateDur*(U6-U5)/100 -> 0.003743 | AQ6: =-RateDur*(V6-V5)/100 -> -0.00304
A7: 38107 | B7: 3.23 | C7: 2.025 | D7: 2.865 | E7: 2.349 | F7: 3.336 | G7: -0.181 | H7: 4.36 | I7: 2.107 | J7: 1.833 | K7: 2.339 | L7: 1.979 | M7: 2.277 | N7: 0.134 | O7: 2.152 | P7: 3.547 | Q7: 2.249 | R7: 3.109 | S7: 2.669 | T7: 3.53 | U7: 0.049 | V7: 4.599 | W7: =B7-I7 -> 1.123 | X7: =C7-J7 -> 0.192 | Y7: =D7-K7 -> 0.526 | Z7: =E7-L7 -> 0.37 | AA7: =F7-M7 -> 1.059 | AB7: =G7-N7 -> -0.315 | AC7: =H7-O7 -> 2.208 | AD7: =W7-AVERAGE(W$4:W7) -> 0.403 | AE7: =X7-AVERAGE(X$4:X7) -> 0.1285 | AF7: =Y7-AVERAGE(Y$4:Y7) -> 0.03175 | AG7: =Z7-AVERAGE(Z$4:Z7) -> 0.19575 | AH7: =AA7-AVERAGE(AA$4:AA7) -> 0.03225 | AI7: =AB7-AVERAGE(AB$4:AB7) -> -0.0325 | AJ7: =AC7-AVERAGE(AC$4:AC7) -> 0.1745 | AK7: =-RateDur*(P7-P6)/100 -> -0.008626 | AL7: =-RateDur*(Q7-Q6)/100 -> -0.004427 | AM7: =-RateDur*(R7-R6)/100 -> -0.00152 | AN7: =-RateDur*(S7-S6)/100 -> -0.004332 | AO7: =-RateDur*(T7-T6)/100 -> 0.009367 | AP7: =-RateDur*(U7-U6)/100 -> -0.001577 | AQ7: =-RateDur*(V7-V6)/100 -> -0.001729
A8: 38138 | B8: 2.954 | C8: 1.983 | D8: 2.703 | E8: 2.658 | F8: 3.164 | G8: -0.274 | H8: 4.04 | I8: 1.983 | J8: 1.818 | K8: 2.262 | L8: 2.026 | M8: 2.364 | N8: 0.265 | O8: 2.096 | P8: 3.289 | Q8: 1.974 | R8: 3.033 | S8: 2.873 | T8: 3.454 | U8: -0.004 | V8: 4.215 | W8: =B8-I8 -> 0.971 | X8: =C8-J8 -> 0.165 | Y8: =D8-K8 -> 0.441 | Z8: =E8-L8 -> 0.632 | AA8: =F8-M8 -> 0.8 | AB8: =G8-N8 -> -0.539 | AC8: =H8-O8 -> 1.944 | AD8: =W8-AVERAGE(W$4:W8) -> 0.2008 | AE8: =X8-AVERAGE(X$4:X8) -> 0.0812 | AF8: =Y8-AVERAGE(Y$4:Y8) -> -0.0426 | AG8: =Z8-AVERAGE(Z$4:Z8) -> 0.3662 | AH8: =AA8-AVERAGE(AA$4:AA8) -> -0.1814 | AI8: =AB8-AVERAGE(AB$4:AB8) -> -0.2052 | AJ8: =AC8-AVERAGE(AC$4:AC8) -> -0.0716 | AK8: =-RateDur*(P8-P7)/100 -> 0.004902 | AL8: =-RateDur*(Q8-Q7)/100 -> 0.005225 | AM8: =-RateDur*(R8-R7)/100 -> 0.001444 | AN8: =-RateDur*(S8-S7)/100 -> -0.003876 | AO8: =-RateDur*(T8-T7)/100 -> 0.001444 | AP8: =-RateDur*(U8-U7)/100 -> 0.001007 | AQ8: =-RateDur*(V8-V7)/100 -> 0.007296
A9: 38168 | B9: 2.965 | C9: 1.962 | D9: 2.59 | E9: 2.669 | F9: 2.972 | G9: -0.142 | H9: 4.152 | I9: 1.985 | J9: 1.836 | K9: 2.19 | L9: 2.186 | M9: 2.493 | N9: 0.064 | O9: 2.197 | P9: 3.234 | Q9: 2.202 | R9: 2.756 | S9: 2.888 | T9: 3.195 | U9: 0.065 | V9: 4.405 | W9: =B9-I9 -> 0.98 | X9: =C9-J9 -> 0.126 | Y9: =D9-K9 -> 0.4 | Z9: =E9-L9 -> 0.483 | AA9: =F9-M9 -> 0.479 | AB9: =G9-N9 -> -0.206 | AC9: =H9-O9 -> 1.955 | AD9: =W9-AVERAGE(W$4:W9) -> 0.17483333 | AE9: =X9-AVERAGE(X$4:X9) -> 0.035166667 | AF9: =Y9-AVERAGE(Y$4:Y9) -> -0.069666667 | AG9: =Z9-AVERAGE(Z$4:Z9) -> 0.181 | AH9: =AA9-AVERAGE(AA$4:AA9) -> -0.41866667 | AI9: =AB9-AVERAGE(AB$4:AB9) -> 0.1065 | AJ9: =AC9-AVERAGE(AC$4:AC9) -> -0.0505 | AK9: =-RateDur*(P9-P8)/100 -> 0.001045 | AL9: =-RateDur*(Q9-Q8)/100 -> -0.004332 | AM9: =-RateDur*(R9-R8)/100 -> 0.005263 | AN9: =-RateDur*(S9-S8)/100 -> -0.000285 | AO9: =-RateDur*(T9-T8)/100 -> 0.004921 | AP9: =-RateDur*(U9-U8)/100 -> -0.001311 | AQ9: =-RateDur*(V9-V8)/100 -> -0.00361
A10: 38199 | B10: 2.887 | C10: 1.77 | D10: 2.54 | E10: 2.53 | F10: 2.774 | G10: -0.32 | H10: 4.295 | I10: 1.974 | J10: 1.833 | K10: 2.208 | L10: 2.239 | M10: 2.567 | N10: 0.169 | O10: 2.031 | P10: 3.031 | Q10: 2.071 | R10: 2.765 | S10: 2.752 | T10: 3.086 | U10: 0.026 | V10: 4.575 | W10: =B10-I10 -> 0.913 | X10: =C10-J10 -> -0.063 | Y10: =D10-K10 -> 0.332 | Z10: =E10-L10 -> 0.291 | AA10: =F10-M10 -> 0.207 | AB10: =G10-N10 -> -0.489 | AC10: =H10-O10 -> 2.264 | AD10: =W10-AVERAGE(W$4:W10) -> 0.092428571 | AE10: =X10-AVERAGE(X$4:X10) -> -0.13185714 | AF10: =Y10-AVERAGE(Y$4:Y10) -> -0.118 | AG10: =Z10-AVERAGE(Z$4:Z10) -> -0.0094285714 | AH10: =AA10-AVERAGE(AA$4:AA10) -> -0.592 | AI10: =AB10-AVERAGE(AB$4:AB10) -> -0.15128571 | AJ10: =AC10-AVERAGE(AC$4:AC10) -> 0.22157143 | AK10: =-RateDur*(P10-P9)/100 -> 0.003857 | AL10: =-RateDur*(Q10-Q9)/100 -> 0.002489 | AM10: =-RateDur*(R10-R9)/100 -> -0.000171 | AN10: =-RateDur*(S10-S9)/100 -> 0.002584 | AO10: =-RateDur*(T10-T9)/100 -> 0.002071 | AP10: =-RateDur*(U10-U9)/100 -> 0.000741 | AQ10: =-RateDur*(V10-V9)/100 -> -0.00323
A11: 38230 | B11: 2.93 | C11: 2.087 | D11: 2.351 | E11: 2.242 | F11: 2.642 | G11: -0.267 | H11: 4.058 | I11: 1.983 | J11: 1.902 | K11: 2.247 | L11: 2.113 | M11: 2.48 | N11: 0.188 | O11: 2.108 | P11: 3.156 | Q11: 2.399 | R11: 2.372 | S11: 2.503 | T11: 2.872 | U11: -0.007 | V11: 4.437 | W11: =B11-I11 -> 0.947 | X11: =C11-J11 -> 0.185 | Y11: =D11-K11 -> 0.104 | Z11: =E11-L11 -> 0.129 | AA11: =F11-M11 -> 0.162 | AB11: =G11-N11 -> -0.455 | AC11: =H11-O11 -> 1.95 | AD11: =W11-AVERAGE(W$4:W11) -> 0.110625 | AE11: =X11-AVERAGE(X$4:X11) -> 0.101625 | AF11: =Y11-AVERAGE(Y$4:Y11) -> -0.30275 | AG11: =Z11-AVERAGE(Z$4:Z11) -> -0.15 | AH11: =AA11-AVERAGE(AA$4:AA11) -> -0.557375 | AI11: =AB11-AVERAGE(AB$4:AB11) -> -0.102625 | AJ11: =AC11-AVERAGE(AC$4:AC11) -> -0.080875 | AK11: =-RateDur*(P11-P10)/100 -> -0.002375 | AL11: =-RateDur*(Q11-Q10)/100 -> -0.006232 | AM11: =-RateDur*(R11-R10)/100 -> 0.007467 | AN11: =-RateDur*(S11-S10)/100 -> 0.004731 | AO11: =-RateDur*(T11-T10)/100 -> 0.004066 | AP11: =-RateDur*(U11-U10)/100 -> 0.000627 | AQ11: =-RateDur*(V11-V10)/100 -> 0.002622
A12: 38260 | B12: 2.777 | C12: 2.059 | D12: 2.298 | E12: 2.139 | F12: 2.579 | G12: -0.248 | H12: 4.234 | I12: 1.971 | J12: 1.796 | K12: 2.319 | L12: 2.211 | M12: 2.517 | N12: 0.239 | O12: 2.172 | P12: 2.876 | Q12: 2.264 | R12: 2.575 | S12: 2.337 | T12: 2.853 | U12: 0.059 | V12: 4.601 | W12: =B12-I12 -> 0.806 | X12: =C12-J12 -> 0.263 | Y12: =D12-K12 -> -0.021 | Z12: =E12-L12 -> -0.072 | AA12: =F12-M12 -> 0.062 | AB12: =G12-N12 -> -0.487 | AC12: =H12-O12 -> 2.062 | AD12: =W12-AVERAGE(W$4:W12) -> -0.027 | AE12: =X12-AVERAGE(X$4:X12) -> 0.15966667 | AF12: =Y12-AVERAGE(Y$4:Y12) -> -0.38022222 | AG12: =Z12-AVERAGE(Z$4:Z12) -> -0.312 | AH12: =AA12-AVERAGE(AA$4:AA12) -> -0.58433333 | AI12: =AB12-AVERAGE(AB$4:AB12) -> -0.11966667 | AJ12: =AC12-AVERAGE(AC$4:AC12) -> 0.027666667 | AK12: =-RateDur*(P12-P11)/100 -> 0.00532 | AL12: =-RateDur*(Q12-Q11)/100 -> 0.002565 | AM12: =-RateDur*(R12-R11)/100 -> -0.003857 | AN12: =-RateDur*(S12-S11)/100 -> 0.003154 | AO12: =-RateDur*(T12-T11)/100 -> 0.000361 | AP12: =-RateDur*(U12-U11)/100 -> -0.001254 | AQ12: =-RateDur*(V12-V11)/100 -> -0.003116
A13: 38291 | B13: 2.678 | C13: 1.807 | D13: 2.512 | E13: 1.913 | F13: 2.432 | G13: -0.248 | H13: 4.511 | I13: 1.91 | J13: 1.785 | K13: 2.318 | L13: 2.144 | M13: 2.435 | N13: 0.192 | O13: 2.14 | P13: 3.056 | Q13: 2.167 | R13: 2.82 | S13: 2.047 | T13: 2.652 | U13: 0.162 | V13: 4.923 | W13: =B13-I13 -> 0.768 | X13: =C13-J13 -> 0.022 | Y13: =D13-K13 -> 0.194 | Z13: =E13-L13 -> -0.231 | AA13: =F13-M13 -> -0.003 | AB13: =G13-N13 -> -0.44 | AC13: =H13-O13 -> 2.371 | AD13: =W13-AVERAGE(W$4:W13) -> -0.0585 | AE13: =X13-AVERAGE(X$4:X13) -> -0.0732 | AF13: =Y13-AVERAGE(Y$4:Y13) -> -0.1487 | AG13: =Z13-AVERAGE(Z$4:Z13) -> -0.4239 | AH13: =AA13-AVERAGE(AA$4:AA13) -> -0.5844 | AI13: =AB13-AVERAGE(AB$4:AB13) -> -0.0654 | AJ13: =AC13-AVERAGE(AC$4:AC13) -> 0.303 | AK13: =-RateDur*(P13-P12)/100 -> -0.00342 | AL13: =-RateDur*(Q13-Q12)/100 -> 0.001843 | AM13: =-RateDur*(R13-R12)/100 -> -0.004655 | AN13: =-RateDur*(S13-S12)/100 -> 0.00551 | AO13: =-RateDur*(T13-T12)/100 -> 0.003819 | AP13: =-RateDur*(U13-U12)/100 -> -0.001957 | AQ13: =-RateDur*(V13-V12)/100 -> -0.006118
A14: 38321 | B14: 2.48 | C14: 1.991 | D14: 2.508 | E14: 2.145 | F14: 2.724 | G14: -0.294 | H14: 4.408 | I14: 1.89 | J14: 1.846 | K14: 2.279 | L14: 2.08 | M14: 2.39 | N14: 0.147 | O14: 2.052 | P14: 2.732 | Q14: 2.245 | R14: 2.794 | S14: 2.557 | T14: 3.029 | U14: 0.186 | V14: 4.724 | W14: =B14-I14 -> 0.59 | X14: =C14-J14 -> 0.145 | Y14: =D14-K14 -> 0.229 | Z14: =E14-L14 -> 0.065 | AA14: =F14-M14 -> 0.334 | AB14: =G14-N14 -> -0.441 | AC14: =H14-O14 -> 2.356 | AD14: =W14-AVERAGE(W$4:W14) -> -0.215 | AE14: =X14-AVERAGE(X$4:X14) -> 0.045272727 | AF14: =Y14-AVERAGE(Y$4:Y14) -> -0.10336364 | AG14: =Z14-AVERAGE(Z$4:Z14) -> -0.11627273 | AH14: =AA14-AVERAGE(AA$4:AA14) -> -0.22490909 | AI14: =AB14-AVERAGE(AB$4:AB14) -> -0.060363636 | AJ14: =AC14-AVERAGE(AC$4:AC14) -> 0.26181818 | AK14: =-RateDur*(P14-P13)/100 -> 0.006156 | AL14: =-RateDur*(Q14-Q13)/100 -> -0.001482 | AM14: =-RateDur*(R14-R13)/100 -> 0.000494 | AN14: =-RateDur*(S14-S13)/100 -> -0.00969 | AO14: =-RateDur*(T14-T13)/100 -> -0.007163 | AP14: =-RateDur*(U14-U13)/100 -> -0.000456 | AQ14: =-RateDur*(V14-V13)/100 -> 0.003781
A15: 38352 | B15: 2.592 | C15: 2.15 | D15: 2.664 | E15: 2.255 | F15: 2.658 | G15: -0.245 | H15: 4.5 | I15: 1.935 | J15: 1.819 | K15: 2.131 | L15: 2.22 | M15: 2.424 | N15: 0.146 | O15: 2.088 | P15: 2.843 | Q15: 2.204 | R15: 2.828 | S15: 2.504 | T15: 2.845 | U15: -0.13 | V15: 4.693 | W15: =B15-I15 -> 0.657 | X15: =C15-J15 -> 0.331 | Y15: =D15-K15 -> 0.533 | Z15: =E15-L15 -> 0.035 | AA15: =F15-M15 -> 0.234 | AB15: =G15-N15 -> -0.391 | AC15: =H15-O15 -> 2.412 | AD15: =W15-AVERAGE(W$4:W15) -> -0.13566667 | AE15: =X15-AVERAGE(X$4:X15) -> 0.212 | AF15: =Y15-AVERAGE(Y$4:Y15) -> 0.18391667 | AG15: =Z15-AVERAGE(Z$4:Z15) -> -0.13408333 | AH15: =AA15-AVERAGE(AA$4:AA15) -> -0.29783333 | AI15: =AB15-AVERAGE(AB$4:AB15) -> -0.0095 | AJ15: =AC15-AVERAGE(AC$4:AC15) -> 0.29133333 | AK15: =-RateDur*(P15-P14)/100 -> -0.002109 | AL15: =-RateDur*(Q15-Q14)/100 -> 0.000779 | AM15: =-RateDur*(R15-R14)/100 -> -0.000646 | AN15: =-RateDur*(S15-S14)/100 -> 0.001007 | AO15: =-RateDur*(T15-T14)/100 -> 0.003496 | AP15: =-RateDur*(U15-U14)/100 -> 0.006004 | AQ15: =-RateDur*(V15-V14)/100 -> 0.000589
A16: 38383 | B16: 2.925 | C16: 2.15 | D16: 2.272 | E16: 2.405 | F16: 2.781 | G16: -0.392 | H16: 4.56 | I16: 1.944 | J16: 1.817 | K16: 2.065 | L16: 2.06 | M16: 2.362 | N16: 0.251 | O16: 2.084 | P16: 3.207 | Q16: 2.226 | R16: 2.386 | S16: 2.617 | T16: 2.95 | U16: -0.173 | V16: 5.063 | W16: =B16-I16 -> 0.981 | X16: =C16-J16 -> 0.333 | Y16: =D16-K16 -> 0.207 | Z16: =E16-L16 -> 0.345 | AA16: =F16-M16 -> 0.419 | AB16: =G16-N16 -> -0.643 | AC16: =H16-O16 -> 2.476 | AD16: =W16-AVERAGE(W$4:W16) -> 0.17384615 | AE16: =X16-AVERAGE(X$4:X16) -> 0.19753846 | AF16: =Y16-AVERAGE(Y$4:Y16) -> -0.13115385 | AG16: =Z16-AVERAGE(Z$4:Z16) -> 0.16238462 | AH16: =AA16-AVERAGE(AA$4:AA16) -> -0.10415385 | AI16: =AB16-AVERAGE(AB$4:AB16) -> -0.24138462 | AJ16: =AC16-AVERAGE(AC$4:AC16) -> 0.328 | AK16: =-RateDur*(P16-P15)/100 -> -0.006916 | AL16: =-RateDur*(Q16-Q15)/100 -> -0.000418 | AM16: =-RateDur*(R16-R15)/100 -> 0.008398 | AN16: =-RateDur*(S16-S15)/100 -> -0.002147 | AO16: =-RateDur*(T16-T15)/100 -> -0.001995 | AP16: =-RateDur*(U16-U15)/100 -> 0.000817 | AQ16: =-RateDur*(V16-V15)/100 -> -0.00703
... A276: 46295 | B276: 3.127 | C276: 2.17 | D276: 2.554 | E276: 2.202 | F276: 3.686 | G276: -0.428 | H276: 4.116 | I276: 1.884 | J276: 1.714 | K276: 2.264 | L276: 1.782 | M276: 2.772 | N276: 0.333 | O276: 2.365 | P276: 3.283 | Q276: 2.391 | R276: 2.7 | S276: 2.32 | T276: 3.91 | U276: -0.358 | V276: 4.376 | W276: =B276-I276 -> 1.243 | X276: =C276-J276 -> 0.456 | Y276: =D276-K276 -> 0.29 | Z276: =E276-L276 -> 0.42 | AA276: =F276-M276 -> 0.914 | AB276: =G276-N276 -> -0.761 | AC276: =H276-O276 -> 1.751 | AD276: =W276-AVERAGE(W$4:W276) -> 0.86494505 | AE276: =X276-AVERAGE(X$4:X276) -> 0.24174725 | AF276: =Y276-AVERAGE(Y$4:Y276) -> 0.13683516 | AG276: =Z276-AVERAGE(Z$4:Z276) -> 0.1169304 | AH276: =AA276-AVERAGE(AA$4:AA276) -> -0.13205128 | AI276: =AB276-AVERAGE(AB$4:AB276) -> -0.76060073 | AJ276: =AC276-AVERAGE(AC$4:AC276) -> 0.29982784 | AK276: =-RateDur*(P276-P275)/100 -> 0.000703 | AL276: =-RateDur*(Q276-Q275)/100 -> 0.001007 | AM276: =-RateDur*(R276-R275)/100 -> -0.002261 | AN276: =-RateDur*(S276-S275)/100 -> -0.009329 | AO276: =-RateDur*(T276-T275)/100 -> -0.001862 | AP276: =-RateDur*(U276-U275)/100 -> 0.012958 | AQ276: =-RateDur*(V276-V275)/100 -> -0.005263
A278: Synthetic placeholder data. Replace the yellow blocks with BDH pulls from Tickers. Formula columns update automatically.
A279: Note on the signal: the raw real-rate LEVEL across markets is largely a carry signal, because structural real-rate gaps between countries persist for decades.
A280: Measuring each market against its own expanding mean is what turns it into a value signal, which is what this framework is trying to harvest. Delete the AVERAGE term to run the raw-level version.

Sheet EMFX_Pairs
A1: EMFX Pairs
A2: One column per pair. Long the cheaper currency, short the richer, direction set by the previous month's valuation so there is no look-ahead. | B2: Valuation spread | W2: Expanding z-score | AR2: Risk multiplier (ladder) | BM2: Pair return (long cheap / short rich) | CH2: Trailing vol, annualised | DC2: Position | DX2: Weighted return | ES2: Sleeve
A3: Date | B3: BRL/MXN | C3: BRL/CLP | D3: BRL/COP | E3: BRL/ZAR | F3: BRL/TRY | G3: BRL/PLN | H3: MXN/CLP | I3: MXN/COP | J3: MXN/ZAR | K3: MXN/TRY | L3: MXN/PLN | M3: CLP/COP | N3: CLP/ZAR | O3: CLP/TRY | P3: CLP/PLN | Q3: COP/ZAR | R3: COP/TRY | S3: COP/PLN | T3: ZAR/TRY | U3: ZAR/PLN | V3: TRY/PLN | W3: BRL/MXN | X3: BRL/CLP | Y3: BRL/COP | Z3: BRL/ZAR | AA3: BRL/TRY | AB3: BRL/PLN | AC3: MXN/CLP | AD3: MXN/COP | AE3: MXN/ZAR | AF3: MXN/TRY | AG3: MXN/PLN | AH3: CLP/COP | AI3: CLP/ZAR | AJ3: CLP/TRY | AK3: CLP/PLN | AL3: COP/ZAR | AM3: COP/TRY | AN3: COP/PLN | AO3: ZAR/TRY | AP3: ZAR/PLN | AQ3: TRY/PLN | AR3: BRL/MXN | AS3: BRL/CLP | AT3: BRL/COP | AU3: BRL/ZAR | AV3: BRL/TRY | AW3: BRL/PLN | AX3: MXN/CLP | AY3: MXN/COP | AZ3: MXN/ZAR | BA3: MXN/TRY | BB3: MXN/PLN | BC3: CLP/COP | BD3: CLP/ZAR | BE3: CLP/TRY | BF3: CLP/PLN | BG3: COP/ZAR | BH3: COP/TRY | BI3: COP/PLN | BJ3: ZAR/TRY | BK3: ZAR/PLN | BL3: TRY/PLN | BM3: BRL/MXN | BN3: BRL/CLP | BO3: BRL/COP | BP3: BRL/ZAR | BQ3: BRL/TRY | BR3: BRL/PLN | BS3: MXN/CLP | BT3: MXN/COP | BU3: MXN/ZAR | BV3: MXN/TRY | BW3: MXN/PLN | BX3: CLP/COP | BY3: CLP/ZAR | BZ3: CLP/TRY | CA3: CLP/PLN | CB3: COP/ZAR | CC3: COP/TRY | CD3: COP/PLN | CE3: ZAR/TRY | CF3: ZAR/PLN | CG3: TRY/PLN | CH3: BRL/MXN | CI3: BRL/CLP | CJ3: BRL/COP | CK3: BRL/ZAR | CL3: BRL/TRY | CM3: BRL/PLN | CN3: MXN/CLP | CO3: MXN/COP | CP3: MXN/ZAR | CQ3: MXN/TRY | CR3: MXN/PLN | CS3: CLP/COP | CT3: CLP/ZAR | CU3: CLP/TRY | CV3: CLP/PLN | CW3: COP/ZAR | CX3: COP/TRY | CY3: COP/PLN | CZ3: ZAR/TRY | DA3: ZAR/PLN | DB3: TRY/PLN | DC3: BRL/MXN | DD3: BRL/CLP | DE3: BRL/COP | DF3: BRL/ZAR | DG3: BRL/TRY | DH3: BRL/PLN | DI3: MXN/CLP | DJ3: MXN/COP | DK3: MXN/ZAR | DL3: MXN/TRY | DM3: MXN/PLN | DN3: CLP/COP | DO3: CLP/ZAR | DP3: CLP/TRY | DQ3: CLP/PLN | DR3: COP/ZAR | DS3: COP/TRY | DT3: COP/PLN | DU3: ZAR/TRY | DV3: ZAR/PLN | DW3: TRY/PLN | DX3: BRL/MXN | DY3: BRL/CLP | DZ3: BRL/COP | EA3: BRL/ZAR | EB3: BRL/TRY | EC3: BRL/PLN | ED3: MXN/CLP | EE3: MXN/COP | EF3: MXN/ZAR | EG3: MXN/TRY | EH3: MXN/PLN | EI3: CLP/COP | EJ3: CLP/ZAR | EK3: CLP/TRY | EL3: CLP/PLN | EM3: COP/ZAR | EN3: COP/TRY | EO3: COP/PLN | EP3: ZAR/TRY | EQ3: ZAR/PLN | ER3: TRY/PLN | ES3: Gross ret | ET3: # included
A4: 38017 | B4: =ABS(EMFX_Data!X4-EMFX_Data!Y4) -> 0 | C4: =ABS(EMFX_Data!X4-EMFX_Data!Z4) -> 0 | D4: =ABS(EMFX_Data!X4-EMFX_Data!AA4) -> 0 | E4: =ABS(EMFX_Data!X4-EMFX_Data!AB4) -> 0 | F4: =ABS(EMFX_Data!X4-EMFX_Data!AC4) -> 0 | G4: =ABS(EMFX_Data!X4-EMFX_Data!AD4) -> 3.912023 | H4: =ABS(EMFX_Data!Y4-EMFX_Data!Z4) -> 0 | I4: =ABS(EMFX_Data!Y4-EMFX_Data!AA4) -> 0 | J4: =ABS(EMFX_Data!Y4-EMFX_Data!AB4) -> 0 | K4: =ABS(EMFX_Data!Y4-EMFX_Data!AC4) -> 0 | L4: =ABS(EMFX_Data!Y4-EMFX_Data!AD4) -> 3.912023 | M4: =ABS(EMFX_Data!Z4-EMFX_Data!AA4) -> 0 | N4: =ABS(EMFX_Data!Z4-EMFX_Data!AB4) -> 0 | O4: =ABS(EMFX_Data!Z4-EMFX_Data!AC4) -> 0 | P4: =ABS(EMFX_Data!Z4-EMFX_Data!AD4) -> 3.912023 | Q4: =ABS(EMFX_Data!AA4-EMFX_Data!AB4) -> 0 | R4: =ABS(EMFX_Data!AA4-EMFX_Data!AC4) -> 0 | S4: =ABS(EMFX_Data!AA4-EMFX_Data!AD4) -> 3.912023 | T4: =ABS(EMFX_Data!AB4-EMFX_Data!AC4) -> 0 | U4: =ABS(EMFX_Data!AB4-EMFX_Data!AD4) -> 3.912023 | V4: =ABS(EMFX_Data!AC4-EMFX_Data!AD4) -> 3.912023 | W4: =IF(ROW()<4+MinObs-1,"",IFERROR((B4-AVERAGE(B$4:B4))/STDEV(B$4:B4),"")) | X4: =IF(ROW()<4+MinObs-1,"",IFERROR((C4-AVERAGE(C$4:C4))/STDEV(C$4:C4),"")) | Y4: =IF(ROW()<4+MinObs-1,"",IFERROR((D4-AVERAGE(D$4:D4))/STDEV(D$4:D4),"")) | Z4: =IF(ROW()<4+MinObs-1,"",IFERROR((E4-AVERAGE(E$4:E4))/STDEV(E$4:E4),"")) | AA4: =IF(ROW()<4+MinObs-1,"",IFERROR((F4-AVERAGE(F$4:F4))/STDEV(F$4:F4),"")) | AB4: =IF(ROW()<4+MinObs-1,"",IFERROR((G4-AVERAGE(G$4:G4))/STDEV(G$4:G4),"")) | AC4: =IF(ROW()<4+MinObs-1,"",IFERROR((H4-AVERAGE(H$4:H4))/STDEV(H$4:H4),"")) | AD4: =IF(ROW()<4+MinObs-1,"",IFERROR((I4-AVERAGE(I$4:I4))/STDEV(I$4:I4),"")) | ... AQ4: =IF(ROW()<4+MinObs-1,"",IFERROR((V4-AVERAGE(V$4:V4))/STDEV(V$4:V4),"")) | AR4: =IF(w4="",0,IF(w4>=z4,w4,IF(w4>=z3,w3,IF(w4>=zEntry,w2,IF(AND(w4>=ExitZ,0>0),w2,0))))) -> 1 | AS4: =IF(X4="",0,IF(X4>=z4,w4,IF(X4>=z3,w3,IF(X4>=zEntry,w2,IF(AND(X4>=ExitZ,0>0),w2,0))))) -> 0 | AT4: =IF(Y4="",0,IF(Y4>=z4,w4,IF(Y4>=z3,w3,IF(Y4>=zEntry,w2,IF(AND(Y4>=ExitZ,0>0),w2,0))))) -> 0 | AU4: =IF(z4="",0,IF(z4>=z4,w4,IF(z4>=z3,w3,IF(z4>=zEntry,w2,IF(AND(z4>=ExitZ,0>0),w2,0))))) -> 2 | AV4: =IF(AA4="",0,IF(AA4>=z4,w4,IF(AA4>=z3,w3,IF(AA4>=zEntry,w2,IF(AND(AA4>=ExitZ,0>0),w2,0))))) -> 0 | AW4: =IF(AB4="",0,IF(AB4>=z4,w4,IF(AB4>=z3,w3,IF(AB4>=zEntry,w2,IF(AND(AB4>=ExitZ,0>0),w2,0))))) -> 0 | AX4: =IF(AC4="",0,IF(AC4>=z4,w4,IF(AC4>=z3,w3,IF(AC4>=zEntry,w2,IF(AND(AC4>=ExitZ,0>0),w2,0))))) -> 0 | AY4: =IF(AD4="",0,IF(AD4>=z4,w4,IF(AD4>=z3,w3,IF(AD4>=zEntry,w2,IF(AND(AD4>=ExitZ,0>0),w2,0))))) -> 0 | AZ4: =IF(AE4="",0,IF(AE4>=z4,w4,IF(AE4>=z3,w3,IF(AE4>=zEntry,w2,IF(AND(AE4>=ExitZ,0>0),w2,0))))) -> 0 | BA4: =IF(AF4="",0,IF(AF4>=z4,w4,IF(AF4>=z3,w3,IF(AF4>=zEntry,w2,IF(AND(AF4>=ExitZ,0>0),w2,0))))) -> 0 | BB4: =IF(AG4="",0,IF(AG4>=z4,w4,IF(AG4>=z3,w3,IF(AG4>=zEntry,w2,IF(AND(AG4>=ExitZ,0>0),w2,0))))) -> 0 | BC4: =IF(AH4="",0,IF(AH4>=z4,w4,IF(AH4>=z3,w3,IF(AH4>=zEntry,w2,IF(AND(AH4>=ExitZ,0>0),w2,0))))) -> 0 | ... BL4: =IF(AQ4="",0,IF(AQ4>=z4,w4,IF(AQ4>=z3,w3,IF(AQ4>=zEntry,w2,IF(AND(AQ4>=ExitZ,0>0),w2,0))))) -> 0 | DC4: =IF(OR(AR4=0,CH4="",CH4=0),0,AR4*MIN(MaxScal,TgtVol/CH4)) -> 0 | DD4: =IF(OR(AS4=0,CI4="",CI4=0),0,AS4*MIN(MaxScal,TgtVol/CI4)) -> 0 | DE4: =IF(OR(AT4=0,CJ4="",CJ4=0),0,AT4*MIN(MaxScal,TgtVol/CJ4)) -> 0 | DF4: =IF(OR(AU4=0,CK4="",CK4=0),0,AU4*MIN(MaxScal,TgtVol/CK4)) -> 0 | DG4: =IF(OR(AV4=0,CL4="",CL4=0),0,AV4*MIN(MaxScal,TgtVol/CL4)) -> 0 | DH4: =IF(OR(AW4=0,CM4="",CM4=0),0,AW4*MIN(MaxScal,TgtVol/CM4)) -> 0 | DI4: =IF(OR(AX4=0,CN4="",CN4=0),0,AX4*MIN(MaxScal,TgtVol/CN4)) -> 0 | DJ4: =IF(OR(AY4=0,CO4="",CO4=0),0,AY4*MIN(MaxScal,TgtVol/CO4)) -> 0 | ... DW4: =IF(OR(BL4=0,DB4="",DB4=0),0,BL4*MIN(MaxScal,TgtVol/DB4)) -> 0 | ES4: =IF(ROW()=4,"",SUM(DX4:ER4)) | ET4: =COUNTIF(AR4:BL4,">0") -> 2
A5: 38046 | B5: =ABS(EMFX_Data!X5-EMFX_Data!Y5) -> 0.0075281306 | C5: =ABS(EMFX_Data!X5-EMFX_Data!Z5) -> 0.02423662 | D5: =ABS(EMFX_Data!X5-EMFX_Data!AA5) -> 0.0037926515 | E5: =ABS(EMFX_Data!X5-EMFX_Data!AB5) -> 0.024383664 | F5: =ABS(EMFX_Data!X5-EMFX_Data!AC5) -> 0.0074127575 | G5: =ABS(EMFX_Data!X5-EMFX_Data!AD5) -> 0.014008914 | H5: =ABS(EMFX_Data!Y5-EMFX_Data!Z5) -> 0.01670849 | I5: =ABS(EMFX_Data!Y5-EMFX_Data!AA5) -> 0.0037354791 | J5: =ABS(EMFX_Data!Y5-EMFX_Data!AB5) -> 0.016855534 | K5: =ABS(EMFX_Data!Y5-EMFX_Data!AC5) -> 0.014940888 | L5: =ABS(EMFX_Data!Y5-EMFX_Data!AD5) -> 0.021537044 | M5: =ABS(EMFX_Data!Z5-EMFX_Data!AA5) -> 0.020443969 | N5: =ABS(EMFX_Data!Z5-EMFX_Data!AB5) -> 0.00014704409 | O5: =ABS(EMFX_Data!Z5-EMFX_Data!AC5) -> 0.031649378 | P5: =ABS(EMFX_Data!Z5-EMFX_Data!AD5) -> 0.038245534 | Q5: =ABS(EMFX_Data!AA5-EMFX_Data!AB5) -> 0.020591013 | R5: =ABS(EMFX_Data!AA5-EMFX_Data!AC5) -> 0.011205409 | S5: =ABS(EMFX_Data!AA5-EMFX_Data!AD5) -> 0.017801565 | T5: =ABS(EMFX_Data!AB5-EMFX_Data!AC5) -> 0.031796422 | U5: =ABS(EMFX_Data!AB5-EMFX_Data!AD5) -> 0.038392578 | V5: =ABS(EMFX_Data!AC5-EMFX_Data!AD5) -> 0.0065961563 | W5: =IF(ROW()<4+MinObs-1,"",IFERROR((B5-AVERAGE(B$4:B5))/STDEV(B$4:B5),"")) | X5: =IF(ROW()<4+MinObs-1,"",IFERROR((C5-AVERAGE(C$4:C5))/STDEV(C$4:C5),"")) | Y5: =IF(ROW()<4+MinObs-1,"",IFERROR((D5-AVERAGE(D$4:D5))/STDEV(D$4:D5),"")) | Z5: =IF(ROW()<4+MinObs-1,"",IFERROR((E5-AVERAGE(E$4:E5))/STDEV(E$4:E5),"")) | AA5: =IF(ROW()<4+MinObs-1,"",IFERROR((F5-AVERAGE(F$4:F5))/STDEV(F$4:F5),"")) | AB5: =IF(ROW()<4+MinObs-1,"",IFERROR((G5-AVERAGE(G$4:G5))/STDEV(G$4:G5),"")) | AC5: =IF(ROW()<4+MinObs-1,"",IFERROR((H5-AVERAGE(H$4:H5))/STDEV(H$4:H5),"")) | AD5: =IF(ROW()<4+MinObs-1,"",IFERROR((I5-AVERAGE(I$4:I5))/STDEV(I$4:I5),"")) | ... AQ5: =IF(ROW()<4+MinObs-1,"",IFERROR((V5-AVERAGE(V$4:V5))/STDEV(V$4:V5),"")) | AR5: =IF(W5="",0,IF(W5>=z4,w4,IF(W5>=z3,w3,IF(W5>=zEntry,w2,IF(AND(W5>=ExitZ,AR4>0),w2,0))))) -> 0 | AS5: =IF(X5="",0,IF(X5>=z4,w4,IF(X5>=z3,w3,IF(X5>=zEntry,w2,IF(AND(X5>=ExitZ,AS4>0),w2,0))))) -> 0 | AT5: =IF(Y5="",0,IF(Y5>=z4,w4,IF(Y5>=z3,w3,IF(Y5>=zEntry,w2,IF(AND(Y5>=ExitZ,AT4>0),w2,0))))) -> 0 | AU5: =IF(Z5="",0,IF(Z5>=z4,w4,IF(Z5>=z3,w3,IF(Z5>=zEntry,w2,IF(AND(Z5>=ExitZ,AU4>0),w2,0))))) -> 0 | AV5: =IF(AA5="",0,IF(AA5>=z4,w4,IF(AA5>=z3,w3,IF(AA5>=zEntry,w2,IF(AND(AA5>=ExitZ,AV4>0),w2,0))))) -> 0 | AW5: =IF(AB5="",0,IF(AB5>=z4,w4,IF(AB5>=z3,w3,IF(AB5>=zEntry,w2,IF(AND(AB5>=ExitZ,AW4>0),w2,0))))) -> 0 | AX5: =IF(AC5="",0,IF(AC5>=z4,w4,IF(AC5>=z3,w3,IF(AC5>=zEntry,w2,IF(AND(AC5>=ExitZ,AX4>0),w2,0))))) -> 0 | AY5: =IF(AD5="",0,IF(AD5>=z4,w4,IF(AD5>=z3,w3,IF(AD5>=zEntry,w2,IF(AND(AD5>=ExitZ,AY4>0),w2,0))))) -> 0 | ... BL5: =IF(AQ5="",0,IF(AQ5>=z4,w4,IF(AQ5>=z3,w3,IF(AQ5>=zEntry,w2,IF(AND(AQ5>=ExitZ,BL4>0),w2,0))))) -> 0 | BM5: =IF(EMFX_Data!X4>=EMFX_Data!Y4,EMFX_Data!AE5-EMFX_Data!AF5,EMFX_Data!AF5-EMFX_Data!AE5) -> 0.015060996 | BN5: =IF(EMFX_Data!X4>=EMFX_Data!Z4,EMFX_Data!AE5-EMFX_Data!AG5,EMFX_Data!AG5-EMFX_Data!AE5) -> 0.044923701 | BO5: =IF(EMFX_Data!X4>=EMFX_Data!AA4,EMFX_Data!AE5-EMFX_Data!AH5,EMFX_Data!AH5-EMFX_Data!AE5) -> 0.0038804946 | BP5: =IF(EMFX_Data!X4>=EMFX_Data!AB4,EMFX_Data!AE5-EMFX_Data!AI5,EMFX_Data!AI5-EMFX_Data!AE5) -> 0.04705575 | BQ5: =IF(EMFX_Data!X4>=EMFX_Data!AC4,EMFX_Data!AE5-EMFX_Data!AJ5,EMFX_Data!AJ5-EMFX_Data!AE5) -> -0.0087128272 | BR5: =IF(EMFX_Data!X4>=EMFX_Data!AD4,EMFX_Data!AE5-EMFX_Data!AK5,EMFX_Data!AK5-EMFX_Data!AE5) -> 0.031992094 | BS5: =IF(EMFX_Data!Y4>=EMFX_Data!Z4,EMFX_Data!AF5-EMFX_Data!AG5,EMFX_Data!AG5-EMFX_Data!AF5) -> 0.029862705 | BT5: =IF(EMFX_Data!Y4>=EMFX_Data!AA4,EMFX_Data!AF5-EMFX_Data!AH5,EMFX_Data!AH5-EMFX_Data!AF5) -> -0.011180502 | BU5: =IF(EMFX_Data!Y4>=EMFX_Data!AB4,EMFX_Data!AF5-EMFX_Data!AI5,EMFX_Data!AI5-EMFX_Data!AF5) -> 0.031994754 | BV5: =IF(EMFX_Data!Y4>=EMFX_Data!AC4,EMFX_Data!AF5-EMFX_Data!AJ5,EMFX_Data!AJ5-EMFX_Data!AF5) -> -0.023773823 | BW5: =IF(EMFX_Data!Y4>=EMFX_Data!AD4,EMFX_Data!AF5-EMFX_Data!AK5,EMFX_Data!AK5-EMFX_Data!AF5) -> 0.04705309 | BX5: =IF(EMFX_Data!Z4>=EMFX_Data!AA4,EMFX_Data!AG5-EMFX_Data!AH5,EMFX_Data!AH5-EMFX_Data!AG5) -> -0.041043207 | BY5: =IF(EMFX_Data!Z4>=EMFX_Data!AB4,EMFX_Data!AG5-EMFX_Data!AI5,EMFX_Data!AI5-EMFX_Data!AG5) -> 0.0021320488 | BZ5: =IF(EMFX_Data!Z4>=EMFX_Data!AC4,EMFX_Data!AG5-EMFX_Data!AJ5,EMFX_Data!AJ5-EMFX_Data!AG5) -> -0.053636528 | CA5: =IF(EMFX_Data!Z4>=EMFX_Data!AD4,EMFX_Data!AG5-EMFX_Data!AK5,EMFX_Data!AK5-EMFX_Data!AG5) -> 0.076915795 | CB5: =IF(EMFX_Data!AA4>=EMFX_Data!AB4,EMFX_Data!AH5-EMFX_Data!AI5,EMFX_Data!AI5-EMFX_Data!AH5) -> 0.043175255 | CC5: =IF(EMFX_Data!AA4>=EMFX_Data!AC4,EMFX_Data!AH5-EMFX_Data!AJ5,EMFX_Data!AJ5-EMFX_Data!AH5) -> -0.012593322 | CD5: =IF(EMFX_Data!AA4>=EMFX_Data!AD4,EMFX_Data!AH5-EMFX_Data!AK5,EMFX_Data!AK5-EMFX_Data!AH5) -> 0.035872589 | CE5: =IF(EMFX_Data!AB4>=EMFX_Data!AC4,EMFX_Data!AI5-EMFX_Data!AJ5,EMFX_Data!AJ5-EMFX_Data!AI5) -> -0.055768577 | CF5: =IF(EMFX_Data!AB4>=EMFX_Data!AD4,EMFX_Data!AI5-EMFX_Data!AK5,EMFX_Data!AK5-EMFX_Data!AI5) -> 0.079047844 | CG5: =IF(EMFX_Data!AC4>=EMFX_Data!AD4,EMFX_Data!AJ5-EMFX_Data!AK5,EMFX_Data!AK5-EMFX_Data!AJ5) -> 0.023279267 | CH5: =IF(ROW()<4+VolLB,"",STDEV(INDEX($BM:$BM,ROW()-VolLB+1):INDEX($BM:$BM,ROW()))*SQRT(12)) | CI5: =IF(ROW()<4+VolLB,"",STDEV(INDEX($BN:$BN,ROW()-VolLB+1):INDEX($BN:$BN,ROW()))*SQRT(12)) | CJ5: =IF(ROW()<4+VolLB,"",STDEV(INDEX($BO:$BO,ROW()-VolLB+1):INDEX($BO:$BO,ROW()))*SQRT(12)) | CK5: =IF(ROW()<4+VolLB,"",STDEV(INDEX($BP:$BP,ROW()-VolLB+1):INDEX($BP:$BP,ROW()))*SQRT(12)) | CL5: =IF(ROW()<4+VolLB,"",STDEV(INDEX($BQ:$BQ,ROW()-VolLB+1):INDEX($BQ:$BQ,ROW()))*SQRT(12)) | CM5: =IF(ROW()<4+VolLB,"",STDEV(INDEX($BR:$BR,ROW()-VolLB+1):INDEX($BR:$BR,ROW()))*SQRT(12)) | CN5: =IF(ROW()<4+VolLB,"",STDEV(INDEX($BS:$BS,ROW()-VolLB+1):INDEX($BS:$BS,ROW()))*SQRT(12)) | CO5: =IF(ROW()<4+VolLB,"",STDEV(INDEX($BT:$BT,ROW()-VolLB+1):INDEX($BT:$BT,ROW()))*SQRT(12)) | CP5: =IF(ROW()<4+VolLB,"",STDEV(INDEX($BU:$BU,ROW()-VolLB+1):INDEX($BU:$BU,ROW()))*SQRT(12)) | CQ5: =IF(ROW()<4+VolLB,"",STDEV(INDEX($BV:$BV,ROW()-VolLB+1):INDEX($BV:$BV,ROW()))*SQRT(12)) | CR5: =IF(ROW()<4+VolLB,"",STDEV(INDEX($BW:$BW,ROW()-VolLB+1):INDEX($BW:$BW,ROW()))*SQRT(12)) | CS5: =IF(ROW()<4+VolLB,"",STDEV(INDEX($BX:$BX,ROW()-VolLB+1):INDEX($BX:$BX,ROW()))*SQRT(12)) | CT5: =IF(ROW()<4+VolLB,"",STDEV(INDEX($BY:$BY,ROW()-VolLB+1):INDEX($BY:$BY,ROW()))*SQRT(12)) | CU5: =IF(ROW()<4+VolLB,"",STDEV(INDEX($BZ:$BZ,ROW()-VolLB+1):INDEX($BZ:$BZ,ROW()))*SQRT(12)) | CV5: =IF(ROW()<4+VolLB,"",STDEV(INDEX($CA:$CA,ROW()-VolLB+1):INDEX($CA:$CA,ROW()))*SQRT(12)) | CW5: =IF(ROW()<4+VolLB,"",STDEV(INDEX($CB:$CB,ROW()-VolLB+1):INDEX($CB:$CB,ROW()))*SQRT(12)) | CX5: =IF(ROW()<4+VolLB,"",STDEV(INDEX($CC:$CC,ROW()-VolLB+1):INDEX($CC:$CC,ROW()))*SQRT(12)) | CY5: =IF(ROW()<4+VolLB,"",STDEV(INDEX($CD:$CD,ROW()-VolLB+1):INDEX($CD:$CD,ROW()))*SQRT(12)) | CZ5: =IF(ROW()<4+VolLB,"",STDEV(INDEX($CE:$CE,ROW()-VolLB+1):INDEX($CE:$CE,ROW()))*SQRT(12)) | DA5: =IF(ROW()<4+VolLB,"",STDEV(INDEX($CF:$CF,ROW()-VolLB+1):INDEX($CF:$CF,ROW()))*SQRT(12)) | DB5: =IF(ROW()<4+VolLB,"",STDEV(INDEX($CG:$CG,ROW()-VolLB+1):INDEX($CG:$CG,ROW()))*SQRT(12)) | DC5: =IF(OR(AR5=0,CH5="",CH5=0),0,AR5*MIN(MaxScal,TgtVol/CH5)) -> 0 | DD5: =IF(OR(AS5=0,CI5="",CI5=0),0,AS5*MIN(MaxScal,TgtVol/CI5)) -> 0 | DE5: =IF(OR(AT5=0,CJ5="",CJ5=0),0,AT5*MIN(MaxScal,TgtVol/CJ5)) -> 0 | DF5: =IF(OR(AU5=0,CK5="",CK5=0),0,AU5*MIN(MaxScal,TgtVol/CK5)) -> 0 | DG5: =IF(OR(AV5=0,CL5="",CL5=0),0,AV5*MIN(MaxScal,TgtVol/CL5)) -> 0 | DH5: =IF(OR(AW5=0,CM5="",CM5=0),0,AW5*MIN(MaxScal,TgtVol/CM5)) -> 0 | DI5: =IF(OR(AX5=0,CN5="",CN5=0),0,AX5*MIN(MaxScal,TgtVol/CN5)) -> 0 | DJ5: =IF(OR(AY5=0,CO5="",CO5=0),0,AY5*MIN(MaxScal,TgtVol/CO5)) -> 0 | ... DW5: =IF(OR(BL5=0,DB5="",DB5=0),0,BL5*MIN(MaxScal,TgtVol/DB5)) -> 0 | DX5: =IFERROR(DC4*BM5,"") -> 0 | DY5: =IFERROR(DD4*BN5,"") -> 0 | DZ5: =IFERROR(DE4*BO5,"") -> 0 | EA5: =IFERROR(DF4*BP5,"") -> 0 | EB5: =IFERROR(DG4*BQ5,"") -> 0 | EC5: =IFERROR(DH4*BR5,"") -> 0 | ED5: =IFERROR(DI4*BS5,"") -> 0 | EE5: =IFERROR(DJ4*BT5,"") -> 0 | ... ER5: =IFERROR(DW4*CG5,"") -> 0 | ES5: =IF(ROW()=4,"",SUM(DX5:ER5)) -> 0 | ET5: =COUNTIF(AR5:BL5,">0") -> 0
A6: 38077 | B6: =ABS(EMFX_Data!X6-EMFX_Data!Y6) -> 0.0055390545 | C6: =ABS(EMFX_Data!X6-EMFX_Data!Z6) -> 0.034881805 | D6: =ABS(EMFX_Data!X6-EMFX_Data!AA6) -> 0.031496448 | E6: =ABS(EMFX_Data!X6-EMFX_Data!AB6) -> 0.044724976 | F6: =ABS(EMFX_Data!X6-EMFX_Data!AC6) -> 0.002776513 | G6: =ABS(EMFX_Data!X6-EMFX_Data!AD6) -> 0.0093422306 | H6: =ABS(EMFX_Data!Y6-EMFX_Data!Z6) -> 0.02934275 | I6: =ABS(EMFX_Data!Y6-EMFX_Data!AA6) -> 0.025957394 | J6: =ABS(EMFX_Data!Y6-EMFX_Data!AB6) -> 0.039185921 | K6: =ABS(EMFX_Data!Y6-EMFX_Data!AC6) -> 0.0083155675 | L6: =ABS(EMFX_Data!Y6-EMFX_Data!AD6) -> 0.014881285 | M6: =ABS(EMFX_Data!Z6-EMFX_Data!AA6) -> 0.0033853567 | N6: =ABS(EMFX_Data!Z6-EMFX_Data!AB6) -> 0.0098431707 | O6: =ABS(EMFX_Data!Z6-EMFX_Data!AC6) -> 0.037658318 | P6: =ABS(EMFX_Data!Z6-EMFX_Data!AD6) -> 0.044224036 | Q6: =ABS(EMFX_Data!AA6-EMFX_Data!AB6) -> 0.013228527 | R6: =ABS(EMFX_Data!AA6-EMFX_Data!AC6) -> 0.034272961 | S6: =ABS(EMFX_Data!AA6-EMFX_Data!AD6) -> 0.040838679 | T6: =ABS(EMFX_Data!AB6-EMFX_Data!AC6) -> 0.047501489 | U6: =ABS(EMFX_Data!AB6-EMFX_Data!AD6) -> 0.054067206 | V6: =ABS(EMFX_Data!AC6-EMFX_Data!AD6) -> 0.0065657176 | W6: =IF(ROW()<4+MinObs-1,"",IFERROR((B6-AVERAGE(B$4:B6))/STDEV(B$4:B6),"")) | X6: =IF(ROW()<4+MinObs-1,"",IFERROR((C6-AVERAGE(C$4:C6))/STDEV(C$4:C6),"")) | Y6: =IF(ROW()<4+MinObs-1,"",IFERROR((D6-AVERAGE(D$4:D6))/STDEV(D$4:D6),"")) | Z6: =IF(ROW()<4+MinObs-1,"",IFERROR((E6-AVERAGE(E$4:E6))/STDEV(E$4:E6),"")) | AA6: =IF(ROW()<4+MinObs-1,"",IFERROR((F6-AVERAGE(F$4:F6))/STDEV(F$4:F6),"")) | AB6: =IF(ROW()<4+MinObs-1,"",IFERROR((G6-AVERAGE(G$4:G6))/STDEV(G$4:G6),"")) | AC6: =IF(ROW()<4+MinObs-1,"",IFERROR((H6-AVERAGE(H$4:H6))/STDEV(H$4:H6),"")) | AD6: =IF(ROW()<4+MinObs-1,"",IFERROR((I6-AVERAGE(I$4:I6))/STDEV(I$4:I6),"")) | ... AQ6: =IF(ROW()<4+MinObs-1,"",IFERROR((V6-AVERAGE(V$4:V6))/STDEV(V$4:V6),"")) | AR6: =IF(W6="",0,IF(W6>=z4,w4,IF(W6>=z3,w3,IF(W6>=zEntry,w2,IF(AND(W6>=ExitZ,AR5>0),w2,0))))) -> 0 | AS6: =IF(X6="",0,IF(X6>=z4,w4,IF(X6>=z3,w3,IF(X6>=zEntry,w2,IF(AND(X6>=ExitZ,AS5>0),w2,0))))) -> 0 | AT6: =IF(Y6="",0,IF(Y6>=z4,w4,IF(Y6>=z3,w3,IF(Y6>=zEntry,w2,IF(AND(Y6>=ExitZ,AT5>0),w2,0))))) -> 0 | AU6: =IF(Z6="",0,IF(Z6>=z4,w4,IF(Z6>=z3,w3,IF(Z6>=zEntry,w2,IF(AND(Z6>=ExitZ,AU5>0),w2,0))))) -> 0 | AV6: =IF(AA6="",0,IF(AA6>=z4,w4,IF(AA6>=z3,w3,IF(AA6>=zEntry,w2,IF(AND(AA6>=ExitZ,AV5>0),w2,0))))) -> 0 | AW6: =IF(AB6="",0,IF(AB6>=z4,w4,IF(AB6>=z3,w3,IF(AB6>=zEntry,w2,IF(AND(AB6>=ExitZ,AW5>0),w2,0))))) -> 0 | AX6: =IF(AC6="",0,IF(AC6>=z4,w4,IF(AC6>=z3,w3,IF(AC6>=zEntry,w2,IF(AND(AC6>=ExitZ,AX5>0),w2,0))))) -> 0 | AY6: =IF(AD6="",0,IF(AD6>=z4,w4,IF(AD6>=z3,w3,IF(AD6>=zEntry,w2,IF(AND(AD6>=ExitZ,AY5>0),w2,0))))) -> 0 | ... BL6: =IF(AQ6="",0,IF(AQ6>=z4,w4,IF(AQ6>=z3,w3,IF(AQ6>=zEntry,w2,IF(AND(AQ6>=ExitZ,BL5>0),w2,0))))) -> 0 | BM6: =IF(EMFX_Data!X5>=EMFX_Data!Y5,EMFX_Data!AE6-EMFX_Data!AF6,EMFX_Data!AF6-EMFX_Data!AE6) -> -0.00063656909 | BN6: =IF(EMFX_Data!X5>=EMFX_Data!Z5,EMFX_Data!AE6-EMFX_Data!AG6,EMFX_Data!AG6-EMFX_Data!AE6) -> -0.027624507 | BO6: =IF(EMFX_Data!X5>=EMFX_Data!AA5,EMFX_Data!AE6-EMFX_Data!AH6,EMFX_Data!AH6-EMFX_Data!AE6) -> -0.043920945 | BP6: =IF(EMFX_Data!X5>=EMFX_Data!AB5,EMFX_Data!AE6-EMFX_Data!AI6,EMFX_Data!AI6-EMFX_Data!AE6) -> -0.042537732 | BQ6: =IF(EMFX_Data!X5>=EMFX_Data!AC5,EMFX_Data!AE6-EMFX_Data!AJ6,EMFX_Data!AJ6-EMFX_Data!AE6) -> 0.012863925 | BR6: =IF(EMFX_Data!X5>=EMFX_Data!AD5,EMFX_Data!AE6-EMFX_Data!AK6,EMFX_Data!AK6-EMFX_Data!AE6) -> -0.0039808063 | BS6: =IF(EMFX_Data!Y5>=EMFX_Data!Z5,EMFX_Data!AF6-EMFX_Data!AG6,EMFX_Data!AG6-EMFX_Data!AF6) -> -0.026987938 | BT6: =IF(EMFX_Data!Y5>=EMFX_Data!AA5,EMFX_Data!AF6-EMFX_Data!AH6,EMFX_Data!AH6-EMFX_Data!AF6) -> 0.043284375 | BU6: =IF(EMFX_Data!Y5>=EMFX_Data!AB5,EMFX_Data!AF6-EMFX_Data!AI6,EMFX_Data!AI6-EMFX_Data!AF6) -> -0.041901163 | BV6: =IF(EMFX_Data!Y5>=EMFX_Data!AC5,EMFX_Data!AF6-EMFX_Data!AJ6,EMFX_Data!AJ6-EMFX_Data!AF6) -> 0.012227356 | BW6: =IF(EMFX_Data!Y5>=EMFX_Data!AD5,EMFX_Data!AF6-EMFX_Data!AK6,EMFX_Data!AK6-EMFX_Data!AF6) -> -0.0046173754 | BX6: =IF(EMFX_Data!Z5>=EMFX_Data!AA5,EMFX_Data!AG6-EMFX_Data!AH6,EMFX_Data!AH6-EMFX_Data!AG6) -> 0.016296437 | BY6: =IF(EMFX_Data!Z5>=EMFX_Data!AB5,EMFX_Data!AG6-EMFX_Data!AI6,EMFX_Data!AI6-EMFX_Data!AG6) -> -0.014913225 | BZ6: =IF(EMFX_Data!Z5>=EMFX_Data!AC5,EMFX_Data!AG6-EMFX_Data!AJ6,EMFX_Data!AJ6-EMFX_Data!AG6) -> -0.014760582 | CA6: =IF(EMFX_Data!Z5>=EMFX_Data!AD5,EMFX_Data!AG6-EMFX_Data!AK6,EMFX_Data!AK6-EMFX_Data!AG6) -> -0.031605314 | CB6: =IF(EMFX_Data!AA5>=EMFX_Data!AB5,EMFX_Data!AH6-EMFX_Data!AI6,EMFX_Data!AI6-EMFX_Data!AH6) -> 0.0013832125 | CC6: =IF(EMFX_Data!AA5>=EMFX_Data!AC5,EMFX_Data!AH6-EMFX_Data!AJ6,EMFX_Data!AJ6-EMFX_Data!AH6) -> -0.031057019 | CD6: =IF(EMFX_Data!AA5>=EMFX_Data!AD5,EMFX_Data!AH6-EMFX_Data!AK6,EMFX_Data!AK6-EMFX_Data!AH6) -> -0.047901751 | CE6: =IF(EMFX_Data!AB5>=EMFX_Data!AC5,EMFX_Data!AI6-EMFX_Data!AJ6,EMFX_Data!AJ6-EMFX_Data!AI6) -> -0.029673807 | CF6: =IF(EMFX_Data!AB5>=EMFX_Data!AD5,EMFX_Data!AI6-EMFX_Data!AK6,EMFX_Data!AK6-EMFX_Data!AI6) -> -0.046518538 | CG6: =IF(EMFX_Data!AC5>=EMFX_Data!AD5,EMFX_Data!AJ6-EMFX_Data!AK6,EMFX_Data!AK6-EMFX_Data!AJ6) -> -0.016844732 | CH6: =IF(ROW()<4+VolLB,"",STDEV(INDEX($BM:$BM,ROW()-VolLB+1):INDEX($BM:$BM,ROW()))*SQRT(12)) | CI6: =IF(ROW()<4+VolLB,"",STDEV(INDEX($BN:$BN,ROW()-VolLB+1):INDEX($BN:$BN,ROW()))*SQRT(12)) | CJ6: =IF(ROW()<4+VolLB,"",STDEV(INDEX($BO:$BO,ROW()-VolLB+1):INDEX($BO:$BO,ROW()))*SQRT(12)) | CK6: =IF(ROW()<4+VolLB,"",STDEV(INDEX($BP:$BP,ROW()-VolLB+1):INDEX($BP:$BP,ROW()))*SQRT(12)) | CL6: =IF(ROW()<4+VolLB,"",STDEV(INDEX($BQ:$BQ,ROW()-VolLB+1):INDEX($BQ:$BQ,ROW()))*SQRT(12)) | CM6: =IF(ROW()<4+VolLB,"",STDEV(INDEX($BR:$BR,ROW()-VolLB+1):INDEX($BR:$BR,ROW()))*SQRT(12)) | CN6: =IF(ROW()<4+VolLB,"",STDEV(INDEX($BS:$BS,ROW()-VolLB+1):INDEX($BS:$BS,ROW()))*SQRT(12)) | CO6: =IF(ROW()<4+VolLB,"",STDEV(INDEX($BT:$BT,ROW()-VolLB+1):INDEX($BT:$BT,ROW()))*SQRT(12)) | CP6: =IF(ROW()<4+VolLB,"",STDEV(INDEX($BU:$BU,ROW()-VolLB+1):INDEX($BU:$BU,ROW()))*SQRT(12)) | CQ6: =IF(ROW()<4+VolLB,"",STDEV(INDEX($BV:$BV,ROW()-VolLB+1):INDEX($BV:$BV,ROW()))*SQRT(12)) | CR6: =IF(ROW()<4+VolLB,"",STDEV(INDEX($BW:$BW,ROW()-VolLB+1):INDEX($BW:$BW,ROW()))*SQRT(12)) | CS6: =IF(ROW()<4+VolLB,"",STDEV(INDEX($BX:$BX,ROW()-VolLB+1):INDEX($BX:$BX,ROW()))*SQRT(12)) | CT6: =IF(ROW()<4+VolLB,"",STDEV(INDEX($BY:$BY,ROW()-VolLB+1):INDEX($BY:$BY,ROW()))*SQRT(12)) | CU6: =IF(ROW()<4+VolLB,"",STDEV(INDEX($BZ:$BZ,ROW()-VolLB+1):INDEX($BZ:$BZ,ROW()))*SQRT(12)) | CV6: =IF(ROW()<4+VolLB,"",STDEV(INDEX($CA:$CA,ROW()-VolLB+1):INDEX($CA:$CA,ROW()))*SQRT(12)) | CW6: =IF(ROW()<4+VolLB,"",STDEV(INDEX($CB:$CB,ROW()-VolLB+1):INDEX($CB:$CB,ROW()))*SQRT(12)) | CX6: =IF(ROW()<4+VolLB,"",STDEV(INDEX($CC:$CC,ROW()-VolLB+1):INDEX($CC:$CC,ROW()))*SQRT(12)) | CY6: =IF(ROW()<4+VolLB,"",STDEV(INDEX($CD:$CD,ROW()-VolLB+1):INDEX($CD:$CD,ROW()))*SQRT(12)) | CZ6: =IF(ROW()<4+VolLB,"",STDEV(INDEX($CE:$CE,ROW()-VolLB+1):INDEX($CE:$CE,ROW()))*SQRT(12)) | DA6: =IF(ROW()<4+VolLB,"",STDEV(INDEX($CF:$CF,ROW()-VolLB+1):INDEX($CF:$CF,ROW()))*SQRT(12)) | DB6: =IF(ROW()<4+VolLB,"",STDEV(INDEX($CG:$CG,ROW()-VolLB+1):INDEX($CG:$CG,ROW()))*SQRT(12)) | DC6: =IF(OR(AR6=0,CH6="",CH6=0),0,AR6*MIN(MaxScal,TgtVol/CH6)) -> 0 | DD6: =IF(OR(AS6=0,CI6="",CI6=0),0,AS6*MIN(MaxScal,TgtVol/CI6)) -> 0 | DE6: =IF(OR(AT6=0,CJ6="",CJ6=0),0,AT6*MIN(MaxScal,TgtVol/CJ6)) -> 0 | DF6: =IF(OR(AU6=0,CK6="",CK6=0),0,AU6*MIN(MaxScal,TgtVol/CK6)) -> 0 | DG6: =IF(OR(AV6=0,CL6="",CL6=0),0,AV6*MIN(MaxScal,TgtVol/CL6)) -> 0 | DH6: =IF(OR(AW6=0,CM6="",CM6=0),0,AW6*MIN(MaxScal,TgtVol/CM6)) -> 0 | DI6: =IF(OR(AX6=0,CN6="",CN6=0),0,AX6*MIN(MaxScal,TgtVol/CN6)) -> 0 | DJ6: =IF(OR(AY6=0,CO6="",CO6=0),0,AY6*MIN(MaxScal,TgtVol/CO6)) -> 0 | ... DW6: =IF(OR(BL6=0,DB6="",DB6=0),0,BL6*MIN(MaxScal,TgtVol/DB6)) -> 0 | DX6: =IFERROR(DC5*BM6,"") -> 0 | DY6: =IFERROR(DD5*BN6,"") -> 0 | DZ6: =IFERROR(DE5*BO6,"") -> 0 | EA6: =IFERROR(DF5*BP6,"") -> 0 | EB6: =IFERROR(DG5*BQ6,"") -> 0 | EC6: =IFERROR(DH5*BR6,"") -> 0 | ED6: =IFERROR(DI5*BS6,"") -> 0 | EE6: =IFERROR(DJ5*BT6,"") -> 0 | ... ER6: =IFERROR(DW5*CG6,"") -> 0 | ES6: =IF(ROW()=4,"",SUM(DX6:ER6)) -> 0 | ET6: =COUNTIF(AR6:BL6,">0") -> 0
A7: 38107 | B7: =ABS(EMFX_Data!X7-EMFX_Data!Y7) -> 0.049726553 | C7: =ABS(EMFX_Data!X7-EMFX_Data!Z7) -> 0.062229245 | D7: =ABS(EMFX_Data!X7-EMFX_Data!AA7) -> 0.098895975 | E7: =ABS(EMFX_Data!X7-EMFX_Data!AB7) -> 0.061873419 | F7: =ABS(EMFX_Data!X7-EMFX_Data!AC7) -> 0.0042994924 | G7: =ABS(EMFX_Data!X7-EMFX_Data!AD7) -> 0.044871213 | H7: =ABS(EMFX_Data!Y7-EMFX_Data!Z7) -> 0.012502692 | I7: =ABS(EMFX_Data!Y7-EMFX_Data!AA7) -> 0.049169422 | J7: =ABS(EMFX_Data!Y7-EMFX_Data!AB7) -> 0.012146865 | K7: =ABS(EMFX_Data!Y7-EMFX_Data!AC7) -> 0.054026046 | L7: =ABS(EMFX_Data!Y7-EMFX_Data!AD7) -> 0.00485534 | M7: =ABS(EMFX_Data!Z7-EMFX_Data!AA7) -> 0.03666673 | N7: =ABS(EMFX_Data!Z7-EMFX_Data!AB7) -> 0.00035582625 | O7: =ABS(EMFX_Data!Z7-EMFX_Data!AC7) -> 0.066528737 | P7: =ABS(EMFX_Data!Z7-EMFX_Data!AD7) -> 0.017358032 | Q7: =ABS(EMFX_Data!AA7-EMFX_Data!AB7) -> 0.037022556 | R7: =ABS(EMFX_Data!AA7-EMFX_Data!AC7) -> 0.10319547 | S7: =ABS(EMFX_Data!AA7-EMFX_Data!AD7) -> 0.054024762 | T7: =ABS(EMFX_Data!AB7-EMFX_Data!AC7) -> 0.066172911 | U7: =ABS(EMFX_Data!AB7-EMFX_Data!AD7) -> 0.017002205 | V7: =ABS(EMFX_Data!AC7-EMFX_Data!AD7) -> 0.049170706 | W7: =IF(ROW()<4+MinObs-1,"",IFERROR((B7-AVERAGE(B$4:B7))/STDEV(B$4:B7),"")) | X7: =IF(ROW()<4+MinObs-1,"",IFERROR((C7-AVERAGE(C$4:C7))/STDEV(C$4:C7),"")) | Y7: =IF(ROW()<4+MinObs-1,"",IFERROR((D7-AVERAGE(D$4:D7))/STDEV(D$4:D7),"")) | Z7: =IF(ROW()<4+MinObs-1,"",IFERROR((E7-AVERAGE(E$4:E7))/STDEV(E$4:E7),"")) | AA7: =IF(ROW()<4+MinObs-1,"",IFERROR((F7-AVERAGE(F$4:F7))/STDEV(F$4:F7),"")) | AB7: =IF(ROW()<4+MinObs-1,"",IFERROR((G7-AVERAGE(G$4:G7))/STDEV(G$4:G7),"")) | AC7: =IF(ROW()<4+MinObs-1,"",IFERROR((H7-AVERAGE(H$4:H7))/STDEV(H$4:H7),"")) | AD7: =IF(ROW()<4+MinObs-1,"",IFERROR((I7-AVERAGE(I$4:I7))/STDEV(I$4:I7),"")) | ... AQ7: =IF(ROW()<4+MinObs-1,"",IFERROR((V7-AVERAGE(V$4:V7))/STDEV(V$4:V7),"")) | AR7: =IF(W7="",0,IF(W7>=z4,w4,IF(W7>=z3,w3,IF(W7>=zEntry,w2,IF(AND(W7>=ExitZ,AR6>0),w2,0))))) -> 0 | AS7: =IF(X7="",0,IF(X7>=z4,w4,IF(X7>=z3,w3,IF(X7>=zEntry,w2,IF(AND(X7>=ExitZ,AS6>0),w2,0))))) -> 0 | AT7: =IF(Y7="",0,IF(Y7>=z4,w4,IF(Y7>=z3,w3,IF(Y7>=zEntry,w2,IF(AND(Y7>=ExitZ,AT6>0),w2,0))))) -> 0 | AU7: =IF(Z7="",0,IF(Z7>=z4,w4,IF(Z7>=z3,w3,IF(Z7>=zEntry,w2,IF(AND(Z7>=ExitZ,AU6>0),w2,0))))) -> 0 | AV7: =IF(AA7="",0,IF(AA7>=z4,w4,IF(AA7>=z3,w3,IF(AA7>=zEntry,w2,IF(AND(AA7>=ExitZ,AV6>0),w2,0))))) -> 0 | AW7: =IF(AB7="",0,IF(AB7>=z4,w4,IF(AB7>=z3,w3,IF(AB7>=zEntry,w2,IF(AND(AB7>=ExitZ,AW6>0),w2,0))))) -> 0 | AX7: =IF(AC7="",0,IF(AC7>=z4,w4,IF(AC7>=z3,w3,IF(AC7>=zEntry,w2,IF(AND(AC7>=ExitZ,AX6>0),w2,0))))) -> 0 | AY7: =IF(AD7="",0,IF(AD7>=z4,w4,IF(AD7>=z3,w3,IF(AD7>=zEntry,w2,IF(AND(AD7>=ExitZ,AY6>0),w2,0))))) -> 0 | ... BL7: =IF(AQ7="",0,IF(AQ7>=z4,w4,IF(AQ7>=z3,w3,IF(AQ7>=zEntry,w2,IF(AND(AQ7>=ExitZ,BL6>0),w2,0))))) -> 0 | BM7: =IF(EMFX_Data!X6>=EMFX_Data!Y6,EMFX_Data!AE7-EMFX_Data!AF7,EMFX_Data!AF7-EMFX_Data!AE7) -> -0.060076131 | BN7: =IF(EMFX_Data!X6>=EMFX_Data!Z6,EMFX_Data!AE7-EMFX_Data!AG7,EMFX_Data!AG7-EMFX_Data!AE7) -> -0.047215059 | BO7: =IF(EMFX_Data!X6>=EMFX_Data!AA6,EMFX_Data!AE7-EMFX_Data!AH7,EMFX_Data!AH7-EMFX_Data!AE7) -> -0.096961451 | BP7: =IF(EMFX_Data!X6>=EMFX_Data!AB6,EMFX_Data!AE7-EMFX_Data!AI7,EMFX_Data!AI7-EMFX_Data!AE7) -> -0.037977267 | BQ7: =IF(EMFX_Data!X6>=EMFX_Data!AC6,EMFX_Data!AE7-EMFX_Data!AJ7,EMFX_Data!AJ7-EMFX_Data!AE7) -> 0.0045506728 | BR7: =IF(EMFX_Data!X6>=EMFX_Data!AD6,EMFX_Data!AE7-EMFX_Data!AK7,EMFX_Data!AK7-EMFX_Data!AE7) -> 0.066758174 | BS7: =IF(EMFX_Data!Y6>=EMFX_Data!Z6,EMFX_Data!AF7-EMFX_Data!AG7,EMFX_Data!AG7-EMFX_Data!AF7) -> 0.012861072 | BT7: =IF(EMFX_Data!Y6>=EMFX_Data!AA6,EMFX_Data!AF7-EMFX_Data!AH7,EMFX_Data!AH7-EMFX_Data!AF7) -> -0.03688532 | BU7: =IF(EMFX_Data!Y6>=EMFX_Data!AB6,EMFX_Data!AF7-EMFX_Data!AI7,EMFX_Data!AI7-EMFX_Data!AF7) -> 0.022098864 | BV7: =IF(EMFX_Data!Y6>=EMFX_Data!AC6,EMFX_Data!AF7-EMFX_Data!AJ7,EMFX_Data!AJ7-EMFX_Data!AF7) -> -0.055525458 | BW7: =IF(EMFX_Data!Y6>=EMFX_Data!AD6,EMFX_Data!AF7-EMFX_Data!AK7,EMFX_Data!AK7-EMFX_Data!AF7) -> 0.0066820427 | BX7: =IF(EMFX_Data!Z6>=EMFX_Data!AA6,EMFX_Data!AG7-EMFX_Data!AH7,EMFX_Data!AH7-EMFX_Data!AG7) -> 0.049746392 | BY7: =IF(EMFX_Data!Z6>=EMFX_Data!AB6,EMFX_Data!AG7-EMFX_Data!AI7,EMFX_Data!AI7-EMFX_Data!AG7) -> 0.0092377919 | BZ7: =IF(EMFX_Data!Z6>=EMFX_Data!AC6,EMFX_Data!AG7-EMFX_Data!AJ7,EMFX_Data!AJ7-EMFX_Data!AG7) -> -0.042664386 | CA7: =IF(EMFX_Data!Z6>=EMFX_Data!AD6,EMFX_Data!AG7-EMFX_Data!AK7,EMFX_Data!AK7-EMFX_Data!AG7) -> 0.019543115 | CB7: =IF(EMFX_Data!AA6>=EMFX_Data!AB6,EMFX_Data!AH7-EMFX_Data!AI7,EMFX_Data!AI7-EMFX_Data!AH7) -> 0.058984184 | CC7: =IF(EMFX_Data!AA6>=EMFX_Data!AC6,EMFX_Data!AH7-EMFX_Data!AJ7,EMFX_Data!AJ7-EMFX_Data!AH7) -> -0.092410779 | CD7: =IF(EMFX_Data!AA6>=EMFX_Data!AD6,EMFX_Data!AH7-EMFX_Data!AK7,EMFX_Data!AK7-EMFX_Data!AH7) -> -0.030203278 | CE7: =IF(EMFX_Data!AB6>=EMFX_Data!AC6,EMFX_Data!AI7-EMFX_Data!AJ7,EMFX_Data!AJ7-EMFX_Data!AI7) -> -0.033426594 | CF7: =IF(EMFX_Data!AB6>=EMFX_Data!AD6,EMFX_Data!AI7-EMFX_Data!AK7,EMFX_Data!AK7-EMFX_Data!AI7) -> 0.028780907 | CG7: =IF(EMFX_Data!AC6>=EMFX_Data!AD6,EMFX_Data!AJ7-EMFX_Data!AK7,EMFX_Data!AK7-EMFX_Data!AJ7) -> 0.062207501 | CH7: =IF(ROW()<4+VolLB,"",STDEV(INDEX($BM:$BM,ROW()-VolLB+1):INDEX($BM:$BM,ROW()))*SQRT(12)) | CI7: =IF(ROW()<4+VolLB,"",STDEV(INDEX($BN:$BN,ROW()-VolLB+1):INDEX($BN:$BN,ROW()))*SQRT(12)) | CJ7: =IF(ROW()<4+VolLB,"",STDEV(INDEX($BO:$BO,ROW()-VolLB+1):INDEX($BO:$BO,ROW()))*SQRT(12)) | CK7: =IF(ROW()<4+VolLB,"",STDEV(INDEX($BP:$BP,ROW()-VolLB+1):INDEX($BP:$BP,ROW()))*SQRT(12)) | CL7: =IF(ROW()<4+VolLB,"",STDEV(INDEX($BQ:$BQ,ROW()-VolLB+1):INDEX($BQ:$BQ,ROW()))*SQRT(12)) | CM7: =IF(ROW()<4+VolLB,"",STDEV(INDEX($BR:$BR,ROW()-VolLB+1):INDEX($BR:$BR,ROW()))*SQRT(12)) | CN7: =IF(ROW()<4+VolLB,"",STDEV(INDEX($BS:$BS,ROW()-VolLB+1):INDEX($BS:$BS,ROW()))*SQRT(12)) | CO7: =IF(ROW()<4+VolLB,"",STDEV(INDEX($BT:$BT,ROW()-VolLB+1):INDEX($BT:$BT,ROW()))*SQRT(12)) | CP7: =IF(ROW()<4+VolLB,"",STDEV(INDEX($BU:$BU,ROW()-VolLB+1):INDEX($BU:$BU,ROW()))*SQRT(12)) | CQ7: =IF(ROW()<4+VolLB,"",STDEV(INDEX($BV:$BV,ROW()-VolLB+1):INDEX($BV:$BV,ROW()))*SQRT(12)) | CR7: =IF(ROW()<4+VolLB,"",STDEV(INDEX($BW:$BW,ROW()-VolLB+1):INDEX($BW:$BW,ROW()))*SQRT(12)) | CS7: =IF(ROW()<4+VolLB,"",STDEV(INDEX($BX:$BX,ROW()-VolLB+1):INDEX($BX:$BX,ROW()))*SQRT(12)) | CT7: =IF(ROW()<4+VolLB,"",STDEV(INDEX($BY:$BY,ROW()-VolLB+1):INDEX($BY:$BY,ROW()))*SQRT(12)) | CU7: =IF(ROW()<4+VolLB,"",STDEV(INDEX($BZ:$BZ,ROW()-VolLB+1):INDEX($BZ:$BZ,ROW()))*SQRT(12)) | CV7: =IF(ROW()<4+VolLB,"",STDEV(INDEX($CA:$CA,ROW()-VolLB+1):INDEX($CA:$CA,ROW()))*SQRT(12)) | CW7: =IF(ROW()<4+VolLB,"",STDEV(INDEX($CB:$CB,ROW()-VolLB+1):INDEX($CB:$CB,ROW()))*SQRT(12)) | CX7: =IF(ROW()<4+VolLB,"",STDEV(INDEX($CC:$CC,ROW()-VolLB+1):INDEX($CC:$CC,ROW()))*SQRT(12)) | CY7: =IF(ROW()<4+VolLB,"",STDEV(INDEX($CD:$CD,ROW()-VolLB+1):INDEX($CD:$CD,ROW()))*SQRT(12)) | CZ7: =IF(ROW()<4+VolLB,"",STDEV(INDEX($CE:$CE,ROW()-VolLB+1):INDEX($CE:$CE,ROW()))*SQRT(12)) | DA7: =IF(ROW()<4+VolLB,"",STDEV(INDEX($CF:$CF,ROW()-VolLB+1):INDEX($CF:$CF,ROW()))*SQRT(12)) | DB7: =IF(ROW()<4+VolLB,"",STDEV(INDEX($CG:$CG,ROW()-VolLB+1):INDEX($CG:$CG,ROW()))*SQRT(12)) | DC7: =IF(OR(AR7=0,CH7="",CH7=0),0,AR7*MIN(MaxScal,TgtVol/CH7)) -> 0 | DD7: =IF(OR(AS7=0,CI7="",CI7=0),0,AS7*MIN(MaxScal,TgtVol/CI7)) -> 0 | DE7: =IF(OR(AT7=0,CJ7="",CJ7=0),0,AT7*MIN(MaxScal,TgtVol/CJ7)) -> 0 | DF7: =IF(OR(AU7=0,CK7="",CK7=0),0,AU7*MIN(MaxScal,TgtVol/CK7)) -> 0 | DG7: =IF(OR(AV7=0,CL7="",CL7=0),0,AV7*MIN(MaxScal,TgtVol/CL7)) -> 0 | DH7: =IF(OR(AW7=0,CM7="",CM7=0),0,AW7*MIN(MaxScal,TgtVol/CM7)) -> 0 | DI7: =IF(OR(AX7=0,CN7="",CN7=0),0,AX7*MIN(MaxScal,TgtVol/CN7)) -> 0 | DJ7: =IF(OR(AY7=0,CO7="",CO7=0),0,AY7*MIN(MaxScal,TgtVol/CO7)) -> 0 | ... DW7: =IF(OR(BL7=0,DB7="",DB7=0),0,BL7*MIN(MaxScal,TgtVol/DB7)) -> 0 | DX7: =IFERROR(DC6*BM7,"") -> 0 | DY7: =IFERROR(DD6*BN7,"") -> 0 | DZ7: =IFERROR(DE6*BO7,"") -> 0 | EA7: =IFERROR(DF6*BP7,"") -> 0 | EB7: =IFERROR(DG6*BQ7,"") -> 0 | EC7: =IFERROR(DH6*BR7,"") -> 0 | ED7: =IFERROR(DI6*BS7,"") -> 0 | EE7: =IFERROR(DJ6*BT7,"") -> 0 | ... ER7: =IFERROR(DW6*CG7,"") -> 0 | ES7: =IF(ROW()=4,"",SUM(DX7:ER7)) -> 0 | ET7: =COUNTIF(AR7:BL7,">0") -> 0
A8: 38138 | B8: =ABS(EMFX_Data!X8-EMFX_Data!Y8) -> 0.042377386 | C8: =ABS(EMFX_Data!X8-EMFX_Data!Z8) -> 0.0083026582 | D8: =ABS(EMFX_Data!X8-EMFX_Data!AA8) -> 0.12557789 | E8: =ABS(EMFX_Data!X8-EMFX_Data!AB8) -> 0.051331166 | F8: =ABS(EMFX_Data!X8-EMFX_Data!AC8) -> 0.017987429 | G8: =ABS(EMFX_Data!X8-EMFX_Data!AD8) -> 0.051551134 | H8: =ABS(EMFX_Data!Y8-EMFX_Data!Z8) -> 0.034074728 | I8: =ABS(EMFX_Data!Y8-EMFX_Data!AA8) -> 0.083200503 | J8: =ABS(EMFX_Data!Y8-EMFX_Data!AB8) -> 0.0089537796 | K8: =ABS(EMFX_Data!Y8-EMFX_Data!AC8) -> 0.024389957 | L8: =ABS(EMFX_Data!Y8-EMFX_Data!AD8) -> 0.0091737481 | M8: =ABS(EMFX_Data!Z8-EMFX_Data!AA8) -> 0.11727523 | N8: =ABS(EMFX_Data!Z8-EMFX_Data!AB8) -> 0.043028508 | O8: =ABS(EMFX_Data!Z8-EMFX_Data!AC8) -> 0.0096847711 | P8: =ABS(EMFX_Data!Z8-EMFX_Data!AD8) -> 0.043248476 | Q8: =ABS(EMFX_Data!AA8-EMFX_Data!AB8) -> 0.074246724 | R8: =ABS(EMFX_Data!AA8-EMFX_Data!AC8) -> 0.10759046 | S8: =ABS(EMFX_Data!AA8-EMFX_Data!AD8) -> 0.074026755 | T8: =ABS(EMFX_Data!AB8-EMFX_Data!AC8) -> 0.033343737 | U8: =ABS(EMFX_Data!AB8-EMFX_Data!AD8) -> 0.00021996853 | V8: =ABS(EMFX_Data!AC8-EMFX_Data!AD8) -> 0.033563705 | W8: =IF(ROW()<4+MinObs-1,"",IFERROR((B8-AVERAGE(B$4:B8))/STDEV(B$4:B8),"")) | X8: =IF(ROW()<4+MinObs-1,"",IFERROR((C8-AVERAGE(C$4:C8))/STDEV(C$4:C8),"")) | Y8: =IF(ROW()<4+MinObs-1,"",IFERROR((D8-AVERAGE(D$4:D8))/STDEV(D$4:D8),"")) | Z8: =IF(ROW()<4+MinObs-1,"",IFERROR((E8-AVERAGE(E$4:E8))/STDEV(E$4:E8),"")) | AA8: =IF(ROW()<4+MinObs-1,"",IFERROR((F8-AVERAGE(F$4:F8))/STDEV(F$4:F8),"")) | AB8: =IF(ROW()<4+MinObs-1,"",IFERROR((G8-AVERAGE(G$4:G8))/STDEV(G$4:G8),"")) | AC8: =IF(ROW()<4+MinObs-1,"",IFERROR((H8-AVERAGE(H$4:H8))/STDEV(H$4:H8),"")) | AD8: =IF(ROW()<4+MinObs-1,"",IFERROR((I8-AVERAGE(I$4:I8))/STDEV(I$4:I8),"")) | ... AQ8: =IF(ROW()<4+MinObs-1,"",IFERROR((V8-AVERAGE(V$4:V8))/STDEV(V$4:V8),"")) | AR8: =IF(W8="",0,IF(W8>=z4,w4,IF(W8>=z3,w3,IF(W8>=zEntry,w2,IF(AND(W8>=ExitZ,AR7>0),w2,0))))) -> 0 | AS8: =IF(X8="",0,IF(X8>=z4,w4,IF(X8>=z3,w3,IF(X8>=zEntry,w2,IF(AND(X8>=ExitZ,AS7>0),w2,0))))) -> 0 | AT8: =IF(Y8="",0,IF(Y8>=z4,w4,IF(Y8>=z3,w3,IF(Y8>=zEntry,w2,IF(AND(Y8>=ExitZ,AT7>0),w2,0))))) -> 0 | AU8: =IF(Z8="",0,IF(Z8>=z4,w4,IF(Z8>=z3,w3,IF(Z8>=zEntry,w2,IF(AND(Z8>=ExitZ,AU7>0),w2,0))))) -> 0 | AV8: =IF(AA8="",0,IF(AA8>=z4,w4,IF(AA8>=z3,w3,IF(AA8>=zEntry,w2,IF(AND(AA8>=ExitZ,AV7>0),w2,0))))) -> 0 | AW8: =IF(AB8="",0,IF(AB8>=z4,w4,IF(AB8>=z3,w3,IF(AB8>=zEntry,w2,IF(AND(AB8>=ExitZ,AW7>0),w2,0))))) -> 0 | AX8: =IF(AC8="",0,IF(AC8>=z4,w4,IF(AC8>=z3,w3,IF(AC8>=zEntry,w2,IF(AND(AC8>=ExitZ,AX7>0),w2,0))))) -> 0 | AY8: =IF(AD8="",0,IF(AD8>=z4,w4,IF(AD8>=z3,w3,IF(AD8>=zEntry,w2,IF(AND(AD8>=ExitZ,AY7>0),w2,0))))) -> 0 | ... BL8: =IF(AQ8="",0,IF(AQ8>=z4,w4,IF(AQ8>=z3,w3,IF(AQ8>=zEntry,w2,IF(AND(AQ8>=ExitZ,BL7>0),w2,0))))) -> 0 | BM8: =IF(EMFX_Data!X7>=EMFX_Data!Y7,EMFX_Data!AE8-EMFX_Data!AF8,EMFX_Data!AF8-EMFX_Data!AE8) -> -0.0011007937 | BN8: =IF(EMFX_Data!X7>=EMFX_Data!Z7,EMFX_Data!AE8-EMFX_Data!AG8,EMFX_Data!AG8-EMFX_Data!AE8) -> 0.052678728 | BO8: =IF(EMFX_Data!X7>=EMFX_Data!AA7,EMFX_Data!AE8-EMFX_Data!AH8,EMFX_Data!AH8-EMFX_Data!AE8) -> -0.056425035 | BP8: =IF(EMFX_Data!X7>=EMFX_Data!AB7,EMFX_Data!AE8-EMFX_Data!AI8,EMFX_Data!AI8-EMFX_Data!AE8) -> -0.0032812256 | BQ8: =IF(EMFX_Data!X7>=EMFX_Data!AC7,EMFX_Data!AE8-EMFX_Data!AJ8,EMFX_Data!AJ8-EMFX_Data!AE8) -> 0.031361734 | BR8: =IF(EMFX_Data!X7>=EMFX_Data!AD7,EMFX_Data!AE8-EMFX_Data!AK8,EMFX_Data!AK8-EMFX_Data!AE8) -> -0.0164242 | BS8: =IF(EMFX_Data!Y7>=EMFX_Data!Z7,EMFX_Data!AF8-EMFX_Data!AG8,EMFX_Data!AG8-EMFX_Data!AF8) -> 0.053779521 | BT8: =IF(EMFX_Data!Y7>=EMFX_Data!AA7,EMFX_Data!AF8-EMFX_Data!AH8,EMFX_Data!AH8-EMFX_Data!AF8) -> -0.055324241 | BU8: =IF(EMFX_Data!Y7>=EMFX_Data!AB7,EMFX_Data!AF8-EMFX_Data!AI8,EMFX_Data!AI8-EMFX_Data!AF8) -> -0.0021804319 | BV8: =IF(EMFX_Data!Y7>=EMFX_Data!AC7,EMFX_Data!AF8-EMFX_Data!AJ8,EMFX_Data!AJ8-EMFX_Data!AF8) -> 0.030260941 | BW8: =IF(EMFX_Data!Y7>=EMFX_Data!AD7,EMFX_Data!AF8-EMFX_Data!AK8,EMFX_Data!AK8-EMFX_Data!AF8) -> 0.015323406 | BX8: =IF(EMFX_Data!Z7>=EMFX_Data!AA7,EMFX_Data!AG8-EMFX_Data!AH8,EMFX_Data!AH8-EMFX_Data!AG8) -> -0.10910376 | BY8: =IF(EMFX_Data!Z7>=EMFX_Data!AB7,EMFX_Data!AG8-EMFX_Data!AI8,EMFX_Data!AI8-EMFX_Data!AG8) -> 0.055959953 | BZ8: =IF(EMFX_Data!Z7>=EMFX_Data!AC7,EMFX_Data!AG8-EMFX_Data!AJ8,EMFX_Data!AJ8-EMFX_Data!AG8) -> 0.084040462 | CA8: =IF(EMFX_Data!Z7>=EMFX_Data!AD7,EMFX_Data!AG8-EMFX_Data!AK8,EMFX_Data!AK8-EMFX_Data!AG8) -> 0.069102928 | CB8: =IF(EMFX_Data!AA7>=EMFX_Data!AB7,EMFX_Data!AH8-EMFX_Data!AI8,EMFX_Data!AI8-EMFX_Data!AH8) -> -0.053143809 | CC8: =IF(EMFX_Data!AA7>=EMFX_Data!AC7,EMFX_Data!AH8-EMFX_Data!AJ8,EMFX_Data!AJ8-EMFX_Data!AH8) -> -0.0250633 | CD8: =IF(EMFX_Data!AA7>=EMFX_Data!AD7,EMFX_Data!AH8-EMFX_Data!AK8,EMFX_Data!AK8-EMFX_Data!AH8) -> -0.040000835 | CE8: =IF(EMFX_Data!AB7>=EMFX_Data!AC7,EMFX_Data!AI8-EMFX_Data!AJ8,EMFX_Data!AJ8-EMFX_Data!AI8) -> 0.028080509 | CF8: =IF(EMFX_Data!AB7>=EMFX_Data!AD7,EMFX_Data!AI8-EMFX_Data!AK8,EMFX_Data!AK8-EMFX_Data!AI8) -> 0.013142974 | CG8: =IF(EMFX_Data!AC7>=EMFX_Data!AD7,EMFX_Data!AJ8-EMFX_Data!AK8,EMFX_Data!AK8-EMFX_Data!AJ8) -> 0.014937534 | CH8: =IF(ROW()<4+VolLB,"",STDEV(INDEX($BM:$BM,ROW()-VolLB+1):INDEX($BM:$BM,ROW()))*SQRT(12)) | CI8: =IF(ROW()<4+VolLB,"",STDEV(INDEX($BN:$BN,ROW()-VolLB+1):INDEX($BN:$BN,ROW()))*SQRT(12)) | CJ8: =IF(ROW()<4+VolLB,"",STDEV(INDEX($BO:$BO,ROW()-VolLB+1):INDEX($BO:$BO,ROW()))*SQRT(12)) | CK8: =IF(ROW()<4+VolLB,"",STDEV(INDEX($BP:$BP,ROW()-VolLB+1):INDEX($BP:$BP,ROW()))*SQRT(12)) | CL8: =IF(ROW()<4+VolLB,"",STDEV(INDEX($BQ:$BQ,ROW()-VolLB+1):INDEX($BQ:$BQ,ROW()))*SQRT(12)) | CM8: =IF(ROW()<4+VolLB,"",STDEV(INDEX($BR:$BR,ROW()-VolLB+1):INDEX($BR:$BR,ROW()))*SQRT(12)) | CN8: =IF(ROW()<4+VolLB,"",STDEV(INDEX($BS:$BS,ROW()-VolLB+1):INDEX($BS:$BS,ROW()))*SQRT(12)) | CO8: =IF(ROW()<4+VolLB,"",STDEV(INDEX($BT:$BT,ROW()-VolLB+1):INDEX($BT:$BT,ROW()))*SQRT(12)) | CP8: =IF(ROW()<4+VolLB,"",STDEV(INDEX($BU:$BU,ROW()-VolLB+1):INDEX($BU:$BU,ROW()))*SQRT(12)) | CQ8: =IF(ROW()<4+VolLB,"",STDEV(INDEX($BV:$BV,ROW()-VolLB+1):INDEX($BV:$BV,ROW()))*SQRT(12)) | CR8: =IF(ROW()<4+VolLB,"",STDEV(INDEX($BW:$BW,ROW()-VolLB+1):INDEX($BW:$BW,ROW()))*SQRT(12)) | CS8: =IF(ROW()<4+VolLB,"",STDEV(INDEX($BX:$BX,ROW()-VolLB+1):INDEX($BX:$BX,ROW()))*SQRT(12)) | CT8: =IF(ROW()<4+VolLB,"",STDEV(INDEX($BY:$BY,ROW()-VolLB+1):INDEX($BY:$BY,ROW()))*SQRT(12)) | CU8: =IF(ROW()<4+VolLB,"",STDEV(INDEX($BZ:$BZ,ROW()-VolLB+1):INDEX($BZ:$BZ,ROW()))*SQRT(12)) | CV8: =IF(ROW()<4+VolLB,"",STDEV(INDEX($CA:$CA,ROW()-VolLB+1):INDEX($CA:$CA,ROW()))*SQRT(12)) | CW8: =IF(ROW()<4+VolLB,"",STDEV(INDEX($CB:$CB,ROW()-VolLB+1):INDEX($CB:$CB,ROW()))*SQRT(12)) | CX8: =IF(ROW()<4+VolLB,"",STDEV(INDEX($CC:$CC,ROW()-VolLB+1):INDEX($CC:$CC,ROW()))*SQRT(12)) | CY8: =IF(ROW()<4+VolLB,"",STDEV(INDEX($CD:$CD,ROW()-VolLB+1):INDEX($CD:$CD,ROW()))*SQRT(12)) | CZ8: =IF(ROW()<4+VolLB,"",STDEV(INDEX($CE:$CE,ROW()-VolLB+1):INDEX($CE:$CE,ROW()))*SQRT(12)) | DA8: =IF(ROW()<4+VolLB,"",STDEV(INDEX($CF:$CF,ROW()-VolLB+1):INDEX($CF:$CF,ROW()))*SQRT(12)) | DB8: =IF(ROW()<4+VolLB,"",STDEV(INDEX($CG:$CG,ROW()-VolLB+1):INDEX($CG:$CG,ROW()))*SQRT(12)) | DC8: =IF(OR(AR8=0,CH8="",CH8=0),0,AR8*MIN(MaxScal,TgtVol/CH8)) -> 0 | DD8: =IF(OR(AS8=0,CI8="",CI8=0),0,AS8*MIN(MaxScal,TgtVol/CI8)) -> 0 | DE8: =IF(OR(AT8=0,CJ8="",CJ8=0),0,AT8*MIN(MaxScal,TgtVol/CJ8)) -> 0 | DF8: =IF(OR(AU8=0,CK8="",CK8=0),0,AU8*MIN(MaxScal,TgtVol/CK8)) -> 0 | DG8: =IF(OR(AV8=0,CL8="",CL8=0),0,AV8*MIN(MaxScal,TgtVol/CL8)) -> 0 | DH8: =IF(OR(AW8=0,CM8="",CM8=0),0,AW8*MIN(MaxScal,TgtVol/CM8)) -> 0 | DI8: =IF(OR(AX8=0,CN8="",CN8=0),0,AX8*MIN(MaxScal,TgtVol/CN8)) -> 0 | DJ8: =IF(OR(AY8=0,CO8="",CO8=0),0,AY8*MIN(MaxScal,TgtVol/CO8)) -> 0 | ... DW8: =IF(OR(BL8=0,DB8="",DB8=0),0,BL8*MIN(MaxScal,TgtVol/DB8)) -> 0 | DX8: =IFERROR(DC7*BM8,"") -> 0 | DY8: =IFERROR(DD7*BN8,"") -> 0 | DZ8: =IFERROR(DE7*BO8,"") -> 0 | EA8: =IFERROR(DF7*BP8,"") -> 0 | EB8: =IFERROR(DG7*BQ8,"") -> 0 | EC8: =IFERROR(DH7*BR8,"") -> 0 | ED8: =IFERROR(DI7*BS8,"") -> 0 | EE8: =IFERROR(DJ7*BT8,"") -> 0 | ... ER8: =IFERROR(DW7*CG8,"") -> 0 | ES8: =IF(ROW()=4,"",SUM(DX8:ER8)) -> 0 | ET8: =COUNTIF(AR8:BL8,">0") -> 0
A9: 38168 | B9: =ABS(EMFX_Data!X9-EMFX_Data!Y9) -> 0.037372529 | C9: =ABS(EMFX_Data!X9-EMFX_Data!Z9) -> 0.067613267 | D9: =ABS(EMFX_Data!X9-EMFX_Data!AA9) -> 0.039754038 | E9: =ABS(EMFX_Data!X9-EMFX_Data!AB9) -> 0.037955934 | F9: =ABS(EMFX_Data!X9-EMFX_Data!AC9) -> 0.050666452 | G9: =ABS(EMFX_Data!X9-EMFX_Data!AD9) -> 0.026747505 | H9: =ABS(EMFX_Data!Y9-EMFX_Data!Z9) -> 0.1049858 | I9: =ABS(EMFX_Data!Y9-EMFX_Data!AA9) -> 0.0023815094 | J9: =ABS(EMFX_Data!Y9-EMFX_Data!AB9) -> 0.075328463 | K9: =ABS(EMFX_Data!Y9-EMFX_Data!AC9) -> 0.08803898 | L9: =ABS(EMFX_Data!Y9-EMFX_Data!AD9) -> 0.010625024 | M9: =ABS(EMFX_Data!Z9-EMFX_Data!AA9) -> 0.10736731 | N9: =ABS(EMFX_Data!Z9-EMFX_Data!AB9) -> 0.029657333 | O9: =ABS(EMFX_Data!Z9-EMFX_Data!AC9) -> 0.016946815 | P9: =ABS(EMFX_Data!Z9-EMFX_Data!AD9) -> 0.094360772 | Q9: =ABS(EMFX_Data!AA9-EMFX_Data!AB9) -> 0.077709972 | R9: =ABS(EMFX_Data!AA9-EMFX_Data!AC9) -> 0.09042049 | S9: =ABS(EMFX_Data!AA9-EMFX_Data!AD9) -> 0.013006533 | T9: =ABS(EMFX_Data!AB9-EMFX_Data!AC9) -> 0.012710517 | U9: =ABS(EMFX_Data!AB9-EMFX_Data!AD9) -> 0.064703439 | V9: =ABS(EMFX_Data!AC9-EMFX_Data!AD9) -> 0.077413956 | W9: =IF(ROW()<4+MinObs-1,"",IFERROR((B9-AVERAGE(B$4:B9))/STDEV(B$4:B9),"")) | X9: =IF(ROW()<4+MinObs-1,"",IFERROR((C9-AVERAGE(C$4:C9))/STDEV(C$4:C9),"")) | Y9: =IF(ROW()<4+MinObs-1,"",IFERROR((D9-AVERAGE(D$4:D9))/STDEV(D$4:D9),"")) | Z9: =IF(ROW()<4+MinObs-1,"",IFERROR((E9-AVERAGE(E$4:E9))/STDEV(E$4:E9),"")) | AA9: =IF(ROW()<4+MinObs-1,"",IFERROR((F9-AVERAGE(F$4:F9))/STDEV(F$4:F9),"")) | AB9: =IF(ROW()<4+MinObs-1,"",IFERROR((G9-AVERAGE(G$4:G9))/STDEV(G$4:G9),"")) | AC9: =IF(ROW()<4+MinObs-1,"",IFERROR((H9-AVERAGE(H$4:H9))/STDEV(H$4:H9),"")) | AD9: =IF(ROW()<4+MinObs-1,"",IFERROR((I9-AVERAGE(I$4:I9))/STDEV(I$4:I9),"")) | ... AQ9: =IF(ROW()<4+MinObs-1,"",IFERROR((V9-AVERAGE(V$4:V9))/STDEV(V$4:V9),"")) | AR9: =IF(W9="",0,IF(W9>=z4,w4,IF(W9>=z3,w3,IF(W9>=zEntry,w2,IF(AND(W9>=ExitZ,AR8>0),w2,0))))) -> 0 | AS9: =IF(X9="",0,IF(X9>=z4,w4,IF(X9>=z3,w3,IF(X9>=zEntry,w2,IF(AND(X9>=ExitZ,AS8>0),w2,0))))) -> 0 | AT9: =IF(Y9="",0,IF(Y9>=z4,w4,IF(Y9>=z3,w3,IF(Y9>=zEntry,w2,IF(AND(Y9>=ExitZ,AT8>0),w2,0))))) -> 0 | AU9: =IF(Z9="",0,IF(Z9>=z4,w4,IF(Z9>=z3,w3,IF(Z9>=zEntry,w2,IF(AND(Z9>=ExitZ,AU8>0),w2,0))))) -> 0 | AV9: =IF(AA9="",0,IF(AA9>=z4,w4,IF(AA9>=z3,w3,IF(AA9>=zEntry,w2,IF(AND(AA9>=ExitZ,AV8>0),w2,0))))) -> 0 | AW9: =IF(AB9="",0,IF(AB9>=z4,w4,IF(AB9>=z3,w3,IF(AB9>=zEntry,w2,IF(AND(AB9>=ExitZ,AW8>0),w2,0))))) -> 0 | AX9: =IF(AC9="",0,IF(AC9>=z4,w4,IF(AC9>=z3,w3,IF(AC9>=zEntry,w2,IF(AND(AC9>=ExitZ,AX8>0),w2,0))))) -> 0 | AY9: =IF(AD9="",0,IF(AD9>=z4,w4,IF(AD9>=z3,w3,IF(AD9>=zEntry,w2,IF(AND(AD9>=ExitZ,AY8>0),w2,0))))) -> 0 | ... BL9: =IF(AQ9="",0,IF(AQ9>=z4,w4,IF(AQ9>=z3,w3,IF(AQ9>=zEntry,w2,IF(AND(AQ9>=ExitZ,BL8>0),w2,0))))) -> 0 | BM9: =IF(EMFX_Data!X8>=EMFX_Data!Y8,EMFX_Data!AE9-EMFX_Data!AF9,EMFX_Data!AF9-EMFX_Data!AE9) -> -0.002350943 | BN9: =IF(EMFX_Data!X8>=EMFX_Data!Z8,EMFX_Data!AE9-EMFX_Data!AG9,EMFX_Data!AG9-EMFX_Data!AE9) -> 0.089530287 | BO9: =IF(EMFX_Data!X8>=EMFX_Data!AA8,EMFX_Data!AE9-EMFX_Data!AH9,EMFX_Data!AH9-EMFX_Data!AE9) -> 0.074564303 | BP9: =IF(EMFX_Data!X8>=EMFX_Data!AB8,EMFX_Data!AE9-EMFX_Data!AI9,EMFX_Data!AI9-EMFX_Data!AE9) -> 0.095699011 | BQ9: =IF(EMFX_Data!X8>=EMFX_Data!AC8,EMFX_Data!AE9-EMFX_Data!AJ9,EMFX_Data!AJ9-EMFX_Data!AE9) -> 0.072205762 | BR9: =IF(EMFX_Data!X8>=EMFX_Data!AD8,EMFX_Data!AE9-EMFX_Data!AK9,EMFX_Data!AK9-EMFX_Data!AE9) -> 0.021101537 | BS9: =IF(EMFX_Data!Y8>=EMFX_Data!Z8,EMFX_Data!AF9-EMFX_Data!AG9,EMFX_Data!AG9-EMFX_Data!AF9) -> -0.09188123 | BT9: =IF(EMFX_Data!Y8>=EMFX_Data!AA8,EMFX_Data!AF9-EMFX_Data!AH9,EMFX_Data!AH9-EMFX_Data!AF9) -> 0.076915246 | BU9: =IF(EMFX_Data!Y8>=EMFX_Data!AB8,EMFX_Data!AF9-EMFX_Data!AI9,EMFX_Data!AI9-EMFX_Data!AF9) -> 0.098049954 | BV9: =IF(EMFX_Data!Y8>=EMFX_Data!AC8,EMFX_Data!AF9-EMFX_Data!AJ9,EMFX_Data!AJ9-EMFX_Data!AF9) -> -0.074556704 | BW9: =IF(EMFX_Data!Y8>=EMFX_Data!AD8,EMFX_Data!AF9-EMFX_Data!AK9,EMFX_Data!AK9-EMFX_Data!AF9) -> 0.02345248 | BX9: =IF(EMFX_Data!Z8>=EMFX_Data!AA8,EMFX_Data!AG9-EMFX_Data!AH9,EMFX_Data!AH9-EMFX_Data!AG9) -> -0.014965984 | BY9: =IF(EMFX_Data!Z8>=EMFX_Data!AB8,EMFX_Data!AG9-EMFX_Data!AI9,EMFX_Data!AI9-EMFX_Data!AG9) -> 0.0061687238 | BZ9: =IF(EMFX_Data!Z8>=EMFX_Data!AC8,EMFX_Data!AG9-EMFX_Data!AJ9,EMFX_Data!AJ9-EMFX_Data!AG9) -> -0.017324526 | CA9: =IF(EMFX_Data!Z8>=EMFX_Data!AD8,EMFX_Data!AG9-EMFX_Data!AK9,EMFX_Data!AK9-EMFX_Data!AG9) -> -0.068428751 | CB9: =IF(EMFX_Data!AA8>=EMFX_Data!AB8,EMFX_Data!AH9-EMFX_Data!AI9,EMFX_Data!AI9-EMFX_Data!AH9) -> -0.021134708 | CC9: =IF(EMFX_Data!AA8>=EMFX_Data!AC8,EMFX_Data!AH9-EMFX_Data!AJ9,EMFX_Data!AJ9-EMFX_Data!AH9) -> 0.0023585417 | CD9: =IF(EMFX_Data!AA8>=EMFX_Data!AD8,EMFX_Data!AH9-EMFX_Data!AK9,EMFX_Data!AK9-EMFX_Data!AH9) -> 0.053462767 | CE9: =IF(EMFX_Data!AB8>=EMFX_Data!AC8,EMFX_Data!AI9-EMFX_Data!AJ9,EMFX_Data!AJ9-EMFX_Data!AI9) -> 0.02349325 | CF9: =IF(EMFX_Data!AB8>=EMFX_Data!AD8,EMFX_Data!AI9-EMFX_Data!AK9,EMFX_Data!AK9-EMFX_Data!AI9) -> -0.074597474 | CG9: =IF(EMFX_Data!AC8>=EMFX_Data!AD8,EMFX_Data!AJ9-EMFX_Data!AK9,EMFX_Data!AK9-EMFX_Data!AJ9) -> -0.051104225 | CH9: =IF(ROW()<4+VolLB,"",STDEV(INDEX($BM:$BM,ROW()-VolLB+1):INDEX($BM:$BM,ROW()))*SQRT(12)) | CI9: =IF(ROW()<4+VolLB,"",STDEV(INDEX($BN:$BN,ROW()-VolLB+1):INDEX($BN:$BN,ROW()))*SQRT(12)) | CJ9: =IF(ROW()<4+VolLB,"",STDEV(INDEX($BO:$BO,ROW()-VolLB+1):INDEX($BO:$BO,ROW()))*SQRT(12)) | CK9: =IF(ROW()<4+VolLB,"",STDEV(INDEX($BP:$BP,ROW()-VolLB+1):INDEX($BP:$BP,ROW()))*SQRT(12)) | CL9: =IF(ROW()<4+VolLB,"",STDEV(INDEX($BQ:$BQ,ROW()-VolLB+1):INDEX($BQ:$BQ,ROW()))*SQRT(12)) | CM9: =IF(ROW()<4+VolLB,"",STDEV(INDEX($BR:$BR,ROW()-VolLB+1):INDEX($BR:$BR,ROW()))*SQRT(12)) | CN9: =IF(ROW()<4+VolLB,"",STDEV(INDEX($BS:$BS,ROW()-VolLB+1):INDEX($BS:$BS,ROW()))*SQRT(12)) | CO9: =IF(ROW()<4+VolLB,"",STDEV(INDEX($BT:$BT,ROW()-VolLB+1):INDEX($BT:$BT,ROW()))*SQRT(12)) | CP9: =IF(ROW()<4+VolLB,"",STDEV(INDEX($BU:$BU,ROW()-VolLB+1):INDEX($BU:$BU,ROW()))*SQRT(12)) | CQ9: =IF(ROW()<4+VolLB,"",STDEV(INDEX($BV:$BV,ROW()-VolLB+1):INDEX($BV:$BV,ROW()))*SQRT(12)) | CR9: =IF(ROW()<4+VolLB,"",STDEV(INDEX($BW:$BW,ROW()-VolLB+1):INDEX($BW:$BW,ROW()))*SQRT(12)) | CS9: =IF(ROW()<4+VolLB,"",STDEV(INDEX($BX:$BX,ROW()-VolLB+1):INDEX($BX:$BX,ROW()))*SQRT(12)) | CT9: =IF(ROW()<4+VolLB,"",STDEV(INDEX($BY:$BY,ROW()-VolLB+1):INDEX($BY:$BY,ROW()))*SQRT(12)) | CU9: =IF(ROW()<4+VolLB,"",STDEV(INDEX($BZ:$BZ,ROW()-VolLB+1):INDEX($BZ:$BZ,ROW()))*SQRT(12)) | CV9: =IF(ROW()<4+VolLB,"",STDEV(INDEX($CA:$CA,ROW()-VolLB+1):INDEX($CA:$CA,ROW()))*SQRT(12)) | CW9: =IF(ROW()<4+VolLB,"",STDEV(INDEX($CB:$CB,ROW()-VolLB+1):INDEX($CB:$CB,ROW()))*SQRT(12)) | CX9: =IF(ROW()<4+VolLB,"",STDEV(INDEX($CC:$CC,ROW()-VolLB+1):INDEX($CC:$CC,ROW()))*SQRT(12)) | CY9: =IF(ROW()<4+VolLB,"",STDEV(INDEX($CD:$CD,ROW()-VolLB+1):INDEX($CD:$CD,ROW()))*SQRT(12)) | CZ9: =IF(ROW()<4+VolLB,"",STDEV(INDEX($CE:$CE,ROW()-VolLB+1):INDEX($CE:$CE,ROW()))*SQRT(12)) | DA9: =IF(ROW()<4+VolLB,"",STDEV(INDEX($CF:$CF,ROW()-VolLB+1):INDEX($CF:$CF,ROW()))*SQRT(12)) | DB9: =IF(ROW()<4+VolLB,"",STDEV(INDEX($CG:$CG,ROW()-VolLB+1):INDEX($CG:$CG,ROW()))*SQRT(12)) | DC9: =IF(OR(AR9=0,CH9="",CH9=0),0,AR9*MIN(MaxScal,TgtVol/CH9)) -> 0 | DD9: =IF(OR(AS9=0,CI9="",CI9=0),0,AS9*MIN(MaxScal,TgtVol/CI9)) -> 0 | DE9: =IF(OR(AT9=0,CJ9="",CJ9=0),0,AT9*MIN(MaxScal,TgtVol/CJ9)) -> 0 | DF9: =IF(OR(AU9=0,CK9="",CK9=0),0,AU9*MIN(MaxScal,TgtVol/CK9)) -> 0 | DG9: =IF(OR(AV9=0,CL9="",CL9=0),0,AV9*MIN(MaxScal,TgtVol/CL9)) -> 0 | DH9: =IF(OR(AW9=0,CM9="",CM9=0),0,AW9*MIN(MaxScal,TgtVol/CM9)) -> 0 | DI9: =IF(OR(AX9=0,CN9="",CN9=0),0,AX9*MIN(MaxScal,TgtVol/CN9)) -> 0 | DJ9: =IF(OR(AY9=0,CO9="",CO9=0),0,AY9*MIN(MaxScal,TgtVol/CO9)) -> 0 | ... DW9: =IF(OR(BL9=0,DB9="",DB9=0),0,BL9*MIN(MaxScal,TgtVol/DB9)) -> 0 | DX9: =IFERROR(DC8*BM9,"") -> 0 | DY9: =IFERROR(DD8*BN9,"") -> 0 | DZ9: =IFERROR(DE8*BO9,"") -> 0 | EA9: =IFERROR(DF8*BP9,"") -> 0 | EB9: =IFERROR(DG8*BQ9,"") -> 0 | EC9: =IFERROR(DH8*BR9,"") -> 0 | ED9: =IFERROR(DI8*BS9,"") -> 0 | EE9: =IFERROR(DJ8*BT9,"") -> 0 | ... ER9: =IFERROR(DW8*CG9,"") -> 0 | ES9: =IF(ROW()=4,"",SUM(DX9:ER9)) -> 0 | ET9: =COUNTIF(AR9:BL9,">0") -> 0
A10: 38199 | B10: =ABS(EMFX_Data!X10-EMFX_Data!Y10) -> 0.048725438 | C10: =ABS(EMFX_Data!X10-EMFX_Data!Z10) -> 0.035771009 | D10: =ABS(EMFX_Data!X10-EMFX_Data!AA10) -> 0.038424739 | E10: =ABS(EMFX_Data!X10-EMFX_Data!AB10) -> 0.0075710077 | F10: =ABS(EMFX_Data!X10-EMFX_Data!AC10) -> 0.0043829584 | G10: =ABS(EMFX_Data!X10-EMFX_Data!AD10) -> 0.076788925 | H10: =ABS(EMFX_Data!Y10-EMFX_Data!Z10) -> 0.01295443 | I10: =ABS(EMFX_Data!Y10-EMFX_Data!AA10) -> 0.010300699 | J10: =ABS(EMFX_Data!Y10-EMFX_Data!AB10) -> 0.056296446 | K10: =ABS(EMFX_Data!Y10-EMFX_Data!AC10) -> 0.04434248 | L10: =ABS(EMFX_Data!Y10-EMFX_Data!AD10) -> 0.028063487 | M10: =ABS(EMFX_Data!Z10-EMFX_Data!AA10) -> 0.0026537304 | N10: =ABS(EMFX_Data!Z10-EMFX_Data!AB10) -> 0.043342016 | O10: =ABS(EMFX_Data!Z10-EMFX_Data!AC10) -> 0.03138805 | P10: =ABS(EMFX_Data!Z10-EMFX_Data!AD10) -> 0.041017917 | Q10: =ABS(EMFX_Data!AA10-EMFX_Data!AB10) -> 0.045995747 | R10: =ABS(EMFX_Data!AA10-EMFX_Data!AC10) -> 0.034041781 | S10: =ABS(EMFX_Data!AA10-EMFX_Data!AD10) -> 0.038364186 | T10: =ABS(EMFX_Data!AB10-EMFX_Data!AC10) -> 0.011953966 | U10: =ABS(EMFX_Data!AB10-EMFX_Data!AD10) -> 0.084359933 | V10: =ABS(EMFX_Data!AC10-EMFX_Data!AD10) -> 0.072405967 | W10: =IF(ROW()<4+MinObs-1,"",IFERROR((B10-AVERAGE(B$4:B10))/STDEV(B$4:B10),"")) | X10: =IF(ROW()<4+MinObs-1,"",IFERROR((C10-AVERAGE(C$4:C10))/STDEV(C$4:C10),"")) | Y10: =IF(ROW()<4+MinObs-1,"",IFERROR((D10-AVERAGE(D$4:D10))/STDEV(D$4:D10),"")) | Z10: =IF(ROW()<4+MinObs-1,"",IFERROR((E10-AVERAGE(E$4:E10))/STDEV(E$4:E10),"")) | AA10: =IF(ROW()<4+MinObs-1,"",IFERROR((F10-AVERAGE(F$4:F10))/STDEV(F$4:F10),"")) | AB10: =IF(ROW()<4+MinObs-1,"",IFERROR((G10-AVERAGE(G$4:G10))/STDEV(G$4:G10),"")) | AC10: =IF(ROW()<4+MinObs-1,"",IFERROR((H10-AVERAGE(H$4:H10))/STDEV(H$4:H10),"")) | AD10: =IF(ROW()<4+MinObs-1,"",IFERROR((I10-AVERAGE(I$4:I10))/STDEV(I$4:I10),"")) | ... AQ10: =IF(ROW()<4+MinObs-1,"",IFERROR((V10-AVERAGE(V$4:V10))/STDEV(V$4:V10),"")) | AR10: =IF(W10="",0,IF(W10>=z4,w4,IF(W10>=z3,w3,IF(W10>=zEntry,w2,IF(AND(W10>=ExitZ,AR9>0),w2,0))))) -> 0 | AS10: =IF(X10="",0,IF(X10>=z4,w4,IF(X10>=z3,w3,IF(X10>=zEntry,w2,IF(AND(X10>=ExitZ,AS9>0),w2,0))))) -> 0 | AT10: =IF(Y10="",0,IF(Y10>=z4,w4,IF(Y10>=z3,w3,IF(Y10>=zEntry,w2,IF(AND(Y10>=ExitZ,AT9>0),w2,0))))) -> 0 | AU10: =IF(Z10="",0,IF(Z10>=z4,w4,IF(Z10>=z3,w3,IF(Z10>=zEntry,w2,IF(AND(Z10>=ExitZ,AU9>0),w2,0))))) -> 0 | AV10: =IF(AA10="",0,IF(AA10>=z4,w4,IF(AA10>=z3,w3,IF(AA10>=zEntry,w2,IF(AND(AA10>=ExitZ,AV9>0),w2,0))))) -> 0 | AW10: =IF(AB10="",0,IF(AB10>=z4,w4,IF(AB10>=z3,w3,IF(AB10>=zEntry,w2,IF(AND(AB10>=ExitZ,AW9>0),w2,0))))) -> 0 | AX10: =IF(AC10="",0,IF(AC10>=z4,w4,IF(AC10>=z3,w3,IF(AC10>=zEntry,w2,IF(AND(AC10>=ExitZ,AX9>0),w2,0))))) -> 0 | AY10: =IF(AD10="",0,IF(AD10>=z4,w4,IF(AD10>=z3,w3,IF(AD10>=zEntry,w2,IF(AND(AD10>=ExitZ,AY9>0),w2,0))))) -> 0 | ... BL10: =IF(AQ10="",0,IF(AQ10>=z4,w4,IF(AQ10>=z3,w3,IF(AQ10>=zEntry,w2,IF(AND(AQ10>=ExitZ,BL9>0),w2,0))))) -> 0 | BM10: =IF(EMFX_Data!X9>=EMFX_Data!Y9,EMFX_Data!AE10-EMFX_Data!AF10,EMFX_Data!AF10-EMFX_Data!AE10) -> -0.019082567 | BN10: =IF(EMFX_Data!X9>=EMFX_Data!Z9,EMFX_Data!AE10-EMFX_Data!AG10,EMFX_Data!AG10-EMFX_Data!AE10) -> 0.10883266 | BO10: =IF(EMFX_Data!X9>=EMFX_Data!AA9,EMFX_Data!AE10-EMFX_Data!AH10,EMFX_Data!AH10-EMFX_Data!AE10) -> -0.0026287692 | BP10: =IF(EMFX_Data!X9>=EMFX_Data!AB9,EMFX_Data!AE10-EMFX_Data!AI10,EMFX_Data!AI10-EMFX_Data!AE10) -> 0.027888575 | BQ10: =IF(EMFX_Data!X9>=EMFX_Data!AC9,EMFX_Data!AE10-EMFX_Data!AJ10,EMFX_Data!AJ10-EMFX_Data!AE10) -> 0.061429375 | BR10: =IF(EMFX_Data!X9>=EMFX_Data!AD9,EMFX_Data!AE10-EMFX_Data!AK10,EMFX_Data!AK10-EMFX_Data!AE10) -> -0.058377535 | BS10: =IF(EMFX_Data!Y9>=EMFX_Data!Z9,EMFX_Data!AF10-EMFX_Data!AG10,EMFX_Data!AG10-EMFX_Data!AF10) -> 0.089750096 | BT10: =IF(EMFX_Data!Y9>=EMFX_Data!AA9,EMFX_Data!AF10-EMFX_Data!AH10,EMFX_Data!AH10-EMFX_Data!AF10) -> 0.016453798 | BU10: =IF(EMFX_Data!Y9>=EMFX_Data!AB9,EMFX_Data!AF10-EMFX_Data!AI10,EMFX_Data!AI10-EMFX_Data!AF10) -> 0.0088060078 | BV10: =IF(EMFX_Data!Y9>=EMFX_Data!AC9,EMFX_Data!AF10-EMFX_Data!AJ10,EMFX_Data!AJ10-EMFX_Data!AF10) -> 0.042346808 | BW10: =IF(EMFX_Data!Y9>=EMFX_Data!AD9,EMFX_Data!AF10-EMFX_Data!AK10,EMFX_Data!AK10-EMFX_Data!AF10) -> 0.039294968 | BX10: =IF(EMFX_Data!Z9>=EMFX_Data!AA9,EMFX_Data!AG10-EMFX_Data!AH10,EMFX_Data!AH10-EMFX_Data!AG10) -> 0.10620389 | BY10: =IF(EMFX_Data!Z9>=EMFX_Data!AB9,EMFX_Data!AG10-EMFX_Data!AI10,EMFX_Data!AI10-EMFX_Data!AG10) -> 0.080944088 | BZ10: =IF(EMFX_Data!Z9>=EMFX_Data!AC9,EMFX_Data!AG10-EMFX_Data!AJ10,EMFX_Data!AJ10-EMFX_Data!AG10) -> 0.047403287 | CA10: =IF(EMFX_Data!Z9>=EMFX_Data!AD9,EMFX_Data!AG10-EMFX_Data!AK10,EMFX_Data!AK10-EMFX_Data!AG10) -> 0.050455128 | CB10: =IF(EMFX_Data!AA9>=EMFX_Data!AB9,EMFX_Data!AH10-EMFX_Data!AI10,EMFX_Data!AI10-EMFX_Data!AH10) -> 0.025259805 | CC10: =IF(EMFX_Data!AA9>=EMFX_Data!AC9,EMFX_Data!AH10-EMFX_Data!AJ10,EMFX_Data!AJ10-EMFX_Data!AH10) -> 0.058800606 | CD10: =IF(EMFX_Data!AA9>=EMFX_Data!AD9,EMFX_Data!AH10-EMFX_Data!AK10,EMFX_Data!AK10-EMFX_Data!AH10) -> 0.055748765 | CE10: =IF(EMFX_Data!AB9>=EMFX_Data!AC9,EMFX_Data!AI10-EMFX_Data!AJ10,EMFX_Data!AJ10-EMFX_Data!AI10) -> 0.033540801 | CF10: =IF(EMFX_Data!AB9>=EMFX_Data!AD9,EMFX_Data!AI10-EMFX_Data!AK10,EMFX_Data!AK10-EMFX_Data!AI10) -> -0.03048896 | CG10: =IF(EMFX_Data!AC9>=EMFX_Data!AD9,EMFX_Data!AJ10-EMFX_Data!AK10,EMFX_Data!AK10-EMFX_Data!AJ10) -> 0.0030518406 | CH10: =IF(ROW()<4+VolLB,"",STDEV(INDEX($BM:$BM,ROW()-VolLB+1):INDEX($BM:$BM,ROW()))*SQRT(12)) | CI10: =IF(ROW()<4+VolLB,"",STDEV(INDEX($BN:$BN,ROW()-VolLB+1):INDEX($BN:$BN,ROW()))*SQRT(12)) | CJ10: =IF(ROW()<4+VolLB,"",STDEV(INDEX($BO:$BO,ROW()-VolLB+1):INDEX($BO:$BO,ROW()))*SQRT(12)) | CK10: =IF(ROW()<4+VolLB,"",STDEV(INDEX($BP:$BP,ROW()-VolLB+1):INDEX($BP:$BP,ROW()))*SQRT(12)) | CL10: =IF(ROW()<4+VolLB,"",STDEV(INDEX($BQ:$BQ,ROW()-VolLB+1):INDEX($BQ:$BQ,ROW()))*SQRT(12)) | CM10: =IF(ROW()<4+VolLB,"",STDEV(INDEX($BR:$BR,ROW()-VolLB+1):INDEX($BR:$BR,ROW()))*SQRT(12)) | CN10: =IF(ROW()<4+VolLB,"",STDEV(INDEX($BS:$BS,ROW()-VolLB+1):INDEX($BS:$BS,ROW()))*SQRT(12)) | CO10: =IF(ROW()<4+VolLB,"",STDEV(INDEX($BT:$BT,ROW()-VolLB+1):INDEX($BT:$BT,ROW()))*SQRT(12)) | CP10: =IF(ROW()<4+VolLB,"",STDEV(INDEX($BU:$BU,ROW()-VolLB+1):INDEX($BU:$BU,ROW()))*SQRT(12)) | CQ10: =IF(ROW()<4+VolLB,"",STDEV(INDEX($BV:$BV,ROW()-VolLB+1):INDEX($BV:$BV,ROW()))*SQRT(12)) | CR10: =IF(ROW()<4+VolLB,"",STDEV(INDEX($BW:$BW,ROW()-VolLB+1):INDEX($BW:$BW,ROW()))*SQRT(12)) | CS10: =IF(ROW()<4+VolLB,"",STDEV(INDEX($BX:$BX,ROW()-VolLB+1):INDEX($BX:$BX,ROW()))*SQRT(12)) | CT10: =IF(ROW()<4+VolLB,"",STDEV(INDEX($BY:$BY,ROW()-VolLB+1):INDEX($BY:$BY,ROW()))*SQRT(12)) | CU10: =IF(ROW()<4+VolLB,"",STDEV(INDEX($BZ:$BZ,ROW()-VolLB+1):INDEX($BZ:$BZ,ROW()))*SQRT(12)) | CV10: =IF(ROW()<4+VolLB,"",STDEV(INDEX($CA:$CA,ROW()-VolLB+1):INDEX($CA:$CA,ROW()))*SQRT(12)) | CW10: =IF(ROW()<4+VolLB,"",STDEV(INDEX($CB:$CB,ROW()-VolLB+1):INDEX($CB:$CB,ROW()))*SQRT(12)) | CX10: =IF(ROW()<4+VolLB,"",STDEV(INDEX($CC:$CC,ROW()-VolLB+1):INDEX($CC:$CC,ROW()))*SQRT(12)) | CY10: =IF(ROW()<4+VolLB,"",STDEV(INDEX($CD:$CD,ROW()-VolLB+1):INDEX($CD:$CD,ROW()))*SQRT(12)) | CZ10: =IF(ROW()<4+VolLB,"",STDEV(INDEX($CE:$CE,ROW()-VolLB+1):INDEX($CE:$CE,ROW()))*SQRT(12)) | DA10: =IF(ROW()<4+VolLB,"",STDEV(INDEX($CF:$CF,ROW()-VolLB+1):INDEX($CF:$CF,ROW()))*SQRT(12)) | DB10: =IF(ROW()<4+VolLB,"",STDEV(INDEX($CG:$CG,ROW()-VolLB+1):INDEX($CG:$CG,ROW()))*SQRT(12)) | DC10: =IF(OR(AR10=0,CH10="",CH10=0),0,AR10*MIN(MaxScal,TgtVol/CH10)) -> 0 | DD10: =IF(OR(AS10=0,CI10="",CI10=0),0,AS10*MIN(MaxScal,TgtVol/CI10)) -> 0 | DE10: =IF(OR(AT10=0,CJ10="",CJ10=0),0,AT10*MIN(MaxScal,TgtVol/CJ10)) -> 0 | DF10: =IF(OR(AU10=0,CK10="",CK10=0),0,AU10*MIN(MaxScal,TgtVol/CK10)) -> 0 | DG10: =IF(OR(AV10=0,CL10="",CL10=0),0,AV10*MIN(MaxScal,TgtVol/CL10)) -> 0 | DH10: =IF(OR(AW10=0,CM10="",CM10=0),0,AW10*MIN(MaxScal,TgtVol/CM10)) -> 0 | DI10: =IF(OR(AX10=0,CN10="",CN10=0),0,AX10*MIN(MaxScal,TgtVol/CN10)) -> 0 | DJ10: =IF(OR(AY10=0,CO10="",CO10=0),0,AY10*MIN(MaxScal,TgtVol/CO10)) -> 0 | ... DW10: =IF(OR(BL10=0,DB10="",DB10=0),0,BL10*MIN(MaxScal,TgtVol/DB10)) -> 0 | DX10: =IFERROR(DC9*BM10,"") -> 0 | DY10: =IFERROR(DD9*BN10,"") -> 0 | DZ10: =IFERROR(DE9*BO10,"") -> 0 | EA10: =IFERROR(DF9*BP10,"") -> 0 | EB10: =IFERROR(DG9*BQ10,"") -> 0 | EC10: =IFERROR(DH9*BR10,"") -> 0 | ED10: =IFERROR(DI9*BS10,"") -> 0 | EE10: =IFERROR(DJ9*BT10,"") -> 0 | ... ER10: =IFERROR(DW9*CG10,"") -> 0 | ES10: =IF(ROW()=4,"",SUM(DX10:ER10)) -> 0 | ET10: =COUNTIF(AR10:BL10,">0") -> 0
A11: 38230 | B11: =ABS(EMFX_Data!X11-EMFX_Data!Y11) -> 0.018390527 | C11: =ABS(EMFX_Data!X11-EMFX_Data!Z11) -> 0.0096569428 | D11: =ABS(EMFX_Data!X11-EMFX_Data!AA11) -> 0.097661141 | E11: =ABS(EMFX_Data!X11-EMFX_Data!AB11) -> 0.019837605 | F11: =ABS(EMFX_Data!X11-EMFX_Data!AC11) -> 0.0058192757 | G11: =ABS(EMFX_Data!X11-EMFX_Data!AD11) -> 0.10007839 | H11: =ABS(EMFX_Data!Y11-EMFX_Data!Z11) -> 0.0087335841 | I11: =ABS(EMFX_Data!Y11-EMFX_Data!AA11) -> 0.079270614 | J11: =ABS(EMFX_Data!Y11-EMFX_Data!AB11) -> 0.0014470784 | K11: =ABS(EMFX_Data!Y11-EMFX_Data!AC11) -> 0.024209803 | L11: =ABS(EMFX_Data!Y11-EMFX_Data!AD11) -> 0.081687865 | M11: =ABS(EMFX_Data!Z11-EMFX_Data!AA11) -> 0.088004198 | N11: =ABS(EMFX_Data!Z11-EMFX_Data!AB11) -> 0.010180662 | O11: =ABS(EMFX_Data!Z11-EMFX_Data!AC11) -> 0.015476218 | P11: =ABS(EMFX_Data!Z11-EMFX_Data!AD11) -> 0.090421449 | Q11: =ABS(EMFX_Data!AA11-EMFX_Data!AB11) -> 0.077823535 | R11: =ABS(EMFX_Data!AA11-EMFX_Data!AC11) -> 0.10348042 | S11: =ABS(EMFX_Data!AA11-EMFX_Data!AD11) -> 0.002417251 | T11: =ABS(EMFX_Data!AB11-EMFX_Data!AC11) -> 0.025656881 | U11: =ABS(EMFX_Data!AB11-EMFX_Data!AD11) -> 0.080240786 | V11: =ABS(EMFX_Data!AC11-EMFX_Data!AD11) -> 0.10589767 | W11: =IF(ROW()<4+MinObs-1,"",IFERROR((B11-AVERAGE(B$4:B11))/STDEV(B$4:B11),"")) | X11: =IF(ROW()<4+MinObs-1,"",IFERROR((C11-AVERAGE(C$4:C11))/STDEV(C$4:C11),"")) | Y11: =IF(ROW()<4+MinObs-1,"",IFERROR((D11-AVERAGE(D$4:D11))/STDEV(D$4:D11),"")) | Z11: =IF(ROW()<4+MinObs-1,"",IFERROR((E11-AVERAGE(E$4:E11))/STDEV(E$4:E11),"")) | AA11: =IF(ROW()<4+MinObs-1,"",IFERROR((F11-AVERAGE(F$4:F11))/STDEV(F$4:F11),"")) | AB11: =IF(ROW()<4+MinObs-1,"",IFERROR((G11-AVERAGE(G$4:G11))/STDEV(G$4:G11),"")) | AC11: =IF(ROW()<4+MinObs-1,"",IFERROR((H11-AVERAGE(H$4:H11))/STDEV(H$4:H11),"")) | AD11: =IF(ROW()<4+MinObs-1,"",IFERROR((I11-AVERAGE(I$4:I11))/STDEV(I$4:I11),"")) | ... AQ11: =IF(ROW()<4+MinObs-1,"",IFERROR((V11-AVERAGE(V$4:V11))/STDEV(V$4:V11),"")) | AR11: =IF(W11="",0,IF(W11>=z4,w4,IF(W11>=z3,w3,IF(W11>=zEntry,w2,IF(AND(W11>=ExitZ,AR10>0),w2,0))))) -> 0 | AS11: =IF(X11="",0,IF(X11>=z4,w4,IF(X11>=z3,w3,IF(X11>=zEntry,w2,IF(AND(X11>=ExitZ,AS10>0),w2,0))))) -> 0 | AT11: =IF(Y11="",0,IF(Y11>=z4,w4,IF(Y11>=z3,w3,IF(Y11>=zEntry,w2,IF(AND(Y11>=ExitZ,AT10>0),w2,0))))) -> 0 | AU11: =IF(Z11="",0,IF(Z11>=z4,w4,IF(Z11>=z3,w3,IF(Z11>=zEntry,w2,IF(AND(Z11>=ExitZ,AU10>0),w2,0))))) -> 0 | AV11: =IF(AA11="",0,IF(AA11>=z4,w4,IF(AA11>=z3,w3,IF(AA11>=zEntry,w2,IF(AND(AA11>=ExitZ,AV10>0),w2,0))))) -> 0 | AW11: =IF(AB11="",0,IF(AB11>=z4,w4,IF(AB11>=z3,w3,IF(AB11>=zEntry,w2,IF(AND(AB11>=ExitZ,AW10>0),w2,0))))) -> 0 | AX11: =IF(AC11="",0,IF(AC11>=z4,w4,IF(AC11>=z3,w3,IF(AC11>=zEntry,w2,IF(AND(AC11>=ExitZ,AX10>0),w2,0))))) -> 0 | AY11: =IF(AD11="",0,IF(AD11>=z4,w4,IF(AD11>=z3,w3,IF(AD11>=zEntry,w2,IF(AND(AD11>=ExitZ,AY10>0),w2,0))))) -> 0 | ... BL11: =IF(AQ11="",0,IF(AQ11>=z4,w4,IF(AQ11>=z3,w3,IF(AQ11>=zEntry,w2,IF(AND(AQ11>=ExitZ,BL10>0),w2,0))))) -> 0 | BM11: =IF(EMFX_Data!X10>=EMFX_Data!Y10,EMFX_Data!AE11-EMFX_Data!AF11,EMFX_Data!AF11-EMFX_Data!AE11) -> 0.028431573 | BN11: =IF(EMFX_Data!X10>=EMFX_Data!Z10,EMFX_Data!AE11-EMFX_Data!AG11,EMFX_Data!AG11-EMFX_Data!AE11) -> 0.027040841 | BO11: =IF(EMFX_Data!X10>=EMFX_Data!AA10,EMFX_Data!AE11-EMFX_Data!AH11,EMFX_Data!AH11-EMFX_Data!AE11) -> -0.072260579 | BP11: =IF(EMFX_Data!X10>=EMFX_Data!AB10,EMFX_Data!AE11-EMFX_Data!AI11,EMFX_Data!AI11-EMFX_Data!AE11) -> 0.030322567 | BQ11: =IF(EMFX_Data!X10>=EMFX_Data!AC10,EMFX_Data!AE11-EMFX_Data!AJ11,EMFX_Data!AJ11-EMFX_Data!AE11) -> 0.0021711376 | BR11: =IF(EMFX_Data!X10>=EMFX_Data!AD10,EMFX_Data!AE11-EMFX_Data!AK11,EMFX_Data!AK11-EMFX_Data!AE11) -> -0.034373603 | BS11: =IF(EMFX_Data!Y10>=EMFX_Data!Z10,EMFX_Data!AF11-EMFX_Data!AG11,EMFX_Data!AG11-EMFX_Data!AF11) -> 0.0013907318 | BT11: =IF(EMFX_Data!Y10>=EMFX_Data!AA10,EMFX_Data!AF11-EMFX_Data!AH11,EMFX_Data!AH11-EMFX_Data!AF11) -> 0.10069215 | BU11: =IF(EMFX_Data!Y10>=EMFX_Data!AB10,EMFX_Data!AF11-EMFX_Data!AI11,EMFX_Data!AI11-EMFX_Data!AF11) -> 0.05875414 | BV11: =IF(EMFX_Data!Y10>=EMFX_Data!AC10,EMFX_Data!AF11-EMFX_Data!AJ11,EMFX_Data!AJ11-EMFX_Data!AF11) -> 0.026260435 | BW11: =IF(EMFX_Data!Y10>=EMFX_Data!AD10,EMFX_Data!AF11-EMFX_Data!AK11,EMFX_Data!AK11-EMFX_Data!AF11) -> -0.062805175 | BX11: =IF(EMFX_Data!Z10>=EMFX_Data!AA10,EMFX_Data!AG11-EMFX_Data!AH11,EMFX_Data!AH11-EMFX_Data!AG11) -> -0.09930142 | BY11: =IF(EMFX_Data!Z10>=EMFX_Data!AB10,EMFX_Data!AG11-EMFX_Data!AI11,EMFX_Data!AI11-EMFX_Data!AG11) -> 0.057363408 | BZ11: =IF(EMFX_Data!Z10>=EMFX_Data!AC10,EMFX_Data!AG11-EMFX_Data!AJ11,EMFX_Data!AJ11-EMFX_Data!AG11) -> 0.024869703 | CA11: =IF(EMFX_Data!Z10>=EMFX_Data!AD10,EMFX_Data!AG11-EMFX_Data!AK11,EMFX_Data!AK11-EMFX_Data!AG11) -> -0.061414444 | CB11: =IF(EMFX_Data!AA10>=EMFX_Data!AB10,EMFX_Data!AH11-EMFX_Data!AI11,EMFX_Data!AI11-EMFX_Data!AH11) -> -0.041938012 | CC11: =IF(EMFX_Data!AA10>=EMFX_Data!AC10,EMFX_Data!AH11-EMFX_Data!AJ11,EMFX_Data!AJ11-EMFX_Data!AH11) -> -0.074431717 | CD11: =IF(EMFX_Data!AA10>=EMFX_Data!AD10,EMFX_Data!AH11-EMFX_Data!AK11,EMFX_Data!AK11-EMFX_Data!AH11) -> 0.037886977 | CE11: =IF(EMFX_Data!AB10>=EMFX_Data!AC10,EMFX_Data!AI11-EMFX_Data!AJ11,EMFX_Data!AJ11-EMFX_Data!AI11) -> 0.032493705 | CF11: =IF(EMFX_Data!AB10>=EMFX_Data!AD10,EMFX_Data!AI11-EMFX_Data!AK11,EMFX_Data!AK11-EMFX_Data!AI11) -> -0.0040510351 | CG11: =IF(EMFX_Data!AC10>=EMFX_Data!AD10,EMFX_Data!AJ11-EMFX_Data!AK11,EMFX_Data!AK11-EMFX_Data!AJ11) -> -0.03654474 | CH11: =IF(ROW()<4+VolLB,"",STDEV(INDEX($BM:$BM,ROW()-VolLB+1):INDEX($BM:$BM,ROW()))*SQRT(12)) | CI11: =IF(ROW()<4+VolLB,"",STDEV(INDEX($BN:$BN,ROW()-VolLB+1):INDEX($BN:$BN,ROW()))*SQRT(12)) | CJ11: =IF(ROW()<4+VolLB,"",STDEV(INDEX($BO:$BO,ROW()-VolLB+1):INDEX($BO:$BO,ROW()))*SQRT(12)) | CK11: =IF(ROW()<4+VolLB,"",STDEV(INDEX($BP:$BP,ROW()-VolLB+1):INDEX($BP:$BP,ROW()))*SQRT(12)) | CL11: =IF(ROW()<4+VolLB,"",STDEV(INDEX($BQ:$BQ,ROW()-VolLB+1):INDEX($BQ:$BQ,ROW()))*SQRT(12)) | CM11: =IF(ROW()<4+VolLB,"",STDEV(INDEX($BR:$BR,ROW()-VolLB+1):INDEX($BR:$BR,ROW()))*SQRT(12)) | CN11: =IF(ROW()<4+VolLB,"",STDEV(INDEX($BS:$BS,ROW()-VolLB+1):INDEX($BS:$BS,ROW()))*SQRT(12)) | CO11: =IF(ROW()<4+VolLB,"",STDEV(INDEX($BT:$BT,ROW()-VolLB+1):INDEX($BT:$BT,ROW()))*SQRT(12)) | CP11: =IF(ROW()<4+VolLB,"",STDEV(INDEX($BU:$BU,ROW()-VolLB+1):INDEX($BU:$BU,ROW()))*SQRT(12)) | CQ11: =IF(ROW()<4+VolLB,"",STDEV(INDEX($BV:$BV,ROW()-VolLB+1):INDEX($BV:$BV,ROW()))*SQRT(12)) | CR11: =IF(ROW()<4+VolLB,"",STDEV(INDEX($BW:$BW,ROW()-VolLB+1):INDEX($BW:$BW,ROW()))*SQRT(12)) | CS11: =IF(ROW()<4+VolLB,"",STDEV(INDEX($BX:$BX,ROW()-VolLB+1):INDEX($BX:$BX,ROW()))*SQRT(12)) | CT11: =IF(ROW()<4+VolLB,"",STDEV(INDEX($BY:$BY,ROW()-VolLB+1):INDEX($BY:$BY,ROW()))*SQRT(12)) | CU11: =IF(ROW()<4+VolLB,"",STDEV(INDEX($BZ:$BZ,ROW()-VolLB+1):INDEX($BZ:$BZ,ROW()))*SQRT(12)) | CV11: =IF(ROW()<4+VolLB,"",STDEV(INDEX($CA:$CA,ROW()-VolLB+1):INDEX($CA:$CA,ROW()))*SQRT(12)) | CW11: =IF(ROW()<4+VolLB,"",STDEV(INDEX($CB:$CB,ROW()-VolLB+1):INDEX($CB:$CB,ROW()))*SQRT(12)) | CX11: =IF(ROW()<4+VolLB,"",STDEV(INDEX($CC:$CC,ROW()-VolLB+1):INDEX($CC:$CC,ROW()))*SQRT(12)) | CY11: =IF(ROW()<4+VolLB,"",STDEV(INDEX($CD:$CD,ROW()-VolLB+1):INDEX($CD:$CD,ROW()))*SQRT(12)) | CZ11: =IF(ROW()<4+VolLB,"",STDEV(INDEX($CE:$CE,ROW()-VolLB+1):INDEX($CE:$CE,ROW()))*SQRT(12)) | DA11: =IF(ROW()<4+VolLB,"",STDEV(INDEX($CF:$CF,ROW()-VolLB+1):INDEX($CF:$CF,ROW()))*SQRT(12)) | DB11: =IF(ROW()<4+VolLB,"",STDEV(INDEX($CG:$CG,ROW()-VolLB+1):INDEX($CG:$CG,ROW()))*SQRT(12)) | DC11: =IF(OR(AR11=0,CH11="",CH11=0),0,AR11*MIN(MaxScal,TgtVol/CH11)) -> 0 | DD11: =IF(OR(AS11=0,CI11="",CI11=0),0,AS11*MIN(MaxScal,TgtVol/CI11)) -> 0 | DE11: =IF(OR(AT11=0,CJ11="",CJ11=0),0,AT11*MIN(MaxScal,TgtVol/CJ11)) -> 0 | DF11: =IF(OR(AU11=0,CK11="",CK11=0),0,AU11*MIN(MaxScal,TgtVol/CK11)) -> 0 | DG11: =IF(OR(AV11=0,CL11="",CL11=0),0,AV11*MIN(MaxScal,TgtVol/CL11)) -> 0 | DH11: =IF(OR(AW11=0,CM11="",CM11=0),0,AW11*MIN(MaxScal,TgtVol/CM11)) -> 0 | DI11: =IF(OR(AX11=0,CN11="",CN11=0),0,AX11*MIN(MaxScal,TgtVol/CN11)) -> 0 | DJ11: =IF(OR(AY11=0,CO11="",CO11=0),0,AY11*MIN(MaxScal,TgtVol/CO11)) -> 0 | ... DW11: =IF(OR(BL11=0,DB11="",DB11=0),0,BL11*MIN(MaxScal,TgtVol/DB11)) -> 0 | DX11: =IFERROR(DC10*BM11,"") -> 0 | DY11: =IFERROR(DD10*BN11,"") -> 0 | DZ11: =IFERROR(DE10*BO11,"") -> 0 | EA11: =IFERROR(DF10*BP11,"") -> 0 | EB11: =IFERROR(DG10*BQ11,"") -> 0 | EC11: =IFERROR(DH10*BR11,"") -> 0 | ED11: =IFERROR(DI10*BS11,"") -> 0 | EE11: =IFERROR(DJ10*BT11,"") -> 0 | ... ER11: =IFERROR(DW10*CG11,"") -> 0 | ES11: =IF(ROW()=4,"",SUM(DX11:ER11)) -> 0 | ET11: =COUNTIF(AR11:BL11,">0") -> 0
A12: 38260 | B12: =ABS(EMFX_Data!X12-EMFX_Data!Y12) -> 0.07819538 | C12: =ABS(EMFX_Data!X12-EMFX_Data!Z12) -> 0.025022916 | D12: =ABS(EMFX_Data!X12-EMFX_Data!AA12) -> 0.038407102 | E12: =ABS(EMFX_Data!X12-EMFX_Data!AB12) -> 0.002042631 | F12: =ABS(EMFX_Data!X12-EMFX_Data!AC12) -> 0.0079807421 | G12: =ABS(EMFX_Data!X12-EMFX_Data!AD12) -> 0.055253941 | H12: =ABS(EMFX_Data!Y12-EMFX_Data!Z12) -> 0.1032183 | I12: =ABS(EMFX_Data!Y12-EMFX_Data!AA12) -> 0.11660248 | J12: =ABS(EMFX_Data!Y12-EMFX_Data!AB12) -> 0.080238011 | K12: =ABS(EMFX_Data!Y12-EMFX_Data!AC12) -> 0.070214638 | L12: =ABS(EMFX_Data!Y12-EMFX_Data!AD12) -> 0.13344932 | M12: =ABS(EMFX_Data!Z12-EMFX_Data!AA12) -> 0.013384186 | N12: =ABS(EMFX_Data!Z12-EMFX_Data!AB12) -> 0.022980285 | O12: =ABS(EMFX_Data!Z12-EMFX_Data!AC12) -> 0.033003658 | P12: =ABS(EMFX_Data!Z12-EMFX_Data!AD12) -> 0.030231025 | Q12: =ABS(EMFX_Data!AA12-EMFX_Data!AB12) -> 0.036364471 | R12: =ABS(EMFX_Data!AA12-EMFX_Data!AC12) -> 0.046387844 | S12: =ABS(EMFX_Data!AA12-EMFX_Data!AD12) -> 0.016846839 | T12: =ABS(EMFX_Data!AB12-EMFX_Data!AC12) -> 0.010023373 | U12: =ABS(EMFX_Data!AB12-EMFX_Data!AD12) -> 0.05321131 | V12: =ABS(EMFX_Data!AC12-EMFX_Data!AD12) -> 0.063234683 | W12: =IF(ROW()<4+MinObs-1,"",IFERROR((B12-AVERAGE(B$4:B12))/STDEV(B$4:B12),"")) | X12: =IF(ROW()<4+MinObs-1,"",IFERROR((C12-AVERAGE(C$4:C12))/STDEV(C$4:C12),"")) | Y12: =IF(ROW()<4+MinObs-1,"",IFERROR((D12-AVERAGE(D$4:D12))/STDEV(D$4:D12),"")) | Z12: =IF(ROW()<4+MinObs-1,"",IFERROR((E12-AVERAGE(E$4:E12))/STDEV(E$4:E12),"")) | AA12: =IF(ROW()<4+MinObs-1,"",IFERROR((F12-AVERAGE(F$4:F12))/STDEV(F$4:F12),"")) | AB12: =IF(ROW()<4+MinObs-1,"",IFERROR((G12-AVERAGE(G$4:G12))/STDEV(G$4:G12),"")) | AC12: =IF(ROW()<4+MinObs-1,"",IFERROR((H12-AVERAGE(H$4:H12))/STDEV(H$4:H12),"")) | AD12: =IF(ROW()<4+MinObs-1,"",IFERROR((I12-AVERAGE(I$4:I12))/STDEV(I$4:I12),"")) | ... AQ12: =IF(ROW()<4+MinObs-1,"",IFERROR((V12-AVERAGE(V$4:V12))/STDEV(V$4:V12),"")) | AR12: =IF(W12="",0,IF(W12>=z4,w4,IF(W12>=z3,w3,IF(W12>=zEntry,w2,IF(AND(W12>=ExitZ,AR11>0),w2,0))))) -> 0 | AS12: =IF(X12="",0,IF(X12>=z4,w4,IF(X12>=z3,w3,IF(X12>=zEntry,w2,IF(AND(X12>=ExitZ,AS11>0),w2,0))))) -> 0 | AT12: =IF(Y12="",0,IF(Y12>=z4,w4,IF(Y12>=z3,w3,IF(Y12>=zEntry,w2,IF(AND(Y12>=ExitZ,AT11>0),w2,0))))) -> 0 | AU12: =IF(Z12="",0,IF(Z12>=z4,w4,IF(Z12>=z3,w3,IF(Z12>=zEntry,w2,IF(AND(Z12>=ExitZ,AU11>0),w2,0))))) -> 0 | AV12: =IF(AA12="",0,IF(AA12>=z4,w4,IF(AA12>=z3,w3,IF(AA12>=zEntry,w2,IF(AND(AA12>=ExitZ,AV11>0),w2,0))))) -> 0 | AW12: =IF(AB12="",0,IF(AB12>=z4,w4,IF(AB12>=z3,w3,IF(AB12>=zEntry,w2,IF(AND(AB12>=ExitZ,AW11>0),w2,0))))) -> 0 | AX12: =IF(AC12="",0,IF(AC12>=z4,w4,IF(AC12>=z3,w3,IF(AC12>=zEntry,w2,IF(AND(AC12>=ExitZ,AX11>0),w2,0))))) -> 0 | AY12: =IF(AD12="",0,IF(AD12>=z4,w4,IF(AD12>=z3,w3,IF(AD12>=zEntry,w2,IF(AND(AD12>=ExitZ,AY11>0),w2,0))))) -> 0 | ... BL12: =IF(AQ12="",0,IF(AQ12>=z4,w4,IF(AQ12>=z3,w3,IF(AQ12>=zEntry,w2,IF(AND(AQ12>=ExitZ,BL11>0),w2,0))))) -> 0 | BM12: =IF(EMFX_Data!X11>=EMFX_Data!Y11,EMFX_Data!AE12-EMFX_Data!AF12,EMFX_Data!AF12-EMFX_Data!AE12) -> 0.10798747 | BN12: =IF(EMFX_Data!X11>=EMFX_Data!Z11,EMFX_Data!AE12-EMFX_Data!AG12,EMFX_Data!AG12-EMFX_Data!AE12) -> -0.014471971 | BO12: =IF(EMFX_Data!X11>=EMFX_Data!AA11,EMFX_Data!AE12-EMFX_Data!AH12,EMFX_Data!AH12-EMFX_Data!AE12) -> 0.05720849 | BP12: =IF(EMFX_Data!X11>=EMFX_Data!AB11,EMFX_Data!AE12-EMFX_Data!AI12,EMFX_Data!AI12-EMFX_Data!AE12) -> 0.017148597 | BQ12: =IF(EMFX_Data!X11>=EMFX_Data!AC11,EMFX_Data!AE12-EMFX_Data!AJ12,EMFX_Data!AJ12-EMFX_Data!AE12) -> 0.0026066946 | BR12: =IF(EMFX_Data!X11>=EMFX_Data!AD11,EMFX_Data!AE12-EMFX_Data!AK12,EMFX_Data!AK12-EMFX_Data!AE12) -> 0.039178045 | BS12: =IF(EMFX_Data!Y11>=EMFX_Data!Z11,EMFX_Data!AF12-EMFX_Data!AG12,EMFX_Data!AG12-EMFX_Data!AF12) -> 0.12245944 | BT12: =IF(EMFX_Data!Y11>=EMFX_Data!AA11,EMFX_Data!AF12-EMFX_Data!AH12,EMFX_Data!AH12-EMFX_Data!AF12) -> -0.050778978 | BU12: =IF(EMFX_Data!Y11>=EMFX_Data!AB11,EMFX_Data!AF12-EMFX_Data!AI12,EMFX_Data!AI12-EMFX_Data!AF12) -> -0.09083887 | BV12: =IF(EMFX_Data!Y11>=EMFX_Data!AC11,EMFX_Data!AF12-EMFX_Data!AJ12,EMFX_Data!AJ12-EMFX_Data!AF12) -> 0.11059416 | BW12: =IF(EMFX_Data!Y11>=EMFX_Data!AD11,EMFX_Data!AF12-EMFX_Data!AK12,EMFX_Data!AK12-EMFX_Data!AF12) -> -0.068809422 | BX12: =IF(EMFX_Data!Z11>=EMFX_Data!AA11,EMFX_Data!AG12-EMFX_Data!AH12,EMFX_Data!AH12-EMFX_Data!AG12) -> 0.071680461 | BY12: =IF(EMFX_Data!Z11>=EMFX_Data!AB11,EMFX_Data!AG12-EMFX_Data!AI12,EMFX_Data!AI12-EMFX_Data!AG12) -> 0.031620569 | BZ12: =IF(EMFX_Data!Z11>=EMFX_Data!AC11,EMFX_Data!AG12-EMFX_Data!AJ12,EMFX_Data!AJ12-EMFX_Data!AG12) -> -0.011865277 | CA12: =IF(EMFX_Data!Z11>=EMFX_Data!AD11,EMFX_Data!AG12-EMFX_Data!AK12,EMFX_Data!AK12-EMFX_Data!AG12) -> 0.053650017 | CB12: =IF(EMFX_Data!AA11>=EMFX_Data!AB11,EMFX_Data!AH12-EMFX_Data!AI12,EMFX_Data!AI12-EMFX_Data!AH12) -> 0.040059892 | CC12: =IF(EMFX_Data!AA11>=EMFX_Data!AC11,EMFX_Data!AH12-EMFX_Data!AJ12,EMFX_Data!AJ12-EMFX_Data!AH12) -> 0.059815184 | CD12: =IF(EMFX_Data!AA11>=EMFX_Data!AD11,EMFX_Data!AH12-EMFX_Data!AK12,EMFX_Data!AK12-EMFX_Data!AH12) -> -0.018030445 | CE12: =IF(EMFX_Data!AB11>=EMFX_Data!AC11,EMFX_Data!AI12-EMFX_Data!AJ12,EMFX_Data!AJ12-EMFX_Data!AI12) -> 0.019755292 | CF12: =IF(EMFX_Data!AB11>=EMFX_Data!AD11,EMFX_Data!AI12-EMFX_Data!AK12,EMFX_Data!AK12-EMFX_Data!AI12) -> 0.022029448 | CG12: =IF(EMFX_Data!AC11>=EMFX_Data!AD11,EMFX_Data!AJ12-EMFX_Data!AK12,EMFX_Data!AK12-EMFX_Data!AJ12) -> 0.04178474 | CH12: =IF(ROW()<4+VolLB,"",STDEV(INDEX($BM:$BM,ROW()-VolLB+1):INDEX($BM:$BM,ROW()))*SQRT(12)) | CI12: =IF(ROW()<4+VolLB,"",STDEV(INDEX($BN:$BN,ROW()-VolLB+1):INDEX($BN:$BN,ROW()))*SQRT(12)) | CJ12: =IF(ROW()<4+VolLB,"",STDEV(INDEX($BO:$BO,ROW()-VolLB+1):INDEX($BO:$BO,ROW()))*SQRT(12)) | CK12: =IF(ROW()<4+VolLB,"",STDEV(INDEX($BP:$BP,ROW()-VolLB+1):INDEX($BP:$BP,ROW()))*SQRT(12)) | CL12: =IF(ROW()<4+VolLB,"",STDEV(INDEX($BQ:$BQ,ROW()-VolLB+1):INDEX($BQ:$BQ,ROW()))*SQRT(12)) | CM12: =IF(ROW()<4+VolLB,"",STDEV(INDEX($BR:$BR,ROW()-VolLB+1):INDEX($BR:$BR,ROW()))*SQRT(12)) | CN12: =IF(ROW()<4+VolLB,"",STDEV(INDEX($BS:$BS,ROW()-VolLB+1):INDEX($BS:$BS,ROW()))*SQRT(12)) | CO12: =IF(ROW()<4+VolLB,"",STDEV(INDEX($BT:$BT,ROW()-VolLB+1):INDEX($BT:$BT,ROW()))*SQRT(12)) | CP12: =IF(ROW()<4+VolLB,"",STDEV(INDEX($BU:$BU,ROW()-VolLB+1):INDEX($BU:$BU,ROW()))*SQRT(12)) | CQ12: =IF(ROW()<4+VolLB,"",STDEV(INDEX($BV:$BV,ROW()-VolLB+1):INDEX($BV:$BV,ROW()))*SQRT(12)) | CR12: =IF(ROW()<4+VolLB,"",STDEV(INDEX($BW:$BW,ROW()-VolLB+1):INDEX($BW:$BW,ROW()))*SQRT(12)) | CS12: =IF(ROW()<4+VolLB,"",STDEV(INDEX($BX:$BX,ROW()-VolLB+1):INDEX($BX:$BX,ROW()))*SQRT(12)) | CT12: =IF(ROW()<4+VolLB,"",STDEV(INDEX($BY:$BY,ROW()-VolLB+1):INDEX($BY:$BY,ROW()))*SQRT(12)) | CU12: =IF(ROW()<4+VolLB,"",STDEV(INDEX($BZ:$BZ,ROW()-VolLB+1):INDEX($BZ:$BZ,ROW()))*SQRT(12)) | CV12: =IF(ROW()<4+VolLB,"",STDEV(INDEX($CA:$CA,ROW()-VolLB+1):INDEX($CA:$CA,ROW()))*SQRT(12)) | CW12: =IF(ROW()<4+VolLB,"",STDEV(INDEX($CB:$CB,ROW()-VolLB+1):INDEX($CB:$CB,ROW()))*SQRT(12)) | CX12: =IF(ROW()<4+VolLB,"",STDEV(INDEX($CC:$CC,ROW()-VolLB+1):INDEX($CC:$CC,ROW()))*SQRT(12)) | CY12: =IF(ROW()<4+VolLB,"",STDEV(INDEX($CD:$CD,ROW()-VolLB+1):INDEX($CD:$CD,ROW()))*SQRT(12)) | CZ12: =IF(ROW()<4+VolLB,"",STDEV(INDEX($CE:$CE,ROW()-VolLB+1):INDEX($CE:$CE,ROW()))*SQRT(12)) | DA12: =IF(ROW()<4+VolLB,"",STDEV(INDEX($CF:$CF,ROW()-VolLB+1):INDEX($CF:$CF,ROW()))*SQRT(12)) | DB12: =IF(ROW()<4+VolLB,"",STDEV(INDEX($CG:$CG,ROW()-VolLB+1):INDEX($CG:$CG,ROW()))*SQRT(12)) | DC12: =IF(OR(AR12=0,CH12="",CH12=0),0,AR12*MIN(MaxScal,TgtVol/CH12)) -> 0 | DD12: =IF(OR(AS12=0,CI12="",CI12=0),0,AS12*MIN(MaxScal,TgtVol/CI12)) -> 0 | DE12: =IF(OR(AT12=0,CJ12="",CJ12=0),0,AT12*MIN(MaxScal,TgtVol/CJ12)) -> 0 | DF12: =IF(OR(AU12=0,CK12="",CK12=0),0,AU12*MIN(MaxScal,TgtVol/CK12)) -> 0 | DG12: =IF(OR(AV12=0,CL12="",CL12=0),0,AV12*MIN(MaxScal,TgtVol/CL12)) -> 0 | DH12: =IF(OR(AW12=0,CM12="",CM12=0),0,AW12*MIN(MaxScal,TgtVol/CM12)) -> 0 | DI12: =IF(OR(AX12=0,CN12="",CN12=0),0,AX12*MIN(MaxScal,TgtVol/CN12)) -> 0 | DJ12: =IF(OR(AY12=0,CO12="",CO12=0),0,AY12*MIN(MaxScal,TgtVol/CO12)) -> 0 | ... DW12: =IF(OR(BL12=0,DB12="",DB12=0),0,BL12*MIN(MaxScal,TgtVol/DB12)) -> 0 | DX12: =IFERROR(DC11*BM12,"") -> 0 | DY12: =IFERROR(DD11*BN12,"") -> 0 | DZ12: =IFERROR(DE11*BO12,"") -> 0 | EA12: =IFERROR(DF11*BP12,"") -> 0 | EB12: =IFERROR(DG11*BQ12,"") -> 0 | EC12: =IFERROR(DH11*BR12,"") -> 0 | ED12: =IFERROR(DI11*BS12,"") -> 0 | EE12: =IFERROR(DJ11*BT12,"") -> 0 | ... ER12: =IFERROR(DW11*CG12,"") -> 0 | ES12: =IF(ROW()=4,"",SUM(DX12:ER12)) -> 0 | ET12: =COUNTIF(AR12:BL12,">0") -> 0
A13: 38291 | B13: =ABS(EMFX_Data!X13-EMFX_Data!Y13) -> 0.12045288 | C13: =ABS(EMFX_Data!X13-EMFX_Data!Z13) -> 0.033841772 | D13: =ABS(EMFX_Data!X13-EMFX_Data!AA13) -> 0.030910723 | E13: =ABS(EMFX_Data!X13-EMFX_Data!AB13) -> 0.039879509 | F13: =ABS(EMFX_Data!X13-EMFX_Data!AC13) -> 0.032074094 | G13: =ABS(EMFX_Data!X13-EMFX_Data!AD13) -> 0.062143154 | H13: =ABS(EMFX_Data!Y13-EMFX_Data!Z13) -> 0.15429466 | I13: =ABS(EMFX_Data!Y13-EMFX_Data!AA13) -> 0.15136361 | J13: =ABS(EMFX_Data!Y13-EMFX_Data!AB13) -> 0.16033239 | K13: =ABS(EMFX_Data!Y13-EMFX_Data!AC13) -> 0.088378791 | L13: =ABS(EMFX_Data!Y13-EMFX_Data!AD13) -> 0.05830973 | M13: =ABS(EMFX_Data!Z13-EMFX_Data!AA13) -> 0.0029310494 | N13: =ABS(EMFX_Data!Z13-EMFX_Data!AB13) -> 0.0060377369 | O13: =ABS(EMFX_Data!Z13-EMFX_Data!AC13) -> 0.065915866 | P13: =ABS(EMFX_Data!Z13-EMFX_Data!AD13) -> 0.095984926 | Q13: =ABS(EMFX_Data!AA13-EMFX_Data!AB13) -> 0.0089687863 | R13: =ABS(EMFX_Data!AA13-EMFX_Data!AC13) -> 0.062984817 | S13: =ABS(EMFX_Data!AA13-EMFX_Data!AD13) -> 0.093053877 | T13: =ABS(EMFX_Data!AB13-EMFX_Data!AC13) -> 0.071953603 | U13: =ABS(EMFX_Data!AB13-EMFX_Data!AD13) -> 0.10202266 | V13: =ABS(EMFX_Data!AC13-EMFX_Data!AD13) -> 0.03006906 | W13: =IF(ROW()<4+MinObs-1,"",IFERROR((B13-AVERAGE(B$4:B13))/STDEV(B$4:B13),"")) | X13: =IF(ROW()<4+MinObs-1,"",IFERROR((C13-AVERAGE(C$4:C13))/STDEV(C$4:C13),"")) | Y13: =IF(ROW()<4+MinObs-1,"",IFERROR((D13-AVERAGE(D$4:D13))/STDEV(D$4:D13),"")) | Z13: =IF(ROW()<4+MinObs-1,"",IFERROR((E13-AVERAGE(E$4:E13))/STDEV(E$4:E13),"")) | AA13: =IF(ROW()<4+MinObs-1,"",IFERROR((F13-AVERAGE(F$4:F13))/STDEV(F$4:F13),"")) | AB13: =IF(ROW()<4+MinObs-1,"",IFERROR((G13-AVERAGE(G$4:G13))/STDEV(G$4:G13),"")) | AC13: =IF(ROW()<4+MinObs-1,"",IFERROR((H13-AVERAGE(H$4:H13))/STDEV(H$4:H13),"")) | AD13: =IF(ROW()<4+MinObs-1,"",IFERROR((I13-AVERAGE(I$4:I13))/STDEV(I$4:I13),"")) | ... AQ13: =IF(ROW()<4+MinObs-1,"",IFERROR((V13-AVERAGE(V$4:V13))/STDEV(V$4:V13),"")) | AR13: =IF(W13="",0,IF(W13>=z4,w4,IF(W13>=z3,w3,IF(W13>=zEntry,w2,IF(AND(W13>=ExitZ,AR12>0),w2,0))))) -> 0 | AS13: =IF(X13="",0,IF(X13>=z4,w4,IF(X13>=z3,w3,IF(X13>=zEntry,w2,IF(AND(X13>=ExitZ,AS12>0),w2,0))))) -> 0 | AT13: =IF(Y13="",0,IF(Y13>=z4,w4,IF(Y13>=z3,w3,IF(Y13>=zEntry,w2,IF(AND(Y13>=ExitZ,AT12>0),w2,0))))) -> 0 | AU13: =IF(Z13="",0,IF(Z13>=z4,w4,IF(Z13>=z3,w3,IF(Z13>=zEntry,w2,IF(AND(Z13>=ExitZ,AU12>0),w2,0))))) -> 0 | AV13: =IF(AA13="",0,IF(AA13>=z4,w4,IF(AA13>=z3,w3,IF(AA13>=zEntry,w2,IF(AND(AA13>=ExitZ,AV12>0),w2,0))))) -> 0 | AW13: =IF(AB13="",0,IF(AB13>=z4,w4,IF(AB13>=z3,w3,IF(AB13>=zEntry,w2,IF(AND(AB13>=ExitZ,AW12>0),w2,0))))) -> 0 | AX13: =IF(AC13="",0,IF(AC13>=z4,w4,IF(AC13>=z3,w3,IF(AC13>=zEntry,w2,IF(AND(AC13>=ExitZ,AX12>0),w2,0))))) -> 0 | AY13: =IF(AD13="",0,IF(AD13>=z4,w4,IF(AD13>=z3,w3,IF(AD13>=zEntry,w2,IF(AND(AD13>=ExitZ,AY12>0),w2,0))))) -> 0 | ... BL13: =IF(AQ13="",0,IF(AQ13>=z4,w4,IF(AQ13>=z3,w3,IF(AQ13>=zEntry,w2,IF(AND(AQ13>=ExitZ,BL12>0),w2,0))))) -> 0 | BM13: =IF(EMFX_Data!X12>=EMFX_Data!Y12,EMFX_Data!AE13-EMFX_Data!AF13,EMFX_Data!AF13-EMFX_Data!AE13) -> -0.055418708 | BN13: =IF(EMFX_Data!X12>=EMFX_Data!Z12,EMFX_Data!AE13-EMFX_Data!AG13,EMFX_Data!AG13-EMFX_Data!AE13) -> -0.010334792 | BO13: =IF(EMFX_Data!X12>=EMFX_Data!AA12,EMFX_Data!AE13-EMFX_Data!AH13,EMFX_Data!AH13-EMFX_Data!AE13) -> 0.0054671364 | BP13: =IF(EMFX_Data!X12>=EMFX_Data!AB12,EMFX_Data!AE13-EMFX_Data!AI13,EMFX_Data!AI13-EMFX_Data!AE13) -> -0.044724268 | BQ13: =IF(EMFX_Data!X12>=EMFX_Data!AC12,EMFX_Data!AE13-EMFX_Data!AJ13,EMFX_Data!AJ13-EMFX_Data!AE13) -> -0.021220554 | BR13: =IF(EMFX_Data!X12>=EMFX_Data!AD12,EMFX_Data!AE13-EMFX_Data!AK13,EMFX_Data!AK13-EMFX_Data!AE13) -> 0.12669214 | BS13: =IF(EMFX_Data!Y12>=EMFX_Data!Z12,EMFX_Data!AF13-EMFX_Data!AG13,EMFX_Data!AG13-EMFX_Data!AF13) -> -0.065753499 | BT13: =IF(EMFX_Data!Y12>=EMFX_Data!AA12,EMFX_Data!AF13-EMFX_Data!AH13,EMFX_Data!AH13-EMFX_Data!AF13) -> -0.049951571 | BU13: =IF(EMFX_Data!Y12>=EMFX_Data!AB12,EMFX_Data!AF13-EMFX_Data!AI13,EMFX_Data!AI13-EMFX_Data!AF13) -> -0.10014298 | BV13: =IF(EMFX_Data!Y12>=EMFX_Data!AC12,EMFX_Data!AF13-EMFX_Data!AJ13,EMFX_Data!AJ13-EMFX_Data!AF13) -> -0.034198154 | BW13: =IF(EMFX_Data!Y12>=EMFX_Data!AD12,EMFX_Data!AF13-EMFX_Data!AK13,EMFX_Data!AK13-EMFX_Data!AF13) -> 0.071273434 | BX13: =IF(EMFX_Data!Z12>=EMFX_Data!AA12,EMFX_Data!AG13-EMFX_Data!AH13,EMFX_Data!AH13-EMFX_Data!AG13) -> 0.015801928 | BY13: =IF(EMFX_Data!Z12>=EMFX_Data!AB12,EMFX_Data!AG13-EMFX_Data!AI13,EMFX_Data!AI13-EMFX_Data!AG13) -> 0.034389477 | BZ13: =IF(EMFX_Data!Z12>=EMFX_Data!AC12,EMFX_Data!AG13-EMFX_Data!AJ13,EMFX_Data!AJ13-EMFX_Data!AG13) -> -0.031555345 | CA13: =IF(EMFX_Data!Z12>=EMFX_Data!AD12,EMFX_Data!AG13-EMFX_Data!AK13,EMFX_Data!AK13-EMFX_Data!AG13) -> 0.13702693 | CB13: =IF(EMFX_Data!AA12>=EMFX_Data!AB12,EMFX_Data!AH13-EMFX_Data!AI13,EMFX_Data!AI13-EMFX_Data!AH13) -> 0.050191405 | CC13: =IF(EMFX_Data!AA12>=EMFX_Data!AC12,EMFX_Data!AH13-EMFX_Data!AJ13,EMFX_Data!AJ13-EMFX_Data!AH13) -> -0.015753417 | CD13: =IF(EMFX_Data!AA12>=EMFX_Data!AD12,EMFX_Data!AH13-EMFX_Data!AK13,EMFX_Data!AK13-EMFX_Data!AH13) -> 0.12122501 | CE13: =IF(EMFX_Data!AB12>=EMFX_Data!AC12,EMFX_Data!AI13-EMFX_Data!AJ13,EMFX_Data!AJ13-EMFX_Data!AI13) -> -0.065944822 | CF13: =IF(EMFX_Data!AB12>=EMFX_Data!AD12,EMFX_Data!AI13-EMFX_Data!AK13,EMFX_Data!AK13-EMFX_Data!AI13) -> 0.17141641 | CG13: =IF(EMFX_Data!AC12>=EMFX_Data!AD12,EMFX_Data!AJ13-EMFX_Data!AK13,EMFX_Data!AK13-EMFX_Data!AJ13) -> 0.10547159 | CH13: =IF(ROW()<4+VolLB,"",STDEV(INDEX($BM:$BM,ROW()-VolLB+1):INDEX($BM:$BM,ROW()))*SQRT(12)) | CI13: =IF(ROW()<4+VolLB,"",STDEV(INDEX($BN:$BN,ROW()-VolLB+1):INDEX($BN:$BN,ROW()))*SQRT(12)) | CJ13: =IF(ROW()<4+VolLB,"",STDEV(INDEX($BO:$BO,ROW()-VolLB+1):INDEX($BO:$BO,ROW()))*SQRT(12)) | CK13: =IF(ROW()<4+VolLB,"",STDEV(INDEX($BP:$BP,ROW()-VolLB+1):INDEX($BP:$BP,ROW()))*SQRT(12)) | CL13: =IF(ROW()<4+VolLB,"",STDEV(INDEX($BQ:$BQ,ROW()-VolLB+1):INDEX($BQ:$BQ,ROW()))*SQRT(12)) | CM13: =IF(ROW()<4+VolLB,"",STDEV(INDEX($BR:$BR,ROW()-VolLB+1):INDEX($BR:$BR,ROW()))*SQRT(12)) | CN13: =IF(ROW()<4+VolLB,"",STDEV(INDEX($BS:$BS,ROW()-VolLB+1):INDEX($BS:$BS,ROW()))*SQRT(12)) | CO13: =IF(ROW()<4+VolLB,"",STDEV(INDEX($BT:$BT,ROW()-VolLB+1):INDEX($BT:$BT,ROW()))*SQRT(12)) | CP13: =IF(ROW()<4+VolLB,"",STDEV(INDEX($BU:$BU,ROW()-VolLB+1):INDEX($BU:$BU,ROW()))*SQRT(12)) | CQ13: =IF(ROW()<4+VolLB,"",STDEV(INDEX($BV:$BV,ROW()-VolLB+1):INDEX($BV:$BV,ROW()))*SQRT(12)) | CR13: =IF(ROW()<4+VolLB,"",STDEV(INDEX($BW:$BW,ROW()-VolLB+1):INDEX($BW:$BW,ROW()))*SQRT(12)) | CS13: =IF(ROW()<4+VolLB,"",STDEV(INDEX($BX:$BX,ROW()-VolLB+1):INDEX($BX:$BX,ROW()))*SQRT(12)) | CT13: =IF(ROW()<4+VolLB,"",STDEV(INDEX($BY:$BY,ROW()-VolLB+1):INDEX($BY:$BY,ROW()))*SQRT(12)) | CU13: =IF(ROW()<4+VolLB,"",STDEV(INDEX($BZ:$BZ,ROW()-VolLB+1):INDEX($BZ:$BZ,ROW()))*SQRT(12)) | CV13: =IF(ROW()<4+VolLB,"",STDEV(INDEX($CA:$CA,ROW()-VolLB+1):INDEX($CA:$CA,ROW()))*SQRT(12)) | CW13: =IF(ROW()<4+VolLB,"",STDEV(INDEX($CB:$CB,ROW()-VolLB+1):INDEX($CB:$CB,ROW()))*SQRT(12)) | CX13: =IF(ROW()<4+VolLB,"",STDEV(INDEX($CC:$CC,ROW()-VolLB+1):INDEX($CC:$CC,ROW()))*SQRT(12)) | CY13: =IF(ROW()<4+VolLB,"",STDEV(INDEX($CD:$CD,ROW()-VolLB+1):INDEX($CD:$CD,ROW()))*SQRT(12)) | CZ13: =IF(ROW()<4+VolLB,"",STDEV(INDEX($CE:$CE,ROW()-VolLB+1):INDEX($CE:$CE,ROW()))*SQRT(12)) | DA13: =IF(ROW()<4+VolLB,"",STDEV(INDEX($CF:$CF,ROW()-VolLB+1):INDEX($CF:$CF,ROW()))*SQRT(12)) | DB13: =IF(ROW()<4+VolLB,"",STDEV(INDEX($CG:$CG,ROW()-VolLB+1):INDEX($CG:$CG,ROW()))*SQRT(12)) | DC13: =IF(OR(AR13=0,CH13="",CH13=0),0,AR13*MIN(MaxScal,TgtVol/CH13)) -> 0 | DD13: =IF(OR(AS13=0,CI13="",CI13=0),0,AS13*MIN(MaxScal,TgtVol/CI13)) -> 0 | DE13: =IF(OR(AT13=0,CJ13="",CJ13=0),0,AT13*MIN(MaxScal,TgtVol/CJ13)) -> 0 | DF13: =IF(OR(AU13=0,CK13="",CK13=0),0,AU13*MIN(MaxScal,TgtVol/CK13)) -> 0 | DG13: =IF(OR(AV13=0,CL13="",CL13=0),0,AV13*MIN(MaxScal,TgtVol/CL13)) -> 0 | DH13: =IF(OR(AW13=0,CM13="",CM13=0),0,AW13*MIN(MaxScal,TgtVol/CM13)) -> 0 | DI13: =IF(OR(AX13=0,CN13="",CN13=0),0,AX13*MIN(MaxScal,TgtVol/CN13)) -> 0 | DJ13: =IF(OR(AY13=0,CO13="",CO13=0),0,AY13*MIN(MaxScal,TgtVol/CO13)) -> 0 | ... DW13: =IF(OR(BL13=0,DB13="",DB13=0),0,BL13*MIN(MaxScal,TgtVol/DB13)) -> 0 | DX13: =IFERROR(DC12*BM13,"") -> 0 | DY13: =IFERROR(DD12*BN13,"") -> 0 | DZ13: =IFERROR(DE12*BO13,"") -> 0 | EA13: =IFERROR(DF12*BP13,"") -> 0 | EB13: =IFERROR(DG12*BQ13,"") -> 0 | EC13: =IFERROR(DH12*BR13,"") -> 0 | ED13: =IFERROR(DI12*BS13,"") -> 0 | EE13: =IFERROR(DJ12*BT13,"") -> 0 | ... ER13: =IFERROR(DW12*CG13,"") -> 0 | ES13: =IF(ROW()=4,"",SUM(DX13:ER13)) -> 0 | ET13: =COUNTIF(AR13:BL13,">0") -> 0
A14: 38321 | B14: =ABS(EMFX_Data!X14-EMFX_Data!Y14) -> 0.15659967 | C14: =ABS(EMFX_Data!X14-EMFX_Data!Z14) -> 0.014883308 | D14: =ABS(EMFX_Data!X14-EMFX_Data!AA14) -> 0.022564523 | E14: =ABS(EMFX_Data!X14-EMFX_Data!AB14) -> 0.026869491 | F14: =ABS(EMFX_Data!X14-EMFX_Data!AC14) -> 0.038002644 | G14: =ABS(EMFX_Data!X14-EMFX_Data!AD14) -> 0.080269067 | H14: =ABS(EMFX_Data!Y14-EMFX_Data!Z14) -> 0.17148298 | I14: =ABS(EMFX_Data!Y14-EMFX_Data!AA14) -> 0.13403515 | J14: =ABS(EMFX_Data!Y14-EMFX_Data!AB14) -> 0.18346916 | K14: =ABS(EMFX_Data!Y14-EMFX_Data!AC14) -> 0.11859703 | L14: =ABS(EMFX_Data!Y14-EMFX_Data!AD14) -> 0.076330605 | M14: =ABS(EMFX_Data!Z14-EMFX_Data!AA14) -> 0.037447831 | N14: =ABS(EMFX_Data!Z14-EMFX_Data!AB14) -> 0.011986183 | O14: =ABS(EMFX_Data!Z14-EMFX_Data!AC14) -> 0.052885952 | P14: =ABS(EMFX_Data!Z14-EMFX_Data!AD14) -> 0.095152375 | Q14: =ABS(EMFX_Data!AA14-EMFX_Data!AB14) -> 0.049434015 | R14: =ABS(EMFX_Data!AA14-EMFX_Data!AC14) -> 0.01543812 | S14: =ABS(EMFX_Data!AA14-EMFX_Data!AD14) -> 0.057704543 | T14: =ABS(EMFX_Data!AB14-EMFX_Data!AC14) -> 0.064872135 | U14: =ABS(EMFX_Data!AB14-EMFX_Data!AD14) -> 0.10713856 | V14: =ABS(EMFX_Data!AC14-EMFX_Data!AD14) -> 0.042266423 | W14: =IF(ROW()<4+MinObs-1,"",IFERROR((B14-AVERAGE(B$4:B14))/STDEV(B$4:B14),"")) | X14: =IF(ROW()<4+MinObs-1,"",IFERROR((C14-AVERAGE(C$4:C14))/STDEV(C$4:C14),"")) | Y14: =IF(ROW()<4+MinObs-1,"",IFERROR((D14-AVERAGE(D$4:D14))/STDEV(D$4:D14),"")) | Z14: =IF(ROW()<4+MinObs-1,"",IFERROR((E14-AVERAGE(E$4:E14))/STDEV(E$4:E14),"")) | AA14: =IF(ROW()<4+MinObs-1,"",IFERROR((F14-AVERAGE(F$4:F14))/STDEV(F$4:F14),"")) | AB14: =IF(ROW()<4+MinObs-1,"",IFERROR((G14-AVERAGE(G$4:G14))/STDEV(G$4:G14),"")) | AC14: =IF(ROW()<4+MinObs-1,"",IFERROR((H14-AVERAGE(H$4:H14))/STDEV(H$4:H14),"")) | AD14: =IF(ROW()<4+MinObs-1,"",IFERROR((I14-AVERAGE(I$4:I14))/STDEV(I$4:I14),"")) | ... AQ14: =IF(ROW()<4+MinObs-1,"",IFERROR((V14-AVERAGE(V$4:V14))/STDEV(V$4:V14),"")) | AR14: =IF(W14="",0,IF(W14>=z4,w4,IF(W14>=z3,w3,IF(W14>=zEntry,w2,IF(AND(W14>=ExitZ,AR13>0),w2,0))))) -> 0 | AS14: =IF(X14="",0,IF(X14>=z4,w4,IF(X14>=z3,w3,IF(X14>=zEntry,w2,IF(AND(X14>=ExitZ,AS13>0),w2,0))))) -> 0 | AT14: =IF(Y14="",0,IF(Y14>=z4,w4,IF(Y14>=z3,w3,IF(Y14>=zEntry,w2,IF(AND(Y14>=ExitZ,AT13>0),w2,0))))) -> 0 | AU14: =IF(Z14="",0,IF(Z14>=z4,w4,IF(Z14>=z3,w3,IF(Z14>=zEntry,w2,IF(AND(Z14>=ExitZ,AU13>0),w2,0))))) -> 0 | AV14: =IF(AA14="",0,IF(AA14>=z4,w4,IF(AA14>=z3,w3,IF(AA14>=zEntry,w2,IF(AND(AA14>=ExitZ,AV13>0),w2,0))))) -> 0 | AW14: =IF(AB14="",0,IF(AB14>=z4,w4,IF(AB14>=z3,w3,IF(AB14>=zEntry,w2,IF(AND(AB14>=ExitZ,AW13>0),w2,0))))) -> 0 | AX14: =IF(AC14="",0,IF(AC14>=z4,w4,IF(AC14>=z3,w3,IF(AC14>=zEntry,w2,IF(AND(AC14>=ExitZ,AX13>0),w2,0))))) -> 0 | AY14: =IF(AD14="",0,IF(AD14>=z4,w4,IF(AD14>=z3,w3,IF(AD14>=zEntry,w2,IF(AND(AD14>=ExitZ,AY13>0),w2,0))))) -> 0 | ... BL14: =IF(AQ14="",0,IF(AQ14>=z4,w4,IF(AQ14>=z3,w3,IF(AQ14>=zEntry,w2,IF(AND(AQ14>=ExitZ,BL13>0),w2,0))))) -> 0 | BM14: =IF(EMFX_Data!X13>=EMFX_Data!Y13,EMFX_Data!AE14-EMFX_Data!AF14,EMFX_Data!AF14-EMFX_Data!AE14) -> -0.054457998 | BN14: =IF(EMFX_Data!X13>=EMFX_Data!Z13,EMFX_Data!AE14-EMFX_Data!AG14,EMFX_Data!AG14-EMFX_Data!AE14) -> 0.021935635 | BO14: =IF(EMFX_Data!X13>=EMFX_Data!AA13,EMFX_Data!AE14-EMFX_Data!AH14,EMFX_Data!AH14-EMFX_Data!AE14) -> 0.057866665 | BP14: =IF(EMFX_Data!X13>=EMFX_Data!AB13,EMFX_Data!AE14-EMFX_Data!AI14,EMFX_Data!AI14-EMFX_Data!AE14) -> 0.012376119 | BQ14: =IF(EMFX_Data!X13>=EMFX_Data!AC13,EMFX_Data!AE14-EMFX_Data!AJ14,EMFX_Data!AJ14-EMFX_Data!AE14) -> -0.0068154283 | BR14: =IF(EMFX_Data!X13>=EMFX_Data!AD13,EMFX_Data!AE14-EMFX_Data!AK14,EMFX_Data!AK14-EMFX_Data!AE14) -> -0.029391644 | BS14: =IF(EMFX_Data!Y13>=EMFX_Data!Z13,EMFX_Data!AF14-EMFX_Data!AG14,EMFX_Data!AG14-EMFX_Data!AF14) -> -0.032522363 | BT14: =IF(EMFX_Data!Y13>=EMFX_Data!AA13,EMFX_Data!AF14-EMFX_Data!AH14,EMFX_Data!AH14-EMFX_Data!AF14) -> 0.0034086668 | BU14: =IF(EMFX_Data!Y13>=EMFX_Data!AB13,EMFX_Data!AF14-EMFX_Data!AI14,EMFX_Data!AI14-EMFX_Data!AF14) -> -0.042081879 | BV14: =IF(EMFX_Data!Y13>=EMFX_Data!AC13,EMFX_Data!AF14-EMFX_Data!AJ14,EMFX_Data!AJ14-EMFX_Data!AF14) -> -0.04764257 | BW14: =IF(EMFX_Data!Y13>=EMFX_Data!AD13,EMFX_Data!AF14-EMFX_Data!AK14,EMFX_Data!AK14-EMFX_Data!AF14) -> -0.025066354 | BX14: =IF(EMFX_Data!Z13>=EMFX_Data!AA13,EMFX_Data!AG14-EMFX_Data!AH14,EMFX_Data!AH14-EMFX_Data!AG14) -> -0.03593103 | BY14: =IF(EMFX_Data!Z13>=EMFX_Data!AB13,EMFX_Data!AG14-EMFX_Data!AI14,EMFX_Data!AI14-EMFX_Data!AG14) -> -0.0095595159 | BZ14: =IF(EMFX_Data!Z13>=EMFX_Data!AC13,EMFX_Data!AG14-EMFX_Data!AJ14,EMFX_Data!AJ14-EMFX_Data!AG14) -> 0.015120206 | CA14: =IF(EMFX_Data!Z13>=EMFX_Data!AD13,EMFX_Data!AG14-EMFX_Data!AK14,EMFX_Data!AK14-EMFX_Data!AG14) -> -0.0074560094 | CB14: =IF(EMFX_Data!AA13>=EMFX_Data!AB13,EMFX_Data!AH14-EMFX_Data!AI14,EMFX_Data!AI14-EMFX_Data!AH14) -> -0.045490546 | CC14: =IF(EMFX_Data!AA13>=EMFX_Data!AC13,EMFX_Data!AH14-EMFX_Data!AJ14,EMFX_Data!AJ14-EMFX_Data!AH14) -> 0.051051236 | CD14: =IF(EMFX_Data!AA13>=EMFX_Data!AD13,EMFX_Data!AH14-EMFX_Data!AK14,EMFX_Data!AK14-EMFX_Data!AH14) -> 0.028475021 | CE14: =IF(EMFX_Data!AB13>=EMFX_Data!AC13,EMFX_Data!AI14-EMFX_Data!AJ14,EMFX_Data!AJ14-EMFX_Data!AI14) -> 0.0055606903 | CF14: =IF(EMFX_Data!AB13>=EMFX_Data!AD13,EMFX_Data!AI14-EMFX_Data!AK14,EMFX_Data!AK14-EMFX_Data!AI14) -> -0.017015525 | CG14: =IF(EMFX_Data!AC13>=EMFX_Data!AD13,EMFX_Data!AJ14-EMFX_Data!AK14,EMFX_Data!AK14-EMFX_Data!AJ14) -> -0.022576216 | CH14: =IF(ROW()<4+VolLB,"",STDEV(INDEX($BM:$BM,ROW()-VolLB+1):INDEX($BM:$BM,ROW()))*SQRT(12)) | CI14: =IF(ROW()<4+VolLB,"",STDEV(INDEX($BN:$BN,ROW()-VolLB+1):INDEX($BN:$BN,ROW()))*SQRT(12)) | CJ14: =IF(ROW()<4+VolLB,"",STDEV(INDEX($BO:$BO,ROW()-VolLB+1):INDEX($BO:$BO,ROW()))*SQRT(12)) | CK14: =IF(ROW()<4+VolLB,"",STDEV(INDEX($BP:$BP,ROW()-VolLB+1):INDEX($BP:$BP,ROW()))*SQRT(12)) | CL14: =IF(ROW()<4+VolLB,"",STDEV(INDEX($BQ:$BQ,ROW()-VolLB+1):INDEX($BQ:$BQ,ROW()))*SQRT(12)) | CM14: =IF(ROW()<4+VolLB,"",STDEV(INDEX($BR:$BR,ROW()-VolLB+1):INDEX($BR:$BR,ROW()))*SQRT(12)) | CN14: =IF(ROW()<4+VolLB,"",STDEV(INDEX($BS:$BS,ROW()-VolLB+1):INDEX($BS:$BS,ROW()))*SQRT(12)) | CO14: =IF(ROW()<4+VolLB,"",STDEV(INDEX($BT:$BT,ROW()-VolLB+1):INDEX($BT:$BT,ROW()))*SQRT(12)) | CP14: =IF(ROW()<4+VolLB,"",STDEV(INDEX($BU:$BU,ROW()-VolLB+1):INDEX($BU:$BU,ROW()))*SQRT(12)) | CQ14: =IF(ROW()<4+VolLB,"",STDEV(INDEX($BV:$BV,ROW()-VolLB+1):INDEX($BV:$BV,ROW()))*SQRT(12)) | CR14: =IF(ROW()<4+VolLB,"",STDEV(INDEX($BW:$BW,ROW()-VolLB+1):INDEX($BW:$BW,ROW()))*SQRT(12)) | CS14: =IF(ROW()<4+VolLB,"",STDEV(INDEX($BX:$BX,ROW()-VolLB+1):INDEX($BX:$BX,ROW()))*SQRT(12)) | CT14: =IF(ROW()<4+VolLB,"",STDEV(INDEX($BY:$BY,ROW()-VolLB+1):INDEX($BY:$BY,ROW()))*SQRT(12)) | CU14: =IF(ROW()<4+VolLB,"",STDEV(INDEX($BZ:$BZ,ROW()-VolLB+1):INDEX($BZ:$BZ,ROW()))*SQRT(12)) | CV14: =IF(ROW()<4+VolLB,"",STDEV(INDEX($CA:$CA,ROW()-VolLB+1):INDEX($CA:$CA,ROW()))*SQRT(12)) | CW14: =IF(ROW()<4+VolLB,"",STDEV(INDEX($CB:$CB,ROW()-VolLB+1):INDEX($CB:$CB,ROW()))*SQRT(12)) | CX14: =IF(ROW()<4+VolLB,"",STDEV(INDEX($CC:$CC,ROW()-VolLB+1):INDEX($CC:$CC,ROW()))*SQRT(12)) | CY14: =IF(ROW()<4+VolLB,"",STDEV(INDEX($CD:$CD,ROW()-VolLB+1):INDEX($CD:$CD,ROW()))*SQRT(12)) | CZ14: =IF(ROW()<4+VolLB,"",STDEV(INDEX($CE:$CE,ROW()-VolLB+1):INDEX($CE:$CE,ROW()))*SQRT(12)) | DA14: =IF(ROW()<4+VolLB,"",STDEV(INDEX($CF:$CF,ROW()-VolLB+1):INDEX($CF:$CF,ROW()))*SQRT(12)) | DB14: =IF(ROW()<4+VolLB,"",STDEV(INDEX($CG:$CG,ROW()-VolLB+1):INDEX($CG:$CG,ROW()))*SQRT(12)) | DC14: =IF(OR(AR14=0,CH14="",CH14=0),0,AR14*MIN(MaxScal,TgtVol/CH14)) -> 0 | DD14: =IF(OR(AS14=0,CI14="",CI14=0),0,AS14*MIN(MaxScal,TgtVol/CI14)) -> 0 | DE14: =IF(OR(AT14=0,CJ14="",CJ14=0),0,AT14*MIN(MaxScal,TgtVol/CJ14)) -> 0 | DF14: =IF(OR(AU14=0,CK14="",CK14=0),0,AU14*MIN(MaxScal,TgtVol/CK14)) -> 0 | DG14: =IF(OR(AV14=0,CL14="",CL14=0),0,AV14*MIN(MaxScal,TgtVol/CL14)) -> 0 | DH14: =IF(OR(AW14=0,CM14="",CM14=0),0,AW14*MIN(MaxScal,TgtVol/CM14)) -> 0 | DI14: =IF(OR(AX14=0,CN14="",CN14=0),0,AX14*MIN(MaxScal,TgtVol/CN14)) -> 0 | DJ14: =IF(OR(AY14=0,CO14="",CO14=0),0,AY14*MIN(MaxScal,TgtVol/CO14)) -> 0 | ... DW14: =IF(OR(BL14=0,DB14="",DB14=0),0,BL14*MIN(MaxScal,TgtVol/DB14)) -> 0 | DX14: =IFERROR(DC13*BM14,"") -> 0 | DY14: =IFERROR(DD13*BN14,"") -> 0 | DZ14: =IFERROR(DE13*BO14,"") -> 0 | EA14: =IFERROR(DF13*BP14,"") -> 0 | EB14: =IFERROR(DG13*BQ14,"") -> 0 | EC14: =IFERROR(DH13*BR14,"") -> 0 | ED14: =IFERROR(DI13*BS14,"") -> 0 | EE14: =IFERROR(DJ13*BT14,"") -> 0 | ... ER14: =IFERROR(DW13*CG14,"") -> 0 | ES14: =IF(ROW()=4,"",SUM(DX14:ER14)) -> 0 | ET14: =COUNTIF(AR14:BL14,">0") -> 0
A15: 38352 | B15: =ABS(EMFX_Data!X15-EMFX_Data!Y15) -> 0.18720803 | C15: =ABS(EMFX_Data!X15-EMFX_Data!Z15) -> 0.014328832 | D15: =ABS(EMFX_Data!X15-EMFX_Data!AA15) -> 0.05188552 | E15: =ABS(EMFX_Data!X15-EMFX_Data!AB15) -> 0.023862423 | F15: =ABS(EMFX_Data!X15-EMFX_Data!AC15) -> 0.029169437 | G15: =ABS(EMFX_Data!X15-EMFX_Data!AD15) -> 0.10964495 | H15: =ABS(EMFX_Data!Y15-EMFX_Data!Z15) -> 0.20153687 | I15: =ABS(EMFX_Data!Y15-EMFX_Data!AA15) -> 0.13532251 | J15: =ABS(EMFX_Data!Y15-EMFX_Data!AB15) -> 0.16334561 | K15: =ABS(EMFX_Data!Y15-EMFX_Data!AC15) -> 0.1580386 | L15: =ABS(EMFX_Data!Y15-EMFX_Data!AD15) -> 0.077563083 | M15: =ABS(EMFX_Data!Z15-EMFX_Data!AA15) -> 0.066214352 | N15: =ABS(EMFX_Data!Z15-EMFX_Data!AB15) -> 0.038191256 | O15: =ABS(EMFX_Data!Z15-EMFX_Data!AC15) -> 0.043498269 | P15: =ABS(EMFX_Data!Z15-EMFX_Data!AD15) -> 0.12397378 | Q15: =ABS(EMFX_Data!AA15-EMFX_Data!AB15) -> 0.028023096 | R15: =ABS(EMFX_Data!AA15-EMFX_Data!AC15) -> 0.022716083 | S15: =ABS(EMFX_Data!AA15-EMFX_Data!AD15) -> 0.057759432 | T15: =ABS(EMFX_Data!AB15-EMFX_Data!AC15) -> 0.0053070137 | U15: =ABS(EMFX_Data!AB15-EMFX_Data!AD15) -> 0.085782528 | V15: =ABS(EMFX_Data!AC15-EMFX_Data!AD15) -> 0.080475514 | W15: =IF(ROW()<4+MinObs-1,"",IFERROR((B15-AVERAGE(B$4:B15))/STDEV(B$4:B15),"")) | X15: =IF(ROW()<4+MinObs-1,"",IFERROR((C15-AVERAGE(C$4:C15))/STDEV(C$4:C15),"")) | Y15: =IF(ROW()<4+MinObs-1,"",IFERROR((D15-AVERAGE(D$4:D15))/STDEV(D$4:D15),"")) | Z15: =IF(ROW()<4+MinObs-1,"",IFERROR((E15-AVERAGE(E$4:E15))/STDEV(E$4:E15),"")) | AA15: =IF(ROW()<4+MinObs-1,"",IFERROR((F15-AVERAGE(F$4:F15))/STDEV(F$4:F15),"")) | AB15: =IF(ROW()<4+MinObs-1,"",IFERROR((G15-AVERAGE(G$4:G15))/STDEV(G$4:G15),"")) | AC15: =IF(ROW()<4+MinObs-1,"",IFERROR((H15-AVERAGE(H$4:H15))/STDEV(H$4:H15),"")) | AD15: =IF(ROW()<4+MinObs-1,"",IFERROR((I15-AVERAGE(I$4:I15))/STDEV(I$4:I15),"")) | ... AQ15: =IF(ROW()<4+MinObs-1,"",IFERROR((V15-AVERAGE(V$4:V15))/STDEV(V$4:V15),"")) | AR15: =IF(W15="",0,IF(W15>=z4,w4,IF(W15>=z3,w3,IF(W15>=zEntry,w2,IF(AND(W15>=ExitZ,AR14>0),w2,0))))) -> 0 | AS15: =IF(X15="",0,IF(X15>=z4,w4,IF(X15>=z3,w3,IF(X15>=zEntry,w2,IF(AND(X15>=ExitZ,AS14>0),w2,0))))) -> 0 | AT15: =IF(Y15="",0,IF(Y15>=z4,w4,IF(Y15>=z3,w3,IF(Y15>=zEntry,w2,IF(AND(Y15>=ExitZ,AT14>0),w2,0))))) -> 0 | AU15: =IF(Z15="",0,IF(Z15>=z4,w4,IF(Z15>=z3,w3,IF(Z15>=zEntry,w2,IF(AND(Z15>=ExitZ,AU14>0),w2,0))))) -> 0 | AV15: =IF(AA15="",0,IF(AA15>=z4,w4,IF(AA15>=z3,w3,IF(AA15>=zEntry,w2,IF(AND(AA15>=ExitZ,AV14>0),w2,0))))) -> 0 | AW15: =IF(AB15="",0,IF(AB15>=z4,w4,IF(AB15>=z3,w3,IF(AB15>=zEntry,w2,IF(AND(AB15>=ExitZ,AW14>0),w2,0))))) -> 0 | AX15: =IF(AC15="",0,IF(AC15>=z4,w4,IF(AC15>=z3,w3,IF(AC15>=zEntry,w2,IF(AND(AC15>=ExitZ,AX14>0),w2,0))))) -> 0 | AY15: =IF(AD15="",0,IF(AD15>=z4,w4,IF(AD15>=z3,w3,IF(AD15>=zEntry,w2,IF(AND(AD15>=ExitZ,AY14>0),w2,0))))) -> 0 | ... BL15: =IF(AQ15="",0,IF(AQ15>=z4,w4,IF(AQ15>=z3,w3,IF(AQ15>=zEntry,w2,IF(AND(AQ15>=ExitZ,BL14>0),w2,0))))) -> 0 | BM15: =IF(EMFX_Data!X14>=EMFX_Data!Y14,EMFX_Data!AE15-EMFX_Data!AF15,EMFX_Data!AF15-EMFX_Data!AE15) -> -0.045235297 | BN15: =IF(EMFX_Data!X14>=EMFX_Data!Z14,EMFX_Data!AE15-EMFX_Data!AG15,EMFX_Data!AG15-EMFX_Data!AE15) -> -0.0015322883 | BO15: =IF(EMFX_Data!X14>=EMFX_Data!AA14,EMFX_Data!AE15-EMFX_Data!AH15,EMFX_Data!AH15-EMFX_Data!AE15) -> -0.031120005 | BP15: =IF(EMFX_Data!X14>=EMFX_Data!AB14,EMFX_Data!AE15-EMFX_Data!AI15,EMFX_Data!AI15-EMFX_Data!AE15) -> 0.052859103 | BQ15: =IF(EMFX_Data!X14>=EMFX_Data!AC14,EMFX_Data!AE15-EMFX_Data!AJ15,EMFX_Data!AJ15-EMFX_Data!AE15) -> 0.014403152 | BR15: =IF(EMFX_Data!X14>=EMFX_Data!AD14,EMFX_Data!AE15-EMFX_Data!AK15,EMFX_Data!AK15-EMFX_Data!AE15) -> -0.039181766 | BS15: =IF(EMFX_Data!Y14>=EMFX_Data!Z14,EMFX_Data!AF15-EMFX_Data!AG15,EMFX_Data!AG15-EMFX_Data!AF15) -> -0.046767585 | BT15: =IF(EMFX_Data!Y14>=EMFX_Data!AA14,EMFX_Data!AF15-EMFX_Data!AH15,EMFX_Data!AH15-EMFX_Data!AF15) -> -0.014115292 | BU15: =IF(EMFX_Data!Y14>=EMFX_Data!AB14,EMFX_Data!AF15-EMFX_Data!AI15,EMFX_Data!AI15-EMFX_Data!AF15) -> 0.0076238062 | BV15: =IF(EMFX_Data!Y14>=EMFX_Data!AC14,EMFX_Data!AF15-EMFX_Data!AJ15,EMFX_Data!AJ15-EMFX_Data!AF15) -> -0.059638448 | BW15: =IF(EMFX_Data!Y14>=EMFX_Data!AD14,EMFX_Data!AF15-EMFX_Data!AK15,EMFX_Data!AK15-EMFX_Data!AF15) -> -0.0060535304 | BX15: =IF(EMFX_Data!Z14>=EMFX_Data!AA14,EMFX_Data!AG15-EMFX_Data!AH15,EMFX_Data!AH15-EMFX_Data!AG15) -> -0.032652293 | BY15: =IF(EMFX_Data!Z14>=EMFX_Data!AB14,EMFX_Data!AG15-EMFX_Data!AI15,EMFX_Data!AI15-EMFX_Data!AG15) -> 0.054391391 | BZ15: =IF(EMFX_Data!Z14>=EMFX_Data!AC14,EMFX_Data!AG15-EMFX_Data!AJ15,EMFX_Data!AJ15-EMFX_Data!AG15) -> 0.012870863 | CA15: =IF(EMFX_Data!Z14>=EMFX_Data!AD14,EMFX_Data!AG15-EMFX_Data!AK15,EMFX_Data!AK15-EMFX_Data!AG15) -> -0.040714055 | CB15: =IF(EMFX_Data!AA14>=EMFX_Data!AB14,EMFX_Data!AH15-EMFX_Data!AI15,EMFX_Data!AI15-EMFX_Data!AH15) -> 0.021739098 | CC15: =IF(EMFX_Data!AA14>=EMFX_Data!AC14,EMFX_Data!AH15-EMFX_Data!AJ15,EMFX_Data!AJ15-EMFX_Data!AH15) -> 0.045523156 | CD15: =IF(EMFX_Data!AA14>=EMFX_Data!AD14,EMFX_Data!AH15-EMFX_Data!AK15,EMFX_Data!AK15-EMFX_Data!AH15) -> -0.0080617616 | CE15: =IF(EMFX_Data!AB14>=EMFX_Data!AC14,EMFX_Data!AI15-EMFX_Data!AJ15,EMFX_Data!AJ15-EMFX_Data!AI15) -> 0.067262255 | CF15: =IF(EMFX_Data!AB14>=EMFX_Data!AD14,EMFX_Data!AI15-EMFX_Data!AK15,EMFX_Data!AK15-EMFX_Data!AI15) -> 0.013677337 | CG15: =IF(EMFX_Data!AC14>=EMFX_Data!AD14,EMFX_Data!AJ15-EMFX_Data!AK15,EMFX_Data!AK15-EMFX_Data!AJ15) -> -0.053584918 | CH15: =IF(ROW()<4+VolLB,"",STDEV(INDEX($BM:$BM,ROW()-VolLB+1):INDEX($BM:$BM,ROW()))*SQRT(12)) | CI15: =IF(ROW()<4+VolLB,"",STDEV(INDEX($BN:$BN,ROW()-VolLB+1):INDEX($BN:$BN,ROW()))*SQRT(12)) | CJ15: =IF(ROW()<4+VolLB,"",STDEV(INDEX($BO:$BO,ROW()-VolLB+1):INDEX($BO:$BO,ROW()))*SQRT(12)) | CK15: =IF(ROW()<4+VolLB,"",STDEV(INDEX($BP:$BP,ROW()-VolLB+1):INDEX($BP:$BP,ROW()))*SQRT(12)) | CL15: =IF(ROW()<4+VolLB,"",STDEV(INDEX($BQ:$BQ,ROW()-VolLB+1):INDEX($BQ:$BQ,ROW()))*SQRT(12)) | CM15: =IF(ROW()<4+VolLB,"",STDEV(INDEX($BR:$BR,ROW()-VolLB+1):INDEX($BR:$BR,ROW()))*SQRT(12)) | CN15: =IF(ROW()<4+VolLB,"",STDEV(INDEX($BS:$BS,ROW()-VolLB+1):INDEX($BS:$BS,ROW()))*SQRT(12)) | CO15: =IF(ROW()<4+VolLB,"",STDEV(INDEX($BT:$BT,ROW()-VolLB+1):INDEX($BT:$BT,ROW()))*SQRT(12)) | CP15: =IF(ROW()<4+VolLB,"",STDEV(INDEX($BU:$BU,ROW()-VolLB+1):INDEX($BU:$BU,ROW()))*SQRT(12)) | CQ15: =IF(ROW()<4+VolLB,"",STDEV(INDEX($BV:$BV,ROW()-VolLB+1):INDEX($BV:$BV,ROW()))*SQRT(12)) | CR15: =IF(ROW()<4+VolLB,"",STDEV(INDEX($BW:$BW,ROW()-VolLB+1):INDEX($BW:$BW,ROW()))*SQRT(12)) | CS15: =IF(ROW()<4+VolLB,"",STDEV(INDEX($BX:$BX,ROW()-VolLB+1):INDEX($BX:$BX,ROW()))*SQRT(12)) | CT15: =IF(ROW()<4+VolLB,"",STDEV(INDEX($BY:$BY,ROW()-VolLB+1):INDEX($BY:$BY,ROW()))*SQRT(12)) | CU15: =IF(ROW()<4+VolLB,"",STDEV(INDEX($BZ:$BZ,ROW()-VolLB+1):INDEX($BZ:$BZ,ROW()))*SQRT(12)) | CV15: =IF(ROW()<4+VolLB,"",STDEV(INDEX($CA:$CA,ROW()-VolLB+1):INDEX($CA:$CA,ROW()))*SQRT(12)) | CW15: =IF(ROW()<4+VolLB,"",STDEV(INDEX($CB:$CB,ROW()-VolLB+1):INDEX($CB:$CB,ROW()))*SQRT(12)) | CX15: =IF(ROW()<4+VolLB,"",STDEV(INDEX($CC:$CC,ROW()-VolLB+1):INDEX($CC:$CC,ROW()))*SQRT(12)) | CY15: =IF(ROW()<4+VolLB,"",STDEV(INDEX($CD:$CD,ROW()-VolLB+1):INDEX($CD:$CD,ROW()))*SQRT(12)) | CZ15: =IF(ROW()<4+VolLB,"",STDEV(INDEX($CE:$CE,ROW()-VolLB+1):INDEX($CE:$CE,ROW()))*SQRT(12)) | DA15: =IF(ROW()<4+VolLB,"",STDEV(INDEX($CF:$CF,ROW()-VolLB+1):INDEX($CF:$CF,ROW()))*SQRT(12)) | DB15: =IF(ROW()<4+VolLB,"",STDEV(INDEX($CG:$CG,ROW()-VolLB+1):INDEX($CG:$CG,ROW()))*SQRT(12)) | DC15: =IF(OR(AR15=0,CH15="",CH15=0),0,AR15*MIN(MaxScal,TgtVol/CH15)) -> 0 | DD15: =IF(OR(AS15=0,CI15="",CI15=0),0,AS15*MIN(MaxScal,TgtVol/CI15)) -> 0 | DE15: =IF(OR(AT15=0,CJ15="",CJ15=0),0,AT15*MIN(MaxScal,TgtVol/CJ15)) -> 0 | DF15: =IF(OR(AU15=0,CK15="",CK15=0),0,AU15*MIN(MaxScal,TgtVol/CK15)) -> 0 | DG15: =IF(OR(AV15=0,CL15="",CL15=0),0,AV15*MIN(MaxScal,TgtVol/CL15)) -> 0 | DH15: =IF(OR(AW15=0,CM15="",CM15=0),0,AW15*MIN(MaxScal,TgtVol/CM15)) -> 0 | DI15: =IF(OR(AX15=0,CN15="",CN15=0),0,AX15*MIN(MaxScal,TgtVol/CN15)) -> 0 | DJ15: =IF(OR(AY15=0,CO15="",CO15=0),0,AY15*MIN(MaxScal,TgtVol/CO15)) -> 0 | ... DW15: =IF(OR(BL15=0,DB15="",DB15=0),0,BL15*MIN(MaxScal,TgtVol/DB15)) -> 0 | DX15: =IFERROR(DC14*BM15,"") -> 0 | DY15: =IFERROR(DD14*BN15,"") -> 0 | DZ15: =IFERROR(DE14*BO15,"") -> 0 | EA15: =IFERROR(DF14*BP15,"") -> 0 | EB15: =IFERROR(DG14*BQ15,"") -> 0 | EC15: =IFERROR(DH14*BR15,"") -> 0 | ED15: =IFERROR(DI14*BS15,"") -> 0 | EE15: =IFERROR(DJ14*BT15,"") -> 0 | ... ER15: =IFERROR(DW14*CG15,"") -> 0 | ES15: =IF(ROW()=4,"",SUM(DX15:ER15)) -> 0 | ET15: =COUNTIF(AR15:BL15,">0") -> 0
A16: 38383 | B16: =ABS(EMFX_Data!X16-EMFX_Data!Y16) -> 0.1826335 | C16: =ABS(EMFX_Data!X16-EMFX_Data!Z16) -> 0.012846479 | D16: =ABS(EMFX_Data!X16-EMFX_Data!AA16) -> 0.054850674 | E16: =ABS(EMFX_Data!X16-EMFX_Data!AB16) -> 0.0098042783 | F16: =ABS(EMFX_Data!X16-EMFX_Data!AC16) -> 0.005167219 | G16: =ABS(EMFX_Data!X16-EMFX_Data!AD16) -> 0.071187172 | H16: =ABS(EMFX_Data!Y16-EMFX_Data!Z16) -> 0.19547998 | I16: =ABS(EMFX_Data!Y16-EMFX_Data!AA16) -> 0.12778283 | J16: =ABS(EMFX_Data!Y16-EMFX_Data!AB16) -> 0.17282922 | K16: =ABS(EMFX_Data!Y16-EMFX_Data!AC16) -> 0.17746628 | L16: =ABS(EMFX_Data!Y16-EMFX_Data!AD16) -> 0.11144633 | M16: =ABS(EMFX_Data!Z16-EMFX_Data!AA16) -> 0.067697153 | N16: =ABS(EMFX_Data!Z16-EMFX_Data!AB16) -> 0.022650757 | O16: =ABS(EMFX_Data!Z16-EMFX_Data!AC16) -> 0.018013698 | P16: =ABS(EMFX_Data!Z16-EMFX_Data!AD16) -> 0.08403365 | Q16: =ABS(EMFX_Data!AA16-EMFX_Data!AB16) -> 0.045046396 | R16: =ABS(EMFX_Data!AA16-EMFX_Data!AC16) -> 0.049683455 | S16: =ABS(EMFX_Data!AA16-EMFX_Data!AD16) -> 0.016336497 | T16: =ABS(EMFX_Data!AB16-EMFX_Data!AC16) -> 0.0046370592 | U16: =ABS(EMFX_Data!AB16-EMFX_Data!AD16) -> 0.061382893 | V16: =ABS(EMFX_Data!AC16-EMFX_Data!AD16) -> 0.066019953 | W16: =IF(ROW()<4+MinObs-1,"",IFERROR((B16-AVERAGE(B$4:B16))/STDEV(B$4:B16),"")) | X16: =IF(ROW()<4+MinObs-1,"",IFERROR((C16-AVERAGE(C$4:C16))/STDEV(C$4:C16),"")) | Y16: =IF(ROW()<4+MinObs-1,"",IFERROR((D16-AVERAGE(D$4:D16))/STDEV(D$4:D16),"")) | Z16: =IF(ROW()<4+MinObs-1,"",IFERROR((E16-AVERAGE(E$4:E16))/STDEV(E$4:E16),"")) | AA16: =IF(ROW()<4+MinObs-1,"",IFERROR((F16-AVERAGE(F$4:F16))/STDEV(F$4:F16),"")) | AB16: =IF(ROW()<4+MinObs-1,"",IFERROR((G16-AVERAGE(G$4:G16))/STDEV(G$4:G16),"")) | AC16: =IF(ROW()<4+MinObs-1,"",IFERROR((H16-AVERAGE(H$4:H16))/STDEV(H$4:H16),"")) | AD16: =IF(ROW()<4+MinObs-1,"",IFERROR((I16-AVERAGE(I$4:I16))/STDEV(I$4:I16),"")) | ... AQ16: =IF(ROW()<4+MinObs-1,"",IFERROR((V16-AVERAGE(V$4:V16))/STDEV(V$4:V16),"")) | AR16: =IF(W16="",0,IF(W16>=z4,w4,IF(W16>=z3,w3,IF(W16>=zEntry,w2,IF(AND(W16>=ExitZ,AR15>0),w2,0))))) -> 0 | AS16: =IF(X16="",0,IF(X16>=z4,w4,IF(X16>=z3,w3,IF(X16>=zEntry,w2,IF(AND(X16>=ExitZ,AS15>0),w2,0))))) -> 0 | AT16: =IF(Y16="",0,IF(Y16>=z4,w4,IF(Y16>=z3,w3,IF(Y16>=zEntry,w2,IF(AND(Y16>=ExitZ,AT15>0),w2,0))))) -> 0 | AU16: =IF(Z16="",0,IF(Z16>=z4,w4,IF(Z16>=z3,w3,IF(Z16>=zEntry,w2,IF(AND(Z16>=ExitZ,AU15>0),w2,0))))) -> 0 | AV16: =IF(AA16="",0,IF(AA16>=z4,w4,IF(AA16>=z3,w3,IF(AA16>=zEntry,w2,IF(AND(AA16>=ExitZ,AV15>0),w2,0))))) -> 0 | AW16: =IF(AB16="",0,IF(AB16>=z4,w4,IF(AB16>=z3,w3,IF(AB16>=zEntry,w2,IF(AND(AB16>=ExitZ,AW15>0),w2,0))))) -> 0 | AX16: =IF(AC16="",0,IF(AC16>=z4,w4,IF(AC16>=z3,w3,IF(AC16>=zEntry,w2,IF(AND(AC16>=ExitZ,AX15>0),w2,0))))) -> 0 | AY16: =IF(AD16="",0,IF(AD16>=z4,w4,IF(AD16>=z3,w3,IF(AD16>=zEntry,w2,IF(AND(AD16>=ExitZ,AY15>0),w2,0))))) -> 0 | ... BL16: =IF(AQ16="",0,IF(AQ16>=z4,w4,IF(AQ16>=z3,w3,IF(AQ16>=zEntry,w2,IF(AND(AQ16>=ExitZ,BL15>0),w2,0))))) -> 0 | BM16: =IF(EMFX_Data!X15>=EMFX_Data!Y15,EMFX_Data!AE16-EMFX_Data!AF16,EMFX_Data!AF16-EMFX_Data!AE16) -> -0.011173992 | BN16: =IF(EMFX_Data!X15>=EMFX_Data!Z15,EMFX_Data!AE16-EMFX_Data!AG16,EMFX_Data!AG16-EMFX_Data!AE16) -> 0.0020087706 | BO16: =IF(EMFX_Data!X15>=EMFX_Data!AA15,EMFX_Data!AE16-EMFX_Data!AH16,EMFX_Data!AH16-EMFX_Data!AE16) -> -0.0064212484 | BP16: =IF(EMFX_Data!X15>=EMFX_Data!AB15,EMFX_Data!AE16-EMFX_Data!AI16,EMFX_Data!AI16-EMFX_Data!AE16) -> 0.011011834 | BQ16: =IF(EMFX_Data!X15>=EMFX_Data!AC15,EMFX_Data!AE16-EMFX_Data!AJ16,EMFX_Data!AJ16-EMFX_Data!AE16) -> 0.029300637 | BR16: =IF(EMFX_Data!X15>=EMFX_Data!AD15,EMFX_Data!AE16-EMFX_Data!AK16,EMFX_Data!AK16-EMFX_Data!AE16) -> 0.031038801 | BS16: =IF(EMFX_Data!Y15>=EMFX_Data!Z15,EMFX_Data!AF16-EMFX_Data!AG16,EMFX_Data!AG16-EMFX_Data!AF16) -> -0.0091652211 | BT16: =IF(EMFX_Data!Y15>=EMFX_Data!AA15,EMFX_Data!AF16-EMFX_Data!AH16,EMFX_Data!AH16-EMFX_Data!AF16) -> -0.0047527433 | BU16: =IF(EMFX_Data!Y15>=EMFX_Data!AB15,EMFX_Data!AF16-EMFX_Data!AI16,EMFX_Data!AI16-EMFX_Data!AF16) -> -0.022185826 | BV16: =IF(EMFX_Data!Y15>=EMFX_Data!AC15,EMFX_Data!AF16-EMFX_Data!AJ16,EMFX_Data!AJ16-EMFX_Data!AF16) -> -0.040474629 | BW16: =IF(EMFX_Data!Y15>=EMFX_Data!AD15,EMFX_Data!AF16-EMFX_Data!AK16,EMFX_Data!AK16-EMFX_Data!AF16) -> -0.042212793 | BX16: =IF(EMFX_Data!Z15>=EMFX_Data!AA15,EMFX_Data!AG16-EMFX_Data!AH16,EMFX_Data!AH16-EMFX_Data!AG16) -> -0.0044124778 | BY16: =IF(EMFX_Data!Z15>=EMFX_Data!AB15,EMFX_Data!AG16-EMFX_Data!AI16,EMFX_Data!AI16-EMFX_Data!AG16) -> 0.013020605 | BZ16: =IF(EMFX_Data!Z15>=EMFX_Data!AC15,EMFX_Data!AG16-EMFX_Data!AJ16,EMFX_Data!AJ16-EMFX_Data!AG16) -> 0.031309408 | CA16: =IF(EMFX_Data!Z15>=EMFX_Data!AD15,EMFX_Data!AG16-EMFX_Data!AK16,EMFX_Data!AK16-EMFX_Data!AG16) -> 0.033047572 | CB16: =IF(EMFX_Data!AA15>=EMFX_Data!AB15,EMFX_Data!AH16-EMFX_Data!AI16,EMFX_Data!AI16-EMFX_Data!AH16) -> -0.017433083 | CC16: =IF(EMFX_Data!AA15>=EMFX_Data!AC15,EMFX_Data!AH16-EMFX_Data!AJ16,EMFX_Data!AJ16-EMFX_Data!AH16) -> -0.035721886 | CD16: =IF(EMFX_Data!AA15>=EMFX_Data!AD15,EMFX_Data!AH16-EMFX_Data!AK16,EMFX_Data!AK16-EMFX_Data!AH16) -> 0.03746005 | CE16: =IF(EMFX_Data!AB15>=EMFX_Data!AC15,EMFX_Data!AI16-EMFX_Data!AJ16,EMFX_Data!AJ16-EMFX_Data!AI16) -> 0.018288803 | CF16: =IF(EMFX_Data!AB15>=EMFX_Data!AD15,EMFX_Data!AI16-EMFX_Data!AK16,EMFX_Data!AK16-EMFX_Data!AI16) -> 0.020026967 | CG16: =IF(EMFX_Data!AC15>=EMFX_Data!AD15,EMFX_Data!AJ16-EMFX_Data!AK16,EMFX_Data!AK16-EMFX_Data!AJ16) -> 0.0017381636 | CH16: =IF(ROW()<4+VolLB,"",STDEV(INDEX($BM:$BM,ROW()-VolLB+1):INDEX($BM:$BM,ROW()))*SQRT(12)) | CI16: =IF(ROW()<4+VolLB,"",STDEV(INDEX($BN:$BN,ROW()-VolLB+1):INDEX($BN:$BN,ROW()))*SQRT(12)) | CJ16: =IF(ROW()<4+VolLB,"",STDEV(INDEX($BO:$BO,ROW()-VolLB+1):INDEX($BO:$BO,ROW()))*SQRT(12)) | CK16: =IF(ROW()<4+VolLB,"",STDEV(INDEX($BP:$BP,ROW()-VolLB+1):INDEX($BP:$BP,ROW()))*SQRT(12)) | CL16: =IF(ROW()<4+VolLB,"",STDEV(INDEX($BQ:$BQ,ROW()-VolLB+1):INDEX($BQ:$BQ,ROW()))*SQRT(12)) | CM16: =IF(ROW()<4+VolLB,"",STDEV(INDEX($BR:$BR,ROW()-VolLB+1):INDEX($BR:$BR,ROW()))*SQRT(12)) | CN16: =IF(ROW()<4+VolLB,"",STDEV(INDEX($BS:$BS,ROW()-VolLB+1):INDEX($BS:$BS,ROW()))*SQRT(12)) | CO16: =IF(ROW()<4+VolLB,"",STDEV(INDEX($BT:$BT,ROW()-VolLB+1):INDEX($BT:$BT,ROW()))*SQRT(12)) | CP16: =IF(ROW()<4+VolLB,"",STDEV(INDEX($BU:$BU,ROW()-VolLB+1):INDEX($BU:$BU,ROW()))*SQRT(12)) | CQ16: =IF(ROW()<4+VolLB,"",STDEV(INDEX($BV:$BV,ROW()-VolLB+1):INDEX($BV:$BV,ROW()))*SQRT(12)) | CR16: =IF(ROW()<4+VolLB,"",STDEV(INDEX($BW:$BW,ROW()-VolLB+1):INDEX($BW:$BW,ROW()))*SQRT(12)) | CS16: =IF(ROW()<4+VolLB,"",STDEV(INDEX($BX:$BX,ROW()-VolLB+1):INDEX($BX:$BX,ROW()))*SQRT(12)) | CT16: =IF(ROW()<4+VolLB,"",STDEV(INDEX($BY:$BY,ROW()-VolLB+1):INDEX($BY:$BY,ROW()))*SQRT(12)) | CU16: =IF(ROW()<4+VolLB,"",STDEV(INDEX($BZ:$BZ,ROW()-VolLB+1):INDEX($BZ:$BZ,ROW()))*SQRT(12)) | CV16: =IF(ROW()<4+VolLB,"",STDEV(INDEX($CA:$CA,ROW()-VolLB+1):INDEX($CA:$CA,ROW()))*SQRT(12)) | CW16: =IF(ROW()<4+VolLB,"",STDEV(INDEX($CB:$CB,ROW()-VolLB+1):INDEX($CB:$CB,ROW()))*SQRT(12)) | CX16: =IF(ROW()<4+VolLB,"",STDEV(INDEX($CC:$CC,ROW()-VolLB+1):INDEX($CC:$CC,ROW()))*SQRT(12)) | CY16: =IF(ROW()<4+VolLB,"",STDEV(INDEX($CD:$CD,ROW()-VolLB+1):INDEX($CD:$CD,ROW()))*SQRT(12)) | CZ16: =IF(ROW()<4+VolLB,"",STDEV(INDEX($CE:$CE,ROW()-VolLB+1):INDEX($CE:$CE,ROW()))*SQRT(12)) | DA16: =IF(ROW()<4+VolLB,"",STDEV(INDEX($CF:$CF,ROW()-VolLB+1):INDEX($CF:$CF,ROW()))*SQRT(12)) | DB16: =IF(ROW()<4+VolLB,"",STDEV(INDEX($CG:$CG,ROW()-VolLB+1):INDEX($CG:$CG,ROW()))*SQRT(12)) | DC16: =IF(OR(AR16=0,CH16="",CH16=0),0,AR16*MIN(MaxScal,TgtVol/CH16)) -> 0 | DD16: =IF(OR(AS16=0,CI16="",CI16=0),0,AS16*MIN(MaxScal,TgtVol/CI16)) -> 0 | DE16: =IF(OR(AT16=0,CJ16="",CJ16=0),0,AT16*MIN(MaxScal,TgtVol/CJ16)) -> 0 | DF16: =IF(OR(AU16=0,CK16="",CK16=0),0,AU16*MIN(MaxScal,TgtVol/CK16)) -> 0 | DG16: =IF(OR(AV16=0,CL16="",CL16=0),0,AV16*MIN(MaxScal,TgtVol/CL16)) -> 0 | DH16: =IF(OR(AW16=0,CM16="",CM16=0),0,AW16*MIN(MaxScal,TgtVol/CM16)) -> 0 | DI16: =IF(OR(AX16=0,CN16="",CN16=0),0,AX16*MIN(MaxScal,TgtVol/CN16)) -> 0 | DJ16: =IF(OR(AY16=0,CO16="",CO16=0),0,AY16*MIN(MaxScal,TgtVol/CO16)) -> 0 | ... DW16: =IF(OR(BL16=0,DB16="",DB16=0),0,BL16*MIN(MaxScal,TgtVol/DB16)) -> 0 | DX16: =IFERROR(DC15*BM16,"") -> 0 | DY16: =IFERROR(DD15*BN16,"") -> 0 | DZ16: =IFERROR(DE15*BO16,"") -> 0 | EA16: =IFERROR(DF15*BP16,"") -> 0 | EB16: =IFERROR(DG15*BQ16,"") -> 0 | EC16: =IFERROR(DH15*BR16,"") -> 0 | ED16: =IFERROR(DI15*BS16,"") -> 0 | EE16: =IFERROR(DJ15*BT16,"") -> 0 | ... ER16: =IFERROR(DW15*CG16,"") -> 0 | ES16: =IF(ROW()=4,"",SUM(DX16:ER16)) -> 0 | ET16: =COUNTIF(AR16:BL16,">0") -> 0
... A276: 46295 | B276: =ABS(EMFX_Data!X276-EMFX_Data!Y276) -> 0.085624154 | C276: =ABS(EMFX_Data!X276-EMFX_Data!Z276) -> 0.13889704 | D276: =ABS(EMFX_Data!X276-EMFX_Data!AA276) -> 0.11949397 | E276: =ABS(EMFX_Data!X276-EMFX_Data!AB276) -> 0.027834083 | F276: =ABS(EMFX_Data!X276-EMFX_Data!AC276) -> 0.059841075 | G276: =ABS(EMFX_Data!X276-EMFX_Data!AD276) -> 0.14837797 | H276: =ABS(EMFX_Data!Y276-EMFX_Data!Z276) -> 0.22452119 | I276: =ABS(EMFX_Data!Y276-EMFX_Data!AA276) -> 0.03386982 | J276: =ABS(EMFX_Data!Y276-EMFX_Data!AB276) -> 0.11345824 | K276: =ABS(EMFX_Data!Y276-EMFX_Data!AC276) -> 0.14546523 | L276: =ABS(EMFX_Data!Y276-EMFX_Data!AD276) -> 0.062753813 | M276: =ABS(EMFX_Data!Z276-EMFX_Data!AA276) -> 0.25839101 | N276: =ABS(EMFX_Data!Z276-EMFX_Data!AB276) -> 0.11106295 | O276: =ABS(EMFX_Data!Z276-EMFX_Data!AC276) -> 0.079055963 | P276: =ABS(EMFX_Data!Z276-EMFX_Data!AD276) -> 0.287275 | Q276: =ABS(EMFX_Data!AA276-EMFX_Data!AB276) -> 0.14732806 | R276: =ABS(EMFX_Data!AA276-EMFX_Data!AC276) -> 0.17933505 | S276: =ABS(EMFX_Data!AA276-EMFX_Data!AD276) -> 0.028883993 | T276: =ABS(EMFX_Data!AB276-EMFX_Data!AC276) -> 0.032006991 | U276: =ABS(EMFX_Data!AB276-EMFX_Data!AD276) -> 0.17621205 | V276: =ABS(EMFX_Data!AC276-EMFX_Data!AD276) -> 0.20821904 | W276: =IF(ROW()<4+MinObs-1,"",IFERROR((B276-AVERAGE(B$4:B276))/STDEV(B$4:B276),"")) -> -0.48880236 | X276: =IF(ROW()<4+MinObs-1,"",IFERROR((C276-AVERAGE(C$4:C276))/STDEV(C$4:C276),"")) -> 0.39016853 | Y276: =IF(ROW()<4+MinObs-1,"",IFERROR((D276-AVERAGE(D$4:D276))/STDEV(D$4:D276),"")) -> -0.22229025 | Z276: =IF(ROW()<4+MinObs-1,"",IFERROR((E276-AVERAGE(E$4:E276))/STDEV(E$4:E276),"")) -> -0.94697631 | AA276: =IF(ROW()<4+MinObs-1,"",IFERROR((F276-AVERAGE(F$4:F276))/STDEV(F$4:F276),"")) -> -0.5457922 | AB276: =IF(ROW()<4+MinObs-1,"",IFERROR((G276-AVERAGE(G$4:G276))/STDEV(G$4:G276),"")) -> 0.050523061 | AC276: =IF(ROW()<4+MinObs-1,"",IFERROR((H276-AVERAGE(H$4:H276))/STDEV(H$4:H276),"")) -> 0.72758898 | AD276: =IF(ROW()<4+MinObs-1,"",IFERROR((I276-AVERAGE(I$4:I276))/STDEV(I$4:I276),"")) -> -0.92777342 | ... AQ276: =IF(ROW()<4+MinObs-1,"",IFERROR((V276-AVERAGE(V$4:V276))/STDEV(V$4:V276),"")) -> 0.20362713 | AR276: =IF(W276="",0,IF(W276>=z4,w4,IF(W276>=z3,w3,IF(W276>=zEntry,w2,IF(AND(W276>=ExitZ,AR275>0),w2,0))))) -> 0 | AS276: =IF(X276="",0,IF(X276>=z4,w4,IF(X276>=z3,w3,IF(X276>=zEntry,w2,IF(AND(X276>=ExitZ,AS275>0),w2,0))))) -> 0 | AT276: =IF(Y276="",0,IF(Y276>=z4,w4,IF(Y276>=z3,w3,IF(Y276>=zEntry,w2,IF(AND(Y276>=ExitZ,AT275>0),w2,0))))) -> 0 | AU276: =IF(Z276="",0,IF(Z276>=z4,w4,IF(Z276>=z3,w3,IF(Z276>=zEntry,w2,IF(AND(Z276>=ExitZ,AU275>0),w2,0))))) -> 0 | AV276: =IF(AA276="",0,IF(AA276>=z4,w4,IF(AA276>=z3,w3,IF(AA276>=zEntry,w2,IF(AND(AA276>=ExitZ,AV275>0),w2,0))))) -> 0 | AW276: =IF(AB276="",0,IF(AB276>=z4,w4,IF(AB276>=z3,w3,IF(AB276>=zEntry,w2,IF(AND(AB276>=ExitZ,AW275>0),w2,0))))) -> 0 | AX276: =IF(AC276="",0,IF(AC276>=z4,w4,IF(AC276>=z3,w3,IF(AC276>=zEntry,w2,IF(AND(AC276>=ExitZ,AX275>0),w2,0))))) -> 0 | AY276: =IF(AD276="",0,IF(AD276>=z4,w4,IF(AD276>=z3,w3,IF(AD276>=zEntry,w2,IF(AND(AD276>=ExitZ,AY275>0),w2,0))))) -> 0 | ... BL276: =IF(AQ276="",0,IF(AQ276>=z4,w4,IF(AQ276>=z3,w3,IF(AQ276>=zEntry,w2,IF(AND(AQ276>=ExitZ,BL275>0),w2,0))))) -> 0 | BM276: =IF(EMFX_Data!X275>=EMFX_Data!Y275,EMFX_Data!AE276-EMFX_Data!AF276,EMFX_Data!AF276-EMFX_Data!AE276) -> 0.095776565 | BN276: =IF(EMFX_Data!X275>=EMFX_Data!Z275,EMFX_Data!AE276-EMFX_Data!AG276,EMFX_Data!AG276-EMFX_Data!AE276) -> -0.087337494 | BO276: =IF(EMFX_Data!X275>=EMFX_Data!AA275,EMFX_Data!AE276-EMFX_Data!AH276,EMFX_Data!AH276-EMFX_Data!AE276) -> 0.029578082 | BP276: =IF(EMFX_Data!X275>=EMFX_Data!AB275,EMFX_Data!AE276-EMFX_Data!AI276,EMFX_Data!AI276-EMFX_Data!AE276) -> 0.073444855 | BQ276: =IF(EMFX_Data!X275>=EMFX_Data!AC275,EMFX_Data!AE276-EMFX_Data!AJ276,EMFX_Data!AJ276-EMFX_Data!AE276) -> 0.054106792 | BR276: =IF(EMFX_Data!X275>=EMFX_Data!AD275,EMFX_Data!AE276-EMFX_Data!AK276,EMFX_Data!AK276-EMFX_Data!AE276) -> 0.017808593 | BS276: =IF(EMFX_Data!Y275>=EMFX_Data!Z275,EMFX_Data!AF276-EMFX_Data!AG276,EMFX_Data!AG276-EMFX_Data!AF276) -> 0.0084390709 | BT276: =IF(EMFX_Data!Y275>=EMFX_Data!AA275,EMFX_Data!AF276-EMFX_Data!AH276,EMFX_Data!AH276-EMFX_Data!AF276) -> 0.066198483 | BU276: =IF(EMFX_Data!Y275>=EMFX_Data!AB275,EMFX_Data!AF276-EMFX_Data!AI276,EMFX_Data!AI276-EMFX_Data!AF276) -> 0.02233171 | BV276: =IF(EMFX_Data!Y275>=EMFX_Data!AC275,EMFX_Data!AF276-EMFX_Data!AJ276,EMFX_Data!AJ276-EMFX_Data!AF276) -> 0.041669773 | BW276: =IF(EMFX_Data!Y275>=EMFX_Data!AD275,EMFX_Data!AF276-EMFX_Data!AK276,EMFX_Data!AK276-EMFX_Data!AF276) -> 0.077967973 | BX276: =IF(EMFX_Data!Z275>=EMFX_Data!AA275,EMFX_Data!AG276-EMFX_Data!AH276,EMFX_Data!AH276-EMFX_Data!AG276) -> -0.057759413 | BY276: =IF(EMFX_Data!Z275>=EMFX_Data!AB275,EMFX_Data!AG276-EMFX_Data!AI276,EMFX_Data!AI276-EMFX_Data!AG276) -> -0.013892639 | BZ276: =IF(EMFX_Data!Z275>=EMFX_Data!AC275,EMFX_Data!AG276-EMFX_Data!AJ276,EMFX_Data!AJ276-EMFX_Data!AG276) -> -0.033230702 | CA276: =IF(EMFX_Data!Z275>=EMFX_Data!AD275,EMFX_Data!AG276-EMFX_Data!AK276,EMFX_Data!AK276-EMFX_Data!AG276) -> -0.069528902 | CB276: =IF(EMFX_Data!AA275>=EMFX_Data!AB275,EMFX_Data!AH276-EMFX_Data!AI276,EMFX_Data!AI276-EMFX_Data!AH276) -> -0.043866773 | CC276: =IF(EMFX_Data!AA275>=EMFX_Data!AC275,EMFX_Data!AH276-EMFX_Data!AJ276,EMFX_Data!AJ276-EMFX_Data!AH276) -> -0.024528711 | CD276: =IF(EMFX_Data!AA275>=EMFX_Data!AD275,EMFX_Data!AH276-EMFX_Data!AK276,EMFX_Data!AK276-EMFX_Data!AH276) -> -0.011769489 | CE276: =IF(EMFX_Data!AB275>=EMFX_Data!AC275,EMFX_Data!AI276-EMFX_Data!AJ276,EMFX_Data!AJ276-EMFX_Data!AI276) -> 0.019338063 | CF276: =IF(EMFX_Data!AB275>=EMFX_Data!AD275,EMFX_Data!AI276-EMFX_Data!AK276,EMFX_Data!AK276-EMFX_Data!AI276) -> -0.055636262 | CG276: =IF(EMFX_Data!AC275>=EMFX_Data!AD275,EMFX_Data!AJ276-EMFX_Data!AK276,EMFX_Data!AK276-EMFX_Data!AJ276) -> -0.0362982 | CH276: =IF(ROW()<4+VolLB,"",STDEV(INDEX($BM:$BM,ROW()-VolLB+1):INDEX($BM:$BM,ROW()))*SQRT(12)) -> 0.19768308 | CI276: =IF(ROW()<4+VolLB,"",STDEV(INDEX($BN:$BN,ROW()-VolLB+1):INDEX($BN:$BN,ROW()))*SQRT(12)) -> 0.20395191 | CJ276: =IF(ROW()<4+VolLB,"",STDEV(INDEX($BO:$BO,ROW()-VolLB+1):INDEX($BO:$BO,ROW()))*SQRT(12)) -> 0.19280336 | CK276: =IF(ROW()<4+VolLB,"",STDEV(INDEX($BP:$BP,ROW()-VolLB+1):INDEX($BP:$BP,ROW()))*SQRT(12)) -> 0.18009158 | CL276: =IF(ROW()<4+VolLB,"",STDEV(INDEX($BQ:$BQ,ROW()-VolLB+1):INDEX($BQ:$BQ,ROW()))*SQRT(12)) -> 0.16699184 | CM276: =IF(ROW()<4+VolLB,"",STDEV(INDEX($BR:$BR,ROW()-VolLB+1):INDEX($BR:$BR,ROW()))*SQRT(12)) -> 0.19943581 | CN276: =IF(ROW()<4+VolLB,"",STDEV(INDEX($BS:$BS,ROW()-VolLB+1):INDEX($BS:$BS,ROW()))*SQRT(12)) -> 0.18911522 | CO276: =IF(ROW()<4+VolLB,"",STDEV(INDEX($BT:$BT,ROW()-VolLB+1):INDEX($BT:$BT,ROW()))*SQRT(12)) -> 0.20812771 | CP276: =IF(ROW()<4+VolLB,"",STDEV(INDEX($BU:$BU,ROW()-VolLB+1):INDEX($BU:$BU,ROW()))*SQRT(12)) -> 0.1807271 | CQ276: =IF(ROW()<4+VolLB,"",STDEV(INDEX($BV:$BV,ROW()-VolLB+1):INDEX($BV:$BV,ROW()))*SQRT(12)) -> 0.19023927 | CR276: =IF(ROW()<4+VolLB,"",STDEV(INDEX($BW:$BW,ROW()-VolLB+1):INDEX($BW:$BW,ROW()))*SQRT(12)) -> 0.19912933 | CS276: =IF(ROW()<4+VolLB,"",STDEV(INDEX($BX:$BX,ROW()-VolLB+1):INDEX($BX:$BX,ROW()))*SQRT(12)) -> 0.16458143 | CT276: =IF(ROW()<4+VolLB,"",STDEV(INDEX($BY:$BY,ROW()-VolLB+1):INDEX($BY:$BY,ROW()))*SQRT(12)) -> 0.14350593 | CU276: =IF(ROW()<4+VolLB,"",STDEV(INDEX($BZ:$BZ,ROW()-VolLB+1):INDEX($BZ:$BZ,ROW()))*SQRT(12)) -> 0.14282425 | CV276: =IF(ROW()<4+VolLB,"",STDEV(INDEX($CA:$CA,ROW()-VolLB+1):INDEX($CA:$CA,ROW()))*SQRT(12)) -> 0.17866328 | CW276: =IF(ROW()<4+VolLB,"",STDEV(INDEX($CB:$CB,ROW()-VolLB+1):INDEX($CB:$CB,ROW()))*SQRT(12)) -> 0.16502005 | CX276: =IF(ROW()<4+VolLB,"",STDEV(INDEX($CC:$CC,ROW()-VolLB+1):INDEX($CC:$CC,ROW()))*SQRT(12)) -> 0.14952 | CY276: =IF(ROW()<4+VolLB,"",STDEV(INDEX($CD:$CD,ROW()-VolLB+1):INDEX($CD:$CD,ROW()))*SQRT(12)) -> 0.17272949 | CZ276: =IF(ROW()<4+VolLB,"",STDEV(INDEX($CE:$CE,ROW()-VolLB+1):INDEX($CE:$CE,ROW()))*SQRT(12)) -> 0.15584052 | DA276: =IF(ROW()<4+VolLB,"",STDEV(INDEX($CF:$CF,ROW()-VolLB+1):INDEX($CF:$CF,ROW()))*SQRT(12)) -> 0.17289675 | DB276: =IF(ROW()<4+VolLB,"",STDEV(INDEX($CG:$CG,ROW()-VolLB+1):INDEX($CG:$CG,ROW()))*SQRT(12)) -> 0.15231987 | DC276: =IF(OR(AR276=0,CH276="",CH276=0),0,AR276*MIN(MaxScal,TgtVol/CH276)) -> 0 | DD276: =IF(OR(AS276=0,CI276="",CI276=0),0,AS276*MIN(MaxScal,TgtVol/CI276)) -> 0 | DE276: =IF(OR(AT276=0,CJ276="",CJ276=0),0,AT276*MIN(MaxScal,TgtVol/CJ276)) -> 0 | DF276: =IF(OR(AU276=0,CK276="",CK276=0),0,AU276*MIN(MaxScal,TgtVol/CK276)) -> 0 | DG276: =IF(OR(AV276=0,CL276="",CL276=0),0,AV276*MIN(MaxScal,TgtVol/CL276)) -> 0 | DH276: =IF(OR(AW276=0,CM276="",CM276=0),0,AW276*MIN(MaxScal,TgtVol/CM276)) -> 0 | DI276: =IF(OR(AX276=0,CN276="",CN276=0),0,AX276*MIN(MaxScal,TgtVol/CN276)) -> 0 | DJ276: =IF(OR(AY276=0,CO276="",CO276=0),0,AY276*MIN(MaxScal,TgtVol/CO276)) -> 0 | ... DW276: =IF(OR(BL276=0,DB276="",DB276=0),0,BL276*MIN(MaxScal,TgtVol/DB276)) -> 0 | DX276: =IFERROR(DC275*BM276,"") -> 0 | DY276: =IFERROR(DD275*BN276,"") -> 0 | DZ276: =IFERROR(DE275*BO276,"") -> 0 | EA276: =IFERROR(DF275*BP276,"") -> 0 | EB276: =IFERROR(DG275*BQ276,"") -> 0 | EC276: =IFERROR(DH275*BR276,"") -> 0 | ED276: =IFERROR(DI275*BS276,"") -> 0 | EE276: =IFERROR(DJ275*BT276,"") -> 0 | ... ER276: =IFERROR(DW275*CG276,"") -> 0 | ES276: =IF(ROW()=4,"",SUM(DX276:ER276)) -> 0 | ET276: =COUNTIF(AR276:BL276,">0") -> 0

Sheet Rates_Pairs
A1: Rates Pairs
A2: One column per pair. Long the market with the higher real short rate, short the lower, direction set by the previous month's valuation. | B2: Valuation spread | W2: Expanding z-score | AR2: Risk multiplier (ladder) | BM2: Pair return (long cheap / short rich) | CH2: Trailing vol, annualised | DC2: Position | DX2: Weighted return | ES2: Sleeve
A3: Date | B3: US/DE | C3: US/GB | D3: US/CA | E3: US/AU | F3: US/JP | G3: US/NZ | H3: DE/GB | I3: DE/CA | J3: DE/AU | K3: DE/JP | L3: DE/NZ | M3: GB/CA | N3: GB/AU | O3: GB/JP | P3: GB/NZ | Q3: CA/AU | R3: CA/JP | S3: CA/NZ | T3: AU/JP | U3: AU/NZ | V3: JP/NZ | W3: US/DE | X3: US/GB | Y3: US/CA | Z3: US/AU | AA3: US/JP | AB3: US/NZ | AC3: DE/GB | AD3: DE/CA | AE3: DE/AU | AF3: DE/JP | AG3: DE/NZ | AH3: GB/CA | AI3: GB/AU | AJ3: GB/JP | AK3: GB/NZ | AL3: CA/AU | AM3: CA/JP | AN3: CA/NZ | AO3: AU/JP | AP3: AU/NZ | AQ3: JP/NZ | AR3: US/DE | AS3: US/GB | AT3: US/CA | AU3: US/AU | AV3: US/JP | AW3: US/NZ | AX3: DE/GB | AY3: DE/CA | AZ3: DE/AU | BA3: DE/JP | BB3: DE/NZ | BC3: GB/CA | BD3: GB/AU | BE3: GB/JP | BF3: GB/NZ | BG3: CA/AU | BH3: CA/JP | BI3: CA/NZ | BJ3: AU/JP | BK3: AU/NZ | BL3: JP/NZ | BM3: US/DE | BN3: US/GB | BO3: US/CA | BP3: US/AU | BQ3: US/JP | BR3: US/NZ | BS3: DE/GB | BT3: DE/CA | BU3: DE/AU | BV3: DE/JP | BW3: DE/NZ | BX3: GB/CA | BY3: GB/AU | BZ3: GB/JP | CA3: GB/NZ | CB3: CA/AU | CC3: CA/JP | CD3: CA/NZ | CE3: AU/JP | CF3: AU/NZ | CG3: JP/NZ | CH3: US/DE | CI3: US/GB | CJ3: US/CA | CK3: US/AU | CL3: US/JP | CM3: US/NZ | CN3: DE/GB | CO3: DE/CA | CP3: DE/AU | CQ3: DE/JP | CR3: DE/NZ | CS3: GB/CA | CT3: GB/AU | CU3: GB/JP | CV3: GB/NZ | CW3: CA/AU | CX3: CA/JP | CY3: CA/NZ | CZ3: AU/JP | DA3: AU/NZ | DB3: JP/NZ | DC3: US/DE | DD3: US/GB | DE3: US/CA | DF3: US/AU | DG3: US/JP | DH3: US/NZ | DI3: DE/GB | DJ3: DE/CA | DK3: DE/AU | DL3: DE/JP | DM3: DE/NZ | DN3: GB/CA | DO3: GB/AU | DP3: GB/JP | DQ3: GB/NZ | DR3: CA/AU | DS3: CA/JP | DT3: CA/NZ | DU3: AU/JP | DV3: AU/NZ | DW3: JP/NZ | DX3: US/DE | DY3: US/GB | DZ3: US/CA | EA3: US/AU | EB3: US/JP | EC3: US/NZ | ED3: DE/GB | EE3: DE/CA | EF3: DE/AU | EG3: DE/JP | EH3: DE/NZ | EI3: GB/CA | EJ3: GB/AU | EK3: GB/JP | EL3: GB/NZ | EM3: CA/AU | EN3: CA/JP | EO3: CA/NZ | EP3: AU/JP | EQ3: AU/NZ | ER3: JP/NZ | ES3: Gross ret | ET3: # included
A4: 38017 | B4: =ABS(Rates_Data!AD4-Rates_Data!AE4) -> 1.555 | C4: =ABS(Rates_Data!AD4-Rates_Data!AF4) -> 1.555 | D4: =ABS(Rates_Data!AD4-Rates_Data!AG4) -> 2.261 | E4: =ABS(Rates_Data!AD4-Rates_Data!AH4) -> 1.555 | F4: =ABS(Rates_Data!AD4-Rates_Data!AI4) -> 1.555 | G4: =ABS(Rates_Data!AD4-Rates_Data!AJ4) -> 1.555 | H4: =ABS(Rates_Data!AE4-Rates_Data!AF4) -> 0 | I4: =ABS(Rates_Data!AE4-Rates_Data!AG4) -> 3.816 | J4: =ABS(Rates_Data!AE4-Rates_Data!AH4) -> 0 | K4: =ABS(Rates_Data!AE4-Rates_Data!AI4) -> 0 | L4: =ABS(Rates_Data!AE4-Rates_Data!AJ4) -> 0 | M4: =ABS(Rates_Data!AF4-Rates_Data!AG4) -> 3.816 | N4: =ABS(Rates_Data!AF4-Rates_Data!AH4) -> 0 | O4: =ABS(Rates_Data!AF4-Rates_Data!AI4) -> 0 | P4: =ABS(Rates_Data!AF4-Rates_Data!AJ4) -> 0 | Q4: =ABS(Rates_Data!AG4-Rates_Data!AH4) -> 3.816 | R4: =ABS(Rates_Data!AG4-Rates_Data!AI4) -> 3.816 | S4: =ABS(Rates_Data!AG4-Rates_Data!AJ4) -> 3.816 | T4: =ABS(Rates_Data!AH4-Rates_Data!AI4) -> 0 | U4: =ABS(Rates_Data!AH4-Rates_Data!AJ4) -> 0 | V4: =ABS(Rates_Data!AI4-Rates_Data!AJ4) -> 0 | W4: =IF(ROW()<4+MinObs-1,"",IFERROR((B4-AVERAGE(B$4:B4))/STDEV(B$4:B4),"")) | X4: =IF(ROW()<4+MinObs-1,"",IFERROR((C4-AVERAGE(C$4:C4))/STDEV(C$4:C4),"")) | Y4: =IF(ROW()<4+MinObs-1,"",IFERROR((D4-AVERAGE(D$4:D4))/STDEV(D$4:D4),"")) | Z4: =IF(ROW()<4+MinObs-1,"",IFERROR((E4-AVERAGE(E$4:E4))/STDEV(E$4:E4),"")) | AA4: =IF(ROW()<4+MinObs-1,"",IFERROR((F4-AVERAGE(F$4:F4))/STDEV(F$4:F4),"")) | AB4: =IF(ROW()<4+MinObs-1,"",IFERROR((G4-AVERAGE(G$4:G4))/STDEV(G$4:G4),"")) | AC4: =IF(ROW()<4+MinObs-1,"",IFERROR((H4-AVERAGE(H$4:H4))/STDEV(H$4:H4),"")) | AD4: =IF(ROW()<4+MinObs-1,"",IFERROR((I4-AVERAGE(I$4:I4))/STDEV(I$4:I4),"")) | ... AQ4: =IF(ROW()<4+MinObs-1,"",IFERROR((V4-AVERAGE(V$4:V4))/STDEV(V$4:V4),"")) | AR4: =IF(w4="",0,IF(w4>=z4,w4,IF(w4>=z3,w3,IF(w4>=zEntry,w2,IF(AND(w4>=ExitZ,0>0),w2,0))))) -> 1 | AS4: =IF(X4="",0,IF(X4>=z4,w4,IF(X4>=z3,w3,IF(X4>=zEntry,w2,IF(AND(X4>=ExitZ,0>0),w2,0))))) -> 0 | AT4: =IF(Y4="",0,IF(Y4>=z4,w4,IF(Y4>=z3,w3,IF(Y4>=zEntry,w2,IF(AND(Y4>=ExitZ,0>0),w2,0))))) -> 0 | AU4: =IF(z4="",0,IF(z4>=z4,w4,IF(z4>=z3,w3,IF(z4>=zEntry,w2,IF(AND(z4>=ExitZ,0>0),w2,0))))) -> 2 | AV4: =IF(AA4="",0,IF(AA4>=z4,w4,IF(AA4>=z3,w3,IF(AA4>=zEntry,w2,IF(AND(AA4>=ExitZ,0>0),w2,0))))) -> 0 | AW4: =IF(AB4="",0,IF(AB4>=z4,w4,IF(AB4>=z3,w3,IF(AB4>=zEntry,w2,IF(AND(AB4>=ExitZ,0>0),w2,0))))) -> 0 | AX4: =IF(AC4="",0,IF(AC4>=z4,w4,IF(AC4>=z3,w3,IF(AC4>=zEntry,w2,IF(AND(AC4>=ExitZ,0>0),w2,0))))) -> 0 | AY4: =IF(AD4="",0,IF(AD4>=z4,w4,IF(AD4>=z3,w3,IF(AD4>=zEntry,w2,IF(AND(AD4>=ExitZ,0>0),w2,0))))) -> 0 | AZ4: =IF(AE4="",0,IF(AE4>=z4,w4,IF(AE4>=z3,w3,IF(AE4>=zEntry,w2,IF(AND(AE4>=ExitZ,0>0),w2,0))))) -> 0 | BA4: =IF(AF4="",0,IF(AF4>=z4,w4,IF(AF4>=z3,w3,IF(AF4>=zEntry,w2,IF(AND(AF4>=ExitZ,0>0),w2,0))))) -> 0 | BB4: =IF(AG4="",0,IF(AG4>=z4,w4,IF(AG4>=z3,w3,IF(AG4>=zEntry,w2,IF(AND(AG4>=ExitZ,0>0),w2,0))))) -> 0 | BC4: =IF(AH4="",0,IF(AH4>=z4,w4,IF(AH4>=z3,w3,IF(AH4>=zEntry,w2,IF(AND(AH4>=ExitZ,0>0),w2,0))))) -> 0 | ... BL4: =IF(AQ4="",0,IF(AQ4>=z4,w4,IF(AQ4>=z3,w3,IF(AQ4>=zEntry,w2,IF(AND(AQ4>=ExitZ,0>0),w2,0))))) -> 0 | DC4: =IF(OR(AR4=0,CH4="",CH4=0),0,AR4*MIN(MaxScal,TgtVol/CH4)) -> 0 | DD4: =IF(OR(AS4=0,CI4="",CI4=0),0,AS4*MIN(MaxScal,TgtVol/CI4)) -> 0 | DE4: =IF(OR(AT4=0,CJ4="",CJ4=0),0,AT4*MIN(MaxScal,TgtVol/CJ4)) -> 0 | DF4: =IF(OR(AU4=0,CK4="",CK4=0),0,AU4*MIN(MaxScal,TgtVol/CK4)) -> 0 | DG4: =IF(OR(AV4=0,CL4="",CL4=0),0,AV4*MIN(MaxScal,TgtVol/CL4)) -> 0 | DH4: =IF(OR(AW4=0,CM4="",CM4=0),0,AW4*MIN(MaxScal,TgtVol/CM4)) -> 0 | DI4: =IF(OR(AX4=0,CN4="",CN4=0),0,AX4*MIN(MaxScal,TgtVol/CN4)) -> 0 | DJ4: =IF(OR(AY4=0,CO4="",CO4=0),0,AY4*MIN(MaxScal,TgtVol/CO4)) -> 0 | ... DW4: =IF(OR(BL4=0,DB4="",DB4=0),0,BL4*MIN(MaxScal,TgtVol/DB4)) -> 0 | ES4: =IF(ROW()=4,"",SUM(DX4:ER4)) | ET4: =COUNTIF(AR4:BL4,">0") -> 2
A5: 38046 | B5: =ABS(Rates_Data!AD5-Rates_Data!AE5) -> 0.032 | C5: =ABS(Rates_Data!AD5-Rates_Data!AF5) -> 0.176 | D5: =ABS(Rates_Data!AD5-Rates_Data!AG5) -> 0.0995 | E5: =ABS(Rates_Data!AD5-Rates_Data!AH5) -> 0.0765 | F5: =ABS(Rates_Data!AD5-Rates_Data!AI5) -> 0.218 | G5: =ABS(Rates_Data!AD5-Rates_Data!AJ5) -> 0.008 | H5: =ABS(Rates_Data!AE5-Rates_Data!AF5) -> 0.144 | I5: =ABS(Rates_Data!AE5-Rates_Data!AG5) -> 0.0675 | J5: =ABS(Rates_Data!AE5-Rates_Data!AH5) -> 0.1085 | K5: =ABS(Rates_Data!AE5-Rates_Data!AI5) -> 0.186 | L5: =ABS(Rates_Data!AE5-Rates_Data!AJ5) -> 0.024 | M5: =ABS(Rates_Data!AF5-Rates_Data!AG5) -> 0.0765 | N5: =ABS(Rates_Data!AF5-Rates_Data!AH5) -> 0.2525 | O5: =ABS(Rates_Data!AF5-Rates_Data!AI5) -> 0.042 | P5: =ABS(Rates_Data!AF5-Rates_Data!AJ5) -> 0.168 | Q5: =ABS(Rates_Data!AG5-Rates_Data!AH5) -> 0.176 | R5: =ABS(Rates_Data!AG5-Rates_Data!AI5) -> 0.1185 | S5: =ABS(Rates_Data!AG5-Rates_Data!AJ5) -> 0.0915 | T5: =ABS(Rates_Data!AH5-Rates_Data!AI5) -> 0.2945 | U5: =ABS(Rates_Data!AH5-Rates_Data!AJ5) -> 0.0845 | V5: =ABS(Rates_Data!AI5-Rates_Data!AJ5) -> 0.21 | W5: =IF(ROW()<4+MinObs-1,"",IFERROR((B5-AVERAGE(B$4:B5))/STDEV(B$4:B5),"")) | X5: =IF(ROW()<4+MinObs-1,"",IFERROR((C5-AVERAGE(C$4:C5))/STDEV(C$4:C5),"")) | Y5: =IF(ROW()<4+MinObs-1,"",IFERROR((D5-AVERAGE(D$4:D5))/STDEV(D$4:D5),"")) | Z5: =IF(ROW()<4+MinObs-1,"",IFERROR((E5-AVERAGE(E$4:E5))/STDEV(E$4:E5),"")) | AA5: =IF(ROW()<4+MinObs-1,"",IFERROR((F5-AVERAGE(F$4:F5))/STDEV(F$4:F5),"")) | AB5: =IF(ROW()<4+MinObs-1,"",IFERROR((G5-AVERAGE(G$4:G5))/STDEV(G$4:G5),"")) | AC5: =IF(ROW()<4+MinObs-1,"",IFERROR((H5-AVERAGE(H$4:H5))/STDEV(H$4:H5),"")) | AD5: =IF(ROW()<4+MinObs-1,"",IFERROR((I5-AVERAGE(I$4:I5))/STDEV(I$4:I5),"")) | ... AQ5: =IF(ROW()<4+MinObs-1,"",IFERROR((V5-AVERAGE(V$4:V5))/STDEV(V$4:V5),"")) | AR5: =IF(W5="",0,IF(W5>=z4,w4,IF(W5>=z3,w3,IF(W5>=zEntry,w2,IF(AND(W5>=ExitZ,AR4>0),w2,0))))) -> 0 | AS5: =IF(X5="",0,IF(X5>=z4,w4,IF(X5>=z3,w3,IF(X5>=zEntry,w2,IF(AND(X5>=ExitZ,AS4>0),w2,0))))) -> 0 | AT5: =IF(Y5="",0,IF(Y5>=z4,w4,IF(Y5>=z3,w3,IF(Y5>=zEntry,w2,IF(AND(Y5>=ExitZ,AT4>0),w2,0))))) -> 0 | AU5: =IF(Z5="",0,IF(Z5>=z4,w4,IF(Z5>=z3,w3,IF(Z5>=zEntry,w2,IF(AND(Z5>=ExitZ,AU4>0),w2,0))))) -> 0 | AV5: =IF(AA5="",0,IF(AA5>=z4,w4,IF(AA5>=z3,w3,IF(AA5>=zEntry,w2,IF(AND(AA5>=ExitZ,AV4>0),w2,0))))) -> 0 | AW5: =IF(AB5="",0,IF(AB5>=z4,w4,IF(AB5>=z3,w3,IF(AB5>=zEntry,w2,IF(AND(AB5>=ExitZ,AW4>0),w2,0))))) -> 0 | AX5: =IF(AC5="",0,IF(AC5>=z4,w4,IF(AC5>=z3,w3,IF(AC5>=zEntry,w2,IF(AND(AC5>=ExitZ,AX4>0),w2,0))))) -> 0 | AY5: =IF(AD5="",0,IF(AD5>=z4,w4,IF(AD5>=z3,w3,IF(AD5>=zEntry,w2,IF(AND(AD5>=ExitZ,AY4>0),w2,0))))) -> 0 | ... BL5: =IF(AQ5="",0,IF(AQ5>=z4,w4,IF(AQ5>=z3,w3,IF(AQ5>=zEntry,w2,IF(AND(AQ5>=ExitZ,BL4>0),w2,0))))) -> 0 | BM5: =IF(Rates_Data!AD4>=Rates_Data!AE4,Rates_Data!AK5-Rates_Data!AL5,Rates_Data!AL5-Rates_Data!AK5) -> 0.002831 | BN5: =IF(Rates_Data!AD4>=Rates_Data!AF4,Rates_Data!AK5-Rates_Data!AM5,Rates_Data!AM5-Rates_Data!AK5) -> -0.005738 | BO5: =IF(Rates_Data!AD4>=Rates_Data!AG4,Rates_Data!AK5-Rates_Data!AN5,Rates_Data!AN5-Rates_Data!AK5) -> 0.001463 | BP5: =IF(Rates_Data!AD4>=Rates_Data!AH4,Rates_Data!AK5-Rates_Data!AO5,Rates_Data!AO5-Rates_Data!AK5) -> 0.004503 | BQ5: =IF(Rates_Data!AD4>=Rates_Data!AI4,Rates_Data!AK5-Rates_Data!AP5,Rates_Data!AP5-Rates_Data!AK5) -> -0.010773 | BR5: =IF(Rates_Data!AD4>=Rates_Data!AJ4,Rates_Data!AK5-Rates_Data!AQ5,Rates_Data!AQ5-Rates_Data!AK5) -> -0.002698 | BS5: =IF(Rates_Data!AE4>=Rates_Data!AF4,Rates_Data!AL5-Rates_Data!AM5,Rates_Data!AM5-Rates_Data!AL5) -> -0.008569 | BT5: =IF(Rates_Data!AE4>=Rates_Data!AG4,Rates_Data!AL5-Rates_Data!AN5,Rates_Data!AN5-Rates_Data!AL5) -> 0.004294 | BU5: =IF(Rates_Data!AE4>=Rates_Data!AH4,Rates_Data!AL5-Rates_Data!AO5,Rates_Data!AO5-Rates_Data!AL5) -> 0.001672 | BV5: =IF(Rates_Data!AE4>=Rates_Data!AI4,Rates_Data!AL5-Rates_Data!AP5,Rates_Data!AP5-Rates_Data!AL5) -> -0.013604 | BW5: =IF(Rates_Data!AE4>=Rates_Data!AJ4,Rates_Data!AL5-Rates_Data!AQ5,Rates_Data!AQ5-Rates_Data!AL5) -> -0.005529 | BX5: =IF(Rates_Data!AF4>=Rates_Data!AG4,Rates_Data!AM5-Rates_Data!AN5,Rates_Data!AN5-Rates_Data!AM5) -> -0.004275 | BY5: =IF(Rates_Data!AF4>=Rates_Data!AH4,Rates_Data!AM5-Rates_Data!AO5,Rates_Data!AO5-Rates_Data!AM5) -> 0.010241 | BZ5: =IF(Rates_Data!AF4>=Rates_Data!AI4,Rates_Data!AM5-Rates_Data!AP5,Rates_Data!AP5-Rates_Data!AM5) -> -0.005035 | CA5: =IF(Rates_Data!AF4>=Rates_Data!AJ4,Rates_Data!AM5-Rates_Data!AQ5,Rates_Data!AQ5-Rates_Data!AM5) -> 0.00304 | CB5: =IF(Rates_Data!AG4>=Rates_Data!AH4,Rates_Data!AN5-Rates_Data!AO5,Rates_Data!AO5-Rates_Data!AN5) -> 0.005966 | CC5: =IF(Rates_Data!AG4>=Rates_Data!AI4,Rates_Data!AN5-Rates_Data!AP5,Rates_Data!AP5-Rates_Data!AN5) -> -0.00931 | CD5: =IF(Rates_Data!AG4>=Rates_Data!AJ4,Rates_Data!AN5-Rates_Data!AQ5,Rates_Data!AQ5-Rates_Data!AN5) -> -0.001235 | CE5: =IF(Rates_Data!AH4>=Rates_Data!AI4,Rates_Data!AO5-Rates_Data!AP5,Rates_Data!AP5-Rates_Data!AO5) -> -0.015276 | CF5: =IF(Rates_Data!AH4>=Rates_Data!AJ4,Rates_Data!AO5-Rates_Data!AQ5,Rates_Data!AQ5-Rates_Data!AO5) -> -0.007201 | CG5: =IF(Rates_Data!AI4>=Rates_Data!AJ4,Rates_Data!AP5-Rates_Data!AQ5,Rates_Data!AQ5-Rates_Data!AP5) -> 0.008075 | CH5: =IF(ROW()<4+VolLB,"",STDEV(INDEX($BM:$BM,ROW()-VolLB+1):INDEX($BM:$BM,ROW()))*SQRT(12)) | CI5: =IF(ROW()<4+VolLB,"",STDEV(INDEX($BN:$BN,ROW()-VolLB+1):INDEX($BN:$BN,ROW()))*SQRT(12)) | CJ5: =IF(ROW()<4+VolLB,"",STDEV(INDEX($BO:$BO,ROW()-VolLB+1):INDEX($BO:$BO,ROW()))*SQRT(12)) | CK5: =IF(ROW()<4+VolLB,"",STDEV(INDEX($BP:$BP,ROW()-VolLB+1):INDEX($BP:$BP,ROW()))*SQRT(12)) | CL5: =IF(ROW()<4+VolLB,"",STDEV(INDEX($BQ:$BQ,ROW()-VolLB+1):INDEX($BQ:$BQ,ROW()))*SQRT(12)) | CM5: =IF(ROW()<4+VolLB,"",STDEV(INDEX($BR:$BR,ROW()-VolLB+1):INDEX($BR:$BR,ROW()))*SQRT(12)) | CN5: =IF(ROW()<4+VolLB,"",STDEV(INDEX($BS:$BS,ROW()-VolLB+1):INDEX($BS:$BS,ROW()))*SQRT(12)) | CO5: =IF(ROW()<4+VolLB,"",STDEV(INDEX($BT:$BT,ROW()-VolLB+1):INDEX($BT:$BT,ROW()))*SQRT(12)) | CP5: =IF(ROW()<4+VolLB,"",STDEV(INDEX($BU:$BU,ROW()-VolLB+1):INDEX($BU:$BU,ROW()))*SQRT(12)) | CQ5: =IF(ROW()<4+VolLB,"",STDEV(INDEX($BV:$BV,ROW()-VolLB+1):INDEX($BV:$BV,ROW()))*SQRT(12)) | CR5: =IF(ROW()<4+VolLB,"",STDEV(INDEX($BW:$BW,ROW()-VolLB+1):INDEX($BW:$BW,ROW()))*SQRT(12)) | CS5: =IF(ROW()<4+VolLB,"",STDEV(INDEX($BX:$BX,ROW()-VolLB+1):INDEX($BX:$BX,ROW()))*SQRT(12)) | CT5: =IF(ROW()<4+VolLB,"",STDEV(INDEX($BY:$BY,ROW()-VolLB+1):INDEX($BY:$BY,ROW()))*SQRT(12)) | CU5: =IF(ROW()<4+VolLB,"",STDEV(INDEX($BZ:$BZ,ROW()-VolLB+1):INDEX($BZ:$BZ,ROW()))*SQRT(12)) | CV5: =IF(ROW()<4+VolLB,"",STDEV(INDEX($CA:$CA,ROW()-VolLB+1):INDEX($CA:$CA,ROW()))*SQRT(12)) | CW5: =IF(ROW()<4+VolLB,"",STDEV(INDEX($CB:$CB,ROW()-VolLB+1):INDEX($CB:$CB,ROW()))*SQRT(12)) | CX5: =IF(ROW()<4+VolLB,"",STDEV(INDEX($CC:$CC,ROW()-VolLB+1):INDEX($CC:$CC,ROW()))*SQRT(12)) | CY5: =IF(ROW()<4+VolLB,"",STDEV(INDEX($CD:$CD,ROW()-VolLB+1):INDEX($CD:$CD,ROW()))*SQRT(12)) | CZ5: =IF(ROW()<4+VolLB,"",STDEV(INDEX($CE:$CE,ROW()-VolLB+1):INDEX($CE:$CE,ROW()))*SQRT(12)) | DA5: =IF(ROW()<4+VolLB,"",STDEV(INDEX($CF:$CF,ROW()-VolLB+1):INDEX($CF:$CF,ROW()))*SQRT(12)) | DB5: =IF(ROW()<4+VolLB,"",STDEV(INDEX($CG:$CG,ROW()-VolLB+1):INDEX($CG:$CG,ROW()))*SQRT(12)) | DC5: =IF(OR(AR5=0,CH5="",CH5=0),0,AR5*MIN(MaxScal,TgtVol/CH5)) -> 0 | DD5: =IF(OR(AS5=0,CI5="",CI5=0),0,AS5*MIN(MaxScal,TgtVol/CI5)) -> 0 | DE5: =IF(OR(AT5=0,CJ5="",CJ5=0),0,AT5*MIN(MaxScal,TgtVol/CJ5)) -> 0 | DF5: =IF(OR(AU5=0,CK5="",CK5=0),0,AU5*MIN(MaxScal,TgtVol/CK5)) -> 0 | DG5: =IF(OR(AV5=0,CL5="",CL5=0),0,AV5*MIN(MaxScal,TgtVol/CL5)) -> 0 | DH5: =IF(OR(AW5=0,CM5="",CM5=0),0,AW5*MIN(MaxScal,TgtVol/CM5)) -> 0 | DI5: =IF(OR(AX5=0,CN5="",CN5=0),0,AX5*MIN(MaxScal,TgtVol/CN5)) -> 0 | DJ5: =IF(OR(AY5=0,CO5="",CO5=0),0,AY5*MIN(MaxScal,TgtVol/CO5)) -> 0 | ... DW5: =IF(OR(BL5=0,DB5="",DB5=0),0,BL5*MIN(MaxScal,TgtVol/DB5)) -> 0 | DX5: =IFERROR(DC4*BM5,"") -> 0 | DY5: =IFERROR(DD4*BN5,"") -> 0 | DZ5: =IFERROR(DE4*BO5,"") -> 0 | EA5: =IFERROR(DF4*BP5,"") -> 0 | EB5: =IFERROR(DG4*BQ5,"") -> 0 | EC5: =IFERROR(DH4*BR5,"") -> 0 | ED5: =IFERROR(DI4*BS5,"") -> 0 | EE5: =IFERROR(DJ4*BT5,"") -> 0 | ... ER5: =IFERROR(DW4*CG5,"") -> 0 | ES5: =IF(ROW()=4,"",SUM(DX5:ER5)) -> 0 | ET5: =COUNTIF(AR5:BL5,">0") -> 0
A6: 38077 | B6: =ABS(Rates_Data!AD6-Rates_Data!AE6) -> 0.124 | C6: =ABS(Rates_Data!AD6-Rates_Data!AF6) -> 0.24 | D6: =ABS(Rates_Data!AD6-Rates_Data!AG6) -> 0.23233333 | E6: =ABS(Rates_Data!AD6-Rates_Data!AH6) -> 0.13233333 | F6: =ABS(Rates_Data!AD6-Rates_Data!AI6) -> 0.38866667 | G6: =ABS(Rates_Data!AD6-Rates_Data!AJ6) -> 0.066666667 | H6: =ABS(Rates_Data!AE6-Rates_Data!AF6) -> 0.116 | I6: =ABS(Rates_Data!AE6-Rates_Data!AG6) -> 0.10833333 | J6: =ABS(Rates_Data!AE6-Rates_Data!AH6) -> 0.0083333333 | K6: =ABS(Rates_Data!AE6-Rates_Data!AI6) -> 0.26466667 | L6: =ABS(Rates_Data!AE6-Rates_Data!AJ6) -> 0.057333333 | M6: =ABS(Rates_Data!AF6-Rates_Data!AG6) -> 0.0076666667 | N6: =ABS(Rates_Data!AF6-Rates_Data!AH6) -> 0.10766667 | O6: =ABS(Rates_Data!AF6-Rates_Data!AI6) -> 0.14866667 | P6: =ABS(Rates_Data!AF6-Rates_Data!AJ6) -> 0.17333333 | Q6: =ABS(Rates_Data!AG6-Rates_Data!AH6) -> 0.1 | R6: =ABS(Rates_Data!AG6-Rates_Data!AI6) -> 0.15633333 | S6: =ABS(Rates_Data!AG6-Rates_Data!AJ6) -> 0.16566667 | T6: =ABS(Rates_Data!AH6-Rates_Data!AI6) -> 0.25633333 | U6: =ABS(Rates_Data!AH6-Rates_Data!AJ6) -> 0.065666667 | V6: =ABS(Rates_Data!AI6-Rates_Data!AJ6) -> 0.322 | W6: =IF(ROW()<4+MinObs-1,"",IFERROR((B6-AVERAGE(B$4:B6))/STDEV(B$4:B6),"")) | X6: =IF(ROW()<4+MinObs-1,"",IFERROR((C6-AVERAGE(C$4:C6))/STDEV(C$4:C6),"")) | Y6: =IF(ROW()<4+MinObs-1,"",IFERROR((D6-AVERAGE(D$4:D6))/STDEV(D$4:D6),"")) | Z6: =IF(ROW()<4+MinObs-1,"",IFERROR((E6-AVERAGE(E$4:E6))/STDEV(E$4:E6),"")) | AA6: =IF(ROW()<4+MinObs-1,"",IFERROR((F6-AVERAGE(F$4:F6))/STDEV(F$4:F6),"")) | AB6: =IF(ROW()<4+MinObs-1,"",IFERROR((G6-AVERAGE(G$4:G6))/STDEV(G$4:G6),"")) | AC6: =IF(ROW()<4+MinObs-1,"",IFERROR((H6-AVERAGE(H$4:H6))/STDEV(H$4:H6),"")) | AD6: =IF(ROW()<4+MinObs-1,"",IFERROR((I6-AVERAGE(I$4:I6))/STDEV(I$4:I6),"")) | ... AQ6: =IF(ROW()<4+MinObs-1,"",IFERROR((V6-AVERAGE(V$4:V6))/STDEV(V$4:V6),"")) | AR6: =IF(W6="",0,IF(W6>=z4,w4,IF(W6>=z3,w3,IF(W6>=zEntry,w2,IF(AND(W6>=ExitZ,AR5>0),w2,0))))) -> 0 | AS6: =IF(X6="",0,IF(X6>=z4,w4,IF(X6>=z3,w3,IF(X6>=zEntry,w2,IF(AND(X6>=ExitZ,AS5>0),w2,0))))) -> 0 | AT6: =IF(Y6="",0,IF(Y6>=z4,w4,IF(Y6>=z3,w3,IF(Y6>=zEntry,w2,IF(AND(Y6>=ExitZ,AT5>0),w2,0))))) -> 0 | AU6: =IF(Z6="",0,IF(Z6>=z4,w4,IF(Z6>=z3,w3,IF(Z6>=zEntry,w2,IF(AND(Z6>=ExitZ,AU5>0),w2,0))))) -> 0 | AV6: =IF(AA6="",0,IF(AA6>=z4,w4,IF(AA6>=z3,w3,IF(AA6>=zEntry,w2,IF(AND(AA6>=ExitZ,AV5>0),w2,0))))) -> 0 | AW6: =IF(AB6="",0,IF(AB6>=z4,w4,IF(AB6>=z3,w3,IF(AB6>=zEntry,w2,IF(AND(AB6>=ExitZ,AW5>0),w2,0))))) -> 0 | AX6: =IF(AC6="",0,IF(AC6>=z4,w4,IF(AC6>=z3,w3,IF(AC6>=zEntry,w2,IF(AND(AC6>=ExitZ,AX5>0),w2,0))))) -> 0 | AY6: =IF(AD6="",0,IF(AD6>=z4,w4,IF(AD6>=z3,w3,IF(AD6>=zEntry,w2,IF(AND(AD6>=ExitZ,AY5>0),w2,0))))) -> 0 | ... BL6: =IF(AQ6="",0,IF(AQ6>=z4,w4,IF(AQ6>=z3,w3,IF(AQ6>=zEntry,w2,IF(AND(AQ6>=ExitZ,BL5>0),w2,0))))) -> 0 | BM6: =IF(Rates_Data!AD5>=Rates_Data!AE5,Rates_Data!AK6-Rates_Data!AL6,Rates_Data!AL6-Rates_Data!AK6) -> -0.009462 | BN6: =IF(Rates_Data!AD5>=Rates_Data!AF5,Rates_Data!AK6-Rates_Data!AM6,Rates_Data!AM6-Rates_Data!AK6) -> -0.000703 | BO6: =IF(Rates_Data!AD5>=Rates_Data!AG5,Rates_Data!AK6-Rates_Data!AN6,Rates_Data!AN6-Rates_Data!AK6) -> -0.004123 | BP6: =IF(Rates_Data!AD5>=Rates_Data!AH5,Rates_Data!AK6-Rates_Data!AO6,Rates_Data!AO6-Rates_Data!AK6) -> 0.001558 | BQ6: =IF(Rates_Data!AD5>=Rates_Data!AI5,Rates_Data!AK6-Rates_Data!AP6,Rates_Data!AP6-Rates_Data!AK6) -> -0.008664 | BR6: =IF(Rates_Data!AD5>=Rates_Data!AJ5,Rates_Data!AK6-Rates_Data!AQ6,Rates_Data!AQ6-Rates_Data!AK6) -> -0.001881 | BS6: =IF(Rates_Data!AE5>=Rates_Data!AF5,Rates_Data!AL6-Rates_Data!AM6,Rates_Data!AM6-Rates_Data!AL6) -> 0.008759 | BT6: =IF(Rates_Data!AE5>=Rates_Data!AG5,Rates_Data!AL6-Rates_Data!AN6,Rates_Data!AN6-Rates_Data!AL6) -> 0.005339 | BU6: =IF(Rates_Data!AE5>=Rates_Data!AH5,Rates_Data!AL6-Rates_Data!AO6,Rates_Data!AO6-Rates_Data!AL6) -> -0.007904 | BV6: =IF(Rates_Data!AE5>=Rates_Data!AI5,Rates_Data!AL6-Rates_Data!AP6,Rates_Data!AP6-Rates_Data!AL6) -> 0.000798 | BW6: =IF(Rates_Data!AE5>=Rates_Data!AJ5,Rates_Data!AL6-Rates_Data!AQ6,Rates_Data!AQ6-Rates_Data!AL6) -> -0.007581 | BX6: =IF(Rates_Data!AF5>=Rates_Data!AG5,Rates_Data!AM6-Rates_Data!AN6,Rates_Data!AN6-Rates_Data!AM6) -> 0.00342 | BY6: =IF(Rates_Data!AF5>=Rates_Data!AH5,Rates_Data!AM6-Rates_Data!AO6,Rates_Data!AO6-Rates_Data!AM6) -> 0.000855 | BZ6: =IF(Rates_Data!AF5>=Rates_Data!AI5,Rates_Data!AM6-Rates_Data!AP6,Rates_Data!AP6-Rates_Data!AM6) -> -0.007961 | CA6: =IF(Rates_Data!AF5>=Rates_Data!AJ5,Rates_Data!AM6-Rates_Data!AQ6,Rates_Data!AQ6-Rates_Data!AM6) -> 0.001178 | CB6: =IF(Rates_Data!AG5>=Rates_Data!AH5,Rates_Data!AN6-Rates_Data!AO6,Rates_Data!AO6-Rates_Data!AN6) -> -0.002565 | CC6: =IF(Rates_Data!AG5>=Rates_Data!AI5,Rates_Data!AN6-Rates_Data!AP6,Rates_Data!AP6-Rates_Data!AN6) -> -0.004541 | CD6: =IF(Rates_Data!AG5>=Rates_Data!AJ5,Rates_Data!AN6-Rates_Data!AQ6,Rates_Data!AQ6-Rates_Data!AN6) -> -0.002242 | CE6: =IF(Rates_Data!AH5>=Rates_Data!AI5,Rates_Data!AO6-Rates_Data!AP6,Rates_Data!AP6-Rates_Data!AO6) -> -0.007106 | CF6: =IF(Rates_Data!AH5>=Rates_Data!AJ5,Rates_Data!AO6-Rates_Data!AQ6,Rates_Data!AQ6-Rates_Data!AO6) -> -0.000323 | CG6: =IF(Rates_Data!AI5>=Rates_Data!AJ5,Rates_Data!AP6-Rates_Data!AQ6,Rates_Data!AQ6-Rates_Data!AP6) -> -0.006783 | CH6: =IF(ROW()<4+VolLB,"",STDEV(INDEX($BM:$BM,ROW()-VolLB+1):INDEX($BM:$BM,ROW()))*SQRT(12)) | CI6: =IF(ROW()<4+VolLB,"",STDEV(INDEX($BN:$BN,ROW()-VolLB+1):INDEX($BN:$BN,ROW()))*SQRT(12)) | CJ6: =IF(ROW()<4+VolLB,"",STDEV(INDEX($BO:$BO,ROW()-VolLB+1):INDEX($BO:$BO,ROW()))*SQRT(12)) | CK6: =IF(ROW()<4+VolLB,"",STDEV(INDEX($BP:$BP,ROW()-VolLB+1):INDEX($BP:$BP,ROW()))*SQRT(12)) | CL6: =IF(ROW()<4+VolLB,"",STDEV(INDEX($BQ:$BQ,ROW()-VolLB+1):INDEX($BQ:$BQ,ROW()))*SQRT(12)) | CM6: =IF(ROW()<4+VolLB,"",STDEV(INDEX($BR:$BR,ROW()-VolLB+1):INDEX($BR:$BR,ROW()))*SQRT(12)) | CN6: =IF(ROW()<4+VolLB,"",STDEV(INDEX($BS:$BS,ROW()-VolLB+1):INDEX($BS:$BS,ROW()))*SQRT(12)) | CO6: =IF(ROW()<4+VolLB,"",STDEV(INDEX($BT:$BT,ROW()-VolLB+1):INDEX($BT:$BT,ROW()))*SQRT(12)) | CP6: =IF(ROW()<4+VolLB,"",STDEV(INDEX($BU:$BU,ROW()-VolLB+1):INDEX($BU:$BU,ROW()))*SQRT(12)) | CQ6: =IF(ROW()<4+VolLB,"",STDEV(INDEX($BV:$BV,ROW()-VolLB+1):INDEX($BV:$BV,ROW()))*SQRT(12)) | CR6: =IF(ROW()<4+VolLB,"",STDEV(INDEX($BW:$BW,ROW()-VolLB+1):INDEX($BW:$BW,ROW()))*SQRT(12)) | CS6: =IF(ROW()<4+VolLB,"",STDEV(INDEX($BX:$BX,ROW()-VolLB+1):INDEX($BX:$BX,ROW()))*SQRT(12)) | CT6: =IF(ROW()<4+VolLB,"",STDEV(INDEX($BY:$BY,ROW()-VolLB+1):INDEX($BY:$BY,ROW()))*SQRT(12)) | CU6: =IF(ROW()<4+VolLB,"",STDEV(INDEX($BZ:$BZ,ROW()-VolLB+1):INDEX($BZ:$BZ,ROW()))*SQRT(12)) | CV6: =IF(ROW()<4+VolLB,"",STDEV(INDEX($CA:$CA,ROW()-VolLB+1):INDEX($CA:$CA,ROW()))*SQRT(12)) | CW6: =IF(ROW()<4+VolLB,"",STDEV(INDEX($CB:$CB,ROW()-VolLB+1):INDEX($CB:$CB,ROW()))*SQRT(12)) | CX6: =IF(ROW()<4+VolLB,"",STDEV(INDEX($CC:$CC,ROW()-VolLB+1):INDEX($CC:$CC,ROW()))*SQRT(12)) | CY6: =IF(ROW()<4+VolLB,"",STDEV(INDEX($CD:$CD,ROW()-VolLB+1):INDEX($CD:$CD,ROW()))*SQRT(12)) | CZ6: =IF(ROW()<4+VolLB,"",STDEV(INDEX($CE:$CE,ROW()-VolLB+1):INDEX($CE:$CE,ROW()))*SQRT(12)) | DA6: =IF(ROW()<4+VolLB,"",STDEV(INDEX($CF:$CF,ROW()-VolLB+1):INDEX($CF:$CF,ROW()))*SQRT(12)) | DB6: =IF(ROW()<4+VolLB,"",STDEV(INDEX($CG:$CG,ROW()-VolLB+1):INDEX($CG:$CG,ROW()))*SQRT(12)) | DC6: =IF(OR(AR6=0,CH6="",CH6=0),0,AR6*MIN(MaxScal,TgtVol/CH6)) -> 0 | DD6: =IF(OR(AS6=0,CI6="",CI6=0),0,AS6*MIN(MaxScal,TgtVol/CI6)) -> 0 | DE6: =IF(OR(AT6=0,CJ6="",CJ6=0),0,AT6*MIN(MaxScal,TgtVol/CJ6)) -> 0 | DF6: =IF(OR(AU6=0,CK6="",CK6=0),0,AU6*MIN(MaxScal,TgtVol/CK6)) -> 0 | DG6: =IF(OR(AV6=0,CL6="",CL6=0),0,AV6*MIN(MaxScal,TgtVol/CL6)) -> 0 | DH6: =IF(OR(AW6=0,CM6="",CM6=0),0,AW6*MIN(MaxScal,TgtVol/CM6)) -> 0 | DI6: =IF(OR(AX6=0,CN6="",CN6=0),0,AX6*MIN(MaxScal,TgtVol/CN6)) -> 0 | DJ6: =IF(OR(AY6=0,CO6="",CO6=0),0,AY6*MIN(MaxScal,TgtVol/CO6)) -> 0 | ... DW6: =IF(OR(BL6=0,DB6="",DB6=0),0,BL6*MIN(MaxScal,TgtVol/DB6)) -> 0 | DX6: =IFERROR(DC5*BM6,"") -> 0 | DY6: =IFERROR(DD5*BN6,"") -> 0 | DZ6: =IFERROR(DE5*BO6,"") -> 0 | EA6: =IFERROR(DF5*BP6,"") -> 0 | EB6: =IFERROR(DG5*BQ6,"") -> 0 | EC6: =IFERROR(DH5*BR6,"") -> 0 | ED6: =IFERROR(DI5*BS6,"") -> 0 | EE6: =IFERROR(DJ5*BT6,"") -> 0 | ... ER6: =IFERROR(DW5*CG6,"") -> 0 | ES6: =IF(ROW()=4,"",SUM(DX6:ER6)) -> 0 | ET6: =COUNTIF(AR6:BL6,">0") -> 0
A7: 38107 | B7: =ABS(Rates_Data!AD7-Rates_Data!AE7) -> 0.2745 | C7: =ABS(Rates_Data!AD7-Rates_Data!AF7) -> 0.37125 | D7: =ABS(Rates_Data!AD7-Rates_Data!AG7) -> 0.20725 | E7: =ABS(Rates_Data!AD7-Rates_Data!AH7) -> 0.37075 | F7: =ABS(Rates_Data!AD7-Rates_Data!AI7) -> 0.4355 | G7: =ABS(Rates_Data!AD7-Rates_Data!AJ7) -> 0.2285 | H7: =ABS(Rates_Data!AE7-Rates_Data!AF7) -> 0.09675 | I7: =ABS(Rates_Data!AE7-Rates_Data!AG7) -> 0.06725 | J7: =ABS(Rates_Data!AE7-Rates_Data!AH7) -> 0.09625 | K7: =ABS(Rates_Data!AE7-Rates_Data!AI7) -> 0.161 | L7: =ABS(Rates_Data!AE7-Rates_Data!AJ7) -> 0.046 | M7: =ABS(Rates_Data!AF7-Rates_Data!AG7) -> 0.164 | N7: =ABS(Rates_Data!AF7-Rates_Data!AH7) -> 0.0005 | O7: =ABS(Rates_Data!AF7-Rates_Data!AI7) -> 0.06425 | P7: =ABS(Rates_Data!AF7-Rates_Data!AJ7) -> 0.14275 | Q7: =ABS(Rates_Data!AG7-Rates_Data!AH7) -> 0.1635 | R7: =ABS(Rates_Data!AG7-Rates_Data!AI7) -> 0.22825 | S7: =ABS(Rates_Data!AG7-Rates_Data!AJ7) -> 0.02125 | T7: =ABS(Rates_Data!AH7-Rates_Data!AI7) -> 0.06475 | U7: =ABS(Rates_Data!AH7-Rates_Data!AJ7) -> 0.14225 | V7: =ABS(Rates_Data!AI7-Rates_Data!AJ7) -> 0.207 | W7: =IF(ROW()<4+MinObs-1,"",IFERROR((B7-AVERAGE(B$4:B7))/STDEV(B$4:B7),"")) | X7: =IF(ROW()<4+MinObs-1,"",IFERROR((C7-AVERAGE(C$4:C7))/STDEV(C$4:C7),"")) | Y7: =IF(ROW()<4+MinObs-1,"",IFERROR((D7-AVERAGE(D$4:D7))/STDEV(D$4:D7),"")) | Z7: =IF(ROW()<4+MinObs-1,"",IFERROR((E7-AVERAGE(E$4:E7))/STDEV(E$4:E7),"")) | AA7: =IF(ROW()<4+MinObs-1,"",IFERROR((F7-AVERAGE(F$4:F7))/STDEV(F$4:F7),"")) | AB7: =IF(ROW()<4+MinObs-1,"",IFERROR((G7-AVERAGE(G$4:G7))/STDEV(G$4:G7),"")) | AC7: =IF(ROW()<4+MinObs-1,"",IFERROR((H7-AVERAGE(H$4:H7))/STDEV(H$4:H7),"")) | AD7: =IF(ROW()<4+MinObs-1,"",IFERROR((I7-AVERAGE(I$4:I7))/STDEV(I$4:I7),"")) | ... AQ7: =IF(ROW()<4+MinObs-1,"",IFERROR((V7-AVERAGE(V$4:V7))/STDEV(V$4:V7),"")) | AR7: =IF(W7="",0,IF(W7>=z4,w4,IF(W7>=z3,w3,IF(W7>=zEntry,w2,IF(AND(W7>=ExitZ,AR6>0),w2,0))))) -> 0 | AS7: =IF(X7="",0,IF(X7>=z4,w4,IF(X7>=z3,w3,IF(X7>=zEntry,w2,IF(AND(X7>=ExitZ,AS6>0),w2,0))))) -> 0 | AT7: =IF(Y7="",0,IF(Y7>=z4,w4,IF(Y7>=z3,w3,IF(Y7>=zEntry,w2,IF(AND(Y7>=ExitZ,AT6>0),w2,0))))) -> 0 | AU7: =IF(Z7="",0,IF(Z7>=z4,w4,IF(Z7>=z3,w3,IF(Z7>=zEntry,w2,IF(AND(Z7>=ExitZ,AU6>0),w2,0))))) -> 0 | AV7: =IF(AA7="",0,IF(AA7>=z4,w4,IF(AA7>=z3,w3,IF(AA7>=zEntry,w2,IF(AND(AA7>=ExitZ,AV6>0),w2,0))))) -> 0 | AW7: =IF(AB7="",0,IF(AB7>=z4,w4,IF(AB7>=z3,w3,IF(AB7>=zEntry,w2,IF(AND(AB7>=ExitZ,AW6>0),w2,0))))) -> 0 | AX7: =IF(AC7="",0,IF(AC7>=z4,w4,IF(AC7>=z3,w3,IF(AC7>=zEntry,w2,IF(AND(AC7>=ExitZ,AX6>0),w2,0))))) -> 0 | AY7: =IF(AD7="",0,IF(AD7>=z4,w4,IF(AD7>=z3,w3,IF(AD7>=zEntry,w2,IF(AND(AD7>=ExitZ,AY6>0),w2,0))))) -> 0 | ... BL7: =IF(AQ7="",0,IF(AQ7>=z4,w4,IF(AQ7>=z3,w3,IF(AQ7>=zEntry,w2,IF(AND(AQ7>=ExitZ,BL6>0),w2,0))))) -> 0 | BM7: =IF(Rates_Data!AD6>=Rates_Data!AE6,Rates_Data!AK7-Rates_Data!AL7,Rates_Data!AL7-Rates_Data!AK7) -> -0.004199 | BN7: =IF(Rates_Data!AD6>=Rates_Data!AF6,Rates_Data!AK7-Rates_Data!AM7,Rates_Data!AM7-Rates_Data!AK7) -> -0.007106 | BO7: =IF(Rates_Data!AD6>=Rates_Data!AG6,Rates_Data!AK7-Rates_Data!AN7,Rates_Data!AN7-Rates_Data!AK7) -> -0.004294 | BP7: =IF(Rates_Data!AD6>=Rates_Data!AH6,Rates_Data!AK7-Rates_Data!AO7,Rates_Data!AO7-Rates_Data!AK7) -> -0.017993 | BQ7: =IF(Rates_Data!AD6>=Rates_Data!AI6,Rates_Data!AK7-Rates_Data!AP7,Rates_Data!AP7-Rates_Data!AK7) -> -0.007049 | BR7: =IF(Rates_Data!AD6>=Rates_Data!AJ6,Rates_Data!AK7-Rates_Data!AQ7,Rates_Data!AQ7-Rates_Data!AK7) -> -0.006897 | BS7: =IF(Rates_Data!AE6>=Rates_Data!AF6,Rates_Data!AL7-Rates_Data!AM7,Rates_Data!AM7-Rates_Data!AL7) -> -0.002907 | BT7: =IF(Rates_Data!AE6>=Rates_Data!AG6,Rates_Data!AL7-Rates_Data!AN7,Rates_Data!AN7-Rates_Data!AL7) -> -9.5e-05 | BU7: =IF(Rates_Data!AE6>=Rates_Data!AH6,Rates_Data!AL7-Rates_Data!AO7,Rates_Data!AO7-Rates_Data!AL7) -> -0.013794 | BV7: =IF(Rates_Data!AE6>=Rates_Data!AI6,Rates_Data!AL7-Rates_Data!AP7,Rates_Data!AP7-Rates_Data!AL7) -> -0.00285 | BW7: =IF(Rates_Data!AE6>=Rates_Data!AJ6,Rates_Data!AL7-Rates_Data!AQ7,Rates_Data!AQ7-Rates_Data!AL7) -> 0.002698 | BX7: =IF(Rates_Data!AF6>=Rates_Data!AG6,Rates_Data!AM7-Rates_Data!AN7,Rates_Data!AN7-Rates_Data!AM7) -> -0.002812 | BY7: =IF(Rates_Data!AF6>=Rates_Data!AH6,Rates_Data!AM7-Rates_Data!AO7,Rates_Data!AO7-Rates_Data!AM7) -> 0.010887 | BZ7: =IF(Rates_Data!AF6>=Rates_Data!AI6,Rates_Data!AM7-Rates_Data!AP7,Rates_Data!AP7-Rates_Data!AM7) -> 5.7e-05 | CA7: =IF(Rates_Data!AF6>=Rates_Data!AJ6,Rates_Data!AM7-Rates_Data!AQ7,Rates_Data!AQ7-Rates_Data!AM7) -> -0.000209 | CB7: =IF(Rates_Data!AG6>=Rates_Data!AH6,Rates_Data!AN7-Rates_Data!AO7,Rates_Data!AO7-Rates_Data!AN7) -> 0.013699 | CC7: =IF(Rates_Data!AG6>=Rates_Data!AI6,Rates_Data!AN7-Rates_Data!AP7,Rates_Data!AP7-Rates_Data!AN7) -> -0.002755 | CD7: =IF(Rates_Data!AG6>=Rates_Data!AJ6,Rates_Data!AN7-Rates_Data!AQ7,Rates_Data!AQ7-Rates_Data!AN7) -> 0.002603 | CE7: =IF(Rates_Data!AH6>=Rates_Data!AI6,Rates_Data!AO7-Rates_Data!AP7,Rates_Data!AP7-Rates_Data!AO7) -> 0.010944 | CF7: =IF(Rates_Data!AH6>=Rates_Data!AJ6,Rates_Data!AO7-Rates_Data!AQ7,Rates_Data!AQ7-Rates_Data!AO7) -> -0.011096 | CG7: =IF(Rates_Data!AI6>=Rates_Data!AJ6,Rates_Data!AP7-Rates_Data!AQ7,Rates_Data!AQ7-Rates_Data!AP7) -> -0.000152 | CH7: =IF(ROW()<4+VolLB,"",STDEV(INDEX($BM:$BM,ROW()-VolLB+1):INDEX($BM:$BM,ROW()))*SQRT(12)) | CI7: =IF(ROW()<4+VolLB,"",STDEV(INDEX($BN:$BN,ROW()-VolLB+1):INDEX($BN:$BN,ROW()))*SQRT(12)) | CJ7: =IF(ROW()<4+VolLB,"",STDEV(INDEX($BO:$BO,ROW()-VolLB+1):INDEX($BO:$BO,ROW()))*SQRT(12)) | CK7: =IF(ROW()<4+VolLB,"",STDEV(INDEX($BP:$BP,ROW()-VolLB+1):INDEX($BP:$BP,ROW()))*SQRT(12)) | CL7: =IF(ROW()<4+VolLB,"",STDEV(INDEX($BQ:$BQ,ROW()-VolLB+1):INDEX($BQ:$BQ,ROW()))*SQRT(12)) | CM7: =IF(ROW()<4+VolLB,"",STDEV(INDEX($BR:$BR,ROW()-VolLB+1):INDEX($BR:$BR,ROW()))*SQRT(12)) | CN7: =IF(ROW()<4+VolLB,"",STDEV(INDEX($BS:$BS,ROW()-VolLB+1):INDEX($BS:$BS,ROW()))*SQRT(12)) | CO7: =IF(ROW()<4+VolLB,"",STDEV(INDEX($BT:$BT,ROW()-VolLB+1):INDEX($BT:$BT,ROW()))*SQRT(12)) | CP7: =IF(ROW()<4+VolLB,"",STDEV(INDEX($BU:$BU,ROW()-VolLB+1):INDEX($BU:$BU,ROW()))*SQRT(12)) | CQ7: =IF(ROW()<4+VolLB,"",STDEV(INDEX($BV:$BV,ROW()-VolLB+1):INDEX($BV:$BV,ROW()))*SQRT(12)) | CR7: =IF(ROW()<4+VolLB,"",STDEV(INDEX($BW:$BW,ROW()-VolLB+1):INDEX($BW:$BW,ROW()))*SQRT(12)) | CS7: =IF(ROW()<4+VolLB,"",STDEV(INDEX($BX:$BX,ROW()-VolLB+1):INDEX($BX:$BX,ROW()))*SQRT(12)) | CT7: =IF(ROW()<4+VolLB,"",STDEV(INDEX($BY:$BY,ROW()-VolLB+1):INDEX($BY:$BY,ROW()))*SQRT(12)) | CU7: =IF(ROW()<4+VolLB,"",STDEV(INDEX($BZ:$BZ,ROW()-VolLB+1):INDEX($BZ:$BZ,ROW()))*SQRT(12)) | CV7: =IF(ROW()<4+VolLB,"",STDEV(INDEX($CA:$CA,ROW()-VolLB+1):INDEX($CA:$CA,ROW()))*SQRT(12)) | CW7: =IF(ROW()<4+VolLB,"",STDEV(INDEX($CB:$CB,ROW()-VolLB+1):INDEX($CB:$CB,ROW()))*SQRT(12)) | CX7: =IF(ROW()<4+VolLB,"",STDEV(INDEX($CC:$CC,ROW()-VolLB+1):INDEX($CC:$CC,ROW()))*SQRT(12)) | CY7: =IF(ROW()<4+VolLB,"",STDEV(INDEX($CD:$CD,ROW()-VolLB+1):INDEX($CD:$CD,ROW()))*SQRT(12)) | CZ7: =IF(ROW()<4+VolLB,"",STDEV(INDEX($CE:$CE,ROW()-VolLB+1):INDEX($CE:$CE,ROW()))*SQRT(12)) | DA7: =IF(ROW()<4+VolLB,"",STDEV(INDEX($CF:$CF,ROW()-VolLB+1):INDEX($CF:$CF,ROW()))*SQRT(12)) | DB7: =IF(ROW()<4+VolLB,"",STDEV(INDEX($CG:$CG,ROW()-VolLB+1):INDEX($CG:$CG,ROW()))*SQRT(12)) | DC7: =IF(OR(AR7=0,CH7="",CH7=0),0,AR7*MIN(MaxScal,TgtVol/CH7)) -> 0 | DD7: =IF(OR(AS7=0,CI7="",CI7=0),0,AS7*MIN(MaxScal,TgtVol/CI7)) -> 0 | DE7: =IF(OR(AT7=0,CJ7="",CJ7=0),0,AT7*MIN(MaxScal,TgtVol/CJ7)) -> 0 | DF7: =IF(OR(AU7=0,CK7="",CK7=0),0,AU7*MIN(MaxScal,TgtVol/CK7)) -> 0 | DG7: =IF(OR(AV7=0,CL7="",CL7=0),0,AV7*MIN(MaxScal,TgtVol/CL7)) -> 0 | DH7: =IF(OR(AW7=0,CM7="",CM7=0),0,AW7*MIN(MaxScal,TgtVol/CM7)) -> 0 | DI7: =IF(OR(AX7=0,CN7="",CN7=0),0,AX7*MIN(MaxScal,TgtVol/CN7)) -> 0 | DJ7: =IF(OR(AY7=0,CO7="",CO7=0),0,AY7*MIN(MaxScal,TgtVol/CO7)) -> 0 | ... DW7: =IF(OR(BL7=0,DB7="",DB7=0),0,BL7*MIN(MaxScal,TgtVol/DB7)) -> 0 | DX7: =IFERROR(DC6*BM7,"") -> 0 | DY7: =IFERROR(DD6*BN7,"") -> 0 | DZ7: =IFERROR(DE6*BO7,"") -> 0 | EA7: =IFERROR(DF6*BP7,"") -> 0 | EB7: =IFERROR(DG6*BQ7,"") -> 0 | EC7: =IFERROR(DH6*BR7,"") -> 0 | ED7: =IFERROR(DI6*BS7,"") -> 0 | EE7: =IFERROR(DJ6*BT7,"") -> 0 | ... ER7: =IFERROR(DW6*CG7,"") -> 0 | ES7: =IF(ROW()=4,"",SUM(DX7:ER7)) -> 0 | ET7: =COUNTIF(AR7:BL7,">0") -> 0
A8: 38138 | B8: =ABS(Rates_Data!AD8-Rates_Data!AE8) -> 0.1196 | C8: =ABS(Rates_Data!AD8-Rates_Data!AF8) -> 0.2434 | D8: =ABS(Rates_Data!AD8-Rates_Data!AG8) -> 0.1654 | E8: =ABS(Rates_Data!AD8-Rates_Data!AH8) -> 0.3822 | F8: =ABS(Rates_Data!AD8-Rates_Data!AI8) -> 0.406 | G8: =ABS(Rates_Data!AD8-Rates_Data!AJ8) -> 0.2724 | H8: =ABS(Rates_Data!AE8-Rates_Data!AF8) -> 0.1238 | I8: =ABS(Rates_Data!AE8-Rates_Data!AG8) -> 0.285 | J8: =ABS(Rates_Data!AE8-Rates_Data!AH8) -> 0.2626 | K8: =ABS(Rates_Data!AE8-Rates_Data!AI8) -> 0.2864 | L8: =ABS(Rates_Data!AE8-Rates_Data!AJ8) -> 0.1528 | M8: =ABS(Rates_Data!AF8-Rates_Data!AG8) -> 0.4088 | N8: =ABS(Rates_Data!AF8-Rates_Data!AH8) -> 0.1388 | O8: =ABS(Rates_Data!AF8-Rates_Data!AI8) -> 0.1626 | P8: =ABS(Rates_Data!AF8-Rates_Data!AJ8) -> 0.029 | Q8: =ABS(Rates_Data!AG8-Rates_Data!AH8) -> 0.5476 | R8: =ABS(Rates_Data!AG8-Rates_Data!AI8) -> 0.5714 | S8: =ABS(Rates_Data!AG8-Rates_Data!AJ8) -> 0.4378 | T8: =ABS(Rates_Data!AH8-Rates_Data!AI8) -> 0.0238 | U8: =ABS(Rates_Data!AH8-Rates_Data!AJ8) -> 0.1098 | V8: =ABS(Rates_Data!AI8-Rates_Data!AJ8) -> 0.1336 | W8: =IF(ROW()<4+MinObs-1,"",IFERROR((B8-AVERAGE(B$4:B8))/STDEV(B$4:B8),"")) | X8: =IF(ROW()<4+MinObs-1,"",IFERROR((C8-AVERAGE(C$4:C8))/STDEV(C$4:C8),"")) | Y8: =IF(ROW()<4+MinObs-1,"",IFERROR((D8-AVERAGE(D$4:D8))/STDEV(D$4:D8),"")) | Z8: =IF(ROW()<4+MinObs-1,"",IFERROR((E8-AVERAGE(E$4:E8))/STDEV(E$4:E8),"")) | AA8: =IF(ROW()<4+MinObs-1,"",IFERROR((F8-AVERAGE(F$4:F8))/STDEV(F$4:F8),"")) | AB8: =IF(ROW()<4+MinObs-1,"",IFERROR((G8-AVERAGE(G$4:G8))/STDEV(G$4:G8),"")) | AC8: =IF(ROW()<4+MinObs-1,"",IFERROR((H8-AVERAGE(H$4:H8))/STDEV(H$4:H8),"")) | AD8: =IF(ROW()<4+MinObs-1,"",IFERROR((I8-AVERAGE(I$4:I8))/STDEV(I$4:I8),"")) | ... AQ8: =IF(ROW()<4+MinObs-1,"",IFERROR((V8-AVERAGE(V$4:V8))/STDEV(V$4:V8),"")) | AR8: =IF(W8="",0,IF(W8>=z4,w4,IF(W8>=z3,w3,IF(W8>=zEntry,w2,IF(AND(W8>=ExitZ,AR7>0),w2,0))))) -> 0 | AS8: =IF(X8="",0,IF(X8>=z4,w4,IF(X8>=z3,w3,IF(X8>=zEntry,w2,IF(AND(X8>=ExitZ,AS7>0),w2,0))))) -> 0 | AT8: =IF(Y8="",0,IF(Y8>=z4,w4,IF(Y8>=z3,w3,IF(Y8>=zEntry,w2,IF(AND(Y8>=ExitZ,AT7>0),w2,0))))) -> 0 | AU8: =IF(Z8="",0,IF(Z8>=z4,w4,IF(Z8>=z3,w3,IF(Z8>=zEntry,w2,IF(AND(Z8>=ExitZ,AU7>0),w2,0))))) -> 0 | AV8: =IF(AA8="",0,IF(AA8>=z4,w4,IF(AA8>=z3,w3,IF(AA8>=zEntry,w2,IF(AND(AA8>=ExitZ,AV7>0),w2,0))))) -> 0 | AW8: =IF(AB8="",0,IF(AB8>=z4,w4,IF(AB8>=z3,w3,IF(AB8>=zEntry,w2,IF(AND(AB8>=ExitZ,AW7>0),w2,0))))) -> 0 | AX8: =IF(AC8="",0,IF(AC8>=z4,w4,IF(AC8>=z3,w3,IF(AC8>=zEntry,w2,IF(AND(AC8>=ExitZ,AX7>0),w2,0))))) -> 0 | AY8: =IF(AD8="",0,IF(AD8>=z4,w4,IF(AD8>=z3,w3,IF(AD8>=zEntry,w2,IF(AND(AD8>=ExitZ,AY7>0),w2,0))))) -> 0 | ... BL8: =IF(AQ8="",0,IF(AQ8>=z4,w4,IF(AQ8>=z3,w3,IF(AQ8>=zEntry,w2,IF(AND(AQ8>=ExitZ,BL7>0),w2,0))))) -> 0 | BM8: =IF(Rates_Data!AD7>=Rates_Data!AE7,Rates_Data!AK8-Rates_Data!AL8,Rates_Data!AL8-Rates_Data!AK8) -> -0.000323 | BN8: =IF(Rates_Data!AD7>=Rates_Data!AF7,Rates_Data!AK8-Rates_Data!AM8,Rates_Data!AM8-Rates_Data!AK8) -> 0.003458 | BO8: =IF(Rates_Data!AD7>=Rates_Data!AG7,Rates_Data!AK8-Rates_Data!AN8,Rates_Data!AN8-Rates_Data!AK8) -> 0.008778 | BP8: =IF(Rates_Data!AD7>=Rates_Data!AH7,Rates_Data!AK8-Rates_Data!AO8,Rates_Data!AO8-Rates_Data!AK8) -> 0.003458 | BQ8: =IF(Rates_Data!AD7>=Rates_Data!AI7,Rates_Data!AK8-Rates_Data!AP8,Rates_Data!AP8-Rates_Data!AK8) -> 0.003895 | BR8: =IF(Rates_Data!AD7>=Rates_Data!AJ7,Rates_Data!AK8-Rates_Data!AQ8,Rates_Data!AQ8-Rates_Data!AK8) -> -0.002394 | BS8: =IF(Rates_Data!AE7>=Rates_Data!AF7,Rates_Data!AL8-Rates_Data!AM8,Rates_Data!AM8-Rates_Data!AL8) -> 0.003781 | BT8: =IF(Rates_Data!AE7>=Rates_Data!AG7,Rates_Data!AL8-Rates_Data!AN8,Rates_Data!AN8-Rates_Data!AL8) -> -0.009101 | BU8: =IF(Rates_Data!AE7>=Rates_Data!AH7,Rates_Data!AL8-Rates_Data!AO8,Rates_Data!AO8-Rates_Data!AL8) -> 0.003781 | BV8: =IF(Rates_Data!AE7>=Rates_Data!AI7,Rates_Data!AL8-Rates_Data!AP8,Rates_Data!AP8-Rates_Data!AL8) -> 0.004218 | BW8: =IF(Rates_Data!AE7>=Rates_Data!AJ7,Rates_Data!AL8-Rates_Data!AQ8,Rates_Data!AQ8-Rates_Data!AL8) -> 0.002071 | BX8: =IF(Rates_Data!AF7>=Rates_Data!AG7,Rates_Data!AM8-Rates_Data!AN8,Rates_Data!AN8-Rates_Data!AM8) -> -0.00532 | BY8: =IF(Rates_Data!AF7>=Rates_Data!AH7,Rates_Data!AM8-Rates_Data!AO8,Rates_Data!AO8-Rates_Data!AM8) -> -8.2399365e-18 | BZ8: =IF(Rates_Data!AF7>=Rates_Data!AI7,Rates_Data!AM8-Rates_Data!AP8,Rates_Data!AP8-Rates_Data!AM8) -> 0.000437 | CA8: =IF(Rates_Data!AF7>=Rates_Data!AJ7,Rates_Data!AM8-Rates_Data!AQ8,Rates_Data!AQ8-Rates_Data!AM8) -> 0.005852 | CB8: =IF(Rates_Data!AG7>=Rates_Data!AH7,Rates_Data!AN8-Rates_Data!AO8,Rates_Data!AO8-Rates_Data!AN8) -> -0.00532 | CC8: =IF(Rates_Data!AG7>=Rates_Data!AI7,Rates_Data!AN8-Rates_Data!AP8,Rates_Data!AP8-Rates_Data!AN8) -> -0.004883 | CD8: =IF(Rates_Data!AG7>=Rates_Data!AJ7,Rates_Data!AN8-Rates_Data!AQ8,Rates_Data!AQ8-Rates_Data!AN8) -> -0.011172 | CE8: =IF(Rates_Data!AH7>=Rates_Data!AI7,Rates_Data!AO8-Rates_Data!AP8,Rates_Data!AP8-Rates_Data!AO8) -> 0.000437 | CF8: =IF(Rates_Data!AH7>=Rates_Data!AJ7,Rates_Data!AO8-Rates_Data!AQ8,Rates_Data!AQ8-Rates_Data!AO8) -> 0.005852 | CG8: =IF(Rates_Data!AI7>=Rates_Data!AJ7,Rates_Data!AP8-Rates_Data!AQ8,Rates_Data!AQ8-Rates_Data!AP8) -> 0.006289 | CH8: =IF(ROW()<4+VolLB,"",STDEV(INDEX($BM:$BM,ROW()-VolLB+1):INDEX($BM:$BM,ROW()))*SQRT(12)) | CI8: =IF(ROW()<4+VolLB,"",STDEV(INDEX($BN:$BN,ROW()-VolLB+1):INDEX($BN:$BN,ROW()))*SQRT(12)) | CJ8: =IF(ROW()<4+VolLB,"",STDEV(INDEX($BO:$BO,ROW()-VolLB+1):INDEX($BO:$BO,ROW()))*SQRT(12)) | CK8: =IF(ROW()<4+VolLB,"",STDEV(INDEX($BP:$BP,ROW()-VolLB+1):INDEX($BP:$BP,ROW()))*SQRT(12)) | CL8: =IF(ROW()<4+VolLB,"",STDEV(INDEX($BQ:$BQ,ROW()-VolLB+1):INDEX($BQ:$BQ,ROW()))*SQRT(12)) | CM8: =IF(ROW()<4+VolLB,"",STDEV(INDEX($BR:$BR,ROW()-VolLB+1):INDEX($BR:$BR,ROW()))*SQRT(12)) | CN8: =IF(ROW()<4+VolLB,"",STDEV(INDEX($BS:$BS,ROW()-VolLB+1):INDEX($BS:$BS,ROW()))*SQRT(12)) | CO8: =IF(ROW()<4+VolLB,"",STDEV(INDEX($BT:$BT,ROW()-VolLB+1):INDEX($BT:$BT,ROW()))*SQRT(12)) | CP8: =IF(ROW()<4+VolLB,"",STDEV(INDEX($BU:$BU,ROW()-VolLB+1):INDEX($BU:$BU,ROW()))*SQRT(12)) | CQ8: =IF(ROW()<4+VolLB,"",STDEV(INDEX($BV:$BV,ROW()-VolLB+1):INDEX($BV:$BV,ROW()))*SQRT(12)) | CR8: =IF(ROW()<4+VolLB,"",STDEV(INDEX($BW:$BW,ROW()-VolLB+1):INDEX($BW:$BW,ROW()))*SQRT(12)) | CS8: =IF(ROW()<4+VolLB,"",STDEV(INDEX($BX:$BX,ROW()-VolLB+1):INDEX($BX:$BX,ROW()))*SQRT(12)) | CT8: =IF(ROW()<4+VolLB,"",STDEV(INDEX($BY:$BY,ROW()-VolLB+1):INDEX($BY:$BY,ROW()))*SQRT(12)) | CU8: =IF(ROW()<4+VolLB,"",STDEV(INDEX($BZ:$BZ,ROW()-VolLB+1):INDEX($BZ:$BZ,ROW()))*SQRT(12)) | CV8: =IF(ROW()<4+VolLB,"",STDEV(INDEX($CA:$CA,ROW()-VolLB+1):INDEX($CA:$CA,ROW()))*SQRT(12)) | CW8: =IF(ROW()<4+VolLB,"",STDEV(INDEX($CB:$CB,ROW()-VolLB+1):INDEX($CB:$CB,ROW()))*SQRT(12)) | CX8: =IF(ROW()<4+VolLB,"",STDEV(INDEX($CC:$CC,ROW()-VolLB+1):INDEX($CC:$CC,ROW()))*SQRT(12)) | CY8: =IF(ROW()<4+VolLB,"",STDEV(INDEX($CD:$CD,ROW()-VolLB+1):INDEX($CD:$CD,ROW()))*SQRT(12)) | CZ8: =IF(ROW()<4+VolLB,"",STDEV(INDEX($CE:$CE,ROW()-VolLB+1):INDEX($CE:$CE,ROW()))*SQRT(12)) | DA8: =IF(ROW()<4+VolLB,"",STDEV(INDEX($CF:$CF,ROW()-VolLB+1):INDEX($CF:$CF,ROW()))*SQRT(12)) | DB8: =IF(ROW()<4+VolLB,"",STDEV(INDEX($CG:$CG,ROW()-VolLB+1):INDEX($CG:$CG,ROW()))*SQRT(12)) | DC8: =IF(OR(AR8=0,CH8="",CH8=0),0,AR8*MIN(MaxScal,TgtVol/CH8)) -> 0 | DD8: =IF(OR(AS8=0,CI8="",CI8=0),0,AS8*MIN(MaxScal,TgtVol/CI8)) -> 0 | DE8: =IF(OR(AT8=0,CJ8="",CJ8=0),0,AT8*MIN(MaxScal,TgtVol/CJ8)) -> 0 | DF8: =IF(OR(AU8=0,CK8="",CK8=0),0,AU8*MIN(MaxScal,TgtVol/CK8)) -> 0 | DG8: =IF(OR(AV8=0,CL8="",CL8=0),0,AV8*MIN(MaxScal,TgtVol/CL8)) -> 0 | DH8: =IF(OR(AW8=0,CM8="",CM8=0),0,AW8*MIN(MaxScal,TgtVol/CM8)) -> 0 | DI8: =IF(OR(AX8=0,CN8="",CN8=0),0,AX8*MIN(MaxScal,TgtVol/CN8)) -> 0 | DJ8: =IF(OR(AY8=0,CO8="",CO8=0),0,AY8*MIN(MaxScal,TgtVol/CO8)) -> 0 | ... DW8: =IF(OR(BL8=0,DB8="",DB8=0),0,BL8*MIN(MaxScal,TgtVol/DB8)) -> 0 | DX8: =IFERROR(DC7*BM8,"") -> 0 | DY8: =IFERROR(DD7*BN8,"") -> 0 | DZ8: =IFERROR(DE7*BO8,"") -> 0 | EA8: =IFERROR(DF7*BP8,"") -> 0 | EB8: =IFERROR(DG7*BQ8,"") -> 0 | EC8: =IFERROR(DH7*BR8,"") -> 0 | ED8: =IFERROR(DI7*BS8,"") -> 0 | EE8: =IFERROR(DJ7*BT8,"") -> 0 | ... ER8: =IFERROR(DW7*CG8,"") -> 0 | ES8: =IF(ROW()=4,"",SUM(DX8:ER8)) -> 0 | ET8: =COUNTIF(AR8:BL8,">0") -> 0
