Workbook

Sheet Control
A1: EM ASSET MONITOR — FX / EQUITIES / EM USD CREDIT
A2: Bloomberg-linked. Every cell is a formula; nothing is pasted as a value. Companion to US_Rates_Credit_Monitor.xlsx. Built for A. Rojas, UBS CIO Americas.
A4: SETTINGS — every pull and every calculation on every tab points at these cells
E5: Horizon | F5: Obs back (rows)
A6: History start — daily block | B6: =EDATE(TODAY(),-126) | E6: 1D | F6: 2 | H6: 10.5y buffer so the 10y window is always full
A7: History end | B7: =TODAY() | E7: 1W | F7: 6 | H7: BDH end date
A8: Daily observations pulled | B8: 2610 | E8: 1M | F8: 23 | H8: weekdays; block is HIST_D rows 8:2617
A9: bp per 1% | B9: 100 | E9: 3M | F9: 66 | H9: scaling constant used by every change column
A10: Total-return horizon (years) | B10: 1 | E10: 6M | F10: 131 | H10: used on Scenario
A11: Cash hurdle (%) | B11: 4.5 | E11: 1Y | F11: 262 | H11: your stated hurdle for 'EM debt still attractive vs cash'
A12: EM USD index modified duration (yrs) | B12: 6.6 | E12: 2Y | F12: 523 | H12: INPUT — from embi_tracker.py / Bbg DUR_ADJ_MID
A13: EM USD index YTW (%) | B13: 6.55 | E13: 3Y | F13: 784 | H13: INPUT — from embi_tracker.py / Bbg INDEX_YIELD_TO_WORST
A14: EMBIGD stripped spread (bp) | B14: 208 | E14: 5Y | F14: 1305 | H14: INPUT — embi_tracker.py, 'Dur Wgt STW (Trsy)'. Chain-link across the 04-Sep-26 JPM break.
A15: UST 10Y mod duration proxy (yrs) | B15: 7.9 | E15: 10Y | F15: 2610 | H15: INPUT — par-bond duration at the current 10Y; used for the rates leg only
A16: Point-in-time: 1M ago date | B16: =WORKDAY(TODAY(),-22) | E16: YTD | F16: =NETWORKDAYS(DATE(YEAR(TODAY())-1,12,31),TODAY()) | H16: single-point BDP/BDH pulls
A17: Point-in-time: prior year-end | B17: =DATE(YEAR(TODAY())-1,12,31) | H17: same
A20: HOW TO READ THIS WORKBOOK
A21: 1. Row n of HIST_D is n-1 weekdays ago. Every lookback is INDEX(range, <offset on this sheet>); every window is range_start:INDEX(range, N).
A22: Change one cell in column F and the whole workbook re-windows.
A23: 2. If a history column shows one number instead of a full column, you are on pre-dynamic-array Excel: select the block and re-enter the BDH with Ctrl+Shift+Enter.
A24: 3. FX is quoted EM per USD throughout. Every FX return shown in this workbook is the return ON the EM currency = prior/current - 1. A positive number is EM strength.
A25: 4. The rates leg and the spread leg of EM USD credit are shown separately everywhere. There is no cell that collapses them into one undecomposed number.
A26: 5. Pass-through on the Passthrough tab is d(local 10Y) / d(UST 10Y) over the same window. Below 1.0 means the EM curve absorbed less than the US move.
A27: 6. Uncertain pulls use IFERROR(live, fallback input) with a LIVE/FALLBACK status beside them. Nothing is silently substituted with a modelled proxy.
A28: 7. Anything on Tickers flagged Verify has NOT been confirmed in SECF/FLDS. Confirm before publishing a number that depends on it.
A30: COLOUR LEGEND
A31: Blue text | E31: Hardcoded input or scenario lever — yours to change
A32: Green text | E32: Link to another tab in this workbook
A33: Purple text | E33: Live Bloomberg pull (BDH / BDP)
A34: Black text | E34: Formula computed inside this workbook

Sheet Dashboard
A1: EM ASSET MONITOR — DASHBOARD
A2: Everything on this sheet is a link. Nothing is computed here that is not computed somewhere else first.
A3: ="As of "&TEXT(INDEX(HIST_D!$A$8:$A$2617,1),"d mmm yyyy")&" | built "&TEXT(TODAY(),"d mmm yyyy")
A5: THE US SIDE — what EM is being asked to absorb
A6: Series | B6: Unit | C6: Level | D6: 1W | E6: 1M | F6: 3M | G6: YTD | H6: 1Y | I6: %ile 1y | J6: %ile 5y
A7: UST 2Y | B7: bp | C7: =INDEX(HIST_D!$B$8:$B$2617,1) | D7: =IFERROR((INDEX(HIST_D!$B$8:$B$2617,1)-INDEX(HIST_D!$B$8:$B$2617,Control!$F$7))*100,"") | E7: =IFERROR((INDEX(HIST_D!$B$8:$B$2617,1)-INDEX(HIST_D!$B$8:$B$2617,Control!$F$8))*100,"") | F7: =IFERROR((INDEX(HIST_D!$B$8:$B$2617,1)-INDEX(HIST_D!$B$8:$B$2617,Control!$F$9))*100,"") | G7: =IFERROR((INDEX(HIST_D!$B$8:$B$2617,1)-INDEX(HIST_D!$B$8:$B$2617,Control!$F$16))*100,"") | H7: =IFERROR((INDEX(HIST_D!$B$8:$B$2617,1)-INDEX(HIST_D!$B$8:$B$2617,Control!$F$11))*100,"") | I7: =IFERROR(PERCENTRANK(HIST_D!$B$8:INDEX(HIST_D!$B$8:$B$2617,Control!$F$11),INDEX(HIST_D!$B$8:$B$2617,1)),"") | J7: =IFERROR(PERCENTRANK(HIST_D!$B$8:INDEX(HIST_D!$B$8:$B$2617,Control!$F$14),INDEX(HIST_D!$B$8:$B$2617,1)),"")
A8: UST 10Y | B8: bp | C8: =INDEX(HIST_D!$D$8:$D$2617,1) | D8: =IFERROR((INDEX(HIST_D!$D$8:$D$2617,1)-INDEX(HIST_D!$D$8:$D$2617,Control!$F$7))*100,"") | E8: =IFERROR((INDEX(HIST_D!$D$8:$D$2617,1)-INDEX(HIST_D!$D$8:$D$2617,Control!$F$8))*100,"") | F8: =IFERROR((INDEX(HIST_D!$D$8:$D$2617,1)-INDEX(HIST_D!$D$8:$D$2617,Control!$F$9))*100,"") | G8: =IFERROR((INDEX(HIST_D!$D$8:$D$2617,1)-INDEX(HIST_D!$D$8:$D$2617,Control!$F$16))*100,"") | H8: =IFERROR((INDEX(HIST_D!$D$8:$D$2617,1)-INDEX(HIST_D!$D$8:$D$2617,Control!$F$11))*100,"") | I8: =IFERROR(PERCENTRANK(HIST_D!$D$8:INDEX(HIST_D!$D$8:$D$2617,Control!$F$11),INDEX(HIST_D!$D$8:$D$2617,1)),"") | J8: =IFERROR(PERCENTRANK(HIST_D!$D$8:INDEX(HIST_D!$D$8:$D$2617,Control!$F$14),INDEX(HIST_D!$D$8:$D$2617,1)),"")
A9: UST 30Y | B9: bp | C9: =INDEX(HIST_D!$E$8:$E$2617,1) | D9: =IFERROR((INDEX(HIST_D!$E$8:$E$2617,1)-INDEX(HIST_D!$E$8:$E$2617,Control!$F$7))*100,"") | E9: =IFERROR((INDEX(HIST_D!$E$8:$E$2617,1)-INDEX(HIST_D!$E$8:$E$2617,Control!$F$8))*100,"") | F9: =IFERROR((INDEX(HIST_D!$E$8:$E$2617,1)-INDEX(HIST_D!$E$8:$E$2617,Control!$F$9))*100,"") | G9: =IFERROR((INDEX(HIST_D!$E$8:$E$2617,1)-INDEX(HIST_D!$E$8:$E$2617,Control!$F$16))*100,"") | H9: =IFERROR((INDEX(HIST_D!$E$8:$E$2617,1)-INDEX(HIST_D!$E$8:$E$2617,Control!$F$11))*100,"") | I9: =IFERROR(PERCENTRANK(HIST_D!$E$8:INDEX(HIST_D!$E$8:$E$2617,Control!$F$11),INDEX(HIST_D!$E$8:$E$2617,1)),"") | J9: =IFERROR(PERCENTRANK(HIST_D!$E$8:INDEX(HIST_D!$E$8:$E$2617,Control!$F$14),INDEX(HIST_D!$E$8:$E$2617,1)),"")
A10: UST 10Y real | B10: bp | C10: =INDEX(HIST_D!$F$8:$F$2617,1) | D10: =IFERROR((INDEX(HIST_D!$F$8:$F$2617,1)-INDEX(HIST_D!$F$8:$F$2617,Control!$F$7))*100,"") | E10: =IFERROR((INDEX(HIST_D!$F$8:$F$2617,1)-INDEX(HIST_D!$F$8:$F$2617,Control!$F$8))*100,"") | F10: =IFERROR((INDEX(HIST_D!$F$8:$F$2617,1)-INDEX(HIST_D!$F$8:$F$2617,Control!$F$9))*100,"") | G10: =IFERROR((INDEX(HIST_D!$F$8:$F$2617,1)-INDEX(HIST_D!$F$8:$F$2617,Control!$F$16))*100,"") | H10: =IFERROR((INDEX(HIST_D!$F$8:$F$2617,1)-INDEX(HIST_D!$F$8:$F$2617,Control!$F$11))*100,"") | I10: =IFERROR(PERCENTRANK(HIST_D!$F$8:INDEX(HIST_D!$F$8:$F$2617,Control!$F$11),INDEX(HIST_D!$F$8:$F$2617,1)),"") | J10: =IFERROR(PERCENTRANK(HIST_D!$F$8:INDEX(HIST_D!$F$8:$F$2617,Control!$F$14),INDEX(HIST_D!$F$8:$F$2617,1)),"")
A11: ACM term premium 10Y | B11: bp | C11: =INDEX(HIST_D!$H$8:$H$2617,1) | D11: =IFERROR((INDEX(HIST_D!$H$8:$H$2617,1)-INDEX(HIST_D!$H$8:$H$2617,Control!$F$7))*100,"") | E11: =IFERROR((INDEX(HIST_D!$H$8:$H$2617,1)-INDEX(HIST_D!$H$8:$H$2617,Control!$F$8))*100,"") | F11: =IFERROR((INDEX(HIST_D!$H$8:$H$2617,1)-INDEX(HIST_D!$H$8:$H$2617,Control!$F$9))*100,"") | G11: =IFERROR((INDEX(HIST_D!$H$8:$H$2617,1)-INDEX(HIST_D!$H$8:$H$2617,Control!$F$16))*100,"") | H11: =IFERROR((INDEX(HIST_D!$H$8:$H$2617,1)-INDEX(HIST_D!$H$8:$H$2617,Control!$F$11))*100,"") | I11: =IFERROR(PERCENTRANK(HIST_D!$H$8:INDEX(HIST_D!$H$8:$H$2617,Control!$F$11),INDEX(HIST_D!$H$8:$H$2617,1)),"") | J11: =IFERROR(PERCENTRANK(HIST_D!$H$8:INDEX(HIST_D!$H$8:$H$2617,Control!$F$14),INDEX(HIST_D!$H$8:$H$2617,1)),"")
A12: DXY | B12: pt | C12: =INDEX(HIST_D!$J$8:$J$2617,1) | D12: =IFERROR(IFERROR(INDEX(HIST_D!$J$8:$J$2617,1)/INDEX(HIST_D!$J$8:$J$2617,Control!$F$7)-1,""),"") | E12: =IFERROR(IFERROR(INDEX(HIST_D!$J$8:$J$2617,1)/INDEX(HIST_D!$J$8:$J$2617,Control!$F$8)-1,""),"") | F12: =IFERROR(IFERROR(INDEX(HIST_D!$J$8:$J$2617,1)/INDEX(HIST_D!$J$8:$J$2617,Control!$F$9)-1,""),"") | G12: =IFERROR(IFERROR(INDEX(HIST_D!$J$8:$J$2617,1)/INDEX(HIST_D!$J$8:$J$2617,Control!$F$16)-1,""),"") | H12: =IFERROR(IFERROR(INDEX(HIST_D!$J$8:$J$2617,1)/INDEX(HIST_D!$J$8:$J$2617,Control!$F$11)-1,""),"") | I12: =IFERROR(PERCENTRANK(HIST_D!$J$8:INDEX(HIST_D!$J$8:$J$2617,Control!$F$11),INDEX(HIST_D!$J$8:$J$2617,1)),"") | J12: =IFERROR(PERCENTRANK(HIST_D!$J$8:INDEX(HIST_D!$J$8:$J$2617,Control!$F$14),INDEX(HIST_D!$J$8:$J$2617,1)),"")
A13: Brent | B13: px | C13: =INDEX(HIST_D!$N$8:$N$2617,1) | D13: =IFERROR(IFERROR(INDEX(HIST_D!$N$8:$N$2617,1)/INDEX(HIST_D!$N$8:$N$2617,Control!$F$7)-1,""),"") | E13: =IFERROR(IFERROR(INDEX(HIST_D!$N$8:$N$2617,1)/INDEX(HIST_D!$N$8:$N$2617,Control!$F$8)-1,""),"") | F13: =IFERROR(IFERROR(INDEX(HIST_D!$N$8:$N$2617,1)/INDEX(HIST_D!$N$8:$N$2617,Control!$F$9)-1,""),"") | G13: =IFERROR(IFERROR(INDEX(HIST_D!$N$8:$N$2617,1)/INDEX(HIST_D!$N$8:$N$2617,Control!$F$16)-1,""),"") | H13: =IFERROR(IFERROR(INDEX(HIST_D!$N$8:$N$2617,1)/INDEX(HIST_D!$N$8:$N$2617,Control!$F$11)-1,""),"") | I13: =IFERROR(PERCENTRANK(HIST_D!$N$8:INDEX(HIST_D!$N$8:$N$2617,Control!$F$11),INDEX(HIST_D!$N$8:$N$2617,1)),"") | J13: =IFERROR(PERCENTRANK(HIST_D!$N$8:INDEX(HIST_D!$N$8:$N$2617,Control!$F$14),INDEX(HIST_D!$N$8:$N$2617,1)),"")
A14: MOVE | B14: bp | C14: =INDEX(HIST_D!$K$8:$K$2617,1) | D14: =IFERROR((INDEX(HIST_D!$K$8:$K$2617,1)-INDEX(HIST_D!$K$8:$K$2617,Control!$F$7)),"") | E14: =IFERROR((INDEX(HIST_D!$K$8:$K$2617,1)-INDEX(HIST_D!$K$8:$K$2617,Control!$F$8)),"") | F14: =IFERROR((INDEX(HIST_D!$K$8:$K$2617,1)-INDEX(HIST_D!$K$8:$K$2617,Control!$F$9)),"") | G14: =IFERROR((INDEX(HIST_D!$K$8:$K$2617,1)-INDEX(HIST_D!$K$8:$K$2617,Control!$F$16)),"") | H14: =IFERROR((INDEX(HIST_D!$K$8:$K$2617,1)-INDEX(HIST_D!$K$8:$K$2617,Control!$F$11)),"") | I14: =IFERROR(PERCENTRANK(HIST_D!$K$8:INDEX(HIST_D!$K$8:$K$2617,Control!$F$11),INDEX(HIST_D!$K$8:$K$2617,1)),"") | J14: =IFERROR(PERCENTRANK(HIST_D!$K$8:INDEX(HIST_D!$K$8:$K$2617,Control!$F$14),INDEX(HIST_D!$K$8:$K$2617,1)),"")
A15: VIX | B15: pt | C15: =INDEX(HIST_D!$L$8:$L$2617,1) | D15: =IFERROR((INDEX(HIST_D!$L$8:$L$2617,1)-INDEX(HIST_D!$L$8:$L$2617,Control!$F$7)),"") | E15: =IFERROR((INDEX(HIST_D!$L$8:$L$2617,1)-INDEX(HIST_D!$L$8:$L$2617,Control!$F$8)),"") | F15: =IFERROR((INDEX(HIST_D!$L$8:$L$2617,1)-INDEX(HIST_D!$L$8:$L$2617,Control!$F$9)),"") | G15: =IFERROR((INDEX(HIST_D!$L$8:$L$2617,1)-INDEX(HIST_D!$L$8:$L$2617,Control!$F$16)),"") | H15: =IFERROR((INDEX(HIST_D!$L$8:$L$2617,1)-INDEX(HIST_D!$L$8:$L$2617,Control!$F$11)),"") | I15: =IFERROR(PERCENTRANK(HIST_D!$L$8:INDEX(HIST_D!$L$8:$L$2617,Control!$F$11),INDEX(HIST_D!$L$8:$L$2617,1)),"") | J15: =IFERROR(PERCENTRANK(HIST_D!$L$8:INDEX(HIST_D!$L$8:$L$2617,Control!$F$14),INDEX(HIST_D!$L$8:$L$2617,1)),"")
A17: THE EM RESPONSE — the three legs side by side
A18: Series | B18: Unit | C18: Level | D18: 1W | E18: 1M | F18: 3M | G18: YTD | H18: 1Y | I18: %ile 1y | J18: %ile 5y
A19: EM FX basket (return on EM ccy) | B19: % | D19: =FX!E51 | E19: =FX!F51 | F19: =FX!G51 | G19: =FX!I51 | H19: =FX!J51
A20: EM FX basket ex-USD | B20: % | D20: =FX!K51 | E20: =FX!L51 | F20: =FX!M51 | G20: =FX!M51 | H20: =FX!M51
A21: MSCI EM (USD) | B21: idx | C21: =INDEX(HIST_D!$AZ$8:$AZ$2617,1) | D21: =IFERROR(IFERROR(INDEX(HIST_D!$AZ$8:$AZ$2617,1)/INDEX(HIST_D!$AZ$8:$AZ$2617,Control!$F$7)-1,""),"") | E21: =IFERROR(IFERROR(INDEX(HIST_D!$AZ$8:$AZ$2617,1)/INDEX(HIST_D!$AZ$8:$AZ$2617,Control!$F$8)-1,""),"") | F21: =IFERROR(IFERROR(INDEX(HIST_D!$AZ$8:$AZ$2617,1)/INDEX(HIST_D!$AZ$8:$AZ$2617,Control!$F$9)-1,""),"") | G21: =IFERROR(IFERROR(INDEX(HIST_D!$AZ$8:$AZ$2617,1)/INDEX(HIST_D!$AZ$8:$AZ$2617,Control!$F$16)-1,""),"") | H21: =IFERROR(IFERROR(INDEX(HIST_D!$AZ$8:$AZ$2617,1)/INDEX(HIST_D!$AZ$8:$AZ$2617,Control!$F$11)-1,""),"") | I21: =IFERROR(PERCENTRANK(HIST_D!$AZ$8:INDEX(HIST_D!$AZ$8:$AZ$2617,Control!$F$11),INDEX(HIST_D!$AZ$8:$AZ$2617,1)),"") | J21: =IFERROR(PERCENTRANK(HIST_D!$AZ$8:INDEX(HIST_D!$AZ$8:$AZ$2617,Control!$F$14),INDEX(HIST_D!$AZ$8:$AZ$2617,1)),"")
A22: MSCI World (USD) | B22: idx | C22: =INDEX(HIST_D!$BA$8:$BA$2617,1) | D22: =IFERROR(IFERROR(INDEX(HIST_D!$BA$8:$BA$2617,1)/INDEX(HIST_D!$BA$8:$BA$2617,Control!$F$7)-1,""),"") | E22: =IFERROR(IFERROR(INDEX(HIST_D!$BA$8:$BA$2617,1)/INDEX(HIST_D!$BA$8:$BA$2617,Control!$F$8)-1,""),"") | F22: =IFERROR(IFERROR(INDEX(HIST_D!$BA$8:$BA$2617,1)/INDEX(HIST_D!$BA$8:$BA$2617,Control!$F$9)-1,""),"") | G22: =IFERROR(IFERROR(INDEX(HIST_D!$BA$8:$BA$2617,1)/INDEX(HIST_D!$BA$8:$BA$2617,Control!$F$16)-1,""),"") | H22: =IFERROR(IFERROR(INDEX(HIST_D!$BA$8:$BA$2617,1)/INDEX(HIST_D!$BA$8:$BA$2617,Control!$F$11)-1,""),"") | I22: =IFERROR(PERCENTRANK(HIST_D!$BA$8:INDEX(HIST_D!$BA$8:$BA$2617,Control!$F$11),INDEX(HIST_D!$BA$8:$BA$2617,1)),"") | J22: =IFERROR(PERCENTRANK(HIST_D!$BA$8:INDEX(HIST_D!$BA$8:$BA$2617,Control!$F$14),INDEX(HIST_D!$BA$8:$BA$2617,1)),"")
A23: EM USD Agg OAS | B23: bp | C23: =INDEX(HIST_D!$Q$8:$Q$2617,1) | D23: =IFERROR((INDEX(HIST_D!$Q$8:$Q$2617,1)-INDEX(HIST_D!$Q$8:$Q$2617,Control!$F$7)),"") | E23: =IFERROR((INDEX(HIST_D!$Q$8:$Q$2617,1)-INDEX(HIST_D!$Q$8:$Q$2617,Control!$F$8)),"") | F23: =IFERROR((INDEX(HIST_D!$Q$8:$Q$2617,1)-INDEX(HIST_D!$Q$8:$Q$2617,Control!$F$9)),"") | G23: =IFERROR((INDEX(HIST_D!$Q$8:$Q$2617,1)-INDEX(HIST_D!$Q$8:$Q$2617,Control!$F$16)),"") | H23: =IFERROR((INDEX(HIST_D!$Q$8:$Q$2617,1)-INDEX(HIST_D!$Q$8:$Q$2617,Control!$F$11)),"") | I23: =IFERROR(PERCENTRANK(HIST_D!$Q$8:INDEX(HIST_D!$Q$8:$Q$2617,Control!$F$11),INDEX(HIST_D!$Q$8:$Q$2617,1)),"") | J23: =IFERROR(PERCENTRANK(HIST_D!$Q$8:INDEX(HIST_D!$Q$8:$Q$2617,Control!$F$14),INDEX(HIST_D!$Q$8:$Q$2617,1)),"")
A24: EM USD Sovereign OAS | B24: bp | C24: =INDEX(HIST_D!$S$8:$S$2617,1) | D24: =IFERROR((INDEX(HIST_D!$S$8:$S$2617,1)-INDEX(HIST_D!$S$8:$S$2617,Control!$F$7)),"") | E24: =IFERROR((INDEX(HIST_D!$S$8:$S$2617,1)-INDEX(HIST_D!$S$8:$S$2617,Control!$F$8)),"") | F24: =IFERROR((INDEX(HIST_D!$S$8:$S$2617,1)-INDEX(HIST_D!$S$8:$S$2617,Control!$F$9)),"") | G24: =IFERROR((INDEX(HIST_D!$S$8:$S$2617,1)-INDEX(HIST_D!$S$8:$S$2617,Control!$F$16)),"") | H24: =IFERROR((INDEX(HIST_D!$S$8:$S$2617,1)-INDEX(HIST_D!$S$8:$S$2617,Control!$F$11)),"") | I24: =IFERROR(PERCENTRANK(HIST_D!$S$8:INDEX(HIST_D!$S$8:$S$2617,Control!$F$11),INDEX(HIST_D!$S$8:$S$2617,1)),"") | J24: =IFERROR(PERCENTRANK(HIST_D!$S$8:INDEX(HIST_D!$S$8:$S$2617,Control!$F$14),INDEX(HIST_D!$S$8:$S$2617,1)),"")
A25: US IG OAS | B25: bp | C25: =INDEX(HIST_D!$O$8:$O$2617,1) | D25: =IFERROR((INDEX(HIST_D!$O$8:$O$2617,1)-INDEX(HIST_D!$O$8:$O$2617,Control!$F$7)),"") | E25: =IFERROR((INDEX(HIST_D!$O$8:$O$2617,1)-INDEX(HIST_D!$O$8:$O$2617,Control!$F$8)),"") | F25: =IFERROR((INDEX(HIST_D!$O$8:$O$2617,1)-INDEX(HIST_D!$O$8:$O$2617,Control!$F$9)),"") | G25: =IFERROR((INDEX(HIST_D!$O$8:$O$2617,1)-INDEX(HIST_D!$O$8:$O$2617,Control!$F$16)),"") | H25: =IFERROR((INDEX(HIST_D!$O$8:$O$2617,1)-INDEX(HIST_D!$O$8:$O$2617,Control!$F$11)),"") | I25: =IFERROR(PERCENTRANK(HIST_D!$O$8:INDEX(HIST_D!$O$8:$O$2617,Control!$F$11),INDEX(HIST_D!$O$8:$O$2617,1)),"") | J25: =IFERROR(PERCENTRANK(HIST_D!$O$8:INDEX(HIST_D!$O$8:$O$2617,Control!$F$14),INDEX(HIST_D!$O$8:$O$2617,1)),"")
A26: US HY OAS | B26: bp | C26: =INDEX(HIST_D!$P$8:$P$2617,1) | D26: =IFERROR((INDEX(HIST_D!$P$8:$P$2617,1)-INDEX(HIST_D!$P$8:$P$2617,Control!$F$7)),"") | E26: =IFERROR((INDEX(HIST_D!$P$8:$P$2617,1)-INDEX(HIST_D!$P$8:$P$2617,Control!$F$8)),"") | F26: =IFERROR((INDEX(HIST_D!$P$8:$P$2617,1)-INDEX(HIST_D!$P$8:$P$2617,Control!$F$9)),"") | G26: =IFERROR((INDEX(HIST_D!$P$8:$P$2617,1)-INDEX(HIST_D!$P$8:$P$2617,Control!$F$16)),"") | H26: =IFERROR((INDEX(HIST_D!$P$8:$P$2617,1)-INDEX(HIST_D!$P$8:$P$2617,Control!$F$11)),"") | I26: =IFERROR(PERCENTRANK(HIST_D!$P$8:INDEX(HIST_D!$P$8:$P$2617,Control!$F$11),INDEX(HIST_D!$P$8:$P$2617,1)),"") | J26: =IFERROR(PERCENTRANK(HIST_D!$P$8:INDEX(HIST_D!$P$8:$P$2617,Control!$F$14),INDEX(HIST_D!$P$8:$P$2617,1)),"")
A27: EM local 10Y, eq-wgt | B27: bp | C27: =INDEX(HIST_D!$DW$8:$DW$2617,1) | D27: =IFERROR((INDEX(HIST_D!$DW$8:$DW$2617,1)-INDEX(HIST_D!$DW$8:$DW$2617,Control!$F$7))*100,"") | E27: =IFERROR((INDEX(HIST_D!$DW$8:$DW$2617,1)-INDEX(HIST_D!$DW$8:$DW$2617,Control!$F$8))*100,"") | F27: =IFERROR((INDEX(HIST_D!$DW$8:$DW$2617,1)-INDEX(HIST_D!$DW$8:$DW$2617,Control!$F$9))*100,"") | G27: =IFERROR((INDEX(HIST_D!$DW$8:$DW$2617,1)-INDEX(HIST_D!$DW$8:$DW$2617,Control!$F$16))*100,"") | H27: =IFERROR((INDEX(HIST_D!$DW$8:$DW$2617,1)-INDEX(HIST_D!$DW$8:$DW$2617,Control!$F$11))*100,"") | I27: =IFERROR(PERCENTRANK(HIST_D!$DW$8:INDEX(HIST_D!$DW$8:$DW$2617,Control!$F$11),INDEX(HIST_D!$DW$8:$DW$2617,1)),"") | J27: =IFERROR(PERCENTRANK(HIST_D!$DW$8:INDEX(HIST_D!$DW$8:$DW$2617,Control!$F$14),INDEX(HIST_D!$DW$8:$DW$2617,1)),"")
A28: EM local 10Y less UST 10Y | B28: bp | C28: =INDEX(HIST_D!$EA$8:$EA$2617,1) | D28: =IFERROR((INDEX(HIST_D!$EA$8:$EA$2617,1)-INDEX(HIST_D!$EA$8:$EA$2617,Control!$F$7)),"") | E28: =IFERROR((INDEX(HIST_D!$EA$8:$EA$2617,1)-INDEX(HIST_D!$EA$8:$EA$2617,Control!$F$8)),"") | F28: =IFERROR((INDEX(HIST_D!$EA$8:$EA$2617,1)-INDEX(HIST_D!$EA$8:$EA$2617,Control!$F$9)),"") | G28: =IFERROR((INDEX(HIST_D!$EA$8:$EA$2617,1)-INDEX(HIST_D!$EA$8:$EA$2617,Control!$F$16)),"") | H28: =IFERROR((INDEX(HIST_D!$EA$8:$EA$2617,1)-INDEX(HIST_D!$EA$8:$EA$2617,Control!$F$11)),"") | I28: =IFERROR(PERCENTRANK(HIST_D!$EA$8:INDEX(HIST_D!$EA$8:$EA$2617,Control!$F$11),INDEX(HIST_D!$EA$8:$EA$2617,1)),"") | J28: =IFERROR(PERCENTRANK(HIST_D!$EA$8:INDEX(HIST_D!$EA$8:$EA$2617,Control!$F$14),INDEX(HIST_D!$EA$8:$EA$2617,1)),"")
A30: BY REGION — the three legs side by side
A31: Region | B31: FX 1M | C31: FX YTD | D31: FX 1M ex-USD | E31: Equity USD 1M | F31: Equity USD YTD | G31: Equity vs World 1M | H31: Credit d spread 1M (bp) | I31: Credit TR 1M (%)
A32: LatAm | B32: =FX!$F$12 | C32: =FX!$I$12 | D32: =FX!$K$12 | E32: =Equities!$F$17 | F32: =Equities!$L$17 | G32: =Equities!$N$17 | H32: =IF(Credit!$E$39="","",Credit!$E$39) | I32: =IF(Credit!$F$39="","",Credit!$F$39)
A33: EM Europe | B33: =FX!$F$22 | C33: =FX!$I$22 | D33: =FX!$K$22 | E33: =Equities!$F$27 | F33: =Equities!$L$27 | G33: =Equities!$N$27 | H33: =IF(Credit!$E$40="","",Credit!$E$40) | I33: =IF(Credit!$F$40="","",Credit!$F$40)
A34: Middle East & Africa | B34: =FX!$F$33 | C34: =FX!$I$33 | D34: =FX!$K$33 | E34: =Equities!$F$38 | F34: =Equities!$L$38 | G34: =Equities!$N$38 | H34: =IF(Credit!$E$41="","",Credit!$E$41) | I34: =IF(Credit!$F$41="","",Credit!$F$41)
A35: Asia | B35: =FX!$F$46 | C35: =FX!$I$46 | D35: =FX!$K$46 | E35: =Equities!$F$52 | F35: =Equities!$L$52 | G35: =Equities!$N$52 | H35: =IF(Credit!$E$42="","",Credit!$E$42) | I35: =IF(Credit!$F$42="","",Credit!$F$42)
A37: Per-region read — generated, not typed
A38: =IFERROR("LatAm: FX "&TEXT($B32,"+0.0%;-0.0%")&" ("&TEXT($D32,"+0.0%;-0.0%")&" ex-dollar), equity "&TEXT($E32,"+0.0%;-0.0%")&" USD ("&TEXT($G32,"+0.0%;-0.0%")&" vs World), credit "&IF(ISNUMBER($H32),TEXT($H32,"+0;-0")&"bp","n/a")&". "&IF(AND($B32>=-0.005,$E32>=0),"Both market legs holding — the region is absorbing the US move rather than importing it.",IF(AND($B32<-0.005,$E32<0),"Both market legs are soft; this region is importing the US move and is where the digestion argument breaks first.",IF($B32<-0.005,"The currency is the weak leg while equity holds — an FX problem, not a growth or credit problem.","Equity is the weak leg while the currency holds — a sector or earnings story rather than a rates transmission story."))),"")
A39: =IFERROR("EM Europe: FX "&TEXT($B33,"+0.0%;-0.0%")&" ("&TEXT($D33,"+0.0%;-0.0%")&" ex-dollar), equity "&TEXT($E33,"+0.0%;-0.0%")&" USD ("&TEXT($G33,"+0.0%;-0.0%")&" vs World), credit "&IF(ISNUMBER($H33),TEXT($H33,"+0;-0")&"bp","n/a")&". "&IF(AND($B33>=-0.005,$E33>=0),"Both market legs holding — the region is absorbing the US move rather than importing it.",IF(AND($B33<-0.005,$E33<0),"Both market legs are soft; this region is importing the US move and is where the digestion argument breaks first.",IF($B33<-0.005,"The currency is the weak leg while equity holds — an FX problem, not a growth or credit problem.","Equity is the weak leg while the currency holds — a sector or earnings story rather than a rates transmission story."))),"")
A40: =IFERROR("Middle East & Africa: FX "&TEXT($B34,"+0.0%;-0.0%")&" ("&TEXT($D34,"+0.0%;-0.0%")&" ex-dollar), equity "&TEXT($E34,"+0.0%;-0.0%")&" USD ("&TEXT($G34,"+0.0%;-0.0%")&" vs World), credit "&IF(ISNUMBER($H34),TEXT($H34,"+0;-0")&"bp","n/a")&". "&IF(AND($B34>=-0.005,$E34>=0),"Both market legs holding — the region is absorbing the US move rather than importing it.",IF(AND($B34<-0.005,$E34<0),"Both market legs are soft; this region is importing the US move and is where the digestion argument breaks first.",IF($B34<-0.005,"The currency is the weak leg while equity holds — an FX problem, not a growth or credit problem.","Equity is the weak leg while the currency holds — a sector or earnings story rather than a rates transmission story."))),"")
A41: =IFERROR("Asia: FX "&TEXT($B35,"+0.0%;-0.0%")&" ("&TEXT($D35,"+0.0%;-0.0%")&" ex-dollar), equity "&TEXT($E35,"+0.0%;-0.0%")&" USD ("&TEXT($G35,"+0.0%;-0.0%")&" vs World), credit "&IF(ISNUMBER($H35),TEXT($H35,"+0;-0")&"bp","n/a")&". "&IF(AND($B35>=-0.005,$E35>=0),"Both market legs holding — the region is absorbing the US move rather than importing it.",IF(AND($B35<-0.005,$E35<0),"Both market legs are soft; this region is importing the US move and is where the digestion argument breaks first.",IF($B35<-0.005,"The currency is the weak leg while equity holds — an FX problem, not a growth or credit problem.","Equity is the weak leg while the currency holds — a sector or earnings story rather than a rates transmission story."))),"")
A44: DIGESTION — the three numbers the story rests on
A45: Measure | C45: 1M | D45: 3M | E45: 1Y | F45: 5Y
A46: Pass-through: EM local 10Y / UST 10Y | C46: =Passthrough!$G$48 | D46: =Passthrough!$H$48 | E46: =Passthrough!$J$48 | F46: =Passthrough!$K$48
A47: Beta: EM USD Agg OAS to UST 10Y (bp per bp) | C47: =Betas!C$6 | D47: =Betas!D$6 | E47: =Betas!F$6 | F47: =Betas!H$6
A48: Beta: EM FX basket to DXY (% per %) | C48: =Betas!C$14 | D48: =Betas!D$14 | E48: =Betas!F$14 | F48: =Betas!H$14
A50: READ — generated from the cells above, not typed
A51: ="Past month: UST 10Y "&TEXT($E$8+0,"+0;-0")&"bp, ACM term premium "&TEXT($E$11+0,"+0;-0")&"bp, DXY "&TEXT($E$12,"+0.0%;-0.0%")&", Brent "&TEXT($E$13,"+0.0%;-0.0%")&"."
A52: ="EM USD Aggregate spread "&TEXT($E$23+0,"+0;-0")&"bp over the same window, against US IG "&TEXT($E$25+0,"+0;-0")&"bp and US HY "&TEXT($E$26+0,"+0;-0")&"bp."
A53: ="Decomposing the month: carry "&TEXT(Credit!$F$26,"+0.00%;-0.00%")&", rates leg "&TEXT(Credit!$F$27,"+0.00%;-0.00%")&", spread leg "&TEXT(Credit!$F$29,"+0.00%;-0.00%")&" - on those numbers this is "&IF(ABS(Credit!$F$27)>ABS(Credit!$F$29),"a duration event, not a credit event","a credit event")&"."
A54: ="EM local curves took "&IF(ISNUMBER($C$46),TEXT($C$46,"0.00")&"x","n/m")&" of the US move over the month against "&IF(ISNUMBER($F$46),TEXT($F$46,"0.00")&"x","n/m")&" over five years; EM FX beta to the dollar is "&TEXT($C$48,"0.00")&" on the month against "&TEXT($F$48,"0.00")&" over five years."
A56: These sentences recompute with the workbook. They are a prompt for the note, not the note.

Sheet FX
A1: EM FX — by region. Return on the currency, not the pair.
A2: Every pair is quoted EM per USD; the columns are the return ON the EM currency (prior/current - 1), so positive = EM strength. 'ex-USD' adds back the DXY move over the same window and isolates what is regional rather than dollar. Region baskets are equal-weighted across floating currencies only.
A4: LATAM
A5: Currency | B5: Peg | C5: Spot (EM/USD) | D5: 1D | E5: 1W | F5: 1M | G5: 3M | H5: 6M | I5: YTD | J5: 1Y | K5: 1M ex-USD | L5: 3M ex-USD | M5: YTD ex-USD | N5: %ile 1y (spot) | O5: %ile 5y (spot)
A6: Brazil BRL | B6: float | C6: =INDEX(HIST_D!$AA$8:$AA$2617,1) | D6: =IFERROR(INDEX(HIST_D!$AA$8:$AA$2617,Control!$F$6)/INDEX(HIST_D!$AA$8:$AA$2617,1)-1,"") | E6: =IFERROR(INDEX(HIST_D!$AA$8:$AA$2617,Control!$F$7)/INDEX(HIST_D!$AA$8:$AA$2617,1)-1,"") | F6: =IFERROR(INDEX(HIST_D!$AA$8:$AA$2617,Control!$F$8)/INDEX(HIST_D!$AA$8:$AA$2617,1)-1,"") | G6: =IFERROR(INDEX(HIST_D!$AA$8:$AA$2617,Control!$F$9)/INDEX(HIST_D!$AA$8:$AA$2617,1)-1,"") | H6: =IFERROR(INDEX(HIST_D!$AA$8:$AA$2617,Control!$F$10)/INDEX(HIST_D!$AA$8:$AA$2617,1)-1,"") | I6: =IFERROR(INDEX(HIST_D!$AA$8:$AA$2617,Control!$F$16)/INDEX(HIST_D!$AA$8:$AA$2617,1)-1,"") | J6: =IFERROR(INDEX(HIST_D!$AA$8:$AA$2617,Control!$F$11)/INDEX(HIST_D!$AA$8:$AA$2617,1)-1,"") | K6: =IFERROR(IFERROR(INDEX(HIST_D!$AA$8:$AA$2617,Control!$F$8)/INDEX(HIST_D!$AA$8:$AA$2617,1)-1,"")+IFERROR(INDEX(HIST_D!$J$8:$J$2617,1)/INDEX(HIST_D!$J$8:$J$2617,Control!$F$8)-1,""),"") | L6: =IFERROR(IFERROR(INDEX(HIST_D!$AA$8:$AA$2617,Control!$F$9)/INDEX(HIST_D!$AA$8:$AA$2617,1)-1,"")+IFERROR(INDEX(HIST_D!$J$8:$J$2617,1)/INDEX(HIST_D!$J$8:$J$2617,Control!$F$9)-1,""),"") | M6: =IFERROR(IFERROR(INDEX(HIST_D!$AA$8:$AA$2617,Control!$F$16)/INDEX(HIST_D!$AA$8:$AA$2617,1)-1,"")+IFERROR(INDEX(HIST_D!$J$8:$J$2617,1)/INDEX(HIST_D!$J$8:$J$2617,Control!$F$16)-1,""),"") | N6: =IFERROR(PERCENTRANK(HIST_D!$AA$8:INDEX(HIST_D!$AA$8:$AA$2617,Control!$F$11),INDEX(HIST_D!$AA$8:$AA$2617,1)),"") | O6: =IFERROR(PERCENTRANK(HIST_D!$AA$8:INDEX(HIST_D!$AA$8:$AA$2617,Control!$F$14),INDEX(HIST_D!$AA$8:$AA$2617,1)),"")
A7: Mexico MXN | B7: float | C7: =INDEX(HIST_D!$AB$8:$AB$2617,1) | D7: =IFERROR(INDEX(HIST_D!$AB$8:$AB$2617,Control!$F$6)/INDEX(HIST_D!$AB$8:$AB$2617,1)-1,"") | E7: =IFERROR(INDEX(HIST_D!$AB$8:$AB$2617,Control!$F$7)/INDEX(HIST_D!$AB$8:$AB$2617,1)-1,"") | F7: =IFERROR(INDEX(HIST_D!$AB$8:$AB$2617,Control!$F$8)/INDEX(HIST_D!$AB$8:$AB$2617,1)-1,"") | G7: =IFERROR(INDEX(HIST_D!$AB$8:$AB$2617,Control!$F$9)/INDEX(HIST_D!$AB$8:$AB$2617,1)-1,"") | H7: =IFERROR(INDEX(HIST_D!$AB$8:$AB$2617,Control!$F$10)/INDEX(HIST_D!$AB$8:$AB$2617,1)-1,"") | I7: =IFERROR(INDEX(HIST_D!$AB$8:$AB$2617,Control!$F$16)/INDEX(HIST_D!$AB$8:$AB$2617,1)-1,"") | J7: =IFERROR(INDEX(HIST_D!$AB$8:$AB$2617,Control!$F$11)/INDEX(HIST_D!$AB$8:$AB$2617,1)-1,"") | K7: =IFERROR(IFERROR(INDEX(HIST_D!$AB$8:$AB$2617,Control!$F$8)/INDEX(HIST_D!$AB$8:$AB$2617,1)-1,"")+IFERROR(INDEX(HIST_D!$J$8:$J$2617,1)/INDEX(HIST_D!$J$8:$J$2617,Control!$F$8)-1,""),"") | L7: =IFERROR(IFERROR(INDEX(HIST_D!$AB$8:$AB$2617,Control!$F$9)/INDEX(HIST_D!$AB$8:$AB$2617,1)-1,"")+IFERROR(INDEX(HIST_D!$J$8:$J$2617,1)/INDEX(HIST_D!$J$8:$J$2617,Control!$F$9)-1,""),"") | M7: =IFERROR(IFERROR(INDEX(HIST_D!$AB$8:$AB$2617,Control!$F$16)/INDEX(HIST_D!$AB$8:$AB$2617,1)-1,"")+IFERROR(INDEX(HIST_D!$J$8:$J$2617,1)/INDEX(HIST_D!$J$8:$J$2617,Control!$F$16)-1,""),"") | N7: =IFERROR(PERCENTRANK(HIST_D!$AB$8:INDEX(HIST_D!$AB$8:$AB$2617,Control!$F$11),INDEX(HIST_D!$AB$8:$AB$2617,1)),"") | O7: =IFERROR(PERCENTRANK(HIST_D!$AB$8:INDEX(HIST_D!$AB$8:$AB$2617,Control!$F$14),INDEX(HIST_D!$AB$8:$AB$2617,1)),"")
A8: Chile CLP | B8: float | C8: =INDEX(HIST_D!$AC$8:$AC$2617,1) | D8: =IFERROR(INDEX(HIST_D!$AC$8:$AC$2617,Control!$F$6)/INDEX(HIST_D!$AC$8:$AC$2617,1)-1,"") | E8: =IFERROR(INDEX(HIST_D!$AC$8:$AC$2617,Control!$F$7)/INDEX(HIST_D!$AC$8:$AC$2617,1)-1,"") | F8: =IFERROR(INDEX(HIST_D!$AC$8:$AC$2617,Control!$F$8)/INDEX(HIST_D!$AC$8:$AC$2617,1)-1,"") | G8: =IFERROR(INDEX(HIST_D!$AC$8:$AC$2617,Control!$F$9)/INDEX(HIST_D!$AC$8:$AC$2617,1)-1,"") | H8: =IFERROR(INDEX(HIST_D!$AC$8:$AC$2617,Control!$F$10)/INDEX(HIST_D!$AC$8:$AC$2617,1)-1,"") | I8: =IFERROR(INDEX(HIST_D!$AC$8:$AC$2617,Control!$F$16)/INDEX(HIST_D!$AC$8:$AC$2617,1)-1,"") | J8: =IFERROR(INDEX(HIST_D!$AC$8:$AC$2617,Control!$F$11)/INDEX(HIST_D!$AC$8:$AC$2617,1)-1,"") | K8: =IFERROR(IFERROR(INDEX(HIST_D!$AC$8:$AC$2617,Control!$F$8)/INDEX(HIST_D!$AC$8:$AC$2617,1)-1,"")+IFERROR(INDEX(HIST_D!$J$8:$J$2617,1)/INDEX(HIST_D!$J$8:$J$2617,Control!$F$8)-1,""),"") | L8: =IFERROR(IFERROR(INDEX(HIST_D!$AC$8:$AC$2617,Control!$F$9)/INDEX(HIST_D!$AC$8:$AC$2617,1)-1,"")+IFERROR(INDEX(HIST_D!$J$8:$J$2617,1)/INDEX(HIST_D!$J$8:$J$2617,Control!$F$9)-1,""),"") | M8: =IFERROR(IFERROR(INDEX(HIST_D!$AC$8:$AC$2617,Control!$F$16)/INDEX(HIST_D!$AC$8:$AC$2617,1)-1,"")+IFERROR(INDEX(HIST_D!$J$8:$J$2617,1)/INDEX(HIST_D!$J$8:$J$2617,Control!$F$16)-1,""),"") | N8: =IFERROR(PERCENTRANK(HIST_D!$AC$8:INDEX(HIST_D!$AC$8:$AC$2617,Control!$F$11),INDEX(HIST_D!$AC$8:$AC$2617,1)),"") | O8: =IFERROR(PERCENTRANK(HIST_D!$AC$8:INDEX(HIST_D!$AC$8:$AC$2617,Control!$F$14),INDEX(HIST_D!$AC$8:$AC$2617,1)),"")
A9: Colombia COP | B9: float | C9: =INDEX(HIST_D!$AD$8:$AD$2617,1) | D9: =IFERROR(INDEX(HIST_D!$AD$8:$AD$2617,Control!$F$6)/INDEX(HIST_D!$AD$8:$AD$2617,1)-1,"") | E9: =IFERROR(INDEX(HIST_D!$AD$8:$AD$2617,Control!$F$7)/INDEX(HIST_D!$AD$8:$AD$2617,1)-1,"") | F9: =IFERROR(INDEX(HIST_D!$AD$8:$AD$2617,Control!$F$8)/INDEX(HIST_D!$AD$8:$AD$2617,1)-1,"") | G9: =IFERROR(INDEX(HIST_D!$AD$8:$AD$2617,Control!$F$9)/INDEX(HIST_D!$AD$8:$AD$2617,1)-1,"") | H9: =IFERROR(INDEX(HIST_D!$AD$8:$AD$2617,Control!$F$10)/INDEX(HIST_D!$AD$8:$AD$2617,1)-1,"") | I9: =IFERROR(INDEX(HIST_D!$AD$8:$AD$2617,Control!$F$16)/INDEX(HIST_D!$AD$8:$AD$2617,1)-1,"") | J9: =IFERROR(INDEX(HIST_D!$AD$8:$AD$2617,Control!$F$11)/INDEX(HIST_D!$AD$8:$AD$2617,1)-1,"") | K9: =IFERROR(IFERROR(INDEX(HIST_D!$AD$8:$AD$2617,Control!$F$8)/INDEX(HIST_D!$AD$8:$AD$2617,1)-1,"")+IFERROR(INDEX(HIST_D!$J$8:$J$2617,1)/INDEX(HIST_D!$J$8:$J$2617,Control!$F$8)-1,""),"") | L9: =IFERROR(IFERROR(INDEX(HIST_D!$AD$8:$AD$2617,Control!$F$9)/INDEX(HIST_D!$AD$8:$AD$2617,1)-1,"")+IFERROR(INDEX(HIST_D!$J$8:$J$2617,1)/INDEX(HIST_D!$J$8:$J$2617,Control!$F$9)-1,""),"") | M9: =IFERROR(IFERROR(INDEX(HIST_D!$AD$8:$AD$2617,Control!$F$16)/INDEX(HIST_D!$AD$8:$AD$2617,1)-1,"")+IFERROR(INDEX(HIST_D!$J$8:$J$2617,1)/INDEX(HIST_D!$J$8:$J$2617,Control!$F$16)-1,""),"") | N9: =IFERROR(PERCENTRANK(HIST_D!$AD$8:INDEX(HIST_D!$AD$8:$AD$2617,Control!$F$11),INDEX(HIST_D!$AD$8:$AD$2617,1)),"") | O9: =IFERROR(PERCENTRANK(HIST_D!$AD$8:INDEX(HIST_D!$AD$8:$AD$2617,Control!$F$14),INDEX(HIST_D!$AD$8:$AD$2617,1)),"")
A10: Peru PEN | B10: float | C10: =INDEX(HIST_D!$AE$8:$AE$2617,1) | D10: =IFERROR(INDEX(HIST_D!$AE$8:$AE$2617,Control!$F$6)/INDEX(HIST_D!$AE$8:$AE$2617,1)-1,"") | E10: =IFERROR(INDEX(HIST_D!$AE$8:$AE$2617,Control!$F$7)/INDEX(HIST_D!$AE$8:$AE$2617,1)-1,"") | F10: =IFERROR(INDEX(HIST_D!$AE$8:$AE$2617,Control!$F$8)/INDEX(HIST_D!$AE$8:$AE$2617,1)-1,"") | G10: =IFERROR(INDEX(HIST_D!$AE$8:$AE$2617,Control!$F$9)/INDEX(HIST_D!$AE$8:$AE$2617,1)-1,"") | H10: =IFERROR(INDEX(HIST_D!$AE$8:$AE$2617,Control!$F$10)/INDEX(HIST_D!$AE$8:$AE$2617,1)-1,"") | I10: =IFERROR(INDEX(HIST_D!$AE$8:$AE$2617,Control!$F$16)/INDEX(HIST_D!$AE$8:$AE$2617,1)-1,"") | J10: =IFERROR(INDEX(HIST_D!$AE$8:$AE$2617,Control!$F$11)/INDEX(HIST_D!$AE$8:$AE$2617,1)-1,"") | K10: =IFERROR(IFERROR(INDEX(HIST_D!$AE$8:$AE$2617,Control!$F$8)/INDEX(HIST_D!$AE$8:$AE$2617,1)-1,"")+IFERROR(INDEX(HIST_D!$J$8:$J$2617,1)/INDEX(HIST_D!$J$8:$J$2617,Control!$F$8)-1,""),"") | L10: =IFERROR(IFERROR(INDEX(HIST_D!$AE$8:$AE$2617,Control!$F$9)/INDEX(HIST_D!$AE$8:$AE$2617,1)-1,"")+IFERROR(INDEX(HIST_D!$J$8:$J$2617,1)/INDEX(HIST_D!$J$8:$J$2617,Control!$F$9)-1,""),"") | M10: =IFERROR(IFERROR(INDEX(HIST_D!$AE$8:$AE$2617,Control!$F$16)/INDEX(HIST_D!$AE$8:$AE$2617,1)-1,"")+IFERROR(INDEX(HIST_D!$J$8:$J$2617,1)/INDEX(HIST_D!$J$8:$J$2617,Control!$F$16)-1,""),"") | N10: =IFERROR(PERCENTRANK(HIST_D!$AE$8:INDEX(HIST_D!$AE$8:$AE$2617,Control!$F$11),INDEX(HIST_D!$AE$8:$AE$2617,1)),"") | O10: =IFERROR(PERCENTRANK(HIST_D!$AE$8:INDEX(HIST_D!$AE$8:$AE$2617,Control!$F$14),INDEX(HIST_D!$AE$8:$AE$2617,1)),"")
A11: Argentina ARS | B11: float | C11: =INDEX(HIST_D!$AF$8:$AF$2617,1) | D11: =IFERROR(INDEX(HIST_D!$AF$8:$AF$2617,Control!$F$6)/INDEX(HIST_D!$AF$8:$AF$2617,1)-1,"") | E11: =IFERROR(INDEX(HIST_D!$AF$8:$AF$2617,Control!$F$7)/INDEX(HIST_D!$AF$8:$AF$2617,1)-1,"") | F11: =IFERROR(INDEX(HIST_D!$AF$8:$AF$2617,Control!$F$8)/INDEX(HIST_D!$AF$8:$AF$2617,1)-1,"") | G11: =IFERROR(INDEX(HIST_D!$AF$8:$AF$2617,Control!$F$9)/INDEX(HIST_D!$AF$8:$AF$2617,1)-1,"") | H11: =IFERROR(INDEX(HIST_D!$AF$8:$AF$2617,Control!$F$10)/INDEX(HIST_D!$AF$8:$AF$2617,1)-1,"") | I11: =IFERROR(INDEX(HIST_D!$AF$8:$AF$2617,Control!$F$16)/INDEX(HIST_D!$AF$8:$AF$2617,1)-1,"") | J11: =IFERROR(INDEX(HIST_D!$AF$8:$AF$2617,Control!$F$11)/INDEX(HIST_D!$AF$8:$AF$2617,1)-1,"") | K11: =IFERROR(IFERROR(INDEX(HIST_D!$AF$8:$AF$2617,Control!$F$8)/INDEX(HIST_D!$AF$8:$AF$2617,1)-1,"")+IFERROR(INDEX(HIST_D!$J$8:$J$2617,1)/INDEX(HIST_D!$J$8:$J$2617,Control!$F$8)-1,""),"") | L11: =IFERROR(IFERROR(INDEX(HIST_D!$AF$8:$AF$2617,Control!$F$9)/INDEX(HIST_D!$AF$8:$AF$2617,1)-1,"")+IFERROR(INDEX(HIST_D!$J$8:$J$2617,1)/INDEX(HIST_D!$J$8:$J$2617,Control!$F$9)-1,""),"") | M11: =IFERROR(IFERROR(INDEX(HIST_D!$AF$8:$AF$2617,Control!$F$16)/INDEX(HIST_D!$AF$8:$AF$2617,1)-1,"")+IFERROR(INDEX(HIST_D!$J$8:$J$2617,1)/INDEX(HIST_D!$J$8:$J$2617,Control!$F$16)-1,""),"") | N11: =IFERROR(PERCENTRANK(HIST_D!$AF$8:INDEX(HIST_D!$AF$8:$AF$2617,Control!$F$11),INDEX(HIST_D!$AF$8:$AF$2617,1)),"") | O11: =IFERROR(PERCENTRANK(HIST_D!$AF$8:INDEX(HIST_D!$AF$8:$AF$2617,Control!$F$14),INDEX(HIST_D!$AF$8:$AF$2617,1)),"")
A12: LatAm basket (floating, n=6) | D12: =IFERROR(AVERAGE(D6,D7,D8,D9,D10,D11),"") | E12: =IFERROR(AVERAGE(E6,E7,E8,E9,E10,E11),"") | F12: =IFERROR(AVERAGE(F6,F7,F8,F9,F10,F11),"") | G12: =IFERROR(AVERAGE(G6,G7,G8,G9,G10,G11),"") | H12: =IFERROR(AVERAGE(H6,H7,H8,H9,H10,H11),"") | I12: =IFERROR(AVERAGE(I6,I7,I8,I9,I10,I11),"") | J12: =IFERROR(AVERAGE(J6,J7,J8,J9,J10,J11),"") | K12: =IFERROR(AVERAGE(K6,K7,K8,K9,K10,K11),"") | ... O12: =IFERROR(AVERAGE(O6,O7,O8,O9,O10,O11),"")
A13: =IFERROR("LatAm: "&TEXT($F$12,"+0.0%;-0.0%")&" on the month, "&TEXT($I$12,"+0.0%;-0.0%")&" YTD, "&TEXT($K$12,"+0.0%;-0.0%")&" ex-dollar. "&IF($F$12>$F$51,"Ahead of","Behind")&" the EM basket at "&TEXT($F$51,"+0.0%;-0.0%")&". "&IF($K$12>0.005,"Regional support beyond the dollar.",IF($K$12<-0.005,"Lagging even after adjusting for the dollar.","Tracking the dollar; no regional signal.")),"")
A15: EM EUROPE
A16: Currency | B16: Peg | C16: Spot (EM/USD) | D16: 1D | E16: 1W | F16: 1M | G16: 3M | H16: 6M | I16: YTD | J16: 1Y | K16: 1M ex-USD | L16: 3M ex-USD | M16: YTD ex-USD | N16: %ile 1y (spot) | O16: %ile 5y (spot)
A17: Poland PLN | B17: float | C17: =INDEX(HIST_D!$AG$8:$AG$2617,1) | D17: =IFERROR(INDEX(HIST_D!$AG$8:$AG$2617,Control!$F$6)/INDEX(HIST_D!$AG$8:$AG$2617,1)-1,"") | E17: =IFERROR(INDEX(HIST_D!$AG$8:$AG$2617,Control!$F$7)/INDEX(HIST_D!$AG$8:$AG$2617,1)-1,"") | F17: =IFERROR(INDEX(HIST_D!$AG$8:$AG$2617,Control!$F$8)/INDEX(HIST_D!$AG$8:$AG$2617,1)-1,"") | G17: =IFERROR(INDEX(HIST_D!$AG$8:$AG$2617,Control!$F$9)/INDEX(HIST_D!$AG$8:$AG$2617,1)-1,"") | H17: =IFERROR(INDEX(HIST_D!$AG$8:$AG$2617,Control!$F$10)/INDEX(HIST_D!$AG$8:$AG$2617,1)-1,"") | I17: =IFERROR(INDEX(HIST_D!$AG$8:$AG$2617,Control!$F$16)/INDEX(HIST_D!$AG$8:$AG$2617,1)-1,"") | J17: =IFERROR(INDEX(HIST_D!$AG$8:$AG$2617,Control!$F$11)/INDEX(HIST_D!$AG$8:$AG$2617,1)-1,"") | K17: =IFERROR(IFERROR(INDEX(HIST_D!$AG$8:$AG$2617,Control!$F$8)/INDEX(HIST_D!$AG$8:$AG$2617,1)-1,"")+IFERROR(INDEX(HIST_D!$J$8:$J$2617,1)/INDEX(HIST_D!$J$8:$J$2617,Control!$F$8)-1,""),"") | L17: =IFERROR(IFERROR(INDEX(HIST_D!$AG$8:$AG$2617,Control!$F$9)/INDEX(HIST_D!$AG$8:$AG$2617,1)-1,"")+IFERROR(INDEX(HIST_D!$J$8:$J$2617,1)/INDEX(HIST_D!$J$8:$J$2617,Control!$F$9)-1,""),"") | M17: =IFERROR(IFERROR(INDEX(HIST_D!$AG$8:$AG$2617,Control!$F$16)/INDEX(HIST_D!$AG$8:$AG$2617,1)-1,"")+IFERROR(INDEX(HIST_D!$J$8:$J$2617,1)/INDEX(HIST_D!$J$8:$J$2617,Control!$F$16)-1,""),"") | N17: =IFERROR(PERCENTRANK(HIST_D!$AG$8:INDEX(HIST_D!$AG$8:$AG$2617,Control!$F$11),INDEX(HIST_D!$AG$8:$AG$2617,1)),"") | O17: =IFERROR(PERCENTRANK(HIST_D!$AG$8:INDEX(HIST_D!$AG$8:$AG$2617,Control!$F$14),INDEX(HIST_D!$AG$8:$AG$2617,1)),"")
A18: Hungary HUF | B18: float | C18: =INDEX(HIST_D!$AH$8:$AH$2617,1) | D18: =IFERROR(INDEX(HIST_D!$AH$8:$AH$2617,Control!$F$6)/INDEX(HIST_D!$AH$8:$AH$2617,1)-1,"") | E18: =IFERROR(INDEX(HIST_D!$AH$8:$AH$2617,Control!$F$7)/INDEX(HIST_D!$AH$8:$AH$2617,1)-1,"") | F18: =IFERROR(INDEX(HIST_D!$AH$8:$AH$2617,Control!$F$8)/INDEX(HIST_D!$AH$8:$AH$2617,1)-1,"") | G18: =IFERROR(INDEX(HIST_D!$AH$8:$AH$2617,Control!$F$9)/INDEX(HIST_D!$AH$8:$AH$2617,1)-1,"") | H18: =IFERROR(INDEX(HIST_D!$AH$8:$AH$2617,Control!$F$10)/INDEX(HIST_D!$AH$8:$AH$2617,1)-1,"") | I18: =IFERROR(INDEX(HIST_D!$AH$8:$AH$2617,Control!$F$16)/INDEX(HIST_D!$AH$8:$AH$2617,1)-1,"") | J18: =IFERROR(INDEX(HIST_D!$AH$8:$AH$2617,Control!$F$11)/INDEX(HIST_D!$AH$8:$AH$2617,1)-1,"") | K18: =IFERROR(IFERROR(INDEX(HIST_D!$AH$8:$AH$2617,Control!$F$8)/INDEX(HIST_D!$AH$8:$AH$2617,1)-1,"")+IFERROR(INDEX(HIST_D!$J$8:$J$2617,1)/INDEX(HIST_D!$J$8:$J$2617,Control!$F$8)-1,""),"") | L18: =IFERROR(IFERROR(INDEX(HIST_D!$AH$8:$AH$2617,Control!$F$9)/INDEX(HIST_D!$AH$8:$AH$2617,1)-1,"")+IFERROR(INDEX(HIST_D!$J$8:$J$2617,1)/INDEX(HIST_D!$J$8:$J$2617,Control!$F$9)-1,""),"") | M18: =IFERROR(IFERROR(INDEX(HIST_D!$AH$8:$AH$2617,Control!$F$16)/INDEX(HIST_D!$AH$8:$AH$2617,1)-1,"")+IFERROR(INDEX(HIST_D!$J$8:$J$2617,1)/INDEX(HIST_D!$J$8:$J$2617,Control!$F$16)-1,""),"") | N18: =IFERROR(PERCENTRANK(HIST_D!$AH$8:INDEX(HIST_D!$AH$8:$AH$2617,Control!$F$11),INDEX(HIST_D!$AH$8:$AH$2617,1)),"") | O18: =IFERROR(PERCENTRANK(HIST_D!$AH$8:INDEX(HIST_D!$AH$8:$AH$2617,Control!$F$14),INDEX(HIST_D!$AH$8:$AH$2617,1)),"")
A19: Czechia CZK | B19: float | C19: =INDEX(HIST_D!$AI$8:$AI$2617,1) | D19: =IFERROR(INDEX(HIST_D!$AI$8:$AI$2617,Control!$F$6)/INDEX(HIST_D!$AI$8:$AI$2617,1)-1,"") | E19: =IFERROR(INDEX(HIST_D!$AI$8:$AI$2617,Control!$F$7)/INDEX(HIST_D!$AI$8:$AI$2617,1)-1,"") | F19: =IFERROR(INDEX(HIST_D!$AI$8:$AI$2617,Control!$F$8)/INDEX(HIST_D!$AI$8:$AI$2617,1)-1,"") | G19: =IFERROR(INDEX(HIST_D!$AI$8:$AI$2617,Control!$F$9)/INDEX(HIST_D!$AI$8:$AI$2617,1)-1,"") | H19: =IFERROR(INDEX(HIST_D!$AI$8:$AI$2617,Control!$F$10)/INDEX(HIST_D!$AI$8:$AI$2617,1)-1,"") | I19: =IFERROR(INDEX(HIST_D!$AI$8:$AI$2617,Control!$F$16)/INDEX(HIST_D!$AI$8:$AI$2617,1)-1,"") | J19: =IFERROR(INDEX(HIST_D!$AI$8:$AI$2617,Control!$F$11)/INDEX(HIST_D!$AI$8:$AI$2617,1)-1,"") | K19: =IFERROR(IFERROR(INDEX(HIST_D!$AI$8:$AI$2617,Control!$F$8)/INDEX(HIST_D!$AI$8:$AI$2617,1)-1,"")+IFERROR(INDEX(HIST_D!$J$8:$J$2617,1)/INDEX(HIST_D!$J$8:$J$2617,Control!$F$8)-1,""),"") | L19: =IFERROR(IFERROR(INDEX(HIST_D!$AI$8:$AI$2617,Control!$F$9)/INDEX(HIST_D!$AI$8:$AI$2617,1)-1,"")+IFERROR(INDEX(HIST_D!$J$8:$J$2617,1)/INDEX(HIST_D!$J$8:$J$2617,Control!$F$9)-1,""),"") | M19: =IFERROR(IFERROR(INDEX(HIST_D!$AI$8:$AI$2617,Control!$F$16)/INDEX(HIST_D!$AI$8:$AI$2617,1)-1,"")+IFERROR(INDEX(HIST_D!$J$8:$J$2617,1)/INDEX(HIST_D!$J$8:$J$2617,Control!$F$16)-1,""),"") | N19: =IFERROR(PERCENTRANK(HIST_D!$AI$8:INDEX(HIST_D!$AI$8:$AI$2617,Control!$F$11),INDEX(HIST_D!$AI$8:$AI$2617,1)),"") | O19: =IFERROR(PERCENTRANK(HIST_D!$AI$8:INDEX(HIST_D!$AI$8:$AI$2617,Control!$F$14),INDEX(HIST_D!$AI$8:$AI$2617,1)),"")
A20: Romania RON | B20: float | C20: =INDEX(HIST_D!$AJ$8:$AJ$2617,1) | D20: =IFERROR(INDEX(HIST_D!$AJ$8:$AJ$2617,Control!$F$6)/INDEX(HIST_D!$AJ$8:$AJ$2617,1)-1,"") | E20: =IFERROR(INDEX(HIST_D!$AJ$8:$AJ$2617,Control!$F$7)/INDEX(HIST_D!$AJ$8:$AJ$2617,1)-1,"") | F20: =IFERROR(INDEX(HIST_D!$AJ$8:$AJ$2617,Control!$F$8)/INDEX(HIST_D!$AJ$8:$AJ$2617,1)-1,"") | G20: =IFERROR(INDEX(HIST_D!$AJ$8:$AJ$2617,Control!$F$9)/INDEX(HIST_D!$AJ$8:$AJ$2617,1)-1,"") | H20: =IFERROR(INDEX(HIST_D!$AJ$8:$AJ$2617,Control!$F$10)/INDEX(HIST_D!$AJ$8:$AJ$2617,1)-1,"") | I20: =IFERROR(INDEX(HIST_D!$AJ$8:$AJ$2617,Control!$F$16)/INDEX(HIST_D!$AJ$8:$AJ$2617,1)-1,"") | J20: =IFERROR(INDEX(HIST_D!$AJ$8:$AJ$2617,Control!$F$11)/INDEX(HIST_D!$AJ$8:$AJ$2617,1)-1,"") | K20: =IFERROR(IFERROR(INDEX(HIST_D!$AJ$8:$AJ$2617,Control!$F$8)/INDEX(HIST_D!$AJ$8:$AJ$2617,1)-1,"")+IFERROR(INDEX(HIST_D!$J$8:$J$2617,1)/INDEX(HIST_D!$J$8:$J$2617,Control!$F$8)-1,""),"") | L20: =IFERROR(IFERROR(INDEX(HIST_D!$AJ$8:$AJ$2617,Control!$F$9)/INDEX(HIST_D!$AJ$8:$AJ$2617,1)-1,"")+IFERROR(INDEX(HIST_D!$J$8:$J$2617,1)/INDEX(HIST_D!$J$8:$J$2617,Control!$F$9)-1,""),"") | M20: =IFERROR(IFERROR(INDEX(HIST_D!$AJ$8:$AJ$2617,Control!$F$16)/INDEX(HIST_D!$AJ$8:$AJ$2617,1)-1,"")+IFERROR(INDEX(HIST_D!$J$8:$J$2617,1)/INDEX(HIST_D!$J$8:$J$2617,Control!$F$16)-1,""),"") | N20: =IFERROR(PERCENTRANK(HIST_D!$AJ$8:INDEX(HIST_D!$AJ$8:$AJ$2617,Control!$F$11),INDEX(HIST_D!$AJ$8:$AJ$2617,1)),"") | O20: =IFERROR(PERCENTRANK(HIST_D!$AJ$8:INDEX(HIST_D!$AJ$8:$AJ$2617,Control!$F$14),INDEX(HIST_D!$AJ$8:$AJ$2617,1)),"")
A21: Turkiye TRY | B21: float | C21: =INDEX(HIST_D!$AK$8:$AK$2617,1) | D21: =IFERROR(INDEX(HIST_D!$AK$8:$AK$2617,Control!$F$6)/INDEX(HIST_D!$AK$8:$AK$2617,1)-1,"") | E21: =IFERROR(INDEX(HIST_D!$AK$8:$AK$2617,Control!$F$7)/INDEX(HIST_D!$AK$8:$AK$2617,1)-1,"") | F21: =IFERROR(INDEX(HIST_D!$AK$8:$AK$2617,Control!$F$8)/INDEX(HIST_D!$AK$8:$AK$2617,1)-1,"") | G21: =IFERROR(INDEX(HIST_D!$AK$8:$AK$2617,Control!$F$9)/INDEX(HIST_D!$AK$8:$AK$2617,1)-1,"") | H21: =IFERROR(INDEX(HIST_D!$AK$8:$AK$2617,Control!$F$10)/INDEX(HIST_D!$AK$8:$AK$2617,1)-1,"") | I21: =IFERROR(INDEX(HIST_D!$AK$8:$AK$2617,Control!$F$16)/INDEX(HIST_D!$AK$8:$AK$2617,1)-1,"") | J21: =IFERROR(INDEX(HIST_D!$AK$8:$AK$2617,Control!$F$11)/INDEX(HIST_D!$AK$8:$AK$2617,1)-1,"") | K21: =IFERROR(IFERROR(INDEX(HIST_D!$AK$8:$AK$2617,Control!$F$8)/INDEX(HIST_D!$AK$8:$AK$2617,1)-1,"")+IFERROR(INDEX(HIST_D!$J$8:$J$2617,1)/INDEX(HIST_D!$J$8:$J$2617,Control!$F$8)-1,""),"") | L21: =IFERROR(IFERROR(INDEX(HIST_D!$AK$8:$AK$2617,Control!$F$9)/INDEX(HIST_D!$AK$8:$AK$2617,1)-1,"")+IFERROR(INDEX(HIST_D!$J$8:$J$2617,1)/INDEX(HIST_D!$J$8:$J$2617,Control!$F$9)-1,""),"") | M21: =IFERROR(IFERROR(INDEX(HIST_D!$AK$8:$AK$2617,Control!$F$16)/INDEX(HIST_D!$AK$8:$AK$2617,1)-1,"")+IFERROR(INDEX(HIST_D!$J$8:$J$2617,1)/INDEX(HIST_D!$J$8:$J$2617,Control!$F$16)-1,""),"") | N21: =IFERROR(PERCENTRANK(HIST_D!$AK$8:INDEX(HIST_D!$AK$8:$AK$2617,Control!$F$11),INDEX(HIST_D!$AK$8:$AK$2617,1)),"") | O21: =IFERROR(PERCENTRANK(HIST_D!$AK$8:INDEX(HIST_D!$AK$8:$AK$2617,Control!$F$14),INDEX(HIST_D!$AK$8:$AK$2617,1)),"")
A22: EM Europe basket (floating, n=5) | D22: =IFERROR(AVERAGE(D17,D18,D19,D20,D21),"") | E22: =IFERROR(AVERAGE(E17,E18,E19,E20,E21),"") | F22: =IFERROR(AVERAGE(F17,F18,F19,F20,F21),"") | G22: =IFERROR(AVERAGE(G17,G18,G19,G20,G21),"") | H22: =IFERROR(AVERAGE(H17,H18,H19,H20,H21),"") | I22: =IFERROR(AVERAGE(I17,I18,I19,I20,I21),"") | J22: =IFERROR(AVERAGE(J17,J18,J19,J20,J21),"") | K22: =IFERROR(AVERAGE(K17,K18,K19,K20,K21),"") | ... O22: =IFERROR(AVERAGE(O17,O18,O19,O20,O21),"")
A23: =IFERROR("EM Europe: "&TEXT($F$22,"+0.0%;-0.0%")&" on the month, "&TEXT($I$22,"+0.0%;-0.0%")&" YTD, "&TEXT($K$22,"+0.0%;-0.0%")&" ex-dollar. "&IF($F$22>$F$51,"Ahead of","Behind")&" the EM basket at "&TEXT($F$51,"+0.0%;-0.0%")&". "&IF($K$22>0.005,"Regional support beyond the dollar.",IF($K$22<-0.005,"Lagging even after adjusting for the dollar.","Tracking the dollar; no regional signal.")),"")
A25: MIDDLE EAST & AFRICA
A26: Currency | B26: Peg | C26: Spot (EM/USD) | D26: 1D | E26: 1W | F26: 1M | G26: 3M | H26: 6M | I26: YTD | J26: 1Y | K26: 1M ex-USD | L26: 3M ex-USD | M26: YTD ex-USD | N26: %ile 1y (spot) | O26: %ile 5y (spot)
A27: Israel ILS | B27: float | C27: =INDEX(HIST_D!$AL$8:$AL$2617,1) | D27: =IFERROR(INDEX(HIST_D!$AL$8:$AL$2617,Control!$F$6)/INDEX(HIST_D!$AL$8:$AL$2617,1)-1,"") | E27: =IFERROR(INDEX(HIST_D!$AL$8:$AL$2617,Control!$F$7)/INDEX(HIST_D!$AL$8:$AL$2617,1)-1,"") | F27: =IFERROR(INDEX(HIST_D!$AL$8:$AL$2617,Control!$F$8)/INDEX(HIST_D!$AL$8:$AL$2617,1)-1,"") | G27: =IFERROR(INDEX(HIST_D!$AL$8:$AL$2617,Control!$F$9)/INDEX(HIST_D!$AL$8:$AL$2617,1)-1,"") | H27: =IFERROR(INDEX(HIST_D!$AL$8:$AL$2617,Control!$F$10)/INDEX(HIST_D!$AL$8:$AL$2617,1)-1,"") | I27: =IFERROR(INDEX(HIST_D!$AL$8:$AL$2617,Control!$F$16)/INDEX(HIST_D!$AL$8:$AL$2617,1)-1,"") | J27: =IFERROR(INDEX(HIST_D!$AL$8:$AL$2617,Control!$F$11)/INDEX(HIST_D!$AL$8:$AL$2617,1)-1,"") | K27: =IFERROR(IFERROR(INDEX(HIST_D!$AL$8:$AL$2617,Control!$F$8)/INDEX(HIST_D!$AL$8:$AL$2617,1)-1,"")+IFERROR(INDEX(HIST_D!$J$8:$J$2617,1)/INDEX(HIST_D!$J$8:$J$2617,Control!$F$8)-1,""),"") | L27: =IFERROR(IFERROR(INDEX(HIST_D!$AL$8:$AL$2617,Control!$F$9)/INDEX(HIST_D!$AL$8:$AL$2617,1)-1,"")+IFERROR(INDEX(HIST_D!$J$8:$J$2617,1)/INDEX(HIST_D!$J$8:$J$2617,Control!$F$9)-1,""),"") | M27: =IFERROR(IFERROR(INDEX(HIST_D!$AL$8:$AL$2617,Control!$F$16)/INDEX(HIST_D!$AL$8:$AL$2617,1)-1,"")+IFERROR(INDEX(HIST_D!$J$8:$J$2617,1)/INDEX(HIST_D!$J$8:$J$2617,Control!$F$16)-1,""),"") | N27: =IFERROR(PERCENTRANK(HIST_D!$AL$8:INDEX(HIST_D!$AL$8:$AL$2617,Control!$F$11),INDEX(HIST_D!$AL$8:$AL$2617,1)),"") | O27: =IFERROR(PERCENTRANK(HIST_D!$AL$8:INDEX(HIST_D!$AL$8:$AL$2617,Control!$F$14),INDEX(HIST_D!$AL$8:$AL$2617,1)),"")
A28: South Africa ZAR | B28: float | C28: =INDEX(HIST_D!$AM$8:$AM$2617,1) | D28: =IFERROR(INDEX(HIST_D!$AM$8:$AM$2617,Control!$F$6)/INDEX(HIST_D!$AM$8:$AM$2617,1)-1,"") | E28: =IFERROR(INDEX(HIST_D!$AM$8:$AM$2617,Control!$F$7)/INDEX(HIST_D!$AM$8:$AM$2617,1)-1,"") | F28: =IFERROR(INDEX(HIST_D!$AM$8:$AM$2617,Control!$F$8)/INDEX(HIST_D!$AM$8:$AM$2617,1)-1,"") | G28: =IFERROR(INDEX(HIST_D!$AM$8:$AM$2617,Control!$F$9)/INDEX(HIST_D!$AM$8:$AM$2617,1)-1,"") | H28: =IFERROR(INDEX(HIST_D!$AM$8:$AM$2617,Control!$F$10)/INDEX(HIST_D!$AM$8:$AM$2617,1)-1,"") | I28: =IFERROR(INDEX(HIST_D!$AM$8:$AM$2617,Control!$F$16)/INDEX(HIST_D!$AM$8:$AM$2617,1)-1,"") | J28: =IFERROR(INDEX(HIST_D!$AM$8:$AM$2617,Control!$F$11)/INDEX(HIST_D!$AM$8:$AM$2617,1)-1,"") | K28: =IFERROR(IFERROR(INDEX(HIST_D!$AM$8:$AM$2617,Control!$F$8)/INDEX(HIST_D!$AM$8:$AM$2617,1)-1,"")+IFERROR(INDEX(HIST_D!$J$8:$J$2617,1)/INDEX(HIST_D!$J$8:$J$2617,Control!$F$8)-1,""),"") | L28: =IFERROR(IFERROR(INDEX(HIST_D!$AM$8:$AM$2617,Control!$F$9)/INDEX(HIST_D!$AM$8:$AM$2617,1)-1,"")+IFERROR(INDEX(HIST_D!$J$8:$J$2617,1)/INDEX(HIST_D!$J$8:$J$2617,Control!$F$9)-1,""),"") | M28: =IFERROR(IFERROR(INDEX(HIST_D!$AM$8:$AM$2617,Control!$F$16)/INDEX(HIST_D!$AM$8:$AM$2617,1)-1,"")+IFERROR(INDEX(HIST_D!$J$8:$J$2617,1)/INDEX(HIST_D!$J$8:$J$2617,Control!$F$16)-1,""),"") | N28: =IFERROR(PERCENTRANK(HIST_D!$AM$8:INDEX(HIST_D!$AM$8:$AM$2617,Control!$F$11),INDEX(HIST_D!$AM$8:$AM$2617,1)),"") | O28: =IFERROR(PERCENTRANK(HIST_D!$AM$8:INDEX(HIST_D!$AM$8:$AM$2617,Control!$F$14),INDEX(HIST_D!$AM$8:$AM$2617,1)),"")
A29: Egypt EGP | B29: float | C29: =INDEX(HIST_D!$AN$8:$AN$2617,1) | D29: =IFERROR(INDEX(HIST_D!$AN$8:$AN$2617,Control!$F$6)/INDEX(HIST_D!$AN$8:$AN$2617,1)-1,"") | E29: =IFERROR(INDEX(HIST_D!$AN$8:$AN$2617,Control!$F$7)/INDEX(HIST_D!$AN$8:$AN$2617,1)-1,"") | F29: =IFERROR(INDEX(HIST_D!$AN$8:$AN$2617,Control!$F$8)/INDEX(HIST_D!$AN$8:$AN$2617,1)-1,"") | G29: =IFERROR(INDEX(HIST_D!$AN$8:$AN$2617,Control!$F$9)/INDEX(HIST_D!$AN$8:$AN$2617,1)-1,"") | H29: =IFERROR(INDEX(HIST_D!$AN$8:$AN$2617,Control!$F$10)/INDEX(HIST_D!$AN$8:$AN$2617,1)-1,"") | I29: =IFERROR(INDEX(HIST_D!$AN$8:$AN$2617,Control!$F$16)/INDEX(HIST_D!$AN$8:$AN$2617,1)-1,"") | J29: =IFERROR(INDEX(HIST_D!$AN$8:$AN$2617,Control!$F$11)/INDEX(HIST_D!$AN$8:$AN$2617,1)-1,"") | K29: =IFERROR(IFERROR(INDEX(HIST_D!$AN$8:$AN$2617,Control!$F$8)/INDEX(HIST_D!$AN$8:$AN$2617,1)-1,"")+IFERROR(INDEX(HIST_D!$J$8:$J$2617,1)/INDEX(HIST_D!$J$8:$J$2617,Control!$F$8)-1,""),"") | L29: =IFERROR(IFERROR(INDEX(HIST_D!$AN$8:$AN$2617,Control!$F$9)/INDEX(HIST_D!$AN$8:$AN$2617,1)-1,"")+IFERROR(INDEX(HIST_D!$J$8:$J$2617,1)/INDEX(HIST_D!$J$8:$J$2617,Control!$F$9)-1,""),"") | M29: =IFERROR(IFERROR(INDEX(HIST_D!$AN$8:$AN$2617,Control!$F$16)/INDEX(HIST_D!$AN$8:$AN$2617,1)-1,"")+IFERROR(INDEX(HIST_D!$J$8:$J$2617,1)/INDEX(HIST_D!$J$8:$J$2617,Control!$F$16)-1,""),"") | N29: =IFERROR(PERCENTRANK(HIST_D!$AN$8:INDEX(HIST_D!$AN$8:$AN$2617,Control!$F$11),INDEX(HIST_D!$AN$8:$AN$2617,1)),"") | O29: =IFERROR(PERCENTRANK(HIST_D!$AN$8:INDEX(HIST_D!$AN$8:$AN$2617,Control!$F$14),INDEX(HIST_D!$AN$8:$AN$2617,1)),"")
A30: Saudi SAR (pegged) | B30: peg | C30: =INDEX(HIST_D!$AO$8:$AO$2617,1) | D30: =IFERROR(INDEX(HIST_D!$AO$8:$AO$2617,Control!$F$6)/INDEX(HIST_D!$AO$8:$AO$2617,1)-1,"") | E30: =IFERROR(INDEX(HIST_D!$AO$8:$AO$2617,Control!$F$7)/INDEX(HIST_D!$AO$8:$AO$2617,1)-1,"") | F30: =IFERROR(INDEX(HIST_D!$AO$8:$AO$2617,Control!$F$8)/INDEX(HIST_D!$AO$8:$AO$2617,1)-1,"") | G30: =IFERROR(INDEX(HIST_D!$AO$8:$AO$2617,Control!$F$9)/INDEX(HIST_D!$AO$8:$AO$2617,1)-1,"") | H30: =IFERROR(INDEX(HIST_D!$AO$8:$AO$2617,Control!$F$10)/INDEX(HIST_D!$AO$8:$AO$2617,1)-1,"") | I30: =IFERROR(INDEX(HIST_D!$AO$8:$AO$2617,Control!$F$16)/INDEX(HIST_D!$AO$8:$AO$2617,1)-1,"") | J30: =IFERROR(INDEX(HIST_D!$AO$8:$AO$2617,Control!$F$11)/INDEX(HIST_D!$AO$8:$AO$2617,1)-1,"") | K30: =IFERROR(IFERROR(INDEX(HIST_D!$AO$8:$AO$2617,Control!$F$8)/INDEX(HIST_D!$AO$8:$AO$2617,1)-1,"")+IFERROR(INDEX(HIST_D!$J$8:$J$2617,1)/INDEX(HIST_D!$J$8:$J$2617,Control!$F$8)-1,""),"") | L30: =IFERROR(IFERROR(INDEX(HIST_D!$AO$8:$AO$2617,Control!$F$9)/INDEX(HIST_D!$AO$8:$AO$2617,1)-1,"")+IFERROR(INDEX(HIST_D!$J$8:$J$2617,1)/INDEX(HIST_D!$J$8:$J$2617,Control!$F$9)-1,""),"") | M30: =IFERROR(IFERROR(INDEX(HIST_D!$AO$8:$AO$2617,Control!$F$16)/INDEX(HIST_D!$AO$8:$AO$2617,1)-1,"")+IFERROR(INDEX(HIST_D!$J$8:$J$2617,1)/INDEX(HIST_D!$J$8:$J$2617,Control!$F$16)-1,""),"") | N30: =IFERROR(PERCENTRANK(HIST_D!$AO$8:INDEX(HIST_D!$AO$8:$AO$2617,Control!$F$11),INDEX(HIST_D!$AO$8:$AO$2617,1)),"") | O30: =IFERROR(PERCENTRANK(HIST_D!$AO$8:INDEX(HIST_D!$AO$8:$AO$2617,Control!$F$14),INDEX(HIST_D!$AO$8:$AO$2617,1)),"")
A31: UAE AED (pegged) | B31: peg | C31: =INDEX(HIST_D!$AP$8:$AP$2617,1) | D31: =IFERROR(INDEX(HIST_D!$AP$8:$AP$2617,Control!$F$6)/INDEX(HIST_D!$AP$8:$AP$2617,1)-1,"") | E31: =IFERROR(INDEX(HIST_D!$AP$8:$AP$2617,Control!$F$7)/INDEX(HIST_D!$AP$8:$AP$2617,1)-1,"") | F31: =IFERROR(INDEX(HIST_D!$AP$8:$AP$2617,Control!$F$8)/INDEX(HIST_D!$AP$8:$AP$2617,1)-1,"") | G31: =IFERROR(INDEX(HIST_D!$AP$8:$AP$2617,Control!$F$9)/INDEX(HIST_D!$AP$8:$AP$2617,1)-1,"") | H31: =IFERROR(INDEX(HIST_D!$AP$8:$AP$2617,Control!$F$10)/INDEX(HIST_D!$AP$8:$AP$2617,1)-1,"") | I31: =IFERROR(INDEX(HIST_D!$AP$8:$AP$2617,Control!$F$16)/INDEX(HIST_D!$AP$8:$AP$2617,1)-1,"") | J31: =IFERROR(INDEX(HIST_D!$AP$8:$AP$2617,Control!$F$11)/INDEX(HIST_D!$AP$8:$AP$2617,1)-1,"") | K31: =IFERROR(IFERROR(INDEX(HIST_D!$AP$8:$AP$2617,Control!$F$8)/INDEX(HIST_D!$AP$8:$AP$2617,1)-1,"")+IFERROR(INDEX(HIST_D!$J$8:$J$2617,1)/INDEX(HIST_D!$J$8:$J$2617,Control!$F$8)-1,""),"") | L31: =IFERROR(IFERROR(INDEX(HIST_D!$AP$8:$AP$2617,Control!$F$9)/INDEX(HIST_D!$AP$8:$AP$2617,1)-1,"")+IFERROR(INDEX(HIST_D!$J$8:$J$2617,1)/INDEX(HIST_D!$J$8:$J$2617,Control!$F$9)-1,""),"") | M31: =IFERROR(IFERROR(INDEX(HIST_D!$AP$8:$AP$2617,Control!$F$16)/INDEX(HIST_D!$AP$8:$AP$2617,1)-1,"")+IFERROR(INDEX(HIST_D!$J$8:$J$2617,1)/INDEX(HIST_D!$J$8:$J$2617,Control!$F$16)-1,""),"") | N31: =IFERROR(PERCENTRANK(HIST_D!$AP$8:INDEX(HIST_D!$AP$8:$AP$2617,Control!$F$11),INDEX(HIST_D!$AP$8:$AP$2617,1)),"") | O31: =IFERROR(PERCENTRANK(HIST_D!$AP$8:INDEX(HIST_D!$AP$8:$AP$2617,Control!$F$14),INDEX(HIST_D!$AP$8:$AP$2617,1)),"")
A32: Qatar QAR (pegged) | B32: peg | C32: =INDEX(HIST_D!$AQ$8:$AQ$2617,1) | D32: =IFERROR(INDEX(HIST_D!$AQ$8:$AQ$2617,Control!$F$6)/INDEX(HIST_D!$AQ$8:$AQ$2617,1)-1,"") | E32: =IFERROR(INDEX(HIST_D!$AQ$8:$AQ$2617,Control!$F$7)/INDEX(HIST_D!$AQ$8:$AQ$2617,1)-1,"") | F32: =IFERROR(INDEX(HIST_D!$AQ$8:$AQ$2617,Control!$F$8)/INDEX(HIST_D!$AQ$8:$AQ$2617,1)-1,"") | G32: =IFERROR(INDEX(HIST_D!$AQ$8:$AQ$2617,Control!$F$9)/INDEX(HIST_D!$AQ$8:$AQ$2617,1)-1,"") | H32: =IFERROR(INDEX(HIST_D!$AQ$8:$AQ$2617,Control!$F$10)/INDEX(HIST_D!$AQ$8:$AQ$2617,1)-1,"") | I32: =IFERROR(INDEX(HIST_D!$AQ$8:$AQ$2617,Control!$F$16)/INDEX(HIST_D!$AQ$8:$AQ$2617,1)-1,"") | J32: =IFERROR(INDEX(HIST_D!$AQ$8:$AQ$2617,Control!$F$11)/INDEX(HIST_D!$AQ$8:$AQ$2617,1)-1,"") | K32: =IFERROR(IFERROR(INDEX(HIST_D!$AQ$8:$AQ$2617,Control!$F$8)/INDEX(HIST_D!$AQ$8:$AQ$2617,1)-1,"")+IFERROR(INDEX(HIST_D!$J$8:$J$2617,1)/INDEX(HIST_D!$J$8:$J$2617,Control!$F$8)-1,""),"") | L32: =IFERROR(IFERROR(INDEX(HIST_D!$AQ$8:$AQ$2617,Control!$F$9)/INDEX(HIST_D!$AQ$8:$AQ$2617,1)-1,"")+IFERROR(INDEX(HIST_D!$J$8:$J$2617,1)/INDEX(HIST_D!$J$8:$J$2617,Control!$F$9)-1,""),"") | M32: =IFERROR(IFERROR(INDEX(HIST_D!$AQ$8:$AQ$2617,Control!$F$16)/INDEX(HIST_D!$AQ$8:$AQ$2617,1)-1,"")+IFERROR(INDEX(HIST_D!$J$8:$J$2617,1)/INDEX(HIST_D!$J$8:$J$2617,Control!$F$16)-1,""),"") | N32: =IFERROR(PERCENTRANK(HIST_D!$AQ$8:INDEX(HIST_D!$AQ$8:$AQ$2617,Control!$F$11),INDEX(HIST_D!$AQ$8:$AQ$2617,1)),"") | O32: =IFERROR(PERCENTRANK(HIST_D!$AQ$8:INDEX(HIST_D!$AQ$8:$AQ$2617,Control!$F$14),INDEX(HIST_D!$AQ$8:$AQ$2617,1)),"")
A33: Middle East & Africa basket (floating, n=3) | D33: =IFERROR(AVERAGE(D27,D28,D29),"") | E33: =IFERROR(AVERAGE(E27,E28,E29),"") | F33: =IFERROR(AVERAGE(F27,F28,F29),"") | G33: =IFERROR(AVERAGE(G27,G28,G29),"") | H33: =IFERROR(AVERAGE(H27,H28,H29),"") | I33: =IFERROR(AVERAGE(I27,I28,I29),"") | J33: =IFERROR(AVERAGE(J27,J28,J29),"") | K33: =IFERROR(AVERAGE(K27,K28,K29),"") | ... O33: =IFERROR(AVERAGE(O27,O28,O29),"")
A34: =IFERROR("Middle East & Africa: "&TEXT($F$33,"+0.0%;-0.0%")&" on the month, "&TEXT($I$33,"+0.0%;-0.0%")&" YTD, "&TEXT($K$33,"+0.0%;-0.0%")&" ex-dollar. "&IF($F$33>$F$51,"Ahead of","Behind")&" the EM basket at "&TEXT($F$51,"+0.0%;-0.0%")&". "&IF($K$33>0.005,"Regional support beyond the dollar.",IF($K$33<-0.005,"Lagging even after adjusting for the dollar.","Tracking the dollar; no regional signal.")),"")
A36: ASIA
A37: Currency | B37: Peg | C37: Spot (EM/USD) | D37: 1D | E37: 1W | F37: 1M | G37: 3M | H37: 6M | I37: YTD | J37: 1Y | K37: 1M ex-USD | L37: 3M ex-USD | M37: YTD ex-USD | N37: %ile 1y (spot) | O37: %ile 5y (spot)
A38: China CNH | B38: float | C38: =INDEX(HIST_D!$AR$8:$AR$2617,1) | D38: =IFERROR(INDEX(HIST_D!$AR$8:$AR$2617,Control!$F$6)/INDEX(HIST_D!$AR$8:$AR$2617,1)-1,"") | E38: =IFERROR(INDEX(HIST_D!$AR$8:$AR$2617,Control!$F$7)/INDEX(HIST_D!$AR$8:$AR$2617,1)-1,"") | F38: =IFERROR(INDEX(HIST_D!$AR$8:$AR$2617,Control!$F$8)/INDEX(HIST_D!$AR$8:$AR$2617,1)-1,"") | G38: =IFERROR(INDEX(HIST_D!$AR$8:$AR$2617,Control!$F$9)/INDEX(HIST_D!$AR$8:$AR$2617,1)-1,"") | H38: =IFERROR(INDEX(HIST_D!$AR$8:$AR$2617,Control!$F$10)/INDEX(HIST_D!$AR$8:$AR$2617,1)-1,"") | I38: =IFERROR(INDEX(HIST_D!$AR$8:$AR$2617,Control!$F$16)/INDEX(HIST_D!$AR$8:$AR$2617,1)-1,"") | J38: =IFERROR(INDEX(HIST_D!$AR$8:$AR$2617,Control!$F$11)/INDEX(HIST_D!$AR$8:$AR$2617,1)-1,"") | K38: =IFERROR(IFERROR(INDEX(HIST_D!$AR$8:$AR$2617,Control!$F$8)/INDEX(HIST_D!$AR$8:$AR$2617,1)-1,"")+IFERROR(INDEX(HIST_D!$J$8:$J$2617,1)/INDEX(HIST_D!$J$8:$J$2617,Control!$F$8)-1,""),"") | L38: =IFERROR(IFERROR(INDEX(HIST_D!$AR$8:$AR$2617,Control!$F$9)/INDEX(HIST_D!$AR$8:$AR$2617,1)-1,"")+IFERROR(INDEX(HIST_D!$J$8:$J$2617,1)/INDEX(HIST_D!$J$8:$J$2617,Control!$F$9)-1,""),"") | M38: =IFERROR(IFERROR(INDEX(HIST_D!$AR$8:$AR$2617,Control!$F$16)/INDEX(HIST_D!$AR$8:$AR$2617,1)-1,"")+IFERROR(INDEX(HIST_D!$J$8:$J$2617,1)/INDEX(HIST_D!$J$8:$J$2617,Control!$F$16)-1,""),"") | N38: =IFERROR(PERCENTRANK(HIST_D!$AR$8:INDEX(HIST_D!$AR$8:$AR$2617,Control!$F$11),INDEX(HIST_D!$AR$8:$AR$2617,1)),"") | O38: =IFERROR(PERCENTRANK(HIST_D!$AR$8:INDEX(HIST_D!$AR$8:$AR$2617,Control!$F$14),INDEX(HIST_D!$AR$8:$AR$2617,1)),"")
A39: India INR | B39: float | C39: =INDEX(HIST_D!$AS$8:$AS$2617,1) | D39: =IFERROR(INDEX(HIST_D!$AS$8:$AS$2617,Control!$F$6)/INDEX(HIST_D!$AS$8:$AS$2617,1)-1,"") | E39: =IFERROR(INDEX(HIST_D!$AS$8:$AS$2617,Control!$F$7)/INDEX(HIST_D!$AS$8:$AS$2617,1)-1,"") | F39: =IFERROR(INDEX(HIST_D!$AS$8:$AS$2617,Control!$F$8)/INDEX(HIST_D!$AS$8:$AS$2617,1)-1,"") | G39: =IFERROR(INDEX(HIST_D!$AS$8:$AS$2617,Control!$F$9)/INDEX(HIST_D!$AS$8:$AS$2617,1)-1,"") | H39: =IFERROR(INDEX(HIST_D!$AS$8:$AS$2617,Control!$F$10)/INDEX(HIST_D!$AS$8:$AS$2617,1)-1,"") | I39: =IFERROR(INDEX(HIST_D!$AS$8:$AS$2617,Control!$F$16)/INDEX(HIST_D!$AS$8:$AS$2617,1)-1,"") | J39: =IFERROR(INDEX(HIST_D!$AS$8:$AS$2617,Control!$F$11)/INDEX(HIST_D!$AS$8:$AS$2617,1)-1,"") | K39: =IFERROR(IFERROR(INDEX(HIST_D!$AS$8:$AS$2617,Control!$F$8)/INDEX(HIST_D!$AS$8:$AS$2617,1)-1,"")+IFERROR(INDEX(HIST_D!$J$8:$J$2617,1)/INDEX(HIST_D!$J$8:$J$2617,Control!$F$8)-1,""),"") | L39: =IFERROR(IFERROR(INDEX(HIST_D!$AS$8:$AS$2617,Control!$F$9)/INDEX(HIST_D!$AS$8:$AS$2617,1)-1,"")+IFERROR(INDEX(HIST_D!$J$8:$J$2617,1)/INDEX(HIST_D!$J$8:$J$2617,Control!$F$9)-1,""),"") | M39: =IFERROR(IFERROR(INDEX(HIST_D!$AS$8:$AS$2617,Control!$F$16)/INDEX(HIST_D!$AS$8:$AS$2617,1)-1,"")+IFERROR(INDEX(HIST_D!$J$8:$J$2617,1)/INDEX(HIST_D!$J$8:$J$2617,Control!$F$16)-1,""),"") | N39: =IFERROR(PERCENTRANK(HIST_D!$AS$8:INDEX(HIST_D!$AS$8:$AS$2617,Control!$F$11),INDEX(HIST_D!$AS$8:$AS$2617,1)),"") | O39: =IFERROR(PERCENTRANK(HIST_D!$AS$8:INDEX(HIST_D!$AS$8:$AS$2617,Control!$F$14),INDEX(HIST_D!$AS$8:$AS$2617,1)),"")
A40: Indonesia IDR | B40: float | C40: =INDEX(HIST_D!$AT$8:$AT$2617,1) | D40: =IFERROR(INDEX(HIST_D!$AT$8:$AT$2617,Control!$F$6)/INDEX(HIST_D!$AT$8:$AT$2617,1)-1,"") | E40: =IFERROR(INDEX(HIST_D!$AT$8:$AT$2617,Control!$F$7)/INDEX(HIST_D!$AT$8:$AT$2617,1)-1,"") | F40: =IFERROR(INDEX(HIST_D!$AT$8:$AT$2617,Control!$F$8)/INDEX(HIST_D!$AT$8:$AT$2617,1)-1,"") | G40: =IFERROR(INDEX(HIST_D!$AT$8:$AT$2617,Control!$F$9)/INDEX(HIST_D!$AT$8:$AT$2617,1)-1,"") | H40: =IFERROR(INDEX(HIST_D!$AT$8:$AT$2617,Control!$F$10)/INDEX(HIST_D!$AT$8:$AT$2617,1)-1,"") | I40: =IFERROR(INDEX(HIST_D!$AT$8:$AT$2617,Control!$F$16)/INDEX(HIST_D!$AT$8:$AT$2617,1)-1,"") | J40: =IFERROR(INDEX(HIST_D!$AT$8:$AT$2617,Control!$F$11)/INDEX(HIST_D!$AT$8:$AT$2617,1)-1,"") | K40: =IFERROR(IFERROR(INDEX(HIST_D!$AT$8:$AT$2617,Control!$F$8)/INDEX(HIST_D!$AT$8:$AT$2617,1)-1,"")+IFERROR(INDEX(HIST_D!$J$8:$J$2617,1)/INDEX(HIST_D!$J$8:$J$2617,Control!$F$8)-1,""),"") | L40: =IFERROR(IFERROR(INDEX(HIST_D!$AT$8:$AT$2617,Control!$F$9)/INDEX(HIST_D!$AT$8:$AT$2617,1)-1,"")+IFERROR(INDEX(HIST_D!$J$8:$J$2617,1)/INDEX(HIST_D!$J$8:$J$2617,Control!$F$9)-1,""),"") | M40: =IFERROR(IFERROR(INDEX(HIST_D!$AT$8:$AT$2617,Control!$F$16)/INDEX(HIST_D!$AT$8:$AT$2617,1)-1,"")+IFERROR(INDEX(HIST_D!$J$8:$J$2617,1)/INDEX(HIST_D!$J$8:$J$2617,Control!$F$16)-1,""),"") | N40: =IFERROR(PERCENTRANK(HIST_D!$AT$8:INDEX(HIST_D!$AT$8:$AT$2617,Control!$F$11),INDEX(HIST_D!$AT$8:$AT$2617,1)),"") | O40: =IFERROR(PERCENTRANK(HIST_D!$AT$8:INDEX(HIST_D!$AT$8:$AT$2617,Control!$F$14),INDEX(HIST_D!$AT$8:$AT$2617,1)),"")
A41: Korea KRW | B41: float | C41: =INDEX(HIST_D!$AU$8:$AU$2617,1) | D41: =IFERROR(INDEX(HIST_D!$AU$8:$AU$2617,Control!$F$6)/INDEX(HIST_D!$AU$8:$AU$2617,1)-1,"") | E41: =IFERROR(INDEX(HIST_D!$AU$8:$AU$2617,Control!$F$7)/INDEX(HIST_D!$AU$8:$AU$2617,1)-1,"") | F41: =IFERROR(INDEX(HIST_D!$AU$8:$AU$2617,Control!$F$8)/INDEX(HIST_D!$AU$8:$AU$2617,1)-1,"") | G41: =IFERROR(INDEX(HIST_D!$AU$8:$AU$2617,Control!$F$9)/INDEX(HIST_D!$AU$8:$AU$2617,1)-1,"") | H41: =IFERROR(INDEX(HIST_D!$AU$8:$AU$2617,Control!$F$10)/INDEX(HIST_D!$AU$8:$AU$2617,1)-1,"") | I41: =IFERROR(INDEX(HIST_D!$AU$8:$AU$2617,Control!$F$16)/INDEX(HIST_D!$AU$8:$AU$2617,1)-1,"") | J41: =IFERROR(INDEX(HIST_D!$AU$8:$AU$2617,Control!$F$11)/INDEX(HIST_D!$AU$8:$AU$2617,1)-1,"") | K41: =IFERROR(IFERROR(INDEX(HIST_D!$AU$8:$AU$2617,Control!$F$8)/INDEX(HIST_D!$AU$8:$AU$2617,1)-1,"")+IFERROR(INDEX(HIST_D!$J$8:$J$2617,1)/INDEX(HIST_D!$J$8:$J$2617,Control!$F$8)-1,""),"") | L41: =IFERROR(IFERROR(INDEX(HIST_D!$AU$8:$AU$2617,Control!$F$9)/INDEX(HIST_D!$AU$8:$AU$2617,1)-1,"")+IFERROR(INDEX(HIST_D!$J$8:$J$2617,1)/INDEX(HIST_D!$J$8:$J$2617,Control!$F$9)-1,""),"") | M41: =IFERROR(IFERROR(INDEX(HIST_D!$AU$8:$AU$2617,Control!$F$16)/INDEX(HIST_D!$AU$8:$AU$2617,1)-1,"")+IFERROR(INDEX(HIST_D!$J$8:$J$2617,1)/INDEX(HIST_D!$J$8:$J$2617,Control!$F$16)-1,""),"") | N41: =IFERROR(PERCENTRANK(HIST_D!$AU$8:INDEX(HIST_D!$AU$8:$AU$2617,Control!$F$11),INDEX(HIST_D!$AU$8:$AU$2617,1)),"") | O41: =IFERROR(PERCENTRANK(HIST_D!$AU$8:INDEX(HIST_D!$AU$8:$AU$2617,Control!$F$14),INDEX(HIST_D!$AU$8:$AU$2617,1)),"")
A42: Taiwan TWD | B42: float | C42: =INDEX(HIST_D!$AV$8:$AV$2617,1) | D42: =IFERROR(INDEX(HIST_D!$AV$8:$AV$2617,Control!$F$6)/INDEX(HIST_D!$AV$8:$AV$2617,1)-1,"") | E42: =IFERROR(INDEX(HIST_D!$AV$8:$AV$2617,Control!$F$7)/INDEX(HIST_D!$AV$8:$AV$2617,1)-1,"") | F42: =IFERROR(INDEX(HIST_D!$AV$8:$AV$2617,Control!$F$8)/INDEX(HIST_D!$AV$8:$AV$2617,1)-1,"") | G42: =IFERROR(INDEX(HIST_D!$AV$8:$AV$2617,Control!$F$9)/INDEX(HIST_D!$AV$8:$AV$2617,1)-1,"") | H42: =IFERROR(INDEX(HIST_D!$AV$8:$AV$2617,Control!$F$10)/INDEX(HIST_D!$AV$8:$AV$2617,1)-1,"") | I42: =IFERROR(INDEX(HIST_D!$AV$8:$AV$2617,Control!$F$16)/INDEX(HIST_D!$AV$8:$AV$2617,1)-1,"") | J42: =IFERROR(INDEX(HIST_D!$AV$8:$AV$2617,Control!$F$11)/INDEX(HIST_D!$AV$8:$AV$2617,1)-1,"") | K42: =IFERROR(IFERROR(INDEX(HIST_D!$AV$8:$AV$2617,Control!$F$8)/INDEX(HIST_D!$AV$8:$AV$2617,1)-1,"")+IFERROR(INDEX(HIST_D!$J$8:$J$2617,1)/INDEX(HIST_D!$J$8:$J$2617,Control!$F$8)-1,""),"") | L42: =IFERROR(IFERROR(INDEX(HIST_D!$AV$8:$AV$2617,Control!$F$9)/INDEX(HIST_D!$AV$8:$AV$2617,1)-1,"")+IFERROR(INDEX(HIST_D!$J$8:$J$2617,1)/INDEX(HIST_D!$J$8:$J$2617,Control!$F$9)-1,""),"") | M42: =IFERROR(IFERROR(INDEX(HIST_D!$AV$8:$AV$2617,Control!$F$16)/INDEX(HIST_D!$AV$8:$AV$2617,1)-1,"")+IFERROR(INDEX(HIST_D!$J$8:$J$2617,1)/INDEX(HIST_D!$J$8:$J$2617,Control!$F$16)-1,""),"") | N42: =IFERROR(PERCENTRANK(HIST_D!$AV$8:INDEX(HIST_D!$AV$8:$AV$2617,Control!$F$11),INDEX(HIST_D!$AV$8:$AV$2617,1)),"") | O42: =IFERROR(PERCENTRANK(HIST_D!$AV$8:INDEX(HIST_D!$AV$8:$AV$2617,Control!$F$14),INDEX(HIST_D!$AV$8:$AV$2617,1)),"")
A43: Thailand THB | B43: float | C43: =INDEX(HIST_D!$AW$8:$AW$2617,1) | D43: =IFERROR(INDEX(HIST_D!$AW$8:$AW$2617,Control!$F$6)/INDEX(HIST_D!$AW$8:$AW$2617,1)-1,"") | E43: =IFERROR(INDEX(HIST_D!$AW$8:$AW$2617,Control!$F$7)/INDEX(HIST_D!$AW$8:$AW$2617,1)-1,"") | F43: =IFERROR(INDEX(HIST_D!$AW$8:$AW$2617,Control!$F$8)/INDEX(HIST_D!$AW$8:$AW$2617,1)-1,"") | G43: =IFERROR(INDEX(HIST_D!$AW$8:$AW$2617,Control!$F$9)/INDEX(HIST_D!$AW$8:$AW$2617,1)-1,"") | H43: =IFERROR(INDEX(HIST_D!$AW$8:$AW$2617,Control!$F$10)/INDEX(HIST_D!$AW$8:$AW$2617,1)-1,"") | I43: =IFERROR(INDEX(HIST_D!$AW$8:$AW$2617,Control!$F$16)/INDEX(HIST_D!$AW$8:$AW$2617,1)-1,"") | J43: =IFERROR(INDEX(HIST_D!$AW$8:$AW$2617,Control!$F$11)/INDEX(HIST_D!$AW$8:$AW$2617,1)-1,"") | K43: =IFERROR(IFERROR(INDEX(HIST_D!$AW$8:$AW$2617,Control!$F$8)/INDEX(HIST_D!$AW$8:$AW$2617,1)-1,"")+IFERROR(INDEX(HIST_D!$J$8:$J$2617,1)/INDEX(HIST_D!$J$8:$J$2617,Control!$F$8)-1,""),"") | L43: =IFERROR(IFERROR(INDEX(HIST_D!$AW$8:$AW$2617,Control!$F$9)/INDEX(HIST_D!$AW$8:$AW$2617,1)-1,"")+IFERROR(INDEX(HIST_D!$J$8:$J$2617,1)/INDEX(HIST_D!$J$8:$J$2617,Control!$F$9)-1,""),"") | M43: =IFERROR(IFERROR(INDEX(HIST_D!$AW$8:$AW$2617,Control!$F$16)/INDEX(HIST_D!$AW$8:$AW$2617,1)-1,"")+IFERROR(INDEX(HIST_D!$J$8:$J$2617,1)/INDEX(HIST_D!$J$8:$J$2617,Control!$F$16)-1,""),"") | N43: =IFERROR(PERCENTRANK(HIST_D!$AW$8:INDEX(HIST_D!$AW$8:$AW$2617,Control!$F$11),INDEX(HIST_D!$AW$8:$AW$2617,1)),"") | O43: =IFERROR(PERCENTRANK(HIST_D!$AW$8:INDEX(HIST_D!$AW$8:$AW$2617,Control!$F$14),INDEX(HIST_D!$AW$8:$AW$2617,1)),"")
A44: Philippines PHP | B44: float | C44: =INDEX(HIST_D!$AX$8:$AX$2617,1) | D44: =IFERROR(INDEX(HIST_D!$AX$8:$AX$2617,Control!$F$6)/INDEX(HIST_D!$AX$8:$AX$2617,1)-1,"") | E44: =IFERROR(INDEX(HIST_D!$AX$8:$AX$2617,Control!$F$7)/INDEX(HIST_D!$AX$8:$AX$2617,1)-1,"") | F44: =IFERROR(INDEX(HIST_D!$AX$8:$AX$2617,Control!$F$8)/INDEX(HIST_D!$AX$8:$AX$2617,1)-1,"") | G44: =IFERROR(INDEX(HIST_D!$AX$8:$AX$2617,Control!$F$9)/INDEX(HIST_D!$AX$8:$AX$2617,1)-1,"") | H44: =IFERROR(INDEX(HIST_D!$AX$8:$AX$2617,Control!$F$10)/INDEX(HIST_D!$AX$8:$AX$2617,1)-1,"") | I44: =IFERROR(INDEX(HIST_D!$AX$8:$AX$2617,Control!$F$16)/INDEX(HIST_D!$AX$8:$AX$2617,1)-1,"") | J44: =IFERROR(INDEX(HIST_D!$AX$8:$AX$2617,Control!$F$11)/INDEX(HIST_D!$AX$8:$AX$2617,1)-1,"") | K44: =IFERROR(IFERROR(INDEX(HIST_D!$AX$8:$AX$2617,Control!$F$8)/INDEX(HIST_D!$AX$8:$AX$2617,1)-1,"")+IFERROR(INDEX(HIST_D!$J$8:$J$2617,1)/INDEX(HIST_D!$J$8:$J$2617,Control!$F$8)-1,""),"") | L44: =IFERROR(IFERROR(INDEX(HIST_D!$AX$8:$AX$2617,Control!$F$9)/INDEX(HIST_D!$AX$8:$AX$2617,1)-1,"")+IFERROR(INDEX(HIST_D!$J$8:$J$2617,1)/INDEX(HIST_D!$J$8:$J$2617,Control!$F$9)-1,""),"") | M44: =IFERROR(IFERROR(INDEX(HIST_D!$AX$8:$AX$2617,Control!$F$16)/INDEX(HIST_D!$AX$8:$AX$2617,1)-1,"")+IFERROR(INDEX(HIST_D!$J$8:$J$2617,1)/INDEX(HIST_D!$J$8:$J$2617,Control!$F$16)-1,""),"") | N44: =IFERROR(PERCENTRANK(HIST_D!$AX$8:INDEX(HIST_D!$AX$8:$AX$2617,Control!$F$11),INDEX(HIST_D!$AX$8:$AX$2617,1)),"") | O44: =IFERROR(PERCENTRANK(HIST_D!$AX$8:INDEX(HIST_D!$AX$8:$AX$2617,Control!$F$14),INDEX(HIST_D!$AX$8:$AX$2617,1)),"")
A45: Malaysia MYR | B45: float | C45: =INDEX(HIST_D!$AY$8:$AY$2617,1) | D45: =IFERROR(INDEX(HIST_D!$AY$8:$AY$2617,Control!$F$6)/INDEX(HIST_D!$AY$8:$AY$2617,1)-1,"") | E45: =IFERROR(INDEX(HIST_D!$AY$8:$AY$2617,Control!$F$7)/INDEX(HIST_D!$AY$8:$AY$2617,1)-1,"") | F45: =IFERROR(INDEX(HIST_D!$AY$8:$AY$2617,Control!$F$8)/INDEX(HIST_D!$AY$8:$AY$2617,1)-1,"") | G45: =IFERROR(INDEX(HIST_D!$AY$8:$AY$2617,Control!$F$9)/INDEX(HIST_D!$AY$8:$AY$2617,1)-1,"") | H45: =IFERROR(INDEX(HIST_D!$AY$8:$AY$2617,Control!$F$10)/INDEX(HIST_D!$AY$8:$AY$2617,1)-1,"") | I45: =IFERROR(INDEX(HIST_D!$AY$8:$AY$2617,Control!$F$16)/INDEX(HIST_D!$AY$8:$AY$2617,1)-1,"") | J45: =IFERROR(INDEX(HIST_D!$AY$8:$AY$2617,Control!$F$11)/INDEX(HIST_D!$AY$8:$AY$2617,1)-1,"") | K45: =IFERROR(IFERROR(INDEX(HIST_D!$AY$8:$AY$2617,Control!$F$8)/INDEX(HIST_D!$AY$8:$AY$2617,1)-1,"")+IFERROR(INDEX(HIST_D!$J$8:$J$2617,1)/INDEX(HIST_D!$J$8:$J$2617,Control!$F$8)-1,""),"") | L45: =IFERROR(IFERROR(INDEX(HIST_D!$AY$8:$AY$2617,Control!$F$9)/INDEX(HIST_D!$AY$8:$AY$2617,1)-1,"")+IFERROR(INDEX(HIST_D!$J$8:$J$2617,1)/INDEX(HIST_D!$J$8:$J$2617,Control!$F$9)-1,""),"") | M45: =IFERROR(IFERROR(INDEX(HIST_D!$AY$8:$AY$2617,Control!$F$16)/INDEX(HIST_D!$AY$8:$AY$2617,1)-1,"")+IFERROR(INDEX(HIST_D!$J$8:$J$2617,1)/INDEX(HIST_D!$J$8:$J$2617,Control!$F$16)-1,""),"") | N45: =IFERROR(PERCENTRANK(HIST_D!$AY$8:INDEX(HIST_D!$AY$8:$AY$2617,Control!$F$11),INDEX(HIST_D!$AY$8:$AY$2617,1)),"") | O45: =IFERROR(PERCENTRANK(HIST_D!$AY$8:INDEX(HIST_D!$AY$8:$AY$2617,Control!$F$14),INDEX(HIST_D!$AY$8:$AY$2617,1)),"")
A46: Asia basket (floating, n=8) | D46: =IFERROR(AVERAGE(D38,D39,D40,D41,D42,D43,D44,D45),"") | E46: =IFERROR(AVERAGE(E38,E39,E40,E41,E42,E43,E44,E45),"") | F46: =IFERROR(AVERAGE(F38,F39,F40,F41,F42,F43,F44,F45),"") | G46: =IFERROR(AVERAGE(G38,G39,G40,G41,G42,G43,G44,G45),"") | H46: =IFERROR(AVERAGE(H38,H39,H40,H41,H42,H43,H44,H45),"") | I46: =IFERROR(AVERAGE(I38,I39,I40,I41,I42,I43,I44,I45),"") | J46: =IFERROR(AVERAGE(J38,J39,J40,J41,J42,J43,J44,J45),"") | K46: =IFERROR(AVERAGE(K38,K39,K40,K41,K42,K43,K44,K45),"") | ... O46: =IFERROR(AVERAGE(O38,O39,O40,O41,O42,O43,O44,O45),"")
A47: =IFERROR("Asia: "&TEXT($F$46,"+0.0%;-0.0%")&" on the month, "&TEXT($I$46,"+0.0%;-0.0%")&" YTD, "&TEXT($K$46,"+0.0%;-0.0%")&" ex-dollar. "&IF($F$46>$F$51,"Ahead of","Behind")&" the EM basket at "&TEXT($F$51,"+0.0%;-0.0%")&". "&IF($K$46>0.005,"Regional support beyond the dollar.",IF($K$46<-0.005,"Lagging even after adjusting for the dollar.","Tracking the dollar; no regional signal.")),"")
A49: EM AGGREGATE
A50: Basket | D50: 1D | E50: 1W | F50: 1M | G50: 3M | H50: 6M | I50: YTD | J50: 1Y | K50: 1M ex-USD | L50: 3M ex-USD | M50: YTD ex-USD | N50: %ile 1y | O50: %ile 5y
A51: EM basket — floating, ex ARS/TRY/EGP | B51: n=19 | D51: =IFERROR(AVERAGE(D6,D7,D8,D9,D10,D17,D18,D19,D20,D27,D28,D38,D39,D40,D41,D42,D43,D44,D45),"") | E51: =IFERROR(AVERAGE(E6,E7,E8,E9,E10,E17,E18,E19,E20,E27,E28,E38,E39,E40,E41,E42,E43,E44,E45),"") | F51: =IFERROR(AVERAGE(F6,F7,F8,F9,F10,F17,F18,F19,F20,F27,F28,F38,F39,F40,F41,F42,F43,F44,F45),"") | G51: =IFERROR(AVERAGE(G6,G7,G8,G9,G10,G17,G18,G19,G20,G27,G28,G38,G39,G40,G41,G42,G43,G44,G45),"") | H51: =IFERROR(AVERAGE(H6,H7,H8,H9,H10,H17,H18,H19,H20,H27,H28,H38,H39,H40,H41,H42,H43,H44,H45),"") | I51: =IFERROR(AVERAGE(I6,I7,I8,I9,I10,I17,I18,I19,I20,I27,I28,I38,I39,I40,I41,I42,I43,I44,I45),"") | J51: =IFERROR(AVERAGE(J6,J7,J8,J9,J10,J17,J18,J19,J20,J27,J28,J38,J39,J40,J41,J42,J43,J44,J45),"") | K51: =IFERROR(AVERAGE(K6,K7,K8,K9,K10,K17,K18,K19,K20,K27,K28,K38,K39,K40,K41,K42,K43,K44,K45),"") | ... O51: =IFERROR(AVERAGE(O6,O7,O8,O9,O10,O17,O18,O19,O20,O27,O28,O38,O39,O40,O41,O42,O43,O44,O45),"")
A52: EM basket — all floating | B52: n=22 | D52: =IFERROR(AVERAGE(D6,D7,D8,D9,D10,D11,D17,D18,D19,D20,D21,D27,D28,D29,D38,D39,D40,D41,D42,D43,D44,D45),"") | E52: =IFERROR(AVERAGE(E6,E7,E8,E9,E10,E11,E17,E18,E19,E20,E21,E27,E28,E29,E38,E39,E40,E41,E42,E43,E44,E45),"") | F52: =IFERROR(AVERAGE(F6,F7,F8,F9,F10,F11,F17,F18,F19,F20,F21,F27,F28,F29,F38,F39,F40,F41,F42,F43,F44,F45),"") | G52: =IFERROR(AVERAGE(G6,G7,G8,G9,G10,G11,G17,G18,G19,G20,G21,G27,G28,G29,G38,G39,G40,G41,G42,G43,G44,G45),"") | H52: =IFERROR(AVERAGE(H6,H7,H8,H9,H10,H11,H17,H18,H19,H20,H21,H27,H28,H29,H38,H39,H40,H41,H42,H43,H44,H45),"") | I52: =IFERROR(AVERAGE(I6,I7,I8,I9,I10,I11,I17,I18,I19,I20,I21,I27,I28,I29,I38,I39,I40,I41,I42,I43,I44,I45),"") | J52: =IFERROR(AVERAGE(J6,J7,J8,J9,J10,J11,J17,J18,J19,J20,J21,J27,J28,J29,J38,J39,J40,J41,J42,J43,J44,J45),"") | K52: =IFERROR(AVERAGE(K6,K7,K8,K9,K10,K11,K17,K18,K19,K20,K21,K27,K28,K29,K38,K39,K40,K41,K42,K43,K44,K45),"") | ... O52: =IFERROR(AVERAGE(O6,O7,O8,O9,O10,O11,O17,O18,O19,O20,O21,O27,O28,O29,O38,O39,O40,O41,O42,O43,O44,O45),"")
A53: High-beta (BRL MXN ZAR COP IDR) | B53: n=5 | D53: =IFERROR(AVERAGE(D6,D7,D28,D9,D40),"") | E53: =IFERROR(AVERAGE(E6,E7,E28,E9,E40),"") | F53: =IFERROR(AVERAGE(F6,F7,F28,F9,F40),"") | G53: =IFERROR(AVERAGE(G6,G7,G28,G9,G40),"") | H53: =IFERROR(AVERAGE(H6,H7,H28,H9,H40),"") | I53: =IFERROR(AVERAGE(I6,I7,I28,I9,I40),"") | J53: =IFERROR(AVERAGE(J6,J7,J28,J9,J40),"") | K53: =IFERROR(AVERAGE(K6,K7,K28,K9,K40),"") | ... O53: =IFERROR(AVERAGE(O6,O7,O28,O9,O40),"")
A54: Pegs (SAR, AED, QAR) are excluded from every basket: their return is zero by construction, so including them would understate the dispersion that matters. ARS, TRY and EGP are excluded from the headline for the opposite reason — a structural depreciation trend that swamps an equal-weighted average.
A56: THE DOLLAR AND FX VOLATILITY — is this being priced as a risk event?
A57: Series | B57: Unit | C57: Level | D57: 1D | E57: 1W | F57: 1M | G57: 3M | H57: 6M | I57: YTD | J57: 1Y | N57: %ile 1y | O57: %ile 5y
A58: DXY (rise = USD strength) | B58: pt | C58: =INDEX(HIST_D!$J$8:$J$2617,1) | D58: =IFERROR(IFERROR(INDEX(HIST_D!$J$8:$J$2617,1)/INDEX(HIST_D!$J$8:$J$2617,Control!$F$6)-1,""),"") | E58: =IFERROR(IFERROR(INDEX(HIST_D!$J$8:$J$2617,1)/INDEX(HIST_D!$J$8:$J$2617,Control!$F$7)-1,""),"") | F58: =IFERROR(IFERROR(INDEX(HIST_D!$J$8:$J$2617,1)/INDEX(HIST_D!$J$8:$J$2617,Control!$F$8)-1,""),"") | G58: =IFERROR(IFERROR(INDEX(HIST_D!$J$8:$J$2617,1)/INDEX(HIST_D!$J$8:$J$2617,Control!$F$9)-1,""),"") | H58: =IFERROR(IFERROR(INDEX(HIST_D!$J$8:$J$2617,1)/INDEX(HIST_D!$J$8:$J$2617,Control!$F$10)-1,""),"") | I58: =IFERROR(IFERROR(INDEX(HIST_D!$J$8:$J$2617,1)/INDEX(HIST_D!$J$8:$J$2617,Control!$F$16)-1,""),"") | J58: =IFERROR(IFERROR(INDEX(HIST_D!$J$8:$J$2617,1)/INDEX(HIST_D!$J$8:$J$2617,Control!$F$11)-1,""),"") | N58: =IFERROR(PERCENTRANK(HIST_D!$J$8:INDEX(HIST_D!$J$8:$J$2617,Control!$F$11),INDEX(HIST_D!$J$8:$J$2617,1)),"") | O58: =IFERROR(PERCENTRANK(HIST_D!$J$8:INDEX(HIST_D!$J$8:$J$2617,Control!$F$14),INDEX(HIST_D!$J$8:$J$2617,1)),"")
A59: Asia Dollar Index (rise = Asia strength) | B59: idx | C59: =INDEX(HIST_D!$X$8:$X$2617,1) | D59: =IFERROR(IFERROR(INDEX(HIST_D!$X$8:$X$2617,1)/INDEX(HIST_D!$X$8:$X$2617,Control!$F$6)-1,""),"") | E59: =IFERROR(IFERROR(INDEX(HIST_D!$X$8:$X$2617,1)/INDEX(HIST_D!$X$8:$X$2617,Control!$F$7)-1,""),"") | F59: =IFERROR(IFERROR(INDEX(HIST_D!$X$8:$X$2617,1)/INDEX(HIST_D!$X$8:$X$2617,Control!$F$8)-1,""),"") | G59: =IFERROR(IFERROR(INDEX(HIST_D!$X$8:$X$2617,1)/INDEX(HIST_D!$X$8:$X$2617,Control!$F$9)-1,""),"") | H59: =IFERROR(IFERROR(INDEX(HIST_D!$X$8:$X$2617,1)/INDEX(HIST_D!$X$8:$X$2617,Control!$F$10)-1,""),"") | I59: =IFERROR(IFERROR(INDEX(HIST_D!$X$8:$X$2617,1)/INDEX(HIST_D!$X$8:$X$2617,Control!$F$16)-1,""),"") | J59: =IFERROR(IFERROR(INDEX(HIST_D!$X$8:$X$2617,1)/INDEX(HIST_D!$X$8:$X$2617,Control!$F$11)-1,""),"") | N59: =IFERROR(PERCENTRANK(HIST_D!$X$8:INDEX(HIST_D!$X$8:$X$2617,Control!$F$11),INDEX(HIST_D!$X$8:$X$2617,1)),"") | O59: =IFERROR(PERCENTRANK(HIST_D!$X$8:INDEX(HIST_D!$X$8:$X$2617,Control!$F$14),INDEX(HIST_D!$X$8:$X$2617,1)),"")
A60: JPM EM FX implied vol, 3m | B60: pt | C60: =INDEX(HIST_D!$Y$8:$Y$2617,1) | D60: =IFERROR(INDEX(HIST_D!$Y$8:$Y$2617,1)-INDEX(HIST_D!$Y$8:$Y$2617,Control!$F$6),"") | E60: =IFERROR(INDEX(HIST_D!$Y$8:$Y$2617,1)-INDEX(HIST_D!$Y$8:$Y$2617,Control!$F$7),"") | F60: =IFERROR(INDEX(HIST_D!$Y$8:$Y$2617,1)-INDEX(HIST_D!$Y$8:$Y$2617,Control!$F$8),"") | G60: =IFERROR(INDEX(HIST_D!$Y$8:$Y$2617,1)-INDEX(HIST_D!$Y$8:$Y$2617,Control!$F$9),"") | H60: =IFERROR(INDEX(HIST_D!$Y$8:$Y$2617,1)-INDEX(HIST_D!$Y$8:$Y$2617,Control!$F$10),"") | I60: =IFERROR(INDEX(HIST_D!$Y$8:$Y$2617,1)-INDEX(HIST_D!$Y$8:$Y$2617,Control!$F$16),"") | J60: =IFERROR(INDEX(HIST_D!$Y$8:$Y$2617,1)-INDEX(HIST_D!$Y$8:$Y$2617,Control!$F$11),"") | N60: =IFERROR(PERCENTRANK(HIST_D!$Y$8:INDEX(HIST_D!$Y$8:$Y$2617,Control!$F$11),INDEX(HIST_D!$Y$8:$Y$2617,1)),"") | O60: =IFERROR(PERCENTRANK(HIST_D!$Y$8:INDEX(HIST_D!$Y$8:$Y$2617,Control!$F$14),INDEX(HIST_D!$Y$8:$Y$2617,1)),"")
A61: JPM G7 FX implied vol, 3m | B61: pt | C61: =INDEX(HIST_D!$Z$8:$Z$2617,1) | D61: =IFERROR(INDEX(HIST_D!$Z$8:$Z$2617,1)-INDEX(HIST_D!$Z$8:$Z$2617,Control!$F$6),"") | E61: =IFERROR(INDEX(HIST_D!$Z$8:$Z$2617,1)-INDEX(HIST_D!$Z$8:$Z$2617,Control!$F$7),"") | F61: =IFERROR(INDEX(HIST_D!$Z$8:$Z$2617,1)-INDEX(HIST_D!$Z$8:$Z$2617,Control!$F$8),"") | G61: =IFERROR(INDEX(HIST_D!$Z$8:$Z$2617,1)-INDEX(HIST_D!$Z$8:$Z$2617,Control!$F$9),"") | H61: =IFERROR(INDEX(HIST_D!$Z$8:$Z$2617,1)-INDEX(HIST_D!$Z$8:$Z$2617,Control!$F$10),"") | I61: =IFERROR(INDEX(HIST_D!$Z$8:$Z$2617,1)-INDEX(HIST_D!$Z$8:$Z$2617,Control!$F$16),"") | J61: =IFERROR(INDEX(HIST_D!$Z$8:$Z$2617,1)-INDEX(HIST_D!$Z$8:$Z$2617,Control!$F$11),"") | N61: =IFERROR(PERCENTRANK(HIST_D!$Z$8:INDEX(HIST_D!$Z$8:$Z$2617,Control!$F$11),INDEX(HIST_D!$Z$8:$Z$2617,1)),"") | O61: =IFERROR(PERCENTRANK(HIST_D!$Z$8:INDEX(HIST_D!$Z$8:$Z$2617,Control!$F$14),INDEX(HIST_D!$Z$8:$Z$2617,1)),"")
A62: EM less G7 implied vol | B62: pt | C62: =IFERROR(INDEX(HIST_D!$Y$8:$Y$2617,1)-INDEX(HIST_D!$Z$8:$Z$2617,1),"") | D62: =IFERROR((INDEX(HIST_D!$Y$8:$Y$2617,1)-INDEX(HIST_D!$Z$8:$Z$2617,1))-(INDEX(HIST_D!$Y$8:$Y$2617,Control!$F$6)-INDEX(HIST_D!$Z$8:$Z$2617,Control!$F$6)),"") | E62: =IFERROR((INDEX(HIST_D!$Y$8:$Y$2617,1)-INDEX(HIST_D!$Z$8:$Z$2617,1))-(INDEX(HIST_D!$Y$8:$Y$2617,Control!$F$7)-INDEX(HIST_D!$Z$8:$Z$2617,Control!$F$7)),"") | F62: =IFERROR((INDEX(HIST_D!$Y$8:$Y$2617,1)-INDEX(HIST_D!$Z$8:$Z$2617,1))-(INDEX(HIST_D!$Y$8:$Y$2617,Control!$F$8)-INDEX(HIST_D!$Z$8:$Z$2617,Control!$F$8)),"") | G62: =IFERROR((INDEX(HIST_D!$Y$8:$Y$2617,1)-INDEX(HIST_D!$Z$8:$Z$2617,1))-(INDEX(HIST_D!$Y$8:$Y$2617,Control!$F$9)-INDEX(HIST_D!$Z$8:$Z$2617,Control!$F$9)),"") | H62: =IFERROR((INDEX(HIST_D!$Y$8:$Y$2617,1)-INDEX(HIST_D!$Z$8:$Z$2617,1))-(INDEX(HIST_D!$Y$8:$Y$2617,Control!$F$10)-INDEX(HIST_D!$Z$8:$Z$2617,Control!$F$10)),"") | I62: =IFERROR((INDEX(HIST_D!$Y$8:$Y$2617,1)-INDEX(HIST_D!$Z$8:$Z$2617,1))-(INDEX(HIST_D!$Y$8:$Y$2617,Control!$F$16)-INDEX(HIST_D!$Z$8:$Z$2617,Control!$F$16)),"") | J62: =IFERROR((INDEX(HIST_D!$Y$8:$Y$2617,1)-INDEX(HIST_D!$Z$8:$Z$2617,1))-(INDEX(HIST_D!$Y$8:$Y$2617,Control!$F$11)-INDEX(HIST_D!$Z$8:$Z$2617,Control!$F$11)),"")
A64: COMMENT — FX
A65: =IFERROR("EM FX: the basket is "&TEXT($F$51,"+0.0%;-0.0%")&" on the month against a dollar that is "&TEXT($F$58,"+0.0%;-0.0%")&". "&IF(AND($F$58>0,$F$51>-0.005),"EM FX is holding with the dollar firmer, which is the decoupling result — the funding channel is not transmitting.",IF(AND($F$58<0,$F$51>0),"EM FX is up on a softer dollar, so most of the move is dollar beta rather than EM-specific strength — check the ex-USD columns before claiming resilience.","EM FX is losing ground; the funding channel is engaging and the pass-through ratios on Passthrough are the thing to watch."))&" EM less G7 implied vol is "&TEXT($C$62,"0.0")&"pt, "&IF($F$62>0,"widening","narrowing")&" over the month — "&IF($F$62>0,"the option market is starting to charge for EM risk.","the option market is not charging for EM risk."),"")
A67: Dispersion, not level, is the regional story: the ex-USD columns are what separate a market that is being rewarded from one that is simply long the dollar trade.

Sheet Equities
A1: EM EQUITIES — by region. Local return and the FX leg, kept apart.
A2: Country indices are local currency. The FX column is the return on that currency vs USD over the same window. USD return = (1 + local)*(1 + FX) - 1, so both legs stay visible instead of being netted before you see them. GCC indices carry a pegged FX leg, so their local and USD returns are the same number by construction.
A4: BENCHMARKS
A5: Index | B5: Ccy | C5: Level | D5: 1M local | E5: 1M FX | F5: 1M USD | G5: 3M local | H5: 3M FX | I5: 3M USD | J5: YTD local | K5: YTD FX | L5: YTD USD | M5: 1Y USD | N5: vs World 1M | O5: vs World YTD
A6: MSCI EM (USD) | B6: USD | C6: =INDEX(HIST_D!$AZ$8:$AZ$2617,1) | D6: =IFERROR(INDEX(HIST_D!$AZ$8:$AZ$2617,1)/INDEX(HIST_D!$AZ$8:$AZ$2617,Control!$F$8)-1,"") | E6: — | F6: =D6 | G6: =IFERROR(INDEX(HIST_D!$AZ$8:$AZ$2617,1)/INDEX(HIST_D!$AZ$8:$AZ$2617,Control!$F$9)-1,"") | H6: — | I6: =G6 | J6: =IFERROR(INDEX(HIST_D!$AZ$8:$AZ$2617,1)/INDEX(HIST_D!$AZ$8:$AZ$2617,Control!$F$16)-1,"") | K6: — | L6: =J6 | M6: =IFERROR(INDEX(HIST_D!$AZ$8:$AZ$2617,1)/INDEX(HIST_D!$AZ$8:$AZ$2617,Control!$F$11)-1,"") | N6: =IFERROR(F6-F7,"") | O6: =IFERROR(L6-L7,"")
A7: MSCI World (USD) | B7: USD | C7: =INDEX(HIST_D!$BA$8:$BA$2617,1) | D7: =IFERROR(INDEX(HIST_D!$BA$8:$BA$2617,1)/INDEX(HIST_D!$BA$8:$BA$2617,Control!$F$8)-1,"") | E7: — | F7: =D7 | G7: =IFERROR(INDEX(HIST_D!$BA$8:$BA$2617,1)/INDEX(HIST_D!$BA$8:$BA$2617,Control!$F$9)-1,"") | H7: — | I7: =G7 | J7: =IFERROR(INDEX(HIST_D!$BA$8:$BA$2617,1)/INDEX(HIST_D!$BA$8:$BA$2617,Control!$F$16)-1,"") | K7: — | L7: =J7 | M7: =IFERROR(INDEX(HIST_D!$BA$8:$BA$2617,1)/INDEX(HIST_D!$BA$8:$BA$2617,Control!$F$11)-1,"") | N7: =IFERROR(F7-F7,"") | O7: =IFERROR(L7-L7,"")
A9: LATAM
A10: Index | B10: Ccy | C10: Level | D10: 1M local | E10: 1M FX | F10: 1M USD | G10: 3M local | H10: 3M FX | I10: 3M USD | J10: YTD local | K10: YTD FX | L10: YTD USD | M10: 1Y USD | N10: vs World 1M | O10: vs World YTD
A11: Brazil Ibovespa | B11: BRL | C11: =INDEX(HIST_D!$BB$8:$BB$2617,1) | D11: =IFERROR(INDEX(HIST_D!$BB$8:$BB$2617,1)/INDEX(HIST_D!$BB$8:$BB$2617,Control!$F$8)-1,"") | E11: =IFERROR(INDEX(HIST_D!$AA$8:$AA$2617,Control!$F$8)/INDEX(HIST_D!$AA$8:$AA$2617,1)-1,"") | F11: =IFERROR((1+D11)*(1+E11)-1,"") | G11: =IFERROR(INDEX(HIST_D!$BB$8:$BB$2617,1)/INDEX(HIST_D!$BB$8:$BB$2617,Control!$F$9)-1,"") | H11: =IFERROR(INDEX(HIST_D!$AA$8:$AA$2617,Control!$F$9)/INDEX(HIST_D!$AA$8:$AA$2617,1)-1,"") | I11: =IFERROR((1+G11)*(1+H11)-1,"") | J11: =IFERROR(INDEX(HIST_D!$BB$8:$BB$2617,1)/INDEX(HIST_D!$BB$8:$BB$2617,Control!$F$16)-1,"") | K11: =IFERROR(INDEX(HIST_D!$AA$8:$AA$2617,Control!$F$16)/INDEX(HIST_D!$AA$8:$AA$2617,1)-1,"") | L11: =IFERROR((1+J11)*(1+K11)-1,"") | M11: =IFERROR((1+IFERROR(INDEX(HIST_D!$BB$8:$BB$2617,1)/INDEX(HIST_D!$BB$8:$BB$2617,Control!$F$11)-1,""))*(1+IFERROR(INDEX(HIST_D!$AA$8:$AA$2617,Control!$F$11)/INDEX(HIST_D!$AA$8:$AA$2617,1)-1,""))-1,"") | N11: =IFERROR(F11-F7,"") | O11: =IFERROR(L11-L7,"")
A12: Mexico S&P/BMV IPC | B12: MXN | C12: =INDEX(HIST_D!$BC$8:$BC$2617,1) | D12: =IFERROR(INDEX(HIST_D!$BC$8:$BC$2617,1)/INDEX(HIST_D!$BC$8:$BC$2617,Control!$F$8)-1,"") | E12: =IFERROR(INDEX(HIST_D!$AB$8:$AB$2617,Control!$F$8)/INDEX(HIST_D!$AB$8:$AB$2617,1)-1,"") | F12: =IFERROR((1+D12)*(1+E12)-1,"") | G12: =IFERROR(INDEX(HIST_D!$BC$8:$BC$2617,1)/INDEX(HIST_D!$BC$8:$BC$2617,Control!$F$9)-1,"") | H12: =IFERROR(INDEX(HIST_D!$AB$8:$AB$2617,Control!$F$9)/INDEX(HIST_D!$AB$8:$AB$2617,1)-1,"") | I12: =IFERROR((1+G12)*(1+H12)-1,"") | J12: =IFERROR(INDEX(HIST_D!$BC$8:$BC$2617,1)/INDEX(HIST_D!$BC$8:$BC$2617,Control!$F$16)-1,"") | K12: =IFERROR(INDEX(HIST_D!$AB$8:$AB$2617,Control!$F$16)/INDEX(HIST_D!$AB$8:$AB$2617,1)-1,"") | L12: =IFERROR((1+J12)*(1+K12)-1,"") | M12: =IFERROR((1+IFERROR(INDEX(HIST_D!$BC$8:$BC$2617,1)/INDEX(HIST_D!$BC$8:$BC$2617,Control!$F$11)-1,""))*(1+IFERROR(INDEX(HIST_D!$AB$8:$AB$2617,Control!$F$11)/INDEX(HIST_D!$AB$8:$AB$2617,1)-1,""))-1,"") | N12: =IFERROR(F12-F7,"") | O12: =IFERROR(L12-L7,"")
A13: Chile IPSA | B13: CLP | C13: =INDEX(HIST_D!$BD$8:$BD$2617,1) | D13: =IFERROR(INDEX(HIST_D!$BD$8:$BD$2617,1)/INDEX(HIST_D!$BD$8:$BD$2617,Control!$F$8)-1,"") | E13: =IFERROR(INDEX(HIST_D!$AC$8:$AC$2617,Control!$F$8)/INDEX(HIST_D!$AC$8:$AC$2617,1)-1,"") | F13: =IFERROR((1+D13)*(1+E13)-1,"") | G13: =IFERROR(INDEX(HIST_D!$BD$8:$BD$2617,1)/INDEX(HIST_D!$BD$8:$BD$2617,Control!$F$9)-1,"") | H13: =IFERROR(INDEX(HIST_D!$AC$8:$AC$2617,Control!$F$9)/INDEX(HIST_D!$AC$8:$AC$2617,1)-1,"") | I13: =IFERROR((1+G13)*(1+H13)-1,"") | J13: =IFERROR(INDEX(HIST_D!$BD$8:$BD$2617,1)/INDEX(HIST_D!$BD$8:$BD$2617,Control!$F$16)-1,"") | K13: =IFERROR(INDEX(HIST_D!$AC$8:$AC$2617,Control!$F$16)/INDEX(HIST_D!$AC$8:$AC$2617,1)-1,"") | L13: =IFERROR((1+J13)*(1+K13)-1,"") | M13: =IFERROR((1+IFERROR(INDEX(HIST_D!$BD$8:$BD$2617,1)/INDEX(HIST_D!$BD$8:$BD$2617,Control!$F$11)-1,""))*(1+IFERROR(INDEX(HIST_D!$AC$8:$AC$2617,Control!$F$11)/INDEX(HIST_D!$AC$8:$AC$2617,1)-1,""))-1,"") | N13: =IFERROR(F13-F7,"") | O13: =IFERROR(L13-L7,"")
A14: Colombia COLCAP | B14: COP | C14: =INDEX(HIST_D!$BE$8:$BE$2617,1) | D14: =IFERROR(INDEX(HIST_D!$BE$8:$BE$2617,1)/INDEX(HIST_D!$BE$8:$BE$2617,Control!$F$8)-1,"") | E14: =IFERROR(INDEX(HIST_D!$AD$8:$AD$2617,Control!$F$8)/INDEX(HIST_D!$AD$8:$AD$2617,1)-1,"") | F14: =IFERROR((1+D14)*(1+E14)-1,"") | G14: =IFERROR(INDEX(HIST_D!$BE$8:$BE$2617,1)/INDEX(HIST_D!$BE$8:$BE$2617,Control!$F$9)-1,"") | H14: =IFERROR(INDEX(HIST_D!$AD$8:$AD$2617,Control!$F$9)/INDEX(HIST_D!$AD$8:$AD$2617,1)-1,"") | I14: =IFERROR((1+G14)*(1+H14)-1,"") | J14: =IFERROR(INDEX(HIST_D!$BE$8:$BE$2617,1)/INDEX(HIST_D!$BE$8:$BE$2617,Control!$F$16)-1,"") | K14: =IFERROR(INDEX(HIST_D!$AD$8:$AD$2617,Control!$F$16)/INDEX(HIST_D!$AD$8:$AD$2617,1)-1,"") | L14: =IFERROR((1+J14)*(1+K14)-1,"") | M14: =IFERROR((1+IFERROR(INDEX(HIST_D!$BE$8:$BE$2617,1)/INDEX(HIST_D!$BE$8:$BE$2617,Control!$F$11)-1,""))*(1+IFERROR(INDEX(HIST_D!$AD$8:$AD$2617,Control!$F$11)/INDEX(HIST_D!$AD$8:$AD$2617,1)-1,""))-1,"") | N14: =IFERROR(F14-F7,"") | O14: =IFERROR(L14-L7,"")
A15: Peru S&P/BVL | B15: PEN | C15: =INDEX(HIST_D!$BF$8:$BF$2617,1) | D15: =IFERROR(INDEX(HIST_D!$BF$8:$BF$2617,1)/INDEX(HIST_D!$BF$8:$BF$2617,Control!$F$8)-1,"") | E15: =IFERROR(INDEX(HIST_D!$AE$8:$AE$2617,Control!$F$8)/INDEX(HIST_D!$AE$8:$AE$2617,1)-1,"") | F15: =IFERROR((1+D15)*(1+E15)-1,"") | G15: =IFERROR(INDEX(HIST_D!$BF$8:$BF$2617,1)/INDEX(HIST_D!$BF$8:$BF$2617,Control!$F$9)-1,"") | H15: =IFERROR(INDEX(HIST_D!$AE$8:$AE$2617,Control!$F$9)/INDEX(HIST_D!$AE$8:$AE$2617,1)-1,"") | I15: =IFERROR((1+G15)*(1+H15)-1,"") | J15: =IFERROR(INDEX(HIST_D!$BF$8:$BF$2617,1)/INDEX(HIST_D!$BF$8:$BF$2617,Control!$F$16)-1,"") | K15: =IFERROR(INDEX(HIST_D!$AE$8:$AE$2617,Control!$F$16)/INDEX(HIST_D!$AE$8:$AE$2617,1)-1,"") | L15: =IFERROR((1+J15)*(1+K15)-1,"") | M15: =IFERROR((1+IFERROR(INDEX(HIST_D!$BF$8:$BF$2617,1)/INDEX(HIST_D!$BF$8:$BF$2617,Control!$F$11)-1,""))*(1+IFERROR(INDEX(HIST_D!$AE$8:$AE$2617,Control!$F$11)/INDEX(HIST_D!$AE$8:$AE$2617,1)-1,""))-1,"") | N15: =IFERROR(F15-F7,"") | O15: =IFERROR(L15-L7,"")
A16: Argentina Merval | B16: ARS | C16: =INDEX(HIST_D!$BG$8:$BG$2617,1) | D16: =IFERROR(INDEX(HIST_D!$BG$8:$BG$2617,1)/INDEX(HIST_D!$BG$8:$BG$2617,Control!$F$8)-1,"") | E16: =IFERROR(INDEX(HIST_D!$AF$8:$AF$2617,Control!$F$8)/INDEX(HIST_D!$AF$8:$AF$2617,1)-1,"") | F16: =IFERROR((1+D16)*(1+E16)-1,"") | G16: =IFERROR(INDEX(HIST_D!$BG$8:$BG$2617,1)/INDEX(HIST_D!$BG$8:$BG$2617,Control!$F$9)-1,"") | H16: =IFERROR(INDEX(HIST_D!$AF$8:$AF$2617,Control!$F$9)/INDEX(HIST_D!$AF$8:$AF$2617,1)-1,"") | I16: =IFERROR((1+G16)*(1+H16)-1,"") | J16: =IFERROR(INDEX(HIST_D!$BG$8:$BG$2617,1)/INDEX(HIST_D!$BG$8:$BG$2617,Control!$F$16)-1,"") | K16: =IFERROR(INDEX(HIST_D!$AF$8:$AF$2617,Control!$F$16)/INDEX(HIST_D!$AF$8:$AF$2617,1)-1,"") | L16: =IFERROR((1+J16)*(1+K16)-1,"") | M16: =IFERROR((1+IFERROR(INDEX(HIST_D!$BG$8:$BG$2617,1)/INDEX(HIST_D!$BG$8:$BG$2617,Control!$F$11)-1,""))*(1+IFERROR(INDEX(HIST_D!$AF$8:$AF$2617,Control!$F$11)/INDEX(HIST_D!$AF$8:$AF$2617,1)-1,""))-1,"") | N16: =IFERROR(F16-F7,"") | O16: =IFERROR(L16-L7,"")
A17: LatAm basket (eq-wgt, n=6) | D17: =IFERROR(AVERAGE(D11,D12,D13,D14,D15,D16),"") | E17: =IFERROR(AVERAGE(E11,E12,E13,E14,E15,E16),"") | F17: =IFERROR(AVERAGE(F11,F12,F13,F14,F15,F16),"") | G17: =IFERROR(AVERAGE(G11,G12,G13,G14,G15,G16),"") | H17: =IFERROR(AVERAGE(H11,H12,H13,H14,H15,H16),"") | I17: =IFERROR(AVERAGE(I11,I12,I13,I14,I15,I16),"") | J17: =IFERROR(AVERAGE(J11,J12,J13,J14,J15,J16),"") | K17: =IFERROR(AVERAGE(K11,K12,K13,K14,K15,K16),"") | ... M17: =IFERROR(AVERAGE(M11,M12,M13,M14,M15,M16),"") | N17: =IFERROR(F17-F7,"") | O17: =IFERROR(L17-L7,"")
A18: =IFERROR("LatAm: "&TEXT($F$17,"+0.0%;-0.0%")&" in USD on the month ("&TEXT($D$17,"+0.0%;-0.0%")&" local, "&TEXT($E$17,"+0.0%;-0.0%")&" FX), "&TEXT($L$17,"+0.0%;-0.0%")&" YTD, "&TEXT($N$17,"+0.0%;-0.0%")&" vs MSCI World. "&IF($E$17<-0.005,"The currency is taxing the equity story here.",IF($E$17>0.005,"The currency is adding to it.","The currency is neutral; this is an earnings and multiple story, not an FX one.")),"")
A20: EM EUROPE
A21: Index | B21: Ccy | C21: Level | D21: 1M local | E21: 1M FX | F21: 1M USD | G21: 3M local | H21: 3M FX | I21: 3M USD | J21: YTD local | K21: YTD FX | L21: YTD USD | M21: 1Y USD | N21: vs World 1M | O21: vs World YTD
A22: Poland WIG | B22: PLN | C22: =INDEX(HIST_D!$BH$8:$BH$2617,1) | D22: =IFERROR(INDEX(HIST_D!$BH$8:$BH$2617,1)/INDEX(HIST_D!$BH$8:$BH$2617,Control!$F$8)-1,"") | E22: =IFERROR(INDEX(HIST_D!$AG$8:$AG$2617,Control!$F$8)/INDEX(HIST_D!$AG$8:$AG$2617,1)-1,"") | F22: =IFERROR((1+D22)*(1+E22)-1,"") | G22: =IFERROR(INDEX(HIST_D!$BH$8:$BH$2617,1)/INDEX(HIST_D!$BH$8:$BH$2617,Control!$F$9)-1,"") | H22: =IFERROR(INDEX(HIST_D!$AG$8:$AG$2617,Control!$F$9)/INDEX(HIST_D!$AG$8:$AG$2617,1)-1,"") | I22: =IFERROR((1+G22)*(1+H22)-1,"") | J22: =IFERROR(INDEX(HIST_D!$BH$8:$BH$2617,1)/INDEX(HIST_D!$BH$8:$BH$2617,Control!$F$16)-1,"") | K22: =IFERROR(INDEX(HIST_D!$AG$8:$AG$2617,Control!$F$16)/INDEX(HIST_D!$AG$8:$AG$2617,1)-1,"") | L22: =IFERROR((1+J22)*(1+K22)-1,"") | M22: =IFERROR((1+IFERROR(INDEX(HIST_D!$BH$8:$BH$2617,1)/INDEX(HIST_D!$BH$8:$BH$2617,Control!$F$11)-1,""))*(1+IFERROR(INDEX(HIST_D!$AG$8:$AG$2617,Control!$F$11)/INDEX(HIST_D!$AG$8:$AG$2617,1)-1,""))-1,"") | N22: =IFERROR(F22-F7,"") | O22: =IFERROR(L22-L7,"")
A23: Hungary BUX | B23: HUF | C23: =INDEX(HIST_D!$BI$8:$BI$2617,1) | D23: =IFERROR(INDEX(HIST_D!$BI$8:$BI$2617,1)/INDEX(HIST_D!$BI$8:$BI$2617,Control!$F$8)-1,"") | E23: =IFERROR(INDEX(HIST_D!$AH$8:$AH$2617,Control!$F$8)/INDEX(HIST_D!$AH$8:$AH$2617,1)-1,"") | F23: =IFERROR((1+D23)*(1+E23)-1,"") | G23: =IFERROR(INDEX(HIST_D!$BI$8:$BI$2617,1)/INDEX(HIST_D!$BI$8:$BI$2617,Control!$F$9)-1,"") | H23: =IFERROR(INDEX(HIST_D!$AH$8:$AH$2617,Control!$F$9)/INDEX(HIST_D!$AH$8:$AH$2617,1)-1,"") | I23: =IFERROR((1+G23)*(1+H23)-1,"") | J23: =IFERROR(INDEX(HIST_D!$BI$8:$BI$2617,1)/INDEX(HIST_D!$BI$8:$BI$2617,Control!$F$16)-1,"") | K23: =IFERROR(INDEX(HIST_D!$AH$8:$AH$2617,Control!$F$16)/INDEX(HIST_D!$AH$8:$AH$2617,1)-1,"") | L23: =IFERROR((1+J23)*(1+K23)-1,"") | M23: =IFERROR((1+IFERROR(INDEX(HIST_D!$BI$8:$BI$2617,1)/INDEX(HIST_D!$BI$8:$BI$2617,Control!$F$11)-1,""))*(1+IFERROR(INDEX(HIST_D!$AH$8:$AH$2617,Control!$F$11)/INDEX(HIST_D!$AH$8:$AH$2617,1)-1,""))-1,"") | N23: =IFERROR(F23-F7,"") | O23: =IFERROR(L23-L7,"")
A24: Czechia PX | B24: CZK | C24: =INDEX(HIST_D!$BJ$8:$BJ$2617,1) | D24: =IFERROR(INDEX(HIST_D!$BJ$8:$BJ$2617,1)/INDEX(HIST_D!$BJ$8:$BJ$2617,Control!$F$8)-1,"") | E24: =IFERROR(INDEX(HIST_D!$AI$8:$AI$2617,Control!$F$8)/INDEX(HIST_D!$AI$8:$AI$2617,1)-1,"") | F24: =IFERROR((1+D24)*(1+E24)-1,"") | G24: =IFERROR(INDEX(HIST_D!$BJ$8:$BJ$2617,1)/INDEX(HIST_D!$BJ$8:$BJ$2617,Control!$F$9)-1,"") | H24: =IFERROR(INDEX(HIST_D!$AI$8:$AI$2617,Control!$F$9)/INDEX(HIST_D!$AI$8:$AI$2617,1)-1,"") | I24: =IFERROR((1+G24)*(1+H24)-1,"") | J24: =IFERROR(INDEX(HIST_D!$BJ$8:$BJ$2617,1)/INDEX(HIST_D!$BJ$8:$BJ$2617,Control!$F$16)-1,"") | K24: =IFERROR(INDEX(HIST_D!$AI$8:$AI$2617,Control!$F$16)/INDEX(HIST_D!$AI$8:$AI$2617,1)-1,"") | L24: =IFERROR((1+J24)*(1+K24)-1,"") | M24: =IFERROR((1+IFERROR(INDEX(HIST_D!$BJ$8:$BJ$2617,1)/INDEX(HIST_D!$BJ$8:$BJ$2617,Control!$F$11)-1,""))*(1+IFERROR(INDEX(HIST_D!$AI$8:$AI$2617,Control!$F$11)/INDEX(HIST_D!$AI$8:$AI$2617,1)-1,""))-1,"") | N24: =IFERROR(F24-F7,"") | O24: =IFERROR(L24-L7,"")
A25: Romania BET | B25: RON | C25: =INDEX(HIST_D!$BK$8:$BK$2617,1) | D25: =IFERROR(INDEX(HIST_D!$BK$8:$BK$2617,1)/INDEX(HIST_D!$BK$8:$BK$2617,Control!$F$8)-1,"") | E25: =IFERROR(INDEX(HIST_D!$AJ$8:$AJ$2617,Control!$F$8)/INDEX(HIST_D!$AJ$8:$AJ$2617,1)-1,"") | F25: =IFERROR((1+D25)*(1+E25)-1,"") | G25: =IFERROR(INDEX(HIST_D!$BK$8:$BK$2617,1)/INDEX(HIST_D!$BK$8:$BK$2617,Control!$F$9)-1,"") | H25: =IFERROR(INDEX(HIST_D!$AJ$8:$AJ$2617,Control!$F$9)/INDEX(HIST_D!$AJ$8:$AJ$2617,1)-1,"") | I25: =IFERROR((1+G25)*(1+H25)-1,"") | J25: =IFERROR(INDEX(HIST_D!$BK$8:$BK$2617,1)/INDEX(HIST_D!$BK$8:$BK$2617,Control!$F$16)-1,"") | K25: =IFERROR(INDEX(HIST_D!$AJ$8:$AJ$2617,Control!$F$16)/INDEX(HIST_D!$AJ$8:$AJ$2617,1)-1,"") | L25: =IFERROR((1+J25)*(1+K25)-1,"") | M25: =IFERROR((1+IFERROR(INDEX(HIST_D!$BK$8:$BK$2617,1)/INDEX(HIST_D!$BK$8:$BK$2617,Control!$F$11)-1,""))*(1+IFERROR(INDEX(HIST_D!$AJ$8:$AJ$2617,Control!$F$11)/INDEX(HIST_D!$AJ$8:$AJ$2617,1)-1,""))-1,"") | N25: =IFERROR(F25-F7,"") | O25: =IFERROR(L25-L7,"")
A26: Turkiye BIST 100 | B26: TRY | C26: =INDEX(HIST_D!$BL$8:$BL$2617,1) | D26: =IFERROR(INDEX(HIST_D!$BL$8:$BL$2617,1)/INDEX(HIST_D!$BL$8:$BL$2617,Control!$F$8)-1,"") | E26: =IFERROR(INDEX(HIST_D!$AK$8:$AK$2617,Control!$F$8)/INDEX(HIST_D!$AK$8:$AK$2617,1)-1,"") | F26: =IFERROR((1+D26)*(1+E26)-1,"") | G26: =IFERROR(INDEX(HIST_D!$BL$8:$BL$2617,1)/INDEX(HIST_D!$BL$8:$BL$2617,Control!$F$9)-1,"") | H26: =IFERROR(INDEX(HIST_D!$AK$8:$AK$2617,Control!$F$9)/INDEX(HIST_D!$AK$8:$AK$2617,1)-1,"") | I26: =IFERROR((1+G26)*(1+H26)-1,"") | J26: =IFERROR(INDEX(HIST_D!$BL$8:$BL$2617,1)/INDEX(HIST_D!$BL$8:$BL$2617,Control!$F$16)-1,"") | K26: =IFERROR(INDEX(HIST_D!$AK$8:$AK$2617,Control!$F$16)/INDEX(HIST_D!$AK$8:$AK$2617,1)-1,"") | L26: =IFERROR((1+J26)*(1+K26)-1,"") | M26: =IFERROR((1+IFERROR(INDEX(HIST_D!$BL$8:$BL$2617,1)/INDEX(HIST_D!$BL$8:$BL$2617,Control!$F$11)-1,""))*(1+IFERROR(INDEX(HIST_D!$AK$8:$AK$2617,Control!$F$11)/INDEX(HIST_D!$AK$8:$AK$2617,1)-1,""))-1,"") | N26: =IFERROR(F26-F7,"") | O26: =IFERROR(L26-L7,"")
A27: EM Europe basket (eq-wgt, n=5) | D27: =IFERROR(AVERAGE(D22,D23,D24,D25,D26),"") | E27: =IFERROR(AVERAGE(E22,E23,E24,E25,E26),"") | F27: =IFERROR(AVERAGE(F22,F23,F24,F25,F26),"") | G27: =IFERROR(AVERAGE(G22,G23,G24,G25,G26),"") | H27: =IFERROR(AVERAGE(H22,H23,H24,H25,H26),"") | I27: =IFERROR(AVERAGE(I22,I23,I24,I25,I26),"") | J27: =IFERROR(AVERAGE(J22,J23,J24,J25,J26),"") | K27: =IFERROR(AVERAGE(K22,K23,K24,K25,K26),"") | ... M27: =IFERROR(AVERAGE(M22,M23,M24,M25,M26),"") | N27: =IFERROR(F27-F7,"") | O27: =IFERROR(L27-L7,"")
A28: =IFERROR("EM Europe: "&TEXT($F$27,"+0.0%;-0.0%")&" in USD on the month ("&TEXT($D$27,"+0.0%;-0.0%")&" local, "&TEXT($E$27,"+0.0%;-0.0%")&" FX), "&TEXT($L$27,"+0.0%;-0.0%")&" YTD, "&TEXT($N$27,"+0.0%;-0.0%")&" vs MSCI World. "&IF($E$27<-0.005,"The currency is taxing the equity story here.",IF($E$27>0.005,"The currency is adding to it.","The currency is neutral; this is an earnings and multiple story, not an FX one.")),"")
A30: MIDDLE EAST & AFRICA
A31: Index | B31: Ccy | C31: Level | D31: 1M local | E31: 1M FX | F31: 1M USD | G31: 3M local | H31: 3M FX | I31: 3M USD | J31: YTD local | K31: YTD FX | L31: YTD USD | M31: 1Y USD | N31: vs World 1M | O31: vs World YTD
A32: Israel TA-35 | B32: ILS | C32: =INDEX(HIST_D!$BM$8:$BM$2617,1) | D32: =IFERROR(INDEX(HIST_D!$BM$8:$BM$2617,1)/INDEX(HIST_D!$BM$8:$BM$2617,Control!$F$8)-1,"") | E32: =IFERROR(INDEX(HIST_D!$AL$8:$AL$2617,Control!$F$8)/INDEX(HIST_D!$AL$8:$AL$2617,1)-1,"") | F32: =IFERROR((1+D32)*(1+E32)-1,"") | G32: =IFERROR(INDEX(HIST_D!$BM$8:$BM$2617,1)/INDEX(HIST_D!$BM$8:$BM$2617,Control!$F$9)-1,"") | H32: =IFERROR(INDEX(HIST_D!$AL$8:$AL$2617,Control!$F$9)/INDEX(HIST_D!$AL$8:$AL$2617,1)-1,"") | I32: =IFERROR((1+G32)*(1+H32)-1,"") | J32: =IFERROR(INDEX(HIST_D!$BM$8:$BM$2617,1)/INDEX(HIST_D!$BM$8:$BM$2617,Control!$F$16)-1,"") | K32: =IFERROR(INDEX(HIST_D!$AL$8:$AL$2617,Control!$F$16)/INDEX(HIST_D!$AL$8:$AL$2617,1)-1,"") | L32: =IFERROR((1+J32)*(1+K32)-1,"") | M32: =IFERROR((1+IFERROR(INDEX(HIST_D!$BM$8:$BM$2617,1)/INDEX(HIST_D!$BM$8:$BM$2617,Control!$F$11)-1,""))*(1+IFERROR(INDEX(HIST_D!$AL$8:$AL$2617,Control!$F$11)/INDEX(HIST_D!$AL$8:$AL$2617,1)-1,""))-1,"") | N32: =IFERROR(F32-F7,"") | O32: =IFERROR(L32-L7,"")
A33: South Africa All Share | B33: ZAR | C33: =INDEX(HIST_D!$BN$8:$BN$2617,1) | D33: =IFERROR(INDEX(HIST_D!$BN$8:$BN$2617,1)/INDEX(HIST_D!$BN$8:$BN$2617,Control!$F$8)-1,"") | E33: =IFERROR(INDEX(HIST_D!$AM$8:$AM$2617,Control!$F$8)/INDEX(HIST_D!$AM$8:$AM$2617,1)-1,"") | F33: =IFERROR((1+D33)*(1+E33)-1,"") | G33: =IFERROR(INDEX(HIST_D!$BN$8:$BN$2617,1)/INDEX(HIST_D!$BN$8:$BN$2617,Control!$F$9)-1,"") | H33: =IFERROR(INDEX(HIST_D!$AM$8:$AM$2617,Control!$F$9)/INDEX(HIST_D!$AM$8:$AM$2617,1)-1,"") | I33: =IFERROR((1+G33)*(1+H33)-1,"") | J33: =IFERROR(INDEX(HIST_D!$BN$8:$BN$2617,1)/INDEX(HIST_D!$BN$8:$BN$2617,Control!$F$16)-1,"") | K33: =IFERROR(INDEX(HIST_D!$AM$8:$AM$2617,Control!$F$16)/INDEX(HIST_D!$AM$8:$AM$2617,1)-1,"") | L33: =IFERROR((1+J33)*(1+K33)-1,"") | M33: =IFERROR((1+IFERROR(INDEX(HIST_D!$BN$8:$BN$2617,1)/INDEX(HIST_D!$BN$8:$BN$2617,Control!$F$11)-1,""))*(1+IFERROR(INDEX(HIST_D!$AM$8:$AM$2617,Control!$F$11)/INDEX(HIST_D!$AM$8:$AM$2617,1)-1,""))-1,"") | N33: =IFERROR(F33-F7,"") | O33: =IFERROR(L33-L7,"")
A34: Saudi Tadawul All Share | B34: SAR | C34: =INDEX(HIST_D!$BO$8:$BO$2617,1) | D34: =IFERROR(INDEX(HIST_D!$BO$8:$BO$2617,1)/INDEX(HIST_D!$BO$8:$BO$2617,Control!$F$8)-1,"") | E34: =IFERROR(INDEX(HIST_D!$AO$8:$AO$2617,Control!$F$8)/INDEX(HIST_D!$AO$8:$AO$2617,1)-1,"") | F34: =IFERROR((1+D34)*(1+E34)-1,"") | G34: =IFERROR(INDEX(HIST_D!$BO$8:$BO$2617,1)/INDEX(HIST_D!$BO$8:$BO$2617,Control!$F$9)-1,"") | H34: =IFERROR(INDEX(HIST_D!$AO$8:$AO$2617,Control!$F$9)/INDEX(HIST_D!$AO$8:$AO$2617,1)-1,"") | I34: =IFERROR((1+G34)*(1+H34)-1,"") | J34: =IFERROR(INDEX(HIST_D!$BO$8:$BO$2617,1)/INDEX(HIST_D!$BO$8:$BO$2617,Control!$F$16)-1,"") | K34: =IFERROR(INDEX(HIST_D!$AO$8:$AO$2617,Control!$F$16)/INDEX(HIST_D!$AO$8:$AO$2617,1)-1,"") | L34: =IFERROR((1+J34)*(1+K34)-1,"") | M34: =IFERROR((1+IFERROR(INDEX(HIST_D!$BO$8:$BO$2617,1)/INDEX(HIST_D!$BO$8:$BO$2617,Control!$F$11)-1,""))*(1+IFERROR(INDEX(HIST_D!$AO$8:$AO$2617,Control!$F$11)/INDEX(HIST_D!$AO$8:$AO$2617,1)-1,""))-1,"") | N34: =IFERROR(F34-F7,"") | O34: =IFERROR(L34-L7,"")
A35: Abu Dhabi ADX General | B35: AED | C35: =INDEX(HIST_D!$BP$8:$BP$2617,1) | D35: =IFERROR(INDEX(HIST_D!$BP$8:$BP$2617,1)/INDEX(HIST_D!$BP$8:$BP$2617,Control!$F$8)-1,"") | E35: =IFERROR(INDEX(HIST_D!$AP$8:$AP$2617,Control!$F$8)/INDEX(HIST_D!$AP$8:$AP$2617,1)-1,"") | F35: =IFERROR((1+D35)*(1+E35)-1,"") | G35: =IFERROR(INDEX(HIST_D!$BP$8:$BP$2617,1)/INDEX(HIST_D!$BP$8:$BP$2617,Control!$F$9)-1,"") | H35: =IFERROR(INDEX(HIST_D!$AP$8:$AP$2617,Control!$F$9)/INDEX(HIST_D!$AP$8:$AP$2617,1)-1,"") | I35: =IFERROR((1+G35)*(1+H35)-1,"") | J35: =IFERROR(INDEX(HIST_D!$BP$8:$BP$2617,1)/INDEX(HIST_D!$BP$8:$BP$2617,Control!$F$16)-1,"") | K35: =IFERROR(INDEX(HIST_D!$AP$8:$AP$2617,Control!$F$16)/INDEX(HIST_D!$AP$8:$AP$2617,1)-1,"") | L35: =IFERROR((1+J35)*(1+K35)-1,"") | M35: =IFERROR((1+IFERROR(INDEX(HIST_D!$BP$8:$BP$2617,1)/INDEX(HIST_D!$BP$8:$BP$2617,Control!$F$11)-1,""))*(1+IFERROR(INDEX(HIST_D!$AP$8:$AP$2617,Control!$F$11)/INDEX(HIST_D!$AP$8:$AP$2617,1)-1,""))-1,"") | N35: =IFERROR(F35-F7,"") | O35: =IFERROR(L35-L7,"")
A36: Qatar QE Index | B36: QAR | C36: =INDEX(HIST_D!$BQ$8:$BQ$2617,1) | D36: =IFERROR(INDEX(HIST_D!$BQ$8:$BQ$2617,1)/INDEX(HIST_D!$BQ$8:$BQ$2617,Control!$F$8)-1,"") | E36: =IFERROR(INDEX(HIST_D!$AQ$8:$AQ$2617,Control!$F$8)/INDEX(HIST_D!$AQ$8:$AQ$2617,1)-1,"") | F36: =IFERROR((1+D36)*(1+E36)-1,"") | G36: =IFERROR(INDEX(HIST_D!$BQ$8:$BQ$2617,1)/INDEX(HIST_D!$BQ$8:$BQ$2617,Control!$F$9)-1,"") | H36: =IFERROR(INDEX(HIST_D!$AQ$8:$AQ$2617,Control!$F$9)/INDEX(HIST_D!$AQ$8:$AQ$2617,1)-1,"") | I36: =IFERROR((1+G36)*(1+H36)-1,"") | J36: =IFERROR(INDEX(HIST_D!$BQ$8:$BQ$2617,1)/INDEX(HIST_D!$BQ$8:$BQ$2617,Control!$F$16)-1,"") | K36: =IFERROR(INDEX(HIST_D!$AQ$8:$AQ$2617,Control!$F$16)/INDEX(HIST_D!$AQ$8:$AQ$2617,1)-1,"") | L36: =IFERROR((1+J36)*(1+K36)-1,"") | M36: =IFERROR((1+IFERROR(INDEX(HIST_D!$BQ$8:$BQ$2617,1)/INDEX(HIST_D!$BQ$8:$BQ$2617,Control!$F$11)-1,""))*(1+IFERROR(INDEX(HIST_D!$AQ$8:$AQ$2617,Control!$F$11)/INDEX(HIST_D!$AQ$8:$AQ$2617,1)-1,""))-1,"") | N36: =IFERROR(F36-F7,"") | O36: =IFERROR(L36-L7,"")
A37: Egypt EGX 30 | B37: EGP | C37: =INDEX(HIST_D!$BR$8:$BR$2617,1) | D37: =IFERROR(INDEX(HIST_D!$BR$8:$BR$2617,1)/INDEX(HIST_D!$BR$8:$BR$2617,Control!$F$8)-1,"") | E37: =IFERROR(INDEX(HIST_D!$AN$8:$AN$2617,Control!$F$8)/INDEX(HIST_D!$AN$8:$AN$2617,1)-1,"") | F37: =IFERROR((1+D37)*(1+E37)-1,"") | G37: =IFERROR(INDEX(HIST_D!$BR$8:$BR$2617,1)/INDEX(HIST_D!$BR$8:$BR$2617,Control!$F$9)-1,"") | H37: =IFERROR(INDEX(HIST_D!$AN$8:$AN$2617,Control!$F$9)/INDEX(HIST_D!$AN$8:$AN$2617,1)-1,"") | I37: =IFERROR((1+G37)*(1+H37)-1,"") | J37: =IFERROR(INDEX(HIST_D!$BR$8:$BR$2617,1)/INDEX(HIST_D!$BR$8:$BR$2617,Control!$F$16)-1,"") | K37: =IFERROR(INDEX(HIST_D!$AN$8:$AN$2617,Control!$F$16)/INDEX(HIST_D!$AN$8:$AN$2617,1)-1,"") | L37: =IFERROR((1+J37)*(1+K37)-1,"") | M37: =IFERROR((1+IFERROR(INDEX(HIST_D!$BR$8:$BR$2617,1)/INDEX(HIST_D!$BR$8:$BR$2617,Control!$F$11)-1,""))*(1+IFERROR(INDEX(HIST_D!$AN$8:$AN$2617,Control!$F$11)/INDEX(HIST_D!$AN$8:$AN$2617,1)-1,""))-1,"") | N37: =IFERROR(F37-F7,"") | O37: =IFERROR(L37-L7,"")
A38: Middle East & Africa basket (eq-wgt, n=6) | D38: =IFERROR(AVERAGE(D32,D33,D34,D35,D36,D37),"") | E38: =IFERROR(AVERAGE(E32,E33,E34,E35,E36,E37),"") | F38: =IFERROR(AVERAGE(F32,F33,F34,F35,F36,F37),"") | G38: =IFERROR(AVERAGE(G32,G33,G34,G35,G36,G37),"") | H38: =IFERROR(AVERAGE(H32,H33,H34,H35,H36,H37),"") | I38: =IFERROR(AVERAGE(I32,I33,I34,I35,I36,I37),"") | J38: =IFERROR(AVERAGE(J32,J33,J34,J35,J36,J37),"") | K38: =IFERROR(AVERAGE(K32,K33,K34,K35,K36,K37),"") | ... M38: =IFERROR(AVERAGE(M32,M33,M34,M35,M36,M37),"") | N38: =IFERROR(F38-F7,"") | O38: =IFERROR(L38-L7,"")
A39: =IFERROR("Middle East & Africa: "&TEXT($F$38,"+0.0%;-0.0%")&" in USD on the month ("&TEXT($D$38,"+0.0%;-0.0%")&" local, "&TEXT($E$38,"+0.0%;-0.0%")&" FX), "&TEXT($L$38,"+0.0%;-0.0%")&" YTD, "&TEXT($N$38,"+0.0%;-0.0%")&" vs MSCI World. "&IF($E$38<-0.005,"The currency is taxing the equity story here.",IF($E$38>0.005,"The currency is adding to it.","The currency is neutral; this is an earnings and multiple story, not an FX one.")),"")
A41: ASIA
A42: Index | B42: Ccy | C42: Level | D42: 1M local | E42: 1M FX | F42: 1M USD | G42: 3M local | H42: 3M FX | I42: 3M USD | J42: YTD local | K42: YTD FX | L42: YTD USD | M42: 1Y USD | N42: vs World 1M | O42: vs World YTD
A43: China Shanghai Comp | B43: CNH | C43: =INDEX(HIST_D!$BS$8:$BS$2617,1) | D43: =IFERROR(INDEX(HIST_D!$BS$8:$BS$2617,1)/INDEX(HIST_D!$BS$8:$BS$2617,Control!$F$8)-1,"") | E43: =IFERROR(INDEX(HIST_D!$AR$8:$AR$2617,Control!$F$8)/INDEX(HIST_D!$AR$8:$AR$2617,1)-1,"") | F43: =IFERROR((1+D43)*(1+E43)-1,"") | G43: =IFERROR(INDEX(HIST_D!$BS$8:$BS$2617,1)/INDEX(HIST_D!$BS$8:$BS$2617,Control!$F$9)-1,"") | H43: =IFERROR(INDEX(HIST_D!$AR$8:$AR$2617,Control!$F$9)/INDEX(HIST_D!$AR$8:$AR$2617,1)-1,"") | I43: =IFERROR((1+G43)*(1+H43)-1,"") | J43: =IFERROR(INDEX(HIST_D!$BS$8:$BS$2617,1)/INDEX(HIST_D!$BS$8:$BS$2617,Control!$F$16)-1,"") | K43: =IFERROR(INDEX(HIST_D!$AR$8:$AR$2617,Control!$F$16)/INDEX(HIST_D!$AR$8:$AR$2617,1)-1,"") | L43: =IFERROR((1+J43)*(1+K43)-1,"") | M43: =IFERROR((1+IFERROR(INDEX(HIST_D!$BS$8:$BS$2617,1)/INDEX(HIST_D!$BS$8:$BS$2617,Control!$F$11)-1,""))*(1+IFERROR(INDEX(HIST_D!$AR$8:$AR$2617,Control!$F$11)/INDEX(HIST_D!$AR$8:$AR$2617,1)-1,""))-1,"") | N43: =IFERROR(F43-F7,"") | O43: =IFERROR(L43-L7,"")
A44: Hong Kong Hang Seng | B44: CNH | C44: =INDEX(HIST_D!$BT$8:$BT$2617,1) | D44: =IFERROR(INDEX(HIST_D!$BT$8:$BT$2617,1)/INDEX(HIST_D!$BT$8:$BT$2617,Control!$F$8)-1,"") | E44: =IFERROR(INDEX(HIST_D!$AR$8:$AR$2617,Control!$F$8)/INDEX(HIST_D!$AR$8:$AR$2617,1)-1,"") | F44: =IFERROR((1+D44)*(1+E44)-1,"") | G44: =IFERROR(INDEX(HIST_D!$BT$8:$BT$2617,1)/INDEX(HIST_D!$BT$8:$BT$2617,Control!$F$9)-1,"") | H44: =IFERROR(INDEX(HIST_D!$AR$8:$AR$2617,Control!$F$9)/INDEX(HIST_D!$AR$8:$AR$2617,1)-1,"") | I44: =IFERROR((1+G44)*(1+H44)-1,"") | J44: =IFERROR(INDEX(HIST_D!$BT$8:$BT$2617,1)/INDEX(HIST_D!$BT$8:$BT$2617,Control!$F$16)-1,"") | K44: =IFERROR(INDEX(HIST_D!$AR$8:$AR$2617,Control!$F$16)/INDEX(HIST_D!$AR$8:$AR$2617,1)-1,"") | L44: =IFERROR((1+J44)*(1+K44)-1,"") | M44: =IFERROR((1+IFERROR(INDEX(HIST_D!$BT$8:$BT$2617,1)/INDEX(HIST_D!$BT$8:$BT$2617,Control!$F$11)-1,""))*(1+IFERROR(INDEX(HIST_D!$AR$8:$AR$2617,Control!$F$11)/INDEX(HIST_D!$AR$8:$AR$2617,1)-1,""))-1,"") | N44: =IFERROR(F44-F7,"") | O44: =IFERROR(L44-L7,"")
A45: India Nifty 50 | B45: INR | C45: =INDEX(HIST_D!$BU$8:$BU$2617,1) | D45: =IFERROR(INDEX(HIST_D!$BU$8:$BU$2617,1)/INDEX(HIST_D!$BU$8:$BU$2617,Control!$F$8)-1,"") | E45: =IFERROR(INDEX(HIST_D!$AS$8:$AS$2617,Control!$F$8)/INDEX(HIST_D!$AS$8:$AS$2617,1)-1,"") | F45: =IFERROR((1+D45)*(1+E45)-1,"") | G45: =IFERROR(INDEX(HIST_D!$BU$8:$BU$2617,1)/INDEX(HIST_D!$BU$8:$BU$2617,Control!$F$9)-1,"") | H45: =IFERROR(INDEX(HIST_D!$AS$8:$AS$2617,Control!$F$9)/INDEX(HIST_D!$AS$8:$AS$2617,1)-1,"") | I45: =IFERROR((1+G45)*(1+H45)-1,"") | J45: =IFERROR(INDEX(HIST_D!$BU$8:$BU$2617,1)/INDEX(HIST_D!$BU$8:$BU$2617,Control!$F$16)-1,"") | K45: =IFERROR(INDEX(HIST_D!$AS$8:$AS$2617,Control!$F$16)/INDEX(HIST_D!$AS$8:$AS$2617,1)-1,"") | L45: =IFERROR((1+J45)*(1+K45)-1,"") | M45: =IFERROR((1+IFERROR(INDEX(HIST_D!$BU$8:$BU$2617,1)/INDEX(HIST_D!$BU$8:$BU$2617,Control!$F$11)-1,""))*(1+IFERROR(INDEX(HIST_D!$AS$8:$AS$2617,Control!$F$11)/INDEX(HIST_D!$AS$8:$AS$2617,1)-1,""))-1,"") | N45: =IFERROR(F45-F7,"") | O45: =IFERROR(L45-L7,"")
A46: Indonesia JCI | B46: IDR | C46: =INDEX(HIST_D!$BV$8:$BV$2617,1) | D46: =IFERROR(INDEX(HIST_D!$BV$8:$BV$2617,1)/INDEX(HIST_D!$BV$8:$BV$2617,Control!$F$8)-1,"") | E46: =IFERROR(INDEX(HIST_D!$AT$8:$AT$2617,Control!$F$8)/INDEX(HIST_D!$AT$8:$AT$2617,1)-1,"") | F46: =IFERROR((1+D46)*(1+E46)-1,"") | G46: =IFERROR(INDEX(HIST_D!$BV$8:$BV$2617,1)/INDEX(HIST_D!$BV$8:$BV$2617,Control!$F$9)-1,"") | H46: =IFERROR(INDEX(HIST_D!$AT$8:$AT$2617,Control!$F$9)/INDEX(HIST_D!$AT$8:$AT$2617,1)-1,"") | I46: =IFERROR((1+G46)*(1+H46)-1,"") | J46: =IFERROR(INDEX(HIST_D!$BV$8:$BV$2617,1)/INDEX(HIST_D!$BV$8:$BV$2617,Control!$F$16)-1,"") | K46: =IFERROR(INDEX(HIST_D!$AT$8:$AT$2617,Control!$F$16)/INDEX(HIST_D!$AT$8:$AT$2617,1)-1,"") | L46: =IFERROR((1+J46)*(1+K46)-1,"") | M46: =IFERROR((1+IFERROR(INDEX(HIST_D!$BV$8:$BV$2617,1)/INDEX(HIST_D!$BV$8:$BV$2617,Control!$F$11)-1,""))*(1+IFERROR(INDEX(HIST_D!$AT$8:$AT$2617,Control!$F$11)/INDEX(HIST_D!$AT$8:$AT$2617,1)-1,""))-1,"") | N46: =IFERROR(F46-F7,"") | O46: =IFERROR(L46-L7,"")
A47: Korea KOSPI | B47: KRW | C47: =INDEX(HIST_D!$BW$8:$BW$2617,1) | D47: =IFERROR(INDEX(HIST_D!$BW$8:$BW$2617,1)/INDEX(HIST_D!$BW$8:$BW$2617,Control!$F$8)-1,"") | E47: =IFERROR(INDEX(HIST_D!$AU$8:$AU$2617,Control!$F$8)/INDEX(HIST_D!$AU$8:$AU$2617,1)-1,"") | F47: =IFERROR((1+D47)*(1+E47)-1,"") | G47: =IFERROR(INDEX(HIST_D!$BW$8:$BW$2617,1)/INDEX(HIST_D!$BW$8:$BW$2617,Control!$F$9)-1,"") | H47: =IFERROR(INDEX(HIST_D!$AU$8:$AU$2617,Control!$F$9)/INDEX(HIST_D!$AU$8:$AU$2617,1)-1,"") | I47: =IFERROR((1+G47)*(1+H47)-1,"") | J47: =IFERROR(INDEX(HIST_D!$BW$8:$BW$2617,1)/INDEX(HIST_D!$BW$8:$BW$2617,Control!$F$16)-1,"") | K47: =IFERROR(INDEX(HIST_D!$AU$8:$AU$2617,Control!$F$16)/INDEX(HIST_D!$AU$8:$AU$2617,1)-1,"") | L47: =IFERROR((1+J47)*(1+K47)-1,"") | M47: =IFERROR((1+IFERROR(INDEX(HIST_D!$BW$8:$BW$2617,1)/INDEX(HIST_D!$BW$8:$BW$2617,Control!$F$11)-1,""))*(1+IFERROR(INDEX(HIST_D!$AU$8:$AU$2617,Control!$F$11)/INDEX(HIST_D!$AU$8:$AU$2617,1)-1,""))-1,"") | N47: =IFERROR(F47-F7,"") | O47: =IFERROR(L47-L7,"")
A48: Taiwan TAIEX | B48: TWD | C48: =INDEX(HIST_D!$BX$8:$BX$2617,1) | D48: =IFERROR(INDEX(HIST_D!$BX$8:$BX$2617,1)/INDEX(HIST_D!$BX$8:$BX$2617,Control!$F$8)-1,"") | E48: =IFERROR(INDEX(HIST_D!$AV$8:$AV$2617,Control!$F$8)/INDEX(HIST_D!$AV$8:$AV$2617,1)-1,"") | F48: =IFERROR((1+D48)*(1+E48)-1,"") | G48: =IFERROR(INDEX(HIST_D!$BX$8:$BX$2617,1)/INDEX(HIST_D!$BX$8:$BX$2617,Control!$F$9)-1,"") | H48: =IFERROR(INDEX(HIST_D!$AV$8:$AV$2617,Control!$F$9)/INDEX(HIST_D!$AV$8:$AV$2617,1)-1,"") | I48: =IFERROR((1+G48)*(1+H48)-1,"") | J48: =IFERROR(INDEX(HIST_D!$BX$8:$BX$2617,1)/INDEX(HIST_D!$BX$8:$BX$2617,Control!$F$16)-1,"") | K48: =IFERROR(INDEX(HIST_D!$AV$8:$AV$2617,Control!$F$16)/INDEX(HIST_D!$AV$8:$AV$2617,1)-1,"") | L48: =IFERROR((1+J48)*(1+K48)-1,"") | M48: =IFERROR((1+IFERROR(INDEX(HIST_D!$BX$8:$BX$2617,1)/INDEX(HIST_D!$BX$8:$BX$2617,Control!$F$11)-1,""))*(1+IFERROR(INDEX(HIST_D!$AV$8:$AV$2617,Control!$F$11)/INDEX(HIST_D!$AV$8:$AV$2617,1)-1,""))-1,"") | N48: =IFERROR(F48-F7,"") | O48: =IFERROR(L48-L7,"")
A49: Thailand SET | B49: THB | C49: =INDEX(HIST_D!$BY$8:$BY$2617,1) | D49: =IFERROR(INDEX(HIST_D!$BY$8:$BY$2617,1)/INDEX(HIST_D!$BY$8:$BY$2617,Control!$F$8)-1,"") | E49: =IFERROR(INDEX(HIST_D!$AW$8:$AW$2617,Control!$F$8)/INDEX(HIST_D!$AW$8:$AW$2617,1)-1,"") | F49: =IFERROR((1+D49)*(1+E49)-1,"") | G49: =IFERROR(INDEX(HIST_D!$BY$8:$BY$2617,1)/INDEX(HIST_D!$BY$8:$BY$2617,Control!$F$9)-1,"") | H49: =IFERROR(INDEX(HIST_D!$AW$8:$AW$2617,Control!$F$9)/INDEX(HIST_D!$AW$8:$AW$2617,1)-1,"") | I49: =IFERROR((1+G49)*(1+H49)-1,"") | J49: =IFERROR(INDEX(HIST_D!$BY$8:$BY$2617,1)/INDEX(HIST_D!$BY$8:$BY$2617,Control!$F$16)-1,"") | K49: =IFERROR(INDEX(HIST_D!$AW$8:$AW$2617,Control!$F$16)/INDEX(HIST_D!$AW$8:$AW$2617,1)-1,"") | L49: =IFERROR((1+J49)*(1+K49)-1,"") | M49: =IFERROR((1+IFERROR(INDEX(HIST_D!$BY$8:$BY$2617,1)/INDEX(HIST_D!$BY$8:$BY$2617,Control!$F$11)-1,""))*(1+IFERROR(INDEX(HIST_D!$AW$8:$AW$2617,Control!$F$11)/INDEX(HIST_D!$AW$8:$AW$2617,1)-1,""))-1,"") | N49: =IFERROR(F49-F7,"") | O49: =IFERROR(L49-L7,"")
A50: Philippines PSEi | B50: PHP | C50: =INDEX(HIST_D!$BZ$8:$BZ$2617,1) | D50: =IFERROR(INDEX(HIST_D!$BZ$8:$BZ$2617,1)/INDEX(HIST_D!$BZ$8:$BZ$2617,Control!$F$8)-1,"") | E50: =IFERROR(INDEX(HIST_D!$AX$8:$AX$2617,Control!$F$8)/INDEX(HIST_D!$AX$8:$AX$2617,1)-1,"") | F50: =IFERROR((1+D50)*(1+E50)-1,"") | G50: =IFERROR(INDEX(HIST_D!$BZ$8:$BZ$2617,1)/INDEX(HIST_D!$BZ$8:$BZ$2617,Control!$F$9)-1,"") | H50: =IFERROR(INDEX(HIST_D!$AX$8:$AX$2617,Control!$F$9)/INDEX(HIST_D!$AX$8:$AX$2617,1)-1,"") | I50: =IFERROR((1+G50)*(1+H50)-1,"") | J50: =IFERROR(INDEX(HIST_D!$BZ$8:$BZ$2617,1)/INDEX(HIST_D!$BZ$8:$BZ$2617,Control!$F$16)-1,"") | K50: =IFERROR(INDEX(HIST_D!$AX$8:$AX$2617,Control!$F$16)/INDEX(HIST_D!$AX$8:$AX$2617,1)-1,"") | L50: =IFERROR((1+J50)*(1+K50)-1,"") | M50: =IFERROR((1+IFERROR(INDEX(HIST_D!$BZ$8:$BZ$2617,1)/INDEX(HIST_D!$BZ$8:$BZ$2617,Control!$F$11)-1,""))*(1+IFERROR(INDEX(HIST_D!$AX$8:$AX$2617,Control!$F$11)/INDEX(HIST_D!$AX$8:$AX$2617,1)-1,""))-1,"") | N50: =IFERROR(F50-F7,"") | O50: =IFERROR(L50-L7,"")
A51: Malaysia KLCI | B51: MYR | C51: =INDEX(HIST_D!$CA$8:$CA$2617,1) | D51: =IFERROR(INDEX(HIST_D!$CA$8:$CA$2617,1)/INDEX(HIST_D!$CA$8:$CA$2617,Control!$F$8)-1,"") | E51: =IFERROR(INDEX(HIST_D!$AY$8:$AY$2617,Control!$F$8)/INDEX(HIST_D!$AY$8:$AY$2617,1)-1,"") | F51: =IFERROR((1+D51)*(1+E51)-1,"") | G51: =IFERROR(INDEX(HIST_D!$CA$8:$CA$2617,1)/INDEX(HIST_D!$CA$8:$CA$2617,Control!$F$9)-1,"") | H51: =IFERROR(INDEX(HIST_D!$AY$8:$AY$2617,Control!$F$9)/INDEX(HIST_D!$AY$8:$AY$2617,1)-1,"") | I51: =IFERROR((1+G51)*(1+H51)-1,"") | J51: =IFERROR(INDEX(HIST_D!$CA$8:$CA$2617,1)/INDEX(HIST_D!$CA$8:$CA$2617,Control!$F$16)-1,"") | K51: =IFERROR(INDEX(HIST_D!$AY$8:$AY$2617,Control!$F$16)/INDEX(HIST_D!$AY$8:$AY$2617,1)-1,"") | L51: =IFERROR((1+J51)*(1+K51)-1,"") | M51: =IFERROR((1+IFERROR(INDEX(HIST_D!$CA$8:$CA$2617,1)/INDEX(HIST_D!$CA$8:$CA$2617,Control!$F$11)-1,""))*(1+IFERROR(INDEX(HIST_D!$AY$8:$AY$2617,Control!$F$11)/INDEX(HIST_D!$AY$8:$AY$2617,1)-1,""))-1,"") | N51: =IFERROR(F51-F7,"") | O51: =IFERROR(L51-L7,"")
A52: Asia basket (eq-wgt, n=9) | D52: =IFERROR(AVERAGE(D43,D44,D45,D46,D47,D48,D49,D50,D51),"") | E52: =IFERROR(AVERAGE(E43,E44,E45,E46,E47,E48,E49,E50,E51),"") | F52: =IFERROR(AVERAGE(F43,F44,F45,F46,F47,F48,F49,F50,F51),"") | G52: =IFERROR(AVERAGE(G43,G44,G45,G46,G47,G48,G49,G50,G51),"") | H52: =IFERROR(AVERAGE(H43,H44,H45,H46,H47,H48,H49,H50,H51),"") | I52: =IFERROR(AVERAGE(I43,I44,I45,I46,I47,I48,I49,I50,I51),"") | J52: =IFERROR(AVERAGE(J43,J44,J45,J46,J47,J48,J49,J50,J51),"") | K52: =IFERROR(AVERAGE(K43,K44,K45,K46,K47,K48,K49,K50,K51),"") | ... M52: =IFERROR(AVERAGE(M43,M44,M45,M46,M47,M48,M49,M50,M51),"") | N52: =IFERROR(F52-F7,"") | O52: =IFERROR(L52-L7,"")
A53: =IFERROR("Asia: "&TEXT($F$52,"+0.0%;-0.0%")&" in USD on the month ("&TEXT($D$52,"+0.0%;-0.0%")&" local, "&TEXT($E$52,"+0.0%;-0.0%")&" FX), "&TEXT($L$52,"+0.0%;-0.0%")&" YTD, "&TEXT($N$52,"+0.0%;-0.0%")&" vs MSCI World. "&IF($E$52<-0.005,"The currency is taxing the equity story here.",IF($E$52>0.005,"The currency is adding to it.","The currency is neutral; this is an earnings and multiple story, not an FX one.")),"")
A55: COMMENT — EQUITIES
A56: =IFERROR("EM equities: MSCI EM "&TEXT($F$6,"+0.0%;-0.0%")&" on the month and "&TEXT($L$6,"+0.0%;-0.0%")&" YTD in USD, against MSCI World at "&TEXT($F$7,"+0.0%;-0.0%")&" and "&TEXT($L$7,"+0.0%;-0.0%")&". "&IF($L$6>$L$7,"EM is ahead of DM year-to-date, which is the part of the story that does not depend on the rates call — it is earnings, and it is concentrated in the semiconductor complex.","EM is behind DM year-to-date; the rates backdrop is doing more damage to the equity leg than to credit.")&" The regional dispersion below is wider than the aggregate suggests, and the FX column is where most of it sits.","")
A58: An equity index is not rate-sensitive the way a long-duration credit index is. If EM equity is firm while EM credit is soft, that is a duration result, not a risk-appetite result — and it is corroborating evidence, not a separate argument.

Sheet Credit
A1: EM USD CREDIT — spread leg and rates leg, never netted
A2: Total return comes straight from the total-return sub-indices. The decomposition below is shown leg by leg with the residual left visible; it is not a substitute for the index return and is not netted into a single number anywhere.
A4: SPREADS
A5: Series | B5: Unit | C5: Level | D5: 1D | E5: 1W | F5: 1M | G5: 3M | H5: 6M | I5: YTD | J5: 1Y | K5: 1y min | L5: 1y max | M5: %ile 1y | N5: %ile 3y | O5: %ile 5y | P5: z (5y)
A6: EM USD Aggregate OAS | B6: bp | C6: =INDEX(HIST_D!$Q$8:$Q$2617,1) | D6: =IFERROR(INDEX(HIST_D!$Q$8:$Q$2617,1)-INDEX(HIST_D!$Q$8:$Q$2617,Control!$F$6),"") | E6: =IFERROR(INDEX(HIST_D!$Q$8:$Q$2617,1)-INDEX(HIST_D!$Q$8:$Q$2617,Control!$F$7),"") | F6: =IFERROR(INDEX(HIST_D!$Q$8:$Q$2617,1)-INDEX(HIST_D!$Q$8:$Q$2617,Control!$F$8),"") | G6: =IFERROR(INDEX(HIST_D!$Q$8:$Q$2617,1)-INDEX(HIST_D!$Q$8:$Q$2617,Control!$F$9),"") | H6: =IFERROR(INDEX(HIST_D!$Q$8:$Q$2617,1)-INDEX(HIST_D!$Q$8:$Q$2617,Control!$F$10),"") | I6: =IFERROR(INDEX(HIST_D!$Q$8:$Q$2617,1)-INDEX(HIST_D!$Q$8:$Q$2617,Control!$F$16),"") | J6: =IFERROR(INDEX(HIST_D!$Q$8:$Q$2617,1)-INDEX(HIST_D!$Q$8:$Q$2617,Control!$F$11),"") | K6: =IFERROR(MIN(HIST_D!$Q$8:INDEX(HIST_D!$Q$8:$Q$2617,Control!$F$11)),"") | L6: =IFERROR(MAX(HIST_D!$Q$8:INDEX(HIST_D!$Q$8:$Q$2617,Control!$F$11)),"") | M6: =IFERROR(PERCENTRANK(HIST_D!$Q$8:INDEX(HIST_D!$Q$8:$Q$2617,Control!$F$11),INDEX(HIST_D!$Q$8:$Q$2617,1)),"") | N6: =IFERROR(PERCENTRANK(HIST_D!$Q$8:INDEX(HIST_D!$Q$8:$Q$2617,Control!$F$13),INDEX(HIST_D!$Q$8:$Q$2617,1)),"") | O6: =IFERROR(PERCENTRANK(HIST_D!$Q$8:INDEX(HIST_D!$Q$8:$Q$2617,Control!$F$14),INDEX(HIST_D!$Q$8:$Q$2617,1)),"") | P6: =IFERROR((INDEX(HIST_D!$Q$8:$Q$2617,1)-AVERAGE(HIST_D!$Q$8:INDEX(HIST_D!$Q$8:$Q$2617,Control!$F$14)))/STDEV(HIST_D!$Q$8:INDEX(HIST_D!$Q$8:$Q$2617,Control!$F$14)),"")
A7: EM USD Sovereign OAS | B7: bp | C7: =INDEX(HIST_D!$S$8:$S$2617,1) | D7: =IFERROR(INDEX(HIST_D!$S$8:$S$2617,1)-INDEX(HIST_D!$S$8:$S$2617,Control!$F$6),"") | E7: =IFERROR(INDEX(HIST_D!$S$8:$S$2617,1)-INDEX(HIST_D!$S$8:$S$2617,Control!$F$7),"") | F7: =IFERROR(INDEX(HIST_D!$S$8:$S$2617,1)-INDEX(HIST_D!$S$8:$S$2617,Control!$F$8),"") | G7: =IFERROR(INDEX(HIST_D!$S$8:$S$2617,1)-INDEX(HIST_D!$S$8:$S$2617,Control!$F$9),"") | H7: =IFERROR(INDEX(HIST_D!$S$8:$S$2617,1)-INDEX(HIST_D!$S$8:$S$2617,Control!$F$10),"") | I7: =IFERROR(INDEX(HIST_D!$S$8:$S$2617,1)-INDEX(HIST_D!$S$8:$S$2617,Control!$F$16),"") | J7: =IFERROR(INDEX(HIST_D!$S$8:$S$2617,1)-INDEX(HIST_D!$S$8:$S$2617,Control!$F$11),"") | K7: =IFERROR(MIN(HIST_D!$S$8:INDEX(HIST_D!$S$8:$S$2617,Control!$F$11)),"") | L7: =IFERROR(MAX(HIST_D!$S$8:INDEX(HIST_D!$S$8:$S$2617,Control!$F$11)),"") | M7: =IFERROR(PERCENTRANK(HIST_D!$S$8:INDEX(HIST_D!$S$8:$S$2617,Control!$F$11),INDEX(HIST_D!$S$8:$S$2617,1)),"") | N7: =IFERROR(PERCENTRANK(HIST_D!$S$8:INDEX(HIST_D!$S$8:$S$2617,Control!$F$13),INDEX(HIST_D!$S$8:$S$2617,1)),"") | O7: =IFERROR(PERCENTRANK(HIST_D!$S$8:INDEX(HIST_D!$S$8:$S$2617,Control!$F$14),INDEX(HIST_D!$S$8:$S$2617,1)),"") | P7: =IFERROR((INDEX(HIST_D!$S$8:$S$2617,1)-AVERAGE(HIST_D!$S$8:INDEX(HIST_D!$S$8:$S$2617,Control!$F$14)))/STDEV(HIST_D!$S$8:INDEX(HIST_D!$S$8:$S$2617,Control!$F$14)),"")
A8: CDX EM 5Y | B8: bp | C8: =INDEX(HIST_D!$W$8:$W$2617,1) | D8: =IFERROR(INDEX(HIST_D!$W$8:$W$2617,1)-INDEX(HIST_D!$W$8:$W$2617,Control!$F$6),"") | E8: =IFERROR(INDEX(HIST_D!$W$8:$W$2617,1)-INDEX(HIST_D!$W$8:$W$2617,Control!$F$7),"") | F8: =IFERROR(INDEX(HIST_D!$W$8:$W$2617,1)-INDEX(HIST_D!$W$8:$W$2617,Control!$F$8),"") | G8: =IFERROR(INDEX(HIST_D!$W$8:$W$2617,1)-INDEX(HIST_D!$W$8:$W$2617,Control!$F$9),"") | H8: =IFERROR(INDEX(HIST_D!$W$8:$W$2617,1)-INDEX(HIST_D!$W$8:$W$2617,Control!$F$10),"") | I8: =IFERROR(INDEX(HIST_D!$W$8:$W$2617,1)-INDEX(HIST_D!$W$8:$W$2617,Control!$F$16),"") | J8: =IFERROR(INDEX(HIST_D!$W$8:$W$2617,1)-INDEX(HIST_D!$W$8:$W$2617,Control!$F$11),"") | K8: =IFERROR(MIN(HIST_D!$W$8:INDEX(HIST_D!$W$8:$W$2617,Control!$F$11)),"") | L8: =IFERROR(MAX(HIST_D!$W$8:INDEX(HIST_D!$W$8:$W$2617,Control!$F$11)),"") | M8: =IFERROR(PERCENTRANK(HIST_D!$W$8:INDEX(HIST_D!$W$8:$W$2617,Control!$F$11),INDEX(HIST_D!$W$8:$W$2617,1)),"") | N8: =IFERROR(PERCENTRANK(HIST_D!$W$8:INDEX(HIST_D!$W$8:$W$2617,Control!$F$13),INDEX(HIST_D!$W$8:$W$2617,1)),"") | O8: =IFERROR(PERCENTRANK(HIST_D!$W$8:INDEX(HIST_D!$W$8:$W$2617,Control!$F$14),INDEX(HIST_D!$W$8:$W$2617,1)),"") | P8: =IFERROR((INDEX(HIST_D!$W$8:$W$2617,1)-AVERAGE(HIST_D!$W$8:INDEX(HIST_D!$W$8:$W$2617,Control!$F$14)))/STDEV(HIST_D!$W$8:INDEX(HIST_D!$W$8:$W$2617,Control!$F$14)),"")
A9: US IG OAS | B9: bp | C9: =INDEX(HIST_D!$O$8:$O$2617,1) | D9: =IFERROR(INDEX(HIST_D!$O$8:$O$2617,1)-INDEX(HIST_D!$O$8:$O$2617,Control!$F$6),"") | E9: =IFERROR(INDEX(HIST_D!$O$8:$O$2617,1)-INDEX(HIST_D!$O$8:$O$2617,Control!$F$7),"") | F9: =IFERROR(INDEX(HIST_D!$O$8:$O$2617,1)-INDEX(HIST_D!$O$8:$O$2617,Control!$F$8),"") | G9: =IFERROR(INDEX(HIST_D!$O$8:$O$2617,1)-INDEX(HIST_D!$O$8:$O$2617,Control!$F$9),"") | H9: =IFERROR(INDEX(HIST_D!$O$8:$O$2617,1)-INDEX(HIST_D!$O$8:$O$2617,Control!$F$10),"") | I9: =IFERROR(INDEX(HIST_D!$O$8:$O$2617,1)-INDEX(HIST_D!$O$8:$O$2617,Control!$F$16),"") | J9: =IFERROR(INDEX(HIST_D!$O$8:$O$2617,1)-INDEX(HIST_D!$O$8:$O$2617,Control!$F$11),"") | K9: =IFERROR(MIN(HIST_D!$O$8:INDEX(HIST_D!$O$8:$O$2617,Control!$F$11)),"") | L9: =IFERROR(MAX(HIST_D!$O$8:INDEX(HIST_D!$O$8:$O$2617,Control!$F$11)),"") | M9: =IFERROR(PERCENTRANK(HIST_D!$O$8:INDEX(HIST_D!$O$8:$O$2617,Control!$F$11),INDEX(HIST_D!$O$8:$O$2617,1)),"") | N9: =IFERROR(PERCENTRANK(HIST_D!$O$8:INDEX(HIST_D!$O$8:$O$2617,Control!$F$13),INDEX(HIST_D!$O$8:$O$2617,1)),"") | O9: =IFERROR(PERCENTRANK(HIST_D!$O$8:INDEX(HIST_D!$O$8:$O$2617,Control!$F$14),INDEX(HIST_D!$O$8:$O$2617,1)),"") | P9: =IFERROR((INDEX(HIST_D!$O$8:$O$2617,1)-AVERAGE(HIST_D!$O$8:INDEX(HIST_D!$O$8:$O$2617,Control!$F$14)))/STDEV(HIST_D!$O$8:INDEX(HIST_D!$O$8:$O$2617,Control!$F$14)),"")
A10: US HY OAS | B10: bp | C10: =INDEX(HIST_D!$P$8:$P$2617,1) | D10: =IFERROR(INDEX(HIST_D!$P$8:$P$2617,1)-INDEX(HIST_D!$P$8:$P$2617,Control!$F$6),"") | E10: =IFERROR(INDEX(HIST_D!$P$8:$P$2617,1)-INDEX(HIST_D!$P$8:$P$2617,Control!$F$7),"") | F10: =IFERROR(INDEX(HIST_D!$P$8:$P$2617,1)-INDEX(HIST_D!$P$8:$P$2617,Control!$F$8),"") | G10: =IFERROR(INDEX(HIST_D!$P$8:$P$2617,1)-INDEX(HIST_D!$P$8:$P$2617,Control!$F$9),"") | H10: =IFERROR(INDEX(HIST_D!$P$8:$P$2617,1)-INDEX(HIST_D!$P$8:$P$2617,Control!$F$10),"") | I10: =IFERROR(INDEX(HIST_D!$P$8:$P$2617,1)-INDEX(HIST_D!$P$8:$P$2617,Control!$F$16),"") | J10: =IFERROR(INDEX(HIST_D!$P$8:$P$2617,1)-INDEX(HIST_D!$P$8:$P$2617,Control!$F$11),"") | K10: =IFERROR(MIN(HIST_D!$P$8:INDEX(HIST_D!$P$8:$P$2617,Control!$F$11)),"") | L10: =IFERROR(MAX(HIST_D!$P$8:INDEX(HIST_D!$P$8:$P$2617,Control!$F$11)),"") | M10: =IFERROR(PERCENTRANK(HIST_D!$P$8:INDEX(HIST_D!$P$8:$P$2617,Control!$F$11),INDEX(HIST_D!$P$8:$P$2617,1)),"") | N10: =IFERROR(PERCENTRANK(HIST_D!$P$8:INDEX(HIST_D!$P$8:$P$2617,Control!$F$13),INDEX(HIST_D!$P$8:$P$2617,1)),"") | O10: =IFERROR(PERCENTRANK(HIST_D!$P$8:INDEX(HIST_D!$P$8:$P$2617,Control!$F$14),INDEX(HIST_D!$P$8:$P$2617,1)),"") | P10: =IFERROR((INDEX(HIST_D!$P$8:$P$2617,1)-AVERAGE(HIST_D!$P$8:INDEX(HIST_D!$P$8:$P$2617,Control!$F$14)))/STDEV(HIST_D!$P$8:INDEX(HIST_D!$P$8:$P$2617,Control!$F$14)),"")
A11: EM USD Agg OAS less US IG | B11: bp | C11: =INDEX(HIST_D!$EB$8:$EB$2617,1) | D11: =IFERROR(INDEX(HIST_D!$EB$8:$EB$2617,1)-INDEX(HIST_D!$EB$8:$EB$2617,Control!$F$6),"") | E11: =IFERROR(INDEX(HIST_D!$EB$8:$EB$2617,1)-INDEX(HIST_D!$EB$8:$EB$2617,Control!$F$7),"") | F11: =IFERROR(INDEX(HIST_D!$EB$8:$EB$2617,1)-INDEX(HIST_D!$EB$8:$EB$2617,Control!$F$8),"") | G11: =IFERROR(INDEX(HIST_D!$EB$8:$EB$2617,1)-INDEX(HIST_D!$EB$8:$EB$2617,Control!$F$9),"") | H11: =IFERROR(INDEX(HIST_D!$EB$8:$EB$2617,1)-INDEX(HIST_D!$EB$8:$EB$2617,Control!$F$10),"") | I11: =IFERROR(INDEX(HIST_D!$EB$8:$EB$2617,1)-INDEX(HIST_D!$EB$8:$EB$2617,Control!$F$16),"") | J11: =IFERROR(INDEX(HIST_D!$EB$8:$EB$2617,1)-INDEX(HIST_D!$EB$8:$EB$2617,Control!$F$11),"") | K11: =IFERROR(MIN(HIST_D!$EB$8:INDEX(HIST_D!$EB$8:$EB$2617,Control!$F$11)),"") | L11: =IFERROR(MAX(HIST_D!$EB$8:INDEX(HIST_D!$EB$8:$EB$2617,Control!$F$11)),"") | M11: =IFERROR(PERCENTRANK(HIST_D!$EB$8:INDEX(HIST_D!$EB$8:$EB$2617,Control!$F$11),INDEX(HIST_D!$EB$8:$EB$2617,1)),"") | N11: =IFERROR(PERCENTRANK(HIST_D!$EB$8:INDEX(HIST_D!$EB$8:$EB$2617,Control!$F$13),INDEX(HIST_D!$EB$8:$EB$2617,1)),"") | O11: =IFERROR(PERCENTRANK(HIST_D!$EB$8:INDEX(HIST_D!$EB$8:$EB$2617,Control!$F$14),INDEX(HIST_D!$EB$8:$EB$2617,1)),"") | P11: =IFERROR((INDEX(HIST_D!$EB$8:$EB$2617,1)-AVERAGE(HIST_D!$EB$8:INDEX(HIST_D!$EB$8:$EB$2617,Control!$F$14)))/STDEV(HIST_D!$EB$8:INDEX(HIST_D!$EB$8:$EB$2617,Control!$F$14)),"")
A12: EM / US HY OAS ratio | B12: x | C12: =INDEX(HIST_D!$EC$8:$EC$2617,1) | D12: =IFERROR(INDEX(HIST_D!$EC$8:$EC$2617,1)-INDEX(HIST_D!$EC$8:$EC$2617,Control!$F$6),"") | E12: =IFERROR(INDEX(HIST_D!$EC$8:$EC$2617,1)-INDEX(HIST_D!$EC$8:$EC$2617,Control!$F$7),"") | F12: =IFERROR(INDEX(HIST_D!$EC$8:$EC$2617,1)-INDEX(HIST_D!$EC$8:$EC$2617,Control!$F$8),"") | G12: =IFERROR(INDEX(HIST_D!$EC$8:$EC$2617,1)-INDEX(HIST_D!$EC$8:$EC$2617,Control!$F$9),"") | H12: =IFERROR(INDEX(HIST_D!$EC$8:$EC$2617,1)-INDEX(HIST_D!$EC$8:$EC$2617,Control!$F$10),"") | I12: =IFERROR(INDEX(HIST_D!$EC$8:$EC$2617,1)-INDEX(HIST_D!$EC$8:$EC$2617,Control!$F$16),"") | J12: =IFERROR(INDEX(HIST_D!$EC$8:$EC$2617,1)-INDEX(HIST_D!$EC$8:$EC$2617,Control!$F$11),"") | K12: =IFERROR(MIN(HIST_D!$EC$8:INDEX(HIST_D!$EC$8:$EC$2617,Control!$F$11)),"") | L12: =IFERROR(MAX(HIST_D!$EC$8:INDEX(HIST_D!$EC$8:$EC$2617,Control!$F$11)),"") | M12: =IFERROR(PERCENTRANK(HIST_D!$EC$8:INDEX(HIST_D!$EC$8:$EC$2617,Control!$F$11),INDEX(HIST_D!$EC$8:$EC$2617,1)),"") | N12: =IFERROR(PERCENTRANK(HIST_D!$EC$8:INDEX(HIST_D!$EC$8:$EC$2617,Control!$F$13),INDEX(HIST_D!$EC$8:$EC$2617,1)),"") | O12: =IFERROR(PERCENTRANK(HIST_D!$EC$8:INDEX(HIST_D!$EC$8:$EC$2617,Control!$F$14),INDEX(HIST_D!$EC$8:$EC$2617,1)),"") | P12: =IFERROR((INDEX(HIST_D!$EC$8:$EC$2617,1)-AVERAGE(HIST_D!$EC$8:INDEX(HIST_D!$EC$8:$EC$2617,Control!$F$14)))/STDEV(HIST_D!$EC$8:INDEX(HIST_D!$EC$8:$EC$2617,Control!$F$14)),"")
A13: EMBIGD stripped spread (embi_tracker.py) | B13: bp | C13: =Control!$B$14 | D13: 1M ago (bp) → | E13: 218 | F13: =IFERROR($C13-$E13,"") | H13: INPUT. Chain-link across the 04-Sep-26 JPM methodology break before using this.
A15: REALISED TOTAL RETURN — from the total-return sub-indices (end/start - 1)
A16: Index | D16: 1D | E16: 1W | F16: 1M | G16: 3M | H16: 6M | I16: YTD | J16: 1Y
A17: Bbg EM USD Aggregate | D17: =IFERROR(INDEX(HIST_D!$R$8:$R$2617,1)/INDEX(HIST_D!$R$8:$R$2617,Control!$F$6)-1,"") | E17: =IFERROR(INDEX(HIST_D!$R$8:$R$2617,1)/INDEX(HIST_D!$R$8:$R$2617,Control!$F$7)-1,"") | F17: =IFERROR(INDEX(HIST_D!$R$8:$R$2617,1)/INDEX(HIST_D!$R$8:$R$2617,Control!$F$8)-1,"") | G17: =IFERROR(INDEX(HIST_D!$R$8:$R$2617,1)/INDEX(HIST_D!$R$8:$R$2617,Control!$F$9)-1,"") | H17: =IFERROR(INDEX(HIST_D!$R$8:$R$2617,1)/INDEX(HIST_D!$R$8:$R$2617,Control!$F$10)-1,"") | I17: =IFERROR(INDEX(HIST_D!$R$8:$R$2617,1)/INDEX(HIST_D!$R$8:$R$2617,Control!$F$16)-1,"") | J17: =IFERROR(INDEX(HIST_D!$R$8:$R$2617,1)/INDEX(HIST_D!$R$8:$R$2617,Control!$F$11)-1,"")
A18: Bbg EM USD Sovereign | D18: =IFERROR(INDEX(HIST_D!$T$8:$T$2617,1)/INDEX(HIST_D!$T$8:$T$2617,Control!$F$6)-1,"") | E18: =IFERROR(INDEX(HIST_D!$T$8:$T$2617,1)/INDEX(HIST_D!$T$8:$T$2617,Control!$F$7)-1,"") | F18: =IFERROR(INDEX(HIST_D!$T$8:$T$2617,1)/INDEX(HIST_D!$T$8:$T$2617,Control!$F$8)-1,"") | G18: =IFERROR(INDEX(HIST_D!$T$8:$T$2617,1)/INDEX(HIST_D!$T$8:$T$2617,Control!$F$9)-1,"") | H18: =IFERROR(INDEX(HIST_D!$T$8:$T$2617,1)/INDEX(HIST_D!$T$8:$T$2617,Control!$F$10)-1,"") | I18: =IFERROR(INDEX(HIST_D!$T$8:$T$2617,1)/INDEX(HIST_D!$T$8:$T$2617,Control!$F$16)-1,"") | J18: =IFERROR(INDEX(HIST_D!$T$8:$T$2617,1)/INDEX(HIST_D!$T$8:$T$2617,Control!$F$11)-1,"")
A19: JPM EMBI Global Diversified | D19: =IFERROR(INDEX(HIST_D!$U$8:$U$2617,1)/INDEX(HIST_D!$U$8:$U$2617,Control!$F$6)-1,"") | E19: =IFERROR(INDEX(HIST_D!$U$8:$U$2617,1)/INDEX(HIST_D!$U$8:$U$2617,Control!$F$7)-1,"") | F19: =IFERROR(INDEX(HIST_D!$U$8:$U$2617,1)/INDEX(HIST_D!$U$8:$U$2617,Control!$F$8)-1,"") | G19: =IFERROR(INDEX(HIST_D!$U$8:$U$2617,1)/INDEX(HIST_D!$U$8:$U$2617,Control!$F$9)-1,"") | H19: =IFERROR(INDEX(HIST_D!$U$8:$U$2617,1)/INDEX(HIST_D!$U$8:$U$2617,Control!$F$10)-1,"") | I19: =IFERROR(INDEX(HIST_D!$U$8:$U$2617,1)/INDEX(HIST_D!$U$8:$U$2617,Control!$F$16)-1,"") | J19: =IFERROR(INDEX(HIST_D!$U$8:$U$2617,1)/INDEX(HIST_D!$U$8:$U$2617,Control!$F$11)-1,"")
A20: JPM CEMBI Broad Diversified | D20: =IFERROR(INDEX(HIST_D!$V$8:$V$2617,1)/INDEX(HIST_D!$V$8:$V$2617,Control!$F$6)-1,"") | E20: =IFERROR(INDEX(HIST_D!$V$8:$V$2617,1)/INDEX(HIST_D!$V$8:$V$2617,Control!$F$7)-1,"") | F20: =IFERROR(INDEX(HIST_D!$V$8:$V$2617,1)/INDEX(HIST_D!$V$8:$V$2617,Control!$F$8)-1,"") | G20: =IFERROR(INDEX(HIST_D!$V$8:$V$2617,1)/INDEX(HIST_D!$V$8:$V$2617,Control!$F$9)-1,"") | H20: =IFERROR(INDEX(HIST_D!$V$8:$V$2617,1)/INDEX(HIST_D!$V$8:$V$2617,Control!$F$10)-1,"") | I20: =IFERROR(INDEX(HIST_D!$V$8:$V$2617,1)/INDEX(HIST_D!$V$8:$V$2617,Control!$F$16)-1,"") | J20: =IFERROR(INDEX(HIST_D!$V$8:$V$2617,1)/INDEX(HIST_D!$V$8:$V$2617,Control!$F$11)-1,"")
A21: Duration-derived decompositions are not used here. Total return is the index, full stop.
A23: DECOMPOSITION OF THE MOVE — each leg on its own row, residual left visible
A24: Index duration and YTW are the inputs on Control (B12, B13). The rates leg uses the UST tenor named on each row; neither leg is combined with the other before you see it.
A25: Component | F25: 1M | G25: 3M | I25: YTD
A26: Carry (YTW x window/262) | F26: =IFERROR(Control!$B$13/100*(Control!$F$8-1)/262,"") | G26: =IFERROR(Control!$B$13/100*(Control!$F$9-1)/262,"") | I26: =IFERROR(Control!$B$13/100*(Control!$F$16-1)/262,"")
A27: Rates leg (-D x d UST 10Y) | F27: =IFERROR(-Control!$B$12*(INDEX(HIST_D!$D$8:$D$2617,1)-INDEX(HIST_D!$D$8:$D$2617,Control!$F$8))*100/10000,"") | G27: =IFERROR(-Control!$B$12*(INDEX(HIST_D!$D$8:$D$2617,1)-INDEX(HIST_D!$D$8:$D$2617,Control!$F$9))*100/10000,"") | I27: =IFERROR(-Control!$B$12*(INDEX(HIST_D!$D$8:$D$2617,1)-INDEX(HIST_D!$D$8:$D$2617,Control!$F$16))*100/10000,"")
A28: Rates leg, 5Y reference (-D x d UST 5Y) | F28: =IFERROR(-Control!$B$12*(INDEX(HIST_D!$C$8:$C$2617,1)-INDEX(HIST_D!$C$8:$C$2617,Control!$F$8))*100/10000,"") | G28: =IFERROR(-Control!$B$12*(INDEX(HIST_D!$C$8:$C$2617,1)-INDEX(HIST_D!$C$8:$C$2617,Control!$F$9))*100/10000,"") | I28: =IFERROR(-Control!$B$12*(INDEX(HIST_D!$C$8:$C$2617,1)-INDEX(HIST_D!$C$8:$C$2617,Control!$F$16))*100/10000,"")
A29: Spread leg (-D x d EM USD Agg OAS) | F29: =IFERROR(-Control!$B$12*(INDEX(HIST_D!$Q$8:$Q$2617,1)-INDEX(HIST_D!$Q$8:$Q$2617,Control!$F$8))/10000,"") | G29: =IFERROR(-Control!$B$12*(INDEX(HIST_D!$Q$8:$Q$2617,1)-INDEX(HIST_D!$Q$8:$Q$2617,Control!$F$9))/10000,"") | I29: =IFERROR(-Control!$B$12*(INDEX(HIST_D!$Q$8:$Q$2617,1)-INDEX(HIST_D!$Q$8:$Q$2617,Control!$F$16))/10000,"")
A30: Sum of carry + rates leg (10Y) + spread leg | F30: =IFERROR(F26+F27+F29,"") | G30: =IFERROR(G26+G27+G29,"") | I30: =IFERROR(I26+I27+I29,"")
A31: Realised index total return (Bbg EM USD Agg) | F31: =F17 | G31: =G17 | I31: =I17
A32: Residual (realised less sum) | F32: =IFERROR(F31-F30,"") | G32: =IFERROR(G31-G30,"") | I32: =IFERROR(I31-I30,"")
A33: Spread leg using the EMBIGD stripped spread instead (1M only) | F33: =IFERROR(-Control!$B$12*($C13-$E13)/10000,"")
A35: Read: when the rates leg is the whole of a negative month and the spread leg is flat or positive, the asset class is not being repriced for credit — it is being repriced for US duration, and the carry keeps accruing underneath it.
A36: EM USD CREDIT BY REGION — fed from embi_tracker.py, not from Bloomberg
A37: Deliberate. There is no Bloomberg ticker in this workbook I trust for regional EMBIGD spread and return, and the tracker already produces the region breakdown. JPM's own regions are Africa / Asia / Europe / Latin America / Middle East — fold Africa into Middle East & Africa below so South Africa, Nigeria, Egypt, Angola and Ghana have a home. Enter total return in percent (type -0.22 for -0.22%).
A38: Region | B38: Index weight (%) | C38: Spread now (bp) | D38: Spread 1M ago (bp) | E38: d 1M (bp) | F38: TR 1M (%) | G38: TR 3M (%) | H38: TR YTD (%) | I38: d 1M vs EM (bp) | J38: TR 1M vs EM (pp)
A39: LatAm | E39: =IF(OR($C39="",$D39=""),"",$C39-$D39) | I39: =IF(OR($E39="",$E$43=""),"",$E39-$E$43) | J39: =IF(OR($F39="",$F$43=""),"",$F39-$F$43)
A40: EM Europe | E40: =IF(OR($C40="",$D40=""),"",$C40-$D40) | I40: =IF(OR($E40="",$E$43=""),"",$E40-$E$43) | J40: =IF(OR($F40="",$F$43=""),"",$F40-$F$43)
A41: Middle East & Africa | E41: =IF(OR($C41="",$D41=""),"",$C41-$D41) | I41: =IF(OR($E41="",$E$43=""),"",$E41-$E$43) | J41: =IF(OR($F41="",$F$43=""),"",$F41-$F$43)
A42: Asia | E42: =IF(OR($C42="",$D42=""),"",$C42-$D42) | I42: =IF(OR($E42="",$E$43=""),"",$E42-$E$43) | J42: =IF(OR($F42="",$F$43=""),"",$F42-$F$43)
A43: EM total (EMBIGD) | B43: 100 | C43: =Control!$B$14 | D43: =$E13 | E43: =IF(OR($C43="",$D43=""),"",$C43-$D43)
A45: =IF($C39="","LatAm: awaiting the tracker input.","LatAm: "&TEXT($C39,"0")&"bp, "&TEXT($E39,"+0;-0")&"bp on the month ("&TEXT($I39,"+0;-0")&"bp vs EM), total return "&TEXT($F39,"+0.00;-0.00")&"%. "&IF($E39<0,"Spread tightened into the Treasury move — the loss here is duration, not credit.",IF($E39<10,"Spread broadly held; the return is a rates outcome.","Spread widened materially — this region is being repriced for credit, not just rates.")))
A46: =IF($C40="","EM Europe: awaiting the tracker input.","EM Europe: "&TEXT($C40,"0")&"bp, "&TEXT($E40,"+0;-0")&"bp on the month ("&TEXT($I40,"+0;-0")&"bp vs EM), total return "&TEXT($F40,"+0.00;-0.00")&"%. "&IF($E40<0,"Spread tightened into the Treasury move — the loss here is duration, not credit.",IF($E40<10,"Spread broadly held; the return is a rates outcome.","Spread widened materially — this region is being repriced for credit, not just rates.")))
A47: =IF($C41="","Middle East & Africa: awaiting the tracker input.","Middle East & Africa: "&TEXT($C41,"0")&"bp, "&TEXT($E41,"+0;-0")&"bp on the month ("&TEXT($I41,"+0;-0")&"bp vs EM), total return "&TEXT($F41,"+0.00;-0.00")&"%. "&IF($E41<0,"Spread tightened into the Treasury move — the loss here is duration, not credit.",IF($E41<10,"Spread broadly held; the return is a rates outcome.","Spread widened materially — this region is being repriced for credit, not just rates.")))
A48: =IF($C42="","Asia: awaiting the tracker input.","Asia: "&TEXT($C42,"0")&"bp, "&TEXT($E42,"+0;-0")&"bp on the month ("&TEXT($I42,"+0;-0")&"bp vs EM), total return "&TEXT($F42,"+0.00;-0.00")&"%. "&IF($E42<0,"Spread tightened into the Treasury move — the loss here is duration, not credit.",IF($E42<10,"Spread broadly held; the return is a rates outcome.","Spread widened materially — this region is being repriced for credit, not just rates.")))
A50: COMMENT — EM USD CREDIT
A51: =IFERROR("EM USD credit: carry "&TEXT($F$26,"+0.00%;-0.00%")&", rates leg "&TEXT($F$27,"+0.00%;-0.00%")&", spread leg "&TEXT($F$29,"+0.00%;-0.00%")&" over the past month. "&IF(ABS($F$27)>ABS($F$29),"The rates leg dominates, so this is a duration event and the carry keeps accruing underneath it.","The spread leg dominates, so this is a credit repricing and the digestion argument does not hold for this window.")&" EM USD Aggregate OAS sits at "&TEXT($C$6,"0")&"bp, "&TEXT($C$6-$C$9,"0")&"bp over US IG, at the "&TEXT($M$6,"0%")&" percentile of its own last five years — "&IF($O$6<0.25,"which is the weak point of the case: there is very little spread cushion left to absorb a genuine risk event.","which leaves some room before valuation becomes the binding constraint."),"")
A53: Regional dispersion in credit is mostly a duration and rating story, not a geography story: Middle East and Asia index weight is long-dated investment grade, LatAm carries more high yield and less duration. That is why LatAm can outperform in a rates selloff and underperform in a risk selloff, and it is the single most useful thing to say about the regional table above.

Sheet Passthrough
A1: PASS-THROUGH — how much of the US move each region actually took
A2: Pass-through = d(local 10Y) / d(UST 10Y) over the same window. Below 1.0 means the local curve absorbed less than the US curve; below 0 means it moved the other way. The ratio is suppressed as n/m when the US move over that window is under 25bp, because a ratio off a small base is noise.
A4: LATAM
A5: Market | B5: Local 10Y (%) | C5: d 1M (bp) | D5: d 3M (bp) | E5: d 6M (bp) | F5: d 1Y (bp) | G5: PT 1M | H5: PT 3M | I5: PT 6M | J5: PT 1Y | K5: PT 3Y | L5: FX 1M | M5: Local less UST (bp) | N5: %ile 5y (gap) | O5: Verdict
A6: Brazil 10Y | B6: =INDEX(HIST_D!$CB$8:$CB$2617,1) | C6: =IFERROR((INDEX(HIST_D!$CB$8:$CB$2617,1)-INDEX(HIST_D!$CB$8:$CB$2617,Control!$F$8))*100,"") | D6: =IFERROR((INDEX(HIST_D!$CB$8:$CB$2617,1)-INDEX(HIST_D!$CB$8:$CB$2617,Control!$F$9))*100,"") | E6: =IFERROR((INDEX(HIST_D!$CB$8:$CB$2617,1)-INDEX(HIST_D!$CB$8:$CB$2617,Control!$F$10))*100,"") | F6: =IFERROR((INDEX(HIST_D!$CB$8:$CB$2617,1)-INDEX(HIST_D!$CB$8:$CB$2617,Control!$F$11))*100,"") | G6: =IF(ABS(((INDEX(HIST_D!$D$8:$D$2617,1)-INDEX(HIST_D!$D$8:$D$2617,Control!$F$8))*100))<25,"n/m",IFERROR((((INDEX(HIST_D!$CB$8:$CB$2617,1)-INDEX(HIST_D!$CB$8:$CB$2617,Control!$F$8))*100))/(((INDEX(HIST_D!$D$8:$D$2617,1)-INDEX(HIST_D!$D$8:$D$2617,Control!$F$8))*100)),"n/m")) | H6: =IF(ABS(((INDEX(HIST_D!$D$8:$D$2617,1)-INDEX(HIST_D!$D$8:$D$2617,Control!$F$9))*100))<25,"n/m",IFERROR((((INDEX(HIST_D!$CB$8:$CB$2617,1)-INDEX(HIST_D!$CB$8:$CB$2617,Control!$F$9))*100))/(((INDEX(HIST_D!$D$8:$D$2617,1)-INDEX(HIST_D!$D$8:$D$2617,Control!$F$9))*100)),"n/m")) | I6: =IF(ABS(((INDEX(HIST_D!$D$8:$D$2617,1)-INDEX(HIST_D!$D$8:$D$2617,Control!$F$10))*100))<25,"n/m",IFERROR((((INDEX(HIST_D!$CB$8:$CB$2617,1)-INDEX(HIST_D!$CB$8:$CB$2617,Control!$F$10))*100))/(((INDEX(HIST_D!$D$8:$D$2617,1)-INDEX(HIST_D!$D$8:$D$2617,Control!$F$10))*100)),"n/m")) | J6: =IF(ABS(((INDEX(HIST_D!$D$8:$D$2617,1)-INDEX(HIST_D!$D$8:$D$2617,Control!$F$11))*100))<25,"n/m",IFERROR((((INDEX(HIST_D!$CB$8:$CB$2617,1)-INDEX(HIST_D!$CB$8:$CB$2617,Control!$F$11))*100))/(((INDEX(HIST_D!$D$8:$D$2617,1)-INDEX(HIST_D!$D$8:$D$2617,Control!$F$11))*100)),"n/m")) | K6: =IF(ABS(((INDEX(HIST_D!$D$8:$D$2617,1)-INDEX(HIST_D!$D$8:$D$2617,Control!$F$13))*100))<25,"n/m",IFERROR((((INDEX(HIST_D!$CB$8:$CB$2617,1)-INDEX(HIST_D!$CB$8:$CB$2617,Control!$F$13))*100))/(((INDEX(HIST_D!$D$8:$D$2617,1)-INDEX(HIST_D!$D$8:$D$2617,Control!$F$13))*100)),"n/m")) | L6: =IFERROR(INDEX(HIST_D!$AA$8:$AA$2617,Control!$F$8)/INDEX(HIST_D!$AA$8:$AA$2617,1)-1,"") | M6: =IFERROR((INDEX(HIST_D!$CB$8:$CB$2617,1)-INDEX(HIST_D!$D$8:$D$2617,1))*100,"") | N6: =IFERROR(PERCENTRANK(HIST_D!$EA$8:INDEX(HIST_D!$EA$8:$EA$2617,Control!$F$14),(INDEX(HIST_D!$CB$8:$CB$2617,1)-INDEX(HIST_D!$D$8:$D$2617,1))*100),"") | O6: =IF(NOT(ISNUMBER($G6)),"n/m",IF($G6<0,"absorbed and tightened",IF($G6<0.5,"absorbed most of it",IF($G6<1,"partial pass-through",IF($G6<1.5,"one-for-one","amplified")))))
A7: Mexico 10Y | B7: =INDEX(HIST_D!$CC$8:$CC$2617,1) | C7: =IFERROR((INDEX(HIST_D!$CC$8:$CC$2617,1)-INDEX(HIST_D!$CC$8:$CC$2617,Control!$F$8))*100,"") | D7: =IFERROR((INDEX(HIST_D!$CC$8:$CC$2617,1)-INDEX(HIST_D!$CC$8:$CC$2617,Control!$F$9))*100,"") | E7: =IFERROR((INDEX(HIST_D!$CC$8:$CC$2617,1)-INDEX(HIST_D!$CC$8:$CC$2617,Control!$F$10))*100,"") | F7: =IFERROR((INDEX(HIST_D!$CC$8:$CC$2617,1)-INDEX(HIST_D!$CC$8:$CC$2617,Control!$F$11))*100,"") | G7: =IF(ABS(((INDEX(HIST_D!$D$8:$D$2617,1)-INDEX(HIST_D!$D$8:$D$2617,Control!$F$8))*100))<25,"n/m",IFERROR((((INDEX(HIST_D!$CC$8:$CC$2617,1)-INDEX(HIST_D!$CC$8:$CC$2617,Control!$F$8))*100))/(((INDEX(HIST_D!$D$8:$D$2617,1)-INDEX(HIST_D!$D$8:$D$2617,Control!$F$8))*100)),"n/m")) | H7: =IF(ABS(((INDEX(HIST_D!$D$8:$D$2617,1)-INDEX(HIST_D!$D$8:$D$2617,Control!$F$9))*100))<25,"n/m",IFERROR((((INDEX(HIST_D!$CC$8:$CC$2617,1)-INDEX(HIST_D!$CC$8:$CC$2617,Control!$F$9))*100))/(((INDEX(HIST_D!$D$8:$D$2617,1)-INDEX(HIST_D!$D$8:$D$2617,Control!$F$9))*100)),"n/m")) | I7: =IF(ABS(((INDEX(HIST_D!$D$8:$D$2617,1)-INDEX(HIST_D!$D$8:$D$2617,Control!$F$10))*100))<25,"n/m",IFERROR((((INDEX(HIST_D!$CC$8:$CC$2617,1)-INDEX(HIST_D!$CC$8:$CC$2617,Control!$F$10))*100))/(((INDEX(HIST_D!$D$8:$D$2617,1)-INDEX(HIST_D!$D$8:$D$2617,Control!$F$10))*100)),"n/m")) | J7: =IF(ABS(((INDEX(HIST_D!$D$8:$D$2617,1)-INDEX(HIST_D!$D$8:$D$2617,Control!$F$11))*100))<25,"n/m",IFERROR((((INDEX(HIST_D!$CC$8:$CC$2617,1)-INDEX(HIST_D!$CC$8:$CC$2617,Control!$F$11))*100))/(((INDEX(HIST_D!$D$8:$D$2617,1)-INDEX(HIST_D!$D$8:$D$2617,Control!$F$11))*100)),"n/m")) | K7: =IF(ABS(((INDEX(HIST_D!$D$8:$D$2617,1)-INDEX(HIST_D!$D$8:$D$2617,Control!$F$13))*100))<25,"n/m",IFERROR((((INDEX(HIST_D!$CC$8:$CC$2617,1)-INDEX(HIST_D!$CC$8:$CC$2617,Control!$F$13))*100))/(((INDEX(HIST_D!$D$8:$D$2617,1)-INDEX(HIST_D!$D$8:$D$2617,Control!$F$13))*100)),"n/m")) | L7: =IFERROR(INDEX(HIST_D!$AB$8:$AB$2617,Control!$F$8)/INDEX(HIST_D!$AB$8:$AB$2617,1)-1,"") | M7: =IFERROR((INDEX(HIST_D!$CC$8:$CC$2617,1)-INDEX(HIST_D!$D$8:$D$2617,1))*100,"") | N7: =IFERROR(PERCENTRANK(HIST_D!$EA$8:INDEX(HIST_D!$EA$8:$EA$2617,Control!$F$14),(INDEX(HIST_D!$CC$8:$CC$2617,1)-INDEX(HIST_D!$D$8:$D$2617,1))*100),"") | O7: =IF(NOT(ISNUMBER($G7)),"n/m",IF($G7<0,"absorbed and tightened",IF($G7<0.5,"absorbed most of it",IF($G7<1,"partial pass-through",IF($G7<1.5,"one-for-one","amplified")))))
A8: Chile 10Y | B8: =INDEX(HIST_D!$CD$8:$CD$2617,1) | C8: =IFERROR((INDEX(HIST_D!$CD$8:$CD$2617,1)-INDEX(HIST_D!$CD$8:$CD$2617,Control!$F$8))*100,"") | D8: =IFERROR((INDEX(HIST_D!$CD$8:$CD$2617,1)-INDEX(HIST_D!$CD$8:$CD$2617,Control!$F$9))*100,"") | E8: =IFERROR((INDEX(HIST_D!$CD$8:$CD$2617,1)-INDEX(HIST_D!$CD$8:$CD$2617,Control!$F$10))*100,"") | F8: =IFERROR((INDEX(HIST_D!$CD$8:$CD$2617,1)-INDEX(HIST_D!$CD$8:$CD$2617,Control!$F$11))*100,"") | G8: =IF(ABS(((INDEX(HIST_D!$D$8:$D$2617,1)-INDEX(HIST_D!$D$8:$D$2617,Control!$F$8))*100))<25,"n/m",IFERROR((((INDEX(HIST_D!$CD$8:$CD$2617,1)-INDEX(HIST_D!$CD$8:$CD$2617,Control!$F$8))*100))/(((INDEX(HIST_D!$D$8:$D$2617,1)-INDEX(HIST_D!$D$8:$D$2617,Control!$F$8))*100)),"n/m")) | H8: =IF(ABS(((INDEX(HIST_D!$D$8:$D$2617,1)-INDEX(HIST_D!$D$8:$D$2617,Control!$F$9))*100))<25,"n/m",IFERROR((((INDEX(HIST_D!$CD$8:$CD$2617,1)-INDEX(HIST_D!$CD$8:$CD$2617,Control!$F$9))*100))/(((INDEX(HIST_D!$D$8:$D$2617,1)-INDEX(HIST_D!$D$8:$D$2617,Control!$F$9))*100)),"n/m")) | I8: =IF(ABS(((INDEX(HIST_D!$D$8:$D$2617,1)-INDEX(HIST_D!$D$8:$D$2617,Control!$F$10))*100))<25,"n/m",IFERROR((((INDEX(HIST_D!$CD$8:$CD$2617,1)-INDEX(HIST_D!$CD$8:$CD$2617,Control!$F$10))*100))/(((INDEX(HIST_D!$D$8:$D$2617,1)-INDEX(HIST_D!$D$8:$D$2617,Control!$F$10))*100)),"n/m")) | J8: =IF(ABS(((INDEX(HIST_D!$D$8:$D$2617,1)-INDEX(HIST_D!$D$8:$D$2617,Control!$F$11))*100))<25,"n/m",IFERROR((((INDEX(HIST_D!$CD$8:$CD$2617,1)-INDEX(HIST_D!$CD$8:$CD$2617,Control!$F$11))*100))/(((INDEX(HIST_D!$D$8:$D$2617,1)-INDEX(HIST_D!$D$8:$D$2617,Control!$F$11))*100)),"n/m")) | K8: =IF(ABS(((INDEX(HIST_D!$D$8:$D$2617,1)-INDEX(HIST_D!$D$8:$D$2617,Control!$F$13))*100))<25,"n/m",IFERROR((((INDEX(HIST_D!$CD$8:$CD$2617,1)-INDEX(HIST_D!$CD$8:$CD$2617,Control!$F$13))*100))/(((INDEX(HIST_D!$D$8:$D$2617,1)-INDEX(HIST_D!$D$8:$D$2617,Control!$F$13))*100)),"n/m")) | L8: =IFERROR(INDEX(HIST_D!$AC$8:$AC$2617,Control!$F$8)/INDEX(HIST_D!$AC$8:$AC$2617,1)-1,"") | M8: =IFERROR((INDEX(HIST_D!$CD$8:$CD$2617,1)-INDEX(HIST_D!$D$8:$D$2617,1))*100,"") | N8: =IFERROR(PERCENTRANK(HIST_D!$EA$8:INDEX(HIST_D!$EA$8:$EA$2617,Control!$F$14),(INDEX(HIST_D!$CD$8:$CD$2617,1)-INDEX(HIST_D!$D$8:$D$2617,1))*100),"") | O8: =IF(NOT(ISNUMBER($G8)),"n/m",IF($G8<0,"absorbed and tightened",IF($G8<0.5,"absorbed most of it",IF($G8<1,"partial pass-through",IF($G8<1.5,"one-for-one","amplified")))))
A9: Colombia 10Y | B9: =INDEX(HIST_D!$CE$8:$CE$2617,1) | C9: =IFERROR((INDEX(HIST_D!$CE$8:$CE$2617,1)-INDEX(HIST_D!$CE$8:$CE$2617,Control!$F$8))*100,"") | D9: =IFERROR((INDEX(HIST_D!$CE$8:$CE$2617,1)-INDEX(HIST_D!$CE$8:$CE$2617,Control!$F$9))*100,"") | E9: =IFERROR((INDEX(HIST_D!$CE$8:$CE$2617,1)-INDEX(HIST_D!$CE$8:$CE$2617,Control!$F$10))*100,"") | F9: =IFERROR((INDEX(HIST_D!$CE$8:$CE$2617,1)-INDEX(HIST_D!$CE$8:$CE$2617,Control!$F$11))*100,"") | G9: =IF(ABS(((INDEX(HIST_D!$D$8:$D$2617,1)-INDEX(HIST_D!$D$8:$D$2617,Control!$F$8))*100))<25,"n/m",IFERROR((((INDEX(HIST_D!$CE$8:$CE$2617,1)-INDEX(HIST_D!$CE$8:$CE$2617,Control!$F$8))*100))/(((INDEX(HIST_D!$D$8:$D$2617,1)-INDEX(HIST_D!$D$8:$D$2617,Control!$F$8))*100)),"n/m")) | H9: =IF(ABS(((INDEX(HIST_D!$D$8:$D$2617,1)-INDEX(HIST_D!$D$8:$D$2617,Control!$F$9))*100))<25,"n/m",IFERROR((((INDEX(HIST_D!$CE$8:$CE$2617,1)-INDEX(HIST_D!$CE$8:$CE$2617,Control!$F$9))*100))/(((INDEX(HIST_D!$D$8:$D$2617,1)-INDEX(HIST_D!$D$8:$D$2617,Control!$F$9))*100)),"n/m")) | I9: =IF(ABS(((INDEX(HIST_D!$D$8:$D$2617,1)-INDEX(HIST_D!$D$8:$D$2617,Control!$F$10))*100))<25,"n/m",IFERROR((((INDEX(HIST_D!$CE$8:$CE$2617,1)-INDEX(HIST_D!$CE$8:$CE$2617,Control!$F$10))*100))/(((INDEX(HIST_D!$D$8:$D$2617,1)-INDEX(HIST_D!$D$8:$D$2617,Control!$F$10))*100)),"n/m")) | J9: =IF(ABS(((INDEX(HIST_D!$D$8:$D$2617,1)-INDEX(HIST_D!$D$8:$D$2617,Control!$F$11))*100))<25,"n/m",IFERROR((((INDEX(HIST_D!$CE$8:$CE$2617,1)-INDEX(HIST_D!$CE$8:$CE$2617,Control!$F$11))*100))/(((INDEX(HIST_D!$D$8:$D$2617,1)-INDEX(HIST_D!$D$8:$D$2617,Control!$F$11))*100)),"n/m")) | K9: =IF(ABS(((INDEX(HIST_D!$D$8:$D$2617,1)-INDEX(HIST_D!$D$8:$D$2617,Control!$F$13))*100))<25,"n/m",IFERROR((((INDEX(HIST_D!$CE$8:$CE$2617,1)-INDEX(HIST_D!$CE$8:$CE$2617,Control!$F$13))*100))/(((INDEX(HIST_D!$D$8:$D$2617,1)-INDEX(HIST_D!$D$8:$D$2617,Control!$F$13))*100)),"n/m")) | L9: =IFERROR(INDEX(HIST_D!$AD$8:$AD$2617,Control!$F$8)/INDEX(HIST_D!$AD$8:$AD$2617,1)-1,"") | M9: =IFERROR((INDEX(HIST_D!$CE$8:$CE$2617,1)-INDEX(HIST_D!$D$8:$D$2617,1))*100,"") | N9: =IFERROR(PERCENTRANK(HIST_D!$EA$8:INDEX(HIST_D!$EA$8:$EA$2617,Control!$F$14),(INDEX(HIST_D!$CE$8:$CE$2617,1)-INDEX(HIST_D!$D$8:$D$2617,1))*100),"") | O9: =IF(NOT(ISNUMBER($G9)),"n/m",IF($G9<0,"absorbed and tightened",IF($G9<0.5,"absorbed most of it",IF($G9<1,"partial pass-through",IF($G9<1.5,"one-for-one","amplified")))))
A10: Peru 10Y | B10: =INDEX(HIST_D!$CF$8:$CF$2617,1) | C10: =IFERROR((INDEX(HIST_D!$CF$8:$CF$2617,1)-INDEX(HIST_D!$CF$8:$CF$2617,Control!$F$8))*100,"") | D10: =IFERROR((INDEX(HIST_D!$CF$8:$CF$2617,1)-INDEX(HIST_D!$CF$8:$CF$2617,Control!$F$9))*100,"") | E10: =IFERROR((INDEX(HIST_D!$CF$8:$CF$2617,1)-INDEX(HIST_D!$CF$8:$CF$2617,Control!$F$10))*100,"") | F10: =IFERROR((INDEX(HIST_D!$CF$8:$CF$2617,1)-INDEX(HIST_D!$CF$8:$CF$2617,Control!$F$11))*100,"") | G10: =IF(ABS(((INDEX(HIST_D!$D$8:$D$2617,1)-INDEX(HIST_D!$D$8:$D$2617,Control!$F$8))*100))<25,"n/m",IFERROR((((INDEX(HIST_D!$CF$8:$CF$2617,1)-INDEX(HIST_D!$CF$8:$CF$2617,Control!$F$8))*100))/(((INDEX(HIST_D!$D$8:$D$2617,1)-INDEX(HIST_D!$D$8:$D$2617,Control!$F$8))*100)),"n/m")) | H10: =IF(ABS(((INDEX(HIST_D!$D$8:$D$2617,1)-INDEX(HIST_D!$D$8:$D$2617,Control!$F$9))*100))<25,"n/m",IFERROR((((INDEX(HIST_D!$CF$8:$CF$2617,1)-INDEX(HIST_D!$CF$8:$CF$2617,Control!$F$9))*100))/(((INDEX(HIST_D!$D$8:$D$2617,1)-INDEX(HIST_D!$D$8:$D$2617,Control!$F$9))*100)),"n/m")) | I10: =IF(ABS(((INDEX(HIST_D!$D$8:$D$2617,1)-INDEX(HIST_D!$D$8:$D$2617,Control!$F$10))*100))<25,"n/m",IFERROR((((INDEX(HIST_D!$CF$8:$CF$2617,1)-INDEX(HIST_D!$CF$8:$CF$2617,Control!$F$10))*100))/(((INDEX(HIST_D!$D$8:$D$2617,1)-INDEX(HIST_D!$D$8:$D$2617,Control!$F$10))*100)),"n/m")) | J10: =IF(ABS(((INDEX(HIST_D!$D$8:$D$2617,1)-INDEX(HIST_D!$D$8:$D$2617,Control!$F$11))*100))<25,"n/m",IFERROR((((INDEX(HIST_D!$CF$8:$CF$2617,1)-INDEX(HIST_D!$CF$8:$CF$2617,Control!$F$11))*100))/(((INDEX(HIST_D!$D$8:$D$2617,1)-INDEX(HIST_D!$D$8:$D$2617,Control!$F$11))*100)),"n/m")) | K10: =IF(ABS(((INDEX(HIST_D!$D$8:$D$2617,1)-INDEX(HIST_D!$D$8:$D$2617,Control!$F$13))*100))<25,"n/m",IFERROR((((INDEX(HIST_D!$CF$8:$CF$2617,1)-INDEX(HIST_D!$CF$8:$CF$2617,Control!$F$13))*100))/(((INDEX(HIST_D!$D$8:$D$2617,1)-INDEX(HIST_D!$D$8:$D$2617,Control!$F$13))*100)),"n/m")) | L10: =IFERROR(INDEX(HIST_D!$AE$8:$AE$2617,Control!$F$8)/INDEX(HIST_D!$AE$8:$AE$2617,1)-1,"") | M10: =IFERROR((INDEX(HIST_D!$CF$8:$CF$2617,1)-INDEX(HIST_D!$D$8:$D$2617,1))*100,"") | N10: =IFERROR(PERCENTRANK(HIST_D!$EA$8:INDEX(HIST_D!$EA$8:$EA$2617,Control!$F$14),(INDEX(HIST_D!$CF$8:$CF$2617,1)-INDEX(HIST_D!$D$8:$D$2617,1))*100),"") | O10: =IF(NOT(ISNUMBER($G10)),"n/m",IF($G10<0,"absorbed and tightened",IF($G10<0.5,"absorbed most of it",IF($G10<1,"partial pass-through",IF($G10<1.5,"one-for-one","amplified")))))
A11: LatAm (eq-wgt, n=5) | B11: =IFERROR(AVERAGE(B6,B7,B8,B9,B10),"") | C11: =IFERROR(AVERAGE(C6,C7,C8,C9,C10),"") | D11: =IFERROR(AVERAGE(D6,D7,D8,D9,D10),"") | E11: =IFERROR(AVERAGE(E6,E7,E8,E9,E10),"") | F11: =IFERROR(AVERAGE(F6,F7,F8,F9,F10),"") | G11: =IFERROR(AVERAGE(G6,G7,G8,G9,G10),"") | H11: =IFERROR(AVERAGE(H6,H7,H8,H9,H10),"") | I11: =IFERROR(AVERAGE(I6,I7,I8,I9,I10),"") | ... N11: =IFERROR(AVERAGE(N6,N7,N8,N9,N10),"")
A12: =IFERROR("LatAm: local 10Y "&TEXT($C$11,"+0;-0")&"bp on the month against the US, pass-through "&IF(ISNUMBER($G$11),TEXT($G$11,"0.00")&"x","n/m")&" over 1M and "&IF(ISNUMBER($J$11),TEXT($J$11,"0.00")&"x","n/m")&" over 1Y; FX "&TEXT($L$11,"+0.0%;-0.0%")&". "&IF(NOT(ISNUMBER($G$11)),"The US move over this window is too small to form a ratio.",IF($G$11<0.5,"The curve is absorbing most of the US move rather than importing it.",IF($G$11<1,"Partial pass-through — some import, but less than one-for-one.","The curve is taking the full US move or more; this is where the digestion argument is weakest.")))&" ","")
A14: EM EUROPE
A15: Market | B15: Local 10Y (%) | C15: d 1M (bp) | D15: d 3M (bp) | E15: d 6M (bp) | F15: d 1Y (bp) | G15: PT 1M | H15: PT 3M | I15: PT 6M | J15: PT 1Y | K15: PT 3Y | L15: FX 1M | M15: Local less UST (bp) | N15: %ile 5y (gap) | O15: Verdict
A16: Poland 10Y | B16: =INDEX(HIST_D!$CG$8:$CG$2617,1) | C16: =IFERROR((INDEX(HIST_D!$CG$8:$CG$2617,1)-INDEX(HIST_D!$CG$8:$CG$2617,Control!$F$8))*100,"") | D16: =IFERROR((INDEX(HIST_D!$CG$8:$CG$2617,1)-INDEX(HIST_D!$CG$8:$CG$2617,Control!$F$9))*100,"") | E16: =IFERROR((INDEX(HIST_D!$CG$8:$CG$2617,1)-INDEX(HIST_D!$CG$8:$CG$2617,Control!$F$10))*100,"") | F16: =IFERROR((INDEX(HIST_D!$CG$8:$CG$2617,1)-INDEX(HIST_D!$CG$8:$CG$2617,Control!$F$11))*100,"") | G16: =IF(ABS(((INDEX(HIST_D!$D$8:$D$2617,1)-INDEX(HIST_D!$D$8:$D$2617,Control!$F$8))*100))<25,"n/m",IFERROR((((INDEX(HIST_D!$CG$8:$CG$2617,1)-INDEX(HIST_D!$CG$8:$CG$2617,Control!$F$8))*100))/(((INDEX(HIST_D!$D$8:$D$2617,1)-INDEX(HIST_D!$D$8:$D$2617,Control!$F$8))*100)),"n/m")) | H16: =IF(ABS(((INDEX(HIST_D!$D$8:$D$2617,1)-INDEX(HIST_D!$D$8:$D$2617,Control!$F$9))*100))<25,"n/m",IFERROR((((INDEX(HIST_D!$CG$8:$CG$2617,1)-INDEX(HIST_D!$CG$8:$CG$2617,Control!$F$9))*100))/(((INDEX(HIST_D!$D$8:$D$2617,1)-INDEX(HIST_D!$D$8:$D$2617,Control!$F$9))*100)),"n/m")) | I16: =IF(ABS(((INDEX(HIST_D!$D$8:$D$2617,1)-INDEX(HIST_D!$D$8:$D$2617,Control!$F$10))*100))<25,"n/m",IFERROR((((INDEX(HIST_D!$CG$8:$CG$2617,1)-INDEX(HIST_D!$CG$8:$CG$2617,Control!$F$10))*100))/(((INDEX(HIST_D!$D$8:$D$2617,1)-INDEX(HIST_D!$D$8:$D$2617,Control!$F$10))*100)),"n/m")) | J16: =IF(ABS(((INDEX(HIST_D!$D$8:$D$2617,1)-INDEX(HIST_D!$D$8:$D$2617,Control!$F$11))*100))<25,"n/m",IFERROR((((INDEX(HIST_D!$CG$8:$CG$2617,1)-INDEX(HIST_D!$CG$8:$CG$2617,Control!$F$11))*100))/(((INDEX(HIST_D!$D$8:$D$2617,1)-INDEX(HIST_D!$D$8:$D$2617,Control!$F$11))*100)),"n/m")) | K16: =IF(ABS(((INDEX(HIST_D!$D$8:$D$2617,1)-INDEX(HIST_D!$D$8:$D$2617,Control!$F$13))*100))<25,"n/m",IFERROR((((INDEX(HIST_D!$CG$8:$CG$2617,1)-INDEX(HIST_D!$CG$8:$CG$2617,Control!$F$13))*100))/(((INDEX(HIST_D!$D$8:$D$2617,1)-INDEX(HIST_D!$D$8:$D$2617,Control!$F$13))*100)),"n/m")) | L16: =IFERROR(INDEX(HIST_D!$AG$8:$AG$2617,Control!$F$8)/INDEX(HIST_D!$AG$8:$AG$2617,1)-1,"") | M16: =IFERROR((INDEX(HIST_D!$CG$8:$CG$2617,1)-INDEX(HIST_D!$D$8:$D$2617,1))*100,"") | N16: =IFERROR(PERCENTRANK(HIST_D!$EA$8:INDEX(HIST_D!$EA$8:$EA$2617,Control!$F$14),(INDEX(HIST_D!$CG$8:$CG$2617,1)-INDEX(HIST_D!$D$8:$D$2617,1))*100),"") | O16: =IF(NOT(ISNUMBER($G16)),"n/m",IF($G16<0,"absorbed and tightened",IF($G16<0.5,"absorbed most of it",IF($G16<1,"partial pass-through",IF($G16<1.5,"one-for-one","amplified")))))
A17: Hungary 10Y | B17: =INDEX(HIST_D!$CH$8:$CH$2617,1) | C17: =IFERROR((INDEX(HIST_D!$CH$8:$CH$2617,1)-INDEX(HIST_D!$CH$8:$CH$2617,Control!$F$8))*100,"") | D17: =IFERROR((INDEX(HIST_D!$CH$8:$CH$2617,1)-INDEX(HIST_D!$CH$8:$CH$2617,Control!$F$9))*100,"") | E17: =IFERROR((INDEX(HIST_D!$CH$8:$CH$2617,1)-INDEX(HIST_D!$CH$8:$CH$2617,Control!$F$10))*100,"") | F17: =IFERROR((INDEX(HIST_D!$CH$8:$CH$2617,1)-INDEX(HIST_D!$CH$8:$CH$2617,Control!$F$11))*100,"") | G17: =IF(ABS(((INDEX(HIST_D!$D$8:$D$2617,1)-INDEX(HIST_D!$D$8:$D$2617,Control!$F$8))*100))<25,"n/m",IFERROR((((INDEX(HIST_D!$CH$8:$CH$2617,1)-INDEX(HIST_D!$CH$8:$CH$2617,Control!$F$8))*100))/(((INDEX(HIST_D!$D$8:$D$2617,1)-INDEX(HIST_D!$D$8:$D$2617,Control!$F$8))*100)),"n/m")) | H17: =IF(ABS(((INDEX(HIST_D!$D$8:$D$2617,1)-INDEX(HIST_D!$D$8:$D$2617,Control!$F$9))*100))<25,"n/m",IFERROR((((INDEX(HIST_D!$CH$8:$CH$2617,1)-INDEX(HIST_D!$CH$8:$CH$2617,Control!$F$9))*100))/(((INDEX(HIST_D!$D$8:$D$2617,1)-INDEX(HIST_D!$D$8:$D$2617,Control!$F$9))*100)),"n/m")) | I17: =IF(ABS(((INDEX(HIST_D!$D$8:$D$2617,1)-INDEX(HIST_D!$D$8:$D$2617,Control!$F$10))*100))<25,"n/m",IFERROR((((INDEX(HIST_D!$CH$8:$CH$2617,1)-INDEX(HIST_D!$CH$8:$CH$2617,Control!$F$10))*100))/(((INDEX(HIST_D!$D$8:$D$2617,1)-INDEX(HIST_D!$D$8:$D$2617,Control!$F$10))*100)),"n/m")) | J17: =IF(ABS(((INDEX(HIST_D!$D$8:$D$2617,1)-INDEX(HIST_D!$D$8:$D$2617,Control!$F$11))*100))<25,"n/m",IFERROR((((INDEX(HIST_D!$CH$8:$CH$2617,1)-INDEX(HIST_D!$CH$8:$CH$2617,Control!$F$11))*100))/(((INDEX(HIST_D!$D$8:$D$2617,1)-INDEX(HIST_D!$D$8:$D$2617,Control!$F$11))*100)),"n/m")) | K17: =IF(ABS(((INDEX(HIST_D!$D$8:$D$2617,1)-INDEX(HIST_D!$D$8:$D$2617,Control!$F$13))*100))<25,"n/m",IFERROR((((INDEX(HIST_D!$CH$8:$CH$2617,1)-INDEX(HIST_D!$CH$8:$CH$2617,Control!$F$13))*100))/(((INDEX(HIST_D!$D$8:$D$2617,1)-INDEX(HIST_D!$D$8:$D$2617,Control!$F$13))*100)),"n/m")) | L17: =IFERROR(INDEX(HIST_D!$AH$8:$AH$2617,Control!$F$8)/INDEX(HIST_D!$AH$8:$AH$2617,1)-1,"") | M17: =IFERROR((INDEX(HIST_D!$CH$8:$CH$2617,1)-INDEX(HIST_D!$D$8:$D$2617,1))*100,"") | N17: =IFERROR(PERCENTRANK(HIST_D!$EA$8:INDEX(HIST_D!$EA$8:$EA$2617,Control!$F$14),(INDEX(HIST_D!$CH$8:$CH$2617,1)-INDEX(HIST_D!$D$8:$D$2617,1))*100),"") | O17: =IF(NOT(ISNUMBER($G17)),"n/m",IF($G17<0,"absorbed and tightened",IF($G17<0.5,"absorbed most of it",IF($G17<1,"partial pass-through",IF($G17<1.5,"one-for-one","amplified")))))
A18: Czechia 10Y | B18: =INDEX(HIST_D!$CI$8:$CI$2617,1) | C18: =IFERROR((INDEX(HIST_D!$CI$8:$CI$2617,1)-INDEX(HIST_D!$CI$8:$CI$2617,Control!$F$8))*100,"") | D18: =IFERROR((INDEX(HIST_D!$CI$8:$CI$2617,1)-INDEX(HIST_D!$CI$8:$CI$2617,Control!$F$9))*100,"") | E18: =IFERROR((INDEX(HIST_D!$CI$8:$CI$2617,1)-INDEX(HIST_D!$CI$8:$CI$2617,Control!$F$10))*100,"") | F18: =IFERROR((INDEX(HIST_D!$CI$8:$CI$2617,1)-INDEX(HIST_D!$CI$8:$CI$2617,Control!$F$11))*100,"") | G18: =IF(ABS(((INDEX(HIST_D!$D$8:$D$2617,1)-INDEX(HIST_D!$D$8:$D$2617,Control!$F$8))*100))<25,"n/m",IFERROR((((INDEX(HIST_D!$CI$8:$CI$2617,1)-INDEX(HIST_D!$CI$8:$CI$2617,Control!$F$8))*100))/(((INDEX(HIST_D!$D$8:$D$2617,1)-INDEX(HIST_D!$D$8:$D$2617,Control!$F$8))*100)),"n/m")) | H18: =IF(ABS(((INDEX(HIST_D!$D$8:$D$2617,1)-INDEX(HIST_D!$D$8:$D$2617,Control!$F$9))*100))<25,"n/m",IFERROR((((INDEX(HIST_D!$CI$8:$CI$2617,1)-INDEX(HIST_D!$CI$8:$CI$2617,Control!$F$9))*100))/(((INDEX(HIST_D!$D$8:$D$2617,1)-INDEX(HIST_D!$D$8:$D$2617,Control!$F$9))*100)),"n/m")) | I18: =IF(ABS(((INDEX(HIST_D!$D$8:$D$2617,1)-INDEX(HIST_D!$D$8:$D$2617,Control!$F$10))*100))<25,"n/m",IFERROR((((INDEX(HIST_D!$CI$8:$CI$2617,1)-INDEX(HIST_D!$CI$8:$CI$2617,Control!$F$10))*100))/(((INDEX(HIST_D!$D$8:$D$2617,1)-INDEX(HIST_D!$D$8:$D$2617,Control!$F$10))*100)),"n/m")) | J18: =IF(ABS(((INDEX(HIST_D!$D$8:$D$2617,1)-INDEX(HIST_D!$D$8:$D$2617,Control!$F$11))*100))<25,"n/m",IFERROR((((INDEX(HIST_D!$CI$8:$CI$2617,1)-INDEX(HIST_D!$CI$8:$CI$2617,Control!$F$11))*100))/(((INDEX(HIST_D!$D$8:$D$2617,1)-INDEX(HIST_D!$D$8:$D$2617,Control!$F$11))*100)),"n/m")) | K18: =IF(ABS(((INDEX(HIST_D!$D$8:$D$2617,1)-INDEX(HIST_D!$D$8:$D$2617,Control!$F$13))*100))<25,"n/m",IFERROR((((INDEX(HIST_D!$CI$8:$CI$2617,1)-INDEX(HIST_D!$CI$8:$CI$2617,Control!$F$13))*100))/(((INDEX(HIST_D!$D$8:$D$2617,1)-INDEX(HIST_D!$D$8:$D$2617,Control!$F$13))*100)),"n/m")) | L18: =IFERROR(INDEX(HIST_D!$AI$8:$AI$2617,Control!$F$8)/INDEX(HIST_D!$AI$8:$AI$2617,1)-1,"") | M18: =IFERROR((INDEX(HIST_D!$CI$8:$CI$2617,1)-INDEX(HIST_D!$D$8:$D$2617,1))*100,"") | N18: =IFERROR(PERCENTRANK(HIST_D!$EA$8:INDEX(HIST_D!$EA$8:$EA$2617,Control!$F$14),(INDEX(HIST_D!$CI$8:$CI$2617,1)-INDEX(HIST_D!$D$8:$D$2617,1))*100),"") | O18: =IF(NOT(ISNUMBER($G18)),"n/m",IF($G18<0,"absorbed and tightened",IF($G18<0.5,"absorbed most of it",IF($G18<1,"partial pass-through",IF($G18<1.5,"one-for-one","amplified")))))
A19: Romania 10Y | B19: =INDEX(HIST_D!$CJ$8:$CJ$2617,1) | C19: =IFERROR((INDEX(HIST_D!$CJ$8:$CJ$2617,1)-INDEX(HIST_D!$CJ$8:$CJ$2617,Control!$F$8))*100,"") | D19: =IFERROR((INDEX(HIST_D!$CJ$8:$CJ$2617,1)-INDEX(HIST_D!$CJ$8:$CJ$2617,Control!$F$9))*100,"") | E19: =IFERROR((INDEX(HIST_D!$CJ$8:$CJ$2617,1)-INDEX(HIST_D!$CJ$8:$CJ$2617,Control!$F$10))*100,"") | F19: =IFERROR((INDEX(HIST_D!$CJ$8:$CJ$2617,1)-INDEX(HIST_D!$CJ$8:$CJ$2617,Control!$F$11))*100,"") | G19: =IF(ABS(((INDEX(HIST_D!$D$8:$D$2617,1)-INDEX(HIST_D!$D$8:$D$2617,Control!$F$8))*100))<25,"n/m",IFERROR((((INDEX(HIST_D!$CJ$8:$CJ$2617,1)-INDEX(HIST_D!$CJ$8:$CJ$2617,Control!$F$8))*100))/(((INDEX(HIST_D!$D$8:$D$2617,1)-INDEX(HIST_D!$D$8:$D$2617,Control!$F$8))*100)),"n/m")) | H19: =IF(ABS(((INDEX(HIST_D!$D$8:$D$2617,1)-INDEX(HIST_D!$D$8:$D$2617,Control!$F$9))*100))<25,"n/m",IFERROR((((INDEX(HIST_D!$CJ$8:$CJ$2617,1)-INDEX(HIST_D!$CJ$8:$CJ$2617,Control!$F$9))*100))/(((INDEX(HIST_D!$D$8:$D$2617,1)-INDEX(HIST_D!$D$8:$D$2617,Control!$F$9))*100)),"n/m")) | I19: =IF(ABS(((INDEX(HIST_D!$D$8:$D$2617,1)-INDEX(HIST_D!$D$8:$D$2617,Control!$F$10))*100))<25,"n/m",IFERROR((((INDEX(HIST_D!$CJ$8:$CJ$2617,1)-INDEX(HIST_D!$CJ$8:$CJ$2617,Control!$F$10))*100))/(((INDEX(HIST_D!$D$8:$D$2617,1)-INDEX(HIST_D!$D$8:$D$2617,Control!$F$10))*100)),"n/m")) | J19: =IF(ABS(((INDEX(HIST_D!$D$8:$D$2617,1)-INDEX(HIST_D!$D$8:$D$2617,Control!$F$11))*100))<25,"n/m",IFERROR((((INDEX(HIST_D!$CJ$8:$CJ$2617,1)-INDEX(HIST_D!$CJ$8:$CJ$2617,Control!$F$11))*100))/(((INDEX(HIST_D!$D$8:$D$2617,1)-INDEX(HIST_D!$D$8:$D$2617,Control!$F$11))*100)),"n/m")) | K19: =IF(ABS(((INDEX(HIST_D!$D$8:$D$2617,1)-INDEX(HIST_D!$D$8:$D$2617,Control!$F$13))*100))<25,"n/m",IFERROR((((INDEX(HIST_D!$CJ$8:$CJ$2617,1)-INDEX(HIST_D!$CJ$8:$CJ$2617,Control!$F$13))*100))/(((INDEX(HIST_D!$D$8:$D$2617,1)-INDEX(HIST_D!$D$8:$D$2617,Control!$F$13))*100)),"n/m")) | L19: =IFERROR(INDEX(HIST_D!$AJ$8:$AJ$2617,Control!$F$8)/INDEX(HIST_D!$AJ$8:$AJ$2617,1)-1,"") | M19: =IFERROR((INDEX(HIST_D!$CJ$8:$CJ$2617,1)-INDEX(HIST_D!$D$8:$D$2617,1))*100,"") | N19: =IFERROR(PERCENTRANK(HIST_D!$EA$8:INDEX(HIST_D!$EA$8:$EA$2617,Control!$F$14),(INDEX(HIST_D!$CJ$8:$CJ$2617,1)-INDEX(HIST_D!$D$8:$D$2617,1))*100),"") | O19: =IF(NOT(ISNUMBER($G19)),"n/m",IF($G19<0,"absorbed and tightened",IF($G19<0.5,"absorbed most of it",IF($G19<1,"partial pass-through",IF($G19<1.5,"one-for-one","amplified")))))
A20: Turkiye 10Y | B20: =INDEX(HIST_D!$CK$8:$CK$2617,1) | C20: =IFERROR((INDEX(HIST_D!$CK$8:$CK$2617,1)-INDEX(HIST_D!$CK$8:$CK$2617,Control!$F$8))*100,"") | D20: =IFERROR((INDEX(HIST_D!$CK$8:$CK$2617,1)-INDEX(HIST_D!$CK$8:$CK$2617,Control!$F$9))*100,"") | E20: =IFERROR((INDEX(HIST_D!$CK$8:$CK$2617,1)-INDEX(HIST_D!$CK$8:$CK$2617,Control!$F$10))*100,"") | F20: =IFERROR((INDEX(HIST_D!$CK$8:$CK$2617,1)-INDEX(HIST_D!$CK$8:$CK$2617,Control!$F$11))*100,"") | G20: =IF(ABS(((INDEX(HIST_D!$D$8:$D$2617,1)-INDEX(HIST_D!$D$8:$D$2617,Control!$F$8))*100))<25,"n/m",IFERROR((((INDEX(HIST_D!$CK$8:$CK$2617,1)-INDEX(HIST_D!$CK$8:$CK$2617,Control!$F$8))*100))/(((INDEX(HIST_D!$D$8:$D$2617,1)-INDEX(HIST_D!$D$8:$D$2617,Control!$F$8))*100)),"n/m")) | H20: =IF(ABS(((INDEX(HIST_D!$D$8:$D$2617,1)-INDEX(HIST_D!$D$8:$D$2617,Control!$F$9))*100))<25,"n/m",IFERROR((((INDEX(HIST_D!$CK$8:$CK$2617,1)-INDEX(HIST_D!$CK$8:$CK$2617,Control!$F$9))*100))/(((INDEX(HIST_D!$D$8:$D$2617,1)-INDEX(HIST_D!$D$8:$D$2617,Control!$F$9))*100)),"n/m")) | I20: =IF(ABS(((INDEX(HIST_D!$D$8:$D$2617,1)-INDEX(HIST_D!$D$8:$D$2617,Control!$F$10))*100))<25,"n/m",IFERROR((((INDEX(HIST_D!$CK$8:$CK$2617,1)-INDEX(HIST_D!$CK$8:$CK$2617,Control!$F$10))*100))/(((INDEX(HIST_D!$D$8:$D$2617,1)-INDEX(HIST_D!$D$8:$D$2617,Control!$F$10))*100)),"n/m")) | J20: =IF(ABS(((INDEX(HIST_D!$D$8:$D$2617,1)-INDEX(HIST_D!$D$8:$D$2617,Control!$F$11))*100))<25,"n/m",IFERROR((((INDEX(HIST_D!$CK$8:$CK$2617,1)-INDEX(HIST_D!$CK$8:$CK$2617,Control!$F$11))*100))/(((INDEX(HIST_D!$D$8:$D$2617,1)-INDEX(HIST_D!$D$8:$D$2617,Control!$F$11))*100)),"n/m")) | K20: =IF(ABS(((INDEX(HIST_D!$D$8:$D$2617,1)-INDEX(HIST_D!$D$8:$D$2617,Control!$F$13))*100))<25,"n/m",IFERROR((((INDEX(HIST_D!$CK$8:$CK$2617,1)-INDEX(HIST_D!$CK$8:$CK$2617,Control!$F$13))*100))/(((INDEX(HIST_D!$D$8:$D$2617,1)-INDEX(HIST_D!$D$8:$D$2617,Control!$F$13))*100)),"n/m")) | L20: =IFERROR(INDEX(HIST_D!$AK$8:$AK$2617,Control!$F$8)/INDEX(HIST_D!$AK$8:$AK$2617,1)-1,"") | M20: =IFERROR((INDEX(HIST_D!$CK$8:$CK$2617,1)-INDEX(HIST_D!$D$8:$D$2617,1))*100,"") | N20: =IFERROR(PERCENTRANK(HIST_D!$EA$8:INDEX(HIST_D!$EA$8:$EA$2617,Control!$F$14),(INDEX(HIST_D!$CK$8:$CK$2617,1)-INDEX(HIST_D!$D$8:$D$2617,1))*100),"") | O20: =IF(NOT(ISNUMBER($G20)),"n/m",IF($G20<0,"absorbed and tightened",IF($G20<0.5,"absorbed most of it",IF($G20<1,"partial pass-through",IF($G20<1.5,"one-for-one","amplified")))))
A21: EM Europe (eq-wgt, n=5) | B21: =IFERROR(AVERAGE(B16,B17,B18,B19,B20),"") | C21: =IFERROR(AVERAGE(C16,C17,C18,C19,C20),"") | D21: =IFERROR(AVERAGE(D16,D17,D18,D19,D20),"") | E21: =IFERROR(AVERAGE(E16,E17,E18,E19,E20),"") | F21: =IFERROR(AVERAGE(F16,F17,F18,F19,F20),"") | G21: =IFERROR(AVERAGE(G16,G17,G18,G19,G20),"") | H21: =IFERROR(AVERAGE(H16,H17,H18,H19,H20),"") | I21: =IFERROR(AVERAGE(I16,I17,I18,I19,I20),"") | ... N21: =IFERROR(AVERAGE(N16,N17,N18,N19,N20),"")
A22: =IFERROR("EM Europe: local 10Y "&TEXT($C$21,"+0;-0")&"bp on the month against the US, pass-through "&IF(ISNUMBER($G$21),TEXT($G$21,"0.00")&"x","n/m")&" over 1M and "&IF(ISNUMBER($J$21),TEXT($J$21,"0.00")&"x","n/m")&" over 1Y; FX "&TEXT($L$21,"+0.0%;-0.0%")&". "&IF(NOT(ISNUMBER($G$21)),"The US move over this window is too small to form a ratio.",IF($G$21<0.5,"The curve is absorbing most of the US move rather than importing it.",IF($G$21<1,"Partial pass-through — some import, but less than one-for-one.","The curve is taking the full US move or more; this is where the digestion argument is weakest.")))&" ","")
A24: MIDDLE EAST & AFRICA
A25: Market | B25: Local 10Y (%) | C25: d 1M (bp) | D25: d 3M (bp) | E25: d 6M (bp) | F25: d 1Y (bp) | G25: PT 1M | H25: PT 3M | I25: PT 6M | J25: PT 1Y | K25: PT 3Y | L25: FX 1M | M25: Local less UST (bp) | N25: %ile 5y (gap) | O25: Verdict
A26: Israel 10Y | B26: =INDEX(HIST_D!$CL$8:$CL$2617,1) | C26: =IFERROR((INDEX(HIST_D!$CL$8:$CL$2617,1)-INDEX(HIST_D!$CL$8:$CL$2617,Control!$F$8))*100,"") | D26: =IFERROR((INDEX(HIST_D!$CL$8:$CL$2617,1)-INDEX(HIST_D!$CL$8:$CL$2617,Control!$F$9))*100,"") | E26: =IFERROR((INDEX(HIST_D!$CL$8:$CL$2617,1)-INDEX(HIST_D!$CL$8:$CL$2617,Control!$F$10))*100,"") | F26: =IFERROR((INDEX(HIST_D!$CL$8:$CL$2617,1)-INDEX(HIST_D!$CL$8:$CL$2617,Control!$F$11))*100,"") | G26: =IF(ABS(((INDEX(HIST_D!$D$8:$D$2617,1)-INDEX(HIST_D!$D$8:$D$2617,Control!$F$8))*100))<25,"n/m",IFERROR((((INDEX(HIST_D!$CL$8:$CL$2617,1)-INDEX(HIST_D!$CL$8:$CL$2617,Control!$F$8))*100))/(((INDEX(HIST_D!$D$8:$D$2617,1)-INDEX(HIST_D!$D$8:$D$2617,Control!$F$8))*100)),"n/m")) | H26: =IF(ABS(((INDEX(HIST_D!$D$8:$D$2617,1)-INDEX(HIST_D!$D$8:$D$2617,Control!$F$9))*100))<25,"n/m",IFERROR((((INDEX(HIST_D!$CL$8:$CL$2617,1)-INDEX(HIST_D!$CL$8:$CL$2617,Control!$F$9))*100))/(((INDEX(HIST_D!$D$8:$D$2617,1)-INDEX(HIST_D!$D$8:$D$2617,Control!$F$9))*100)),"n/m")) | I26: =IF(ABS(((INDEX(HIST_D!$D$8:$D$2617,1)-INDEX(HIST_D!$D$8:$D$2617,Control!$F$10))*100))<25,"n/m",IFERROR((((INDEX(HIST_D!$CL$8:$CL$2617,1)-INDEX(HIST_D!$CL$8:$CL$2617,Control!$F$10))*100))/(((INDEX(HIST_D!$D$8:$D$2617,1)-INDEX(HIST_D!$D$8:$D$2617,Control!$F$10))*100)),"n/m")) | J26: =IF(ABS(((INDEX(HIST_D!$D$8:$D$2617,1)-INDEX(HIST_D!$D$8:$D$2617,Control!$F$11))*100))<25,"n/m",IFERROR((((INDEX(HIST_D!$CL$8:$CL$2617,1)-INDEX(HIST_D!$CL$8:$CL$2617,Control!$F$11))*100))/(((INDEX(HIST_D!$D$8:$D$2617,1)-INDEX(HIST_D!$D$8:$D$2617,Control!$F$11))*100)),"n/m")) | K26: =IF(ABS(((INDEX(HIST_D!$D$8:$D$2617,1)-INDEX(HIST_D!$D$8:$D$2617,Control!$F$13))*100))<25,"n/m",IFERROR((((INDEX(HIST_D!$CL$8:$CL$2617,1)-INDEX(HIST_D!$CL$8:$CL$2617,Control!$F$13))*100))/(((INDEX(HIST_D!$D$8:$D$2617,1)-INDEX(HIST_D!$D$8:$D$2617,Control!$F$13))*100)),"n/m")) | L26: =IFERROR(INDEX(HIST_D!$AL$8:$AL$2617,Control!$F$8)/INDEX(HIST_D!$AL$8:$AL$2617,1)-1,"") | M26: =IFERROR((INDEX(HIST_D!$CL$8:$CL$2617,1)-INDEX(HIST_D!$D$8:$D$2617,1))*100,"") | N26: =IFERROR(PERCENTRANK(HIST_D!$EA$8:INDEX(HIST_D!$EA$8:$EA$2617,Control!$F$14),(INDEX(HIST_D!$CL$8:$CL$2617,1)-INDEX(HIST_D!$D$8:$D$2617,1))*100),"") | O26: =IF(NOT(ISNUMBER($G26)),"n/m",IF($G26<0,"absorbed and tightened",IF($G26<0.5,"absorbed most of it",IF($G26<1,"partial pass-through",IF($G26<1.5,"one-for-one","amplified")))))
A27: South Africa 10Y | B27: =INDEX(HIST_D!$CM$8:$CM$2617,1) | C27: =IFERROR((INDEX(HIST_D!$CM$8:$CM$2617,1)-INDEX(HIST_D!$CM$8:$CM$2617,Control!$F$8))*100,"") | D27: =IFERROR((INDEX(HIST_D!$CM$8:$CM$2617,1)-INDEX(HIST_D!$CM$8:$CM$2617,Control!$F$9))*100,"") | E27: =IFERROR((INDEX(HIST_D!$CM$8:$CM$2617,1)-INDEX(HIST_D!$CM$8:$CM$2617,Control!$F$10))*100,"") | F27: =IFERROR((INDEX(HIST_D!$CM$8:$CM$2617,1)-INDEX(HIST_D!$CM$8:$CM$2617,Control!$F$11))*100,"") | G27: =IF(ABS(((INDEX(HIST_D!$D$8:$D$2617,1)-INDEX(HIST_D!$D$8:$D$2617,Control!$F$8))*100))<25,"n/m",IFERROR((((INDEX(HIST_D!$CM$8:$CM$2617,1)-INDEX(HIST_D!$CM$8:$CM$2617,Control!$F$8))*100))/(((INDEX(HIST_D!$D$8:$D$2617,1)-INDEX(HIST_D!$D$8:$D$2617,Control!$F$8))*100)),"n/m")) | H27: =IF(ABS(((INDEX(HIST_D!$D$8:$D$2617,1)-INDEX(HIST_D!$D$8:$D$2617,Control!$F$9))*100))<25,"n/m",IFERROR((((INDEX(HIST_D!$CM$8:$CM$2617,1)-INDEX(HIST_D!$CM$8:$CM$2617,Control!$F$9))*100))/(((INDEX(HIST_D!$D$8:$D$2617,1)-INDEX(HIST_D!$D$8:$D$2617,Control!$F$9))*100)),"n/m")) | I27: =IF(ABS(((INDEX(HIST_D!$D$8:$D$2617,1)-INDEX(HIST_D!$D$8:$D$2617,Control!$F$10))*100))<25,"n/m",IFERROR((((INDEX(HIST_D!$CM$8:$CM$2617,1)-INDEX(HIST_D!$CM$8:$CM$2617,Control!$F$10))*100))/(((INDEX(HIST_D!$D$8:$D$2617,1)-INDEX(HIST_D!$D$8:$D$2617,Control!$F$10))*100)),"n/m")) | J27: =IF(ABS(((INDEX(HIST_D!$D$8:$D$2617,1)-INDEX(HIST_D!$D$8:$D$2617,Control!$F$11))*100))<25,"n/m",IFERROR((((INDEX(HIST_D!$CM$8:$CM$2617,1)-INDEX(HIST_D!$CM$8:$CM$2617,Control!$F$11))*100))/(((INDEX(HIST_D!$D$8:$D$2617,1)-INDEX(HIST_D!$D$8:$D$2617,Control!$F$11))*100)),"n/m")) | K27: =IF(ABS(((INDEX(HIST_D!$D$8:$D$2617,1)-INDEX(HIST_D!$D$8:$D$2617,Control!$F$13))*100))<25,"n/m",IFERROR((((INDEX(HIST_D!$CM$8:$CM$2617,1)-INDEX(HIST_D!$CM$8:$CM$2617,Control!$F$13))*100))/(((INDEX(HIST_D!$D$8:$D$2617,1)-INDEX(HIST_D!$D$8:$D$2617,Control!$F$13))*100)),"n/m")) | L27: =IFERROR(INDEX(HIST_D!$AM$8:$AM$2617,Control!$F$8)/INDEX(HIST_D!$AM$8:$AM$2617,1)-1,"") | M27: =IFERROR((INDEX(HIST_D!$CM$8:$CM$2617,1)-INDEX(HIST_D!$D$8:$D$2617,1))*100,"") | N27: =IFERROR(PERCENTRANK(HIST_D!$EA$8:INDEX(HIST_D!$EA$8:$EA$2617,Control!$F$14),(INDEX(HIST_D!$CM$8:$CM$2617,1)-INDEX(HIST_D!$D$8:$D$2617,1))*100),"") | O27: =IF(NOT(ISNUMBER($G27)),"n/m",IF($G27<0,"absorbed and tightened",IF($G27<0.5,"absorbed most of it",IF($G27<1,"partial pass-through",IF($G27<1.5,"one-for-one","amplified")))))
A28: Middle East & Africa (eq-wgt, n=2) | B28: =IFERROR(AVERAGE(B26,B27),"") | C28: =IFERROR(AVERAGE(C26,C27),"") | D28: =IFERROR(AVERAGE(D26,D27),"") | E28: =IFERROR(AVERAGE(E26,E27),"") | F28: =IFERROR(AVERAGE(F26,F27),"") | G28: =IFERROR(AVERAGE(G26,G27),"") | H28: =IFERROR(AVERAGE(H26,H27),"") | I28: =IFERROR(AVERAGE(I26,I27),"") | ... N28: =IFERROR(AVERAGE(N26,N27),"")
A29: =IFERROR("Middle East & Africa: local 10Y "&TEXT($C$28,"+0;-0")&"bp on the month against the US, pass-through "&IF(ISNUMBER($G$28),TEXT($G$28,"0.00")&"x","n/m")&" over 1M and "&IF(ISNUMBER($J$28),TEXT($J$28,"0.00")&"x","n/m")&" over 1Y; FX "&TEXT($L$28,"+0.0%;-0.0%")&". "&IF(NOT(ISNUMBER($G$28)),"The US move over this window is too small to form a ratio.",IF($G$28<0.5,"The curve is absorbing most of the US move rather than importing it.",IF($G$28<1,"Partial pass-through — some import, but less than one-for-one.","The curve is taking the full US move or more; this is where the digestion argument is weakest.")))&" Only Israel and South Africa carry a usable local curve here — the GCC runs pegged currencies and thin local markets, so this region's rate transmission shows up in USD credit, not in a local curve or an FX rate. ","")
A31: ASIA
A32: Market | B32: Local 10Y (%) | C32: d 1M (bp) | D32: d 3M (bp) | E32: d 6M (bp) | F32: d 1Y (bp) | G32: PT 1M | H32: PT 3M | I32: PT 6M | J32: PT 1Y | K32: PT 3Y | L32: FX 1M | M32: Local less UST (bp) | N32: %ile 5y (gap) | O32: Verdict
A33: China 10Y | B33: =INDEX(HIST_D!$CN$8:$CN$2617,1) | C33: =IFERROR((INDEX(HIST_D!$CN$8:$CN$2617,1)-INDEX(HIST_D!$CN$8:$CN$2617,Control!$F$8))*100,"") | D33: =IFERROR((INDEX(HIST_D!$CN$8:$CN$2617,1)-INDEX(HIST_D!$CN$8:$CN$2617,Control!$F$9))*100,"") | E33: =IFERROR((INDEX(HIST_D!$CN$8:$CN$2617,1)-INDEX(HIST_D!$CN$8:$CN$2617,Control!$F$10))*100,"") | F33: =IFERROR((INDEX(HIST_D!$CN$8:$CN$2617,1)-INDEX(HIST_D!$CN$8:$CN$2617,Control!$F$11))*100,"") | G33: =IF(ABS(((INDEX(HIST_D!$D$8:$D$2617,1)-INDEX(HIST_D!$D$8:$D$2617,Control!$F$8))*100))<25,"n/m",IFERROR((((INDEX(HIST_D!$CN$8:$CN$2617,1)-INDEX(HIST_D!$CN$8:$CN$2617,Control!$F$8))*100))/(((INDEX(HIST_D!$D$8:$D$2617,1)-INDEX(HIST_D!$D$8:$D$2617,Control!$F$8))*100)),"n/m")) | H33: =IF(ABS(((INDEX(HIST_D!$D$8:$D$2617,1)-INDEX(HIST_D!$D$8:$D$2617,Control!$F$9))*100))<25,"n/m",IFERROR((((INDEX(HIST_D!$CN$8:$CN$2617,1)-INDEX(HIST_D!$CN$8:$CN$2617,Control!$F$9))*100))/(((INDEX(HIST_D!$D$8:$D$2617,1)-INDEX(HIST_D!$D$8:$D$2617,Control!$F$9))*100)),"n/m")) | I33: =IF(ABS(((INDEX(HIST_D!$D$8:$D$2617,1)-INDEX(HIST_D!$D$8:$D$2617,Control!$F$10))*100))<25,"n/m",IFERROR((((INDEX(HIST_D!$CN$8:$CN$2617,1)-INDEX(HIST_D!$CN$8:$CN$2617,Control!$F$10))*100))/(((INDEX(HIST_D!$D$8:$D$2617,1)-INDEX(HIST_D!$D$8:$D$2617,Control!$F$10))*100)),"n/m")) | J33: =IF(ABS(((INDEX(HIST_D!$D$8:$D$2617,1)-INDEX(HIST_D!$D$8:$D$2617,Control!$F$11))*100))<25,"n/m",IFERROR((((INDEX(HIST_D!$CN$8:$CN$2617,1)-INDEX(HIST_D!$CN$8:$CN$2617,Control!$F$11))*100))/(((INDEX(HIST_D!$D$8:$D$2617,1)-INDEX(HIST_D!$D$8:$D$2617,Control!$F$11))*100)),"n/m")) | K33: =IF(ABS(((INDEX(HIST_D!$D$8:$D$2617,1)-INDEX(HIST_D!$D$8:$D$2617,Control!$F$13))*100))<25,"n/m",IFERROR((((INDEX(HIST_D!$CN$8:$CN$2617,1)-INDEX(HIST_D!$CN$8:$CN$2617,Control!$F$13))*100))/(((INDEX(HIST_D!$D$8:$D$2617,1)-INDEX(HIST_D!$D$8:$D$2617,Control!$F$13))*100)),"n/m")) | L33: =IFERROR(INDEX(HIST_D!$AR$8:$AR$2617,Control!$F$8)/INDEX(HIST_D!$AR$8:$AR$2617,1)-1,"") | M33: =IFERROR((INDEX(HIST_D!$CN$8:$CN$2617,1)-INDEX(HIST_D!$D$8:$D$2617,1))*100,"") | N33: =IFERROR(PERCENTRANK(HIST_D!$EA$8:INDEX(HIST_D!$EA$8:$EA$2617,Control!$F$14),(INDEX(HIST_D!$CN$8:$CN$2617,1)-INDEX(HIST_D!$D$8:$D$2617,1))*100),"") | O33: =IF(NOT(ISNUMBER($G33)),"n/m",IF($G33<0,"absorbed and tightened",IF($G33<0.5,"absorbed most of it",IF($G33<1,"partial pass-through",IF($G33<1.5,"one-for-one","amplified")))))
A34: India 10Y | B34: =INDEX(HIST_D!$CO$8:$CO$2617,1) | C34: =IFERROR((INDEX(HIST_D!$CO$8:$CO$2617,1)-INDEX(HIST_D!$CO$8:$CO$2617,Control!$F$8))*100,"") | D34: =IFERROR((INDEX(HIST_D!$CO$8:$CO$2617,1)-INDEX(HIST_D!$CO$8:$CO$2617,Control!$F$9))*100,"") | E34: =IFERROR((INDEX(HIST_D!$CO$8:$CO$2617,1)-INDEX(HIST_D!$CO$8:$CO$2617,Control!$F$10))*100,"") | F34: =IFERROR((INDEX(HIST_D!$CO$8:$CO$2617,1)-INDEX(HIST_D!$CO$8:$CO$2617,Control!$F$11))*100,"") | G34: =IF(ABS(((INDEX(HIST_D!$D$8:$D$2617,1)-INDEX(HIST_D!$D$8:$D$2617,Control!$F$8))*100))<25,"n/m",IFERROR((((INDEX(HIST_D!$CO$8:$CO$2617,1)-INDEX(HIST_D!$CO$8:$CO$2617,Control!$F$8))*100))/(((INDEX(HIST_D!$D$8:$D$2617,1)-INDEX(HIST_D!$D$8:$D$2617,Control!$F$8))*100)),"n/m")) | H34: =IF(ABS(((INDEX(HIST_D!$D$8:$D$2617,1)-INDEX(HIST_D!$D$8:$D$2617,Control!$F$9))*100))<25,"n/m",IFERROR((((INDEX(HIST_D!$CO$8:$CO$2617,1)-INDEX(HIST_D!$CO$8:$CO$2617,Control!$F$9))*100))/(((INDEX(HIST_D!$D$8:$D$2617,1)-INDEX(HIST_D!$D$8:$D$2617,Control!$F$9))*100)),"n/m")) | I34: =IF(ABS(((INDEX(HIST_D!$D$8:$D$2617,1)-INDEX(HIST_D!$D$8:$D$2617,Control!$F$10))*100))<25,"n/m",IFERROR((((INDEX(HIST_D!$CO$8:$CO$2617,1)-INDEX(HIST_D!$CO$8:$CO$2617,Control!$F$10))*100))/(((INDEX(HIST_D!$D$8:$D$2617,1)-INDEX(HIST_D!$D$8:$D$2617,Control!$F$10))*100)),"n/m")) | J34: =IF(ABS(((INDEX(HIST_D!$D$8:$D$2617,1)-INDEX(HIST_D!$D$8:$D$2617,Control!$F$11))*100))<25,"n/m",IFERROR((((INDEX(HIST_D!$CO$8:$CO$2617,1)-INDEX(HIST_D!$CO$8:$CO$2617,Control!$F$11))*100))/(((INDEX(HIST_D!$D$8:$D$2617,1)-INDEX(HIST_D!$D$8:$D$2617,Control!$F$11))*100)),"n/m")) | K34: =IF(ABS(((INDEX(HIST_D!$D$8:$D$2617,1)-INDEX(HIST_D!$D$8:$D$2617,Control!$F$13))*100))<25,"n/m",IFERROR((((INDEX(HIST_D!$CO$8:$CO$2617,1)-INDEX(HIST_D!$CO$8:$CO$2617,Control!$F$13))*100))/(((INDEX(HIST_D!$D$8:$D$2617,1)-INDEX(HIST_D!$D$8:$D$2617,Control!$F$13))*100)),"n/m")) | L34: =IFERROR(INDEX(HIST_D!$AS$8:$AS$2617,Control!$F$8)/INDEX(HIST_D!$AS$8:$AS$2617,1)-1,"") | M34: =IFERROR((INDEX(HIST_D!$CO$8:$CO$2617,1)-INDEX(HIST_D!$D$8:$D$2617,1))*100,"") | N34: =IFERROR(PERCENTRANK(HIST_D!$EA$8:INDEX(HIST_D!$EA$8:$EA$2617,Control!$F$14),(INDEX(HIST_D!$CO$8:$CO$2617,1)-INDEX(HIST_D!$D$8:$D$2617,1))*100),"") | O34: =IF(NOT(ISNUMBER($G34)),"n/m",IF($G34<0,"absorbed and tightened",IF($G34<0.5,"absorbed most of it",IF($G34<1,"partial pass-through",IF($G34<1.5,"one-for-one","amplified")))))
A35: Indonesia 10Y | B35: =INDEX(HIST_D!$CP$8:$CP$2617,1) | C35: =IFERROR((INDEX(HIST_D!$CP$8:$CP$2617,1)-INDEX(HIST_D!$CP$8:$CP$2617,Control!$F$8))*100,"") | D35: =IFERROR((INDEX(HIST_D!$CP$8:$CP$2617,1)-INDEX(HIST_D!$CP$8:$CP$2617,Control!$F$9))*100,"") | E35: =IFERROR((INDEX(HIST_D!$CP$8:$CP$2617,1)-INDEX(HIST_D!$CP$8:$CP$2617,Control!$F$10))*100,"") | F35: =IFERROR((INDEX(HIST_D!$CP$8:$CP$2617,1)-INDEX(HIST_D!$CP$8:$CP$2617,Control!$F$11))*100,"") | G35: =IF(ABS(((INDEX(HIST_D!$D$8:$D$2617,1)-INDEX(HIST_D!$D$8:$D$2617,Control!$F$8))*100))<25,"n/m",IFERROR((((INDEX(HIST_D!$CP$8:$CP$2617,1)-INDEX(HIST_D!$CP$8:$CP$2617,Control!$F$8))*100))/(((INDEX(HIST_D!$D$8:$D$2617,1)-INDEX(HIST_D!$D$8:$D$2617,Control!$F$8))*100)),"n/m")) | H35: =IF(ABS(((INDEX(HIST_D!$D$8:$D$2617,1)-INDEX(HIST_D!$D$8:$D$2617,Control!$F$9))*100))<25,"n/m",IFERROR((((INDEX(HIST_D!$CP$8:$CP$2617,1)-INDEX(HIST_D!$CP$8:$CP$2617,Control!$F$9))*100))/(((INDEX(HIST_D!$D$8:$D$2617,1)-INDEX(HIST_D!$D$8:$D$2617,Control!$F$9))*100)),"n/m")) | I35: =IF(ABS(((INDEX(HIST_D!$D$8:$D$2617,1)-INDEX(HIST_D!$D$8:$D$2617,Control!$F$10))*100))<25,"n/m",IFERROR((((INDEX(HIST_D!$CP$8:$CP$2617,1)-INDEX(HIST_D!$CP$8:$CP$2617,Control!$F$10))*100))/(((INDEX(HIST_D!$D$8:$D$2617,1)-INDEX(HIST_D!$D$8:$D$2617,Control!$F$10))*100)),"n/m")) | J35: =IF(ABS(((INDEX(HIST_D!$D$8:$D$2617,1)-INDEX(HIST_D!$D$8:$D$2617,Control!$F$11))*100))<25,"n/m",IFERROR((((INDEX(HIST_D!$CP$8:$CP$2617,1)-INDEX(HIST_D!$CP$8:$CP$2617,Control!$F$11))*100))/(((INDEX(HIST_D!$D$8:$D$2617,1)-INDEX(HIST_D!$D$8:$D$2617,Control!$F$11))*100)),"n/m")) | K35: =IF(ABS(((INDEX(HIST_D!$D$8:$D$2617,1)-INDEX(HIST_D!$D$8:$D$2617,Control!$F$13))*100))<25,"n/m",IFERROR((((INDEX(HIST_D!$CP$8:$CP$2617,1)-INDEX(HIST_D!$CP$8:$CP$2617,Control!$F$13))*100))/(((INDEX(HIST_D!$D$8:$D$2617,1)-INDEX(HIST_D!$D$8:$D$2617,Control!$F$13))*100)),"n/m")) | L35: =IFERROR(INDEX(HIST_D!$AT$8:$AT$2617,Control!$F$8)/INDEX(HIST_D!$AT$8:$AT$2617,1)-1,"") | M35: =IFERROR((INDEX(HIST_D!$CP$8:$CP$2617,1)-INDEX(HIST_D!$D$8:$D$2617,1))*100,"") | N35: =IFERROR(PERCENTRANK(HIST_D!$EA$8:INDEX(HIST_D!$EA$8:$EA$2617,Control!$F$14),(INDEX(HIST_D!$CP$8:$CP$2617,1)-INDEX(HIST_D!$D$8:$D$2617,1))*100),"") | O35: =IF(NOT(ISNUMBER($G35)),"n/m",IF($G35<0,"absorbed and tightened",IF($G35<0.5,"absorbed most of it",IF($G35<1,"partial pass-through",IF($G35<1.5,"one-for-one","amplified")))))
A36: Korea 10Y | B36: =INDEX(HIST_D!$CQ$8:$CQ$2617,1) | C36: =IFERROR((INDEX(HIST_D!$CQ$8:$CQ$2617,1)-INDEX(HIST_D!$CQ$8:$CQ$2617,Control!$F$8))*100,"") | D36: =IFERROR((INDEX(HIST_D!$CQ$8:$CQ$2617,1)-INDEX(HIST_D!$CQ$8:$CQ$2617,Control!$F$9))*100,"") | E36: =IFERROR((INDEX(HIST_D!$CQ$8:$CQ$2617,1)-INDEX(HIST_D!$CQ$8:$CQ$2617,Control!$F$10))*100,"") | F36: =IFERROR((INDEX(HIST_D!$CQ$8:$CQ$2617,1)-INDEX(HIST_D!$CQ$8:$CQ$2617,Control!$F$11))*100,"") | G36: =IF(ABS(((INDEX(HIST_D!$D$8:$D$2617,1)-INDEX(HIST_D!$D$8:$D$2617,Control!$F$8))*100))<25,"n/m",IFERROR((((INDEX(HIST_D!$CQ$8:$CQ$2617,1)-INDEX(HIST_D!$CQ$8:$CQ$2617,Control!$F$8))*100))/(((INDEX(HIST_D!$D$8:$D$2617,1)-INDEX(HIST_D!$D$8:$D$2617,Control!$F$8))*100)),"n/m")) | H36: =IF(ABS(((INDEX(HIST_D!$D$8:$D$2617,1)-INDEX(HIST_D!$D$8:$D$2617,Control!$F$9))*100))<25,"n/m",IFERROR((((INDEX(HIST_D!$CQ$8:$CQ$2617,1)-INDEX(HIST_D!$CQ$8:$CQ$2617,Control!$F$9))*100))/(((INDEX(HIST_D!$D$8:$D$2617,1)-INDEX(HIST_D!$D$8:$D$2617,Control!$F$9))*100)),"n/m")) | I36: =IF(ABS(((INDEX(HIST_D!$D$8:$D$2617,1)-INDEX(HIST_D!$D$8:$D$2617,Control!$F$10))*100))<25,"n/m",IFERROR((((INDEX(HIST_D!$CQ$8:$CQ$2617,1)-INDEX(HIST_D!$CQ$8:$CQ$2617,Control!$F$10))*100))/(((INDEX(HIST_D!$D$8:$D$2617,1)-INDEX(HIST_D!$D$8:$D$2617,Control!$F$10))*100)),"n/m")) | J36: =IF(ABS(((INDEX(HIST_D!$D$8:$D$2617,1)-INDEX(HIST_D!$D$8:$D$2617,Control!$F$11))*100))<25,"n/m",IFERROR((((INDEX(HIST_D!$CQ$8:$CQ$2617,1)-INDEX(HIST_D!$CQ$8:$CQ$2617,Control!$F$11))*100))/(((INDEX(HIST_D!$D$8:$D$2617,1)-INDEX(HIST_D!$D$8:$D$2617,Control!$F$11))*100)),"n/m")) | K36: =IF(ABS(((INDEX(HIST_D!$D$8:$D$2617,1)-INDEX(HIST_D!$D$8:$D$2617,Control!$F$13))*100))<25,"n/m",IFERROR((((INDEX(HIST_D!$CQ$8:$CQ$2617,1)-INDEX(HIST_D!$CQ$8:$CQ$2617,Control!$F$13))*100))/(((INDEX(HIST_D!$D$8:$D$2617,1)-INDEX(HIST_D!$D$8:$D$2617,Control!$F$13))*100)),"n/m")) | L36: =IFERROR(INDEX(HIST_D!$AU$8:$AU$2617,Control!$F$8)/INDEX(HIST_D!$AU$8:$AU$2617,1)-1,"") | M36: =IFERROR((INDEX(HIST_D!$CQ$8:$CQ$2617,1)-INDEX(HIST_D!$D$8:$D$2617,1))*100,"") | N36: =IFERROR(PERCENTRANK(HIST_D!$EA$8:INDEX(HIST_D!$EA$8:$EA$2617,Control!$F$14),(INDEX(HIST_D!$CQ$8:$CQ$2617,1)-INDEX(HIST_D!$D$8:$D$2617,1))*100),"") | O36: =IF(NOT(ISNUMBER($G36)),"n/m",IF($G36<0,"absorbed and tightened",IF($G36<0.5,"absorbed most of it",IF($G36<1,"partial pass-through",IF($G36<1.5,"one-for-one","amplified")))))
A37: Thailand 10Y | B37: =INDEX(HIST_D!$CR$8:$CR$2617,1) | C37: =IFERROR((INDEX(HIST_D!$CR$8:$CR$2617,1)-INDEX(HIST_D!$CR$8:$CR$2617,Control!$F$8))*100,"") | D37: =IFERROR((INDEX(HIST_D!$CR$8:$CR$2617,1)-INDEX(HIST_D!$CR$8:$CR$2617,Control!$F$9))*100,"") | E37: =IFERROR((INDEX(HIST_D!$CR$8:$CR$2617,1)-INDEX(HIST_D!$CR$8:$CR$2617,Control!$F$10))*100,"") | F37: =IFERROR((INDEX(HIST_D!$CR$8:$CR$2617,1)-INDEX(HIST_D!$CR$8:$CR$2617,Control!$F$11))*100,"") | G37: =IF(ABS(((INDEX(HIST_D!$D$8:$D$2617,1)-INDEX(HIST_D!$D$8:$D$2617,Control!$F$8))*100))<25,"n/m",IFERROR((((INDEX(HIST_D!$CR$8:$CR$2617,1)-INDEX(HIST_D!$CR$8:$CR$2617,Control!$F$8))*100))/(((INDEX(HIST_D!$D$8:$D$2617,1)-INDEX(HIST_D!$D$8:$D$2617,Control!$F$8))*100)),"n/m")) | H37: =IF(ABS(((INDEX(HIST_D!$D$8:$D$2617,1)-INDEX(HIST_D!$D$8:$D$2617,Control!$F$9))*100))<25,"n/m",IFERROR((((INDEX(HIST_D!$CR$8:$CR$2617,1)-INDEX(HIST_D!$CR$8:$CR$2617,Control!$F$9))*100))/(((INDEX(HIST_D!$D$8:$D$2617,1)-INDEX(HIST_D!$D$8:$D$2617,Control!$F$9))*100)),"n/m")) | I37: =IF(ABS(((INDEX(HIST_D!$D$8:$D$2617,1)-INDEX(HIST_D!$D$8:$D$2617,Control!$F$10))*100))<25,"n/m",IFERROR((((INDEX(HIST_D!$CR$8:$CR$2617,1)-INDEX(HIST_D!$CR$8:$CR$2617,Control!$F$10))*100))/(((INDEX(HIST_D!$D$8:$D$2617,1)-INDEX(HIST_D!$D$8:$D$2617,Control!$F$10))*100)),"n/m")) | J37: =IF(ABS(((INDEX(HIST_D!$D$8:$D$2617,1)-INDEX(HIST_D!$D$8:$D$2617,Control!$F$11))*100))<25,"n/m",IFERROR((((INDEX(HIST_D!$CR$8:$CR$2617,1)-INDEX(HIST_D!$CR$8:$CR$2617,Control!$F$11))*100))/(((INDEX(HIST_D!$D$8:$D$2617,1)-INDEX(HIST_D!$D$8:$D$2617,Control!$F$11))*100)),"n/m")) | K37: =IF(ABS(((INDEX(HIST_D!$D$8:$D$2617,1)-INDEX(HIST_D!$D$8:$D$2617,Control!$F$13))*100))<25,"n/m",IFERROR((((INDEX(HIST_D!$CR$8:$CR$2617,1)-INDEX(HIST_D!$CR$8:$CR$2617,Control!$F$13))*100))/(((INDEX(HIST_D!$D$8:$D$2617,1)-INDEX(HIST_D!$D$8:$D$2617,Control!$F$13))*100)),"n/m")) | L37: =IFERROR(INDEX(HIST_D!$AW$8:$AW$2617,Control!$F$8)/INDEX(HIST_D!$AW$8:$AW$2617,1)-1,"") | M37: =IFERROR((INDEX(HIST_D!$CR$8:$CR$2617,1)-INDEX(HIST_D!$D$8:$D$2617,1))*100,"") | N37: =IFERROR(PERCENTRANK(HIST_D!$EA$8:INDEX(HIST_D!$EA$8:$EA$2617,Control!$F$14),(INDEX(HIST_D!$CR$8:$CR$2617,1)-INDEX(HIST_D!$D$8:$D$2617,1))*100),"") | O37: =IF(NOT(ISNUMBER($G37)),"n/m",IF($G37<0,"absorbed and tightened",IF($G37<0.5,"absorbed most of it",IF($G37<1,"partial pass-through",IF($G37<1.5,"one-for-one","amplified")))))
A38: Philippines 10Y | B38: =INDEX(HIST_D!$CS$8:$CS$2617,1) | C38: =IFERROR((INDEX(HIST_D!$CS$8:$CS$2617,1)-INDEX(HIST_D!$CS$8:$CS$2617,Control!$F$8))*100,"") | D38: =IFERROR((INDEX(HIST_D!$CS$8:$CS$2617,1)-INDEX(HIST_D!$CS$8:$CS$2617,Control!$F$9))*100,"") | E38: =IFERROR((INDEX(HIST_D!$CS$8:$CS$2617,1)-INDEX(HIST_D!$CS$8:$CS$2617,Control!$F$10))*100,"") | F38: =IFERROR((INDEX(HIST_D!$CS$8:$CS$2617,1)-INDEX(HIST_D!$CS$8:$CS$2617,Control!$F$11))*100,"") | G38: =IF(ABS(((INDEX(HIST_D!$D$8:$D$2617,1)-INDEX(HIST_D!$D$8:$D$2617,Control!$F$8))*100))<25,"n/m",IFERROR((((INDEX(HIST_D!$CS$8:$CS$2617,1)-INDEX(HIST_D!$CS$8:$CS$2617,Control!$F$8))*100))/(((INDEX(HIST_D!$D$8:$D$2617,1)-INDEX(HIST_D!$D$8:$D$2617,Control!$F$8))*100)),"n/m")) | H38: =IF(ABS(((INDEX(HIST_D!$D$8:$D$2617,1)-INDEX(HIST_D!$D$8:$D$2617,Control!$F$9))*100))<25,"n/m",IFERROR((((INDEX(HIST_D!$CS$8:$CS$2617,1)-INDEX(HIST_D!$CS$8:$CS$2617,Control!$F$9))*100))/(((INDEX(HIST_D!$D$8:$D$2617,1)-INDEX(HIST_D!$D$8:$D$2617,Control!$F$9))*100)),"n/m")) | I38: =IF(ABS(((INDEX(HIST_D!$D$8:$D$2617,1)-INDEX(HIST_D!$D$8:$D$2617,Control!$F$10))*100))<25,"n/m",IFERROR((((INDEX(HIST_D!$CS$8:$CS$2617,1)-INDEX(HIST_D!$CS$8:$CS$2617,Control!$F$10))*100))/(((INDEX(HIST_D!$D$8:$D$2617,1)-INDEX(HIST_D!$D$8:$D$2617,Control!$F$10))*100)),"n/m")) | J38: =IF(ABS(((INDEX(HIST_D!$D$8:$D$2617,1)-INDEX(HIST_D!$D$8:$D$2617,Control!$F$11))*100))<25,"n/m",IFERROR((((INDEX(HIST_D!$CS$8:$CS$2617,1)-INDEX(HIST_D!$CS$8:$CS$2617,Control!$F$11))*100))/(((INDEX(HIST_D!$D$8:$D$2617,1)-INDEX(HIST_D!$D$8:$D$2617,Control!$F$11))*100)),"n/m")) | K38: =IF(ABS(((INDEX(HIST_D!$D$8:$D$2617,1)-INDEX(HIST_D!$D$8:$D$2617,Control!$F$13))*100))<25,"n/m",IFERROR((((INDEX(HIST_D!$CS$8:$CS$2617,1)-INDEX(HIST_D!$CS$8:$CS$2617,Control!$F$13))*100))/(((INDEX(HIST_D!$D$8:$D$2617,1)-INDEX(HIST_D!$D$8:$D$2617,Control!$F$13))*100)),"n/m")) | L38: =IFERROR(INDEX(HIST_D!$AX$8:$AX$2617,Control!$F$8)/INDEX(HIST_D!$AX$8:$AX$2617,1)-1,"") | M38: =IFERROR((INDEX(HIST_D!$CS$8:$CS$2617,1)-INDEX(HIST_D!$D$8:$D$2617,1))*100,"") | N38: =IFERROR(PERCENTRANK(HIST_D!$EA$8:INDEX(HIST_D!$EA$8:$EA$2617,Control!$F$14),(INDEX(HIST_D!$CS$8:$CS$2617,1)-INDEX(HIST_D!$D$8:$D$2617,1))*100),"") | O38: =IF(NOT(ISNUMBER($G38)),"n/m",IF($G38<0,"absorbed and tightened",IF($G38<0.5,"absorbed most of it",IF($G38<1,"partial pass-through",IF($G38<1.5,"one-for-one","amplified")))))
A39: Malaysia 10Y | B39: =INDEX(HIST_D!$CT$8:$CT$2617,1) | C39: =IFERROR((INDEX(HIST_D!$CT$8:$CT$2617,1)-INDEX(HIST_D!$CT$8:$CT$2617,Control!$F$8))*100,"") | D39: =IFERROR((INDEX(HIST_D!$CT$8:$CT$2617,1)-INDEX(HIST_D!$CT$8:$CT$2617,Control!$F$9))*100,"") | E39: =IFERROR((INDEX(HIST_D!$CT$8:$CT$2617,1)-INDEX(HIST_D!$CT$8:$CT$2617,Control!$F$10))*100,"") | F39: =IFERROR((INDEX(HIST_D!$CT$8:$CT$2617,1)-INDEX(HIST_D!$CT$8:$CT$2617,Control!$F$11))*100,"") | G39: =IF(ABS(((INDEX(HIST_D!$D$8:$D$2617,1)-INDEX(HIST_D!$D$8:$D$2617,Control!$F$8))*100))<25,"n/m",IFERROR((((INDEX(HIST_D!$CT$8:$CT$2617,1)-INDEX(HIST_D!$CT$8:$CT$2617,Control!$F$8))*100))/(((INDEX(HIST_D!$D$8:$D$2617,1)-INDEX(HIST_D!$D$8:$D$2617,Control!$F$8))*100)),"n/m")) | H39: =IF(ABS(((INDEX(HIST_D!$D$8:$D$2617,1)-INDEX(HIST_D!$D$8:$D$2617,Control!$F$9))*100))<25,"n/m",IFERROR((((INDEX(HIST_D!$CT$8:$CT$2617,1)-INDEX(HIST_D!$CT$8:$CT$2617,Control!$F$9))*100))/(((INDEX(HIST_D!$D$8:$D$2617,1)-INDEX(HIST_D!$D$8:$D$2617,Control!$F$9))*100)),"n/m")) | I39: =IF(ABS(((INDEX(HIST_D!$D$8:$D$2617,1)-INDEX(HIST_D!$D$8:$D$2617,Control!$F$10))*100))<25,"n/m",IFERROR((((INDEX(HIST_D!$CT$8:$CT$2617,1)-INDEX(HIST_D!$CT$8:$CT$2617,Control!$F$10))*100))/(((INDEX(HIST_D!$D$8:$D$2617,1)-INDEX(HIST_D!$D$8:$D$2617,Control!$F$10))*100)),"n/m")) | J39: =IF(ABS(((INDEX(HIST_D!$D$8:$D$2617,1)-INDEX(HIST_D!$D$8:$D$2617,Control!$F$11))*100))<25,"n/m",IFERROR((((INDEX(HIST_D!$CT$8:$CT$2617,1)-INDEX(HIST_D!$CT$8:$CT$2617,Control!$F$11))*100))/(((INDEX(HIST_D!$D$8:$D$2617,1)-INDEX(HIST_D!$D$8:$D$2617,Control!$F$11))*100)),"n/m")) | K39: =IF(ABS(((INDEX(HIST_D!$D$8:$D$2617,1)-INDEX(HIST_D!$D$8:$D$2617,Control!$F$13))*100))<25,"n/m",IFERROR((((INDEX(HIST_D!$CT$8:$CT$2617,1)-INDEX(HIST_D!$CT$8:$CT$2617,Control!$F$13))*100))/(((INDEX(HIST_D!$D$8:$D$2617,1)-INDEX(HIST_D!$D$8:$D$2617,Control!$F$13))*100)),"n/m")) | L39: =IFERROR(INDEX(HIST_D!$AY$8:$AY$2617,Control!$F$8)/INDEX(HIST_D!$AY$8:$AY$2617,1)-1,"") | M39: =IFERROR((INDEX(HIST_D!$CT$8:$CT$2617,1)-INDEX(HIST_D!$D$8:$D$2617,1))*100,"") | N39: =IFERROR(PERCENTRANK(HIST_D!$EA$8:INDEX(HIST_D!$EA$8:$EA$2617,Control!$F$14),(INDEX(HIST_D!$CT$8:$CT$2617,1)-INDEX(HIST_D!$D$8:$D$2617,1))*100),"") | O39: =IF(NOT(ISNUMBER($G39)),"n/m",IF($G39<0,"absorbed and tightened",IF($G39<0.5,"absorbed most of it",IF($G39<1,"partial pass-through",IF($G39<1.5,"one-for-one","amplified")))))
A40: Asia (eq-wgt, n=7) | B40: =IFERROR(AVERAGE(B33,B34,B35,B36,B37,B38,B39),"") | C40: =IFERROR(AVERAGE(C33,C34,C35,C36,C37,C38,C39),"") | D40: =IFERROR(AVERAGE(D33,D34,D35,D36,D37,D38,D39),"") | E40: =IFERROR(AVERAGE(E33,E34,E35,E36,E37,E38,E39),"") | F40: =IFERROR(AVERAGE(F33,F34,F35,F36,F37,F38,F39),"") | G40: =IFERROR(AVERAGE(G33,G34,G35,G36,G37,G38,G39),"") | H40: =IFERROR(AVERAGE(H33,H34,H35,H36,H37,H38,H39),"") | I40: =IFERROR(AVERAGE(I33,I34,I35,I36,I37,I38,I39),"") | ... N40: =IFERROR(AVERAGE(N33,N34,N35,N36,N37,N38,N39),"")
A41: =IFERROR("Asia: local 10Y "&TEXT($C$40,"+0;-0")&"bp on the month against the US, pass-through "&IF(ISNUMBER($G$40),TEXT($G$40,"0.00")&"x","n/m")&" over 1M and "&IF(ISNUMBER($J$40),TEXT($J$40,"0.00")&"x","n/m")&" over 1Y; FX "&TEXT($L$40,"+0.0%;-0.0%")&". "&IF(NOT(ISNUMBER($G$40)),"The US move over this window is too small to form a ratio.",IF($G$40<0.5,"The curve is absorbing most of the US move rather than importing it.",IF($G$40<1,"Partial pass-through — some import, but less than one-for-one.","The curve is taking the full US move or more; this is where the digestion argument is weakest.")))&" ","")
A43: EM AGGREGATE
A44: Market | B44: Local 10Y (%) | C44: d 1M (bp) | D44: d 3M (bp) | E44: d 6M (bp) | F44: d 1Y (bp) | G44: PT 1M | H44: PT 3M | I44: PT 6M | J44: PT 1Y | K44: PT 3Y | L44: FX 1M | M44: Local less UST (bp) | N44: %ile 5y (gap) | O44: Verdict
A45: EM, ex Turkiye (n=18) | B45: =IFERROR(AVERAGE(B6,B7,B8,B9,B10,B16,B17,B18,B19,B26,B27,B33,B34,B35,B36,B37,B38,B39),"") | C45: =IFERROR(AVERAGE(C6,C7,C8,C9,C10,C16,C17,C18,C19,C26,C27,C33,C34,C35,C36,C37,C38,C39),"") | D45: =IFERROR(AVERAGE(D6,D7,D8,D9,D10,D16,D17,D18,D19,D26,D27,D33,D34,D35,D36,D37,D38,D39),"") | E45: =IFERROR(AVERAGE(E6,E7,E8,E9,E10,E16,E17,E18,E19,E26,E27,E33,E34,E35,E36,E37,E38,E39),"") | F45: =IFERROR(AVERAGE(F6,F7,F8,F9,F10,F16,F17,F18,F19,F26,F27,F33,F34,F35,F36,F37,F38,F39),"") | G45: =IFERROR(AVERAGE(G6,G7,G8,G9,G10,G16,G17,G18,G19,G26,G27,G33,G34,G35,G36,G37,G38,G39),"") | H45: =IFERROR(AVERAGE(H6,H7,H8,H9,H10,H16,H17,H18,H19,H26,H27,H33,H34,H35,H36,H37,H38,H39),"") | I45: =IFERROR(AVERAGE(I6,I7,I8,I9,I10,I16,I17,I18,I19,I26,I27,I33,I34,I35,I36,I37,I38,I39),"") | ... N45: =IFERROR(AVERAGE(N6,N7,N8,N9,N10,N16,N17,N18,N19,N26,N27,N33,N34,N35,N36,N37,N38,N39),"")
A46: EM, all markets | B46: =IFERROR(AVERAGE(B6,B7,B8,B9,B10,B16,B17,B18,B19,B20,B26,B27,B33,B34,B35,B36,B37,B38,B39),"") | C46: =IFERROR(AVERAGE(C6,C7,C8,C9,C10,C16,C17,C18,C19,C20,C26,C27,C33,C34,C35,C36,C37,C38,C39),"") | D46: =IFERROR(AVERAGE(D6,D7,D8,D9,D10,D16,D17,D18,D19,D20,D26,D27,D33,D34,D35,D36,D37,D38,D39),"") | E46: =IFERROR(AVERAGE(E6,E7,E8,E9,E10,E16,E17,E18,E19,E20,E26,E27,E33,E34,E35,E36,E37,E38,E39),"") | F46: =IFERROR(AVERAGE(F6,F7,F8,F9,F10,F16,F17,F18,F19,F20,F26,F27,F33,F34,F35,F36,F37,F38,F39),"") | G46: =IFERROR(AVERAGE(G6,G7,G8,G9,G10,G16,G17,G18,G19,G20,G26,G27,G33,G34,G35,G36,G37,G38,G39),"") | H46: =IFERROR(AVERAGE(H6,H7,H8,H9,H10,H16,H17,H18,H19,H20,H26,H27,H33,H34,H35,H36,H37,H38,H39),"") | I46: =IFERROR(AVERAGE(I6,I7,I8,I9,I10,I16,I17,I18,I19,I20,I26,I27,I33,I34,I35,I36,I37,I38,I39),"") | ... N46: =IFERROR(AVERAGE(N6,N7,N8,N9,N10,N16,N17,N18,N19,N20,N26,N27,N33,N34,N35,N36,N37,N38,N39),"")
A47: High-beta (BRL MXN ZAR COP IDR) | B47: =IFERROR(AVERAGE(B6,B7,B27,B9,B35),"") | C47: =IFERROR(AVERAGE(C6,C7,C27,C9,C35),"") | D47: =IFERROR(AVERAGE(D6,D7,D27,D9,D35),"") | E47: =IFERROR(AVERAGE(E6,E7,E27,E9,E35),"") | F47: =IFERROR(AVERAGE(F6,F7,F27,F9,F35),"") | G47: =IFERROR(AVERAGE(G6,G7,G27,G9,G35),"") | H47: =IFERROR(AVERAGE(H6,H7,H27,H9,H35),"") | I47: =IFERROR(AVERAGE(I6,I7,I27,I9,I35),"") | ... N47: =IFERROR(AVERAGE(N6,N7,N27,N9,N35),"")
A48: EM basket ex TRY, ratio of the averages | B48: =INDEX(HIST_D!$DW$8:$DW$2617,1) | C48: =IFERROR((INDEX(HIST_D!$DW$8:$DW$2617,1)-INDEX(HIST_D!$DW$8:$DW$2617,Control!$F$8))*100,"") | D48: =IFERROR((INDEX(HIST_D!$DW$8:$DW$2617,1)-INDEX(HIST_D!$DW$8:$DW$2617,Control!$F$9))*100,"") | E48: =IFERROR((INDEX(HIST_D!$DW$8:$DW$2617,1)-INDEX(HIST_D!$DW$8:$DW$2617,Control!$F$10))*100,"") | F48: =IFERROR((INDEX(HIST_D!$DW$8:$DW$2617,1)-INDEX(HIST_D!$DW$8:$DW$2617,Control!$F$11))*100,"") | G48: =IF(ABS(((INDEX(HIST_D!$D$8:$D$2617,1)-INDEX(HIST_D!$D$8:$D$2617,Control!$F$8))*100))<25,"n/m",IFERROR((((INDEX(HIST_D!$DW$8:$DW$2617,1)-INDEX(HIST_D!$DW$8:$DW$2617,Control!$F$8))*100))/(((INDEX(HIST_D!$D$8:$D$2617,1)-INDEX(HIST_D!$D$8:$D$2617,Control!$F$8))*100)),"n/m")) | H48: =IF(ABS(((INDEX(HIST_D!$D$8:$D$2617,1)-INDEX(HIST_D!$D$8:$D$2617,Control!$F$9))*100))<25,"n/m",IFERROR((((INDEX(HIST_D!$DW$8:$DW$2617,1)-INDEX(HIST_D!$DW$8:$DW$2617,Control!$F$9))*100))/(((INDEX(HIST_D!$D$8:$D$2617,1)-INDEX(HIST_D!$D$8:$D$2617,Control!$F$9))*100)),"n/m")) | I48: =IF(ABS(((INDEX(HIST_D!$D$8:$D$2617,1)-INDEX(HIST_D!$D$8:$D$2617,Control!$F$10))*100))<25,"n/m",IFERROR((((INDEX(HIST_D!$DW$8:$DW$2617,1)-INDEX(HIST_D!$DW$8:$DW$2617,Control!$F$10))*100))/(((INDEX(HIST_D!$D$8:$D$2617,1)-INDEX(HIST_D!$D$8:$D$2617,Control!$F$10))*100)),"n/m")) | J48: =IF(ABS(((INDEX(HIST_D!$D$8:$D$2617,1)-INDEX(HIST_D!$D$8:$D$2617,Control!$F$11))*100))<25,"n/m",IFERROR((((INDEX(HIST_D!$DW$8:$DW$2617,1)-INDEX(HIST_D!$DW$8:$DW$2617,Control!$F$11))*100))/(((INDEX(HIST_D!$D$8:$D$2617,1)-INDEX(HIST_D!$D$8:$D$2617,Control!$F$11))*100)),"n/m")) | K48: =IF(ABS(((INDEX(HIST_D!$D$8:$D$2617,1)-INDEX(HIST_D!$D$8:$D$2617,Control!$F$13))*100))<25,"n/m",IFERROR((((INDEX(HIST_D!$DW$8:$DW$2617,1)-INDEX(HIST_D!$DW$8:$DW$2617,Control!$F$13))*100))/(((INDEX(HIST_D!$D$8:$D$2617,1)-INDEX(HIST_D!$D$8:$D$2617,Control!$F$13))*100)),"n/m")) | M48: =INDEX(HIST_D!$EA$8:$EA$2617,1) | N48: =IFERROR(PERCENTRANK(HIST_D!$EA$8:INDEX(HIST_D!$EA$8:$EA$2617,Control!$F$14),INDEX(HIST_D!$EA$8:$EA$2617,1)),"")
A49: Averaging country ratios is not the same as the ratio of the averages. Both are shown; the row above is the one the Dashboard reads.
A51: FX DEFENCE CHECK — did the front end have to be tightened to hold the currency?
A52: A currency can weaken without a policy response. What signals real funding stress is the front end repricing by MORE than the US front end while the currency is still losing ground. That combination, not the FX move on its own, is the thing to look for.
A53: Market | B53: FX 1M | C53: Local 2Y d 1M (bp) | D53: UST 2Y d 1M (bp) | E53: Local less US (bp) | F53: FX 3M | G53: Local 2Y d 3M (bp) | H53: UST 2Y d 3M (bp) | I53: Local less US (bp) | J53: Region | K53: Verdict (1M)
A54: Brazil 2Y | B54: =IFERROR(INDEX(HIST_D!$AA$8:$AA$2617,Control!$F$8)/INDEX(HIST_D!$AA$8:$AA$2617,1)-1,"") | C54: =IFERROR((INDEX(HIST_D!$CU$8:$CU$2617,1)-INDEX(HIST_D!$CU$8:$CU$2617,Control!$F$8))*100,"") | D54: =IFERROR((INDEX(HIST_D!$B$8:$B$2617,1)-INDEX(HIST_D!$B$8:$B$2617,Control!$F$8))*100,"") | E54: =IFERROR(C54-D54,"") | F54: =IFERROR(INDEX(HIST_D!$AA$8:$AA$2617,Control!$F$9)/INDEX(HIST_D!$AA$8:$AA$2617,1)-1,"") | G54: =IFERROR((INDEX(HIST_D!$CU$8:$CU$2617,1)-INDEX(HIST_D!$CU$8:$CU$2617,Control!$F$9))*100,"") | H54: =IFERROR((INDEX(HIST_D!$B$8:$B$2617,1)-INDEX(HIST_D!$B$8:$B$2617,Control!$F$9))*100,"") | I54: =IFERROR(G54-H54,"") | J54: LatAm | K54: =IF(AND($B54<-0.01,$E54>15),"defending the currency",IF(AND($B54<-0.01,$E54<=15),"weaker FX, no policy response",IF($E54>15,"tightening without FX pressure","no pressure")))
A55: Mexico 2Y | B55: =IFERROR(INDEX(HIST_D!$AB$8:$AB$2617,Control!$F$8)/INDEX(HIST_D!$AB$8:$AB$2617,1)-1,"") | C55: =IFERROR((INDEX(HIST_D!$CV$8:$CV$2617,1)-INDEX(HIST_D!$CV$8:$CV$2617,Control!$F$8))*100,"") | D55: =IFERROR((INDEX(HIST_D!$B$8:$B$2617,1)-INDEX(HIST_D!$B$8:$B$2617,Control!$F$8))*100,"") | E55: =IFERROR(C55-D55,"") | F55: =IFERROR(INDEX(HIST_D!$AB$8:$AB$2617,Control!$F$9)/INDEX(HIST_D!$AB$8:$AB$2617,1)-1,"") | G55: =IFERROR((INDEX(HIST_D!$CV$8:$CV$2617,1)-INDEX(HIST_D!$CV$8:$CV$2617,Control!$F$9))*100,"") | H55: =IFERROR((INDEX(HIST_D!$B$8:$B$2617,1)-INDEX(HIST_D!$B$8:$B$2617,Control!$F$9))*100,"") | I55: =IFERROR(G55-H55,"") | J55: LatAm | K55: =IF(AND($B55<-0.01,$E55>15),"defending the currency",IF(AND($B55<-0.01,$E55<=15),"weaker FX, no policy response",IF($E55>15,"tightening without FX pressure","no pressure")))
A56: Colombia 2Y | B56: =IFERROR(INDEX(HIST_D!$AD$8:$AD$2617,Control!$F$8)/INDEX(HIST_D!$AD$8:$AD$2617,1)-1,"") | C56: =IFERROR((INDEX(HIST_D!$CW$8:$CW$2617,1)-INDEX(HIST_D!$CW$8:$CW$2617,Control!$F$8))*100,"") | D56: =IFERROR((INDEX(HIST_D!$B$8:$B$2617,1)-INDEX(HIST_D!$B$8:$B$2617,Control!$F$8))*100,"") | E56: =IFERROR(C56-D56,"") | F56: =IFERROR(INDEX(HIST_D!$AD$8:$AD$2617,Control!$F$9)/INDEX(HIST_D!$AD$8:$AD$2617,1)-1,"") | G56: =IFERROR((INDEX(HIST_D!$CW$8:$CW$2617,1)-INDEX(HIST_D!$CW$8:$CW$2617,Control!$F$9))*100,"") | H56: =IFERROR((INDEX(HIST_D!$B$8:$B$2617,1)-INDEX(HIST_D!$B$8:$B$2617,Control!$F$9))*100,"") | I56: =IFERROR(G56-H56,"") | J56: LatAm | K56: =IF(AND($B56<-0.01,$E56>15),"defending the currency",IF(AND($B56<-0.01,$E56<=15),"weaker FX, no policy response",IF($E56>15,"tightening without FX pressure","no pressure")))
A57: Poland 2Y | B57: =IFERROR(INDEX(HIST_D!$AG$8:$AG$2617,Control!$F$8)/INDEX(HIST_D!$AG$8:$AG$2617,1)-1,"") | C57: =IFERROR((INDEX(HIST_D!$CX$8:$CX$2617,1)-INDEX(HIST_D!$CX$8:$CX$2617,Control!$F$8))*100,"") | D57: =IFERROR((INDEX(HIST_D!$B$8:$B$2617,1)-INDEX(HIST_D!$B$8:$B$2617,Control!$F$8))*100,"") | E57: =IFERROR(C57-D57,"") | F57: =IFERROR(INDEX(HIST_D!$AG$8:$AG$2617,Control!$F$9)/INDEX(HIST_D!$AG$8:$AG$2617,1)-1,"") | G57: =IFERROR((INDEX(HIST_D!$CX$8:$CX$2617,1)-INDEX(HIST_D!$CX$8:$CX$2617,Control!$F$9))*100,"") | H57: =IFERROR((INDEX(HIST_D!$B$8:$B$2617,1)-INDEX(HIST_D!$B$8:$B$2617,Control!$F$9))*100,"") | I57: =IFERROR(G57-H57,"") | J57: EM Europe | K57: =IF(AND($B57<-0.01,$E57>15),"defending the currency",IF(AND($B57<-0.01,$E57<=15),"weaker FX, no policy response",IF($E57>15,"tightening without FX pressure","no pressure")))
A58: Hungary 2Y | B58: =IFERROR(INDEX(HIST_D!$AH$8:$AH$2617,Control!$F$8)/INDEX(HIST_D!$AH$8:$AH$2617,1)-1,"") | C58: =IFERROR((INDEX(HIST_D!$CY$8:$CY$2617,1)-INDEX(HIST_D!$CY$8:$CY$2617,Control!$F$8))*100,"") | D58: =IFERROR((INDEX(HIST_D!$B$8:$B$2617,1)-INDEX(HIST_D!$B$8:$B$2617,Control!$F$8))*100,"") | E58: =IFERROR(C58-D58,"") | F58: =IFERROR(INDEX(HIST_D!$AH$8:$AH$2617,Control!$F$9)/INDEX(HIST_D!$AH$8:$AH$2617,1)-1,"") | G58: =IFERROR((INDEX(HIST_D!$CY$8:$CY$2617,1)-INDEX(HIST_D!$CY$8:$CY$2617,Control!$F$9))*100,"") | H58: =IFERROR((INDEX(HIST_D!$B$8:$B$2617,1)-INDEX(HIST_D!$B$8:$B$2617,Control!$F$9))*100,"") | I58: =IFERROR(G58-H58,"") | J58: EM Europe | K58: =IF(AND($B58<-0.01,$E58>15),"defending the currency",IF(AND($B58<-0.01,$E58<=15),"weaker FX, no policy response",IF($E58>15,"tightening without FX pressure","no pressure")))
A59: Turkiye 2Y | B59: =IFERROR(INDEX(HIST_D!$AK$8:$AK$2617,Control!$F$8)/INDEX(HIST_D!$AK$8:$AK$2617,1)-1,"") | C59: =IFERROR((INDEX(HIST_D!$CZ$8:$CZ$2617,1)-INDEX(HIST_D!$CZ$8:$CZ$2617,Control!$F$8))*100,"") | D59: =IFERROR((INDEX(HIST_D!$B$8:$B$2617,1)-INDEX(HIST_D!$B$8:$B$2617,Control!$F$8))*100,"") | E59: =IFERROR(C59-D59,"") | F59: =IFERROR(INDEX(HIST_D!$AK$8:$AK$2617,Control!$F$9)/INDEX(HIST_D!$AK$8:$AK$2617,1)-1,"") | G59: =IFERROR((INDEX(HIST_D!$CZ$8:$CZ$2617,1)-INDEX(HIST_D!$CZ$8:$CZ$2617,Control!$F$9))*100,"") | H59: =IFERROR((INDEX(HIST_D!$B$8:$B$2617,1)-INDEX(HIST_D!$B$8:$B$2617,Control!$F$9))*100,"") | I59: =IFERROR(G59-H59,"") | J59: EM Europe | K59: =IF(AND($B59<-0.01,$E59>15),"defending the currency",IF(AND($B59<-0.01,$E59<=15),"weaker FX, no policy response",IF($E59>15,"tightening without FX pressure","no pressure")))
A60: Israel 2Y | B60: =IFERROR(INDEX(HIST_D!$AL$8:$AL$2617,Control!$F$8)/INDEX(HIST_D!$AL$8:$AL$2617,1)-1,"") | C60: =IFERROR((INDEX(HIST_D!$DA$8:$DA$2617,1)-INDEX(HIST_D!$DA$8:$DA$2617,Control!$F$8))*100,"") | D60: =IFERROR((INDEX(HIST_D!$B$8:$B$2617,1)-INDEX(HIST_D!$B$8:$B$2617,Control!$F$8))*100,"") | E60: =IFERROR(C60-D60,"") | F60: =IFERROR(INDEX(HIST_D!$AL$8:$AL$2617,Control!$F$9)/INDEX(HIST_D!$AL$8:$AL$2617,1)-1,"") | G60: =IFERROR((INDEX(HIST_D!$DA$8:$DA$2617,1)-INDEX(HIST_D!$DA$8:$DA$2617,Control!$F$9))*100,"") | H60: =IFERROR((INDEX(HIST_D!$B$8:$B$2617,1)-INDEX(HIST_D!$B$8:$B$2617,Control!$F$9))*100,"") | I60: =IFERROR(G60-H60,"") | J60: Middle East & Africa | K60: =IF(AND($B60<-0.01,$E60>15),"defending the currency",IF(AND($B60<-0.01,$E60<=15),"weaker FX, no policy response",IF($E60>15,"tightening without FX pressure","no pressure")))
A61: South Africa 2Y | B61: =IFERROR(INDEX(HIST_D!$AM$8:$AM$2617,Control!$F$8)/INDEX(HIST_D!$AM$8:$AM$2617,1)-1,"") | C61: =IFERROR((INDEX(HIST_D!$DB$8:$DB$2617,1)-INDEX(HIST_D!$DB$8:$DB$2617,Control!$F$8))*100,"") | D61: =IFERROR((INDEX(HIST_D!$B$8:$B$2617,1)-INDEX(HIST_D!$B$8:$B$2617,Control!$F$8))*100,"") | E61: =IFERROR(C61-D61,"") | F61: =IFERROR(INDEX(HIST_D!$AM$8:$AM$2617,Control!$F$9)/INDEX(HIST_D!$AM$8:$AM$2617,1)-1,"") | G61: =IFERROR((INDEX(HIST_D!$DB$8:$DB$2617,1)-INDEX(HIST_D!$DB$8:$DB$2617,Control!$F$9))*100,"") | H61: =IFERROR((INDEX(HIST_D!$B$8:$B$2617,1)-INDEX(HIST_D!$B$8:$B$2617,Control!$F$9))*100,"") | I61: =IFERROR(G61-H61,"") | J61: Middle East & Africa | K61: =IF(AND($B61<-0.01,$E61>15),"defending the currency",IF(AND($B61<-0.01,$E61<=15),"weaker FX, no policy response",IF($E61>15,"tightening without FX pressure","no pressure")))
A62: India 2Y | B62: =IFERROR(INDEX(HIST_D!$AS$8:$AS$2617,Control!$F$8)/INDEX(HIST_D!$AS$8:$AS$2617,1)-1,"") | C62: =IFERROR((INDEX(HIST_D!$DC$8:$DC$2617,1)-INDEX(HIST_D!$DC$8:$DC$2617,Control!$F$8))*100,"") | D62: =IFERROR((INDEX(HIST_D!$B$8:$B$2617,1)-INDEX(HIST_D!$B$8:$B$2617,Control!$F$8))*100,"") | E62: =IFERROR(C62-D62,"") | F62: =IFERROR(INDEX(HIST_D!$AS$8:$AS$2617,Control!$F$9)/INDEX(HIST_D!$AS$8:$AS$2617,1)-1,"") | G62: =IFERROR((INDEX(HIST_D!$DC$8:$DC$2617,1)-INDEX(HIST_D!$DC$8:$DC$2617,Control!$F$9))*100,"") | H62: =IFERROR((INDEX(HIST_D!$B$8:$B$2617,1)-INDEX(HIST_D!$B$8:$B$2617,Control!$F$9))*100,"") | I62: =IFERROR(G62-H62,"") | J62: Asia | K62: =IF(AND($B62<-0.01,$E62>15),"defending the currency",IF(AND($B62<-0.01,$E62<=15),"weaker FX, no policy response",IF($E62>15,"tightening without FX pressure","no pressure")))
A63: Indonesia 2Y | B63: =IFERROR(INDEX(HIST_D!$AT$8:$AT$2617,Control!$F$8)/INDEX(HIST_D!$AT$8:$AT$2617,1)-1,"") | C63: =IFERROR((INDEX(HIST_D!$DD$8:$DD$2617,1)-INDEX(HIST_D!$DD$8:$DD$2617,Control!$F$8))*100,"") | D63: =IFERROR((INDEX(HIST_D!$B$8:$B$2617,1)-INDEX(HIST_D!$B$8:$B$2617,Control!$F$8))*100,"") | E63: =IFERROR(C63-D63,"") | F63: =IFERROR(INDEX(HIST_D!$AT$8:$AT$2617,Control!$F$9)/INDEX(HIST_D!$AT$8:$AT$2617,1)-1,"") | G63: =IFERROR((INDEX(HIST_D!$DD$8:$DD$2617,1)-INDEX(HIST_D!$DD$8:$DD$2617,Control!$F$9))*100,"") | H63: =IFERROR((INDEX(HIST_D!$B$8:$B$2617,1)-INDEX(HIST_D!$B$8:$B$2617,Control!$F$9))*100,"") | I63: =IFERROR(G63-H63,"") | J63: Asia | K63: =IF(AND($B63<-0.01,$E63>15),"defending the currency",IF(AND($B63<-0.01,$E63<=15),"weaker FX, no policy response",IF($E63>15,"tightening without FX pressure","no pressure")))
A64: Korea 2Y | B64: =IFERROR(INDEX(HIST_D!$AU$8:$AU$2617,Control!$F$8)/INDEX(HIST_D!$AU$8:$AU$2617,1)-1,"") | C64: =IFERROR((INDEX(HIST_D!$DE$8:$DE$2617,1)-INDEX(HIST_D!$DE$8:$DE$2617,Control!$F$8))*100,"") | D64: =IFERROR((INDEX(HIST_D!$B$8:$B$2617,1)-INDEX(HIST_D!$B$8:$B$2617,Control!$F$8))*100,"") | E64: =IFERROR(C64-D64,"") | F64: =IFERROR(INDEX(HIST_D!$AU$8:$AU$2617,Control!$F$9)/INDEX(HIST_D!$AU$8:$AU$2617,1)-1,"") | G64: =IFERROR((INDEX(HIST_D!$DE$8:$DE$2617,1)-INDEX(HIST_D!$DE$8:$DE$2617,Control!$F$9))*100,"") | H64: =IFERROR((INDEX(HIST_D!$B$8:$B$2617,1)-INDEX(HIST_D!$B$8:$B$2617,Control!$F$9))*100,"") | I64: =IFERROR(G64-H64,"") | J64: Asia | K64: =IF(AND($B64<-0.01,$E64>15),"defending the currency",IF(AND($B64<-0.01,$E64<=15),"weaker FX, no policy response",IF($E64>15,"tightening without FX pressure","no pressure")))
A65: Thailand 2Y | B65: =IFERROR(INDEX(HIST_D!$AW$8:$AW$2617,Control!$F$8)/INDEX(HIST_D!$AW$8:$AW$2617,1)-1,"") | C65: =IFERROR((INDEX(HIST_D!$DF$8:$DF$2617,1)-INDEX(HIST_D!$DF$8:$DF$2617,Control!$F$8))*100,"") | D65: =IFERROR((INDEX(HIST_D!$B$8:$B$2617,1)-INDEX(HIST_D!$B$8:$B$2617,Control!$F$8))*100,"") | E65: =IFERROR(C65-D65,"") | F65: =IFERROR(INDEX(HIST_D!$AW$8:$AW$2617,Control!$F$9)/INDEX(HIST_D!$AW$8:$AW$2617,1)-1,"") | G65: =IFERROR((INDEX(HIST_D!$DF$8:$DF$2617,1)-INDEX(HIST_D!$DF$8:$DF$2617,Control!$F$9))*100,"") | H65: =IFERROR((INDEX(HIST_D!$B$8:$B$2617,1)-INDEX(HIST_D!$B$8:$B$2617,Control!$F$9))*100,"") | I65: =IFERROR(G65-H65,"") | J65: Asia | K65: =IF(AND($B65<-0.01,$E65>15),"defending the currency",IF(AND($B65<-0.01,$E65<=15),"weaker FX, no policy response",IF($E65>15,"tightening without FX pressure","no pressure")))
A67: POLICY SPACE — real policy rates. Blue cells are yours to fill from the primary release.
A68: Left blank on purpose rather than filled with a modelled proxy. Each row names the exact release the number comes from. Real rate = policy rate less core inflation, ex post.
A69: Country | B69: Region | C69: Policy rate (%) | D69: Core CPI y/y (%) | E69: Real policy rate (%) | F69: less US real (pp) | G69: Policy rate source | H69: Core CPI source
A70: Brazil | B70: LatAm | E70: =IF(OR($C70="",$D70=""),"",$C70-$D70) | F70: =IF(OR($E70="",$E$89=""),"",$E70-$E$89) | G70: BCB Selic target (COPOM release) | H70: IBGE IPCA core EX3, y/y
A71: Mexico | B71: LatAm | E71: =IF(OR($C71="",$D71=""),"",$C71-$D71) | F71: =IF(OR($E71="",$E$89=""),"",$E71-$E$89) | G71: Banxico tasa objetivo (Anuncio de politica) | H71: INEGI INPC subyacente, y/y
A72: Chile | B72: LatAm | E72: =IF(OR($C72="",$D72=""),"",$C72-$D72) | F72: =IF(OR($E72="",$E$89=""),"",$E72-$E$89) | G72: BCCh TPM (Reunion de Politica Monetaria) | H72: INE IPC sin volatiles, y/y
A73: Colombia | B73: LatAm | E73: =IF(OR($C73="",$D73=""),"",$C73-$D73) | F73: =IF(OR($E73="",$E$89=""),"",$E73-$E$89) | G73: BanRep tasa de intervencion | H73: DANE IPC sin alimentos, y/y
A74: Peru | B74: LatAm | E74: =IF(OR($C74="",$D74=""),"",$C74-$D74) | F74: =IF(OR($E74="",$E$89=""),"",$E74-$E$89) | G74: BCRP tasa de referencia | H74: INEI IPC subyacente Lima, y/y
A75: Poland | B75: EM Europe | E75: =IF(OR($C75="",$D75=""),"",$C75-$D75) | F75: =IF(OR($E75="",$E$89=""),"",$E75-$E$89) | G75: NBP reference rate | H75: GUS core ex food/energy, y/y
A76: Hungary | B76: EM Europe | E76: =IF(OR($C76="",$D76=""),"",$C76-$D76) | F76: =IF(OR($E76="",$E$89=""),"",$E76-$E$89) | G76: MNB base rate | H76: KSH core, y/y
A77: Czechia | B77: EM Europe | E77: =IF(OR($C77="",$D77=""),"",$C77-$D77) | F77: =IF(OR($E77="",$E$89=""),"",$E77-$E$89) | G77: CNB two-week repo | H77: CZSO core, y/y
A78: Romania | B78: EM Europe | E78: =IF(OR($C78="",$D78=""),"",$C78-$D78) | F78: =IF(OR($E78="",$E$89=""),"",$E78-$E$89) | G78: BNR policy rate | H78: INS core2 adjusted, y/y
A79: Turkiye | B79: EM Europe | E79: =IF(OR($C79="",$D79=""),"",$C79-$D79) | F79: =IF(OR($E79="",$E$89=""),"",$E79-$E$89) | G79: CBRT 1-week repo | H79: TurkStat CPI-C, y/y
A80: Israel | B80: Middle East & Africa | E80: =IF(OR($C80="",$D80=""),"",$C80-$D80) | F80: =IF(OR($E80="",$E$89=""),"",$E80-$E$89) | G80: BoI rate (Monetary Committee decision) | H80: CBS core CPI, y/y
A81: South Africa | B81: Middle East & Africa | E81: =IF(OR($C81="",$D81=""),"",$C81-$D81) | F81: =IF(OR($E81="",$E$89=""),"",$E81-$E$89) | G81: SARB repo rate (MPC statement) | H81: StatsSA CPI core, y/y
... A89: United States | B89: — | E89: =IF(OR($C89="",$D89=""),"",$C89-$D89) | F89: =IF(OR($E89="",$E$89=""),"",$E89-$E$89) | G89: FOMC target midpoint | H89: BLS CPI ex food & energy, y/y
A91: COMMENT — LOCAL RATES AND POLICY
