Workbook

Sheet Control
A1: EM DECOMPOSITION — US factor vs intrinsic EM (rates, FX, equities, USD credit)
A2: Bloomberg-linked; every cell is a formula. Built for A. Rojas, UBS CIO Americas.
A4: SETTINGS
A6: History start | B6: =EDATE(TODAY(),-38) | D6: 3y buffer so the 2y beta window is always full
A7: History end | B7: =TODAY()
A8: Daily observations pulled | B8: 784 | D8: HIST_D rows 8:791, newest first
A9: bp per 1% | B9: 100
A10: 1M window (weekday obs back) | B10: 23 | D10: row offset in HIST_D; 23 = one calendar month
A11: YTD window (weekday obs back) | B11: =NETWORKDAYS(DATE(YEAR(TODAY())-1,12,31),TODAY()) | D11: row offset to the prior year-end
A12: Beta window (weekday obs) | B12: 523 | D12: 2y of daily changes for every measured beta
A13: Minimum US move to form a ratio (bp) | B13: 15 | D13: pass-through is suppressed as n/m below this
A14: EM USD index modified duration (yrs) | B14: 6.6 | D14: INPUT — embi_tracker.py or Bbg DUR_ADJ_MID
A15: EM USD index YTW (%) | B15: 6.55 | D15: INPUT — embi_tracker.py or INDEX_YIELD_TO_WORST
A16: EMBIGD stripped spread now (bp) | B16: 208 | D16: INPUT — embi_tracker.py 'Dur Wgt STW (Trsy)'
A17: EMBIGD stripped spread 1M ago (bp) | B17: 218 | D17: INPUT — chain-link across the 04-Sep-26 JPM break
A18: EMBIGD stripped spread at prior year-end (bp) | D18: INPUT — from EMBI_global_history.xlsx
A21: THE ONE IDEA, APPLIED THREE TIMES
A22: total move = US-driven + intrinsic EM. Same split on every tab.
A23: Local rates: d(local 10Y) = d(UST 10Y) + d(local less UST). US-driven is the UST move; intrinsic is the change in the gap.
A24: FX: return on the EM currency = -(DXY return) + return ex-dollar. US-driven is the dollar; intrinsic is what is left after the dollar.
A25: Equities: USD return on the MSCI country index = MSCI World return + relative return. US/DM-driven is World under a beta of one; intrinsic is relative performance.
A26: USD credit: d(UST 5Y + CDS 5Y) = d(UST 5Y) + d(CDS 5Y). US-driven is Treasuries; intrinsic is the spread. This is exact.
A27: The identity assumes a beta of one. Next to it, a measured 2y beta gives the move history would have predicted, and surprise = actual less predicted.
A28: Pass-through (rates, FX) = total / US-driven: how much of the US move the market took. Under 1 = absorbed. US share (credit) = Treasuries / total yield move.
A29: Region averages are equal-weighted over the flagged members only. Ratios on average rows are ratios of the averages, not averages of the ratios.
A30: Turkiye is out of the rates and FX averages; Egypt out of FX; India has no CDS; the GCC has no local curve or floating currency. Each is shown, and each exclusion is written on the row.
A31: South Africa is not in any of the four regions you named. It is a memo line in no average.
A32: Blue = input. Green = link. Purple = Bloomberg pull. Black = computed here.

Sheet Summary
A1: EM DECOMPOSITION — SUMMARY
A2: ="As of "&TEXT(INDEX(HIST_D!$A$8:$A$791,1),"d mmm yyyy")&". Every cell here is a link to the asset tabs."
A4: THE US MOVE — what EM was asked to absorb
A5: Series | B5: Level | C5: d 1M | D5: d YTD
A6: UST 2Y | B6: =INDEX(HIST_D!$D$8:$D$791,1) | C6: =IFERROR((INDEX(HIST_D!$D$8:$D$791,1)-INDEX(HIST_D!$D$8:$D$791,Control!$B$10))*100,"") | D6: =IFERROR((INDEX(HIST_D!$D$8:$D$791,1)-INDEX(HIST_D!$D$8:$D$791,Control!$B$11))*100,"")
A7: UST 5Y | B7: =INDEX(HIST_D!$E$8:$E$791,1) | C7: =IFERROR((INDEX(HIST_D!$E$8:$E$791,1)-INDEX(HIST_D!$E$8:$E$791,Control!$B$10))*100,"") | D7: =IFERROR((INDEX(HIST_D!$E$8:$E$791,1)-INDEX(HIST_D!$E$8:$E$791,Control!$B$11))*100,"")
A8: UST 10Y | B8: =INDEX(HIST_D!$F$8:$F$791,1) | C8: =IFERROR((INDEX(HIST_D!$F$8:$F$791,1)-INDEX(HIST_D!$F$8:$F$791,Control!$B$10))*100,"") | D8: =IFERROR((INDEX(HIST_D!$F$8:$F$791,1)-INDEX(HIST_D!$F$8:$F$791,Control!$B$11))*100,"")
A9: UST 30Y | B9: =INDEX(HIST_D!$G$8:$G$791,1) | C9: =IFERROR((INDEX(HIST_D!$G$8:$G$791,1)-INDEX(HIST_D!$G$8:$G$791,Control!$B$10))*100,"") | D9: =IFERROR((INDEX(HIST_D!$G$8:$G$791,1)-INDEX(HIST_D!$G$8:$G$791,Control!$B$11))*100,"")
A10: UST 10Y real | B10: =INDEX(HIST_D!$H$8:$H$791,1) | C10: =IFERROR((INDEX(HIST_D!$H$8:$H$791,1)-INDEX(HIST_D!$H$8:$H$791,Control!$B$10))*100,"") | D10: =IFERROR((INDEX(HIST_D!$H$8:$H$791,1)-INDEX(HIST_D!$H$8:$H$791,Control!$B$11))*100,"")
A11: Breakeven 10Y | B11: =INDEX(HIST_D!$I$8:$I$791,1) | C11: =IFERROR((INDEX(HIST_D!$I$8:$I$791,1)-INDEX(HIST_D!$I$8:$I$791,Control!$B$10))*100,"") | D11: =IFERROR((INDEX(HIST_D!$I$8:$I$791,1)-INDEX(HIST_D!$I$8:$I$791,Control!$B$11))*100,"")
A12: ACM term premium 10Y | B12: =INDEX(HIST_D!$J$8:$J$791,1) | C12: =IFERROR((INDEX(HIST_D!$J$8:$J$791,1)-INDEX(HIST_D!$J$8:$J$791,Control!$B$10))*100,"") | D12: =IFERROR((INDEX(HIST_D!$J$8:$J$791,1)-INDEX(HIST_D!$J$8:$J$791,Control!$B$11))*100,"")
A13: DXY | B13: =INDEX(HIST_D!$K$8:$K$791,1) | C13: =IFERROR(INDEX(HIST_D!$K$8:$K$791,1)/INDEX(HIST_D!$K$8:$K$791,Control!$B$10)-1,"") | D13: =IFERROR(INDEX(HIST_D!$K$8:$K$791,1)/INDEX(HIST_D!$K$8:$K$791,Control!$B$11)-1,"")
A14: MSCI World (USD) | B14: =INDEX(HIST_D!$B$8:$B$791,1) | C14: =IFERROR(INDEX(HIST_D!$B$8:$B$791,1)/INDEX(HIST_D!$B$8:$B$791,Control!$B$10)-1,"") | D14: =IFERROR(INDEX(HIST_D!$B$8:$B$791,1)/INDEX(HIST_D!$B$8:$B$791,Control!$B$11)-1,"")
A15: MSCI EM (USD) | B15: =INDEX(HIST_D!$C$8:$C$791,1) | C15: =IFERROR(INDEX(HIST_D!$C$8:$C$791,1)/INDEX(HIST_D!$C$8:$C$791,Control!$B$10)-1,"") | D15: =IFERROR(INDEX(HIST_D!$C$8:$C$791,1)/INDEX(HIST_D!$C$8:$C$791,Control!$B$11)-1,"")
A16: EM USD Aggregate OAS (Bbg) | B16: =INDEX(HIST_D!$L$8:$L$791,1) | C16: =IFERROR(INDEX(HIST_D!$L$8:$L$791,1)-INDEX(HIST_D!$L$8:$L$791,Control!$B$10),"") | D16: =IFERROR(INDEX(HIST_D!$L$8:$L$791,1)-INDEX(HIST_D!$L$8:$L$791,Control!$B$11),"")
A18: PAST MONTH — total = US-driven + intrinsic, by region
A19: Region | B19: Rates: total (bp) | C19: Rates: US (bp) | D19: Rates: intrinsic (bp) | E19: Rates: pass-through | F19: FX: total | G19: FX: US | H19: FX: intrinsic | I19: FX: pass-through | J19: Equities: total (USD) | K19: Equities: World | L19: Equities: relative | M19: Equities: pass-through | N19: Credit: total (bp) | O19: Credit: US (bp) | P19: Credit: spread (bp) | Q19: Credit: US share
A20: LatAm | B20: =Rates!$E$11 | C20: =Rates!$F$11 | D20: =Rates!$G$11 | E20: =Rates!$H$11 | F20: =FX!$E$11 | G20: =FX!$F$11 | H20: =FX!$G$11 | I20: =FX!$H$11 | J20: =Equities!$E$11 | K20: =Equities!$F$11 | L20: =Equities!$G$11 | M20: =Equities!$H$11 | N20: =Credit!$E$11 | O20: =Credit!$F$11 | P20: =Credit!$G$11 | Q20: =Credit!$H$11
A21: EM Europe | B21: =Rates!$E$21 | C21: =Rates!$F$21 | D21: =Rates!$G$21 | E21: =Rates!$H$21 | F21: =FX!$E$21 | G21: =FX!$F$21 | H21: =FX!$G$21 | I21: =FX!$H$21 | J21: =Equities!$E$21 | K21: =Equities!$F$21 | L21: =Equities!$G$21 | M21: =Equities!$H$21 | N21: =Credit!$E$21 | O21: =Credit!$F$21 | P21: =Credit!$G$21 | Q21: =Credit!$H$21
A22: Middle East | B22: =Rates!$E$28 | C22: =Rates!$F$28 | D22: =Rates!$G$28 | E22: =Rates!$H$28 | F22: =FX!$E$28 | G22: =FX!$F$28 | H22: =FX!$G$28 | I22: =FX!$H$28 | J22: =Equities!$E$31 | K22: =Equities!$F$31 | L22: =Equities!$G$31 | M22: =Equities!$H$31 | N22: =Credit!$E$31 | O22: =Credit!$F$31 | P22: =Credit!$G$31 | Q22: =Credit!$H$31
A23: EM Asia | B23: =Rates!$E$40 | C23: =Rates!$F$40 | D23: =Rates!$G$40 | E23: =Rates!$H$40 | F23: =FX!$E$40 | G23: =FX!$F$40 | H23: =FX!$G$40 | I23: =FX!$H$40 | J23: =Equities!$E$43 | K23: =Equities!$F$43 | L23: =Equities!$G$43 | M23: =Equities!$H$43 | N23: =Credit!$E$42 | O23: =Credit!$F$42 | P23: =Credit!$G$42 | Q23: =Credit!$H$42
A24: EM average | B24: =Rates!$E$45 | C24: =Rates!$F$45 | D24: =Rates!$G$45 | E24: =Rates!$H$45 | F24: =FX!$E$45 | G24: =FX!$F$45 | H24: =FX!$G$45 | I24: =FX!$H$45 | J24: =Equities!$E$48 | K24: =Equities!$F$48 | L24: =Equities!$G$48 | M24: =Equities!$H$48 | N24: =Credit!$E$47 | O24: =Credit!$F$47 | P24: =Credit!$G$47 | Q24: =Credit!$H$47
A25: South Africa (memo) | B25: =Rates!$E$46 | C25: =Rates!$F$46 | D25: =Rates!$G$46 | E25: =Rates!$H$46 | F25: =FX!$E$46 | G25: =FX!$F$46 | H25: =FX!$G$46 | I25: =FX!$H$46 | J25: =Equities!$E$49 | K25: =Equities!$F$49 | L25: =Equities!$G$49 | M25: =Equities!$H$49 | N25: =Credit!$E$48 | O25: =Credit!$F$48 | P25: =Credit!$G$48 | Q25: =Credit!$H$48
A27: YEAR TO DATE — total = US-driven + intrinsic, by region
A28: Region | B28: Rates: total (bp) | C28: Rates: US (bp) | D28: Rates: intrinsic (bp) | E28: Rates: pass-through | F28: FX: total | G28: FX: US | H28: FX: intrinsic | I28: FX: pass-through | J28: Equities: total (USD) | K28: Equities: World | L28: Equities: relative | M28: Equities: pass-through | N28: Credit: total (bp) | O28: Credit: US (bp) | P28: Credit: spread (bp) | Q28: Credit: US share
A29: LatAm | B29: =Rates!$L$11 | C29: =Rates!$M$11 | D29: =Rates!$N$11 | E29: =Rates!$O$11 | F29: =FX!$L$11 | G29: =FX!$M$11 | H29: =FX!$N$11 | I29: =FX!$O$11 | J29: =Equities!$L$11 | K29: =Equities!$M$11 | L29: =Equities!$N$11 | M29: =Equities!$O$11 | N29: =Credit!$L$11 | O29: =Credit!$M$11 | P29: =Credit!$N$11 | Q29: =Credit!$O$11
A30: EM Europe | B30: =Rates!$L$21 | C30: =Rates!$M$21 | D30: =Rates!$N$21 | E30: =Rates!$O$21 | F30: =FX!$L$21 | G30: =FX!$M$21 | H30: =FX!$N$21 | I30: =FX!$O$21 | J30: =Equities!$L$21 | K30: =Equities!$M$21 | L30: =Equities!$N$21 | M30: =Equities!$O$21 | N30: =Credit!$L$21 | O30: =Credit!$M$21 | P30: =Credit!$N$21 | Q30: =Credit!$O$21
A31: Middle East | B31: =Rates!$L$28 | C31: =Rates!$M$28 | D31: =Rates!$N$28 | E31: =Rates!$O$28 | F31: =FX!$L$28 | G31: =FX!$M$28 | H31: =FX!$N$28 | I31: =FX!$O$28 | J31: =Equities!$L$31 | K31: =Equities!$M$31 | L31: =Equities!$N$31 | M31: =Equities!$O$31 | N31: =Credit!$L$31 | O31: =Credit!$M$31 | P31: =Credit!$N$31 | Q31: =Credit!$O$31
A32: EM Asia | B32: =Rates!$L$40 | C32: =Rates!$M$40 | D32: =Rates!$N$40 | E32: =Rates!$O$40 | F32: =FX!$L$40 | G32: =FX!$M$40 | H32: =FX!$N$40 | I32: =FX!$O$40 | J32: =Equities!$L$43 | K32: =Equities!$M$43 | L32: =Equities!$N$43 | M32: =Equities!$O$43 | N32: =Credit!$L$42 | O32: =Credit!$M$42 | P32: =Credit!$N$42 | Q32: =Credit!$O$42
A33: EM average | B33: =Rates!$L$45 | C33: =Rates!$M$45 | D33: =Rates!$N$45 | E33: =Rates!$O$45 | F33: =FX!$L$45 | G33: =FX!$M$45 | H33: =FX!$N$45 | I33: =FX!$O$45 | J33: =Equities!$L$48 | K33: =Equities!$M$48 | L33: =Equities!$N$48 | M33: =Equities!$O$48 | N33: =Credit!$L$47 | O33: =Credit!$M$47 | P33: =Credit!$N$47 | Q33: =Credit!$O$47
A34: South Africa (memo) | B34: =Rates!$L$46 | C34: =Rates!$M$46 | D34: =Rates!$N$46 | E34: =Rates!$O$46 | F34: =FX!$L$46 | G34: =FX!$M$46 | H34: =FX!$N$46 | I34: =FX!$O$46 | J34: =Equities!$L$49 | K34: =Equities!$M$49 | L34: =Equities!$N$49 | M34: =Equities!$O$49 | N34: =Credit!$L$48 | O34: =Credit!$M$48 | P34: =Credit!$N$48 | Q34: =Credit!$O$48
A36: WHERE THE US MOVE LANDED — pass-through by asset class and region (1M | YTD)
A37: Region | B37: Rates 1M | C37: FX 1M | D37: Equities 1M | E37: Credit US share 1M | G37: Rates YTD | H37: FX YTD | I37: Equities YTD | J37: Credit US share YTD
A38: LatAm | B38: =$E$20 | C38: =$I$20 | D38: =$M$20 | E38: =$Q$20 | G38: =$E$29 | H38: =$I$29 | I38: =$M$29 | J38: =$Q$29
A39: EM Europe | B39: =$E$21 | C39: =$I$21 | D39: =$M$21 | E39: =$Q$21 | G39: =$E$30 | H39: =$I$30 | I39: =$M$30 | J39: =$Q$30
A40: Middle East | B40: =$E$22 | C40: =$I$22 | D40: =$M$22 | E40: =$Q$22 | G40: =$E$31 | H40: =$I$31 | I40: =$M$31 | J40: =$Q$31
A41: EM Asia | B41: =$E$23 | C41: =$I$23 | D41: =$M$23 | E41: =$Q$23 | G41: =$E$32 | H41: =$I$32 | I41: =$M$32 | J41: =$Q$32
A42: EM average | B42: =$E$24 | C42: =$I$24 | D42: =$M$24 | E42: =$Q$24 | G42: =$E$33 | H42: =$I$33 | I42: =$M$33 | J42: =$Q$33
A43: Read across a row: the asset class with the lower pass-through is the one that absorbed more. Read down a column: the region with the lower number absorbed more. Rates, FX and equities are pass-through (under 1 = absorbed; for equities, under 1 = lagged the global move). Credit is the share of the yield move that is Treasuries.
A45: EM USD CREDIT — the index return, leg by leg. Never netted.
A46: Component | B46: 1M | C46: YTD | D46: Note
A47: Carry (YTW x window / 262) | B47: =IFERROR(Control!$B$15/100*(Control!$B$10-1)/262,"") | C47: =IFERROR(Control!$B$15/100*(Control!$B$11-1)/262,"") | D47: YTW from Control
A48: Rates leg vs UST 10Y (-D x d UST) | B48: =IFERROR(-Control!$B$14*$C$8/10000,"") | C48: =IFERROR(-Control!$B$14*$D$8/10000,"") | D48: US factor
A49: Rates leg vs UST 5Y (-D x d UST) | B49: =IFERROR(-Control!$B$14*$C$7/10000,"") | C49: =IFERROR(-Control!$B$14*$D$7/10000,"") | D49: US factor, shorter reference
A50: Spread leg (-D x d EMBIGD stripped spread) | B50: =IFERROR(-Control!$B$14*(Control!$B$16-Control!$B$17)/10000,"") | C50: =IF(Control!$B$18="","",-Control!$B$14*(Control!$B$16-Control!$B$18)/10000) | D50: intrinsic EM; from embi_tracker.py inputs on Control
A51: Spread leg, Bbg EM USD Agg OAS instead | B51: =IFERROR(-Control!$B$14*(INDEX(HIST_D!$L$8:$L$791,1)-INDEX(HIST_D!$L$8:$L$791,Control!$B$10))/10000,"") | C51: =IFERROR(-Control!$B$14*(INDEX(HIST_D!$L$8:$L$791,1)-INDEX(HIST_D!$L$8:$L$791,Control!$B$11))/10000,"") | D51: cross-check on a live Bloomberg series
A52: Sum: carry + rates (10Y) + spread (EMBIGD) | B52: =IFERROR($B$47+$B$48+$B$50,"") | C52: =IF($C$50="","",$C$47+$C$48+$C$50)
A53: Realised: Bbg EM USD Aggregate TR | B53: =IFERROR(INDEX(HIST_D!$M$8:$M$791,1)/INDEX(HIST_D!$M$8:$M$791,Control!$B$10)-1,"") | C53: =IFERROR(INDEX(HIST_D!$M$8:$M$791,1)/INDEX(HIST_D!$M$8:$M$791,Control!$B$11)-1,"") | D53: from the TR index, not derived
A54: Residual (realised less sum) | B54: =IFERROR($B$53-$B$52,"") | C54: =IF($C$52="","",$C$53-$C$52) | D54: what the decomposition does not explain
A56: Read: if the rates leg is the bulk of a negative month and the spread leg is flat or positive, EM USD credit is being repriced for US duration, not for EM risk — and the carry keeps accruing underneath.
A58: CONCLUSION — generated from the cells above
A59: =IFERROR("US: over the past month UST 10Y "&TEXT($C$8,"+0;-0")&"bp, UST 5Y "&TEXT($C$7,"+0;-0")&"bp, DXY "&TEXT($C$13,"+0.0%;-0.0%")&". YTD: UST 10Y "&TEXT($D$8,"+0;-0")&"bp, DXY "&TEXT($D$13,"+0.0%;-0.0%")&".","")
A60: =IFERROR("EM local rates: the average local 10Y moved "&TEXT($B$24,"+0;-0")&"bp on the month, of which "&TEXT($C$24,"+0;-0")&"bp is the US move and "&TEXT($D$24,"+0;-0")&"bp is intrinsic"&IF(ISNUMBER($E$24),"; pass-through "&TEXT($E$24,"0.00")&"x","")&". YTD "&TEXT($B$33,"+0;-0")&"bp, intrinsic "&TEXT($D$33,"+0;-0")&"bp.","")
A61: =IFERROR("EM FX: the average currency returned "&TEXT($F$24,"+0.0%;-0.0%")&" on the month against a dollar-implied "&TEXT($G$24,"+0.0%;-0.0%")&", so "&TEXT($H$24,"+0.0%;-0.0%")&" is ex-dollar. YTD "&TEXT($F$33,"+0.0%;-0.0%")&", ex-dollar "&TEXT($H$33,"+0.0%;-0.0%")&".","")
A62: =IFERROR("EM equities: the equal-weighted MSCI country average returned "&TEXT($J$24,"+0.0%;-0.0%")&" in USD on the month against MSCI World "&TEXT($K$24,"+0.0%;-0.0%")&", so "&TEXT($L$24,"+0.0%;-0.0%")&" is relative. MSCI EM itself "&TEXT($C$15,"+0.0%;-0.0%")&" ("&TEXT($C$15-$C$14,"+0.0%;-0.0%")&" vs World). YTD: average "&TEXT($J$33,"+0.0%;-0.0%")&", relative "&TEXT($L$33,"+0.0%;-0.0%")&"; MSCI EM "&TEXT($D$15,"+0.0%;-0.0%")&" ("&TEXT($D$15-$D$14,"+0.0%;-0.0%")&" vs World).","")
A63: =IFERROR("EM USD credit: the 5y yield proxy moved "&TEXT($N$24,"+0;-0")&"bp on the month — "&TEXT($O$24,"+0;-0")&"bp Treasuries and "&TEXT($P$24,"+0;-0")&"bp spread"&IF(ISNUMBER($Q$24),", "&TEXT($Q$24,"0%")&" US","")&". YTD "&TEXT($N$33,"+0;-0")&"bp: "&TEXT($O$33,"+0;-0")&"bp Treasuries, "&TEXT($P$33,"+0;-0")&"bp spread. Index-level: rates leg "&TEXT($B$48,"+0.00%;-0.00%")&", spread leg "&TEXT($B$50,"+0.00%;-0.00%")&".","")
A64: =IFERROR("Verdict: "&IF(AND($P$24<=0,$D$24<=0,$H$24>=-0.005),"on every leg the intrinsic EM component is flat or favourable while the US component carries the move. The asset class has digested it.",IF(AND($P$24<=5,$D$24<=10),"the US component carries the move in rates and credit; FX is the leg to watch. Largely digested.","the intrinsic EM component is doing real work on at least one leg — this is not purely a US story, and the digestion claim needs qualifying by region.")),"")
A66: Per-region reads are on the bottom of each asset tab. Region-level 'which asset class took more' is the pass-through grid above.

Sheet Charts
A1: CHARTS — the decomposition, by region and EM average
A2: Units: rates and credit in bp, FX in percent (the Summary decimals are multiplied by 100 in the block). Each bar is the total move; the two segments are the US-driven part (grey) and the intrinsic EM part (blue). Segments with opposite signs sit on either side of zero, so a short bar with two long segments means EM offset the US. Data blocks on the left are links to Summary; the charts read the blocks.
A4: Local rates — past month (bp)
A5: Region | B5: US-driven | C5: Intrinsic EM | D5: Total
A6: LatAm | B6: =IF(ISNUMBER(Summary!$C$20),Summary!$C$20,0) | C6: =IF(ISNUMBER(Summary!$D$20),Summary!$D$20,0) | D6: =B6+C6
A7: EM Europe | B7: =IF(ISNUMBER(Summary!$C$21),Summary!$C$21,0) | C7: =IF(ISNUMBER(Summary!$D$21),Summary!$D$21,0) | D7: =B7+C7
A8: Middle East | B8: =IF(ISNUMBER(Summary!$C$22),Summary!$C$22,0) | C8: =IF(ISNUMBER(Summary!$D$22),Summary!$D$22,0) | D8: =B8+C8
A9: EM Asia | B9: =IF(ISNUMBER(Summary!$C$23),Summary!$C$23,0) | C9: =IF(ISNUMBER(Summary!$D$23),Summary!$D$23,0) | D9: =B9+C9
A10: EM average | B10: =IF(ISNUMBER(Summary!$C$24),Summary!$C$24,0) | C10: =IF(ISNUMBER(Summary!$D$24),Summary!$D$24,0) | D10: =B10+C10
A13: Local rates — year to date (bp)
A14: Region | B14: US-driven | C14: Intrinsic EM | D14: Total
A15: LatAm | B15: =IF(ISNUMBER(Summary!$C$29),Summary!$C$29,0) | C15: =IF(ISNUMBER(Summary!$D$29),Summary!$D$29,0) | D15: =B15+C15
A16: EM Europe | B16: =IF(ISNUMBER(Summary!$C$30),Summary!$C$30,0) | C16: =IF(ISNUMBER(Summary!$D$30),Summary!$D$30,0) | D16: =B16+C16
A17: Middle East | B17: =IF(ISNUMBER(Summary!$C$31),Summary!$C$31,0) | C17: =IF(ISNUMBER(Summary!$D$31),Summary!$D$31,0) | D17: =B17+C17
A18: EM Asia | B18: =IF(ISNUMBER(Summary!$C$32),Summary!$C$32,0) | C18: =IF(ISNUMBER(Summary!$D$32),Summary!$D$32,0) | D18: =B18+C18
A19: EM average | B19: =IF(ISNUMBER(Summary!$C$33),Summary!$C$33,0) | C19: =IF(ISNUMBER(Summary!$D$33),Summary!$D$33,0) | D19: =B19+C19
A22: FX — past month (return on EM ccy, %)
A23: Region | B23: US-driven | C23: Intrinsic EM | D23: Total
A24: LatAm | B24: =IF(ISNUMBER(Summary!$G$20),Summary!$G$20*100,0) | C24: =IF(ISNUMBER(Summary!$H$20),Summary!$H$20*100,0) | D24: =B24+C24
A25: EM Europe | B25: =IF(ISNUMBER(Summary!$G$21),Summary!$G$21*100,0) | C25: =IF(ISNUMBER(Summary!$H$21),Summary!$H$21*100,0) | D25: =B25+C25
A26: Middle East | B26: =IF(ISNUMBER(Summary!$G$22),Summary!$G$22*100,0) | C26: =IF(ISNUMBER(Summary!$H$22),Summary!$H$22*100,0) | D26: =B26+C26
A27: EM Asia | B27: =IF(ISNUMBER(Summary!$G$23),Summary!$G$23*100,0) | C27: =IF(ISNUMBER(Summary!$H$23),Summary!$H$23*100,0) | D27: =B27+C27
A28: EM average | B28: =IF(ISNUMBER(Summary!$G$24),Summary!$G$24*100,0) | C28: =IF(ISNUMBER(Summary!$H$24),Summary!$H$24*100,0) | D28: =B28+C28
A31: FX — year to date (return on EM ccy, %)
A32: Region | B32: US-driven | C32: Intrinsic EM | D32: Total
A33: LatAm | B33: =IF(ISNUMBER(Summary!$G$29),Summary!$G$29*100,0) | C33: =IF(ISNUMBER(Summary!$H$29),Summary!$H$29*100,0) | D33: =B33+C33
A34: EM Europe | B34: =IF(ISNUMBER(Summary!$G$30),Summary!$G$30*100,0) | C34: =IF(ISNUMBER(Summary!$H$30),Summary!$H$30*100,0) | D34: =B34+C34
A35: Middle East | B35: =IF(ISNUMBER(Summary!$G$31),Summary!$G$31*100,0) | C35: =IF(ISNUMBER(Summary!$H$31),Summary!$H$31*100,0) | D35: =B35+C35
A36: EM Asia | B36: =IF(ISNUMBER(Summary!$G$32),Summary!$G$32*100,0) | C36: =IF(ISNUMBER(Summary!$H$32),Summary!$H$32*100,0) | D36: =B36+C36
A37: EM average | B37: =IF(ISNUMBER(Summary!$G$33),Summary!$G$33*100,0) | C37: =IF(ISNUMBER(Summary!$H$33),Summary!$H$33*100,0) | D37: =B37+C37
A40: Equities — past month (MSCI, USD, %)
A41: Region | B41: US-driven | C41: Intrinsic EM | D41: Total
A42: LatAm | B42: =IF(ISNUMBER(Summary!$K$20),Summary!$K$20*100,0) | C42: =IF(ISNUMBER(Summary!$L$20),Summary!$L$20*100,0) | D42: =B42+C42
A43: EM Europe | B43: =IF(ISNUMBER(Summary!$K$21),Summary!$K$21*100,0) | C43: =IF(ISNUMBER(Summary!$L$21),Summary!$L$21*100,0) | D43: =B43+C43
A44: Middle East | B44: =IF(ISNUMBER(Summary!$K$22),Summary!$K$22*100,0) | C44: =IF(ISNUMBER(Summary!$L$22),Summary!$L$22*100,0) | D44: =B44+C44
A45: EM Asia | B45: =IF(ISNUMBER(Summary!$K$23),Summary!$K$23*100,0) | C45: =IF(ISNUMBER(Summary!$L$23),Summary!$L$23*100,0) | D45: =B45+C45
A46: EM average | B46: =IF(ISNUMBER(Summary!$K$24),Summary!$K$24*100,0) | C46: =IF(ISNUMBER(Summary!$L$24),Summary!$L$24*100,0) | D46: =B46+C46
A49: Equities — year to date (MSCI, USD, %)
A50: Region | B50: US-driven | C50: Intrinsic EM | D50: Total
A51: LatAm | B51: =IF(ISNUMBER(Summary!$K$29),Summary!$K$29*100,0) | C51: =IF(ISNUMBER(Summary!$L$29),Summary!$L$29*100,0) | D51: =B51+C51
A52: EM Europe | B52: =IF(ISNUMBER(Summary!$K$30),Summary!$K$30*100,0) | C52: =IF(ISNUMBER(Summary!$L$30),Summary!$L$30*100,0) | D52: =B52+C52
A53: Middle East | B53: =IF(ISNUMBER(Summary!$K$31),Summary!$K$31*100,0) | C53: =IF(ISNUMBER(Summary!$L$31),Summary!$L$31*100,0) | D53: =B53+C53
A54: EM Asia | B54: =IF(ISNUMBER(Summary!$K$32),Summary!$K$32*100,0) | C54: =IF(ISNUMBER(Summary!$L$32),Summary!$L$32*100,0) | D54: =B54+C54
A55: EM average | B55: =IF(ISNUMBER(Summary!$K$33),Summary!$K$33*100,0) | C55: =IF(ISNUMBER(Summary!$L$33),Summary!$L$33*100,0) | D55: =B55+C55
A58: USD credit — past month (bp)
A59: Region | B59: US-driven | C59: Intrinsic EM | D59: Total
A60: LatAm | B60: =IF(ISNUMBER(Summary!$O$20),Summary!$O$20,0) | C60: =IF(ISNUMBER(Summary!$P$20),Summary!$P$20,0) | D60: =B60+C60
A61: EM Europe | B61: =IF(ISNUMBER(Summary!$O$21),Summary!$O$21,0) | C61: =IF(ISNUMBER(Summary!$P$21),Summary!$P$21,0) | D61: =B61+C61
A62: Middle East | B62: =IF(ISNUMBER(Summary!$O$22),Summary!$O$22,0) | C62: =IF(ISNUMBER(Summary!$P$22),Summary!$P$22,0) | D62: =B62+C62
A63: EM Asia | B63: =IF(ISNUMBER(Summary!$O$23),Summary!$O$23,0) | C63: =IF(ISNUMBER(Summary!$P$23),Summary!$P$23,0) | D63: =B63+C63
A64: EM average | B64: =IF(ISNUMBER(Summary!$O$24),Summary!$O$24,0) | C64: =IF(ISNUMBER(Summary!$P$24),Summary!$P$24,0) | D64: =B64+C64
A67: USD credit — year to date (bp)
A68: Region | B68: US-driven | C68: Intrinsic EM | D68: Total
A69: LatAm | B69: =IF(ISNUMBER(Summary!$O$29),Summary!$O$29,0) | C69: =IF(ISNUMBER(Summary!$P$29),Summary!$P$29,0) | D69: =B69+C69
A70: EM Europe | B70: =IF(ISNUMBER(Summary!$O$30),Summary!$O$30,0) | C70: =IF(ISNUMBER(Summary!$P$30),Summary!$P$30,0) | D70: =B70+C70
A71: Middle East | B71: =IF(ISNUMBER(Summary!$O$31),Summary!$O$31,0) | C71: =IF(ISNUMBER(Summary!$P$31),Summary!$P$31,0) | D71: =B71+C71
A72: EM Asia | B72: =IF(ISNUMBER(Summary!$O$32),Summary!$O$32,0) | C72: =IF(ISNUMBER(Summary!$P$32),Summary!$P$32,0) | D72: =B72+C72
A73: EM average | B73: =IF(ISNUMBER(Summary!$O$33),Summary!$O$33,0) | C73: =IF(ISNUMBER(Summary!$P$33),Summary!$P$33,0) | D73: =B73+C73
A76: Pass-through — how much of the US move each region took (under 1 = absorbed)
A77: Region | B77: Rates 1M | C77: Rates YTD | D77: FX 1M | E77: FX YTD | F77: Equities 1M | G77: Equities YTD
A78: LatAm | B78: =IF(ISNUMBER(Summary!$E$20),Summary!$E$20,0) | C78: =IF(ISNUMBER(Summary!$E$29),Summary!$E$29,0) | D78: =IF(ISNUMBER(Summary!$I$20),Summary!$I$20,0) | E78: =IF(ISNUMBER(Summary!$I$29),Summary!$I$29,0) | F78: =IF(ISNUMBER(Summary!$M$20),Summary!$M$20,0) | G78: =IF(ISNUMBER(Summary!$M$29),Summary!$M$29,0)
A79: EM Europe | B79: =IF(ISNUMBER(Summary!$E$21),Summary!$E$21,0) | C79: =IF(ISNUMBER(Summary!$E$30),Summary!$E$30,0) | D79: =IF(ISNUMBER(Summary!$I$21),Summary!$I$21,0) | E79: =IF(ISNUMBER(Summary!$I$30),Summary!$I$30,0) | F79: =IF(ISNUMBER(Summary!$M$21),Summary!$M$21,0) | G79: =IF(ISNUMBER(Summary!$M$30),Summary!$M$30,0)
A80: Middle East | B80: =IF(ISNUMBER(Summary!$E$22),Summary!$E$22,0) | C80: =IF(ISNUMBER(Summary!$E$31),Summary!$E$31,0) | D80: =IF(ISNUMBER(Summary!$I$22),Summary!$I$22,0) | E80: =IF(ISNUMBER(Summary!$I$31),Summary!$I$31,0) | F80: =IF(ISNUMBER(Summary!$M$22),Summary!$M$22,0) | G80: =IF(ISNUMBER(Summary!$M$31),Summary!$M$31,0)
A81: EM Asia | B81: =IF(ISNUMBER(Summary!$E$23),Summary!$E$23,0) | C81: =IF(ISNUMBER(Summary!$E$32),Summary!$E$32,0) | D81: =IF(ISNUMBER(Summary!$I$23),Summary!$I$23,0) | E81: =IF(ISNUMBER(Summary!$I$32),Summary!$I$32,0) | F81: =IF(ISNUMBER(Summary!$M$23),Summary!$M$23,0) | G81: =IF(ISNUMBER(Summary!$M$32),Summary!$M$32,0)
A82: EM average | B82: =IF(ISNUMBER(Summary!$E$24),Summary!$E$24,0) | C82: =IF(ISNUMBER(Summary!$E$33),Summary!$E$33,0) | D82: =IF(ISNUMBER(Summary!$I$24),Summary!$I$24,0) | E82: =IF(ISNUMBER(Summary!$I$33),Summary!$I$33,0) | F82: =IF(ISNUMBER(Summary!$M$24),Summary!$M$24,0) | G82: =IF(ISNUMBER(Summary!$M$33),Summary!$M$33,0)
A85: USD credit — share of the yield move that is Treasuries (near 100% = spreads did nothing)
A86: Region | B86: 1M | C86: YTD
A87: LatAm | B87: =IF(ISNUMBER(Summary!$Q$20),Summary!$Q$20,0) | C87: =IF(ISNUMBER(Summary!$Q$29),Summary!$Q$29,0)
A88: EM Europe | B88: =IF(ISNUMBER(Summary!$Q$21),Summary!$Q$21,0) | C88: =IF(ISNUMBER(Summary!$Q$30),Summary!$Q$30,0)
A89: Middle East | B89: =IF(ISNUMBER(Summary!$Q$22),Summary!$Q$22,0) | C89: =IF(ISNUMBER(Summary!$Q$31),Summary!$Q$31,0)
A90: EM Asia | B90: =IF(ISNUMBER(Summary!$Q$23),Summary!$Q$23,0) | C90: =IF(ISNUMBER(Summary!$Q$32),Summary!$Q$32,0)
A91: EM average | B91: =IF(ISNUMBER(Summary!$Q$24),Summary!$Q$24,0) | C91: =IF(ISNUMBER(Summary!$Q$33),Summary!$Q$33,0)
A93: Above 100% means spreads tightened while Treasuries sold off — more than all of the move was the US. That is the strongest form of the digestion result.

Sheet Rates
A1: EM LOCAL RATES — 10Y generic, by country and region
A2: d(local 10Y) = d(UST 10Y) + d(local less UST). US-driven is the Treasury move; intrinsic is the change in the gap to Treasuries. Pass-through = total / US-driven: how much of the US move the local curve took. Under 1.0 = absorbed.
A4: LATAM
A5: Country | B5: Region | C5: Level | D5: In avg | E5: 1M: Total move (bp) | F5: 1M: US-driven: d UST 10Y (bp) | G5: 1M: Intrinsic: d gap to UST (bp) | H5: 1M: Pass-through (total / US) | I5: 1M: Beta to UST 10Y (2y) | J5: 1M: Predicted by beta (bp) | K5: 1M: Surprise: actual less predicted (bp) | L5: YTD: Total move (bp) | M5: YTD: US-driven: d UST 10Y (bp) | N5: YTD: Intrinsic: d gap to UST (bp) | O5: YTD: Pass-through (total / US) | P5: YTD: Beta to UST 10Y (2y) | Q5: YTD: Predicted by beta (bp) | R5: YTD: Surprise: actual less predicted (bp)
A6: Brazil | B6: LatAm | C6: =INDEX(HIST_D!$AH$8:$AH$791,1) | D6: yes | E6: =IFERROR((INDEX(HIST_D!$AH$8:$AH$791,1)-INDEX(HIST_D!$AH$8:$AH$791,Control!$B$10))*100,"") | F6: =IFERROR((INDEX(HIST_D!$F$8:$F$791,1)-INDEX(HIST_D!$F$8:$F$791,Control!$B$10))*100,"") | G6: =IFERROR(E6-F6,"") | H6: =IFERROR(IF(ABS(F6)<Control!$B$13,"n/m",E6/F6),"n/m") | I6: =IFERROR(SLOPE(HIST_D!$CY$8:INDEX(HIST_D!$CY$8:$CY$791,Control!$B$12),HIST_D!$CV$8:INDEX(HIST_D!$CV$8:$CV$791,Control!$B$12)),"") | J6: =IFERROR(I6*(INDEX(HIST_D!$F$8:$F$791,1)-INDEX(HIST_D!$F$8:$F$791,Control!$B$10))*100,"") | K6: =IFERROR(E6-J6,"") | L6: =IFERROR((INDEX(HIST_D!$AH$8:$AH$791,1)-INDEX(HIST_D!$AH$8:$AH$791,Control!$B$11))*100,"") | M6: =IFERROR((INDEX(HIST_D!$F$8:$F$791,1)-INDEX(HIST_D!$F$8:$F$791,Control!$B$11))*100,"") | N6: =IFERROR(L6-M6,"") | O6: =IFERROR(IF(ABS(M6)<Control!$B$13,"n/m",L6/M6),"n/m") | P6: =IFERROR(SLOPE(HIST_D!$CY$8:INDEX(HIST_D!$CY$8:$CY$791,Control!$B$12),HIST_D!$CV$8:INDEX(HIST_D!$CV$8:$CV$791,Control!$B$12)),"") | Q6: =IFERROR(P6*(INDEX(HIST_D!$F$8:$F$791,1)-INDEX(HIST_D!$F$8:$F$791,Control!$B$11))*100,"") | R6: =IFERROR(L6-Q6,"")
A7: Mexico | B7: LatAm | C7: =INDEX(HIST_D!$AI$8:$AI$791,1) | D7: yes | E7: =IFERROR((INDEX(HIST_D!$AI$8:$AI$791,1)-INDEX(HIST_D!$AI$8:$AI$791,Control!$B$10))*100,"") | F7: =IFERROR((INDEX(HIST_D!$F$8:$F$791,1)-INDEX(HIST_D!$F$8:$F$791,Control!$B$10))*100,"") | G7: =IFERROR(E7-F7,"") | H7: =IFERROR(IF(ABS(F7)<Control!$B$13,"n/m",E7/F7),"n/m") | I7: =IFERROR(SLOPE(HIST_D!$CZ$8:INDEX(HIST_D!$CZ$8:$CZ$791,Control!$B$12),HIST_D!$CV$8:INDEX(HIST_D!$CV$8:$CV$791,Control!$B$12)),"") | J7: =IFERROR(I7*(INDEX(HIST_D!$F$8:$F$791,1)-INDEX(HIST_D!$F$8:$F$791,Control!$B$10))*100,"") | K7: =IFERROR(E7-J7,"") | L7: =IFERROR((INDEX(HIST_D!$AI$8:$AI$791,1)-INDEX(HIST_D!$AI$8:$AI$791,Control!$B$11))*100,"") | M7: =IFERROR((INDEX(HIST_D!$F$8:$F$791,1)-INDEX(HIST_D!$F$8:$F$791,Control!$B$11))*100,"") | N7: =IFERROR(L7-M7,"") | O7: =IFERROR(IF(ABS(M7)<Control!$B$13,"n/m",L7/M7),"n/m") | P7: =IFERROR(SLOPE(HIST_D!$CZ$8:INDEX(HIST_D!$CZ$8:$CZ$791,Control!$B$12),HIST_D!$CV$8:INDEX(HIST_D!$CV$8:$CV$791,Control!$B$12)),"") | Q7: =IFERROR(P7*(INDEX(HIST_D!$F$8:$F$791,1)-INDEX(HIST_D!$F$8:$F$791,Control!$B$11))*100,"") | R7: =IFERROR(L7-Q7,"")
A8: Chile | B8: LatAm | C8: =INDEX(HIST_D!$AJ$8:$AJ$791,1) | D8: yes | E8: =IFERROR((INDEX(HIST_D!$AJ$8:$AJ$791,1)-INDEX(HIST_D!$AJ$8:$AJ$791,Control!$B$10))*100,"") | F8: =IFERROR((INDEX(HIST_D!$F$8:$F$791,1)-INDEX(HIST_D!$F$8:$F$791,Control!$B$10))*100,"") | G8: =IFERROR(E8-F8,"") | H8: =IFERROR(IF(ABS(F8)<Control!$B$13,"n/m",E8/F8),"n/m") | I8: =IFERROR(SLOPE(HIST_D!$DA$8:INDEX(HIST_D!$DA$8:$DA$791,Control!$B$12),HIST_D!$CV$8:INDEX(HIST_D!$CV$8:$CV$791,Control!$B$12)),"") | J8: =IFERROR(I8*(INDEX(HIST_D!$F$8:$F$791,1)-INDEX(HIST_D!$F$8:$F$791,Control!$B$10))*100,"") | K8: =IFERROR(E8-J8,"") | L8: =IFERROR((INDEX(HIST_D!$AJ$8:$AJ$791,1)-INDEX(HIST_D!$AJ$8:$AJ$791,Control!$B$11))*100,"") | M8: =IFERROR((INDEX(HIST_D!$F$8:$F$791,1)-INDEX(HIST_D!$F$8:$F$791,Control!$B$11))*100,"") | N8: =IFERROR(L8-M8,"") | O8: =IFERROR(IF(ABS(M8)<Control!$B$13,"n/m",L8/M8),"n/m") | P8: =IFERROR(SLOPE(HIST_D!$DA$8:INDEX(HIST_D!$DA$8:$DA$791,Control!$B$12),HIST_D!$CV$8:INDEX(HIST_D!$CV$8:$CV$791,Control!$B$12)),"") | Q8: =IFERROR(P8*(INDEX(HIST_D!$F$8:$F$791,1)-INDEX(HIST_D!$F$8:$F$791,Control!$B$11))*100,"") | R8: =IFERROR(L8-Q8,"")
A9: Colombia | B9: LatAm | C9: =INDEX(HIST_D!$AK$8:$AK$791,1) | D9: yes | E9: =IFERROR((INDEX(HIST_D!$AK$8:$AK$791,1)-INDEX(HIST_D!$AK$8:$AK$791,Control!$B$10))*100,"") | F9: =IFERROR((INDEX(HIST_D!$F$8:$F$791,1)-INDEX(HIST_D!$F$8:$F$791,Control!$B$10))*100,"") | G9: =IFERROR(E9-F9,"") | H9: =IFERROR(IF(ABS(F9)<Control!$B$13,"n/m",E9/F9),"n/m") | I9: =IFERROR(SLOPE(HIST_D!$DB$8:INDEX(HIST_D!$DB$8:$DB$791,Control!$B$12),HIST_D!$CV$8:INDEX(HIST_D!$CV$8:$CV$791,Control!$B$12)),"") | J9: =IFERROR(I9*(INDEX(HIST_D!$F$8:$F$791,1)-INDEX(HIST_D!$F$8:$F$791,Control!$B$10))*100,"") | K9: =IFERROR(E9-J9,"") | L9: =IFERROR((INDEX(HIST_D!$AK$8:$AK$791,1)-INDEX(HIST_D!$AK$8:$AK$791,Control!$B$11))*100,"") | M9: =IFERROR((INDEX(HIST_D!$F$8:$F$791,1)-INDEX(HIST_D!$F$8:$F$791,Control!$B$11))*100,"") | N9: =IFERROR(L9-M9,"") | O9: =IFERROR(IF(ABS(M9)<Control!$B$13,"n/m",L9/M9),"n/m") | P9: =IFERROR(SLOPE(HIST_D!$DB$8:INDEX(HIST_D!$DB$8:$DB$791,Control!$B$12),HIST_D!$CV$8:INDEX(HIST_D!$CV$8:$CV$791,Control!$B$12)),"") | Q9: =IFERROR(P9*(INDEX(HIST_D!$F$8:$F$791,1)-INDEX(HIST_D!$F$8:$F$791,Control!$B$11))*100,"") | R9: =IFERROR(L9-Q9,"")
A10: Peru | B10: LatAm | C10: =INDEX(HIST_D!$AL$8:$AL$791,1) | D10: yes | E10: =IFERROR((INDEX(HIST_D!$AL$8:$AL$791,1)-INDEX(HIST_D!$AL$8:$AL$791,Control!$B$10))*100,"") | F10: =IFERROR((INDEX(HIST_D!$F$8:$F$791,1)-INDEX(HIST_D!$F$8:$F$791,Control!$B$10))*100,"") | G10: =IFERROR(E10-F10,"") | H10: =IFERROR(IF(ABS(F10)<Control!$B$13,"n/m",E10/F10),"n/m") | I10: =IFERROR(SLOPE(HIST_D!$DC$8:INDEX(HIST_D!$DC$8:$DC$791,Control!$B$12),HIST_D!$CV$8:INDEX(HIST_D!$CV$8:$CV$791,Control!$B$12)),"") | J10: =IFERROR(I10*(INDEX(HIST_D!$F$8:$F$791,1)-INDEX(HIST_D!$F$8:$F$791,Control!$B$10))*100,"") | K10: =IFERROR(E10-J10,"") | L10: =IFERROR((INDEX(HIST_D!$AL$8:$AL$791,1)-INDEX(HIST_D!$AL$8:$AL$791,Control!$B$11))*100,"") | M10: =IFERROR((INDEX(HIST_D!$F$8:$F$791,1)-INDEX(HIST_D!$F$8:$F$791,Control!$B$11))*100,"") | N10: =IFERROR(L10-M10,"") | O10: =IFERROR(IF(ABS(M10)<Control!$B$13,"n/m",L10/M10),"n/m") | P10: =IFERROR(SLOPE(HIST_D!$DC$8:INDEX(HIST_D!$DC$8:$DC$791,Control!$B$12),HIST_D!$CV$8:INDEX(HIST_D!$CV$8:$CV$791,Control!$B$12)),"") | Q10: =IFERROR(P10*(INDEX(HIST_D!$F$8:$F$791,1)-INDEX(HIST_D!$F$8:$F$791,Control!$B$11))*100,"") | R10: =IFERROR(L10-Q10,"")
A11: LatAm average | B11: n=5 | E11: =IFERROR(AVERAGE(E6,E7,E8,E9,E10),"") | F11: =IFERROR(AVERAGE(F6,F7,F8,F9,F10),"") | G11: =IFERROR(AVERAGE(G6,G7,G8,G9,G10),"") | H11: =IFERROR(IF(ABS(F11)<Control!$B$13,"n/m",E11/F11),"n/m") | I11: =IFERROR(AVERAGE(I6,I7,I8,I9,I10),"") | J11: =IFERROR(AVERAGE(J6,J7,J8,J9,J10),"") | K11: =IFERROR(AVERAGE(K6,K7,K8,K9,K10),"") | L11: =IFERROR(AVERAGE(L6,L7,L8,L9,L10),"") | M11: =IFERROR(AVERAGE(M6,M7,M8,M9,M10),"") | N11: =IFERROR(AVERAGE(N6,N7,N8,N9,N10),"") | O11: =IFERROR(IF(ABS(M11)<Control!$B$13,"n/m",L11/M11),"n/m") | P11: =IFERROR(AVERAGE(P6,P7,P8,P9,P10),"") | Q11: =IFERROR(AVERAGE(Q6,Q7,Q8,Q9,Q10),"") | R11: =IFERROR(AVERAGE(R6,R7,R8,R9,R10),"")
A12: =IFERROR("LatAm: local 10Y "&TEXT($E$11,"+0;-0")&"bp on the month against UST 10Y "&TEXT($F$11,"+0;-0")&"bp, so the gap to Treasuries moved "&TEXT($G$11,"+0;-0")&"bp"&IF(ISNUMBER($H$11)," (pass-through "&TEXT($H$11,"0.00")&"x)","")&". History (2y beta "&TEXT($I$11,"0.00")&") would have predicted "&TEXT($J$11,"+0;-0")&"bp; the surprise is "&TEXT($K$11,"+0;-0")&"bp. YTD: "&TEXT($L$11,"+0;-0")&"bp against "&TEXT($M$11,"+0;-0")&"bp, gap "&TEXT($N$11,"+0;-0")&"bp"&IF(ISNUMBER($O$11)," (pass-through "&TEXT($O$11,"0.00")&"x)","")&". "&IF($K$11<-5,"The curve did better than its own history — absorbed.",IF($K$11>5,"The curve did worse than its own history — imported.","Moved in line with its own history.")),"")
A14: EM EUROPE
A15: Country | B15: Region | C15: Level | D15: In avg | E15: 1M: Total move (bp) | F15: 1M: US-driven: d UST 10Y (bp) | G15: 1M: Intrinsic: d gap to UST (bp) | H15: 1M: Pass-through (total / US) | I15: 1M: Beta to UST 10Y (2y) | J15: 1M: Predicted by beta (bp) | K15: 1M: Surprise: actual less predicted (bp) | L15: YTD: Total move (bp) | M15: YTD: US-driven: d UST 10Y (bp) | N15: YTD: Intrinsic: d gap to UST (bp) | O15: YTD: Pass-through (total / US) | P15: YTD: Beta to UST 10Y (2y) | Q15: YTD: Predicted by beta (bp) | R15: YTD: Surprise: actual less predicted (bp)
A16: Poland | B16: EM Europe | C16: =INDEX(HIST_D!$AM$8:$AM$791,1) | D16: yes | E16: =IFERROR((INDEX(HIST_D!$AM$8:$AM$791,1)-INDEX(HIST_D!$AM$8:$AM$791,Control!$B$10))*100,"") | F16: =IFERROR((INDEX(HIST_D!$F$8:$F$791,1)-INDEX(HIST_D!$F$8:$F$791,Control!$B$10))*100,"") | G16: =IFERROR(E16-F16,"") | H16: =IFERROR(IF(ABS(F16)<Control!$B$13,"n/m",E16/F16),"n/m") | I16: =IFERROR(SLOPE(HIST_D!$DD$8:INDEX(HIST_D!$DD$8:$DD$791,Control!$B$12),HIST_D!$CV$8:INDEX(HIST_D!$CV$8:$CV$791,Control!$B$12)),"") | J16: =IFERROR(I16*(INDEX(HIST_D!$F$8:$F$791,1)-INDEX(HIST_D!$F$8:$F$791,Control!$B$10))*100,"") | K16: =IFERROR(E16-J16,"") | L16: =IFERROR((INDEX(HIST_D!$AM$8:$AM$791,1)-INDEX(HIST_D!$AM$8:$AM$791,Control!$B$11))*100,"") | M16: =IFERROR((INDEX(HIST_D!$F$8:$F$791,1)-INDEX(HIST_D!$F$8:$F$791,Control!$B$11))*100,"") | N16: =IFERROR(L16-M16,"") | O16: =IFERROR(IF(ABS(M16)<Control!$B$13,"n/m",L16/M16),"n/m") | P16: =IFERROR(SLOPE(HIST_D!$DD$8:INDEX(HIST_D!$DD$8:$DD$791,Control!$B$12),HIST_D!$CV$8:INDEX(HIST_D!$CV$8:$CV$791,Control!$B$12)),"") | Q16: =IFERROR(P16*(INDEX(HIST_D!$F$8:$F$791,1)-INDEX(HIST_D!$F$8:$F$791,Control!$B$11))*100,"") | R16: =IFERROR(L16-Q16,"")
A17: Hungary | B17: EM Europe | C17: =INDEX(HIST_D!$AN$8:$AN$791,1) | D17: yes | E17: =IFERROR((INDEX(HIST_D!$AN$8:$AN$791,1)-INDEX(HIST_D!$AN$8:$AN$791,Control!$B$10))*100,"") | F17: =IFERROR((INDEX(HIST_D!$F$8:$F$791,1)-INDEX(HIST_D!$F$8:$F$791,Control!$B$10))*100,"") | G17: =IFERROR(E17-F17,"") | H17: =IFERROR(IF(ABS(F17)<Control!$B$13,"n/m",E17/F17),"n/m") | I17: =IFERROR(SLOPE(HIST_D!$DE$8:INDEX(HIST_D!$DE$8:$DE$791,Control!$B$12),HIST_D!$CV$8:INDEX(HIST_D!$CV$8:$CV$791,Control!$B$12)),"") | J17: =IFERROR(I17*(INDEX(HIST_D!$F$8:$F$791,1)-INDEX(HIST_D!$F$8:$F$791,Control!$B$10))*100,"") | K17: =IFERROR(E17-J17,"") | L17: =IFERROR((INDEX(HIST_D!$AN$8:$AN$791,1)-INDEX(HIST_D!$AN$8:$AN$791,Control!$B$11))*100,"") | M17: =IFERROR((INDEX(HIST_D!$F$8:$F$791,1)-INDEX(HIST_D!$F$8:$F$791,Control!$B$11))*100,"") | N17: =IFERROR(L17-M17,"") | O17: =IFERROR(IF(ABS(M17)<Control!$B$13,"n/m",L17/M17),"n/m") | P17: =IFERROR(SLOPE(HIST_D!$DE$8:INDEX(HIST_D!$DE$8:$DE$791,Control!$B$12),HIST_D!$CV$8:INDEX(HIST_D!$CV$8:$CV$791,Control!$B$12)),"") | Q17: =IFERROR(P17*(INDEX(HIST_D!$F$8:$F$791,1)-INDEX(HIST_D!$F$8:$F$791,Control!$B$11))*100,"") | R17: =IFERROR(L17-Q17,"")
A18: Czechia | B18: EM Europe | C18: =INDEX(HIST_D!$AO$8:$AO$791,1) | D18: yes | E18: =IFERROR((INDEX(HIST_D!$AO$8:$AO$791,1)-INDEX(HIST_D!$AO$8:$AO$791,Control!$B$10))*100,"") | F18: =IFERROR((INDEX(HIST_D!$F$8:$F$791,1)-INDEX(HIST_D!$F$8:$F$791,Control!$B$10))*100,"") | G18: =IFERROR(E18-F18,"") | H18: =IFERROR(IF(ABS(F18)<Control!$B$13,"n/m",E18/F18),"n/m") | I18: =IFERROR(SLOPE(HIST_D!$DF$8:INDEX(HIST_D!$DF$8:$DF$791,Control!$B$12),HIST_D!$CV$8:INDEX(HIST_D!$CV$8:$CV$791,Control!$B$12)),"") | J18: =IFERROR(I18*(INDEX(HIST_D!$F$8:$F$791,1)-INDEX(HIST_D!$F$8:$F$791,Control!$B$10))*100,"") | K18: =IFERROR(E18-J18,"") | L18: =IFERROR((INDEX(HIST_D!$AO$8:$AO$791,1)-INDEX(HIST_D!$AO$8:$AO$791,Control!$B$11))*100,"") | M18: =IFERROR((INDEX(HIST_D!$F$8:$F$791,1)-INDEX(HIST_D!$F$8:$F$791,Control!$B$11))*100,"") | N18: =IFERROR(L18-M18,"") | O18: =IFERROR(IF(ABS(M18)<Control!$B$13,"n/m",L18/M18),"n/m") | P18: =IFERROR(SLOPE(HIST_D!$DF$8:INDEX(HIST_D!$DF$8:$DF$791,Control!$B$12),HIST_D!$CV$8:INDEX(HIST_D!$CV$8:$CV$791,Control!$B$12)),"") | Q18: =IFERROR(P18*(INDEX(HIST_D!$F$8:$F$791,1)-INDEX(HIST_D!$F$8:$F$791,Control!$B$11))*100,"") | R18: =IFERROR(L18-Q18,"")
A19: Romania | B19: EM Europe | C19: =INDEX(HIST_D!$AP$8:$AP$791,1) | D19: yes | E19: =IFERROR((INDEX(HIST_D!$AP$8:$AP$791,1)-INDEX(HIST_D!$AP$8:$AP$791,Control!$B$10))*100,"") | F19: =IFERROR((INDEX(HIST_D!$F$8:$F$791,1)-INDEX(HIST_D!$F$8:$F$791,Control!$B$10))*100,"") | G19: =IFERROR(E19-F19,"") | H19: =IFERROR(IF(ABS(F19)<Control!$B$13,"n/m",E19/F19),"n/m") | I19: =IFERROR(SLOPE(HIST_D!$DG$8:INDEX(HIST_D!$DG$8:$DG$791,Control!$B$12),HIST_D!$CV$8:INDEX(HIST_D!$CV$8:$CV$791,Control!$B$12)),"") | J19: =IFERROR(I19*(INDEX(HIST_D!$F$8:$F$791,1)-INDEX(HIST_D!$F$8:$F$791,Control!$B$10))*100,"") | K19: =IFERROR(E19-J19,"") | L19: =IFERROR((INDEX(HIST_D!$AP$8:$AP$791,1)-INDEX(HIST_D!$AP$8:$AP$791,Control!$B$11))*100,"") | M19: =IFERROR((INDEX(HIST_D!$F$8:$F$791,1)-INDEX(HIST_D!$F$8:$F$791,Control!$B$11))*100,"") | N19: =IFERROR(L19-M19,"") | O19: =IFERROR(IF(ABS(M19)<Control!$B$13,"n/m",L19/M19),"n/m") | P19: =IFERROR(SLOPE(HIST_D!$DG$8:INDEX(HIST_D!$DG$8:$DG$791,Control!$B$12),HIST_D!$CV$8:INDEX(HIST_D!$CV$8:$CV$791,Control!$B$12)),"") | Q19: =IFERROR(P19*(INDEX(HIST_D!$F$8:$F$791,1)-INDEX(HIST_D!$F$8:$F$791,Control!$B$11))*100,"") | R19: =IFERROR(L19-Q19,"")
A20: Turkiye | B20: EM Europe | C20: =INDEX(HIST_D!$AQ$8:$AQ$791,1) | D20: no | E20: =IFERROR((INDEX(HIST_D!$AQ$8:$AQ$791,1)-INDEX(HIST_D!$AQ$8:$AQ$791,Control!$B$10))*100,"") | F20: =IFERROR((INDEX(HIST_D!$F$8:$F$791,1)-INDEX(HIST_D!$F$8:$F$791,Control!$B$10))*100,"") | G20: =IFERROR(E20-F20,"") | H20: =IFERROR(IF(ABS(F20)<Control!$B$13,"n/m",E20/F20),"n/m") | I20: =IFERROR(SLOPE(HIST_D!$DH$8:INDEX(HIST_D!$DH$8:$DH$791,Control!$B$12),HIST_D!$CV$8:INDEX(HIST_D!$CV$8:$CV$791,Control!$B$12)),"") | J20: =IFERROR(I20*(INDEX(HIST_D!$F$8:$F$791,1)-INDEX(HIST_D!$F$8:$F$791,Control!$B$10))*100,"") | K20: =IFERROR(E20-J20,"") | L20: =IFERROR((INDEX(HIST_D!$AQ$8:$AQ$791,1)-INDEX(HIST_D!$AQ$8:$AQ$791,Control!$B$11))*100,"") | M20: =IFERROR((INDEX(HIST_D!$F$8:$F$791,1)-INDEX(HIST_D!$F$8:$F$791,Control!$B$11))*100,"") | N20: =IFERROR(L20-M20,"") | O20: =IFERROR(IF(ABS(M20)<Control!$B$13,"n/m",L20/M20),"n/m") | P20: =IFERROR(SLOPE(HIST_D!$DH$8:INDEX(HIST_D!$DH$8:$DH$791,Control!$B$12),HIST_D!$CV$8:INDEX(HIST_D!$CV$8:$CV$791,Control!$B$12)),"") | Q20: =IFERROR(P20*(INDEX(HIST_D!$F$8:$F$791,1)-INDEX(HIST_D!$F$8:$F$791,Control!$B$11))*100,"") | R20: =IFERROR(L20-Q20,"") | S20: excluded from rates and FX averages: structural depreciation and a 30% curve swamp an equal weight
A21: EM Europe average | B21: n=4 | E21: =IFERROR(AVERAGE(E16,E17,E18,E19),"") | F21: =IFERROR(AVERAGE(F16,F17,F18,F19),"") | G21: =IFERROR(AVERAGE(G16,G17,G18,G19),"") | H21: =IFERROR(IF(ABS(F21)<Control!$B$13,"n/m",E21/F21),"n/m") | I21: =IFERROR(AVERAGE(I16,I17,I18,I19),"") | J21: =IFERROR(AVERAGE(J16,J17,J18,J19),"") | K21: =IFERROR(AVERAGE(K16,K17,K18,K19),"") | L21: =IFERROR(AVERAGE(L16,L17,L18,L19),"") | M21: =IFERROR(AVERAGE(M16,M17,M18,M19),"") | N21: =IFERROR(AVERAGE(N16,N17,N18,N19),"") | O21: =IFERROR(IF(ABS(M21)<Control!$B$13,"n/m",L21/M21),"n/m") | P21: =IFERROR(AVERAGE(P16,P17,P18,P19),"") | Q21: =IFERROR(AVERAGE(Q16,Q17,Q18,Q19),"") | R21: =IFERROR(AVERAGE(R16,R17,R18,R19),"")
A22: =IFERROR("EM Europe: local 10Y "&TEXT($E$21,"+0;-0")&"bp on the month against UST 10Y "&TEXT($F$21,"+0;-0")&"bp, so the gap to Treasuries moved "&TEXT($G$21,"+0;-0")&"bp"&IF(ISNUMBER($H$21)," (pass-through "&TEXT($H$21,"0.00")&"x)","")&". History (2y beta "&TEXT($I$21,"0.00")&") would have predicted "&TEXT($J$21,"+0;-0")&"bp; the surprise is "&TEXT($K$21,"+0;-0")&"bp. YTD: "&TEXT($L$21,"+0;-0")&"bp against "&TEXT($M$21,"+0;-0")&"bp, gap "&TEXT($N$21,"+0;-0")&"bp"&IF(ISNUMBER($O$21)," (pass-through "&TEXT($O$21,"0.00")&"x)","")&". "&IF($K$21<-5,"The curve did better than its own history — absorbed.",IF($K$21>5,"The curve did worse than its own history — imported.","Moved in line with its own history.")),"")
A24: MIDDLE EAST
A25: Country | B25: Region | C25: Level | D25: In avg | E25: 1M: Total move (bp) | F25: 1M: US-driven: d UST 10Y (bp) | G25: 1M: Intrinsic: d gap to UST (bp) | H25: 1M: Pass-through (total / US) | I25: 1M: Beta to UST 10Y (2y) | J25: 1M: Predicted by beta (bp) | K25: 1M: Surprise: actual less predicted (bp) | L25: YTD: Total move (bp) | M25: YTD: US-driven: d UST 10Y (bp) | N25: YTD: Intrinsic: d gap to UST (bp) | O25: YTD: Pass-through (total / US) | P25: YTD: Beta to UST 10Y (2y) | Q25: YTD: Predicted by beta (bp) | R25: YTD: Surprise: actual less predicted (bp)
A26: Israel | B26: Middle East | C26: =INDEX(HIST_D!$AR$8:$AR$791,1) | D26: yes | E26: =IFERROR((INDEX(HIST_D!$AR$8:$AR$791,1)-INDEX(HIST_D!$AR$8:$AR$791,Control!$B$10))*100,"") | F26: =IFERROR((INDEX(HIST_D!$F$8:$F$791,1)-INDEX(HIST_D!$F$8:$F$791,Control!$B$10))*100,"") | G26: =IFERROR(E26-F26,"") | H26: =IFERROR(IF(ABS(F26)<Control!$B$13,"n/m",E26/F26),"n/m") | I26: =IFERROR(SLOPE(HIST_D!$DI$8:INDEX(HIST_D!$DI$8:$DI$791,Control!$B$12),HIST_D!$CV$8:INDEX(HIST_D!$CV$8:$CV$791,Control!$B$12)),"") | J26: =IFERROR(I26*(INDEX(HIST_D!$F$8:$F$791,1)-INDEX(HIST_D!$F$8:$F$791,Control!$B$10))*100,"") | K26: =IFERROR(E26-J26,"") | L26: =IFERROR((INDEX(HIST_D!$AR$8:$AR$791,1)-INDEX(HIST_D!$AR$8:$AR$791,Control!$B$11))*100,"") | M26: =IFERROR((INDEX(HIST_D!$F$8:$F$791,1)-INDEX(HIST_D!$F$8:$F$791,Control!$B$11))*100,"") | N26: =IFERROR(L26-M26,"") | O26: =IFERROR(IF(ABS(M26)<Control!$B$13,"n/m",L26/M26),"n/m") | P26: =IFERROR(SLOPE(HIST_D!$DI$8:INDEX(HIST_D!$DI$8:$DI$791,Control!$B$12),HIST_D!$CV$8:INDEX(HIST_D!$CV$8:$CV$791,Control!$B$12)),"") | Q26: =IFERROR(P26*(INDEX(HIST_D!$F$8:$F$791,1)-INDEX(HIST_D!$F$8:$F$791,Control!$B$11))*100,"") | R26: =IFERROR(L26-Q26,"")
A27: Egypt | B27: Middle East | C27: =INDEX(HIST_D!$AS$8:$AS$791,1) | D27: yes | E27: =IFERROR((INDEX(HIST_D!$AS$8:$AS$791,1)-INDEX(HIST_D!$AS$8:$AS$791,Control!$B$10))*100,"") | F27: =IFERROR((INDEX(HIST_D!$F$8:$F$791,1)-INDEX(HIST_D!$F$8:$F$791,Control!$B$10))*100,"") | G27: =IFERROR(E27-F27,"") | H27: =IFERROR(IF(ABS(F27)<Control!$B$13,"n/m",E27/F27),"n/m") | I27: =IFERROR(SLOPE(HIST_D!$DJ$8:INDEX(HIST_D!$DJ$8:$DJ$791,Control!$B$12),HIST_D!$CV$8:INDEX(HIST_D!$CV$8:$CV$791,Control!$B$12)),"") | J27: =IFERROR(I27*(INDEX(HIST_D!$F$8:$F$791,1)-INDEX(HIST_D!$F$8:$F$791,Control!$B$10))*100,"") | K27: =IFERROR(E27-J27,"") | L27: =IFERROR((INDEX(HIST_D!$AS$8:$AS$791,1)-INDEX(HIST_D!$AS$8:$AS$791,Control!$B$11))*100,"") | M27: =IFERROR((INDEX(HIST_D!$F$8:$F$791,1)-INDEX(HIST_D!$F$8:$F$791,Control!$B$11))*100,"") | N27: =IFERROR(L27-M27,"") | O27: =IFERROR(IF(ABS(M27)<Control!$B$13,"n/m",L27/M27),"n/m") | P27: =IFERROR(SLOPE(HIST_D!$DJ$8:INDEX(HIST_D!$DJ$8:$DJ$791,Control!$B$12),HIST_D!$CV$8:INDEX(HIST_D!$CV$8:$CV$791,Control!$B$12)),"") | Q27: =IFERROR(P27*(INDEX(HIST_D!$F$8:$F$791,1)-INDEX(HIST_D!$F$8:$F$791,Control!$B$11))*100,"") | R27: =IFERROR(L27-Q27,"") | S27: excluded from FX average: managed float with step devaluations; GTEGP10Y is Verify
A28: Middle East average | B28: n=2 | E28: =IFERROR(AVERAGE(E26,E27),"") | F28: =IFERROR(AVERAGE(F26,F27),"") | G28: =IFERROR(AVERAGE(G26,G27),"") | H28: =IFERROR(IF(ABS(F28)<Control!$B$13,"n/m",E28/F28),"n/m") | I28: =IFERROR(AVERAGE(I26,I27),"") | J28: =IFERROR(AVERAGE(J26,J27),"") | K28: =IFERROR(AVERAGE(K26,K27),"") | L28: =IFERROR(AVERAGE(L26,L27),"") | M28: =IFERROR(AVERAGE(M26,M27),"") | N28: =IFERROR(AVERAGE(N26,N27),"") | O28: =IFERROR(IF(ABS(M28)<Control!$B$13,"n/m",L28/M28),"n/m") | P28: =IFERROR(AVERAGE(P26,P27),"") | Q28: =IFERROR(AVERAGE(Q26,Q27),"") | R28: =IFERROR(AVERAGE(R26,R27),"")
A29: =IFERROR("Middle East: local 10Y "&TEXT($E$28,"+0;-0")&"bp on the month against UST 10Y "&TEXT($F$28,"+0;-0")&"bp, so the gap to Treasuries moved "&TEXT($G$28,"+0;-0")&"bp"&IF(ISNUMBER($H$28)," (pass-through "&TEXT($H$28,"0.00")&"x)","")&". History (2y beta "&TEXT($I$28,"0.00")&") would have predicted "&TEXT($J$28,"+0;-0")&"bp; the surprise is "&TEXT($K$28,"+0;-0")&"bp. YTD: "&TEXT($L$28,"+0;-0")&"bp against "&TEXT($M$28,"+0;-0")&"bp, gap "&TEXT($N$28,"+0;-0")&"bp"&IF(ISNUMBER($O$28)," (pass-through "&TEXT($O$28,"0.00")&"x)","")&". "&IF($K$28<-5,"The curve did better than its own history — absorbed.",IF($K$28>5,"The curve did worse than its own history — imported.","Moved in line with its own history.")),"")
A31: EM ASIA
A32: Country | B32: Region | C32: Level | D32: In avg | E32: 1M: Total move (bp) | F32: 1M: US-driven: d UST 10Y (bp) | G32: 1M: Intrinsic: d gap to UST (bp) | H32: 1M: Pass-through (total / US) | I32: 1M: Beta to UST 10Y (2y) | J32: 1M: Predicted by beta (bp) | K32: 1M: Surprise: actual less predicted (bp) | L32: YTD: Total move (bp) | M32: YTD: US-driven: d UST 10Y (bp) | N32: YTD: Intrinsic: d gap to UST (bp) | O32: YTD: Pass-through (total / US) | P32: YTD: Beta to UST 10Y (2y) | Q32: YTD: Predicted by beta (bp) | R32: YTD: Surprise: actual less predicted (bp)
A33: China | B33: EM Asia | C33: =INDEX(HIST_D!$AT$8:$AT$791,1) | D33: yes | E33: =IFERROR((INDEX(HIST_D!$AT$8:$AT$791,1)-INDEX(HIST_D!$AT$8:$AT$791,Control!$B$10))*100,"") | F33: =IFERROR((INDEX(HIST_D!$F$8:$F$791,1)-INDEX(HIST_D!$F$8:$F$791,Control!$B$10))*100,"") | G33: =IFERROR(E33-F33,"") | H33: =IFERROR(IF(ABS(F33)<Control!$B$13,"n/m",E33/F33),"n/m") | I33: =IFERROR(SLOPE(HIST_D!$DK$8:INDEX(HIST_D!$DK$8:$DK$791,Control!$B$12),HIST_D!$CV$8:INDEX(HIST_D!$CV$8:$CV$791,Control!$B$12)),"") | J33: =IFERROR(I33*(INDEX(HIST_D!$F$8:$F$791,1)-INDEX(HIST_D!$F$8:$F$791,Control!$B$10))*100,"") | K33: =IFERROR(E33-J33,"") | L33: =IFERROR((INDEX(HIST_D!$AT$8:$AT$791,1)-INDEX(HIST_D!$AT$8:$AT$791,Control!$B$11))*100,"") | M33: =IFERROR((INDEX(HIST_D!$F$8:$F$791,1)-INDEX(HIST_D!$F$8:$F$791,Control!$B$11))*100,"") | N33: =IFERROR(L33-M33,"") | O33: =IFERROR(IF(ABS(M33)<Control!$B$13,"n/m",L33/M33),"n/m") | P33: =IFERROR(SLOPE(HIST_D!$DK$8:INDEX(HIST_D!$DK$8:$DK$791,Control!$B$12),HIST_D!$CV$8:INDEX(HIST_D!$CV$8:$CV$791,Control!$B$12)),"") | Q33: =IFERROR(P33*(INDEX(HIST_D!$F$8:$F$791,1)-INDEX(HIST_D!$F$8:$F$791,Control!$B$11))*100,"") | R33: =IFERROR(L33-Q33,"")
A34: India | B34: EM Asia | C34: =INDEX(HIST_D!$AU$8:$AU$791,1) | D34: yes | E34: =IFERROR((INDEX(HIST_D!$AU$8:$AU$791,1)-INDEX(HIST_D!$AU$8:$AU$791,Control!$B$10))*100,"") | F34: =IFERROR((INDEX(HIST_D!$F$8:$F$791,1)-INDEX(HIST_D!$F$8:$F$791,Control!$B$10))*100,"") | G34: =IFERROR(E34-F34,"") | H34: =IFERROR(IF(ABS(F34)<Control!$B$13,"n/m",E34/F34),"n/m") | I34: =IFERROR(SLOPE(HIST_D!$DL$8:INDEX(HIST_D!$DL$8:$DL$791,Control!$B$12),HIST_D!$CV$8:INDEX(HIST_D!$CV$8:$CV$791,Control!$B$12)),"") | J34: =IFERROR(I34*(INDEX(HIST_D!$F$8:$F$791,1)-INDEX(HIST_D!$F$8:$F$791,Control!$B$10))*100,"") | K34: =IFERROR(E34-J34,"") | L34: =IFERROR((INDEX(HIST_D!$AU$8:$AU$791,1)-INDEX(HIST_D!$AU$8:$AU$791,Control!$B$11))*100,"") | M34: =IFERROR((INDEX(HIST_D!$F$8:$F$791,1)-INDEX(HIST_D!$F$8:$F$791,Control!$B$11))*100,"") | N34: =IFERROR(L34-M34,"") | O34: =IFERROR(IF(ABS(M34)<Control!$B$13,"n/m",L34/M34),"n/m") | P34: =IFERROR(SLOPE(HIST_D!$DL$8:INDEX(HIST_D!$DL$8:$DL$791,Control!$B$12),HIST_D!$CV$8:INDEX(HIST_D!$CV$8:$CV$791,Control!$B$12)),"") | Q34: =IFERROR(P34*(INDEX(HIST_D!$F$8:$F$791,1)-INDEX(HIST_D!$F$8:$F$791,Control!$B$11))*100,"") | R34: =IFERROR(L34-Q34,"") | S34: no sovereign USD debt, no CDS — rates and FX only
A35: Indonesia | B35: EM Asia | C35: =INDEX(HIST_D!$AV$8:$AV$791,1) | D35: yes | E35: =IFERROR((INDEX(HIST_D!$AV$8:$AV$791,1)-INDEX(HIST_D!$AV$8:$AV$791,Control!$B$10))*100,"") | F35: =IFERROR((INDEX(HIST_D!$F$8:$F$791,1)-INDEX(HIST_D!$F$8:$F$791,Control!$B$10))*100,"") | G35: =IFERROR(E35-F35,"") | H35: =IFERROR(IF(ABS(F35)<Control!$B$13,"n/m",E35/F35),"n/m") | I35: =IFERROR(SLOPE(HIST_D!$DM$8:INDEX(HIST_D!$DM$8:$DM$791,Control!$B$12),HIST_D!$CV$8:INDEX(HIST_D!$CV$8:$CV$791,Control!$B$12)),"") | J35: =IFERROR(I35*(INDEX(HIST_D!$F$8:$F$791,1)-INDEX(HIST_D!$F$8:$F$791,Control!$B$10))*100,"") | K35: =IFERROR(E35-J35,"") | L35: =IFERROR((INDEX(HIST_D!$AV$8:$AV$791,1)-INDEX(HIST_D!$AV$8:$AV$791,Control!$B$11))*100,"") | M35: =IFERROR((INDEX(HIST_D!$F$8:$F$791,1)-INDEX(HIST_D!$F$8:$F$791,Control!$B$11))*100,"") | N35: =IFERROR(L35-M35,"") | O35: =IFERROR(IF(ABS(M35)<Control!$B$13,"n/m",L35/M35),"n/m") | P35: =IFERROR(SLOPE(HIST_D!$DM$8:INDEX(HIST_D!$DM$8:$DM$791,Control!$B$12),HIST_D!$CV$8:INDEX(HIST_D!$CV$8:$CV$791,Control!$B$12)),"") | Q35: =IFERROR(P35*(INDEX(HIST_D!$F$8:$F$791,1)-INDEX(HIST_D!$F$8:$F$791,Control!$B$11))*100,"") | R35: =IFERROR(L35-Q35,"")
A36: Korea | B36: EM Asia | C36: =INDEX(HIST_D!$AW$8:$AW$791,1) | D36: yes | E36: =IFERROR((INDEX(HIST_D!$AW$8:$AW$791,1)-INDEX(HIST_D!$AW$8:$AW$791,Control!$B$10))*100,"") | F36: =IFERROR((INDEX(HIST_D!$F$8:$F$791,1)-INDEX(HIST_D!$F$8:$F$791,Control!$B$10))*100,"") | G36: =IFERROR(E36-F36,"") | H36: =IFERROR(IF(ABS(F36)<Control!$B$13,"n/m",E36/F36),"n/m") | I36: =IFERROR(SLOPE(HIST_D!$DN$8:INDEX(HIST_D!$DN$8:$DN$791,Control!$B$12),HIST_D!$CV$8:INDEX(HIST_D!$CV$8:$CV$791,Control!$B$12)),"") | J36: =IFERROR(I36*(INDEX(HIST_D!$F$8:$F$791,1)-INDEX(HIST_D!$F$8:$F$791,Control!$B$10))*100,"") | K36: =IFERROR(E36-J36,"") | L36: =IFERROR((INDEX(HIST_D!$AW$8:$AW$791,1)-INDEX(HIST_D!$AW$8:$AW$791,Control!$B$11))*100,"") | M36: =IFERROR((INDEX(HIST_D!$F$8:$F$791,1)-INDEX(HIST_D!$F$8:$F$791,Control!$B$11))*100,"") | N36: =IFERROR(L36-M36,"") | O36: =IFERROR(IF(ABS(M36)<Control!$B$13,"n/m",L36/M36),"n/m") | P36: =IFERROR(SLOPE(HIST_D!$DN$8:INDEX(HIST_D!$DN$8:$DN$791,Control!$B$12),HIST_D!$CV$8:INDEX(HIST_D!$CV$8:$CV$791,Control!$B$12)),"") | Q36: =IFERROR(P36*(INDEX(HIST_D!$F$8:$F$791,1)-INDEX(HIST_D!$F$8:$F$791,Control!$B$11))*100,"") | R36: =IFERROR(L36-Q36,"")
A37: Thailand | B37: EM Asia | C37: =INDEX(HIST_D!$AX$8:$AX$791,1) | D37: yes | E37: =IFERROR((INDEX(HIST_D!$AX$8:$AX$791,1)-INDEX(HIST_D!$AX$8:$AX$791,Control!$B$10))*100,"") | F37: =IFERROR((INDEX(HIST_D!$F$8:$F$791,1)-INDEX(HIST_D!$F$8:$F$791,Control!$B$10))*100,"") | G37: =IFERROR(E37-F37,"") | H37: =IFERROR(IF(ABS(F37)<Control!$B$13,"n/m",E37/F37),"n/m") | I37: =IFERROR(SLOPE(HIST_D!$DO$8:INDEX(HIST_D!$DO$8:$DO$791,Control!$B$12),HIST_D!$CV$8:INDEX(HIST_D!$CV$8:$CV$791,Control!$B$12)),"") | J37: =IFERROR(I37*(INDEX(HIST_D!$F$8:$F$791,1)-INDEX(HIST_D!$F$8:$F$791,Control!$B$10))*100,"") | K37: =IFERROR(E37-J37,"") | L37: =IFERROR((INDEX(HIST_D!$AX$8:$AX$791,1)-INDEX(HIST_D!$AX$8:$AX$791,Control!$B$11))*100,"") | M37: =IFERROR((INDEX(HIST_D!$F$8:$F$791,1)-INDEX(HIST_D!$F$8:$F$791,Control!$B$11))*100,"") | N37: =IFERROR(L37-M37,"") | O37: =IFERROR(IF(ABS(M37)<Control!$B$13,"n/m",L37/M37),"n/m") | P37: =IFERROR(SLOPE(HIST_D!$DO$8:INDEX(HIST_D!$DO$8:$DO$791,Control!$B$12),HIST_D!$CV$8:INDEX(HIST_D!$CV$8:$CV$791,Control!$B$12)),"") | Q37: =IFERROR(P37*(INDEX(HIST_D!$F$8:$F$791,1)-INDEX(HIST_D!$F$8:$F$791,Control!$B$11))*100,"") | R37: =IFERROR(L37-Q37,"")
A38: Malaysia | B38: EM Asia | C38: =INDEX(HIST_D!$AY$8:$AY$791,1) | D38: yes | E38: =IFERROR((INDEX(HIST_D!$AY$8:$AY$791,1)-INDEX(HIST_D!$AY$8:$AY$791,Control!$B$10))*100,"") | F38: =IFERROR((INDEX(HIST_D!$F$8:$F$791,1)-INDEX(HIST_D!$F$8:$F$791,Control!$B$10))*100,"") | G38: =IFERROR(E38-F38,"") | H38: =IFERROR(IF(ABS(F38)<Control!$B$13,"n/m",E38/F38),"n/m") | I38: =IFERROR(SLOPE(HIST_D!$DP$8:INDEX(HIST_D!$DP$8:$DP$791,Control!$B$12),HIST_D!$CV$8:INDEX(HIST_D!$CV$8:$CV$791,Control!$B$12)),"") | J38: =IFERROR(I38*(INDEX(HIST_D!$F$8:$F$791,1)-INDEX(HIST_D!$F$8:$F$791,Control!$B$10))*100,"") | K38: =IFERROR(E38-J38,"") | L38: =IFERROR((INDEX(HIST_D!$AY$8:$AY$791,1)-INDEX(HIST_D!$AY$8:$AY$791,Control!$B$11))*100,"") | M38: =IFERROR((INDEX(HIST_D!$F$8:$F$791,1)-INDEX(HIST_D!$F$8:$F$791,Control!$B$11))*100,"") | N38: =IFERROR(L38-M38,"") | O38: =IFERROR(IF(ABS(M38)<Control!$B$13,"n/m",L38/M38),"n/m") | P38: =IFERROR(SLOPE(HIST_D!$DP$8:INDEX(HIST_D!$DP$8:$DP$791,Control!$B$12),HIST_D!$CV$8:INDEX(HIST_D!$CV$8:$CV$791,Control!$B$12)),"") | Q38: =IFERROR(P38*(INDEX(HIST_D!$F$8:$F$791,1)-INDEX(HIST_D!$F$8:$F$791,Control!$B$11))*100,"") | R38: =IFERROR(L38-Q38,"")
A39: Philippines | B39: EM Asia | C39: =INDEX(HIST_D!$AZ$8:$AZ$791,1) | D39: yes | E39: =IFERROR((INDEX(HIST_D!$AZ$8:$AZ$791,1)-INDEX(HIST_D!$AZ$8:$AZ$791,Control!$B$10))*100,"") | F39: =IFERROR((INDEX(HIST_D!$F$8:$F$791,1)-INDEX(HIST_D!$F$8:$F$791,Control!$B$10))*100,"") | G39: =IFERROR(E39-F39,"") | H39: =IFERROR(IF(ABS(F39)<Control!$B$13,"n/m",E39/F39),"n/m") | I39: =IFERROR(SLOPE(HIST_D!$DQ$8:INDEX(HIST_D!$DQ$8:$DQ$791,Control!$B$12),HIST_D!$CV$8:INDEX(HIST_D!$CV$8:$CV$791,Control!$B$12)),"") | J39: =IFERROR(I39*(INDEX(HIST_D!$F$8:$F$791,1)-INDEX(HIST_D!$F$8:$F$791,Control!$B$10))*100,"") | K39: =IFERROR(E39-J39,"") | L39: =IFERROR((INDEX(HIST_D!$AZ$8:$AZ$791,1)-INDEX(HIST_D!$AZ$8:$AZ$791,Control!$B$11))*100,"") | M39: =IFERROR((INDEX(HIST_D!$F$8:$F$791,1)-INDEX(HIST_D!$F$8:$F$791,Control!$B$11))*100,"") | N39: =IFERROR(L39-M39,"") | O39: =IFERROR(IF(ABS(M39)<Control!$B$13,"n/m",L39/M39),"n/m") | P39: =IFERROR(SLOPE(HIST_D!$DQ$8:INDEX(HIST_D!$DQ$8:$DQ$791,Control!$B$12),HIST_D!$CV$8:INDEX(HIST_D!$CV$8:$CV$791,Control!$B$12)),"") | Q39: =IFERROR(P39*(INDEX(HIST_D!$F$8:$F$791,1)-INDEX(HIST_D!$F$8:$F$791,Control!$B$11))*100,"") | R39: =IFERROR(L39-Q39,"")
A40: EM Asia average | B40: n=7 | E40: =IFERROR(AVERAGE(E33,E34,E35,E36,E37,E38,E39),"") | F40: =IFERROR(AVERAGE(F33,F34,F35,F36,F37,F38,F39),"") | G40: =IFERROR(AVERAGE(G33,G34,G35,G36,G37,G38,G39),"") | H40: =IFERROR(IF(ABS(F40)<Control!$B$13,"n/m",E40/F40),"n/m") | I40: =IFERROR(AVERAGE(I33,I34,I35,I36,I37,I38,I39),"") | J40: =IFERROR(AVERAGE(J33,J34,J35,J36,J37,J38,J39),"") | K40: =IFERROR(AVERAGE(K33,K34,K35,K36,K37,K38,K39),"") | L40: =IFERROR(AVERAGE(L33,L34,L35,L36,L37,L38,L39),"") | M40: =IFERROR(AVERAGE(M33,M34,M35,M36,M37,M38,M39),"") | N40: =IFERROR(AVERAGE(N33,N34,N35,N36,N37,N38,N39),"") | O40: =IFERROR(IF(ABS(M40)<Control!$B$13,"n/m",L40/M40),"n/m") | P40: =IFERROR(AVERAGE(P33,P34,P35,P36,P37,P38,P39),"") | Q40: =IFERROR(AVERAGE(Q33,Q34,Q35,Q36,Q37,Q38,Q39),"") | R40: =IFERROR(AVERAGE(R33,R34,R35,R36,R37,R38,R39),"")
A41: =IFERROR("EM Asia: local 10Y "&TEXT($E$40,"+0;-0")&"bp on the month against UST 10Y "&TEXT($F$40,"+0;-0")&"bp, so the gap to Treasuries moved "&TEXT($G$40,"+0;-0")&"bp"&IF(ISNUMBER($H$40)," (pass-through "&TEXT($H$40,"0.00")&"x)","")&". History (2y beta "&TEXT($I$40,"0.00")&") would have predicted "&TEXT($J$40,"+0;-0")&"bp; the surprise is "&TEXT($K$40,"+0;-0")&"bp. YTD: "&TEXT($L$40,"+0;-0")&"bp against "&TEXT($M$40,"+0;-0")&"bp, gap "&TEXT($N$40,"+0;-0")&"bp"&IF(ISNUMBER($O$40)," (pass-through "&TEXT($O$40,"0.00")&"x)","")&". "&IF($K$40<-5,"The curve did better than its own history — absorbed.",IF($K$40>5,"The curve did worse than its own history — imported.","Moved in line with its own history.")),"")
A43: EM AVERAGE AND MEMO
A44: Country | B44: Region | C44: Level | D44: In avg | E44: 1M: Total move (bp) | F44: 1M: US-driven: d UST 10Y (bp) | G44: 1M: Intrinsic: d gap to UST (bp) | H44: 1M: Pass-through (total / US) | I44: 1M: Beta to UST 10Y (2y) | J44: 1M: Predicted by beta (bp) | K44: 1M: Surprise: actual less predicted (bp) | L44: YTD: Total move (bp) | M44: YTD: US-driven: d UST 10Y (bp) | N44: YTD: Intrinsic: d gap to UST (bp) | O44: YTD: Pass-through (total / US) | P44: YTD: Beta to UST 10Y (2y) | Q44: YTD: Predicted by beta (bp) | R44: YTD: Surprise: actual less predicted (bp)
A45: EM average (all flagged) | B45: n=18 | E45: =IFERROR(AVERAGE(E6,E7,E8,E9,E10,E16,E17,E18,E19,E26,E27,E33,E34,E35,E36,E37,E38,E39),"") | F45: =IFERROR(AVERAGE(F6,F7,F8,F9,F10,F16,F17,F18,F19,F26,F27,F33,F34,F35,F36,F37,F38,F39),"") | G45: =IFERROR(AVERAGE(G6,G7,G8,G9,G10,G16,G17,G18,G19,G26,G27,G33,G34,G35,G36,G37,G38,G39),"") | H45: =IFERROR(IF(ABS(F45)<Control!$B$13,"n/m",E45/F45),"n/m") | I45: =IFERROR(AVERAGE(I6,I7,I8,I9,I10,I16,I17,I18,I19,I26,I27,I33,I34,I35,I36,I37,I38,I39),"") | J45: =IFERROR(AVERAGE(J6,J7,J8,J9,J10,J16,J17,J18,J19,J26,J27,J33,J34,J35,J36,J37,J38,J39),"") | K45: =IFERROR(AVERAGE(K6,K7,K8,K9,K10,K16,K17,K18,K19,K26,K27,K33,K34,K35,K36,K37,K38,K39),"") | L45: =IFERROR(AVERAGE(L6,L7,L8,L9,L10,L16,L17,L18,L19,L26,L27,L33,L34,L35,L36,L37,L38,L39),"") | M45: =IFERROR(AVERAGE(M6,M7,M8,M9,M10,M16,M17,M18,M19,M26,M27,M33,M34,M35,M36,M37,M38,M39),"") | N45: =IFERROR(AVERAGE(N6,N7,N8,N9,N10,N16,N17,N18,N19,N26,N27,N33,N34,N35,N36,N37,N38,N39),"") | O45: =IFERROR(IF(ABS(M45)<Control!$B$13,"n/m",L45/M45),"n/m") | P45: =IFERROR(AVERAGE(P6,P7,P8,P9,P10,P16,P17,P18,P19,P26,P27,P33,P34,P35,P36,P37,P38,P39),"") | Q45: =IFERROR(AVERAGE(Q6,Q7,Q8,Q9,Q10,Q16,Q17,Q18,Q19,Q26,Q27,Q33,Q34,Q35,Q36,Q37,Q38,Q39),"") | R45: =IFERROR(AVERAGE(R6,R7,R8,R9,R10,R16,R17,R18,R19,R26,R27,R33,R34,R35,R36,R37,R38,R39),"")
A46: South Africa | B46: (memo) | C46: =INDEX(HIST_D!$BA$8:$BA$791,1) | D46: no | E46: =IFERROR((INDEX(HIST_D!$BA$8:$BA$791,1)-INDEX(HIST_D!$BA$8:$BA$791,Control!$B$10))*100,"") | F46: =IFERROR((INDEX(HIST_D!$F$8:$F$791,1)-INDEX(HIST_D!$F$8:$F$791,Control!$B$10))*100,"") | G46: =IFERROR(E46-F46,"") | H46: =IFERROR(IF(ABS(F46)<Control!$B$13,"n/m",E46/F46),"n/m") | I46: =IFERROR(SLOPE(HIST_D!$DR$8:INDEX(HIST_D!$DR$8:$DR$791,Control!$B$12),HIST_D!$CV$8:INDEX(HIST_D!$CV$8:$CV$791,Control!$B$12)),"") | J46: =IFERROR(I46*(INDEX(HIST_D!$F$8:$F$791,1)-INDEX(HIST_D!$F$8:$F$791,Control!$B$10))*100,"") | K46: =IFERROR(E46-J46,"") | L46: =IFERROR((INDEX(HIST_D!$BA$8:$BA$791,1)-INDEX(HIST_D!$BA$8:$BA$791,Control!$B$11))*100,"") | M46: =IFERROR((INDEX(HIST_D!$F$8:$F$791,1)-INDEX(HIST_D!$F$8:$F$791,Control!$B$11))*100,"") | N46: =IFERROR(L46-M46,"") | O46: =IFERROR(IF(ABS(M46)<Control!$B$13,"n/m",L46/M46),"n/m") | P46: =IFERROR(SLOPE(HIST_D!$DR$8:INDEX(HIST_D!$DR$8:$DR$791,Control!$B$12),HIST_D!$CV$8:INDEX(HIST_D!$CV$8:$CV$791,Control!$B$12)),"") | Q46: =IFERROR(P46*(INDEX(HIST_D!$F$8:$F$791,1)-INDEX(HIST_D!$F$8:$F$791,Control!$B$11))*100,"") | R46: =IFERROR(L46-Q46,"") | S46: not in any of the four regions you named; shown as a memo line, in no average
A47: =IFERROR("EM: local 10Y "&TEXT($E$45,"+0;-0")&"bp on the month against UST 10Y "&TEXT($F$45,"+0;-0")&"bp, so the gap to Treasuries moved "&TEXT($G$45,"+0;-0")&"bp"&IF(ISNUMBER($H$45)," (pass-through "&TEXT($H$45,"0.00")&"x)","")&". History (2y beta "&TEXT($I$45,"0.00")&") would have predicted "&TEXT($J$45,"+0;-0")&"bp; the surprise is "&TEXT($K$45,"+0;-0")&"bp. YTD: "&TEXT($L$45,"+0;-0")&"bp against "&TEXT($M$45,"+0;-0")&"bp, gap "&TEXT($N$45,"+0;-0")&"bp"&IF(ISNUMBER($O$45)," (pass-through "&TEXT($O$45,"0.00")&"x)","")&". "&IF($K$45<-5,"The curve did better than its own history — absorbed.",IF($K$45>5,"The curve did worse than its own history — imported.","Moved in line with its own history.")),"")

Sheet FX
A1: EM CURRENCIES — return on the currency, by country and region
A2: Return on the EM currency (prior/current - 1, so positive = EM strength) = -(DXY return) + return ex-dollar. US-driven is the dollar under a beta of one; intrinsic is what is left after the dollar. Pass-through = total / US-driven.
A4: LATAM
A5: Country | B5: Region | C5: Level | D5: In avg | E5: 1M: Total: return on EM ccy | F5: 1M: US-driven: -(DXY return) | G5: 1M: Intrinsic: return ex-dollar | H5: 1M: Pass-through (total / US) | I5: 1M: Beta to DXY (2y) | J5: 1M: Predicted by beta | K5: 1M: Surprise: actual less predicted | L5: YTD: Total: return on EM ccy | M5: YTD: US-driven: -(DXY return) | N5: YTD: Intrinsic: return ex-dollar | O5: YTD: Pass-through (total / US) | P5: YTD: Beta to DXY (2y) | Q5: YTD: Predicted by beta | R5: YTD: Surprise: actual less predicted
A6: Brazil | B6: LatAm | C6: =INDEX(HIST_D!$N$8:$N$791,1) | D6: yes | E6: =IFERROR((INDEX(HIST_D!$N$8:$N$791,Control!$B$10)/INDEX(HIST_D!$N$8:$N$791,1)-1),"") | F6: =IFERROR(-(INDEX(HIST_D!$K$8:$K$791,1)/INDEX(HIST_D!$K$8:$K$791,Control!$B$10)-1),"") | G6: =IFERROR(E6-F6,"") | H6: =IFERROR(IF(ABS(F6)<0.005,"n/m",E6/F6),"n/m") | I6: =IFERROR(SLOPE(HIST_D!$DS$8:INDEX(HIST_D!$DS$8:$DS$791,Control!$B$12),HIST_D!$CX$8:INDEX(HIST_D!$CX$8:$CX$791,Control!$B$12)),"") | J6: =IFERROR(I6*(INDEX(HIST_D!$K$8:$K$791,1)/INDEX(HIST_D!$K$8:$K$791,Control!$B$10)-1),"") | K6: =IFERROR(E6-J6,"") | L6: =IFERROR((INDEX(HIST_D!$N$8:$N$791,Control!$B$11)/INDEX(HIST_D!$N$8:$N$791,1)-1),"") | M6: =IFERROR(-(INDEX(HIST_D!$K$8:$K$791,1)/INDEX(HIST_D!$K$8:$K$791,Control!$B$11)-1),"") | N6: =IFERROR(L6-M6,"") | O6: =IFERROR(IF(ABS(M6)<0.005,"n/m",L6/M6),"n/m") | P6: =IFERROR(SLOPE(HIST_D!$DS$8:INDEX(HIST_D!$DS$8:$DS$791,Control!$B$12),HIST_D!$CX$8:INDEX(HIST_D!$CX$8:$CX$791,Control!$B$12)),"") | Q6: =IFERROR(P6*(INDEX(HIST_D!$K$8:$K$791,1)/INDEX(HIST_D!$K$8:$K$791,Control!$B$11)-1),"") | R6: =IFERROR(L6-Q6,"")
A7: Mexico | B7: LatAm | C7: =INDEX(HIST_D!$O$8:$O$791,1) | D7: yes | E7: =IFERROR((INDEX(HIST_D!$O$8:$O$791,Control!$B$10)/INDEX(HIST_D!$O$8:$O$791,1)-1),"") | F7: =IFERROR(-(INDEX(HIST_D!$K$8:$K$791,1)/INDEX(HIST_D!$K$8:$K$791,Control!$B$10)-1),"") | G7: =IFERROR(E7-F7,"") | H7: =IFERROR(IF(ABS(F7)<0.005,"n/m",E7/F7),"n/m") | I7: =IFERROR(SLOPE(HIST_D!$DT$8:INDEX(HIST_D!$DT$8:$DT$791,Control!$B$12),HIST_D!$CX$8:INDEX(HIST_D!$CX$8:$CX$791,Control!$B$12)),"") | J7: =IFERROR(I7*(INDEX(HIST_D!$K$8:$K$791,1)/INDEX(HIST_D!$K$8:$K$791,Control!$B$10)-1),"") | K7: =IFERROR(E7-J7,"") | L7: =IFERROR((INDEX(HIST_D!$O$8:$O$791,Control!$B$11)/INDEX(HIST_D!$O$8:$O$791,1)-1),"") | M7: =IFERROR(-(INDEX(HIST_D!$K$8:$K$791,1)/INDEX(HIST_D!$K$8:$K$791,Control!$B$11)-1),"") | N7: =IFERROR(L7-M7,"") | O7: =IFERROR(IF(ABS(M7)<0.005,"n/m",L7/M7),"n/m") | P7: =IFERROR(SLOPE(HIST_D!$DT$8:INDEX(HIST_D!$DT$8:$DT$791,Control!$B$12),HIST_D!$CX$8:INDEX(HIST_D!$CX$8:$CX$791,Control!$B$12)),"") | Q7: =IFERROR(P7*(INDEX(HIST_D!$K$8:$K$791,1)/INDEX(HIST_D!$K$8:$K$791,Control!$B$11)-1),"") | R7: =IFERROR(L7-Q7,"")
A8: Chile | B8: LatAm | C8: =INDEX(HIST_D!$P$8:$P$791,1) | D8: yes | E8: =IFERROR((INDEX(HIST_D!$P$8:$P$791,Control!$B$10)/INDEX(HIST_D!$P$8:$P$791,1)-1),"") | F8: =IFERROR(-(INDEX(HIST_D!$K$8:$K$791,1)/INDEX(HIST_D!$K$8:$K$791,Control!$B$10)-1),"") | G8: =IFERROR(E8-F8,"") | H8: =IFERROR(IF(ABS(F8)<0.005,"n/m",E8/F8),"n/m") | I8: =IFERROR(SLOPE(HIST_D!$DU$8:INDEX(HIST_D!$DU$8:$DU$791,Control!$B$12),HIST_D!$CX$8:INDEX(HIST_D!$CX$8:$CX$791,Control!$B$12)),"") | J8: =IFERROR(I8*(INDEX(HIST_D!$K$8:$K$791,1)/INDEX(HIST_D!$K$8:$K$791,Control!$B$10)-1),"") | K8: =IFERROR(E8-J8,"") | L8: =IFERROR((INDEX(HIST_D!$P$8:$P$791,Control!$B$11)/INDEX(HIST_D!$P$8:$P$791,1)-1),"") | M8: =IFERROR(-(INDEX(HIST_D!$K$8:$K$791,1)/INDEX(HIST_D!$K$8:$K$791,Control!$B$11)-1),"") | N8: =IFERROR(L8-M8,"") | O8: =IFERROR(IF(ABS(M8)<0.005,"n/m",L8/M8),"n/m") | P8: =IFERROR(SLOPE(HIST_D!$DU$8:INDEX(HIST_D!$DU$8:$DU$791,Control!$B$12),HIST_D!$CX$8:INDEX(HIST_D!$CX$8:$CX$791,Control!$B$12)),"") | Q8: =IFERROR(P8*(INDEX(HIST_D!$K$8:$K$791,1)/INDEX(HIST_D!$K$8:$K$791,Control!$B$11)-1),"") | R8: =IFERROR(L8-Q8,"")
A9: Colombia | B9: LatAm | C9: =INDEX(HIST_D!$Q$8:$Q$791,1) | D9: yes | E9: =IFERROR((INDEX(HIST_D!$Q$8:$Q$791,Control!$B$10)/INDEX(HIST_D!$Q$8:$Q$791,1)-1),"") | F9: =IFERROR(-(INDEX(HIST_D!$K$8:$K$791,1)/INDEX(HIST_D!$K$8:$K$791,Control!$B$10)-1),"") | G9: =IFERROR(E9-F9,"") | H9: =IFERROR(IF(ABS(F9)<0.005,"n/m",E9/F9),"n/m") | I9: =IFERROR(SLOPE(HIST_D!$DV$8:INDEX(HIST_D!$DV$8:$DV$791,Control!$B$12),HIST_D!$CX$8:INDEX(HIST_D!$CX$8:$CX$791,Control!$B$12)),"") | J9: =IFERROR(I9*(INDEX(HIST_D!$K$8:$K$791,1)/INDEX(HIST_D!$K$8:$K$791,Control!$B$10)-1),"") | K9: =IFERROR(E9-J9,"") | L9: =IFERROR((INDEX(HIST_D!$Q$8:$Q$791,Control!$B$11)/INDEX(HIST_D!$Q$8:$Q$791,1)-1),"") | M9: =IFERROR(-(INDEX(HIST_D!$K$8:$K$791,1)/INDEX(HIST_D!$K$8:$K$791,Control!$B$11)-1),"") | N9: =IFERROR(L9-M9,"") | O9: =IFERROR(IF(ABS(M9)<0.005,"n/m",L9/M9),"n/m") | P9: =IFERROR(SLOPE(HIST_D!$DV$8:INDEX(HIST_D!$DV$8:$DV$791,Control!$B$12),HIST_D!$CX$8:INDEX(HIST_D!$CX$8:$CX$791,Control!$B$12)),"") | Q9: =IFERROR(P9*(INDEX(HIST_D!$K$8:$K$791,1)/INDEX(HIST_D!$K$8:$K$791,Control!$B$11)-1),"") | R9: =IFERROR(L9-Q9,"")
A10: Peru | B10: LatAm | C10: =INDEX(HIST_D!$R$8:$R$791,1) | D10: yes | E10: =IFERROR((INDEX(HIST_D!$R$8:$R$791,Control!$B$10)/INDEX(HIST_D!$R$8:$R$791,1)-1),"") | F10: =IFERROR(-(INDEX(HIST_D!$K$8:$K$791,1)/INDEX(HIST_D!$K$8:$K$791,Control!$B$10)-1),"") | G10: =IFERROR(E10-F10,"") | H10: =IFERROR(IF(ABS(F10)<0.005,"n/m",E10/F10),"n/m") | I10: =IFERROR(SLOPE(HIST_D!$DW$8:INDEX(HIST_D!$DW$8:$DW$791,Control!$B$12),HIST_D!$CX$8:INDEX(HIST_D!$CX$8:$CX$791,Control!$B$12)),"") | J10: =IFERROR(I10*(INDEX(HIST_D!$K$8:$K$791,1)/INDEX(HIST_D!$K$8:$K$791,Control!$B$10)-1),"") | K10: =IFERROR(E10-J10,"") | L10: =IFERROR((INDEX(HIST_D!$R$8:$R$791,Control!$B$11)/INDEX(HIST_D!$R$8:$R$791,1)-1),"") | M10: =IFERROR(-(INDEX(HIST_D!$K$8:$K$791,1)/INDEX(HIST_D!$K$8:$K$791,Control!$B$11)-1),"") | N10: =IFERROR(L10-M10,"") | O10: =IFERROR(IF(ABS(M10)<0.005,"n/m",L10/M10),"n/m") | P10: =IFERROR(SLOPE(HIST_D!$DW$8:INDEX(HIST_D!$DW$8:$DW$791,Control!$B$12),HIST_D!$CX$8:INDEX(HIST_D!$CX$8:$CX$791,Control!$B$12)),"") | Q10: =IFERROR(P10*(INDEX(HIST_D!$K$8:$K$791,1)/INDEX(HIST_D!$K$8:$K$791,Control!$B$11)-1),"") | R10: =IFERROR(L10-Q10,"")
A11: LatAm average | B11: n=5 | E11: =IFERROR(AVERAGE(E6,E7,E8,E9,E10),"") | F11: =IFERROR(AVERAGE(F6,F7,F8,F9,F10),"") | G11: =IFERROR(AVERAGE(G6,G7,G8,G9,G10),"") | H11: =IFERROR(IF(ABS(F11)<0.005,"n/m",E11/F11),"n/m") | I11: =IFERROR(AVERAGE(I6,I7,I8,I9,I10),"") | J11: =IFERROR(AVERAGE(J6,J7,J8,J9,J10),"") | K11: =IFERROR(AVERAGE(K6,K7,K8,K9,K10),"") | L11: =IFERROR(AVERAGE(L6,L7,L8,L9,L10),"") | M11: =IFERROR(AVERAGE(M6,M7,M8,M9,M10),"") | N11: =IFERROR(AVERAGE(N6,N7,N8,N9,N10),"") | O11: =IFERROR(IF(ABS(M11)<0.005,"n/m",L11/M11),"n/m") | P11: =IFERROR(AVERAGE(P6,P7,P8,P9,P10),"") | Q11: =IFERROR(AVERAGE(Q6,Q7,Q8,Q9,Q10),"") | R11: =IFERROR(AVERAGE(R6,R7,R8,R9,R10),"")
A12: =IFERROR("LatAm: the currency returned "&TEXT($E$11,"+0.0%;-0.0%")&" on the month; a beta-of-one to the dollar implies "&TEXT($F$11,"+0.0%;-0.0%")&", so "&TEXT($G$11,"+0.0%;-0.0%")&" is ex-dollar"&IF(ISNUMBER($H$11)," (pass-through "&TEXT($H$11,"0.00")&"x)","")&". Against its 2y beta to DXY of "&TEXT($I$11,"0.00")&" the surprise is "&TEXT($K$11,"+0.0%;-0.0%")&". YTD: "&TEXT($L$11,"+0.0%;-0.0%")&", of which "&TEXT($N$11,"+0.0%;-0.0%")&" ex-dollar. "&IF($K$11>0.005,"Stronger than the dollar relationship implies — intrinsic support.",IF($K$11<-0.005,"Weaker than the dollar relationship implies — intrinsic pressure.","In line with the dollar; nothing EM-specific here.")),"")
A14: EM EUROPE
A15: Country | B15: Region | C15: Level | D15: In avg | E15: 1M: Total: return on EM ccy | F15: 1M: US-driven: -(DXY return) | G15: 1M: Intrinsic: return ex-dollar | H15: 1M: Pass-through (total / US) | I15: 1M: Beta to DXY (2y) | J15: 1M: Predicted by beta | K15: 1M: Surprise: actual less predicted | L15: YTD: Total: return on EM ccy | M15: YTD: US-driven: -(DXY return) | N15: YTD: Intrinsic: return ex-dollar | O15: YTD: Pass-through (total / US) | P15: YTD: Beta to DXY (2y) | Q15: YTD: Predicted by beta | R15: YTD: Surprise: actual less predicted
A16: Poland | B16: EM Europe | C16: =INDEX(HIST_D!$S$8:$S$791,1) | D16: yes | E16: =IFERROR((INDEX(HIST_D!$S$8:$S$791,Control!$B$10)/INDEX(HIST_D!$S$8:$S$791,1)-1),"") | F16: =IFERROR(-(INDEX(HIST_D!$K$8:$K$791,1)/INDEX(HIST_D!$K$8:$K$791,Control!$B$10)-1),"") | G16: =IFERROR(E16-F16,"") | H16: =IFERROR(IF(ABS(F16)<0.005,"n/m",E16/F16),"n/m") | I16: =IFERROR(SLOPE(HIST_D!$DX$8:INDEX(HIST_D!$DX$8:$DX$791,Control!$B$12),HIST_D!$CX$8:INDEX(HIST_D!$CX$8:$CX$791,Control!$B$12)),"") | J16: =IFERROR(I16*(INDEX(HIST_D!$K$8:$K$791,1)/INDEX(HIST_D!$K$8:$K$791,Control!$B$10)-1),"") | K16: =IFERROR(E16-J16,"") | L16: =IFERROR((INDEX(HIST_D!$S$8:$S$791,Control!$B$11)/INDEX(HIST_D!$S$8:$S$791,1)-1),"") | M16: =IFERROR(-(INDEX(HIST_D!$K$8:$K$791,1)/INDEX(HIST_D!$K$8:$K$791,Control!$B$11)-1),"") | N16: =IFERROR(L16-M16,"") | O16: =IFERROR(IF(ABS(M16)<0.005,"n/m",L16/M16),"n/m") | P16: =IFERROR(SLOPE(HIST_D!$DX$8:INDEX(HIST_D!$DX$8:$DX$791,Control!$B$12),HIST_D!$CX$8:INDEX(HIST_D!$CX$8:$CX$791,Control!$B$12)),"") | Q16: =IFERROR(P16*(INDEX(HIST_D!$K$8:$K$791,1)/INDEX(HIST_D!$K$8:$K$791,Control!$B$11)-1),"") | R16: =IFERROR(L16-Q16,"")
A17: Hungary | B17: EM Europe | C17: =INDEX(HIST_D!$T$8:$T$791,1) | D17: yes | E17: =IFERROR((INDEX(HIST_D!$T$8:$T$791,Control!$B$10)/INDEX(HIST_D!$T$8:$T$791,1)-1),"") | F17: =IFERROR(-(INDEX(HIST_D!$K$8:$K$791,1)/INDEX(HIST_D!$K$8:$K$791,Control!$B$10)-1),"") | G17: =IFERROR(E17-F17,"") | H17: =IFERROR(IF(ABS(F17)<0.005,"n/m",E17/F17),"n/m") | I17: =IFERROR(SLOPE(HIST_D!$DY$8:INDEX(HIST_D!$DY$8:$DY$791,Control!$B$12),HIST_D!$CX$8:INDEX(HIST_D!$CX$8:$CX$791,Control!$B$12)),"") | J17: =IFERROR(I17*(INDEX(HIST_D!$K$8:$K$791,1)/INDEX(HIST_D!$K$8:$K$791,Control!$B$10)-1),"") | K17: =IFERROR(E17-J17,"") | L17: =IFERROR((INDEX(HIST_D!$T$8:$T$791,Control!$B$11)/INDEX(HIST_D!$T$8:$T$791,1)-1),"") | M17: =IFERROR(-(INDEX(HIST_D!$K$8:$K$791,1)/INDEX(HIST_D!$K$8:$K$791,Control!$B$11)-1),"") | N17: =IFERROR(L17-M17,"") | O17: =IFERROR(IF(ABS(M17)<0.005,"n/m",L17/M17),"n/m") | P17: =IFERROR(SLOPE(HIST_D!$DY$8:INDEX(HIST_D!$DY$8:$DY$791,Control!$B$12),HIST_D!$CX$8:INDEX(HIST_D!$CX$8:$CX$791,Control!$B$12)),"") | Q17: =IFERROR(P17*(INDEX(HIST_D!$K$8:$K$791,1)/INDEX(HIST_D!$K$8:$K$791,Control!$B$11)-1),"") | R17: =IFERROR(L17-Q17,"")
A18: Czechia | B18: EM Europe | C18: =INDEX(HIST_D!$U$8:$U$791,1) | D18: yes | E18: =IFERROR((INDEX(HIST_D!$U$8:$U$791,Control!$B$10)/INDEX(HIST_D!$U$8:$U$791,1)-1),"") | F18: =IFERROR(-(INDEX(HIST_D!$K$8:$K$791,1)/INDEX(HIST_D!$K$8:$K$791,Control!$B$10)-1),"") | G18: =IFERROR(E18-F18,"") | H18: =IFERROR(IF(ABS(F18)<0.005,"n/m",E18/F18),"n/m") | I18: =IFERROR(SLOPE(HIST_D!$DZ$8:INDEX(HIST_D!$DZ$8:$DZ$791,Control!$B$12),HIST_D!$CX$8:INDEX(HIST_D!$CX$8:$CX$791,Control!$B$12)),"") | J18: =IFERROR(I18*(INDEX(HIST_D!$K$8:$K$791,1)/INDEX(HIST_D!$K$8:$K$791,Control!$B$10)-1),"") | K18: =IFERROR(E18-J18,"") | L18: =IFERROR((INDEX(HIST_D!$U$8:$U$791,Control!$B$11)/INDEX(HIST_D!$U$8:$U$791,1)-1),"") | M18: =IFERROR(-(INDEX(HIST_D!$K$8:$K$791,1)/INDEX(HIST_D!$K$8:$K$791,Control!$B$11)-1),"") | N18: =IFERROR(L18-M18,"") | O18: =IFERROR(IF(ABS(M18)<0.005,"n/m",L18/M18),"n/m") | P18: =IFERROR(SLOPE(HIST_D!$DZ$8:INDEX(HIST_D!$DZ$8:$DZ$791,Control!$B$12),HIST_D!$CX$8:INDEX(HIST_D!$CX$8:$CX$791,Control!$B$12)),"") | Q18: =IFERROR(P18*(INDEX(HIST_D!$K$8:$K$791,1)/INDEX(HIST_D!$K$8:$K$791,Control!$B$11)-1),"") | R18: =IFERROR(L18-Q18,"")
A19: Romania | B19: EM Europe | C19: =INDEX(HIST_D!$V$8:$V$791,1) | D19: yes | E19: =IFERROR((INDEX(HIST_D!$V$8:$V$791,Control!$B$10)/INDEX(HIST_D!$V$8:$V$791,1)-1),"") | F19: =IFERROR(-(INDEX(HIST_D!$K$8:$K$791,1)/INDEX(HIST_D!$K$8:$K$791,Control!$B$10)-1),"") | G19: =IFERROR(E19-F19,"") | H19: =IFERROR(IF(ABS(F19)<0.005,"n/m",E19/F19),"n/m") | I19: =IFERROR(SLOPE(HIST_D!$EA$8:INDEX(HIST_D!$EA$8:$EA$791,Control!$B$12),HIST_D!$CX$8:INDEX(HIST_D!$CX$8:$CX$791,Control!$B$12)),"") | J19: =IFERROR(I19*(INDEX(HIST_D!$K$8:$K$791,1)/INDEX(HIST_D!$K$8:$K$791,Control!$B$10)-1),"") | K19: =IFERROR(E19-J19,"") | L19: =IFERROR((INDEX(HIST_D!$V$8:$V$791,Control!$B$11)/INDEX(HIST_D!$V$8:$V$791,1)-1),"") | M19: =IFERROR(-(INDEX(HIST_D!$K$8:$K$791,1)/INDEX(HIST_D!$K$8:$K$791,Control!$B$11)-1),"") | N19: =IFERROR(L19-M19,"") | O19: =IFERROR(IF(ABS(M19)<0.005,"n/m",L19/M19),"n/m") | P19: =IFERROR(SLOPE(HIST_D!$EA$8:INDEX(HIST_D!$EA$8:$EA$791,Control!$B$12),HIST_D!$CX$8:INDEX(HIST_D!$CX$8:$CX$791,Control!$B$12)),"") | Q19: =IFERROR(P19*(INDEX(HIST_D!$K$8:$K$791,1)/INDEX(HIST_D!$K$8:$K$791,Control!$B$11)-1),"") | R19: =IFERROR(L19-Q19,"")
A20: Turkiye | B20: EM Europe | C20: =INDEX(HIST_D!$W$8:$W$791,1) | D20: no | E20: =IFERROR((INDEX(HIST_D!$W$8:$W$791,Control!$B$10)/INDEX(HIST_D!$W$8:$W$791,1)-1),"") | F20: =IFERROR(-(INDEX(HIST_D!$K$8:$K$791,1)/INDEX(HIST_D!$K$8:$K$791,Control!$B$10)-1),"") | G20: =IFERROR(E20-F20,"") | H20: =IFERROR(IF(ABS(F20)<0.005,"n/m",E20/F20),"n/m") | I20: =IFERROR(SLOPE(HIST_D!$EB$8:INDEX(HIST_D!$EB$8:$EB$791,Control!$B$12),HIST_D!$CX$8:INDEX(HIST_D!$CX$8:$CX$791,Control!$B$12)),"") | J20: =IFERROR(I20*(INDEX(HIST_D!$K$8:$K$791,1)/INDEX(HIST_D!$K$8:$K$791,Control!$B$10)-1),"") | K20: =IFERROR(E20-J20,"") | L20: =IFERROR((INDEX(HIST_D!$W$8:$W$791,Control!$B$11)/INDEX(HIST_D!$W$8:$W$791,1)-1),"") | M20: =IFERROR(-(INDEX(HIST_D!$K$8:$K$791,1)/INDEX(HIST_D!$K$8:$K$791,Control!$B$11)-1),"") | N20: =IFERROR(L20-M20,"") | O20: =IFERROR(IF(ABS(M20)<0.005,"n/m",L20/M20),"n/m") | P20: =IFERROR(SLOPE(HIST_D!$EB$8:INDEX(HIST_D!$EB$8:$EB$791,Control!$B$12),HIST_D!$CX$8:INDEX(HIST_D!$CX$8:$CX$791,Control!$B$12)),"") | Q20: =IFERROR(P20*(INDEX(HIST_D!$K$8:$K$791,1)/INDEX(HIST_D!$K$8:$K$791,Control!$B$11)-1),"") | R20: =IFERROR(L20-Q20,"") | S20: excluded from rates and FX averages: structural depreciation and a 30% curve swamp an equal weight
A21: EM Europe average | B21: n=4 | E21: =IFERROR(AVERAGE(E16,E17,E18,E19),"") | F21: =IFERROR(AVERAGE(F16,F17,F18,F19),"") | G21: =IFERROR(AVERAGE(G16,G17,G18,G19),"") | H21: =IFERROR(IF(ABS(F21)<0.005,"n/m",E21/F21),"n/m") | I21: =IFERROR(AVERAGE(I16,I17,I18,I19),"") | J21: =IFERROR(AVERAGE(J16,J17,J18,J19),"") | K21: =IFERROR(AVERAGE(K16,K17,K18,K19),"") | L21: =IFERROR(AVERAGE(L16,L17,L18,L19),"") | M21: =IFERROR(AVERAGE(M16,M17,M18,M19),"") | N21: =IFERROR(AVERAGE(N16,N17,N18,N19),"") | O21: =IFERROR(IF(ABS(M21)<0.005,"n/m",L21/M21),"n/m") | P21: =IFERROR(AVERAGE(P16,P17,P18,P19),"") | Q21: =IFERROR(AVERAGE(Q16,Q17,Q18,Q19),"") | R21: =IFERROR(AVERAGE(R16,R17,R18,R19),"")
A22: =IFERROR("EM Europe: the currency returned "&TEXT($E$21,"+0.0%;-0.0%")&" on the month; a beta-of-one to the dollar implies "&TEXT($F$21,"+0.0%;-0.0%")&", so "&TEXT($G$21,"+0.0%;-0.0%")&" is ex-dollar"&IF(ISNUMBER($H$21)," (pass-through "&TEXT($H$21,"0.00")&"x)","")&". Against its 2y beta to DXY of "&TEXT($I$21,"0.00")&" the surprise is "&TEXT($K$21,"+0.0%;-0.0%")&". YTD: "&TEXT($L$21,"+0.0%;-0.0%")&", of which "&TEXT($N$21,"+0.0%;-0.0%")&" ex-dollar. "&IF($K$21>0.005,"Stronger than the dollar relationship implies — intrinsic support.",IF($K$21<-0.005,"Weaker than the dollar relationship implies — intrinsic pressure.","In line with the dollar; nothing EM-specific here.")),"")
A24: MIDDLE EAST
A25: Country | B25: Region | C25: Level | D25: In avg | E25: 1M: Total: return on EM ccy | F25: 1M: US-driven: -(DXY return) | G25: 1M: Intrinsic: return ex-dollar | H25: 1M: Pass-through (total / US) | I25: 1M: Beta to DXY (2y) | J25: 1M: Predicted by beta | K25: 1M: Surprise: actual less predicted | L25: YTD: Total: return on EM ccy | M25: YTD: US-driven: -(DXY return) | N25: YTD: Intrinsic: return ex-dollar | O25: YTD: Pass-through (total / US) | P25: YTD: Beta to DXY (2y) | Q25: YTD: Predicted by beta | R25: YTD: Surprise: actual less predicted
A26: Israel | B26: Middle East | C26: =INDEX(HIST_D!$X$8:$X$791,1) | D26: yes | E26: =IFERROR((INDEX(HIST_D!$X$8:$X$791,Control!$B$10)/INDEX(HIST_D!$X$8:$X$791,1)-1),"") | F26: =IFERROR(-(INDEX(HIST_D!$K$8:$K$791,1)/INDEX(HIST_D!$K$8:$K$791,Control!$B$10)-1),"") | G26: =IFERROR(E26-F26,"") | H26: =IFERROR(IF(ABS(F26)<0.005,"n/m",E26/F26),"n/m") | I26: =IFERROR(SLOPE(HIST_D!$EC$8:INDEX(HIST_D!$EC$8:$EC$791,Control!$B$12),HIST_D!$CX$8:INDEX(HIST_D!$CX$8:$CX$791,Control!$B$12)),"") | J26: =IFERROR(I26*(INDEX(HIST_D!$K$8:$K$791,1)/INDEX(HIST_D!$K$8:$K$791,Control!$B$10)-1),"") | K26: =IFERROR(E26-J26,"") | L26: =IFERROR((INDEX(HIST_D!$X$8:$X$791,Control!$B$11)/INDEX(HIST_D!$X$8:$X$791,1)-1),"") | M26: =IFERROR(-(INDEX(HIST_D!$K$8:$K$791,1)/INDEX(HIST_D!$K$8:$K$791,Control!$B$11)-1),"") | N26: =IFERROR(L26-M26,"") | O26: =IFERROR(IF(ABS(M26)<0.005,"n/m",L26/M26),"n/m") | P26: =IFERROR(SLOPE(HIST_D!$EC$8:INDEX(HIST_D!$EC$8:$EC$791,Control!$B$12),HIST_D!$CX$8:INDEX(HIST_D!$CX$8:$CX$791,Control!$B$12)),"") | Q26: =IFERROR(P26*(INDEX(HIST_D!$K$8:$K$791,1)/INDEX(HIST_D!$K$8:$K$791,Control!$B$11)-1),"") | R26: =IFERROR(L26-Q26,"")
A27: Egypt | B27: Middle East | C27: =INDEX(HIST_D!$Y$8:$Y$791,1) | D27: no | E27: =IFERROR((INDEX(HIST_D!$Y$8:$Y$791,Control!$B$10)/INDEX(HIST_D!$Y$8:$Y$791,1)-1),"") | F27: =IFERROR(-(INDEX(HIST_D!$K$8:$K$791,1)/INDEX(HIST_D!$K$8:$K$791,Control!$B$10)-1),"") | G27: =IFERROR(E27-F27,"") | H27: =IFERROR(IF(ABS(F27)<0.005,"n/m",E27/F27),"n/m") | I27: =IFERROR(SLOPE(HIST_D!$ED$8:INDEX(HIST_D!$ED$8:$ED$791,Control!$B$12),HIST_D!$CX$8:INDEX(HIST_D!$CX$8:$CX$791,Control!$B$12)),"") | J27: =IFERROR(I27*(INDEX(HIST_D!$K$8:$K$791,1)/INDEX(HIST_D!$K$8:$K$791,Control!$B$10)-1),"") | K27: =IFERROR(E27-J27,"") | L27: =IFERROR((INDEX(HIST_D!$Y$8:$Y$791,Control!$B$11)/INDEX(HIST_D!$Y$8:$Y$791,1)-1),"") | M27: =IFERROR(-(INDEX(HIST_D!$K$8:$K$791,1)/INDEX(HIST_D!$K$8:$K$791,Control!$B$11)-1),"") | N27: =IFERROR(L27-M27,"") | O27: =IFERROR(IF(ABS(M27)<0.005,"n/m",L27/M27),"n/m") | P27: =IFERROR(SLOPE(HIST_D!$ED$8:INDEX(HIST_D!$ED$8:$ED$791,Control!$B$12),HIST_D!$CX$8:INDEX(HIST_D!$CX$8:$CX$791,Control!$B$12)),"") | Q27: =IFERROR(P27*(INDEX(HIST_D!$K$8:$K$791,1)/INDEX(HIST_D!$K$8:$K$791,Control!$B$11)-1),"") | R27: =IFERROR(L27-Q27,"") | S27: excluded from FX average: managed float with step devaluations; GTEGP10Y is Verify
A28: Middle East average | B28: n=1 | E28: =IFERROR(AVERAGE(E26),"") | F28: =IFERROR(AVERAGE(F26),"") | G28: =IFERROR(AVERAGE(G26),"") | H28: =IFERROR(IF(ABS(F28)<0.005,"n/m",E28/F28),"n/m") | I28: =IFERROR(AVERAGE(I26),"") | J28: =IFERROR(AVERAGE(J26),"") | K28: =IFERROR(AVERAGE(K26),"") | L28: =IFERROR(AVERAGE(L26),"") | M28: =IFERROR(AVERAGE(M26),"") | N28: =IFERROR(AVERAGE(N26),"") | O28: =IFERROR(IF(ABS(M28)<0.005,"n/m",L28/M28),"n/m") | P28: =IFERROR(AVERAGE(P26),"") | Q28: =IFERROR(AVERAGE(Q26),"") | R28: =IFERROR(AVERAGE(R26),"")
A29: =IFERROR("Middle East: the currency returned "&TEXT($E$28,"+0.0%;-0.0%")&" on the month; a beta-of-one to the dollar implies "&TEXT($F$28,"+0.0%;-0.0%")&", so "&TEXT($G$28,"+0.0%;-0.0%")&" is ex-dollar"&IF(ISNUMBER($H$28)," (pass-through "&TEXT($H$28,"0.00")&"x)","")&". Against its 2y beta to DXY of "&TEXT($I$28,"0.00")&" the surprise is "&TEXT($K$28,"+0.0%;-0.0%")&". YTD: "&TEXT($L$28,"+0.0%;-0.0%")&", of which "&TEXT($N$28,"+0.0%;-0.0%")&" ex-dollar. "&IF($K$28>0.005,"Stronger than the dollar relationship implies — intrinsic support.",IF($K$28<-0.005,"Weaker than the dollar relationship implies — intrinsic pressure.","In line with the dollar; nothing EM-specific here.")),"")
A31: EM ASIA
A32: Country | B32: Region | C32: Level | D32: In avg | E32: 1M: Total: return on EM ccy | F32: 1M: US-driven: -(DXY return) | G32: 1M: Intrinsic: return ex-dollar | H32: 1M: Pass-through (total / US) | I32: 1M: Beta to DXY (2y) | J32: 1M: Predicted by beta | K32: 1M: Surprise: actual less predicted | L32: YTD: Total: return on EM ccy | M32: YTD: US-driven: -(DXY return) | N32: YTD: Intrinsic: return ex-dollar | O32: YTD: Pass-through (total / US) | P32: YTD: Beta to DXY (2y) | Q32: YTD: Predicted by beta | R32: YTD: Surprise: actual less predicted
A33: China | B33: EM Asia | C33: =INDEX(HIST_D!$Z$8:$Z$791,1) | D33: yes | E33: =IFERROR((INDEX(HIST_D!$Z$8:$Z$791,Control!$B$10)/INDEX(HIST_D!$Z$8:$Z$791,1)-1),"") | F33: =IFERROR(-(INDEX(HIST_D!$K$8:$K$791,1)/INDEX(HIST_D!$K$8:$K$791,Control!$B$10)-1),"") | G33: =IFERROR(E33-F33,"") | H33: =IFERROR(IF(ABS(F33)<0.005,"n/m",E33/F33),"n/m") | I33: =IFERROR(SLOPE(HIST_D!$EE$8:INDEX(HIST_D!$EE$8:$EE$791,Control!$B$12),HIST_D!$CX$8:INDEX(HIST_D!$CX$8:$CX$791,Control!$B$12)),"") | J33: =IFERROR(I33*(INDEX(HIST_D!$K$8:$K$791,1)/INDEX(HIST_D!$K$8:$K$791,Control!$B$10)-1),"") | K33: =IFERROR(E33-J33,"") | L33: =IFERROR((INDEX(HIST_D!$Z$8:$Z$791,Control!$B$11)/INDEX(HIST_D!$Z$8:$Z$791,1)-1),"") | M33: =IFERROR(-(INDEX(HIST_D!$K$8:$K$791,1)/INDEX(HIST_D!$K$8:$K$791,Control!$B$11)-1),"") | N33: =IFERROR(L33-M33,"") | O33: =IFERROR(IF(ABS(M33)<0.005,"n/m",L33/M33),"n/m") | P33: =IFERROR(SLOPE(HIST_D!$EE$8:INDEX(HIST_D!$EE$8:$EE$791,Control!$B$12),HIST_D!$CX$8:INDEX(HIST_D!$CX$8:$CX$791,Control!$B$12)),"") | Q33: =IFERROR(P33*(INDEX(HIST_D!$K$8:$K$791,1)/INDEX(HIST_D!$K$8:$K$791,Control!$B$11)-1),"") | R33: =IFERROR(L33-Q33,"")
A34: India | B34: EM Asia | C34: =INDEX(HIST_D!$AA$8:$AA$791,1) | D34: yes | E34: =IFERROR((INDEX(HIST_D!$AA$8:$AA$791,Control!$B$10)/INDEX(HIST_D!$AA$8:$AA$791,1)-1),"") | F34: =IFERROR(-(INDEX(HIST_D!$K$8:$K$791,1)/INDEX(HIST_D!$K$8:$K$791,Control!$B$10)-1),"") | G34: =IFERROR(E34-F34,"") | H34: =IFERROR(IF(ABS(F34)<0.005,"n/m",E34/F34),"n/m") | I34: =IFERROR(SLOPE(HIST_D!$EF$8:INDEX(HIST_D!$EF$8:$EF$791,Control!$B$12),HIST_D!$CX$8:INDEX(HIST_D!$CX$8:$CX$791,Control!$B$12)),"") | J34: =IFERROR(I34*(INDEX(HIST_D!$K$8:$K$791,1)/INDEX(HIST_D!$K$8:$K$791,Control!$B$10)-1),"") | K34: =IFERROR(E34-J34,"") | L34: =IFERROR((INDEX(HIST_D!$AA$8:$AA$791,Control!$B$11)/INDEX(HIST_D!$AA$8:$AA$791,1)-1),"") | M34: =IFERROR(-(INDEX(HIST_D!$K$8:$K$791,1)/INDEX(HIST_D!$K$8:$K$791,Control!$B$11)-1),"") | N34: =IFERROR(L34-M34,"") | O34: =IFERROR(IF(ABS(M34)<0.005,"n/m",L34/M34),"n/m") | P34: =IFERROR(SLOPE(HIST_D!$EF$8:INDEX(HIST_D!$EF$8:$EF$791,Control!$B$12),HIST_D!$CX$8:INDEX(HIST_D!$CX$8:$CX$791,Control!$B$12)),"") | Q34: =IFERROR(P34*(INDEX(HIST_D!$K$8:$K$791,1)/INDEX(HIST_D!$K$8:$K$791,Control!$B$11)-1),"") | R34: =IFERROR(L34-Q34,"") | S34: no sovereign USD debt, no CDS — rates and FX only
A35: Indonesia | B35: EM Asia | C35: =INDEX(HIST_D!$AB$8:$AB$791,1) | D35: yes | E35: =IFERROR((INDEX(HIST_D!$AB$8:$AB$791,Control!$B$10)/INDEX(HIST_D!$AB$8:$AB$791,1)-1),"") | F35: =IFERROR(-(INDEX(HIST_D!$K$8:$K$791,1)/INDEX(HIST_D!$K$8:$K$791,Control!$B$10)-1),"") | G35: =IFERROR(E35-F35,"") | H35: =IFERROR(IF(ABS(F35)<0.005,"n/m",E35/F35),"n/m") | I35: =IFERROR(SLOPE(HIST_D!$EG$8:INDEX(HIST_D!$EG$8:$EG$791,Control!$B$12),HIST_D!$CX$8:INDEX(HIST_D!$CX$8:$CX$791,Control!$B$12)),"") | J35: =IFERROR(I35*(INDEX(HIST_D!$K$8:$K$791,1)/INDEX(HIST_D!$K$8:$K$791,Control!$B$10)-1),"") | K35: =IFERROR(E35-J35,"") | L35: =IFERROR((INDEX(HIST_D!$AB$8:$AB$791,Control!$B$11)/INDEX(HIST_D!$AB$8:$AB$791,1)-1),"") | M35: =IFERROR(-(INDEX(HIST_D!$K$8:$K$791,1)/INDEX(HIST_D!$K$8:$K$791,Control!$B$11)-1),"") | N35: =IFERROR(L35-M35,"") | O35: =IFERROR(IF(ABS(M35)<0.005,"n/m",L35/M35),"n/m") | P35: =IFERROR(SLOPE(HIST_D!$EG$8:INDEX(HIST_D!$EG$8:$EG$791,Control!$B$12),HIST_D!$CX$8:INDEX(HIST_D!$CX$8:$CX$791,Control!$B$12)),"") | Q35: =IFERROR(P35*(INDEX(HIST_D!$K$8:$K$791,1)/INDEX(HIST_D!$K$8:$K$791,Control!$B$11)-1),"") | R35: =IFERROR(L35-Q35,"")
A36: Korea | B36: EM Asia | C36: =INDEX(HIST_D!$AC$8:$AC$791,1) | D36: yes | E36: =IFERROR((INDEX(HIST_D!$AC$8:$AC$791,Control!$B$10)/INDEX(HIST_D!$AC$8:$AC$791,1)-1),"") | F36: =IFERROR(-(INDEX(HIST_D!$K$8:$K$791,1)/INDEX(HIST_D!$K$8:$K$791,Control!$B$10)-1),"") | G36: =IFERROR(E36-F36,"") | H36: =IFERROR(IF(ABS(F36)<0.005,"n/m",E36/F36),"n/m") | I36: =IFERROR(SLOPE(HIST_D!$EH$8:INDEX(HIST_D!$EH$8:$EH$791,Control!$B$12),HIST_D!$CX$8:INDEX(HIST_D!$CX$8:$CX$791,Control!$B$12)),"") | J36: =IFERROR(I36*(INDEX(HIST_D!$K$8:$K$791,1)/INDEX(HIST_D!$K$8:$K$791,Control!$B$10)-1),"") | K36: =IFERROR(E36-J36,"") | L36: =IFERROR((INDEX(HIST_D!$AC$8:$AC$791,Control!$B$11)/INDEX(HIST_D!$AC$8:$AC$791,1)-1),"") | M36: =IFERROR(-(INDEX(HIST_D!$K$8:$K$791,1)/INDEX(HIST_D!$K$8:$K$791,Control!$B$11)-1),"") | N36: =IFERROR(L36-M36,"") | O36: =IFERROR(IF(ABS(M36)<0.005,"n/m",L36/M36),"n/m") | P36: =IFERROR(SLOPE(HIST_D!$EH$8:INDEX(HIST_D!$EH$8:$EH$791,Control!$B$12),HIST_D!$CX$8:INDEX(HIST_D!$CX$8:$CX$791,Control!$B$12)),"") | Q36: =IFERROR(P36*(INDEX(HIST_D!$K$8:$K$791,1)/INDEX(HIST_D!$K$8:$K$791,Control!$B$11)-1),"") | R36: =IFERROR(L36-Q36,"")
A37: Thailand | B37: EM Asia | C37: =INDEX(HIST_D!$AD$8:$AD$791,1) | D37: yes | E37: =IFERROR((INDEX(HIST_D!$AD$8:$AD$791,Control!$B$10)/INDEX(HIST_D!$AD$8:$AD$791,1)-1),"") | F37: =IFERROR(-(INDEX(HIST_D!$K$8:$K$791,1)/INDEX(HIST_D!$K$8:$K$791,Control!$B$10)-1),"") | G37: =IFERROR(E37-F37,"") | H37: =IFERROR(IF(ABS(F37)<0.005,"n/m",E37/F37),"n/m") | I37: =IFERROR(SLOPE(HIST_D!$EI$8:INDEX(HIST_D!$EI$8:$EI$791,Control!$B$12),HIST_D!$CX$8:INDEX(HIST_D!$CX$8:$CX$791,Control!$B$12)),"") | J37: =IFERROR(I37*(INDEX(HIST_D!$K$8:$K$791,1)/INDEX(HIST_D!$K$8:$K$791,Control!$B$10)-1),"") | K37: =IFERROR(E37-J37,"") | L37: =IFERROR((INDEX(HIST_D!$AD$8:$AD$791,Control!$B$11)/INDEX(HIST_D!$AD$8:$AD$791,1)-1),"") | M37: =IFERROR(-(INDEX(HIST_D!$K$8:$K$791,1)/INDEX(HIST_D!$K$8:$K$791,Control!$B$11)-1),"") | N37: =IFERROR(L37-M37,"") | O37: =IFERROR(IF(ABS(M37)<0.005,"n/m",L37/M37),"n/m") | P37: =IFERROR(SLOPE(HIST_D!$EI$8:INDEX(HIST_D!$EI$8:$EI$791,Control!$B$12),HIST_D!$CX$8:INDEX(HIST_D!$CX$8:$CX$791,Control!$B$12)),"") | Q37: =IFERROR(P37*(INDEX(HIST_D!$K$8:$K$791,1)/INDEX(HIST_D!$K$8:$K$791,Control!$B$11)-1),"") | R37: =IFERROR(L37-Q37,"")
A38: Malaysia | B38: EM Asia | C38: =INDEX(HIST_D!$AE$8:$AE$791,1) | D38: yes | E38: =IFERROR((INDEX(HIST_D!$AE$8:$AE$791,Control!$B$10)/INDEX(HIST_D!$AE$8:$AE$791,1)-1),"") | F38: =IFERROR(-(INDEX(HIST_D!$K$8:$K$791,1)/INDEX(HIST_D!$K$8:$K$791,Control!$B$10)-1),"") | G38: =IFERROR(E38-F38,"") | H38: =IFERROR(IF(ABS(F38)<0.005,"n/m",E38/F38),"n/m") | I38: =IFERROR(SLOPE(HIST_D!$EJ$8:INDEX(HIST_D!$EJ$8:$EJ$791,Control!$B$12),HIST_D!$CX$8:INDEX(HIST_D!$CX$8:$CX$791,Control!$B$12)),"") | J38: =IFERROR(I38*(INDEX(HIST_D!$K$8:$K$791,1)/INDEX(HIST_D!$K$8:$K$791,Control!$B$10)-1),"") | K38: =IFERROR(E38-J38,"") | L38: =IFERROR((INDEX(HIST_D!$AE$8:$AE$791,Control!$B$11)/INDEX(HIST_D!$AE$8:$AE$791,1)-1),"") | M38: =IFERROR(-(INDEX(HIST_D!$K$8:$K$791,1)/INDEX(HIST_D!$K$8:$K$791,Control!$B$11)-1),"") | N38: =IFERROR(L38-M38,"") | O38: =IFERROR(IF(ABS(M38)<0.005,"n/m",L38/M38),"n/m") | P38: =IFERROR(SLOPE(HIST_D!$EJ$8:INDEX(HIST_D!$EJ$8:$EJ$791,Control!$B$12),HIST_D!$CX$8:INDEX(HIST_D!$CX$8:$CX$791,Control!$B$12)),"") | Q38: =IFERROR(P38*(INDEX(HIST_D!$K$8:$K$791,1)/INDEX(HIST_D!$K$8:$K$791,Control!$B$11)-1),"") | R38: =IFERROR(L38-Q38,"")
A39: Philippines | B39: EM Asia | C39: =INDEX(HIST_D!$AF$8:$AF$791,1) | D39: yes | E39: =IFERROR((INDEX(HIST_D!$AF$8:$AF$791,Control!$B$10)/INDEX(HIST_D!$AF$8:$AF$791,1)-1),"") | F39: =IFERROR(-(INDEX(HIST_D!$K$8:$K$791,1)/INDEX(HIST_D!$K$8:$K$791,Control!$B$10)-1),"") | G39: =IFERROR(E39-F39,"") | H39: =IFERROR(IF(ABS(F39)<0.005,"n/m",E39/F39),"n/m") | I39: =IFERROR(SLOPE(HIST_D!$EK$8:INDEX(HIST_D!$EK$8:$EK$791,Control!$B$12),HIST_D!$CX$8:INDEX(HIST_D!$CX$8:$CX$791,Control!$B$12)),"") | J39: =IFERROR(I39*(INDEX(HIST_D!$K$8:$K$791,1)/INDEX(HIST_D!$K$8:$K$791,Control!$B$10)-1),"") | K39: =IFERROR(E39-J39,"") | L39: =IFERROR((INDEX(HIST_D!$AF$8:$AF$791,Control!$B$11)/INDEX(HIST_D!$AF$8:$AF$791,1)-1),"") | M39: =IFERROR(-(INDEX(HIST_D!$K$8:$K$791,1)/INDEX(HIST_D!$K$8:$K$791,Control!$B$11)-1),"") | N39: =IFERROR(L39-M39,"") | O39: =IFERROR(IF(ABS(M39)<0.005,"n/m",L39/M39),"n/m") | P39: =IFERROR(SLOPE(HIST_D!$EK$8:INDEX(HIST_D!$EK$8:$EK$791,Control!$B$12),HIST_D!$CX$8:INDEX(HIST_D!$CX$8:$CX$791,Control!$B$12)),"") | Q39: =IFERROR(P39*(INDEX(HIST_D!$K$8:$K$791,1)/INDEX(HIST_D!$K$8:$K$791,Control!$B$11)-1),"") | R39: =IFERROR(L39-Q39,"")
A40: EM Asia average | B40: n=7 | E40: =IFERROR(AVERAGE(E33,E34,E35,E36,E37,E38,E39),"") | F40: =IFERROR(AVERAGE(F33,F34,F35,F36,F37,F38,F39),"") | G40: =IFERROR(AVERAGE(G33,G34,G35,G36,G37,G38,G39),"") | H40: =IFERROR(IF(ABS(F40)<0.005,"n/m",E40/F40),"n/m") | I40: =IFERROR(AVERAGE(I33,I34,I35,I36,I37,I38,I39),"") | J40: =IFERROR(AVERAGE(J33,J34,J35,J36,J37,J38,J39),"") | K40: =IFERROR(AVERAGE(K33,K34,K35,K36,K37,K38,K39),"") | L40: =IFERROR(AVERAGE(L33,L34,L35,L36,L37,L38,L39),"") | M40: =IFERROR(AVERAGE(M33,M34,M35,M36,M37,M38,M39),"") | N40: =IFERROR(AVERAGE(N33,N34,N35,N36,N37,N38,N39),"") | O40: =IFERROR(IF(ABS(M40)<0.005,"n/m",L40/M40),"n/m") | P40: =IFERROR(AVERAGE(P33,P34,P35,P36,P37,P38,P39),"") | Q40: =IFERROR(AVERAGE(Q33,Q34,Q35,Q36,Q37,Q38,Q39),"") | R40: =IFERROR(AVERAGE(R33,R34,R35,R36,R37,R38,R39),"")
A41: =IFERROR("EM Asia: the currency returned "&TEXT($E$40,"+0.0%;-0.0%")&" on the month; a beta-of-one to the dollar implies "&TEXT($F$40,"+0.0%;-0.0%")&", so "&TEXT($G$40,"+0.0%;-0.0%")&" is ex-dollar"&IF(ISNUMBER($H$40)," (pass-through "&TEXT($H$40,"0.00")&"x)","")&". Against its 2y beta to DXY of "&TEXT($I$40,"0.00")&" the surprise is "&TEXT($K$40,"+0.0%;-0.0%")&". YTD: "&TEXT($L$40,"+0.0%;-0.0%")&", of which "&TEXT($N$40,"+0.0%;-0.0%")&" ex-dollar. "&IF($K$40>0.005,"Stronger than the dollar relationship implies — intrinsic support.",IF($K$40<-0.005,"Weaker than the dollar relationship implies — intrinsic pressure.","In line with the dollar; nothing EM-specific here.")),"")
A43: EM AVERAGE AND MEMO
A44: Country | B44: Region | C44: Level | D44: In avg | E44: 1M: Total: return on EM ccy | F44: 1M: US-driven: -(DXY return) | G44: 1M: Intrinsic: return ex-dollar | H44: 1M: Pass-through (total / US) | I44: 1M: Beta to DXY (2y) | J44: 1M: Predicted by beta | K44: 1M: Surprise: actual less predicted | L44: YTD: Total: return on EM ccy | M44: YTD: US-driven: -(DXY return) | N44: YTD: Intrinsic: return ex-dollar | O44: YTD: Pass-through (total / US) | P44: YTD: Beta to DXY (2y) | Q44: YTD: Predicted by beta | R44: YTD: Surprise: actual less predicted
A45: EM average (all flagged) | B45: n=17 | E45: =IFERROR(AVERAGE(E6,E7,E8,E9,E10,E16,E17,E18,E19,E26,E33,E34,E35,E36,E37,E38,E39),"") | F45: =IFERROR(AVERAGE(F6,F7,F8,F9,F10,F16,F17,F18,F19,F26,F33,F34,F35,F36,F37,F38,F39),"") | G45: =IFERROR(AVERAGE(G6,G7,G8,G9,G10,G16,G17,G18,G19,G26,G33,G34,G35,G36,G37,G38,G39),"") | H45: =IFERROR(IF(ABS(F45)<0.005,"n/m",E45/F45),"n/m") | I45: =IFERROR(AVERAGE(I6,I7,I8,I9,I10,I16,I17,I18,I19,I26,I33,I34,I35,I36,I37,I38,I39),"") | J45: =IFERROR(AVERAGE(J6,J7,J8,J9,J10,J16,J17,J18,J19,J26,J33,J34,J35,J36,J37,J38,J39),"") | K45: =IFERROR(AVERAGE(K6,K7,K8,K9,K10,K16,K17,K18,K19,K26,K33,K34,K35,K36,K37,K38,K39),"") | L45: =IFERROR(AVERAGE(L6,L7,L8,L9,L10,L16,L17,L18,L19,L26,L33,L34,L35,L36,L37,L38,L39),"") | M45: =IFERROR(AVERAGE(M6,M7,M8,M9,M10,M16,M17,M18,M19,M26,M33,M34,M35,M36,M37,M38,M39),"") | N45: =IFERROR(AVERAGE(N6,N7,N8,N9,N10,N16,N17,N18,N19,N26,N33,N34,N35,N36,N37,N38,N39),"") | O45: =IFERROR(IF(ABS(M45)<0.005,"n/m",L45/M45),"n/m") | P45: =IFERROR(AVERAGE(P6,P7,P8,P9,P10,P16,P17,P18,P19,P26,P33,P34,P35,P36,P37,P38,P39),"") | Q45: =IFERROR(AVERAGE(Q6,Q7,Q8,Q9,Q10,Q16,Q17,Q18,Q19,Q26,Q33,Q34,Q35,Q36,Q37,Q38,Q39),"") | R45: =IFERROR(AVERAGE(R6,R7,R8,R9,R10,R16,R17,R18,R19,R26,R33,R34,R35,R36,R37,R38,R39),"")
A46: South Africa | B46: (memo) | C46: =INDEX(HIST_D!$AG$8:$AG$791,1) | D46: no | E46: =IFERROR((INDEX(HIST_D!$AG$8:$AG$791,Control!$B$10)/INDEX(HIST_D!$AG$8:$AG$791,1)-1),"") | F46: =IFERROR(-(INDEX(HIST_D!$K$8:$K$791,1)/INDEX(HIST_D!$K$8:$K$791,Control!$B$10)-1),"") | G46: =IFERROR(E46-F46,"") | H46: =IFERROR(IF(ABS(F46)<0.005,"n/m",E46/F46),"n/m") | I46: =IFERROR(SLOPE(HIST_D!$EL$8:INDEX(HIST_D!$EL$8:$EL$791,Control!$B$12),HIST_D!$CX$8:INDEX(HIST_D!$CX$8:$CX$791,Control!$B$12)),"") | J46: =IFERROR(I46*(INDEX(HIST_D!$K$8:$K$791,1)/INDEX(HIST_D!$K$8:$K$791,Control!$B$10)-1),"") | K46: =IFERROR(E46-J46,"") | L46: =IFERROR((INDEX(HIST_D!$AG$8:$AG$791,Control!$B$11)/INDEX(HIST_D!$AG$8:$AG$791,1)-1),"") | M46: =IFERROR(-(INDEX(HIST_D!$K$8:$K$791,1)/INDEX(HIST_D!$K$8:$K$791,Control!$B$11)-1),"") | N46: =IFERROR(L46-M46,"") | O46: =IFERROR(IF(ABS(M46)<0.005,"n/m",L46/M46),"n/m") | P46: =IFERROR(SLOPE(HIST_D!$EL$8:INDEX(HIST_D!$EL$8:$EL$791,Control!$B$12),HIST_D!$CX$8:INDEX(HIST_D!$CX$8:$CX$791,Control!$B$12)),"") | Q46: =IFERROR(P46*(INDEX(HIST_D!$K$8:$K$791,1)/INDEX(HIST_D!$K$8:$K$791,Control!$B$11)-1),"") | R46: =IFERROR(L46-Q46,"") | S46: not in any of the four regions you named; shown as a memo line, in no average
A47: =IFERROR("EM: the currency returned "&TEXT($E$45,"+0.0%;-0.0%")&" on the month; a beta-of-one to the dollar implies "&TEXT($F$45,"+0.0%;-0.0%")&", so "&TEXT($G$45,"+0.0%;-0.0%")&" is ex-dollar"&IF(ISNUMBER($H$45)," (pass-through "&TEXT($H$45,"0.00")&"x)","")&". Against its 2y beta to DXY of "&TEXT($I$45,"0.00")&" the surprise is "&TEXT($K$45,"+0.0%;-0.0%")&". YTD: "&TEXT($L$45,"+0.0%;-0.0%")&", of which "&TEXT($N$45,"+0.0%;-0.0%")&" ex-dollar. "&IF($K$45>0.005,"Stronger than the dollar relationship implies — intrinsic support.",IF($K$45<-0.005,"Weaker than the dollar relationship implies — intrinsic pressure.","In line with the dollar; nothing EM-specific here.")),"")

Sheet Equities
A1: EM EQUITIES — MSCI country indices in USD, by country and region
A2: USD return on the MSCI country index = MSCI World return + relative return vs World. US/DM-driven is the World move under a beta of one; intrinsic is the relative performance. Pass-through = total / World: under 1 = lagged the global move, over 1 = outran it, negative = went the other way.
A4: LATAM
A5: Country | B5: Region | C5: Level | D5: In avg | E5: 1M: Total: USD return | F5: 1M: US/DM-driven: MSCI World return | G5: 1M: Intrinsic: relative to World | H5: 1M: Pass-through (total / World) | I5: 1M: Beta to MSCI World (2y) | J5: 1M: Predicted by beta | K5: 1M: Surprise: actual less predicted | L5: YTD: Total: USD return | M5: YTD: US/DM-driven: MSCI World return | N5: YTD: Intrinsic: relative to World | O5: YTD: Pass-through (total / World) | P5: YTD: Beta to MSCI World (2y) | Q5: YTD: Predicted by beta | R5: YTD: Surprise: actual less predicted
A6: Brazil | B6: LatAm | C6: =INDEX(HIST_D!$BB$8:$BB$791,1) | D6: yes | E6: =IFERROR((INDEX(HIST_D!$BB$8:$BB$791,1)/INDEX(HIST_D!$BB$8:$BB$791,Control!$B$10)-1),"") | F6: =IFERROR((INDEX(HIST_D!$B$8:$B$791,1)/INDEX(HIST_D!$B$8:$B$791,Control!$B$10)-1),"") | G6: =IFERROR(E6-F6,"") | H6: =IFERROR(IF(ABS(F6)<0.005,"n/m",E6/F6),"n/m") | I6: =IFERROR(SLOPE(HIST_D!$EM$8:INDEX(HIST_D!$EM$8:$EM$791,Control!$B$12),HIST_D!$CU$8:INDEX(HIST_D!$CU$8:$CU$791,Control!$B$12)),"") | J6: =IFERROR(I6*(INDEX(HIST_D!$B$8:$B$791,1)/INDEX(HIST_D!$B$8:$B$791,Control!$B$10)-1),"") | K6: =IFERROR(E6-J6,"") | L6: =IFERROR((INDEX(HIST_D!$BB$8:$BB$791,1)/INDEX(HIST_D!$BB$8:$BB$791,Control!$B$11)-1),"") | M6: =IFERROR((INDEX(HIST_D!$B$8:$B$791,1)/INDEX(HIST_D!$B$8:$B$791,Control!$B$11)-1),"") | N6: =IFERROR(L6-M6,"") | O6: =IFERROR(IF(ABS(M6)<0.005,"n/m",L6/M6),"n/m") | P6: =IFERROR(SLOPE(HIST_D!$EM$8:INDEX(HIST_D!$EM$8:$EM$791,Control!$B$12),HIST_D!$CU$8:INDEX(HIST_D!$CU$8:$CU$791,Control!$B$12)),"") | Q6: =IFERROR(P6*(INDEX(HIST_D!$B$8:$B$791,1)/INDEX(HIST_D!$B$8:$B$791,Control!$B$11)-1),"") | R6: =IFERROR(L6-Q6,"")
A7: Mexico | B7: LatAm | C7: =INDEX(HIST_D!$BC$8:$BC$791,1) | D7: yes | E7: =IFERROR((INDEX(HIST_D!$BC$8:$BC$791,1)/INDEX(HIST_D!$BC$8:$BC$791,Control!$B$10)-1),"") | F7: =IFERROR((INDEX(HIST_D!$B$8:$B$791,1)/INDEX(HIST_D!$B$8:$B$791,Control!$B$10)-1),"") | G7: =IFERROR(E7-F7,"") | H7: =IFERROR(IF(ABS(F7)<0.005,"n/m",E7/F7),"n/m") | I7: =IFERROR(SLOPE(HIST_D!$EN$8:INDEX(HIST_D!$EN$8:$EN$791,Control!$B$12),HIST_D!$CU$8:INDEX(HIST_D!$CU$8:$CU$791,Control!$B$12)),"") | J7: =IFERROR(I7*(INDEX(HIST_D!$B$8:$B$791,1)/INDEX(HIST_D!$B$8:$B$791,Control!$B$10)-1),"") | K7: =IFERROR(E7-J7,"") | L7: =IFERROR((INDEX(HIST_D!$BC$8:$BC$791,1)/INDEX(HIST_D!$BC$8:$BC$791,Control!$B$11)-1),"") | M7: =IFERROR((INDEX(HIST_D!$B$8:$B$791,1)/INDEX(HIST_D!$B$8:$B$791,Control!$B$11)-1),"") | N7: =IFERROR(L7-M7,"") | O7: =IFERROR(IF(ABS(M7)<0.005,"n/m",L7/M7),"n/m") | P7: =IFERROR(SLOPE(HIST_D!$EN$8:INDEX(HIST_D!$EN$8:$EN$791,Control!$B$12),HIST_D!$CU$8:INDEX(HIST_D!$CU$8:$CU$791,Control!$B$12)),"") | Q7: =IFERROR(P7*(INDEX(HIST_D!$B$8:$B$791,1)/INDEX(HIST_D!$B$8:$B$791,Control!$B$11)-1),"") | R7: =IFERROR(L7-Q7,"")
A8: Chile | B8: LatAm | C8: =INDEX(HIST_D!$BD$8:$BD$791,1) | D8: yes | E8: =IFERROR((INDEX(HIST_D!$BD$8:$BD$791,1)/INDEX(HIST_D!$BD$8:$BD$791,Control!$B$10)-1),"") | F8: =IFERROR((INDEX(HIST_D!$B$8:$B$791,1)/INDEX(HIST_D!$B$8:$B$791,Control!$B$10)-1),"") | G8: =IFERROR(E8-F8,"") | H8: =IFERROR(IF(ABS(F8)<0.005,"n/m",E8/F8),"n/m") | I8: =IFERROR(SLOPE(HIST_D!$EO$8:INDEX(HIST_D!$EO$8:$EO$791,Control!$B$12),HIST_D!$CU$8:INDEX(HIST_D!$CU$8:$CU$791,Control!$B$12)),"") | J8: =IFERROR(I8*(INDEX(HIST_D!$B$8:$B$791,1)/INDEX(HIST_D!$B$8:$B$791,Control!$B$10)-1),"") | K8: =IFERROR(E8-J8,"") | L8: =IFERROR((INDEX(HIST_D!$BD$8:$BD$791,1)/INDEX(HIST_D!$BD$8:$BD$791,Control!$B$11)-1),"") | M8: =IFERROR((INDEX(HIST_D!$B$8:$B$791,1)/INDEX(HIST_D!$B$8:$B$791,Control!$B$11)-1),"") | N8: =IFERROR(L8-M8,"") | O8: =IFERROR(IF(ABS(M8)<0.005,"n/m",L8/M8),"n/m") | P8: =IFERROR(SLOPE(HIST_D!$EO$8:INDEX(HIST_D!$EO$8:$EO$791,Control!$B$12),HIST_D!$CU$8:INDEX(HIST_D!$CU$8:$CU$791,Control!$B$12)),"") | Q8: =IFERROR(P8*(INDEX(HIST_D!$B$8:$B$791,1)/INDEX(HIST_D!$B$8:$B$791,Control!$B$11)-1),"") | R8: =IFERROR(L8-Q8,"")
A9: Colombia | B9: LatAm | C9: =INDEX(HIST_D!$BE$8:$BE$791,1) | D9: yes | E9: =IFERROR((INDEX(HIST_D!$BE$8:$BE$791,1)/INDEX(HIST_D!$BE$8:$BE$791,Control!$B$10)-1),"") | F9: =IFERROR((INDEX(HIST_D!$B$8:$B$791,1)/INDEX(HIST_D!$B$8:$B$791,Control!$B$10)-1),"") | G9: =IFERROR(E9-F9,"") | H9: =IFERROR(IF(ABS(F9)<0.005,"n/m",E9/F9),"n/m") | I9: =IFERROR(SLOPE(HIST_D!$EP$8:INDEX(HIST_D!$EP$8:$EP$791,Control!$B$12),HIST_D!$CU$8:INDEX(HIST_D!$CU$8:$CU$791,Control!$B$12)),"") | J9: =IFERROR(I9*(INDEX(HIST_D!$B$8:$B$791,1)/INDEX(HIST_D!$B$8:$B$791,Control!$B$10)-1),"") | K9: =IFERROR(E9-J9,"") | L9: =IFERROR((INDEX(HIST_D!$BE$8:$BE$791,1)/INDEX(HIST_D!$BE$8:$BE$791,Control!$B$11)-1),"") | M9: =IFERROR((INDEX(HIST_D!$B$8:$B$791,1)/INDEX(HIST_D!$B$8:$B$791,Control!$B$11)-1),"") | N9: =IFERROR(L9-M9,"") | O9: =IFERROR(IF(ABS(M9)<0.005,"n/m",L9/M9),"n/m") | P9: =IFERROR(SLOPE(HIST_D!$EP$8:INDEX(HIST_D!$EP$8:$EP$791,Control!$B$12),HIST_D!$CU$8:INDEX(HIST_D!$CU$8:$CU$791,Control!$B$12)),"") | Q9: =IFERROR(P9*(INDEX(HIST_D!$B$8:$B$791,1)/INDEX(HIST_D!$B$8:$B$791,Control!$B$11)-1),"") | R9: =IFERROR(L9-Q9,"")
A10: Peru | B10: LatAm | C10: =INDEX(HIST_D!$BF$8:$BF$791,1) | D10: yes | E10: =IFERROR((INDEX(HIST_D!$BF$8:$BF$791,1)/INDEX(HIST_D!$BF$8:$BF$791,Control!$B$10)-1),"") | F10: =IFERROR((INDEX(HIST_D!$B$8:$B$791,1)/INDEX(HIST_D!$B$8:$B$791,Control!$B$10)-1),"") | G10: =IFERROR(E10-F10,"") | H10: =IFERROR(IF(ABS(F10)<0.005,"n/m",E10/F10),"n/m") | I10: =IFERROR(SLOPE(HIST_D!$EQ$8:INDEX(HIST_D!$EQ$8:$EQ$791,Control!$B$12),HIST_D!$CU$8:INDEX(HIST_D!$CU$8:$CU$791,Control!$B$12)),"") | J10: =IFERROR(I10*(INDEX(HIST_D!$B$8:$B$791,1)/INDEX(HIST_D!$B$8:$B$791,Control!$B$10)-1),"") | K10: =IFERROR(E10-J10,"") | L10: =IFERROR((INDEX(HIST_D!$BF$8:$BF$791,1)/INDEX(HIST_D!$BF$8:$BF$791,Control!$B$11)-1),"") | M10: =IFERROR((INDEX(HIST_D!$B$8:$B$791,1)/INDEX(HIST_D!$B$8:$B$791,Control!$B$11)-1),"") | N10: =IFERROR(L10-M10,"") | O10: =IFERROR(IF(ABS(M10)<0.005,"n/m",L10/M10),"n/m") | P10: =IFERROR(SLOPE(HIST_D!$EQ$8:INDEX(HIST_D!$EQ$8:$EQ$791,Control!$B$12),HIST_D!$CU$8:INDEX(HIST_D!$CU$8:$CU$791,Control!$B$12)),"") | Q10: =IFERROR(P10*(INDEX(HIST_D!$B$8:$B$791,1)/INDEX(HIST_D!$B$8:$B$791,Control!$B$11)-1),"") | R10: =IFERROR(L10-Q10,"")
A11: LatAm average | B11: n=5 | E11: =IFERROR(AVERAGE(E6,E7,E8,E9,E10),"") | F11: =IFERROR(AVERAGE(F6,F7,F8,F9,F10),"") | G11: =IFERROR(AVERAGE(G6,G7,G8,G9,G10),"") | H11: =IFERROR(IF(ABS(F11)<0.005,"n/m",E11/F11),"n/m") | I11: =IFERROR(AVERAGE(I6,I7,I8,I9,I10),"") | J11: =IFERROR(AVERAGE(J6,J7,J8,J9,J10),"") | K11: =IFERROR(AVERAGE(K6,K7,K8,K9,K10),"") | L11: =IFERROR(AVERAGE(L6,L7,L8,L9,L10),"") | M11: =IFERROR(AVERAGE(M6,M7,M8,M9,M10),"") | N11: =IFERROR(AVERAGE(N6,N7,N8,N9,N10),"") | O11: =IFERROR(IF(ABS(M11)<0.005,"n/m",L11/M11),"n/m") | P11: =IFERROR(AVERAGE(P6,P7,P8,P9,P10),"") | Q11: =IFERROR(AVERAGE(Q6,Q7,Q8,Q9,Q10),"") | R11: =IFERROR(AVERAGE(R6,R7,R8,R9,R10),"")
A12: =IFERROR("LatAm: MSCI in USD "&TEXT($E$11,"+0.0%;-0.0%")&" on the month against MSCI World "&TEXT($F$11,"+0.0%;-0.0%")&", so "&TEXT($G$11,"+0.0%;-0.0%")&" is relative"&IF(ISNUMBER($H$11)," (pass-through "&TEXT($H$11,"0.00")&"x)","")&". Against a 2y beta to World of "&TEXT($I$11,"0.00")&" the surprise is "&TEXT($K$11,"+0.0%;-0.0%")&". YTD: "&TEXT($L$11,"+0.0%;-0.0%")&" against World "&TEXT($M$11,"+0.0%;-0.0%")&", relative "&TEXT($N$11,"+0.0%;-0.0%")&". "&IF($K$11>0.01,"Outran what the global beta implies — an EM earnings story, not a rates story.",IF($K$11<-0.01,"Lagged what the global beta implies — EM-specific weakness.","In line with the global beta; nothing EM-specific.")),"")
A14: EM EUROPE
A15: Country | B15: Region | C15: Level | D15: In avg | E15: 1M: Total: USD return | F15: 1M: US/DM-driven: MSCI World return | G15: 1M: Intrinsic: relative to World | H15: 1M: Pass-through (total / World) | I15: 1M: Beta to MSCI World (2y) | J15: 1M: Predicted by beta | K15: 1M: Surprise: actual less predicted | L15: YTD: Total: USD return | M15: YTD: US/DM-driven: MSCI World return | N15: YTD: Intrinsic: relative to World | O15: YTD: Pass-through (total / World) | P15: YTD: Beta to MSCI World (2y) | Q15: YTD: Predicted by beta | R15: YTD: Surprise: actual less predicted
A16: Poland | B16: EM Europe | C16: =INDEX(HIST_D!$BG$8:$BG$791,1) | D16: yes | E16: =IFERROR((INDEX(HIST_D!$BG$8:$BG$791,1)/INDEX(HIST_D!$BG$8:$BG$791,Control!$B$10)-1),"") | F16: =IFERROR((INDEX(HIST_D!$B$8:$B$791,1)/INDEX(HIST_D!$B$8:$B$791,Control!$B$10)-1),"") | G16: =IFERROR(E16-F16,"") | H16: =IFERROR(IF(ABS(F16)<0.005,"n/m",E16/F16),"n/m") | I16: =IFERROR(SLOPE(HIST_D!$ER$8:INDEX(HIST_D!$ER$8:$ER$791,Control!$B$12),HIST_D!$CU$8:INDEX(HIST_D!$CU$8:$CU$791,Control!$B$12)),"") | J16: =IFERROR(I16*(INDEX(HIST_D!$B$8:$B$791,1)/INDEX(HIST_D!$B$8:$B$791,Control!$B$10)-1),"") | K16: =IFERROR(E16-J16,"") | L16: =IFERROR((INDEX(HIST_D!$BG$8:$BG$791,1)/INDEX(HIST_D!$BG$8:$BG$791,Control!$B$11)-1),"") | M16: =IFERROR((INDEX(HIST_D!$B$8:$B$791,1)/INDEX(HIST_D!$B$8:$B$791,Control!$B$11)-1),"") | N16: =IFERROR(L16-M16,"") | O16: =IFERROR(IF(ABS(M16)<0.005,"n/m",L16/M16),"n/m") | P16: =IFERROR(SLOPE(HIST_D!$ER$8:INDEX(HIST_D!$ER$8:$ER$791,Control!$B$12),HIST_D!$CU$8:INDEX(HIST_D!$CU$8:$CU$791,Control!$B$12)),"") | Q16: =IFERROR(P16*(INDEX(HIST_D!$B$8:$B$791,1)/INDEX(HIST_D!$B$8:$B$791,Control!$B$11)-1),"") | R16: =IFERROR(L16-Q16,"")
A17: Hungary | B17: EM Europe | C17: =INDEX(HIST_D!$BH$8:$BH$791,1) | D17: yes | E17: =IFERROR((INDEX(HIST_D!$BH$8:$BH$791,1)/INDEX(HIST_D!$BH$8:$BH$791,Control!$B$10)-1),"") | F17: =IFERROR((INDEX(HIST_D!$B$8:$B$791,1)/INDEX(HIST_D!$B$8:$B$791,Control!$B$10)-1),"") | G17: =IFERROR(E17-F17,"") | H17: =IFERROR(IF(ABS(F17)<0.005,"n/m",E17/F17),"n/m") | I17: =IFERROR(SLOPE(HIST_D!$ES$8:INDEX(HIST_D!$ES$8:$ES$791,Control!$B$12),HIST_D!$CU$8:INDEX(HIST_D!$CU$8:$CU$791,Control!$B$12)),"") | J17: =IFERROR(I17*(INDEX(HIST_D!$B$8:$B$791,1)/INDEX(HIST_D!$B$8:$B$791,Control!$B$10)-1),"") | K17: =IFERROR(E17-J17,"") | L17: =IFERROR((INDEX(HIST_D!$BH$8:$BH$791,1)/INDEX(HIST_D!$BH$8:$BH$791,Control!$B$11)-1),"") | M17: =IFERROR((INDEX(HIST_D!$B$8:$B$791,1)/INDEX(HIST_D!$B$8:$B$791,Control!$B$11)-1),"") | N17: =IFERROR(L17-M17,"") | O17: =IFERROR(IF(ABS(M17)<0.005,"n/m",L17/M17),"n/m") | P17: =IFERROR(SLOPE(HIST_D!$ES$8:INDEX(HIST_D!$ES$8:$ES$791,Control!$B$12),HIST_D!$CU$8:INDEX(HIST_D!$CU$8:$CU$791,Control!$B$12)),"") | Q17: =IFERROR(P17*(INDEX(HIST_D!$B$8:$B$791,1)/INDEX(HIST_D!$B$8:$B$791,Control!$B$11)-1),"") | R17: =IFERROR(L17-Q17,"")
A18: Czechia | B18: EM Europe | C18: =INDEX(HIST_D!$BI$8:$BI$791,1) | D18: yes | E18: =IFERROR((INDEX(HIST_D!$BI$8:$BI$791,1)/INDEX(HIST_D!$BI$8:$BI$791,Control!$B$10)-1),"") | F18: =IFERROR((INDEX(HIST_D!$B$8:$B$791,1)/INDEX(HIST_D!$B$8:$B$791,Control!$B$10)-1),"") | G18: =IFERROR(E18-F18,"") | H18: =IFERROR(IF(ABS(F18)<0.005,"n/m",E18/F18),"n/m") | I18: =IFERROR(SLOPE(HIST_D!$ET$8:INDEX(HIST_D!$ET$8:$ET$791,Control!$B$12),HIST_D!$CU$8:INDEX(HIST_D!$CU$8:$CU$791,Control!$B$12)),"") | J18: =IFERROR(I18*(INDEX(HIST_D!$B$8:$B$791,1)/INDEX(HIST_D!$B$8:$B$791,Control!$B$10)-1),"") | K18: =IFERROR(E18-J18,"") | L18: =IFERROR((INDEX(HIST_D!$BI$8:$BI$791,1)/INDEX(HIST_D!$BI$8:$BI$791,Control!$B$11)-1),"") | M18: =IFERROR((INDEX(HIST_D!$B$8:$B$791,1)/INDEX(HIST_D!$B$8:$B$791,Control!$B$11)-1),"") | N18: =IFERROR(L18-M18,"") | O18: =IFERROR(IF(ABS(M18)<0.005,"n/m",L18/M18),"n/m") | P18: =IFERROR(SLOPE(HIST_D!$ET$8:INDEX(HIST_D!$ET$8:$ET$791,Control!$B$12),HIST_D!$CU$8:INDEX(HIST_D!$CU$8:$CU$791,Control!$B$12)),"") | Q18: =IFERROR(P18*(INDEX(HIST_D!$B$8:$B$791,1)/INDEX(HIST_D!$B$8:$B$791,Control!$B$11)-1),"") | R18: =IFERROR(L18-Q18,"")
A19: Romania | B19: EM Europe | C19: =INDEX(HIST_D!$BJ$8:$BJ$791,1) | D19: yes | E19: =IFERROR((INDEX(HIST_D!$BJ$8:$BJ$791,1)/INDEX(HIST_D!$BJ$8:$BJ$791,Control!$B$10)-1),"") | F19: =IFERROR((INDEX(HIST_D!$B$8:$B$791,1)/INDEX(HIST_D!$B$8:$B$791,Control!$B$10)-1),"") | G19: =IFERROR(E19-F19,"") | H19: =IFERROR(IF(ABS(F19)<0.005,"n/m",E19/F19),"n/m") | I19: =IFERROR(SLOPE(HIST_D!$EU$8:INDEX(HIST_D!$EU$8:$EU$791,Control!$B$12),HIST_D!$CU$8:INDEX(HIST_D!$CU$8:$CU$791,Control!$B$12)),"") | J19: =IFERROR(I19*(INDEX(HIST_D!$B$8:$B$791,1)/INDEX(HIST_D!$B$8:$B$791,Control!$B$10)-1),"") | K19: =IFERROR(E19-J19,"") | L19: =IFERROR((INDEX(HIST_D!$BJ$8:$BJ$791,1)/INDEX(HIST_D!$BJ$8:$BJ$791,Control!$B$11)-1),"") | M19: =IFERROR((INDEX(HIST_D!$B$8:$B$791,1)/INDEX(HIST_D!$B$8:$B$791,Control!$B$11)-1),"") | N19: =IFERROR(L19-M19,"") | O19: =IFERROR(IF(ABS(M19)<0.005,"n/m",L19/M19),"n/m") | P19: =IFERROR(SLOPE(HIST_D!$EU$8:INDEX(HIST_D!$EU$8:$EU$791,Control!$B$12),HIST_D!$CU$8:INDEX(HIST_D!$CU$8:$CU$791,Control!$B$12)),"") | Q19: =IFERROR(P19*(INDEX(HIST_D!$B$8:$B$791,1)/INDEX(HIST_D!$B$8:$B$791,Control!$B$11)-1),"") | R19: =IFERROR(L19-Q19,"")
A20: Turkiye | B20: EM Europe | C20: =INDEX(HIST_D!$BK$8:$BK$791,1) | D20: yes | E20: =IFERROR((INDEX(HIST_D!$BK$8:$BK$791,1)/INDEX(HIST_D!$BK$8:$BK$791,Control!$B$10)-1),"") | F20: =IFERROR((INDEX(HIST_D!$B$8:$B$791,1)/INDEX(HIST_D!$B$8:$B$791,Control!$B$10)-1),"") | G20: =IFERROR(E20-F20,"") | H20: =IFERROR(IF(ABS(F20)<0.005,"n/m",E20/F20),"n/m") | I20: =IFERROR(SLOPE(HIST_D!$EV$8:INDEX(HIST_D!$EV$8:$EV$791,Control!$B$12),HIST_D!$CU$8:INDEX(HIST_D!$CU$8:$CU$791,Control!$B$12)),"") | J20: =IFERROR(I20*(INDEX(HIST_D!$B$8:$B$791,1)/INDEX(HIST_D!$B$8:$B$791,Control!$B$10)-1),"") | K20: =IFERROR(E20-J20,"") | L20: =IFERROR((INDEX(HIST_D!$BK$8:$BK$791,1)/INDEX(HIST_D!$BK$8:$BK$791,Control!$B$11)-1),"") | M20: =IFERROR((INDEX(HIST_D!$B$8:$B$791,1)/INDEX(HIST_D!$B$8:$B$791,Control!$B$11)-1),"") | N20: =IFERROR(L20-M20,"") | O20: =IFERROR(IF(ABS(M20)<0.005,"n/m",L20/M20),"n/m") | P20: =IFERROR(SLOPE(HIST_D!$EV$8:INDEX(HIST_D!$EV$8:$EV$791,Control!$B$12),HIST_D!$CU$8:INDEX(HIST_D!$CU$8:$CU$791,Control!$B$12)),"") | Q20: =IFERROR(P20*(INDEX(HIST_D!$B$8:$B$791,1)/INDEX(HIST_D!$B$8:$B$791,Control!$B$11)-1),"") | R20: =IFERROR(L20-Q20,"") | S20: excluded from rates and FX averages: structural depreciation and a 30% curve swamp an equal weight
A21: EM Europe average | B21: n=5 | E21: =IFERROR(AVERAGE(E16,E17,E18,E19,E20),"") | F21: =IFERROR(AVERAGE(F16,F17,F18,F19,F20),"") | G21: =IFERROR(AVERAGE(G16,G17,G18,G19,G20),"") | H21: =IFERROR(IF(ABS(F21)<0.005,"n/m",E21/F21),"n/m") | I21: =IFERROR(AVERAGE(I16,I17,I18,I19,I20),"") | J21: =IFERROR(AVERAGE(J16,J17,J18,J19,J20),"") | K21: =IFERROR(AVERAGE(K16,K17,K18,K19,K20),"") | L21: =IFERROR(AVERAGE(L16,L17,L18,L19,L20),"") | M21: =IFERROR(AVERAGE(M16,M17,M18,M19,M20),"") | N21: =IFERROR(AVERAGE(N16,N17,N18,N19,N20),"") | O21: =IFERROR(IF(ABS(M21)<0.005,"n/m",L21/M21),"n/m") | P21: =IFERROR(AVERAGE(P16,P17,P18,P19,P20),"") | Q21: =IFERROR(AVERAGE(Q16,Q17,Q18,Q19,Q20),"") | R21: =IFERROR(AVERAGE(R16,R17,R18,R19,R20),"")
A22: =IFERROR("EM Europe: MSCI in USD "&TEXT($E$21,"+0.0%;-0.0%")&" on the month against MSCI World "&TEXT($F$21,"+0.0%;-0.0%")&", so "&TEXT($G$21,"+0.0%;-0.0%")&" is relative"&IF(ISNUMBER($H$21)," (pass-through "&TEXT($H$21,"0.00")&"x)","")&". Against a 2y beta to World of "&TEXT($I$21,"0.00")&" the surprise is "&TEXT($K$21,"+0.0%;-0.0%")&". YTD: "&TEXT($L$21,"+0.0%;-0.0%")&" against World "&TEXT($M$21,"+0.0%;-0.0%")&", relative "&TEXT($N$21,"+0.0%;-0.0%")&". "&IF($K$21>0.01,"Outran what the global beta implies — an EM earnings story, not a rates story.",IF($K$21<-0.01,"Lagged what the global beta implies — EM-specific weakness.","In line with the global beta; nothing EM-specific.")),"")
A24: MIDDLE EAST
A25: Country | B25: Region | C25: Level | D25: In avg | E25: 1M: Total: USD return | F25: 1M: US/DM-driven: MSCI World return | G25: 1M: Intrinsic: relative to World | H25: 1M: Pass-through (total / World) | I25: 1M: Beta to MSCI World (2y) | J25: 1M: Predicted by beta | K25: 1M: Surprise: actual less predicted | L25: YTD: Total: USD return | M25: YTD: US/DM-driven: MSCI World return | N25: YTD: Intrinsic: relative to World | O25: YTD: Pass-through (total / World) | P25: YTD: Beta to MSCI World (2y) | Q25: YTD: Predicted by beta | R25: YTD: Surprise: actual less predicted
A26: Saudi Arabia | B26: Middle East | C26: =INDEX(HIST_D!$BL$8:$BL$791,1) | D26: yes | E26: =IFERROR((INDEX(HIST_D!$BL$8:$BL$791,1)/INDEX(HIST_D!$BL$8:$BL$791,Control!$B$10)-1),"") | F26: =IFERROR((INDEX(HIST_D!$B$8:$B$791,1)/INDEX(HIST_D!$B$8:$B$791,Control!$B$10)-1),"") | G26: =IFERROR(E26-F26,"") | H26: =IFERROR(IF(ABS(F26)<0.005,"n/m",E26/F26),"n/m") | I26: =IFERROR(SLOPE(HIST_D!$EW$8:INDEX(HIST_D!$EW$8:$EW$791,Control!$B$12),HIST_D!$CU$8:INDEX(HIST_D!$CU$8:$CU$791,Control!$B$12)),"") | J26: =IFERROR(I26*(INDEX(HIST_D!$B$8:$B$791,1)/INDEX(HIST_D!$B$8:$B$791,Control!$B$10)-1),"") | K26: =IFERROR(E26-J26,"") | L26: =IFERROR((INDEX(HIST_D!$BL$8:$BL$791,1)/INDEX(HIST_D!$BL$8:$BL$791,Control!$B$11)-1),"") | M26: =IFERROR((INDEX(HIST_D!$B$8:$B$791,1)/INDEX(HIST_D!$B$8:$B$791,Control!$B$11)-1),"") | N26: =IFERROR(L26-M26,"") | O26: =IFERROR(IF(ABS(M26)<0.005,"n/m",L26/M26),"n/m") | P26: =IFERROR(SLOPE(HIST_D!$EW$8:INDEX(HIST_D!$EW$8:$EW$791,Control!$B$12),HIST_D!$CU$8:INDEX(HIST_D!$CU$8:$CU$791,Control!$B$12)),"") | Q26: =IFERROR(P26*(INDEX(HIST_D!$B$8:$B$791,1)/INDEX(HIST_D!$B$8:$B$791,Control!$B$11)-1),"") | R26: =IFERROR(L26-Q26,"") | S26: pegged; no local generic — credit only
A27: UAE (Abu Dhabi) | B27: Middle East | C27: =INDEX(HIST_D!$BM$8:$BM$791,1) | D27: yes | E27: =IFERROR((INDEX(HIST_D!$BM$8:$BM$791,1)/INDEX(HIST_D!$BM$8:$BM$791,Control!$B$10)-1),"") | F27: =IFERROR((INDEX(HIST_D!$B$8:$B$791,1)/INDEX(HIST_D!$B$8:$B$791,Control!$B$10)-1),"") | G27: =IFERROR(E27-F27,"") | H27: =IFERROR(IF(ABS(F27)<0.005,"n/m",E27/F27),"n/m") | I27: =IFERROR(SLOPE(HIST_D!$EX$8:INDEX(HIST_D!$EX$8:$EX$791,Control!$B$12),HIST_D!$CU$8:INDEX(HIST_D!$CU$8:$CU$791,Control!$B$12)),"") | J27: =IFERROR(I27*(INDEX(HIST_D!$B$8:$B$791,1)/INDEX(HIST_D!$B$8:$B$791,Control!$B$10)-1),"") | K27: =IFERROR(E27-J27,"") | L27: =IFERROR((INDEX(HIST_D!$BM$8:$BM$791,1)/INDEX(HIST_D!$BM$8:$BM$791,Control!$B$11)-1),"") | M27: =IFERROR((INDEX(HIST_D!$B$8:$B$791,1)/INDEX(HIST_D!$B$8:$B$791,Control!$B$11)-1),"") | N27: =IFERROR(L27-M27,"") | O27: =IFERROR(IF(ABS(M27)<0.005,"n/m",L27/M27),"n/m") | P27: =IFERROR(SLOPE(HIST_D!$EX$8:INDEX(HIST_D!$EX$8:$EX$791,Control!$B$12),HIST_D!$CU$8:INDEX(HIST_D!$CU$8:$CU$791,Control!$B$12)),"") | Q27: =IFERROR(P27*(INDEX(HIST_D!$B$8:$B$791,1)/INDEX(HIST_D!$B$8:$B$791,Control!$B$11)-1),"") | R27: =IFERROR(L27-Q27,"") | S27: pegged; no local generic — credit only
A28: Qatar | B28: Middle East | C28: =INDEX(HIST_D!$BN$8:$BN$791,1) | D28: yes | E28: =IFERROR((INDEX(HIST_D!$BN$8:$BN$791,1)/INDEX(HIST_D!$BN$8:$BN$791,Control!$B$10)-1),"") | F28: =IFERROR((INDEX(HIST_D!$B$8:$B$791,1)/INDEX(HIST_D!$B$8:$B$791,Control!$B$10)-1),"") | G28: =IFERROR(E28-F28,"") | H28: =IFERROR(IF(ABS(F28)<0.005,"n/m",E28/F28),"n/m") | I28: =IFERROR(SLOPE(HIST_D!$EY$8:INDEX(HIST_D!$EY$8:$EY$791,Control!$B$12),HIST_D!$CU$8:INDEX(HIST_D!$CU$8:$CU$791,Control!$B$12)),"") | J28: =IFERROR(I28*(INDEX(HIST_D!$B$8:$B$791,1)/INDEX(HIST_D!$B$8:$B$791,Control!$B$10)-1),"") | K28: =IFERROR(E28-J28,"") | L28: =IFERROR((INDEX(HIST_D!$BN$8:$BN$791,1)/INDEX(HIST_D!$BN$8:$BN$791,Control!$B$11)-1),"") | M28: =IFERROR((INDEX(HIST_D!$B$8:$B$791,1)/INDEX(HIST_D!$B$8:$B$791,Control!$B$11)-1),"") | N28: =IFERROR(L28-M28,"") | O28: =IFERROR(IF(ABS(M28)<0.005,"n/m",L28/M28),"n/m") | P28: =IFERROR(SLOPE(HIST_D!$EY$8:INDEX(HIST_D!$EY$8:$EY$791,Control!$B$12),HIST_D!$CU$8:INDEX(HIST_D!$CU$8:$CU$791,Control!$B$12)),"") | Q28: =IFERROR(P28*(INDEX(HIST_D!$B$8:$B$791,1)/INDEX(HIST_D!$B$8:$B$791,Control!$B$11)-1),"") | R28: =IFERROR(L28-Q28,"") | S28: pegged; no local generic — credit only
A29: Israel | B29: Middle East | C29: =INDEX(HIST_D!$BO$8:$BO$791,1) | D29: yes | E29: =IFERROR((INDEX(HIST_D!$BO$8:$BO$791,1)/INDEX(HIST_D!$BO$8:$BO$791,Control!$B$10)-1),"") | F29: =IFERROR((INDEX(HIST_D!$B$8:$B$791,1)/INDEX(HIST_D!$B$8:$B$791,Control!$B$10)-1),"") | G29: =IFERROR(E29-F29,"") | H29: =IFERROR(IF(ABS(F29)<0.005,"n/m",E29/F29),"n/m") | I29: =IFERROR(SLOPE(HIST_D!$EZ$8:INDEX(HIST_D!$EZ$8:$EZ$791,Control!$B$12),HIST_D!$CU$8:INDEX(HIST_D!$CU$8:$CU$791,Control!$B$12)),"") | J29: =IFERROR(I29*(INDEX(HIST_D!$B$8:$B$791,1)/INDEX(HIST_D!$B$8:$B$791,Control!$B$10)-1),"") | K29: =IFERROR(E29-J29,"") | L29: =IFERROR((INDEX(HIST_D!$BO$8:$BO$791,1)/INDEX(HIST_D!$BO$8:$BO$791,Control!$B$11)-1),"") | M29: =IFERROR((INDEX(HIST_D!$B$8:$B$791,1)/INDEX(HIST_D!$B$8:$B$791,Control!$B$11)-1),"") | N29: =IFERROR(L29-M29,"") | O29: =IFERROR(IF(ABS(M29)<0.005,"n/m",L29/M29),"n/m") | P29: =IFERROR(SLOPE(HIST_D!$EZ$8:INDEX(HIST_D!$EZ$8:$EZ$791,Control!$B$12),HIST_D!$CU$8:INDEX(HIST_D!$CU$8:$CU$791,Control!$B$12)),"") | Q29: =IFERROR(P29*(INDEX(HIST_D!$B$8:$B$791,1)/INDEX(HIST_D!$B$8:$B$791,Control!$B$11)-1),"") | R29: =IFERROR(L29-Q29,"")
A30: Egypt | B30: Middle East | C30: =INDEX(HIST_D!$BP$8:$BP$791,1) | D30: yes | E30: =IFERROR((INDEX(HIST_D!$BP$8:$BP$791,1)/INDEX(HIST_D!$BP$8:$BP$791,Control!$B$10)-1),"") | F30: =IFERROR((INDEX(HIST_D!$B$8:$B$791,1)/INDEX(HIST_D!$B$8:$B$791,Control!$B$10)-1),"") | G30: =IFERROR(E30-F30,"") | H30: =IFERROR(IF(ABS(F30)<0.005,"n/m",E30/F30),"n/m") | I30: =IFERROR(SLOPE(HIST_D!$FA$8:INDEX(HIST_D!$FA$8:$FA$791,Control!$B$12),HIST_D!$CU$8:INDEX(HIST_D!$CU$8:$CU$791,Control!$B$12)),"") | J30: =IFERROR(I30*(INDEX(HIST_D!$B$8:$B$791,1)/INDEX(HIST_D!$B$8:$B$791,Control!$B$10)-1),"") | K30: =IFERROR(E30-J30,"") | L30: =IFERROR((INDEX(HIST_D!$BP$8:$BP$791,1)/INDEX(HIST_D!$BP$8:$BP$791,Control!$B$11)-1),"") | M30: =IFERROR((INDEX(HIST_D!$B$8:$B$791,1)/INDEX(HIST_D!$B$8:$B$791,Control!$B$11)-1),"") | N30: =IFERROR(L30-M30,"") | O30: =IFERROR(IF(ABS(M30)<0.005,"n/m",L30/M30),"n/m") | P30: =IFERROR(SLOPE(HIST_D!$FA$8:INDEX(HIST_D!$FA$8:$FA$791,Control!$B$12),HIST_D!$CU$8:INDEX(HIST_D!$CU$8:$CU$791,Control!$B$12)),"") | Q30: =IFERROR(P30*(INDEX(HIST_D!$B$8:$B$791,1)/INDEX(HIST_D!$B$8:$B$791,Control!$B$11)-1),"") | R30: =IFERROR(L30-Q30,"") | S30: excluded from FX average: managed float with step devaluations; GTEGP10Y is Verify
A31: Middle East average | B31: n=5 | E31: =IFERROR(AVERAGE(E26,E27,E28,E29,E30),"") | F31: =IFERROR(AVERAGE(F26,F27,F28,F29,F30),"") | G31: =IFERROR(AVERAGE(G26,G27,G28,G29,G30),"") | H31: =IFERROR(IF(ABS(F31)<0.005,"n/m",E31/F31),"n/m") | I31: =IFERROR(AVERAGE(I26,I27,I28,I29,I30),"") | J31: =IFERROR(AVERAGE(J26,J27,J28,J29,J30),"") | K31: =IFERROR(AVERAGE(K26,K27,K28,K29,K30),"") | L31: =IFERROR(AVERAGE(L26,L27,L28,L29,L30),"") | M31: =IFERROR(AVERAGE(M26,M27,M28,M29,M30),"") | N31: =IFERROR(AVERAGE(N26,N27,N28,N29,N30),"") | O31: =IFERROR(IF(ABS(M31)<0.005,"n/m",L31/M31),"n/m") | P31: =IFERROR(AVERAGE(P26,P27,P28,P29,P30),"") | Q31: =IFERROR(AVERAGE(Q26,Q27,Q28,Q29,Q30),"") | R31: =IFERROR(AVERAGE(R26,R27,R28,R29,R30),"")
A32: =IFERROR("Middle East: MSCI in USD "&TEXT($E$31,"+0.0%;-0.0%")&" on the month against MSCI World "&TEXT($F$31,"+0.0%;-0.0%")&", so "&TEXT($G$31,"+0.0%;-0.0%")&" is relative"&IF(ISNUMBER($H$31)," (pass-through "&TEXT($H$31,"0.00")&"x)","")&". Against a 2y beta to World of "&TEXT($I$31,"0.00")&" the surprise is "&TEXT($K$31,"+0.0%;-0.0%")&". YTD: "&TEXT($L$31,"+0.0%;-0.0%")&" against World "&TEXT($M$31,"+0.0%;-0.0%")&", relative "&TEXT($N$31,"+0.0%;-0.0%")&". "&IF($K$31>0.01,"Outran what the global beta implies — an EM earnings story, not a rates story.",IF($K$31<-0.01,"Lagged what the global beta implies — EM-specific weakness.","In line with the global beta; nothing EM-specific.")),"")
A34: EM ASIA
A35: Country | B35: Region | C35: Level | D35: In avg | E35: 1M: Total: USD return | F35: 1M: US/DM-driven: MSCI World return | G35: 1M: Intrinsic: relative to World | H35: 1M: Pass-through (total / World) | I35: 1M: Beta to MSCI World (2y) | J35: 1M: Predicted by beta | K35: 1M: Surprise: actual less predicted | L35: YTD: Total: USD return | M35: YTD: US/DM-driven: MSCI World return | N35: YTD: Intrinsic: relative to World | O35: YTD: Pass-through (total / World) | P35: YTD: Beta to MSCI World (2y) | Q35: YTD: Predicted by beta | R35: YTD: Surprise: actual less predicted
A36: China | B36: EM Asia | C36: =INDEX(HIST_D!$BQ$8:$BQ$791,1) | D36: yes | E36: =IFERROR((INDEX(HIST_D!$BQ$8:$BQ$791,1)/INDEX(HIST_D!$BQ$8:$BQ$791,Control!$B$10)-1),"") | F36: =IFERROR((INDEX(HIST_D!$B$8:$B$791,1)/INDEX(HIST_D!$B$8:$B$791,Control!$B$10)-1),"") | G36: =IFERROR(E36-F36,"") | H36: =IFERROR(IF(ABS(F36)<0.005,"n/m",E36/F36),"n/m") | I36: =IFERROR(SLOPE(HIST_D!$FB$8:INDEX(HIST_D!$FB$8:$FB$791,Control!$B$12),HIST_D!$CU$8:INDEX(HIST_D!$CU$8:$CU$791,Control!$B$12)),"") | J36: =IFERROR(I36*(INDEX(HIST_D!$B$8:$B$791,1)/INDEX(HIST_D!$B$8:$B$791,Control!$B$10)-1),"") | K36: =IFERROR(E36-J36,"") | L36: =IFERROR((INDEX(HIST_D!$BQ$8:$BQ$791,1)/INDEX(HIST_D!$BQ$8:$BQ$791,Control!$B$11)-1),"") | M36: =IFERROR((INDEX(HIST_D!$B$8:$B$791,1)/INDEX(HIST_D!$B$8:$B$791,Control!$B$11)-1),"") | N36: =IFERROR(L36-M36,"") | O36: =IFERROR(IF(ABS(M36)<0.005,"n/m",L36/M36),"n/m") | P36: =IFERROR(SLOPE(HIST_D!$FB$8:INDEX(HIST_D!$FB$8:$FB$791,Control!$B$12),HIST_D!$CU$8:INDEX(HIST_D!$CU$8:$CU$791,Control!$B$12)),"") | Q36: =IFERROR(P36*(INDEX(HIST_D!$B$8:$B$791,1)/INDEX(HIST_D!$B$8:$B$791,Control!$B$11)-1),"") | R36: =IFERROR(L36-Q36,"")
A37: India | B37: EM Asia | C37: =INDEX(HIST_D!$BR$8:$BR$791,1) | D37: yes | E37: =IFERROR((INDEX(HIST_D!$BR$8:$BR$791,1)/INDEX(HIST_D!$BR$8:$BR$791,Control!$B$10)-1),"") | F37: =IFERROR((INDEX(HIST_D!$B$8:$B$791,1)/INDEX(HIST_D!$B$8:$B$791,Control!$B$10)-1),"") | G37: =IFERROR(E37-F37,"") | H37: =IFERROR(IF(ABS(F37)<0.005,"n/m",E37/F37),"n/m") | I37: =IFERROR(SLOPE(HIST_D!$FC$8:INDEX(HIST_D!$FC$8:$FC$791,Control!$B$12),HIST_D!$CU$8:INDEX(HIST_D!$CU$8:$CU$791,Control!$B$12)),"") | J37: =IFERROR(I37*(INDEX(HIST_D!$B$8:$B$791,1)/INDEX(HIST_D!$B$8:$B$791,Control!$B$10)-1),"") | K37: =IFERROR(E37-J37,"") | L37: =IFERROR((INDEX(HIST_D!$BR$8:$BR$791,1)/INDEX(HIST_D!$BR$8:$BR$791,Control!$B$11)-1),"") | M37: =IFERROR((INDEX(HIST_D!$B$8:$B$791,1)/INDEX(HIST_D!$B$8:$B$791,Control!$B$11)-1),"") | N37: =IFERROR(L37-M37,"") | O37: =IFERROR(IF(ABS(M37)<0.005,"n/m",L37/M37),"n/m") | P37: =IFERROR(SLOPE(HIST_D!$FC$8:INDEX(HIST_D!$FC$8:$FC$791,Control!$B$12),HIST_D!$CU$8:INDEX(HIST_D!$CU$8:$CU$791,Control!$B$12)),"") | Q37: =IFERROR(P37*(INDEX(HIST_D!$B$8:$B$791,1)/INDEX(HIST_D!$B$8:$B$791,Control!$B$11)-1),"") | R37: =IFERROR(L37-Q37,"") | S37: no sovereign USD debt, no CDS — rates and FX only
A38: Indonesia | B38: EM Asia | C38: =INDEX(HIST_D!$BS$8:$BS$791,1) | D38: yes | E38: =IFERROR((INDEX(HIST_D!$BS$8:$BS$791,1)/INDEX(HIST_D!$BS$8:$BS$791,Control!$B$10)-1),"") | F38: =IFERROR((INDEX(HIST_D!$B$8:$B$791,1)/INDEX(HIST_D!$B$8:$B$791,Control!$B$10)-1),"") | G38: =IFERROR(E38-F38,"") | H38: =IFERROR(IF(ABS(F38)<0.005,"n/m",E38/F38),"n/m") | I38: =IFERROR(SLOPE(HIST_D!$FD$8:INDEX(HIST_D!$FD$8:$FD$791,Control!$B$12),HIST_D!$CU$8:INDEX(HIST_D!$CU$8:$CU$791,Control!$B$12)),"") | J38: =IFERROR(I38*(INDEX(HIST_D!$B$8:$B$791,1)/INDEX(HIST_D!$B$8:$B$791,Control!$B$10)-1),"") | K38: =IFERROR(E38-J38,"") | L38: =IFERROR((INDEX(HIST_D!$BS$8:$BS$791,1)/INDEX(HIST_D!$BS$8:$BS$791,Control!$B$11)-1),"") | M38: =IFERROR((INDEX(HIST_D!$B$8:$B$791,1)/INDEX(HIST_D!$B$8:$B$791,Control!$B$11)-1),"") | N38: =IFERROR(L38-M38,"") | O38: =IFERROR(IF(ABS(M38)<0.005,"n/m",L38/M38),"n/m") | P38: =IFERROR(SLOPE(HIST_D!$FD$8:INDEX(HIST_D!$FD$8:$FD$791,Control!$B$12),HIST_D!$CU$8:INDEX(HIST_D!$CU$8:$CU$791,Control!$B$12)),"") | Q38: =IFERROR(P38*(INDEX(HIST_D!$B$8:$B$791,1)/INDEX(HIST_D!$B$8:$B$791,Control!$B$11)-1),"") | R38: =IFERROR(L38-Q38,"")
A39: Korea | B39: EM Asia | C39: =INDEX(HIST_D!$BT$8:$BT$791,1) | D39: yes | E39: =IFERROR((INDEX(HIST_D!$BT$8:$BT$791,1)/INDEX(HIST_D!$BT$8:$BT$791,Control!$B$10)-1),"") | F39: =IFERROR((INDEX(HIST_D!$B$8:$B$791,1)/INDEX(HIST_D!$B$8:$B$791,Control!$B$10)-1),"") | G39: =IFERROR(E39-F39,"") | H39: =IFERROR(IF(ABS(F39)<0.005,"n/m",E39/F39),"n/m") | I39: =IFERROR(SLOPE(HIST_D!$FE$8:INDEX(HIST_D!$FE$8:$FE$791,Control!$B$12),HIST_D!$CU$8:INDEX(HIST_D!$CU$8:$CU$791,Control!$B$12)),"") | J39: =IFERROR(I39*(INDEX(HIST_D!$B$8:$B$791,1)/INDEX(HIST_D!$B$8:$B$791,Control!$B$10)-1),"") | K39: =IFERROR(E39-J39,"") | L39: =IFERROR((INDEX(HIST_D!$BT$8:$BT$791,1)/INDEX(HIST_D!$BT$8:$BT$791,Control!$B$11)-1),"") | M39: =IFERROR((INDEX(HIST_D!$B$8:$B$791,1)/INDEX(HIST_D!$B$8:$B$791,Control!$B$11)-1),"") | N39: =IFERROR(L39-M39,"") | O39: =IFERROR(IF(ABS(M39)<0.005,"n/m",L39/M39),"n/m") | P39: =IFERROR(SLOPE(HIST_D!$FE$8:INDEX(HIST_D!$FE$8:$FE$791,Control!$B$12),HIST_D!$CU$8:INDEX(HIST_D!$CU$8:$CU$791,Control!$B$12)),"") | Q39: =IFERROR(P39*(INDEX(HIST_D!$B$8:$B$791,1)/INDEX(HIST_D!$B$8:$B$791,Control!$B$11)-1),"") | R39: =IFERROR(L39-Q39,"")
A40: Thailand | B40: EM Asia | C40: =INDEX(HIST_D!$BU$8:$BU$791,1) | D40: yes | E40: =IFERROR((INDEX(HIST_D!$BU$8:$BU$791,1)/INDEX(HIST_D!$BU$8:$BU$791,Control!$B$10)-1),"") | F40: =IFERROR((INDEX(HIST_D!$B$8:$B$791,1)/INDEX(HIST_D!$B$8:$B$791,Control!$B$10)-1),"") | G40: =IFERROR(E40-F40,"") | H40: =IFERROR(IF(ABS(F40)<0.005,"n/m",E40/F40),"n/m") | I40: =IFERROR(SLOPE(HIST_D!$FF$8:INDEX(HIST_D!$FF$8:$FF$791,Control!$B$12),HIST_D!$CU$8:INDEX(HIST_D!$CU$8:$CU$791,Control!$B$12)),"") | J40: =IFERROR(I40*(INDEX(HIST_D!$B$8:$B$791,1)/INDEX(HIST_D!$B$8:$B$791,Control!$B$10)-1),"") | K40: =IFERROR(E40-J40,"") | L40: =IFERROR((INDEX(HIST_D!$BU$8:$BU$791,1)/INDEX(HIST_D!$BU$8:$BU$791,Control!$B$11)-1),"") | M40: =IFERROR((INDEX(HIST_D!$B$8:$B$791,1)/INDEX(HIST_D!$B$8:$B$791,Control!$B$11)-1),"") | N40: =IFERROR(L40-M40,"") | O40: =IFERROR(IF(ABS(M40)<0.005,"n/m",L40/M40),"n/m") | P40: =IFERROR(SLOPE(HIST_D!$FF$8:INDEX(HIST_D!$FF$8:$FF$791,Control!$B$12),HIST_D!$CU$8:INDEX(HIST_D!$CU$8:$CU$791,Control!$B$12)),"") | Q40: =IFERROR(P40*(INDEX(HIST_D!$B$8:$B$791,1)/INDEX(HIST_D!$B$8:$B$791,Control!$B$11)-1),"") | R40: =IFERROR(L40-Q40,"")
A41: Malaysia | B41: EM Asia | C41: =INDEX(HIST_D!$BV$8:$BV$791,1) | D41: yes | E41: =IFERROR((INDEX(HIST_D!$BV$8:$BV$791,1)/INDEX(HIST_D!$BV$8:$BV$791,Control!$B$10)-1),"") | F41: =IFERROR((INDEX(HIST_D!$B$8:$B$791,1)/INDEX(HIST_D!$B$8:$B$791,Control!$B$10)-1),"") | G41: =IFERROR(E41-F41,"") | H41: =IFERROR(IF(ABS(F41)<0.005,"n/m",E41/F41),"n/m") | I41: =IFERROR(SLOPE(HIST_D!$FG$8:INDEX(HIST_D!$FG$8:$FG$791,Control!$B$12),HIST_D!$CU$8:INDEX(HIST_D!$CU$8:$CU$791,Control!$B$12)),"") | J41: =IFERROR(I41*(INDEX(HIST_D!$B$8:$B$791,1)/INDEX(HIST_D!$B$8:$B$791,Control!$B$10)-1),"") | K41: =IFERROR(E41-J41,"") | L41: =IFERROR((INDEX(HIST_D!$BV$8:$BV$791,1)/INDEX(HIST_D!$BV$8:$BV$791,Control!$B$11)-1),"") | M41: =IFERROR((INDEX(HIST_D!$B$8:$B$791,1)/INDEX(HIST_D!$B$8:$B$791,Control!$B$11)-1),"") | N41: =IFERROR(L41-M41,"") | O41: =IFERROR(IF(ABS(M41)<0.005,"n/m",L41/M41),"n/m") | P41: =IFERROR(SLOPE(HIST_D!$FG$8:INDEX(HIST_D!$FG$8:$FG$791,Control!$B$12),HIST_D!$CU$8:INDEX(HIST_D!$CU$8:$CU$791,Control!$B$12)),"") | Q41: =IFERROR(P41*(INDEX(HIST_D!$B$8:$B$791,1)/INDEX(HIST_D!$B$8:$B$791,Control!$B$11)-1),"") | R41: =IFERROR(L41-Q41,"")
A42: Philippines | B42: EM Asia | C42: =INDEX(HIST_D!$BW$8:$BW$791,1) | D42: yes | E42: =IFERROR((INDEX(HIST_D!$BW$8:$BW$791,1)/INDEX(HIST_D!$BW$8:$BW$791,Control!$B$10)-1),"") | F42: =IFERROR((INDEX(HIST_D!$B$8:$B$791,1)/INDEX(HIST_D!$B$8:$B$791,Control!$B$10)-1),"") | G42: =IFERROR(E42-F42,"") | H42: =IFERROR(IF(ABS(F42)<0.005,"n/m",E42/F42),"n/m") | I42: =IFERROR(SLOPE(HIST_D!$FH$8:INDEX(HIST_D!$FH$8:$FH$791,Control!$B$12),HIST_D!$CU$8:INDEX(HIST_D!$CU$8:$CU$791,Control!$B$12)),"") | J42: =IFERROR(I42*(INDEX(HIST_D!$B$8:$B$791,1)/INDEX(HIST_D!$B$8:$B$791,Control!$B$10)-1),"") | K42: =IFERROR(E42-J42,"") | L42: =IFERROR((INDEX(HIST_D!$BW$8:$BW$791,1)/INDEX(HIST_D!$BW$8:$BW$791,Control!$B$11)-1),"") | M42: =IFERROR((INDEX(HIST_D!$B$8:$B$791,1)/INDEX(HIST_D!$B$8:$B$791,Control!$B$11)-1),"") | N42: =IFERROR(L42-M42,"") | O42: =IFERROR(IF(ABS(M42)<0.005,"n/m",L42/M42),"n/m") | P42: =IFERROR(SLOPE(HIST_D!$FH$8:INDEX(HIST_D!$FH$8:$FH$791,Control!$B$12),HIST_D!$CU$8:INDEX(HIST_D!$CU$8:$CU$791,Control!$B$12)),"") | Q42: =IFERROR(P42*(INDEX(HIST_D!$B$8:$B$791,1)/INDEX(HIST_D!$B$8:$B$791,Control!$B$11)-1),"") | R42: =IFERROR(L42-Q42,"")
A43: EM Asia average | B43: n=7 | E43: =IFERROR(AVERAGE(E36,E37,E38,E39,E40,E41,E42),"") | F43: =IFERROR(AVERAGE(F36,F37,F38,F39,F40,F41,F42),"") | G43: =IFERROR(AVERAGE(G36,G37,G38,G39,G40,G41,G42),"") | H43: =IFERROR(IF(ABS(F43)<0.005,"n/m",E43/F43),"n/m") | I43: =IFERROR(AVERAGE(I36,I37,I38,I39,I40,I41,I42),"") | J43: =IFERROR(AVERAGE(J36,J37,J38,J39,J40,J41,J42),"") | K43: =IFERROR(AVERAGE(K36,K37,K38,K39,K40,K41,K42),"") | L43: =IFERROR(AVERAGE(L36,L37,L38,L39,L40,L41,L42),"") | M43: =IFERROR(AVERAGE(M36,M37,M38,M39,M40,M41,M42),"") | N43: =IFERROR(AVERAGE(N36,N37,N38,N39,N40,N41,N42),"") | O43: =IFERROR(IF(ABS(M43)<0.005,"n/m",L43/M43),"n/m") | P43: =IFERROR(AVERAGE(P36,P37,P38,P39,P40,P41,P42),"") | Q43: =IFERROR(AVERAGE(Q36,Q37,Q38,Q39,Q40,Q41,Q42),"") | R43: =IFERROR(AVERAGE(R36,R37,R38,R39,R40,R41,R42),"")
A44: =IFERROR("EM Asia: MSCI in USD "&TEXT($E$43,"+0.0%;-0.0%")&" on the month against MSCI World "&TEXT($F$43,"+0.0%;-0.0%")&", so "&TEXT($G$43,"+0.0%;-0.0%")&" is relative"&IF(ISNUMBER($H$43)," (pass-through "&TEXT($H$43,"0.00")&"x)","")&". Against a 2y beta to World of "&TEXT($I$43,"0.00")&" the surprise is "&TEXT($K$43,"+0.0%;-0.0%")&". YTD: "&TEXT($L$43,"+0.0%;-0.0%")&" against World "&TEXT($M$43,"+0.0%;-0.0%")&", relative "&TEXT($N$43,"+0.0%;-0.0%")&". "&IF($K$43>0.01,"Outran what the global beta implies — an EM earnings story, not a rates story.",IF($K$43<-0.01,"Lagged what the global beta implies — EM-specific weakness.","In line with the global beta; nothing EM-specific.")),"")
A46: EM AVERAGE AND MEMO
A47: Country | B47: Region | C47: Level | D47: In avg | E47: 1M: Total: USD return | F47: 1M: US/DM-driven: MSCI World return | G47: 1M: Intrinsic: relative to World | H47: 1M: Pass-through (total / World) | I47: 1M: Beta to MSCI World (2y) | J47: 1M: Predicted by beta | K47: 1M: Surprise: actual less predicted | L47: YTD: Total: USD return | M47: YTD: US/DM-driven: MSCI World return | N47: YTD: Intrinsic: relative to World | O47: YTD: Pass-through (total / World) | P47: YTD: Beta to MSCI World (2y) | Q47: YTD: Predicted by beta | R47: YTD: Surprise: actual less predicted
A48: EM average (all flagged) | B48: n=22 | E48: =IFERROR(AVERAGE(E6,E7,E8,E9,E10,E16,E17,E18,E19,E20,E26,E27,E28,E29,E30,E36,E37,E38,E39,E40,E41,E42),"") | F48: =IFERROR(AVERAGE(F6,F7,F8,F9,F10,F16,F17,F18,F19,F20,F26,F27,F28,F29,F30,F36,F37,F38,F39,F40,F41,F42),"") | G48: =IFERROR(AVERAGE(G6,G7,G8,G9,G10,G16,G17,G18,G19,G20,G26,G27,G28,G29,G30,G36,G37,G38,G39,G40,G41,G42),"") | H48: =IFERROR(IF(ABS(F48)<0.005,"n/m",E48/F48),"n/m") | I48: =IFERROR(AVERAGE(I6,I7,I8,I9,I10,I16,I17,I18,I19,I20,I26,I27,I28,I29,I30,I36,I37,I38,I39,I40,I41,I42),"") | J48: =IFERROR(AVERAGE(J6,J7,J8,J9,J10,J16,J17,J18,J19,J20,J26,J27,J28,J29,J30,J36,J37,J38,J39,J40,J41,J42),"") | K48: =IFERROR(AVERAGE(K6,K7,K8,K9,K10,K16,K17,K18,K19,K20,K26,K27,K28,K29,K30,K36,K37,K38,K39,K40,K41,K42),"") | L48: =IFERROR(AVERAGE(L6,L7,L8,L9,L10,L16,L17,L18,L19,L20,L26,L27,L28,L29,L30,L36,L37,L38,L39,L40,L41,L42),"") | M48: =IFERROR(AVERAGE(M6,M7,M8,M9,M10,M16,M17,M18,M19,M20,M26,M27,M28,M29,M30,M36,M37,M38,M39,M40,M41,M42),"") | N48: =IFERROR(AVERAGE(N6,N7,N8,N9,N10,N16,N17,N18,N19,N20,N26,N27,N28,N29,N30,N36,N37,N38,N39,N40,N41,N42),"") | O48: =IFERROR(IF(ABS(M48)<0.005,"n/m",L48/M48),"n/m") | P48: =IFERROR(AVERAGE(P6,P7,P8,P9,P10,P16,P17,P18,P19,P20,P26,P27,P28,P29,P30,P36,P37,P38,P39,P40,P41,P42),"") | Q48: =IFERROR(AVERAGE(Q6,Q7,Q8,Q9,Q10,Q16,Q17,Q18,Q19,Q20,Q26,Q27,Q28,Q29,Q30,Q36,Q37,Q38,Q39,Q40,Q41,Q42),"") | R48: =IFERROR(AVERAGE(R6,R7,R8,R9,R10,R16,R17,R18,R19,R20,R26,R27,R28,R29,R30,R36,R37,R38,R39,R40,R41,R42),"")
A49: South Africa | B49: (memo) | C49: =INDEX(HIST_D!$BX$8:$BX$791,1) | D49: no | E49: =IFERROR((INDEX(HIST_D!$BX$8:$BX$791,1)/INDEX(HIST_D!$BX$8:$BX$791,Control!$B$10)-1),"") | F49: =IFERROR((INDEX(HIST_D!$B$8:$B$791,1)/INDEX(HIST_D!$B$8:$B$791,Control!$B$10)-1),"") | G49: =IFERROR(E49-F49,"") | H49: =IFERROR(IF(ABS(F49)<0.005,"n/m",E49/F49),"n/m") | I49: =IFERROR(SLOPE(HIST_D!$FI$8:INDEX(HIST_D!$FI$8:$FI$791,Control!$B$12),HIST_D!$CU$8:INDEX(HIST_D!$CU$8:$CU$791,Control!$B$12)),"") | J49: =IFERROR(I49*(INDEX(HIST_D!$B$8:$B$791,1)/INDEX(HIST_D!$B$8:$B$791,Control!$B$10)-1),"") | K49: =IFERROR(E49-J49,"") | L49: =IFERROR((INDEX(HIST_D!$BX$8:$BX$791,1)/INDEX(HIST_D!$BX$8:$BX$791,Control!$B$11)-1),"") | M49: =IFERROR((INDEX(HIST_D!$B$8:$B$791,1)/INDEX(HIST_D!$B$8:$B$791,Control!$B$11)-1),"") | N49: =IFERROR(L49-M49,"") | O49: =IFERROR(IF(ABS(M49)<0.005,"n/m",L49/M49),"n/m") | P49: =IFERROR(SLOPE(HIST_D!$FI$8:INDEX(HIST_D!$FI$8:$FI$791,Control!$B$12),HIST_D!$CU$8:INDEX(HIST_D!$CU$8:$CU$791,Control!$B$12)),"") | Q49: =IFERROR(P49*(INDEX(HIST_D!$B$8:$B$791,1)/INDEX(HIST_D!$B$8:$B$791,Control!$B$11)-1),"") | R49: =IFERROR(L49-Q49,"") | S49: not in any of the four regions you named; shown as a memo line, in no average
A50: MSCI EM — the benchmark | B50: memo | C50: =INDEX(HIST_D!$C$8:$C$791,1) | D50: no | E50: =IFERROR((INDEX(HIST_D!$C$8:$C$791,1)/INDEX(HIST_D!$C$8:$C$791,Control!$B$10)-1),"") | F50: =IFERROR((INDEX(HIST_D!$B$8:$B$791,1)/INDEX(HIST_D!$B$8:$B$791,Control!$B$10)-1),"") | G50: =IFERROR(E50-F50,"") | H50: =IFERROR(IF(ABS(F50)<0.005,"n/m",E50/F50),"n/m") | L50: =IFERROR((INDEX(HIST_D!$C$8:$C$791,1)/INDEX(HIST_D!$C$8:$C$791,Control!$B$11)-1),"") | M50: =IFERROR((INDEX(HIST_D!$B$8:$B$791,1)/INDEX(HIST_D!$B$8:$B$791,Control!$B$11)-1),"") | N50: =IFERROR(L50-M50,"") | O50: =IFERROR(IF(ABS(M50)<0.005,"n/m",L50/M50),"n/m") | S50: cap-weighted, so it will differ from the equal-weighted average above — China, Taiwan, India and Korea dominate it
A51: =IFERROR("EM: MSCI in USD "&TEXT($E$48,"+0.0%;-0.0%")&" on the month against MSCI World "&TEXT($F$48,"+0.0%;-0.0%")&", so "&TEXT($G$48,"+0.0%;-0.0%")&" is relative"&IF(ISNUMBER($H$48)," (pass-through "&TEXT($H$48,"0.00")&"x)","")&". Against a 2y beta to World of "&TEXT($I$48,"0.00")&" the surprise is "&TEXT($K$48,"+0.0%;-0.0%")&". YTD: "&TEXT($L$48,"+0.0%;-0.0%")&" against World "&TEXT($M$48,"+0.0%;-0.0%")&", relative "&TEXT($N$48,"+0.0%;-0.0%")&". "&IF($K$48>0.01,"Outran what the global beta implies — an EM earnings story, not a rates story.",IF($K$48<-0.01,"Lagged what the global beta implies — EM-specific weakness.","In line with the global beta; nothing EM-specific.")),"")

Sheet Credit
A1: EM USD SOVEREIGN CREDIT — 5y CDS as the spread, by country and region
A2: A 5y USD sovereign yield is UST 5Y + spread, so d(yield) = d(UST 5Y) + d(CDS 5Y). This split is exact: US-driven is Treasuries, intrinsic is the spread. US share = Treasuries / total yield move.
A4: LATAM
A5: Country | B5: Region | C5: Level | D5: In avg | E5: 1M: Total: d(UST 5Y + CDS) (bp) | F5: 1M: US-driven: d UST 5Y (bp) | G5: 1M: Intrinsic: d CDS 5Y (bp) | H5: 1M: US share (UST / total) | I5: 1M: Spread beta to UST 5Y (2y) | J5: 1M: Predicted d spread (bp) | K5: 1M: Spread surprise: actual less predicted (bp) | L5: YTD: Total: d(UST 5Y + CDS) (bp) | M5: YTD: US-driven: d UST 5Y (bp) | N5: YTD: Intrinsic: d CDS 5Y (bp) | O5: YTD: US share (UST / total) | P5: YTD: Spread beta to UST 5Y (2y) | Q5: YTD: Predicted d spread (bp) | R5: YTD: Spread surprise: actual less predicted (bp)
A6: Brazil | B6: LatAm | C6: =INDEX(HIST_D!$BY$8:$BY$791,1) | D6: yes | E6: =IFERROR((INDEX(HIST_D!$E$8:$E$791,1)-INDEX(HIST_D!$E$8:$E$791,Control!$B$10))*100+(INDEX(HIST_D!$BY$8:$BY$791,1)-INDEX(HIST_D!$BY$8:$BY$791,Control!$B$10)),"") | F6: =IFERROR((INDEX(HIST_D!$E$8:$E$791,1)-INDEX(HIST_D!$E$8:$E$791,Control!$B$10))*100,"") | G6: =IFERROR((INDEX(HIST_D!$BY$8:$BY$791,1)-INDEX(HIST_D!$BY$8:$BY$791,Control!$B$10)),"") | H6: =IFERROR(IF(ABS(E6)<1,"n/m",F6/E6),"n/m") | I6: =IFERROR(SLOPE(HIST_D!$FJ$8:INDEX(HIST_D!$FJ$8:$FJ$791,Control!$B$12),HIST_D!$CW$8:INDEX(HIST_D!$CW$8:$CW$791,Control!$B$12)),"") | J6: =IFERROR(I6*(INDEX(HIST_D!$E$8:$E$791,1)-INDEX(HIST_D!$E$8:$E$791,Control!$B$10))*100,"") | K6: =IFERROR(G6-J6,"") | L6: =IFERROR((INDEX(HIST_D!$E$8:$E$791,1)-INDEX(HIST_D!$E$8:$E$791,Control!$B$11))*100+(INDEX(HIST_D!$BY$8:$BY$791,1)-INDEX(HIST_D!$BY$8:$BY$791,Control!$B$11)),"") | M6: =IFERROR((INDEX(HIST_D!$E$8:$E$791,1)-INDEX(HIST_D!$E$8:$E$791,Control!$B$11))*100,"") | N6: =IFERROR((INDEX(HIST_D!$BY$8:$BY$791,1)-INDEX(HIST_D!$BY$8:$BY$791,Control!$B$11)),"") | O6: =IFERROR(IF(ABS(L6)<1,"n/m",M6/L6),"n/m") | P6: =IFERROR(SLOPE(HIST_D!$FJ$8:INDEX(HIST_D!$FJ$8:$FJ$791,Control!$B$12),HIST_D!$CW$8:INDEX(HIST_D!$CW$8:$CW$791,Control!$B$12)),"") | Q6: =IFERROR(P6*(INDEX(HIST_D!$E$8:$E$791,1)-INDEX(HIST_D!$E$8:$E$791,Control!$B$11))*100,"") | R6: =IFERROR(N6-Q6,"")
A7: Mexico | B7: LatAm | C7: =INDEX(HIST_D!$BZ$8:$BZ$791,1) | D7: yes | E7: =IFERROR((INDEX(HIST_D!$E$8:$E$791,1)-INDEX(HIST_D!$E$8:$E$791,Control!$B$10))*100+(INDEX(HIST_D!$BZ$8:$BZ$791,1)-INDEX(HIST_D!$BZ$8:$BZ$791,Control!$B$10)),"") | F7: =IFERROR((INDEX(HIST_D!$E$8:$E$791,1)-INDEX(HIST_D!$E$8:$E$791,Control!$B$10))*100,"") | G7: =IFERROR((INDEX(HIST_D!$BZ$8:$BZ$791,1)-INDEX(HIST_D!$BZ$8:$BZ$791,Control!$B$10)),"") | H7: =IFERROR(IF(ABS(E7)<1,"n/m",F7/E7),"n/m") | I7: =IFERROR(SLOPE(HIST_D!$FK$8:INDEX(HIST_D!$FK$8:$FK$791,Control!$B$12),HIST_D!$CW$8:INDEX(HIST_D!$CW$8:$CW$791,Control!$B$12)),"") | J7: =IFERROR(I7*(INDEX(HIST_D!$E$8:$E$791,1)-INDEX(HIST_D!$E$8:$E$791,Control!$B$10))*100,"") | K7: =IFERROR(G7-J7,"") | L7: =IFERROR((INDEX(HIST_D!$E$8:$E$791,1)-INDEX(HIST_D!$E$8:$E$791,Control!$B$11))*100+(INDEX(HIST_D!$BZ$8:$BZ$791,1)-INDEX(HIST_D!$BZ$8:$BZ$791,Control!$B$11)),"") | M7: =IFERROR((INDEX(HIST_D!$E$8:$E$791,1)-INDEX(HIST_D!$E$8:$E$791,Control!$B$11))*100,"") | N7: =IFERROR((INDEX(HIST_D!$BZ$8:$BZ$791,1)-INDEX(HIST_D!$BZ$8:$BZ$791,Control!$B$11)),"") | O7: =IFERROR(IF(ABS(L7)<1,"n/m",M7/L7),"n/m") | P7: =IFERROR(SLOPE(HIST_D!$FK$8:INDEX(HIST_D!$FK$8:$FK$791,Control!$B$12),HIST_D!$CW$8:INDEX(HIST_D!$CW$8:$CW$791,Control!$B$12)),"") | Q7: =IFERROR(P7*(INDEX(HIST_D!$E$8:$E$791,1)-INDEX(HIST_D!$E$8:$E$791,Control!$B$11))*100,"") | R7: =IFERROR(N7-Q7,"")
A8: Chile | B8: LatAm | C8: =INDEX(HIST_D!$CA$8:$CA$791,1) | D8: yes | E8: =IFERROR((INDEX(HIST_D!$E$8:$E$791,1)-INDEX(HIST_D!$E$8:$E$791,Control!$B$10))*100+(INDEX(HIST_D!$CA$8:$CA$791,1)-INDEX(HIST_D!$CA$8:$CA$791,Control!$B$10)),"") | F8: =IFERROR((INDEX(HIST_D!$E$8:$E$791,1)-INDEX(HIST_D!$E$8:$E$791,Control!$B$10))*100,"") | G8: =IFERROR((INDEX(HIST_D!$CA$8:$CA$791,1)-INDEX(HIST_D!$CA$8:$CA$791,Control!$B$10)),"") | H8: =IFERROR(IF(ABS(E8)<1,"n/m",F8/E8),"n/m") | I8: =IFERROR(SLOPE(HIST_D!$FL$8:INDEX(HIST_D!$FL$8:$FL$791,Control!$B$12),HIST_D!$CW$8:INDEX(HIST_D!$CW$8:$CW$791,Control!$B$12)),"") | J8: =IFERROR(I8*(INDEX(HIST_D!$E$8:$E$791,1)-INDEX(HIST_D!$E$8:$E$791,Control!$B$10))*100,"") | K8: =IFERROR(G8-J8,"") | L8: =IFERROR((INDEX(HIST_D!$E$8:$E$791,1)-INDEX(HIST_D!$E$8:$E$791,Control!$B$11))*100+(INDEX(HIST_D!$CA$8:$CA$791,1)-INDEX(HIST_D!$CA$8:$CA$791,Control!$B$11)),"") | M8: =IFERROR((INDEX(HIST_D!$E$8:$E$791,1)-INDEX(HIST_D!$E$8:$E$791,Control!$B$11))*100,"") | N8: =IFERROR((INDEX(HIST_D!$CA$8:$CA$791,1)-INDEX(HIST_D!$CA$8:$CA$791,Control!$B$11)),"") | O8: =IFERROR(IF(ABS(L8)<1,"n/m",M8/L8),"n/m") | P8: =IFERROR(SLOPE(HIST_D!$FL$8:INDEX(HIST_D!$FL$8:$FL$791,Control!$B$12),HIST_D!$CW$8:INDEX(HIST_D!$CW$8:$CW$791,Control!$B$12)),"") | Q8: =IFERROR(P8*(INDEX(HIST_D!$E$8:$E$791,1)-INDEX(HIST_D!$E$8:$E$791,Control!$B$11))*100,"") | R8: =IFERROR(N8-Q8,"")
A9: Colombia | B9: LatAm | C9: =INDEX(HIST_D!$CB$8:$CB$791,1) | D9: yes | E9: =IFERROR((INDEX(HIST_D!$E$8:$E$791,1)-INDEX(HIST_D!$E$8:$E$791,Control!$B$10))*100+(INDEX(HIST_D!$CB$8:$CB$791,1)-INDEX(HIST_D!$CB$8:$CB$791,Control!$B$10)),"") | F9: =IFERROR((INDEX(HIST_D!$E$8:$E$791,1)-INDEX(HIST_D!$E$8:$E$791,Control!$B$10))*100,"") | G9: =IFERROR((INDEX(HIST_D!$CB$8:$CB$791,1)-INDEX(HIST_D!$CB$8:$CB$791,Control!$B$10)),"") | H9: =IFERROR(IF(ABS(E9)<1,"n/m",F9/E9),"n/m") | I9: =IFERROR(SLOPE(HIST_D!$FM$8:INDEX(HIST_D!$FM$8:$FM$791,Control!$B$12),HIST_D!$CW$8:INDEX(HIST_D!$CW$8:$CW$791,Control!$B$12)),"") | J9: =IFERROR(I9*(INDEX(HIST_D!$E$8:$E$791,1)-INDEX(HIST_D!$E$8:$E$791,Control!$B$10))*100,"") | K9: =IFERROR(G9-J9,"") | L9: =IFERROR((INDEX(HIST_D!$E$8:$E$791,1)-INDEX(HIST_D!$E$8:$E$791,Control!$B$11))*100+(INDEX(HIST_D!$CB$8:$CB$791,1)-INDEX(HIST_D!$CB$8:$CB$791,Control!$B$11)),"") | M9: =IFERROR((INDEX(HIST_D!$E$8:$E$791,1)-INDEX(HIST_D!$E$8:$E$791,Control!$B$11))*100,"") | N9: =IFERROR((INDEX(HIST_D!$CB$8:$CB$791,1)-INDEX(HIST_D!$CB$8:$CB$791,Control!$B$11)),"") | O9: =IFERROR(IF(ABS(L9)<1,"n/m",M9/L9),"n/m") | P9: =IFERROR(SLOPE(HIST_D!$FM$8:INDEX(HIST_D!$FM$8:$FM$791,Control!$B$12),HIST_D!$CW$8:INDEX(HIST_D!$CW$8:$CW$791,Control!$B$12)),"") | Q9: =IFERROR(P9*(INDEX(HIST_D!$E$8:$E$791,1)-INDEX(HIST_D!$E$8:$E$791,Control!$B$11))*100,"") | R9: =IFERROR(N9-Q9,"")
A10: Peru | B10: LatAm | C10: =INDEX(HIST_D!$CC$8:$CC$791,1) | D10: yes | E10: =IFERROR((INDEX(HIST_D!$E$8:$E$791,1)-INDEX(HIST_D!$E$8:$E$791,Control!$B$10))*100+(INDEX(HIST_D!$CC$8:$CC$791,1)-INDEX(HIST_D!$CC$8:$CC$791,Control!$B$10)),"") | F10: =IFERROR((INDEX(HIST_D!$E$8:$E$791,1)-INDEX(HIST_D!$E$8:$E$791,Control!$B$10))*100,"") | G10: =IFERROR((INDEX(HIST_D!$CC$8:$CC$791,1)-INDEX(HIST_D!$CC$8:$CC$791,Control!$B$10)),"") | H10: =IFERROR(IF(ABS(E10)<1,"n/m",F10/E10),"n/m") | I10: =IFERROR(SLOPE(HIST_D!$FN$8:INDEX(HIST_D!$FN$8:$FN$791,Control!$B$12),HIST_D!$CW$8:INDEX(HIST_D!$CW$8:$CW$791,Control!$B$12)),"") | J10: =IFERROR(I10*(INDEX(HIST_D!$E$8:$E$791,1)-INDEX(HIST_D!$E$8:$E$791,Control!$B$10))*100,"") | K10: =IFERROR(G10-J10,"") | L10: =IFERROR((INDEX(HIST_D!$E$8:$E$791,1)-INDEX(HIST_D!$E$8:$E$791,Control!$B$11))*100+(INDEX(HIST_D!$CC$8:$CC$791,1)-INDEX(HIST_D!$CC$8:$CC$791,Control!$B$11)),"") | M10: =IFERROR((INDEX(HIST_D!$E$8:$E$791,1)-INDEX(HIST_D!$E$8:$E$791,Control!$B$11))*100,"") | N10: =IFERROR((INDEX(HIST_D!$CC$8:$CC$791,1)-INDEX(HIST_D!$CC$8:$CC$791,Control!$B$11)),"") | O10: =IFERROR(IF(ABS(L10)<1,"n/m",M10/L10),"n/m") | P10: =IFERROR(SLOPE(HIST_D!$FN$8:INDEX(HIST_D!$FN$8:$FN$791,Control!$B$12),HIST_D!$CW$8:INDEX(HIST_D!$CW$8:$CW$791,Control!$B$12)),"") | Q10: =IFERROR(P10*(INDEX(HIST_D!$E$8:$E$791,1)-INDEX(HIST_D!$E$8:$E$791,Control!$B$11))*100,"") | R10: =IFERROR(N10-Q10,"")
A11: LatAm average | B11: n=5 | E11: =IFERROR(AVERAGE(E6,E7,E8,E9,E10),"") | F11: =IFERROR(AVERAGE(F6,F7,F8,F9,F10),"") | G11: =IFERROR(AVERAGE(G6,G7,G8,G9,G10),"") | H11: =IFERROR(IF(ABS(E11)<1,"n/m",F11/E11),"n/m") | I11: =IFERROR(AVERAGE(I6,I7,I8,I9,I10),"") | J11: =IFERROR(AVERAGE(J6,J7,J8,J9,J10),"") | K11: =IFERROR(AVERAGE(K6,K7,K8,K9,K10),"") | L11: =IFERROR(AVERAGE(L6,L7,L8,L9,L10),"") | M11: =IFERROR(AVERAGE(M6,M7,M8,M9,M10),"") | N11: =IFERROR(AVERAGE(N6,N7,N8,N9,N10),"") | O11: =IFERROR(IF(ABS(L11)<1,"n/m",M11/L11),"n/m") | P11: =IFERROR(AVERAGE(P6,P7,P8,P9,P10),"") | Q11: =IFERROR(AVERAGE(Q6,Q7,Q8,Q9,Q10),"") | R11: =IFERROR(AVERAGE(R6,R7,R8,R9,R10),"")
A12: =IFERROR("LatAm: the 5y USD yield proxy moved "&TEXT($E$11,"+0;-0")&"bp on the month — "&TEXT($F$11,"+0;-0")&"bp Treasuries, "&TEXT($G$11,"+0;-0")&"bp spread"&IF(ISNUMBER($H$11),", so "&TEXT($H$11,"0%")&" of the move is the US","")&". YTD "&TEXT($L$11,"+0;-0")&"bp: "&TEXT($M$11,"+0;-0")&"bp Treasuries, "&TEXT($N$11,"+0;-0")&"bp spread. "&IF($G$11<=0,"Spreads did not widen into the Treasury move — the loss here is duration, not credit.",IF($G$11<$F$11*0.5,"Spreads widened, but by less than half the Treasury move — mostly a duration story.","Spreads widened by a comparable amount to Treasuries — this is being repriced for credit, not just rates.")),"")
A14: EM EUROPE
A15: Country | B15: Region | C15: Level | D15: In avg | E15: 1M: Total: d(UST 5Y + CDS) (bp) | F15: 1M: US-driven: d UST 5Y (bp) | G15: 1M: Intrinsic: d CDS 5Y (bp) | H15: 1M: US share (UST / total) | I15: 1M: Spread beta to UST 5Y (2y) | J15: 1M: Predicted d spread (bp) | K15: 1M: Spread surprise: actual less predicted (bp) | L15: YTD: Total: d(UST 5Y + CDS) (bp) | M15: YTD: US-driven: d UST 5Y (bp) | N15: YTD: Intrinsic: d CDS 5Y (bp) | O15: YTD: US share (UST / total) | P15: YTD: Spread beta to UST 5Y (2y) | Q15: YTD: Predicted d spread (bp) | R15: YTD: Spread surprise: actual less predicted (bp)
A16: Poland | B16: EM Europe | C16: =INDEX(HIST_D!$CD$8:$CD$791,1) | D16: yes | E16: =IFERROR((INDEX(HIST_D!$E$8:$E$791,1)-INDEX(HIST_D!$E$8:$E$791,Control!$B$10))*100+(INDEX(HIST_D!$CD$8:$CD$791,1)-INDEX(HIST_D!$CD$8:$CD$791,Control!$B$10)),"") | F16: =IFERROR((INDEX(HIST_D!$E$8:$E$791,1)-INDEX(HIST_D!$E$8:$E$791,Control!$B$10))*100,"") | G16: =IFERROR((INDEX(HIST_D!$CD$8:$CD$791,1)-INDEX(HIST_D!$CD$8:$CD$791,Control!$B$10)),"") | H16: =IFERROR(IF(ABS(E16)<1,"n/m",F16/E16),"n/m") | I16: =IFERROR(SLOPE(HIST_D!$FO$8:INDEX(HIST_D!$FO$8:$FO$791,Control!$B$12),HIST_D!$CW$8:INDEX(HIST_D!$CW$8:$CW$791,Control!$B$12)),"") | J16: =IFERROR(I16*(INDEX(HIST_D!$E$8:$E$791,1)-INDEX(HIST_D!$E$8:$E$791,Control!$B$10))*100,"") | K16: =IFERROR(G16-J16,"") | L16: =IFERROR((INDEX(HIST_D!$E$8:$E$791,1)-INDEX(HIST_D!$E$8:$E$791,Control!$B$11))*100+(INDEX(HIST_D!$CD$8:$CD$791,1)-INDEX(HIST_D!$CD$8:$CD$791,Control!$B$11)),"") | M16: =IFERROR((INDEX(HIST_D!$E$8:$E$791,1)-INDEX(HIST_D!$E$8:$E$791,Control!$B$11))*100,"") | N16: =IFERROR((INDEX(HIST_D!$CD$8:$CD$791,1)-INDEX(HIST_D!$CD$8:$CD$791,Control!$B$11)),"") | O16: =IFERROR(IF(ABS(L16)<1,"n/m",M16/L16),"n/m") | P16: =IFERROR(SLOPE(HIST_D!$FO$8:INDEX(HIST_D!$FO$8:$FO$791,Control!$B$12),HIST_D!$CW$8:INDEX(HIST_D!$CW$8:$CW$791,Control!$B$12)),"") | Q16: =IFERROR(P16*(INDEX(HIST_D!$E$8:$E$791,1)-INDEX(HIST_D!$E$8:$E$791,Control!$B$11))*100,"") | R16: =IFERROR(N16-Q16,"")
A17: Hungary | B17: EM Europe | C17: =INDEX(HIST_D!$CE$8:$CE$791,1) | D17: yes | E17: =IFERROR((INDEX(HIST_D!$E$8:$E$791,1)-INDEX(HIST_D!$E$8:$E$791,Control!$B$10))*100+(INDEX(HIST_D!$CE$8:$CE$791,1)-INDEX(HIST_D!$CE$8:$CE$791,Control!$B$10)),"") | F17: =IFERROR((INDEX(HIST_D!$E$8:$E$791,1)-INDEX(HIST_D!$E$8:$E$791,Control!$B$10))*100,"") | G17: =IFERROR((INDEX(HIST_D!$CE$8:$CE$791,1)-INDEX(HIST_D!$CE$8:$CE$791,Control!$B$10)),"") | H17: =IFERROR(IF(ABS(E17)<1,"n/m",F17/E17),"n/m") | I17: =IFERROR(SLOPE(HIST_D!$FP$8:INDEX(HIST_D!$FP$8:$FP$791,Control!$B$12),HIST_D!$CW$8:INDEX(HIST_D!$CW$8:$CW$791,Control!$B$12)),"") | J17: =IFERROR(I17*(INDEX(HIST_D!$E$8:$E$791,1)-INDEX(HIST_D!$E$8:$E$791,Control!$B$10))*100,"") | K17: =IFERROR(G17-J17,"") | L17: =IFERROR((INDEX(HIST_D!$E$8:$E$791,1)-INDEX(HIST_D!$E$8:$E$791,Control!$B$11))*100+(INDEX(HIST_D!$CE$8:$CE$791,1)-INDEX(HIST_D!$CE$8:$CE$791,Control!$B$11)),"") | M17: =IFERROR((INDEX(HIST_D!$E$8:$E$791,1)-INDEX(HIST_D!$E$8:$E$791,Control!$B$11))*100,"") | N17: =IFERROR((INDEX(HIST_D!$CE$8:$CE$791,1)-INDEX(HIST_D!$CE$8:$CE$791,Control!$B$11)),"") | O17: =IFERROR(IF(ABS(L17)<1,"n/m",M17/L17),"n/m") | P17: =IFERROR(SLOPE(HIST_D!$FP$8:INDEX(HIST_D!$FP$8:$FP$791,Control!$B$12),HIST_D!$CW$8:INDEX(HIST_D!$CW$8:$CW$791,Control!$B$12)),"") | Q17: =IFERROR(P17*(INDEX(HIST_D!$E$8:$E$791,1)-INDEX(HIST_D!$E$8:$E$791,Control!$B$11))*100,"") | R17: =IFERROR(N17-Q17,"")
A18: Czechia | B18: EM Europe | C18: =INDEX(HIST_D!$CF$8:$CF$791,1) | D18: yes | E18: =IFERROR((INDEX(HIST_D!$E$8:$E$791,1)-INDEX(HIST_D!$E$8:$E$791,Control!$B$10))*100+(INDEX(HIST_D!$CF$8:$CF$791,1)-INDEX(HIST_D!$CF$8:$CF$791,Control!$B$10)),"") | F18: =IFERROR((INDEX(HIST_D!$E$8:$E$791,1)-INDEX(HIST_D!$E$8:$E$791,Control!$B$10))*100,"") | G18: =IFERROR((INDEX(HIST_D!$CF$8:$CF$791,1)-INDEX(HIST_D!$CF$8:$CF$791,Control!$B$10)),"") | H18: =IFERROR(IF(ABS(E18)<1,"n/m",F18/E18),"n/m") | I18: =IFERROR(SLOPE(HIST_D!$FQ$8:INDEX(HIST_D!$FQ$8:$FQ$791,Control!$B$12),HIST_D!$CW$8:INDEX(HIST_D!$CW$8:$CW$791,Control!$B$12)),"") | J18: =IFERROR(I18*(INDEX(HIST_D!$E$8:$E$791,1)-INDEX(HIST_D!$E$8:$E$791,Control!$B$10))*100,"") | K18: =IFERROR(G18-J18,"") | L18: =IFERROR((INDEX(HIST_D!$E$8:$E$791,1)-INDEX(HIST_D!$E$8:$E$791,Control!$B$11))*100+(INDEX(HIST_D!$CF$8:$CF$791,1)-INDEX(HIST_D!$CF$8:$CF$791,Control!$B$11)),"") | M18: =IFERROR((INDEX(HIST_D!$E$8:$E$791,1)-INDEX(HIST_D!$E$8:$E$791,Control!$B$11))*100,"") | N18: =IFERROR((INDEX(HIST_D!$CF$8:$CF$791,1)-INDEX(HIST_D!$CF$8:$CF$791,Control!$B$11)),"") | O18: =IFERROR(IF(ABS(L18)<1,"n/m",M18/L18),"n/m") | P18: =IFERROR(SLOPE(HIST_D!$FQ$8:INDEX(HIST_D!$FQ$8:$FQ$791,Control!$B$12),HIST_D!$CW$8:INDEX(HIST_D!$CW$8:$CW$791,Control!$B$12)),"") | Q18: =IFERROR(P18*(INDEX(HIST_D!$E$8:$E$791,1)-INDEX(HIST_D!$E$8:$E$791,Control!$B$11))*100,"") | R18: =IFERROR(N18-Q18,"")
A19: Romania | B19: EM Europe | C19: =INDEX(HIST_D!$CG$8:$CG$791,1) | D19: yes | E19: =IFERROR((INDEX(HIST_D!$E$8:$E$791,1)-INDEX(HIST_D!$E$8:$E$791,Control!$B$10))*100+(INDEX(HIST_D!$CG$8:$CG$791,1)-INDEX(HIST_D!$CG$8:$CG$791,Control!$B$10)),"") | F19: =IFERROR((INDEX(HIST_D!$E$8:$E$791,1)-INDEX(HIST_D!$E$8:$E$791,Control!$B$10))*100,"") | G19: =IFERROR((INDEX(HIST_D!$CG$8:$CG$791,1)-INDEX(HIST_D!$CG$8:$CG$791,Control!$B$10)),"") | H19: =IFERROR(IF(ABS(E19)<1,"n/m",F19/E19),"n/m") | I19: =IFERROR(SLOPE(HIST_D!$FR$8:INDEX(HIST_D!$FR$8:$FR$791,Control!$B$12),HIST_D!$CW$8:INDEX(HIST_D!$CW$8:$CW$791,Control!$B$12)),"") | J19: =IFERROR(I19*(INDEX(HIST_D!$E$8:$E$791,1)-INDEX(HIST_D!$E$8:$E$791,Control!$B$10))*100,"") | K19: =IFERROR(G19-J19,"") | L19: =IFERROR((INDEX(HIST_D!$E$8:$E$791,1)-INDEX(HIST_D!$E$8:$E$791,Control!$B$11))*100+(INDEX(HIST_D!$CG$8:$CG$791,1)-INDEX(HIST_D!$CG$8:$CG$791,Control!$B$11)),"") | M19: =IFERROR((INDEX(HIST_D!$E$8:$E$791,1)-INDEX(HIST_D!$E$8:$E$791,Control!$B$11))*100,"") | N19: =IFERROR((INDEX(HIST_D!$CG$8:$CG$791,1)-INDEX(HIST_D!$CG$8:$CG$791,Control!$B$11)),"") | O19: =IFERROR(IF(ABS(L19)<1,"n/m",M19/L19),"n/m") | P19: =IFERROR(SLOPE(HIST_D!$FR$8:INDEX(HIST_D!$FR$8:$FR$791,Control!$B$12),HIST_D!$CW$8:INDEX(HIST_D!$CW$8:$CW$791,Control!$B$12)),"") | Q19: =IFERROR(P19*(INDEX(HIST_D!$E$8:$E$791,1)-INDEX(HIST_D!$E$8:$E$791,Control!$B$11))*100,"") | R19: =IFERROR(N19-Q19,"")
A20: Turkiye | B20: EM Europe | C20: =INDEX(HIST_D!$CH$8:$CH$791,1) | D20: yes | E20: =IFERROR((INDEX(HIST_D!$E$8:$E$791,1)-INDEX(HIST_D!$E$8:$E$791,Control!$B$10))*100+(INDEX(HIST_D!$CH$8:$CH$791,1)-INDEX(HIST_D!$CH$8:$CH$791,Control!$B$10)),"") | F20: =IFERROR((INDEX(HIST_D!$E$8:$E$791,1)-INDEX(HIST_D!$E$8:$E$791,Control!$B$10))*100,"") | G20: =IFERROR((INDEX(HIST_D!$CH$8:$CH$791,1)-INDEX(HIST_D!$CH$8:$CH$791,Control!$B$10)),"") | H20: =IFERROR(IF(ABS(E20)<1,"n/m",F20/E20),"n/m") | I20: =IFERROR(SLOPE(HIST_D!$FS$8:INDEX(HIST_D!$FS$8:$FS$791,Control!$B$12),HIST_D!$CW$8:INDEX(HIST_D!$CW$8:$CW$791,Control!$B$12)),"") | J20: =IFERROR(I20*(INDEX(HIST_D!$E$8:$E$791,1)-INDEX(HIST_D!$E$8:$E$791,Control!$B$10))*100,"") | K20: =IFERROR(G20-J20,"") | L20: =IFERROR((INDEX(HIST_D!$E$8:$E$791,1)-INDEX(HIST_D!$E$8:$E$791,Control!$B$11))*100+(INDEX(HIST_D!$CH$8:$CH$791,1)-INDEX(HIST_D!$CH$8:$CH$791,Control!$B$11)),"") | M20: =IFERROR((INDEX(HIST_D!$E$8:$E$791,1)-INDEX(HIST_D!$E$8:$E$791,Control!$B$11))*100,"") | N20: =IFERROR((INDEX(HIST_D!$CH$8:$CH$791,1)-INDEX(HIST_D!$CH$8:$CH$791,Control!$B$11)),"") | O20: =IFERROR(IF(ABS(L20)<1,"n/m",M20/L20),"n/m") | P20: =IFERROR(SLOPE(HIST_D!$FS$8:INDEX(HIST_D!$FS$8:$FS$791,Control!$B$12),HIST_D!$CW$8:INDEX(HIST_D!$CW$8:$CW$791,Control!$B$12)),"") | Q20: =IFERROR(P20*(INDEX(HIST_D!$E$8:$E$791,1)-INDEX(HIST_D!$E$8:$E$791,Control!$B$11))*100,"") | R20: =IFERROR(N20-Q20,"") | S20: excluded from rates and FX averages: structural depreciation and a 30% curve swamp an equal weight
A21: EM Europe average | B21: n=5 | E21: =IFERROR(AVERAGE(E16,E17,E18,E19,E20),"") | F21: =IFERROR(AVERAGE(F16,F17,F18,F19,F20),"") | G21: =IFERROR(AVERAGE(G16,G17,G18,G19,G20),"") | H21: =IFERROR(IF(ABS(E21)<1,"n/m",F21/E21),"n/m") | I21: =IFERROR(AVERAGE(I16,I17,I18,I19,I20),"") | J21: =IFERROR(AVERAGE(J16,J17,J18,J19,J20),"") | K21: =IFERROR(AVERAGE(K16,K17,K18,K19,K20),"") | L21: =IFERROR(AVERAGE(L16,L17,L18,L19,L20),"") | M21: =IFERROR(AVERAGE(M16,M17,M18,M19,M20),"") | N21: =IFERROR(AVERAGE(N16,N17,N18,N19,N20),"") | O21: =IFERROR(IF(ABS(L21)<1,"n/m",M21/L21),"n/m") | P21: =IFERROR(AVERAGE(P16,P17,P18,P19,P20),"") | Q21: =IFERROR(AVERAGE(Q16,Q17,Q18,Q19,Q20),"") | R21: =IFERROR(AVERAGE(R16,R17,R18,R19,R20),"")
A22: =IFERROR("EM Europe: the 5y USD yield proxy moved "&TEXT($E$21,"+0;-0")&"bp on the month — "&TEXT($F$21,"+0;-0")&"bp Treasuries, "&TEXT($G$21,"+0;-0")&"bp spread"&IF(ISNUMBER($H$21),", so "&TEXT($H$21,"0%")&" of the move is the US","")&". YTD "&TEXT($L$21,"+0;-0")&"bp: "&TEXT($M$21,"+0;-0")&"bp Treasuries, "&TEXT($N$21,"+0;-0")&"bp spread. "&IF($G$21<=0,"Spreads did not widen into the Treasury move — the loss here is duration, not credit.",IF($G$21<$F$21*0.5,"Spreads widened, but by less than half the Treasury move — mostly a duration story.","Spreads widened by a comparable amount to Treasuries — this is being repriced for credit, not just rates.")),"")
A24: MIDDLE EAST
A25: Country | B25: Region | C25: Level | D25: In avg | E25: 1M: Total: d(UST 5Y + CDS) (bp) | F25: 1M: US-driven: d UST 5Y (bp) | G25: 1M: Intrinsic: d CDS 5Y (bp) | H25: 1M: US share (UST / total) | I25: 1M: Spread beta to UST 5Y (2y) | J25: 1M: Predicted d spread (bp) | K25: 1M: Spread surprise: actual less predicted (bp) | L25: YTD: Total: d(UST 5Y + CDS) (bp) | M25: YTD: US-driven: d UST 5Y (bp) | N25: YTD: Intrinsic: d CDS 5Y (bp) | O25: YTD: US share (UST / total) | P25: YTD: Spread beta to UST 5Y (2y) | Q25: YTD: Predicted d spread (bp) | R25: YTD: Spread surprise: actual less predicted (bp)
A26: Saudi Arabia | B26: Middle East | C26: =INDEX(HIST_D!$CI$8:$CI$791,1) | D26: yes | E26: =IFERROR((INDEX(HIST_D!$E$8:$E$791,1)-INDEX(HIST_D!$E$8:$E$791,Control!$B$10))*100+(INDEX(HIST_D!$CI$8:$CI$791,1)-INDEX(HIST_D!$CI$8:$CI$791,Control!$B$10)),"") | F26: =IFERROR((INDEX(HIST_D!$E$8:$E$791,1)-INDEX(HIST_D!$E$8:$E$791,Control!$B$10))*100,"") | G26: =IFERROR((INDEX(HIST_D!$CI$8:$CI$791,1)-INDEX(HIST_D!$CI$8:$CI$791,Control!$B$10)),"") | H26: =IFERROR(IF(ABS(E26)<1,"n/m",F26/E26),"n/m") | I26: =IFERROR(SLOPE(HIST_D!$FT$8:INDEX(HIST_D!$FT$8:$FT$791,Control!$B$12),HIST_D!$CW$8:INDEX(HIST_D!$CW$8:$CW$791,Control!$B$12)),"") | J26: =IFERROR(I26*(INDEX(HIST_D!$E$8:$E$791,1)-INDEX(HIST_D!$E$8:$E$791,Control!$B$10))*100,"") | K26: =IFERROR(G26-J26,"") | L26: =IFERROR((INDEX(HIST_D!$E$8:$E$791,1)-INDEX(HIST_D!$E$8:$E$791,Control!$B$11))*100+(INDEX(HIST_D!$CI$8:$CI$791,1)-INDEX(HIST_D!$CI$8:$CI$791,Control!$B$11)),"") | M26: =IFERROR((INDEX(HIST_D!$E$8:$E$791,1)-INDEX(HIST_D!$E$8:$E$791,Control!$B$11))*100,"") | N26: =IFERROR((INDEX(HIST_D!$CI$8:$CI$791,1)-INDEX(HIST_D!$CI$8:$CI$791,Control!$B$11)),"") | O26: =IFERROR(IF(ABS(L26)<1,"n/m",M26/L26),"n/m") | P26: =IFERROR(SLOPE(HIST_D!$FT$8:INDEX(HIST_D!$FT$8:$FT$791,Control!$B$12),HIST_D!$CW$8:INDEX(HIST_D!$CW$8:$CW$791,Control!$B$12)),"") | Q26: =IFERROR(P26*(INDEX(HIST_D!$E$8:$E$791,1)-INDEX(HIST_D!$E$8:$E$791,Control!$B$11))*100,"") | R26: =IFERROR(N26-Q26,"") | S26: pegged; no local generic — credit only
A27: UAE (Abu Dhabi) | B27: Middle East | C27: =INDEX(HIST_D!$CJ$8:$CJ$791,1) | D27: yes | E27: =IFERROR((INDEX(HIST_D!$E$8:$E$791,1)-INDEX(HIST_D!$E$8:$E$791,Control!$B$10))*100+(INDEX(HIST_D!$CJ$8:$CJ$791,1)-INDEX(HIST_D!$CJ$8:$CJ$791,Control!$B$10)),"") | F27: =IFERROR((INDEX(HIST_D!$E$8:$E$791,1)-INDEX(HIST_D!$E$8:$E$791,Control!$B$10))*100,"") | G27: =IFERROR((INDEX(HIST_D!$CJ$8:$CJ$791,1)-INDEX(HIST_D!$CJ$8:$CJ$791,Control!$B$10)),"") | H27: =IFERROR(IF(ABS(E27)<1,"n/m",F27/E27),"n/m") | I27: =IFERROR(SLOPE(HIST_D!$FU$8:INDEX(HIST_D!$FU$8:$FU$791,Control!$B$12),HIST_D!$CW$8:INDEX(HIST_D!$CW$8:$CW$791,Control!$B$12)),"") | J27: =IFERROR(I27*(INDEX(HIST_D!$E$8:$E$791,1)-INDEX(HIST_D!$E$8:$E$791,Control!$B$10))*100,"") | K27: =IFERROR(G27-J27,"") | L27: =IFERROR((INDEX(HIST_D!$E$8:$E$791,1)-INDEX(HIST_D!$E$8:$E$791,Control!$B$11))*100+(INDEX(HIST_D!$CJ$8:$CJ$791,1)-INDEX(HIST_D!$CJ$8:$CJ$791,Control!$B$11)),"") | M27: =IFERROR((INDEX(HIST_D!$E$8:$E$791,1)-INDEX(HIST_D!$E$8:$E$791,Control!$B$11))*100,"") | N27: =IFERROR((INDEX(HIST_D!$CJ$8:$CJ$791,1)-INDEX(HIST_D!$CJ$8:$CJ$791,Control!$B$11)),"") | O27: =IFERROR(IF(ABS(L27)<1,"n/m",M27/L27),"n/m") | P27: =IFERROR(SLOPE(HIST_D!$FU$8:INDEX(HIST_D!$FU$8:$FU$791,Control!$B$12),HIST_D!$CW$8:INDEX(HIST_D!$CW$8:$CW$791,Control!$B$12)),"") | Q27: =IFERROR(P27*(INDEX(HIST_D!$E$8:$E$791,1)-INDEX(HIST_D!$E$8:$E$791,Control!$B$11))*100,"") | R27: =IFERROR(N27-Q27,"") | S27: pegged; no local generic — credit only
A28: Qatar | B28: Middle East | C28: =INDEX(HIST_D!$CK$8:$CK$791,1) | D28: yes | E28: =IFERROR((INDEX(HIST_D!$E$8:$E$791,1)-INDEX(HIST_D!$E$8:$E$791,Control!$B$10))*100+(INDEX(HIST_D!$CK$8:$CK$791,1)-INDEX(HIST_D!$CK$8:$CK$791,Control!$B$10)),"") | F28: =IFERROR((INDEX(HIST_D!$E$8:$E$791,1)-INDEX(HIST_D!$E$8:$E$791,Control!$B$10))*100,"") | G28: =IFERROR((INDEX(HIST_D!$CK$8:$CK$791,1)-INDEX(HIST_D!$CK$8:$CK$791,Control!$B$10)),"") | H28: =IFERROR(IF(ABS(E28)<1,"n/m",F28/E28),"n/m") | I28: =IFERROR(SLOPE(HIST_D!$FV$8:INDEX(HIST_D!$FV$8:$FV$791,Control!$B$12),HIST_D!$CW$8:INDEX(HIST_D!$CW$8:$CW$791,Control!$B$12)),"") | J28: =IFERROR(I28*(INDEX(HIST_D!$E$8:$E$791,1)-INDEX(HIST_D!$E$8:$E$791,Control!$B$10))*100,"") | K28: =IFERROR(G28-J28,"") | L28: =IFERROR((INDEX(HIST_D!$E$8:$E$791,1)-INDEX(HIST_D!$E$8:$E$791,Control!$B$11))*100+(INDEX(HIST_D!$CK$8:$CK$791,1)-INDEX(HIST_D!$CK$8:$CK$791,Control!$B$11)),"") | M28: =IFERROR((INDEX(HIST_D!$E$8:$E$791,1)-INDEX(HIST_D!$E$8:$E$791,Control!$B$11))*100,"") | N28: =IFERROR((INDEX(HIST_D!$CK$8:$CK$791,1)-INDEX(HIST_D!$CK$8:$CK$791,Control!$B$11)),"") | O28: =IFERROR(IF(ABS(L28)<1,"n/m",M28/L28),"n/m") | P28: =IFERROR(SLOPE(HIST_D!$FV$8:INDEX(HIST_D!$FV$8:$FV$791,Control!$B$12),HIST_D!$CW$8:INDEX(HIST_D!$CW$8:$CW$791,Control!$B$12)),"") | Q28: =IFERROR(P28*(INDEX(HIST_D!$E$8:$E$791,1)-INDEX(HIST_D!$E$8:$E$791,Control!$B$11))*100,"") | R28: =IFERROR(N28-Q28,"") | S28: pegged; no local generic — credit only
A29: Israel | B29: Middle East | C29: =INDEX(HIST_D!$CL$8:$CL$791,1) | D29: yes | E29: =IFERROR((INDEX(HIST_D!$E$8:$E$791,1)-INDEX(HIST_D!$E$8:$E$791,Control!$B$10))*100+(INDEX(HIST_D!$CL$8:$CL$791,1)-INDEX(HIST_D!$CL$8:$CL$791,Control!$B$10)),"") | F29: =IFERROR((INDEX(HIST_D!$E$8:$E$791,1)-INDEX(HIST_D!$E$8:$E$791,Control!$B$10))*100,"") | G29: =IFERROR((INDEX(HIST_D!$CL$8:$CL$791,1)-INDEX(HIST_D!$CL$8:$CL$791,Control!$B$10)),"") | H29: =IFERROR(IF(ABS(E29)<1,"n/m",F29/E29),"n/m") | I29: =IFERROR(SLOPE(HIST_D!$FW$8:INDEX(HIST_D!$FW$8:$FW$791,Control!$B$12),HIST_D!$CW$8:INDEX(HIST_D!$CW$8:$CW$791,Control!$B$12)),"") | J29: =IFERROR(I29*(INDEX(HIST_D!$E$8:$E$791,1)-INDEX(HIST_D!$E$8:$E$791,Control!$B$10))*100,"") | K29: =IFERROR(G29-J29,"") | L29: =IFERROR((INDEX(HIST_D!$E$8:$E$791,1)-INDEX(HIST_D!$E$8:$E$791,Control!$B$11))*100+(INDEX(HIST_D!$CL$8:$CL$791,1)-INDEX(HIST_D!$CL$8:$CL$791,Control!$B$11)),"") | M29: =IFERROR((INDEX(HIST_D!$E$8:$E$791,1)-INDEX(HIST_D!$E$8:$E$791,Control!$B$11))*100,"") | N29: =IFERROR((INDEX(HIST_D!$CL$8:$CL$791,1)-INDEX(HIST_D!$CL$8:$CL$791,Control!$B$11)),"") | O29: =IFERROR(IF(ABS(L29)<1,"n/m",M29/L29),"n/m") | P29: =IFERROR(SLOPE(HIST_D!$FW$8:INDEX(HIST_D!$FW$8:$FW$791,Control!$B$12),HIST_D!$CW$8:INDEX(HIST_D!$CW$8:$CW$791,Control!$B$12)),"") | Q29: =IFERROR(P29*(INDEX(HIST_D!$E$8:$E$791,1)-INDEX(HIST_D!$E$8:$E$791,Control!$B$11))*100,"") | R29: =IFERROR(N29-Q29,"")
A30: Egypt | B30: Middle East | C30: =INDEX(HIST_D!$CM$8:$CM$791,1) | D30: yes | E30: =IFERROR((INDEX(HIST_D!$E$8:$E$791,1)-INDEX(HIST_D!$E$8:$E$791,Control!$B$10))*100+(INDEX(HIST_D!$CM$8:$CM$791,1)-INDEX(HIST_D!$CM$8:$CM$791,Control!$B$10)),"") | F30: =IFERROR((INDEX(HIST_D!$E$8:$E$791,1)-INDEX(HIST_D!$E$8:$E$791,Control!$B$10))*100,"") | G30: =IFERROR((INDEX(HIST_D!$CM$8:$CM$791,1)-INDEX(HIST_D!$CM$8:$CM$791,Control!$B$10)),"") | H30: =IFERROR(IF(ABS(E30)<1,"n/m",F30/E30),"n/m") | I30: =IFERROR(SLOPE(HIST_D!$FX$8:INDEX(HIST_D!$FX$8:$FX$791,Control!$B$12),HIST_D!$CW$8:INDEX(HIST_D!$CW$8:$CW$791,Control!$B$12)),"") | J30: =IFERROR(I30*(INDEX(HIST_D!$E$8:$E$791,1)-INDEX(HIST_D!$E$8:$E$791,Control!$B$10))*100,"") | K30: =IFERROR(G30-J30,"") | L30: =IFERROR((INDEX(HIST_D!$E$8:$E$791,1)-INDEX(HIST_D!$E$8:$E$791,Control!$B$11))*100+(INDEX(HIST_D!$CM$8:$CM$791,1)-INDEX(HIST_D!$CM$8:$CM$791,Control!$B$11)),"") | M30: =IFERROR((INDEX(HIST_D!$E$8:$E$791,1)-INDEX(HIST_D!$E$8:$E$791,Control!$B$11))*100,"") | N30: =IFERROR((INDEX(HIST_D!$CM$8:$CM$791,1)-INDEX(HIST_D!$CM$8:$CM$791,Control!$B$11)),"") | O30: =IFERROR(IF(ABS(L30)<1,"n/m",M30/L30),"n/m") | P30: =IFERROR(SLOPE(HIST_D!$FX$8:INDEX(HIST_D!$FX$8:$FX$791,Control!$B$12),HIST_D!$CW$8:INDEX(HIST_D!$CW$8:$CW$791,Control!$B$12)),"") | Q30: =IFERROR(P30*(INDEX(HIST_D!$E$8:$E$791,1)-INDEX(HIST_D!$E$8:$E$791,Control!$B$11))*100,"") | R30: =IFERROR(N30-Q30,"") | S30: excluded from FX average: managed float with step devaluations; GTEGP10Y is Verify
A31: Middle East average | B31: n=5 | E31: =IFERROR(AVERAGE(E26,E27,E28,E29,E30),"") | F31: =IFERROR(AVERAGE(F26,F27,F28,F29,F30),"") | G31: =IFERROR(AVERAGE(G26,G27,G28,G29,G30),"") | H31: =IFERROR(IF(ABS(E31)<1,"n/m",F31/E31),"n/m") | I31: =IFERROR(AVERAGE(I26,I27,I28,I29,I30),"") | J31: =IFERROR(AVERAGE(J26,J27,J28,J29,J30),"") | K31: =IFERROR(AVERAGE(K26,K27,K28,K29,K30),"") | L31: =IFERROR(AVERAGE(L26,L27,L28,L29,L30),"") | M31: =IFERROR(AVERAGE(M26,M27,M28,M29,M30),"") | N31: =IFERROR(AVERAGE(N26,N27,N28,N29,N30),"") | O31: =IFERROR(IF(ABS(L31)<1,"n/m",M31/L31),"n/m") | P31: =IFERROR(AVERAGE(P26,P27,P28,P29,P30),"") | Q31: =IFERROR(AVERAGE(Q26,Q27,Q28,Q29,Q30),"") | R31: =IFERROR(AVERAGE(R26,R27,R28,R29,R30),"")
A32: =IFERROR("Middle East: the 5y USD yield proxy moved "&TEXT($E$31,"+0;-0")&"bp on the month — "&TEXT($F$31,"+0;-0")&"bp Treasuries, "&TEXT($G$31,"+0;-0")&"bp spread"&IF(ISNUMBER($H$31),", so "&TEXT($H$31,"0%")&" of the move is the US","")&". YTD "&TEXT($L$31,"+0;-0")&"bp: "&TEXT($M$31,"+0;-0")&"bp Treasuries, "&TEXT($N$31,"+0;-0")&"bp spread. "&IF($G$31<=0,"Spreads did not widen into the Treasury move — the loss here is duration, not credit.",IF($G$31<$F$31*0.5,"Spreads widened, but by less than half the Treasury move — mostly a duration story.","Spreads widened by a comparable amount to Treasuries — this is being repriced for credit, not just rates.")),"")
A34: EM ASIA
A35: Country | B35: Region | C35: Level | D35: In avg | E35: 1M: Total: d(UST 5Y + CDS) (bp) | F35: 1M: US-driven: d UST 5Y (bp) | G35: 1M: Intrinsic: d CDS 5Y (bp) | H35: 1M: US share (UST / total) | I35: 1M: Spread beta to UST 5Y (2y) | J35: 1M: Predicted d spread (bp) | K35: 1M: Spread surprise: actual less predicted (bp) | L35: YTD: Total: d(UST 5Y + CDS) (bp) | M35: YTD: US-driven: d UST 5Y (bp) | N35: YTD: Intrinsic: d CDS 5Y (bp) | O35: YTD: US share (UST / total) | P35: YTD: Spread beta to UST 5Y (2y) | Q35: YTD: Predicted d spread (bp) | R35: YTD: Spread surprise: actual less predicted (bp)
A36: China | B36: EM Asia | C36: =INDEX(HIST_D!$CN$8:$CN$791,1) | D36: yes | E36: =IFERROR((INDEX(HIST_D!$E$8:$E$791,1)-INDEX(HIST_D!$E$8:$E$791,Control!$B$10))*100+(INDEX(HIST_D!$CN$8:$CN$791,1)-INDEX(HIST_D!$CN$8:$CN$791,Control!$B$10)),"") | F36: =IFERROR((INDEX(HIST_D!$E$8:$E$791,1)-INDEX(HIST_D!$E$8:$E$791,Control!$B$10))*100,"") | G36: =IFERROR((INDEX(HIST_D!$CN$8:$CN$791,1)-INDEX(HIST_D!$CN$8:$CN$791,Control!$B$10)),"") | H36: =IFERROR(IF(ABS(E36)<1,"n/m",F36/E36),"n/m") | I36: =IFERROR(SLOPE(HIST_D!$FY$8:INDEX(HIST_D!$FY$8:$FY$791,Control!$B$12),HIST_D!$CW$8:INDEX(HIST_D!$CW$8:$CW$791,Control!$B$12)),"") | J36: =IFERROR(I36*(INDEX(HIST_D!$E$8:$E$791,1)-INDEX(HIST_D!$E$8:$E$791,Control!$B$10))*100,"") | K36: =IFERROR(G36-J36,"") | L36: =IFERROR((INDEX(HIST_D!$E$8:$E$791,1)-INDEX(HIST_D!$E$8:$E$791,Control!$B$11))*100+(INDEX(HIST_D!$CN$8:$CN$791,1)-INDEX(HIST_D!$CN$8:$CN$791,Control!$B$11)),"") | M36: =IFERROR((INDEX(HIST_D!$E$8:$E$791,1)-INDEX(HIST_D!$E$8:$E$791,Control!$B$11))*100,"") | N36: =IFERROR((INDEX(HIST_D!$CN$8:$CN$791,1)-INDEX(HIST_D!$CN$8:$CN$791,Control!$B$11)),"") | O36: =IFERROR(IF(ABS(L36)<1,"n/m",M36/L36),"n/m") | P36: =IFERROR(SLOPE(HIST_D!$FY$8:INDEX(HIST_D!$FY$8:$FY$791,Control!$B$12),HIST_D!$CW$8:INDEX(HIST_D!$CW$8:$CW$791,Control!$B$12)),"") | Q36: =IFERROR(P36*(INDEX(HIST_D!$E$8:$E$791,1)-INDEX(HIST_D!$E$8:$E$791,Control!$B$11))*100,"") | R36: =IFERROR(N36-Q36,"")
A37: Indonesia | B37: EM Asia | C37: =INDEX(HIST_D!$CO$8:$CO$791,1) | D37: yes | E37: =IFERROR((INDEX(HIST_D!$E$8:$E$791,1)-INDEX(HIST_D!$E$8:$E$791,Control!$B$10))*100+(INDEX(HIST_D!$CO$8:$CO$791,1)-INDEX(HIST_D!$CO$8:$CO$791,Control!$B$10)),"") | F37: =IFERROR((INDEX(HIST_D!$E$8:$E$791,1)-INDEX(HIST_D!$E$8:$E$791,Control!$B$10))*100,"") | G37: =IFERROR((INDEX(HIST_D!$CO$8:$CO$791,1)-INDEX(HIST_D!$CO$8:$CO$791,Control!$B$10)),"") | H37: =IFERROR(IF(ABS(E37)<1,"n/m",F37/E37),"n/m") | I37: =IFERROR(SLOPE(HIST_D!$FZ$8:INDEX(HIST_D!$FZ$8:$FZ$791,Control!$B$12),HIST_D!$CW$8:INDEX(HIST_D!$CW$8:$CW$791,Control!$B$12)),"") | J37: =IFERROR(I37*(INDEX(HIST_D!$E$8:$E$791,1)-INDEX(HIST_D!$E$8:$E$791,Control!$B$10))*100,"") | K37: =IFERROR(G37-J37,"") | L37: =IFERROR((INDEX(HIST_D!$E$8:$E$791,1)-INDEX(HIST_D!$E$8:$E$791,Control!$B$11))*100+(INDEX(HIST_D!$CO$8:$CO$791,1)-INDEX(HIST_D!$CO$8:$CO$791,Control!$B$11)),"") | M37: =IFERROR((INDEX(HIST_D!$E$8:$E$791,1)-INDEX(HIST_D!$E$8:$E$791,Control!$B$11))*100,"") | N37: =IFERROR((INDEX(HIST_D!$CO$8:$CO$791,1)-INDEX(HIST_D!$CO$8:$CO$791,Control!$B$11)),"") | O37: =IFERROR(IF(ABS(L37)<1,"n/m",M37/L37),"n/m") | P37: =IFERROR(SLOPE(HIST_D!$FZ$8:INDEX(HIST_D!$FZ$8:$FZ$791,Control!$B$12),HIST_D!$CW$8:INDEX(HIST_D!$CW$8:$CW$791,Control!$B$12)),"") | Q37: =IFERROR(P37*(INDEX(HIST_D!$E$8:$E$791,1)-INDEX(HIST_D!$E$8:$E$791,Control!$B$11))*100,"") | R37: =IFERROR(N37-Q37,"")
A38: Korea | B38: EM Asia | C38: =INDEX(HIST_D!$CP$8:$CP$791,1) | D38: yes | E38: =IFERROR((INDEX(HIST_D!$E$8:$E$791,1)-INDEX(HIST_D!$E$8:$E$791,Control!$B$10))*100+(INDEX(HIST_D!$CP$8:$CP$791,1)-INDEX(HIST_D!$CP$8:$CP$791,Control!$B$10)),"") | F38: =IFERROR((INDEX(HIST_D!$E$8:$E$791,1)-INDEX(HIST_D!$E$8:$E$791,Control!$B$10))*100,"") | G38: =IFERROR((INDEX(HIST_D!$CP$8:$CP$791,1)-INDEX(HIST_D!$CP$8:$CP$791,Control!$B$10)),"") | H38: =IFERROR(IF(ABS(E38)<1,"n/m",F38/E38),"n/m") | I38: =IFERROR(SLOPE(HIST_D!$GA$8:INDEX(HIST_D!$GA$8:$GA$791,Control!$B$12),HIST_D!$CW$8:INDEX(HIST_D!$CW$8:$CW$791,Control!$B$12)),"") | J38: =IFERROR(I38*(INDEX(HIST_D!$E$8:$E$791,1)-INDEX(HIST_D!$E$8:$E$791,Control!$B$10))*100,"") | K38: =IFERROR(G38-J38,"") | L38: =IFERROR((INDEX(HIST_D!$E$8:$E$791,1)-INDEX(HIST_D!$E$8:$E$791,Control!$B$11))*100+(INDEX(HIST_D!$CP$8:$CP$791,1)-INDEX(HIST_D!$CP$8:$CP$791,Control!$B$11)),"") | M38: =IFERROR((INDEX(HIST_D!$E$8:$E$791,1)-INDEX(HIST_D!$E$8:$E$791,Control!$B$11))*100,"") | N38: =IFERROR((INDEX(HIST_D!$CP$8:$CP$791,1)-INDEX(HIST_D!$CP$8:$CP$791,Control!$B$11)),"") | O38: =IFERROR(IF(ABS(L38)<1,"n/m",M38/L38),"n/m") | P38: =IFERROR(SLOPE(HIST_D!$GA$8:INDEX(HIST_D!$GA$8:$GA$791,Control!$B$12),HIST_D!$CW$8:INDEX(HIST_D!$CW$8:$CW$791,Control!$B$12)),"") | Q38: =IFERROR(P38*(INDEX(HIST_D!$E$8:$E$791,1)-INDEX(HIST_D!$E$8:$E$791,Control!$B$11))*100,"") | R38: =IFERROR(N38-Q38,"")
A39: Thailand | B39: EM Asia | C39: =INDEX(HIST_D!$CQ$8:$CQ$791,1) | D39: yes | E39: =IFERROR((INDEX(HIST_D!$E$8:$E$791,1)-INDEX(HIST_D!$E$8:$E$791,Control!$B$10))*100+(INDEX(HIST_D!$CQ$8:$CQ$791,1)-INDEX(HIST_D!$CQ$8:$CQ$791,Control!$B$10)),"") | F39: =IFERROR((INDEX(HIST_D!$E$8:$E$791,1)-INDEX(HIST_D!$E$8:$E$791,Control!$B$10))*100,"") | G39: =IFERROR((INDEX(HIST_D!$CQ$8:$CQ$791,1)-INDEX(HIST_D!$CQ$8:$CQ$791,Control!$B$10)),"") | H39: =IFERROR(IF(ABS(E39)<1,"n/m",F39/E39),"n/m") | I39: =IFERROR(SLOPE(HIST_D!$GB$8:INDEX(HIST_D!$GB$8:$GB$791,Control!$B$12),HIST_D!$CW$8:INDEX(HIST_D!$CW$8:$CW$791,Control!$B$12)),"") | J39: =IFERROR(I39*(INDEX(HIST_D!$E$8:$E$791,1)-INDEX(HIST_D!$E$8:$E$791,Control!$B$10))*100,"") | K39: =IFERROR(G39-J39,"") | L39: =IFERROR((INDEX(HIST_D!$E$8:$E$791,1)-INDEX(HIST_D!$E$8:$E$791,Control!$B$11))*100+(INDEX(HIST_D!$CQ$8:$CQ$791,1)-INDEX(HIST_D!$CQ$8:$CQ$791,Control!$B$11)),"") | M39: =IFERROR((INDEX(HIST_D!$E$8:$E$791,1)-INDEX(HIST_D!$E$8:$E$791,Control!$B$11))*100,"") | N39: =IFERROR((INDEX(HIST_D!$CQ$8:$CQ$791,1)-INDEX(HIST_D!$CQ$8:$CQ$791,Control!$B$11)),"") | O39: =IFERROR(IF(ABS(L39)<1,"n/m",M39/L39),"n/m") | P39: =IFERROR(SLOPE(HIST_D!$GB$8:INDEX(HIST_D!$GB$8:$GB$791,Control!$B$12),HIST_D!$CW$8:INDEX(HIST_D!$CW$8:$CW$791,Control!$B$12)),"") | Q39: =IFERROR(P39*(INDEX(HIST_D!$E$8:$E$791,1)-INDEX(HIST_D!$E$8:$E$791,Control!$B$11))*100,"") | R39: =IFERROR(N39-Q39,"")
A40: Malaysia | B40: EM Asia | C40: =INDEX(HIST_D!$CR$8:$CR$791,1) | D40: yes | E40: =IFERROR((INDEX(HIST_D!$E$8:$E$791,1)-INDEX(HIST_D!$E$8:$E$791,Control!$B$10))*100+(INDEX(HIST_D!$CR$8:$CR$791,1)-INDEX(HIST_D!$CR$8:$CR$791,Control!$B$10)),"") | F40: =IFERROR((INDEX(HIST_D!$E$8:$E$791,1)-INDEX(HIST_D!$E$8:$E$791,Control!$B$10))*100,"") | G40: =IFERROR((INDEX(HIST_D!$CR$8:$CR$791,1)-INDEX(HIST_D!$CR$8:$CR$791,Control!$B$10)),"") | H40: =IFERROR(IF(ABS(E40)<1,"n/m",F40/E40),"n/m") | I40: =IFERROR(SLOPE(HIST_D!$GC$8:INDEX(HIST_D!$GC$8:$GC$791,Control!$B$12),HIST_D!$CW$8:INDEX(HIST_D!$CW$8:$CW$791,Control!$B$12)),"") | J40: =IFERROR(I40*(INDEX(HIST_D!$E$8:$E$791,1)-INDEX(HIST_D!$E$8:$E$791,Control!$B$10))*100,"") | K40: =IFERROR(G40-J40,"") | L40: =IFERROR((INDEX(HIST_D!$E$8:$E$791,1)-INDEX(HIST_D!$E$8:$E$791,Control!$B$11))*100+(INDEX(HIST_D!$CR$8:$CR$791,1)-INDEX(HIST_D!$CR$8:$CR$791,Control!$B$11)),"") | M40: =IFERROR((INDEX(HIST_D!$E$8:$E$791,1)-INDEX(HIST_D!$E$8:$E$791,Control!$B$11))*100,"") | N40: =IFERROR((INDEX(HIST_D!$CR$8:$CR$791,1)-INDEX(HIST_D!$CR$8:$CR$791,Control!$B$11)),"") | O40: =IFERROR(IF(ABS(L40)<1,"n/m",M40/L40),"n/m") | P40: =IFERROR(SLOPE(HIST_D!$GC$8:INDEX(HIST_D!$GC$8:$GC$791,Control!$B$12),HIST_D!$CW$8:INDEX(HIST_D!$CW$8:$CW$791,Control!$B$12)),"") | Q40: =IFERROR(P40*(INDEX(HIST_D!$E$8:$E$791,1)-INDEX(HIST_D!$E$8:$E$791,Control!$B$11))*100,"") | R40: =IFERROR(N40-Q40,"")
A41: Philippines | B41: EM Asia | C41: =INDEX(HIST_D!$CS$8:$CS$791,1) | D41: yes | E41: =IFERROR((INDEX(HIST_D!$E$8:$E$791,1)-INDEX(HIST_D!$E$8:$E$791,Control!$B$10))*100+(INDEX(HIST_D!$CS$8:$CS$791,1)-INDEX(HIST_D!$CS$8:$CS$791,Control!$B$10)),"") | F41: =IFERROR((INDEX(HIST_D!$E$8:$E$791,1)-INDEX(HIST_D!$E$8:$E$791,Control!$B$10))*100,"") | G41: =IFERROR((INDEX(HIST_D!$CS$8:$CS$791,1)-INDEX(HIST_D!$CS$8:$CS$791,Control!$B$10)),"") | H41: =IFERROR(IF(ABS(E41)<1,"n/m",F41/E41),"n/m") | I41: =IFERROR(SLOPE(HIST_D!$GD$8:INDEX(HIST_D!$GD$8:$GD$791,Control!$B$12),HIST_D!$CW$8:INDEX(HIST_D!$CW$8:$CW$791,Control!$B$12)),"") | J41: =IFERROR(I41*(INDEX(HIST_D!$E$8:$E$791,1)-INDEX(HIST_D!$E$8:$E$791,Control!$B$10))*100,"") | K41: =IFERROR(G41-J41,"") | L41: =IFERROR((INDEX(HIST_D!$E$8:$E$791,1)-INDEX(HIST_D!$E$8:$E$791,Control!$B$11))*100+(INDEX(HIST_D!$CS$8:$CS$791,1)-INDEX(HIST_D!$CS$8:$CS$791,Control!$B$11)),"") | M41: =IFERROR((INDEX(HIST_D!$E$8:$E$791,1)-INDEX(HIST_D!$E$8:$E$791,Control!$B$11))*100,"") | N41: =IFERROR((INDEX(HIST_D!$CS$8:$CS$791,1)-INDEX(HIST_D!$CS$8:$CS$791,Control!$B$11)),"") | O41: =IFERROR(IF(ABS(L41)<1,"n/m",M41/L41),"n/m") | P41: =IFERROR(SLOPE(HIST_D!$GD$8:INDEX(HIST_D!$GD$8:$GD$791,Control!$B$12),HIST_D!$CW$8:INDEX(HIST_D!$CW$8:$CW$791,Control!$B$12)),"") | Q41: =IFERROR(P41*(INDEX(HIST_D!$E$8:$E$791,1)-INDEX(HIST_D!$E$8:$E$791,Control!$B$11))*100,"") | R41: =IFERROR(N41-Q41,"")
A42: EM Asia average | B42: n=6 | E42: =IFERROR(AVERAGE(E36,E37,E38,E39,E40,E41),"") | F42: =IFERROR(AVERAGE(F36,F37,F38,F39,F40,F41),"") | G42: =IFERROR(AVERAGE(G36,G37,G38,G39,G40,G41),"") | H42: =IFERROR(IF(ABS(E42)<1,"n/m",F42/E42),"n/m") | I42: =IFERROR(AVERAGE(I36,I37,I38,I39,I40,I41),"") | J42: =IFERROR(AVERAGE(J36,J37,J38,J39,J40,J41),"") | K42: =IFERROR(AVERAGE(K36,K37,K38,K39,K40,K41),"") | L42: =IFERROR(AVERAGE(L36,L37,L38,L39,L40,L41),"") | M42: =IFERROR(AVERAGE(M36,M37,M38,M39,M40,M41),"") | N42: =IFERROR(AVERAGE(N36,N37,N38,N39,N40,N41),"") | O42: =IFERROR(IF(ABS(L42)<1,"n/m",M42/L42),"n/m") | P42: =IFERROR(AVERAGE(P36,P37,P38,P39,P40,P41),"") | Q42: =IFERROR(AVERAGE(Q36,Q37,Q38,Q39,Q40,Q41),"") | R42: =IFERROR(AVERAGE(R36,R37,R38,R39,R40,R41),"")
A43: =IFERROR("EM Asia: the 5y USD yield proxy moved "&TEXT($E$42,"+0;-0")&"bp on the month — "&TEXT($F$42,"+0;-0")&"bp Treasuries, "&TEXT($G$42,"+0;-0")&"bp spread"&IF(ISNUMBER($H$42),", so "&TEXT($H$42,"0%")&" of the move is the US","")&". YTD "&TEXT($L$42,"+0;-0")&"bp: "&TEXT($M$42,"+0;-0")&"bp Treasuries, "&TEXT($N$42,"+0;-0")&"bp spread. "&IF($G$42<=0,"Spreads did not widen into the Treasury move — the loss here is duration, not credit.",IF($G$42<$F$42*0.5,"Spreads widened, but by less than half the Treasury move — mostly a duration story.","Spreads widened by a comparable amount to Treasuries — this is being repriced for credit, not just rates.")),"")
A45: EM AVERAGE AND MEMO
A46: Country | B46: Region | C46: Level | D46: In avg | E46: 1M: Total: d(UST 5Y + CDS) (bp) | F46: 1M: US-driven: d UST 5Y (bp) | G46: 1M: Intrinsic: d CDS 5Y (bp) | H46: 1M: US share (UST / total) | I46: 1M: Spread beta to UST 5Y (2y) | J46: 1M: Predicted d spread (bp) | K46: 1M: Spread surprise: actual less predicted (bp) | L46: YTD: Total: d(UST 5Y + CDS) (bp) | M46: YTD: US-driven: d UST 5Y (bp) | N46: YTD: Intrinsic: d CDS 5Y (bp) | O46: YTD: US share (UST / total) | P46: YTD: Spread beta to UST 5Y (2y) | Q46: YTD: Predicted d spread (bp) | R46: YTD: Spread surprise: actual less predicted (bp)
A47: EM average (all flagged) | B47: n=21 | E47: =IFERROR(AVERAGE(E6,E7,E8,E9,E10,E16,E17,E18,E19,E20,E26,E27,E28,E29,E30,E36,E37,E38,E39,E40,E41),"") | F47: =IFERROR(AVERAGE(F6,F7,F8,F9,F10,F16,F17,F18,F19,F20,F26,F27,F28,F29,F30,F36,F37,F38,F39,F40,F41),"") | G47: =IFERROR(AVERAGE(G6,G7,G8,G9,G10,G16,G17,G18,G19,G20,G26,G27,G28,G29,G30,G36,G37,G38,G39,G40,G41),"") | H47: =IFERROR(IF(ABS(E47)<1,"n/m",F47/E47),"n/m") | I47: =IFERROR(AVERAGE(I6,I7,I8,I9,I10,I16,I17,I18,I19,I20,I26,I27,I28,I29,I30,I36,I37,I38,I39,I40,I41),"") | J47: =IFERROR(AVERAGE(J6,J7,J8,J9,J10,J16,J17,J18,J19,J20,J26,J27,J28,J29,J30,J36,J37,J38,J39,J40,J41),"") | K47: =IFERROR(AVERAGE(K6,K7,K8,K9,K10,K16,K17,K18,K19,K20,K26,K27,K28,K29,K30,K36,K37,K38,K39,K40,K41),"") | L47: =IFERROR(AVERAGE(L6,L7,L8,L9,L10,L16,L17,L18,L19,L20,L26,L27,L28,L29,L30,L36,L37,L38,L39,L40,L41),"") | M47: =IFERROR(AVERAGE(M6,M7,M8,M9,M10,M16,M17,M18,M19,M20,M26,M27,M28,M29,M30,M36,M37,M38,M39,M40,M41),"") | N47: =IFERROR(AVERAGE(N6,N7,N8,N9,N10,N16,N17,N18,N19,N20,N26,N27,N28,N29,N30,N36,N37,N38,N39,N40,N41),"") | O47: =IFERROR(IF(ABS(L47)<1,"n/m",M47/L47),"n/m") | P47: =IFERROR(AVERAGE(P6,P7,P8,P9,P10,P16,P17,P18,P19,P20,P26,P27,P28,P29,P30,P36,P37,P38,P39,P40,P41),"") | Q47: =IFERROR(AVERAGE(Q6,Q7,Q8,Q9,Q10,Q16,Q17,Q18,Q19,Q20,Q26,Q27,Q28,Q29,Q30,Q36,Q37,Q38,Q39,Q40,Q41),"") | R47: =IFERROR(AVERAGE(R6,R7,R8,R9,R10,R16,R17,R18,R19,R20,R26,R27,R28,R29,R30,R36,R37,R38,R39,R40,R41),"")
A48: South Africa | B48: (memo) | C48: =INDEX(HIST_D!$CT$8:$CT$791,1) | D48: no | E48: =IFERROR((INDEX(HIST_D!$E$8:$E$791,1)-INDEX(HIST_D!$E$8:$E$791,Control!$B$10))*100+(INDEX(HIST_D!$CT$8:$CT$791,1)-INDEX(HIST_D!$CT$8:$CT$791,Control!$B$10)),"") | F48: =IFERROR((INDEX(HIST_D!$E$8:$E$791,1)-INDEX(HIST_D!$E$8:$E$791,Control!$B$10))*100,"") | G48: =IFERROR((INDEX(HIST_D!$CT$8:$CT$791,1)-INDEX(HIST_D!$CT$8:$CT$791,Control!$B$10)),"") | H48: =IFERROR(IF(ABS(E48)<1,"n/m",F48/E48),"n/m") | I48: =IFERROR(SLOPE(HIST_D!$GE$8:INDEX(HIST_D!$GE$8:$GE$791,Control!$B$12),HIST_D!$CW$8:INDEX(HIST_D!$CW$8:$CW$791,Control!$B$12)),"") | J48: =IFERROR(I48*(INDEX(HIST_D!$E$8:$E$791,1)-INDEX(HIST_D!$E$8:$E$791,Control!$B$10))*100,"") | K48: =IFERROR(G48-J48,"") | L48: =IFERROR((INDEX(HIST_D!$E$8:$E$791,1)-INDEX(HIST_D!$E$8:$E$791,Control!$B$11))*100+(INDEX(HIST_D!$CT$8:$CT$791,1)-INDEX(HIST_D!$CT$8:$CT$791,Control!$B$11)),"") | M48: =IFERROR((INDEX(HIST_D!$E$8:$E$791,1)-INDEX(HIST_D!$E$8:$E$791,Control!$B$11))*100,"") | N48: =IFERROR((INDEX(HIST_D!$CT$8:$CT$791,1)-INDEX(HIST_D!$CT$8:$CT$791,Control!$B$11)),"") | O48: =IFERROR(IF(ABS(L48)<1,"n/m",M48/L48),"n/m") | P48: =IFERROR(SLOPE(HIST_D!$GE$8:INDEX(HIST_D!$GE$8:$GE$791,Control!$B$12),HIST_D!$CW$8:INDEX(HIST_D!$CW$8:$CW$791,Control!$B$12)),"") | Q48: =IFERROR(P48*(INDEX(HIST_D!$E$8:$E$791,1)-INDEX(HIST_D!$E$8:$E$791,Control!$B$11))*100,"") | R48: =IFERROR(N48-Q48,"") | S48: not in any of the four regions you named; shown as a memo line, in no average
A49: =IFERROR("EM: the 5y USD yield proxy moved "&TEXT($E$47,"+0;-0")&"bp on the month — "&TEXT($F$47,"+0;-0")&"bp Treasuries, "&TEXT($G$47,"+0;-0")&"bp spread"&IF(ISNUMBER($H$47),", so "&TEXT($H$47,"0%")&" of the move is the US","")&". YTD "&TEXT($L$47,"+0;-0")&"bp: "&TEXT($M$47,"+0;-0")&"bp Treasuries, "&TEXT($N$47,"+0;-0")&"bp spread. "&IF($G$47<=0,"Spreads did not widen into the Treasury move — the loss here is duration, not credit.",IF($G$47<$F$47*0.5,"Spreads widened, but by less than half the Treasury move — mostly a duration story.","Spreads widened by a comparable amount to Treasuries — this is being repriced for credit, not just rates.")),"")

Sheet Tickers
A1: TICKERS — single source of truth
A2: Every pull reads column B here. CDS tickers follow '<SOVR> CDS USD SR 5Y D14 Corp' and are all Verify; confirm each in SECF.
A5: Series | B5: Bloomberg ticker | C5: Field | D5: Unit | E5: Confidence | F5: Note
A6: MSCI World (USD) | B6: MXWO Index | C6: PX_LAST | D6: idx | E6: High | F6: equity benchmark: the US/DM factor
A7: MSCI EM (USD) | B7: MXEF Index | C7: PX_LAST | D7: idx | E7: High | F7: the EM equity benchmark itself
A8: UST 2Y | B8: USGG2YR Index | C8: PX_LAST | D8: % | E8: High
A9: UST 5Y | B9: USGG5YR Index | C9: PX_LAST | D9: % | E9: High | F9: credit benchmark (5y CDS)
A10: UST 10Y | B10: USGG10YR Index | C10: PX_LAST | D10: % | E10: High | F10: rates benchmark
A11: UST 30Y | B11: USGG30YR Index | C11: PX_LAST | D11: % | E11: High
A12: UST 10Y real | B12: USGGT10Y Index | C12: PX_LAST | D12: % | E12: High
A13: Breakeven 10Y | B13: USGGBE10 Index | C13: PX_LAST | D13: % | E13: High
A14: ACM term premium 10Y | B14: ACMTP10 Index | C14: PX_LAST | D14: % | E14: Verify | F14: NY Fed; publication lag
A15: DXY | B15: DXY Curncy | C15: PX_LAST | D15: pt | E15: High | F15: FX benchmark
A16: EM USD Aggregate OAS | B16: EMUSOAS Index | C16: PX_LAST | D16: bp | E16: Verify | F16: Bbg; aggregate spread cross-check
A17: EM USD Aggregate TR idx | B17: EMUSTRUU Index | C17: PX_LAST | D17: idx | E17: Verify | F17: realised index return
A18: Brazil FX | B18: USDBRL Curncy | C18: PX_LAST | D18: fx | E18: High | F18: LatAm
A19: Mexico FX | B19: USDMXN Curncy | C19: PX_LAST | D19: fx | E19: High | F19: LatAm
A20: Chile FX | B20: USDCLP Curncy | C20: PX_LAST | D20: fx | E20: High | F20: LatAm
A21: Colombia FX | B21: USDCOP Curncy | C21: PX_LAST | D21: fx | E21: High | F21: LatAm
A22: Peru FX | B22: USDPEN Curncy | C22: PX_LAST | D22: fx | E22: High | F22: LatAm
A23: Poland FX | B23: USDPLN Curncy | C23: PX_LAST | D23: fx | E23: High | F23: EM Europe
A24: Hungary FX | B24: USDHUF Curncy | C24: PX_LAST | D24: fx | E24: High | F24: EM Europe
A25: Czechia FX | B25: USDCZK Curncy | C25: PX_LAST | D25: fx | E25: High | F25: EM Europe
... A102: South Africa CDS 5Y | B102: SOAF CDS USD SR 5Y D14 Corp | C102: PX_LAST | D102: bp | E102: Verify | F102: (memo)

Sheet HIST_D
A1: DAILY HISTORY — 3y weekday block, newest first
A2: One BDH per series, row 8 = most recent. Column A/B come from one BDH with Dts=S; every other pulled column uses Dts=H.
A4: Pulled from Bloomberg
A5: Date | B5: MSCI World (USD) | C5: MSCI EM (USD) | D5: UST 2Y | E5: UST 5Y | F5: UST 10Y | G5: UST 30Y | H5: UST 10Y real | I5: Breakeven 10Y | J5: ACM term premium 10Y | K5: DXY | L5: EM USD Aggregate OAS | M5: EM USD Aggregate TR idx | N5: Brazil FX | O5: Mexico FX | P5: Chile FX | Q5: Colombia FX | R5: Peru FX | S5: Poland FX | T5: Hungary FX | U5: Czechia FX | V5: Romania FX | W5: Turkiye FX | X5: Israel FX | Y5: Egypt FX | Z5: China FX | AA5: India FX | AB5: Indonesia FX | AC5: Korea FX | AD5: Thailand FX | AE5: Malaysia FX | AF5: Philippines FX | AG5: South Africa FX | AH5: Brazil 10Y | AI5: Mexico 10Y | AJ5: Chile 10Y | AK5: Colombia 10Y | AL5: Peru 10Y | AM5: Poland 10Y | AN5: Hungary 10Y | AO5: Czechia 10Y | AP5: Romania 10Y | AQ5: Turkiye 10Y | AR5: Israel 10Y | AS5: Egypt 10Y | AT5: China 10Y | AU5: India 10Y | AV5: Indonesia 10Y | AW5: Korea 10Y | AX5: Thailand 10Y | AY5: Malaysia 10Y | AZ5: Philippines 10Y | BA5: South Africa 10Y | BB5: Brazil MSCI (USD) | BC5: Mexico MSCI (USD) | BD5: Chile MSCI (USD) | BE5: Colombia MSCI (USD) | BF5: Peru MSCI (USD) | BG5: Poland MSCI (USD) | BH5: Hungary MSCI (USD) | BI5: Czechia MSCI (USD) | BJ5: Romania MSCI (USD) | BK5: Turkiye MSCI (USD) | BL5: Saudi Arabia MSCI (USD) | BM5: UAE (Abu Dhabi) MSCI (USD) | BN5: Qatar MSCI (USD) | BO5: Israel MSCI (USD) | BP5: Egypt MSCI (USD) | BQ5: China MSCI (USD) | BR5: India MSCI (USD) | BS5: Indonesia MSCI (USD) | BT5: Korea MSCI (USD) | BU5: Thailand MSCI (USD) | BV5: Malaysia MSCI (USD) | BW5: Philippines MSCI (USD) | BX5: South Africa MSCI (USD) | BY5: Brazil CDS 5Y | BZ5: Mexico CDS 5Y | CA5: Chile CDS 5Y | CB5: Colombia CDS 5Y | CC5: Peru CDS 5Y | CD5: Poland CDS 5Y | CE5: Hungary CDS 5Y | CF5: Czechia CDS 5Y | CG5: Romania CDS 5Y | CH5: Turkiye CDS 5Y | CI5: Saudi Arabia CDS 5Y | CJ5: UAE (Abu Dhabi) CDS 5Y | CK5: Qatar CDS 5Y | CL5: Israel CDS 5Y | CM5: Egypt CDS 5Y | CN5: China CDS 5Y | CO5: Indonesia CDS 5Y | CP5: Korea CDS 5Y | CQ5: Thailand CDS 5Y | CR5: Malaysia CDS 5Y | CS5: Philippines CDS 5Y | CT5: South Africa CDS 5Y | CU5: MSCI World return (1d) | CV5: d UST 10Y (1d) | CW5: d UST 5Y (1d) | CX5: DXY return (1d) | CY5: d Brazil 10Y (1d) | CZ5: d Mexico 10Y (1d) | DA5: d Chile 10Y (1d) | DB5: d Colombia 10Y (1d) | DC5: d Peru 10Y (1d) | DD5: d Poland 10Y (1d) | DE5: d Hungary 10Y (1d) | DF5: d Czechia 10Y (1d) | DG5: d Romania 10Y (1d) | DH5: d Turkiye 10Y (1d) | DI5: d Israel 10Y (1d) | DJ5: d Egypt 10Y (1d) | DK5: d China 10Y (1d) | DL5: d India 10Y (1d) | DM5: d Indonesia 10Y (1d) | DN5: d Korea 10Y (1d) | DO5: d Thailand 10Y (1d) | DP5: d Malaysia 10Y (1d) | DQ5: d Philippines 10Y (1d) | DR5: d South Africa 10Y (1d) | DS5: Brazil ccy return (1d) | DT5: Mexico ccy return (1d) | DU5: Chile ccy return (1d) | DV5: Colombia ccy return (1d) | DW5: Peru ccy return (1d) | DX5: Poland ccy return (1d) | DY5: Hungary ccy return (1d) | DZ5: Czechia ccy return (1d) | EA5: Romania ccy return (1d) | EB5: Turkiye ccy return (1d) | EC5: Israel ccy return (1d) | ED5: Egypt ccy return (1d) | EE5: China ccy return (1d) | EF5: India ccy return (1d) | EG5: Indonesia ccy return (1d) | EH5: Korea ccy return (1d) | EI5: Thailand ccy return (1d) | EJ5: Malaysia ccy return (1d) | EK5: Philippines ccy return (1d) | EL5: South Africa ccy return (1d) | EM5: Brazil MSCI return (1d) | EN5: Mexico MSCI return (1d) | EO5: Chile MSCI return (1d) | EP5: Colombia MSCI return (1d) | EQ5: Peru MSCI return (1d) | ER5: Poland MSCI return (1d) | ES5: Hungary MSCI return (1d) | ET5: Czechia MSCI return (1d) | EU5: Romania MSCI return (1d) | EV5: Turkiye MSCI return (1d) | EW5: Saudi Arabia MSCI return (1d) | EX5: UAE (Abu Dhabi) MSCI return (1d) | EY5: Qatar MSCI return (1d) | EZ5: Israel MSCI return (1d) | FA5: Egypt MSCI return (1d) | FB5: China MSCI return (1d) | FC5: India MSCI return (1d) | FD5: Indonesia MSCI return (1d) | FE5: Korea MSCI return (1d) | FF5: Thailand MSCI return (1d) | FG5: Malaysia MSCI return (1d) | FH5: Philippines MSCI return (1d) | FI5: South Africa MSCI return (1d) | FJ5: d Brazil CDS (1d) | FK5: d Mexico CDS (1d) | FL5: d Chile CDS (1d) | FM5: d Colombia CDS (1d) | FN5: d Peru CDS (1d) | FO5: d Poland CDS (1d) | FP5: d Hungary CDS (1d) | FQ5: d Czechia CDS (1d) | FR5: d Romania CDS (1d) | FS5: d Turkiye CDS (1d) | FT5: d Saudi Arabia CDS (1d) | FU5: d UAE (Abu Dhabi) CDS (1d) | FV5: d Qatar CDS (1d) | FW5: d Israel CDS (1d) | FX5: d Egypt CDS (1d) | FY5: d China CDS (1d) | FZ5: d Indonesia CDS (1d) | GA5: d Korea CDS (1d) | GB5: d Thailand CDS (1d) | GC5: d Malaysia CDS (1d) | GD5: d Philippines CDS (1d) | GE5: d South Africa CDS (1d)
B6: =Tickers!$B$6 | C6: =Tickers!$B$7 | D6: =Tickers!$B$8 | E6: =Tickers!$B$9 | F6: =Tickers!$B$10 | G6: =Tickers!$B$11 | H6: =Tickers!$B$12 | I6: =Tickers!$B$13 | J6: =Tickers!$B$14 | K6: =Tickers!$B$15 | L6: =Tickers!$B$16 | M6: =Tickers!$B$17 | N6: =Tickers!$B$18 | O6: =Tickers!$B$19 | P6: =Tickers!$B$20 | Q6: =Tickers!$B$21 | R6: =Tickers!$B$22 | S6: =Tickers!$B$23 | T6: =Tickers!$B$24 | U6: =Tickers!$B$25 | V6: =Tickers!$B$26 | W6: =Tickers!$B$27 | X6: =Tickers!$B$28 | Y6: =Tickers!$B$29 | Z6: =Tickers!$B$30 | AA6: =Tickers!$B$31 | AB6: =Tickers!$B$32 | AC6: =Tickers!$B$33 | AD6: =Tickers!$B$34 | AE6: =Tickers!$B$35 | AF6: =Tickers!$B$36 | AG6: =Tickers!$B$37 | AH6: =Tickers!$B$38 | AI6: =Tickers!$B$39 | AJ6: =Tickers!$B$40 | AK6: =Tickers!$B$41 | AL6: =Tickers!$B$42 | AM6: =Tickers!$B$43 | AN6: =Tickers!$B$44 | AO6: =Tickers!$B$45 | AP6: =Tickers!$B$46 | AQ6: =Tickers!$B$47 | AR6: =Tickers!$B$48 | AS6: =Tickers!$B$49 | AT6: =Tickers!$B$50 | AU6: =Tickers!$B$51 | AV6: =Tickers!$B$52 | AW6: =Tickers!$B$53 | AX6: =Tickers!$B$54 | AY6: =Tickers!$B$55 | AZ6: =Tickers!$B$56 | BA6: =Tickers!$B$57 | BB6: =Tickers!$B$58 | BC6: =Tickers!$B$59 | BD6: =Tickers!$B$60 | BE6: =Tickers!$B$61 | BF6: =Tickers!$B$62 | BG6: =Tickers!$B$63 | BH6: =Tickers!$B$64 | BI6: =Tickers!$B$65 | BJ6: =Tickers!$B$66 | BK6: =Tickers!$B$67 | BL6: =Tickers!$B$68 | BM6: =Tickers!$B$69 | BN6: =Tickers!$B$70 | BO6: =Tickers!$B$71 | BP6: =Tickers!$B$72 | BQ6: =Tickers!$B$73 | BR6: =Tickers!$B$74 | BS6: =Tickers!$B$75 | BT6: =Tickers!$B$76 | BU6: =Tickers!$B$77 | BV6: =Tickers!$B$78 | BW6: =Tickers!$B$79 | BX6: =Tickers!$B$80 | BY6: =Tickers!$B$81 | BZ6: =Tickers!$B$82 | CA6: =Tickers!$B$83 | CB6: =Tickers!$B$84 | CC6: =Tickers!$B$85 | CD6: =Tickers!$B$86 | CE6: =Tickers!$B$87 | CF6: =Tickers!$B$88 | CG6: =Tickers!$B$89 | CH6: =Tickers!$B$90 | CI6: =Tickers!$B$91 | CJ6: =Tickers!$B$92 | CK6: =Tickers!$B$93 | CL6: =Tickers!$B$94 | CM6: =Tickers!$B$95 | CN6: =Tickers!$B$96 | CO6: =Tickers!$B$97 | CP6: =Tickers!$B$98 | CQ6: =Tickers!$B$99 | CR6: =Tickers!$B$100 | CS6: =Tickers!$B$101 | CT6: =Tickers!$B$102 | CU6: derived | CV6: derived | CW6: derived | CX6: derived | CY6: derived | CZ6: derived | DA6: derived | DB6: derived | DC6: derived | DD6: derived | DE6: derived | DF6: derived | DG6: derived | DH6: derived | DI6: derived | DJ6: derived | DK6: derived | DL6: derived | DM6: derived | DN6: derived | DO6: derived | DP6: derived | DQ6: derived | DR6: derived | DS6: derived | DT6: derived | DU6: derived | DV6: derived | DW6: derived | DX6: derived | DY6: derived | DZ6: derived | EA6: derived | EB6: derived | EC6: derived | ED6: derived | EE6: derived | EF6: derived | EG6: derived | EH6: derived | EI6: derived | EJ6: derived | EK6: derived | EL6: derived | EM6: derived | EN6: derived | EO6: derived | EP6: derived | EQ6: derived | ER6: derived | ES6: derived | ET6: derived | EU6: derived | EV6: derived | EW6: derived | EX6: derived | EY6: derived | EZ6: derived | FA6: derived | FB6: derived | FC6: derived | FD6: derived | FE6: derived | FF6: derived | FG6: derived | FH6: derived | FI6: derived | FJ6: derived | FK6: derived | FL6: derived | FM6: derived | FN6: derived | FO6: derived | FP6: derived | FQ6: derived | FR6: derived | FS6: derived | FT6: derived | FU6: derived | FV6: derived | FW6: derived | FX6: derived | FY6: derived | FZ6: derived | GA6: derived | GB6: derived | GC6: derived | GD6: derived | GE6: derived
A7: date | B7: idx | C7: idx | D7: % | E7: % | F7: % | G7: % | H7: % | I7: % | J7: % | K7: pt | L7: bp | M7: idx | N7: fx | O7: fx | P7: fx | Q7: fx | R7: fx | S7: fx | T7: fx | U7: fx | V7: fx | W7: fx | X7: fx | Y7: fx | Z7: fx | AA7: fx | AB7: fx | AC7: fx | AD7: fx | AE7: fx | AF7: fx | AG7: fx | AH7: % | AI7: % | AJ7: % | AK7: % | AL7: % | AM7: % | AN7: % | AO7: % | AP7: % | AQ7: % | AR7: % | AS7: % | AT7: % | AU7: % | AV7: % | AW7: % | AX7: % | AY7: % | AZ7: % | BA7: % | BB7: idx | BC7: idx | BD7: idx | BE7: idx | BF7: idx | BG7: idx | BH7: idx | BI7: idx | BJ7: idx | BK7: idx | BL7: idx | BM7: idx | BN7: idx | BO7: idx | BP7: idx | BQ7: idx | BR7: idx | BS7: idx | BT7: idx | BU7: idx | BV7: idx | BW7: idx | BX7: idx | BY7: bp | BZ7: bp | CA7: bp | CB7: bp | CC7: bp | CD7: bp | CE7: bp | CF7: bp | CG7: bp | CH7: bp | CI7: bp | CJ7: bp | CK7: bp | CL7: bp | CM7: bp | CN7: bp | CO7: bp | CP7: bp | CQ7: bp | CR7: bp | CS7: bp | CT7: bp | CU7: ret | CV7: bp | CW7: bp | CX7: ret | CY7: bp | CZ7: bp | DA7: bp | DB7: bp | DC7: bp | DD7: bp | DE7: bp | DF7: bp | DG7: bp | DH7: bp | DI7: bp | DJ7: bp | DK7: bp | DL7: bp | DM7: bp | DN7: bp | DO7: bp | DP7: bp | DQ7: bp | DR7: bp | DS7: ret | DT7: ret | DU7: ret | DV7: ret | DW7: ret | DX7: ret | DY7: ret | DZ7: ret | EA7: ret | EB7: ret | EC7: ret | ED7: ret | EE7: ret | EF7: ret | EG7: ret | EH7: ret | EI7: ret | EJ7: ret | EK7: ret | EL7: ret | EM7: ret | EN7: ret | EO7: ret | EP7: ret | EQ7: ret | ER7: ret | ES7: ret | ET7: ret | EU7: ret | EV7: ret | EW7: ret | EX7: ret | EY7: ret | EZ7: ret | FA7: ret | FB7: ret | FC7: ret | FD7: ret | FE7: ret | FF7: ret | FG7: ret | FH7: ret | FI7: ret | FJ7: bp | FK7: bp | FL7: bp | FM7: bp | FN7: bp | FO7: bp | FP7: bp | FQ7: bp | FR7: bp | FS7: bp | FT7: bp | FU7: bp | FV7: bp | FW7: bp | FX7: bp | FY7: bp | FZ7: bp | GA7: bp | GB7: bp | GC7: bp | GD7: bp | GE7: bp
