Workbook

Sheet Dashboard
B2: EM Sovereign Credit
B6: Cross-section fair value across the EMBI universe · re-fits every Bloomberg refresh · no frozen anything
B8: Snapshot | E8: Universe | H8: EM median spread | K8: HIGH-conf | N8: Live R² | Q8: Live β (slope) | V8: k | W8: country | X8: z-resid
B9: =TODAY() | E9: =COUNTA(Model!$B$15:$B$85) | H9: =IFERROR(ROUND(MEDIAN(Model!$E$15:$E$85),0),NA()) | K9: =COUNTIF(Model!$Y$15:$Y$85,"HIGH") | N9: =IFERROR(RSQ(Model!$S$15:$S$85,Model!$R$15:$R$85),NA()) | Q9: =IFERROR(SLOPE(Model!$S$15:$S$85,Model!$R$15:$R$85),NA()) | V9: 1 | W9: =IFERROR(INDEX(Model!$B$15:$B$85,MATCH(X9,Model!$V$15:$V$85,0)),"") | X9: =IFERROR(LARGE(Model!$V$15:$V$85,1),"")
V10: 2 | W10: =IFERROR(INDEX(Model!$B$15:$B$85,MATCH(X10,Model!$V$15:$V$85,0)),"") | X10: =IFERROR(LARGE(Model!$V$15:$V$85,2),"")
V11: 3 | W11: =IFERROR(INDEX(Model!$B$15:$B$85,MATCH(X11,Model!$V$15:$V$85,0)),"") | X11: =IFERROR(LARGE(Model!$V$15:$V$85,3),"")
V12: 4 | W12: =IFERROR(INDEX(Model!$B$15:$B$85,MATCH(X12,Model!$V$15:$V$85,0)),"") | X12: =IFERROR(LARGE(Model!$V$15:$V$85,4),"")
B13: Cheap / Rich distribution | V13: 5 | W13: =IFERROR(INDEX(Model!$B$15:$B$85,MATCH(X13,Model!$V$15:$V$85,0)),"") | X13: =IFERROR(LARGE(Model!$V$15:$V$85,5),"")
B14: CHEAP | F14: Slightly cheap | J14: Fair | N14: Slightly rich | Q14: RICH | V14: 6 | W14: =IFERROR(INDEX(Model!$B$15:$B$85,MATCH(X14,Model!$V$15:$V$85,0)),"") | X14: =IFERROR(LARGE(Model!$V$15:$V$85,6),"")
B15: =COUNTIF(Model!$W$15:$W$85,"CHEAP") | F15: =COUNTIF(Model!$W$15:$W$85,"slightly cheap") | J15: =COUNTIF(Model!$W$15:$W$85,"fair") | N15: =COUNTIF(Model!$W$15:$W$85,"slightly rich") | Q15: =COUNTIF(Model!$W$15:$W$85,"RICH") | V15: 7 | W15: =IFERROR(INDEX(Model!$B$15:$B$85,MATCH(X15,Model!$V$15:$V$85,0)),"") | X15: =IFERROR(LARGE(Model!$V$15:$V$85,7),"")
V16: 8 | W16: =IFERROR(INDEX(Model!$B$15:$B$85,MATCH(X16,Model!$V$15:$V$85,0)),"") | X16: =IFERROR(LARGE(Model!$V$15:$V$85,8),"")
B17: Data Coverage · countries by confidence tier | V17: 9 | W17: =IFERROR(INDEX(Model!$B$15:$B$85,MATCH(X17,Model!$V$15:$V$85,0)),"") | X17: =IFERROR(LARGE(Model!$V$15:$V$85,9),"")
B18: HIGH (5-6 vars) | H18: MED (3-4 vars) | N18: LOW (0-2 vars) | V18: 10 | W18: =IFERROR(INDEX(Model!$B$15:$B$85,MATCH(X18,Model!$V$15:$V$85,0)),"") | X18: =IFERROR(LARGE(Model!$V$15:$V$85,10),"")
B19: =COUNTIF(Model!$Y$15:$Y$85,"HIGH") | H19: =COUNTIF(Model!$Y$15:$Y$85,"MED") | N19: =COUNTIF(Model!$Y$15:$Y$85,"LOW") | V19: 11 | W19: =IFERROR(INDEX(Model!$B$15:$B$85,MATCH(X19,Model!$V$15:$V$85,0)),"") | X19: =IFERROR(LARGE(Model!$V$15:$V$85,11),"")
B20: Rank | C20: Country | D20: Spread | E20: Fund Z | F20: Resid | G20: Z-resid | H20: Signal | K20: Rank | L20: Country | M20: Spread | N20: Fund Z | O20: Resid | P20: Z-resid | Q20: Signal | V20: 12 | W20: =IFERROR(INDEX(Model!$B$15:$B$85,MATCH(X20,Model!$V$15:$V$85,0)),"") | X20: =IFERROR(LARGE(Model!$V$15:$V$85,12),"")
B21: 1 | C21: =IFERROR(INDEX(Model!$B$15:$B$85,MATCH(G21,Model!$V$15:$V$85,0)),"") | D21: =IFERROR(INDEX(Model!$E$15:$E$85,MATCH(G21,Model!$V$15:$V$85,0)),"") | E21: =IFERROR(INDEX(Model!$R$15:$R$85,MATCH(G21,Model!$V$15:$V$85,0)),"") | F21: =IFERROR(INDEX(Model!$U$15:$U$85,MATCH(G21,Model!$V$15:$V$85,0)),"") | G21: =IFERROR(LARGE(Model!$V$15:$V$85,1),"") | H21: =IFERROR(INDEX(Model!$W$15:$W$85,MATCH(G21,Model!$V$15:$V$85,0)),"") | K21: 1 | L21: =IFERROR(INDEX(Model!$B$15:$B$85,MATCH(P21,Model!$V$15:$V$85,0)),"") | M21: =IFERROR(INDEX(Model!$E$15:$E$85,MATCH(P21,Model!$V$15:$V$85,0)),"") | N21: =IFERROR(INDEX(Model!$R$15:$R$85,MATCH(P21,Model!$V$15:$V$85,0)),"") | O21: =IFERROR(INDEX(Model!$U$15:$U$85,MATCH(P21,Model!$V$15:$V$85,0)),"") | P21: =IFERROR(SMALL(Model!$V$15:$V$85,1),"") | Q21: =IFERROR(INDEX(Model!$W$15:$W$85,MATCH(P21,Model!$V$15:$V$85,0)),"") | V21: 13 | W21: =IFERROR(INDEX(Model!$B$15:$B$85,MATCH(X21,Model!$V$15:$V$85,0)),"") | X21: =IFERROR(LARGE(Model!$V$15:$V$85,13),"")
B22: 2 | C22: =IFERROR(INDEX(Model!$B$15:$B$85,MATCH(G22,Model!$V$15:$V$85,0)),"") | D22: =IFERROR(INDEX(Model!$E$15:$E$85,MATCH(G22,Model!$V$15:$V$85,0)),"") | E22: =IFERROR(INDEX(Model!$R$15:$R$85,MATCH(G22,Model!$V$15:$V$85,0)),"") | F22: =IFERROR(INDEX(Model!$U$15:$U$85,MATCH(G22,Model!$V$15:$V$85,0)),"") | G22: =IFERROR(LARGE(Model!$V$15:$V$85,2),"") | H22: =IFERROR(INDEX(Model!$W$15:$W$85,MATCH(G22,Model!$V$15:$V$85,0)),"") | K22: 2 | L22: =IFERROR(INDEX(Model!$B$15:$B$85,MATCH(P22,Model!$V$15:$V$85,0)),"") | M22: =IFERROR(INDEX(Model!$E$15:$E$85,MATCH(P22,Model!$V$15:$V$85,0)),"") | N22: =IFERROR(INDEX(Model!$R$15:$R$85,MATCH(P22,Model!$V$15:$V$85,0)),"") | O22: =IFERROR(INDEX(Model!$U$15:$U$85,MATCH(P22,Model!$V$15:$V$85,0)),"") | P22: =IFERROR(SMALL(Model!$V$15:$V$85,2),"") | Q22: =IFERROR(INDEX(Model!$W$15:$W$85,MATCH(P22,Model!$V$15:$V$85,0)),"") | V22: 14 | W22: =IFERROR(INDEX(Model!$B$15:$B$85,MATCH(X22,Model!$V$15:$V$85,0)),"") | X22: =IFERROR(LARGE(Model!$V$15:$V$85,14),"")
B23: 3 | C23: =IFERROR(INDEX(Model!$B$15:$B$85,MATCH(G23,Model!$V$15:$V$85,0)),"") | D23: =IFERROR(INDEX(Model!$E$15:$E$85,MATCH(G23,Model!$V$15:$V$85,0)),"") | E23: =IFERROR(INDEX(Model!$R$15:$R$85,MATCH(G23,Model!$V$15:$V$85,0)),"") | F23: =IFERROR(INDEX(Model!$U$15:$U$85,MATCH(G23,Model!$V$15:$V$85,0)),"") | G23: =IFERROR(LARGE(Model!$V$15:$V$85,3),"") | H23: =IFERROR(INDEX(Model!$W$15:$W$85,MATCH(G23,Model!$V$15:$V$85,0)),"") | K23: 3 | L23: =IFERROR(INDEX(Model!$B$15:$B$85,MATCH(P23,Model!$V$15:$V$85,0)),"") | M23: =IFERROR(INDEX(Model!$E$15:$E$85,MATCH(P23,Model!$V$15:$V$85,0)),"") | N23: =IFERROR(INDEX(Model!$R$15:$R$85,MATCH(P23,Model!$V$15:$V$85,0)),"") | O23: =IFERROR(INDEX(Model!$U$15:$U$85,MATCH(P23,Model!$V$15:$V$85,0)),"") | P23: =IFERROR(SMALL(Model!$V$15:$V$85,3),"") | Q23: =IFERROR(INDEX(Model!$W$15:$W$85,MATCH(P23,Model!$V$15:$V$85,0)),"") | V23: 15 | W23: =IFERROR(INDEX(Model!$B$15:$B$85,MATCH(X23,Model!$V$15:$V$85,0)),"") | X23: =IFERROR(LARGE(Model!$V$15:$V$85,15),"")
B24: 4 | C24: =IFERROR(INDEX(Model!$B$15:$B$85,MATCH(G24,Model!$V$15:$V$85,0)),"") | D24: =IFERROR(INDEX(Model!$E$15:$E$85,MATCH(G24,Model!$V$15:$V$85,0)),"") | E24: =IFERROR(INDEX(Model!$R$15:$R$85,MATCH(G24,Model!$V$15:$V$85,0)),"") | F24: =IFERROR(INDEX(Model!$U$15:$U$85,MATCH(G24,Model!$V$15:$V$85,0)),"") | G24: =IFERROR(LARGE(Model!$V$15:$V$85,4),"") | H24: =IFERROR(INDEX(Model!$W$15:$W$85,MATCH(G24,Model!$V$15:$V$85,0)),"") | K24: 4 | L24: =IFERROR(INDEX(Model!$B$15:$B$85,MATCH(P24,Model!$V$15:$V$85,0)),"") | M24: =IFERROR(INDEX(Model!$E$15:$E$85,MATCH(P24,Model!$V$15:$V$85,0)),"") | N24: =IFERROR(INDEX(Model!$R$15:$R$85,MATCH(P24,Model!$V$15:$V$85,0)),"") | O24: =IFERROR(INDEX(Model!$U$15:$U$85,MATCH(P24,Model!$V$15:$V$85,0)),"") | P24: =IFERROR(SMALL(Model!$V$15:$V$85,4),"") | Q24: =IFERROR(INDEX(Model!$W$15:$W$85,MATCH(P24,Model!$V$15:$V$85,0)),"") | V24: 16 | W24: =IFERROR(INDEX(Model!$B$15:$B$85,MATCH(X24,Model!$V$15:$V$85,0)),"") | X24: =IFERROR(LARGE(Model!$V$15:$V$85,16),"")
B25: 5 | C25: =IFERROR(INDEX(Model!$B$15:$B$85,MATCH(G25,Model!$V$15:$V$85,0)),"") | D25: =IFERROR(INDEX(Model!$E$15:$E$85,MATCH(G25,Model!$V$15:$V$85,0)),"") | E25: =IFERROR(INDEX(Model!$R$15:$R$85,MATCH(G25,Model!$V$15:$V$85,0)),"") | F25: =IFERROR(INDEX(Model!$U$15:$U$85,MATCH(G25,Model!$V$15:$V$85,0)),"") | G25: =IFERROR(LARGE(Model!$V$15:$V$85,5),"") | H25: =IFERROR(INDEX(Model!$W$15:$W$85,MATCH(G25,Model!$V$15:$V$85,0)),"") | K25: 5 | L25: =IFERROR(INDEX(Model!$B$15:$B$85,MATCH(P25,Model!$V$15:$V$85,0)),"") | M25: =IFERROR(INDEX(Model!$E$15:$E$85,MATCH(P25,Model!$V$15:$V$85,0)),"") | N25: =IFERROR(INDEX(Model!$R$15:$R$85,MATCH(P25,Model!$V$15:$V$85,0)),"") | O25: =IFERROR(INDEX(Model!$U$15:$U$85,MATCH(P25,Model!$V$15:$V$85,0)),"") | P25: =IFERROR(SMALL(Model!$V$15:$V$85,5),"") | Q25: =IFERROR(INDEX(Model!$W$15:$W$85,MATCH(P25,Model!$V$15:$V$85,0)),"") | V25: 17 | W25: =IFERROR(INDEX(Model!$B$15:$B$85,MATCH(X25,Model!$V$15:$V$85,0)),"") | X25: =IFERROR(LARGE(Model!$V$15:$V$85,17),"")
B26: 6 | C26: =IFERROR(INDEX(Model!$B$15:$B$85,MATCH(G26,Model!$V$15:$V$85,0)),"") | D26: =IFERROR(INDEX(Model!$E$15:$E$85,MATCH(G26,Model!$V$15:$V$85,0)),"") | E26: =IFERROR(INDEX(Model!$R$15:$R$85,MATCH(G26,Model!$V$15:$V$85,0)),"") | F26: =IFERROR(INDEX(Model!$U$15:$U$85,MATCH(G26,Model!$V$15:$V$85,0)),"") | G26: =IFERROR(LARGE(Model!$V$15:$V$85,6),"") | H26: =IFERROR(INDEX(Model!$W$15:$W$85,MATCH(G26,Model!$V$15:$V$85,0)),"") | K26: 6 | L26: =IFERROR(INDEX(Model!$B$15:$B$85,MATCH(P26,Model!$V$15:$V$85,0)),"") | M26: =IFERROR(INDEX(Model!$E$15:$E$85,MATCH(P26,Model!$V$15:$V$85,0)),"") | N26: =IFERROR(INDEX(Model!$R$15:$R$85,MATCH(P26,Model!$V$15:$V$85,0)),"") | O26: =IFERROR(INDEX(Model!$U$15:$U$85,MATCH(P26,Model!$V$15:$V$85,0)),"") | P26: =IFERROR(SMALL(Model!$V$15:$V$85,6),"") | Q26: =IFERROR(INDEX(Model!$W$15:$W$85,MATCH(P26,Model!$V$15:$V$85,0)),"") | V26: 18 | W26: =IFERROR(INDEX(Model!$B$15:$B$85,MATCH(X26,Model!$V$15:$V$85,0)),"") | X26: =IFERROR(LARGE(Model!$V$15:$V$85,18),"")
B27: 7 | C27: =IFERROR(INDEX(Model!$B$15:$B$85,MATCH(G27,Model!$V$15:$V$85,0)),"") | D27: =IFERROR(INDEX(Model!$E$15:$E$85,MATCH(G27,Model!$V$15:$V$85,0)),"") | E27: =IFERROR(INDEX(Model!$R$15:$R$85,MATCH(G27,Model!$V$15:$V$85,0)),"") | F27: =IFERROR(INDEX(Model!$U$15:$U$85,MATCH(G27,Model!$V$15:$V$85,0)),"") | G27: =IFERROR(LARGE(Model!$V$15:$V$85,7),"") | H27: =IFERROR(INDEX(Model!$W$15:$W$85,MATCH(G27,Model!$V$15:$V$85,0)),"") | K27: 7 | L27: =IFERROR(INDEX(Model!$B$15:$B$85,MATCH(P27,Model!$V$15:$V$85,0)),"") | M27: =IFERROR(INDEX(Model!$E$15:$E$85,MATCH(P27,Model!$V$15:$V$85,0)),"") | N27: =IFERROR(INDEX(Model!$R$15:$R$85,MATCH(P27,Model!$V$15:$V$85,0)),"") | O27: =IFERROR(INDEX(Model!$U$15:$U$85,MATCH(P27,Model!$V$15:$V$85,0)),"") | P27: =IFERROR(SMALL(Model!$V$15:$V$85,7),"") | Q27: =IFERROR(INDEX(Model!$W$15:$W$85,MATCH(P27,Model!$V$15:$V$85,0)),"") | V27: 19 | W27: =IFERROR(INDEX(Model!$B$15:$B$85,MATCH(X27,Model!$V$15:$V$85,0)),"") | X27: =IFERROR(LARGE(Model!$V$15:$V$85,19),"")
B28: 8 | C28: =IFERROR(INDEX(Model!$B$15:$B$85,MATCH(G28,Model!$V$15:$V$85,0)),"") | D28: =IFERROR(INDEX(Model!$E$15:$E$85,MATCH(G28,Model!$V$15:$V$85,0)),"") | E28: =IFERROR(INDEX(Model!$R$15:$R$85,MATCH(G28,Model!$V$15:$V$85,0)),"") | F28: =IFERROR(INDEX(Model!$U$15:$U$85,MATCH(G28,Model!$V$15:$V$85,0)),"") | G28: =IFERROR(LARGE(Model!$V$15:$V$85,8),"") | H28: =IFERROR(INDEX(Model!$W$15:$W$85,MATCH(G28,Model!$V$15:$V$85,0)),"") | K28: 8 | L28: =IFERROR(INDEX(Model!$B$15:$B$85,MATCH(P28,Model!$V$15:$V$85,0)),"") | M28: =IFERROR(INDEX(Model!$E$15:$E$85,MATCH(P28,Model!$V$15:$V$85,0)),"") | N28: =IFERROR(INDEX(Model!$R$15:$R$85,MATCH(P28,Model!$V$15:$V$85,0)),"") | O28: =IFERROR(INDEX(Model!$U$15:$U$85,MATCH(P28,Model!$V$15:$V$85,0)),"") | P28: =IFERROR(SMALL(Model!$V$15:$V$85,8),"") | Q28: =IFERROR(INDEX(Model!$W$15:$W$85,MATCH(P28,Model!$V$15:$V$85,0)),"") | V28: 20 | W28: =IFERROR(INDEX(Model!$B$15:$B$85,MATCH(X28,Model!$V$15:$V$85,0)),"") | X28: =IFERROR(LARGE(Model!$V$15:$V$85,20),"")
B29: 9 | C29: =IFERROR(INDEX(Model!$B$15:$B$85,MATCH(G29,Model!$V$15:$V$85,0)),"") | D29: =IFERROR(INDEX(Model!$E$15:$E$85,MATCH(G29,Model!$V$15:$V$85,0)),"") | E29: =IFERROR(INDEX(Model!$R$15:$R$85,MATCH(G29,Model!$V$15:$V$85,0)),"") | F29: =IFERROR(INDEX(Model!$U$15:$U$85,MATCH(G29,Model!$V$15:$V$85,0)),"") | G29: =IFERROR(LARGE(Model!$V$15:$V$85,9),"") | H29: =IFERROR(INDEX(Model!$W$15:$W$85,MATCH(G29,Model!$V$15:$V$85,0)),"") | K29: 9 | L29: =IFERROR(INDEX(Model!$B$15:$B$85,MATCH(P29,Model!$V$15:$V$85,0)),"") | M29: =IFERROR(INDEX(Model!$E$15:$E$85,MATCH(P29,Model!$V$15:$V$85,0)),"") | N29: =IFERROR(INDEX(Model!$R$15:$R$85,MATCH(P29,Model!$V$15:$V$85,0)),"") | O29: =IFERROR(INDEX(Model!$U$15:$U$85,MATCH(P29,Model!$V$15:$V$85,0)),"") | P29: =IFERROR(SMALL(Model!$V$15:$V$85,9),"") | Q29: =IFERROR(INDEX(Model!$W$15:$W$85,MATCH(P29,Model!$V$15:$V$85,0)),"") | V29: 21 | W29: =IFERROR(INDEX(Model!$B$15:$B$85,MATCH(X29,Model!$V$15:$V$85,0)),"") | X29: =IFERROR(LARGE(Model!$V$15:$V$85,21),"")
B30: 10 | C30: =IFERROR(INDEX(Model!$B$15:$B$85,MATCH(G30,Model!$V$15:$V$85,0)),"") | D30: =IFERROR(INDEX(Model!$E$15:$E$85,MATCH(G30,Model!$V$15:$V$85,0)),"") | E30: =IFERROR(INDEX(Model!$R$15:$R$85,MATCH(G30,Model!$V$15:$V$85,0)),"") | F30: =IFERROR(INDEX(Model!$U$15:$U$85,MATCH(G30,Model!$V$15:$V$85,0)),"") | G30: =IFERROR(LARGE(Model!$V$15:$V$85,10),"") | H30: =IFERROR(INDEX(Model!$W$15:$W$85,MATCH(G30,Model!$V$15:$V$85,0)),"") | K30: 10 | L30: =IFERROR(INDEX(Model!$B$15:$B$85,MATCH(P30,Model!$V$15:$V$85,0)),"") | M30: =IFERROR(INDEX(Model!$E$15:$E$85,MATCH(P30,Model!$V$15:$V$85,0)),"") | N30: =IFERROR(INDEX(Model!$R$15:$R$85,MATCH(P30,Model!$V$15:$V$85,0)),"") | O30: =IFERROR(INDEX(Model!$U$15:$U$85,MATCH(P30,Model!$V$15:$V$85,0)),"") | P30: =IFERROR(SMALL(Model!$V$15:$V$85,10),"") | Q30: =IFERROR(INDEX(Model!$W$15:$W$85,MATCH(P30,Model!$V$15:$V$85,0)),"") | V30: 22 | W30: =IFERROR(INDEX(Model!$B$15:$B$85,MATCH(X30,Model!$V$15:$V$85,0)),"") | X30: =IFERROR(LARGE(Model!$V$15:$V$85,22),"")
V31: 23 | W31: =IFERROR(INDEX(Model!$B$15:$B$85,MATCH(X31,Model!$V$15:$V$85,0)),"") | X31: =IFERROR(LARGE(Model!$V$15:$V$85,23),"")
V32: 24 | W32: =IFERROR(INDEX(Model!$B$15:$B$85,MATCH(X32,Model!$V$15:$V$85,0)),"") | X32: =IFERROR(LARGE(Model!$V$15:$V$85,24),"")
V33: 25 | W33: =IFERROR(INDEX(Model!$B$15:$B$85,MATCH(X33,Model!$V$15:$V$85,0)),"") | X33: =IFERROR(LARGE(Model!$V$15:$V$85,25),"")
V34: 26 | W34: =IFERROR(INDEX(Model!$B$15:$B$85,MATCH(X34,Model!$V$15:$V$85,0)),"") | X34: =IFERROR(LARGE(Model!$V$15:$V$85,26),"")
V35: 27 | W35: =IFERROR(INDEX(Model!$B$15:$B$85,MATCH(X35,Model!$V$15:$V$85,0)),"") | X35: =IFERROR(LARGE(Model!$V$15:$V$85,27),"")
V36: 28 | W36: =IFERROR(INDEX(Model!$B$15:$B$85,MATCH(X36,Model!$V$15:$V$85,0)),"") | X36: =IFERROR(LARGE(Model!$V$15:$V$85,28),"")
V37: 29 | W37: =IFERROR(INDEX(Model!$B$15:$B$85,MATCH(X37,Model!$V$15:$V$85,0)),"") | X37: =IFERROR(LARGE(Model!$V$15:$V$85,29),"")
V38: 30 | W38: =IFERROR(INDEX(Model!$B$15:$B$85,MATCH(X38,Model!$V$15:$V$85,0)),"") | X38: =IFERROR(LARGE(Model!$V$15:$V$85,30),"")
V39: 31 | W39: =IFERROR(INDEX(Model!$B$15:$B$85,MATCH(X39,Model!$V$15:$V$85,0)),"") | X39: =IFERROR(LARGE(Model!$V$15:$V$85,31),"")
V40: 32 | W40: =IFERROR(INDEX(Model!$B$15:$B$85,MATCH(X40,Model!$V$15:$V$85,0)),"") | X40: =IFERROR(LARGE(Model!$V$15:$V$85,32),"")
V41: 33 | W41: =IFERROR(INDEX(Model!$B$15:$B$85,MATCH(X41,Model!$V$15:$V$85,0)),"") | X41: =IFERROR(LARGE(Model!$V$15:$V$85,33),"")
V42: 34 | W42: =IFERROR(INDEX(Model!$B$15:$B$85,MATCH(X42,Model!$V$15:$V$85,0)),"") | X42: =IFERROR(LARGE(Model!$V$15:$V$85,34),"")
V43: 35 | W43: =IFERROR(INDEX(Model!$B$15:$B$85,MATCH(X43,Model!$V$15:$V$85,0)),"") | X43: =IFERROR(LARGE(Model!$V$15:$V$85,35),"")
V44: 36 | W44: =IFERROR(INDEX(Model!$B$15:$B$85,MATCH(X44,Model!$V$15:$V$85,0)),"") | X44: =IFERROR(LARGE(Model!$V$15:$V$85,36),"")
V45: 37 | W45: =IFERROR(INDEX(Model!$B$15:$B$85,MATCH(X45,Model!$V$15:$V$85,0)),"") | X45: =IFERROR(LARGE(Model!$V$15:$V$85,37),"")
V46: 38 | W46: =IFERROR(INDEX(Model!$B$15:$B$85,MATCH(X46,Model!$V$15:$V$85,0)),"") | X46: =IFERROR(LARGE(Model!$V$15:$V$85,38),"")
V47: 39 | W47: =IFERROR(INDEX(Model!$B$15:$B$85,MATCH(X47,Model!$V$15:$V$85,0)),"") | X47: =IFERROR(LARGE(Model!$V$15:$V$85,39),"")
V48: 40 | W48: =IFERROR(INDEX(Model!$B$15:$B$85,MATCH(X48,Model!$V$15:$V$85,0)),"") | X48: =IFERROR(LARGE(Model!$V$15:$V$85,40),"")
V49: 41 | W49: =IFERROR(INDEX(Model!$B$15:$B$85,MATCH(X49,Model!$V$15:$V$85,0)),"") | X49: =IFERROR(LARGE(Model!$V$15:$V$85,41),"")
V50: 42 | W50: =IFERROR(INDEX(Model!$B$15:$B$85,MATCH(X50,Model!$V$15:$V$85,0)),"") | X50: =IFERROR(LARGE(Model!$V$15:$V$85,42),"")
V51: 43 | W51: =IFERROR(INDEX(Model!$B$15:$B$85,MATCH(X51,Model!$V$15:$V$85,0)),"") | X51: =IFERROR(LARGE(Model!$V$15:$V$85,43),"")
V52: 44 | W52: =IFERROR(INDEX(Model!$B$15:$B$85,MATCH(X52,Model!$V$15:$V$85,0)),"") | X52: =IFERROR(LARGE(Model!$V$15:$V$85,44),"")
V53: 45 | W53: =IFERROR(INDEX(Model!$B$15:$B$85,MATCH(X53,Model!$V$15:$V$85,0)),"") | X53: =IFERROR(LARGE(Model!$V$15:$V$85,45),"")
V54: 46 | W54: =IFERROR(INDEX(Model!$B$15:$B$85,MATCH(X54,Model!$V$15:$V$85,0)),"") | X54: =IFERROR(LARGE(Model!$V$15:$V$85,46),"")
V55: 47 | W55: =IFERROR(INDEX(Model!$B$15:$B$85,MATCH(X55,Model!$V$15:$V$85,0)),"") | X55: =IFERROR(LARGE(Model!$V$15:$V$85,47),"")
V56: 48 | W56: =IFERROR(INDEX(Model!$B$15:$B$85,MATCH(X56,Model!$V$15:$V$85,0)),"") | X56: =IFERROR(LARGE(Model!$V$15:$V$85,48),"")
V57: 49 | W57: =IFERROR(INDEX(Model!$B$15:$B$85,MATCH(X57,Model!$V$15:$V$85,0)),"") | X57: =IFERROR(LARGE(Model!$V$15:$V$85,49),"")
V58: 50 | W58: =IFERROR(INDEX(Model!$B$15:$B$85,MATCH(X58,Model!$V$15:$V$85,0)),"") | X58: =IFERROR(LARGE(Model!$V$15:$V$85,50),"")
V59: 51 | W59: =IFERROR(INDEX(Model!$B$15:$B$85,MATCH(X59,Model!$V$15:$V$85,0)),"") | X59: =IFERROR(LARGE(Model!$V$15:$V$85,51),"")
V60: 52 | W60: =IFERROR(INDEX(Model!$B$15:$B$85,MATCH(X60,Model!$V$15:$V$85,0)),"") | X60: =IFERROR(LARGE(Model!$V$15:$V$85,52),"")
V61: 53 | W61: =IFERROR(INDEX(Model!$B$15:$B$85,MATCH(X61,Model!$V$15:$V$85,0)),"") | X61: =IFERROR(LARGE(Model!$V$15:$V$85,53),"")
V62: 54 | W62: =IFERROR(INDEX(Model!$B$15:$B$85,MATCH(X62,Model!$V$15:$V$85,0)),"") | X62: =IFERROR(LARGE(Model!$V$15:$V$85,54),"")
V63: 55 | W63: =IFERROR(INDEX(Model!$B$15:$B$85,MATCH(X63,Model!$V$15:$V$85,0)),"") | X63: =IFERROR(LARGE(Model!$V$15:$V$85,55),"")
V64: 56 | W64: =IFERROR(INDEX(Model!$B$15:$B$85,MATCH(X64,Model!$V$15:$V$85,0)),"") | X64: =IFERROR(LARGE(Model!$V$15:$V$85,56),"")
V65: 57 | W65: =IFERROR(INDEX(Model!$B$15:$B$85,MATCH(X65,Model!$V$15:$V$85,0)),"") | X65: =IFERROR(LARGE(Model!$V$15:$V$85,57),"")
V66: 58 | W66: =IFERROR(INDEX(Model!$B$15:$B$85,MATCH(X66,Model!$V$15:$V$85,0)),"") | X66: =IFERROR(LARGE(Model!$V$15:$V$85,58),"")
V67: 59 | W67: =IFERROR(INDEX(Model!$B$15:$B$85,MATCH(X67,Model!$V$15:$V$85,0)),"") | X67: =IFERROR(LARGE(Model!$V$15:$V$85,59),"")
V68: 60 | W68: =IFERROR(INDEX(Model!$B$15:$B$85,MATCH(X68,Model!$V$15:$V$85,0)),"") | X68: =IFERROR(LARGE(Model!$V$15:$V$85,60),"")
V69: 61 | W69: =IFERROR(INDEX(Model!$B$15:$B$85,MATCH(X69,Model!$V$15:$V$85,0)),"") | X69: =IFERROR(LARGE(Model!$V$15:$V$85,61),"")
V70: 62 | W70: =IFERROR(INDEX(Model!$B$15:$B$85,MATCH(X70,Model!$V$15:$V$85,0)),"") | X70: =IFERROR(LARGE(Model!$V$15:$V$85,62),"")
V71: 63 | W71: =IFERROR(INDEX(Model!$B$15:$B$85,MATCH(X71,Model!$V$15:$V$85,0)),"") | X71: =IFERROR(LARGE(Model!$V$15:$V$85,63),"")
V72: 64 | W72: =IFERROR(INDEX(Model!$B$15:$B$85,MATCH(X72,Model!$V$15:$V$85,0)),"") | X72: =IFERROR(LARGE(Model!$V$15:$V$85,64),"")
V73: 65 | W73: =IFERROR(INDEX(Model!$B$15:$B$85,MATCH(X73,Model!$V$15:$V$85,0)),"") | X73: =IFERROR(LARGE(Model!$V$15:$V$85,65),"")
V74: 66 | W74: =IFERROR(INDEX(Model!$B$15:$B$85,MATCH(X74,Model!$V$15:$V$85,0)),"") | X74: =IFERROR(LARGE(Model!$V$15:$V$85,66),"")
V75: 67 | W75: =IFERROR(INDEX(Model!$B$15:$B$85,MATCH(X75,Model!$V$15:$V$85,0)),"") | X75: =IFERROR(LARGE(Model!$V$15:$V$85,67),"")
V76: 68 | W76: =IFERROR(INDEX(Model!$B$15:$B$85,MATCH(X76,Model!$V$15:$V$85,0)),"") | X76: =IFERROR(LARGE(Model!$V$15:$V$85,68),"")
V77: 69 | W77: =IFERROR(INDEX(Model!$B$15:$B$85,MATCH(X77,Model!$V$15:$V$85,0)),"") | X77: =IFERROR(LARGE(Model!$V$15:$V$85,69),"")
V78: 70 | W78: =IFERROR(INDEX(Model!$B$15:$B$85,MATCH(X78,Model!$V$15:$V$85,0)),"") | X78: =IFERROR(LARGE(Model!$V$15:$V$85,70),"")
V79: 71 | W79: =IFERROR(INDEX(Model!$B$15:$B$85,MATCH(X79,Model!$V$15:$V$85,0)),"") | X79: =IFERROR(LARGE(Model!$V$15:$V$85,71),"")

Sheet Country
B2: Country Detail
B4: Pick a sovereign — KPIs and the scatter all update from live Bloomberg data.
B6: Sovereign: | C6: BRAZIL
B8: Spread (bps) | E8: Composite rating | H8: Fund. score | K8: Resid (log) | N8: Z-score signal
B9: =IFERROR(INDEX(Model!$E$15:$E$85,MATCH($C$6,Model!$B$15:$B$85,0)),NA()) | E9: =IFERROR(INDEX(Model!$D$15:$D$85,MATCH($C$6,Model!$B$15:$B$85,0)),NA()) | H9: =IFERROR(INDEX(Model!$R$15:$R$85,MATCH($C$6,Model!$B$15:$B$85,0)),NA()) | K9: =IFERROR(INDEX(Model!$U$15:$U$85,MATCH($C$6,Model!$B$15:$B$85,0)),NA()) | N9: =IFERROR(INDEX(Model!$V$15:$V$85,MATCH($C$6,Model!$B$15:$B$85,0)),NA())
B12: =IFERROR(INDEX(Model!$W$15:$W$85,MATCH($C$6,Model!$B$15:$B$85,0)),"-")
B14: Macro fundamentals · vs. peer-group cross-section
E15: Latest value | H15: Peer median | K15: Cross-section z
B16: GDP growth (%) | E16: =IFERROR(INDEX(Model!$G$15:$G$85,MATCH($C$6,Model!$B$15:$B$85,0)),"") | H16: =IFERROR(MEDIAN(Model!$G$15:$G$85),"") | K16: =IFERROR(INDEX(Model!$Q$15:$Q$85,MATCH($C$6,Model!$B$15:$B$85,0)),"")
B17: Inflation (%) | E17: =IFERROR(INDEX(Model!$H$15:$H$85,MATCH($C$6,Model!$B$15:$B$85,0)),"") | H17: =IFERROR(MEDIAN(Model!$H$15:$H$85),"") | K17: =IFERROR(INDEX(Model!$R$15:$R$85,MATCH($C$6,Model!$B$15:$B$85,0)),"")
B18: Govt debt (%GDP) | E18: =IFERROR(INDEX(Model!$I$15:$I$85,MATCH($C$6,Model!$B$15:$B$85,0)),"") | H18: =IFERROR(MEDIAN(Model!$I$15:$I$85),"") | K18: =IFERROR(INDEX(Model!$M$15:$M$85,MATCH($C$6,Model!$B$15:$B$85,0)),"")
B19: Curr acct (%GDP) | E19: =IFERROR(INDEX(Model!$J$15:$J$85,MATCH($C$6,Model!$B$15:$B$85,0)),"") | H19: =IFERROR(MEDIAN(Model!$J$15:$J$85),"") | K19: =IFERROR(INDEX(Model!$N$15:$N$85,MATCH($C$6,Model!$B$15:$B$85,0)),"")
B20: FX reserves (USD) | E20: =IFERROR(INDEX(Model!$K$15:$K$85,MATCH($C$6,Model!$B$15:$B$85,0)),"") | H20: =IFERROR(MEDIAN(Model!$K$15:$K$85),"") | K20: =IFERROR(INDEX(Model!$O$15:$O$85,MATCH($C$6,Model!$B$15:$B$85,0)),"")
B21: Rating (1=AAA→22=D) | E21: =IFERROR(INDEX(Model!$D$15:$D$85,MATCH($C$6,Model!$B$15:$B$85,0)),"") | H21: =IFERROR(MEDIAN(Model!$D$15:$D$85),"") | K21: =IFERROR(INDEX(Model!$L$15:$L$85,MATCH($C$6,Model!$B$15:$B$85,0)),"")
R200: helper
R201: =IFERROR(INDEX(Model!$R$15:$R$85,MATCH($C$6,Model!$B$15:$B$85,0)),NA()) | S201: =IFERROR(INDEX(Model!$S$15:$S$85,MATCH($C$6,Model!$B$15:$B$85,0)),NA())

Sheet Model
B2: Cross-Section Fair Value Model
B4: log(EMBI spread) = α + β · Composite Fundamental Score · coefficients re-estimated every Bloomberg refresh · no frozen anything
B6: Factor weights (editable, blue cells) | I6: Live regression coefficients
B7: Rating | C7: w_R | D7: 0.35 | I7: Intercept (α) | N7: =IFERROR(INTERCEPT($Z$15:$Z$85,$AA$15:$AA$85),"")
B8: Govt debt | C8: w_D | D8: 0.2 | I8: Slope (β) | N8: =IFERROR(SLOPE($Z$15:$Z$85,$AA$15:$AA$85),"")
B9: Curr acct | C9: w_C | D9: 0.15 | I9: R² | N9: =IFERROR(RSQ($Z$15:$Z$85,$AA$15:$AA$85),"")
B10: FX reserves | C10: w_X | D10: 0.1 | I10: # countries with full data | N10: =COUNT($AA$15:$AA$85)
B11: GDP growth | C11: w_g | D11: 0.12 | I11: Median spread (bps) | N11: =IFERROR(ROUND(MEDIAN($E$15:$E$85),0),"") | P11: Min vars in regression | S11: 4
B12: Inflation | C12: w_p | D12: 0.08 | I12: Snapshot | N12: =TODAY()
B13: Sum | D13: =SUM(D7:D12)
B14: Country | C14: ISO | D14: Rating# | E14: Spread bps | F14: CDS bps | G14: GDP % | H14: CPI % | I14: Debt %GDP | J14: CA %GDP | K14: Reserves | L14: zR | M14: zD | N14: zC | O14: zX | P14: zg | Q14: zp | R14: Fund Score | S14: log(spread) | T14: Fitted log | U14: Resid | V14: Z resid | W14: Signal | X14: Coverage | Y14: Conf | Z14: flt_logS | AA14: flt_F
B15: =Tickers!B7 | C15: =Tickers!C7 | D15: =Tickers!E7 | E15: =IFERROR(Tickers!G7,"") | F15: =IFERROR(Tickers!I7,"") | G15: =IFERROR(IF(ISNUMBER(Tickers!K7),Tickers!K7,IF(ISNUMBER(Haver!E7),Haver!E7,IF(ISNUMBER(Tickers!T7),Tickers!T7,""))),"") | H15: =IFERROR(IF(ISNUMBER(Tickers!M7),Tickers!M7,IF(ISNUMBER(Haver!G7),Haver!G7,IF(ISNUMBER(Tickers!U7),Tickers!U7,""))),"") | I15: =IFERROR(IF(ISNUMBER(Tickers!O7),Tickers!O7,IF(ISNUMBER(Haver!I7),Haver!I7,IF(ISNUMBER(Tickers!V7),Tickers!V7,""))),"") | J15: =IFERROR(IF(ISNUMBER(Tickers!Q7),Tickers!Q7,IF(ISNUMBER(Haver!K7),Haver!K7,IF(ISNUMBER(Tickers!W7),Tickers!W7,""))),"") | K15: =IFERROR(IF(ISNUMBER(Tickers!S7),Tickers!S7,IF(ISNUMBER(Haver!M7),Haver!M7,IF(ISNUMBER(Tickers!X7),Tickers!X7,""))),"") | L15: =IFERROR(($D$15-AVERAGE($D$15:$D$85))/STDEV($D$15:$D$85),"") | M15: =IFERROR(($I$15-AVERAGE($I$15:$I$85))/STDEV($I$15:$I$85),"") | N15: =IFERROR(-($J$15-AVERAGE($J$15:$J$85))/STDEV($J$15:$J$85),"") | O15: =IFERROR(-($K$15-AVERAGE($K$15:$K$85))/STDEV($K$15:$K$85),"") | P15: =IFERROR(-($G$15-AVERAGE($G$15:$G$85))/STDEV($G$15:$G$85),"") | Q15: =IFERROR(($H$15-AVERAGE($H$15:$H$85))/STDEV($H$15:$H$85),"") | R15: =IFERROR((IF(ISNUMBER(L15),$D$7*L15,0)+IF(ISNUMBER(M15),$D$8*M15,0)+IF(ISNUMBER(N15),$D$9*N15,0)+IF(ISNUMBER(O15),$D$10*O15,0)+IF(ISNUMBER(P15),$D$11*P15,0)+IF(ISNUMBER(Q15),$D$12*Q15,0))/(IF(ISNUMBER(L15),$D$7,0)+IF(ISNUMBER(M15),$D$8,0)+IF(ISNUMBER(N15),$D$9,0)+IF(ISNUMBER(O15),$D$10,0)+IF(ISNUMBER(P15),$D$11,0)+IF(ISNUMBER(Q15),$D$12,0)),"") | S15: =IFERROR(LN($E$15),"") | T15: =IFERROR($N$7+$N$8*$R$15,"") | U15: =IFERROR($S$15-$T$15,"") | V15: =IFERROR(($U$15-AVERAGE($U$15:$U$85))/STDEV($U$15:$U$85),"") | W15: =IF(ISNUMBER($V$15),IF($V$15>=1.5,"CHEAP",IF($V$15>=0.5,"slightly cheap",IF($V$15<=-1.5,"RICH",IF($V$15<=-0.5,"slightly rich","fair")))),"") | X15: =SUMPRODUCT(--ISNUMBER((D15,G15,H15,I15,J15,K15))) | Y15: =IF(X15>=5,"HIGH",IF(X15>=3,"MED","LOW")) | Z15: =IF(AND(ISNUMBER(S15),X15>=$S$11),S15,"") | AA15: =IF(AND(ISNUMBER(R15),X15>=$S$11),R15,"")
B16: =Tickers!B8 | C16: =Tickers!C8 | D16: =Tickers!E8 | E16: =IFERROR(Tickers!G8,"") | F16: =IFERROR(Tickers!I8,"") | G16: =IFERROR(IF(ISNUMBER(Tickers!K8),Tickers!K8,IF(ISNUMBER(Haver!E8),Haver!E8,IF(ISNUMBER(Tickers!T8),Tickers!T8,""))),"") | H16: =IFERROR(IF(ISNUMBER(Tickers!M8),Tickers!M8,IF(ISNUMBER(Haver!G8),Haver!G8,IF(ISNUMBER(Tickers!U8),Tickers!U8,""))),"") | I16: =IFERROR(IF(ISNUMBER(Tickers!O8),Tickers!O8,IF(ISNUMBER(Haver!I8),Haver!I8,IF(ISNUMBER(Tickers!V8),Tickers!V8,""))),"") | J16: =IFERROR(IF(ISNUMBER(Tickers!Q8),Tickers!Q8,IF(ISNUMBER(Haver!K8),Haver!K8,IF(ISNUMBER(Tickers!W8),Tickers!W8,""))),"") | K16: =IFERROR(IF(ISNUMBER(Tickers!S8),Tickers!S8,IF(ISNUMBER(Haver!M8),Haver!M8,IF(ISNUMBER(Tickers!X8),Tickers!X8,""))),"") | L16: =IFERROR(($D$16-AVERAGE($D$15:$D$85))/STDEV($D$15:$D$85),"") | M16: =IFERROR(($I$16-AVERAGE($I$15:$I$85))/STDEV($I$15:$I$85),"") | N16: =IFERROR(-($J$16-AVERAGE($J$15:$J$85))/STDEV($J$15:$J$85),"") | O16: =IFERROR(-($K$16-AVERAGE($K$15:$K$85))/STDEV($K$15:$K$85),"") | P16: =IFERROR(-($G$16-AVERAGE($G$15:$G$85))/STDEV($G$15:$G$85),"") | Q16: =IFERROR(($H$16-AVERAGE($H$15:$H$85))/STDEV($H$15:$H$85),"") | R16: =IFERROR((IF(ISNUMBER(L16),$D$7*L16,0)+IF(ISNUMBER(M16),$D$8*M16,0)+IF(ISNUMBER(N16),$D$9*N16,0)+IF(ISNUMBER(O16),$D$10*O16,0)+IF(ISNUMBER(P16),$D$11*P16,0)+IF(ISNUMBER(Q16),$D$12*Q16,0))/(IF(ISNUMBER(L16),$D$7,0)+IF(ISNUMBER(M16),$D$8,0)+IF(ISNUMBER(N16),$D$9,0)+IF(ISNUMBER(O16),$D$10,0)+IF(ISNUMBER(P16),$D$11,0)+IF(ISNUMBER(Q16),$D$12,0)),"") | S16: =IFERROR(LN($E$16),"") | T16: =IFERROR($N$7+$N$8*$R$16,"") | U16: =IFERROR($S$16-$T$16,"") | V16: =IFERROR(($U$16-AVERAGE($U$15:$U$85))/STDEV($U$15:$U$85),"") | W16: =IF(ISNUMBER($V$16),IF($V$16>=1.5,"CHEAP",IF($V$16>=0.5,"slightly cheap",IF($V$16<=-1.5,"RICH",IF($V$16<=-0.5,"slightly rich","fair")))),"") | X16: =SUMPRODUCT(--ISNUMBER((D16,G16,H16,I16,J16,K16))) | Y16: =IF(X16>=5,"HIGH",IF(X16>=3,"MED","LOW")) | Z16: =IF(AND(ISNUMBER(S16),X16>=$S$11),S16,"") | AA16: =IF(AND(ISNUMBER(R16),X16>=$S$11),R16,"")
B17: =Tickers!B9 | C17: =Tickers!C9 | D17: =Tickers!E9 | E17: =IFERROR(Tickers!G9,"") | F17: =IFERROR(Tickers!I9,"") | G17: =IFERROR(IF(ISNUMBER(Tickers!K9),Tickers!K9,IF(ISNUMBER(Haver!E9),Haver!E9,IF(ISNUMBER(Tickers!T9),Tickers!T9,""))),"") | H17: =IFERROR(IF(ISNUMBER(Tickers!M9),Tickers!M9,IF(ISNUMBER(Haver!G9),Haver!G9,IF(ISNUMBER(Tickers!U9),Tickers!U9,""))),"") | I17: =IFERROR(IF(ISNUMBER(Tickers!O9),Tickers!O9,IF(ISNUMBER(Haver!I9),Haver!I9,IF(ISNUMBER(Tickers!V9),Tickers!V9,""))),"") | J17: =IFERROR(IF(ISNUMBER(Tickers!Q9),Tickers!Q9,IF(ISNUMBER(Haver!K9),Haver!K9,IF(ISNUMBER(Tickers!W9),Tickers!W9,""))),"") | K17: =IFERROR(IF(ISNUMBER(Tickers!S9),Tickers!S9,IF(ISNUMBER(Haver!M9),Haver!M9,IF(ISNUMBER(Tickers!X9),Tickers!X9,""))),"") | L17: =IFERROR(($D$17-AVERAGE($D$15:$D$85))/STDEV($D$15:$D$85),"") | M17: =IFERROR(($I$17-AVERAGE($I$15:$I$85))/STDEV($I$15:$I$85),"") | N17: =IFERROR(-($J$17-AVERAGE($J$15:$J$85))/STDEV($J$15:$J$85),"") | O17: =IFERROR(-($K$17-AVERAGE($K$15:$K$85))/STDEV($K$15:$K$85),"") | P17: =IFERROR(-($G$17-AVERAGE($G$15:$G$85))/STDEV($G$15:$G$85),"") | Q17: =IFERROR(($H$17-AVERAGE($H$15:$H$85))/STDEV($H$15:$H$85),"") | R17: =IFERROR((IF(ISNUMBER(L17),$D$7*L17,0)+IF(ISNUMBER(M17),$D$8*M17,0)+IF(ISNUMBER(N17),$D$9*N17,0)+IF(ISNUMBER(O17),$D$10*O17,0)+IF(ISNUMBER(P17),$D$11*P17,0)+IF(ISNUMBER(Q17),$D$12*Q17,0))/(IF(ISNUMBER(L17),$D$7,0)+IF(ISNUMBER(M17),$D$8,0)+IF(ISNUMBER(N17),$D$9,0)+IF(ISNUMBER(O17),$D$10,0)+IF(ISNUMBER(P17),$D$11,0)+IF(ISNUMBER(Q17),$D$12,0)),"") | S17: =IFERROR(LN($E$17),"") | T17: =IFERROR($N$7+$N$8*$R$17,"") | U17: =IFERROR($S$17-$T$17,"") | V17: =IFERROR(($U$17-AVERAGE($U$15:$U$85))/STDEV($U$15:$U$85),"") | W17: =IF(ISNUMBER($V$17),IF($V$17>=1.5,"CHEAP",IF($V$17>=0.5,"slightly cheap",IF($V$17<=-1.5,"RICH",IF($V$17<=-0.5,"slightly rich","fair")))),"") | X17: =SUMPRODUCT(--ISNUMBER((D17,G17,H17,I17,J17,K17))) | Y17: =IF(X17>=5,"HIGH",IF(X17>=3,"MED","LOW")) | Z17: =IF(AND(ISNUMBER(S17),X17>=$S$11),S17,"") | AA17: =IF(AND(ISNUMBER(R17),X17>=$S$11),R17,"")
B18: =Tickers!B10 | C18: =Tickers!C10 | D18: =Tickers!E10 | E18: =IFERROR(Tickers!G10,"") | F18: =IFERROR(Tickers!I10,"") | G18: =IFERROR(IF(ISNUMBER(Tickers!K10),Tickers!K10,IF(ISNUMBER(Haver!E10),Haver!E10,IF(ISNUMBER(Tickers!T10),Tickers!T10,""))),"") | H18: =IFERROR(IF(ISNUMBER(Tickers!M10),Tickers!M10,IF(ISNUMBER(Haver!G10),Haver!G10,IF(ISNUMBER(Tickers!U10),Tickers!U10,""))),"") | I18: =IFERROR(IF(ISNUMBER(Tickers!O10),Tickers!O10,IF(ISNUMBER(Haver!I10),Haver!I10,IF(ISNUMBER(Tickers!V10),Tickers!V10,""))),"") | J18: =IFERROR(IF(ISNUMBER(Tickers!Q10),Tickers!Q10,IF(ISNUMBER(Haver!K10),Haver!K10,IF(ISNUMBER(Tickers!W10),Tickers!W10,""))),"") | K18: =IFERROR(IF(ISNUMBER(Tickers!S10),Tickers!S10,IF(ISNUMBER(Haver!M10),Haver!M10,IF(ISNUMBER(Tickers!X10),Tickers!X10,""))),"") | L18: =IFERROR(($D$18-AVERAGE($D$15:$D$85))/STDEV($D$15:$D$85),"") | M18: =IFERROR(($I$18-AVERAGE($I$15:$I$85))/STDEV($I$15:$I$85),"") | N18: =IFERROR(-($J$18-AVERAGE($J$15:$J$85))/STDEV($J$15:$J$85),"") | O18: =IFERROR(-($K$18-AVERAGE($K$15:$K$85))/STDEV($K$15:$K$85),"") | P18: =IFERROR(-($G$18-AVERAGE($G$15:$G$85))/STDEV($G$15:$G$85),"") | Q18: =IFERROR(($H$18-AVERAGE($H$15:$H$85))/STDEV($H$15:$H$85),"") | R18: =IFERROR((IF(ISNUMBER(L18),$D$7*L18,0)+IF(ISNUMBER(M18),$D$8*M18,0)+IF(ISNUMBER(N18),$D$9*N18,0)+IF(ISNUMBER(O18),$D$10*O18,0)+IF(ISNUMBER(P18),$D$11*P18,0)+IF(ISNUMBER(Q18),$D$12*Q18,0))/(IF(ISNUMBER(L18),$D$7,0)+IF(ISNUMBER(M18),$D$8,0)+IF(ISNUMBER(N18),$D$9,0)+IF(ISNUMBER(O18),$D$10,0)+IF(ISNUMBER(P18),$D$11,0)+IF(ISNUMBER(Q18),$D$12,0)),"") | S18: =IFERROR(LN($E$18),"") | T18: =IFERROR($N$7+$N$8*$R$18,"") | U18: =IFERROR($S$18-$T$18,"") | V18: =IFERROR(($U$18-AVERAGE($U$15:$U$85))/STDEV($U$15:$U$85),"") | W18: =IF(ISNUMBER($V$18),IF($V$18>=1.5,"CHEAP",IF($V$18>=0.5,"slightly cheap",IF($V$18<=-1.5,"RICH",IF($V$18<=-0.5,"slightly rich","fair")))),"") | X18: =SUMPRODUCT(--ISNUMBER((D18,G18,H18,I18,J18,K18))) | Y18: =IF(X18>=5,"HIGH",IF(X18>=3,"MED","LOW")) | Z18: =IF(AND(ISNUMBER(S18),X18>=$S$11),S18,"") | AA18: =IF(AND(ISNUMBER(R18),X18>=$S$11),R18,"")
B19: =Tickers!B11 | C19: =Tickers!C11 | D19: =Tickers!E11 | E19: =IFERROR(Tickers!G11,"") | F19: =IFERROR(Tickers!I11,"") | G19: =IFERROR(IF(ISNUMBER(Tickers!K11),Tickers!K11,IF(ISNUMBER(Haver!E11),Haver!E11,IF(ISNUMBER(Tickers!T11),Tickers!T11,""))),"") | H19: =IFERROR(IF(ISNUMBER(Tickers!M11),Tickers!M11,IF(ISNUMBER(Haver!G11),Haver!G11,IF(ISNUMBER(Tickers!U11),Tickers!U11,""))),"") | I19: =IFERROR(IF(ISNUMBER(Tickers!O11),Tickers!O11,IF(ISNUMBER(Haver!I11),Haver!I11,IF(ISNUMBER(Tickers!V11),Tickers!V11,""))),"") | J19: =IFERROR(IF(ISNUMBER(Tickers!Q11),Tickers!Q11,IF(ISNUMBER(Haver!K11),Haver!K11,IF(ISNUMBER(Tickers!W11),Tickers!W11,""))),"") | K19: =IFERROR(IF(ISNUMBER(Tickers!S11),Tickers!S11,IF(ISNUMBER(Haver!M11),Haver!M11,IF(ISNUMBER(Tickers!X11),Tickers!X11,""))),"") | L19: =IFERROR(($D$19-AVERAGE($D$15:$D$85))/STDEV($D$15:$D$85),"") | M19: =IFERROR(($I$19-AVERAGE($I$15:$I$85))/STDEV($I$15:$I$85),"") | N19: =IFERROR(-($J$19-AVERAGE($J$15:$J$85))/STDEV($J$15:$J$85),"") | O19: =IFERROR(-($K$19-AVERAGE($K$15:$K$85))/STDEV($K$15:$K$85),"") | P19: =IFERROR(-($G$19-AVERAGE($G$15:$G$85))/STDEV($G$15:$G$85),"") | Q19: =IFERROR(($H$19-AVERAGE($H$15:$H$85))/STDEV($H$15:$H$85),"") | R19: =IFERROR((IF(ISNUMBER(L19),$D$7*L19,0)+IF(ISNUMBER(M19),$D$8*M19,0)+IF(ISNUMBER(N19),$D$9*N19,0)+IF(ISNUMBER(O19),$D$10*O19,0)+IF(ISNUMBER(P19),$D$11*P19,0)+IF(ISNUMBER(Q19),$D$12*Q19,0))/(IF(ISNUMBER(L19),$D$7,0)+IF(ISNUMBER(M19),$D$8,0)+IF(ISNUMBER(N19),$D$9,0)+IF(ISNUMBER(O19),$D$10,0)+IF(ISNUMBER(P19),$D$11,0)+IF(ISNUMBER(Q19),$D$12,0)),"") | S19: =IFERROR(LN($E$19),"") | T19: =IFERROR($N$7+$N$8*$R$19,"") | U19: =IFERROR($S$19-$T$19,"") | V19: =IFERROR(($U$19-AVERAGE($U$15:$U$85))/STDEV($U$15:$U$85),"") | W19: =IF(ISNUMBER($V$19),IF($V$19>=1.5,"CHEAP",IF($V$19>=0.5,"slightly cheap",IF($V$19<=-1.5,"RICH",IF($V$19<=-0.5,"slightly rich","fair")))),"") | X19: =SUMPRODUCT(--ISNUMBER((D19,G19,H19,I19,J19,K19))) | Y19: =IF(X19>=5,"HIGH",IF(X19>=3,"MED","LOW")) | Z19: =IF(AND(ISNUMBER(S19),X19>=$S$11),S19,"") | AA19: =IF(AND(ISNUMBER(R19),X19>=$S$11),R19,"")
B20: =Tickers!B12 | C20: =Tickers!C12 | D20: =Tickers!E12 | E20: =IFERROR(Tickers!G12,"") | F20: =IFERROR(Tickers!I12,"") | G20: =IFERROR(IF(ISNUMBER(Tickers!K12),Tickers!K12,IF(ISNUMBER(Haver!E12),Haver!E12,IF(ISNUMBER(Tickers!T12),Tickers!T12,""))),"") | H20: =IFERROR(IF(ISNUMBER(Tickers!M12),Tickers!M12,IF(ISNUMBER(Haver!G12),Haver!G12,IF(ISNUMBER(Tickers!U12),Tickers!U12,""))),"") | I20: =IFERROR(IF(ISNUMBER(Tickers!O12),Tickers!O12,IF(ISNUMBER(Haver!I12),Haver!I12,IF(ISNUMBER(Tickers!V12),Tickers!V12,""))),"") | J20: =IFERROR(IF(ISNUMBER(Tickers!Q12),Tickers!Q12,IF(ISNUMBER(Haver!K12),Haver!K12,IF(ISNUMBER(Tickers!W12),Tickers!W12,""))),"") | K20: =IFERROR(IF(ISNUMBER(Tickers!S12),Tickers!S12,IF(ISNUMBER(Haver!M12),Haver!M12,IF(ISNUMBER(Tickers!X12),Tickers!X12,""))),"") | L20: =IFERROR(($D$20-AVERAGE($D$15:$D$85))/STDEV($D$15:$D$85),"") | M20: =IFERROR(($I$20-AVERAGE($I$15:$I$85))/STDEV($I$15:$I$85),"") | N20: =IFERROR(-($J$20-AVERAGE($J$15:$J$85))/STDEV($J$15:$J$85),"") | O20: =IFERROR(-($K$20-AVERAGE($K$15:$K$85))/STDEV($K$15:$K$85),"") | P20: =IFERROR(-($G$20-AVERAGE($G$15:$G$85))/STDEV($G$15:$G$85),"") | Q20: =IFERROR(($H$20-AVERAGE($H$15:$H$85))/STDEV($H$15:$H$85),"") | R20: =IFERROR((IF(ISNUMBER(L20),$D$7*L20,0)+IF(ISNUMBER(M20),$D$8*M20,0)+IF(ISNUMBER(N20),$D$9*N20,0)+IF(ISNUMBER(O20),$D$10*O20,0)+IF(ISNUMBER(P20),$D$11*P20,0)+IF(ISNUMBER(Q20),$D$12*Q20,0))/(IF(ISNUMBER(L20),$D$7,0)+IF(ISNUMBER(M20),$D$8,0)+IF(ISNUMBER(N20),$D$9,0)+IF(ISNUMBER(O20),$D$10,0)+IF(ISNUMBER(P20),$D$11,0)+IF(ISNUMBER(Q20),$D$12,0)),"") | S20: =IFERROR(LN($E$20),"") | T20: =IFERROR($N$7+$N$8*$R$20,"") | U20: =IFERROR($S$20-$T$20,"") | V20: =IFERROR(($U$20-AVERAGE($U$15:$U$85))/STDEV($U$15:$U$85),"") | W20: =IF(ISNUMBER($V$20),IF($V$20>=1.5,"CHEAP",IF($V$20>=0.5,"slightly cheap",IF($V$20<=-1.5,"RICH",IF($V$20<=-0.5,"slightly rich","fair")))),"") | X20: =SUMPRODUCT(--ISNUMBER((D20,G20,H20,I20,J20,K20))) | Y20: =IF(X20>=5,"HIGH",IF(X20>=3,"MED","LOW")) | Z20: =IF(AND(ISNUMBER(S20),X20>=$S$11),S20,"") | AA20: =IF(AND(ISNUMBER(R20),X20>=$S$11),R20,"")
B21: =Tickers!B13 | C21: =Tickers!C13 | D21: =Tickers!E13 | E21: =IFERROR(Tickers!G13,"") | F21: =IFERROR(Tickers!I13,"") | G21: =IFERROR(IF(ISNUMBER(Tickers!K13),Tickers!K13,IF(ISNUMBER(Haver!E13),Haver!E13,IF(ISNUMBER(Tickers!T13),Tickers!T13,""))),"") | H21: =IFERROR(IF(ISNUMBER(Tickers!M13),Tickers!M13,IF(ISNUMBER(Haver!G13),Haver!G13,IF(ISNUMBER(Tickers!U13),Tickers!U13,""))),"") | I21: =IFERROR(IF(ISNUMBER(Tickers!O13),Tickers!O13,IF(ISNUMBER(Haver!I13),Haver!I13,IF(ISNUMBER(Tickers!V13),Tickers!V13,""))),"") | J21: =IFERROR(IF(ISNUMBER(Tickers!Q13),Tickers!Q13,IF(ISNUMBER(Haver!K13),Haver!K13,IF(ISNUMBER(Tickers!W13),Tickers!W13,""))),"") | K21: =IFERROR(IF(ISNUMBER(Tickers!S13),Tickers!S13,IF(ISNUMBER(Haver!M13),Haver!M13,IF(ISNUMBER(Tickers!X13),Tickers!X13,""))),"") | L21: =IFERROR(($D$21-AVERAGE($D$15:$D$85))/STDEV($D$15:$D$85),"") | M21: =IFERROR(($I$21-AVERAGE($I$15:$I$85))/STDEV($I$15:$I$85),"") | N21: =IFERROR(-($J$21-AVERAGE($J$15:$J$85))/STDEV($J$15:$J$85),"") | O21: =IFERROR(-($K$21-AVERAGE($K$15:$K$85))/STDEV($K$15:$K$85),"") | P21: =IFERROR(-($G$21-AVERAGE($G$15:$G$85))/STDEV($G$15:$G$85),"") | Q21: =IFERROR(($H$21-AVERAGE($H$15:$H$85))/STDEV($H$15:$H$85),"") | R21: =IFERROR((IF(ISNUMBER(L21),$D$7*L21,0)+IF(ISNUMBER(M21),$D$8*M21,0)+IF(ISNUMBER(N21),$D$9*N21,0)+IF(ISNUMBER(O21),$D$10*O21,0)+IF(ISNUMBER(P21),$D$11*P21,0)+IF(ISNUMBER(Q21),$D$12*Q21,0))/(IF(ISNUMBER(L21),$D$7,0)+IF(ISNUMBER(M21),$D$8,0)+IF(ISNUMBER(N21),$D$9,0)+IF(ISNUMBER(O21),$D$10,0)+IF(ISNUMBER(P21),$D$11,0)+IF(ISNUMBER(Q21),$D$12,0)),"") | S21: =IFERROR(LN($E$21),"") | T21: =IFERROR($N$7+$N$8*$R$21,"") | U21: =IFERROR($S$21-$T$21,"") | V21: =IFERROR(($U$21-AVERAGE($U$15:$U$85))/STDEV($U$15:$U$85),"") | W21: =IF(ISNUMBER($V$21),IF($V$21>=1.5,"CHEAP",IF($V$21>=0.5,"slightly cheap",IF($V$21<=-1.5,"RICH",IF($V$21<=-0.5,"slightly rich","fair")))),"") | X21: =SUMPRODUCT(--ISNUMBER((D21,G21,H21,I21,J21,K21))) | Y21: =IF(X21>=5,"HIGH",IF(X21>=3,"MED","LOW")) | Z21: =IF(AND(ISNUMBER(S21),X21>=$S$11),S21,"") | AA21: =IF(AND(ISNUMBER(R21),X21>=$S$11),R21,"")
B22: =Tickers!B14 | C22: =Tickers!C14 | D22: =Tickers!E14 | E22: =IFERROR(Tickers!G14,"") | F22: =IFERROR(Tickers!I14,"") | G22: =IFERROR(IF(ISNUMBER(Tickers!K14),Tickers!K14,IF(ISNUMBER(Haver!E14),Haver!E14,IF(ISNUMBER(Tickers!T14),Tickers!T14,""))),"") | H22: =IFERROR(IF(ISNUMBER(Tickers!M14),Tickers!M14,IF(ISNUMBER(Haver!G14),Haver!G14,IF(ISNUMBER(Tickers!U14),Tickers!U14,""))),"") | I22: =IFERROR(IF(ISNUMBER(Tickers!O14),Tickers!O14,IF(ISNUMBER(Haver!I14),Haver!I14,IF(ISNUMBER(Tickers!V14),Tickers!V14,""))),"") | J22: =IFERROR(IF(ISNUMBER(Tickers!Q14),Tickers!Q14,IF(ISNUMBER(Haver!K14),Haver!K14,IF(ISNUMBER(Tickers!W14),Tickers!W14,""))),"") | K22: =IFERROR(IF(ISNUMBER(Tickers!S14),Tickers!S14,IF(ISNUMBER(Haver!M14),Haver!M14,IF(ISNUMBER(Tickers!X14),Tickers!X14,""))),"") | L22: =IFERROR(($D$22-AVERAGE($D$15:$D$85))/STDEV($D$15:$D$85),"") | M22: =IFERROR(($I$22-AVERAGE($I$15:$I$85))/STDEV($I$15:$I$85),"") | N22: =IFERROR(-($J$22-AVERAGE($J$15:$J$85))/STDEV($J$15:$J$85),"") | O22: =IFERROR(-($K$22-AVERAGE($K$15:$K$85))/STDEV($K$15:$K$85),"") | P22: =IFERROR(-($G$22-AVERAGE($G$15:$G$85))/STDEV($G$15:$G$85),"") | Q22: =IFERROR(($H$22-AVERAGE($H$15:$H$85))/STDEV($H$15:$H$85),"") | R22: =IFERROR((IF(ISNUMBER(L22),$D$7*L22,0)+IF(ISNUMBER(M22),$D$8*M22,0)+IF(ISNUMBER(N22),$D$9*N22,0)+IF(ISNUMBER(O22),$D$10*O22,0)+IF(ISNUMBER(P22),$D$11*P22,0)+IF(ISNUMBER(Q22),$D$12*Q22,0))/(IF(ISNUMBER(L22),$D$7,0)+IF(ISNUMBER(M22),$D$8,0)+IF(ISNUMBER(N22),$D$9,0)+IF(ISNUMBER(O22),$D$10,0)+IF(ISNUMBER(P22),$D$11,0)+IF(ISNUMBER(Q22),$D$12,0)),"") | S22: =IFERROR(LN($E$22),"") | T22: =IFERROR($N$7+$N$8*$R$22,"") | U22: =IFERROR($S$22-$T$22,"") | V22: =IFERROR(($U$22-AVERAGE($U$15:$U$85))/STDEV($U$15:$U$85),"") | W22: =IF(ISNUMBER($V$22),IF($V$22>=1.5,"CHEAP",IF($V$22>=0.5,"slightly cheap",IF($V$22<=-1.5,"RICH",IF($V$22<=-0.5,"slightly rich","fair")))),"") | X22: =SUMPRODUCT(--ISNUMBER((D22,G22,H22,I22,J22,K22))) | Y22: =IF(X22>=5,"HIGH",IF(X22>=3,"MED","LOW")) | Z22: =IF(AND(ISNUMBER(S22),X22>=$S$11),S22,"") | AA22: =IF(AND(ISNUMBER(R22),X22>=$S$11),R22,"")
B23: =Tickers!B15 | C23: =Tickers!C15 | D23: =Tickers!E15 | E23: =IFERROR(Tickers!G15,"") | F23: =IFERROR(Tickers!I15,"") | G23: =IFERROR(IF(ISNUMBER(Tickers!K15),Tickers!K15,IF(ISNUMBER(Haver!E15),Haver!E15,IF(ISNUMBER(Tickers!T15),Tickers!T15,""))),"") | H23: =IFERROR(IF(ISNUMBER(Tickers!M15),Tickers!M15,IF(ISNUMBER(Haver!G15),Haver!G15,IF(ISNUMBER(Tickers!U15),Tickers!U15,""))),"") | I23: =IFERROR(IF(ISNUMBER(Tickers!O15),Tickers!O15,IF(ISNUMBER(Haver!I15),Haver!I15,IF(ISNUMBER(Tickers!V15),Tickers!V15,""))),"") | J23: =IFERROR(IF(ISNUMBER(Tickers!Q15),Tickers!Q15,IF(ISNUMBER(Haver!K15),Haver!K15,IF(ISNUMBER(Tickers!W15),Tickers!W15,""))),"") | K23: =IFERROR(IF(ISNUMBER(Tickers!S15),Tickers!S15,IF(ISNUMBER(Haver!M15),Haver!M15,IF(ISNUMBER(Tickers!X15),Tickers!X15,""))),"") | L23: =IFERROR(($D$23-AVERAGE($D$15:$D$85))/STDEV($D$15:$D$85),"") | M23: =IFERROR(($I$23-AVERAGE($I$15:$I$85))/STDEV($I$15:$I$85),"") | N23: =IFERROR(-($J$23-AVERAGE($J$15:$J$85))/STDEV($J$15:$J$85),"") | O23: =IFERROR(-($K$23-AVERAGE($K$15:$K$85))/STDEV($K$15:$K$85),"") | P23: =IFERROR(-($G$23-AVERAGE($G$15:$G$85))/STDEV($G$15:$G$85),"") | Q23: =IFERROR(($H$23-AVERAGE($H$15:$H$85))/STDEV($H$15:$H$85),"") | R23: =IFERROR((IF(ISNUMBER(L23),$D$7*L23,0)+IF(ISNUMBER(M23),$D$8*M23,0)+IF(ISNUMBER(N23),$D$9*N23,0)+IF(ISNUMBER(O23),$D$10*O23,0)+IF(ISNUMBER(P23),$D$11*P23,0)+IF(ISNUMBER(Q23),$D$12*Q23,0))/(IF(ISNUMBER(L23),$D$7,0)+IF(ISNUMBER(M23),$D$8,0)+IF(ISNUMBER(N23),$D$9,0)+IF(ISNUMBER(O23),$D$10,0)+IF(ISNUMBER(P23),$D$11,0)+IF(ISNUMBER(Q23),$D$12,0)),"") | S23: =IFERROR(LN($E$23),"") | T23: =IFERROR($N$7+$N$8*$R$23,"") | U23: =IFERROR($S$23-$T$23,"") | V23: =IFERROR(($U$23-AVERAGE($U$15:$U$85))/STDEV($U$15:$U$85),"") | W23: =IF(ISNUMBER($V$23),IF($V$23>=1.5,"CHEAP",IF($V$23>=0.5,"slightly cheap",IF($V$23<=-1.5,"RICH",IF($V$23<=-0.5,"slightly rich","fair")))),"") | X23: =SUMPRODUCT(--ISNUMBER((D23,G23,H23,I23,J23,K23))) | Y23: =IF(X23>=5,"HIGH",IF(X23>=3,"MED","LOW")) | Z23: =IF(AND(ISNUMBER(S23),X23>=$S$11),S23,"") | AA23: =IF(AND(ISNUMBER(R23),X23>=$S$11),R23,"")
B24: =Tickers!B16 | C24: =Tickers!C16 | D24: =Tickers!E16 | E24: =IFERROR(Tickers!G16,"") | F24: =IFERROR(Tickers!I16,"") | G24: =IFERROR(IF(ISNUMBER(Tickers!K16),Tickers!K16,IF(ISNUMBER(Haver!E16),Haver!E16,IF(ISNUMBER(Tickers!T16),Tickers!T16,""))),"") | H24: =IFERROR(IF(ISNUMBER(Tickers!M16),Tickers!M16,IF(ISNUMBER(Haver!G16),Haver!G16,IF(ISNUMBER(Tickers!U16),Tickers!U16,""))),"") | I24: =IFERROR(IF(ISNUMBER(Tickers!O16),Tickers!O16,IF(ISNUMBER(Haver!I16),Haver!I16,IF(ISNUMBER(Tickers!V16),Tickers!V16,""))),"") | J24: =IFERROR(IF(ISNUMBER(Tickers!Q16),Tickers!Q16,IF(ISNUMBER(Haver!K16),Haver!K16,IF(ISNUMBER(Tickers!W16),Tickers!W16,""))),"") | K24: =IFERROR(IF(ISNUMBER(Tickers!S16),Tickers!S16,IF(ISNUMBER(Haver!M16),Haver!M16,IF(ISNUMBER(Tickers!X16),Tickers!X16,""))),"") | L24: =IFERROR(($D$24-AVERAGE($D$15:$D$85))/STDEV($D$15:$D$85),"") | M24: =IFERROR(($I$24-AVERAGE($I$15:$I$85))/STDEV($I$15:$I$85),"") | N24: =IFERROR(-($J$24-AVERAGE($J$15:$J$85))/STDEV($J$15:$J$85),"") | O24: =IFERROR(-($K$24-AVERAGE($K$15:$K$85))/STDEV($K$15:$K$85),"") | P24: =IFERROR(-($G$24-AVERAGE($G$15:$G$85))/STDEV($G$15:$G$85),"") | Q24: =IFERROR(($H$24-AVERAGE($H$15:$H$85))/STDEV($H$15:$H$85),"") | R24: =IFERROR((IF(ISNUMBER(L24),$D$7*L24,0)+IF(ISNUMBER(M24),$D$8*M24,0)+IF(ISNUMBER(N24),$D$9*N24,0)+IF(ISNUMBER(O24),$D$10*O24,0)+IF(ISNUMBER(P24),$D$11*P24,0)+IF(ISNUMBER(Q24),$D$12*Q24,0))/(IF(ISNUMBER(L24),$D$7,0)+IF(ISNUMBER(M24),$D$8,0)+IF(ISNUMBER(N24),$D$9,0)+IF(ISNUMBER(O24),$D$10,0)+IF(ISNUMBER(P24),$D$11,0)+IF(ISNUMBER(Q24),$D$12,0)),"") | S24: =IFERROR(LN($E$24),"") | T24: =IFERROR($N$7+$N$8*$R$24,"") | U24: =IFERROR($S$24-$T$24,"") | V24: =IFERROR(($U$24-AVERAGE($U$15:$U$85))/STDEV($U$15:$U$85),"") | W24: =IF(ISNUMBER($V$24),IF($V$24>=1.5,"CHEAP",IF($V$24>=0.5,"slightly cheap",IF($V$24<=-1.5,"RICH",IF($V$24<=-0.5,"slightly rich","fair")))),"") | X24: =SUMPRODUCT(--ISNUMBER((D24,G24,H24,I24,J24,K24))) | Y24: =IF(X24>=5,"HIGH",IF(X24>=3,"MED","LOW")) | Z24: =IF(AND(ISNUMBER(S24),X24>=$S$11),S24,"") | AA24: =IF(AND(ISNUMBER(R24),X24>=$S$11),R24,"")
B25: =Tickers!B17 | C25: =Tickers!C17 | D25: =Tickers!E17 | E25: =IFERROR(Tickers!G17,"") | F25: =IFERROR(Tickers!I17,"") | G25: =IFERROR(IF(ISNUMBER(Tickers!K17),Tickers!K17,IF(ISNUMBER(Haver!E17),Haver!E17,IF(ISNUMBER(Tickers!T17),Tickers!T17,""))),"") | H25: =IFERROR(IF(ISNUMBER(Tickers!M17),Tickers!M17,IF(ISNUMBER(Haver!G17),Haver!G17,IF(ISNUMBER(Tickers!U17),Tickers!U17,""))),"") | I25: =IFERROR(IF(ISNUMBER(Tickers!O17),Tickers!O17,IF(ISNUMBER(Haver!I17),Haver!I17,IF(ISNUMBER(Tickers!V17),Tickers!V17,""))),"") | J25: =IFERROR(IF(ISNUMBER(Tickers!Q17),Tickers!Q17,IF(ISNUMBER(Haver!K17),Haver!K17,IF(ISNUMBER(Tickers!W17),Tickers!W17,""))),"") | K25: =IFERROR(IF(ISNUMBER(Tickers!S17),Tickers!S17,IF(ISNUMBER(Haver!M17),Haver!M17,IF(ISNUMBER(Tickers!X17),Tickers!X17,""))),"") | L25: =IFERROR(($D$25-AVERAGE($D$15:$D$85))/STDEV($D$15:$D$85),"") | M25: =IFERROR(($I$25-AVERAGE($I$15:$I$85))/STDEV($I$15:$I$85),"") | N25: =IFERROR(-($J$25-AVERAGE($J$15:$J$85))/STDEV($J$15:$J$85),"") | O25: =IFERROR(-($K$25-AVERAGE($K$15:$K$85))/STDEV($K$15:$K$85),"") | P25: =IFERROR(-($G$25-AVERAGE($G$15:$G$85))/STDEV($G$15:$G$85),"") | Q25: =IFERROR(($H$25-AVERAGE($H$15:$H$85))/STDEV($H$15:$H$85),"") | R25: =IFERROR((IF(ISNUMBER(L25),$D$7*L25,0)+IF(ISNUMBER(M25),$D$8*M25,0)+IF(ISNUMBER(N25),$D$9*N25,0)+IF(ISNUMBER(O25),$D$10*O25,0)+IF(ISNUMBER(P25),$D$11*P25,0)+IF(ISNUMBER(Q25),$D$12*Q25,0))/(IF(ISNUMBER(L25),$D$7,0)+IF(ISNUMBER(M25),$D$8,0)+IF(ISNUMBER(N25),$D$9,0)+IF(ISNUMBER(O25),$D$10,0)+IF(ISNUMBER(P25),$D$11,0)+IF(ISNUMBER(Q25),$D$12,0)),"") | S25: =IFERROR(LN($E$25),"") | T25: =IFERROR($N$7+$N$8*$R$25,"") | U25: =IFERROR($S$25-$T$25,"") | V25: =IFERROR(($U$25-AVERAGE($U$15:$U$85))/STDEV($U$15:$U$85),"") | W25: =IF(ISNUMBER($V$25),IF($V$25>=1.5,"CHEAP",IF($V$25>=0.5,"slightly cheap",IF($V$25<=-1.5,"RICH",IF($V$25<=-0.5,"slightly rich","fair")))),"") | X25: =SUMPRODUCT(--ISNUMBER((D25,G25,H25,I25,J25,K25))) | Y25: =IF(X25>=5,"HIGH",IF(X25>=3,"MED","LOW")) | Z25: =IF(AND(ISNUMBER(S25),X25>=$S$11),S25,"") | AA25: =IF(AND(ISNUMBER(R25),X25>=$S$11),R25,"")
B26: =Tickers!B18 | C26: =Tickers!C18 | D26: =Tickers!E18 | E26: =IFERROR(Tickers!G18,"") | F26: =IFERROR(Tickers!I18,"") | G26: =IFERROR(IF(ISNUMBER(Tickers!K18),Tickers!K18,IF(ISNUMBER(Haver!E18),Haver!E18,IF(ISNUMBER(Tickers!T18),Tickers!T18,""))),"") | H26: =IFERROR(IF(ISNUMBER(Tickers!M18),Tickers!M18,IF(ISNUMBER(Haver!G18),Haver!G18,IF(ISNUMBER(Tickers!U18),Tickers!U18,""))),"") | I26: =IFERROR(IF(ISNUMBER(Tickers!O18),Tickers!O18,IF(ISNUMBER(Haver!I18),Haver!I18,IF(ISNUMBER(Tickers!V18),Tickers!V18,""))),"") | J26: =IFERROR(IF(ISNUMBER(Tickers!Q18),Tickers!Q18,IF(ISNUMBER(Haver!K18),Haver!K18,IF(ISNUMBER(Tickers!W18),Tickers!W18,""))),"") | K26: =IFERROR(IF(ISNUMBER(Tickers!S18),Tickers!S18,IF(ISNUMBER(Haver!M18),Haver!M18,IF(ISNUMBER(Tickers!X18),Tickers!X18,""))),"") | L26: =IFERROR(($D$26-AVERAGE($D$15:$D$85))/STDEV($D$15:$D$85),"") | M26: =IFERROR(($I$26-AVERAGE($I$15:$I$85))/STDEV($I$15:$I$85),"") | N26: =IFERROR(-($J$26-AVERAGE($J$15:$J$85))/STDEV($J$15:$J$85),"") | O26: =IFERROR(-($K$26-AVERAGE($K$15:$K$85))/STDEV($K$15:$K$85),"") | P26: =IFERROR(-($G$26-AVERAGE($G$15:$G$85))/STDEV($G$15:$G$85),"") | Q26: =IFERROR(($H$26-AVERAGE($H$15:$H$85))/STDEV($H$15:$H$85),"") | R26: =IFERROR((IF(ISNUMBER(L26),$D$7*L26,0)+IF(ISNUMBER(M26),$D$8*M26,0)+IF(ISNUMBER(N26),$D$9*N26,0)+IF(ISNUMBER(O26),$D$10*O26,0)+IF(ISNUMBER(P26),$D$11*P26,0)+IF(ISNUMBER(Q26),$D$12*Q26,0))/(IF(ISNUMBER(L26),$D$7,0)+IF(ISNUMBER(M26),$D$8,0)+IF(ISNUMBER(N26),$D$9,0)+IF(ISNUMBER(O26),$D$10,0)+IF(ISNUMBER(P26),$D$11,0)+IF(ISNUMBER(Q26),$D$12,0)),"") | S26: =IFERROR(LN($E$26),"") | T26: =IFERROR($N$7+$N$8*$R$26,"") | U26: =IFERROR($S$26-$T$26,"") | V26: =IFERROR(($U$26-AVERAGE($U$15:$U$85))/STDEV($U$15:$U$85),"") | W26: =IF(ISNUMBER($V$26),IF($V$26>=1.5,"CHEAP",IF($V$26>=0.5,"slightly cheap",IF($V$26<=-1.5,"RICH",IF($V$26<=-0.5,"slightly rich","fair")))),"") | X26: =SUMPRODUCT(--ISNUMBER((D26,G26,H26,I26,J26,K26))) | Y26: =IF(X26>=5,"HIGH",IF(X26>=3,"MED","LOW")) | Z26: =IF(AND(ISNUMBER(S26),X26>=$S$11),S26,"") | AA26: =IF(AND(ISNUMBER(R26),X26>=$S$11),R26,"")
B27: =Tickers!B19 | C27: =Tickers!C19 | D27: =Tickers!E19 | E27: =IFERROR(Tickers!G19,"") | F27: =IFERROR(Tickers!I19,"") | G27: =IFERROR(IF(ISNUMBER(Tickers!K19),Tickers!K19,IF(ISNUMBER(Haver!E19),Haver!E19,IF(ISNUMBER(Tickers!T19),Tickers!T19,""))),"") | H27: =IFERROR(IF(ISNUMBER(Tickers!M19),Tickers!M19,IF(ISNUMBER(Haver!G19),Haver!G19,IF(ISNUMBER(Tickers!U19),Tickers!U19,""))),"") | I27: =IFERROR(IF(ISNUMBER(Tickers!O19),Tickers!O19,IF(ISNUMBER(Haver!I19),Haver!I19,IF(ISNUMBER(Tickers!V19),Tickers!V19,""))),"") | J27: =IFERROR(IF(ISNUMBER(Tickers!Q19),Tickers!Q19,IF(ISNUMBER(Haver!K19),Haver!K19,IF(ISNUMBER(Tickers!W19),Tickers!W19,""))),"") | K27: =IFERROR(IF(ISNUMBER(Tickers!S19),Tickers!S19,IF(ISNUMBER(Haver!M19),Haver!M19,IF(ISNUMBER(Tickers!X19),Tickers!X19,""))),"") | L27: =IFERROR(($D$27-AVERAGE($D$15:$D$85))/STDEV($D$15:$D$85),"") | M27: =IFERROR(($I$27-AVERAGE($I$15:$I$85))/STDEV($I$15:$I$85),"") | N27: =IFERROR(-($J$27-AVERAGE($J$15:$J$85))/STDEV($J$15:$J$85),"") | O27: =IFERROR(-($K$27-AVERAGE($K$15:$K$85))/STDEV($K$15:$K$85),"") | P27: =IFERROR(-($G$27-AVERAGE($G$15:$G$85))/STDEV($G$15:$G$85),"") | Q27: =IFERROR(($H$27-AVERAGE($H$15:$H$85))/STDEV($H$15:$H$85),"") | R27: =IFERROR((IF(ISNUMBER(L27),$D$7*L27,0)+IF(ISNUMBER(M27),$D$8*M27,0)+IF(ISNUMBER(N27),$D$9*N27,0)+IF(ISNUMBER(O27),$D$10*O27,0)+IF(ISNUMBER(P27),$D$11*P27,0)+IF(ISNUMBER(Q27),$D$12*Q27,0))/(IF(ISNUMBER(L27),$D$7,0)+IF(ISNUMBER(M27),$D$8,0)+IF(ISNUMBER(N27),$D$9,0)+IF(ISNUMBER(O27),$D$10,0)+IF(ISNUMBER(P27),$D$11,0)+IF(ISNUMBER(Q27),$D$12,0)),"") | S27: =IFERROR(LN($E$27),"") | T27: =IFERROR($N$7+$N$8*$R$27,"") | U27: =IFERROR($S$27-$T$27,"") | V27: =IFERROR(($U$27-AVERAGE($U$15:$U$85))/STDEV($U$15:$U$85),"") | W27: =IF(ISNUMBER($V$27),IF($V$27>=1.5,"CHEAP",IF($V$27>=0.5,"slightly cheap",IF($V$27<=-1.5,"RICH",IF($V$27<=-0.5,"slightly rich","fair")))),"") | X27: =SUMPRODUCT(--ISNUMBER((D27,G27,H27,I27,J27,K27))) | Y27: =IF(X27>=5,"HIGH",IF(X27>=3,"MED","LOW")) | Z27: =IF(AND(ISNUMBER(S27),X27>=$S$11),S27,"") | AA27: =IF(AND(ISNUMBER(R27),X27>=$S$11),R27,"")
B28: =Tickers!B20 | C28: =Tickers!C20 | D28: =Tickers!E20 | E28: =IFERROR(Tickers!G20,"") | F28: =IFERROR(Tickers!I20,"") | G28: =IFERROR(IF(ISNUMBER(Tickers!K20),Tickers!K20,IF(ISNUMBER(Haver!E20),Haver!E20,IF(ISNUMBER(Tickers!T20),Tickers!T20,""))),"") | H28: =IFERROR(IF(ISNUMBER(Tickers!M20),Tickers!M20,IF(ISNUMBER(Haver!G20),Haver!G20,IF(ISNUMBER(Tickers!U20),Tickers!U20,""))),"") | I28: =IFERROR(IF(ISNUMBER(Tickers!O20),Tickers!O20,IF(ISNUMBER(Haver!I20),Haver!I20,IF(ISNUMBER(Tickers!V20),Tickers!V20,""))),"") | J28: =IFERROR(IF(ISNUMBER(Tickers!Q20),Tickers!Q20,IF(ISNUMBER(Haver!K20),Haver!K20,IF(ISNUMBER(Tickers!W20),Tickers!W20,""))),"") | K28: =IFERROR(IF(ISNUMBER(Tickers!S20),Tickers!S20,IF(ISNUMBER(Haver!M20),Haver!M20,IF(ISNUMBER(Tickers!X20),Tickers!X20,""))),"") | L28: =IFERROR(($D$28-AVERAGE($D$15:$D$85))/STDEV($D$15:$D$85),"") | M28: =IFERROR(($I$28-AVERAGE($I$15:$I$85))/STDEV($I$15:$I$85),"") | N28: =IFERROR(-($J$28-AVERAGE($J$15:$J$85))/STDEV($J$15:$J$85),"") | O28: =IFERROR(-($K$28-AVERAGE($K$15:$K$85))/STDEV($K$15:$K$85),"") | P28: =IFERROR(-($G$28-AVERAGE($G$15:$G$85))/STDEV($G$15:$G$85),"") | Q28: =IFERROR(($H$28-AVERAGE($H$15:$H$85))/STDEV($H$15:$H$85),"") | R28: =IFERROR((IF(ISNUMBER(L28),$D$7*L28,0)+IF(ISNUMBER(M28),$D$8*M28,0)+IF(ISNUMBER(N28),$D$9*N28,0)+IF(ISNUMBER(O28),$D$10*O28,0)+IF(ISNUMBER(P28),$D$11*P28,0)+IF(ISNUMBER(Q28),$D$12*Q28,0))/(IF(ISNUMBER(L28),$D$7,0)+IF(ISNUMBER(M28),$D$8,0)+IF(ISNUMBER(N28),$D$9,0)+IF(ISNUMBER(O28),$D$10,0)+IF(ISNUMBER(P28),$D$11,0)+IF(ISNUMBER(Q28),$D$12,0)),"") | S28: =IFERROR(LN($E$28),"") | T28: =IFERROR($N$7+$N$8*$R$28,"") | U28: =IFERROR($S$28-$T$28,"") | V28: =IFERROR(($U$28-AVERAGE($U$15:$U$85))/STDEV($U$15:$U$85),"") | W28: =IF(ISNUMBER($V$28),IF($V$28>=1.5,"CHEAP",IF($V$28>=0.5,"slightly cheap",IF($V$28<=-1.5,"RICH",IF($V$28<=-0.5,"slightly rich","fair")))),"") | X28: =SUMPRODUCT(--ISNUMBER((D28,G28,H28,I28,J28,K28))) | Y28: =IF(X28>=5,"HIGH",IF(X28>=3,"MED","LOW")) | Z28: =IF(AND(ISNUMBER(S28),X28>=$S$11),S28,"") | AA28: =IF(AND(ISNUMBER(R28),X28>=$S$11),R28,"")
B29: =Tickers!B21 | C29: =Tickers!C21 | D29: =Tickers!E21 | E29: =IFERROR(Tickers!G21,"") | F29: =IFERROR(Tickers!I21,"") | G29: =IFERROR(IF(ISNUMBER(Tickers!K21),Tickers!K21,IF(ISNUMBER(Haver!E21),Haver!E21,IF(ISNUMBER(Tickers!T21),Tickers!T21,""))),"") | H29: =IFERROR(IF(ISNUMBER(Tickers!M21),Tickers!M21,IF(ISNUMBER(Haver!G21),Haver!G21,IF(ISNUMBER(Tickers!U21),Tickers!U21,""))),"") | I29: =IFERROR(IF(ISNUMBER(Tickers!O21),Tickers!O21,IF(ISNUMBER(Haver!I21),Haver!I21,IF(ISNUMBER(Tickers!V21),Tickers!V21,""))),"") | J29: =IFERROR(IF(ISNUMBER(Tickers!Q21),Tickers!Q21,IF(ISNUMBER(Haver!K21),Haver!K21,IF(ISNUMBER(Tickers!W21),Tickers!W21,""))),"") | K29: =IFERROR(IF(ISNUMBER(Tickers!S21),Tickers!S21,IF(ISNUMBER(Haver!M21),Haver!M21,IF(ISNUMBER(Tickers!X21),Tickers!X21,""))),"") | L29: =IFERROR(($D$29-AVERAGE($D$15:$D$85))/STDEV($D$15:$D$85),"") | M29: =IFERROR(($I$29-AVERAGE($I$15:$I$85))/STDEV($I$15:$I$85),"") | N29: =IFERROR(-($J$29-AVERAGE($J$15:$J$85))/STDEV($J$15:$J$85),"") | O29: =IFERROR(-($K$29-AVERAGE($K$15:$K$85))/STDEV($K$15:$K$85),"") | P29: =IFERROR(-($G$29-AVERAGE($G$15:$G$85))/STDEV($G$15:$G$85),"") | Q29: =IFERROR(($H$29-AVERAGE($H$15:$H$85))/STDEV($H$15:$H$85),"") | R29: =IFERROR((IF(ISNUMBER(L29),$D$7*L29,0)+IF(ISNUMBER(M29),$D$8*M29,0)+IF(ISNUMBER(N29),$D$9*N29,0)+IF(ISNUMBER(O29),$D$10*O29,0)+IF(ISNUMBER(P29),$D$11*P29,0)+IF(ISNUMBER(Q29),$D$12*Q29,0))/(IF(ISNUMBER(L29),$D$7,0)+IF(ISNUMBER(M29),$D$8,0)+IF(ISNUMBER(N29),$D$9,0)+IF(ISNUMBER(O29),$D$10,0)+IF(ISNUMBER(P29),$D$11,0)+IF(ISNUMBER(Q29),$D$12,0)),"") | S29: =IFERROR(LN($E$29),"") | T29: =IFERROR($N$7+$N$8*$R$29,"") | U29: =IFERROR($S$29-$T$29,"") | V29: =IFERROR(($U$29-AVERAGE($U$15:$U$85))/STDEV($U$15:$U$85),"") | W29: =IF(ISNUMBER($V$29),IF($V$29>=1.5,"CHEAP",IF($V$29>=0.5,"slightly cheap",IF($V$29<=-1.5,"RICH",IF($V$29<=-0.5,"slightly rich","fair")))),"") | X29: =SUMPRODUCT(--ISNUMBER((D29,G29,H29,I29,J29,K29))) | Y29: =IF(X29>=5,"HIGH",IF(X29>=3,"MED","LOW")) | Z29: =IF(AND(ISNUMBER(S29),X29>=$S$11),S29,"") | AA29: =IF(AND(ISNUMBER(R29),X29>=$S$11),R29,"")
B30: =Tickers!B22 | C30: =Tickers!C22 | D30: =Tickers!E22 | E30: =IFERROR(Tickers!G22,"") | F30: =IFERROR(Tickers!I22,"") | G30: =IFERROR(IF(ISNUMBER(Tickers!K22),Tickers!K22,IF(ISNUMBER(Haver!E22),Haver!E22,IF(ISNUMBER(Tickers!T22),Tickers!T22,""))),"") | H30: =IFERROR(IF(ISNUMBER(Tickers!M22),Tickers!M22,IF(ISNUMBER(Haver!G22),Haver!G22,IF(ISNUMBER(Tickers!U22),Tickers!U22,""))),"") | I30: =IFERROR(IF(ISNUMBER(Tickers!O22),Tickers!O22,IF(ISNUMBER(Haver!I22),Haver!I22,IF(ISNUMBER(Tickers!V22),Tickers!V22,""))),"") | J30: =IFERROR(IF(ISNUMBER(Tickers!Q22),Tickers!Q22,IF(ISNUMBER(Haver!K22),Haver!K22,IF(ISNUMBER(Tickers!W22),Tickers!W22,""))),"") | K30: =IFERROR(IF(ISNUMBER(Tickers!S22),Tickers!S22,IF(ISNUMBER(Haver!M22),Haver!M22,IF(ISNUMBER(Tickers!X22),Tickers!X22,""))),"") | L30: =IFERROR(($D$30-AVERAGE($D$15:$D$85))/STDEV($D$15:$D$85),"") | M30: =IFERROR(($I$30-AVERAGE($I$15:$I$85))/STDEV($I$15:$I$85),"") | N30: =IFERROR(-($J$30-AVERAGE($J$15:$J$85))/STDEV($J$15:$J$85),"") | O30: =IFERROR(-($K$30-AVERAGE($K$15:$K$85))/STDEV($K$15:$K$85),"") | P30: =IFERROR(-($G$30-AVERAGE($G$15:$G$85))/STDEV($G$15:$G$85),"") | Q30: =IFERROR(($H$30-AVERAGE($H$15:$H$85))/STDEV($H$15:$H$85),"") | R30: =IFERROR((IF(ISNUMBER(L30),$D$7*L30,0)+IF(ISNUMBER(M30),$D$8*M30,0)+IF(ISNUMBER(N30),$D$9*N30,0)+IF(ISNUMBER(O30),$D$10*O30,0)+IF(ISNUMBER(P30),$D$11*P30,0)+IF(ISNUMBER(Q30),$D$12*Q30,0))/(IF(ISNUMBER(L30),$D$7,0)+IF(ISNUMBER(M30),$D$8,0)+IF(ISNUMBER(N30),$D$9,0)+IF(ISNUMBER(O30),$D$10,0)+IF(ISNUMBER(P30),$D$11,0)+IF(ISNUMBER(Q30),$D$12,0)),"") | S30: =IFERROR(LN($E$30),"") | T30: =IFERROR($N$7+$N$8*$R$30,"") | U30: =IFERROR($S$30-$T$30,"") | V30: =IFERROR(($U$30-AVERAGE($U$15:$U$85))/STDEV($U$15:$U$85),"") | W30: =IF(ISNUMBER($V$30),IF($V$30>=1.5,"CHEAP",IF($V$30>=0.5,"slightly cheap",IF($V$30<=-1.5,"RICH",IF($V$30<=-0.5,"slightly rich","fair")))),"") | X30: =SUMPRODUCT(--ISNUMBER((D30,G30,H30,I30,J30,K30))) | Y30: =IF(X30>=5,"HIGH",IF(X30>=3,"MED","LOW")) | Z30: =IF(AND(ISNUMBER(S30),X30>=$S$11),S30,"") | AA30: =IF(AND(ISNUMBER(R30),X30>=$S$11),R30,"")
B31: =Tickers!B23 | C31: =Tickers!C23 | D31: =Tickers!E23 | E31: =IFERROR(Tickers!G23,"") | F31: =IFERROR(Tickers!I23,"") | G31: =IFERROR(IF(ISNUMBER(Tickers!K23),Tickers!K23,IF(ISNUMBER(Haver!E23),Haver!E23,IF(ISNUMBER(Tickers!T23),Tickers!T23,""))),"") | H31: =IFERROR(IF(ISNUMBER(Tickers!M23),Tickers!M23,IF(ISNUMBER(Haver!G23),Haver!G23,IF(ISNUMBER(Tickers!U23),Tickers!U23,""))),"") | I31: =IFERROR(IF(ISNUMBER(Tickers!O23),Tickers!O23,IF(ISNUMBER(Haver!I23),Haver!I23,IF(ISNUMBER(Tickers!V23),Tickers!V23,""))),"") | J31: =IFERROR(IF(ISNUMBER(Tickers!Q23),Tickers!Q23,IF(ISNUMBER(Haver!K23),Haver!K23,IF(ISNUMBER(Tickers!W23),Tickers!W23,""))),"") | K31: =IFERROR(IF(ISNUMBER(Tickers!S23),Tickers!S23,IF(ISNUMBER(Haver!M23),Haver!M23,IF(ISNUMBER(Tickers!X23),Tickers!X23,""))),"") | L31: =IFERROR(($D$31-AVERAGE($D$15:$D$85))/STDEV($D$15:$D$85),"") | M31: =IFERROR(($I$31-AVERAGE($I$15:$I$85))/STDEV($I$15:$I$85),"") | N31: =IFERROR(-($J$31-AVERAGE($J$15:$J$85))/STDEV($J$15:$J$85),"") | O31: =IFERROR(-($K$31-AVERAGE($K$15:$K$85))/STDEV($K$15:$K$85),"") | P31: =IFERROR(-($G$31-AVERAGE($G$15:$G$85))/STDEV($G$15:$G$85),"") | Q31: =IFERROR(($H$31-AVERAGE($H$15:$H$85))/STDEV($H$15:$H$85),"") | R31: =IFERROR((IF(ISNUMBER(L31),$D$7*L31,0)+IF(ISNUMBER(M31),$D$8*M31,0)+IF(ISNUMBER(N31),$D$9*N31,0)+IF(ISNUMBER(O31),$D$10*O31,0)+IF(ISNUMBER(P31),$D$11*P31,0)+IF(ISNUMBER(Q31),$D$12*Q31,0))/(IF(ISNUMBER(L31),$D$7,0)+IF(ISNUMBER(M31),$D$8,0)+IF(ISNUMBER(N31),$D$9,0)+IF(ISNUMBER(O31),$D$10,0)+IF(ISNUMBER(P31),$D$11,0)+IF(ISNUMBER(Q31),$D$12,0)),"") | S31: =IFERROR(LN($E$31),"") | T31: =IFERROR($N$7+$N$8*$R$31,"") | U31: =IFERROR($S$31-$T$31,"") | V31: =IFERROR(($U$31-AVERAGE($U$15:$U$85))/STDEV($U$15:$U$85),"") | W31: =IF(ISNUMBER($V$31),IF($V$31>=1.5,"CHEAP",IF($V$31>=0.5,"slightly cheap",IF($V$31<=-1.5,"RICH",IF($V$31<=-0.5,"slightly rich","fair")))),"") | X31: =SUMPRODUCT(--ISNUMBER((D31,G31,H31,I31,J31,K31))) | Y31: =IF(X31>=5,"HIGH",IF(X31>=3,"MED","LOW")) | Z31: =IF(AND(ISNUMBER(S31),X31>=$S$11),S31,"") | AA31: =IF(AND(ISNUMBER(R31),X31>=$S$11),R31,"")
B32: =Tickers!B24 | C32: =Tickers!C24 | D32: =Tickers!E24 | E32: =IFERROR(Tickers!G24,"") | F32: =IFERROR(Tickers!I24,"") | G32: =IFERROR(IF(ISNUMBER(Tickers!K24),Tickers!K24,IF(ISNUMBER(Haver!E24),Haver!E24,IF(ISNUMBER(Tickers!T24),Tickers!T24,""))),"") | H32: =IFERROR(IF(ISNUMBER(Tickers!M24),Tickers!M24,IF(ISNUMBER(Haver!G24),Haver!G24,IF(ISNUMBER(Tickers!U24),Tickers!U24,""))),"") | I32: =IFERROR(IF(ISNUMBER(Tickers!O24),Tickers!O24,IF(ISNUMBER(Haver!I24),Haver!I24,IF(ISNUMBER(Tickers!V24),Tickers!V24,""))),"") | J32: =IFERROR(IF(ISNUMBER(Tickers!Q24),Tickers!Q24,IF(ISNUMBER(Haver!K24),Haver!K24,IF(ISNUMBER(Tickers!W24),Tickers!W24,""))),"") | K32: =IFERROR(IF(ISNUMBER(Tickers!S24),Tickers!S24,IF(ISNUMBER(Haver!M24),Haver!M24,IF(ISNUMBER(Tickers!X24),Tickers!X24,""))),"") | L32: =IFERROR(($D$32-AVERAGE($D$15:$D$85))/STDEV($D$15:$D$85),"") | M32: =IFERROR(($I$32-AVERAGE($I$15:$I$85))/STDEV($I$15:$I$85),"") | N32: =IFERROR(-($J$32-AVERAGE($J$15:$J$85))/STDEV($J$15:$J$85),"") | O32: =IFERROR(-($K$32-AVERAGE($K$15:$K$85))/STDEV($K$15:$K$85),"") | P32: =IFERROR(-($G$32-AVERAGE($G$15:$G$85))/STDEV($G$15:$G$85),"") | Q32: =IFERROR(($H$32-AVERAGE($H$15:$H$85))/STDEV($H$15:$H$85),"") | R32: =IFERROR((IF(ISNUMBER(L32),$D$7*L32,0)+IF(ISNUMBER(M32),$D$8*M32,0)+IF(ISNUMBER(N32),$D$9*N32,0)+IF(ISNUMBER(O32),$D$10*O32,0)+IF(ISNUMBER(P32),$D$11*P32,0)+IF(ISNUMBER(Q32),$D$12*Q32,0))/(IF(ISNUMBER(L32),$D$7,0)+IF(ISNUMBER(M32),$D$8,0)+IF(ISNUMBER(N32),$D$9,0)+IF(ISNUMBER(O32),$D$10,0)+IF(ISNUMBER(P32),$D$11,0)+IF(ISNUMBER(Q32),$D$12,0)),"") | S32: =IFERROR(LN($E$32),"") | T32: =IFERROR($N$7+$N$8*$R$32,"") | U32: =IFERROR($S$32-$T$32,"") | V32: =IFERROR(($U$32-AVERAGE($U$15:$U$85))/STDEV($U$15:$U$85),"") | W32: =IF(ISNUMBER($V$32),IF($V$32>=1.5,"CHEAP",IF($V$32>=0.5,"slightly cheap",IF($V$32<=-1.5,"RICH",IF($V$32<=-0.5,"slightly rich","fair")))),"") | X32: =SUMPRODUCT(--ISNUMBER((D32,G32,H32,I32,J32,K32))) | Y32: =IF(X32>=5,"HIGH",IF(X32>=3,"MED","LOW")) | Z32: =IF(AND(ISNUMBER(S32),X32>=$S$11),S32,"") | AA32: =IF(AND(ISNUMBER(R32),X32>=$S$11),R32,"")
B33: =Tickers!B25 | C33: =Tickers!C25 | D33: =Tickers!E25 | E33: =IFERROR(Tickers!G25,"") | F33: =IFERROR(Tickers!I25,"") | G33: =IFERROR(IF(ISNUMBER(Tickers!K25),Tickers!K25,IF(ISNUMBER(Haver!E25),Haver!E25,IF(ISNUMBER(Tickers!T25),Tickers!T25,""))),"") | H33: =IFERROR(IF(ISNUMBER(Tickers!M25),Tickers!M25,IF(ISNUMBER(Haver!G25),Haver!G25,IF(ISNUMBER(Tickers!U25),Tickers!U25,""))),"") | I33: =IFERROR(IF(ISNUMBER(Tickers!O25),Tickers!O25,IF(ISNUMBER(Haver!I25),Haver!I25,IF(ISNUMBER(Tickers!V25),Tickers!V25,""))),"") | J33: =IFERROR(IF(ISNUMBER(Tickers!Q25),Tickers!Q25,IF(ISNUMBER(Haver!K25),Haver!K25,IF(ISNUMBER(Tickers!W25),Tickers!W25,""))),"") | K33: =IFERROR(IF(ISNUMBER(Tickers!S25),Tickers!S25,IF(ISNUMBER(Haver!M25),Haver!M25,IF(ISNUMBER(Tickers!X25),Tickers!X25,""))),"") | L33: =IFERROR(($D$33-AVERAGE($D$15:$D$85))/STDEV($D$15:$D$85),"") | M33: =IFERROR(($I$33-AVERAGE($I$15:$I$85))/STDEV($I$15:$I$85),"") | N33: =IFERROR(-($J$33-AVERAGE($J$15:$J$85))/STDEV($J$15:$J$85),"") | O33: =IFERROR(-($K$33-AVERAGE($K$15:$K$85))/STDEV($K$15:$K$85),"") | P33: =IFERROR(-($G$33-AVERAGE($G$15:$G$85))/STDEV($G$15:$G$85),"") | Q33: =IFERROR(($H$33-AVERAGE($H$15:$H$85))/STDEV($H$15:$H$85),"") | R33: =IFERROR((IF(ISNUMBER(L33),$D$7*L33,0)+IF(ISNUMBER(M33),$D$8*M33,0)+IF(ISNUMBER(N33),$D$9*N33,0)+IF(ISNUMBER(O33),$D$10*O33,0)+IF(ISNUMBER(P33),$D$11*P33,0)+IF(ISNUMBER(Q33),$D$12*Q33,0))/(IF(ISNUMBER(L33),$D$7,0)+IF(ISNUMBER(M33),$D$8,0)+IF(ISNUMBER(N33),$D$9,0)+IF(ISNUMBER(O33),$D$10,0)+IF(ISNUMBER(P33),$D$11,0)+IF(ISNUMBER(Q33),$D$12,0)),"") | S33: =IFERROR(LN($E$33),"") | T33: =IFERROR($N$7+$N$8*$R$33,"") | U33: =IFERROR($S$33-$T$33,"") | V33: =IFERROR(($U$33-AVERAGE($U$15:$U$85))/STDEV($U$15:$U$85),"") | W33: =IF(ISNUMBER($V$33),IF($V$33>=1.5,"CHEAP",IF($V$33>=0.5,"slightly cheap",IF($V$33<=-1.5,"RICH",IF($V$33<=-0.5,"slightly rich","fair")))),"") | X33: =SUMPRODUCT(--ISNUMBER((D33,G33,H33,I33,J33,K33))) | Y33: =IF(X33>=5,"HIGH",IF(X33>=3,"MED","LOW")) | Z33: =IF(AND(ISNUMBER(S33),X33>=$S$11),S33,"") | AA33: =IF(AND(ISNUMBER(R33),X33>=$S$11),R33,"")
B34: =Tickers!B26 | C34: =Tickers!C26 | D34: =Tickers!E26 | E34: =IFERROR(Tickers!G26,"") | F34: =IFERROR(Tickers!I26,"") | G34: =IFERROR(IF(ISNUMBER(Tickers!K26),Tickers!K26,IF(ISNUMBER(Haver!E26),Haver!E26,IF(ISNUMBER(Tickers!T26),Tickers!T26,""))),"") | H34: =IFERROR(IF(ISNUMBER(Tickers!M26),Tickers!M26,IF(ISNUMBER(Haver!G26),Haver!G26,IF(ISNUMBER(Tickers!U26),Tickers!U26,""))),"") | I34: =IFERROR(IF(ISNUMBER(Tickers!O26),Tickers!O26,IF(ISNUMBER(Haver!I26),Haver!I26,IF(ISNUMBER(Tickers!V26),Tickers!V26,""))),"") | J34: =IFERROR(IF(ISNUMBER(Tickers!Q26),Tickers!Q26,IF(ISNUMBER(Haver!K26),Haver!K26,IF(ISNUMBER(Tickers!W26),Tickers!W26,""))),"") | K34: =IFERROR(IF(ISNUMBER(Tickers!S26),Tickers!S26,IF(ISNUMBER(Haver!M26),Haver!M26,IF(ISNUMBER(Tickers!X26),Tickers!X26,""))),"") | L34: =IFERROR(($D$34-AVERAGE($D$15:$D$85))/STDEV($D$15:$D$85),"") | M34: =IFERROR(($I$34-AVERAGE($I$15:$I$85))/STDEV($I$15:$I$85),"") | N34: =IFERROR(-($J$34-AVERAGE($J$15:$J$85))/STDEV($J$15:$J$85),"") | O34: =IFERROR(-($K$34-AVERAGE($K$15:$K$85))/STDEV($K$15:$K$85),"") | P34: =IFERROR(-($G$34-AVERAGE($G$15:$G$85))/STDEV($G$15:$G$85),"") | Q34: =IFERROR(($H$34-AVERAGE($H$15:$H$85))/STDEV($H$15:$H$85),"") | R34: =IFERROR((IF(ISNUMBER(L34),$D$7*L34,0)+IF(ISNUMBER(M34),$D$8*M34,0)+IF(ISNUMBER(N34),$D$9*N34,0)+IF(ISNUMBER(O34),$D$10*O34,0)+IF(ISNUMBER(P34),$D$11*P34,0)+IF(ISNUMBER(Q34),$D$12*Q34,0))/(IF(ISNUMBER(L34),$D$7,0)+IF(ISNUMBER(M34),$D$8,0)+IF(ISNUMBER(N34),$D$9,0)+IF(ISNUMBER(O34),$D$10,0)+IF(ISNUMBER(P34),$D$11,0)+IF(ISNUMBER(Q34),$D$12,0)),"") | S34: =IFERROR(LN($E$34),"") | T34: =IFERROR($N$7+$N$8*$R$34,"") | U34: =IFERROR($S$34-$T$34,"") | V34: =IFERROR(($U$34-AVERAGE($U$15:$U$85))/STDEV($U$15:$U$85),"") | W34: =IF(ISNUMBER($V$34),IF($V$34>=1.5,"CHEAP",IF($V$34>=0.5,"slightly cheap",IF($V$34<=-1.5,"RICH",IF($V$34<=-0.5,"slightly rich","fair")))),"") | X34: =SUMPRODUCT(--ISNUMBER((D34,G34,H34,I34,J34,K34))) | Y34: =IF(X34>=5,"HIGH",IF(X34>=3,"MED","LOW")) | Z34: =IF(AND(ISNUMBER(S34),X34>=$S$11),S34,"") | AA34: =IF(AND(ISNUMBER(R34),X34>=$S$11),R34,"")
B35: =Tickers!B27 | C35: =Tickers!C27 | D35: =Tickers!E27 | E35: =IFERROR(Tickers!G27,"") | F35: =IFERROR(Tickers!I27,"") | G35: =IFERROR(IF(ISNUMBER(Tickers!K27),Tickers!K27,IF(ISNUMBER(Haver!E27),Haver!E27,IF(ISNUMBER(Tickers!T27),Tickers!T27,""))),"") | H35: =IFERROR(IF(ISNUMBER(Tickers!M27),Tickers!M27,IF(ISNUMBER(Haver!G27),Haver!G27,IF(ISNUMBER(Tickers!U27),Tickers!U27,""))),"") | I35: =IFERROR(IF(ISNUMBER(Tickers!O27),Tickers!O27,IF(ISNUMBER(Haver!I27),Haver!I27,IF(ISNUMBER(Tickers!V27),Tickers!V27,""))),"") | J35: =IFERROR(IF(ISNUMBER(Tickers!Q27),Tickers!Q27,IF(ISNUMBER(Haver!K27),Haver!K27,IF(ISNUMBER(Tickers!W27),Tickers!W27,""))),"") | K35: =IFERROR(IF(ISNUMBER(Tickers!S27),Tickers!S27,IF(ISNUMBER(Haver!M27),Haver!M27,IF(ISNUMBER(Tickers!X27),Tickers!X27,""))),"") | L35: =IFERROR(($D$35-AVERAGE($D$15:$D$85))/STDEV($D$15:$D$85),"") | M35: =IFERROR(($I$35-AVERAGE($I$15:$I$85))/STDEV($I$15:$I$85),"") | N35: =IFERROR(-($J$35-AVERAGE($J$15:$J$85))/STDEV($J$15:$J$85),"") | O35: =IFERROR(-($K$35-AVERAGE($K$15:$K$85))/STDEV($K$15:$K$85),"") | P35: =IFERROR(-($G$35-AVERAGE($G$15:$G$85))/STDEV($G$15:$G$85),"") | Q35: =IFERROR(($H$35-AVERAGE($H$15:$H$85))/STDEV($H$15:$H$85),"") | R35: =IFERROR((IF(ISNUMBER(L35),$D$7*L35,0)+IF(ISNUMBER(M35),$D$8*M35,0)+IF(ISNUMBER(N35),$D$9*N35,0)+IF(ISNUMBER(O35),$D$10*O35,0)+IF(ISNUMBER(P35),$D$11*P35,0)+IF(ISNUMBER(Q35),$D$12*Q35,0))/(IF(ISNUMBER(L35),$D$7,0)+IF(ISNUMBER(M35),$D$8,0)+IF(ISNUMBER(N35),$D$9,0)+IF(ISNUMBER(O35),$D$10,0)+IF(ISNUMBER(P35),$D$11,0)+IF(ISNUMBER(Q35),$D$12,0)),"") | S35: =IFERROR(LN($E$35),"") | T35: =IFERROR($N$7+$N$8*$R$35,"") | U35: =IFERROR($S$35-$T$35,"") | V35: =IFERROR(($U$35-AVERAGE($U$15:$U$85))/STDEV($U$15:$U$85),"") | W35: =IF(ISNUMBER($V$35),IF($V$35>=1.5,"CHEAP",IF($V$35>=0.5,"slightly cheap",IF($V$35<=-1.5,"RICH",IF($V$35<=-0.5,"slightly rich","fair")))),"") | X35: =SUMPRODUCT(--ISNUMBER((D35,G35,H35,I35,J35,K35))) | Y35: =IF(X35>=5,"HIGH",IF(X35>=3,"MED","LOW")) | Z35: =IF(AND(ISNUMBER(S35),X35>=$S$11),S35,"") | AA35: =IF(AND(ISNUMBER(R35),X35>=$S$11),R35,"")
B36: =Tickers!B28 | C36: =Tickers!C28 | D36: =Tickers!E28 | E36: =IFERROR(Tickers!G28,"") | F36: =IFERROR(Tickers!I28,"") | G36: =IFERROR(IF(ISNUMBER(Tickers!K28),Tickers!K28,IF(ISNUMBER(Haver!E28),Haver!E28,IF(ISNUMBER(Tickers!T28),Tickers!T28,""))),"") | H36: =IFERROR(IF(ISNUMBER(Tickers!M28),Tickers!M28,IF(ISNUMBER(Haver!G28),Haver!G28,IF(ISNUMBER(Tickers!U28),Tickers!U28,""))),"") | I36: =IFERROR(IF(ISNUMBER(Tickers!O28),Tickers!O28,IF(ISNUMBER(Haver!I28),Haver!I28,IF(ISNUMBER(Tickers!V28),Tickers!V28,""))),"") | J36: =IFERROR(IF(ISNUMBER(Tickers!Q28),Tickers!Q28,IF(ISNUMBER(Haver!K28),Haver!K28,IF(ISNUMBER(Tickers!W28),Tickers!W28,""))),"") | K36: =IFERROR(IF(ISNUMBER(Tickers!S28),Tickers!S28,IF(ISNUMBER(Haver!M28),Haver!M28,IF(ISNUMBER(Tickers!X28),Tickers!X28,""))),"") | L36: =IFERROR(($D$36-AVERAGE($D$15:$D$85))/STDEV($D$15:$D$85),"") | M36: =IFERROR(($I$36-AVERAGE($I$15:$I$85))/STDEV($I$15:$I$85),"") | N36: =IFERROR(-($J$36-AVERAGE($J$15:$J$85))/STDEV($J$15:$J$85),"") | O36: =IFERROR(-($K$36-AVERAGE($K$15:$K$85))/STDEV($K$15:$K$85),"") | P36: =IFERROR(-($G$36-AVERAGE($G$15:$G$85))/STDEV($G$15:$G$85),"") | Q36: =IFERROR(($H$36-AVERAGE($H$15:$H$85))/STDEV($H$15:$H$85),"") | R36: =IFERROR((IF(ISNUMBER(L36),$D$7*L36,0)+IF(ISNUMBER(M36),$D$8*M36,0)+IF(ISNUMBER(N36),$D$9*N36,0)+IF(ISNUMBER(O36),$D$10*O36,0)+IF(ISNUMBER(P36),$D$11*P36,0)+IF(ISNUMBER(Q36),$D$12*Q36,0))/(IF(ISNUMBER(L36),$D$7,0)+IF(ISNUMBER(M36),$D$8,0)+IF(ISNUMBER(N36),$D$9,0)+IF(ISNUMBER(O36),$D$10,0)+IF(ISNUMBER(P36),$D$11,0)+IF(ISNUMBER(Q36),$D$12,0)),"") | S36: =IFERROR(LN($E$36),"") | T36: =IFERROR($N$7+$N$8*$R$36,"") | U36: =IFERROR($S$36-$T$36,"") | V36: =IFERROR(($U$36-AVERAGE($U$15:$U$85))/STDEV($U$15:$U$85),"") | W36: =IF(ISNUMBER($V$36),IF($V$36>=1.5,"CHEAP",IF($V$36>=0.5,"slightly cheap",IF($V$36<=-1.5,"RICH",IF($V$36<=-0.5,"slightly rich","fair")))),"") | X36: =SUMPRODUCT(--ISNUMBER((D36,G36,H36,I36,J36,K36))) | Y36: =IF(X36>=5,"HIGH",IF(X36>=3,"MED","LOW")) | Z36: =IF(AND(ISNUMBER(S36),X36>=$S$11),S36,"") | AA36: =IF(AND(ISNUMBER(R36),X36>=$S$11),R36,"")
B37: =Tickers!B29 | C37: =Tickers!C29 | D37: =Tickers!E29 | E37: =IFERROR(Tickers!G29,"") | F37: =IFERROR(Tickers!I29,"") | G37: =IFERROR(IF(ISNUMBER(Tickers!K29),Tickers!K29,IF(ISNUMBER(Haver!E29),Haver!E29,IF(ISNUMBER(Tickers!T29),Tickers!T29,""))),"") | H37: =IFERROR(IF(ISNUMBER(Tickers!M29),Tickers!M29,IF(ISNUMBER(Haver!G29),Haver!G29,IF(ISNUMBER(Tickers!U29),Tickers!U29,""))),"") | I37: =IFERROR(IF(ISNUMBER(Tickers!O29),Tickers!O29,IF(ISNUMBER(Haver!I29),Haver!I29,IF(ISNUMBER(Tickers!V29),Tickers!V29,""))),"") | J37: =IFERROR(IF(ISNUMBER(Tickers!Q29),Tickers!Q29,IF(ISNUMBER(Haver!K29),Haver!K29,IF(ISNUMBER(Tickers!W29),Tickers!W29,""))),"") | K37: =IFERROR(IF(ISNUMBER(Tickers!S29),Tickers!S29,IF(ISNUMBER(Haver!M29),Haver!M29,IF(ISNUMBER(Tickers!X29),Tickers!X29,""))),"") | L37: =IFERROR(($D$37-AVERAGE($D$15:$D$85))/STDEV($D$15:$D$85),"") | M37: =IFERROR(($I$37-AVERAGE($I$15:$I$85))/STDEV($I$15:$I$85),"") | N37: =IFERROR(-($J$37-AVERAGE($J$15:$J$85))/STDEV($J$15:$J$85),"") | O37: =IFERROR(-($K$37-AVERAGE($K$15:$K$85))/STDEV($K$15:$K$85),"") | P37: =IFERROR(-($G$37-AVERAGE($G$15:$G$85))/STDEV($G$15:$G$85),"") | Q37: =IFERROR(($H$37-AVERAGE($H$15:$H$85))/STDEV($H$15:$H$85),"") | R37: =IFERROR((IF(ISNUMBER(L37),$D$7*L37,0)+IF(ISNUMBER(M37),$D$8*M37,0)+IF(ISNUMBER(N37),$D$9*N37,0)+IF(ISNUMBER(O37),$D$10*O37,0)+IF(ISNUMBER(P37),$D$11*P37,0)+IF(ISNUMBER(Q37),$D$12*Q37,0))/(IF(ISNUMBER(L37),$D$7,0)+IF(ISNUMBER(M37),$D$8,0)+IF(ISNUMBER(N37),$D$9,0)+IF(ISNUMBER(O37),$D$10,0)+IF(ISNUMBER(P37),$D$11,0)+IF(ISNUMBER(Q37),$D$12,0)),"") | S37: =IFERROR(LN($E$37),"") | T37: =IFERROR($N$7+$N$8*$R$37,"") | U37: =IFERROR($S$37-$T$37,"") | V37: =IFERROR(($U$37-AVERAGE($U$15:$U$85))/STDEV($U$15:$U$85),"") | W37: =IF(ISNUMBER($V$37),IF($V$37>=1.5,"CHEAP",IF($V$37>=0.5,"slightly cheap",IF($V$37<=-1.5,"RICH",IF($V$37<=-0.5,"slightly rich","fair")))),"") | X37: =SUMPRODUCT(--ISNUMBER((D37,G37,H37,I37,J37,K37))) | Y37: =IF(X37>=5,"HIGH",IF(X37>=3,"MED","LOW")) | Z37: =IF(AND(ISNUMBER(S37),X37>=$S$11),S37,"") | AA37: =IF(AND(ISNUMBER(R37),X37>=$S$11),R37,"")
B38: =Tickers!B30 | C38: =Tickers!C30 | D38: =Tickers!E30 | E38: =IFERROR(Tickers!G30,"") | F38: =IFERROR(Tickers!I30,"") | G38: =IFERROR(IF(ISNUMBER(Tickers!K30),Tickers!K30,IF(ISNUMBER(Haver!E30),Haver!E30,IF(ISNUMBER(Tickers!T30),Tickers!T30,""))),"") | H38: =IFERROR(IF(ISNUMBER(Tickers!M30),Tickers!M30,IF(ISNUMBER(Haver!G30),Haver!G30,IF(ISNUMBER(Tickers!U30),Tickers!U30,""))),"") | I38: =IFERROR(IF(ISNUMBER(Tickers!O30),Tickers!O30,IF(ISNUMBER(Haver!I30),Haver!I30,IF(ISNUMBER(Tickers!V30),Tickers!V30,""))),"") | J38: =IFERROR(IF(ISNUMBER(Tickers!Q30),Tickers!Q30,IF(ISNUMBER(Haver!K30),Haver!K30,IF(ISNUMBER(Tickers!W30),Tickers!W30,""))),"") | K38: =IFERROR(IF(ISNUMBER(Tickers!S30),Tickers!S30,IF(ISNUMBER(Haver!M30),Haver!M30,IF(ISNUMBER(Tickers!X30),Tickers!X30,""))),"") | L38: =IFERROR(($D$38-AVERAGE($D$15:$D$85))/STDEV($D$15:$D$85),"") | M38: =IFERROR(($I$38-AVERAGE($I$15:$I$85))/STDEV($I$15:$I$85),"") | N38: =IFERROR(-($J$38-AVERAGE($J$15:$J$85))/STDEV($J$15:$J$85),"") | O38: =IFERROR(-($K$38-AVERAGE($K$15:$K$85))/STDEV($K$15:$K$85),"") | P38: =IFERROR(-($G$38-AVERAGE($G$15:$G$85))/STDEV($G$15:$G$85),"") | Q38: =IFERROR(($H$38-AVERAGE($H$15:$H$85))/STDEV($H$15:$H$85),"") | R38: =IFERROR((IF(ISNUMBER(L38),$D$7*L38,0)+IF(ISNUMBER(M38),$D$8*M38,0)+IF(ISNUMBER(N38),$D$9*N38,0)+IF(ISNUMBER(O38),$D$10*O38,0)+IF(ISNUMBER(P38),$D$11*P38,0)+IF(ISNUMBER(Q38),$D$12*Q38,0))/(IF(ISNUMBER(L38),$D$7,0)+IF(ISNUMBER(M38),$D$8,0)+IF(ISNUMBER(N38),$D$9,0)+IF(ISNUMBER(O38),$D$10,0)+IF(ISNUMBER(P38),$D$11,0)+IF(ISNUMBER(Q38),$D$12,0)),"") | S38: =IFERROR(LN($E$38),"") | T38: =IFERROR($N$7+$N$8*$R$38,"") | U38: =IFERROR($S$38-$T$38,"") | V38: =IFERROR(($U$38-AVERAGE($U$15:$U$85))/STDEV($U$15:$U$85),"") | W38: =IF(ISNUMBER($V$38),IF($V$38>=1.5,"CHEAP",IF($V$38>=0.5,"slightly cheap",IF($V$38<=-1.5,"RICH",IF($V$38<=-0.5,"slightly rich","fair")))),"") | X38: =SUMPRODUCT(--ISNUMBER((D38,G38,H38,I38,J38,K38))) | Y38: =IF(X38>=5,"HIGH",IF(X38>=3,"MED","LOW")) | Z38: =IF(AND(ISNUMBER(S38),X38>=$S$11),S38,"") | AA38: =IF(AND(ISNUMBER(R38),X38>=$S$11),R38,"")
B39: =Tickers!B31 | C39: =Tickers!C31 | D39: =Tickers!E31 | E39: =IFERROR(Tickers!G31,"") | F39: =IFERROR(Tickers!I31,"") | G39: =IFERROR(IF(ISNUMBER(Tickers!K31),Tickers!K31,IF(ISNUMBER(Haver!E31),Haver!E31,IF(ISNUMBER(Tickers!T31),Tickers!T31,""))),"") | H39: =IFERROR(IF(ISNUMBER(Tickers!M31),Tickers!M31,IF(ISNUMBER(Haver!G31),Haver!G31,IF(ISNUMBER(Tickers!U31),Tickers!U31,""))),"") | I39: =IFERROR(IF(ISNUMBER(Tickers!O31),Tickers!O31,IF(ISNUMBER(Haver!I31),Haver!I31,IF(ISNUMBER(Tickers!V31),Tickers!V31,""))),"") | J39: =IFERROR(IF(ISNUMBER(Tickers!Q31),Tickers!Q31,IF(ISNUMBER(Haver!K31),Haver!K31,IF(ISNUMBER(Tickers!W31),Tickers!W31,""))),"") | K39: =IFERROR(IF(ISNUMBER(Tickers!S31),Tickers!S31,IF(ISNUMBER(Haver!M31),Haver!M31,IF(ISNUMBER(Tickers!X31),Tickers!X31,""))),"") | L39: =IFERROR(($D$39-AVERAGE($D$15:$D$85))/STDEV($D$15:$D$85),"") | M39: =IFERROR(($I$39-AVERAGE($I$15:$I$85))/STDEV($I$15:$I$85),"") | N39: =IFERROR(-($J$39-AVERAGE($J$15:$J$85))/STDEV($J$15:$J$85),"") | O39: =IFERROR(-($K$39-AVERAGE($K$15:$K$85))/STDEV($K$15:$K$85),"") | P39: =IFERROR(-($G$39-AVERAGE($G$15:$G$85))/STDEV($G$15:$G$85),"") | Q39: =IFERROR(($H$39-AVERAGE($H$15:$H$85))/STDEV($H$15:$H$85),"") | R39: =IFERROR((IF(ISNUMBER(L39),$D$7*L39,0)+IF(ISNUMBER(M39),$D$8*M39,0)+IF(ISNUMBER(N39),$D$9*N39,0)+IF(ISNUMBER(O39),$D$10*O39,0)+IF(ISNUMBER(P39),$D$11*P39,0)+IF(ISNUMBER(Q39),$D$12*Q39,0))/(IF(ISNUMBER(L39),$D$7,0)+IF(ISNUMBER(M39),$D$8,0)+IF(ISNUMBER(N39),$D$9,0)+IF(ISNUMBER(O39),$D$10,0)+IF(ISNUMBER(P39),$D$11,0)+IF(ISNUMBER(Q39),$D$12,0)),"") | S39: =IFERROR(LN($E$39),"") | T39: =IFERROR($N$7+$N$8*$R$39,"") | U39: =IFERROR($S$39-$T$39,"") | V39: =IFERROR(($U$39-AVERAGE($U$15:$U$85))/STDEV($U$15:$U$85),"") | W39: =IF(ISNUMBER($V$39),IF($V$39>=1.5,"CHEAP",IF($V$39>=0.5,"slightly cheap",IF($V$39<=-1.5,"RICH",IF($V$39<=-0.5,"slightly rich","fair")))),"") | X39: =SUMPRODUCT(--ISNUMBER((D39,G39,H39,I39,J39,K39))) | Y39: =IF(X39>=5,"HIGH",IF(X39>=3,"MED","LOW")) | Z39: =IF(AND(ISNUMBER(S39),X39>=$S$11),S39,"") | AA39: =IF(AND(ISNUMBER(R39),X39>=$S$11),R39,"")
B40: =Tickers!B32 | C40: =Tickers!C32 | D40: =Tickers!E32 | E40: =IFERROR(Tickers!G32,"") | F40: =IFERROR(Tickers!I32,"") | G40: =IFERROR(IF(ISNUMBER(Tickers!K32),Tickers!K32,IF(ISNUMBER(Haver!E32),Haver!E32,IF(ISNUMBER(Tickers!T32),Tickers!T32,""))),"") | H40: =IFERROR(IF(ISNUMBER(Tickers!M32),Tickers!M32,IF(ISNUMBER(Haver!G32),Haver!G32,IF(ISNUMBER(Tickers!U32),Tickers!U32,""))),"") | I40: =IFERROR(IF(ISNUMBER(Tickers!O32),Tickers!O32,IF(ISNUMBER(Haver!I32),Haver!I32,IF(ISNUMBER(Tickers!V32),Tickers!V32,""))),"") | J40: =IFERROR(IF(ISNUMBER(Tickers!Q32),Tickers!Q32,IF(ISNUMBER(Haver!K32),Haver!K32,IF(ISNUMBER(Tickers!W32),Tickers!W32,""))),"") | K40: =IFERROR(IF(ISNUMBER(Tickers!S32),Tickers!S32,IF(ISNUMBER(Haver!M32),Haver!M32,IF(ISNUMBER(Tickers!X32),Tickers!X32,""))),"") | L40: =IFERROR(($D$40-AVERAGE($D$15:$D$85))/STDEV($D$15:$D$85),"") | M40: =IFERROR(($I$40-AVERAGE($I$15:$I$85))/STDEV($I$15:$I$85),"") | N40: =IFERROR(-($J$40-AVERAGE($J$15:$J$85))/STDEV($J$15:$J$85),"") | O40: =IFERROR(-($K$40-AVERAGE($K$15:$K$85))/STDEV($K$15:$K$85),"") | P40: =IFERROR(-($G$40-AVERAGE($G$15:$G$85))/STDEV($G$15:$G$85),"") | Q40: =IFERROR(($H$40-AVERAGE($H$15:$H$85))/STDEV($H$15:$H$85),"") | R40: =IFERROR((IF(ISNUMBER(L40),$D$7*L40,0)+IF(ISNUMBER(M40),$D$8*M40,0)+IF(ISNUMBER(N40),$D$9*N40,0)+IF(ISNUMBER(O40),$D$10*O40,0)+IF(ISNUMBER(P40),$D$11*P40,0)+IF(ISNUMBER(Q40),$D$12*Q40,0))/(IF(ISNUMBER(L40),$D$7,0)+IF(ISNUMBER(M40),$D$8,0)+IF(ISNUMBER(N40),$D$9,0)+IF(ISNUMBER(O40),$D$10,0)+IF(ISNUMBER(P40),$D$11,0)+IF(ISNUMBER(Q40),$D$12,0)),"") | S40: =IFERROR(LN($E$40),"") | T40: =IFERROR($N$7+$N$8*$R$40,"") | U40: =IFERROR($S$40-$T$40,"") | V40: =IFERROR(($U$40-AVERAGE($U$15:$U$85))/STDEV($U$15:$U$85),"") | W40: =IF(ISNUMBER($V$40),IF($V$40>=1.5,"CHEAP",IF($V$40>=0.5,"slightly cheap",IF($V$40<=-1.5,"RICH",IF($V$40<=-0.5,"slightly rich","fair")))),"") | X40: =SUMPRODUCT(--ISNUMBER((D40,G40,H40,I40,J40,K40))) | Y40: =IF(X40>=5,"HIGH",IF(X40>=3,"MED","LOW")) | Z40: =IF(AND(ISNUMBER(S40),X40>=$S$11),S40,"") | AA40: =IF(AND(ISNUMBER(R40),X40>=$S$11),R40,"")
B41: =Tickers!B33 | C41: =Tickers!C33 | D41: =Tickers!E33 | E41: =IFERROR(Tickers!G33,"") | F41: =IFERROR(Tickers!I33,"") | G41: =IFERROR(IF(ISNUMBER(Tickers!K33),Tickers!K33,IF(ISNUMBER(Haver!E33),Haver!E33,IF(ISNUMBER(Tickers!T33),Tickers!T33,""))),"") | H41: =IFERROR(IF(ISNUMBER(Tickers!M33),Tickers!M33,IF(ISNUMBER(Haver!G33),Haver!G33,IF(ISNUMBER(Tickers!U33),Tickers!U33,""))),"") | I41: =IFERROR(IF(ISNUMBER(Tickers!O33),Tickers!O33,IF(ISNUMBER(Haver!I33),Haver!I33,IF(ISNUMBER(Tickers!V33),Tickers!V33,""))),"") | J41: =IFERROR(IF(ISNUMBER(Tickers!Q33),Tickers!Q33,IF(ISNUMBER(Haver!K33),Haver!K33,IF(ISNUMBER(Tickers!W33),Tickers!W33,""))),"") | K41: =IFERROR(IF(ISNUMBER(Tickers!S33),Tickers!S33,IF(ISNUMBER(Haver!M33),Haver!M33,IF(ISNUMBER(Tickers!X33),Tickers!X33,""))),"") | L41: =IFERROR(($D$41-AVERAGE($D$15:$D$85))/STDEV($D$15:$D$85),"") | M41: =IFERROR(($I$41-AVERAGE($I$15:$I$85))/STDEV($I$15:$I$85),"") | N41: =IFERROR(-($J$41-AVERAGE($J$15:$J$85))/STDEV($J$15:$J$85),"") | O41: =IFERROR(-($K$41-AVERAGE($K$15:$K$85))/STDEV($K$15:$K$85),"") | P41: =IFERROR(-($G$41-AVERAGE($G$15:$G$85))/STDEV($G$15:$G$85),"") | Q41: =IFERROR(($H$41-AVERAGE($H$15:$H$85))/STDEV($H$15:$H$85),"") | R41: =IFERROR((IF(ISNUMBER(L41),$D$7*L41,0)+IF(ISNUMBER(M41),$D$8*M41,0)+IF(ISNUMBER(N41),$D$9*N41,0)+IF(ISNUMBER(O41),$D$10*O41,0)+IF(ISNUMBER(P41),$D$11*P41,0)+IF(ISNUMBER(Q41),$D$12*Q41,0))/(IF(ISNUMBER(L41),$D$7,0)+IF(ISNUMBER(M41),$D$8,0)+IF(ISNUMBER(N41),$D$9,0)+IF(ISNUMBER(O41),$D$10,0)+IF(ISNUMBER(P41),$D$11,0)+IF(ISNUMBER(Q41),$D$12,0)),"") | S41: =IFERROR(LN($E$41),"") | T41: =IFERROR($N$7+$N$8*$R$41,"") | U41: =IFERROR($S$41-$T$41,"") | V41: =IFERROR(($U$41-AVERAGE($U$15:$U$85))/STDEV($U$15:$U$85),"") | W41: =IF(ISNUMBER($V$41),IF($V$41>=1.5,"CHEAP",IF($V$41>=0.5,"slightly cheap",IF($V$41<=-1.5,"RICH",IF($V$41<=-0.5,"slightly rich","fair")))),"") | X41: =SUMPRODUCT(--ISNUMBER((D41,G41,H41,I41,J41,K41))) | Y41: =IF(X41>=5,"HIGH",IF(X41>=3,"MED","LOW")) | Z41: =IF(AND(ISNUMBER(S41),X41>=$S$11),S41,"") | AA41: =IF(AND(ISNUMBER(R41),X41>=$S$11),R41,"")
B42: =Tickers!B34 | C42: =Tickers!C34 | D42: =Tickers!E34 | E42: =IFERROR(Tickers!G34,"") | F42: =IFERROR(Tickers!I34,"") | G42: =IFERROR(IF(ISNUMBER(Tickers!K34),Tickers!K34,IF(ISNUMBER(Haver!E34),Haver!E34,IF(ISNUMBER(Tickers!T34),Tickers!T34,""))),"") | H42: =IFERROR(IF(ISNUMBER(Tickers!M34),Tickers!M34,IF(ISNUMBER(Haver!G34),Haver!G34,IF(ISNUMBER(Tickers!U34),Tickers!U34,""))),"") | I42: =IFERROR(IF(ISNUMBER(Tickers!O34),Tickers!O34,IF(ISNUMBER(Haver!I34),Haver!I34,IF(ISNUMBER(Tickers!V34),Tickers!V34,""))),"") | J42: =IFERROR(IF(ISNUMBER(Tickers!Q34),Tickers!Q34,IF(ISNUMBER(Haver!K34),Haver!K34,IF(ISNUMBER(Tickers!W34),Tickers!W34,""))),"") | K42: =IFERROR(IF(ISNUMBER(Tickers!S34),Tickers!S34,IF(ISNUMBER(Haver!M34),Haver!M34,IF(ISNUMBER(Tickers!X34),Tickers!X34,""))),"") | L42: =IFERROR(($D$42-AVERAGE($D$15:$D$85))/STDEV($D$15:$D$85),"") | M42: =IFERROR(($I$42-AVERAGE($I$15:$I$85))/STDEV($I$15:$I$85),"") | N42: =IFERROR(-($J$42-AVERAGE($J$15:$J$85))/STDEV($J$15:$J$85),"") | O42: =IFERROR(-($K$42-AVERAGE($K$15:$K$85))/STDEV($K$15:$K$85),"") | P42: =IFERROR(-($G$42-AVERAGE($G$15:$G$85))/STDEV($G$15:$G$85),"") | Q42: =IFERROR(($H$42-AVERAGE($H$15:$H$85))/STDEV($H$15:$H$85),"") | R42: =IFERROR((IF(ISNUMBER(L42),$D$7*L42,0)+IF(ISNUMBER(M42),$D$8*M42,0)+IF(ISNUMBER(N42),$D$9*N42,0)+IF(ISNUMBER(O42),$D$10*O42,0)+IF(ISNUMBER(P42),$D$11*P42,0)+IF(ISNUMBER(Q42),$D$12*Q42,0))/(IF(ISNUMBER(L42),$D$7,0)+IF(ISNUMBER(M42),$D$8,0)+IF(ISNUMBER(N42),$D$9,0)+IF(ISNUMBER(O42),$D$10,0)+IF(ISNUMBER(P42),$D$11,0)+IF(ISNUMBER(Q42),$D$12,0)),"") | S42: =IFERROR(LN($E$42),"") | T42: =IFERROR($N$7+$N$8*$R$42,"") | U42: =IFERROR($S$42-$T$42,"") | V42: =IFERROR(($U$42-AVERAGE($U$15:$U$85))/STDEV($U$15:$U$85),"") | W42: =IF(ISNUMBER($V$42),IF($V$42>=1.5,"CHEAP",IF($V$42>=0.5,"slightly cheap",IF($V$42<=-1.5,"RICH",IF($V$42<=-0.5,"slightly rich","fair")))),"") | X42: =SUMPRODUCT(--ISNUMBER((D42,G42,H42,I42,J42,K42))) | Y42: =IF(X42>=5,"HIGH",IF(X42>=3,"MED","LOW")) | Z42: =IF(AND(ISNUMBER(S42),X42>=$S$11),S42,"") | AA42: =IF(AND(ISNUMBER(R42),X42>=$S$11),R42,"")
B43: =Tickers!B35 | C43: =Tickers!C35 | D43: =Tickers!E35 | E43: =IFERROR(Tickers!G35,"") | F43: =IFERROR(Tickers!I35,"") | G43: =IFERROR(IF(ISNUMBER(Tickers!K35),Tickers!K35,IF(ISNUMBER(Haver!E35),Haver!E35,IF(ISNUMBER(Tickers!T35),Tickers!T35,""))),"") | H43: =IFERROR(IF(ISNUMBER(Tickers!M35),Tickers!M35,IF(ISNUMBER(Haver!G35),Haver!G35,IF(ISNUMBER(Tickers!U35),Tickers!U35,""))),"") | I43: =IFERROR(IF(ISNUMBER(Tickers!O35),Tickers!O35,IF(ISNUMBER(Haver!I35),Haver!I35,IF(ISNUMBER(Tickers!V35),Tickers!V35,""))),"") | J43: =IFERROR(IF(ISNUMBER(Tickers!Q35),Tickers!Q35,IF(ISNUMBER(Haver!K35),Haver!K35,IF(ISNUMBER(Tickers!W35),Tickers!W35,""))),"") | K43: =IFERROR(IF(ISNUMBER(Tickers!S35),Tickers!S35,IF(ISNUMBER(Haver!M35),Haver!M35,IF(ISNUMBER(Tickers!X35),Tickers!X35,""))),"") | L43: =IFERROR(($D$43-AVERAGE($D$15:$D$85))/STDEV($D$15:$D$85),"") | M43: =IFERROR(($I$43-AVERAGE($I$15:$I$85))/STDEV($I$15:$I$85),"") | N43: =IFERROR(-($J$43-AVERAGE($J$15:$J$85))/STDEV($J$15:$J$85),"") | O43: =IFERROR(-($K$43-AVERAGE($K$15:$K$85))/STDEV($K$15:$K$85),"") | P43: =IFERROR(-($G$43-AVERAGE($G$15:$G$85))/STDEV($G$15:$G$85),"") | Q43: =IFERROR(($H$43-AVERAGE($H$15:$H$85))/STDEV($H$15:$H$85),"") | R43: =IFERROR((IF(ISNUMBER(L43),$D$7*L43,0)+IF(ISNUMBER(M43),$D$8*M43,0)+IF(ISNUMBER(N43),$D$9*N43,0)+IF(ISNUMBER(O43),$D$10*O43,0)+IF(ISNUMBER(P43),$D$11*P43,0)+IF(ISNUMBER(Q43),$D$12*Q43,0))/(IF(ISNUMBER(L43),$D$7,0)+IF(ISNUMBER(M43),$D$8,0)+IF(ISNUMBER(N43),$D$9,0)+IF(ISNUMBER(O43),$D$10,0)+IF(ISNUMBER(P43),$D$11,0)+IF(ISNUMBER(Q43),$D$12,0)),"") | S43: =IFERROR(LN($E$43),"") | T43: =IFERROR($N$7+$N$8*$R$43,"") | U43: =IFERROR($S$43-$T$43,"") | V43: =IFERROR(($U$43-AVERAGE($U$15:$U$85))/STDEV($U$15:$U$85),"") | W43: =IF(ISNUMBER($V$43),IF($V$43>=1.5,"CHEAP",IF($V$43>=0.5,"slightly cheap",IF($V$43<=-1.5,"RICH",IF($V$43<=-0.5,"slightly rich","fair")))),"") | X43: =SUMPRODUCT(--ISNUMBER((D43,G43,H43,I43,J43,K43))) | Y43: =IF(X43>=5,"HIGH",IF(X43>=3,"MED","LOW")) | Z43: =IF(AND(ISNUMBER(S43),X43>=$S$11),S43,"") | AA43: =IF(AND(ISNUMBER(R43),X43>=$S$11),R43,"")
B44: =Tickers!B36 | C44: =Tickers!C36 | D44: =Tickers!E36 | E44: =IFERROR(Tickers!G36,"") | F44: =IFERROR(Tickers!I36,"") | G44: =IFERROR(IF(ISNUMBER(Tickers!K36),Tickers!K36,IF(ISNUMBER(Haver!E36),Haver!E36,IF(ISNUMBER(Tickers!T36),Tickers!T36,""))),"") | H44: =IFERROR(IF(ISNUMBER(Tickers!M36),Tickers!M36,IF(ISNUMBER(Haver!G36),Haver!G36,IF(ISNUMBER(Tickers!U36),Tickers!U36,""))),"") | I44: =IFERROR(IF(ISNUMBER(Tickers!O36),Tickers!O36,IF(ISNUMBER(Haver!I36),Haver!I36,IF(ISNUMBER(Tickers!V36),Tickers!V36,""))),"") | J44: =IFERROR(IF(ISNUMBER(Tickers!Q36),Tickers!Q36,IF(ISNUMBER(Haver!K36),Haver!K36,IF(ISNUMBER(Tickers!W36),Tickers!W36,""))),"") | K44: =IFERROR(IF(ISNUMBER(Tickers!S36),Tickers!S36,IF(ISNUMBER(Haver!M36),Haver!M36,IF(ISNUMBER(Tickers!X36),Tickers!X36,""))),"") | L44: =IFERROR(($D$44-AVERAGE($D$15:$D$85))/STDEV($D$15:$D$85),"") | M44: =IFERROR(($I$44-AVERAGE($I$15:$I$85))/STDEV($I$15:$I$85),"") | N44: =IFERROR(-($J$44-AVERAGE($J$15:$J$85))/STDEV($J$15:$J$85),"") | O44: =IFERROR(-($K$44-AVERAGE($K$15:$K$85))/STDEV($K$15:$K$85),"") | P44: =IFERROR(-($G$44-AVERAGE($G$15:$G$85))/STDEV($G$15:$G$85),"") | Q44: =IFERROR(($H$44-AVERAGE($H$15:$H$85))/STDEV($H$15:$H$85),"") | R44: =IFERROR((IF(ISNUMBER(L44),$D$7*L44,0)+IF(ISNUMBER(M44),$D$8*M44,0)+IF(ISNUMBER(N44),$D$9*N44,0)+IF(ISNUMBER(O44),$D$10*O44,0)+IF(ISNUMBER(P44),$D$11*P44,0)+IF(ISNUMBER(Q44),$D$12*Q44,0))/(IF(ISNUMBER(L44),$D$7,0)+IF(ISNUMBER(M44),$D$8,0)+IF(ISNUMBER(N44),$D$9,0)+IF(ISNUMBER(O44),$D$10,0)+IF(ISNUMBER(P44),$D$11,0)+IF(ISNUMBER(Q44),$D$12,0)),"") | S44: =IFERROR(LN($E$44),"") | T44: =IFERROR($N$7+$N$8*$R$44,"") | U44: =IFERROR($S$44-$T$44,"") | V44: =IFERROR(($U$44-AVERAGE($U$15:$U$85))/STDEV($U$15:$U$85),"") | W44: =IF(ISNUMBER($V$44),IF($V$44>=1.5,"CHEAP",IF($V$44>=0.5,"slightly cheap",IF($V$44<=-1.5,"RICH",IF($V$44<=-0.5,"slightly rich","fair")))),"") | X44: =SUMPRODUCT(--ISNUMBER((D44,G44,H44,I44,J44,K44))) | Y44: =IF(X44>=5,"HIGH",IF(X44>=3,"MED","LOW")) | Z44: =IF(AND(ISNUMBER(S44),X44>=$S$11),S44,"") | AA44: =IF(AND(ISNUMBER(R44),X44>=$S$11),R44,"")
B45: =Tickers!B37 | C45: =Tickers!C37 | D45: =Tickers!E37 | E45: =IFERROR(Tickers!G37,"") | F45: =IFERROR(Tickers!I37,"") | G45: =IFERROR(IF(ISNUMBER(Tickers!K37),Tickers!K37,IF(ISNUMBER(Haver!E37),Haver!E37,IF(ISNUMBER(Tickers!T37),Tickers!T37,""))),"") | H45: =IFERROR(IF(ISNUMBER(Tickers!M37),Tickers!M37,IF(ISNUMBER(Haver!G37),Haver!G37,IF(ISNUMBER(Tickers!U37),Tickers!U37,""))),"") | I45: =IFERROR(IF(ISNUMBER(Tickers!O37),Tickers!O37,IF(ISNUMBER(Haver!I37),Haver!I37,IF(ISNUMBER(Tickers!V37),Tickers!V37,""))),"") | J45: =IFERROR(IF(ISNUMBER(Tickers!Q37),Tickers!Q37,IF(ISNUMBER(Haver!K37),Haver!K37,IF(ISNUMBER(Tickers!W37),Tickers!W37,""))),"") | K45: =IFERROR(IF(ISNUMBER(Tickers!S37),Tickers!S37,IF(ISNUMBER(Haver!M37),Haver!M37,IF(ISNUMBER(Tickers!X37),Tickers!X37,""))),"") | L45: =IFERROR(($D$45-AVERAGE($D$15:$D$85))/STDEV($D$15:$D$85),"") | M45: =IFERROR(($I$45-AVERAGE($I$15:$I$85))/STDEV($I$15:$I$85),"") | N45: =IFERROR(-($J$45-AVERAGE($J$15:$J$85))/STDEV($J$15:$J$85),"") | O45: =IFERROR(-($K$45-AVERAGE($K$15:$K$85))/STDEV($K$15:$K$85),"") | P45: =IFERROR(-($G$45-AVERAGE($G$15:$G$85))/STDEV($G$15:$G$85),"") | Q45: =IFERROR(($H$45-AVERAGE($H$15:$H$85))/STDEV($H$15:$H$85),"") | R45: =IFERROR((IF(ISNUMBER(L45),$D$7*L45,0)+IF(ISNUMBER(M45),$D$8*M45,0)+IF(ISNUMBER(N45),$D$9*N45,0)+IF(ISNUMBER(O45),$D$10*O45,0)+IF(ISNUMBER(P45),$D$11*P45,0)+IF(ISNUMBER(Q45),$D$12*Q45,0))/(IF(ISNUMBER(L45),$D$7,0)+IF(ISNUMBER(M45),$D$8,0)+IF(ISNUMBER(N45),$D$9,0)+IF(ISNUMBER(O45),$D$10,0)+IF(ISNUMBER(P45),$D$11,0)+IF(ISNUMBER(Q45),$D$12,0)),"") | S45: =IFERROR(LN($E$45),"") | T45: =IFERROR($N$7+$N$8*$R$45,"") | U45: =IFERROR($S$45-$T$45,"") | V45: =IFERROR(($U$45-AVERAGE($U$15:$U$85))/STDEV($U$15:$U$85),"") | W45: =IF(ISNUMBER($V$45),IF($V$45>=1.5,"CHEAP",IF($V$45>=0.5,"slightly cheap",IF($V$45<=-1.5,"RICH",IF($V$45<=-0.5,"slightly rich","fair")))),"") | X45: =SUMPRODUCT(--ISNUMBER((D45,G45,H45,I45,J45,K45))) | Y45: =IF(X45>=5,"HIGH",IF(X45>=3,"MED","LOW")) | Z45: =IF(AND(ISNUMBER(S45),X45>=$S$11),S45,"") | AA45: =IF(AND(ISNUMBER(R45),X45>=$S$11),R45,"")
B46: =Tickers!B38 | C46: =Tickers!C38 | D46: =Tickers!E38 | E46: =IFERROR(Tickers!G38,"") | F46: =IFERROR(Tickers!I38,"") | G46: =IFERROR(IF(ISNUMBER(Tickers!K38),Tickers!K38,IF(ISNUMBER(Haver!E38),Haver!E38,IF(ISNUMBER(Tickers!T38),Tickers!T38,""))),"") | H46: =IFERROR(IF(ISNUMBER(Tickers!M38),Tickers!M38,IF(ISNUMBER(Haver!G38),Haver!G38,IF(ISNUMBER(Tickers!U38),Tickers!U38,""))),"") | I46: =IFERROR(IF(ISNUMBER(Tickers!O38),Tickers!O38,IF(ISNUMBER(Haver!I38),Haver!I38,IF(ISNUMBER(Tickers!V38),Tickers!V38,""))),"") | J46: =IFERROR(IF(ISNUMBER(Tickers!Q38),Tickers!Q38,IF(ISNUMBER(Haver!K38),Haver!K38,IF(ISNUMBER(Tickers!W38),Tickers!W38,""))),"") | K46: =IFERROR(IF(ISNUMBER(Tickers!S38),Tickers!S38,IF(ISNUMBER(Haver!M38),Haver!M38,IF(ISNUMBER(Tickers!X38),Tickers!X38,""))),"") | L46: =IFERROR(($D$46-AVERAGE($D$15:$D$85))/STDEV($D$15:$D$85),"") | M46: =IFERROR(($I$46-AVERAGE($I$15:$I$85))/STDEV($I$15:$I$85),"") | N46: =IFERROR(-($J$46-AVERAGE($J$15:$J$85))/STDEV($J$15:$J$85),"") | O46: =IFERROR(-($K$46-AVERAGE($K$15:$K$85))/STDEV($K$15:$K$85),"") | P46: =IFERROR(-($G$46-AVERAGE($G$15:$G$85))/STDEV($G$15:$G$85),"") | Q46: =IFERROR(($H$46-AVERAGE($H$15:$H$85))/STDEV($H$15:$H$85),"") | R46: =IFERROR((IF(ISNUMBER(L46),$D$7*L46,0)+IF(ISNUMBER(M46),$D$8*M46,0)+IF(ISNUMBER(N46),$D$9*N46,0)+IF(ISNUMBER(O46),$D$10*O46,0)+IF(ISNUMBER(P46),$D$11*P46,0)+IF(ISNUMBER(Q46),$D$12*Q46,0))/(IF(ISNUMBER(L46),$D$7,0)+IF(ISNUMBER(M46),$D$8,0)+IF(ISNUMBER(N46),$D$9,0)+IF(ISNUMBER(O46),$D$10,0)+IF(ISNUMBER(P46),$D$11,0)+IF(ISNUMBER(Q46),$D$12,0)),"") | S46: =IFERROR(LN($E$46),"") | T46: =IFERROR($N$7+$N$8*$R$46,"") | U46: =IFERROR($S$46-$T$46,"") | V46: =IFERROR(($U$46-AVERAGE($U$15:$U$85))/STDEV($U$15:$U$85),"") | W46: =IF(ISNUMBER($V$46),IF($V$46>=1.5,"CHEAP",IF($V$46>=0.5,"slightly cheap",IF($V$46<=-1.5,"RICH",IF($V$46<=-0.5,"slightly rich","fair")))),"") | X46: =SUMPRODUCT(--ISNUMBER((D46,G46,H46,I46,J46,K46))) | Y46: =IF(X46>=5,"HIGH",IF(X46>=3,"MED","LOW")) | Z46: =IF(AND(ISNUMBER(S46),X46>=$S$11),S46,"") | AA46: =IF(AND(ISNUMBER(R46),X46>=$S$11),R46,"")
B47: =Tickers!B39 | C47: =Tickers!C39 | D47: =Tickers!E39 | E47: =IFERROR(Tickers!G39,"") | F47: =IFERROR(Tickers!I39,"") | G47: =IFERROR(IF(ISNUMBER(Tickers!K39),Tickers!K39,IF(ISNUMBER(Haver!E39),Haver!E39,IF(ISNUMBER(Tickers!T39),Tickers!T39,""))),"") | H47: =IFERROR(IF(ISNUMBER(Tickers!M39),Tickers!M39,IF(ISNUMBER(Haver!G39),Haver!G39,IF(ISNUMBER(Tickers!U39),Tickers!U39,""))),"") | I47: =IFERROR(IF(ISNUMBER(Tickers!O39),Tickers!O39,IF(ISNUMBER(Haver!I39),Haver!I39,IF(ISNUMBER(Tickers!V39),Tickers!V39,""))),"") | J47: =IFERROR(IF(ISNUMBER(Tickers!Q39),Tickers!Q39,IF(ISNUMBER(Haver!K39),Haver!K39,IF(ISNUMBER(Tickers!W39),Tickers!W39,""))),"") | K47: =IFERROR(IF(ISNUMBER(Tickers!S39),Tickers!S39,IF(ISNUMBER(Haver!M39),Haver!M39,IF(ISNUMBER(Tickers!X39),Tickers!X39,""))),"") | L47: =IFERROR(($D$47-AVERAGE($D$15:$D$85))/STDEV($D$15:$D$85),"") | M47: =IFERROR(($I$47-AVERAGE($I$15:$I$85))/STDEV($I$15:$I$85),"") | N47: =IFERROR(-($J$47-AVERAGE($J$15:$J$85))/STDEV($J$15:$J$85),"") | O47: =IFERROR(-($K$47-AVERAGE($K$15:$K$85))/STDEV($K$15:$K$85),"") | P47: =IFERROR(-($G$47-AVERAGE($G$15:$G$85))/STDEV($G$15:$G$85),"") | Q47: =IFERROR(($H$47-AVERAGE($H$15:$H$85))/STDEV($H$15:$H$85),"") | R47: =IFERROR((IF(ISNUMBER(L47),$D$7*L47,0)+IF(ISNUMBER(M47),$D$8*M47,0)+IF(ISNUMBER(N47),$D$9*N47,0)+IF(ISNUMBER(O47),$D$10*O47,0)+IF(ISNUMBER(P47),$D$11*P47,0)+IF(ISNUMBER(Q47),$D$12*Q47,0))/(IF(ISNUMBER(L47),$D$7,0)+IF(ISNUMBER(M47),$D$8,0)+IF(ISNUMBER(N47),$D$9,0)+IF(ISNUMBER(O47),$D$10,0)+IF(ISNUMBER(P47),$D$11,0)+IF(ISNUMBER(Q47),$D$12,0)),"") | S47: =IFERROR(LN($E$47),"") | T47: =IFERROR($N$7+$N$8*$R$47,"") | U47: =IFERROR($S$47-$T$47,"") | V47: =IFERROR(($U$47-AVERAGE($U$15:$U$85))/STDEV($U$15:$U$85),"") | W47: =IF(ISNUMBER($V$47),IF($V$47>=1.5,"CHEAP",IF($V$47>=0.5,"slightly cheap",IF($V$47<=-1.5,"RICH",IF($V$47<=-0.5,"slightly rich","fair")))),"") | X47: =SUMPRODUCT(--ISNUMBER((D47,G47,H47,I47,J47,K47))) | Y47: =IF(X47>=5,"HIGH",IF(X47>=3,"MED","LOW")) | Z47: =IF(AND(ISNUMBER(S47),X47>=$S$11),S47,"") | AA47: =IF(AND(ISNUMBER(R47),X47>=$S$11),R47,"")
B48: =Tickers!B40 | C48: =Tickers!C40 | D48: =Tickers!E40 | E48: =IFERROR(Tickers!G40,"") | F48: =IFERROR(Tickers!I40,"") | G48: =IFERROR(IF(ISNUMBER(Tickers!K40),Tickers!K40,IF(ISNUMBER(Haver!E40),Haver!E40,IF(ISNUMBER(Tickers!T40),Tickers!T40,""))),"") | H48: =IFERROR(IF(ISNUMBER(Tickers!M40),Tickers!M40,IF(ISNUMBER(Haver!G40),Haver!G40,IF(ISNUMBER(Tickers!U40),Tickers!U40,""))),"") | I48: =IFERROR(IF(ISNUMBER(Tickers!O40),Tickers!O40,IF(ISNUMBER(Haver!I40),Haver!I40,IF(ISNUMBER(Tickers!V40),Tickers!V40,""))),"") | J48: =IFERROR(IF(ISNUMBER(Tickers!Q40),Tickers!Q40,IF(ISNUMBER(Haver!K40),Haver!K40,IF(ISNUMBER(Tickers!W40),Tickers!W40,""))),"") | K48: =IFERROR(IF(ISNUMBER(Tickers!S40),Tickers!S40,IF(ISNUMBER(Haver!M40),Haver!M40,IF(ISNUMBER(Tickers!X40),Tickers!X40,""))),"") | L48: =IFERROR(($D$48-AVERAGE($D$15:$D$85))/STDEV($D$15:$D$85),"") | M48: =IFERROR(($I$48-AVERAGE($I$15:$I$85))/STDEV($I$15:$I$85),"") | N48: =IFERROR(-($J$48-AVERAGE($J$15:$J$85))/STDEV($J$15:$J$85),"") | O48: =IFERROR(-($K$48-AVERAGE($K$15:$K$85))/STDEV($K$15:$K$85),"") | P48: =IFERROR(-($G$48-AVERAGE($G$15:$G$85))/STDEV($G$15:$G$85),"") | Q48: =IFERROR(($H$48-AVERAGE($H$15:$H$85))/STDEV($H$15:$H$85),"") | R48: =IFERROR((IF(ISNUMBER(L48),$D$7*L48,0)+IF(ISNUMBER(M48),$D$8*M48,0)+IF(ISNUMBER(N48),$D$9*N48,0)+IF(ISNUMBER(O48),$D$10*O48,0)+IF(ISNUMBER(P48),$D$11*P48,0)+IF(ISNUMBER(Q48),$D$12*Q48,0))/(IF(ISNUMBER(L48),$D$7,0)+IF(ISNUMBER(M48),$D$8,0)+IF(ISNUMBER(N48),$D$9,0)+IF(ISNUMBER(O48),$D$10,0)+IF(ISNUMBER(P48),$D$11,0)+IF(ISNUMBER(Q48),$D$12,0)),"") | S48: =IFERROR(LN($E$48),"") | T48: =IFERROR($N$7+$N$8*$R$48,"") | U48: =IFERROR($S$48-$T$48,"") | V48: =IFERROR(($U$48-AVERAGE($U$15:$U$85))/STDEV($U$15:$U$85),"") | W48: =IF(ISNUMBER($V$48),IF($V$48>=1.5,"CHEAP",IF($V$48>=0.5,"slightly cheap",IF($V$48<=-1.5,"RICH",IF($V$48<=-0.5,"slightly rich","fair")))),"") | X48: =SUMPRODUCT(--ISNUMBER((D48,G48,H48,I48,J48,K48))) | Y48: =IF(X48>=5,"HIGH",IF(X48>=3,"MED","LOW")) | Z48: =IF(AND(ISNUMBER(S48),X48>=$S$11),S48,"") | AA48: =IF(AND(ISNUMBER(R48),X48>=$S$11),R48,"")
B49: =Tickers!B41 | C49: =Tickers!C41 | D49: =Tickers!E41 | E49: =IFERROR(Tickers!G41,"") | F49: =IFERROR(Tickers!I41,"") | G49: =IFERROR(IF(ISNUMBER(Tickers!K41),Tickers!K41,IF(ISNUMBER(Haver!E41),Haver!E41,IF(ISNUMBER(Tickers!T41),Tickers!T41,""))),"") | H49: =IFERROR(IF(ISNUMBER(Tickers!M41),Tickers!M41,IF(ISNUMBER(Haver!G41),Haver!G41,IF(ISNUMBER(Tickers!U41),Tickers!U41,""))),"") | I49: =IFERROR(IF(ISNUMBER(Tickers!O41),Tickers!O41,IF(ISNUMBER(Haver!I41),Haver!I41,IF(ISNUMBER(Tickers!V41),Tickers!V41,""))),"") | J49: =IFERROR(IF(ISNUMBER(Tickers!Q41),Tickers!Q41,IF(ISNUMBER(Haver!K41),Haver!K41,IF(ISNUMBER(Tickers!W41),Tickers!W41,""))),"") | K49: =IFERROR(IF(ISNUMBER(Tickers!S41),Tickers!S41,IF(ISNUMBER(Haver!M41),Haver!M41,IF(ISNUMBER(Tickers!X41),Tickers!X41,""))),"") | L49: =IFERROR(($D$49-AVERAGE($D$15:$D$85))/STDEV($D$15:$D$85),"") | M49: =IFERROR(($I$49-AVERAGE($I$15:$I$85))/STDEV($I$15:$I$85),"") | N49: =IFERROR(-($J$49-AVERAGE($J$15:$J$85))/STDEV($J$15:$J$85),"") | O49: =IFERROR(-($K$49-AVERAGE($K$15:$K$85))/STDEV($K$15:$K$85),"") | P49: =IFERROR(-($G$49-AVERAGE($G$15:$G$85))/STDEV($G$15:$G$85),"") | Q49: =IFERROR(($H$49-AVERAGE($H$15:$H$85))/STDEV($H$15:$H$85),"") | R49: =IFERROR((IF(ISNUMBER(L49),$D$7*L49,0)+IF(ISNUMBER(M49),$D$8*M49,0)+IF(ISNUMBER(N49),$D$9*N49,0)+IF(ISNUMBER(O49),$D$10*O49,0)+IF(ISNUMBER(P49),$D$11*P49,0)+IF(ISNUMBER(Q49),$D$12*Q49,0))/(IF(ISNUMBER(L49),$D$7,0)+IF(ISNUMBER(M49),$D$8,0)+IF(ISNUMBER(N49),$D$9,0)+IF(ISNUMBER(O49),$D$10,0)+IF(ISNUMBER(P49),$D$11,0)+IF(ISNUMBER(Q49),$D$12,0)),"") | S49: =IFERROR(LN($E$49),"") | T49: =IFERROR($N$7+$N$8*$R$49,"") | U49: =IFERROR($S$49-$T$49,"") | V49: =IFERROR(($U$49-AVERAGE($U$15:$U$85))/STDEV($U$15:$U$85),"") | W49: =IF(ISNUMBER($V$49),IF($V$49>=1.5,"CHEAP",IF($V$49>=0.5,"slightly cheap",IF($V$49<=-1.5,"RICH",IF($V$49<=-0.5,"slightly rich","fair")))),"") | X49: =SUMPRODUCT(--ISNUMBER((D49,G49,H49,I49,J49,K49))) | Y49: =IF(X49>=5,"HIGH",IF(X49>=3,"MED","LOW")) | Z49: =IF(AND(ISNUMBER(S49),X49>=$S$11),S49,"") | AA49: =IF(AND(ISNUMBER(R49),X49>=$S$11),R49,"")
B50: =Tickers!B42 | C50: =Tickers!C42 | D50: =Tickers!E42 | E50: =IFERROR(Tickers!G42,"") | F50: =IFERROR(Tickers!I42,"") | G50: =IFERROR(IF(ISNUMBER(Tickers!K42),Tickers!K42,IF(ISNUMBER(Haver!E42),Haver!E42,IF(ISNUMBER(Tickers!T42),Tickers!T42,""))),"") | H50: =IFERROR(IF(ISNUMBER(Tickers!M42),Tickers!M42,IF(ISNUMBER(Haver!G42),Haver!G42,IF(ISNUMBER(Tickers!U42),Tickers!U42,""))),"") | I50: =IFERROR(IF(ISNUMBER(Tickers!O42),Tickers!O42,IF(ISNUMBER(Haver!I42),Haver!I42,IF(ISNUMBER(Tickers!V42),Tickers!V42,""))),"") | J50: =IFERROR(IF(ISNUMBER(Tickers!Q42),Tickers!Q42,IF(ISNUMBER(Haver!K42),Haver!K42,IF(ISNUMBER(Tickers!W42),Tickers!W42,""))),"") | K50: =IFERROR(IF(ISNUMBER(Tickers!S42),Tickers!S42,IF(ISNUMBER(Haver!M42),Haver!M42,IF(ISNUMBER(Tickers!X42),Tickers!X42,""))),"") | L50: =IFERROR(($D$50-AVERAGE($D$15:$D$85))/STDEV($D$15:$D$85),"") | M50: =IFERROR(($I$50-AVERAGE($I$15:$I$85))/STDEV($I$15:$I$85),"") | N50: =IFERROR(-($J$50-AVERAGE($J$15:$J$85))/STDEV($J$15:$J$85),"") | O50: =IFERROR(-($K$50-AVERAGE($K$15:$K$85))/STDEV($K$15:$K$85),"") | P50: =IFERROR(-($G$50-AVERAGE($G$15:$G$85))/STDEV($G$15:$G$85),"") | Q50: =IFERROR(($H$50-AVERAGE($H$15:$H$85))/STDEV($H$15:$H$85),"") | R50: =IFERROR((IF(ISNUMBER(L50),$D$7*L50,0)+IF(ISNUMBER(M50),$D$8*M50,0)+IF(ISNUMBER(N50),$D$9*N50,0)+IF(ISNUMBER(O50),$D$10*O50,0)+IF(ISNUMBER(P50),$D$11*P50,0)+IF(ISNUMBER(Q50),$D$12*Q50,0))/(IF(ISNUMBER(L50),$D$7,0)+IF(ISNUMBER(M50),$D$8,0)+IF(ISNUMBER(N50),$D$9,0)+IF(ISNUMBER(O50),$D$10,0)+IF(ISNUMBER(P50),$D$11,0)+IF(ISNUMBER(Q50),$D$12,0)),"") | S50: =IFERROR(LN($E$50),"") | T50: =IFERROR($N$7+$N$8*$R$50,"") | U50: =IFERROR($S$50-$T$50,"") | V50: =IFERROR(($U$50-AVERAGE($U$15:$U$85))/STDEV($U$15:$U$85),"") | W50: =IF(ISNUMBER($V$50),IF($V$50>=1.5,"CHEAP",IF($V$50>=0.5,"slightly cheap",IF($V$50<=-1.5,"RICH",IF($V$50<=-0.5,"slightly rich","fair")))),"") | X50: =SUMPRODUCT(--ISNUMBER((D50,G50,H50,I50,J50,K50))) | Y50: =IF(X50>=5,"HIGH",IF(X50>=3,"MED","LOW")) | Z50: =IF(AND(ISNUMBER(S50),X50>=$S$11),S50,"") | AA50: =IF(AND(ISNUMBER(R50),X50>=$S$11),R50,"")
B51: =Tickers!B43 | C51: =Tickers!C43 | D51: =Tickers!E43 | E51: =IFERROR(Tickers!G43,"") | F51: =IFERROR(Tickers!I43,"") | G51: =IFERROR(IF(ISNUMBER(Tickers!K43),Tickers!K43,IF(ISNUMBER(Haver!E43),Haver!E43,IF(ISNUMBER(Tickers!T43),Tickers!T43,""))),"") | H51: =IFERROR(IF(ISNUMBER(Tickers!M43),Tickers!M43,IF(ISNUMBER(Haver!G43),Haver!G43,IF(ISNUMBER(Tickers!U43),Tickers!U43,""))),"") | I51: =IFERROR(IF(ISNUMBER(Tickers!O43),Tickers!O43,IF(ISNUMBER(Haver!I43),Haver!I43,IF(ISNUMBER(Tickers!V43),Tickers!V43,""))),"") | J51: =IFERROR(IF(ISNUMBER(Tickers!Q43),Tickers!Q43,IF(ISNUMBER(Haver!K43),Haver!K43,IF(ISNUMBER(Tickers!W43),Tickers!W43,""))),"") | K51: =IFERROR(IF(ISNUMBER(Tickers!S43),Tickers!S43,IF(ISNUMBER(Haver!M43),Haver!M43,IF(ISNUMBER(Tickers!X43),Tickers!X43,""))),"") | L51: =IFERROR(($D$51-AVERAGE($D$15:$D$85))/STDEV($D$15:$D$85),"") | M51: =IFERROR(($I$51-AVERAGE($I$15:$I$85))/STDEV($I$15:$I$85),"") | N51: =IFERROR(-($J$51-AVERAGE($J$15:$J$85))/STDEV($J$15:$J$85),"") | O51: =IFERROR(-($K$51-AVERAGE($K$15:$K$85))/STDEV($K$15:$K$85),"") | P51: =IFERROR(-($G$51-AVERAGE($G$15:$G$85))/STDEV($G$15:$G$85),"") | Q51: =IFERROR(($H$51-AVERAGE($H$15:$H$85))/STDEV($H$15:$H$85),"") | R51: =IFERROR((IF(ISNUMBER(L51),$D$7*L51,0)+IF(ISNUMBER(M51),$D$8*M51,0)+IF(ISNUMBER(N51),$D$9*N51,0)+IF(ISNUMBER(O51),$D$10*O51,0)+IF(ISNUMBER(P51),$D$11*P51,0)+IF(ISNUMBER(Q51),$D$12*Q51,0))/(IF(ISNUMBER(L51),$D$7,0)+IF(ISNUMBER(M51),$D$8,0)+IF(ISNUMBER(N51),$D$9,0)+IF(ISNUMBER(O51),$D$10,0)+IF(ISNUMBER(P51),$D$11,0)+IF(ISNUMBER(Q51),$D$12,0)),"") | S51: =IFERROR(LN($E$51),"") | T51: =IFERROR($N$7+$N$8*$R$51,"") | U51: =IFERROR($S$51-$T$51,"") | V51: =IFERROR(($U$51-AVERAGE($U$15:$U$85))/STDEV($U$15:$U$85),"") | W51: =IF(ISNUMBER($V$51),IF($V$51>=1.5,"CHEAP",IF($V$51>=0.5,"slightly cheap",IF($V$51<=-1.5,"RICH",IF($V$51<=-0.5,"slightly rich","fair")))),"") | X51: =SUMPRODUCT(--ISNUMBER((D51,G51,H51,I51,J51,K51))) | Y51: =IF(X51>=5,"HIGH",IF(X51>=3,"MED","LOW")) | Z51: =IF(AND(ISNUMBER(S51),X51>=$S$11),S51,"") | AA51: =IF(AND(ISNUMBER(R51),X51>=$S$11),R51,"")
B52: =Tickers!B44 | C52: =Tickers!C44 | D52: =Tickers!E44 | E52: =IFERROR(Tickers!G44,"") | F52: =IFERROR(Tickers!I44,"") | G52: =IFERROR(IF(ISNUMBER(Tickers!K44),Tickers!K44,IF(ISNUMBER(Haver!E44),Haver!E44,IF(ISNUMBER(Tickers!T44),Tickers!T44,""))),"") | H52: =IFERROR(IF(ISNUMBER(Tickers!M44),Tickers!M44,IF(ISNUMBER(Haver!G44),Haver!G44,IF(ISNUMBER(Tickers!U44),Tickers!U44,""))),"") | I52: =IFERROR(IF(ISNUMBER(Tickers!O44),Tickers!O44,IF(ISNUMBER(Haver!I44),Haver!I44,IF(ISNUMBER(Tickers!V44),Tickers!V44,""))),"") | J52: =IFERROR(IF(ISNUMBER(Tickers!Q44),Tickers!Q44,IF(ISNUMBER(Haver!K44),Haver!K44,IF(ISNUMBER(Tickers!W44),Tickers!W44,""))),"") | K52: =IFERROR(IF(ISNUMBER(Tickers!S44),Tickers!S44,IF(ISNUMBER(Haver!M44),Haver!M44,IF(ISNUMBER(Tickers!X44),Tickers!X44,""))),"") | L52: =IFERROR(($D$52-AVERAGE($D$15:$D$85))/STDEV($D$15:$D$85),"") | M52: =IFERROR(($I$52-AVERAGE($I$15:$I$85))/STDEV($I$15:$I$85),"") | N52: =IFERROR(-($J$52-AVERAGE($J$15:$J$85))/STDEV($J$15:$J$85),"") | O52: =IFERROR(-($K$52-AVERAGE($K$15:$K$85))/STDEV($K$15:$K$85),"") | P52: =IFERROR(-($G$52-AVERAGE($G$15:$G$85))/STDEV($G$15:$G$85),"") | Q52: =IFERROR(($H$52-AVERAGE($H$15:$H$85))/STDEV($H$15:$H$85),"") | R52: =IFERROR((IF(ISNUMBER(L52),$D$7*L52,0)+IF(ISNUMBER(M52),$D$8*M52,0)+IF(ISNUMBER(N52),$D$9*N52,0)+IF(ISNUMBER(O52),$D$10*O52,0)+IF(ISNUMBER(P52),$D$11*P52,0)+IF(ISNUMBER(Q52),$D$12*Q52,0))/(IF(ISNUMBER(L52),$D$7,0)+IF(ISNUMBER(M52),$D$8,0)+IF(ISNUMBER(N52),$D$9,0)+IF(ISNUMBER(O52),$D$10,0)+IF(ISNUMBER(P52),$D$11,0)+IF(ISNUMBER(Q52),$D$12,0)),"") | S52: =IFERROR(LN($E$52),"") | T52: =IFERROR($N$7+$N$8*$R$52,"") | U52: =IFERROR($S$52-$T$52,"") | V52: =IFERROR(($U$52-AVERAGE($U$15:$U$85))/STDEV($U$15:$U$85),"") | W52: =IF(ISNUMBER($V$52),IF($V$52>=1.5,"CHEAP",IF($V$52>=0.5,"slightly cheap",IF($V$52<=-1.5,"RICH",IF($V$52<=-0.5,"slightly rich","fair")))),"") | X52: =SUMPRODUCT(--ISNUMBER((D52,G52,H52,I52,J52,K52))) | Y52: =IF(X52>=5,"HIGH",IF(X52>=3,"MED","LOW")) | Z52: =IF(AND(ISNUMBER(S52),X52>=$S$11),S52,"") | AA52: =IF(AND(ISNUMBER(R52),X52>=$S$11),R52,"")
B53: =Tickers!B45 | C53: =Tickers!C45 | D53: =Tickers!E45 | E53: =IFERROR(Tickers!G45,"") | F53: =IFERROR(Tickers!I45,"") | G53: =IFERROR(IF(ISNUMBER(Tickers!K45),Tickers!K45,IF(ISNUMBER(Haver!E45),Haver!E45,IF(ISNUMBER(Tickers!T45),Tickers!T45,""))),"") | H53: =IFERROR(IF(ISNUMBER(Tickers!M45),Tickers!M45,IF(ISNUMBER(Haver!G45),Haver!G45,IF(ISNUMBER(Tickers!U45),Tickers!U45,""))),"") | I53: =IFERROR(IF(ISNUMBER(Tickers!O45),Tickers!O45,IF(ISNUMBER(Haver!I45),Haver!I45,IF(ISNUMBER(Tickers!V45),Tickers!V45,""))),"") | J53: =IFERROR(IF(ISNUMBER(Tickers!Q45),Tickers!Q45,IF(ISNUMBER(Haver!K45),Haver!K45,IF(ISNUMBER(Tickers!W45),Tickers!W45,""))),"") | K53: =IFERROR(IF(ISNUMBER(Tickers!S45),Tickers!S45,IF(ISNUMBER(Haver!M45),Haver!M45,IF(ISNUMBER(Tickers!X45),Tickers!X45,""))),"") | L53: =IFERROR(($D$53-AVERAGE($D$15:$D$85))/STDEV($D$15:$D$85),"") | M53: =IFERROR(($I$53-AVERAGE($I$15:$I$85))/STDEV($I$15:$I$85),"") | N53: =IFERROR(-($J$53-AVERAGE($J$15:$J$85))/STDEV($J$15:$J$85),"") | O53: =IFERROR(-($K$53-AVERAGE($K$15:$K$85))/STDEV($K$15:$K$85),"") | P53: =IFERROR(-($G$53-AVERAGE($G$15:$G$85))/STDEV($G$15:$G$85),"") | Q53: =IFERROR(($H$53-AVERAGE($H$15:$H$85))/STDEV($H$15:$H$85),"") | R53: =IFERROR((IF(ISNUMBER(L53),$D$7*L53,0)+IF(ISNUMBER(M53),$D$8*M53,0)+IF(ISNUMBER(N53),$D$9*N53,0)+IF(ISNUMBER(O53),$D$10*O53,0)+IF(ISNUMBER(P53),$D$11*P53,0)+IF(ISNUMBER(Q53),$D$12*Q53,0))/(IF(ISNUMBER(L53),$D$7,0)+IF(ISNUMBER(M53),$D$8,0)+IF(ISNUMBER(N53),$D$9,0)+IF(ISNUMBER(O53),$D$10,0)+IF(ISNUMBER(P53),$D$11,0)+IF(ISNUMBER(Q53),$D$12,0)),"") | S53: =IFERROR(LN($E$53),"") | T53: =IFERROR($N$7+$N$8*$R$53,"") | U53: =IFERROR($S$53-$T$53,"") | V53: =IFERROR(($U$53-AVERAGE($U$15:$U$85))/STDEV($U$15:$U$85),"") | W53: =IF(ISNUMBER($V$53),IF($V$53>=1.5,"CHEAP",IF($V$53>=0.5,"slightly cheap",IF($V$53<=-1.5,"RICH",IF($V$53<=-0.5,"slightly rich","fair")))),"") | X53: =SUMPRODUCT(--ISNUMBER((D53,G53,H53,I53,J53,K53))) | Y53: =IF(X53>=5,"HIGH",IF(X53>=3,"MED","LOW")) | Z53: =IF(AND(ISNUMBER(S53),X53>=$S$11),S53,"") | AA53: =IF(AND(ISNUMBER(R53),X53>=$S$11),R53,"")
B54: =Tickers!B46 | C54: =Tickers!C46 | D54: =Tickers!E46 | E54: =IFERROR(Tickers!G46,"") | F54: =IFERROR(Tickers!I46,"") | G54: =IFERROR(IF(ISNUMBER(Tickers!K46),Tickers!K46,IF(ISNUMBER(Haver!E46),Haver!E46,IF(ISNUMBER(Tickers!T46),Tickers!T46,""))),"") | H54: =IFERROR(IF(ISNUMBER(Tickers!M46),Tickers!M46,IF(ISNUMBER(Haver!G46),Haver!G46,IF(ISNUMBER(Tickers!U46),Tickers!U46,""))),"") | I54: =IFERROR(IF(ISNUMBER(Tickers!O46),Tickers!O46,IF(ISNUMBER(Haver!I46),Haver!I46,IF(ISNUMBER(Tickers!V46),Tickers!V46,""))),"") | J54: =IFERROR(IF(ISNUMBER(Tickers!Q46),Tickers!Q46,IF(ISNUMBER(Haver!K46),Haver!K46,IF(ISNUMBER(Tickers!W46),Tickers!W46,""))),"") | K54: =IFERROR(IF(ISNUMBER(Tickers!S46),Tickers!S46,IF(ISNUMBER(Haver!M46),Haver!M46,IF(ISNUMBER(Tickers!X46),Tickers!X46,""))),"") | L54: =IFERROR(($D$54-AVERAGE($D$15:$D$85))/STDEV($D$15:$D$85),"") | M54: =IFERROR(($I$54-AVERAGE($I$15:$I$85))/STDEV($I$15:$I$85),"") | N54: =IFERROR(-($J$54-AVERAGE($J$15:$J$85))/STDEV($J$15:$J$85),"") | O54: =IFERROR(-($K$54-AVERAGE($K$15:$K$85))/STDEV($K$15:$K$85),"") | P54: =IFERROR(-($G$54-AVERAGE($G$15:$G$85))/STDEV($G$15:$G$85),"") | Q54: =IFERROR(($H$54-AVERAGE($H$15:$H$85))/STDEV($H$15:$H$85),"") | R54: =IFERROR((IF(ISNUMBER(L54),$D$7*L54,0)+IF(ISNUMBER(M54),$D$8*M54,0)+IF(ISNUMBER(N54),$D$9*N54,0)+IF(ISNUMBER(O54),$D$10*O54,0)+IF(ISNUMBER(P54),$D$11*P54,0)+IF(ISNUMBER(Q54),$D$12*Q54,0))/(IF(ISNUMBER(L54),$D$7,0)+IF(ISNUMBER(M54),$D$8,0)+IF(ISNUMBER(N54),$D$9,0)+IF(ISNUMBER(O54),$D$10,0)+IF(ISNUMBER(P54),$D$11,0)+IF(ISNUMBER(Q54),$D$12,0)),"") | S54: =IFERROR(LN($E$54),"") | T54: =IFERROR($N$7+$N$8*$R$54,"") | U54: =IFERROR($S$54-$T$54,"") | V54: =IFERROR(($U$54-AVERAGE($U$15:$U$85))/STDEV($U$15:$U$85),"") | W54: =IF(ISNUMBER($V$54),IF($V$54>=1.5,"CHEAP",IF($V$54>=0.5,"slightly cheap",IF($V$54<=-1.5,"RICH",IF($V$54<=-0.5,"slightly rich","fair")))),"") | X54: =SUMPRODUCT(--ISNUMBER((D54,G54,H54,I54,J54,K54))) | Y54: =IF(X54>=5,"HIGH",IF(X54>=3,"MED","LOW")) | Z54: =IF(AND(ISNUMBER(S54),X54>=$S$11),S54,"") | AA54: =IF(AND(ISNUMBER(R54),X54>=$S$11),R54,"")
B55: =Tickers!B47 | C55: =Tickers!C47 | D55: =Tickers!E47 | E55: =IFERROR(Tickers!G47,"") | F55: =IFERROR(Tickers!I47,"") | G55: =IFERROR(IF(ISNUMBER(Tickers!K47),Tickers!K47,IF(ISNUMBER(Haver!E47),Haver!E47,IF(ISNUMBER(Tickers!T47),Tickers!T47,""))),"") | H55: =IFERROR(IF(ISNUMBER(Tickers!M47),Tickers!M47,IF(ISNUMBER(Haver!G47),Haver!G47,IF(ISNUMBER(Tickers!U47),Tickers!U47,""))),"") | I55: =IFERROR(IF(ISNUMBER(Tickers!O47),Tickers!O47,IF(ISNUMBER(Haver!I47),Haver!I47,IF(ISNUMBER(Tickers!V47),Tickers!V47,""))),"") | J55: =IFERROR(IF(ISNUMBER(Tickers!Q47),Tickers!Q47,IF(ISNUMBER(Haver!K47),Haver!K47,IF(ISNUMBER(Tickers!W47),Tickers!W47,""))),"") | K55: =IFERROR(IF(ISNUMBER(Tickers!S47),Tickers!S47,IF(ISNUMBER(Haver!M47),Haver!M47,IF(ISNUMBER(Tickers!X47),Tickers!X47,""))),"") | L55: =IFERROR(($D$55-AVERAGE($D$15:$D$85))/STDEV($D$15:$D$85),"") | M55: =IFERROR(($I$55-AVERAGE($I$15:$I$85))/STDEV($I$15:$I$85),"") | N55: =IFERROR(-($J$55-AVERAGE($J$15:$J$85))/STDEV($J$15:$J$85),"") | O55: =IFERROR(-($K$55-AVERAGE($K$15:$K$85))/STDEV($K$15:$K$85),"") | P55: =IFERROR(-($G$55-AVERAGE($G$15:$G$85))/STDEV($G$15:$G$85),"") | Q55: =IFERROR(($H$55-AVERAGE($H$15:$H$85))/STDEV($H$15:$H$85),"") | R55: =IFERROR((IF(ISNUMBER(L55),$D$7*L55,0)+IF(ISNUMBER(M55),$D$8*M55,0)+IF(ISNUMBER(N55),$D$9*N55,0)+IF(ISNUMBER(O55),$D$10*O55,0)+IF(ISNUMBER(P55),$D$11*P55,0)+IF(ISNUMBER(Q55),$D$12*Q55,0))/(IF(ISNUMBER(L55),$D$7,0)+IF(ISNUMBER(M55),$D$8,0)+IF(ISNUMBER(N55),$D$9,0)+IF(ISNUMBER(O55),$D$10,0)+IF(ISNUMBER(P55),$D$11,0)+IF(ISNUMBER(Q55),$D$12,0)),"") | S55: =IFERROR(LN($E$55),"") | T55: =IFERROR($N$7+$N$8*$R$55,"") | U55: =IFERROR($S$55-$T$55,"") | V55: =IFERROR(($U$55-AVERAGE($U$15:$U$85))/STDEV($U$15:$U$85),"") | W55: =IF(ISNUMBER($V$55),IF($V$55>=1.5,"CHEAP",IF($V$55>=0.5,"slightly cheap",IF($V$55<=-1.5,"RICH",IF($V$55<=-0.5,"slightly rich","fair")))),"") | X55: =SUMPRODUCT(--ISNUMBER((D55,G55,H55,I55,J55,K55))) | Y55: =IF(X55>=5,"HIGH",IF(X55>=3,"MED","LOW")) | Z55: =IF(AND(ISNUMBER(S55),X55>=$S$11),S55,"") | AA55: =IF(AND(ISNUMBER(R55),X55>=$S$11),R55,"")
B56: =Tickers!B48 | C56: =Tickers!C48 | D56: =Tickers!E48 | E56: =IFERROR(Tickers!G48,"") | F56: =IFERROR(Tickers!I48,"") | G56: =IFERROR(IF(ISNUMBER(Tickers!K48),Tickers!K48,IF(ISNUMBER(Haver!E48),Haver!E48,IF(ISNUMBER(Tickers!T48),Tickers!T48,""))),"") | H56: =IFERROR(IF(ISNUMBER(Tickers!M48),Tickers!M48,IF(ISNUMBER(Haver!G48),Haver!G48,IF(ISNUMBER(Tickers!U48),Tickers!U48,""))),"") | I56: =IFERROR(IF(ISNUMBER(Tickers!O48),Tickers!O48,IF(ISNUMBER(Haver!I48),Haver!I48,IF(ISNUMBER(Tickers!V48),Tickers!V48,""))),"") | J56: =IFERROR(IF(ISNUMBER(Tickers!Q48),Tickers!Q48,IF(ISNUMBER(Haver!K48),Haver!K48,IF(ISNUMBER(Tickers!W48),Tickers!W48,""))),"") | K56: =IFERROR(IF(ISNUMBER(Tickers!S48),Tickers!S48,IF(ISNUMBER(Haver!M48),Haver!M48,IF(ISNUMBER(Tickers!X48),Tickers!X48,""))),"") | L56: =IFERROR(($D$56-AVERAGE($D$15:$D$85))/STDEV($D$15:$D$85),"") | M56: =IFERROR(($I$56-AVERAGE($I$15:$I$85))/STDEV($I$15:$I$85),"") | N56: =IFERROR(-($J$56-AVERAGE($J$15:$J$85))/STDEV($J$15:$J$85),"") | O56: =IFERROR(-($K$56-AVERAGE($K$15:$K$85))/STDEV($K$15:$K$85),"") | P56: =IFERROR(-($G$56-AVERAGE($G$15:$G$85))/STDEV($G$15:$G$85),"") | Q56: =IFERROR(($H$56-AVERAGE($H$15:$H$85))/STDEV($H$15:$H$85),"") | R56: =IFERROR((IF(ISNUMBER(L56),$D$7*L56,0)+IF(ISNUMBER(M56),$D$8*M56,0)+IF(ISNUMBER(N56),$D$9*N56,0)+IF(ISNUMBER(O56),$D$10*O56,0)+IF(ISNUMBER(P56),$D$11*P56,0)+IF(ISNUMBER(Q56),$D$12*Q56,0))/(IF(ISNUMBER(L56),$D$7,0)+IF(ISNUMBER(M56),$D$8,0)+IF(ISNUMBER(N56),$D$9,0)+IF(ISNUMBER(O56),$D$10,0)+IF(ISNUMBER(P56),$D$11,0)+IF(ISNUMBER(Q56),$D$12,0)),"") | S56: =IFERROR(LN($E$56),"") | T56: =IFERROR($N$7+$N$8*$R$56,"") | U56: =IFERROR($S$56-$T$56,"") | V56: =IFERROR(($U$56-AVERAGE($U$15:$U$85))/STDEV($U$15:$U$85),"") | W56: =IF(ISNUMBER($V$56),IF($V$56>=1.5,"CHEAP",IF($V$56>=0.5,"slightly cheap",IF($V$56<=-1.5,"RICH",IF($V$56<=-0.5,"slightly rich","fair")))),"") | X56: =SUMPRODUCT(--ISNUMBER((D56,G56,H56,I56,J56,K56))) | Y56: =IF(X56>=5,"HIGH",IF(X56>=3,"MED","LOW")) | Z56: =IF(AND(ISNUMBER(S56),X56>=$S$11),S56,"") | AA56: =IF(AND(ISNUMBER(R56),X56>=$S$11),R56,"")
B57: =Tickers!B49 | C57: =Tickers!C49 | D57: =Tickers!E49 | E57: =IFERROR(Tickers!G49,"") | F57: =IFERROR(Tickers!I49,"") | G57: =IFERROR(IF(ISNUMBER(Tickers!K49),Tickers!K49,IF(ISNUMBER(Haver!E49),Haver!E49,IF(ISNUMBER(Tickers!T49),Tickers!T49,""))),"") | H57: =IFERROR(IF(ISNUMBER(Tickers!M49),Tickers!M49,IF(ISNUMBER(Haver!G49),Haver!G49,IF(ISNUMBER(Tickers!U49),Tickers!U49,""))),"") | I57: =IFERROR(IF(ISNUMBER(Tickers!O49),Tickers!O49,IF(ISNUMBER(Haver!I49),Haver!I49,IF(ISNUMBER(Tickers!V49),Tickers!V49,""))),"") | J57: =IFERROR(IF(ISNUMBER(Tickers!Q49),Tickers!Q49,IF(ISNUMBER(Haver!K49),Haver!K49,IF(ISNUMBER(Tickers!W49),Tickers!W49,""))),"") | K57: =IFERROR(IF(ISNUMBER(Tickers!S49),Tickers!S49,IF(ISNUMBER(Haver!M49),Haver!M49,IF(ISNUMBER(Tickers!X49),Tickers!X49,""))),"") | L57: =IFERROR(($D$57-AVERAGE($D$15:$D$85))/STDEV($D$15:$D$85),"") | M57: =IFERROR(($I$57-AVERAGE($I$15:$I$85))/STDEV($I$15:$I$85),"") | N57: =IFERROR(-($J$57-AVERAGE($J$15:$J$85))/STDEV($J$15:$J$85),"") | O57: =IFERROR(-($K$57-AVERAGE($K$15:$K$85))/STDEV($K$15:$K$85),"") | P57: =IFERROR(-($G$57-AVERAGE($G$15:$G$85))/STDEV($G$15:$G$85),"") | Q57: =IFERROR(($H$57-AVERAGE($H$15:$H$85))/STDEV($H$15:$H$85),"") | R57: =IFERROR((IF(ISNUMBER(L57),$D$7*L57,0)+IF(ISNUMBER(M57),$D$8*M57,0)+IF(ISNUMBER(N57),$D$9*N57,0)+IF(ISNUMBER(O57),$D$10*O57,0)+IF(ISNUMBER(P57),$D$11*P57,0)+IF(ISNUMBER(Q57),$D$12*Q57,0))/(IF(ISNUMBER(L57),$D$7,0)+IF(ISNUMBER(M57),$D$8,0)+IF(ISNUMBER(N57),$D$9,0)+IF(ISNUMBER(O57),$D$10,0)+IF(ISNUMBER(P57),$D$11,0)+IF(ISNUMBER(Q57),$D$12,0)),"") | S57: =IFERROR(LN($E$57),"") | T57: =IFERROR($N$7+$N$8*$R$57,"") | U57: =IFERROR($S$57-$T$57,"") | V57: =IFERROR(($U$57-AVERAGE($U$15:$U$85))/STDEV($U$15:$U$85),"") | W57: =IF(ISNUMBER($V$57),IF($V$57>=1.5,"CHEAP",IF($V$57>=0.5,"slightly cheap",IF($V$57<=-1.5,"RICH",IF($V$57<=-0.5,"slightly rich","fair")))),"") | X57: =SUMPRODUCT(--ISNUMBER((D57,G57,H57,I57,J57,K57))) | Y57: =IF(X57>=5,"HIGH",IF(X57>=3,"MED","LOW")) | Z57: =IF(AND(ISNUMBER(S57),X57>=$S$11),S57,"") | AA57: =IF(AND(ISNUMBER(R57),X57>=$S$11),R57,"")
B58: =Tickers!B50 | C58: =Tickers!C50 | D58: =Tickers!E50 | E58: =IFERROR(Tickers!G50,"") | F58: =IFERROR(Tickers!I50,"") | G58: =IFERROR(IF(ISNUMBER(Tickers!K50),Tickers!K50,IF(ISNUMBER(Haver!E50),Haver!E50,IF(ISNUMBER(Tickers!T50),Tickers!T50,""))),"") | H58: =IFERROR(IF(ISNUMBER(Tickers!M50),Tickers!M50,IF(ISNUMBER(Haver!G50),Haver!G50,IF(ISNUMBER(Tickers!U50),Tickers!U50,""))),"") | I58: =IFERROR(IF(ISNUMBER(Tickers!O50),Tickers!O50,IF(ISNUMBER(Haver!I50),Haver!I50,IF(ISNUMBER(Tickers!V50),Tickers!V50,""))),"") | J58: =IFERROR(IF(ISNUMBER(Tickers!Q50),Tickers!Q50,IF(ISNUMBER(Haver!K50),Haver!K50,IF(ISNUMBER(Tickers!W50),Tickers!W50,""))),"") | K58: =IFERROR(IF(ISNUMBER(Tickers!S50),Tickers!S50,IF(ISNUMBER(Haver!M50),Haver!M50,IF(ISNUMBER(Tickers!X50),Tickers!X50,""))),"") | L58: =IFERROR(($D$58-AVERAGE($D$15:$D$85))/STDEV($D$15:$D$85),"") | M58: =IFERROR(($I$58-AVERAGE($I$15:$I$85))/STDEV($I$15:$I$85),"") | N58: =IFERROR(-($J$58-AVERAGE($J$15:$J$85))/STDEV($J$15:$J$85),"") | O58: =IFERROR(-($K$58-AVERAGE($K$15:$K$85))/STDEV($K$15:$K$85),"") | P58: =IFERROR(-($G$58-AVERAGE($G$15:$G$85))/STDEV($G$15:$G$85),"") | Q58: =IFERROR(($H$58-AVERAGE($H$15:$H$85))/STDEV($H$15:$H$85),"") | R58: =IFERROR((IF(ISNUMBER(L58),$D$7*L58,0)+IF(ISNUMBER(M58),$D$8*M58,0)+IF(ISNUMBER(N58),$D$9*N58,0)+IF(ISNUMBER(O58),$D$10*O58,0)+IF(ISNUMBER(P58),$D$11*P58,0)+IF(ISNUMBER(Q58),$D$12*Q58,0))/(IF(ISNUMBER(L58),$D$7,0)+IF(ISNUMBER(M58),$D$8,0)+IF(ISNUMBER(N58),$D$9,0)+IF(ISNUMBER(O58),$D$10,0)+IF(ISNUMBER(P58),$D$11,0)+IF(ISNUMBER(Q58),$D$12,0)),"") | S58: =IFERROR(LN($E$58),"") | T58: =IFERROR($N$7+$N$8*$R$58,"") | U58: =IFERROR($S$58-$T$58,"") | V58: =IFERROR(($U$58-AVERAGE($U$15:$U$85))/STDEV($U$15:$U$85),"") | W58: =IF(ISNUMBER($V$58),IF($V$58>=1.5,"CHEAP",IF($V$58>=0.5,"slightly cheap",IF($V$58<=-1.5,"RICH",IF($V$58<=-0.5,"slightly rich","fair")))),"") | X58: =SUMPRODUCT(--ISNUMBER((D58,G58,H58,I58,J58,K58))) | Y58: =IF(X58>=5,"HIGH",IF(X58>=3,"MED","LOW")) | Z58: =IF(AND(ISNUMBER(S58),X58>=$S$11),S58,"") | AA58: =IF(AND(ISNUMBER(R58),X58>=$S$11),R58,"")
B59: =Tickers!B51 | C59: =Tickers!C51 | D59: =Tickers!E51 | E59: =IFERROR(Tickers!G51,"") | F59: =IFERROR(Tickers!I51,"") | G59: =IFERROR(IF(ISNUMBER(Tickers!K51),Tickers!K51,IF(ISNUMBER(Haver!E51),Haver!E51,IF(ISNUMBER(Tickers!T51),Tickers!T51,""))),"") | H59: =IFERROR(IF(ISNUMBER(Tickers!M51),Tickers!M51,IF(ISNUMBER(Haver!G51),Haver!G51,IF(ISNUMBER(Tickers!U51),Tickers!U51,""))),"") | I59: =IFERROR(IF(ISNUMBER(Tickers!O51),Tickers!O51,IF(ISNUMBER(Haver!I51),Haver!I51,IF(ISNUMBER(Tickers!V51),Tickers!V51,""))),"") | J59: =IFERROR(IF(ISNUMBER(Tickers!Q51),Tickers!Q51,IF(ISNUMBER(Haver!K51),Haver!K51,IF(ISNUMBER(Tickers!W51),Tickers!W51,""))),"") | K59: =IFERROR(IF(ISNUMBER(Tickers!S51),Tickers!S51,IF(ISNUMBER(Haver!M51),Haver!M51,IF(ISNUMBER(Tickers!X51),Tickers!X51,""))),"") | L59: =IFERROR(($D$59-AVERAGE($D$15:$D$85))/STDEV($D$15:$D$85),"") | M59: =IFERROR(($I$59-AVERAGE($I$15:$I$85))/STDEV($I$15:$I$85),"") | N59: =IFERROR(-($J$59-AVERAGE($J$15:$J$85))/STDEV($J$15:$J$85),"") | O59: =IFERROR(-($K$59-AVERAGE($K$15:$K$85))/STDEV($K$15:$K$85),"") | P59: =IFERROR(-($G$59-AVERAGE($G$15:$G$85))/STDEV($G$15:$G$85),"") | Q59: =IFERROR(($H$59-AVERAGE($H$15:$H$85))/STDEV($H$15:$H$85),"") | R59: =IFERROR((IF(ISNUMBER(L59),$D$7*L59,0)+IF(ISNUMBER(M59),$D$8*M59,0)+IF(ISNUMBER(N59),$D$9*N59,0)+IF(ISNUMBER(O59),$D$10*O59,0)+IF(ISNUMBER(P59),$D$11*P59,0)+IF(ISNUMBER(Q59),$D$12*Q59,0))/(IF(ISNUMBER(L59),$D$7,0)+IF(ISNUMBER(M59),$D$8,0)+IF(ISNUMBER(N59),$D$9,0)+IF(ISNUMBER(O59),$D$10,0)+IF(ISNUMBER(P59),$D$11,0)+IF(ISNUMBER(Q59),$D$12,0)),"") | S59: =IFERROR(LN($E$59),"") | T59: =IFERROR($N$7+$N$8*$R$59,"") | U59: =IFERROR($S$59-$T$59,"") | V59: =IFERROR(($U$59-AVERAGE($U$15:$U$85))/STDEV($U$15:$U$85),"") | W59: =IF(ISNUMBER($V$59),IF($V$59>=1.5,"CHEAP",IF($V$59>=0.5,"slightly cheap",IF($V$59<=-1.5,"RICH",IF($V$59<=-0.5,"slightly rich","fair")))),"") | X59: =SUMPRODUCT(--ISNUMBER((D59,G59,H59,I59,J59,K59))) | Y59: =IF(X59>=5,"HIGH",IF(X59>=3,"MED","LOW")) | Z59: =IF(AND(ISNUMBER(S59),X59>=$S$11),S59,"") | AA59: =IF(AND(ISNUMBER(R59),X59>=$S$11),R59,"")
B60: =Tickers!B52 | C60: =Tickers!C52 | D60: =Tickers!E52 | E60: =IFERROR(Tickers!G52,"") | F60: =IFERROR(Tickers!I52,"") | G60: =IFERROR(IF(ISNUMBER(Tickers!K52),Tickers!K52,IF(ISNUMBER(Haver!E52),Haver!E52,IF(ISNUMBER(Tickers!T52),Tickers!T52,""))),"") | H60: =IFERROR(IF(ISNUMBER(Tickers!M52),Tickers!M52,IF(ISNUMBER(Haver!G52),Haver!G52,IF(ISNUMBER(Tickers!U52),Tickers!U52,""))),"") | I60: =IFERROR(IF(ISNUMBER(Tickers!O52),Tickers!O52,IF(ISNUMBER(Haver!I52),Haver!I52,IF(ISNUMBER(Tickers!V52),Tickers!V52,""))),"") | J60: =IFERROR(IF(ISNUMBER(Tickers!Q52),Tickers!Q52,IF(ISNUMBER(Haver!K52),Haver!K52,IF(ISNUMBER(Tickers!W52),Tickers!W52,""))),"") | K60: =IFERROR(IF(ISNUMBER(Tickers!S52),Tickers!S52,IF(ISNUMBER(Haver!M52),Haver!M52,IF(ISNUMBER(Tickers!X52),Tickers!X52,""))),"") | L60: =IFERROR(($D$60-AVERAGE($D$15:$D$85))/STDEV($D$15:$D$85),"") | M60: =IFERROR(($I$60-AVERAGE($I$15:$I$85))/STDEV($I$15:$I$85),"") | N60: =IFERROR(-($J$60-AVERAGE($J$15:$J$85))/STDEV($J$15:$J$85),"") | O60: =IFERROR(-($K$60-AVERAGE($K$15:$K$85))/STDEV($K$15:$K$85),"") | P60: =IFERROR(-($G$60-AVERAGE($G$15:$G$85))/STDEV($G$15:$G$85),"") | Q60: =IFERROR(($H$60-AVERAGE($H$15:$H$85))/STDEV($H$15:$H$85),"") | R60: =IFERROR((IF(ISNUMBER(L60),$D$7*L60,0)+IF(ISNUMBER(M60),$D$8*M60,0)+IF(ISNUMBER(N60),$D$9*N60,0)+IF(ISNUMBER(O60),$D$10*O60,0)+IF(ISNUMBER(P60),$D$11*P60,0)+IF(ISNUMBER(Q60),$D$12*Q60,0))/(IF(ISNUMBER(L60),$D$7,0)+IF(ISNUMBER(M60),$D$8,0)+IF(ISNUMBER(N60),$D$9,0)+IF(ISNUMBER(O60),$D$10,0)+IF(ISNUMBER(P60),$D$11,0)+IF(ISNUMBER(Q60),$D$12,0)),"") | S60: =IFERROR(LN($E$60),"") | T60: =IFERROR($N$7+$N$8*$R$60,"") | U60: =IFERROR($S$60-$T$60,"") | V60: =IFERROR(($U$60-AVERAGE($U$15:$U$85))/STDEV($U$15:$U$85),"") | W60: =IF(ISNUMBER($V$60),IF($V$60>=1.5,"CHEAP",IF($V$60>=0.5,"slightly cheap",IF($V$60<=-1.5,"RICH",IF($V$60<=-0.5,"slightly rich","fair")))),"") | X60: =SUMPRODUCT(--ISNUMBER((D60,G60,H60,I60,J60,K60))) | Y60: =IF(X60>=5,"HIGH",IF(X60>=3,"MED","LOW")) | Z60: =IF(AND(ISNUMBER(S60),X60>=$S$11),S60,"") | AA60: =IF(AND(ISNUMBER(R60),X60>=$S$11),R60,"")
B61: =Tickers!B53 | C61: =Tickers!C53 | D61: =Tickers!E53 | E61: =IFERROR(Tickers!G53,"") | F61: =IFERROR(Tickers!I53,"") | G61: =IFERROR(IF(ISNUMBER(Tickers!K53),Tickers!K53,IF(ISNUMBER(Haver!E53),Haver!E53,IF(ISNUMBER(Tickers!T53),Tickers!T53,""))),"") | H61: =IFERROR(IF(ISNUMBER(Tickers!M53),Tickers!M53,IF(ISNUMBER(Haver!G53),Haver!G53,IF(ISNUMBER(Tickers!U53),Tickers!U53,""))),"") | I61: =IFERROR(IF(ISNUMBER(Tickers!O53),Tickers!O53,IF(ISNUMBER(Haver!I53),Haver!I53,IF(ISNUMBER(Tickers!V53),Tickers!V53,""))),"") | J61: =IFERROR(IF(ISNUMBER(Tickers!Q53),Tickers!Q53,IF(ISNUMBER(Haver!K53),Haver!K53,IF(ISNUMBER(Tickers!W53),Tickers!W53,""))),"") | K61: =IFERROR(IF(ISNUMBER(Tickers!S53),Tickers!S53,IF(ISNUMBER(Haver!M53),Haver!M53,IF(ISNUMBER(Tickers!X53),Tickers!X53,""))),"") | L61: =IFERROR(($D$61-AVERAGE($D$15:$D$85))/STDEV($D$15:$D$85),"") | M61: =IFERROR(($I$61-AVERAGE($I$15:$I$85))/STDEV($I$15:$I$85),"") | N61: =IFERROR(-($J$61-AVERAGE($J$15:$J$85))/STDEV($J$15:$J$85),"") | O61: =IFERROR(-($K$61-AVERAGE($K$15:$K$85))/STDEV($K$15:$K$85),"") | P61: =IFERROR(-($G$61-AVERAGE($G$15:$G$85))/STDEV($G$15:$G$85),"") | Q61: =IFERROR(($H$61-AVERAGE($H$15:$H$85))/STDEV($H$15:$H$85),"") | R61: =IFERROR((IF(ISNUMBER(L61),$D$7*L61,0)+IF(ISNUMBER(M61),$D$8*M61,0)+IF(ISNUMBER(N61),$D$9*N61,0)+IF(ISNUMBER(O61),$D$10*O61,0)+IF(ISNUMBER(P61),$D$11*P61,0)+IF(ISNUMBER(Q61),$D$12*Q61,0))/(IF(ISNUMBER(L61),$D$7,0)+IF(ISNUMBER(M61),$D$8,0)+IF(ISNUMBER(N61),$D$9,0)+IF(ISNUMBER(O61),$D$10,0)+IF(ISNUMBER(P61),$D$11,0)+IF(ISNUMBER(Q61),$D$12,0)),"") | S61: =IFERROR(LN($E$61),"") | T61: =IFERROR($N$7+$N$8*$R$61,"") | U61: =IFERROR($S$61-$T$61,"") | V61: =IFERROR(($U$61-AVERAGE($U$15:$U$85))/STDEV($U$15:$U$85),"") | W61: =IF(ISNUMBER($V$61),IF($V$61>=1.5,"CHEAP",IF($V$61>=0.5,"slightly cheap",IF($V$61<=-1.5,"RICH",IF($V$61<=-0.5,"slightly rich","fair")))),"") | X61: =SUMPRODUCT(--ISNUMBER((D61,G61,H61,I61,J61,K61))) | Y61: =IF(X61>=5,"HIGH",IF(X61>=3,"MED","LOW")) | Z61: =IF(AND(ISNUMBER(S61),X61>=$S$11),S61,"") | AA61: =IF(AND(ISNUMBER(R61),X61>=$S$11),R61,"")
B62: =Tickers!B54 | C62: =Tickers!C54 | D62: =Tickers!E54 | E62: =IFERROR(Tickers!G54,"") | F62: =IFERROR(Tickers!I54,"") | G62: =IFERROR(IF(ISNUMBER(Tickers!K54),Tickers!K54,IF(ISNUMBER(Haver!E54),Haver!E54,IF(ISNUMBER(Tickers!T54),Tickers!T54,""))),"") | H62: =IFERROR(IF(ISNUMBER(Tickers!M54),Tickers!M54,IF(ISNUMBER(Haver!G54),Haver!G54,IF(ISNUMBER(Tickers!U54),Tickers!U54,""))),"") | I62: =IFERROR(IF(ISNUMBER(Tickers!O54),Tickers!O54,IF(ISNUMBER(Haver!I54),Haver!I54,IF(ISNUMBER(Tickers!V54),Tickers!V54,""))),"") | J62: =IFERROR(IF(ISNUMBER(Tickers!Q54),Tickers!Q54,IF(ISNUMBER(Haver!K54),Haver!K54,IF(ISNUMBER(Tickers!W54),Tickers!W54,""))),"") | K62: =IFERROR(IF(ISNUMBER(Tickers!S54),Tickers!S54,IF(ISNUMBER(Haver!M54),Haver!M54,IF(ISNUMBER(Tickers!X54),Tickers!X54,""))),"") | L62: =IFERROR(($D$62-AVERAGE($D$15:$D$85))/STDEV($D$15:$D$85),"") | M62: =IFERROR(($I$62-AVERAGE($I$15:$I$85))/STDEV($I$15:$I$85),"") | N62: =IFERROR(-($J$62-AVERAGE($J$15:$J$85))/STDEV($J$15:$J$85),"") | O62: =IFERROR(-($K$62-AVERAGE($K$15:$K$85))/STDEV($K$15:$K$85),"") | P62: =IFERROR(-($G$62-AVERAGE($G$15:$G$85))/STDEV($G$15:$G$85),"") | Q62: =IFERROR(($H$62-AVERAGE($H$15:$H$85))/STDEV($H$15:$H$85),"") | R62: =IFERROR((IF(ISNUMBER(L62),$D$7*L62,0)+IF(ISNUMBER(M62),$D$8*M62,0)+IF(ISNUMBER(N62),$D$9*N62,0)+IF(ISNUMBER(O62),$D$10*O62,0)+IF(ISNUMBER(P62),$D$11*P62,0)+IF(ISNUMBER(Q62),$D$12*Q62,0))/(IF(ISNUMBER(L62),$D$7,0)+IF(ISNUMBER(M62),$D$8,0)+IF(ISNUMBER(N62),$D$9,0)+IF(ISNUMBER(O62),$D$10,0)+IF(ISNUMBER(P62),$D$11,0)+IF(ISNUMBER(Q62),$D$12,0)),"") | S62: =IFERROR(LN($E$62),"") | T62: =IFERROR($N$7+$N$8*$R$62,"") | U62: =IFERROR($S$62-$T$62,"") | V62: =IFERROR(($U$62-AVERAGE($U$15:$U$85))/STDEV($U$15:$U$85),"") | W62: =IF(ISNUMBER($V$62),IF($V$62>=1.5,"CHEAP",IF($V$62>=0.5,"slightly cheap",IF($V$62<=-1.5,"RICH",IF($V$62<=-0.5,"slightly rich","fair")))),"") | X62: =SUMPRODUCT(--ISNUMBER((D62,G62,H62,I62,J62,K62))) | Y62: =IF(X62>=5,"HIGH",IF(X62>=3,"MED","LOW")) | Z62: =IF(AND(ISNUMBER(S62),X62>=$S$11),S62,"") | AA62: =IF(AND(ISNUMBER(R62),X62>=$S$11),R62,"")
B63: =Tickers!B55 | C63: =Tickers!C55 | D63: =Tickers!E55 | E63: =IFERROR(Tickers!G55,"") | F63: =IFERROR(Tickers!I55,"") | G63: =IFERROR(IF(ISNUMBER(Tickers!K55),Tickers!K55,IF(ISNUMBER(Haver!E55),Haver!E55,IF(ISNUMBER(Tickers!T55),Tickers!T55,""))),"") | H63: =IFERROR(IF(ISNUMBER(Tickers!M55),Tickers!M55,IF(ISNUMBER(Haver!G55),Haver!G55,IF(ISNUMBER(Tickers!U55),Tickers!U55,""))),"") | I63: =IFERROR(IF(ISNUMBER(Tickers!O55),Tickers!O55,IF(ISNUMBER(Haver!I55),Haver!I55,IF(ISNUMBER(Tickers!V55),Tickers!V55,""))),"") | J63: =IFERROR(IF(ISNUMBER(Tickers!Q55),Tickers!Q55,IF(ISNUMBER(Haver!K55),Haver!K55,IF(ISNUMBER(Tickers!W55),Tickers!W55,""))),"") | K63: =IFERROR(IF(ISNUMBER(Tickers!S55),Tickers!S55,IF(ISNUMBER(Haver!M55),Haver!M55,IF(ISNUMBER(Tickers!X55),Tickers!X55,""))),"") | L63: =IFERROR(($D$63-AVERAGE($D$15:$D$85))/STDEV($D$15:$D$85),"") | M63: =IFERROR(($I$63-AVERAGE($I$15:$I$85))/STDEV($I$15:$I$85),"") | N63: =IFERROR(-($J$63-AVERAGE($J$15:$J$85))/STDEV($J$15:$J$85),"") | O63: =IFERROR(-($K$63-AVERAGE($K$15:$K$85))/STDEV($K$15:$K$85),"") | P63: =IFERROR(-($G$63-AVERAGE($G$15:$G$85))/STDEV($G$15:$G$85),"") | Q63: =IFERROR(($H$63-AVERAGE($H$15:$H$85))/STDEV($H$15:$H$85),"") | R63: =IFERROR((IF(ISNUMBER(L63),$D$7*L63,0)+IF(ISNUMBER(M63),$D$8*M63,0)+IF(ISNUMBER(N63),$D$9*N63,0)+IF(ISNUMBER(O63),$D$10*O63,0)+IF(ISNUMBER(P63),$D$11*P63,0)+IF(ISNUMBER(Q63),$D$12*Q63,0))/(IF(ISNUMBER(L63),$D$7,0)+IF(ISNUMBER(M63),$D$8,0)+IF(ISNUMBER(N63),$D$9,0)+IF(ISNUMBER(O63),$D$10,0)+IF(ISNUMBER(P63),$D$11,0)+IF(ISNUMBER(Q63),$D$12,0)),"") | S63: =IFERROR(LN($E$63),"") | T63: =IFERROR($N$7+$N$8*$R$63,"") | U63: =IFERROR($S$63-$T$63,"") | V63: =IFERROR(($U$63-AVERAGE($U$15:$U$85))/STDEV($U$15:$U$85),"") | W63: =IF(ISNUMBER($V$63),IF($V$63>=1.5,"CHEAP",IF($V$63>=0.5,"slightly cheap",IF($V$63<=-1.5,"RICH",IF($V$63<=-0.5,"slightly rich","fair")))),"") | X63: =SUMPRODUCT(--ISNUMBER((D63,G63,H63,I63,J63,K63))) | Y63: =IF(X63>=5,"HIGH",IF(X63>=3,"MED","LOW")) | Z63: =IF(AND(ISNUMBER(S63),X63>=$S$11),S63,"") | AA63: =IF(AND(ISNUMBER(R63),X63>=$S$11),R63,"")
B64: =Tickers!B56 | C64: =Tickers!C56 | D64: =Tickers!E56 | E64: =IFERROR(Tickers!G56,"") | F64: =IFERROR(Tickers!I56,"") | G64: =IFERROR(IF(ISNUMBER(Tickers!K56),Tickers!K56,IF(ISNUMBER(Haver!E56),Haver!E56,IF(ISNUMBER(Tickers!T56),Tickers!T56,""))),"") | H64: =IFERROR(IF(ISNUMBER(Tickers!M56),Tickers!M56,IF(ISNUMBER(Haver!G56),Haver!G56,IF(ISNUMBER(Tickers!U56),Tickers!U56,""))),"") | I64: =IFERROR(IF(ISNUMBER(Tickers!O56),Tickers!O56,IF(ISNUMBER(Haver!I56),Haver!I56,IF(ISNUMBER(Tickers!V56),Tickers!V56,""))),"") | J64: =IFERROR(IF(ISNUMBER(Tickers!Q56),Tickers!Q56,IF(ISNUMBER(Haver!K56),Haver!K56,IF(ISNUMBER(Tickers!W56),Tickers!W56,""))),"") | K64: =IFERROR(IF(ISNUMBER(Tickers!S56),Tickers!S56,IF(ISNUMBER(Haver!M56),Haver!M56,IF(ISNUMBER(Tickers!X56),Tickers!X56,""))),"") | L64: =IFERROR(($D$64-AVERAGE($D$15:$D$85))/STDEV($D$15:$D$85),"") | M64: =IFERROR(($I$64-AVERAGE($I$15:$I$85))/STDEV($I$15:$I$85),"") | N64: =IFERROR(-($J$64-AVERAGE($J$15:$J$85))/STDEV($J$15:$J$85),"") | O64: =IFERROR(-($K$64-AVERAGE($K$15:$K$85))/STDEV($K$15:$K$85),"") | P64: =IFERROR(-($G$64-AVERAGE($G$15:$G$85))/STDEV($G$15:$G$85),"") | Q64: =IFERROR(($H$64-AVERAGE($H$15:$H$85))/STDEV($H$15:$H$85),"") | R64: =IFERROR((IF(ISNUMBER(L64),$D$7*L64,0)+IF(ISNUMBER(M64),$D$8*M64,0)+IF(ISNUMBER(N64),$D$9*N64,0)+IF(ISNUMBER(O64),$D$10*O64,0)+IF(ISNUMBER(P64),$D$11*P64,0)+IF(ISNUMBER(Q64),$D$12*Q64,0))/(IF(ISNUMBER(L64),$D$7,0)+IF(ISNUMBER(M64),$D$8,0)+IF(ISNUMBER(N64),$D$9,0)+IF(ISNUMBER(O64),$D$10,0)+IF(ISNUMBER(P64),$D$11,0)+IF(ISNUMBER(Q64),$D$12,0)),"") | S64: =IFERROR(LN($E$64),"") | T64: =IFERROR($N$7+$N$8*$R$64,"") | U64: =IFERROR($S$64-$T$64,"") | V64: =IFERROR(($U$64-AVERAGE($U$15:$U$85))/STDEV($U$15:$U$85),"") | W64: =IF(ISNUMBER($V$64),IF($V$64>=1.5,"CHEAP",IF($V$64>=0.5,"slightly cheap",IF($V$64<=-1.5,"RICH",IF($V$64<=-0.5,"slightly rich","fair")))),"") | X64: =SUMPRODUCT(--ISNUMBER((D64,G64,H64,I64,J64,K64))) | Y64: =IF(X64>=5,"HIGH",IF(X64>=3,"MED","LOW")) | Z64: =IF(AND(ISNUMBER(S64),X64>=$S$11),S64,"") | AA64: =IF(AND(ISNUMBER(R64),X64>=$S$11),R64,"")
B65: =Tickers!B57 | C65: =Tickers!C57 | D65: =Tickers!E57 | E65: =IFERROR(Tickers!G57,"") | F65: =IFERROR(Tickers!I57,"") | G65: =IFERROR(IF(ISNUMBER(Tickers!K57),Tickers!K57,IF(ISNUMBER(Haver!E57),Haver!E57,IF(ISNUMBER(Tickers!T57),Tickers!T57,""))),"") | H65: =IFERROR(IF(ISNUMBER(Tickers!M57),Tickers!M57,IF(ISNUMBER(Haver!G57),Haver!G57,IF(ISNUMBER(Tickers!U57),Tickers!U57,""))),"") | I65: =IFERROR(IF(ISNUMBER(Tickers!O57),Tickers!O57,IF(ISNUMBER(Haver!I57),Haver!I57,IF(ISNUMBER(Tickers!V57),Tickers!V57,""))),"") | J65: =IFERROR(IF(ISNUMBER(Tickers!Q57),Tickers!Q57,IF(ISNUMBER(Haver!K57),Haver!K57,IF(ISNUMBER(Tickers!W57),Tickers!W57,""))),"") | K65: =IFERROR(IF(ISNUMBER(Tickers!S57),Tickers!S57,IF(ISNUMBER(Haver!M57),Haver!M57,IF(ISNUMBER(Tickers!X57),Tickers!X57,""))),"") | L65: =IFERROR(($D$65-AVERAGE($D$15:$D$85))/STDEV($D$15:$D$85),"") | M65: =IFERROR(($I$65-AVERAGE($I$15:$I$85))/STDEV($I$15:$I$85),"") | N65: =IFERROR(-($J$65-AVERAGE($J$15:$J$85))/STDEV($J$15:$J$85),"") | O65: =IFERROR(-($K$65-AVERAGE($K$15:$K$85))/STDEV($K$15:$K$85),"") | P65: =IFERROR(-($G$65-AVERAGE($G$15:$G$85))/STDEV($G$15:$G$85),"") | Q65: =IFERROR(($H$65-AVERAGE($H$15:$H$85))/STDEV($H$15:$H$85),"") | R65: =IFERROR((IF(ISNUMBER(L65),$D$7*L65,0)+IF(ISNUMBER(M65),$D$8*M65,0)+IF(ISNUMBER(N65),$D$9*N65,0)+IF(ISNUMBER(O65),$D$10*O65,0)+IF(ISNUMBER(P65),$D$11*P65,0)+IF(ISNUMBER(Q65),$D$12*Q65,0))/(IF(ISNUMBER(L65),$D$7,0)+IF(ISNUMBER(M65),$D$8,0)+IF(ISNUMBER(N65),$D$9,0)+IF(ISNUMBER(O65),$D$10,0)+IF(ISNUMBER(P65),$D$11,0)+IF(ISNUMBER(Q65),$D$12,0)),"") | S65: =IFERROR(LN($E$65),"") | T65: =IFERROR($N$7+$N$8*$R$65,"") | U65: =IFERROR($S$65-$T$65,"") | V65: =IFERROR(($U$65-AVERAGE($U$15:$U$85))/STDEV($U$15:$U$85),"") | W65: =IF(ISNUMBER($V$65),IF($V$65>=1.5,"CHEAP",IF($V$65>=0.5,"slightly cheap",IF($V$65<=-1.5,"RICH",IF($V$65<=-0.5,"slightly rich","fair")))),"") | X65: =SUMPRODUCT(--ISNUMBER((D65,G65,H65,I65,J65,K65))) | Y65: =IF(X65>=5,"HIGH",IF(X65>=3,"MED","LOW")) | Z65: =IF(AND(ISNUMBER(S65),X65>=$S$11),S65,"") | AA65: =IF(AND(ISNUMBER(R65),X65>=$S$11),R65,"")
B66: =Tickers!B58 | C66: =Tickers!C58 | D66: =Tickers!E58 | E66: =IFERROR(Tickers!G58,"") | F66: =IFERROR(Tickers!I58,"") | G66: =IFERROR(IF(ISNUMBER(Tickers!K58),Tickers!K58,IF(ISNUMBER(Haver!E58),Haver!E58,IF(ISNUMBER(Tickers!T58),Tickers!T58,""))),"") | H66: =IFERROR(IF(ISNUMBER(Tickers!M58),Tickers!M58,IF(ISNUMBER(Haver!G58),Haver!G58,IF(ISNUMBER(Tickers!U58),Tickers!U58,""))),"") | I66: =IFERROR(IF(ISNUMBER(Tickers!O58),Tickers!O58,IF(ISNUMBER(Haver!I58),Haver!I58,IF(ISNUMBER(Tickers!V58),Tickers!V58,""))),"") | J66: =IFERROR(IF(ISNUMBER(Tickers!Q58),Tickers!Q58,IF(ISNUMBER(Haver!K58),Haver!K58,IF(ISNUMBER(Tickers!W58),Tickers!W58,""))),"") | K66: =IFERROR(IF(ISNUMBER(Tickers!S58),Tickers!S58,IF(ISNUMBER(Haver!M58),Haver!M58,IF(ISNUMBER(Tickers!X58),Tickers!X58,""))),"") | L66: =IFERROR(($D$66-AVERAGE($D$15:$D$85))/STDEV($D$15:$D$85),"") | M66: =IFERROR(($I$66-AVERAGE($I$15:$I$85))/STDEV($I$15:$I$85),"") | N66: =IFERROR(-($J$66-AVERAGE($J$15:$J$85))/STDEV($J$15:$J$85),"") | O66: =IFERROR(-($K$66-AVERAGE($K$15:$K$85))/STDEV($K$15:$K$85),"") | P66: =IFERROR(-($G$66-AVERAGE($G$15:$G$85))/STDEV($G$15:$G$85),"") | Q66: =IFERROR(($H$66-AVERAGE($H$15:$H$85))/STDEV($H$15:$H$85),"") | R66: =IFERROR((IF(ISNUMBER(L66),$D$7*L66,0)+IF(ISNUMBER(M66),$D$8*M66,0)+IF(ISNUMBER(N66),$D$9*N66,0)+IF(ISNUMBER(O66),$D$10*O66,0)+IF(ISNUMBER(P66),$D$11*P66,0)+IF(ISNUMBER(Q66),$D$12*Q66,0))/(IF(ISNUMBER(L66),$D$7,0)+IF(ISNUMBER(M66),$D$8,0)+IF(ISNUMBER(N66),$D$9,0)+IF(ISNUMBER(O66),$D$10,0)+IF(ISNUMBER(P66),$D$11,0)+IF(ISNUMBER(Q66),$D$12,0)),"") | S66: =IFERROR(LN($E$66),"") | T66: =IFERROR($N$7+$N$8*$R$66,"") | U66: =IFERROR($S$66-$T$66,"") | V66: =IFERROR(($U$66-AVERAGE($U$15:$U$85))/STDEV($U$15:$U$85),"") | W66: =IF(ISNUMBER($V$66),IF($V$66>=1.5,"CHEAP",IF($V$66>=0.5,"slightly cheap",IF($V$66<=-1.5,"RICH",IF($V$66<=-0.5,"slightly rich","fair")))),"") | X66: =SUMPRODUCT(--ISNUMBER((D66,G66,H66,I66,J66,K66))) | Y66: =IF(X66>=5,"HIGH",IF(X66>=3,"MED","LOW")) | Z66: =IF(AND(ISNUMBER(S66),X66>=$S$11),S66,"") | AA66: =IF(AND(ISNUMBER(R66),X66>=$S$11),R66,"")
B67: =Tickers!B59 | C67: =Tickers!C59 | D67: =Tickers!E59 | E67: =IFERROR(Tickers!G59,"") | F67: =IFERROR(Tickers!I59,"") | G67: =IFERROR(IF(ISNUMBER(Tickers!K59),Tickers!K59,IF(ISNUMBER(Haver!E59),Haver!E59,IF(ISNUMBER(Tickers!T59),Tickers!T59,""))),"") | H67: =IFERROR(IF(ISNUMBER(Tickers!M59),Tickers!M59,IF(ISNUMBER(Haver!G59),Haver!G59,IF(ISNUMBER(Tickers!U59),Tickers!U59,""))),"") | I67: =IFERROR(IF(ISNUMBER(Tickers!O59),Tickers!O59,IF(ISNUMBER(Haver!I59),Haver!I59,IF(ISNUMBER(Tickers!V59),Tickers!V59,""))),"") | J67: =IFERROR(IF(ISNUMBER(Tickers!Q59),Tickers!Q59,IF(ISNUMBER(Haver!K59),Haver!K59,IF(ISNUMBER(Tickers!W59),Tickers!W59,""))),"") | K67: =IFERROR(IF(ISNUMBER(Tickers!S59),Tickers!S59,IF(ISNUMBER(Haver!M59),Haver!M59,IF(ISNUMBER(Tickers!X59),Tickers!X59,""))),"") | L67: =IFERROR(($D$67-AVERAGE($D$15:$D$85))/STDEV($D$15:$D$85),"") | M67: =IFERROR(($I$67-AVERAGE($I$15:$I$85))/STDEV($I$15:$I$85),"") | N67: =IFERROR(-($J$67-AVERAGE($J$15:$J$85))/STDEV($J$15:$J$85),"") | O67: =IFERROR(-($K$67-AVERAGE($K$15:$K$85))/STDEV($K$15:$K$85),"") | P67: =IFERROR(-($G$67-AVERAGE($G$15:$G$85))/STDEV($G$15:$G$85),"") | Q67: =IFERROR(($H$67-AVERAGE($H$15:$H$85))/STDEV($H$15:$H$85),"") | R67: =IFERROR((IF(ISNUMBER(L67),$D$7*L67,0)+IF(ISNUMBER(M67),$D$8*M67,0)+IF(ISNUMBER(N67),$D$9*N67,0)+IF(ISNUMBER(O67),$D$10*O67,0)+IF(ISNUMBER(P67),$D$11*P67,0)+IF(ISNUMBER(Q67),$D$12*Q67,0))/(IF(ISNUMBER(L67),$D$7,0)+IF(ISNUMBER(M67),$D$8,0)+IF(ISNUMBER(N67),$D$9,0)+IF(ISNUMBER(O67),$D$10,0)+IF(ISNUMBER(P67),$D$11,0)+IF(ISNUMBER(Q67),$D$12,0)),"") | S67: =IFERROR(LN($E$67),"") | T67: =IFERROR($N$7+$N$8*$R$67,"") | U67: =IFERROR($S$67-$T$67,"") | V67: =IFERROR(($U$67-AVERAGE($U$15:$U$85))/STDEV($U$15:$U$85),"") | W67: =IF(ISNUMBER($V$67),IF($V$67>=1.5,"CHEAP",IF($V$67>=0.5,"slightly cheap",IF($V$67<=-1.5,"RICH",IF($V$67<=-0.5,"slightly rich","fair")))),"") | X67: =SUMPRODUCT(--ISNUMBER((D67,G67,H67,I67,J67,K67))) | Y67: =IF(X67>=5,"HIGH",IF(X67>=3,"MED","LOW")) | Z67: =IF(AND(ISNUMBER(S67),X67>=$S$11),S67,"") | AA67: =IF(AND(ISNUMBER(R67),X67>=$S$11),R67,"")
B68: =Tickers!B60 | C68: =Tickers!C60 | D68: =Tickers!E60 | E68: =IFERROR(Tickers!G60,"") | F68: =IFERROR(Tickers!I60,"") | G68: =IFERROR(IF(ISNUMBER(Tickers!K60),Tickers!K60,IF(ISNUMBER(Haver!E60),Haver!E60,IF(ISNUMBER(Tickers!T60),Tickers!T60,""))),"") | H68: =IFERROR(IF(ISNUMBER(Tickers!M60),Tickers!M60,IF(ISNUMBER(Haver!G60),Haver!G60,IF(ISNUMBER(Tickers!U60),Tickers!U60,""))),"") | I68: =IFERROR(IF(ISNUMBER(Tickers!O60),Tickers!O60,IF(ISNUMBER(Haver!I60),Haver!I60,IF(ISNUMBER(Tickers!V60),Tickers!V60,""))),"") | J68: =IFERROR(IF(ISNUMBER(Tickers!Q60),Tickers!Q60,IF(ISNUMBER(Haver!K60),Haver!K60,IF(ISNUMBER(Tickers!W60),Tickers!W60,""))),"") | K68: =IFERROR(IF(ISNUMBER(Tickers!S60),Tickers!S60,IF(ISNUMBER(Haver!M60),Haver!M60,IF(ISNUMBER(Tickers!X60),Tickers!X60,""))),"") | L68: =IFERROR(($D$68-AVERAGE($D$15:$D$85))/STDEV($D$15:$D$85),"") | M68: =IFERROR(($I$68-AVERAGE($I$15:$I$85))/STDEV($I$15:$I$85),"") | N68: =IFERROR(-($J$68-AVERAGE($J$15:$J$85))/STDEV($J$15:$J$85),"") | O68: =IFERROR(-($K$68-AVERAGE($K$15:$K$85))/STDEV($K$15:$K$85),"") | P68: =IFERROR(-($G$68-AVERAGE($G$15:$G$85))/STDEV($G$15:$G$85),"") | Q68: =IFERROR(($H$68-AVERAGE($H$15:$H$85))/STDEV($H$15:$H$85),"") | R68: =IFERROR((IF(ISNUMBER(L68),$D$7*L68,0)+IF(ISNUMBER(M68),$D$8*M68,0)+IF(ISNUMBER(N68),$D$9*N68,0)+IF(ISNUMBER(O68),$D$10*O68,0)+IF(ISNUMBER(P68),$D$11*P68,0)+IF(ISNUMBER(Q68),$D$12*Q68,0))/(IF(ISNUMBER(L68),$D$7,0)+IF(ISNUMBER(M68),$D$8,0)+IF(ISNUMBER(N68),$D$9,0)+IF(ISNUMBER(O68),$D$10,0)+IF(ISNUMBER(P68),$D$11,0)+IF(ISNUMBER(Q68),$D$12,0)),"") | S68: =IFERROR(LN($E$68),"") | T68: =IFERROR($N$7+$N$8*$R$68,"") | U68: =IFERROR($S$68-$T$68,"") | V68: =IFERROR(($U$68-AVERAGE($U$15:$U$85))/STDEV($U$15:$U$85),"") | W68: =IF(ISNUMBER($V$68),IF($V$68>=1.5,"CHEAP",IF($V$68>=0.5,"slightly cheap",IF($V$68<=-1.5,"RICH",IF($V$68<=-0.5,"slightly rich","fair")))),"") | X68: =SUMPRODUCT(--ISNUMBER((D68,G68,H68,I68,J68,K68))) | Y68: =IF(X68>=5,"HIGH",IF(X68>=3,"MED","LOW")) | Z68: =IF(AND(ISNUMBER(S68),X68>=$S$11),S68,"") | AA68: =IF(AND(ISNUMBER(R68),X68>=$S$11),R68,"")
B69: =Tickers!B61 | C69: =Tickers!C61 | D69: =Tickers!E61 | E69: =IFERROR(Tickers!G61,"") | F69: =IFERROR(Tickers!I61,"") | G69: =IFERROR(IF(ISNUMBER(Tickers!K61),Tickers!K61,IF(ISNUMBER(Haver!E61),Haver!E61,IF(ISNUMBER(Tickers!T61),Tickers!T61,""))),"") | H69: =IFERROR(IF(ISNUMBER(Tickers!M61),Tickers!M61,IF(ISNUMBER(Haver!G61),Haver!G61,IF(ISNUMBER(Tickers!U61),Tickers!U61,""))),"") | I69: =IFERROR(IF(ISNUMBER(Tickers!O61),Tickers!O61,IF(ISNUMBER(Haver!I61),Haver!I61,IF(ISNUMBER(Tickers!V61),Tickers!V61,""))),"") | J69: =IFERROR(IF(ISNUMBER(Tickers!Q61),Tickers!Q61,IF(ISNUMBER(Haver!K61),Haver!K61,IF(ISNUMBER(Tickers!W61),Tickers!W61,""))),"") | K69: =IFERROR(IF(ISNUMBER(Tickers!S61),Tickers!S61,IF(ISNUMBER(Haver!M61),Haver!M61,IF(ISNUMBER(Tickers!X61),Tickers!X61,""))),"") | L69: =IFERROR(($D$69-AVERAGE($D$15:$D$85))/STDEV($D$15:$D$85),"") | M69: =IFERROR(($I$69-AVERAGE($I$15:$I$85))/STDEV($I$15:$I$85),"") | N69: =IFERROR(-($J$69-AVERAGE($J$15:$J$85))/STDEV($J$15:$J$85),"") | O69: =IFERROR(-($K$69-AVERAGE($K$15:$K$85))/STDEV($K$15:$K$85),"") | P69: =IFERROR(-($G$69-AVERAGE($G$15:$G$85))/STDEV($G$15:$G$85),"") | Q69: =IFERROR(($H$69-AVERAGE($H$15:$H$85))/STDEV($H$15:$H$85),"") | R69: =IFERROR((IF(ISNUMBER(L69),$D$7*L69,0)+IF(ISNUMBER(M69),$D$8*M69,0)+IF(ISNUMBER(N69),$D$9*N69,0)+IF(ISNUMBER(O69),$D$10*O69,0)+IF(ISNUMBER(P69),$D$11*P69,0)+IF(ISNUMBER(Q69),$D$12*Q69,0))/(IF(ISNUMBER(L69),$D$7,0)+IF(ISNUMBER(M69),$D$8,0)+IF(ISNUMBER(N69),$D$9,0)+IF(ISNUMBER(O69),$D$10,0)+IF(ISNUMBER(P69),$D$11,0)+IF(ISNUMBER(Q69),$D$12,0)),"") | S69: =IFERROR(LN($E$69),"") | T69: =IFERROR($N$7+$N$8*$R$69,"") | U69: =IFERROR($S$69-$T$69,"") | V69: =IFERROR(($U$69-AVERAGE($U$15:$U$85))/STDEV($U$15:$U$85),"") | W69: =IF(ISNUMBER($V$69),IF($V$69>=1.5,"CHEAP",IF($V$69>=0.5,"slightly cheap",IF($V$69<=-1.5,"RICH",IF($V$69<=-0.5,"slightly rich","fair")))),"") | X69: =SUMPRODUCT(--ISNUMBER((D69,G69,H69,I69,J69,K69))) | Y69: =IF(X69>=5,"HIGH",IF(X69>=3,"MED","LOW")) | Z69: =IF(AND(ISNUMBER(S69),X69>=$S$11),S69,"") | AA69: =IF(AND(ISNUMBER(R69),X69>=$S$11),R69,"")
B70: =Tickers!B62 | C70: =Tickers!C62 | D70: =Tickers!E62 | E70: =IFERROR(Tickers!G62,"") | F70: =IFERROR(Tickers!I62,"") | G70: =IFERROR(IF(ISNUMBER(Tickers!K62),Tickers!K62,IF(ISNUMBER(Haver!E62),Haver!E62,IF(ISNUMBER(Tickers!T62),Tickers!T62,""))),"") | H70: =IFERROR(IF(ISNUMBER(Tickers!M62),Tickers!M62,IF(ISNUMBER(Haver!G62),Haver!G62,IF(ISNUMBER(Tickers!U62),Tickers!U62,""))),"") | I70: =IFERROR(IF(ISNUMBER(Tickers!O62),Tickers!O62,IF(ISNUMBER(Haver!I62),Haver!I62,IF(ISNUMBER(Tickers!V62),Tickers!V62,""))),"") | J70: =IFERROR(IF(ISNUMBER(Tickers!Q62),Tickers!Q62,IF(ISNUMBER(Haver!K62),Haver!K62,IF(ISNUMBER(Tickers!W62),Tickers!W62,""))),"") | K70: =IFERROR(IF(ISNUMBER(Tickers!S62),Tickers!S62,IF(ISNUMBER(Haver!M62),Haver!M62,IF(ISNUMBER(Tickers!X62),Tickers!X62,""))),"") | L70: =IFERROR(($D$70-AVERAGE($D$15:$D$85))/STDEV($D$15:$D$85),"") | M70: =IFERROR(($I$70-AVERAGE($I$15:$I$85))/STDEV($I$15:$I$85),"") | N70: =IFERROR(-($J$70-AVERAGE($J$15:$J$85))/STDEV($J$15:$J$85),"") | O70: =IFERROR(-($K$70-AVERAGE($K$15:$K$85))/STDEV($K$15:$K$85),"") | P70: =IFERROR(-($G$70-AVERAGE($G$15:$G$85))/STDEV($G$15:$G$85),"") | Q70: =IFERROR(($H$70-AVERAGE($H$15:$H$85))/STDEV($H$15:$H$85),"") | R70: =IFERROR((IF(ISNUMBER(L70),$D$7*L70,0)+IF(ISNUMBER(M70),$D$8*M70,0)+IF(ISNUMBER(N70),$D$9*N70,0)+IF(ISNUMBER(O70),$D$10*O70,0)+IF(ISNUMBER(P70),$D$11*P70,0)+IF(ISNUMBER(Q70),$D$12*Q70,0))/(IF(ISNUMBER(L70),$D$7,0)+IF(ISNUMBER(M70),$D$8,0)+IF(ISNUMBER(N70),$D$9,0)+IF(ISNUMBER(O70),$D$10,0)+IF(ISNUMBER(P70),$D$11,0)+IF(ISNUMBER(Q70),$D$12,0)),"") | S70: =IFERROR(LN($E$70),"") | T70: =IFERROR($N$7+$N$8*$R$70,"") | U70: =IFERROR($S$70-$T$70,"") | V70: =IFERROR(($U$70-AVERAGE($U$15:$U$85))/STDEV($U$15:$U$85),"") | W70: =IF(ISNUMBER($V$70),IF($V$70>=1.5,"CHEAP",IF($V$70>=0.5,"slightly cheap",IF($V$70<=-1.5,"RICH",IF($V$70<=-0.5,"slightly rich","fair")))),"") | X70: =SUMPRODUCT(--ISNUMBER((D70,G70,H70,I70,J70,K70))) | Y70: =IF(X70>=5,"HIGH",IF(X70>=3,"MED","LOW")) | Z70: =IF(AND(ISNUMBER(S70),X70>=$S$11),S70,"") | AA70: =IF(AND(ISNUMBER(R70),X70>=$S$11),R70,"")
B71: =Tickers!B63 | C71: =Tickers!C63 | D71: =Tickers!E63 | E71: =IFERROR(Tickers!G63,"") | F71: =IFERROR(Tickers!I63,"") | G71: =IFERROR(IF(ISNUMBER(Tickers!K63),Tickers!K63,IF(ISNUMBER(Haver!E63),Haver!E63,IF(ISNUMBER(Tickers!T63),Tickers!T63,""))),"") | H71: =IFERROR(IF(ISNUMBER(Tickers!M63),Tickers!M63,IF(ISNUMBER(Haver!G63),Haver!G63,IF(ISNUMBER(Tickers!U63),Tickers!U63,""))),"") | I71: =IFERROR(IF(ISNUMBER(Tickers!O63),Tickers!O63,IF(ISNUMBER(Haver!I63),Haver!I63,IF(ISNUMBER(Tickers!V63),Tickers!V63,""))),"") | J71: =IFERROR(IF(ISNUMBER(Tickers!Q63),Tickers!Q63,IF(ISNUMBER(Haver!K63),Haver!K63,IF(ISNUMBER(Tickers!W63),Tickers!W63,""))),"") | K71: =IFERROR(IF(ISNUMBER(Tickers!S63),Tickers!S63,IF(ISNUMBER(Haver!M63),Haver!M63,IF(ISNUMBER(Tickers!X63),Tickers!X63,""))),"") | L71: =IFERROR(($D$71-AVERAGE($D$15:$D$85))/STDEV($D$15:$D$85),"") | M71: =IFERROR(($I$71-AVERAGE($I$15:$I$85))/STDEV($I$15:$I$85),"") | N71: =IFERROR(-($J$71-AVERAGE($J$15:$J$85))/STDEV($J$15:$J$85),"") | O71: =IFERROR(-($K$71-AVERAGE($K$15:$K$85))/STDEV($K$15:$K$85),"") | P71: =IFERROR(-($G$71-AVERAGE($G$15:$G$85))/STDEV($G$15:$G$85),"") | Q71: =IFERROR(($H$71-AVERAGE($H$15:$H$85))/STDEV($H$15:$H$85),"") | R71: =IFERROR((IF(ISNUMBER(L71),$D$7*L71,0)+IF(ISNUMBER(M71),$D$8*M71,0)+IF(ISNUMBER(N71),$D$9*N71,0)+IF(ISNUMBER(O71),$D$10*O71,0)+IF(ISNUMBER(P71),$D$11*P71,0)+IF(ISNUMBER(Q71),$D$12*Q71,0))/(IF(ISNUMBER(L71),$D$7,0)+IF(ISNUMBER(M71),$D$8,0)+IF(ISNUMBER(N71),$D$9,0)+IF(ISNUMBER(O71),$D$10,0)+IF(ISNUMBER(P71),$D$11,0)+IF(ISNUMBER(Q71),$D$12,0)),"") | S71: =IFERROR(LN($E$71),"") | T71: =IFERROR($N$7+$N$8*$R$71,"") | U71: =IFERROR($S$71-$T$71,"") | V71: =IFERROR(($U$71-AVERAGE($U$15:$U$85))/STDEV($U$15:$U$85),"") | W71: =IF(ISNUMBER($V$71),IF($V$71>=1.5,"CHEAP",IF($V$71>=0.5,"slightly cheap",IF($V$71<=-1.5,"RICH",IF($V$71<=-0.5,"slightly rich","fair")))),"") | X71: =SUMPRODUCT(--ISNUMBER((D71,G71,H71,I71,J71,K71))) | Y71: =IF(X71>=5,"HIGH",IF(X71>=3,"MED","LOW")) | Z71: =IF(AND(ISNUMBER(S71),X71>=$S$11),S71,"") | AA71: =IF(AND(ISNUMBER(R71),X71>=$S$11),R71,"")
B72: =Tickers!B64 | C72: =Tickers!C64 | D72: =Tickers!E64 | E72: =IFERROR(Tickers!G64,"") | F72: =IFERROR(Tickers!I64,"") | G72: =IFERROR(IF(ISNUMBER(Tickers!K64),Tickers!K64,IF(ISNUMBER(Haver!E64),Haver!E64,IF(ISNUMBER(Tickers!T64),Tickers!T64,""))),"") | H72: =IFERROR(IF(ISNUMBER(Tickers!M64),Tickers!M64,IF(ISNUMBER(Haver!G64),Haver!G64,IF(ISNUMBER(Tickers!U64),Tickers!U64,""))),"") | I72: =IFERROR(IF(ISNUMBER(Tickers!O64),Tickers!O64,IF(ISNUMBER(Haver!I64),Haver!I64,IF(ISNUMBER(Tickers!V64),Tickers!V64,""))),"") | J72: =IFERROR(IF(ISNUMBER(Tickers!Q64),Tickers!Q64,IF(ISNUMBER(Haver!K64),Haver!K64,IF(ISNUMBER(Tickers!W64),Tickers!W64,""))),"") | K72: =IFERROR(IF(ISNUMBER(Tickers!S64),Tickers!S64,IF(ISNUMBER(Haver!M64),Haver!M64,IF(ISNUMBER(Tickers!X64),Tickers!X64,""))),"") | L72: =IFERROR(($D$72-AVERAGE($D$15:$D$85))/STDEV($D$15:$D$85),"") | M72: =IFERROR(($I$72-AVERAGE($I$15:$I$85))/STDEV($I$15:$I$85),"") | N72: =IFERROR(-($J$72-AVERAGE($J$15:$J$85))/STDEV($J$15:$J$85),"") | O72: =IFERROR(-($K$72-AVERAGE($K$15:$K$85))/STDEV($K$15:$K$85),"") | P72: =IFERROR(-($G$72-AVERAGE($G$15:$G$85))/STDEV($G$15:$G$85),"") | Q72: =IFERROR(($H$72-AVERAGE($H$15:$H$85))/STDEV($H$15:$H$85),"") | R72: =IFERROR((IF(ISNUMBER(L72),$D$7*L72,0)+IF(ISNUMBER(M72),$D$8*M72,0)+IF(ISNUMBER(N72),$D$9*N72,0)+IF(ISNUMBER(O72),$D$10*O72,0)+IF(ISNUMBER(P72),$D$11*P72,0)+IF(ISNUMBER(Q72),$D$12*Q72,0))/(IF(ISNUMBER(L72),$D$7,0)+IF(ISNUMBER(M72),$D$8,0)+IF(ISNUMBER(N72),$D$9,0)+IF(ISNUMBER(O72),$D$10,0)+IF(ISNUMBER(P72),$D$11,0)+IF(ISNUMBER(Q72),$D$12,0)),"") | S72: =IFERROR(LN($E$72),"") | T72: =IFERROR($N$7+$N$8*$R$72,"") | U72: =IFERROR($S$72-$T$72,"") | V72: =IFERROR(($U$72-AVERAGE($U$15:$U$85))/STDEV($U$15:$U$85),"") | W72: =IF(ISNUMBER($V$72),IF($V$72>=1.5,"CHEAP",IF($V$72>=0.5,"slightly cheap",IF($V$72<=-1.5,"RICH",IF($V$72<=-0.5,"slightly rich","fair")))),"") | X72: =SUMPRODUCT(--ISNUMBER((D72,G72,H72,I72,J72,K72))) | Y72: =IF(X72>=5,"HIGH",IF(X72>=3,"MED","LOW")) | Z72: =IF(AND(ISNUMBER(S72),X72>=$S$11),S72,"") | AA72: =IF(AND(ISNUMBER(R72),X72>=$S$11),R72,"")
B73: =Tickers!B65 | C73: =Tickers!C65 | D73: =Tickers!E65 | E73: =IFERROR(Tickers!G65,"") | F73: =IFERROR(Tickers!I65,"") | G73: =IFERROR(IF(ISNUMBER(Tickers!K65),Tickers!K65,IF(ISNUMBER(Haver!E65),Haver!E65,IF(ISNUMBER(Tickers!T65),Tickers!T65,""))),"") | H73: =IFERROR(IF(ISNUMBER(Tickers!M65),Tickers!M65,IF(ISNUMBER(Haver!G65),Haver!G65,IF(ISNUMBER(Tickers!U65),Tickers!U65,""))),"") | I73: =IFERROR(IF(ISNUMBER(Tickers!O65),Tickers!O65,IF(ISNUMBER(Haver!I65),Haver!I65,IF(ISNUMBER(Tickers!V65),Tickers!V65,""))),"") | J73: =IFERROR(IF(ISNUMBER(Tickers!Q65),Tickers!Q65,IF(ISNUMBER(Haver!K65),Haver!K65,IF(ISNUMBER(Tickers!W65),Tickers!W65,""))),"") | K73: =IFERROR(IF(ISNUMBER(Tickers!S65),Tickers!S65,IF(ISNUMBER(Haver!M65),Haver!M65,IF(ISNUMBER(Tickers!X65),Tickers!X65,""))),"") | L73: =IFERROR(($D$73-AVERAGE($D$15:$D$85))/STDEV($D$15:$D$85),"") | M73: =IFERROR(($I$73-AVERAGE($I$15:$I$85))/STDEV($I$15:$I$85),"") | N73: =IFERROR(-($J$73-AVERAGE($J$15:$J$85))/STDEV($J$15:$J$85),"") | O73: =IFERROR(-($K$73-AVERAGE($K$15:$K$85))/STDEV($K$15:$K$85),"") | P73: =IFERROR(-($G$73-AVERAGE($G$15:$G$85))/STDEV($G$15:$G$85),"") | Q73: =IFERROR(($H$73-AVERAGE($H$15:$H$85))/STDEV($H$15:$H$85),"") | R73: =IFERROR((IF(ISNUMBER(L73),$D$7*L73,0)+IF(ISNUMBER(M73),$D$8*M73,0)+IF(ISNUMBER(N73),$D$9*N73,0)+IF(ISNUMBER(O73),$D$10*O73,0)+IF(ISNUMBER(P73),$D$11*P73,0)+IF(ISNUMBER(Q73),$D$12*Q73,0))/(IF(ISNUMBER(L73),$D$7,0)+IF(ISNUMBER(M73),$D$8,0)+IF(ISNUMBER(N73),$D$9,0)+IF(ISNUMBER(O73),$D$10,0)+IF(ISNUMBER(P73),$D$11,0)+IF(ISNUMBER(Q73),$D$12,0)),"") | S73: =IFERROR(LN($E$73),"") | T73: =IFERROR($N$7+$N$8*$R$73,"") | U73: =IFERROR($S$73-$T$73,"") | V73: =IFERROR(($U$73-AVERAGE($U$15:$U$85))/STDEV($U$15:$U$85),"") | W73: =IF(ISNUMBER($V$73),IF($V$73>=1.5,"CHEAP",IF($V$73>=0.5,"slightly cheap",IF($V$73<=-1.5,"RICH",IF($V$73<=-0.5,"slightly rich","fair")))),"") | X73: =SUMPRODUCT(--ISNUMBER((D73,G73,H73,I73,J73,K73))) | Y73: =IF(X73>=5,"HIGH",IF(X73>=3,"MED","LOW")) | Z73: =IF(AND(ISNUMBER(S73),X73>=$S$11),S73,"") | AA73: =IF(AND(ISNUMBER(R73),X73>=$S$11),R73,"")
B74: =Tickers!B66 | C74: =Tickers!C66 | D74: =Tickers!E66 | E74: =IFERROR(Tickers!G66,"") | F74: =IFERROR(Tickers!I66,"") | G74: =IFERROR(IF(ISNUMBER(Tickers!K66),Tickers!K66,IF(ISNUMBER(Haver!E66),Haver!E66,IF(ISNUMBER(Tickers!T66),Tickers!T66,""))),"") | H74: =IFERROR(IF(ISNUMBER(Tickers!M66),Tickers!M66,IF(ISNUMBER(Haver!G66),Haver!G66,IF(ISNUMBER(Tickers!U66),Tickers!U66,""))),"") | I74: =IFERROR(IF(ISNUMBER(Tickers!O66),Tickers!O66,IF(ISNUMBER(Haver!I66),Haver!I66,IF(ISNUMBER(Tickers!V66),Tickers!V66,""))),"") | J74: =IFERROR(IF(ISNUMBER(Tickers!Q66),Tickers!Q66,IF(ISNUMBER(Haver!K66),Haver!K66,IF(ISNUMBER(Tickers!W66),Tickers!W66,""))),"") | K74: =IFERROR(IF(ISNUMBER(Tickers!S66),Tickers!S66,IF(ISNUMBER(Haver!M66),Haver!M66,IF(ISNUMBER(Tickers!X66),Tickers!X66,""))),"") | L74: =IFERROR(($D$74-AVERAGE($D$15:$D$85))/STDEV($D$15:$D$85),"") | M74: =IFERROR(($I$74-AVERAGE($I$15:$I$85))/STDEV($I$15:$I$85),"") | N74: =IFERROR(-($J$74-AVERAGE($J$15:$J$85))/STDEV($J$15:$J$85),"") | O74: =IFERROR(-($K$74-AVERAGE($K$15:$K$85))/STDEV($K$15:$K$85),"") | P74: =IFERROR(-($G$74-AVERAGE($G$15:$G$85))/STDEV($G$15:$G$85),"") | Q74: =IFERROR(($H$74-AVERAGE($H$15:$H$85))/STDEV($H$15:$H$85),"") | R74: =IFERROR((IF(ISNUMBER(L74),$D$7*L74,0)+IF(ISNUMBER(M74),$D$8*M74,0)+IF(ISNUMBER(N74),$D$9*N74,0)+IF(ISNUMBER(O74),$D$10*O74,0)+IF(ISNUMBER(P74),$D$11*P74,0)+IF(ISNUMBER(Q74),$D$12*Q74,0))/(IF(ISNUMBER(L74),$D$7,0)+IF(ISNUMBER(M74),$D$8,0)+IF(ISNUMBER(N74),$D$9,0)+IF(ISNUMBER(O74),$D$10,0)+IF(ISNUMBER(P74),$D$11,0)+IF(ISNUMBER(Q74),$D$12,0)),"") | S74: =IFERROR(LN($E$74),"") | T74: =IFERROR($N$7+$N$8*$R$74,"") | U74: =IFERROR($S$74-$T$74,"") | V74: =IFERROR(($U$74-AVERAGE($U$15:$U$85))/STDEV($U$15:$U$85),"") | W74: =IF(ISNUMBER($V$74),IF($V$74>=1.5,"CHEAP",IF($V$74>=0.5,"slightly cheap",IF($V$74<=-1.5,"RICH",IF($V$74<=-0.5,"slightly rich","fair")))),"") | X74: =SUMPRODUCT(--ISNUMBER((D74,G74,H74,I74,J74,K74))) | Y74: =IF(X74>=5,"HIGH",IF(X74>=3,"MED","LOW")) | Z74: =IF(AND(ISNUMBER(S74),X74>=$S$11),S74,"") | AA74: =IF(AND(ISNUMBER(R74),X74>=$S$11),R74,"")
B75: =Tickers!B67 | C75: =Tickers!C67 | D75: =Tickers!E67 | E75: =IFERROR(Tickers!G67,"") | F75: =IFERROR(Tickers!I67,"") | G75: =IFERROR(IF(ISNUMBER(Tickers!K67),Tickers!K67,IF(ISNUMBER(Haver!E67),Haver!E67,IF(ISNUMBER(Tickers!T67),Tickers!T67,""))),"") | H75: =IFERROR(IF(ISNUMBER(Tickers!M67),Tickers!M67,IF(ISNUMBER(Haver!G67),Haver!G67,IF(ISNUMBER(Tickers!U67),Tickers!U67,""))),"") | I75: =IFERROR(IF(ISNUMBER(Tickers!O67),Tickers!O67,IF(ISNUMBER(Haver!I67),Haver!I67,IF(ISNUMBER(Tickers!V67),Tickers!V67,""))),"") | J75: =IFERROR(IF(ISNUMBER(Tickers!Q67),Tickers!Q67,IF(ISNUMBER(Haver!K67),Haver!K67,IF(ISNUMBER(Tickers!W67),Tickers!W67,""))),"") | K75: =IFERROR(IF(ISNUMBER(Tickers!S67),Tickers!S67,IF(ISNUMBER(Haver!M67),Haver!M67,IF(ISNUMBER(Tickers!X67),Tickers!X67,""))),"") | L75: =IFERROR(($D$75-AVERAGE($D$15:$D$85))/STDEV($D$15:$D$85),"") | M75: =IFERROR(($I$75-AVERAGE($I$15:$I$85))/STDEV($I$15:$I$85),"") | N75: =IFERROR(-($J$75-AVERAGE($J$15:$J$85))/STDEV($J$15:$J$85),"") | O75: =IFERROR(-($K$75-AVERAGE($K$15:$K$85))/STDEV($K$15:$K$85),"") | P75: =IFERROR(-($G$75-AVERAGE($G$15:$G$85))/STDEV($G$15:$G$85),"") | Q75: =IFERROR(($H$75-AVERAGE($H$15:$H$85))/STDEV($H$15:$H$85),"") | R75: =IFERROR((IF(ISNUMBER(L75),$D$7*L75,0)+IF(ISNUMBER(M75),$D$8*M75,0)+IF(ISNUMBER(N75),$D$9*N75,0)+IF(ISNUMBER(O75),$D$10*O75,0)+IF(ISNUMBER(P75),$D$11*P75,0)+IF(ISNUMBER(Q75),$D$12*Q75,0))/(IF(ISNUMBER(L75),$D$7,0)+IF(ISNUMBER(M75),$D$8,0)+IF(ISNUMBER(N75),$D$9,0)+IF(ISNUMBER(O75),$D$10,0)+IF(ISNUMBER(P75),$D$11,0)+IF(ISNUMBER(Q75),$D$12,0)),"") | S75: =IFERROR(LN($E$75),"") | T75: =IFERROR($N$7+$N$8*$R$75,"") | U75: =IFERROR($S$75-$T$75,"") | V75: =IFERROR(($U$75-AVERAGE($U$15:$U$85))/STDEV($U$15:$U$85),"") | W75: =IF(ISNUMBER($V$75),IF($V$75>=1.5,"CHEAP",IF($V$75>=0.5,"slightly cheap",IF($V$75<=-1.5,"RICH",IF($V$75<=-0.5,"slightly rich","fair")))),"") | X75: =SUMPRODUCT(--ISNUMBER((D75,G75,H75,I75,J75,K75))) | Y75: =IF(X75>=5,"HIGH",IF(X75>=3,"MED","LOW")) | Z75: =IF(AND(ISNUMBER(S75),X75>=$S$11),S75,"") | AA75: =IF(AND(ISNUMBER(R75),X75>=$S$11),R75,"")
B76: =Tickers!B68 | C76: =Tickers!C68 | D76: =Tickers!E68 | E76: =IFERROR(Tickers!G68,"") | F76: =IFERROR(Tickers!I68,"") | G76: =IFERROR(IF(ISNUMBER(Tickers!K68),Tickers!K68,IF(ISNUMBER(Haver!E68),Haver!E68,IF(ISNUMBER(Tickers!T68),Tickers!T68,""))),"") | H76: =IFERROR(IF(ISNUMBER(Tickers!M68),Tickers!M68,IF(ISNUMBER(Haver!G68),Haver!G68,IF(ISNUMBER(Tickers!U68),Tickers!U68,""))),"") | I76: =IFERROR(IF(ISNUMBER(Tickers!O68),Tickers!O68,IF(ISNUMBER(Haver!I68),Haver!I68,IF(ISNUMBER(Tickers!V68),Tickers!V68,""))),"") | J76: =IFERROR(IF(ISNUMBER(Tickers!Q68),Tickers!Q68,IF(ISNUMBER(Haver!K68),Haver!K68,IF(ISNUMBER(Tickers!W68),Tickers!W68,""))),"") | K76: =IFERROR(IF(ISNUMBER(Tickers!S68),Tickers!S68,IF(ISNUMBER(Haver!M68),Haver!M68,IF(ISNUMBER(Tickers!X68),Tickers!X68,""))),"") | L76: =IFERROR(($D$76-AVERAGE($D$15:$D$85))/STDEV($D$15:$D$85),"") | M76: =IFERROR(($I$76-AVERAGE($I$15:$I$85))/STDEV($I$15:$I$85),"") | N76: =IFERROR(-($J$76-AVERAGE($J$15:$J$85))/STDEV($J$15:$J$85),"") | O76: =IFERROR(-($K$76-AVERAGE($K$15:$K$85))/STDEV($K$15:$K$85),"") | P76: =IFERROR(-($G$76-AVERAGE($G$15:$G$85))/STDEV($G$15:$G$85),"") | Q76: =IFERROR(($H$76-AVERAGE($H$15:$H$85))/STDEV($H$15:$H$85),"") | R76: =IFERROR((IF(ISNUMBER(L76),$D$7*L76,0)+IF(ISNUMBER(M76),$D$8*M76,0)+IF(ISNUMBER(N76),$D$9*N76,0)+IF(ISNUMBER(O76),$D$10*O76,0)+IF(ISNUMBER(P76),$D$11*P76,0)+IF(ISNUMBER(Q76),$D$12*Q76,0))/(IF(ISNUMBER(L76),$D$7,0)+IF(ISNUMBER(M76),$D$8,0)+IF(ISNUMBER(N76),$D$9,0)+IF(ISNUMBER(O76),$D$10,0)+IF(ISNUMBER(P76),$D$11,0)+IF(ISNUMBER(Q76),$D$12,0)),"") | S76: =IFERROR(LN($E$76),"") | T76: =IFERROR($N$7+$N$8*$R$76,"") | U76: =IFERROR($S$76-$T$76,"") | V76: =IFERROR(($U$76-AVERAGE($U$15:$U$85))/STDEV($U$15:$U$85),"") | W76: =IF(ISNUMBER($V$76),IF($V$76>=1.5,"CHEAP",IF($V$76>=0.5,"slightly cheap",IF($V$76<=-1.5,"RICH",IF($V$76<=-0.5,"slightly rich","fair")))),"") | X76: =SUMPRODUCT(--ISNUMBER((D76,G76,H76,I76,J76,K76))) | Y76: =IF(X76>=5,"HIGH",IF(X76>=3,"MED","LOW")) | Z76: =IF(AND(ISNUMBER(S76),X76>=$S$11),S76,"") | AA76: =IF(AND(ISNUMBER(R76),X76>=$S$11),R76,"")
B77: =Tickers!B69 | C77: =Tickers!C69 | D77: =Tickers!E69 | E77: =IFERROR(Tickers!G69,"") | F77: =IFERROR(Tickers!I69,"") | G77: =IFERROR(IF(ISNUMBER(Tickers!K69),Tickers!K69,IF(ISNUMBER(Haver!E69),Haver!E69,IF(ISNUMBER(Tickers!T69),Tickers!T69,""))),"") | H77: =IFERROR(IF(ISNUMBER(Tickers!M69),Tickers!M69,IF(ISNUMBER(Haver!G69),Haver!G69,IF(ISNUMBER(Tickers!U69),Tickers!U69,""))),"") | I77: =IFERROR(IF(ISNUMBER(Tickers!O69),Tickers!O69,IF(ISNUMBER(Haver!I69),Haver!I69,IF(ISNUMBER(Tickers!V69),Tickers!V69,""))),"") | J77: =IFERROR(IF(ISNUMBER(Tickers!Q69),Tickers!Q69,IF(ISNUMBER(Haver!K69),Haver!K69,IF(ISNUMBER(Tickers!W69),Tickers!W69,""))),"") | K77: =IFERROR(IF(ISNUMBER(Tickers!S69),Tickers!S69,IF(ISNUMBER(Haver!M69),Haver!M69,IF(ISNUMBER(Tickers!X69),Tickers!X69,""))),"") | L77: =IFERROR(($D$77-AVERAGE($D$15:$D$85))/STDEV($D$15:$D$85),"") | M77: =IFERROR(($I$77-AVERAGE($I$15:$I$85))/STDEV($I$15:$I$85),"") | N77: =IFERROR(-($J$77-AVERAGE($J$15:$J$85))/STDEV($J$15:$J$85),"") | O77: =IFERROR(-($K$77-AVERAGE($K$15:$K$85))/STDEV($K$15:$K$85),"") | P77: =IFERROR(-($G$77-AVERAGE($G$15:$G$85))/STDEV($G$15:$G$85),"") | Q77: =IFERROR(($H$77-AVERAGE($H$15:$H$85))/STDEV($H$15:$H$85),"") | R77: =IFERROR((IF(ISNUMBER(L77),$D$7*L77,0)+IF(ISNUMBER(M77),$D$8*M77,0)+IF(ISNUMBER(N77),$D$9*N77,0)+IF(ISNUMBER(O77),$D$10*O77,0)+IF(ISNUMBER(P77),$D$11*P77,0)+IF(ISNUMBER(Q77),$D$12*Q77,0))/(IF(ISNUMBER(L77),$D$7,0)+IF(ISNUMBER(M77),$D$8,0)+IF(ISNUMBER(N77),$D$9,0)+IF(ISNUMBER(O77),$D$10,0)+IF(ISNUMBER(P77),$D$11,0)+IF(ISNUMBER(Q77),$D$12,0)),"") | S77: =IFERROR(LN($E$77),"") | T77: =IFERROR($N$7+$N$8*$R$77,"") | U77: =IFERROR($S$77-$T$77,"") | V77: =IFERROR(($U$77-AVERAGE($U$15:$U$85))/STDEV($U$15:$U$85),"") | W77: =IF(ISNUMBER($V$77),IF($V$77>=1.5,"CHEAP",IF($V$77>=0.5,"slightly cheap",IF($V$77<=-1.5,"RICH",IF($V$77<=-0.5,"slightly rich","fair")))),"") | X77: =SUMPRODUCT(--ISNUMBER((D77,G77,H77,I77,J77,K77))) | Y77: =IF(X77>=5,"HIGH",IF(X77>=3,"MED","LOW")) | Z77: =IF(AND(ISNUMBER(S77),X77>=$S$11),S77,"") | AA77: =IF(AND(ISNUMBER(R77),X77>=$S$11),R77,"")
B78: =Tickers!B70 | C78: =Tickers!C70 | D78: =Tickers!E70 | E78: =IFERROR(Tickers!G70,"") | F78: =IFERROR(Tickers!I70,"") | G78: =IFERROR(IF(ISNUMBER(Tickers!K70),Tickers!K70,IF(ISNUMBER(Haver!E70),Haver!E70,IF(ISNUMBER(Tickers!T70),Tickers!T70,""))),"") | H78: =IFERROR(IF(ISNUMBER(Tickers!M70),Tickers!M70,IF(ISNUMBER(Haver!G70),Haver!G70,IF(ISNUMBER(Tickers!U70),Tickers!U70,""))),"") | I78: =IFERROR(IF(ISNUMBER(Tickers!O70),Tickers!O70,IF(ISNUMBER(Haver!I70),Haver!I70,IF(ISNUMBER(Tickers!V70),Tickers!V70,""))),"") | J78: =IFERROR(IF(ISNUMBER(Tickers!Q70),Tickers!Q70,IF(ISNUMBER(Haver!K70),Haver!K70,IF(ISNUMBER(Tickers!W70),Tickers!W70,""))),"") | K78: =IFERROR(IF(ISNUMBER(Tickers!S70),Tickers!S70,IF(ISNUMBER(Haver!M70),Haver!M70,IF(ISNUMBER(Tickers!X70),Tickers!X70,""))),"") | L78: =IFERROR(($D$78-AVERAGE($D$15:$D$85))/STDEV($D$15:$D$85),"") | M78: =IFERROR(($I$78-AVERAGE($I$15:$I$85))/STDEV($I$15:$I$85),"") | N78: =IFERROR(-($J$78-AVERAGE($J$15:$J$85))/STDEV($J$15:$J$85),"") | O78: =IFERROR(-($K$78-AVERAGE($K$15:$K$85))/STDEV($K$15:$K$85),"") | P78: =IFERROR(-($G$78-AVERAGE($G$15:$G$85))/STDEV($G$15:$G$85),"") | Q78: =IFERROR(($H$78-AVERAGE($H$15:$H$85))/STDEV($H$15:$H$85),"") | R78: =IFERROR((IF(ISNUMBER(L78),$D$7*L78,0)+IF(ISNUMBER(M78),$D$8*M78,0)+IF(ISNUMBER(N78),$D$9*N78,0)+IF(ISNUMBER(O78),$D$10*O78,0)+IF(ISNUMBER(P78),$D$11*P78,0)+IF(ISNUMBER(Q78),$D$12*Q78,0))/(IF(ISNUMBER(L78),$D$7,0)+IF(ISNUMBER(M78),$D$8,0)+IF(ISNUMBER(N78),$D$9,0)+IF(ISNUMBER(O78),$D$10,0)+IF(ISNUMBER(P78),$D$11,0)+IF(ISNUMBER(Q78),$D$12,0)),"") | S78: =IFERROR(LN($E$78),"") | T78: =IFERROR($N$7+$N$8*$R$78,"") | U78: =IFERROR($S$78-$T$78,"") | V78: =IFERROR(($U$78-AVERAGE($U$15:$U$85))/STDEV($U$15:$U$85),"") | W78: =IF(ISNUMBER($V$78),IF($V$78>=1.5,"CHEAP",IF($V$78>=0.5,"slightly cheap",IF($V$78<=-1.5,"RICH",IF($V$78<=-0.5,"slightly rich","fair")))),"") | X78: =SUMPRODUCT(--ISNUMBER((D78,G78,H78,I78,J78,K78))) | Y78: =IF(X78>=5,"HIGH",IF(X78>=3,"MED","LOW")) | Z78: =IF(AND(ISNUMBER(S78),X78>=$S$11),S78,"") | AA78: =IF(AND(ISNUMBER(R78),X78>=$S$11),R78,"")
B79: =Tickers!B71 | C79: =Tickers!C71 | D79: =Tickers!E71 | E79: =IFERROR(Tickers!G71,"") | F79: =IFERROR(Tickers!I71,"") | G79: =IFERROR(IF(ISNUMBER(Tickers!K71),Tickers!K71,IF(ISNUMBER(Haver!E71),Haver!E71,IF(ISNUMBER(Tickers!T71),Tickers!T71,""))),"") | H79: =IFERROR(IF(ISNUMBER(Tickers!M71),Tickers!M71,IF(ISNUMBER(Haver!G71),Haver!G71,IF(ISNUMBER(Tickers!U71),Tickers!U71,""))),"") | I79: =IFERROR(IF(ISNUMBER(Tickers!O71),Tickers!O71,IF(ISNUMBER(Haver!I71),Haver!I71,IF(ISNUMBER(Tickers!V71),Tickers!V71,""))),"") | J79: =IFERROR(IF(ISNUMBER(Tickers!Q71),Tickers!Q71,IF(ISNUMBER(Haver!K71),Haver!K71,IF(ISNUMBER(Tickers!W71),Tickers!W71,""))),"") | K79: =IFERROR(IF(ISNUMBER(Tickers!S71),Tickers!S71,IF(ISNUMBER(Haver!M71),Haver!M71,IF(ISNUMBER(Tickers!X71),Tickers!X71,""))),"") | L79: =IFERROR(($D$79-AVERAGE($D$15:$D$85))/STDEV($D$15:$D$85),"") | M79: =IFERROR(($I$79-AVERAGE($I$15:$I$85))/STDEV($I$15:$I$85),"") | N79: =IFERROR(-($J$79-AVERAGE($J$15:$J$85))/STDEV($J$15:$J$85),"") | O79: =IFERROR(-($K$79-AVERAGE($K$15:$K$85))/STDEV($K$15:$K$85),"") | P79: =IFERROR(-($G$79-AVERAGE($G$15:$G$85))/STDEV($G$15:$G$85),"") | Q79: =IFERROR(($H$79-AVERAGE($H$15:$H$85))/STDEV($H$15:$H$85),"") | R79: =IFERROR((IF(ISNUMBER(L79),$D$7*L79,0)+IF(ISNUMBER(M79),$D$8*M79,0)+IF(ISNUMBER(N79),$D$9*N79,0)+IF(ISNUMBER(O79),$D$10*O79,0)+IF(ISNUMBER(P79),$D$11*P79,0)+IF(ISNUMBER(Q79),$D$12*Q79,0))/(IF(ISNUMBER(L79),$D$7,0)+IF(ISNUMBER(M79),$D$8,0)+IF(ISNUMBER(N79),$D$9,0)+IF(ISNUMBER(O79),$D$10,0)+IF(ISNUMBER(P79),$D$11,0)+IF(ISNUMBER(Q79),$D$12,0)),"") | S79: =IFERROR(LN($E$79),"") | T79: =IFERROR($N$7+$N$8*$R$79,"") | U79: =IFERROR($S$79-$T$79,"") | V79: =IFERROR(($U$79-AVERAGE($U$15:$U$85))/STDEV($U$15:$U$85),"") | W79: =IF(ISNUMBER($V$79),IF($V$79>=1.5,"CHEAP",IF($V$79>=0.5,"slightly cheap",IF($V$79<=-1.5,"RICH",IF($V$79<=-0.5,"slightly rich","fair")))),"") | X79: =SUMPRODUCT(--ISNUMBER((D79,G79,H79,I79,J79,K79))) | Y79: =IF(X79>=5,"HIGH",IF(X79>=3,"MED","LOW")) | Z79: =IF(AND(ISNUMBER(S79),X79>=$S$11),S79,"") | AA79: =IF(AND(ISNUMBER(R79),X79>=$S$11),R79,"")
B80: =Tickers!B72 | C80: =Tickers!C72 | D80: =Tickers!E72 | E80: =IFERROR(Tickers!G72,"") | F80: =IFERROR(Tickers!I72,"") | G80: =IFERROR(IF(ISNUMBER(Tickers!K72),Tickers!K72,IF(ISNUMBER(Haver!E72),Haver!E72,IF(ISNUMBER(Tickers!T72),Tickers!T72,""))),"") | H80: =IFERROR(IF(ISNUMBER(Tickers!M72),Tickers!M72,IF(ISNUMBER(Haver!G72),Haver!G72,IF(ISNUMBER(Tickers!U72),Tickers!U72,""))),"") | I80: =IFERROR(IF(ISNUMBER(Tickers!O72),Tickers!O72,IF(ISNUMBER(Haver!I72),Haver!I72,IF(ISNUMBER(Tickers!V72),Tickers!V72,""))),"") | J80: =IFERROR(IF(ISNUMBER(Tickers!Q72),Tickers!Q72,IF(ISNUMBER(Haver!K72),Haver!K72,IF(ISNUMBER(Tickers!W72),Tickers!W72,""))),"") | K80: =IFERROR(IF(ISNUMBER(Tickers!S72),Tickers!S72,IF(ISNUMBER(Haver!M72),Haver!M72,IF(ISNUMBER(Tickers!X72),Tickers!X72,""))),"") | L80: =IFERROR(($D$80-AVERAGE($D$15:$D$85))/STDEV($D$15:$D$85),"") | M80: =IFERROR(($I$80-AVERAGE($I$15:$I$85))/STDEV($I$15:$I$85),"") | N80: =IFERROR(-($J$80-AVERAGE($J$15:$J$85))/STDEV($J$15:$J$85),"") | O80: =IFERROR(-($K$80-AVERAGE($K$15:$K$85))/STDEV($K$15:$K$85),"") | P80: =IFERROR(-($G$80-AVERAGE($G$15:$G$85))/STDEV($G$15:$G$85),"") | Q80: =IFERROR(($H$80-AVERAGE($H$15:$H$85))/STDEV($H$15:$H$85),"") | R80: =IFERROR((IF(ISNUMBER(L80),$D$7*L80,0)+IF(ISNUMBER(M80),$D$8*M80,0)+IF(ISNUMBER(N80),$D$9*N80,0)+IF(ISNUMBER(O80),$D$10*O80,0)+IF(ISNUMBER(P80),$D$11*P80,0)+IF(ISNUMBER(Q80),$D$12*Q80,0))/(IF(ISNUMBER(L80),$D$7,0)+IF(ISNUMBER(M80),$D$8,0)+IF(ISNUMBER(N80),$D$9,0)+IF(ISNUMBER(O80),$D$10,0)+IF(ISNUMBER(P80),$D$11,0)+IF(ISNUMBER(Q80),$D$12,0)),"") | S80: =IFERROR(LN($E$80),"") | T80: =IFERROR($N$7+$N$8*$R$80,"") | U80: =IFERROR($S$80-$T$80,"") | V80: =IFERROR(($U$80-AVERAGE($U$15:$U$85))/STDEV($U$15:$U$85),"") | W80: =IF(ISNUMBER($V$80),IF($V$80>=1.5,"CHEAP",IF($V$80>=0.5,"slightly cheap",IF($V$80<=-1.5,"RICH",IF($V$80<=-0.5,"slightly rich","fair")))),"") | X80: =SUMPRODUCT(--ISNUMBER((D80,G80,H80,I80,J80,K80))) | Y80: =IF(X80>=5,"HIGH",IF(X80>=3,"MED","LOW")) | Z80: =IF(AND(ISNUMBER(S80),X80>=$S$11),S80,"") | AA80: =IF(AND(ISNUMBER(R80),X80>=$S$11),R80,"")
B81: =Tickers!B73 | C81: =Tickers!C73 | D81: =Tickers!E73 | E81: =IFERROR(Tickers!G73,"") | F81: =IFERROR(Tickers!I73,"") | G81: =IFERROR(IF(ISNUMBER(Tickers!K73),Tickers!K73,IF(ISNUMBER(Haver!E73),Haver!E73,IF(ISNUMBER(Tickers!T73),Tickers!T73,""))),"") | H81: =IFERROR(IF(ISNUMBER(Tickers!M73),Tickers!M73,IF(ISNUMBER(Haver!G73),Haver!G73,IF(ISNUMBER(Tickers!U73),Tickers!U73,""))),"") | I81: =IFERROR(IF(ISNUMBER(Tickers!O73),Tickers!O73,IF(ISNUMBER(Haver!I73),Haver!I73,IF(ISNUMBER(Tickers!V73),Tickers!V73,""))),"") | J81: =IFERROR(IF(ISNUMBER(Tickers!Q73),Tickers!Q73,IF(ISNUMBER(Haver!K73),Haver!K73,IF(ISNUMBER(Tickers!W73),Tickers!W73,""))),"") | K81: =IFERROR(IF(ISNUMBER(Tickers!S73),Tickers!S73,IF(ISNUMBER(Haver!M73),Haver!M73,IF(ISNUMBER(Tickers!X73),Tickers!X73,""))),"") | L81: =IFERROR(($D$81-AVERAGE($D$15:$D$85))/STDEV($D$15:$D$85),"") | M81: =IFERROR(($I$81-AVERAGE($I$15:$I$85))/STDEV($I$15:$I$85),"") | N81: =IFERROR(-($J$81-AVERAGE($J$15:$J$85))/STDEV($J$15:$J$85),"") | O81: =IFERROR(-($K$81-AVERAGE($K$15:$K$85))/STDEV($K$15:$K$85),"") | P81: =IFERROR(-($G$81-AVERAGE($G$15:$G$85))/STDEV($G$15:$G$85),"") | Q81: =IFERROR(($H$81-AVERAGE($H$15:$H$85))/STDEV($H$15:$H$85),"") | R81: =IFERROR((IF(ISNUMBER(L81),$D$7*L81,0)+IF(ISNUMBER(M81),$D$8*M81,0)+IF(ISNUMBER(N81),$D$9*N81,0)+IF(ISNUMBER(O81),$D$10*O81,0)+IF(ISNUMBER(P81),$D$11*P81,0)+IF(ISNUMBER(Q81),$D$12*Q81,0))/(IF(ISNUMBER(L81),$D$7,0)+IF(ISNUMBER(M81),$D$8,0)+IF(ISNUMBER(N81),$D$9,0)+IF(ISNUMBER(O81),$D$10,0)+IF(ISNUMBER(P81),$D$11,0)+IF(ISNUMBER(Q81),$D$12,0)),"") | S81: =IFERROR(LN($E$81),"") | T81: =IFERROR($N$7+$N$8*$R$81,"") | U81: =IFERROR($S$81-$T$81,"") | V81: =IFERROR(($U$81-AVERAGE($U$15:$U$85))/STDEV($U$15:$U$85),"") | W81: =IF(ISNUMBER($V$81),IF($V$81>=1.5,"CHEAP",IF($V$81>=0.5,"slightly cheap",IF($V$81<=-1.5,"RICH",IF($V$81<=-0.5,"slightly rich","fair")))),"") | X81: =SUMPRODUCT(--ISNUMBER((D81,G81,H81,I81,J81,K81))) | Y81: =IF(X81>=5,"HIGH",IF(X81>=3,"MED","LOW")) | Z81: =IF(AND(ISNUMBER(S81),X81>=$S$11),S81,"") | AA81: =IF(AND(ISNUMBER(R81),X81>=$S$11),R81,"")
B82: =Tickers!B74 | C82: =Tickers!C74 | D82: =Tickers!E74 | E82: =IFERROR(Tickers!G74,"") | F82: =IFERROR(Tickers!I74,"") | G82: =IFERROR(IF(ISNUMBER(Tickers!K74),Tickers!K74,IF(ISNUMBER(Haver!E74),Haver!E74,IF(ISNUMBER(Tickers!T74),Tickers!T74,""))),"") | H82: =IFERROR(IF(ISNUMBER(Tickers!M74),Tickers!M74,IF(ISNUMBER(Haver!G74),Haver!G74,IF(ISNUMBER(Tickers!U74),Tickers!U74,""))),"") | I82: =IFERROR(IF(ISNUMBER(Tickers!O74),Tickers!O74,IF(ISNUMBER(Haver!I74),Haver!I74,IF(ISNUMBER(Tickers!V74),Tickers!V74,""))),"") | J82: =IFERROR(IF(ISNUMBER(Tickers!Q74),Tickers!Q74,IF(ISNUMBER(Haver!K74),Haver!K74,IF(ISNUMBER(Tickers!W74),Tickers!W74,""))),"") | K82: =IFERROR(IF(ISNUMBER(Tickers!S74),Tickers!S74,IF(ISNUMBER(Haver!M74),Haver!M74,IF(ISNUMBER(Tickers!X74),Tickers!X74,""))),"") | L82: =IFERROR(($D$82-AVERAGE($D$15:$D$85))/STDEV($D$15:$D$85),"") | M82: =IFERROR(($I$82-AVERAGE($I$15:$I$85))/STDEV($I$15:$I$85),"") | N82: =IFERROR(-($J$82-AVERAGE($J$15:$J$85))/STDEV($J$15:$J$85),"") | O82: =IFERROR(-($K$82-AVERAGE($K$15:$K$85))/STDEV($K$15:$K$85),"") | P82: =IFERROR(-($G$82-AVERAGE($G$15:$G$85))/STDEV($G$15:$G$85),"") | Q82: =IFERROR(($H$82-AVERAGE($H$15:$H$85))/STDEV($H$15:$H$85),"") | R82: =IFERROR((IF(ISNUMBER(L82),$D$7*L82,0)+IF(ISNUMBER(M82),$D$8*M82,0)+IF(ISNUMBER(N82),$D$9*N82,0)+IF(ISNUMBER(O82),$D$10*O82,0)+IF(ISNUMBER(P82),$D$11*P82,0)+IF(ISNUMBER(Q82),$D$12*Q82,0))/(IF(ISNUMBER(L82),$D$7,0)+IF(ISNUMBER(M82),$D$8,0)+IF(ISNUMBER(N82),$D$9,0)+IF(ISNUMBER(O82),$D$10,0)+IF(ISNUMBER(P82),$D$11,0)+IF(ISNUMBER(Q82),$D$12,0)),"") | S82: =IFERROR(LN($E$82),"") | T82: =IFERROR($N$7+$N$8*$R$82,"") | U82: =IFERROR($S$82-$T$82,"") | V82: =IFERROR(($U$82-AVERAGE($U$15:$U$85))/STDEV($U$15:$U$85),"") | W82: =IF(ISNUMBER($V$82),IF($V$82>=1.5,"CHEAP",IF($V$82>=0.5,"slightly cheap",IF($V$82<=-1.5,"RICH",IF($V$82<=-0.5,"slightly rich","fair")))),"") | X82: =SUMPRODUCT(--ISNUMBER((D82,G82,H82,I82,J82,K82))) | Y82: =IF(X82>=5,"HIGH",IF(X82>=3,"MED","LOW")) | Z82: =IF(AND(ISNUMBER(S82),X82>=$S$11),S82,"") | AA82: =IF(AND(ISNUMBER(R82),X82>=$S$11),R82,"")
B83: =Tickers!B75 | C83: =Tickers!C75 | D83: =Tickers!E75 | E83: =IFERROR(Tickers!G75,"") | F83: =IFERROR(Tickers!I75,"") | G83: =IFERROR(IF(ISNUMBER(Tickers!K75),Tickers!K75,IF(ISNUMBER(Haver!E75),Haver!E75,IF(ISNUMBER(Tickers!T75),Tickers!T75,""))),"") | H83: =IFERROR(IF(ISNUMBER(Tickers!M75),Tickers!M75,IF(ISNUMBER(Haver!G75),Haver!G75,IF(ISNUMBER(Tickers!U75),Tickers!U75,""))),"") | I83: =IFERROR(IF(ISNUMBER(Tickers!O75),Tickers!O75,IF(ISNUMBER(Haver!I75),Haver!I75,IF(ISNUMBER(Tickers!V75),Tickers!V75,""))),"") | J83: =IFERROR(IF(ISNUMBER(Tickers!Q75),Tickers!Q75,IF(ISNUMBER(Haver!K75),Haver!K75,IF(ISNUMBER(Tickers!W75),Tickers!W75,""))),"") | K83: =IFERROR(IF(ISNUMBER(Tickers!S75),Tickers!S75,IF(ISNUMBER(Haver!M75),Haver!M75,IF(ISNUMBER(Tickers!X75),Tickers!X75,""))),"") | L83: =IFERROR(($D$83-AVERAGE($D$15:$D$85))/STDEV($D$15:$D$85),"") | M83: =IFERROR(($I$83-AVERAGE($I$15:$I$85))/STDEV($I$15:$I$85),"") | N83: =IFERROR(-($J$83-AVERAGE($J$15:$J$85))/STDEV($J$15:$J$85),"") | O83: =IFERROR(-($K$83-AVERAGE($K$15:$K$85))/STDEV($K$15:$K$85),"") | P83: =IFERROR(-($G$83-AVERAGE($G$15:$G$85))/STDEV($G$15:$G$85),"") | Q83: =IFERROR(($H$83-AVERAGE($H$15:$H$85))/STDEV($H$15:$H$85),"") | R83: =IFERROR((IF(ISNUMBER(L83),$D$7*L83,0)+IF(ISNUMBER(M83),$D$8*M83,0)+IF(ISNUMBER(N83),$D$9*N83,0)+IF(ISNUMBER(O83),$D$10*O83,0)+IF(ISNUMBER(P83),$D$11*P83,0)+IF(ISNUMBER(Q83),$D$12*Q83,0))/(IF(ISNUMBER(L83),$D$7,0)+IF(ISNUMBER(M83),$D$8,0)+IF(ISNUMBER(N83),$D$9,0)+IF(ISNUMBER(O83),$D$10,0)+IF(ISNUMBER(P83),$D$11,0)+IF(ISNUMBER(Q83),$D$12,0)),"") | S83: =IFERROR(LN($E$83),"") | T83: =IFERROR($N$7+$N$8*$R$83,"") | U83: =IFERROR($S$83-$T$83,"") | V83: =IFERROR(($U$83-AVERAGE($U$15:$U$85))/STDEV($U$15:$U$85),"") | W83: =IF(ISNUMBER($V$83),IF($V$83>=1.5,"CHEAP",IF($V$83>=0.5,"slightly cheap",IF($V$83<=-1.5,"RICH",IF($V$83<=-0.5,"slightly rich","fair")))),"") | X83: =SUMPRODUCT(--ISNUMBER((D83,G83,H83,I83,J83,K83))) | Y83: =IF(X83>=5,"HIGH",IF(X83>=3,"MED","LOW")) | Z83: =IF(AND(ISNUMBER(S83),X83>=$S$11),S83,"") | AA83: =IF(AND(ISNUMBER(R83),X83>=$S$11),R83,"")
B84: =Tickers!B76 | C84: =Tickers!C76 | D84: =Tickers!E76 | E84: =IFERROR(Tickers!G76,"") | F84: =IFERROR(Tickers!I76,"") | G84: =IFERROR(IF(ISNUMBER(Tickers!K76),Tickers!K76,IF(ISNUMBER(Haver!E76),Haver!E76,IF(ISNUMBER(Tickers!T76),Tickers!T76,""))),"") | H84: =IFERROR(IF(ISNUMBER(Tickers!M76),Tickers!M76,IF(ISNUMBER(Haver!G76),Haver!G76,IF(ISNUMBER(Tickers!U76),Tickers!U76,""))),"") | I84: =IFERROR(IF(ISNUMBER(Tickers!O76),Tickers!O76,IF(ISNUMBER(Haver!I76),Haver!I76,IF(ISNUMBER(Tickers!V76),Tickers!V76,""))),"") | J84: =IFERROR(IF(ISNUMBER(Tickers!Q76),Tickers!Q76,IF(ISNUMBER(Haver!K76),Haver!K76,IF(ISNUMBER(Tickers!W76),Tickers!W76,""))),"") | K84: =IFERROR(IF(ISNUMBER(Tickers!S76),Tickers!S76,IF(ISNUMBER(Haver!M76),Haver!M76,IF(ISNUMBER(Tickers!X76),Tickers!X76,""))),"") | L84: =IFERROR(($D$84-AVERAGE($D$15:$D$85))/STDEV($D$15:$D$85),"") | M84: =IFERROR(($I$84-AVERAGE($I$15:$I$85))/STDEV($I$15:$I$85),"") | N84: =IFERROR(-($J$84-AVERAGE($J$15:$J$85))/STDEV($J$15:$J$85),"") | O84: =IFERROR(-($K$84-AVERAGE($K$15:$K$85))/STDEV($K$15:$K$85),"") | P84: =IFERROR(-($G$84-AVERAGE($G$15:$G$85))/STDEV($G$15:$G$85),"") | Q84: =IFERROR(($H$84-AVERAGE($H$15:$H$85))/STDEV($H$15:$H$85),"") | R84: =IFERROR((IF(ISNUMBER(L84),$D$7*L84,0)+IF(ISNUMBER(M84),$D$8*M84,0)+IF(ISNUMBER(N84),$D$9*N84,0)+IF(ISNUMBER(O84),$D$10*O84,0)+IF(ISNUMBER(P84),$D$11*P84,0)+IF(ISNUMBER(Q84),$D$12*Q84,0))/(IF(ISNUMBER(L84),$D$7,0)+IF(ISNUMBER(M84),$D$8,0)+IF(ISNUMBER(N84),$D$9,0)+IF(ISNUMBER(O84),$D$10,0)+IF(ISNUMBER(P84),$D$11,0)+IF(ISNUMBER(Q84),$D$12,0)),"") | S84: =IFERROR(LN($E$84),"") | T84: =IFERROR($N$7+$N$8*$R$84,"") | U84: =IFERROR($S$84-$T$84,"") | V84: =IFERROR(($U$84-AVERAGE($U$15:$U$85))/STDEV($U$15:$U$85),"") | W84: =IF(ISNUMBER($V$84),IF($V$84>=1.5,"CHEAP",IF($V$84>=0.5,"slightly cheap",IF($V$84<=-1.5,"RICH",IF($V$84<=-0.5,"slightly rich","fair")))),"") | X84: =SUMPRODUCT(--ISNUMBER((D84,G84,H84,I84,J84,K84))) | Y84: =IF(X84>=5,"HIGH",IF(X84>=3,"MED","LOW")) | Z84: =IF(AND(ISNUMBER(S84),X84>=$S$11),S84,"") | AA84: =IF(AND(ISNUMBER(R84),X84>=$S$11),R84,"")
B85: =Tickers!B77 | C85: =Tickers!C77 | D85: =Tickers!E77 | E85: =IFERROR(Tickers!G77,"") | F85: =IFERROR(Tickers!I77,"") | G85: =IFERROR(IF(ISNUMBER(Tickers!K77),Tickers!K77,IF(ISNUMBER(Haver!E77),Haver!E77,IF(ISNUMBER(Tickers!T77),Tickers!T77,""))),"") | H85: =IFERROR(IF(ISNUMBER(Tickers!M77),Tickers!M77,IF(ISNUMBER(Haver!G77),Haver!G77,IF(ISNUMBER(Tickers!U77),Tickers!U77,""))),"") | I85: =IFERROR(IF(ISNUMBER(Tickers!O77),Tickers!O77,IF(ISNUMBER(Haver!I77),Haver!I77,IF(ISNUMBER(Tickers!V77),Tickers!V77,""))),"") | J85: =IFERROR(IF(ISNUMBER(Tickers!Q77),Tickers!Q77,IF(ISNUMBER(Haver!K77),Haver!K77,IF(ISNUMBER(Tickers!W77),Tickers!W77,""))),"") | K85: =IFERROR(IF(ISNUMBER(Tickers!S77),Tickers!S77,IF(ISNUMBER(Haver!M77),Haver!M77,IF(ISNUMBER(Tickers!X77),Tickers!X77,""))),"") | L85: =IFERROR(($D$85-AVERAGE($D$15:$D$85))/STDEV($D$15:$D$85),"") | M85: =IFERROR(($I$85-AVERAGE($I$15:$I$85))/STDEV($I$15:$I$85),"") | N85: =IFERROR(-($J$85-AVERAGE($J$15:$J$85))/STDEV($J$15:$J$85),"") | O85: =IFERROR(-($K$85-AVERAGE($K$15:$K$85))/STDEV($K$15:$K$85),"") | P85: =IFERROR(-($G$85-AVERAGE($G$15:$G$85))/STDEV($G$15:$G$85),"") | Q85: =IFERROR(($H$85-AVERAGE($H$15:$H$85))/STDEV($H$15:$H$85),"") | R85: =IFERROR((IF(ISNUMBER(L85),$D$7*L85,0)+IF(ISNUMBER(M85),$D$8*M85,0)+IF(ISNUMBER(N85),$D$9*N85,0)+IF(ISNUMBER(O85),$D$10*O85,0)+IF(ISNUMBER(P85),$D$11*P85,0)+IF(ISNUMBER(Q85),$D$12*Q85,0))/(IF(ISNUMBER(L85),$D$7,0)+IF(ISNUMBER(M85),$D$8,0)+IF(ISNUMBER(N85),$D$9,0)+IF(ISNUMBER(O85),$D$10,0)+IF(ISNUMBER(P85),$D$11,0)+IF(ISNUMBER(Q85),$D$12,0)),"") | S85: =IFERROR(LN($E$85),"") | T85: =IFERROR($N$7+$N$8*$R$85,"") | U85: =IFERROR($S$85-$T$85,"") | V85: =IFERROR(($U$85-AVERAGE($U$15:$U$85))/STDEV($U$15:$U$85),"") | W85: =IF(ISNUMBER($V$85),IF($V$85>=1.5,"CHEAP",IF($V$85>=0.5,"slightly cheap",IF($V$85<=-1.5,"RICH",IF($V$85<=-0.5,"slightly rich","fair")))),"") | X85: =SUMPRODUCT(--ISNUMBER((D85,G85,H85,I85,J85,K85))) | Y85: =IF(X85>=5,"HIGH",IF(X85>=3,"MED","LOW")) | Z85: =IF(AND(ISNUMBER(S85),X85>=$S$11),S85,"") | AA85: =IF(AND(ISNUMBER(R85),X85>=$S$11),R85,"")

Sheet Tickers
B2: Bloomberg Tickers — single source of truth
B4: One row per sovereign. Yellow cells = ticker not yet supplied — fill in from Bloomberg ECON. Composite ratings update manually.
B6: Country | C6: ISO | D6: BBG_CC | E6: Rating# | F6: EMBI ticker | G6: EMBI bps | H6: CDS ticker | I6: CDS bps | J6: GDP ticker | K6: GDP % | L6: CPI ticker | M6: CPI % | N6: Govt debt ticker | O6: Debt %GDP | P6: CurAcc ticker | Q6: CA %GDP | R6: FXRes ticker | S6: Reserves | T6: Manual GDP | U6: Manual CPI | V6: Manual Debt | W6: Manual CA | X6: Manual FXRes
B7: ARGENTINA | C7: ARG | D7: AR | E7: 19 | F7: JPSYARZW Index | G7: =IFERROR(IF(F7="",NA(),BDP(F7,"PX_LAST")),NA()) | H7: CARGEN CDS USD SR 5Y D14 Corp | I7: =IFERROR(IF(H7="",NA(),BDP(H7,"PX_LAST")),NA()) | J7: ARGDPYY Index | K7: =IFERROR(IF(J7="",NA(),BDP(J7,"PX_LAST")),NA()) | L7: ARCPIYOY Index | M7: =IFERROR(IF(L7="",NA(),BDP(L7,"PX_LAST")),NA()) | O7: =IFERROR(IF(N7="",NA(),BDP(N7,"PX_LAST")),NA()) | Q7: =IFERROR(IF(P7="",NA(),BDP(P7,"PX_LAST")),NA()) | R7: ARIRESV Index | S7: =IFERROR(IF(R7="",NA(),BDP(R7,"PX_LAST")),NA())
B8: BOLIVIA | C8: BOL | D8: BO | E8: 17 | F8: JPSYBVZW Index | G8: =IFERROR(IF(F8="",NA(),BDP(F8,"PX_LAST")),NA()) | I8: =IFERROR(IF(H8="",NA(),BDP(H8,"PX_LAST")),NA()) | K8: =IFERROR(IF(J8="",NA(),BDP(J8,"PX_LAST")),NA()) | L8: BOCPIYOY Index | M8: =IFERROR(IF(L8="",NA(),BDP(L8,"PX_LAST")),NA()) | O8: =IFERROR(IF(N8="",NA(),BDP(N8,"PX_LAST")),NA()) | Q8: =IFERROR(IF(P8="",NA(),BDP(P8,"PX_LAST")),NA()) | S8: =IFERROR(IF(R8="",NA(),BDP(R8,"PX_LAST")),NA())
B9: BRAZIL | C9: BRA | D9: BZ | E9: 12 | F9: JPSYBRZW Index | G9: =IFERROR(IF(F9="",NA(),BDP(F9,"PX_LAST")),NA()) | H9: CBRAZL CDS USD SR 5Y D14 Corp | I9: =IFERROR(IF(H9="",NA(),BDP(H9,"PX_LAST")),NA()) | J9: BZGDPYOY Index | K9: =IFERROR(IF(J9="",NA(),BDP(J9,"PX_LAST")),NA()) | L9: BZPIIPCY Index | M9: =IFERROR(IF(L9="",NA(),BDP(L9,"PX_LAST")),NA()) | O9: =IFERROR(IF(N9="",NA(),BDP(N9,"PX_LAST")),NA()) | P9: BZCAR%G Index | Q9: =IFERROR(IF(P9="",NA(),BDP(P9,"PX_LAST")),NA()) | R9: BZRSTOTL Index | S9: =IFERROR(IF(R9="",NA(),BDP(R9,"PX_LAST")),NA())
B10: CHILE | C10: CHL | D10: CH | E10: 6 | F10: JPSYCHZW Index | G10: =IFERROR(IF(F10="",NA(),BDP(F10,"PX_LAST")),NA()) | H10: CCHILE CDS USD SR 5Y D14 Corp | I10: =IFERROR(IF(H10="",NA(),BDP(H10,"PX_LAST")),NA()) | J10: CHGDPNYR Index | K10: =IFERROR(IF(J10="",NA(),BDP(J10,"PX_LAST")),NA()) | L10: CNPINSYO Index | M10: =IFERROR(IF(L10="",NA(),BDP(L10,"PX_LAST")),NA()) | O10: =IFERROR(IF(N10="",NA(),BDP(N10,"PX_LAST")),NA()) | P10: CHCABAL$ Index | Q10: =IFERROR(IF(P10="",NA(),BDP(P10,"PX_LAST")),NA()) | R10: CHIRTOTL Index | S10: =IFERROR(IF(R10="",NA(),BDP(R10,"PX_LAST")),NA())
B11: COLOMBIA | C11: COL | D11: CB | E11: 11 | F11: JPSYCLZW Index | G11: =IFERROR(IF(F11="",NA(),BDP(F11,"PX_LAST")),NA()) | H11: CCOLOM CDS USD SR 5Y D14 Corp | I11: =IFERROR(IF(H11="",NA(),BDP(H11,"PX_LAST")),NA()) | J11: COGDPYOY Index | K11: =IFERROR(IF(J11="",NA(),BDP(J11,"PX_LAST")),NA()) | L11: COCPIYOY Index | M11: =IFERROR(IF(L11="",NA(),BDP(L11,"PX_LAST")),NA()) | O11: =IFERROR(IF(N11="",NA(),BDP(N11,"PX_LAST")),NA()) | P11: COCABAL$ Index | Q11: =IFERROR(IF(P11="",NA(),BDP(P11,"PX_LAST")),NA()) | R11: COIRTOTL Index | S11: =IFERROR(IF(R11="",NA(),BDP(R11,"PX_LAST")),NA())
B12: COSTA RICA | C12: CRI | D12: CR | E12: 13 | F12: JPSYCRZW Index | G12: =IFERROR(IF(F12="",NA(),BDP(F12,"PX_LAST")),NA()) | H12: CCOSTA CDS USD SR 5Y D14 Corp | I12: =IFERROR(IF(H12="",NA(),BDP(H12,"PX_LAST")),NA()) | J12: CRGDPYOY Index | K12: =IFERROR(IF(J12="",NA(),BDP(J12,"PX_LAST")),NA()) | L12: CRCPIYOY Index | M12: =IFERROR(IF(L12="",NA(),BDP(L12,"PX_LAST")),NA()) | O12: =IFERROR(IF(N12="",NA(),BDP(N12,"PX_LAST")),NA()) | Q12: =IFERROR(IF(P12="",NA(),BDP(P12,"PX_LAST")),NA()) | S12: =IFERROR(IF(R12="",NA(),BDP(R12,"PX_LAST")),NA())
B13: DOMINICAN REPUBLIC | C13: DOM | D13: DR | E13: 13 | F13: JPSYDRZW Index | G13: =IFERROR(IF(F13="",NA(),BDP(F13,"PX_LAST")),NA()) | H13: CDOMRP CDS USD SR 5Y D14 Corp | I13: =IFERROR(IF(H13="",NA(),BDP(H13,"PX_LAST")),NA()) | J13: DRGDPYOY Index | K13: =IFERROR(IF(J13="",NA(),BDP(J13,"PX_LAST")),NA()) | L13: DRCPIYOY Index | M13: =IFERROR(IF(L13="",NA(),BDP(L13,"PX_LAST")),NA()) | O13: =IFERROR(IF(N13="",NA(),BDP(N13,"PX_LAST")),NA()) | Q13: =IFERROR(IF(P13="",NA(),BDP(P13,"PX_LAST")),NA()) | S13: =IFERROR(IF(R13="",NA(),BDP(R13,"PX_LAST")),NA())
B14: ECUADOR | C14: ECU | D14: EC | E14: 18 | F14: JPSYECZW Index | G14: =IFERROR(IF(F14="",NA(),BDP(F14,"PX_LAST")),NA()) | H14: CECUA CDS USD SR 5Y D14 Corp | I14: =IFERROR(IF(H14="",NA(),BDP(H14,"PX_LAST")),NA()) | J14: ECGDPYOY Index | K14: =IFERROR(IF(J14="",NA(),BDP(J14,"PX_LAST")),NA()) | L14: ECCPIYOY Index | M14: =IFERROR(IF(L14="",NA(),BDP(L14,"PX_LAST")),NA()) | O14: =IFERROR(IF(N14="",NA(),BDP(N14,"PX_LAST")),NA()) | Q14: =IFERROR(IF(P14="",NA(),BDP(P14,"PX_LAST")),NA()) | S14: =IFERROR(IF(R14="",NA(),BDP(R14,"PX_LAST")),NA())
B15: EL SALVADOR | C15: SLV | D15: ES | E15: 18 | F15: JPSYESZW Index | G15: =IFERROR(IF(F15="",NA(),BDP(F15,"PX_LAST")),NA()) | H15: CELSAL CDS USD SR 5Y D14 Corp | I15: =IFERROR(IF(H15="",NA(),BDP(H15,"PX_LAST")),NA()) | K15: =IFERROR(IF(J15="",NA(),BDP(J15,"PX_LAST")),NA()) | L15: ESCPIYOY Index | M15: =IFERROR(IF(L15="",NA(),BDP(L15,"PX_LAST")),NA()) | O15: =IFERROR(IF(N15="",NA(),BDP(N15,"PX_LAST")),NA()) | Q15: =IFERROR(IF(P15="",NA(),BDP(P15,"PX_LAST")),NA()) | S15: =IFERROR(IF(R15="",NA(),BDP(R15,"PX_LAST")),NA())
B16: GUATEMALA | C16: GTM | D16: GT | E16: 11 | F16: JPSYGTZW Index | G16: =IFERROR(IF(F16="",NA(),BDP(F16,"PX_LAST")),NA()) | I16: =IFERROR(IF(H16="",NA(),BDP(H16,"PX_LAST")),NA()) | K16: =IFERROR(IF(J16="",NA(),BDP(J16,"PX_LAST")),NA()) | L16: GTCPIYOY Index | M16: =IFERROR(IF(L16="",NA(),BDP(L16,"PX_LAST")),NA()) | O16: =IFERROR(IF(N16="",NA(),BDP(N16,"PX_LAST")),NA()) | Q16: =IFERROR(IF(P16="",NA(),BDP(P16,"PX_LAST")),NA()) | S16: =IFERROR(IF(R16="",NA(),BDP(R16,"PX_LAST")),NA())
B17: JAMAICA | C17: JAM | D17: JM | E17: 14 | F17: JPSYJMZW Index | G17: =IFERROR(IF(F17="",NA(),BDP(F17,"PX_LAST")),NA()) | I17: =IFERROR(IF(H17="",NA(),BDP(H17,"PX_LAST")),NA()) | K17: =IFERROR(IF(J17="",NA(),BDP(J17,"PX_LAST")),NA()) | L17: JAMCPIY Index | M17: =IFERROR(IF(L17="",NA(),BDP(L17,"PX_LAST")),NA()) | O17: =IFERROR(IF(N17="",NA(),BDP(N17,"PX_LAST")),NA()) | Q17: =IFERROR(IF(P17="",NA(),BDP(P17,"PX_LAST")),NA()) | S17: =IFERROR(IF(R17="",NA(),BDP(R17,"PX_LAST")),NA())
B18: MEXICO | C18: MEX | D18: MX | E18: 10 | F18: JPSYMXZW Index | G18: =IFERROR(IF(F18="",NA(),BDP(F18,"PX_LAST")),NA()) | H18: CMEX CDS USD SR 5Y D14 Corp | I18: =IFERROR(IF(H18="",NA(),BDP(H18,"PX_LAST")),NA()) | J18: MXGDPYOY Index | K18: =IFERROR(IF(J18="",NA(),BDP(J18,"PX_LAST")),NA()) | L18: MXCPYOY% Index | M18: =IFERROR(IF(L18="",NA(),BDP(L18,"PX_LAST")),NA()) | O18: =IFERROR(IF(N18="",NA(),BDP(N18,"PX_LAST")),NA()) | P18: MXCABAL$ Index | Q18: =IFERROR(IF(P18="",NA(),BDP(P18,"PX_LAST")),NA()) | R18: MXIRTOTL Index | S18: =IFERROR(IF(R18="",NA(),BDP(R18,"PX_LAST")),NA())
B19: PANAMA | C19: PAN | D19: PA | E19: 10 | F19: JPSYPNZW Index | G19: =IFERROR(IF(F19="",NA(),BDP(F19,"PX_LAST")),NA()) | H19: CPANAM CDS USD SR 5Y D14 Corp | I19: =IFERROR(IF(H19="",NA(),BDP(H19,"PX_LAST")),NA()) | K19: =IFERROR(IF(J19="",NA(),BDP(J19,"PX_LAST")),NA()) | L19: PNCPYOY Index | M19: =IFERROR(IF(L19="",NA(),BDP(L19,"PX_LAST")),NA()) | O19: =IFERROR(IF(N19="",NA(),BDP(N19,"PX_LAST")),NA()) | Q19: =IFERROR(IF(P19="",NA(),BDP(P19,"PX_LAST")),NA()) | S19: =IFERROR(IF(R19="",NA(),BDP(R19,"PX_LAST")),NA())
B20: PARAGUAY | C20: PRY | D20: PY | E20: 10 | F20: JPSYPGZW Index | G20: =IFERROR(IF(F20="",NA(),BDP(F20,"PX_LAST")),NA()) | I20: =IFERROR(IF(H20="",NA(),BDP(H20,"PX_LAST")),NA()) | J20: PYGDPYOY Index | K20: =IFERROR(IF(J20="",NA(),BDP(J20,"PX_LAST")),NA()) | L20: PYCPIYOY Index | M20: =IFERROR(IF(L20="",NA(),BDP(L20,"PX_LAST")),NA()) | O20: =IFERROR(IF(N20="",NA(),BDP(N20,"PX_LAST")),NA()) | Q20: =IFERROR(IF(P20="",NA(),BDP(P20,"PX_LAST")),NA()) | S20: =IFERROR(IF(R20="",NA(),BDP(R20,"PX_LAST")),NA())
B21: PERU | C21: PER | D21: PE | E21: 9 | F21: JPSYPEZW Index | G21: =IFERROR(IF(F21="",NA(),BDP(F21,"PX_LAST")),NA()) | H21: CPERU CDS USD SR 5Y D14 Corp | I21: =IFERROR(IF(H21="",NA(),BDP(H21,"PX_LAST")),NA()) | J21: PEGDPYOY Index | K21: =IFERROR(IF(J21="",NA(),BDP(J21,"PX_LAST")),NA()) | L21: PRCPIYOY Index | M21: =IFERROR(IF(L21="",NA(),BDP(L21,"PX_LAST")),NA()) | O21: =IFERROR(IF(N21="",NA(),BDP(N21,"PX_LAST")),NA()) | P21: PEBPCAB% Index | Q21: =IFERROR(IF(P21="",NA(),BDP(P21,"PX_LAST")),NA()) | R21: PEIRTOTL Index | S21: =IFERROR(IF(R21="",NA(),BDP(R21,"PX_LAST")),NA())
B22: URUGUAY | C22: URY | D22: UY | E22: 9 | F22: JPSYUYZW Index | G22: =IFERROR(IF(F22="",NA(),BDP(F22,"PX_LAST")),NA()) | H22: CURUGY CDS USD SR 5Y D14 Corp | I22: =IFERROR(IF(H22="",NA(),BDP(H22,"PX_LAST")),NA()) | J22: URGDPYOY Index | K22: =IFERROR(IF(J22="",NA(),BDP(J22,"PX_LAST")),NA()) | L22: UYCPIYOY Index | M22: =IFERROR(IF(L22="",NA(),BDP(L22,"PX_LAST")),NA()) | O22: =IFERROR(IF(N22="",NA(),BDP(N22,"PX_LAST")),NA()) | Q22: =IFERROR(IF(P22="",NA(),BDP(P22,"PX_LAST")),NA()) | R22: URIRTOTL Index | S22: =IFERROR(IF(R22="",NA(),BDP(R22,"PX_LAST")),NA())
B23: TRINIDAD & TOBAGO | C23: TTO | D23: TT | E23: 13 | F23: JPSYTTZW Index | G23: =IFERROR(IF(F23="",NA(),BDP(F23,"PX_LAST")),NA()) | I23: =IFERROR(IF(H23="",NA(),BDP(H23,"PX_LAST")),NA()) | K23: =IFERROR(IF(J23="",NA(),BDP(J23,"PX_LAST")),NA()) | L23: TTCPIYOY Index | M23: =IFERROR(IF(L23="",NA(),BDP(L23,"PX_LAST")),NA()) | O23: =IFERROR(IF(N23="",NA(),BDP(N23,"PX_LAST")),NA()) | Q23: =IFERROR(IF(P23="",NA(),BDP(P23,"PX_LAST")),NA()) | S23: =IFERROR(IF(R23="",NA(),BDP(R23,"PX_LAST")),NA())
B24: ARMENIA | C24: ARM | D24: AM | E24: 13 | F24: JPSYAMZW Index | G24: =IFERROR(IF(F24="",NA(),BDP(F24,"PX_LAST")),NA()) | I24: =IFERROR(IF(H24="",NA(),BDP(H24,"PX_LAST")),NA()) | K24: =IFERROR(IF(J24="",NA(),BDP(J24,"PX_LAST")),NA()) | M24: =IFERROR(IF(L24="",NA(),BDP(L24,"PX_LAST")),NA()) | O24: =IFERROR(IF(N24="",NA(),BDP(N24,"PX_LAST")),NA()) | Q24: =IFERROR(IF(P24="",NA(),BDP(P24,"PX_LAST")),NA()) | S24: =IFERROR(IF(R24="",NA(),BDP(R24,"PX_LAST")),NA())
B25: AZERBAIJAN | C25: AZE | D25: AZ | E25: 11 | F25: JPSYAZZW Index | G25: =IFERROR(IF(F25="",NA(),BDP(F25,"PX_LAST")),NA()) | I25: =IFERROR(IF(H25="",NA(),BDP(H25,"PX_LAST")),NA()) | K25: =IFERROR(IF(J25="",NA(),BDP(J25,"PX_LAST")),NA()) | M25: =IFERROR(IF(L25="",NA(),BDP(L25,"PX_LAST")),NA()) | O25: =IFERROR(IF(N25="",NA(),BDP(N25,"PX_LAST")),NA()) | Q25: =IFERROR(IF(P25="",NA(),BDP(P25,"PX_LAST")),NA()) | S25: =IFERROR(IF(R25="",NA(),BDP(R25,"PX_LAST")),NA())
B26: BELARUS | C26: BLR | D26: BY | E26: 22 | F26: JPSYBYZW Index | G26: =IFERROR(IF(F26="",NA(),BDP(F26,"PX_LAST")),NA()) | I26: =IFERROR(IF(H26="",NA(),BDP(H26,"PX_LAST")),NA()) | J26: BYGDPYOY Index | K26: =IFERROR(IF(J26="",NA(),BDP(J26,"PX_LAST")),NA()) | L26: BYCPIYOY Index | M26: =IFERROR(IF(L26="",NA(),BDP(L26,"PX_LAST")),NA()) | O26: =IFERROR(IF(N26="",NA(),BDP(N26,"PX_LAST")),NA()) | Q26: =IFERROR(IF(P26="",NA(),BDP(P26,"PX_LAST")),NA()) | S26: =IFERROR(IF(R26="",NA(),BDP(R26,"PX_LAST")),NA())
B27: CROATIA | C27: HRV | D27: CR | E27: 9 | F27: JPSYCRSW Index | G27: =IFERROR(IF(F27="",NA(),BDP(F27,"PX_LAST")),NA()) | H27: CCROAT CDS USD SR 5Y D14 Corp | I27: =IFERROR(IF(H27="",NA(),BDP(H27,"PX_LAST")),NA()) | J27: CRGDPYOY Index | K27: =IFERROR(IF(J27="",NA(),BDP(J27,"PX_LAST")),NA()) | L27: CRCPIYOY Index | M27: =IFERROR(IF(L27="",NA(),BDP(L27,"PX_LAST")),NA()) | O27: =IFERROR(IF(N27="",NA(),BDP(N27,"PX_LAST")),NA()) | Q27: =IFERROR(IF(P27="",NA(),BDP(P27,"PX_LAST")),NA()) | S27: =IFERROR(IF(R27="",NA(),BDP(R27,"PX_LAST")),NA())
B28: GEORGIA | C28: GEO | D28: GE | E28: 12 | F28: JPSYGEZW Index | G28: =IFERROR(IF(F28="",NA(),BDP(F28,"PX_LAST")),NA()) | I28: =IFERROR(IF(H28="",NA(),BDP(H28,"PX_LAST")),NA()) | J28: GEGDPYOY Index | K28: =IFERROR(IF(J28="",NA(),BDP(J28,"PX_LAST")),NA()) | L28: GECPIYOY Index | M28: =IFERROR(IF(L28="",NA(),BDP(L28,"PX_LAST")),NA()) | O28: =IFERROR(IF(N28="",NA(),BDP(N28,"PX_LAST")),NA()) | Q28: =IFERROR(IF(P28="",NA(),BDP(P28,"PX_LAST")),NA()) | S28: =IFERROR(IF(R28="",NA(),BDP(R28,"PX_LAST")),NA())
B29: HUNGARY | C29: HUN | D29: HU | E29: 10 | F29: JPSYHNZW Index | G29: =IFERROR(IF(F29="",NA(),BDP(F29,"PX_LAST")),NA()) | H29: CHUN CDS USD SR 5Y D14 Corp | I29: =IFERROR(IF(H29="",NA(),BDP(H29,"PX_LAST")),NA()) | J29: HUGDPYOY Index | K29: =IFERROR(IF(J29="",NA(),BDP(J29,"PX_LAST")),NA()) | L29: HUCPIYOY Index | M29: =IFERROR(IF(L29="",NA(),BDP(L29,"PX_LAST")),NA()) | O29: =IFERROR(IF(N29="",NA(),BDP(N29,"PX_LAST")),NA()) | P29: HUCAR%G Index | Q29: =IFERROR(IF(P29="",NA(),BDP(P29,"PX_LAST")),NA()) | R29: HUIRTOTL Index | S29: =IFERROR(IF(R29="",NA(),BDP(R29,"PX_LAST")),NA())
B30: KAZAKHSTAN | C30: KAZ | D30: KZ | E30: 10 | F30: JPSYKZZW Index | G30: =IFERROR(IF(F30="",NA(),BDP(F30,"PX_LAST")),NA()) | H30: CKAZAKH CDS USD SR 5Y D14 Corp | I30: =IFERROR(IF(H30="",NA(),BDP(H30,"PX_LAST")),NA()) | J30: KZGDPYOY Index | K30: =IFERROR(IF(J30="",NA(),BDP(J30,"PX_LAST")),NA()) | L30: KZCPIYOY Index | M30: =IFERROR(IF(L30="",NA(),BDP(L30,"PX_LAST")),NA()) | O30: =IFERROR(IF(N30="",NA(),BDP(N30,"PX_LAST")),NA()) | Q30: =IFERROR(IF(P30="",NA(),BDP(P30,"PX_LAST")),NA()) | R30: KZIRTOTL Index | S30: =IFERROR(IF(R30="",NA(),BDP(R30,"PX_LAST")),NA())
B31: LATVIA | C31: LVA | D31: LV | E31: 7 | F31: JPSYLVZW Index | G31: =IFERROR(IF(F31="",NA(),BDP(F31,"PX_LAST")),NA()) | H31: CLATVIA CDS USD SR 5Y D14 Corp | I31: =IFERROR(IF(H31="",NA(),BDP(H31,"PX_LAST")),NA()) | J31: LVGDPYOY Index | K31: =IFERROR(IF(J31="",NA(),BDP(J31,"PX_LAST")),NA()) | L31: LVCPIYOY Index | M31: =IFERROR(IF(L31="",NA(),BDP(L31,"PX_LAST")),NA()) | O31: =IFERROR(IF(N31="",NA(),BDP(N31,"PX_LAST")),NA()) | Q31: =IFERROR(IF(P31="",NA(),BDP(P31,"PX_LAST")),NA()) | S31: =IFERROR(IF(R31="",NA(),BDP(R31,"PX_LAST")),NA())
B32: LITHUANIA | C32: LTU | D32: LT | E32: 6 | F32: JPSYLIZW Index | G32: =IFERROR(IF(F32="",NA(),BDP(F32,"PX_LAST")),NA()) | H32: CLITHUN CDS USD SR 5Y D14 Corp | I32: =IFERROR(IF(H32="",NA(),BDP(H32,"PX_LAST")),NA()) | J32: LTGDPYOY Index | K32: =IFERROR(IF(J32="",NA(),BDP(J32,"PX_LAST")),NA()) | L32: LTCPIYOY Index | M32: =IFERROR(IF(L32="",NA(),BDP(L32,"PX_LAST")),NA()) | O32: =IFERROR(IF(N32="",NA(),BDP(N32,"PX_LAST")),NA()) | Q32: =IFERROR(IF(P32="",NA(),BDP(P32,"PX_LAST")),NA()) | S32: =IFERROR(IF(R32="",NA(),BDP(R32,"PX_LAST")),NA())
B33: NORTH MACEDONIA | C33: MKD | D33: MK | E33: 13 | F33: JPSYMKZW Index | G33: =IFERROR(IF(F33="",NA(),BDP(F33,"PX_LAST")),NA()) | I33: =IFERROR(IF(H33="",NA(),BDP(H33,"PX_LAST")),NA()) | K33: =IFERROR(IF(J33="",NA(),BDP(J33,"PX_LAST")),NA()) | M33: =IFERROR(IF(L33="",NA(),BDP(L33,"PX_LAST")),NA()) | O33: =IFERROR(IF(N33="",NA(),BDP(N33,"PX_LAST")),NA()) | Q33: =IFERROR(IF(P33="",NA(),BDP(P33,"PX_LAST")),NA()) | S33: =IFERROR(IF(R33="",NA(),BDP(R33,"PX_LAST")),NA())
B34: POLAND | C34: POL | D34: PL | E34: 7 | F34: JPSYPOSW Index | G34: =IFERROR(IF(F34="",NA(),BDP(F34,"PX_LAST")),NA()) | H34: CPOLAND CDS USD SR 5Y D14 Corp | I34: =IFERROR(IF(H34="",NA(),BDP(H34,"PX_LAST")),NA()) | J34: POGDPYOY Index | K34: =IFERROR(IF(J34="",NA(),BDP(J34,"PX_LAST")),NA()) | L34: POCPIYOY Index | M34: =IFERROR(IF(L34="",NA(),BDP(L34,"PX_LAST")),NA()) | O34: =IFERROR(IF(N34="",NA(),BDP(N34,"PX_LAST")),NA()) | P34: POCAR%G Index | Q34: =IFERROR(IF(P34="",NA(),BDP(P34,"PX_LAST")),NA()) | R34: POIRTOTL Index | S34: =IFERROR(IF(R34="",NA(),BDP(R34,"PX_LAST")),NA())
B35: ROMANIA | C35: ROU | D35: RM | E35: 10 | F35: JPSYROZW Index | G35: =IFERROR(IF(F35="",NA(),BDP(F35,"PX_LAST")),NA()) | H35: CROMAN CDS USD SR 5Y D14 Corp | I35: =IFERROR(IF(H35="",NA(),BDP(H35,"PX_LAST")),NA()) | J35: RMGDPYOY Index | K35: =IFERROR(IF(J35="",NA(),BDP(J35,"PX_LAST")),NA()) | L35: RMCPIYOY Index | M35: =IFERROR(IF(L35="",NA(),BDP(L35,"PX_LAST")),NA()) | O35: =IFERROR(IF(N35="",NA(),BDP(N35,"PX_LAST")),NA()) | P35: RMCAR%G Index | Q35: =IFERROR(IF(P35="",NA(),BDP(P35,"PX_LAST")),NA()) | R35: RMIRTOTL Index | S35: =IFERROR(IF(R35="",NA(),BDP(R35,"PX_LAST")),NA())
B36: RUSSIAN FEDERATION | C36: RUS | D36: RU | E36: 22 | F36: JPSYRUZW Index | G36: =IFERROR(IF(F36="",NA(),BDP(F36,"PX_LAST")),NA()) | H36: CRUSS CDS USD SR 5Y D14 Corp | I36: =IFERROR(IF(H36="",NA(),BDP(H36,"PX_LAST")),NA()) | J36: RUGDPYOY Index | K36: =IFERROR(IF(J36="",NA(),BDP(J36,"PX_LAST")),NA()) | L36: RUCPIYOY Index | M36: =IFERROR(IF(L36="",NA(),BDP(L36,"PX_LAST")),NA()) | O36: =IFERROR(IF(N36="",NA(),BDP(N36,"PX_LAST")),NA()) | Q36: =IFERROR(IF(P36="",NA(),BDP(P36,"PX_LAST")),NA()) | R36: RUIRTOTL Index | S36: =IFERROR(IF(R36="",NA(),BDP(R36,"PX_LAST")),NA())
B37: SERBIA | C37: SRB | D37: CS | E37: 11 | F37: JPSYCSZW Index | G37: =IFERROR(IF(F37="",NA(),BDP(F37,"PX_LAST")),NA()) | H37: CSERB CDS USD SR 5Y D14 Corp | I37: =IFERROR(IF(H37="",NA(),BDP(H37,"PX_LAST")),NA()) | J37: CSGDPYOY Index | K37: =IFERROR(IF(J37="",NA(),BDP(J37,"PX_LAST")),NA()) | L37: CSCPIYOY Index | M37: =IFERROR(IF(L37="",NA(),BDP(L37,"PX_LAST")),NA()) | O37: =IFERROR(IF(N37="",NA(),BDP(N37,"PX_LAST")),NA()) | Q37: =IFERROR(IF(P37="",NA(),BDP(P37,"PX_LAST")),NA()) | S37: =IFERROR(IF(R37="",NA(),BDP(R37,"PX_LAST")),NA())
B38: SLOVAKIA | C38: SVK | D38: SK | E38: 7 | F38: JPSYSKZW Index | G38: =IFERROR(IF(F38="",NA(),BDP(F38,"PX_LAST")),NA()) | H38: CSLOVAK CDS USD SR 5Y D14 Corp | I38: =IFERROR(IF(H38="",NA(),BDP(H38,"PX_LAST")),NA()) | J38: SXGDPYOY Index | K38: =IFERROR(IF(J38="",NA(),BDP(J38,"PX_LAST")),NA()) | L38: SXCPIYOY Index | M38: =IFERROR(IF(L38="",NA(),BDP(L38,"PX_LAST")),NA()) | O38: =IFERROR(IF(N38="",NA(),BDP(N38,"PX_LAST")),NA()) | Q38: =IFERROR(IF(P38="",NA(),BDP(P38,"PX_LAST")),NA()) | S38: =IFERROR(IF(R38="",NA(),BDP(R38,"PX_LAST")),NA())
B39: SLOVENIA | C39: SVN | D39: SJ | E39: 6 | F39: JPSYSJZW Index | G39: =IFERROR(IF(F39="",NA(),BDP(F39,"PX_LAST")),NA()) | H39: CSLOVEN CDS USD SR 5Y D14 Corp | I39: =IFERROR(IF(H39="",NA(),BDP(H39,"PX_LAST")),NA()) | J39: SJGDPYOY Index | K39: =IFERROR(IF(J39="",NA(),BDP(J39,"PX_LAST")),NA()) | L39: SJCPIYOY Index | M39: =IFERROR(IF(L39="",NA(),BDP(L39,"PX_LAST")),NA()) | O39: =IFERROR(IF(N39="",NA(),BDP(N39,"PX_LAST")),NA()) | Q39: =IFERROR(IF(P39="",NA(),BDP(P39,"PX_LAST")),NA()) | S39: =IFERROR(IF(R39="",NA(),BDP(R39,"PX_LAST")),NA())
B40: TURKEY | C40: TUR | D40: TU | E40: 15 | F40: JPSYTRZW Index | G40: =IFERROR(IF(F40="",NA(),BDP(F40,"PX_LAST")),NA()) | H40: CTURK CDS USD SR 5Y D14 Corp | I40: =IFERROR(IF(H40="",NA(),BDP(H40,"PX_LAST")),NA()) | J40: TUGDPYOY Index | K40: =IFERROR(IF(J40="",NA(),BDP(J40,"PX_LAST")),NA()) | L40: TUCPIYOY Index | M40: =IFERROR(IF(L40="",NA(),BDP(L40,"PX_LAST")),NA()) | O40: =IFERROR(IF(N40="",NA(),BDP(N40,"PX_LAST")),NA()) | P40: TUCAR%G Index | Q40: =IFERROR(IF(P40="",NA(),BDP(P40,"PX_LAST")),NA()) | R40: TUIRTOTL Index | S40: =IFERROR(IF(R40="",NA(),BDP(R40,"PX_LAST")),NA())
B41: UKRAINE | C41: UKR | D41: UK | E41: 19 | F41: JPSYUKZW Index | G41: =IFERROR(IF(F41="",NA(),BDP(F41,"PX_LAST")),NA()) | H41: CUKRAIN CDS USD SR 5Y D14 Corp | I41: =IFERROR(IF(H41="",NA(),BDP(H41,"PX_LAST")),NA()) | J41: UKGDPYOY Index | K41: =IFERROR(IF(J41="",NA(),BDP(J41,"PX_LAST")),NA()) | L41: UKCPIYOY Index | M41: =IFERROR(IF(L41="",NA(),BDP(L41,"PX_LAST")),NA()) | O41: =IFERROR(IF(N41="",NA(),BDP(N41,"PX_LAST")),NA()) | Q41: =IFERROR(IF(P41="",NA(),BDP(P41,"PX_LAST")),NA()) | R41: UKIRTOTL Index | S41: =IFERROR(IF(R41="",NA(),BDP(R41,"PX_LAST")),NA())
B42: UZBEKISTAN | C42: UZB | D42: UZ | E42: 13 | F42: JPSYUZZW Index | G42: =IFERROR(IF(F42="",NA(),BDP(F42,"PX_LAST")),NA()) | I42: =IFERROR(IF(H42="",NA(),BDP(H42,"PX_LAST")),NA()) | K42: =IFERROR(IF(J42="",NA(),BDP(J42,"PX_LAST")),NA()) | M42: =IFERROR(IF(L42="",NA(),BDP(L42,"PX_LAST")),NA()) | O42: =IFERROR(IF(N42="",NA(),BDP(N42,"PX_LAST")),NA()) | Q42: =IFERROR(IF(P42="",NA(),BDP(P42,"PX_LAST")),NA()) | S42: =IFERROR(IF(R42="",NA(),BDP(R42,"PX_LAST")),NA())
B43: BAHRAIN | C43: BHR | D43: BH | E43: 14 | F43: JPEGBHZW Index | G43: =IFERROR(IF(F43="",NA(),BDP(F43,"PX_LAST")),NA()) | H43: CBHRAIN CDS USD SR 5Y D14 Corp | I43: =IFERROR(IF(H43="",NA(),BDP(H43,"PX_LAST")),NA()) | K43: =IFERROR(IF(J43="",NA(),BDP(J43,"PX_LAST")),NA()) | L43: BHCPIYOY Index | M43: =IFERROR(IF(L43="",NA(),BDP(L43,"PX_LAST")),NA()) | O43: =IFERROR(IF(N43="",NA(),BDP(N43,"PX_LAST")),NA()) | Q43: =IFERROR(IF(P43="",NA(),BDP(P43,"PX_LAST")),NA()) | S43: =IFERROR(IF(R43="",NA(),BDP(R43,"PX_LAST")),NA())
B44: EGYPT | C44: EGY | D44: EG | E44: 17 | F44: JPSYEGZW Index | G44: =IFERROR(IF(F44="",NA(),BDP(F44,"PX_LAST")),NA()) | H44: CEGYPT CDS USD SR 5Y D14 Corp | I44: =IFERROR(IF(H44="",NA(),BDP(H44,"PX_LAST")),NA()) | J44: EGGDPYOY Index | K44: =IFERROR(IF(J44="",NA(),BDP(J44,"PX_LAST")),NA()) | L44: EGCPIYOY Index | M44: =IFERROR(IF(L44="",NA(),BDP(L44,"PX_LAST")),NA()) | O44: =IFERROR(IF(N44="",NA(),BDP(N44,"PX_LAST")),NA()) | Q44: =IFERROR(IF(P44="",NA(),BDP(P44,"PX_LAST")),NA()) | R44: EGIRTOTL Index | S44: =IFERROR(IF(R44="",NA(),BDP(R44,"PX_LAST")),NA())
B45: IRAQ | C45: IRQ | D45: IQ | E45: 17 | F45: JPSYIQZW Index | G45: =IFERROR(IF(F45="",NA(),BDP(F45,"PX_LAST")),NA()) | I45: =IFERROR(IF(H45="",NA(),BDP(H45,"PX_LAST")),NA()) | K45: =IFERROR(IF(J45="",NA(),BDP(J45,"PX_LAST")),NA()) | M45: =IFERROR(IF(L45="",NA(),BDP(L45,"PX_LAST")),NA()) | O45: =IFERROR(IF(N45="",NA(),BDP(N45,"PX_LAST")),NA()) | Q45: =IFERROR(IF(P45="",NA(),BDP(P45,"PX_LAST")),NA()) | S45: =IFERROR(IF(R45="",NA(),BDP(R45,"PX_LAST")),NA())
B46: ISRAEL | C46: ISR | D46: IL | E46: 6 | F46: JPSYISZW Index | G46: =IFERROR(IF(F46="",NA(),BDP(F46,"PX_LAST")),NA()) | H46: CISRAEL CDS USD SR 5Y D14 Corp | I46: =IFERROR(IF(H46="",NA(),BDP(H46,"PX_LAST")),NA()) | J46: ISGDPYOY Index | K46: =IFERROR(IF(J46="",NA(),BDP(J46,"PX_LAST")),NA()) | L46: ISCPIYOY Index | M46: =IFERROR(IF(L46="",NA(),BDP(L46,"PX_LAST")),NA()) | O46: =IFERROR(IF(N46="",NA(),BDP(N46,"PX_LAST")),NA()) | Q46: =IFERROR(IF(P46="",NA(),BDP(P46,"PX_LAST")),NA()) | R46: ISIRTOTL Index | S46: =IFERROR(IF(R46="",NA(),BDP(R46,"PX_LAST")),NA())
B47: JORDAN | C47: JOR | D47: JO | E47: 14 | F47: JPSYJOZW Index | G47: =IFERROR(IF(F47="",NA(),BDP(F47,"PX_LAST")),NA()) | H47: CJORDAN CDS USD SR 5Y D14 Corp | I47: =IFERROR(IF(H47="",NA(),BDP(H47,"PX_LAST")),NA()) | K47: =IFERROR(IF(J47="",NA(),BDP(J47,"PX_LAST")),NA()) | L47: JOCPIYOY Index | M47: =IFERROR(IF(L47="",NA(),BDP(L47,"PX_LAST")),NA()) | O47: =IFERROR(IF(N47="",NA(),BDP(N47,"PX_LAST")),NA()) | Q47: =IFERROR(IF(P47="",NA(),BDP(P47,"PX_LAST")),NA()) | S47: =IFERROR(IF(R47="",NA(),BDP(R47,"PX_LAST")),NA())
B48: KUWAIT | C48: KWT | D48: KU | E48: 5 | F48: JPSYKWZW Index | G48: =IFERROR(IF(F48="",NA(),BDP(F48,"PX_LAST")),NA()) | I48: =IFERROR(IF(H48="",NA(),BDP(H48,"PX_LAST")),NA()) | K48: =IFERROR(IF(J48="",NA(),BDP(J48,"PX_LAST")),NA()) | L48: KWCPIYOY Index | M48: =IFERROR(IF(L48="",NA(),BDP(L48,"PX_LAST")),NA()) | O48: =IFERROR(IF(N48="",NA(),BDP(N48,"PX_LAST")),NA()) | Q48: =IFERROR(IF(P48="",NA(),BDP(P48,"PX_LAST")),NA()) | S48: =IFERROR(IF(R48="",NA(),BDP(R48,"PX_LAST")),NA())
B49: LEBANON | C49: LBN | D49: LB | E49: 22 | F49: JPSYLEZW Index | G49: =IFERROR(IF(F49="",NA(),BDP(F49,"PX_LAST")),NA()) | I49: =IFERROR(IF(H49="",NA(),BDP(H49,"PX_LAST")),NA()) | K49: =IFERROR(IF(J49="",NA(),BDP(J49,"PX_LAST")),NA()) | L49: LECPIYOY Index | M49: =IFERROR(IF(L49="",NA(),BDP(L49,"PX_LAST")),NA()) | O49: =IFERROR(IF(N49="",NA(),BDP(N49,"PX_LAST")),NA()) | Q49: =IFERROR(IF(P49="",NA(),BDP(P49,"PX_LAST")),NA()) | S49: =IFERROR(IF(R49="",NA(),BDP(R49,"PX_LAST")),NA())
B50: MOROCCO | C50: MAR | D50: MO | E50: 11 | F50: JPSYMOZW Index | G50: =IFERROR(IF(F50="",NA(),BDP(F50,"PX_LAST")),NA()) | H50: CMOROC CDS USD SR 5Y D14 Corp | I50: =IFERROR(IF(H50="",NA(),BDP(H50,"PX_LAST")),NA()) | J50: MOGDPYOY Index | K50: =IFERROR(IF(J50="",NA(),BDP(J50,"PX_LAST")),NA()) | L50: MOCPIYOY Index | M50: =IFERROR(IF(L50="",NA(),BDP(L50,"PX_LAST")),NA()) | O50: =IFERROR(IF(N50="",NA(),BDP(N50,"PX_LAST")),NA()) | Q50: =IFERROR(IF(P50="",NA(),BDP(P50,"PX_LAST")),NA()) | R50: MOIRTOTL Index | S50: =IFERROR(IF(R50="",NA(),BDP(R50,"PX_LAST")),NA())
B51: OMAN | C51: OMN | D51: OM | E51: 11 | F51: JPSYOMZW Index | G51: =IFERROR(IF(F51="",NA(),BDP(F51,"PX_LAST")),NA()) | H51: COMAN CDS USD SR 5Y D14 Corp | I51: =IFERROR(IF(H51="",NA(),BDP(H51,"PX_LAST")),NA()) | K51: =IFERROR(IF(J51="",NA(),BDP(J51,"PX_LAST")),NA()) | L51: OMCPIYOY Index | M51: =IFERROR(IF(L51="",NA(),BDP(L51,"PX_LAST")),NA()) | O51: =IFERROR(IF(N51="",NA(),BDP(N51,"PX_LAST")),NA()) | Q51: =IFERROR(IF(P51="",NA(),BDP(P51,"PX_LAST")),NA()) | S51: =IFERROR(IF(R51="",NA(),BDP(R51,"PX_LAST")),NA())
B52: QATAR | C52: QAT | D52: QA | E52: 3 | F52: JPSYQAZW Index | G52: =IFERROR(IF(F52="",NA(),BDP(F52,"PX_LAST")),NA()) | H52: CQATAR CDS USD SR 5Y D14 Corp | I52: =IFERROR(IF(H52="",NA(),BDP(H52,"PX_LAST")),NA()) | J52: QAGDPYOY Index | K52: =IFERROR(IF(J52="",NA(),BDP(J52,"PX_LAST")),NA()) | L52: QACPIYOY Index | M52: =IFERROR(IF(L52="",NA(),BDP(L52,"PX_LAST")),NA()) | O52: =IFERROR(IF(N52="",NA(),BDP(N52,"PX_LAST")),NA()) | Q52: =IFERROR(IF(P52="",NA(),BDP(P52,"PX_LAST")),NA()) | R52: QAIRTOTL Index | S52: =IFERROR(IF(R52="",NA(),BDP(R52,"PX_LAST")),NA())
B53: SAUDI ARABIA | C53: SAU | D53: AB | E53: 5 | F53: JPSYSAZW Index | G53: =IFERROR(IF(F53="",NA(),BDP(F53,"PX_LAST")),NA()) | H53: CSAUDI CDS USD SR 5Y D14 Corp | I53: =IFERROR(IF(H53="",NA(),BDP(H53,"PX_LAST")),NA()) | J53: SAGDP_Y Index | K53: =IFERROR(IF(J53="",NA(),BDP(J53,"PX_LAST")),NA()) | L53: SACPIYOY Index | M53: =IFERROR(IF(L53="",NA(),BDP(L53,"PX_LAST")),NA()) | O53: =IFERROR(IF(N53="",NA(),BDP(N53,"PX_LAST")),NA()) | Q53: =IFERROR(IF(P53="",NA(),BDP(P53,"PX_LAST")),NA()) | R53: SAINETRS Index | S53: =IFERROR(IF(R53="",NA(),BDP(R53,"PX_LAST")),NA())
B54: TUNISIA | C54: TUN | D54: TN | E54: 18 | F54: JPEGTNZW Index | G54: =IFERROR(IF(F54="",NA(),BDP(F54,"PX_LAST")),NA()) | I54: =IFERROR(IF(H54="",NA(),BDP(H54,"PX_LAST")),NA()) | J54: TNGDPYOY Index | K54: =IFERROR(IF(J54="",NA(),BDP(J54,"PX_LAST")),NA()) | L54: TNCPIYOY Index | M54: =IFERROR(IF(L54="",NA(),BDP(L54,"PX_LAST")),NA()) | O54: =IFERROR(IF(N54="",NA(),BDP(N54,"PX_LAST")),NA()) | Q54: =IFERROR(IF(P54="",NA(),BDP(P54,"PX_LAST")),NA()) | S54: =IFERROR(IF(R54="",NA(),BDP(R54,"PX_LAST")),NA())
B55: UNITED ARAB EMIRATES | C55: ARE | D55: AE | E55: 3 | F55: JPSYAEZW Index | G55: =IFERROR(IF(F55="",NA(),BDP(F55,"PX_LAST")),NA()) | H55: CABUDH CDS USD SR 5Y D14 Corp | I55: =IFERROR(IF(H55="",NA(),BDP(H55,"PX_LAST")),NA()) | K55: =IFERROR(IF(J55="",NA(),BDP(J55,"PX_LAST")),NA()) | L55: UACPIYOY Index | M55: =IFERROR(IF(L55="",NA(),BDP(L55,"PX_LAST")),NA()) | O55: =IFERROR(IF(N55="",NA(),BDP(N55,"PX_LAST")),NA()) | Q55: =IFERROR(IF(P55="",NA(),BDP(P55,"PX_LAST")),NA()) | S55: =IFERROR(IF(R55="",NA(),BDP(R55,"PX_LAST")),NA())
B56: ANGOLA | C56: AGO | D56: AO | E56: 16 | F56: JPSYAOZW Index | G56: =IFERROR(IF(F56="",NA(),BDP(F56,"PX_LAST")),NA()) | I56: =IFERROR(IF(H56="",NA(),BDP(H56,"PX_LAST")),NA()) | K56: =IFERROR(IF(J56="",NA(),BDP(J56,"PX_LAST")),NA()) | M56: =IFERROR(IF(L56="",NA(),BDP(L56,"PX_LAST")),NA()) | O56: =IFERROR(IF(N56="",NA(),BDP(N56,"PX_LAST")),NA()) | Q56: =IFERROR(IF(P56="",NA(),BDP(P56,"PX_LAST")),NA()) | S56: =IFERROR(IF(R56="",NA(),BDP(R56,"PX_LAST")),NA())
B57: CAMEROON | C57: CMR | D57: CM | E57: 16 | F57: JPEGCMZW Index | G57: =IFERROR(IF(F57="",NA(),BDP(F57,"PX_LAST")),NA()) | I57: =IFERROR(IF(H57="",NA(),BDP(H57,"PX_LAST")),NA()) | K57: =IFERROR(IF(J57="",NA(),BDP(J57,"PX_LAST")),NA()) | M57: =IFERROR(IF(L57="",NA(),BDP(L57,"PX_LAST")),NA()) | O57: =IFERROR(IF(N57="",NA(),BDP(N57,"PX_LAST")),NA()) | Q57: =IFERROR(IF(P57="",NA(),BDP(P57,"PX_LAST")),NA()) | S57: =IFERROR(IF(R57="",NA(),BDP(R57,"PX_LAST")),NA())
B58: COTE D'IVOIRE | C58: CIV | D58: CD | E58: 13 | F58: JPSYCDZW Index | G58: =IFERROR(IF(F58="",NA(),BDP(F58,"PX_LAST")),NA()) | I58: =IFERROR(IF(H58="",NA(),BDP(H58,"PX_LAST")),NA()) | K58: =IFERROR(IF(J58="",NA(),BDP(J58,"PX_LAST")),NA()) | M58: =IFERROR(IF(L58="",NA(),BDP(L58,"PX_LAST")),NA()) | O58: =IFERROR(IF(N58="",NA(),BDP(N58,"PX_LAST")),NA()) | Q58: =IFERROR(IF(P58="",NA(),BDP(P58,"PX_LAST")),NA()) | S58: =IFERROR(IF(R58="",NA(),BDP(R58,"PX_LAST")),NA())
B59: ETHIOPIA | C59: ETH | D59: ET | E59: 21 | F59: JPEGETZW Index | G59: =IFERROR(IF(F59="",NA(),BDP(F59,"PX_LAST")),NA()) | I59: =IFERROR(IF(H59="",NA(),BDP(H59,"PX_LAST")),NA()) | K59: =IFERROR(IF(J59="",NA(),BDP(J59,"PX_LAST")),NA()) | M59: =IFERROR(IF(L59="",NA(),BDP(L59,"PX_LAST")),NA()) | O59: =IFERROR(IF(N59="",NA(),BDP(N59,"PX_LAST")),NA()) | Q59: =IFERROR(IF(P59="",NA(),BDP(P59,"PX_LAST")),NA()) | S59: =IFERROR(IF(R59="",NA(),BDP(R59,"PX_LAST")),NA())
B60: GABON | C60: GAB | D60: GA | E60: 17 | F60: JPSYGAZW Index | G60: =IFERROR(IF(F60="",NA(),BDP(F60,"PX_LAST")),NA()) | I60: =IFERROR(IF(H60="",NA(),BDP(H60,"PX_LAST")),NA()) | K60: =IFERROR(IF(J60="",NA(),BDP(J60,"PX_LAST")),NA()) | M60: =IFERROR(IF(L60="",NA(),BDP(L60,"PX_LAST")),NA()) | O60: =IFERROR(IF(N60="",NA(),BDP(N60,"PX_LAST")),NA()) | Q60: =IFERROR(IF(P60="",NA(),BDP(P60,"PX_LAST")),NA()) | S60: =IFERROR(IF(R60="",NA(),BDP(R60,"PX_LAST")),NA())
B61: GHANA | C61: GHA | D61: GH | E61: 21 | F61: JPSYGHZW Index | G61: =IFERROR(IF(F61="",NA(),BDP(F61,"PX_LAST")),NA()) | I61: =IFERROR(IF(H61="",NA(),BDP(H61,"PX_LAST")),NA()) | J61: GHGDPYOY Index | K61: =IFERROR(IF(J61="",NA(),BDP(J61,"PX_LAST")),NA()) | L61: GHCPIYOY Index | M61: =IFERROR(IF(L61="",NA(),BDP(L61,"PX_LAST")),NA()) | O61: =IFERROR(IF(N61="",NA(),BDP(N61,"PX_LAST")),NA()) | Q61: =IFERROR(IF(P61="",NA(),BDP(P61,"PX_LAST")),NA()) | S61: =IFERROR(IF(R61="",NA(),BDP(R61,"PX_LAST")),NA())
