Workbook

Sheet Read me
A1: EM USD sovereign debt — total return at a 220bp EMBI Global spread
A2: UBS. Built 11-Aug-2026. Market data as of 7-Aug-2026 (Fed H.15, iShares EMB). Index analytics are estimates — refresh from Bloomberg on tab '9 Bloomberg refresh'.
A4: The question
B5: EMBI Global sits at 220bp. The UBS house view looks for modest widening — CIO's published EMBIG Diversified path is 244bp (Apr-26) to 260bp (Dec-26) — yet rates the asset class Attractive. This workbook shows why those two statements are consistent, and — just as important — the two scenarios in which they stop being consistent.
A7: The answer in four numbers
A8: 7.6% | B8: One year of carry + roll-down, before any market move. That is the number the spread move is spent against.
A9: 1.95% | B9: Cost of the 30bp widening to 250bp (6.5 spread duration). It consumes 26% of one year's carry — you are paid ~3.9x the expected loss.
A10: 117bp | B10: Breakeven widening over 12 months, rates unchanged: spreads must reach 337bp before total return turns negative. 125bp once convexity is counted.
A11: +4.6% | B11: Probability-weighted expected return across six Fed paths. Positive, but NOT a layup: there is a 15% chance of a negative year and the worst case is -10.3%.
A13: Tabs
A14: 0 Plain English | B14: START HERE if you want the intuition rather than the maths: why a rate rise does not take your carry away, and exactly when you DO lose money.
A15: 1 Inputs | B15: The only tab to type on. Index analytics, curve, roll assumptions, horizon. Everything downstream is a live formula.
A16: 2 Decomposition | B16: Carry split into cash coupon / pull-to-par / roll-down, by holding period. Answers 'how much is carry vs roll vs pull to par'.
A17: 4 Fed scenarios | B17: Five Fed paths, each with a full six-way P&L attribution and a probability weight. The core tab.
A18: 5 Return grid | B18: Total return for every combination of spread move and Treasury move. Read the diagonal — that is the hedge.
A19: 6 Breakeven | B19: Breakeven widening by holding period, 1-36 months, with and without convexity.
A20: 7 Risk | B20: Return volatility, the correlation benefit, VaR at 95/99, and probability of loss by horizon.
A21: 8 Fed path | B21: Fed funds path per scenario and the Treasury curve the roll is read off.
A22: 9 Bloomberg refresh | B22: Every BDP/BDH call to rebuild from live data. Written without the leading '=' so the tab stays inert offline.
A23: Notes | B23: Method, conventions, what is not modelled, sources.
A25: Legend
A26: Blue | B26: Type here. Hardcoded input or scenario lever.
A27: Black | B27: Formula. Do not overwrite.
A28: Green | B28: Link to another tab.
A30: Charts are deliberately left at Excel defaults — no colours, axis bounds, legend positions or gridlines — per the house rule in the Argentina chart pack. Format them however you like.
A31: Convention: all rates and returns in PERCENT UNITS (6.75 = 6.75%). All yield and spread moves in BASIS POINTS. Consistent with the Argentina carry-cushion model.

Sheet 0 Plain English
A1: Why a rise in rates does not take your carry away
A2: The short version: the carry is cash and you always get it. What a rate rise takes is PRICE — and that loss is temporary if you hold.
A4: First — the honest answer: you ARE right that you can lose
H5: If rates rise AND spreads widen at the same time, both legs move against you and there is no hedge. That is real and this model says so — it is the 'inflation re-acceleration' scenario on tab 4, which returns roughly zero. So the claim is NOT 'rates can't hurt you'. The claim is narrower and it is below.
A7: Step 1 — Separate the two things that happen to you in a year
A8: A) Cash you collect (the carry) | B8: ='1 Inputs'!B30 -> 7.6275 | H8: Coupon, accretion and roll. This lands in your account no matter what rates do. The ONLY thing that stops it is a default. A rate move cannot touch it.
A9: B) Price move (the mark) | B9: depends | H9: If yields rise, the price falls. This is a paper loss — real only if you sell.
A10: Your return = A + B | H10: That is the whole thing. You never 'lose the carry'. You can lose MORE on the price than the carry pays you — which makes the TOTAL negative. Different statement.
A12: Step 2 — The bond does not care WHERE the yield move came from
H13: This is the bit that makes it simple. A bond only feels its own yield. Whether that yield rose because Treasuries sold off or because the spread widened is irrelevant to the price. So stop tracking two numbers and track one: the TOTAL yield move.
A14: Example | B14: Rates move (bp) | C14: Spread move (bp) | D14: TOTAL move (bp) | E14: Price move (%) | F14: Carry (%) | G14: Your return (%)
A15: Rates +50, spread unchanged | B15: 50 | C15: 0 | D15: =B15+C15 -> 50 | E15: =-'1 Inputs'!B12*D15/100+'1 Inputs'!B14*D15^2/2000000 -> -3.175 | F15: ='1 Inputs'!B30 -> 7.6275 | G15: =E15+F15 -> 4.4525
A16: Rates unchanged, spread +50 | B16: 0 | C16: 50 | D16: =B16+C16 -> 50 | E16: =-'1 Inputs'!B12*D16/100+'1 Inputs'!B14*D16^2/2000000 -> -3.175 | F16: ='1 Inputs'!B30 -> 7.6275 | G16: =E16+F16 -> 4.4525
A17: Rates +25, spread +25 | B17: 25 | C17: 25 | D17: =B17+C17 -> 50 | E17: =-'1 Inputs'!B12*D17/100+'1 Inputs'!B14*D17^2/2000000 -> -3.175 | F17: ='1 Inputs'!B30 -> 7.6275 | G17: =E17+F17 -> 4.4525
H19: All three lines give the same answer. 50bp is 50bp. This is why the question 'what if rates rise AND spreads widen' has a simple form: just add them together.
A21: Step 3 — So: how big does the TOTAL move have to be before you lose money?
A22: Carry you earn in a year (%) | B22: ='1 Inputs'!B30 -> 7.6275
A23: Cost of 1bp of total yield rise (%) | B23: ='1 Inputs'!B12/100 -> 0.065 | H23: Duration 6.5 means 1bp costs 0.065%.
A24: So break-even total move (bp) | B24: ='1 Inputs'!B30/('1 Inputs'!B12/100) -> 117.34615 | H24: Rates AND spread COMBINED have to rise by more than this within one year before you are down. Split it however you like: 60bp of rates plus 60bp of spread does it. 40 and 40 does not.
A26: Combined move of rates + spread | B26: Total move (bp) | C26: Carry (%) | D26: Price move (%) | E26: Your return (%)
A27: Nothing happens | B27: 0 | C27: ='1 Inputs'!B30 -> 7.6275 | D27: =-'1 Inputs'!B12*B27/100+'1 Inputs'!B14*B27^2/2000000 -> 0 | E27: =C27+D27 -> 7.6275
A28: Small: e.g. rates +25, spread +25 | B28: 50 | C28: ='1 Inputs'!B30 -> 7.6275 | D28: =-'1 Inputs'!B12*B28/100+'1 Inputs'!B14*B28^2/2000000 -> -3.175 | E28: =C28+D28 -> 4.4525
A29: Our house view: rates -25, spread +30 | B29: 5 | C29: ='1 Inputs'!B30 -> 7.6275 | D29: =-'1 Inputs'!B12*B29/100+'1 Inputs'!B14*B29^2/2000000 -> -0.32425 | E29: =C29+D29 -> 7.30325
A30: Moderate: rates +50, spread +25 | B30: 75 | C30: ='1 Inputs'!B30 -> 7.6275 | D30: =-'1 Inputs'!B12*B30/100+'1 Inputs'!B14*B30^2/2000000 -> -4.70625 | E30: =C30+D30 -> 2.92125
A31: BREAK-EVEN: rates +60, spread +60 | B31: 120 | C31: ='1 Inputs'!B30 -> 7.6275 | D31: =-'1 Inputs'!B12*B31/100+'1 Inputs'!B14*B31^2/2000000 -> -7.368 | E31: =C31+D31 -> 0.2595
A32: Bad: rates +75, spread +75 | B32: 150 | C32: ='1 Inputs'!B30 -> 7.6275 | D32: =-'1 Inputs'!B12*B32/100+'1 Inputs'!B14*B32^2/2000000 -> -9.075 | E32: =C32+D32 -> -1.4475
A33: Very bad: rates +100, spread +100 | B33: 200 | C33: ='1 Inputs'!B30 -> 7.6275 | D33: =-'1 Inputs'!B12*B33/100+'1 Inputs'!B14*B33^2/2000000 -> -11.8 | E33: =C33+D33 -> -4.1725
A34: 2022-style: rates +150, spread +150 | B34: 300 | C34: ='1 Inputs'!B30 -> 7.6275 | D34: =-'1 Inputs'!B12*B34/100+'1 Inputs'!B14*B34^2/2000000 -> -16.8 | E34: =C34+D34 -> -9.1725
H36: Read the last column. You need a genuinely large combined move — bigger than most calendar years produce — before the price loss eats a full year of carry.
A38: Step 4 — THE KEY POINT: a rate rise is a one-off price hit, but it RAISES your future carry
H39: This is the part that answers your question properly. When yields jump, two things happen at once: the price drops today, and every coupon you reinvest from here on earns MORE. The price drop is a one-time event. The higher income lasts for as long as you own the bond. Hold long enough and the second effect fully pays back the first.
A40: Yield today (%) | B40: ='1 Inputs'!B25 -> 6.75
A41: Yield after a +100bp shock (%) | B41: =B40+1 -> 7.75 | H41: Your carry did not go DOWN. It went UP. You are now earning 7.75% instead of 6.75% on everything you hold and reinvest from here.
A42: Starting price | B42: ='1 Inputs'!B26 -> 91.26811
A44: What you ACTUALLY earn per year if the yield jumps today and you simply hold:
A45: Hold for... | B45: Yields fall 100bp | C45: Nothing happens | D45: Yields RISE 100bp | E45: Yields RISE 200bp | F45: Yields RISE 300bp
A46: 1 year | B46: =((('1 Inputs'!B10*((1+((B40+-1)/100))^1-1)/((B40+-1)/100))+(-PV(((B40+-1)/100),'1 Inputs'!B11-1,'1 Inputs'!B10,100)))/B42)^(1/1)-1 -> 0.14478969 | C46: =((('1 Inputs'!B10*((1+((B40+0)/100))^1-1)/((B40+0)/100))+(-PV(((B40+0)/100),'1 Inputs'!B11-1,'1 Inputs'!B10,100)))/B42)^(1/1)-1 -> 0.0675 | D46: =((('1 Inputs'!B10*((1+((B40+1)/100))^1-1)/((B40+1)/100))+(-PV(((B40+1)/100),'1 Inputs'!B11-1,'1 Inputs'!B10,100)))/B42)^(1/1)-1 -> -0.0028365733 | E46: =((('1 Inputs'!B10*((1+((B40+2)/100))^1-1)/((B40+2)/100))+(-PV(((B40+2)/100),'1 Inputs'!B11-1,'1 Inputs'!B10,100)))/B42)^(1/1)-1 -> -0.066924815 | F46: =((('1 Inputs'!B10*((1+((B40+3)/100))^1-1)/((B40+3)/100))+(-PV(((B40+3)/100),'1 Inputs'!B11-1,'1 Inputs'!B10,100)))/B42)^(1/1)-1 -> -0.12539147
A47: 2 years | B47: =((('1 Inputs'!B10*((1+((B40+-1)/100))^2-1)/((B40+-1)/100))+(-PV(((B40+-1)/100),'1 Inputs'!B11-2,'1 Inputs'!B10,100)))/B42)^(1/2)-1 -> 0.10027955 | C47: =((('1 Inputs'!B10*((1+((B40+0)/100))^2-1)/((B40+0)/100))+(-PV(((B40+0)/100),'1 Inputs'!B11-2,'1 Inputs'!B10,100)))/B42)^(1/2)-1 -> 0.0675 | D47: =((('1 Inputs'!B10*((1+((B40+1)/100))^2-1)/((B40+1)/100))+(-PV(((B40+1)/100),'1 Inputs'!B11-2,'1 Inputs'!B10,100)))/B42)^(1/2)-1 -> 0.036553709 | E47: =((('1 Inputs'!B10*((1+((B40+2)/100))^2-1)/((B40+2)/100))+(-PV(((B40+2)/100),'1 Inputs'!B11-2,'1 Inputs'!B10,100)))/B42)^(1/2)-1 -> 0.0073327474 | F47: =((('1 Inputs'!B10*((1+((B40+3)/100))^2-1)/((B40+3)/100))+(-PV(((B40+3)/100),'1 Inputs'!B11-2,'1 Inputs'!B10,100)))/B42)^(1/2)-1 -> -0.020263883
A48: 3 years | B48: =((('1 Inputs'!B10*((1+((B40+-1)/100))^3-1)/((B40+-1)/100))+(-PV(((B40+-1)/100),'1 Inputs'!B11-3,'1 Inputs'!B10,100)))/B42)^(1/3)-1 -> 0.085830794 | C48: =((('1 Inputs'!B10*((1+((B40+0)/100))^3-1)/((B40+0)/100))+(-PV(((B40+0)/100),'1 Inputs'!B11-3,'1 Inputs'!B10,100)))/B42)^(1/3)-1 -> 0.0675 | D48: =((('1 Inputs'!B10*((1+((B40+1)/100))^3-1)/((B40+1)/100))+(-PV(((B40+1)/100),'1 Inputs'!B11-3,'1 Inputs'!B10,100)))/B42)^(1/3)-1 -> 0.050026597 | E48: =((('1 Inputs'!B10*((1+((B40+2)/100))^3-1)/((B40+2)/100))+(-PV(((B40+2)/100),'1 Inputs'!B11-3,'1 Inputs'!B10,100)))/B42)^(1/3)-1 -> 0.033376046 | F48: =((('1 Inputs'!B10*((1+((B40+3)/100))^3-1)/((B40+3)/100))+(-PV(((B40+3)/100),'1 Inputs'!B11-3,'1 Inputs'!B10,100)))/B42)^(1/3)-1 -> 0.017515238
A49: 4 years | B49: =((('1 Inputs'!B10*((1+((B40+-1)/100))^4-1)/((B40+-1)/100))+(-PV(((B40+-1)/100),'1 Inputs'!B11-4,'1 Inputs'!B10,100)))/B42)^(1/4)-1 -> 0.078677723 | C49: =((('1 Inputs'!B10*((1+((B40+0)/100))^4-1)/((B40+0)/100))+(-PV(((B40+0)/100),'1 Inputs'!B11-4,'1 Inputs'!B10,100)))/B42)^(1/4)-1 -> 0.0675 | D49: =((('1 Inputs'!B10*((1+((B40+1)/100))^4-1)/((B40+1)/100))+(-PV(((B40+1)/100),'1 Inputs'!B11-4,'1 Inputs'!B10,100)))/B42)^(1/4)-1 -> 0.056828568 | E49: =((('1 Inputs'!B10*((1+((B40+2)/100))^4-1)/((B40+2)/100))+(-PV(((B40+2)/100),'1 Inputs'!B11-4,'1 Inputs'!B10,100)))/B42)^(1/4)-1 -> 0.046649112 | F49: =((('1 Inputs'!B10*((1+((B40+3)/100))^4-1)/((B40+3)/100))+(-PV(((B40+3)/100),'1 Inputs'!B11-4,'1 Inputs'!B10,100)))/B42)^(1/4)-1 -> 0.036947631
A50: 5 years | B50: =((('1 Inputs'!B10*((1+((B40+-1)/100))^5-1)/((B40+-1)/100))+(-PV(((B40+-1)/100),'1 Inputs'!B11-5,'1 Inputs'!B10,100)))/B42)^(1/5)-1 -> 0.074408518 | C50: =((('1 Inputs'!B10*((1+((B40+0)/100))^5-1)/((B40+0)/100))+(-PV(((B40+0)/100),'1 Inputs'!B11-5,'1 Inputs'!B10,100)))/B42)^(1/5)-1 -> 0.0675 | D50: =((('1 Inputs'!B10*((1+((B40+1)/100))^5-1)/((B40+1)/100))+(-PV(((B40+1)/100),'1 Inputs'!B11-5,'1 Inputs'!B10,100)))/B42)^(1/5)-1 -> 0.060930882 | E50: =((('1 Inputs'!B10*((1+((B40+2)/100))^5-1)/((B40+2)/100))+(-PV(((B40+2)/100),'1 Inputs'!B11-5,'1 Inputs'!B10,100)))/B42)^(1/5)-1 -> 0.054694644 | F50: =((('1 Inputs'!B10*((1+((B40+3)/100))^5-1)/((B40+3)/100))+(-PV(((B40+3)/100),'1 Inputs'!B11-5,'1 Inputs'!B10,100)))/B42)^(1/5)-1 -> 0.048784752
A51: 6 years | B51: =((('1 Inputs'!B10*((1+((B40+-1)/100))^6-1)/((B40+-1)/100))+(-PV(((B40+-1)/100),'1 Inputs'!B11-6,'1 Inputs'!B10,100)))/B42)^(1/6)-1 -> 0.071571773 | C51: =((('1 Inputs'!B10*((1+((B40+0)/100))^6-1)/((B40+0)/100))+(-PV(((B40+0)/100),'1 Inputs'!B11-6,'1 Inputs'!B10,100)))/B42)^(1/6)-1 -> 0.0675 | D51: =((('1 Inputs'!B10*((1+((B40+1)/100))^6-1)/((B40+1)/100))+(-PV(((B40+1)/100),'1 Inputs'!B11-6,'1 Inputs'!B10,100)))/B42)^(1/6)-1 -> 0.063674602 | E51: =((('1 Inputs'!B10*((1+((B40+2)/100))^6-1)/((B40+2)/100))+(-PV(((B40+2)/100),'1 Inputs'!B11-6,'1 Inputs'!B10,100)))/B42)^(1/6)-1 -> 0.060092661 | F51: =((('1 Inputs'!B10*((1+((B40+3)/100))^6-1)/((B40+3)/100))+(-PV(((B40+3)/100),'1 Inputs'!B11-6,'1 Inputs'!B10,100)))/B42)^(1/6)-1 -> 0.056751141
A52: 7 years | B52: =((('1 Inputs'!B10*((1+((B40+-1)/100))^7-1)/((B40+-1)/100))+(-PV(((B40+-1)/100),'1 Inputs'!B11-7,'1 Inputs'!B10,100)))/B42)^(1/7)-1 -> 0.069550113 | C52: =((('1 Inputs'!B10*((1+((B40+0)/100))^7-1)/((B40+0)/100))+(-PV(((B40+0)/100),'1 Inputs'!B11-7,'1 Inputs'!B10,100)))/B42)^(1/7)-1 -> 0.0675 | D52: =((('1 Inputs'!B10*((1+((B40+1)/100))^7-1)/((B40+1)/100))+(-PV(((B40+1)/100),'1 Inputs'!B11-7,'1 Inputs'!B10,100)))/B42)^(1/7)-1 -> 0.065638744 | E52: =((('1 Inputs'!B10*((1+((B40+2)/100))^7-1)/((B40+2)/100))+(-PV(((B40+2)/100),'1 Inputs'!B11-7,'1 Inputs'!B10,100)))/B42)^(1/7)-1 -> 0.063965294 | F52: =((('1 Inputs'!B10*((1+((B40+3)/100))^7-1)/((B40+3)/100))+(-PV(((B40+3)/100),'1 Inputs'!B11-7,'1 Inputs'!B10,100)))/B42)^(1/7)-1 -> 0.06247844
A53: 8 years | B53: =((('1 Inputs'!B10*((1+((B40+-1)/100))^8-1)/((B40+-1)/100))+(-PV(((B40+-1)/100),'1 Inputs'!B11-8,'1 Inputs'!B10,100)))/B42)^(1/8)-1 -> 0.068036372 | C53: =((('1 Inputs'!B10*((1+((B40+0)/100))^8-1)/((B40+0)/100))+(-PV(((B40+0)/100),'1 Inputs'!B11-8,'1 Inputs'!B10,100)))/B42)^(1/8)-1 -> 0.0675 | D53: =((('1 Inputs'!B10*((1+((B40+1)/100))^8-1)/((B40+1)/100))+(-PV(((B40+1)/100),'1 Inputs'!B11-8,'1 Inputs'!B10,100)))/B42)^(1/8)-1 -> 0.067114231 | E53: =((('1 Inputs'!B10*((1+((B40+2)/100))^8-1)/((B40+2)/100))+(-PV(((B40+2)/100),'1 Inputs'!B11-8,'1 Inputs'!B10,100)))/B42)^(1/8)-1 -> 0.066879051 | F53: =((('1 Inputs'!B10*((1+((B40+3)/100))^8-1)/((B40+3)/100))+(-PV(((B40+3)/100),'1 Inputs'!B11-8,'1 Inputs'!B10,100)))/B42)^(1/8)-1 -> 0.066794275
A54: 9 years | B54: =((('1 Inputs'!B10*((1+((B40+-1)/100))^9-1)/((B40+-1)/100))+(-PV(((B40+-1)/100),'1 Inputs'!B11-9,'1 Inputs'!B10,100)))/B42)^(1/9)-1 -> 0.066860499 | C54: =((('1 Inputs'!B10*((1+((B40+0)/100))^9-1)/((B40+0)/100))+(-PV(((B40+0)/100),'1 Inputs'!B11-9,'1 Inputs'!B10,100)))/B42)^(1/9)-1 -> 0.0675 | D54: =((('1 Inputs'!B10*((1+((B40+1)/100))^9-1)/((B40+1)/100))+(-PV(((B40+1)/100),'1 Inputs'!B11-9,'1 Inputs'!B10,100)))/B42)^(1/9)-1 -> 0.068263244 | E54: =((('1 Inputs'!B10*((1+((B40+2)/100))^9-1)/((B40+2)/100))+(-PV(((B40+2)/100),'1 Inputs'!B11-9,'1 Inputs'!B10,100)))/B42)^(1/9)-1 -> 0.069150821 | F54: =((('1 Inputs'!B10*((1+((B40+3)/100))^9-1)/((B40+3)/100))+(-PV(((B40+3)/100),'1 Inputs'!B11-9,'1 Inputs'!B10,100)))/B42)^(1/9)-1 -> 0.070163152
A55: 10 years | B55: =((('1 Inputs'!B10*((1+((B40+-1)/100))^10-1)/((B40+-1)/100))+(-PV(((B40+-1)/100),'1 Inputs'!B11-10,'1 Inputs'!B10,100)))/B42)^(1/10)-1 -> 0.065920732 | C55: =((('1 Inputs'!B10*((1+((B40+0)/100))^10-1)/((B40+0)/100))+(-PV(((B40+0)/100),'1 Inputs'!B11-10,'1 Inputs'!B10,100)))/B42)^(1/10)-1 -> 0.0675 | D55: =((('1 Inputs'!B10*((1+((B40+1)/100))^10-1)/((B40+1)/100))+(-PV(((B40+1)/100),'1 Inputs'!B11-10,'1 Inputs'!B10,100)))/B42)^(1/10)-1 -> 0.069183345 | E55: =((('1 Inputs'!B10*((1+((B40+2)/100))^10-1)/((B40+2)/100))+(-PV(((B40+2)/100),'1 Inputs'!B11-10,'1 Inputs'!B10,100)))/B42)^(1/10)-1 -> 0.07097172 | F55: =((('1 Inputs'!B10*((1+((B40+3)/100))^10-1)/((B40+3)/100))+(-PV(((B40+3)/100),'1 Inputs'!B11-10,'1 Inputs'!B10,100)))/B42)^(1/10)-1 -> 0.072865912
A56: 11 years | B56: =((('1 Inputs'!B10*((1+((B40+-1)/100))^11-1)/((B40+-1)/100))+(-PV(((B40+-1)/100),'1 Inputs'!B11-11,'1 Inputs'!B10,100)))/B42)^(1/11)-1 -> 0.065152449 | C56: =((('1 Inputs'!B10*((1+((B40+0)/100))^11-1)/((B40+0)/100))+(-PV(((B40+0)/100),'1 Inputs'!B11-11,'1 Inputs'!B10,100)))/B42)^(1/11)-1 -> 0.0675 | D56: =((('1 Inputs'!B10*((1+((B40+1)/100))^11-1)/((B40+1)/100))+(-PV(((B40+1)/100),'1 Inputs'!B11-11,'1 Inputs'!B10,100)))/B42)^(1/11)-1 -> 0.069936745 | E56: =((('1 Inputs'!B10*((1+((B40+2)/100))^11-1)/((B40+2)/100))+(-PV(((B40+2)/100),'1 Inputs'!B11-11,'1 Inputs'!B10,100)))/B42)^(1/11)-1 -> 0.072463853 | F56: =((('1 Inputs'!B10*((1+((B40+3)/100))^11-1)/((B40+3)/100))+(-PV(((B40+3)/100),'1 Inputs'!B11-11,'1 Inputs'!B10,100)))/B42)^(1/11)-1 -> 0.075082338
H58: Follow the '+100bp' column down. Year 1 is ugly — you are slightly negative. By year 3 you are earning 5%. By year 8 you are back to 6.7%, the same as if rates had never moved. After that the rate rise has made you BETTER off than if nothing had happened.
H59: That crossover is not a coincidence — it is what duration actually measures: the holding period at which the price loss and the higher reinvestment exactly cancel.
H60: ONE CAVEAT, so you are not caught out. This table prices a simple 11-year bullet bond with an 11-year average life. That bond's own duration is 7.8y, longer than the index's reported 6.5y — real EM indices contain amortisers, sinkers and callables that shorten them. So the table's crossover of ~8.4 years is right for the proxy bond, and the crossover for the ACTUAL index is nearer 7 years. Same conclusion, slightly sooner.
H61: Same story at +200bp and +300bp. The hole is deeper and takes about as long to climb out of. What never happens in any column is the carry disappearing.
A63: The whole thing in five sentences
A64: 1. | B64: The coupon is cash. It arrives whatever rates do. You never lose it — only a default takes it.
A65: 2. | B65: A rate rise cuts the PRICE, not the income. That is a paper loss, and it is only realised if you sell.
A66: 3. | B66: The bond doesn't care whether the yield rose from rates or from spread — only the total matters. Rates and spread combined have to rise about 120bp in a year before the price loss exceeds a year of carry.
A67: 4. | B67: You are right that rates up AND spreads wider is the case that hurts, and it is the one scenario in this model with a negative return. It is also the one worth hedging.
A68: 5. | B68: But if you hold, a rate rise ends up HELPING you: your reinvestment rate is permanently higher, and by roughly the duration of what you own — about 7 years for this index — you have earned more than if rates had never risen at all.
A70: Table in Step 4 is a real cashflow calculation, not a duration approximation: coupons reinvested at the post-shock yield, bond sold at the post-shock yield with its remaining life, annualised against today's price. Assumes no default and a one-off parallel shock on day one.
A71: Blue cells are editable. Change the shock sizes, the horizon, or any input on tab 1 and everything here recalculates.

Sheet 1 Inputs
A1: Index inputs and assumptions
A2: Blue cells only. Everything else on every tab recalculates from here.
A4: Spread and curve
A5: EMBI Global stripped spread, current (bp) | B5: 220 | C5: User's anchor. Cross-check: UBS CIO shows EMBIG Diversified at 244bp (Apr-26). EMBI Global runs tighter than Diversified — market-cap weighting tilts to larger, higher-rated issuers.
A6: EMBI Global spread, house target (bp) | B6: 250 | C6: House view. Corroborated by UBS CIO's published EMBIG Div target of 260bp for Dec-26.
A7: UST reference yield at index duration (%) | B7: 4.55 | C7: Interpolated to the ~8.5y point from Fed H.15, 7-Aug-26: 7y 4.49%, 10y 4.65%.
A9: Index analytics
A10: Average coupon (%) | B10: 5.6 | C10: iShares EMB fund characteristics, 7-Aug-26.
A11: Average life (yrs) | B11: 11 | C11: Estimate. EMBI Global runs ~11-12y average life.
A12: Modified duration (yrs) | B12: 6.5 | C12: iShares EMB effective duration 6.47y, 7-Aug-26.
A13: Spread duration (yrs) | B13: 6.5 | C13: Set equal to modified duration. Separate cell so you can break the equality if you want.
A14: Convexity (yrs^2) | B14: 60 | C14: Estimate for a 6.5y-duration portfolio with a long tail. UNITS TRAP: Bloomberg CVX_MID is quoted /100 — multiply by 100 before pasting.
A16: Roll-down
A17: Treasury curve roll (bp/yr) | B17: 5.5 | C17: Slope of the UST curve at the index duration point. 7y-10y is (4.65-4.49)/3 = 5.3bp/yr; 5y-7y is 7.0bp/yr. See tab 8.
A18: Credit curve roll (bp/yr) | B18: 8 | C18: EM sovereign spread curves slope up ~8-12bp/yr in the 7-12y sector. Blended IG/HY estimate — the softest number in the model.
A20: Horizon
A21: Holding period (months) | B21: 12 | C21: Drives tabs 2, 3, 4, 5 and 7. Tab 6 sweeps horizon independently.
A22: Holding period (yrs) | B22: =B21/12 -> 1
A24: Derived — do not type here
A25: Index yield to maturity (%) | B25: =B7+B5/100 -> 6.75 | C25: UST reference + stripped spread.
A26: Implied average price | B26: =-PV(B25/100,B11,B10,100) -> 91.26811 | C26: Level-yield bond priced off coupon, average life and YTM. Discount to par because the coupon is below the yield.
A27: Current yield (%) | B27: =B10/B26*100 -> 6.1357685 | C27: Cash coupon divided by price. This is the part of the yield that is genuinely banked.
A28: Pull-to-par accretion (%/yr) | B28: =B25-B27 -> 0.61423147 | C28: YTM less current yield. Price drift toward par at a CONSTANT yield. Additive with current yield by construction — the two sum to YTM, so there is no double count.
A29: Total roll-down (bp/yr) | B29: =B17+B18 -> 13.5 | C29: Yield decline from ageing down both curves. Separate from pull-to-par: that holds yield constant, this is the yield moving.
A30: Carry + roll over horizon (%) | B30: =(B27+B28)*B22+B12*B29*B22/100 -> 7.6275 | C30: The cushion. Everything in the pitch is measured against this number.
A32: Sources: Federal Reserve H.15, 7-Aug-2026 (Treasury curve). iShares EMB fund characteristics, 7-Aug-2026 (duration, coupon, OAS 165bp). UBS CIO 'Adding income through emerging market bonds', 13-May-2026 (EMBIG Div 244bp spot, 260bp Dec-26 target, Attractive rating).
A33: Spread of 220bp and target of 250bp are the user's inputs, not observed prints. Average life, convexity and both roll assumptions are estimates — replace from Bloomberg via tab 8.

Sheet 2 Decomposition
A1: What the carry actually is — cash coupon vs pull-to-par vs roll-down
A2: The headline yield is three different things with three different degrees of certainty. Only the first is banked.
A4: Per year, at the current curve
A5: Component | B5: % p.a. | C5: Share | D5: Certainty | E5: Why
A6: Cash coupon | B6: ='1 Inputs'!B27 -> 6.1357685 | C6: =B6/$B$9 -> 0.80442721 | D6: Banked | E6: Received in cash. Lost only on default or a missed payment — not on any mark.
A7: Pull-to-par accretion | B7: ='1 Inputs'!B28 -> 0.61423147 | C7: =B7/$B$9 -> 0.080528544 | D7: If yield holds | E7: Price drift toward par at an unchanged yield. Real, but it is a mark, not cash — it evaporates if the yield rises.
A8: Roll-down | B8: ='1 Inputs'!B12*'1 Inputs'!B29/100 -> 0.8775 | C8: =B8/$B$9 -> 0.11504425 | D8: If curve shape holds | E8: Bond ages into a lower point on both the Treasury and credit curves. Requires the curve to stay upward-sloping, not merely to stay put.
A9: Total carry + roll | B9: =SUM(B6:B8) -> 7.6275 | C9: =B9/B9 -> 1
A11: The split is the point. ~80% of the carry is cash coupon — banked regardless of where the curve goes. That is the opposite of the deep-discount Argentina step-ups, where pull-to-par was the larger half and the 'yield' overstated what you actually collect. Here the headline yield is honest.
A13: By holding period
A14: Months | B14: Cash coupon (%) | C14: Pull-to-par (%) | D14: Roll-down (%) | E14: Total carry + roll (%) | F14: Breakeven widening (bp)
A15: 1 | B15: ='1 Inputs'!B27*A15/12 -> 0.51131404 | C15: ='1 Inputs'!B28*A15/12 -> 0.051185955 | D15: ='1 Inputs'!B12*'1 Inputs'!B29/100*A15/12 -> 0.073125 | E15: =SUM(B15:D15) -> 0.635625 | F15: =E15/'1 Inputs'!B13*100 -> 9.7788462
A16: 2 | B16: ='1 Inputs'!B27*A16/12 -> 1.0226281 | C16: ='1 Inputs'!B28*A16/12 -> 0.10237191 | D16: ='1 Inputs'!B12*'1 Inputs'!B29/100*A16/12 -> 0.14625 | E16: =SUM(B16:D16) -> 1.27125 | F16: =E16/'1 Inputs'!B13*100 -> 19.557692
A17: 3 | B17: ='1 Inputs'!B27*A17/12 -> 1.5339421 | C17: ='1 Inputs'!B28*A17/12 -> 0.15355787 | D17: ='1 Inputs'!B12*'1 Inputs'!B29/100*A17/12 -> 0.219375 | E17: =SUM(B17:D17) -> 1.906875 | F17: =E17/'1 Inputs'!B13*100 -> 29.336538
A18: 6 | B18: ='1 Inputs'!B27*A18/12 -> 3.0678843 | C18: ='1 Inputs'!B28*A18/12 -> 0.30711573 | D18: ='1 Inputs'!B12*'1 Inputs'!B29/100*A18/12 -> 0.43875 | E18: =SUM(B18:D18) -> 3.81375 | F18: =E18/'1 Inputs'!B13*100 -> 58.673077
A19: 9 | B19: ='1 Inputs'!B27*A19/12 -> 4.6018264 | C19: ='1 Inputs'!B28*A19/12 -> 0.4606736 | D19: ='1 Inputs'!B12*'1 Inputs'!B29/100*A19/12 -> 0.658125 | E19: =SUM(B19:D19) -> 5.720625 | F19: =E19/'1 Inputs'!B13*100 -> 88.009615
A20: 12 | B20: ='1 Inputs'!B27*A20/12 -> 6.1357685 | C20: ='1 Inputs'!B28*A20/12 -> 0.61423147 | D20: ='1 Inputs'!B12*'1 Inputs'!B29/100*A20/12 -> 0.8775 | E20: =SUM(B20:D20) -> 7.6275 | F20: =E20/'1 Inputs'!B13*100 -> 117.34615
A21: 18 | B21: ='1 Inputs'!B27*A21/12 -> 9.2036528 | C21: ='1 Inputs'!B28*A21/12 -> 0.9213472 | D21: ='1 Inputs'!B12*'1 Inputs'!B29/100*A21/12 -> 1.31625 | E21: =SUM(B21:D21) -> 11.44125 | F21: =E21/'1 Inputs'!B13*100 -> 176.01923
A22: 24 | B22: ='1 Inputs'!B27*A22/12 -> 12.271537 | C22: ='1 Inputs'!B28*A22/12 -> 1.2284629 | D22: ='1 Inputs'!B12*'1 Inputs'!B29/100*A22/12 -> 1.755 | E22: =SUM(B22:D22) -> 15.255 | F22: =E22/'1 Inputs'!B13*100 -> 234.69231
A23: 36 | B23: ='1 Inputs'!B27*A23/12 -> 18.407306 | C23: ='1 Inputs'!B28*A23/12 -> 1.8426944 | D23: ='1 Inputs'!B12*'1 Inputs'!B29/100*A23/12 -> 2.6325 | E23: =SUM(B23:D23) -> 22.8825 | F23: =E23/'1 Inputs'!B13*100 -> 352.03846
A24: Months are typed as text so the chart axis reads exactly what is in column A. Breakeven = carry+roll / spread duration, ignoring convexity (tab 6 adds it).
H27: The one preset in this workbook: the stacked chart's value axis is forced to zero. Excel would otherwise auto-scale the baseline and visually misstate the split. Correctness, not cosmetics.

Sheet 3 Carry quality
A1: Why the carry is high quality — and why index composition is the reason
A2: Four tests. 'High carry' is common; 'high-quality carry' is the claim that has to be earned, and each test below earns it with a number.
A4: Carry is only worth owning if you keep it. These four tests ask whether you do.
A6: Test 1 — Is it cash, or is it a mark?
A7: Cash coupon share of carry + roll | B7: ='1 Inputs'!B27/'1 Inputs'!B30*'1 Inputs'!B22 -> 0.80442721 | F7: Received in cash. Cannot be revalued away. The other 20% (pull-to-par and roll) are marks that need the curve to behave.
A8: Index average price | B8: ='1 Inputs'!B26 -> 91.26811 | F8: THIS is why the cash share is high. The index trades at a modest discount, not a deep one, so the coupon does the work.
A9: Memo: cash share if the index traded at 60 | B9: =('1 Inputs'!B10/60)/(('1 Inputs'!B10/60)+('1 Inputs'!B25-'1 Inputs'!B10/60)+'1 Inputs'!B12*'1 Inputs'!B29/100) -> 0.012236425 | F9: A distressed index at 60 would show a huge headline yield of which most is accretion — contingent on surviving to maturity. That is low-quality carry. Ours is the opposite case.
A11: Test 2 — Is the spread compensation, or is it expected loss?
A12: A spread is only a risk premium to the extent it exceeds the credit losses you should expect. Build it bottom-up from the rating buckets.
A13: Rating bucket | B13: Index wt (%) | C13: Annual PD (%) | D13: Loss given default (%) | E13: Expected loss (bp) | F13: Source / comment
A14: A | B14: 17.28 | C14: 0.05 | D14: =$B$22 -> 50 | E14: =B14*C14/100*D14/100*100 -> 0.432 | F14: Sovereign IG defaults are rare. iShares EMB, 7-Aug-26.
A15: BBB | B15: 33.41 | C15: 0.15 | D15: =$B$22 -> 50 | E15: =B15*C15/100*D15/100*100 -> 2.50575 | F15: Largest single bucket. This is the investment-grade core of the index.
A16: BB | B16: 24.95 | C16: 0.65 | D16: =$B$22 -> 50 | E16: =B16*C16/100*D16/100*100 -> 8.10875 | F16: Crossover. Most EM sovereigns that get into trouble spend years here first — defaults are telegraphed.
A17: B | B17: 19.13 | C17: 2 | D17: =$B$22 -> 50 | E17: =B17*C17/100*D17/100*100 -> 19.13 | F17: The genuine credit risk in the index.
A18: CCC | B18: 3.79 | C18: 12 | D18: =$B$22 -> 50 | E18: =B18*C18/100*D18/100*100 -> 22.74 | F18: The distressed tail. Note how small it is — 3.8% of the index.
A19: Already in default (D) | B19: 0.32 | F19: Priced at recovery already — no further expected loss to charge.
A20: Cash and derivatives | B20: 1.11
A21: Total | B21: =SUM(B14:B20) -> 99.99 | E21: =SUM(E14:E18) -> 52.9165
A22: Loss given default (%) = 100 less recovery | B22: 50 | F22: Recovery of 50 on the bond. Recent EM sovereign restructurings cleared around 50-65 for bondholders (Ukraine, Ghana, Zambia, Sri Lanka), so 50 is deliberately conservative. NOT the 95% figure in the GEMs/EIB study — that is multilateral lending with preferred creditor status and does not apply to bondholders.
A24: Index spread (bp) | B24: ='1 Inputs'!B5 -> 220
A25: Less: expected credit loss (bp) | B25: =-E21 -> -52.9165
A26: Equals: risk and liquidity premium (bp) | B26: ='1 Inputs'!B5-E21 -> 167.0835 | F26: The part of the spread you keep if the base case happens. This is the real answer to 'is the carry high quality'.
A27: Risk premium as share of spread | B27: =B26/'1 Inputs'!B5 -> 0.75947045
A29: Carry + roll net of expected loss (%) | B29: ='1 Inputs'!B30-E21/100*'1 Inputs'!B22 -> 7.098335
A30: Breakeven widening, net of expected loss (bp) | B30: =B29/'1 Inputs'!B13*100 -> 109.20515 | F30: Charge full through-cycle credit losses against the carry and the breakeven barely moves. That is the test passing.
A32: Test 3 — Can a single name take the carry away?
A33: Diversification is what turns a risky asset into a durable income stream. Measure it in months of carry.
A34: Number of holdings | B34: 612 | F34: iShares EMB, 7-Aug-26. 86.9% sovereign, 12.0% agency.
A35: Largest single country weight (%) | B35: 6.3 | F35: Saudi Arabia. Then Mexico 6.26, Turkey 4.87, Indonesia 4.25, Brazil 3.83. No concentration anywhere.
A36: Carry + roll per month (%) | B36: ='1 Inputs'!B30/'1 Inputs'!B22/12 -> 0.635625
A38: Credit event | B38: Weight hit (%) | C38: Loss given default (%) | D38: Cost to index (%) | E38: Months of carry to repay | F38: Comment
A39: A 1% weight defaults outright | B39: 1 | C39: =$B$22 -> 50 | D39: =B39*C39/100 -> 0.5 | E39: =D39/$B36 -> 0.78662734 | F39: Trivial at index level. Less than one month of carry.
A40: A 3% weight defaults outright | B40: 3 | C40: =$B$22 -> 50 | D40: =B40*C40/100 -> 1.5 | E40: =D40/$B36 -> 2.359882 | F40: A mid-size country gone. Still under three months.
A41: The largest country defaults | B41: =B35 -> 6.3 | C41: =$B$22 -> 50 | D41: =B41*C41/100 -> 3.15 | E41: =D41/$B36 -> 4.9557522 | F41: Saudi Arabia at 6.3%. An almost unthinkable event, and it costs five months of carry.
A42: The ENTIRE CCC bucket defaults | B42: 3.79 | C42: =$B$22 -> 50 | D42: =B42*C42/100 -> 1.895 | E42: =D42/$B36 -> 2.9813176 | F42: Every distressed credit in the index defaults at once. Three months of carry. This is the number that settles the argument.
A43: CCC and half of B default | B43: 13.36 | C43: =$B$22 -> 50 | D43: =B43*C43/100 -> 6.68 | E43: =D43/$B36 -> 10.509341 | F43: A systemic EM credit crisis with no precedent since the 1990s. Roughly ten months of carry.
A45: Loss given default is linked to the same input cell as Test 2, so the whole tab moves together when you flex recovery.
A47: Test 4 — Is the composition itself getting better? (Yes — and this is the core of the call)
A48: The index is not the asset it was. Investment grade has gone from a sixth of it to more than half.
B49: IG share (%) | C49: HY share (%) | F49: Comment
A50: EM hard-currency index, 2000 | B50: 15 | C50: =100-B50 -> 85 | F50: Janus Henderson: IG share was 'around 15% in 2000'. The Brady-era index was a high-yield asset with a handful of IG names.
A51: EM hard-currency index, today | B51: 51.26 | C51: =100-B51 -> 48.74 | F51: iShares EMB, 7-Aug-26: IG 50.69%, HY 48.19%, cash 1.11% — renormalised excluding cash. Janus Henderson: 'now over 50%'.
A53: Rating actions, 2025 | B53: Upgrades > 2x downgrades | F53: Janus Henderson. Oman and Azerbaijan were upgraded to investment grade in July. UBS: no EM sovereign default since end-2023 and agency outlooks now more positive than negative.
A55: What that composition shift is worth — the quality-adjusted spread
A56: Comparing today's 220bp to the long-run average spread compares two different assets. Restate today's index at the 2000 composition to see it like for like.
A57: Assumed IG sub-index spread (bp) | B57: 115 | F57: The only judgement input here. Typical EM sovereign IG spread. Flex it and watch the adjustment move.
A58: Implied HY sub-index spread (bp) | B58: =('1 Inputs'!B5-B51/100*B57)/(1-B51/100) -> 330.42881 | F58: Backed out so the two sub-spreads reprice today's index at today's weights.
A59: Today's index at the 2000 composition (bp) | B59: =B50/100*B57+(1-B50/100)*B58 -> 298.11449 | F59: Same credits, same spreads, 2000's weights. This is what today's index would quote at if it still had the old composition.
A60: Quality adjustment (bp) | B60: =B59-'1 Inputs'!B5 -> 78.114485 | F60: Read this as: 220bp on today's index is roughly as generous as ~300bp was on the index of 2000. 'Spreads are at historic tights' is comparing a safer asset with a riskier one and calling the difference expensive.
A62: The four tests in one line each
A63: 1. Cash, not marks | B63: 80% of the carry is cash coupon, because the index trades at a modest discount rather than a distressed one.
A64: 2. Premium, not loss | B64: ~76% of the 220bp spread is risk premium; only ~53bp is expected credit loss. Charge the loss in full and the breakeven is still >100bp.
A65: 3. No single point of failure | B65: 612 holdings, largest country 6.3%. The entire CCC bucket defaulting costs about three months of carry.
A66: 4. Composition is improving | B66: IG share 15% in 2000 to 51% today; upgrades running at twice downgrades; no EM sovereign default since end-2023.
A68: The honest limit of this tab: PDs and recovery are through-cycle estimates, not a forecast, and the quality-adjusted spread rests on the assumed IG sub-index spread. All are blue. Flex them before quoting the numbers externally.
A69: Sources: iShares EMB fund characteristics and credit-quality breakdown, 7-Aug-2026. Janus Henderson, 'EM sovereign rating upgrades outpace downgrades' (IG share ~15% in 2000 to over 50% today; 2025 upgrades more than double downgrades; Oman and Azerbaijan to IG in July). UBS Asset Management EM Debt update (no sovereign default since end-2023; outlooks more positive than negative).

Sheet 4 Fed scenarios
A1: Total return by Fed path — full P&L attribution
A2: Six-way additive attribution over the horizon on tab 1. Probabilities are a house judgement; edit the blue column.
A4: Scenario | B4: Prob. | C4: Fed path (12m) | D4: d UST (bp) | E4: d Spread (bp) | F4: End spread (bp) | G4: Total d yield (bp) | H4: Cash coupon (%) | I4: Pull-to-par (%) | J4: Roll-down (%) | K4: Rates P&L (%) | L4: Spread P&L (%) | M4: Convexity (%) | N4: TOTAL RETURN (%) | O4: Prob-weighted (%)
A5: Immaculate disinflation | B5: 0.12 | C5: 3 cuts to 2.88% | D5: -60 | E5: -20 | F5: ='1 Inputs'!B5+E5 -> 200 | G5: =D5+E5 -> -80 | H5: ='1 Inputs'!B27*'1 Inputs'!B22 -> 6.1357685 | I5: ='1 Inputs'!B28*'1 Inputs'!B22 -> 0.61423147 | J5: ='1 Inputs'!B12*'1 Inputs'!B29/100*'1 Inputs'!B22 -> 0.8775 | K5: =-'1 Inputs'!B12*D5/100 -> 3.9 | L5: =-'1 Inputs'!B13*E5/100 -> 1.3 | M5: ='1 Inputs'!B14*G5^2/2000000 -> 0.192 | N5: =SUM(H5:M5) -> 13.0195 | O5: =B5*N5 -> 1.56234
A6: Soft landing (base case) | B6: 0.35 | C6: 1 cut to 3.38% | D6: -25 | E6: 30 | F6: ='1 Inputs'!B5+E6 -> 250 | G6: =D6+E6 -> 5 | H6: ='1 Inputs'!B27*'1 Inputs'!B22 -> 6.1357685 | I6: ='1 Inputs'!B28*'1 Inputs'!B22 -> 0.61423147 | J6: ='1 Inputs'!B12*'1 Inputs'!B29/100*'1 Inputs'!B22 -> 0.8775 | K6: =-'1 Inputs'!B12*D6/100 -> 1.625 | L6: =-'1 Inputs'!B13*E6/100 -> -1.95 | M6: ='1 Inputs'!B14*G6^2/2000000 -> 0.00075 | N6: =SUM(H6:M6) -> 7.30325 | O6: =B6*N6 -> 2.5561375
A7: Higher for longer | B7: 0.2 | C7: On hold at 3.63% through 2027 | D7: 25 | E7: 20 | F7: ='1 Inputs'!B5+E7 -> 240 | G7: =D7+E7 -> 45 | H7: ='1 Inputs'!B27*'1 Inputs'!B22 -> 6.1357685 | I7: ='1 Inputs'!B28*'1 Inputs'!B22 -> 0.61423147 | J7: ='1 Inputs'!B12*'1 Inputs'!B29/100*'1 Inputs'!B22 -> 0.8775 | K7: =-'1 Inputs'!B12*D7/100 -> -1.625 | L7: =-'1 Inputs'!B13*E7/100 -> -1.3 | M7: ='1 Inputs'!B14*G7^2/2000000 -> 0.06075 | N7: =SUM(H7:M7) -> 4.76325 | O7: =B7*N7 -> 0.95265
A8: Growth scare / mild recession | B8: 0.18 | C8: 3 cuts to 2.88% | D8: -100 | E8: 150 | F8: ='1 Inputs'!B5+E8 -> 370 | G8: =D8+E8 -> 50 | H8: ='1 Inputs'!B27*'1 Inputs'!B22 -> 6.1357685 | I8: ='1 Inputs'!B28*'1 Inputs'!B22 -> 0.61423147 | J8: ='1 Inputs'!B12*'1 Inputs'!B29/100*'1 Inputs'!B22 -> 0.8775 | K8: =-'1 Inputs'!B12*D8/100 -> 6.5 | L8: =-'1 Inputs'!B13*E8/100 -> -9.75 | M8: ='1 Inputs'!B14*G8^2/2000000 -> 0.075 | N8: =SUM(H8:M8) -> 4.4525 | O8: =B8*N8 -> 0.80145
A9: Stagflation — Fed hikes into weakness | B9: 0.08 | C9: 2-3 hikes to 4.38% | D9: 125 | E9: 200 | F9: ='1 Inputs'!B5+E9 -> 420 | G9: =D9+E9 -> 325 | H9: ='1 Inputs'!B27*'1 Inputs'!B22 -> 6.1357685 | I9: ='1 Inputs'!B28*'1 Inputs'!B22 -> 0.61423147 | J9: ='1 Inputs'!B12*'1 Inputs'!B29/100*'1 Inputs'!B22 -> 0.8775 | K9: =-'1 Inputs'!B12*D9/100 -> -8.125 | L9: =-'1 Inputs'!B13*E9/100 -> -13 | M9: ='1 Inputs'!B14*G9^2/2000000 -> 3.16875 | N9: =SUM(H9:M9) -> -10.32875 | O9: =B9*N9 -> -0.8263
A10: Hard landing / systemic stress | B10: 0.07 | C10: 5+ cuts to 1.88% | D10: -150 | E10: 400 | F10: ='1 Inputs'!B5+E10 -> 620 | G10: =D10+E10 -> 250 | H10: ='1 Inputs'!B27*'1 Inputs'!B22 -> 6.1357685 | I10: ='1 Inputs'!B28*'1 Inputs'!B22 -> 0.61423147 | J10: ='1 Inputs'!B12*'1 Inputs'!B29/100*'1 Inputs'!B22 -> 0.8775 | K10: =-'1 Inputs'!B12*D10/100 -> 9.75 | L10: =-'1 Inputs'!B13*E10/100 -> -26 | M10: ='1 Inputs'!B14*G10^2/2000000 -> 1.875 | N10: =SUM(H10:M10) -> -6.7475 | O10: =B10*N10 -> -0.472325
A11: Probability-weighted expected return | B11: =SUM(B5:B10) -> 1 | O11: =SUM(O5:O10) -> 4.5739525
A12: Worst scenario | O12: =MIN(N5:N10) -> -10.32875
A13: Best scenario | O13: =MAX(N5:N10) -> 13.0195
A14: Probability of a negative return | O14: =SUMIF(N5:N10,"<0",B5:B10) -> 0.15
A16: Why each scenario looks the way it does
A17: Immaculate disinflation | C17: Inflation falls to target without a growth cost. Curve bull-steepens, EM spreads grind tighter on flows.
A18: Soft landing (base case) | C18: UBS base case. Labour cools gradually, inflation drifts down from 3.5%. Spreads widen modestly to the house target on supply and tight-valuation profit-taking.
A19: Higher for longer | C19: Inflation sticks near 3.5%, labour stabilises. Fed does nothing. Carry accrues — the best risk-adjusted outcome even though it is not the best absolute one.
A20: Growth scare / mild recession | C20: A normal cyclical downturn. Spreads widen 150bp — roughly the 2013 taper tantrum or the 2018 EM selloff — and the Treasury rally genuinely does offset it. THIS is the scenario the hedge argument works in.
A21: Stagflation — Fed hikes into weakness | C21: The worst case, and the one to worry about. Inflation forces hikes while EM fundamentals deteriorate: higher funding costs, a stronger dollar, capital outflows. Both legs move against you and there is NO hedge. Three FOMC members already dissented for a hike in July.
A22: Hard landing / systemic stress | C22: A genuine crisis, sized off history rather than optimism: EMBI widened +680bp in 2008 and +430bp in COVID. At +400bp the spread costs 26% and even a 150bp Treasury rally only pays back 9.8%. The hedge is overwhelmed.
A24: THE HEDGE IS PARTIAL, NOT COMPLETE — read these two rows together. In the growth-scare row spreads widen 150bp and the return is STILL +4.5%, because the Treasury rally offsets it. That is the hedge working, and it covers ordinary cyclical stress. In the hard-landing row spreads widen 400bp and the return is -6.8%, because a 400bp spread move costs 26% while a 150bp Treasury rally only pays 9.8%. The hedge is overwhelmed by a systemic event.
A25: The stagflation row is the worst outcome in the set, because it is the only one where both legs move the SAME way — the Fed hiking into deteriorating EM fundamentals. Rates risk and credit risk stop offsetting exactly when inflation, not growth, is the driver. If you hedge anything, hedge that quadrant, not the credit.
A26: Convexity term = C * (total d yield)^2 / 2,000,000, which is 100 * 0.5 * C * dy^2 with dy in decimals. Small at these moves, material beyond +/-200bp.

Sheet 5 Return grid
A1: Total return: spread move x Treasury move
A2: Every cell is a full total return over the horizon on tab 1, carry and roll included. Rows = spread change, columns = Treasury change, both in bp.
A4: d Spread (bp) \ d UST (bp) | B4: -150 | C4: -125 | D4: -100 | E4: -75 | F4: -50 | G4: -25 | H4: 0 | I4: 25 | J4: 50 | K4: 75 | L4: 100 | M4: 125 | N4: 150
A5: -50 | B5: ='1 Inputs'!B30-'1 Inputs'!B12*B$4/100-'1 Inputs'!B13*$A5/100+'1 Inputs'!B14*(B$4+$A5)^2/2000000 -> 21.8275 | C5: ='1 Inputs'!B30-'1 Inputs'!B12*C$4/100-'1 Inputs'!B13*$A5/100+'1 Inputs'!B14*(C$4+$A5)^2/2000000 -> 19.92125 | D5: ='1 Inputs'!B30-'1 Inputs'!B12*D$4/100-'1 Inputs'!B13*$A5/100+'1 Inputs'!B14*(D$4+$A5)^2/2000000 -> 18.0525 | E5: ='1 Inputs'!B30-'1 Inputs'!B12*E$4/100-'1 Inputs'!B13*$A5/100+'1 Inputs'!B14*(E$4+$A5)^2/2000000 -> 16.22125 | F5: ='1 Inputs'!B30-'1 Inputs'!B12*F$4/100-'1 Inputs'!B13*$A5/100+'1 Inputs'!B14*(F$4+$A5)^2/2000000 -> 14.4275 | G5: ='1 Inputs'!B30-'1 Inputs'!B12*G$4/100-'1 Inputs'!B13*$A5/100+'1 Inputs'!B14*(G$4+$A5)^2/2000000 -> 12.67125 | H5: ='1 Inputs'!B30-'1 Inputs'!B12*H$4/100-'1 Inputs'!B13*$A5/100+'1 Inputs'!B14*(H$4+$A5)^2/2000000 -> 10.9525 | I5: ='1 Inputs'!B30-'1 Inputs'!B12*I$4/100-'1 Inputs'!B13*$A5/100+'1 Inputs'!B14*(I$4+$A5)^2/2000000 -> 9.27125 | J5: ='1 Inputs'!B30-'1 Inputs'!B12*J$4/100-'1 Inputs'!B13*$A5/100+'1 Inputs'!B14*(J$4+$A5)^2/2000000 -> 7.6275 | K5: ='1 Inputs'!B30-'1 Inputs'!B12*K$4/100-'1 Inputs'!B13*$A5/100+'1 Inputs'!B14*(K$4+$A5)^2/2000000 -> 6.02125 | L5: ='1 Inputs'!B30-'1 Inputs'!B12*L$4/100-'1 Inputs'!B13*$A5/100+'1 Inputs'!B14*(L$4+$A5)^2/2000000 -> 4.4525 | M5: ='1 Inputs'!B30-'1 Inputs'!B12*M$4/100-'1 Inputs'!B13*$A5/100+'1 Inputs'!B14*(M$4+$A5)^2/2000000 -> 2.92125 | N5: ='1 Inputs'!B30-'1 Inputs'!B12*N$4/100-'1 Inputs'!B13*$A5/100+'1 Inputs'!B14*(N$4+$A5)^2/2000000 -> 1.4275
A6: -25 | B6: ='1 Inputs'!B30-'1 Inputs'!B12*B$4/100-'1 Inputs'!B13*$A6/100+'1 Inputs'!B14*(B$4+$A6)^2/2000000 -> 19.92125 | C6: ='1 Inputs'!B30-'1 Inputs'!B12*C$4/100-'1 Inputs'!B13*$A6/100+'1 Inputs'!B14*(C$4+$A6)^2/2000000 -> 18.0525 | D6: ='1 Inputs'!B30-'1 Inputs'!B12*D$4/100-'1 Inputs'!B13*$A6/100+'1 Inputs'!B14*(D$4+$A6)^2/2000000 -> 16.22125 | E6: ='1 Inputs'!B30-'1 Inputs'!B12*E$4/100-'1 Inputs'!B13*$A6/100+'1 Inputs'!B14*(E$4+$A6)^2/2000000 -> 14.4275 | F6: ='1 Inputs'!B30-'1 Inputs'!B12*F$4/100-'1 Inputs'!B13*$A6/100+'1 Inputs'!B14*(F$4+$A6)^2/2000000 -> 12.67125 | G6: ='1 Inputs'!B30-'1 Inputs'!B12*G$4/100-'1 Inputs'!B13*$A6/100+'1 Inputs'!B14*(G$4+$A6)^2/2000000 -> 10.9525 | H6: ='1 Inputs'!B30-'1 Inputs'!B12*H$4/100-'1 Inputs'!B13*$A6/100+'1 Inputs'!B14*(H$4+$A6)^2/2000000 -> 9.27125 | I6: ='1 Inputs'!B30-'1 Inputs'!B12*I$4/100-'1 Inputs'!B13*$A6/100+'1 Inputs'!B14*(I$4+$A6)^2/2000000 -> 7.6275 | J6: ='1 Inputs'!B30-'1 Inputs'!B12*J$4/100-'1 Inputs'!B13*$A6/100+'1 Inputs'!B14*(J$4+$A6)^2/2000000 -> 6.02125 | K6: ='1 Inputs'!B30-'1 Inputs'!B12*K$4/100-'1 Inputs'!B13*$A6/100+'1 Inputs'!B14*(K$4+$A6)^2/2000000 -> 4.4525 | L6: ='1 Inputs'!B30-'1 Inputs'!B12*L$4/100-'1 Inputs'!B13*$A6/100+'1 Inputs'!B14*(L$4+$A6)^2/2000000 -> 2.92125 | M6: ='1 Inputs'!B30-'1 Inputs'!B12*M$4/100-'1 Inputs'!B13*$A6/100+'1 Inputs'!B14*(M$4+$A6)^2/2000000 -> 1.4275 | N6: ='1 Inputs'!B30-'1 Inputs'!B12*N$4/100-'1 Inputs'!B13*$A6/100+'1 Inputs'!B14*(N$4+$A6)^2/2000000 -> -0.02875
A7: 0 | B7: ='1 Inputs'!B30-'1 Inputs'!B12*B$4/100-'1 Inputs'!B13*$A7/100+'1 Inputs'!B14*(B$4+$A7)^2/2000000 -> 18.0525 | C7: ='1 Inputs'!B30-'1 Inputs'!B12*C$4/100-'1 Inputs'!B13*$A7/100+'1 Inputs'!B14*(C$4+$A7)^2/2000000 -> 16.22125 | D7: ='1 Inputs'!B30-'1 Inputs'!B12*D$4/100-'1 Inputs'!B13*$A7/100+'1 Inputs'!B14*(D$4+$A7)^2/2000000 -> 14.4275 | E7: ='1 Inputs'!B30-'1 Inputs'!B12*E$4/100-'1 Inputs'!B13*$A7/100+'1 Inputs'!B14*(E$4+$A7)^2/2000000 -> 12.67125 | F7: ='1 Inputs'!B30-'1 Inputs'!B12*F$4/100-'1 Inputs'!B13*$A7/100+'1 Inputs'!B14*(F$4+$A7)^2/2000000 -> 10.9525 | G7: ='1 Inputs'!B30-'1 Inputs'!B12*G$4/100-'1 Inputs'!B13*$A7/100+'1 Inputs'!B14*(G$4+$A7)^2/2000000 -> 9.27125 | H7: ='1 Inputs'!B30-'1 Inputs'!B12*H$4/100-'1 Inputs'!B13*$A7/100+'1 Inputs'!B14*(H$4+$A7)^2/2000000 -> 7.6275 | I7: ='1 Inputs'!B30-'1 Inputs'!B12*I$4/100-'1 Inputs'!B13*$A7/100+'1 Inputs'!B14*(I$4+$A7)^2/2000000 -> 6.02125 | J7: ='1 Inputs'!B30-'1 Inputs'!B12*J$4/100-'1 Inputs'!B13*$A7/100+'1 Inputs'!B14*(J$4+$A7)^2/2000000 -> 4.4525 | K7: ='1 Inputs'!B30-'1 Inputs'!B12*K$4/100-'1 Inputs'!B13*$A7/100+'1 Inputs'!B14*(K$4+$A7)^2/2000000 -> 2.92125 | L7: ='1 Inputs'!B30-'1 Inputs'!B12*L$4/100-'1 Inputs'!B13*$A7/100+'1 Inputs'!B14*(L$4+$A7)^2/2000000 -> 1.4275 | M7: ='1 Inputs'!B30-'1 Inputs'!B12*M$4/100-'1 Inputs'!B13*$A7/100+'1 Inputs'!B14*(M$4+$A7)^2/2000000 -> -0.02875 | N7: ='1 Inputs'!B30-'1 Inputs'!B12*N$4/100-'1 Inputs'!B13*$A7/100+'1 Inputs'!B14*(N$4+$A7)^2/2000000 -> -1.4475
A8: 25 | B8: ='1 Inputs'!B30-'1 Inputs'!B12*B$4/100-'1 Inputs'!B13*$A8/100+'1 Inputs'!B14*(B$4+$A8)^2/2000000 -> 16.22125 | C8: ='1 Inputs'!B30-'1 Inputs'!B12*C$4/100-'1 Inputs'!B13*$A8/100+'1 Inputs'!B14*(C$4+$A8)^2/2000000 -> 14.4275 | D8: ='1 Inputs'!B30-'1 Inputs'!B12*D$4/100-'1 Inputs'!B13*$A8/100+'1 Inputs'!B14*(D$4+$A8)^2/2000000 -> 12.67125 | E8: ='1 Inputs'!B30-'1 Inputs'!B12*E$4/100-'1 Inputs'!B13*$A8/100+'1 Inputs'!B14*(E$4+$A8)^2/2000000 -> 10.9525 | F8: ='1 Inputs'!B30-'1 Inputs'!B12*F$4/100-'1 Inputs'!B13*$A8/100+'1 Inputs'!B14*(F$4+$A8)^2/2000000 -> 9.27125 | G8: ='1 Inputs'!B30-'1 Inputs'!B12*G$4/100-'1 Inputs'!B13*$A8/100+'1 Inputs'!B14*(G$4+$A8)^2/2000000 -> 7.6275 | H8: ='1 Inputs'!B30-'1 Inputs'!B12*H$4/100-'1 Inputs'!B13*$A8/100+'1 Inputs'!B14*(H$4+$A8)^2/2000000 -> 6.02125 | I8: ='1 Inputs'!B30-'1 Inputs'!B12*I$4/100-'1 Inputs'!B13*$A8/100+'1 Inputs'!B14*(I$4+$A8)^2/2000000 -> 4.4525 | J8: ='1 Inputs'!B30-'1 Inputs'!B12*J$4/100-'1 Inputs'!B13*$A8/100+'1 Inputs'!B14*(J$4+$A8)^2/2000000 -> 2.92125 | K8: ='1 Inputs'!B30-'1 Inputs'!B12*K$4/100-'1 Inputs'!B13*$A8/100+'1 Inputs'!B14*(K$4+$A8)^2/2000000 -> 1.4275 | L8: ='1 Inputs'!B30-'1 Inputs'!B12*L$4/100-'1 Inputs'!B13*$A8/100+'1 Inputs'!B14*(L$4+$A8)^2/2000000 -> -0.02875 | M8: ='1 Inputs'!B30-'1 Inputs'!B12*M$4/100-'1 Inputs'!B13*$A8/100+'1 Inputs'!B14*(M$4+$A8)^2/2000000 -> -1.4475 | N8: ='1 Inputs'!B30-'1 Inputs'!B12*N$4/100-'1 Inputs'!B13*$A8/100+'1 Inputs'!B14*(N$4+$A8)^2/2000000 -> -2.82875
A9: 50 | B9: ='1 Inputs'!B30-'1 Inputs'!B12*B$4/100-'1 Inputs'!B13*$A9/100+'1 Inputs'!B14*(B$4+$A9)^2/2000000 -> 14.4275 | C9: ='1 Inputs'!B30-'1 Inputs'!B12*C$4/100-'1 Inputs'!B13*$A9/100+'1 Inputs'!B14*(C$4+$A9)^2/2000000 -> 12.67125 | D9: ='1 Inputs'!B30-'1 Inputs'!B12*D$4/100-'1 Inputs'!B13*$A9/100+'1 Inputs'!B14*(D$4+$A9)^2/2000000 -> 10.9525 | E9: ='1 Inputs'!B30-'1 Inputs'!B12*E$4/100-'1 Inputs'!B13*$A9/100+'1 Inputs'!B14*(E$4+$A9)^2/2000000 -> 9.27125 | F9: ='1 Inputs'!B30-'1 Inputs'!B12*F$4/100-'1 Inputs'!B13*$A9/100+'1 Inputs'!B14*(F$4+$A9)^2/2000000 -> 7.6275 | G9: ='1 Inputs'!B30-'1 Inputs'!B12*G$4/100-'1 Inputs'!B13*$A9/100+'1 Inputs'!B14*(G$4+$A9)^2/2000000 -> 6.02125 | H9: ='1 Inputs'!B30-'1 Inputs'!B12*H$4/100-'1 Inputs'!B13*$A9/100+'1 Inputs'!B14*(H$4+$A9)^2/2000000 -> 4.4525 | I9: ='1 Inputs'!B30-'1 Inputs'!B12*I$4/100-'1 Inputs'!B13*$A9/100+'1 Inputs'!B14*(I$4+$A9)^2/2000000 -> 2.92125 | J9: ='1 Inputs'!B30-'1 Inputs'!B12*J$4/100-'1 Inputs'!B13*$A9/100+'1 Inputs'!B14*(J$4+$A9)^2/2000000 -> 1.4275 | K9: ='1 Inputs'!B30-'1 Inputs'!B12*K$4/100-'1 Inputs'!B13*$A9/100+'1 Inputs'!B14*(K$4+$A9)^2/2000000 -> -0.02875 | L9: ='1 Inputs'!B30-'1 Inputs'!B12*L$4/100-'1 Inputs'!B13*$A9/100+'1 Inputs'!B14*(L$4+$A9)^2/2000000 -> -1.4475 | M9: ='1 Inputs'!B30-'1 Inputs'!B12*M$4/100-'1 Inputs'!B13*$A9/100+'1 Inputs'!B14*(M$4+$A9)^2/2000000 -> -2.82875 | N9: ='1 Inputs'!B30-'1 Inputs'!B12*N$4/100-'1 Inputs'!B13*$A9/100+'1 Inputs'!B14*(N$4+$A9)^2/2000000 -> -4.1725
A10: 75 | B10: ='1 Inputs'!B30-'1 Inputs'!B12*B$4/100-'1 Inputs'!B13*$A10/100+'1 Inputs'!B14*(B$4+$A10)^2/2000000 -> 12.67125 | C10: ='1 Inputs'!B30-'1 Inputs'!B12*C$4/100-'1 Inputs'!B13*$A10/100+'1 Inputs'!B14*(C$4+$A10)^2/2000000 -> 10.9525 | D10: ='1 Inputs'!B30-'1 Inputs'!B12*D$4/100-'1 Inputs'!B13*$A10/100+'1 Inputs'!B14*(D$4+$A10)^2/2000000 -> 9.27125 | E10: ='1 Inputs'!B30-'1 Inputs'!B12*E$4/100-'1 Inputs'!B13*$A10/100+'1 Inputs'!B14*(E$4+$A10)^2/2000000 -> 7.6275 | F10: ='1 Inputs'!B30-'1 Inputs'!B12*F$4/100-'1 Inputs'!B13*$A10/100+'1 Inputs'!B14*(F$4+$A10)^2/2000000 -> 6.02125 | G10: ='1 Inputs'!B30-'1 Inputs'!B12*G$4/100-'1 Inputs'!B13*$A10/100+'1 Inputs'!B14*(G$4+$A10)^2/2000000 -> 4.4525 | H10: ='1 Inputs'!B30-'1 Inputs'!B12*H$4/100-'1 Inputs'!B13*$A10/100+'1 Inputs'!B14*(H$4+$A10)^2/2000000 -> 2.92125 | I10: ='1 Inputs'!B30-'1 Inputs'!B12*I$4/100-'1 Inputs'!B13*$A10/100+'1 Inputs'!B14*(I$4+$A10)^2/2000000 -> 1.4275 | J10: ='1 Inputs'!B30-'1 Inputs'!B12*J$4/100-'1 Inputs'!B13*$A10/100+'1 Inputs'!B14*(J$4+$A10)^2/2000000 -> -0.02875 | K10: ='1 Inputs'!B30-'1 Inputs'!B12*K$4/100-'1 Inputs'!B13*$A10/100+'1 Inputs'!B14*(K$4+$A10)^2/2000000 -> -1.4475 | L10: ='1 Inputs'!B30-'1 Inputs'!B12*L$4/100-'1 Inputs'!B13*$A10/100+'1 Inputs'!B14*(L$4+$A10)^2/2000000 -> -2.82875 | M10: ='1 Inputs'!B30-'1 Inputs'!B12*M$4/100-'1 Inputs'!B13*$A10/100+'1 Inputs'!B14*(M$4+$A10)^2/2000000 -> -4.1725 | N10: ='1 Inputs'!B30-'1 Inputs'!B12*N$4/100-'1 Inputs'!B13*$A10/100+'1 Inputs'!B14*(N$4+$A10)^2/2000000 -> -5.47875
A11: 100 | B11: ='1 Inputs'!B30-'1 Inputs'!B12*B$4/100-'1 Inputs'!B13*$A11/100+'1 Inputs'!B14*(B$4+$A11)^2/2000000 -> 10.9525 | C11: ='1 Inputs'!B30-'1 Inputs'!B12*C$4/100-'1 Inputs'!B13*$A11/100+'1 Inputs'!B14*(C$4+$A11)^2/2000000 -> 9.27125 | D11: ='1 Inputs'!B30-'1 Inputs'!B12*D$4/100-'1 Inputs'!B13*$A11/100+'1 Inputs'!B14*(D$4+$A11)^2/2000000 -> 7.6275 | E11: ='1 Inputs'!B30-'1 Inputs'!B12*E$4/100-'1 Inputs'!B13*$A11/100+'1 Inputs'!B14*(E$4+$A11)^2/2000000 -> 6.02125 | F11: ='1 Inputs'!B30-'1 Inputs'!B12*F$4/100-'1 Inputs'!B13*$A11/100+'1 Inputs'!B14*(F$4+$A11)^2/2000000 -> 4.4525 | G11: ='1 Inputs'!B30-'1 Inputs'!B12*G$4/100-'1 Inputs'!B13*$A11/100+'1 Inputs'!B14*(G$4+$A11)^2/2000000 -> 2.92125 | H11: ='1 Inputs'!B30-'1 Inputs'!B12*H$4/100-'1 Inputs'!B13*$A11/100+'1 Inputs'!B14*(H$4+$A11)^2/2000000 -> 1.4275 | I11: ='1 Inputs'!B30-'1 Inputs'!B12*I$4/100-'1 Inputs'!B13*$A11/100+'1 Inputs'!B14*(I$4+$A11)^2/2000000 -> -0.02875 | J11: ='1 Inputs'!B30-'1 Inputs'!B12*J$4/100-'1 Inputs'!B13*$A11/100+'1 Inputs'!B14*(J$4+$A11)^2/2000000 -> -1.4475 | K11: ='1 Inputs'!B30-'1 Inputs'!B12*K$4/100-'1 Inputs'!B13*$A11/100+'1 Inputs'!B14*(K$4+$A11)^2/2000000 -> -2.82875 | L11: ='1 Inputs'!B30-'1 Inputs'!B12*L$4/100-'1 Inputs'!B13*$A11/100+'1 Inputs'!B14*(L$4+$A11)^2/2000000 -> -4.1725 | M11: ='1 Inputs'!B30-'1 Inputs'!B12*M$4/100-'1 Inputs'!B13*$A11/100+'1 Inputs'!B14*(M$4+$A11)^2/2000000 -> -5.47875 | N11: ='1 Inputs'!B30-'1 Inputs'!B12*N$4/100-'1 Inputs'!B13*$A11/100+'1 Inputs'!B14*(N$4+$A11)^2/2000000 -> -6.7475
A12: 125 | B12: ='1 Inputs'!B30-'1 Inputs'!B12*B$4/100-'1 Inputs'!B13*$A12/100+'1 Inputs'!B14*(B$4+$A12)^2/2000000 -> 9.27125 | C12: ='1 Inputs'!B30-'1 Inputs'!B12*C$4/100-'1 Inputs'!B13*$A12/100+'1 Inputs'!B14*(C$4+$A12)^2/2000000 -> 7.6275 | D12: ='1 Inputs'!B30-'1 Inputs'!B12*D$4/100-'1 Inputs'!B13*$A12/100+'1 Inputs'!B14*(D$4+$A12)^2/2000000 -> 6.02125 | E12: ='1 Inputs'!B30-'1 Inputs'!B12*E$4/100-'1 Inputs'!B13*$A12/100+'1 Inputs'!B14*(E$4+$A12)^2/2000000 -> 4.4525 | F12: ='1 Inputs'!B30-'1 Inputs'!B12*F$4/100-'1 Inputs'!B13*$A12/100+'1 Inputs'!B14*(F$4+$A12)^2/2000000 -> 2.92125 | G12: ='1 Inputs'!B30-'1 Inputs'!B12*G$4/100-'1 Inputs'!B13*$A12/100+'1 Inputs'!B14*(G$4+$A12)^2/2000000 -> 1.4275 | H12: ='1 Inputs'!B30-'1 Inputs'!B12*H$4/100-'1 Inputs'!B13*$A12/100+'1 Inputs'!B14*(H$4+$A12)^2/2000000 -> -0.02875 | I12: ='1 Inputs'!B30-'1 Inputs'!B12*I$4/100-'1 Inputs'!B13*$A12/100+'1 Inputs'!B14*(I$4+$A12)^2/2000000 -> -1.4475 | J12: ='1 Inputs'!B30-'1 Inputs'!B12*J$4/100-'1 Inputs'!B13*$A12/100+'1 Inputs'!B14*(J$4+$A12)^2/2000000 -> -2.82875 | K12: ='1 Inputs'!B30-'1 Inputs'!B12*K$4/100-'1 Inputs'!B13*$A12/100+'1 Inputs'!B14*(K$4+$A12)^2/2000000 -> -4.1725 | L12: ='1 Inputs'!B30-'1 Inputs'!B12*L$4/100-'1 Inputs'!B13*$A12/100+'1 Inputs'!B14*(L$4+$A12)^2/2000000 -> -5.47875 | M12: ='1 Inputs'!B30-'1 Inputs'!B12*M$4/100-'1 Inputs'!B13*$A12/100+'1 Inputs'!B14*(M$4+$A12)^2/2000000 -> -6.7475 | N12: ='1 Inputs'!B30-'1 Inputs'!B12*N$4/100-'1 Inputs'!B13*$A12/100+'1 Inputs'!B14*(N$4+$A12)^2/2000000 -> -7.97875
A13: 150 | B13: ='1 Inputs'!B30-'1 Inputs'!B12*B$4/100-'1 Inputs'!B13*$A13/100+'1 Inputs'!B14*(B$4+$A13)^2/2000000 -> 7.6275 | C13: ='1 Inputs'!B30-'1 Inputs'!B12*C$4/100-'1 Inputs'!B13*$A13/100+'1 Inputs'!B14*(C$4+$A13)^2/2000000 -> 6.02125 | D13: ='1 Inputs'!B30-'1 Inputs'!B12*D$4/100-'1 Inputs'!B13*$A13/100+'1 Inputs'!B14*(D$4+$A13)^2/2000000 -> 4.4525 | E13: ='1 Inputs'!B30-'1 Inputs'!B12*E$4/100-'1 Inputs'!B13*$A13/100+'1 Inputs'!B14*(E$4+$A13)^2/2000000 -> 2.92125 | F13: ='1 Inputs'!B30-'1 Inputs'!B12*F$4/100-'1 Inputs'!B13*$A13/100+'1 Inputs'!B14*(F$4+$A13)^2/2000000 -> 1.4275 | G13: ='1 Inputs'!B30-'1 Inputs'!B12*G$4/100-'1 Inputs'!B13*$A13/100+'1 Inputs'!B14*(G$4+$A13)^2/2000000 -> -0.02875 | H13: ='1 Inputs'!B30-'1 Inputs'!B12*H$4/100-'1 Inputs'!B13*$A13/100+'1 Inputs'!B14*(H$4+$A13)^2/2000000 -> -1.4475 | I13: ='1 Inputs'!B30-'1 Inputs'!B12*I$4/100-'1 Inputs'!B13*$A13/100+'1 Inputs'!B14*(I$4+$A13)^2/2000000 -> -2.82875 | J13: ='1 Inputs'!B30-'1 Inputs'!B12*J$4/100-'1 Inputs'!B13*$A13/100+'1 Inputs'!B14*(J$4+$A13)^2/2000000 -> -4.1725 | K13: ='1 Inputs'!B30-'1 Inputs'!B12*K$4/100-'1 Inputs'!B13*$A13/100+'1 Inputs'!B14*(K$4+$A13)^2/2000000 -> -5.47875 | L13: ='1 Inputs'!B30-'1 Inputs'!B12*L$4/100-'1 Inputs'!B13*$A13/100+'1 Inputs'!B14*(L$4+$A13)^2/2000000 -> -6.7475 | M13: ='1 Inputs'!B30-'1 Inputs'!B12*M$4/100-'1 Inputs'!B13*$A13/100+'1 Inputs'!B14*(M$4+$A13)^2/2000000 -> -7.97875 | N13: ='1 Inputs'!B30-'1 Inputs'!B12*N$4/100-'1 Inputs'!B13*$A13/100+'1 Inputs'!B14*(N$4+$A13)^2/2000000 -> -9.1725
A14: 175 | B14: ='1 Inputs'!B30-'1 Inputs'!B12*B$4/100-'1 Inputs'!B13*$A14/100+'1 Inputs'!B14*(B$4+$A14)^2/2000000 -> 6.02125 | C14: ='1 Inputs'!B30-'1 Inputs'!B12*C$4/100-'1 Inputs'!B13*$A14/100+'1 Inputs'!B14*(C$4+$A14)^2/2000000 -> 4.4525 | D14: ='1 Inputs'!B30-'1 Inputs'!B12*D$4/100-'1 Inputs'!B13*$A14/100+'1 Inputs'!B14*(D$4+$A14)^2/2000000 -> 2.92125 | E14: ='1 Inputs'!B30-'1 Inputs'!B12*E$4/100-'1 Inputs'!B13*$A14/100+'1 Inputs'!B14*(E$4+$A14)^2/2000000 -> 1.4275 | F14: ='1 Inputs'!B30-'1 Inputs'!B12*F$4/100-'1 Inputs'!B13*$A14/100+'1 Inputs'!B14*(F$4+$A14)^2/2000000 -> -0.02875 | G14: ='1 Inputs'!B30-'1 Inputs'!B12*G$4/100-'1 Inputs'!B13*$A14/100+'1 Inputs'!B14*(G$4+$A14)^2/2000000 -> -1.4475 | H14: ='1 Inputs'!B30-'1 Inputs'!B12*H$4/100-'1 Inputs'!B13*$A14/100+'1 Inputs'!B14*(H$4+$A14)^2/2000000 -> -2.82875 | I14: ='1 Inputs'!B30-'1 Inputs'!B12*I$4/100-'1 Inputs'!B13*$A14/100+'1 Inputs'!B14*(I$4+$A14)^2/2000000 -> -4.1725 | J14: ='1 Inputs'!B30-'1 Inputs'!B12*J$4/100-'1 Inputs'!B13*$A14/100+'1 Inputs'!B14*(J$4+$A14)^2/2000000 -> -5.47875 | K14: ='1 Inputs'!B30-'1 Inputs'!B12*K$4/100-'1 Inputs'!B13*$A14/100+'1 Inputs'!B14*(K$4+$A14)^2/2000000 -> -6.7475 | L14: ='1 Inputs'!B30-'1 Inputs'!B12*L$4/100-'1 Inputs'!B13*$A14/100+'1 Inputs'!B14*(L$4+$A14)^2/2000000 -> -7.97875 | M14: ='1 Inputs'!B30-'1 Inputs'!B12*M$4/100-'1 Inputs'!B13*$A14/100+'1 Inputs'!B14*(M$4+$A14)^2/2000000 -> -9.1725 | N14: ='1 Inputs'!B30-'1 Inputs'!B12*N$4/100-'1 Inputs'!B13*$A14/100+'1 Inputs'!B14*(N$4+$A14)^2/2000000 -> -10.32875
A15: 200 | B15: ='1 Inputs'!B30-'1 Inputs'!B12*B$4/100-'1 Inputs'!B13*$A15/100+'1 Inputs'!B14*(B$4+$A15)^2/2000000 -> 4.4525 | C15: ='1 Inputs'!B30-'1 Inputs'!B12*C$4/100-'1 Inputs'!B13*$A15/100+'1 Inputs'!B14*(C$4+$A15)^2/2000000 -> 2.92125 | D15: ='1 Inputs'!B30-'1 Inputs'!B12*D$4/100-'1 Inputs'!B13*$A15/100+'1 Inputs'!B14*(D$4+$A15)^2/2000000 -> 1.4275 | E15: ='1 Inputs'!B30-'1 Inputs'!B12*E$4/100-'1 Inputs'!B13*$A15/100+'1 Inputs'!B14*(E$4+$A15)^2/2000000 -> -0.02875 | F15: ='1 Inputs'!B30-'1 Inputs'!B12*F$4/100-'1 Inputs'!B13*$A15/100+'1 Inputs'!B14*(F$4+$A15)^2/2000000 -> -1.4475 | G15: ='1 Inputs'!B30-'1 Inputs'!B12*G$4/100-'1 Inputs'!B13*$A15/100+'1 Inputs'!B14*(G$4+$A15)^2/2000000 -> -2.82875 | H15: ='1 Inputs'!B30-'1 Inputs'!B12*H$4/100-'1 Inputs'!B13*$A15/100+'1 Inputs'!B14*(H$4+$A15)^2/2000000 -> -4.1725 | I15: ='1 Inputs'!B30-'1 Inputs'!B12*I$4/100-'1 Inputs'!B13*$A15/100+'1 Inputs'!B14*(I$4+$A15)^2/2000000 -> -5.47875 | J15: ='1 Inputs'!B30-'1 Inputs'!B12*J$4/100-'1 Inputs'!B13*$A15/100+'1 Inputs'!B14*(J$4+$A15)^2/2000000 -> -6.7475 | K15: ='1 Inputs'!B30-'1 Inputs'!B12*K$4/100-'1 Inputs'!B13*$A15/100+'1 Inputs'!B14*(K$4+$A15)^2/2000000 -> -7.97875 | L15: ='1 Inputs'!B30-'1 Inputs'!B12*L$4/100-'1 Inputs'!B13*$A15/100+'1 Inputs'!B14*(L$4+$A15)^2/2000000 -> -9.1725 | M15: ='1 Inputs'!B30-'1 Inputs'!B12*M$4/100-'1 Inputs'!B13*$A15/100+'1 Inputs'!B14*(M$4+$A15)^2/2000000 -> -10.32875 | N15: ='1 Inputs'!B30-'1 Inputs'!B12*N$4/100-'1 Inputs'!B13*$A15/100+'1 Inputs'!B14*(N$4+$A15)^2/2000000 -> -11.4475
A16: 225 | B16: ='1 Inputs'!B30-'1 Inputs'!B12*B$4/100-'1 Inputs'!B13*$A16/100+'1 Inputs'!B14*(B$4+$A16)^2/2000000 -> 2.92125 | C16: ='1 Inputs'!B30-'1 Inputs'!B12*C$4/100-'1 Inputs'!B13*$A16/100+'1 Inputs'!B14*(C$4+$A16)^2/2000000 -> 1.4275 | D16: ='1 Inputs'!B30-'1 Inputs'!B12*D$4/100-'1 Inputs'!B13*$A16/100+'1 Inputs'!B14*(D$4+$A16)^2/2000000 -> -0.02875 | E16: ='1 Inputs'!B30-'1 Inputs'!B12*E$4/100-'1 Inputs'!B13*$A16/100+'1 Inputs'!B14*(E$4+$A16)^2/2000000 -> -1.4475 | F16: ='1 Inputs'!B30-'1 Inputs'!B12*F$4/100-'1 Inputs'!B13*$A16/100+'1 Inputs'!B14*(F$4+$A16)^2/2000000 -> -2.82875 | G16: ='1 Inputs'!B30-'1 Inputs'!B12*G$4/100-'1 Inputs'!B13*$A16/100+'1 Inputs'!B14*(G$4+$A16)^2/2000000 -> -4.1725 | H16: ='1 Inputs'!B30-'1 Inputs'!B12*H$4/100-'1 Inputs'!B13*$A16/100+'1 Inputs'!B14*(H$4+$A16)^2/2000000 -> -5.47875 | I16: ='1 Inputs'!B30-'1 Inputs'!B12*I$4/100-'1 Inputs'!B13*$A16/100+'1 Inputs'!B14*(I$4+$A16)^2/2000000 -> -6.7475 | J16: ='1 Inputs'!B30-'1 Inputs'!B12*J$4/100-'1 Inputs'!B13*$A16/100+'1 Inputs'!B14*(J$4+$A16)^2/2000000 -> -7.97875 | K16: ='1 Inputs'!B30-'1 Inputs'!B12*K$4/100-'1 Inputs'!B13*$A16/100+'1 Inputs'!B14*(K$4+$A16)^2/2000000 -> -9.1725 | L16: ='1 Inputs'!B30-'1 Inputs'!B12*L$4/100-'1 Inputs'!B13*$A16/100+'1 Inputs'!B14*(L$4+$A16)^2/2000000 -> -10.32875 | M16: ='1 Inputs'!B30-'1 Inputs'!B12*M$4/100-'1 Inputs'!B13*$A16/100+'1 Inputs'!B14*(M$4+$A16)^2/2000000 -> -11.4475 | N16: ='1 Inputs'!B30-'1 Inputs'!B12*N$4/100-'1 Inputs'!B13*$A16/100+'1 Inputs'!B14*(N$4+$A16)^2/2000000 -> -12.52875
A17: 250 | B17: ='1 Inputs'!B30-'1 Inputs'!B12*B$4/100-'1 Inputs'!B13*$A17/100+'1 Inputs'!B14*(B$4+$A17)^2/2000000 -> 1.4275 | C17: ='1 Inputs'!B30-'1 Inputs'!B12*C$4/100-'1 Inputs'!B13*$A17/100+'1 Inputs'!B14*(C$4+$A17)^2/2000000 -> -0.02875 | D17: ='1 Inputs'!B30-'1 Inputs'!B12*D$4/100-'1 Inputs'!B13*$A17/100+'1 Inputs'!B14*(D$4+$A17)^2/2000000 -> -1.4475 | E17: ='1 Inputs'!B30-'1 Inputs'!B12*E$4/100-'1 Inputs'!B13*$A17/100+'1 Inputs'!B14*(E$4+$A17)^2/2000000 -> -2.82875 | F17: ='1 Inputs'!B30-'1 Inputs'!B12*F$4/100-'1 Inputs'!B13*$A17/100+'1 Inputs'!B14*(F$4+$A17)^2/2000000 -> -4.1725 | G17: ='1 Inputs'!B30-'1 Inputs'!B12*G$4/100-'1 Inputs'!B13*$A17/100+'1 Inputs'!B14*(G$4+$A17)^2/2000000 -> -5.47875 | H17: ='1 Inputs'!B30-'1 Inputs'!B12*H$4/100-'1 Inputs'!B13*$A17/100+'1 Inputs'!B14*(H$4+$A17)^2/2000000 -> -6.7475 | I17: ='1 Inputs'!B30-'1 Inputs'!B12*I$4/100-'1 Inputs'!B13*$A17/100+'1 Inputs'!B14*(I$4+$A17)^2/2000000 -> -7.97875 | J17: ='1 Inputs'!B30-'1 Inputs'!B12*J$4/100-'1 Inputs'!B13*$A17/100+'1 Inputs'!B14*(J$4+$A17)^2/2000000 -> -9.1725 | K17: ='1 Inputs'!B30-'1 Inputs'!B12*K$4/100-'1 Inputs'!B13*$A17/100+'1 Inputs'!B14*(K$4+$A17)^2/2000000 -> -10.32875 | L17: ='1 Inputs'!B30-'1 Inputs'!B12*L$4/100-'1 Inputs'!B13*$A17/100+'1 Inputs'!B14*(L$4+$A17)^2/2000000 -> -11.4475 | M17: ='1 Inputs'!B30-'1 Inputs'!B12*M$4/100-'1 Inputs'!B13*$A17/100+'1 Inputs'!B14*(M$4+$A17)^2/2000000 -> -12.52875 | N17: ='1 Inputs'!B30-'1 Inputs'!B12*N$4/100-'1 Inputs'!B13*$A17/100+'1 Inputs'!B14*(N$4+$A17)^2/2000000 -> -13.5725
A19: Colour scale is a three-point red/white/green anchored at zero — the only conditional formatting in the workbook. On a 13x13 matrix the sign pattern is the content; without it the grid is unreadable. Remove it if you would rather format by hand.
A20: The zero contour runs diagonally from bottom-left to top-right. Everything above and left of it makes money. The realistic EM stress path is bottom-left to top-right ALONG the contour — spreads widen while Treasuries rally — which is why the asset survives shocks that look fatal on the spread axis alone.
A22: Reference points | D22: d UST
A23: House view: 30bp wider, Fed cuts once | D23: -25 | E23: 30 | F23: ='1 Inputs'!B30-'1 Inputs'!B12*D23/100-'1 Inputs'!B13*E23/100+'1 Inputs'!B14*(D23+E23)^2/2000000 -> 7.30325
A24: Spreads widen 30bp, Treasuries unchanged | D24: 0 | E24: 30 | F24: ='1 Inputs'!B30-'1 Inputs'!B12*D24/100-'1 Inputs'!B13*E24/100+'1 Inputs'!B14*(D24+E24)^2/2000000 -> 5.7045
A25: Spreads widen 100bp, Treasuries unchanged | D25: 0 | E25: 100 | F25: ='1 Inputs'!B30-'1 Inputs'!B12*D25/100-'1 Inputs'!B13*E25/100+'1 Inputs'!B14*(D25+E25)^2/2000000 -> 1.4275
A26: Taper-tantrum shape: +100bp UST, +100bp spread | D26: 100 | E26: 100 | F26: ='1 Inputs'!B30-'1 Inputs'!B12*D26/100-'1 Inputs'!B13*E26/100+'1 Inputs'!B14*(D26+E26)^2/2000000 -> -4.1725
A27: Growth shock: -125bp UST, +150bp spread | D27: -125 | E27: 150 | F27: ='1 Inputs'!B30-'1 Inputs'!B12*D27/100-'1 Inputs'!B13*E27/100+'1 Inputs'!B14*(D27+E27)^2/2000000 -> 6.02125

Sheet 6 Breakeven
A1: How much widening the carry absorbs, by holding period
A2: Breakeven = the spread widening at which total return is exactly zero. Rates held unchanged.
A4: Months | B4: Carry + roll (%) | C4: Breakeven, duration only (bp) | D4: Breakeven, with convexity (bp) | E4: Convexity adds (bp) | F4: Breakeven end spread (bp)
A5: 1 | B5: =('1 Inputs'!B27+'1 Inputs'!B28)*A5/12+'1 Inputs'!B12*'1 Inputs'!B29/100*A5/12 -> 0.635625 | C5: =B5/'1 Inputs'!B13*100 -> 9.7788462 | D5: =('1 Inputs'!B13-SQRT('1 Inputs'!B13^2-2*'1 Inputs'!B14*B5/100))/'1 Inputs'!B14*10000 -> 9.8233841 | E5: =D5-C5 -> 0.044537942 | F5: ='1 Inputs'!B5+D5 -> 229.82338
A6: 2 | B6: =('1 Inputs'!B27+'1 Inputs'!B28)*A6/12+'1 Inputs'!B12*'1 Inputs'!B29/100*A6/12 -> 1.27125 | C6: =B6/'1 Inputs'!B13*100 -> 19.557692 | D6: =('1 Inputs'!B13-SQRT('1 Inputs'!B13^2-2*'1 Inputs'!B14*B6/100))/'1 Inputs'!B14*10000 -> 19.737493 | E6: =D6-C6 -> 0.17980091 | F6: ='1 Inputs'!B5+D6 -> 239.73749
A7: 3 | B7: =('1 Inputs'!B27+'1 Inputs'!B28)*A7/12+'1 Inputs'!B12*'1 Inputs'!B29/100*A7/12 -> 1.906875 | C7: =B7/'1 Inputs'!B13*100 -> 29.336538 | D7: =('1 Inputs'!B13-SQRT('1 Inputs'!B13^2-2*'1 Inputs'!B14*B7/100))/'1 Inputs'!B14*10000 -> 29.744888 | E7: =D7-C7 -> 0.40835003 | F7: ='1 Inputs'!B5+D7 -> 249.74489
A8: 4 | B8: =('1 Inputs'!B27+'1 Inputs'!B28)*A8/12+'1 Inputs'!B12*'1 Inputs'!B29/100*A8/12 -> 2.5425 | C8: =B8/'1 Inputs'!B13*100 -> 39.115385 | D8: =('1 Inputs'!B13-SQRT('1 Inputs'!B13^2-2*'1 Inputs'!B14*B8/100))/'1 Inputs'!B14*10000 -> 39.848254 | E8: =D8-C8 -> 0.73286923 | F8: ='1 Inputs'!B5+D8 -> 259.84825
A9: 5 | B9: =('1 Inputs'!B27+'1 Inputs'!B28)*A9/12+'1 Inputs'!B12*'1 Inputs'!B29/100*A9/12 -> 3.178125 | C9: =B9/'1 Inputs'!B13*100 -> 48.894231 | D9: =('1 Inputs'!B13-SQRT('1 Inputs'!B13^2-2*'1 Inputs'!B14*B9/100))/'1 Inputs'!B14*10000 -> 50.050404 | E9: =D9-C9 -> 1.1561737 | F9: ='1 Inputs'!B5+D9 -> 270.0504
A10: 6 | B10: =('1 Inputs'!B27+'1 Inputs'!B28)*A10/12+'1 Inputs'!B12*'1 Inputs'!B29/100*A10/12 -> 3.81375 | C10: =B10/'1 Inputs'!B13*100 -> 58.673077 | D10: =('1 Inputs'!B13-SQRT('1 Inputs'!B13^2-2*'1 Inputs'!B14*B10/100))/'1 Inputs'!B14*10000 -> 60.354296 | E10: =D10-C10 -> 1.6812189 | F10: ='1 Inputs'!B5+D10 -> 280.3543
A11: 7 | B11: =('1 Inputs'!B27+'1 Inputs'!B28)*A11/12+'1 Inputs'!B12*'1 Inputs'!B29/100*A11/12 -> 4.449375 | C11: =B11/'1 Inputs'!B13*100 -> 68.451923 | D11: =('1 Inputs'!B13-SQRT('1 Inputs'!B13^2-2*'1 Inputs'!B14*B11/100))/'1 Inputs'!B14*10000 -> 70.763034 | E11: =D11-C11 -> 2.3111109 | F11: ='1 Inputs'!B5+D11 -> 290.76303
A12: 8 | B12: =('1 Inputs'!B27+'1 Inputs'!B28)*A12/12+'1 Inputs'!B12*'1 Inputs'!B29/100*A12/12 -> 5.085 | C12: =B12/'1 Inputs'!B13*100 -> 78.230769 | D12: =('1 Inputs'!B13-SQRT('1 Inputs'!B13^2-2*'1 Inputs'!B14*B12/100))/'1 Inputs'!B14*10000 -> 81.279886 | E12: =D12-C12 -> 3.0491169 | F12: ='1 Inputs'!B5+D12 -> 301.27989
A13: 9 | B13: =('1 Inputs'!B27+'1 Inputs'!B28)*A13/12+'1 Inputs'!B12*'1 Inputs'!B29/100*A13/12 -> 5.720625 | C13: =B13/'1 Inputs'!B13*100 -> 88.009615 | D13: =('1 Inputs'!B13-SQRT('1 Inputs'!B13^2-2*'1 Inputs'!B14*B13/100))/'1 Inputs'!B14*10000 -> 91.908293 | E13: =D13-C13 -> 3.8986774 | F13: ='1 Inputs'!B5+D13 -> 311.90829
A14: 10 | B14: =('1 Inputs'!B27+'1 Inputs'!B28)*A14/12+'1 Inputs'!B12*'1 Inputs'!B29/100*A14/12 -> 6.35625 | C14: =B14/'1 Inputs'!B13*100 -> 97.788462 | D14: =('1 Inputs'!B13-SQRT('1 Inputs'!B13^2-2*'1 Inputs'!B14*B14/100))/'1 Inputs'!B14*10000 -> 102.65188 | E14: =D14-C14 -> 4.8634194 | F14: ='1 Inputs'!B5+D14 -> 322.65188
A15: 11 | B15: =('1 Inputs'!B27+'1 Inputs'!B28)*A15/12+'1 Inputs'!B12*'1 Inputs'!B29/100*A15/12 -> 6.991875 | C15: =B15/'1 Inputs'!B13*100 -> 107.56731 | D15: =('1 Inputs'!B13-SQRT('1 Inputs'!B13^2-2*'1 Inputs'!B14*B15/100))/'1 Inputs'!B14*10000 -> 113.51448 | E15: =D15-C15 -> 5.9471708 | F15: ='1 Inputs'!B5+D15 -> 333.51448
A16: 12 | B16: =('1 Inputs'!B27+'1 Inputs'!B28)*A16/12+'1 Inputs'!B12*'1 Inputs'!B29/100*A16/12 -> 7.6275 | C16: =B16/'1 Inputs'!B13*100 -> 117.34615 | D16: =('1 Inputs'!B13-SQRT('1 Inputs'!B13^2-2*'1 Inputs'!B14*B16/100))/'1 Inputs'!B14*10000 -> 124.50013 | E16: =D16-C16 -> 7.1539765 | F16: ='1 Inputs'!B5+D16 -> 344.50013
A17: 13 | B17: =('1 Inputs'!B27+'1 Inputs'!B28)*A17/12+'1 Inputs'!B12*'1 Inputs'!B29/100*A17/12 -> 8.263125 | C17: =B17/'1 Inputs'!B13*100 -> 127.125 | D17: =('1 Inputs'!B13-SQRT('1 Inputs'!B13^2-2*'1 Inputs'!B14*B17/100))/'1 Inputs'!B14*10000 -> 135.61312 | E17: =D17-C17 -> 8.4881156 | F17: ='1 Inputs'!B5+D17 -> 355.61312
A18: 14 | B18: =('1 Inputs'!B27+'1 Inputs'!B28)*A18/12+'1 Inputs'!B12*'1 Inputs'!B29/100*A18/12 -> 8.89875 | C18: =B18/'1 Inputs'!B13*100 -> 136.90385 | D18: =('1 Inputs'!B13-SQRT('1 Inputs'!B13^2-2*'1 Inputs'!B14*B18/100))/'1 Inputs'!B14*10000 -> 146.85797 | E18: =D18-C18 -> 9.9541212 | F18: ='1 Inputs'!B5+D18 -> 366.85797
A19: 15 | B19: =('1 Inputs'!B27+'1 Inputs'!B28)*A19/12+'1 Inputs'!B12*'1 Inputs'!B29/100*A19/12 -> 9.534375 | C19: =B19/'1 Inputs'!B13*100 -> 146.68269 | D19: =('1 Inputs'!B13-SQRT('1 Inputs'!B13^2-2*'1 Inputs'!B14*B19/100))/'1 Inputs'!B14*10000 -> 158.23949 | E19: =D19-C19 -> 11.556802 | F19: ='1 Inputs'!B5+D19 -> 378.23949
A20: 16 | B20: =('1 Inputs'!B27+'1 Inputs'!B28)*A20/12+'1 Inputs'!B12*'1 Inputs'!B29/100*A20/12 -> 10.17 | C20: =B20/'1 Inputs'!B13*100 -> 156.46154 | D20: =('1 Inputs'!B13-SQRT('1 Inputs'!B13^2-2*'1 Inputs'!B14*B20/100))/'1 Inputs'!B14*10000 -> 169.7628 | E20: =D20-C20 -> 13.301266 | F20: ='1 Inputs'!B5+D20 -> 389.7628
A21: 17 | B21: =('1 Inputs'!B27+'1 Inputs'!B28)*A21/12+'1 Inputs'!B12*'1 Inputs'!B29/100*A21/12 -> 10.805625 | C21: =B21/'1 Inputs'!B13*100 -> 166.24038 | D21: =('1 Inputs'!B13-SQRT('1 Inputs'!B13^2-2*'1 Inputs'!B14*B21/100))/'1 Inputs'!B14*10000 -> 181.43333 | E21: =D21-C21 -> 15.192948 | F21: ='1 Inputs'!B5+D21 -> 401.43333
A22: 18 | B22: =('1 Inputs'!B27+'1 Inputs'!B28)*A22/12+'1 Inputs'!B12*'1 Inputs'!B29/100*A22/12 -> 11.44125 | C22: =B22/'1 Inputs'!B13*100 -> 176.01923 | D22: =('1 Inputs'!B13-SQRT('1 Inputs'!B13^2-2*'1 Inputs'!B14*B22/100))/'1 Inputs'!B14*10000 -> 193.25687 | E22: =D22-C22 -> 17.237639 | F22: ='1 Inputs'!B5+D22 -> 413.25687
A23: 19 | B23: =('1 Inputs'!B27+'1 Inputs'!B28)*A23/12+'1 Inputs'!B12*'1 Inputs'!B29/100*A23/12 -> 12.076875 | C23: =B23/'1 Inputs'!B13*100 -> 185.79808 | D23: =('1 Inputs'!B13-SQRT('1 Inputs'!B13^2-2*'1 Inputs'!B14*B23/100))/'1 Inputs'!B14*10000 -> 205.2396 | E23: =D23-C23 -> 19.441519 | F23: ='1 Inputs'!B5+D23 -> 425.2396
A24: 20 | B24: =('1 Inputs'!B27+'1 Inputs'!B28)*A24/12+'1 Inputs'!B12*'1 Inputs'!B29/100*A24/12 -> 12.7125 | C24: =B24/'1 Inputs'!B13*100 -> 195.57692 | D24: =('1 Inputs'!B13-SQRT('1 Inputs'!B13^2-2*'1 Inputs'!B14*B24/100))/'1 Inputs'!B14*10000 -> 217.38812 | E24: =D24-C24 -> 21.811198 | F24: ='1 Inputs'!B5+D24 -> 437.38812
A25: 21 | B25: =('1 Inputs'!B27+'1 Inputs'!B28)*A25/12+'1 Inputs'!B12*'1 Inputs'!B29/100*A25/12 -> 13.348125 | C25: =B25/'1 Inputs'!B13*100 -> 205.35577 | D25: =('1 Inputs'!B13-SQRT('1 Inputs'!B13^2-2*'1 Inputs'!B14*B25/100))/'1 Inputs'!B14*10000 -> 229.70952 | E25: =D25-C25 -> 24.353753 | F25: ='1 Inputs'!B5+D25 -> 449.70952
A26: 22 | B26: =('1 Inputs'!B27+'1 Inputs'!B28)*A26/12+'1 Inputs'!B12*'1 Inputs'!B29/100*A26/12 -> 13.98375 | C26: =B26/'1 Inputs'!B13*100 -> 215.13462 | D26: =('1 Inputs'!B13-SQRT('1 Inputs'!B13^2-2*'1 Inputs'!B14*B26/100))/'1 Inputs'!B14*10000 -> 242.2114 | E26: =D26-C26 -> 27.076782 | F26: ='1 Inputs'!B5+D26 -> 462.2114
A27: 23 | B27: =('1 Inputs'!B27+'1 Inputs'!B28)*A27/12+'1 Inputs'!B12*'1 Inputs'!B29/100*A27/12 -> 14.619375 | C27: =B27/'1 Inputs'!B13*100 -> 224.91346 | D27: =('1 Inputs'!B13-SQRT('1 Inputs'!B13^2-2*'1 Inputs'!B14*B27/100))/'1 Inputs'!B14*10000 -> 254.90192 | E27: =D27-C27 -> 29.988456 | F27: ='1 Inputs'!B5+D27 -> 474.90192
A28: 24 | B28: =('1 Inputs'!B27+'1 Inputs'!B28)*A28/12+'1 Inputs'!B12*'1 Inputs'!B29/100*A28/12 -> 15.255 | C28: =B28/'1 Inputs'!B13*100 -> 234.69231 | D28: =('1 Inputs'!B13-SQRT('1 Inputs'!B13^2-2*'1 Inputs'!B14*B28/100))/'1 Inputs'!B14*10000 -> 267.78989 | E28: =D28-C28 -> 33.09758 | F28: ='1 Inputs'!B5+D28 -> 487.78989
A29: 25 | B29: =('1 Inputs'!B27+'1 Inputs'!B28)*A29/12+'1 Inputs'!B12*'1 Inputs'!B29/100*A29/12 -> 15.890625 | C29: =B29/'1 Inputs'!B13*100 -> 244.47115 | D29: =('1 Inputs'!B13-SQRT('1 Inputs'!B13^2-2*'1 Inputs'!B14*B29/100))/'1 Inputs'!B14*10000 -> 280.88482 | E29: =D29-C29 -> 36.41367 | F29: ='1 Inputs'!B5+D29 -> 500.88482
A30: 26 | B30: =('1 Inputs'!B27+'1 Inputs'!B28)*A30/12+'1 Inputs'!B12*'1 Inputs'!B29/100*A30/12 -> 16.52625 | C30: =B30/'1 Inputs'!B13*100 -> 254.25 | D30: =('1 Inputs'!B13-SQRT('1 Inputs'!B13^2-2*'1 Inputs'!B14*B30/100))/'1 Inputs'!B14*10000 -> 294.19703 | E30: =D30-C30 -> 39.947026 | F30: ='1 Inputs'!B5+D30 -> 514.19703
A31: 27 | B31: =('1 Inputs'!B27+'1 Inputs'!B28)*A31/12+'1 Inputs'!B12*'1 Inputs'!B29/100*A31/12 -> 17.161875 | C31: =B31/'1 Inputs'!B13*100 -> 264.02885 | D31: =('1 Inputs'!B13-SQRT('1 Inputs'!B13^2-2*'1 Inputs'!B14*B31/100))/'1 Inputs'!B14*10000 -> 307.73768 | E31: =D31-C31 -> 43.708838 | F31: ='1 Inputs'!B5+D31 -> 527.73768
A32: 28 | B32: =('1 Inputs'!B27+'1 Inputs'!B28)*A32/12+'1 Inputs'!B12*'1 Inputs'!B29/100*A32/12 -> 17.7975 | C32: =B32/'1 Inputs'!B13*100 -> 273.80769 | D32: =('1 Inputs'!B13-SQRT('1 Inputs'!B13^2-2*'1 Inputs'!B14*B32/100))/'1 Inputs'!B14*10000 -> 321.51898 | E32: =D32-C32 -> 47.711286 | F32: ='1 Inputs'!B5+D32 -> 541.51898
A33: 29 | B33: =('1 Inputs'!B27+'1 Inputs'!B28)*A33/12+'1 Inputs'!B12*'1 Inputs'!B29/100*A33/12 -> 18.433125 | C33: =B33/'1 Inputs'!B13*100 -> 283.58654 | D33: =('1 Inputs'!B13-SQRT('1 Inputs'!B13^2-2*'1 Inputs'!B14*B33/100))/'1 Inputs'!B14*10000 -> 335.55421 | E33: =D33-C33 -> 51.967676 | F33: ='1 Inputs'!B5+D33 -> 555.55421
A34: 30 | B34: =('1 Inputs'!B27+'1 Inputs'!B28)*A34/12+'1 Inputs'!B12*'1 Inputs'!B29/100*A34/12 -> 19.06875 | C34: =B34/'1 Inputs'!B13*100 -> 293.36538 | D34: =('1 Inputs'!B13-SQRT('1 Inputs'!B13^2-2*'1 Inputs'!B14*B34/100))/'1 Inputs'!B14*10000 -> 349.85797 | E34: =D34-C34 -> 56.492584 | F34: ='1 Inputs'!B5+D34 -> 569.85797
A35: 31 | B35: =('1 Inputs'!B27+'1 Inputs'!B28)*A35/12+'1 Inputs'!B12*'1 Inputs'!B29/100*A35/12 -> 19.704375 | C35: =B35/'1 Inputs'!B13*100 -> 303.14423 | D35: =('1 Inputs'!B13-SQRT('1 Inputs'!B13^2-2*'1 Inputs'!B14*B35/100))/'1 Inputs'!B14*10000 -> 364.44627 | E35: =D35-C35 -> 61.302038 | F35: ='1 Inputs'!B5+D35 -> 584.44627
A36: 32 | B36: =('1 Inputs'!B27+'1 Inputs'!B28)*A36/12+'1 Inputs'!B12*'1 Inputs'!B29/100*A36/12 -> 20.34 | C36: =B36/'1 Inputs'!B13*100 -> 312.92308 | D36: =('1 Inputs'!B13-SQRT('1 Inputs'!B13^2-2*'1 Inputs'!B14*B36/100))/'1 Inputs'!B14*10000 -> 379.33681 | E36: =D36-C36 -> 66.413729 | F36: ='1 Inputs'!B5+D36 -> 599.33681
A37: 33 | B37: =('1 Inputs'!B27+'1 Inputs'!B28)*A37/12+'1 Inputs'!B12*'1 Inputs'!B29/100*A37/12 -> 20.975625 | C37: =B37/'1 Inputs'!B13*100 -> 322.70192 | D37: =('1 Inputs'!B13-SQRT('1 Inputs'!B13^2-2*'1 Inputs'!B14*B37/100))/'1 Inputs'!B14*10000 -> 394.54918 | E37: =D37-C37 -> 71.847256 | F37: ='1 Inputs'!B5+D37 -> 614.54918
A38: 34 | B38: =('1 Inputs'!B27+'1 Inputs'!B28)*A38/12+'1 Inputs'!B12*'1 Inputs'!B29/100*A38/12 -> 21.61125 | C38: =B38/'1 Inputs'!B13*100 -> 332.48077 | D38: =('1 Inputs'!B13-SQRT('1 Inputs'!B13^2-2*'1 Inputs'!B14*B38/100))/'1 Inputs'!B14*10000 -> 410.10521 | E38: =D38-C38 -> 77.624437 | F38: ='1 Inputs'!B5+D38 -> 630.10521
A39: 35 | B39: =('1 Inputs'!B27+'1 Inputs'!B28)*A39/12+'1 Inputs'!B12*'1 Inputs'!B29/100*A39/12 -> 22.246875 | C39: =B39/'1 Inputs'!B13*100 -> 342.25962 | D39: =('1 Inputs'!B13-SQRT('1 Inputs'!B13^2-2*'1 Inputs'!B14*B39/100))/'1 Inputs'!B14*10000 -> 426.02929 | E39: =D39-C39 -> 83.76967 | F39: ='1 Inputs'!B5+D39 -> 646.02929
A40: 36 | B40: =('1 Inputs'!B27+'1 Inputs'!B28)*A40/12+'1 Inputs'!B12*'1 Inputs'!B29/100*A40/12 -> 22.8825 | C40: =B40/'1 Inputs'!B13*100 -> 352.03846 | D40: =('1 Inputs'!B13-SQRT('1 Inputs'!B13^2-2*'1 Inputs'!B14*B40/100))/'1 Inputs'!B14*10000 -> 442.34885 | E40: =D40-C40 -> 90.310386 | F40: ='1 Inputs'!B5+D40 -> 662.34885
A42: Months of carry needed to repay the house-view widening | B42: ='1 Inputs'!B13*('1 Inputs'!B6-'1 Inputs'!B5)/100/(($B$16)/12) -> 3.0678466 | C42: months
A43: Duration-only breakeven is carry+roll / spread duration — the line worth memorising. With convexity, solve 0.5*C*x^2 - D*x + carry = 0 and take the smaller root.
A44: The convexity column must visibly differ from the duration-only column. If the two are within a basis point of each other, the convexity input on tab 1 is 100x too small — that is the Bloomberg CVX_MID units trap.
A45: The house-view 30bp widening costs 1.95%, and carry+roll earns ~0.64%/month, so the move is repaid in roughly three months of holding. After that you are back to collecting.

Sheet 7 Risk
A1: How much is at risk amid volatility
A2: Parametric. Return vol is driven by two correlated legs — Treasury yield and spread — and the correlation is the point.
A4: Volatility inputs
A5: Annualised vol of UST reference yield (bp) | B5: 70 | C5: Typical annualised vol of the 10y yield in a non-crisis regime. Raise it if you think the Fed path is genuinely two-sided — which right now it is.
A6: Annualised vol of EMBI spread (bp) | B6: 65 | C6: EMBI Global spread vol. Runs lower when the index is tight and higher once it is wide — vol of spread is itself a function of spread level.
A7: Correlation, UST yield vs spread | B7: -0.35 | C7: NEGATIVE in growth-driven regimes: bad news widens spreads and rallies Treasuries. Set this to +0.5 to see the 2022 / dollar-funding-stress regime, where both sell off together and the hedge fails.
A9: Resulting risk
A10: Vol of total yield change (bp p.a.) | B10: =SQRT(B5^2+B6^2+2*B7*B5*B6) -> 77.071395 | C10: Combining two vols with the correlation between them.
A11: Vol of total return (% p.a.) | B11: ='1 Inputs'!B12*B10/100 -> 5.0096407
A12: Same, if correlation were zero (% p.a.) | B12: ='1 Inputs'!B12*SQRT(B5^2+B6^2)/100 -> 6.2091163
A13: Volatility saved by the negative correlation | B13: =B11/B12-1 -> -0.19317976 | C13: The rates leg hedging the credit leg is worth roughly a fifth of the asset's volatility. It is not a small effect and it does not show up anywhere on a spread screen.
A15: Loss measures over the horizon on tab 1
A16: Carry + roll over horizon (%) | B16: ='1 Inputs'!B30 -> 7.6275
A17: Return vol over horizon (%) | B17: =B11*SQRT('1 Inputs'!B22) -> 5.0096407 | C17: Vol scales with the square root of time. Carry scales with time. That asymmetry is the whole case for holding the asset rather than trading it.
A18: 95% adverse market move (%) | B18: =1.645*B17 -> 8.240859
A19: Total return at the 95th percentile loss (%) | B19: =B16-B18 -> -0.61335896 | C19: Carry absorbs almost the entire 1-in-20 market move over a 12-month hold. This is the number to quote when someone says spreads are too tight.
A20: 99% adverse market move (%) | B20: =2.326*B17 -> 11.652424
A21: Total return at the 99th percentile loss (%) | B21: =B16-B20 -> -4.0249243
A22: Probability of a negative total return | B22: =NORMSDIST(-B16/B17) -> 0.063933876
A23: Carry-to-vol ratio (annualised) | B23: ='1 Inputs'!B30/'1 Inputs'!B22/B11 -> 1.5225643 | C23: Carry earned per unit of return volatility. Above 1.0 means a year of carry more than covers a one-standard-deviation move.
A25: Probability of loss by holding period
A26: Months | B26: Carry + roll (%) | C26: Vol over period (%) | D26: Prob. of negative return | E26: 95th pct total return (%)
A27: 1 | B27: =('1 Inputs'!B27+'1 Inputs'!B28)*A27/12+'1 Inputs'!B12*'1 Inputs'!B29/100*A27/12 -> 0.635625 | C27: =B11*SQRT(A27/12) -> 1.4461587 | D27: =NORMSDIST(-B27/C27) -> 0.33014006 | E27: =B27-1.645*C27 -> -1.7433061
A28: 2 | B28: =('1 Inputs'!B27+'1 Inputs'!B28)*A28/12+'1 Inputs'!B12*'1 Inputs'!B29/100*A28/12 -> 1.27125 | C28: =B11*SQRT(A28/12) -> 2.0451773 | D28: =NORMSDIST(-B28/C28) -> 0.26710764 | E28: =B28-1.645*C28 -> -2.0930666
A29: 3 | B29: =('1 Inputs'!B27+'1 Inputs'!B28)*A29/12+'1 Inputs'!B12*'1 Inputs'!B29/100*A29/12 -> 1.906875 | C29: =B11*SQRT(A29/12) -> 2.5048204 | D29: =NORMSDIST(-B29/C29) -> 0.22324428 | E29: =B29-1.645*C29 -> -2.2135545
A30: 6 | B30: =('1 Inputs'!B27+'1 Inputs'!B28)*A30/12+'1 Inputs'!B12*'1 Inputs'!B29/100*A30/12 -> 3.81375 | C30: =B11*SQRT(A30/12) -> 3.5423509 | D30: =NORMSDIST(-B30/C30) -> 0.14082603 | E30: =B30-1.645*C30 -> -2.0134173
A31: 9 | B31: =('1 Inputs'!B27+'1 Inputs'!B28)*A31/12+'1 Inputs'!B12*'1 Inputs'!B29/100*A31/12 -> 5.720625 | C31: =B11*SQRT(A31/12) -> 4.3384761 | D31: =NORMSDIST(-B31/C31) -> 0.093654891 | E31: =B31-1.645*C31 -> -1.4161682
A32: 12 | B32: =('1 Inputs'!B27+'1 Inputs'!B28)*A32/12+'1 Inputs'!B12*'1 Inputs'!B29/100*A32/12 -> 7.6275 | C32: =B11*SQRT(A32/12) -> 5.0096407 | D32: =NORMSDIST(-B32/C32) -> 0.063933876 | E32: =B32-1.645*C32 -> -0.61335896
A33: 18 | B33: =('1 Inputs'!B27+'1 Inputs'!B28)*A33/12+'1 Inputs'!B12*'1 Inputs'!B29/100*A33/12 -> 11.44125 | C33: =B11*SQRT(A33/12) -> 6.1355318 | D33: =NORMSDIST(-B33/C33) -> 0.031108031 | E33: =B33-1.645*C33 -> 1.3483003
A34: 24 | B34: =('1 Inputs'!B27+'1 Inputs'!B28)*A34/12+'1 Inputs'!B12*'1 Inputs'!B29/100*A34/12 -> 15.255 | C34: =B11*SQRT(A34/12) -> 7.0847018 | D34: =NORMSDIST(-B34/C34) -> 0.015650262 | E34: =B34-1.645*C34 -> 3.6006655
A35: 36 | B35: =('1 Inputs'!B27+'1 Inputs'!B28)*A35/12+'1 Inputs'!B12*'1 Inputs'!B29/100*A35/12 -> 22.8825 | C35: =B11*SQRT(A35/12) -> 8.6769522 | D35: =NORMSDIST(-B35/C35) -> 0.0041801855 | E35: =B35-1.645*C35 -> 8.6089136
A36: 48 | B36: =('1 Inputs'!B27+'1 Inputs'!B28)*A36/12+'1 Inputs'!B12*'1 Inputs'!B29/100*A36/12 -> 30.51 | C36: =B11*SQRT(A36/12) -> 10.019281 | D36: =NORMSDIST(-B36/C36) -> 0.0011629043 | E36: =B36-1.645*C36 -> 14.028282
A37: 60 | B37: =('1 Inputs'!B27+'1 Inputs'!B28)*A37/12+'1 Inputs'!B12*'1 Inputs'!B29/100*A37/12 -> 38.1375 | C37: =B11*SQRT(A37/12) -> 11.201897 | D37: =NORMSDIST(-B37/C37) -> 0.00033135706 | E37: =B37-1.645*C37 -> 19.710379
A38: Carry grows linearly, vol grows with the square root of time. So the probability of losing money falls monotonically with holding period — from roughly a third at one month to a small tail at three years. The asset rewards patience mechanically, not just rhetorically.

Sheet 8 Fed path
A1: Fed funds path per scenario, and the curve the roll is read off
A2: Starting point: target 3.50-3.75%, effective 3.63%. Market priced ~44% odds of a September HIKE after the July jobs miss, down from 57% before it.
A4: Fed funds target midpoint (%) — projected path
A5: Scenario | B5: Sep-26 | C5: Dec-26 | D5: Mar-27 | E5: Jun-27 | F5: Sep-27
A6: Immaculate disinflation | B6: 3.625 | C6: 3.375 | D6: 3.125 | E6: 2.875 | F6: 2.875
A7: Soft landing (base case) | B7: 3.625 | C7: 3.375 | D7: 3.375 | E7: 3.375 | F7: 3.375
A8: Higher for longer | B8: 3.625 | C8: 3.625 | D8: 3.625 | E8: 3.625 | F8: 3.625
A9: Growth scare / mild recession | B9: 3.375 | C9: 3.125 | D9: 2.875 | E9: 2.875 | F9: 2.875
A10: Stagflation — Fed hikes into weakness | B10: 3.875 | C10: 4.125 | D10: 4.375 | E10: 4.375 | F10: 4.125
A11: Hard landing / systemic stress | B11: 3.375 | C11: 2.625 | D11: 2.125 | E11: 1.875 | F11: 1.875
A13: Current target midpoint 3.625%. Note the two-sided risk: three FOMC members dissented in July preferring +25bp, while July payrolls came in at -23k with 103k of downward revisions to May and June. Both tails are live, which is unusual and is itself an argument for an asset whose two legs offset.
A15: US Treasury curve — Fed H.15, 7-Aug-2026
A16: Tenor | B16: Yield (%) | C16: Slope from previous point (bp/yr) | D16: Yrs
A17: 3m | B17: 3.72 | D17: 0.25
A18: 2y | B18: 4.19 | C18: =(B18-B17)/(D18-D17)*100 -> 26.857143 | D18: 2
A19: 5y | B19: 4.35 | C19: =(B19-B18)/(D19-D18)*100 -> 5.3333333 | D19: 5
A20: 7y | B20: 4.49 | C20: =(B20-B19)/(D20-D19)*100 -> 7 | D20: 7
A21: 10y | B21: 4.65 | C21: =(B21-B20)/(D21-D20)*100 -> 5.3333333 | D21: 10
A22: 30y | B22: 5.19 | C22: =(B22-B21)/(D22-D21)*100 -> 2.7 | D22: 30
A24: Belly slope, 5y-10y (bp/yr) | B24: =(B21-B19)/5*100 -> 6 | C24: This is the number feeding the Treasury roll assumption on tab 1. A positively-sloped curve is worth real money to a 6.5-duration asset.
A25: 2s10s (bp) | B25: =(B21-B18)*100 -> 46
A26: Index YTM pickup over 10y UST (bp) | B26: =('1 Inputs'!B25-B21)*100 -> 210
A28: Sources: Federal Reserve H.15 Selected Interest Rates, 7-Aug-2026. FOMC decision 29-Jul-2026 (held 3.50-3.75%, five consecutive holds, three dissents for +25bp). CME FedWatch via press coverage, 7-Aug-2026 (September hike odds 57% -> 44% on the jobs print). BLS July employment report, released 7-Aug-2026.

Sheet 9 Bloomberg refresh
A1: Bloomberg pulls to rebuild this model from live data
A2: Written WITHOUT the leading '=' so the tab stays inert offline. Add the '=' on your work machine, or copy into the target cell on tab 1.
A4: Field | B4: Target cell | C4: Formula (add leading =)
A5: EMBI Global stripped spread | B5: 1 Inputs!B5 | C5: BDP("JPEIGLBL Index","INDX_OAS_SPREAD_MID")
A6: EMBI Global YTM | B6: check vs B25 | C6: BDP("JPEIGLBL Index","INDX_YLD_YTM_MID")
A7: EMBI Global mod duration | B7: 1 Inputs!B12 | C7: BDP("JPEIGLBL Index","INDX_MODIFIED_DURATION")
A8: EMBI Global convexity | B8: 1 Inputs!B14 | C8: BDP("JPEIGLBL Index","INDX_CONVEXITY")*100
A9: EMBI Global average coupon | B9: 1 Inputs!B10 | C9: BDP("JPEIGLBL Index","INDX_CPN_MID")
A10: EMBI Global average life | B10: 1 Inputs!B11 | C10: BDP("JPEIGLBL Index","INDX_AVERAGE_LIFE")
A11: EMBIG Diversified spread (cross-check) | B11: - | C11: BDP("JPGCCOMP Index","INDX_OAS_SPREAD_MID")
A12: UST 7y | B12: 8 Fed path!B19 | C12: BDP("USGG7YR Index","PX_LAST")
A13: UST 10y | B13: 8 Fed path!B20 | C13: BDP("USGG10YR Index","PX_LAST")
A14: UST 30y | B14: 8 Fed path!B21 | C14: BDP("USGG30YR Index","PX_LAST")
A15: UST 2y | B15: 8 Fed path!B17 | C15: BDP("USGG2YR Index","PX_LAST")
... A19: 10y yield history for vol estimate | B19: 7 Risk B5:B7 | C19: BDH("USGG10YR Index","PX_LAST",today-1825,today)
A21: CONVEXITY: the *100 on the convexity pull is deliberate. Bloomberg quotes INDX_CONVEXITY divided by 100; pasted raw it silently shrinks the convexity benefit by two orders of magnitude and nothing anywhere reports an error. The tell is that the two breakeven columns on tab 6 come out within a basis point of each other.
A22: Ticker for EMBI Global is JPEIGLBL Index; EMBI Global Diversified is JPGCCOMP Index. Verify both on your terminal — index tickers get remapped and the field names differ between the EMBI and CEMBI families.
A23: To re-estimate the vol inputs on tab 7: pull five years of daily spread and 10y yield, take daily changes in bp, annualise by multiplying the daily standard deviation by SQRT(252), and take the correlation of the two daily-change series. Do it on a rolling one-year window as well — the correlation is regime-dependent and the whole hedge argument rests on it.

Sheet Notes
A1: Method, conventions and limitations
A2: Read before quoting anything out of this workbook.
A4: The arithmetic
B5: Total return over horizon h = carry + roll - D*dy + 0.5*C*dy^2
B6: carry + roll = (current yield + pull-to-par)*h + D*roll*h
B7: current yield + pull-to-par = YTM, by construction — so the split is additive with no double count
B8: breakeven widening = (carry + roll) / spread duration <- the line worth memorising
B9: with convexity = smaller root of 0.5*C*x^2 - D*x + carry = 0
A11: Units
B12: All rates and returns in PERCENT UNITS (6.75 = 6.75%). All yield and spread moves in BASIS POINTS.
B13: Convexity in YEARS SQUARED (~60), not Bloomberg's /100 quote. See tab 9.
B14: Same convention as the Argentina carry-cushion model, so the two workbooks can be read side by side.
A16: Why carry, roll and pull-to-par do not overlap
B17: Cash coupon = coupon / price. Actually received.
B18: Pull-to-par = YTM - current yield. Price drift toward par at an UNCHANGED yield.
B19: Roll-down = D * (yield decline from ageing along the curve). The yield MOVING, not held.
B20: The first two sum to YTM exactly. Roll is the separate effect of the curve's shape. No component is counted twice.
A22: Status of the inputs
B23: OBSERVED: Treasury curve (Fed H.15, 7-Aug-26). EMB duration 6.47y, coupon 5.60%, OAS 166bp (iShares, 7-Aug-26).
B24: UBS CIO PUBLISHED: EMBIG Diversified 244bp spot (Apr-26), 260bp target (Dec-26), asset class rated Attractive (13-May-26).
B25: USER-SUPPLIED: EMBI Global at 220bp and the 250bp house target. Not observed prints.
B26: ESTIMATED: average life 11y, convexity 60, Treasury roll 5.5bp/yr, credit roll 8.0bp/yr, all three vol inputs on tab 6.
B27: JUDGEMENT: the five scenarios and their probabilities. Edit them — they are blue for a reason.
B28: The credit-curve roll assumption is the softest number here. It contributes ~0.5% a year. Halve it and the case is unchanged; that is worth saying out loud rather than hiding.
A30: Not modelled
B31: Parallel shifts only. EM stress usually arrives as curve steepening plus dispersion, not a parallel move.
B32: Duration/convexity approximation rather than full cashflow repricing — accurate to a few bp inside roughly +/-200bp.
B33: No default, restructuring or recovery. At index level this matters: a single 5% weight going to 40 recovery costs ~3%.
B34: No index composition drift, no rebalancing, no new-issue concession.
B35: No FX, no financing cost. Unlevered, unhedged USD total return.
B36: Normal distribution in the VaR on tab 6. Spread returns are left-skewed and fat-tailed, so the 99% figure is optimistic. Treat it as a lower bound on the tail.
A38: The honest counter-argument
B39: At 220bp the distribution is asymmetric: perhaps 40bp of room to tighten against 150bp+ of room to widen. Tight spreads are themselves a risk factor.
B40: The rates/credit hedge is regime-dependent. In 2022, and in any dollar-funding squeeze, the correlation flips positive and both legs sell off together — the hedge fails exactly when it is needed. Set the correlation on tab 7 to +0.5 and re-read tab 4.
B41: Scenario 4 (inflation re-acceleration) is the live version of that risk today, with three FOMC dissents in July and oil in the mix. It is the only scenario in the set with a negative return, and it is not a small probability.
B42: Spread level is a poor predictor of forward returns; YIELD level is a good one. The case rests on a 6.75% starting yield, not on spreads being cheap. They are not cheap.
A44: Sources
B45: Federal Reserve, H.15 Selected Interest Rates, 7-Aug-2026 — federalreserve.gov/releases/h15/
B46: iShares J.P. Morgan USD Emerging Markets Bond ETF (EMB), fund characteristics, 7-Aug-2026 — ishares.com
B47: UBS CIO, 'Adding income through emerging market bonds', 13-May-2026 — ubs.com
B48: UBS Asset Management, 'Emerging Markets Debt' market update — ubs.com
B49: Global X, EMBD 2Q26 commentary (EMBI Global Core +4.63% in Q2, spread compression the main driver) — globalxetfs.com
B50: Trading Economics / CME FedWatch coverage of the 29-Jul-2026 FOMC and the 7-Aug-2026 employment report.
