Workbook
Name SETTINGS_LOOK: '01 SETTINGS'!$C$5
Name SETTINGS_FREQ: '01 SETTINGS'!$C$6
Name SETTINGS_ZC: '01 SETTINGS'!$C$7
Name SETTINGS_ZR: '01 SETTINGS'!$C$8
Name SETTINGS_FXSRC: '01 SETTINGS'!$C$9
Name SETTINGS_CAP: '01 SETTINGS'!$C$10
Name SETTINGS_GROSS: '01 SETTINGS'!$C$11
Name SETTINGS_ZMIN: '01 SETTINGS'!$C$12

Sheet 00 README
A1: GLOBAL MACRO VALUE MONITOR — 100 ASSETS, LIVE FROM BLOOMBERG
A2: Cross-sectional value screen with per-asset-class metrics, z-scores, a 50/50 long-short book and paired trades · built 10 October 2026
A4: HOW THIS WORKS — READ THIS FIRST
A5: Every number in this workbook is EMPTY until you open it on a machine with the Bloomberg Excel add-in. The cells contain live BDP and BDH formulas wrapped in IFERROR, so away from a terminal they show blanks rather than errors. On your terminal they populate and everything downstream — z-scores, rankings, the long-short book, the trade pairs — computes itself. Open it, let the add-in finish pulling (the history calls take a minute or two), then press Ctrl+Alt+F9 to force a full recalculation. Do that again any morning you want a fresh read.
A7: THE FOUR-STEP WORKFLOW
B8: Step | C8: What to do | D8: Why
B9: 1 · Open on Bloomberg | C9: Open the file, wait for the add-in, then Ctrl+Alt+F9. | D9: Two BDH history calls per instrument. 100 instruments. Give it a minute.
B10: 2 · Fix the tickers | C10: Go to tab 02 MONITOR, column G. Any row showing CHECK has a ticker Bloomberg did not recognise — overwrite column D with the right one. | D10: I built this without terminal access, so roughly a third of the tickers are flagged VERIFY — mostly EM govvies, credit indices and a few commodity contracts. Column G turns that into a five-minute job instead of a hidden flaw.
B11: 3 · Set your lookback | C11: Tab 01 SETTINGS. Default is 10 years of weekly data. | D11: A z-score is meaningless without its window. 10y spans a full cycle; 5y is more responsive and more regime-contaminated. Run both.
B12: 4 · Read in this order | C12: 03 RANKINGS first (within asset class), then 04 CROSS-ASSET, then 05 PORTFOLIO, then 06 TRADES. | D12: Within-class ranking is the statistically defensible comparison. Cross-asset is interesting and much weaker — the workbook says so where it matters.
A14: TAB MAP
B15: Tab | C15: What it gives you
B16: 01 SETTINGS | C16: Lookback window, z thresholds, capital, and the one toggle that switches FX value between spot and REER.
B17: 02 MONITOR | C17: The master table. 100 instruments, each with its own valuation metric, mean, standard deviation, z-score, a sign-corrected VALUE SCORE where positive always means cheap, percentile, 1-year momentum, and rank within its asset class.
B18: 03 RANKINGS | C18: Cheapest and most expensive WITHIN each asset class. This is the defensible comparison and the one to trust.
B19: 04 CROSS-ASSET | C19: One global list, cheapest to most expensive, plus the ±2 standard deviation extremes screen you asked for. Read the health warning at the top.
B20: 05 PORTFOLIO | C20: 100 positions — 50 long, 50 short — built mechanically from the value scores, risk-weighted, and neutral within every asset class by construction.
B21: 06 TRADES | C21: Eight paired relative-value trades, one per sub-bucket, auto-populated with the cheapest against the richest and a structure note for each.
B22: 07 RISK DASH | C22: Eight regime indicators — VIX, MOVE, CVIX, DXY and others. Context, not positions, and deliberately outside the book.
B23: 08 METHOD | C23: Why each asset class gets the metric it gets, and the four places this screen will mislead you.
A25: THE SIGN CONVENTION THAT MAKES THIS WORK
A26: The one piece of plumbing worth understanding. Each asset class is measured on its own metric, and 'high' means opposite things across them — a high forward P/E is expensive, a high bond yield is cheap. So every instrument carries a sign (+1 or −1) that converts its raw z-score into a VALUE SCORE on a single convention: VALUE SCORE = raw z-score × sign → POSITIVE ALWAYS MEANS CHEAP Equity forward P/E −1 · Bond yield +1 · Credit spread +1 · Commodity price −1 · FX depends on the quote convention, which is the trap: USDBRL rising means a WEAK real, so high = cheap (+1), while EURUSD rising means a STRONG euro, so high = expensive (−1). Column F on the monitor carries that per currency.
A28: Built without Bloomberg access, so every ticker is my best knowledge rather than a verified pull. Column G is the safety net. Nothing here is a recommendation — it is a screen, and a screen is the beginning of the work.

Sheet 01 SETTINGS
A1: SETTINGS
A2: Change these and the entire workbook re-reads. Blue on yellow = input.
B4: Setting | C4: Value | D4: What it does
B5: Lookback start (Bloomberg relative date) | C5: -10Y | D5: Window for the mean and standard deviation. Use -10Y for a full-cycle read, -5Y for a responsive one. Must be a Bloomberg relative date string.
B6: Data frequency | C6: W | D6: D daily, W weekly, M monthly. Weekly is the right trade-off: 520 points over 10 years, light enough that 200 history calls do not hang the sheet.
B7: Cheap threshold (z) | C7: 2 | D7: Flag an asset CHEAP when its value score is at or above this. 2.0 is the convention; 1.5 gives you a longer list.
B8: Rich threshold (z) | C8: -2 | D8: Flag RICH at or below this.
B9: FX value source | C9: SPOT | D9: SPOT uses the 5y/10y z-score of the exchange rate. REER uses the real effective rate tickers in column T of the monitor, which you must supply. REER is the better value measure; SPOT is the one that works out of the box.
B10: Gross capital (USD) | C10: 100000000 | D10: Used only to turn portfolio weights into notional on tab 05.
B11: Target gross exposure (x capital) | C11: 2 | D11: 2.0 means $100mn long and $100mn short on $100mn of capital.
B12: Minimum |z| to take a position | C12: 0.5 | D12: Positions inside this band are set to zero weight on tab 05 — do not pay spread for noise.
B14: As-of (refreshes on open) | C14: =TODAY()
A16: The lookback and frequency cells feed straight into every BDH call on the monitor, so changing them re-pulls all 200 history series. Expect a pause. If the add-in struggles, switch frequency to M before you switch the window.

Sheet 02 MONITOR
A1: MONITOR — 100 GLOBAL MACRO ASSETS
A2: Each asset on its own valuation metric. VALUE SCORE is sign-corrected so POSITIVE ALWAYS MEANS CHEAP. Column G flags bad tickers.
A4: Blank cells mean no Bloomberg connection. Column G: a name = good ticker; CHECK = Bloomberg did not recognise it, fix column D. Column T is optional — paste a REER ticker there and set FX value source to REER on tab 01 to use it instead of spot.
B6: Class | C6: Instrument | D6: Bloomberg ticker | E6: Metric field | F6: Conf. | G6: Ticker check (BDP NAME) | H6: Current | I6: Mean | J6: Std dev | K6: Z (raw) | L6: Sign | M6: VALUE SCORE (+ = cheap) | N6: Percentile | O6: 1y chg % | P6: Rank in class | Q6: N in class | R6: Flag | S6: Metric note / why | T6: REER ticker (FX only, optional) | U6: Global rank
B7: EQUITY | C7: US S&P 500 | D7: SPX Index | E7: BEST_PE_RATIO | F7: HIGH | G7: =IFERROR(IF(BDP($D7,"NAME")="","CHECK",BDP($D7,"NAME")),"CHECK") | H7: =IFERROR(BDP($D7,$E7),"") | I7: =IFERROR(AVERAGE(BDH($D7,$E7,SETTINGS_LOOK,"0D","Days="&SETTINGS_FREQ,"Fill=P")),"") | J7: =IFERROR(STDEV(BDH($D7,$E7,SETTINGS_LOOK,"0D","Days="&SETTINGS_FREQ,"Fill=P")),"") | K7: =IFERROR(($H7-$I7)/$J7,"") | L7: -1 | M7: =IFERROR($K7*$L7,"") | N7: =IFERROR(NORMSDIST($M7),"") | O7: =IFERROR(BDP($D7,"CHG_PCT_1YR")/100,"") | P7: =IFERROR(SUMPRODUCT(($B$7:$B$106=$B7)*($M$7:$M$106>$M7))+1,"") | Q7: =COUNTIF($B$7:$B$106,$B7) | R7: =IFERROR(IF($M7>=SETTINGS_ZC,"CHEAP",IF($M7<=SETTINGS_ZR,"RICH","-")),"") | S7: Forward P/E. High = expensive. | U7: =IFERROR(SUMPRODUCT(($M$7:$M$106>$M7)*1)+1,"")
B8: EQUITY | C8: US Nasdaq 100 | D8: NDX Index | E8: BEST_PE_RATIO | F8: HIGH | G8: =IFERROR(IF(BDP($D8,"NAME")="","CHECK",BDP($D8,"NAME")),"CHECK") | H8: =IFERROR(BDP($D8,$E8),"") | I8: =IFERROR(AVERAGE(BDH($D8,$E8,SETTINGS_LOOK,"0D","Days="&SETTINGS_FREQ,"Fill=P")),"") | J8: =IFERROR(STDEV(BDH($D8,$E8,SETTINGS_LOOK,"0D","Days="&SETTINGS_FREQ,"Fill=P")),"") | K8: =IFERROR(($H8-$I8)/$J8,"") | L8: -1 | M8: =IFERROR($K8*$L8,"") | N8: =IFERROR(NORMSDIST($M8),"") | O8: =IFERROR(BDP($D8,"CHG_PCT_1YR")/100,"") | P8: =IFERROR(SUMPRODUCT(($B$7:$B$106=$B8)*($M$7:$M$106>$M8))+1,"") | Q8: =COUNTIF($B$7:$B$106,$B8) | R8: =IFERROR(IF($M8>=SETTINGS_ZC,"CHEAP",IF($M8<=SETTINGS_ZR,"RICH","-")),"") | S8: Forward P/E. High = expensive. | U8: =IFERROR(SUMPRODUCT(($M$7:$M$106>$M8)*1)+1,"")
B9: EQUITY | C9: US Russell 2000 | D9: RTY Index | E9: BEST_PE_RATIO | F9: HIGH | G9: =IFERROR(IF(BDP($D9,"NAME")="","CHECK",BDP($D9,"NAME")),"CHECK") | H9: =IFERROR(BDP($D9,$E9),"") | I9: =IFERROR(AVERAGE(BDH($D9,$E9,SETTINGS_LOOK,"0D","Days="&SETTINGS_FREQ,"Fill=P")),"") | J9: =IFERROR(STDEV(BDH($D9,$E9,SETTINGS_LOOK,"0D","Days="&SETTINGS_FREQ,"Fill=P")),"") | K9: =IFERROR(($H9-$I9)/$J9,"") | L9: -1 | M9: =IFERROR($K9*$L9,"") | N9: =IFERROR(NORMSDIST($M9),"") | O9: =IFERROR(BDP($D9,"CHG_PCT_1YR")/100,"") | P9: =IFERROR(SUMPRODUCT(($B$7:$B$106=$B9)*($M$7:$M$106>$M9))+1,"") | Q9: =COUNTIF($B$7:$B$106,$B9) | R9: =IFERROR(IF($M9>=SETTINGS_ZC,"CHEAP",IF($M9<=SETTINGS_ZR,"RICH","-")),"") | S9: Forward P/E. High = expensive. | U9: =IFERROR(SUMPRODUCT(($M$7:$M$106>$M9)*1)+1,"")
B10: EQUITY | C10: Euro Stoxx 50 | D10: SX5E Index | E10: BEST_PE_RATIO | F10: HIGH | G10: =IFERROR(IF(BDP($D10,"NAME")="","CHECK",BDP($D10,"NAME")),"CHECK") | H10: =IFERROR(BDP($D10,$E10),"") | I10: =IFERROR(AVERAGE(BDH($D10,$E10,SETTINGS_LOOK,"0D","Days="&SETTINGS_FREQ,"Fill=P")),"") | J10: =IFERROR(STDEV(BDH($D10,$E10,SETTINGS_LOOK,"0D","Days="&SETTINGS_FREQ,"Fill=P")),"") | K10: =IFERROR(($H10-$I10)/$J10,"") | L10: -1 | M10: =IFERROR($K10*$L10,"") | N10: =IFERROR(NORMSDIST($M10),"") | O10: =IFERROR(BDP($D10,"CHG_PCT_1YR")/100,"") | P10: =IFERROR(SUMPRODUCT(($B$7:$B$106=$B10)*($M$7:$M$106>$M10))+1,"") | Q10: =COUNTIF($B$7:$B$106,$B10) | R10: =IFERROR(IF($M10>=SETTINGS_ZC,"CHEAP",IF($M10<=SETTINGS_ZR,"RICH","-")),"") | S10: Forward P/E. High = expensive. | U10: =IFERROR(SUMPRODUCT(($M$7:$M$106>$M10)*1)+1,"")
B11: EQUITY | C11: Germany DAX | D11: DAX Index | E11: BEST_PE_RATIO | F11: HIGH | G11: =IFERROR(IF(BDP($D11,"NAME")="","CHECK",BDP($D11,"NAME")),"CHECK") | H11: =IFERROR(BDP($D11,$E11),"") | I11: =IFERROR(AVERAGE(BDH($D11,$E11,SETTINGS_LOOK,"0D","Days="&SETTINGS_FREQ,"Fill=P")),"") | J11: =IFERROR(STDEV(BDH($D11,$E11,SETTINGS_LOOK,"0D","Days="&SETTINGS_FREQ,"Fill=P")),"") | K11: =IFERROR(($H11-$I11)/$J11,"") | L11: -1 | M11: =IFERROR($K11*$L11,"") | N11: =IFERROR(NORMSDIST($M11),"") | O11: =IFERROR(BDP($D11,"CHG_PCT_1YR")/100,"") | P11: =IFERROR(SUMPRODUCT(($B$7:$B$106=$B11)*($M$7:$M$106>$M11))+1,"") | Q11: =COUNTIF($B$7:$B$106,$B11) | R11: =IFERROR(IF($M11>=SETTINGS_ZC,"CHEAP",IF($M11<=SETTINGS_ZR,"RICH","-")),"") | S11: Forward P/E. High = expensive. | U11: =IFERROR(SUMPRODUCT(($M$7:$M$106>$M11)*1)+1,"")
B12: EQUITY | C12: UK FTSE 100 | D12: UKX Index | E12: BEST_PE_RATIO | F12: HIGH | G12: =IFERROR(IF(BDP($D12,"NAME")="","CHECK",BDP($D12,"NAME")),"CHECK") | H12: =IFERROR(BDP($D12,$E12),"") | I12: =IFERROR(AVERAGE(BDH($D12,$E12,SETTINGS_LOOK,"0D","Days="&SETTINGS_FREQ,"Fill=P")),"") | J12: =IFERROR(STDEV(BDH($D12,$E12,SETTINGS_LOOK,"0D","Days="&SETTINGS_FREQ,"Fill=P")),"") | K12: =IFERROR(($H12-$I12)/$J12,"") | L12: -1 | M12: =IFERROR($K12*$L12,"") | N12: =IFERROR(NORMSDIST($M12),"") | O12: =IFERROR(BDP($D12,"CHG_PCT_1YR")/100,"") | P12: =IFERROR(SUMPRODUCT(($B$7:$B$106=$B12)*($M$7:$M$106>$M12))+1,"") | Q12: =COUNTIF($B$7:$B$106,$B12) | R12: =IFERROR(IF($M12>=SETTINGS_ZC,"CHEAP",IF($M12<=SETTINGS_ZR,"RICH","-")),"") | S12: Forward P/E. High = expensive. | U12: =IFERROR(SUMPRODUCT(($M$7:$M$106>$M12)*1)+1,"")
B13: EQUITY | C13: Japan TOPIX | D13: TPX Index | E13: BEST_PE_RATIO | F13: HIGH | G13: =IFERROR(IF(BDP($D13,"NAME")="","CHECK",BDP($D13,"NAME")),"CHECK") | H13: =IFERROR(BDP($D13,$E13),"") | I13: =IFERROR(AVERAGE(BDH($D13,$E13,SETTINGS_LOOK,"0D","Days="&SETTINGS_FREQ,"Fill=P")),"") | J13: =IFERROR(STDEV(BDH($D13,$E13,SETTINGS_LOOK,"0D","Days="&SETTINGS_FREQ,"Fill=P")),"") | K13: =IFERROR(($H13-$I13)/$J13,"") | L13: -1 | M13: =IFERROR($K13*$L13,"") | N13: =IFERROR(NORMSDIST($M13),"") | O13: =IFERROR(BDP($D13,"CHG_PCT_1YR")/100,"") | P13: =IFERROR(SUMPRODUCT(($B$7:$B$106=$B13)*($M$7:$M$106>$M13))+1,"") | Q13: =COUNTIF($B$7:$B$106,$B13) | R13: =IFERROR(IF($M13>=SETTINGS_ZC,"CHEAP",IF($M13<=SETTINGS_ZR,"RICH","-")),"") | S13: Forward P/E. High = expensive. | U13: =IFERROR(SUMPRODUCT(($M$7:$M$106>$M13)*1)+1,"")
B14: EQUITY | C14: Switzerland SMI | D14: SMI Index | E14: BEST_PE_RATIO | F14: HIGH | G14: =IFERROR(IF(BDP($D14,"NAME")="","CHECK",BDP($D14,"NAME")),"CHECK") | H14: =IFERROR(BDP($D14,$E14),"") | I14: =IFERROR(AVERAGE(BDH($D14,$E14,SETTINGS_LOOK,"0D","Days="&SETTINGS_FREQ,"Fill=P")),"") | J14: =IFERROR(STDEV(BDH($D14,$E14,SETTINGS_LOOK,"0D","Days="&SETTINGS_FREQ,"Fill=P")),"") | K14: =IFERROR(($H14-$I14)/$J14,"") | L14: -1 | M14: =IFERROR($K14*$L14,"") | N14: =IFERROR(NORMSDIST($M14),"") | O14: =IFERROR(BDP($D14,"CHG_PCT_1YR")/100,"") | P14: =IFERROR(SUMPRODUCT(($B$7:$B$106=$B14)*($M$7:$M$106>$M14))+1,"") | Q14: =COUNTIF($B$7:$B$106,$B14) | R14: =IFERROR(IF($M14>=SETTINGS_ZC,"CHEAP",IF($M14<=SETTINGS_ZR,"RICH","-")),"") | S14: Forward P/E. High = expensive. | U14: =IFERROR(SUMPRODUCT(($M$7:$M$106>$M14)*1)+1,"")
B15: EQUITY | C15: Canada S&P/TSX | D15: SPTSX Index | E15: BEST_PE_RATIO | F15: HIGH | G15: =IFERROR(IF(BDP($D15,"NAME")="","CHECK",BDP($D15,"NAME")),"CHECK") | H15: =IFERROR(BDP($D15,$E15),"") | I15: =IFERROR(AVERAGE(BDH($D15,$E15,SETTINGS_LOOK,"0D","Days="&SETTINGS_FREQ,"Fill=P")),"") | J15: =IFERROR(STDEV(BDH($D15,$E15,SETTINGS_LOOK,"0D","Days="&SETTINGS_FREQ,"Fill=P")),"") | K15: =IFERROR(($H15-$I15)/$J15,"") | L15: -1 | M15: =IFERROR($K15*$L15,"") | N15: =IFERROR(NORMSDIST($M15),"") | O15: =IFERROR(BDP($D15,"CHG_PCT_1YR")/100,"") | P15: =IFERROR(SUMPRODUCT(($B$7:$B$106=$B15)*($M$7:$M$106>$M15))+1,"") | Q15: =COUNTIF($B$7:$B$106,$B15) | R15: =IFERROR(IF($M15>=SETTINGS_ZC,"CHEAP",IF($M15<=SETTINGS_ZR,"RICH","-")),"") | S15: Forward P/E. High = expensive. | U15: =IFERROR(SUMPRODUCT(($M$7:$M$106>$M15)*1)+1,"")
B16: EQUITY | C16: Australia ASX 200 | D16: AS51 Index | E16: BEST_PE_RATIO | F16: HIGH | G16: =IFERROR(IF(BDP($D16,"NAME")="","CHECK",BDP($D16,"NAME")),"CHECK") | H16: =IFERROR(BDP($D16,$E16),"") | I16: =IFERROR(AVERAGE(BDH($D16,$E16,SETTINGS_LOOK,"0D","Days="&SETTINGS_FREQ,"Fill=P")),"") | J16: =IFERROR(STDEV(BDH($D16,$E16,SETTINGS_LOOK,"0D","Days="&SETTINGS_FREQ,"Fill=P")),"") | K16: =IFERROR(($H16-$I16)/$J16,"") | L16: -1 | M16: =IFERROR($K16*$L16,"") | N16: =IFERROR(NORMSDIST($M16),"") | O16: =IFERROR(BDP($D16,"CHG_PCT_1YR")/100,"") | P16: =IFERROR(SUMPRODUCT(($B$7:$B$106=$B16)*($M$7:$M$106>$M16))+1,"") | Q16: =COUNTIF($B$7:$B$106,$B16) | R16: =IFERROR(IF($M16>=SETTINGS_ZC,"CHEAP",IF($M16<=SETTINGS_ZR,"RICH","-")),"") | S16: Forward P/E. High = expensive. | U16: =IFERROR(SUMPRODUCT(($M$7:$M$106>$M16)*1)+1,"")
B17: EQUITY | C17: MSCI EM | D17: MXEF Index | E17: BEST_PE_RATIO | F17: HIGH | G17: =IFERROR(IF(BDP($D17,"NAME")="","CHECK",BDP($D17,"NAME")),"CHECK") | H17: =IFERROR(BDP($D17,$E17),"") | I17: =IFERROR(AVERAGE(BDH($D17,$E17,SETTINGS_LOOK,"0D","Days="&SETTINGS_FREQ,"Fill=P")),"") | J17: =IFERROR(STDEV(BDH($D17,$E17,SETTINGS_LOOK,"0D","Days="&SETTINGS_FREQ,"Fill=P")),"") | K17: =IFERROR(($H17-$I17)/$J17,"") | L17: -1 | M17: =IFERROR($K17*$L17,"") | N17: =IFERROR(NORMSDIST($M17),"") | O17: =IFERROR(BDP($D17,"CHG_PCT_1YR")/100,"") | P17: =IFERROR(SUMPRODUCT(($B$7:$B$106=$B17)*($M$7:$M$106>$M17))+1,"") | Q17: =COUNTIF($B$7:$B$106,$B17) | R17: =IFERROR(IF($M17>=SETTINGS_ZC,"CHEAP",IF($M17<=SETTINGS_ZR,"RICH","-")),"") | S17: Forward P/E. High = expensive. | U17: =IFERROR(SUMPRODUCT(($M$7:$M$106>$M17)*1)+1,"")
B18: EQUITY | C18: China CSI 300 | D18: SHSZ300 Index | E18: BEST_PE_RATIO | F18: HIGH | G18: =IFERROR(IF(BDP($D18,"NAME")="","CHECK",BDP($D18,"NAME")),"CHECK") | H18: =IFERROR(BDP($D18,$E18),"") | I18: =IFERROR(AVERAGE(BDH($D18,$E18,SETTINGS_LOOK,"0D","Days="&SETTINGS_FREQ,"Fill=P")),"") | J18: =IFERROR(STDEV(BDH($D18,$E18,SETTINGS_LOOK,"0D","Days="&SETTINGS_FREQ,"Fill=P")),"") | K18: =IFERROR(($H18-$I18)/$J18,"") | L18: -1 | M18: =IFERROR($K18*$L18,"") | N18: =IFERROR(NORMSDIST($M18),"") | O18: =IFERROR(BDP($D18,"CHG_PCT_1YR")/100,"") | P18: =IFERROR(SUMPRODUCT(($B$7:$B$106=$B18)*($M$7:$M$106>$M18))+1,"") | Q18: =COUNTIF($B$7:$B$106,$B18) | R18: =IFERROR(IF($M18>=SETTINGS_ZC,"CHEAP",IF($M18<=SETTINGS_ZR,"RICH","-")),"") | S18: Forward P/E. High = expensive. | U18: =IFERROR(SUMPRODUCT(($M$7:$M$106>$M18)*1)+1,"")
... B50: RATES | C50: Korea 10y | D50: GVSK10YR Index | E50: PX_LAST | F50: VERIFY | G50: =IFERROR(IF(BDP($D50,"NAME")="","CHECK",BDP($D50,"NAME")),"CHECK") | H50: =IFERROR(BDP($D50,$E50),"") | I50: =IFERROR(AVERAGE(BDH($D50,$E50,SETTINGS_LOOK,"0D","Days="&SETTINGS_FREQ,"Fill=P")),"") | J50: =IFERROR(STDEV(BDH($D50,$E50,SETTINGS_LOOK,"0D","Days="&SETTINGS_FREQ,"Fill=P")),"") | K50: =IFERROR(($H50-$I50)/$J50,"") | L50: 1 | M50: =IFERROR($K50*$L50,"") | N50: =IFERROR(NORMSDIST($M50),"") | O50: =IFERROR(BDP($D50,"CHG_PCT_1YR")/100,"") | P50: =IFERROR(SUMPRODUCT(($B$7:$B$106=$B50)*($M$7:$M$106>$M50))+1,"") | Q50: =COUNTIF($B$7:$B$106,$B50) | R50: =IFERROR(IF($M50>=SETTINGS_ZC,"CHEAP",IF($M50<=SETTINGS_ZR,"RICH","-")),"") | S50: 10y nominal yield, %. High yield = cheap bond. | U50: =IFERROR(SUMPRODUCT(($M$7:$M$106>$M50)*1)+1,"")
B51: FX | C51: Euro | D51: EURUSD Curncy | E51: PX_LAST | F51: HIGH | G51: =IFERROR(IF(BDP($D51,"NAME")="","CHECK",BDP($D51,"NAME")),"CHECK") | H51: =IFERROR(BDP($D51,$E51),"") | I51: =IFERROR(AVERAGE(BDH($D51,$E51,SETTINGS_LOOK,"0D","Days="&SETTINGS_FREQ,"Fill=P")),"") | J51: =IFERROR(STDEV(BDH($D51,$E51,SETTINGS_LOOK,"0D","Days="&SETTINGS_FREQ,"Fill=P")),"") | K51: =IFERROR(($H51-$I51)/$J51,"") | L51: -1 | M51: =IFERROR(IF(AND(SETTINGS_FXSRC="REER",$T51<>""),-1*((BDP($T51,"PX_LAST")-AVERAGE(BDH($T51,"PX_LAST",SETTINGS_LOOK,"0D","Days="&SETTINGS_FREQ,"Fill=P")))/STDEV(BDH($T51,"PX_LAST",SETTINGS_LOOK,"0D","Days="&SETTINGS_FREQ,"Fill=P"))),$K51*$L51),"") | N51: =IFERROR(NORMSDIST($M51),"") | O51: =IFERROR(BDP($D51,"CHG_PCT_1YR")/100,"") | P51: =IFERROR(SUMPRODUCT(($B$7:$B$106=$B51)*($M$7:$M$106>$M51))+1,"") | Q51: =COUNTIF($B$7:$B$106,$B51) | R51: =IFERROR(IF($M51>=SETTINGS_ZC,"CHEAP",IF($M51<=SETTINGS_ZR,"RICH","-")),"") | S51: Spot, USD per unit. High = strong local ccy = expensive. | U51: =IFERROR(SUMPRODUCT(($M$7:$M$106>$M51)*1)+1,"")
B52: FX | C52: Japanese yen | D52: USDJPY Curncy | E52: PX_LAST | F52: HIGH | G52: =IFERROR(IF(BDP($D52,"NAME")="","CHECK",BDP($D52,"NAME")),"CHECK") | H52: =IFERROR(BDP($D52,$E52),"") | I52: =IFERROR(AVERAGE(BDH($D52,$E52,SETTINGS_LOOK,"0D","Days="&SETTINGS_FREQ,"Fill=P")),"") | J52: =IFERROR(STDEV(BDH($D52,$E52,SETTINGS_LOOK,"0D","Days="&SETTINGS_FREQ,"Fill=P")),"") | K52: =IFERROR(($H52-$I52)/$J52,"") | L52: 1 | M52: =IFERROR(IF(AND(SETTINGS_FXSRC="REER",$T52<>""),-1*((BDP($T52,"PX_LAST")-AVERAGE(BDH($T52,"PX_LAST",SETTINGS_LOOK,"0D","Days="&SETTINGS_FREQ,"Fill=P")))/STDEV(BDH($T52,"PX_LAST",SETTINGS_LOOK,"0D","Days="&SETTINGS_FREQ,"Fill=P"))),$K52*$L52),"") | N52: =IFERROR(NORMSDIST($M52),"") | O52: =IFERROR(BDP($D52,"CHG_PCT_1YR")/100,"") | P52: =IFERROR(SUMPRODUCT(($B$7:$B$106=$B52)*($M$7:$M$106>$M52))+1,"") | Q52: =COUNTIF($B$7:$B$106,$B52) | R52: =IFERROR(IF($M52>=SETTINGS_ZC,"CHEAP",IF($M52<=SETTINGS_ZR,"RICH","-")),"") | S52: Spot, units per USD. High = weak local ccy = cheap. | U52: =IFERROR(SUMPRODUCT(($M$7:$M$106>$M52)*1)+1,"")
B53: FX | C53: Sterling | D53: GBPUSD Curncy | E53: PX_LAST | F53: HIGH | G53: =IFERROR(IF(BDP($D53,"NAME")="","CHECK",BDP($D53,"NAME")),"CHECK") | H53: =IFERROR(BDP($D53,$E53),"") | I53: =IFERROR(AVERAGE(BDH($D53,$E53,SETTINGS_LOOK,"0D","Days="&SETTINGS_FREQ,"Fill=P")),"") | J53: =IFERROR(STDEV(BDH($D53,$E53,SETTINGS_LOOK,"0D","Days="&SETTINGS_FREQ,"Fill=P")),"") | K53: =IFERROR(($H53-$I53)/$J53,"") | L53: -1 | M53: =IFERROR(IF(AND(SETTINGS_FXSRC="REER",$T53<>""),-1*((BDP($T53,"PX_LAST")-AVERAGE(BDH($T53,"PX_LAST",SETTINGS_LOOK,"0D","Days="&SETTINGS_FREQ,"Fill=P")))/STDEV(BDH($T53,"PX_LAST",SETTINGS_LOOK,"0D","Days="&SETTINGS_FREQ,"Fill=P"))),$K53*$L53),"") | N53: =IFERROR(NORMSDIST($M53),"") | O53: =IFERROR(BDP($D53,"CHG_PCT_1YR")/100,"") | P53: =IFERROR(SUMPRODUCT(($B$7:$B$106=$B53)*($M$7:$M$106>$M53))+1,"") | Q53: =COUNTIF($B$7:$B$106,$B53) | R53: =IFERROR(IF($M53>=SETTINGS_ZC,"CHEAP",IF($M53<=SETTINGS_ZR,"RICH","-")),"") | S53: Spot, USD per unit. High = strong local ccy = expensive. | U53: =IFERROR(SUMPRODUCT(($M$7:$M$106>$M53)*1)+1,"")
B54: FX | C54: Swiss franc | D54: USDCHF Curncy | E54: PX_LAST | F54: HIGH | G54: =IFERROR(IF(BDP($D54,"NAME")="","CHECK",BDP($D54,"NAME")),"CHECK") | H54: =IFERROR(BDP($D54,$E54),"") | I54: =IFERROR(AVERAGE(BDH($D54,$E54,SETTINGS_LOOK,"0D","Days="&SETTINGS_FREQ,"Fill=P")),"") | J54: =IFERROR(STDEV(BDH($D54,$E54,SETTINGS_LOOK,"0D","Days="&SETTINGS_FREQ,"Fill=P")),"") | K54: =IFERROR(($H54-$I54)/$J54,"") | L54: 1 | M54: =IFERROR(IF(AND(SETTINGS_FXSRC="REER",$T54<>""),-1*((BDP($T54,"PX_LAST")-AVERAGE(BDH($T54,"PX_LAST",SETTINGS_LOOK,"0D","Days="&SETTINGS_FREQ,"Fill=P")))/STDEV(BDH($T54,"PX_LAST",SETTINGS_LOOK,"0D","Days="&SETTINGS_FREQ,"Fill=P"))),$K54*$L54),"") | N54: =IFERROR(NORMSDIST($M54),"") | O54: =IFERROR(BDP($D54,"CHG_PCT_1YR")/100,"") | P54: =IFERROR(SUMPRODUCT(($B$7:$B$106=$B54)*($M$7:$M$106>$M54))+1,"") | Q54: =COUNTIF($B$7:$B$106,$B54) | R54: =IFERROR(IF($M54>=SETTINGS_ZC,"CHEAP",IF($M54<=SETTINGS_ZR,"RICH","-")),"") | S54: Spot, units per USD. High = weak local ccy = cheap. | U54: =IFERROR(SUMPRODUCT(($M$7:$M$106>$M54)*1)+1,"")
B55: FX | C55: Canadian dollar | D55: USDCAD Curncy | E55: PX_LAST | F55: HIGH | G55: =IFERROR(IF(BDP($D55,"NAME")="","CHECK",BDP($D55,"NAME")),"CHECK") | H55: =IFERROR(BDP($D55,$E55),"") | I55: =IFERROR(AVERAGE(BDH($D55,$E55,SETTINGS_LOOK,"0D","Days="&SETTINGS_FREQ,"Fill=P")),"") | J55: =IFERROR(STDEV(BDH($D55,$E55,SETTINGS_LOOK,"0D","Days="&SETTINGS_FREQ,"Fill=P")),"") | K55: =IFERROR(($H55-$I55)/$J55,"") | L55: 1 | M55: =IFERROR(IF(AND(SETTINGS_FXSRC="REER",$T55<>""),-1*((BDP($T55,"PX_LAST")-AVERAGE(BDH($T55,"PX_LAST",SETTINGS_LOOK,"0D","Days="&SETTINGS_FREQ,"Fill=P")))/STDEV(BDH($T55,"PX_LAST",SETTINGS_LOOK,"0D","Days="&SETTINGS_FREQ,"Fill=P"))),$K55*$L55),"") | N55: =IFERROR(NORMSDIST($M55),"") | O55: =IFERROR(BDP($D55,"CHG_PCT_1YR")/100,"") | P55: =IFERROR(SUMPRODUCT(($B$7:$B$106=$B55)*($M$7:$M$106>$M55))+1,"") | Q55: =COUNTIF($B$7:$B$106,$B55) | R55: =IFERROR(IF($M55>=SETTINGS_ZC,"CHEAP",IF($M55<=SETTINGS_ZR,"RICH","-")),"") | S55: Spot, units per USD. High = weak local ccy = cheap. | U55: =IFERROR(SUMPRODUCT(($M$7:$M$106>$M55)*1)+1,"")
B56: FX | C56: Australian dollar | D56: AUDUSD Curncy | E56: PX_LAST | F56: HIGH | G56: =IFERROR(IF(BDP($D56,"NAME")="","CHECK",BDP($D56,"NAME")),"CHECK") | H56: =IFERROR(BDP($D56,$E56),"") | I56: =IFERROR(AVERAGE(BDH($D56,$E56,SETTINGS_LOOK,"0D","Days="&SETTINGS_FREQ,"Fill=P")),"") | J56: =IFERROR(STDEV(BDH($D56,$E56,SETTINGS_LOOK,"0D","Days="&SETTINGS_FREQ,"Fill=P")),"") | K56: =IFERROR(($H56-$I56)/$J56,"") | L56: -1 | M56: =IFERROR(IF(AND(SETTINGS_FXSRC="REER",$T56<>""),-1*((BDP($T56,"PX_LAST")-AVERAGE(BDH($T56,"PX_LAST",SETTINGS_LOOK,"0D","Days="&SETTINGS_FREQ,"Fill=P")))/STDEV(BDH($T56,"PX_LAST",SETTINGS_LOOK,"0D","Days="&SETTINGS_FREQ,"Fill=P"))),$K56*$L56),"") | N56: =IFERROR(NORMSDIST($M56),"") | O56: =IFERROR(BDP($D56,"CHG_PCT_1YR")/100,"") | P56: =IFERROR(SUMPRODUCT(($B$7:$B$106=$B56)*($M$7:$M$106>$M56))+1,"") | Q56: =COUNTIF($B$7:$B$106,$B56) | R56: =IFERROR(IF($M56>=SETTINGS_ZC,"CHEAP",IF($M56<=SETTINGS_ZR,"RICH","-")),"") | S56: Spot, USD per unit. High = strong local ccy = expensive. | U56: =IFERROR(SUMPRODUCT(($M$7:$M$106>$M56)*1)+1,"")
B57: FX | C57: NZ dollar | D57: NZDUSD Curncy | E57: PX_LAST | F57: HIGH | G57: =IFERROR(IF(BDP($D57,"NAME")="","CHECK",BDP($D57,"NAME")),"CHECK") | H57: =IFERROR(BDP($D57,$E57),"") | I57: =IFERROR(AVERAGE(BDH($D57,$E57,SETTINGS_LOOK,"0D","Days="&SETTINGS_FREQ,"Fill=P")),"") | J57: =IFERROR(STDEV(BDH($D57,$E57,SETTINGS_LOOK,"0D","Days="&SETTINGS_FREQ,"Fill=P")),"") | K57: =IFERROR(($H57-$I57)/$J57,"") | L57: -1 | M57: =IFERROR(IF(AND(SETTINGS_FXSRC="REER",$T57<>""),-1*((BDP($T57,"PX_LAST")-AVERAGE(BDH($T57,"PX_LAST",SETTINGS_LOOK,"0D","Days="&SETTINGS_FREQ,"Fill=P")))/STDEV(BDH($T57,"PX_LAST",SETTINGS_LOOK,"0D","Days="&SETTINGS_FREQ,"Fill=P"))),$K57*$L57),"") | N57: =IFERROR(NORMSDIST($M57),"") | O57: =IFERROR(BDP($D57,"CHG_PCT_1YR")/100,"") | P57: =IFERROR(SUMPRODUCT(($B$7:$B$106=$B57)*($M$7:$M$106>$M57))+1,"") | Q57: =COUNTIF($B$7:$B$106,$B57) | R57: =IFERROR(IF($M57>=SETTINGS_ZC,"CHEAP",IF($M57<=SETTINGS_ZR,"RICH","-")),"") | S57: Spot, USD per unit. High = strong local ccy = expensive. | U57: =IFERROR(SUMPRODUCT(($M$7:$M$106>$M57)*1)+1,"")
B58: FX | C58: Norwegian krone | D58: USDNOK Curncy | E58: PX_LAST | F58: HIGH | G58: =IFERROR(IF(BDP($D58,"NAME")="","CHECK",BDP($D58,"NAME")),"CHECK") | H58: =IFERROR(BDP($D58,$E58),"") | I58: =IFERROR(AVERAGE(BDH($D58,$E58,SETTINGS_LOOK,"0D","Days="&SETTINGS_FREQ,"Fill=P")),"") | J58: =IFERROR(STDEV(BDH($D58,$E58,SETTINGS_LOOK,"0D","Days="&SETTINGS_FREQ,"Fill=P")),"") | K58: =IFERROR(($H58-$I58)/$J58,"") | L58: 1 | M58: =IFERROR(IF(AND(SETTINGS_FXSRC="REER",$T58<>""),-1*((BDP($T58,"PX_LAST")-AVERAGE(BDH($T58,"PX_LAST",SETTINGS_LOOK,"0D","Days="&SETTINGS_FREQ,"Fill=P")))/STDEV(BDH($T58,"PX_LAST",SETTINGS_LOOK,"0D","Days="&SETTINGS_FREQ,"Fill=P"))),$K58*$L58),"") | N58: =IFERROR(NORMSDIST($M58),"") | O58: =IFERROR(BDP($D58,"CHG_PCT_1YR")/100,"") | P58: =IFERROR(SUMPRODUCT(($B$7:$B$106=$B58)*($M$7:$M$106>$M58))+1,"") | Q58: =COUNTIF($B$7:$B$106,$B58) | R58: =IFERROR(IF($M58>=SETTINGS_ZC,"CHEAP",IF($M58<=SETTINGS_ZR,"RICH","-")),"") | S58: Spot, units per USD. High = weak local ccy = cheap. | U58: =IFERROR(SUMPRODUCT(($M$7:$M$106>$M58)*1)+1,"")
B59: FX | C59: Swedish krona | D59: USDSEK Curncy | E59: PX_LAST | F59: HIGH | G59: =IFERROR(IF(BDP($D59,"NAME")="","CHECK",BDP($D59,"NAME")),"CHECK") | H59: =IFERROR(BDP($D59,$E59),"") | I59: =IFERROR(AVERAGE(BDH($D59,$E59,SETTINGS_LOOK,"0D","Days="&SETTINGS_FREQ,"Fill=P")),"") | J59: =IFERROR(STDEV(BDH($D59,$E59,SETTINGS_LOOK,"0D","Days="&SETTINGS_FREQ,"Fill=P")),"") | K59: =IFERROR(($H59-$I59)/$J59,"") | L59: 1 | M59: =IFERROR(IF(AND(SETTINGS_FXSRC="REER",$T59<>""),-1*((BDP($T59,"PX_LAST")-AVERAGE(BDH($T59,"PX_LAST",SETTINGS_LOOK,"0D","Days="&SETTINGS_FREQ,"Fill=P")))/STDEV(BDH($T59,"PX_LAST",SETTINGS_LOOK,"0D","Days="&SETTINGS_FREQ,"Fill=P"))),$K59*$L59),"") | N59: =IFERROR(NORMSDIST($M59),"") | O59: =IFERROR(BDP($D59,"CHG_PCT_1YR")/100,"") | P59: =IFERROR(SUMPRODUCT(($B$7:$B$106=$B59)*($M$7:$M$106>$M59))+1,"") | Q59: =COUNTIF($B$7:$B$106,$B59) | R59: =IFERROR(IF($M59>=SETTINGS_ZC,"CHEAP",IF($M59<=SETTINGS_ZR,"RICH","-")),"") | S59: Spot, units per USD. High = weak local ccy = cheap. | U59: =IFERROR(SUMPRODUCT(($M$7:$M$106>$M59)*1)+1,"")
B60: FX | C60: Brazilian real | D60: USDBRL Curncy | E60: PX_LAST | F60: HIGH | G60: =IFERROR(IF(BDP($D60,"NAME")="","CHECK",BDP($D60,"NAME")),"CHECK") | H60: =IFERROR(BDP($D60,$E60),"") | I60: =IFERROR(AVERAGE(BDH($D60,$E60,SETTINGS_LOOK,"0D","Days="&SETTINGS_FREQ,"Fill=P")),"") | J60: =IFERROR(STDEV(BDH($D60,$E60,SETTINGS_LOOK,"0D","Days="&SETTINGS_FREQ,"Fill=P")),"") | K60: =IFERROR(($H60-$I60)/$J60,"") | L60: 1 | M60: =IFERROR(IF(AND(SETTINGS_FXSRC="REER",$T60<>""),-1*((BDP($T60,"PX_LAST")-AVERAGE(BDH($T60,"PX_LAST",SETTINGS_LOOK,"0D","Days="&SETTINGS_FREQ,"Fill=P")))/STDEV(BDH($T60,"PX_LAST",SETTINGS_LOOK,"0D","Days="&SETTINGS_FREQ,"Fill=P"))),$K60*$L60),"") | N60: =IFERROR(NORMSDIST($M60),"") | O60: =IFERROR(BDP($D60,"CHG_PCT_1YR")/100,"") | P60: =IFERROR(SUMPRODUCT(($B$7:$B$106=$B60)*($M$7:$M$106>$M60))+1,"") | Q60: =COUNTIF($B$7:$B$106,$B60) | R60: =IFERROR(IF($M60>=SETTINGS_ZC,"CHEAP",IF($M60<=SETTINGS_ZR,"RICH","-")),"") | S60: Spot, units per USD. High = weak local ccy = cheap. | U60: =IFERROR(SUMPRODUCT(($M$7:$M$106>$M60)*1)+1,"")
B61: FX | C61: Mexican peso | D61: USDMXN Curncy | E61: PX_LAST | F61: HIGH | G61: =IFERROR(IF(BDP($D61,"NAME")="","CHECK",BDP($D61,"NAME")),"CHECK") | H61: =IFERROR(BDP($D61,$E61),"") | I61: =IFERROR(AVERAGE(BDH($D61,$E61,SETTINGS_LOOK,"0D","Days="&SETTINGS_FREQ,"Fill=P")),"") | J61: =IFERROR(STDEV(BDH($D61,$E61,SETTINGS_LOOK,"0D","Days="&SETTINGS_FREQ,"Fill=P")),"") | K61: =IFERROR(($H61-$I61)/$J61,"") | L61: 1 | M61: =IFERROR(IF(AND(SETTINGS_FXSRC="REER",$T61<>""),-1*((BDP($T61,"PX_LAST")-AVERAGE(BDH($T61,"PX_LAST",SETTINGS_LOOK,"0D","Days="&SETTINGS_FREQ,"Fill=P")))/STDEV(BDH($T61,"PX_LAST",SETTINGS_LOOK,"0D","Days="&SETTINGS_FREQ,"Fill=P"))),$K61*$L61),"") | N61: =IFERROR(NORMSDIST($M61),"") | O61: =IFERROR(BDP($D61,"CHG_PCT_1YR")/100,"") | P61: =IFERROR(SUMPRODUCT(($B$7:$B$106=$B61)*($M$7:$M$106>$M61))+1,"") | Q61: =COUNTIF($B$7:$B$106,$B61) | R61: =IFERROR(IF($M61>=SETTINGS_ZC,"CHEAP",IF($M61<=SETTINGS_ZR,"RICH","-")),"") | S61: Spot, units per USD. High = weak local ccy = cheap. | U61: =IFERROR(SUMPRODUCT(($M$7:$M$106>$M61)*1)+1,"")
B62: FX | C62: Colombian peso | D62: USDCOP Curncy | E62: PX_LAST | F62: HIGH | G62: =IFERROR(IF(BDP($D62,"NAME")="","CHECK",BDP($D62,"NAME")),"CHECK") | H62: =IFERROR(BDP($D62,$E62),"") | I62: =IFERROR(AVERAGE(BDH($D62,$E62,SETTINGS_LOOK,"0D","Days="&SETTINGS_FREQ,"Fill=P")),"") | J62: =IFERROR(STDEV(BDH($D62,$E62,SETTINGS_LOOK,"0D","Days="&SETTINGS_FREQ,"Fill=P")),"") | K62: =IFERROR(($H62-$I62)/$J62,"") | L62: 1 | M62: =IFERROR(IF(AND(SETTINGS_FXSRC="REER",$T62<>""),-1*((BDP($T62,"PX_LAST")-AVERAGE(BDH($T62,"PX_LAST",SETTINGS_LOOK,"0D","Days="&SETTINGS_FREQ,"Fill=P")))/STDEV(BDH($T62,"PX_LAST",SETTINGS_LOOK,"0D","Days="&SETTINGS_FREQ,"Fill=P"))),$K62*$L62),"") | N62: =IFERROR(NORMSDIST($M62),"") | O62: =IFERROR(BDP($D62,"CHG_PCT_1YR")/100,"") | P62: =IFERROR(SUMPRODUCT(($B$7:$B$106=$B62)*($M$7:$M$106>$M62))+1,"") | Q62: =COUNTIF($B$7:$B$106,$B62) | R62: =IFERROR(IF($M62>=SETTINGS_ZC,"CHEAP",IF($M62<=SETTINGS_ZR,"RICH","-")),"") | S62: Spot, units per USD. High = weak local ccy = cheap. | U62: =IFERROR(SUMPRODUCT(($M$7:$M$106>$M62)*1)+1,"")
... B76: FX | C76: Offshore renminbi | D76: USDCNH Curncy | E76: PX_LAST | F76: HIGH | G76: =IFERROR(IF(BDP($D76,"NAME")="","CHECK",BDP($D76,"NAME")),"CHECK") | H76: =IFERROR(BDP($D76,$E76),"") | I76: =IFERROR(AVERAGE(BDH($D76,$E76,SETTINGS_LOOK,"0D","Days="&SETTINGS_FREQ,"Fill=P")),"") | J76: =IFERROR(STDEV(BDH($D76,$E76,SETTINGS_LOOK,"0D","Days="&SETTINGS_FREQ,"Fill=P")),"") | K76: =IFERROR(($H76-$I76)/$J76,"") | L76: 1 | M76: =IFERROR(IF(AND(SETTINGS_FXSRC="REER",$T76<>""),-1*((BDP($T76,"PX_LAST")-AVERAGE(BDH($T76,"PX_LAST",SETTINGS_LOOK,"0D","Days="&SETTINGS_FREQ,"Fill=P")))/STDEV(BDH($T76,"PX_LAST",SETTINGS_LOOK,"0D","Days="&SETTINGS_FREQ,"Fill=P"))),$K76*$L76),"") | N76: =IFERROR(NORMSDIST($M76),"") | O76: =IFERROR(BDP($D76,"CHG_PCT_1YR")/100,"") | P76: =IFERROR(SUMPRODUCT(($B$7:$B$106=$B76)*($M$7:$M$106>$M76))+1,"") | Q76: =COUNTIF($B$7:$B$106,$B76) | R76: =IFERROR(IF($M76>=SETTINGS_ZC,"CHEAP",IF($M76<=SETTINGS_ZR,"RICH","-")),"") | S76: Spot, units per USD. High = weak local ccy = cheap. | U76: =IFERROR(SUMPRODUCT(($M$7:$M$106>$M76)*1)+1,"")
B77: CREDIT | C77: US IG OAS | D77: LUACOAS Index | E77: PX_LAST | F77: HIGH | G77: =IFERROR(IF(BDP($D77,"NAME")="","CHECK",BDP($D77,"NAME")),"CHECK") | H77: =IFERROR(BDP($D77,$E77),"") | I77: =IFERROR(AVERAGE(BDH($D77,$E77,SETTINGS_LOOK,"0D","Days="&SETTINGS_FREQ,"Fill=P")),"") | J77: =IFERROR(STDEV(BDH($D77,$E77,SETTINGS_LOOK,"0D","Days="&SETTINGS_FREQ,"Fill=P")),"") | K77: =IFERROR(($H77-$I77)/$J77,"") | L77: 1 | M77: =IFERROR($K77*$L77,"") | N77: =IFERROR(NORMSDIST($M77),"") | O77: =IFERROR(BDP($D77,"CHG_PCT_1YR")/100,"") | P77: =IFERROR(SUMPRODUCT(($B$7:$B$106=$B77)*($M$7:$M$106>$M77))+1,"") | Q77: =COUNTIF($B$7:$B$106,$B77) | R77: =IFERROR(IF($M77>=SETTINGS_ZC,"CHEAP",IF($M77<=SETTINGS_ZR,"RICH","-")),"") | S77: Spread in bp. High spread = cheap credit. | U77: =IFERROR(SUMPRODUCT(($M$7:$M$106>$M77)*1)+1,"")
B78: CREDIT | C78: US HY OAS | D78: LF98OAS Index | E78: PX_LAST | F78: HIGH | G78: =IFERROR(IF(BDP($D78,"NAME")="","CHECK",BDP($D78,"NAME")),"CHECK") | H78: =IFERROR(BDP($D78,$E78),"") | I78: =IFERROR(AVERAGE(BDH($D78,$E78,SETTINGS_LOOK,"0D","Days="&SETTINGS_FREQ,"Fill=P")),"") | J78: =IFERROR(STDEV(BDH($D78,$E78,SETTINGS_LOOK,"0D","Days="&SETTINGS_FREQ,"Fill=P")),"") | K78: =IFERROR(($H78-$I78)/$J78,"") | L78: 1 | M78: =IFERROR($K78*$L78,"") | N78: =IFERROR(NORMSDIST($M78),"") | O78: =IFERROR(BDP($D78,"CHG_PCT_1YR")/100,"") | P78: =IFERROR(SUMPRODUCT(($B$7:$B$106=$B78)*($M$7:$M$106>$M78))+1,"") | Q78: =COUNTIF($B$7:$B$106,$B78) | R78: =IFERROR(IF($M78>=SETTINGS_ZC,"CHEAP",IF($M78<=SETTINGS_ZR,"RICH","-")),"") | S78: Spread in bp. High spread = cheap credit. | U78: =IFERROR(SUMPRODUCT(($M$7:$M$106>$M78)*1)+1,"")
B79: CREDIT | C79: Euro IG OAS | D79: LECPOAS Index | E79: PX_LAST | F79: VERIFY | G79: =IFERROR(IF(BDP($D79,"NAME")="","CHECK",BDP($D79,"NAME")),"CHECK") | H79: =IFERROR(BDP($D79,$E79),"") | I79: =IFERROR(AVERAGE(BDH($D79,$E79,SETTINGS_LOOK,"0D","Days="&SETTINGS_FREQ,"Fill=P")),"") | J79: =IFERROR(STDEV(BDH($D79,$E79,SETTINGS_LOOK,"0D","Days="&SETTINGS_FREQ,"Fill=P")),"") | K79: =IFERROR(($H79-$I79)/$J79,"") | L79: 1 | M79: =IFERROR($K79*$L79,"") | N79: =IFERROR(NORMSDIST($M79),"") | O79: =IFERROR(BDP($D79,"CHG_PCT_1YR")/100,"") | P79: =IFERROR(SUMPRODUCT(($B$7:$B$106=$B79)*($M$7:$M$106>$M79))+1,"") | Q79: =COUNTIF($B$7:$B$106,$B79) | R79: =IFERROR(IF($M79>=SETTINGS_ZC,"CHEAP",IF($M79<=SETTINGS_ZR,"RICH","-")),"") | S79: Spread in bp. High spread = cheap credit. | U79: =IFERROR(SUMPRODUCT(($M$7:$M$106>$M79)*1)+1,"")
B80: CREDIT | C80: Euro HY OAS | D80: LP01OAS Index | E80: PX_LAST | F80: VERIFY | G80: =IFERROR(IF(BDP($D80,"NAME")="","CHECK",BDP($D80,"NAME")),"CHECK") | H80: =IFERROR(BDP($D80,$E80),"") | I80: =IFERROR(AVERAGE(BDH($D80,$E80,SETTINGS_LOOK,"0D","Days="&SETTINGS_FREQ,"Fill=P")),"") | J80: =IFERROR(STDEV(BDH($D80,$E80,SETTINGS_LOOK,"0D","Days="&SETTINGS_FREQ,"Fill=P")),"") | K80: =IFERROR(($H80-$I80)/$J80,"") | L80: 1 | M80: =IFERROR($K80*$L80,"") | N80: =IFERROR(NORMSDIST($M80),"") | O80: =IFERROR(BDP($D80,"CHG_PCT_1YR")/100,"") | P80: =IFERROR(SUMPRODUCT(($B$7:$B$106=$B80)*($M$7:$M$106>$M80))+1,"") | Q80: =COUNTIF($B$7:$B$106,$B80) | R80: =IFERROR(IF($M80>=SETTINGS_ZC,"CHEAP",IF($M80<=SETTINGS_ZR,"RICH","-")),"") | S80: Spread in bp. High spread = cheap credit. | U80: =IFERROR(SUMPRODUCT(($M$7:$M$106>$M80)*1)+1,"")
B81: CREDIT | C81: EM sovereign USD (EMBI GD) spread | D81: JPEGSOSD Index | E81: PX_LAST | F81: VERIFY | G81: =IFERROR(IF(BDP($D81,"NAME")="","CHECK",BDP($D81,"NAME")),"CHECK") | H81: =IFERROR(BDP($D81,$E81),"") | I81: =IFERROR(AVERAGE(BDH($D81,$E81,SETTINGS_LOOK,"0D","Days="&SETTINGS_FREQ,"Fill=P")),"") | J81: =IFERROR(STDEV(BDH($D81,$E81,SETTINGS_LOOK,"0D","Days="&SETTINGS_FREQ,"Fill=P")),"") | K81: =IFERROR(($H81-$I81)/$J81,"") | L81: 1 | M81: =IFERROR($K81*$L81,"") | N81: =IFERROR(NORMSDIST($M81),"") | O81: =IFERROR(BDP($D81,"CHG_PCT_1YR")/100,"") | P81: =IFERROR(SUMPRODUCT(($B$7:$B$106=$B81)*($M$7:$M$106>$M81))+1,"") | Q81: =COUNTIF($B$7:$B$106,$B81) | R81: =IFERROR(IF($M81>=SETTINGS_ZC,"CHEAP",IF($M81<=SETTINGS_ZR,"RICH","-")),"") | S81: Spread in bp. High spread = cheap credit. | U81: =IFERROR(SUMPRODUCT(($M$7:$M$106>$M81)*1)+1,"")
B82: CREDIT | C82: EM corporate (CEMBI) spread | D82: JBCDCOMP Index | E82: PX_LAST | F82: VERIFY | G82: =IFERROR(IF(BDP($D82,"NAME")="","CHECK",BDP($D82,"NAME")),"CHECK") | H82: =IFERROR(BDP($D82,$E82),"") | I82: =IFERROR(AVERAGE(BDH($D82,$E82,SETTINGS_LOOK,"0D","Days="&SETTINGS_FREQ,"Fill=P")),"") | J82: =IFERROR(STDEV(BDH($D82,$E82,SETTINGS_LOOK,"0D","Days="&SETTINGS_FREQ,"Fill=P")),"") | K82: =IFERROR(($H82-$I82)/$J82,"") | L82: 1 | M82: =IFERROR($K82*$L82,"") | N82: =IFERROR(NORMSDIST($M82),"") | O82: =IFERROR(BDP($D82,"CHG_PCT_1YR")/100,"") | P82: =IFERROR(SUMPRODUCT(($B$7:$B$106=$B82)*($M$7:$M$106>$M82))+1,"") | Q82: =COUNTIF($B$7:$B$106,$B82) | R82: =IFERROR(IF($M82>=SETTINGS_ZC,"CHEAP",IF($M82<=SETTINGS_ZR,"RICH","-")),"") | S82: Spread in bp. High spread = cheap credit. | U82: =IFERROR(SUMPRODUCT(($M$7:$M$106>$M82)*1)+1,"")
B83: CREDIT | C83: CDX IG 5y | D83: CDX IG CDSI GEN 5Y Corp | E83: PX_LAST | F83: VERIFY | G83: =IFERROR(IF(BDP($D83,"NAME")="","CHECK",BDP($D83,"NAME")),"CHECK") | H83: =IFERROR(BDP($D83,$E83),"") | I83: =IFERROR(AVERAGE(BDH($D83,$E83,SETTINGS_LOOK,"0D","Days="&SETTINGS_FREQ,"Fill=P")),"") | J83: =IFERROR(STDEV(BDH($D83,$E83,SETTINGS_LOOK,"0D","Days="&SETTINGS_FREQ,"Fill=P")),"") | K83: =IFERROR(($H83-$I83)/$J83,"") | L83: 1 | M83: =IFERROR($K83*$L83,"") | N83: =IFERROR(NORMSDIST($M83),"") | O83: =IFERROR(BDP($D83,"CHG_PCT_1YR")/100,"") | P83: =IFERROR(SUMPRODUCT(($B$7:$B$106=$B83)*($M$7:$M$106>$M83))+1,"") | Q83: =COUNTIF($B$7:$B$106,$B83) | R83: =IFERROR(IF($M83>=SETTINGS_ZC,"CHEAP",IF($M83<=SETTINGS_ZR,"RICH","-")),"") | S83: Spread in bp. High spread = cheap credit. | U83: =IFERROR(SUMPRODUCT(($M$7:$M$106>$M83)*1)+1,"")
B84: CREDIT | C84: CDX HY 5y | D84: CDX HY CDSI GEN 5Y Corp | E84: PX_LAST | F84: VERIFY | G84: =IFERROR(IF(BDP($D84,"NAME")="","CHECK",BDP($D84,"NAME")),"CHECK") | H84: =IFERROR(BDP($D84,$E84),"") | I84: =IFERROR(AVERAGE(BDH($D84,$E84,SETTINGS_LOOK,"0D","Days="&SETTINGS_FREQ,"Fill=P")),"") | J84: =IFERROR(STDEV(BDH($D84,$E84,SETTINGS_LOOK,"0D","Days="&SETTINGS_FREQ,"Fill=P")),"") | K84: =IFERROR(($H84-$I84)/$J84,"") | L84: 1 | M84: =IFERROR($K84*$L84,"") | N84: =IFERROR(NORMSDIST($M84),"") | O84: =IFERROR(BDP($D84,"CHG_PCT_1YR")/100,"") | P84: =IFERROR(SUMPRODUCT(($B$7:$B$106=$B84)*($M$7:$M$106>$M84))+1,"") | Q84: =COUNTIF($B$7:$B$106,$B84) | R84: =IFERROR(IF($M84>=SETTINGS_ZC,"CHEAP",IF($M84<=SETTINGS_ZR,"RICH","-")),"") | S84: Spread in bp. High spread = cheap credit. | U84: =IFERROR(SUMPRODUCT(($M$7:$M$106>$M84)*1)+1,"")
B85: CREDIT | C85: iTraxx Main 5y | D85: ITRX EUR CDSI GEN 5Y Corp | E85: PX_LAST | F85: VERIFY | G85: =IFERROR(IF(BDP($D85,"NAME")="","CHECK",BDP($D85,"NAME")),"CHECK") | H85: =IFERROR(BDP($D85,$E85),"") | I85: =IFERROR(AVERAGE(BDH($D85,$E85,SETTINGS_LOOK,"0D","Days="&SETTINGS_FREQ,"Fill=P")),"") | J85: =IFERROR(STDEV(BDH($D85,$E85,SETTINGS_LOOK,"0D","Days="&SETTINGS_FREQ,"Fill=P")),"") | K85: =IFERROR(($H85-$I85)/$J85,"") | L85: 1 | M85: =IFERROR($K85*$L85,"") | N85: =IFERROR(NORMSDIST($M85),"") | O85: =IFERROR(BDP($D85,"CHG_PCT_1YR")/100,"") | P85: =IFERROR(SUMPRODUCT(($B$7:$B$106=$B85)*($M$7:$M$106>$M85))+1,"") | Q85: =COUNTIF($B$7:$B$106,$B85) | R85: =IFERROR(IF($M85>=SETTINGS_ZC,"CHEAP",IF($M85<=SETTINGS_ZR,"RICH","-")),"") | S85: Spread in bp. High spread = cheap credit. | U85: =IFERROR(SUMPRODUCT(($M$7:$M$106>$M85)*1)+1,"")
B86: CREDIT | C86: iTraxx Crossover 5y | D86: ITRX XOVER CDSI GEN 5Y Corp | E86: PX_LAST | F86: VERIFY | G86: =IFERROR(IF(BDP($D86,"NAME")="","CHECK",BDP($D86,"NAME")),"CHECK") | H86: =IFERROR(BDP($D86,$E86),"") | I86: =IFERROR(AVERAGE(BDH($D86,$E86,SETTINGS_LOOK,"0D","Days="&SETTINGS_FREQ,"Fill=P")),"") | J86: =IFERROR(STDEV(BDH($D86,$E86,SETTINGS_LOOK,"0D","Days="&SETTINGS_FREQ,"Fill=P")),"") | K86: =IFERROR(($H86-$I86)/$J86,"") | L86: 1 | M86: =IFERROR($K86*$L86,"") | N86: =IFERROR(NORMSDIST($M86),"") | O86: =IFERROR(BDP($D86,"CHG_PCT_1YR")/100,"") | P86: =IFERROR(SUMPRODUCT(($B$7:$B$106=$B86)*($M$7:$M$106>$M86))+1,"") | Q86: =COUNTIF($B$7:$B$106,$B86) | R86: =IFERROR(IF($M86>=SETTINGS_ZC,"CHEAP",IF($M86<=SETTINGS_ZR,"RICH","-")),"") | S86: Spread in bp. High spread = cheap credit. | U86: =IFERROR(SUMPRODUCT(($M$7:$M$106>$M86)*1)+1,"")
B87: CREDIT | C87: Brazil 5y CDS | D87: CBRA1U5 Curncy | E87: PX_LAST | F87: VERIFY | G87: =IFERROR(IF(BDP($D87,"NAME")="","CHECK",BDP($D87,"NAME")),"CHECK") | H87: =IFERROR(BDP($D87,$E87),"") | I87: =IFERROR(AVERAGE(BDH($D87,$E87,SETTINGS_LOOK,"0D","Days="&SETTINGS_FREQ,"Fill=P")),"") | J87: =IFERROR(STDEV(BDH($D87,$E87,SETTINGS_LOOK,"0D","Days="&SETTINGS_FREQ,"Fill=P")),"") | K87: =IFERROR(($H87-$I87)/$J87,"") | L87: 1 | M87: =IFERROR($K87*$L87,"") | N87: =IFERROR(NORMSDIST($M87),"") | O87: =IFERROR(BDP($D87,"CHG_PCT_1YR")/100,"") | P87: =IFERROR(SUMPRODUCT(($B$7:$B$106=$B87)*($M$7:$M$106>$M87))+1,"") | Q87: =COUNTIF($B$7:$B$106,$B87) | R87: =IFERROR(IF($M87>=SETTINGS_ZC,"CHEAP",IF($M87<=SETTINGS_ZR,"RICH","-")),"") | S87: Spread in bp. High spread = cheap credit. | U87: =IFERROR(SUMPRODUCT(($M$7:$M$106>$M87)*1)+1,"")
B88: CREDIT | C88: Mexico 5y CDS | D88: CMEX1U5 Curncy | E88: PX_LAST | F88: VERIFY | G88: =IFERROR(IF(BDP($D88,"NAME")="","CHECK",BDP($D88,"NAME")),"CHECK") | H88: =IFERROR(BDP($D88,$E88),"") | I88: =IFERROR(AVERAGE(BDH($D88,$E88,SETTINGS_LOOK,"0D","Days="&SETTINGS_FREQ,"Fill=P")),"") | J88: =IFERROR(STDEV(BDH($D88,$E88,SETTINGS_LOOK,"0D","Days="&SETTINGS_FREQ,"Fill=P")),"") | K88: =IFERROR(($H88-$I88)/$J88,"") | L88: 1 | M88: =IFERROR($K88*$L88,"") | N88: =IFERROR(NORMSDIST($M88),"") | O88: =IFERROR(BDP($D88,"CHG_PCT_1YR")/100,"") | P88: =IFERROR(SUMPRODUCT(($B$7:$B$106=$B88)*($M$7:$M$106>$M88))+1,"") | Q88: =COUNTIF($B$7:$B$106,$B88) | R88: =IFERROR(IF($M88>=SETTINGS_ZC,"CHEAP",IF($M88<=SETTINGS_ZR,"RICH","-")),"") | S88: Spread in bp. High spread = cheap credit. | U88: =IFERROR(SUMPRODUCT(($M$7:$M$106>$M88)*1)+1,"")
... B106: COMMODITY | C106: Coffee C | D106: KC1 Comdty | E106: PX_LAST | F106: HIGH | G106: =IFERROR(IF(BDP($D106,"NAME")="","CHECK",BDP($D106,"NAME")),"CHECK") | H106: =IFERROR(BDP($D106,$E106),"") | I106: =IFERROR(AVERAGE(BDH($D106,$E106,SETTINGS_LOOK,"0D","Days="&SETTINGS_FREQ,"Fill=P")),"") | J106: =IFERROR(STDEV(BDH($D106,$E106,SETTINGS_LOOK,"0D","Days="&SETTINGS_FREQ,"Fill=P")),"") | K106: =IFERROR(($H106-$I106)/$J106,"") | L106: -1 | M106: =IFERROR($K106*$L106,"") | N106: =IFERROR(NORMSDIST($M106),"") | O106: =IFERROR(BDP($D106,"CHG_PCT_1YR")/100,"") | P106: =IFERROR(SUMPRODUCT(($B$7:$B$106=$B106)*($M$7:$M$106>$M106))+1,"") | Q106: =COUNTIF($B$7:$B$106,$B106) | R106: =IFERROR(IF($M106>=SETTINGS_ZC,"CHEAP",IF($M106<=SETTINGS_ZR,"RICH","-")),"") | S106: Front-contract price. High = expensive. | U106: =IFERROR(SUMPRODUCT(($M$7:$M$106>$M106)*1)+1,"")
A108: Rank 1 = cheapest in its asset class. The rank formula uses SUMPRODUCT rather than RANK so that it counts only instruments in the same class and produces no ties. Percentile assumes normality — it is a reading aid, not a claim about the distribution, and value-score distributions in credit and FX have fat left tails.

Sheet 03 RANKINGS
A1: CHEAPEST AND MOST EXPENSIVE — WITHIN EACH ASSET CLASS
A2: The statistically defensible comparison. Each instrument is ranked only against others measured the same way.
A4: Left = cheapest in class (highest value score). Right = most expensive. Value score is the sign-corrected z-score, so +2.0 means two standard deviations CHEAP on that asset class's own metric, whatever that metric happens to be.
A6: EQUITY — measured on Forward P/E — 24 instruments
B7: CHEAPEST | C7: Instrument | D7: Ticker | E7: Value score | F7: Z (raw) | G7: Current | H7: 1y chg | J7: MOST EXPENSIVE | K7: Instrument | L7: Ticker | M7: Value score | N7: Z (raw) | O7: Current | P7: 1y chg
B8: 1 | C8: =IFERROR(INDEX('02 MONITOR'!$C$7:$C$106,SUMPRODUCT(('02 MONITOR'!$B$7:$B$106="EQUITY")*('02 MONITOR'!$P$7:$P$106=1)*(ROW('02 MONITOR'!$B$7:$B$106)-6))),"") | D8: =IFERROR(INDEX('02 MONITOR'!$D$7:$D$106,SUMPRODUCT(('02 MONITOR'!$B$7:$B$106="EQUITY")*('02 MONITOR'!$P$7:$P$106=1)*(ROW('02 MONITOR'!$B$7:$B$106)-6))),"") | E8: =IFERROR(INDEX('02 MONITOR'!$M$7:$M$106,SUMPRODUCT(('02 MONITOR'!$B$7:$B$106="EQUITY")*('02 MONITOR'!$P$7:$P$106=1)*(ROW('02 MONITOR'!$B$7:$B$106)-6))),"") | F8: =IFERROR(INDEX('02 MONITOR'!$K$7:$K$106,SUMPRODUCT(('02 MONITOR'!$B$7:$B$106="EQUITY")*('02 MONITOR'!$P$7:$P$106=1)*(ROW('02 MONITOR'!$B$7:$B$106)-6))),"") | G8: =IFERROR(INDEX('02 MONITOR'!$H$7:$H$106,SUMPRODUCT(('02 MONITOR'!$B$7:$B$106="EQUITY")*('02 MONITOR'!$P$7:$P$106=1)*(ROW('02 MONITOR'!$B$7:$B$106)-6))),"") | H8: =IFERROR(INDEX('02 MONITOR'!$O$7:$O$106,SUMPRODUCT(('02 MONITOR'!$B$7:$B$106="EQUITY")*('02 MONITOR'!$P$7:$P$106=1)*(ROW('02 MONITOR'!$B$7:$B$106)-6))),"") | J8: 1 | K8: =IFERROR(INDEX('02 MONITOR'!$C$7:$C$106,SUMPRODUCT(('02 MONITOR'!$B$7:$B$106="EQUITY")*('02 MONITOR'!$P$7:$P$106=24)*(ROW('02 MONITOR'!$B$7:$B$106)-6))),"") | L8: =IFERROR(INDEX('02 MONITOR'!$D$7:$D$106,SUMPRODUCT(('02 MONITOR'!$B$7:$B$106="EQUITY")*('02 MONITOR'!$P$7:$P$106=24)*(ROW('02 MONITOR'!$B$7:$B$106)-6))),"") | M8: =IFERROR(INDEX('02 MONITOR'!$M$7:$M$106,SUMPRODUCT(('02 MONITOR'!$B$7:$B$106="EQUITY")*('02 MONITOR'!$P$7:$P$106=24)*(ROW('02 MONITOR'!$B$7:$B$106)-6))),"") | N8: =IFERROR(INDEX('02 MONITOR'!$K$7:$K$106,SUMPRODUCT(('02 MONITOR'!$B$7:$B$106="EQUITY")*('02 MONITOR'!$P$7:$P$106=24)*(ROW('02 MONITOR'!$B$7:$B$106)-6))),"") | O8: =IFERROR(INDEX('02 MONITOR'!$H$7:$H$106,SUMPRODUCT(('02 MONITOR'!$B$7:$B$106="EQUITY")*('02 MONITOR'!$P$7:$P$106=24)*(ROW('02 MONITOR'!$B$7:$B$106)-6))),"") | P8: =IFERROR(INDEX('02 MONITOR'!$O$7:$O$106,SUMPRODUCT(('02 MONITOR'!$B$7:$B$106="EQUITY")*('02 MONITOR'!$P$7:$P$106=24)*(ROW('02 MONITOR'!$B$7:$B$106)-6))),"")
B9: 2 | C9: =IFERROR(INDEX('02 MONITOR'!$C$7:$C$106,SUMPRODUCT(('02 MONITOR'!$B$7:$B$106="EQUITY")*('02 MONITOR'!$P$7:$P$106=2)*(ROW('02 MONITOR'!$B$7:$B$106)-6))),"") | D9: =IFERROR(INDEX('02 MONITOR'!$D$7:$D$106,SUMPRODUCT(('02 MONITOR'!$B$7:$B$106="EQUITY")*('02 MONITOR'!$P$7:$P$106=2)*(ROW('02 MONITOR'!$B$7:$B$106)-6))),"") | E9: =IFERROR(INDEX('02 MONITOR'!$M$7:$M$106,SUMPRODUCT(('02 MONITOR'!$B$7:$B$106="EQUITY")*('02 MONITOR'!$P$7:$P$106=2)*(ROW('02 MONITOR'!$B$7:$B$106)-6))),"") | F9: =IFERROR(INDEX('02 MONITOR'!$K$7:$K$106,SUMPRODUCT(('02 MONITOR'!$B$7:$B$106="EQUITY")*('02 MONITOR'!$P$7:$P$106=2)*(ROW('02 MONITOR'!$B$7:$B$106)-6))),"") | G9: =IFERROR(INDEX('02 MONITOR'!$H$7:$H$106,SUMPRODUCT(('02 MONITOR'!$B$7:$B$106="EQUITY")*('02 MONITOR'!$P$7:$P$106=2)*(ROW('02 MONITOR'!$B$7:$B$106)-6))),"") | H9: =IFERROR(INDEX('02 MONITOR'!$O$7:$O$106,SUMPRODUCT(('02 MONITOR'!$B$7:$B$106="EQUITY")*('02 MONITOR'!$P$7:$P$106=2)*(ROW('02 MONITOR'!$B$7:$B$106)-6))),"") | J9: 2 | K9: =IFERROR(INDEX('02 MONITOR'!$C$7:$C$106,SUMPRODUCT(('02 MONITOR'!$B$7:$B$106="EQUITY")*('02 MONITOR'!$P$7:$P$106=23)*(ROW('02 MONITOR'!$B$7:$B$106)-6))),"") | L9: =IFERROR(INDEX('02 MONITOR'!$D$7:$D$106,SUMPRODUCT(('02 MONITOR'!$B$7:$B$106="EQUITY")*('02 MONITOR'!$P$7:$P$106=23)*(ROW('02 MONITOR'!$B$7:$B$106)-6))),"") | M9: =IFERROR(INDEX('02 MONITOR'!$M$7:$M$106,SUMPRODUCT(('02 MONITOR'!$B$7:$B$106="EQUITY")*('02 MONITOR'!$P$7:$P$106=23)*(ROW('02 MONITOR'!$B$7:$B$106)-6))),"") | N9: =IFERROR(INDEX('02 MONITOR'!$K$7:$K$106,SUMPRODUCT(('02 MONITOR'!$B$7:$B$106="EQUITY")*('02 MONITOR'!$P$7:$P$106=23)*(ROW('02 MONITOR'!$B$7:$B$106)-6))),"") | O9: =IFERROR(INDEX('02 MONITOR'!$H$7:$H$106,SUMPRODUCT(('02 MONITOR'!$B$7:$B$106="EQUITY")*('02 MONITOR'!$P$7:$P$106=23)*(ROW('02 MONITOR'!$B$7:$B$106)-6))),"") | P9: =IFERROR(INDEX('02 MONITOR'!$O$7:$O$106,SUMPRODUCT(('02 MONITOR'!$B$7:$B$106="EQUITY")*('02 MONITOR'!$P$7:$P$106=23)*(ROW('02 MONITOR'!$B$7:$B$106)-6))),"")
B10: 3 | C10: =IFERROR(INDEX('02 MONITOR'!$C$7:$C$106,SUMPRODUCT(('02 MONITOR'!$B$7:$B$106="EQUITY")*('02 MONITOR'!$P$7:$P$106=3)*(ROW('02 MONITOR'!$B$7:$B$106)-6))),"") | D10: =IFERROR(INDEX('02 MONITOR'!$D$7:$D$106,SUMPRODUCT(('02 MONITOR'!$B$7:$B$106="EQUITY")*('02 MONITOR'!$P$7:$P$106=3)*(ROW('02 MONITOR'!$B$7:$B$106)-6))),"") | E10: =IFERROR(INDEX('02 MONITOR'!$M$7:$M$106,SUMPRODUCT(('02 MONITOR'!$B$7:$B$106="EQUITY")*('02 MONITOR'!$P$7:$P$106=3)*(ROW('02 MONITOR'!$B$7:$B$106)-6))),"") | F10: =IFERROR(INDEX('02 MONITOR'!$K$7:$K$106,SUMPRODUCT(('02 MONITOR'!$B$7:$B$106="EQUITY")*('02 MONITOR'!$P$7:$P$106=3)*(ROW('02 MONITOR'!$B$7:$B$106)-6))),"") | G10: =IFERROR(INDEX('02 MONITOR'!$H$7:$H$106,SUMPRODUCT(('02 MONITOR'!$B$7:$B$106="EQUITY")*('02 MONITOR'!$P$7:$P$106=3)*(ROW('02 MONITOR'!$B$7:$B$106)-6))),"") | H10: =IFERROR(INDEX('02 MONITOR'!$O$7:$O$106,SUMPRODUCT(('02 MONITOR'!$B$7:$B$106="EQUITY")*('02 MONITOR'!$P$7:$P$106=3)*(ROW('02 MONITOR'!$B$7:$B$106)-6))),"") | J10: 3 | K10: =IFERROR(INDEX('02 MONITOR'!$C$7:$C$106,SUMPRODUCT(('02 MONITOR'!$B$7:$B$106="EQUITY")*('02 MONITOR'!$P$7:$P$106=22)*(ROW('02 MONITOR'!$B$7:$B$106)-6))),"") | L10: =IFERROR(INDEX('02 MONITOR'!$D$7:$D$106,SUMPRODUCT(('02 MONITOR'!$B$7:$B$106="EQUITY")*('02 MONITOR'!$P$7:$P$106=22)*(ROW('02 MONITOR'!$B$7:$B$106)-6))),"") | M10: =IFERROR(INDEX('02 MONITOR'!$M$7:$M$106,SUMPRODUCT(('02 MONITOR'!$B$7:$B$106="EQUITY")*('02 MONITOR'!$P$7:$P$106=22)*(ROW('02 MONITOR'!$B$7:$B$106)-6))),"") | N10: =IFERROR(INDEX('02 MONITOR'!$K$7:$K$106,SUMPRODUCT(('02 MONITOR'!$B$7:$B$106="EQUITY")*('02 MONITOR'!$P$7:$P$106=22)*(ROW('02 MONITOR'!$B$7:$B$106)-6))),"") | O10: =IFERROR(INDEX('02 MONITOR'!$H$7:$H$106,SUMPRODUCT(('02 MONITOR'!$B$7:$B$106="EQUITY")*('02 MONITOR'!$P$7:$P$106=22)*(ROW('02 MONITOR'!$B$7:$B$106)-6))),"") | P10: =IFERROR(INDEX('02 MONITOR'!$O$7:$O$106,SUMPRODUCT(('02 MONITOR'!$B$7:$B$106="EQUITY")*('02 MONITOR'!$P$7:$P$106=22)*(ROW('02 MONITOR'!$B$7:$B$106)-6))),"")
B11: 4 | C11: =IFERROR(INDEX('02 MONITOR'!$C$7:$C$106,SUMPRODUCT(('02 MONITOR'!$B$7:$B$106="EQUITY")*('02 MONITOR'!$P$7:$P$106=4)*(ROW('02 MONITOR'!$B$7:$B$106)-6))),"") | D11: =IFERROR(INDEX('02 MONITOR'!$D$7:$D$106,SUMPRODUCT(('02 MONITOR'!$B$7:$B$106="EQUITY")*('02 MONITOR'!$P$7:$P$106=4)*(ROW('02 MONITOR'!$B$7:$B$106)-6))),"") | E11: =IFERROR(INDEX('02 MONITOR'!$M$7:$M$106,SUMPRODUCT(('02 MONITOR'!$B$7:$B$106="EQUITY")*('02 MONITOR'!$P$7:$P$106=4)*(ROW('02 MONITOR'!$B$7:$B$106)-6))),"") | F11: =IFERROR(INDEX('02 MONITOR'!$K$7:$K$106,SUMPRODUCT(('02 MONITOR'!$B$7:$B$106="EQUITY")*('02 MONITOR'!$P$7:$P$106=4)*(ROW('02 MONITOR'!$B$7:$B$106)-6))),"") | G11: =IFERROR(INDEX('02 MONITOR'!$H$7:$H$106,SUMPRODUCT(('02 MONITOR'!$B$7:$B$106="EQUITY")*('02 MONITOR'!$P$7:$P$106=4)*(ROW('02 MONITOR'!$B$7:$B$106)-6))),"") | H11: =IFERROR(INDEX('02 MONITOR'!$O$7:$O$106,SUMPRODUCT(('02 MONITOR'!$B$7:$B$106="EQUITY")*('02 MONITOR'!$P$7:$P$106=4)*(ROW('02 MONITOR'!$B$7:$B$106)-6))),"") | J11: 4 | K11: =IFERROR(INDEX('02 MONITOR'!$C$7:$C$106,SUMPRODUCT(('02 MONITOR'!$B$7:$B$106="EQUITY")*('02 MONITOR'!$P$7:$P$106=21)*(ROW('02 MONITOR'!$B$7:$B$106)-6))),"") | L11: =IFERROR(INDEX('02 MONITOR'!$D$7:$D$106,SUMPRODUCT(('02 MONITOR'!$B$7:$B$106="EQUITY")*('02 MONITOR'!$P$7:$P$106=21)*(ROW('02 MONITOR'!$B$7:$B$106)-6))),"") | M11: =IFERROR(INDEX('02 MONITOR'!$M$7:$M$106,SUMPRODUCT(('02 MONITOR'!$B$7:$B$106="EQUITY")*('02 MONITOR'!$P$7:$P$106=21)*(ROW('02 MONITOR'!$B$7:$B$106)-6))),"") | N11: =IFERROR(INDEX('02 MONITOR'!$K$7:$K$106,SUMPRODUCT(('02 MONITOR'!$B$7:$B$106="EQUITY")*('02 MONITOR'!$P$7:$P$106=21)*(ROW('02 MONITOR'!$B$7:$B$106)-6))),"") | O11: =IFERROR(INDEX('02 MONITOR'!$H$7:$H$106,SUMPRODUCT(('02 MONITOR'!$B$7:$B$106="EQUITY")*('02 MONITOR'!$P$7:$P$106=21)*(ROW('02 MONITOR'!$B$7:$B$106)-6))),"") | P11: =IFERROR(INDEX('02 MONITOR'!$O$7:$O$106,SUMPRODUCT(('02 MONITOR'!$B$7:$B$106="EQUITY")*('02 MONITOR'!$P$7:$P$106=21)*(ROW('02 MONITOR'!$B$7:$B$106)-6))),"")
B12: 5 | C12: =IFERROR(INDEX('02 MONITOR'!$C$7:$C$106,SUMPRODUCT(('02 MONITOR'!$B$7:$B$106="EQUITY")*('02 MONITOR'!$P$7:$P$106=5)*(ROW('02 MONITOR'!$B$7:$B$106)-6))),"") | D12: =IFERROR(INDEX('02 MONITOR'!$D$7:$D$106,SUMPRODUCT(('02 MONITOR'!$B$7:$B$106="EQUITY")*('02 MONITOR'!$P$7:$P$106=5)*(ROW('02 MONITOR'!$B$7:$B$106)-6))),"") | E12: =IFERROR(INDEX('02 MONITOR'!$M$7:$M$106,SUMPRODUCT(('02 MONITOR'!$B$7:$B$106="EQUITY")*('02 MONITOR'!$P$7:$P$106=5)*(ROW('02 MONITOR'!$B$7:$B$106)-6))),"") | F12: =IFERROR(INDEX('02 MONITOR'!$K$7:$K$106,SUMPRODUCT(('02 MONITOR'!$B$7:$B$106="EQUITY")*('02 MONITOR'!$P$7:$P$106=5)*(ROW('02 MONITOR'!$B$7:$B$106)-6))),"") | G12: =IFERROR(INDEX('02 MONITOR'!$H$7:$H$106,SUMPRODUCT(('02 MONITOR'!$B$7:$B$106="EQUITY")*('02 MONITOR'!$P$7:$P$106=5)*(ROW('02 MONITOR'!$B$7:$B$106)-6))),"") | H12: =IFERROR(INDEX('02 MONITOR'!$O$7:$O$106,SUMPRODUCT(('02 MONITOR'!$B$7:$B$106="EQUITY")*('02 MONITOR'!$P$7:$P$106=5)*(ROW('02 MONITOR'!$B$7:$B$106)-6))),"") | J12: 5 | K12: =IFERROR(INDEX('02 MONITOR'!$C$7:$C$106,SUMPRODUCT(('02 MONITOR'!$B$7:$B$106="EQUITY")*('02 MONITOR'!$P$7:$P$106=20)*(ROW('02 MONITOR'!$B$7:$B$106)-6))),"") | L12: =IFERROR(INDEX('02 MONITOR'!$D$7:$D$106,SUMPRODUCT(('02 MONITOR'!$B$7:$B$106="EQUITY")*('02 MONITOR'!$P$7:$P$106=20)*(ROW('02 MONITOR'!$B$7:$B$106)-6))),"") | M12: =IFERROR(INDEX('02 MONITOR'!$M$7:$M$106,SUMPRODUCT(('02 MONITOR'!$B$7:$B$106="EQUITY")*('02 MONITOR'!$P$7:$P$106=20)*(ROW('02 MONITOR'!$B$7:$B$106)-6))),"") | N12: =IFERROR(INDEX('02 MONITOR'!$K$7:$K$106,SUMPRODUCT(('02 MONITOR'!$B$7:$B$106="EQUITY")*('02 MONITOR'!$P$7:$P$106=20)*(ROW('02 MONITOR'!$B$7:$B$106)-6))),"") | O12: =IFERROR(INDEX('02 MONITOR'!$H$7:$H$106,SUMPRODUCT(('02 MONITOR'!$B$7:$B$106="EQUITY")*('02 MONITOR'!$P$7:$P$106=20)*(ROW('02 MONITOR'!$B$7:$B$106)-6))),"") | P12: =IFERROR(INDEX('02 MONITOR'!$O$7:$O$106,SUMPRODUCT(('02 MONITOR'!$B$7:$B$106="EQUITY")*('02 MONITOR'!$P$7:$P$106=20)*(ROW('02 MONITOR'!$B$7:$B$106)-6))),"")
B13: 6 | C13: =IFERROR(INDEX('02 MONITOR'!$C$7:$C$106,SUMPRODUCT(('02 MONITOR'!$B$7:$B$106="EQUITY")*('02 MONITOR'!$P$7:$P$106=6)*(ROW('02 MONITOR'!$B$7:$B$106)-6))),"") | D13: =IFERROR(INDEX('02 MONITOR'!$D$7:$D$106,SUMPRODUCT(('02 MONITOR'!$B$7:$B$106="EQUITY")*('02 MONITOR'!$P$7:$P$106=6)*(ROW('02 MONITOR'!$B$7:$B$106)-6))),"") | E13: =IFERROR(INDEX('02 MONITOR'!$M$7:$M$106,SUMPRODUCT(('02 MONITOR'!$B$7:$B$106="EQUITY")*('02 MONITOR'!$P$7:$P$106=6)*(ROW('02 MONITOR'!$B$7:$B$106)-6))),"") | F13: =IFERROR(INDEX('02 MONITOR'!$K$7:$K$106,SUMPRODUCT(('02 MONITOR'!$B$7:$B$106="EQUITY")*('02 MONITOR'!$P$7:$P$106=6)*(ROW('02 MONITOR'!$B$7:$B$106)-6))),"") | G13: =IFERROR(INDEX('02 MONITOR'!$H$7:$H$106,SUMPRODUCT(('02 MONITOR'!$B$7:$B$106="EQUITY")*('02 MONITOR'!$P$7:$P$106=6)*(ROW('02 MONITOR'!$B$7:$B$106)-6))),"") | H13: =IFERROR(INDEX('02 MONITOR'!$O$7:$O$106,SUMPRODUCT(('02 MONITOR'!$B$7:$B$106="EQUITY")*('02 MONITOR'!$P$7:$P$106=6)*(ROW('02 MONITOR'!$B$7:$B$106)-6))),"") | J13: 6 | K13: =IFERROR(INDEX('02 MONITOR'!$C$7:$C$106,SUMPRODUCT(('02 MONITOR'!$B$7:$B$106="EQUITY")*('02 MONITOR'!$P$7:$P$106=19)*(ROW('02 MONITOR'!$B$7:$B$106)-6))),"") | L13: =IFERROR(INDEX('02 MONITOR'!$D$7:$D$106,SUMPRODUCT(('02 MONITOR'!$B$7:$B$106="EQUITY")*('02 MONITOR'!$P$7:$P$106=19)*(ROW('02 MONITOR'!$B$7:$B$106)-6))),"") | M13: =IFERROR(INDEX('02 MONITOR'!$M$7:$M$106,SUMPRODUCT(('02 MONITOR'!$B$7:$B$106="EQUITY")*('02 MONITOR'!$P$7:$P$106=19)*(ROW('02 MONITOR'!$B$7:$B$106)-6))),"") | N13: =IFERROR(INDEX('02 MONITOR'!$K$7:$K$106,SUMPRODUCT(('02 MONITOR'!$B$7:$B$106="EQUITY")*('02 MONITOR'!$P$7:$P$106=19)*(ROW('02 MONITOR'!$B$7:$B$106)-6))),"") | O13: =IFERROR(INDEX('02 MONITOR'!$H$7:$H$106,SUMPRODUCT(('02 MONITOR'!$B$7:$B$106="EQUITY")*('02 MONITOR'!$P$7:$P$106=19)*(ROW('02 MONITOR'!$B$7:$B$106)-6))),"") | P13: =IFERROR(INDEX('02 MONITOR'!$O$7:$O$106,SUMPRODUCT(('02 MONITOR'!$B$7:$B$106="EQUITY")*('02 MONITOR'!$P$7:$P$106=19)*(ROW('02 MONITOR'!$B$7:$B$106)-6))),"")
A15: RATES — measured on 10y nominal yield — 20 instruments
B16: CHEAPEST | C16: Instrument | D16: Ticker | E16: Value score | F16: Z (raw) | G16: Current | H16: 1y chg | J16: MOST EXPENSIVE | K16: Instrument | L16: Ticker | M16: Value score | N16: Z (raw) | O16: Current | P16: 1y chg
B17: 1 | C17: =IFERROR(INDEX('02 MONITOR'!$C$7:$C$106,SUMPRODUCT(('02 MONITOR'!$B$7:$B$106="RATES")*('02 MONITOR'!$P$7:$P$106=1)*(ROW('02 MONITOR'!$B$7:$B$106)-6))),"") | D17: =IFERROR(INDEX('02 MONITOR'!$D$7:$D$106,SUMPRODUCT(('02 MONITOR'!$B$7:$B$106="RATES")*('02 MONITOR'!$P$7:$P$106=1)*(ROW('02 MONITOR'!$B$7:$B$106)-6))),"") | E17: =IFERROR(INDEX('02 MONITOR'!$M$7:$M$106,SUMPRODUCT(('02 MONITOR'!$B$7:$B$106="RATES")*('02 MONITOR'!$P$7:$P$106=1)*(ROW('02 MONITOR'!$B$7:$B$106)-6))),"") | F17: =IFERROR(INDEX('02 MONITOR'!$K$7:$K$106,SUMPRODUCT(('02 MONITOR'!$B$7:$B$106="RATES")*('02 MONITOR'!$P$7:$P$106=1)*(ROW('02 MONITOR'!$B$7:$B$106)-6))),"") | G17: =IFERROR(INDEX('02 MONITOR'!$H$7:$H$106,SUMPRODUCT(('02 MONITOR'!$B$7:$B$106="RATES")*('02 MONITOR'!$P$7:$P$106=1)*(ROW('02 MONITOR'!$B$7:$B$106)-6))),"") | H17: =IFERROR(INDEX('02 MONITOR'!$O$7:$O$106,SUMPRODUCT(('02 MONITOR'!$B$7:$B$106="RATES")*('02 MONITOR'!$P$7:$P$106=1)*(ROW('02 MONITOR'!$B$7:$B$106)-6))),"") | J17: 1 | K17: =IFERROR(INDEX('02 MONITOR'!$C$7:$C$106,SUMPRODUCT(('02 MONITOR'!$B$7:$B$106="RATES")*('02 MONITOR'!$P$7:$P$106=20)*(ROW('02 MONITOR'!$B$7:$B$106)-6))),"") | L17: =IFERROR(INDEX('02 MONITOR'!$D$7:$D$106,SUMPRODUCT(('02 MONITOR'!$B$7:$B$106="RATES")*('02 MONITOR'!$P$7:$P$106=20)*(ROW('02 MONITOR'!$B$7:$B$106)-6))),"") | M17: =IFERROR(INDEX('02 MONITOR'!$M$7:$M$106,SUMPRODUCT(('02 MONITOR'!$B$7:$B$106="RATES")*('02 MONITOR'!$P$7:$P$106=20)*(ROW('02 MONITOR'!$B$7:$B$106)-6))),"") | N17: =IFERROR(INDEX('02 MONITOR'!$K$7:$K$106,SUMPRODUCT(('02 MONITOR'!$B$7:$B$106="RATES")*('02 MONITOR'!$P$7:$P$106=20)*(ROW('02 MONITOR'!$B$7:$B$106)-6))),"") | O17: =IFERROR(INDEX('02 MONITOR'!$H$7:$H$106,SUMPRODUCT(('02 MONITOR'!$B$7:$B$106="RATES")*('02 MONITOR'!$P$7:$P$106=20)*(ROW('02 MONITOR'!$B$7:$B$106)-6))),"") | P17: =IFERROR(INDEX('02 MONITOR'!$O$7:$O$106,SUMPRODUCT(('02 MONITOR'!$B$7:$B$106="RATES")*('02 MONITOR'!$P$7:$P$106=20)*(ROW('02 MONITOR'!$B$7:$B$106)-6))),"")
B18: 2 | C18: =IFERROR(INDEX('02 MONITOR'!$C$7:$C$106,SUMPRODUCT(('02 MONITOR'!$B$7:$B$106="RATES")*('02 MONITOR'!$P$7:$P$106=2)*(ROW('02 MONITOR'!$B$7:$B$106)-6))),"") | D18: =IFERROR(INDEX('02 MONITOR'!$D$7:$D$106,SUMPRODUCT(('02 MONITOR'!$B$7:$B$106="RATES")*('02 MONITOR'!$P$7:$P$106=2)*(ROW('02 MONITOR'!$B$7:$B$106)-6))),"") | E18: =IFERROR(INDEX('02 MONITOR'!$M$7:$M$106,SUMPRODUCT(('02 MONITOR'!$B$7:$B$106="RATES")*('02 MONITOR'!$P$7:$P$106=2)*(ROW('02 MONITOR'!$B$7:$B$106)-6))),"") | F18: =IFERROR(INDEX('02 MONITOR'!$K$7:$K$106,SUMPRODUCT(('02 MONITOR'!$B$7:$B$106="RATES")*('02 MONITOR'!$P$7:$P$106=2)*(ROW('02 MONITOR'!$B$7:$B$106)-6))),"") | G18: =IFERROR(INDEX('02 MONITOR'!$H$7:$H$106,SUMPRODUCT(('02 MONITOR'!$B$7:$B$106="RATES")*('02 MONITOR'!$P$7:$P$106=2)*(ROW('02 MONITOR'!$B$7:$B$106)-6))),"") | H18: =IFERROR(INDEX('02 MONITOR'!$O$7:$O$106,SUMPRODUCT(('02 MONITOR'!$B$7:$B$106="RATES")*('02 MONITOR'!$P$7:$P$106=2)*(ROW('02 MONITOR'!$B$7:$B$106)-6))),"") | J18: 2 | K18: =IFERROR(INDEX('02 MONITOR'!$C$7:$C$106,SUMPRODUCT(('02 MONITOR'!$B$7:$B$106="RATES")*('02 MONITOR'!$P$7:$P$106=19)*(ROW('02 MONITOR'!$B$7:$B$106)-6))),"") | L18: =IFERROR(INDEX('02 MONITOR'!$D$7:$D$106,SUMPRODUCT(('02 MONITOR'!$B$7:$B$106="RATES")*('02 MONITOR'!$P$7:$P$106=19)*(ROW('02 MONITOR'!$B$7:$B$106)-6))),"") | M18: =IFERROR(INDEX('02 MONITOR'!$M$7:$M$106,SUMPRODUCT(('02 MONITOR'!$B$7:$B$106="RATES")*('02 MONITOR'!$P$7:$P$106=19)*(ROW('02 MONITOR'!$B$7:$B$106)-6))),"") | N18: =IFERROR(INDEX('02 MONITOR'!$K$7:$K$106,SUMPRODUCT(('02 MONITOR'!$B$7:$B$106="RATES")*('02 MONITOR'!$P$7:$P$106=19)*(ROW('02 MONITOR'!$B$7:$B$106)-6))),"") | O18: =IFERROR(INDEX('02 MONITOR'!$H$7:$H$106,SUMPRODUCT(('02 MONITOR'!$B$7:$B$106="RATES")*('02 MONITOR'!$P$7:$P$106=19)*(ROW('02 MONITOR'!$B$7:$B$106)-6))),"") | P18: =IFERROR(INDEX('02 MONITOR'!$O$7:$O$106,SUMPRODUCT(('02 MONITOR'!$B$7:$B$106="RATES")*('02 MONITOR'!$P$7:$P$106=19)*(ROW('02 MONITOR'!$B$7:$B$106)-6))),"")
B19: 3 | C19: =IFERROR(INDEX('02 MONITOR'!$C$7:$C$106,SUMPRODUCT(('02 MONITOR'!$B$7:$B$106="RATES")*('02 MONITOR'!$P$7:$P$106=3)*(ROW('02 MONITOR'!$B$7:$B$106)-6))),"") | D19: =IFERROR(INDEX('02 MONITOR'!$D$7:$D$106,SUMPRODUCT(('02 MONITOR'!$B$7:$B$106="RATES")*('02 MONITOR'!$P$7:$P$106=3)*(ROW('02 MONITOR'!$B$7:$B$106)-6))),"") | E19: =IFERROR(INDEX('02 MONITOR'!$M$7:$M$106,SUMPRODUCT(('02 MONITOR'!$B$7:$B$106="RATES")*('02 MONITOR'!$P$7:$P$106=3)*(ROW('02 MONITOR'!$B$7:$B$106)-6))),"") | F19: =IFERROR(INDEX('02 MONITOR'!$K$7:$K$106,SUMPRODUCT(('02 MONITOR'!$B$7:$B$106="RATES")*('02 MONITOR'!$P$7:$P$106=3)*(ROW('02 MONITOR'!$B$7:$B$106)-6))),"") | G19: =IFERROR(INDEX('02 MONITOR'!$H$7:$H$106,SUMPRODUCT(('02 MONITOR'!$B$7:$B$106="RATES")*('02 MONITOR'!$P$7:$P$106=3)*(ROW('02 MONITOR'!$B$7:$B$106)-6))),"") | H19: =IFERROR(INDEX('02 MONITOR'!$O$7:$O$106,SUMPRODUCT(('02 MONITOR'!$B$7:$B$106="RATES")*('02 MONITOR'!$P$7:$P$106=3)*(ROW('02 MONITOR'!$B$7:$B$106)-6))),"") | J19: 3 | K19: =IFERROR(INDEX('02 MONITOR'!$C$7:$C$106,SUMPRODUCT(('02 MONITOR'!$B$7:$B$106="RATES")*('02 MONITOR'!$P$7:$P$106=18)*(ROW('02 MONITOR'!$B$7:$B$106)-6))),"") | L19: =IFERROR(INDEX('02 MONITOR'!$D$7:$D$106,SUMPRODUCT(('02 MONITOR'!$B$7:$B$106="RATES")*('02 MONITOR'!$P$7:$P$106=18)*(ROW('02 MONITOR'!$B$7:$B$106)-6))),"") | M19: =IFERROR(INDEX('02 MONITOR'!$M$7:$M$106,SUMPRODUCT(('02 MONITOR'!$B$7:$B$106="RATES")*('02 MONITOR'!$P$7:$P$106=18)*(ROW('02 MONITOR'!$B$7:$B$106)-6))),"") | N19: =IFERROR(INDEX('02 MONITOR'!$K$7:$K$106,SUMPRODUCT(('02 MONITOR'!$B$7:$B$106="RATES")*('02 MONITOR'!$P$7:$P$106=18)*(ROW('02 MONITOR'!$B$7:$B$106)-6))),"") | O19: =IFERROR(INDEX('02 MONITOR'!$H$7:$H$106,SUMPRODUCT(('02 MONITOR'!$B$7:$B$106="RATES")*('02 MONITOR'!$P$7:$P$106=18)*(ROW('02 MONITOR'!$B$7:$B$106)-6))),"") | P19: =IFERROR(INDEX('02 MONITOR'!$O$7:$O$106,SUMPRODUCT(('02 MONITOR'!$B$7:$B$106="RATES")*('02 MONITOR'!$P$7:$P$106=18)*(ROW('02 MONITOR'!$B$7:$B$106)-6))),"")
B20: 4 | C20: =IFERROR(INDEX('02 MONITOR'!$C$7:$C$106,SUMPRODUCT(('02 MONITOR'!$B$7:$B$106="RATES")*('02 MONITOR'!$P$7:$P$106=4)*(ROW('02 MONITOR'!$B$7:$B$106)-6))),"") | D20: =IFERROR(INDEX('02 MONITOR'!$D$7:$D$106,SUMPRODUCT(('02 MONITOR'!$B$7:$B$106="RATES")*('02 MONITOR'!$P$7:$P$106=4)*(ROW('02 MONITOR'!$B$7:$B$106)-6))),"") | E20: =IFERROR(INDEX('02 MONITOR'!$M$7:$M$106,SUMPRODUCT(('02 MONITOR'!$B$7:$B$106="RATES")*('02 MONITOR'!$P$7:$P$106=4)*(ROW('02 MONITOR'!$B$7:$B$106)-6))),"") | F20: =IFERROR(INDEX('02 MONITOR'!$K$7:$K$106,SUMPRODUCT(('02 MONITOR'!$B$7:$B$106="RATES")*('02 MONITOR'!$P$7:$P$106=4)*(ROW('02 MONITOR'!$B$7:$B$106)-6))),"") | G20: =IFERROR(INDEX('02 MONITOR'!$H$7:$H$106,SUMPRODUCT(('02 MONITOR'!$B$7:$B$106="RATES")*('02 MONITOR'!$P$7:$P$106=4)*(ROW('02 MONITOR'!$B$7:$B$106)-6))),"") | H20: =IFERROR(INDEX('02 MONITOR'!$O$7:$O$106,SUMPRODUCT(('02 MONITOR'!$B$7:$B$106="RATES")*('02 MONITOR'!$P$7:$P$106=4)*(ROW('02 MONITOR'!$B$7:$B$106)-6))),"") | J20: 4 | K20: =IFERROR(INDEX('02 MONITOR'!$C$7:$C$106,SUMPRODUCT(('02 MONITOR'!$B$7:$B$106="RATES")*('02 MONITOR'!$P$7:$P$106=17)*(ROW('02 MONITOR'!$B$7:$B$106)-6))),"") | L20: =IFERROR(INDEX('02 MONITOR'!$D$7:$D$106,SUMPRODUCT(('02 MONITOR'!$B$7:$B$106="RATES")*('02 MONITOR'!$P$7:$P$106=17)*(ROW('02 MONITOR'!$B$7:$B$106)-6))),"") | M20: =IFERROR(INDEX('02 MONITOR'!$M$7:$M$106,SUMPRODUCT(('02 MONITOR'!$B$7:$B$106="RATES")*('02 MONITOR'!$P$7:$P$106=17)*(ROW('02 MONITOR'!$B$7:$B$106)-6))),"") | N20: =IFERROR(INDEX('02 MONITOR'!$K$7:$K$106,SUMPRODUCT(('02 MONITOR'!$B$7:$B$106="RATES")*('02 MONITOR'!$P$7:$P$106=17)*(ROW('02 MONITOR'!$B$7:$B$106)-6))),"") | O20: =IFERROR(INDEX('02 MONITOR'!$H$7:$H$106,SUMPRODUCT(('02 MONITOR'!$B$7:$B$106="RATES")*('02 MONITOR'!$P$7:$P$106=17)*(ROW('02 MONITOR'!$B$7:$B$106)-6))),"") | P20: =IFERROR(INDEX('02 MONITOR'!$O$7:$O$106,SUMPRODUCT(('02 MONITOR'!$B$7:$B$106="RATES")*('02 MONITOR'!$P$7:$P$106=17)*(ROW('02 MONITOR'!$B$7:$B$106)-6))),"")
B21: 5 | C21: =IFERROR(INDEX('02 MONITOR'!$C$7:$C$106,SUMPRODUCT(('02 MONITOR'!$B$7:$B$106="RATES")*('02 MONITOR'!$P$7:$P$106=5)*(ROW('02 MONITOR'!$B$7:$B$106)-6))),"") | D21: =IFERROR(INDEX('02 MONITOR'!$D$7:$D$106,SUMPRODUCT(('02 MONITOR'!$B$7:$B$106="RATES")*('02 MONITOR'!$P$7:$P$106=5)*(ROW('02 MONITOR'!$B$7:$B$106)-6))),"") | E21: =IFERROR(INDEX('02 MONITOR'!$M$7:$M$106,SUMPRODUCT(('02 MONITOR'!$B$7:$B$106="RATES")*('02 MONITOR'!$P$7:$P$106=5)*(ROW('02 MONITOR'!$B$7:$B$106)-6))),"") | F21: =IFERROR(INDEX('02 MONITOR'!$K$7:$K$106,SUMPRODUCT(('02 MONITOR'!$B$7:$B$106="RATES")*('02 MONITOR'!$P$7:$P$106=5)*(ROW('02 MONITOR'!$B$7:$B$106)-6))),"") | G21: =IFERROR(INDEX('02 MONITOR'!$H$7:$H$106,SUMPRODUCT(('02 MONITOR'!$B$7:$B$106="RATES")*('02 MONITOR'!$P$7:$P$106=5)*(ROW('02 MONITOR'!$B$7:$B$106)-6))),"") | H21: =IFERROR(INDEX('02 MONITOR'!$O$7:$O$106,SUMPRODUCT(('02 MONITOR'!$B$7:$B$106="RATES")*('02 MONITOR'!$P$7:$P$106=5)*(ROW('02 MONITOR'!$B$7:$B$106)-6))),"") | J21: 5 | K21: =IFERROR(INDEX('02 MONITOR'!$C$7:$C$106,SUMPRODUCT(('02 MONITOR'!$B$7:$B$106="RATES")*('02 MONITOR'!$P$7:$P$106=16)*(ROW('02 MONITOR'!$B$7:$B$106)-6))),"") | L21: =IFERROR(INDEX('02 MONITOR'!$D$7:$D$106,SUMPRODUCT(('02 MONITOR'!$B$7:$B$106="RATES")*('02 MONITOR'!$P$7:$P$106=16)*(ROW('02 MONITOR'!$B$7:$B$106)-6))),"") | M21: =IFERROR(INDEX('02 MONITOR'!$M$7:$M$106,SUMPRODUCT(('02 MONITOR'!$B$7:$B$106="RATES")*('02 MONITOR'!$P$7:$P$106=16)*(ROW('02 MONITOR'!$B$7:$B$106)-6))),"") | N21: =IFERROR(INDEX('02 MONITOR'!$K$7:$K$106,SUMPRODUCT(('02 MONITOR'!$B$7:$B$106="RATES")*('02 MONITOR'!$P$7:$P$106=16)*(ROW('02 MONITOR'!$B$7:$B$106)-6))),"") | O21: =IFERROR(INDEX('02 MONITOR'!$H$7:$H$106,SUMPRODUCT(('02 MONITOR'!$B$7:$B$106="RATES")*('02 MONITOR'!$P$7:$P$106=16)*(ROW('02 MONITOR'!$B$7:$B$106)-6))),"") | P21: =IFERROR(INDEX('02 MONITOR'!$O$7:$O$106,SUMPRODUCT(('02 MONITOR'!$B$7:$B$106="RATES")*('02 MONITOR'!$P$7:$P$106=16)*(ROW('02 MONITOR'!$B$7:$B$106)-6))),"")
B22: 6 | C22: =IFERROR(INDEX('02 MONITOR'!$C$7:$C$106,SUMPRODUCT(('02 MONITOR'!$B$7:$B$106="RATES")*('02 MONITOR'!$P$7:$P$106=6)*(ROW('02 MONITOR'!$B$7:$B$106)-6))),"") | D22: =IFERROR(INDEX('02 MONITOR'!$D$7:$D$106,SUMPRODUCT(('02 MONITOR'!$B$7:$B$106="RATES")*('02 MONITOR'!$P$7:$P$106=6)*(ROW('02 MONITOR'!$B$7:$B$106)-6))),"") | E22: =IFERROR(INDEX('02 MONITOR'!$M$7:$M$106,SUMPRODUCT(('02 MONITOR'!$B$7:$B$106="RATES")*('02 MONITOR'!$P$7:$P$106=6)*(ROW('02 MONITOR'!$B$7:$B$106)-6))),"") | F22: =IFERROR(INDEX('02 MONITOR'!$K$7:$K$106,SUMPRODUCT(('02 MONITOR'!$B$7:$B$106="RATES")*('02 MONITOR'!$P$7:$P$106=6)*(ROW('02 MONITOR'!$B$7:$B$106)-6))),"") | G22: =IFERROR(INDEX('02 MONITOR'!$H$7:$H$106,SUMPRODUCT(('02 MONITOR'!$B$7:$B$106="RATES")*('02 MONITOR'!$P$7:$P$106=6)*(ROW('02 MONITOR'!$B$7:$B$106)-6))),"") | H22: =IFERROR(INDEX('02 MONITOR'!$O$7:$O$106,SUMPRODUCT(('02 MONITOR'!$B$7:$B$106="RATES")*('02 MONITOR'!$P$7:$P$106=6)*(ROW('02 MONITOR'!$B$7:$B$106)-6))),"") | J22: 6 | K22: =IFERROR(INDEX('02 MONITOR'!$C$7:$C$106,SUMPRODUCT(('02 MONITOR'!$B$7:$B$106="RATES")*('02 MONITOR'!$P$7:$P$106=15)*(ROW('02 MONITOR'!$B$7:$B$106)-6))),"") | L22: =IFERROR(INDEX('02 MONITOR'!$D$7:$D$106,SUMPRODUCT(('02 MONITOR'!$B$7:$B$106="RATES")*('02 MONITOR'!$P$7:$P$106=15)*(ROW('02 MONITOR'!$B$7:$B$106)-6))),"") | M22: =IFERROR(INDEX('02 MONITOR'!$M$7:$M$106,SUMPRODUCT(('02 MONITOR'!$B$7:$B$106="RATES")*('02 MONITOR'!$P$7:$P$106=15)*(ROW('02 MONITOR'!$B$7:$B$106)-6))),"") | N22: =IFERROR(INDEX('02 MONITOR'!$K$7:$K$106,SUMPRODUCT(('02 MONITOR'!$B$7:$B$106="RATES")*('02 MONITOR'!$P$7:$P$106=15)*(ROW('02 MONITOR'!$B$7:$B$106)-6))),"") | O22: =IFERROR(INDEX('02 MONITOR'!$H$7:$H$106,SUMPRODUCT(('02 MONITOR'!$B$7:$B$106="RATES")*('02 MONITOR'!$P$7:$P$106=15)*(ROW('02 MONITOR'!$B$7:$B$106)-6))),"") | P22: =IFERROR(INDEX('02 MONITOR'!$O$7:$O$106,SUMPRODUCT(('02 MONITOR'!$B$7:$B$106="RATES")*('02 MONITOR'!$P$7:$P$106=15)*(ROW('02 MONITOR'!$B$7:$B$106)-6))),"")
A24: FX — measured on Spot (or REER) — 26 instruments
B25: CHEAPEST | C25: Instrument | D25: Ticker | E25: Value score | F25: Z (raw) | G25: Current | H25: 1y chg | J25: MOST EXPENSIVE | K25: Instrument | L25: Ticker | M25: Value score | N25: Z (raw) | O25: Current | P25: 1y chg
B26: 1 | C26: =IFERROR(INDEX('02 MONITOR'!$C$7:$C$106,SUMPRODUCT(('02 MONITOR'!$B$7:$B$106="FX")*('02 MONITOR'!$P$7:$P$106=1)*(ROW('02 MONITOR'!$B$7:$B$106)-6))),"") | D26: =IFERROR(INDEX('02 MONITOR'!$D$7:$D$106,SUMPRODUCT(('02 MONITOR'!$B$7:$B$106="FX")*('02 MONITOR'!$P$7:$P$106=1)*(ROW('02 MONITOR'!$B$7:$B$106)-6))),"") | E26: =IFERROR(INDEX('02 MONITOR'!$M$7:$M$106,SUMPRODUCT(('02 MONITOR'!$B$7:$B$106="FX")*('02 MONITOR'!$P$7:$P$106=1)*(ROW('02 MONITOR'!$B$7:$B$106)-6))),"") | F26: =IFERROR(INDEX('02 MONITOR'!$K$7:$K$106,SUMPRODUCT(('02 MONITOR'!$B$7:$B$106="FX")*('02 MONITOR'!$P$7:$P$106=1)*(ROW('02 MONITOR'!$B$7:$B$106)-6))),"") | G26: =IFERROR(INDEX('02 MONITOR'!$H$7:$H$106,SUMPRODUCT(('02 MONITOR'!$B$7:$B$106="FX")*('02 MONITOR'!$P$7:$P$106=1)*(ROW('02 MONITOR'!$B$7:$B$106)-6))),"") | H26: =IFERROR(INDEX('02 MONITOR'!$O$7:$O$106,SUMPRODUCT(('02 MONITOR'!$B$7:$B$106="FX")*('02 MONITOR'!$P$7:$P$106=1)*(ROW('02 MONITOR'!$B$7:$B$106)-6))),"") | J26: 1 | K26: =IFERROR(INDEX('02 MONITOR'!$C$7:$C$106,SUMPRODUCT(('02 MONITOR'!$B$7:$B$106="FX")*('02 MONITOR'!$P$7:$P$106=26)*(ROW('02 MONITOR'!$B$7:$B$106)-6))),"") | L26: =IFERROR(INDEX('02 MONITOR'!$D$7:$D$106,SUMPRODUCT(('02 MONITOR'!$B$7:$B$106="FX")*('02 MONITOR'!$P$7:$P$106=26)*(ROW('02 MONITOR'!$B$7:$B$106)-6))),"") | M26: =IFERROR(INDEX('02 MONITOR'!$M$7:$M$106,SUMPRODUCT(('02 MONITOR'!$B$7:$B$106="FX")*('02 MONITOR'!$P$7:$P$106=26)*(ROW('02 MONITOR'!$B$7:$B$106)-6))),"") | N26: =IFERROR(INDEX('02 MONITOR'!$K$7:$K$106,SUMPRODUCT(('02 MONITOR'!$B$7:$B$106="FX")*('02 MONITOR'!$P$7:$P$106=26)*(ROW('02 MONITOR'!$B$7:$B$106)-6))),"") | O26: =IFERROR(INDEX('02 MONITOR'!$H$7:$H$106,SUMPRODUCT(('02 MONITOR'!$B$7:$B$106="FX")*('02 MONITOR'!$P$7:$P$106=26)*(ROW('02 MONITOR'!$B$7:$B$106)-6))),"") | P26: =IFERROR(INDEX('02 MONITOR'!$O$7:$O$106,SUMPRODUCT(('02 MONITOR'!$B$7:$B$106="FX")*('02 MONITOR'!$P$7:$P$106=26)*(ROW('02 MONITOR'!$B$7:$B$106)-6))),"")
B27: 2 | C27: =IFERROR(INDEX('02 MONITOR'!$C$7:$C$106,SUMPRODUCT(('02 MONITOR'!$B$7:$B$106="FX")*('02 MONITOR'!$P$7:$P$106=2)*(ROW('02 MONITOR'!$B$7:$B$106)-6))),"") | D27: =IFERROR(INDEX('02 MONITOR'!$D$7:$D$106,SUMPRODUCT(('02 MONITOR'!$B$7:$B$106="FX")*('02 MONITOR'!$P$7:$P$106=2)*(ROW('02 MONITOR'!$B$7:$B$106)-6))),"") | E27: =IFERROR(INDEX('02 MONITOR'!$M$7:$M$106,SUMPRODUCT(('02 MONITOR'!$B$7:$B$106="FX")*('02 MONITOR'!$P$7:$P$106=2)*(ROW('02 MONITOR'!$B$7:$B$106)-6))),"") | F27: =IFERROR(INDEX('02 MONITOR'!$K$7:$K$106,SUMPRODUCT(('02 MONITOR'!$B$7:$B$106="FX")*('02 MONITOR'!$P$7:$P$106=2)*(ROW('02 MONITOR'!$B$7:$B$106)-6))),"") | G27: =IFERROR(INDEX('02 MONITOR'!$H$7:$H$106,SUMPRODUCT(('02 MONITOR'!$B$7:$B$106="FX")*('02 MONITOR'!$P$7:$P$106=2)*(ROW('02 MONITOR'!$B$7:$B$106)-6))),"") | H27: =IFERROR(INDEX('02 MONITOR'!$O$7:$O$106,SUMPRODUCT(('02 MONITOR'!$B$7:$B$106="FX")*('02 MONITOR'!$P$7:$P$106=2)*(ROW('02 MONITOR'!$B$7:$B$106)-6))),"") | J27: 2 | K27: =IFERROR(INDEX('02 MONITOR'!$C$7:$C$106,SUMPRODUCT(('02 MONITOR'!$B$7:$B$106="FX")*('02 MONITOR'!$P$7:$P$106=25)*(ROW('02 MONITOR'!$B$7:$B$106)-6))),"") | L27: =IFERROR(INDEX('02 MONITOR'!$D$7:$D$106,SUMPRODUCT(('02 MONITOR'!$B$7:$B$106="FX")*('02 MONITOR'!$P$7:$P$106=25)*(ROW('02 MONITOR'!$B$7:$B$106)-6))),"") | M27: =IFERROR(INDEX('02 MONITOR'!$M$7:$M$106,SUMPRODUCT(('02 MONITOR'!$B$7:$B$106="FX")*('02 MONITOR'!$P$7:$P$106=25)*(ROW('02 MONITOR'!$B$7:$B$106)-6))),"") | N27: =IFERROR(INDEX('02 MONITOR'!$K$7:$K$106,SUMPRODUCT(('02 MONITOR'!$B$7:$B$106="FX")*('02 MONITOR'!$P$7:$P$106=25)*(ROW('02 MONITOR'!$B$7:$B$106)-6))),"") | O27: =IFERROR(INDEX('02 MONITOR'!$H$7:$H$106,SUMPRODUCT(('02 MONITOR'!$B$7:$B$106="FX")*('02 MONITOR'!$P$7:$P$106=25)*(ROW('02 MONITOR'!$B$7:$B$106)-6))),"") | P27: =IFERROR(INDEX('02 MONITOR'!$O$7:$O$106,SUMPRODUCT(('02 MONITOR'!$B$7:$B$106="FX")*('02 MONITOR'!$P$7:$P$106=25)*(ROW('02 MONITOR'!$B$7:$B$106)-6))),"")
B28: 3 | C28: =IFERROR(INDEX('02 MONITOR'!$C$7:$C$106,SUMPRODUCT(('02 MONITOR'!$B$7:$B$106="FX")*('02 MONITOR'!$P$7:$P$106=3)*(ROW('02 MONITOR'!$B$7:$B$106)-6))),"") | D28: =IFERROR(INDEX('02 MONITOR'!$D$7:$D$106,SUMPRODUCT(('02 MONITOR'!$B$7:$B$106="FX")*('02 MONITOR'!$P$7:$P$106=3)*(ROW('02 MONITOR'!$B$7:$B$106)-6))),"") | E28: =IFERROR(INDEX('02 MONITOR'!$M$7:$M$106,SUMPRODUCT(('02 MONITOR'!$B$7:$B$106="FX")*('02 MONITOR'!$P$7:$P$106=3)*(ROW('02 MONITOR'!$B$7:$B$106)-6))),"") | F28: =IFERROR(INDEX('02 MONITOR'!$K$7:$K$106,SUMPRODUCT(('02 MONITOR'!$B$7:$B$106="FX")*('02 MONITOR'!$P$7:$P$106=3)*(ROW('02 MONITOR'!$B$7:$B$106)-6))),"") | G28: =IFERROR(INDEX('02 MONITOR'!$H$7:$H$106,SUMPRODUCT(('02 MONITOR'!$B$7:$B$106="FX")*('02 MONITOR'!$P$7:$P$106=3)*(ROW('02 MONITOR'!$B$7:$B$106)-6))),"") | H28: =IFERROR(INDEX('02 MONITOR'!$O$7:$O$106,SUMPRODUCT(('02 MONITOR'!$B$7:$B$106="FX")*('02 MONITOR'!$P$7:$P$106=3)*(ROW('02 MONITOR'!$B$7:$B$106)-6))),"") | J28: 3 | K28: =IFERROR(INDEX('02 MONITOR'!$C$7:$C$106,SUMPRODUCT(('02 MONITOR'!$B$7:$B$106="FX")*('02 MONITOR'!$P$7:$P$106=24)*(ROW('02 MONITOR'!$B$7:$B$106)-6))),"") | L28: =IFERROR(INDEX('02 MONITOR'!$D$7:$D$106,SUMPRODUCT(('02 MONITOR'!$B$7:$B$106="FX")*('02 MONITOR'!$P$7:$P$106=24)*(ROW('02 MONITOR'!$B$7:$B$106)-6))),"") | M28: =IFERROR(INDEX('02 MONITOR'!$M$7:$M$106,SUMPRODUCT(('02 MONITOR'!$B$7:$B$106="FX")*('02 MONITOR'!$P$7:$P$106=24)*(ROW('02 MONITOR'!$B$7:$B$106)-6))),"") | N28: =IFERROR(INDEX('02 MONITOR'!$K$7:$K$106,SUMPRODUCT(('02 MONITOR'!$B$7:$B$106="FX")*('02 MONITOR'!$P$7:$P$106=24)*(ROW('02 MONITOR'!$B$7:$B$106)-6))),"") | O28: =IFERROR(INDEX('02 MONITOR'!$H$7:$H$106,SUMPRODUCT(('02 MONITOR'!$B$7:$B$106="FX")*('02 MONITOR'!$P$7:$P$106=24)*(ROW('02 MONITOR'!$B$7:$B$106)-6))),"") | P28: =IFERROR(INDEX('02 MONITOR'!$O$7:$O$106,SUMPRODUCT(('02 MONITOR'!$B$7:$B$106="FX")*('02 MONITOR'!$P$7:$P$106=24)*(ROW('02 MONITOR'!$B$7:$B$106)-6))),"")
B29: 4 | C29: =IFERROR(INDEX('02 MONITOR'!$C$7:$C$106,SUMPRODUCT(('02 MONITOR'!$B$7:$B$106="FX")*('02 MONITOR'!$P$7:$P$106=4)*(ROW('02 MONITOR'!$B$7:$B$106)-6))),"") | D29: =IFERROR(INDEX('02 MONITOR'!$D$7:$D$106,SUMPRODUCT(('02 MONITOR'!$B$7:$B$106="FX")*('02 MONITOR'!$P$7:$P$106=4)*(ROW('02 MONITOR'!$B$7:$B$106)-6))),"") | E29: =IFERROR(INDEX('02 MONITOR'!$M$7:$M$106,SUMPRODUCT(('02 MONITOR'!$B$7:$B$106="FX")*('02 MONITOR'!$P$7:$P$106=4)*(ROW('02 MONITOR'!$B$7:$B$106)-6))),"") | F29: =IFERROR(INDEX('02 MONITOR'!$K$7:$K$106,SUMPRODUCT(('02 MONITOR'!$B$7:$B$106="FX")*('02 MONITOR'!$P$7:$P$106=4)*(ROW('02 MONITOR'!$B$7:$B$106)-6))),"") | G29: =IFERROR(INDEX('02 MONITOR'!$H$7:$H$106,SUMPRODUCT(('02 MONITOR'!$B$7:$B$106="FX")*('02 MONITOR'!$P$7:$P$106=4)*(ROW('02 MONITOR'!$B$7:$B$106)-6))),"") | H29: =IFERROR(INDEX('02 MONITOR'!$O$7:$O$106,SUMPRODUCT(('02 MONITOR'!$B$7:$B$106="FX")*('02 MONITOR'!$P$7:$P$106=4)*(ROW('02 MONITOR'!$B$7:$B$106)-6))),"") | J29: 4 | K29: =IFERROR(INDEX('02 MONITOR'!$C$7:$C$106,SUMPRODUCT(('02 MONITOR'!$B$7:$B$106="FX")*('02 MONITOR'!$P$7:$P$106=23)*(ROW('02 MONITOR'!$B$7:$B$106)-6))),"") | L29: =IFERROR(INDEX('02 MONITOR'!$D$7:$D$106,SUMPRODUCT(('02 MONITOR'!$B$7:$B$106="FX")*('02 MONITOR'!$P$7:$P$106=23)*(ROW('02 MONITOR'!$B$7:$B$106)-6))),"") | M29: =IFERROR(INDEX('02 MONITOR'!$M$7:$M$106,SUMPRODUCT(('02 MONITOR'!$B$7:$B$106="FX")*('02 MONITOR'!$P$7:$P$106=23)*(ROW('02 MONITOR'!$B$7:$B$106)-6))),"") | N29: =IFERROR(INDEX('02 MONITOR'!$K$7:$K$106,SUMPRODUCT(('02 MONITOR'!$B$7:$B$106="FX")*('02 MONITOR'!$P$7:$P$106=23)*(ROW('02 MONITOR'!$B$7:$B$106)-6))),"") | O29: =IFERROR(INDEX('02 MONITOR'!$H$7:$H$106,SUMPRODUCT(('02 MONITOR'!$B$7:$B$106="FX")*('02 MONITOR'!$P$7:$P$106=23)*(ROW('02 MONITOR'!$B$7:$B$106)-6))),"") | P29: =IFERROR(INDEX('02 MONITOR'!$O$7:$O$106,SUMPRODUCT(('02 MONITOR'!$B$7:$B$106="FX")*('02 MONITOR'!$P$7:$P$106=23)*(ROW('02 MONITOR'!$B$7:$B$106)-6))),"")
B30: 5 | C30: =IFERROR(INDEX('02 MONITOR'!$C$7:$C$106,SUMPRODUCT(('02 MONITOR'!$B$7:$B$106="FX")*('02 MONITOR'!$P$7:$P$106=5)*(ROW('02 MONITOR'!$B$7:$B$106)-6))),"") | D30: =IFERROR(INDEX('02 MONITOR'!$D$7:$D$106,SUMPRODUCT(('02 MONITOR'!$B$7:$B$106="FX")*('02 MONITOR'!$P$7:$P$106=5)*(ROW('02 MONITOR'!$B$7:$B$106)-6))),"") | E30: =IFERROR(INDEX('02 MONITOR'!$M$7:$M$106,SUMPRODUCT(('02 MONITOR'!$B$7:$B$106="FX")*('02 MONITOR'!$P$7:$P$106=5)*(ROW('02 MONITOR'!$B$7:$B$106)-6))),"") | F30: =IFERROR(INDEX('02 MONITOR'!$K$7:$K$106,SUMPRODUCT(('02 MONITOR'!$B$7:$B$106="FX")*('02 MONITOR'!$P$7:$P$106=5)*(ROW('02 MONITOR'!$B$7:$B$106)-6))),"") | G30: =IFERROR(INDEX('02 MONITOR'!$H$7:$H$106,SUMPRODUCT(('02 MONITOR'!$B$7:$B$106="FX")*('02 MONITOR'!$P$7:$P$106=5)*(ROW('02 MONITOR'!$B$7:$B$106)-6))),"") | H30: =IFERROR(INDEX('02 MONITOR'!$O$7:$O$106,SUMPRODUCT(('02 MONITOR'!$B$7:$B$106="FX")*('02 MONITOR'!$P$7:$P$106=5)*(ROW('02 MONITOR'!$B$7:$B$106)-6))),"") | J30: 5 | K30: =IFERROR(INDEX('02 MONITOR'!$C$7:$C$106,SUMPRODUCT(('02 MONITOR'!$B$7:$B$106="FX")*('02 MONITOR'!$P$7:$P$106=22)*(ROW('02 MONITOR'!$B$7:$B$106)-6))),"") | L30: =IFERROR(INDEX('02 MONITOR'!$D$7:$D$106,SUMPRODUCT(('02 MONITOR'!$B$7:$B$106="FX")*('02 MONITOR'!$P$7:$P$106=22)*(ROW('02 MONITOR'!$B$7:$B$106)-6))),"") | M30: =IFERROR(INDEX('02 MONITOR'!$M$7:$M$106,SUMPRODUCT(('02 MONITOR'!$B$7:$B$106="FX")*('02 MONITOR'!$P$7:$P$106=22)*(ROW('02 MONITOR'!$B$7:$B$106)-6))),"") | N30: =IFERROR(INDEX('02 MONITOR'!$K$7:$K$106,SUMPRODUCT(('02 MONITOR'!$B$7:$B$106="FX")*('02 MONITOR'!$P$7:$P$106=22)*(ROW('02 MONITOR'!$B$7:$B$106)-6))),"") | O30: =IFERROR(INDEX('02 MONITOR'!$H$7:$H$106,SUMPRODUCT(('02 MONITOR'!$B$7:$B$106="FX")*('02 MONITOR'!$P$7:$P$106=22)*(ROW('02 MONITOR'!$B$7:$B$106)-6))),"") | P30: =IFERROR(INDEX('02 MONITOR'!$O$7:$O$106,SUMPRODUCT(('02 MONITOR'!$B$7:$B$106="FX")*('02 MONITOR'!$P$7:$P$106=22)*(ROW('02 MONITOR'!$B$7:$B$106)-6))),"")
B31: 6 | C31: =IFERROR(INDEX('02 MONITOR'!$C$7:$C$106,SUMPRODUCT(('02 MONITOR'!$B$7:$B$106="FX")*('02 MONITOR'!$P$7:$P$106=6)*(ROW('02 MONITOR'!$B$7:$B$106)-6))),"") | D31: =IFERROR(INDEX('02 MONITOR'!$D$7:$D$106,SUMPRODUCT(('02 MONITOR'!$B$7:$B$106="FX")*('02 MONITOR'!$P$7:$P$106=6)*(ROW('02 MONITOR'!$B$7:$B$106)-6))),"") | E31: =IFERROR(INDEX('02 MONITOR'!$M$7:$M$106,SUMPRODUCT(('02 MONITOR'!$B$7:$B$106="FX")*('02 MONITOR'!$P$7:$P$106=6)*(ROW('02 MONITOR'!$B$7:$B$106)-6))),"") | F31: =IFERROR(INDEX('02 MONITOR'!$K$7:$K$106,SUMPRODUCT(('02 MONITOR'!$B$7:$B$106="FX")*('02 MONITOR'!$P$7:$P$106=6)*(ROW('02 MONITOR'!$B$7:$B$106)-6))),"") | G31: =IFERROR(INDEX('02 MONITOR'!$H$7:$H$106,SUMPRODUCT(('02 MONITOR'!$B$7:$B$106="FX")*('02 MONITOR'!$P$7:$P$106=6)*(ROW('02 MONITOR'!$B$7:$B$106)-6))),"") | H31: =IFERROR(INDEX('02 MONITOR'!$O$7:$O$106,SUMPRODUCT(('02 MONITOR'!$B$7:$B$106="FX")*('02 MONITOR'!$P$7:$P$106=6)*(ROW('02 MONITOR'!$B$7:$B$106)-6))),"") | J31: 6 | K31: =IFERROR(INDEX('02 MONITOR'!$C$7:$C$106,SUMPRODUCT(('02 MONITOR'!$B$7:$B$106="FX")*('02 MONITOR'!$P$7:$P$106=21)*(ROW('02 MONITOR'!$B$7:$B$106)-6))),"") | L31: =IFERROR(INDEX('02 MONITOR'!$D$7:$D$106,SUMPRODUCT(('02 MONITOR'!$B$7:$B$106="FX")*('02 MONITOR'!$P$7:$P$106=21)*(ROW('02 MONITOR'!$B$7:$B$106)-6))),"") | M31: =IFERROR(INDEX('02 MONITOR'!$M$7:$M$106,SUMPRODUCT(('02 MONITOR'!$B$7:$B$106="FX")*('02 MONITOR'!$P$7:$P$106=21)*(ROW('02 MONITOR'!$B$7:$B$106)-6))),"") | N31: =IFERROR(INDEX('02 MONITOR'!$K$7:$K$106,SUMPRODUCT(('02 MONITOR'!$B$7:$B$106="FX")*('02 MONITOR'!$P$7:$P$106=21)*(ROW('02 MONITOR'!$B$7:$B$106)-6))),"") | O31: =IFERROR(INDEX('02 MONITOR'!$H$7:$H$106,SUMPRODUCT(('02 MONITOR'!$B$7:$B$106="FX")*('02 MONITOR'!$P$7:$P$106=21)*(ROW('02 MONITOR'!$B$7:$B$106)-6))),"") | P31: =IFERROR(INDEX('02 MONITOR'!$O$7:$O$106,SUMPRODUCT(('02 MONITOR'!$B$7:$B$106="FX")*('02 MONITOR'!$P$7:$P$106=21)*(ROW('02 MONITOR'!$B$7:$B$106)-6))),"")
A33: CREDIT — measured on Option-adjusted spread — 12 instruments
B34: CHEAPEST | C34: Instrument | D34: Ticker | E34: Value score | F34: Z (raw) | G34: Current | H34: 1y chg | J34: MOST EXPENSIVE | K34: Instrument | L34: Ticker | M34: Value score | N34: Z (raw) | O34: Current | P34: 1y chg
B35: 1 | C35: =IFERROR(INDEX('02 MONITOR'!$C$7:$C$106,SUMPRODUCT(('02 MONITOR'!$B$7:$B$106="CREDIT")*('02 MONITOR'!$P$7:$P$106=1)*(ROW('02 MONITOR'!$B$7:$B$106)-6))),"") | D35: =IFERROR(INDEX('02 MONITOR'!$D$7:$D$106,SUMPRODUCT(('02 MONITOR'!$B$7:$B$106="CREDIT")*('02 MONITOR'!$P$7:$P$106=1)*(ROW('02 MONITOR'!$B$7:$B$106)-6))),"") | E35: =IFERROR(INDEX('02 MONITOR'!$M$7:$M$106,SUMPRODUCT(('02 MONITOR'!$B$7:$B$106="CREDIT")*('02 MONITOR'!$P$7:$P$106=1)*(ROW('02 MONITOR'!$B$7:$B$106)-6))),"") | F35: =IFERROR(INDEX('02 MONITOR'!$K$7:$K$106,SUMPRODUCT(('02 MONITOR'!$B$7:$B$106="CREDIT")*('02 MONITOR'!$P$7:$P$106=1)*(ROW('02 MONITOR'!$B$7:$B$106)-6))),"") | G35: =IFERROR(INDEX('02 MONITOR'!$H$7:$H$106,SUMPRODUCT(('02 MONITOR'!$B$7:$B$106="CREDIT")*('02 MONITOR'!$P$7:$P$106=1)*(ROW('02 MONITOR'!$B$7:$B$106)-6))),"") | H35: =IFERROR(INDEX('02 MONITOR'!$O$7:$O$106,SUMPRODUCT(('02 MONITOR'!$B$7:$B$106="CREDIT")*('02 MONITOR'!$P$7:$P$106=1)*(ROW('02 MONITOR'!$B$7:$B$106)-6))),"") | J35: 1 | K35: =IFERROR(INDEX('02 MONITOR'!$C$7:$C$106,SUMPRODUCT(('02 MONITOR'!$B$7:$B$106="CREDIT")*('02 MONITOR'!$P$7:$P$106=12)*(ROW('02 MONITOR'!$B$7:$B$106)-6))),"") | L35: =IFERROR(INDEX('02 MONITOR'!$D$7:$D$106,SUMPRODUCT(('02 MONITOR'!$B$7:$B$106="CREDIT")*('02 MONITOR'!$P$7:$P$106=12)*(ROW('02 MONITOR'!$B$7:$B$106)-6))),"") | M35: =IFERROR(INDEX('02 MONITOR'!$M$7:$M$106,SUMPRODUCT(('02 MONITOR'!$B$7:$B$106="CREDIT")*('02 MONITOR'!$P$7:$P$106=12)*(ROW('02 MONITOR'!$B$7:$B$106)-6))),"") | N35: =IFERROR(INDEX('02 MONITOR'!$K$7:$K$106,SUMPRODUCT(('02 MONITOR'!$B$7:$B$106="CREDIT")*('02 MONITOR'!$P$7:$P$106=12)*(ROW('02 MONITOR'!$B$7:$B$106)-6))),"") | O35: =IFERROR(INDEX('02 MONITOR'!$H$7:$H$106,SUMPRODUCT(('02 MONITOR'!$B$7:$B$106="CREDIT")*('02 MONITOR'!$P$7:$P$106=12)*(ROW('02 MONITOR'!$B$7:$B$106)-6))),"") | P35: =IFERROR(INDEX('02 MONITOR'!$O$7:$O$106,SUMPRODUCT(('02 MONITOR'!$B$7:$B$106="CREDIT")*('02 MONITOR'!$P$7:$P$106=12)*(ROW('02 MONITOR'!$B$7:$B$106)-6))),"")
B36: 2 | C36: =IFERROR(INDEX('02 MONITOR'!$C$7:$C$106,SUMPRODUCT(('02 MONITOR'!$B$7:$B$106="CREDIT")*('02 MONITOR'!$P$7:$P$106=2)*(ROW('02 MONITOR'!$B$7:$B$106)-6))),"") | D36: =IFERROR(INDEX('02 MONITOR'!$D$7:$D$106,SUMPRODUCT(('02 MONITOR'!$B$7:$B$106="CREDIT")*('02 MONITOR'!$P$7:$P$106=2)*(ROW('02 MONITOR'!$B$7:$B$106)-6))),"") | E36: =IFERROR(INDEX('02 MONITOR'!$M$7:$M$106,SUMPRODUCT(('02 MONITOR'!$B$7:$B$106="CREDIT")*('02 MONITOR'!$P$7:$P$106=2)*(ROW('02 MONITOR'!$B$7:$B$106)-6))),"") | F36: =IFERROR(INDEX('02 MONITOR'!$K$7:$K$106,SUMPRODUCT(('02 MONITOR'!$B$7:$B$106="CREDIT")*('02 MONITOR'!$P$7:$P$106=2)*(ROW('02 MONITOR'!$B$7:$B$106)-6))),"") | G36: =IFERROR(INDEX('02 MONITOR'!$H$7:$H$106,SUMPRODUCT(('02 MONITOR'!$B$7:$B$106="CREDIT")*('02 MONITOR'!$P$7:$P$106=2)*(ROW('02 MONITOR'!$B$7:$B$106)-6))),"") | H36: =IFERROR(INDEX('02 MONITOR'!$O$7:$O$106,SUMPRODUCT(('02 MONITOR'!$B$7:$B$106="CREDIT")*('02 MONITOR'!$P$7:$P$106=2)*(ROW('02 MONITOR'!$B$7:$B$106)-6))),"") | J36: 2 | K36: =IFERROR(INDEX('02 MONITOR'!$C$7:$C$106,SUMPRODUCT(('02 MONITOR'!$B$7:$B$106="CREDIT")*('02 MONITOR'!$P$7:$P$106=11)*(ROW('02 MONITOR'!$B$7:$B$106)-6))),"") | L36: =IFERROR(INDEX('02 MONITOR'!$D$7:$D$106,SUMPRODUCT(('02 MONITOR'!$B$7:$B$106="CREDIT")*('02 MONITOR'!$P$7:$P$106=11)*(ROW('02 MONITOR'!$B$7:$B$106)-6))),"") | M36: =IFERROR(INDEX('02 MONITOR'!$M$7:$M$106,SUMPRODUCT(('02 MONITOR'!$B$7:$B$106="CREDIT")*('02 MONITOR'!$P$7:$P$106=11)*(ROW('02 MONITOR'!$B$7:$B$106)-6))),"") | N36: =IFERROR(INDEX('02 MONITOR'!$K$7:$K$106,SUMPRODUCT(('02 MONITOR'!$B$7:$B$106="CREDIT")*('02 MONITOR'!$P$7:$P$106=11)*(ROW('02 MONITOR'!$B$7:$B$106)-6))),"") | O36: =IFERROR(INDEX('02 MONITOR'!$H$7:$H$106,SUMPRODUCT(('02 MONITOR'!$B$7:$B$106="CREDIT")*('02 MONITOR'!$P$7:$P$106=11)*(ROW('02 MONITOR'!$B$7:$B$106)-6))),"") | P36: =IFERROR(INDEX('02 MONITOR'!$O$7:$O$106,SUMPRODUCT(('02 MONITOR'!$B$7:$B$106="CREDIT")*('02 MONITOR'!$P$7:$P$106=11)*(ROW('02 MONITOR'!$B$7:$B$106)-6))),"")
B37: 3 | C37: =IFERROR(INDEX('02 MONITOR'!$C$7:$C$106,SUMPRODUCT(('02 MONITOR'!$B$7:$B$106="CREDIT")*('02 MONITOR'!$P$7:$P$106=3)*(ROW('02 MONITOR'!$B$7:$B$106)-6))),"") | D37: =IFERROR(INDEX('02 MONITOR'!$D$7:$D$106,SUMPRODUCT(('02 MONITOR'!$B$7:$B$106="CREDIT")*('02 MONITOR'!$P$7:$P$106=3)*(ROW('02 MONITOR'!$B$7:$B$106)-6))),"") | E37: =IFERROR(INDEX('02 MONITOR'!$M$7:$M$106,SUMPRODUCT(('02 MONITOR'!$B$7:$B$106="CREDIT")*('02 MONITOR'!$P$7:$P$106=3)*(ROW('02 MONITOR'!$B$7:$B$106)-6))),"") | F37: =IFERROR(INDEX('02 MONITOR'!$K$7:$K$106,SUMPRODUCT(('02 MONITOR'!$B$7:$B$106="CREDIT")*('02 MONITOR'!$P$7:$P$106=3)*(ROW('02 MONITOR'!$B$7:$B$106)-6))),"") | G37: =IFERROR(INDEX('02 MONITOR'!$H$7:$H$106,SUMPRODUCT(('02 MONITOR'!$B$7:$B$106="CREDIT")*('02 MONITOR'!$P$7:$P$106=3)*(ROW('02 MONITOR'!$B$7:$B$106)-6))),"") | H37: =IFERROR(INDEX('02 MONITOR'!$O$7:$O$106,SUMPRODUCT(('02 MONITOR'!$B$7:$B$106="CREDIT")*('02 MONITOR'!$P$7:$P$106=3)*(ROW('02 MONITOR'!$B$7:$B$106)-6))),"") | J37: 3 | K37: =IFERROR(INDEX('02 MONITOR'!$C$7:$C$106,SUMPRODUCT(('02 MONITOR'!$B$7:$B$106="CREDIT")*('02 MONITOR'!$P$7:$P$106=10)*(ROW('02 MONITOR'!$B$7:$B$106)-6))),"") | L37: =IFERROR(INDEX('02 MONITOR'!$D$7:$D$106,SUMPRODUCT(('02 MONITOR'!$B$7:$B$106="CREDIT")*('02 MONITOR'!$P$7:$P$106=10)*(ROW('02 MONITOR'!$B$7:$B$106)-6))),"") | M37: =IFERROR(INDEX('02 MONITOR'!$M$7:$M$106,SUMPRODUCT(('02 MONITOR'!$B$7:$B$106="CREDIT")*('02 MONITOR'!$P$7:$P$106=10)*(ROW('02 MONITOR'!$B$7:$B$106)-6))),"") | N37: =IFERROR(INDEX('02 MONITOR'!$K$7:$K$106,SUMPRODUCT(('02 MONITOR'!$B$7:$B$106="CREDIT")*('02 MONITOR'!$P$7:$P$106=10)*(ROW('02 MONITOR'!$B$7:$B$106)-6))),"") | O37: =IFERROR(INDEX('02 MONITOR'!$H$7:$H$106,SUMPRODUCT(('02 MONITOR'!$B$7:$B$106="CREDIT")*('02 MONITOR'!$P$7:$P$106=10)*(ROW('02 MONITOR'!$B$7:$B$106)-6))),"") | P37: =IFERROR(INDEX('02 MONITOR'!$O$7:$O$106,SUMPRODUCT(('02 MONITOR'!$B$7:$B$106="CREDIT")*('02 MONITOR'!$P$7:$P$106=10)*(ROW('02 MONITOR'!$B$7:$B$106)-6))),"")
B38: 4 | C38: =IFERROR(INDEX('02 MONITOR'!$C$7:$C$106,SUMPRODUCT(('02 MONITOR'!$B$7:$B$106="CREDIT")*('02 MONITOR'!$P$7:$P$106=4)*(ROW('02 MONITOR'!$B$7:$B$106)-6))),"") | D38: =IFERROR(INDEX('02 MONITOR'!$D$7:$D$106,SUMPRODUCT(('02 MONITOR'!$B$7:$B$106="CREDIT")*('02 MONITOR'!$P$7:$P$106=4)*(ROW('02 MONITOR'!$B$7:$B$106)-6))),"") | E38: =IFERROR(INDEX('02 MONITOR'!$M$7:$M$106,SUMPRODUCT(('02 MONITOR'!$B$7:$B$106="CREDIT")*('02 MONITOR'!$P$7:$P$106=4)*(ROW('02 MONITOR'!$B$7:$B$106)-6))),"") | F38: =IFERROR(INDEX('02 MONITOR'!$K$7:$K$106,SUMPRODUCT(('02 MONITOR'!$B$7:$B$106="CREDIT")*('02 MONITOR'!$P$7:$P$106=4)*(ROW('02 MONITOR'!$B$7:$B$106)-6))),"") | G38: =IFERROR(INDEX('02 MONITOR'!$H$7:$H$106,SUMPRODUCT(('02 MONITOR'!$B$7:$B$106="CREDIT")*('02 MONITOR'!$P$7:$P$106=4)*(ROW('02 MONITOR'!$B$7:$B$106)-6))),"") | H38: =IFERROR(INDEX('02 MONITOR'!$O$7:$O$106,SUMPRODUCT(('02 MONITOR'!$B$7:$B$106="CREDIT")*('02 MONITOR'!$P$7:$P$106=4)*(ROW('02 MONITOR'!$B$7:$B$106)-6))),"") | J38: 4 | K38: =IFERROR(INDEX('02 MONITOR'!$C$7:$C$106,SUMPRODUCT(('02 MONITOR'!$B$7:$B$106="CREDIT")*('02 MONITOR'!$P$7:$P$106=9)*(ROW('02 MONITOR'!$B$7:$B$106)-6))),"") | L38: =IFERROR(INDEX('02 MONITOR'!$D$7:$D$106,SUMPRODUCT(('02 MONITOR'!$B$7:$B$106="CREDIT")*('02 MONITOR'!$P$7:$P$106=9)*(ROW('02 MONITOR'!$B$7:$B$106)-6))),"") | M38: =IFERROR(INDEX('02 MONITOR'!$M$7:$M$106,SUMPRODUCT(('02 MONITOR'!$B$7:$B$106="CREDIT")*('02 MONITOR'!$P$7:$P$106=9)*(ROW('02 MONITOR'!$B$7:$B$106)-6))),"") | N38: =IFERROR(INDEX('02 MONITOR'!$K$7:$K$106,SUMPRODUCT(('02 MONITOR'!$B$7:$B$106="CREDIT")*('02 MONITOR'!$P$7:$P$106=9)*(ROW('02 MONITOR'!$B$7:$B$106)-6))),"") | O38: =IFERROR(INDEX('02 MONITOR'!$H$7:$H$106,SUMPRODUCT(('02 MONITOR'!$B$7:$B$106="CREDIT")*('02 MONITOR'!$P$7:$P$106=9)*(ROW('02 MONITOR'!$B$7:$B$106)-6))),"") | P38: =IFERROR(INDEX('02 MONITOR'!$O$7:$O$106,SUMPRODUCT(('02 MONITOR'!$B$7:$B$106="CREDIT")*('02 MONITOR'!$P$7:$P$106=9)*(ROW('02 MONITOR'!$B$7:$B$106)-6))),"")
B39: 5 | C39: =IFERROR(INDEX('02 MONITOR'!$C$7:$C$106,SUMPRODUCT(('02 MONITOR'!$B$7:$B$106="CREDIT")*('02 MONITOR'!$P$7:$P$106=5)*(ROW('02 MONITOR'!$B$7:$B$106)-6))),"") | D39: =IFERROR(INDEX('02 MONITOR'!$D$7:$D$106,SUMPRODUCT(('02 MONITOR'!$B$7:$B$106="CREDIT")*('02 MONITOR'!$P$7:$P$106=5)*(ROW('02 MONITOR'!$B$7:$B$106)-6))),"") | E39: =IFERROR(INDEX('02 MONITOR'!$M$7:$M$106,SUMPRODUCT(('02 MONITOR'!$B$7:$B$106="CREDIT")*('02 MONITOR'!$P$7:$P$106=5)*(ROW('02 MONITOR'!$B$7:$B$106)-6))),"") | F39: =IFERROR(INDEX('02 MONITOR'!$K$7:$K$106,SUMPRODUCT(('02 MONITOR'!$B$7:$B$106="CREDIT")*('02 MONITOR'!$P$7:$P$106=5)*(ROW('02 MONITOR'!$B$7:$B$106)-6))),"") | G39: =IFERROR(INDEX('02 MONITOR'!$H$7:$H$106,SUMPRODUCT(('02 MONITOR'!$B$7:$B$106="CREDIT")*('02 MONITOR'!$P$7:$P$106=5)*(ROW('02 MONITOR'!$B$7:$B$106)-6))),"") | H39: =IFERROR(INDEX('02 MONITOR'!$O$7:$O$106,SUMPRODUCT(('02 MONITOR'!$B$7:$B$106="CREDIT")*('02 MONITOR'!$P$7:$P$106=5)*(ROW('02 MONITOR'!$B$7:$B$106)-6))),"") | J39: 5 | K39: =IFERROR(INDEX('02 MONITOR'!$C$7:$C$106,SUMPRODUCT(('02 MONITOR'!$B$7:$B$106="CREDIT")*('02 MONITOR'!$P$7:$P$106=8)*(ROW('02 MONITOR'!$B$7:$B$106)-6))),"") | L39: =IFERROR(INDEX('02 MONITOR'!$D$7:$D$106,SUMPRODUCT(('02 MONITOR'!$B$7:$B$106="CREDIT")*('02 MONITOR'!$P$7:$P$106=8)*(ROW('02 MONITOR'!$B$7:$B$106)-6))),"") | M39: =IFERROR(INDEX('02 MONITOR'!$M$7:$M$106,SUMPRODUCT(('02 MONITOR'!$B$7:$B$106="CREDIT")*('02 MONITOR'!$P$7:$P$106=8)*(ROW('02 MONITOR'!$B$7:$B$106)-6))),"") | N39: =IFERROR(INDEX('02 MONITOR'!$K$7:$K$106,SUMPRODUCT(('02 MONITOR'!$B$7:$B$106="CREDIT")*('02 MONITOR'!$P$7:$P$106=8)*(ROW('02 MONITOR'!$B$7:$B$106)-6))),"") | O39: =IFERROR(INDEX('02 MONITOR'!$H$7:$H$106,SUMPRODUCT(('02 MONITOR'!$B$7:$B$106="CREDIT")*('02 MONITOR'!$P$7:$P$106=8)*(ROW('02 MONITOR'!$B$7:$B$106)-6))),"") | P39: =IFERROR(INDEX('02 MONITOR'!$O$7:$O$106,SUMPRODUCT(('02 MONITOR'!$B$7:$B$106="CREDIT")*('02 MONITOR'!$P$7:$P$106=8)*(ROW('02 MONITOR'!$B$7:$B$106)-6))),"")
B40: 6 | C40: =IFERROR(INDEX('02 MONITOR'!$C$7:$C$106,SUMPRODUCT(('02 MONITOR'!$B$7:$B$106="CREDIT")*('02 MONITOR'!$P$7:$P$106=6)*(ROW('02 MONITOR'!$B$7:$B$106)-6))),"") | D40: =IFERROR(INDEX('02 MONITOR'!$D$7:$D$106,SUMPRODUCT(('02 MONITOR'!$B$7:$B$106="CREDIT")*('02 MONITOR'!$P$7:$P$106=6)*(ROW('02 MONITOR'!$B$7:$B$106)-6))),"") | E40: =IFERROR(INDEX('02 MONITOR'!$M$7:$M$106,SUMPRODUCT(('02 MONITOR'!$B$7:$B$106="CREDIT")*('02 MONITOR'!$P$7:$P$106=6)*(ROW('02 MONITOR'!$B$7:$B$106)-6))),"") | F40: =IFERROR(INDEX('02 MONITOR'!$K$7:$K$106,SUMPRODUCT(('02 MONITOR'!$B$7:$B$106="CREDIT")*('02 MONITOR'!$P$7:$P$106=6)*(ROW('02 MONITOR'!$B$7:$B$106)-6))),"") | G40: =IFERROR(INDEX('02 MONITOR'!$H$7:$H$106,SUMPRODUCT(('02 MONITOR'!$B$7:$B$106="CREDIT")*('02 MONITOR'!$P$7:$P$106=6)*(ROW('02 MONITOR'!$B$7:$B$106)-6))),"") | H40: =IFERROR(INDEX('02 MONITOR'!$O$7:$O$106,SUMPRODUCT(('02 MONITOR'!$B$7:$B$106="CREDIT")*('02 MONITOR'!$P$7:$P$106=6)*(ROW('02 MONITOR'!$B$7:$B$106)-6))),"") | J40: 6 | K40: =IFERROR(INDEX('02 MONITOR'!$C$7:$C$106,SUMPRODUCT(('02 MONITOR'!$B$7:$B$106="CREDIT")*('02 MONITOR'!$P$7:$P$106=7)*(ROW('02 MONITOR'!$B$7:$B$106)-6))),"") | L40: =IFERROR(INDEX('02 MONITOR'!$D$7:$D$106,SUMPRODUCT(('02 MONITOR'!$B$7:$B$106="CREDIT")*('02 MONITOR'!$P$7:$P$106=7)*(ROW('02 MONITOR'!$B$7:$B$106)-6))),"") | M40: =IFERROR(INDEX('02 MONITOR'!$M$7:$M$106,SUMPRODUCT(('02 MONITOR'!$B$7:$B$106="CREDIT")*('02 MONITOR'!$P$7:$P$106=7)*(ROW('02 MONITOR'!$B$7:$B$106)-6))),"") | N40: =IFERROR(INDEX('02 MONITOR'!$K$7:$K$106,SUMPRODUCT(('02 MONITOR'!$B$7:$B$106="CREDIT")*('02 MONITOR'!$P$7:$P$106=7)*(ROW('02 MONITOR'!$B$7:$B$106)-6))),"") | O40: =IFERROR(INDEX('02 MONITOR'!$H$7:$H$106,SUMPRODUCT(('02 MONITOR'!$B$7:$B$106="CREDIT")*('02 MONITOR'!$P$7:$P$106=7)*(ROW('02 MONITOR'!$B$7:$B$106)-6))),"") | P40: =IFERROR(INDEX('02 MONITOR'!$O$7:$O$106,SUMPRODUCT(('02 MONITOR'!$B$7:$B$106="CREDIT")*('02 MONITOR'!$P$7:$P$106=7)*(ROW('02 MONITOR'!$B$7:$B$106)-6))),"")
A42: COMMODITY — measured on Front-contract price — 18 instruments
B43: CHEAPEST | C43: Instrument | D43: Ticker | E43: Value score | F43: Z (raw) | G43: Current | H43: 1y chg | J43: MOST EXPENSIVE | K43: Instrument | L43: Ticker | M43: Value score | N43: Z (raw) | O43: Current | P43: 1y chg
B44: 1 | C44: =IFERROR(INDEX('02 MONITOR'!$C$7:$C$106,SUMPRODUCT(('02 MONITOR'!$B$7:$B$106="COMMODITY")*('02 MONITOR'!$P$7:$P$106=1)*(ROW('02 MONITOR'!$B$7:$B$106)-6))),"") | D44: =IFERROR(INDEX('02 MONITOR'!$D$7:$D$106,SUMPRODUCT(('02 MONITOR'!$B$7:$B$106="COMMODITY")*('02 MONITOR'!$P$7:$P$106=1)*(ROW('02 MONITOR'!$B$7:$B$106)-6))),"") | E44: =IFERROR(INDEX('02 MONITOR'!$M$7:$M$106,SUMPRODUCT(('02 MONITOR'!$B$7:$B$106="COMMODITY")*('02 MONITOR'!$P$7:$P$106=1)*(ROW('02 MONITOR'!$B$7:$B$106)-6))),"") | F44: =IFERROR(INDEX('02 MONITOR'!$K$7:$K$106,SUMPRODUCT(('02 MONITOR'!$B$7:$B$106="COMMODITY")*('02 MONITOR'!$P$7:$P$106=1)*(ROW('02 MONITOR'!$B$7:$B$106)-6))),"") | G44: =IFERROR(INDEX('02 MONITOR'!$H$7:$H$106,SUMPRODUCT(('02 MONITOR'!$B$7:$B$106="COMMODITY")*('02 MONITOR'!$P$7:$P$106=1)*(ROW('02 MONITOR'!$B$7:$B$106)-6))),"") | H44: =IFERROR(INDEX('02 MONITOR'!$O$7:$O$106,SUMPRODUCT(('02 MONITOR'!$B$7:$B$106="COMMODITY")*('02 MONITOR'!$P$7:$P$106=1)*(ROW('02 MONITOR'!$B$7:$B$106)-6))),"") | J44: 1 | K44: =IFERROR(INDEX('02 MONITOR'!$C$7:$C$106,SUMPRODUCT(('02 MONITOR'!$B$7:$B$106="COMMODITY")*('02 MONITOR'!$P$7:$P$106=18)*(ROW('02 MONITOR'!$B$7:$B$106)-6))),"") | L44: =IFERROR(INDEX('02 MONITOR'!$D$7:$D$106,SUMPRODUCT(('02 MONITOR'!$B$7:$B$106="COMMODITY")*('02 MONITOR'!$P$7:$P$106=18)*(ROW('02 MONITOR'!$B$7:$B$106)-6))),"") | M44: =IFERROR(INDEX('02 MONITOR'!$M$7:$M$106,SUMPRODUCT(('02 MONITOR'!$B$7:$B$106="COMMODITY")*('02 MONITOR'!$P$7:$P$106=18)*(ROW('02 MONITOR'!$B$7:$B$106)-6))),"") | N44: =IFERROR(INDEX('02 MONITOR'!$K$7:$K$106,SUMPRODUCT(('02 MONITOR'!$B$7:$B$106="COMMODITY")*('02 MONITOR'!$P$7:$P$106=18)*(ROW('02 MONITOR'!$B$7:$B$106)-6))),"") | O44: =IFERROR(INDEX('02 MONITOR'!$H$7:$H$106,SUMPRODUCT(('02 MONITOR'!$B$7:$B$106="COMMODITY")*('02 MONITOR'!$P$7:$P$106=18)*(ROW('02 MONITOR'!$B$7:$B$106)-6))),"") | P44: =IFERROR(INDEX('02 MONITOR'!$O$7:$O$106,SUMPRODUCT(('02 MONITOR'!$B$7:$B$106="COMMODITY")*('02 MONITOR'!$P$7:$P$106=18)*(ROW('02 MONITOR'!$B$7:$B$106)-6))),"")
B45: 2 | C45: =IFERROR(INDEX('02 MONITOR'!$C$7:$C$106,SUMPRODUCT(('02 MONITOR'!$B$7:$B$106="COMMODITY")*('02 MONITOR'!$P$7:$P$106=2)*(ROW('02 MONITOR'!$B$7:$B$106)-6))),"") | D45: =IFERROR(INDEX('02 MONITOR'!$D$7:$D$106,SUMPRODUCT(('02 MONITOR'!$B$7:$B$106="COMMODITY")*('02 MONITOR'!$P$7:$P$106=2)*(ROW('02 MONITOR'!$B$7:$B$106)-6))),"") | E45: =IFERROR(INDEX('02 MONITOR'!$M$7:$M$106,SUMPRODUCT(('02 MONITOR'!$B$7:$B$106="COMMODITY")*('02 MONITOR'!$P$7:$P$106=2)*(ROW('02 MONITOR'!$B$7:$B$106)-6))),"") | F45: =IFERROR(INDEX('02 MONITOR'!$K$7:$K$106,SUMPRODUCT(('02 MONITOR'!$B$7:$B$106="COMMODITY")*('02 MONITOR'!$P$7:$P$106=2)*(ROW('02 MONITOR'!$B$7:$B$106)-6))),"") | G45: =IFERROR(INDEX('02 MONITOR'!$H$7:$H$106,SUMPRODUCT(('02 MONITOR'!$B$7:$B$106="COMMODITY")*('02 MONITOR'!$P$7:$P$106=2)*(ROW('02 MONITOR'!$B$7:$B$106)-6))),"") | H45: =IFERROR(INDEX('02 MONITOR'!$O$7:$O$106,SUMPRODUCT(('02 MONITOR'!$B$7:$B$106="COMMODITY")*('02 MONITOR'!$P$7:$P$106=2)*(ROW('02 MONITOR'!$B$7:$B$106)-6))),"") | J45: 2 | K45: =IFERROR(INDEX('02 MONITOR'!$C$7:$C$106,SUMPRODUCT(('02 MONITOR'!$B$7:$B$106="COMMODITY")*('02 MONITOR'!$P$7:$P$106=17)*(ROW('02 MONITOR'!$B$7:$B$106)-6))),"") | L45: =IFERROR(INDEX('02 MONITOR'!$D$7:$D$106,SUMPRODUCT(('02 MONITOR'!$B$7:$B$106="COMMODITY")*('02 MONITOR'!$P$7:$P$106=17)*(ROW('02 MONITOR'!$B$7:$B$106)-6))),"") | M45: =IFERROR(INDEX('02 MONITOR'!$M$7:$M$106,SUMPRODUCT(('02 MONITOR'!$B$7:$B$106="COMMODITY")*('02 MONITOR'!$P$7:$P$106=17)*(ROW('02 MONITOR'!$B$7:$B$106)-6))),"") | N45: =IFERROR(INDEX('02 MONITOR'!$K$7:$K$106,SUMPRODUCT(('02 MONITOR'!$B$7:$B$106="COMMODITY")*('02 MONITOR'!$P$7:$P$106=17)*(ROW('02 MONITOR'!$B$7:$B$106)-6))),"") | O45: =IFERROR(INDEX('02 MONITOR'!$H$7:$H$106,SUMPRODUCT(('02 MONITOR'!$B$7:$B$106="COMMODITY")*('02 MONITOR'!$P$7:$P$106=17)*(ROW('02 MONITOR'!$B$7:$B$106)-6))),"") | P45: =IFERROR(INDEX('02 MONITOR'!$O$7:$O$106,SUMPRODUCT(('02 MONITOR'!$B$7:$B$106="COMMODITY")*('02 MONITOR'!$P$7:$P$106=17)*(ROW('02 MONITOR'!$B$7:$B$106)-6))),"")
B46: 3 | C46: =IFERROR(INDEX('02 MONITOR'!$C$7:$C$106,SUMPRODUCT(('02 MONITOR'!$B$7:$B$106="COMMODITY")*('02 MONITOR'!$P$7:$P$106=3)*(ROW('02 MONITOR'!$B$7:$B$106)-6))),"") | D46: =IFERROR(INDEX('02 MONITOR'!$D$7:$D$106,SUMPRODUCT(('02 MONITOR'!$B$7:$B$106="COMMODITY")*('02 MONITOR'!$P$7:$P$106=3)*(ROW('02 MONITOR'!$B$7:$B$106)-6))),"") | E46: =IFERROR(INDEX('02 MONITOR'!$M$7:$M$106,SUMPRODUCT(('02 MONITOR'!$B$7:$B$106="COMMODITY")*('02 MONITOR'!$P$7:$P$106=3)*(ROW('02 MONITOR'!$B$7:$B$106)-6))),"") | F46: =IFERROR(INDEX('02 MONITOR'!$K$7:$K$106,SUMPRODUCT(('02 MONITOR'!$B$7:$B$106="COMMODITY")*('02 MONITOR'!$P$7:$P$106=3)*(ROW('02 MONITOR'!$B$7:$B$106)-6))),"") | G46: =IFERROR(INDEX('02 MONITOR'!$H$7:$H$106,SUMPRODUCT(('02 MONITOR'!$B$7:$B$106="COMMODITY")*('02 MONITOR'!$P$7:$P$106=3)*(ROW('02 MONITOR'!$B$7:$B$106)-6))),"") | H46: =IFERROR(INDEX('02 MONITOR'!$O$7:$O$106,SUMPRODUCT(('02 MONITOR'!$B$7:$B$106="COMMODITY")*('02 MONITOR'!$P$7:$P$106=3)*(ROW('02 MONITOR'!$B$7:$B$106)-6))),"") | J46: 3 | K46: =IFERROR(INDEX('02 MONITOR'!$C$7:$C$106,SUMPRODUCT(('02 MONITOR'!$B$7:$B$106="COMMODITY")*('02 MONITOR'!$P$7:$P$106=16)*(ROW('02 MONITOR'!$B$7:$B$106)-6))),"") | L46: =IFERROR(INDEX('02 MONITOR'!$D$7:$D$106,SUMPRODUCT(('02 MONITOR'!$B$7:$B$106="COMMODITY")*('02 MONITOR'!$P$7:$P$106=16)*(ROW('02 MONITOR'!$B$7:$B$106)-6))),"") | M46: =IFERROR(INDEX('02 MONITOR'!$M$7:$M$106,SUMPRODUCT(('02 MONITOR'!$B$7:$B$106="COMMODITY")*('02 MONITOR'!$P$7:$P$106=16)*(ROW('02 MONITOR'!$B$7:$B$106)-6))),"") | N46: =IFERROR(INDEX('02 MONITOR'!$K$7:$K$106,SUMPRODUCT(('02 MONITOR'!$B$7:$B$106="COMMODITY")*('02 MONITOR'!$P$7:$P$106=16)*(ROW('02 MONITOR'!$B$7:$B$106)-6))),"") | O46: =IFERROR(INDEX('02 MONITOR'!$H$7:$H$106,SUMPRODUCT(('02 MONITOR'!$B$7:$B$106="COMMODITY")*('02 MONITOR'!$P$7:$P$106=16)*(ROW('02 MONITOR'!$B$7:$B$106)-6))),"") | P46: =IFERROR(INDEX('02 MONITOR'!$O$7:$O$106,SUMPRODUCT(('02 MONITOR'!$B$7:$B$106="COMMODITY")*('02 MONITOR'!$P$7:$P$106=16)*(ROW('02 MONITOR'!$B$7:$B$106)-6))),"")
B47: 4 | C47: =IFERROR(INDEX('02 MONITOR'!$C$7:$C$106,SUMPRODUCT(('02 MONITOR'!$B$7:$B$106="COMMODITY")*('02 MONITOR'!$P$7:$P$106=4)*(ROW('02 MONITOR'!$B$7:$B$106)-6))),"") | D47: =IFERROR(INDEX('02 MONITOR'!$D$7:$D$106,SUMPRODUCT(('02 MONITOR'!$B$7:$B$106="COMMODITY")*('02 MONITOR'!$P$7:$P$106=4)*(ROW('02 MONITOR'!$B$7:$B$106)-6))),"") | E47: =IFERROR(INDEX('02 MONITOR'!$M$7:$M$106,SUMPRODUCT(('02 MONITOR'!$B$7:$B$106="COMMODITY")*('02 MONITOR'!$P$7:$P$106=4)*(ROW('02 MONITOR'!$B$7:$B$106)-6))),"") | F47: =IFERROR(INDEX('02 MONITOR'!$K$7:$K$106,SUMPRODUCT(('02 MONITOR'!$B$7:$B$106="COMMODITY")*('02 MONITOR'!$P$7:$P$106=4)*(ROW('02 MONITOR'!$B$7:$B$106)-6))),"") | G47: =IFERROR(INDEX('02 MONITOR'!$H$7:$H$106,SUMPRODUCT(('02 MONITOR'!$B$7:$B$106="COMMODITY")*('02 MONITOR'!$P$7:$P$106=4)*(ROW('02 MONITOR'!$B$7:$B$106)-6))),"") | H47: =IFERROR(INDEX('02 MONITOR'!$O$7:$O$106,SUMPRODUCT(('02 MONITOR'!$B$7:$B$106="COMMODITY")*('02 MONITOR'!$P$7:$P$106=4)*(ROW('02 MONITOR'!$B$7:$B$106)-6))),"") | J47: 4 | K47: =IFERROR(INDEX('02 MONITOR'!$C$7:$C$106,SUMPRODUCT(('02 MONITOR'!$B$7:$B$106="COMMODITY")*('02 MONITOR'!$P$7:$P$106=15)*(ROW('02 MONITOR'!$B$7:$B$106)-6))),"") | L47: =IFERROR(INDEX('02 MONITOR'!$D$7:$D$106,SUMPRODUCT(('02 MONITOR'!$B$7:$B$106="COMMODITY")*('02 MONITOR'!$P$7:$P$106=15)*(ROW('02 MONITOR'!$B$7:$B$106)-6))),"") | M47: =IFERROR(INDEX('02 MONITOR'!$M$7:$M$106,SUMPRODUCT(('02 MONITOR'!$B$7:$B$106="COMMODITY")*('02 MONITOR'!$P$7:$P$106=15)*(ROW('02 MONITOR'!$B$7:$B$106)-6))),"") | N47: =IFERROR(INDEX('02 MONITOR'!$K$7:$K$106,SUMPRODUCT(('02 MONITOR'!$B$7:$B$106="COMMODITY")*('02 MONITOR'!$P$7:$P$106=15)*(ROW('02 MONITOR'!$B$7:$B$106)-6))),"") | O47: =IFERROR(INDEX('02 MONITOR'!$H$7:$H$106,SUMPRODUCT(('02 MONITOR'!$B$7:$B$106="COMMODITY")*('02 MONITOR'!$P$7:$P$106=15)*(ROW('02 MONITOR'!$B$7:$B$106)-6))),"") | P47: =IFERROR(INDEX('02 MONITOR'!$O$7:$O$106,SUMPRODUCT(('02 MONITOR'!$B$7:$B$106="COMMODITY")*('02 MONITOR'!$P$7:$P$106=15)*(ROW('02 MONITOR'!$B$7:$B$106)-6))),"")
B48: 5 | C48: =IFERROR(INDEX('02 MONITOR'!$C$7:$C$106,SUMPRODUCT(('02 MONITOR'!$B$7:$B$106="COMMODITY")*('02 MONITOR'!$P$7:$P$106=5)*(ROW('02 MONITOR'!$B$7:$B$106)-6))),"") | D48: =IFERROR(INDEX('02 MONITOR'!$D$7:$D$106,SUMPRODUCT(('02 MONITOR'!$B$7:$B$106="COMMODITY")*('02 MONITOR'!$P$7:$P$106=5)*(ROW('02 MONITOR'!$B$7:$B$106)-6))),"") | E48: =IFERROR(INDEX('02 MONITOR'!$M$7:$M$106,SUMPRODUCT(('02 MONITOR'!$B$7:$B$106="COMMODITY")*('02 MONITOR'!$P$7:$P$106=5)*(ROW('02 MONITOR'!$B$7:$B$106)-6))),"") | F48: =IFERROR(INDEX('02 MONITOR'!$K$7:$K$106,SUMPRODUCT(('02 MONITOR'!$B$7:$B$106="COMMODITY")*('02 MONITOR'!$P$7:$P$106=5)*(ROW('02 MONITOR'!$B$7:$B$106)-6))),"") | G48: =IFERROR(INDEX('02 MONITOR'!$H$7:$H$106,SUMPRODUCT(('02 MONITOR'!$B$7:$B$106="COMMODITY")*('02 MONITOR'!$P$7:$P$106=5)*(ROW('02 MONITOR'!$B$7:$B$106)-6))),"") | H48: =IFERROR(INDEX('02 MONITOR'!$O$7:$O$106,SUMPRODUCT(('02 MONITOR'!$B$7:$B$106="COMMODITY")*('02 MONITOR'!$P$7:$P$106=5)*(ROW('02 MONITOR'!$B$7:$B$106)-6))),"") | J48: 5 | K48: =IFERROR(INDEX('02 MONITOR'!$C$7:$C$106,SUMPRODUCT(('02 MONITOR'!$B$7:$B$106="COMMODITY")*('02 MONITOR'!$P$7:$P$106=14)*(ROW('02 MONITOR'!$B$7:$B$106)-6))),"") | L48: =IFERROR(INDEX('02 MONITOR'!$D$7:$D$106,SUMPRODUCT(('02 MONITOR'!$B$7:$B$106="COMMODITY")*('02 MONITOR'!$P$7:$P$106=14)*(ROW('02 MONITOR'!$B$7:$B$106)-6))),"") | M48: =IFERROR(INDEX('02 MONITOR'!$M$7:$M$106,SUMPRODUCT(('02 MONITOR'!$B$7:$B$106="COMMODITY")*('02 MONITOR'!$P$7:$P$106=14)*(ROW('02 MONITOR'!$B$7:$B$106)-6))),"") | N48: =IFERROR(INDEX('02 MONITOR'!$K$7:$K$106,SUMPRODUCT(('02 MONITOR'!$B$7:$B$106="COMMODITY")*('02 MONITOR'!$P$7:$P$106=14)*(ROW('02 MONITOR'!$B$7:$B$106)-6))),"") | O48: =IFERROR(INDEX('02 MONITOR'!$H$7:$H$106,SUMPRODUCT(('02 MONITOR'!$B$7:$B$106="COMMODITY")*('02 MONITOR'!$P$7:$P$106=14)*(ROW('02 MONITOR'!$B$7:$B$106)-6))),"") | P48: =IFERROR(INDEX('02 MONITOR'!$O$7:$O$106,SUMPRODUCT(('02 MONITOR'!$B$7:$B$106="COMMODITY")*('02 MONITOR'!$P$7:$P$106=14)*(ROW('02 MONITOR'!$B$7:$B$106)-6))),"")
B49: 6 | C49: =IFERROR(INDEX('02 MONITOR'!$C$7:$C$106,SUMPRODUCT(('02 MONITOR'!$B$7:$B$106="COMMODITY")*('02 MONITOR'!$P$7:$P$106=6)*(ROW('02 MONITOR'!$B$7:$B$106)-6))),"") | D49: =IFERROR(INDEX('02 MONITOR'!$D$7:$D$106,SUMPRODUCT(('02 MONITOR'!$B$7:$B$106="COMMODITY")*('02 MONITOR'!$P$7:$P$106=6)*(ROW('02 MONITOR'!$B$7:$B$106)-6))),"") | E49: =IFERROR(INDEX('02 MONITOR'!$M$7:$M$106,SUMPRODUCT(('02 MONITOR'!$B$7:$B$106="COMMODITY")*('02 MONITOR'!$P$7:$P$106=6)*(ROW('02 MONITOR'!$B$7:$B$106)-6))),"") | F49: =IFERROR(INDEX('02 MONITOR'!$K$7:$K$106,SUMPRODUCT(('02 MONITOR'!$B$7:$B$106="COMMODITY")*('02 MONITOR'!$P$7:$P$106=6)*(ROW('02 MONITOR'!$B$7:$B$106)-6))),"") | G49: =IFERROR(INDEX('02 MONITOR'!$H$7:$H$106,SUMPRODUCT(('02 MONITOR'!$B$7:$B$106="COMMODITY")*('02 MONITOR'!$P$7:$P$106=6)*(ROW('02 MONITOR'!$B$7:$B$106)-6))),"") | H49: =IFERROR(INDEX('02 MONITOR'!$O$7:$O$106,SUMPRODUCT(('02 MONITOR'!$B$7:$B$106="COMMODITY")*('02 MONITOR'!$P$7:$P$106=6)*(ROW('02 MONITOR'!$B$7:$B$106)-6))),"") | J49: 6 | K49: =IFERROR(INDEX('02 MONITOR'!$C$7:$C$106,SUMPRODUCT(('02 MONITOR'!$B$7:$B$106="COMMODITY")*('02 MONITOR'!$P$7:$P$106=13)*(ROW('02 MONITOR'!$B$7:$B$106)-6))),"") | L49: =IFERROR(INDEX('02 MONITOR'!$D$7:$D$106,SUMPRODUCT(('02 MONITOR'!$B$7:$B$106="COMMODITY")*('02 MONITOR'!$P$7:$P$106=13)*(ROW('02 MONITOR'!$B$7:$B$106)-6))),"") | M49: =IFERROR(INDEX('02 MONITOR'!$M$7:$M$106,SUMPRODUCT(('02 MONITOR'!$B$7:$B$106="COMMODITY")*('02 MONITOR'!$P$7:$P$106=13)*(ROW('02 MONITOR'!$B$7:$B$106)-6))),"") | N49: =IFERROR(INDEX('02 MONITOR'!$K$7:$K$106,SUMPRODUCT(('02 MONITOR'!$B$7:$B$106="COMMODITY")*('02 MONITOR'!$P$7:$P$106=13)*(ROW('02 MONITOR'!$B$7:$B$106)-6))),"") | O49: =IFERROR(INDEX('02 MONITOR'!$H$7:$H$106,SUMPRODUCT(('02 MONITOR'!$B$7:$B$106="COMMODITY")*('02 MONITOR'!$P$7:$P$106=13)*(ROW('02 MONITOR'!$B$7:$B$106)-6))),"") | P49: =IFERROR(INDEX('02 MONITOR'!$O$7:$O$106,SUMPRODUCT(('02 MONITOR'!$B$7:$B$106="COMMODITY")*('02 MONITOR'!$P$7:$P$106=13)*(ROW('02 MONITOR'!$B$7:$B$106)-6))),"")

Sheet 04 CROSS-ASSET
A1: CROSS-ASSET RANKING AND THE ±2σ EXTREMES
A2: One global list across all 100 assets. Powerful, popular, and the weakest thing in this workbook — read the warning.
A4: HEALTH WARNING. Ranking a forward P/E z-score against a credit-spread z-score against an FX z-score assumes those four distributions are comparable. They are not. Credit spreads are bounded below and have a fat right tail; equity multiples mean-revert over years, not quarters; FX spot has no anchor at all without a REER or PPP adjustment. A +2σ reading in credit is a much rarer event than a +2σ reading in equity multiples, so the same number carries different information. Use this list to generate questions, not positions. The within-class ranking on tab 03 is what the portfolio on tab 05 is built from, and that is deliberate.
A6: THE ±2σ SCREEN — how many assets are at an extreme right now
B7: Screen | C7: Count
B8: Assets ≥ +2σ CHEAP | E8: =IFERROR(COUNTIF('02 MONITOR'!$M$7:$M$106,">="&SETTINGS_ZC),"")
B9: Assets ≤ −2σ RICH | E9: =IFERROR(COUNTIF('02 MONITOR'!$M$7:$M$106,"<="&SETTINGS_ZR),"")
B10: Assets inside ±0.5σ (no signal) | E10: =IFERROR(COUNTIFS('02 MONITOR'!$M$7:$M$106,">-0.5",'02 MONITOR'!$M$7:$M$106,"<0.5"),"")
B11: Universe with live data | E11: =IFERROR(COUNT('02 MONITOR'!$M$7:$M$106),"")
A13: GLOBAL RANKING — 25 CHEAPEST AND 25 MOST EXPENSIVE ACROSS ALL 100
B14: CHEAPEST OVERALL | C14: Instrument | D14: Ticker | E14: Class | F14: Value score | G14: Percentile | H14: Flag | K14: MOST EXPENSIVE OVERALL | L14: Instrument | M14: Ticker | N14: Class | O14: Value score | P14: Percentile | Q14: Flag
B15: 1 | C15: =IFERROR(INDEX('02 MONITOR'!$C$7:$C$106,SUMPRODUCT(('02 MONITOR'!$U$7:$U$106=1)*(ROW('02 MONITOR'!$B$7:$B$106)-6))),"") | D15: =IFERROR(INDEX('02 MONITOR'!$D$7:$D$106,SUMPRODUCT(('02 MONITOR'!$U$7:$U$106=1)*(ROW('02 MONITOR'!$B$7:$B$106)-6))),"") | E15: =IFERROR(INDEX('02 MONITOR'!$B$7:$B$106,SUMPRODUCT(('02 MONITOR'!$U$7:$U$106=1)*(ROW('02 MONITOR'!$B$7:$B$106)-6))),"") | F15: =IFERROR(INDEX('02 MONITOR'!$M$7:$M$106,SUMPRODUCT(('02 MONITOR'!$U$7:$U$106=1)*(ROW('02 MONITOR'!$B$7:$B$106)-6))),"") | G15: =IFERROR(INDEX('02 MONITOR'!$N$7:$N$106,SUMPRODUCT(('02 MONITOR'!$U$7:$U$106=1)*(ROW('02 MONITOR'!$B$7:$B$106)-6))),"") | H15: =IFERROR(INDEX('02 MONITOR'!$R$7:$R$106,SUMPRODUCT(('02 MONITOR'!$U$7:$U$106=1)*(ROW('02 MONITOR'!$B$7:$B$106)-6))),"") | K15: 1 | L15: =IFERROR(INDEX('02 MONITOR'!$C$7:$C$106,SUMPRODUCT(('02 MONITOR'!$U$7:$U$106=100)*(ROW('02 MONITOR'!$B$7:$B$106)-6))),"") | M15: =IFERROR(INDEX('02 MONITOR'!$D$7:$D$106,SUMPRODUCT(('02 MONITOR'!$U$7:$U$106=100)*(ROW('02 MONITOR'!$B$7:$B$106)-6))),"") | N15: =IFERROR(INDEX('02 MONITOR'!$B$7:$B$106,SUMPRODUCT(('02 MONITOR'!$U$7:$U$106=100)*(ROW('02 MONITOR'!$B$7:$B$106)-6))),"") | O15: =IFERROR(INDEX('02 MONITOR'!$M$7:$M$106,SUMPRODUCT(('02 MONITOR'!$U$7:$U$106=100)*(ROW('02 MONITOR'!$B$7:$B$106)-6))),"") | P15: =IFERROR(INDEX('02 MONITOR'!$N$7:$N$106,SUMPRODUCT(('02 MONITOR'!$U$7:$U$106=100)*(ROW('02 MONITOR'!$B$7:$B$106)-6))),"") | Q15: =IFERROR(INDEX('02 MONITOR'!$R$7:$R$106,SUMPRODUCT(('02 MONITOR'!$U$7:$U$106=100)*(ROW('02 MONITOR'!$B$7:$B$106)-6))),"")
B16: 2 | C16: =IFERROR(INDEX('02 MONITOR'!$C$7:$C$106,SUMPRODUCT(('02 MONITOR'!$U$7:$U$106=2)*(ROW('02 MONITOR'!$B$7:$B$106)-6))),"") | D16: =IFERROR(INDEX('02 MONITOR'!$D$7:$D$106,SUMPRODUCT(('02 MONITOR'!$U$7:$U$106=2)*(ROW('02 MONITOR'!$B$7:$B$106)-6))),"") | E16: =IFERROR(INDEX('02 MONITOR'!$B$7:$B$106,SUMPRODUCT(('02 MONITOR'!$U$7:$U$106=2)*(ROW('02 MONITOR'!$B$7:$B$106)-6))),"") | F16: =IFERROR(INDEX('02 MONITOR'!$M$7:$M$106,SUMPRODUCT(('02 MONITOR'!$U$7:$U$106=2)*(ROW('02 MONITOR'!$B$7:$B$106)-6))),"") | G16: =IFERROR(INDEX('02 MONITOR'!$N$7:$N$106,SUMPRODUCT(('02 MONITOR'!$U$7:$U$106=2)*(ROW('02 MONITOR'!$B$7:$B$106)-6))),"") | H16: =IFERROR(INDEX('02 MONITOR'!$R$7:$R$106,SUMPRODUCT(('02 MONITOR'!$U$7:$U$106=2)*(ROW('02 MONITOR'!$B$7:$B$106)-6))),"") | K16: 2 | L16: =IFERROR(INDEX('02 MONITOR'!$C$7:$C$106,SUMPRODUCT(('02 MONITOR'!$U$7:$U$106=99)*(ROW('02 MONITOR'!$B$7:$B$106)-6))),"") | M16: =IFERROR(INDEX('02 MONITOR'!$D$7:$D$106,SUMPRODUCT(('02 MONITOR'!$U$7:$U$106=99)*(ROW('02 MONITOR'!$B$7:$B$106)-6))),"") | N16: =IFERROR(INDEX('02 MONITOR'!$B$7:$B$106,SUMPRODUCT(('02 MONITOR'!$U$7:$U$106=99)*(ROW('02 MONITOR'!$B$7:$B$106)-6))),"") | O16: =IFERROR(INDEX('02 MONITOR'!$M$7:$M$106,SUMPRODUCT(('02 MONITOR'!$U$7:$U$106=99)*(ROW('02 MONITOR'!$B$7:$B$106)-6))),"") | P16: =IFERROR(INDEX('02 MONITOR'!$N$7:$N$106,SUMPRODUCT(('02 MONITOR'!$U$7:$U$106=99)*(ROW('02 MONITOR'!$B$7:$B$106)-6))),"") | Q16: =IFERROR(INDEX('02 MONITOR'!$R$7:$R$106,SUMPRODUCT(('02 MONITOR'!$U$7:$U$106=99)*(ROW('02 MONITOR'!$B$7:$B$106)-6))),"")
B17: 3 | C17: =IFERROR(INDEX('02 MONITOR'!$C$7:$C$106,SUMPRODUCT(('02 MONITOR'!$U$7:$U$106=3)*(ROW('02 MONITOR'!$B$7:$B$106)-6))),"") | D17: =IFERROR(INDEX('02 MONITOR'!$D$7:$D$106,SUMPRODUCT(('02 MONITOR'!$U$7:$U$106=3)*(ROW('02 MONITOR'!$B$7:$B$106)-6))),"") | E17: =IFERROR(INDEX('02 MONITOR'!$B$7:$B$106,SUMPRODUCT(('02 MONITOR'!$U$7:$U$106=3)*(ROW('02 MONITOR'!$B$7:$B$106)-6))),"") | F17: =IFERROR(INDEX('02 MONITOR'!$M$7:$M$106,SUMPRODUCT(('02 MONITOR'!$U$7:$U$106=3)*(ROW('02 MONITOR'!$B$7:$B$106)-6))),"") | G17: =IFERROR(INDEX('02 MONITOR'!$N$7:$N$106,SUMPRODUCT(('02 MONITOR'!$U$7:$U$106=3)*(ROW('02 MONITOR'!$B$7:$B$106)-6))),"") | H17: =IFERROR(INDEX('02 MONITOR'!$R$7:$R$106,SUMPRODUCT(('02 MONITOR'!$U$7:$U$106=3)*(ROW('02 MONITOR'!$B$7:$B$106)-6))),"") | K17: 3 | L17: =IFERROR(INDEX('02 MONITOR'!$C$7:$C$106,SUMPRODUCT(('02 MONITOR'!$U$7:$U$106=98)*(ROW('02 MONITOR'!$B$7:$B$106)-6))),"") | M17: =IFERROR(INDEX('02 MONITOR'!$D$7:$D$106,SUMPRODUCT(('02 MONITOR'!$U$7:$U$106=98)*(ROW('02 MONITOR'!$B$7:$B$106)-6))),"") | N17: =IFERROR(INDEX('02 MONITOR'!$B$7:$B$106,SUMPRODUCT(('02 MONITOR'!$U$7:$U$106=98)*(ROW('02 MONITOR'!$B$7:$B$106)-6))),"") | O17: =IFERROR(INDEX('02 MONITOR'!$M$7:$M$106,SUMPRODUCT(('02 MONITOR'!$U$7:$U$106=98)*(ROW('02 MONITOR'!$B$7:$B$106)-6))),"") | P17: =IFERROR(INDEX('02 MONITOR'!$N$7:$N$106,SUMPRODUCT(('02 MONITOR'!$U$7:$U$106=98)*(ROW('02 MONITOR'!$B$7:$B$106)-6))),"") | Q17: =IFERROR(INDEX('02 MONITOR'!$R$7:$R$106,SUMPRODUCT(('02 MONITOR'!$U$7:$U$106=98)*(ROW('02 MONITOR'!$B$7:$B$106)-6))),"")
B18: 4 | C18: =IFERROR(INDEX('02 MONITOR'!$C$7:$C$106,SUMPRODUCT(('02 MONITOR'!$U$7:$U$106=4)*(ROW('02 MONITOR'!$B$7:$B$106)-6))),"") | D18: =IFERROR(INDEX('02 MONITOR'!$D$7:$D$106,SUMPRODUCT(('02 MONITOR'!$U$7:$U$106=4)*(ROW('02 MONITOR'!$B$7:$B$106)-6))),"") | E18: =IFERROR(INDEX('02 MONITOR'!$B$7:$B$106,SUMPRODUCT(('02 MONITOR'!$U$7:$U$106=4)*(ROW('02 MONITOR'!$B$7:$B$106)-6))),"") | F18: =IFERROR(INDEX('02 MONITOR'!$M$7:$M$106,SUMPRODUCT(('02 MONITOR'!$U$7:$U$106=4)*(ROW('02 MONITOR'!$B$7:$B$106)-6))),"") | G18: =IFERROR(INDEX('02 MONITOR'!$N$7:$N$106,SUMPRODUCT(('02 MONITOR'!$U$7:$U$106=4)*(ROW('02 MONITOR'!$B$7:$B$106)-6))),"") | H18: =IFERROR(INDEX('02 MONITOR'!$R$7:$R$106,SUMPRODUCT(('02 MONITOR'!$U$7:$U$106=4)*(ROW('02 MONITOR'!$B$7:$B$106)-6))),"") | K18: 4 | L18: =IFERROR(INDEX('02 MONITOR'!$C$7:$C$106,SUMPRODUCT(('02 MONITOR'!$U$7:$U$106=97)*(ROW('02 MONITOR'!$B$7:$B$106)-6))),"") | M18: =IFERROR(INDEX('02 MONITOR'!$D$7:$D$106,SUMPRODUCT(('02 MONITOR'!$U$7:$U$106=97)*(ROW('02 MONITOR'!$B$7:$B$106)-6))),"") | N18: =IFERROR(INDEX('02 MONITOR'!$B$7:$B$106,SUMPRODUCT(('02 MONITOR'!$U$7:$U$106=97)*(ROW('02 MONITOR'!$B$7:$B$106)-6))),"") | O18: =IFERROR(INDEX('02 MONITOR'!$M$7:$M$106,SUMPRODUCT(('02 MONITOR'!$U$7:$U$106=97)*(ROW('02 MONITOR'!$B$7:$B$106)-6))),"") | P18: =IFERROR(INDEX('02 MONITOR'!$N$7:$N$106,SUMPRODUCT(('02 MONITOR'!$U$7:$U$106=97)*(ROW('02 MONITOR'!$B$7:$B$106)-6))),"") | Q18: =IFERROR(INDEX('02 MONITOR'!$R$7:$R$106,SUMPRODUCT(('02 MONITOR'!$U$7:$U$106=97)*(ROW('02 MONITOR'!$B$7:$B$106)-6))),"")
B19: 5 | C19: =IFERROR(INDEX('02 MONITOR'!$C$7:$C$106,SUMPRODUCT(('02 MONITOR'!$U$7:$U$106=5)*(ROW('02 MONITOR'!$B$7:$B$106)-6))),"") | D19: =IFERROR(INDEX('02 MONITOR'!$D$7:$D$106,SUMPRODUCT(('02 MONITOR'!$U$7:$U$106=5)*(ROW('02 MONITOR'!$B$7:$B$106)-6))),"") | E19: =IFERROR(INDEX('02 MONITOR'!$B$7:$B$106,SUMPRODUCT(('02 MONITOR'!$U$7:$U$106=5)*(ROW('02 MONITOR'!$B$7:$B$106)-6))),"") | F19: =IFERROR(INDEX('02 MONITOR'!$M$7:$M$106,SUMPRODUCT(('02 MONITOR'!$U$7:$U$106=5)*(ROW('02 MONITOR'!$B$7:$B$106)-6))),"") | G19: =IFERROR(INDEX('02 MONITOR'!$N$7:$N$106,SUMPRODUCT(('02 MONITOR'!$U$7:$U$106=5)*(ROW('02 MONITOR'!$B$7:$B$106)-6))),"") | H19: =IFERROR(INDEX('02 MONITOR'!$R$7:$R$106,SUMPRODUCT(('02 MONITOR'!$U$7:$U$106=5)*(ROW('02 MONITOR'!$B$7:$B$106)-6))),"") | K19: 5 | L19: =IFERROR(INDEX('02 MONITOR'!$C$7:$C$106,SUMPRODUCT(('02 MONITOR'!$U$7:$U$106=96)*(ROW('02 MONITOR'!$B$7:$B$106)-6))),"") | M19: =IFERROR(INDEX('02 MONITOR'!$D$7:$D$106,SUMPRODUCT(('02 MONITOR'!$U$7:$U$106=96)*(ROW('02 MONITOR'!$B$7:$B$106)-6))),"") | N19: =IFERROR(INDEX('02 MONITOR'!$B$7:$B$106,SUMPRODUCT(('02 MONITOR'!$U$7:$U$106=96)*(ROW('02 MONITOR'!$B$7:$B$106)-6))),"") | O19: =IFERROR(INDEX('02 MONITOR'!$M$7:$M$106,SUMPRODUCT(('02 MONITOR'!$U$7:$U$106=96)*(ROW('02 MONITOR'!$B$7:$B$106)-6))),"") | P19: =IFERROR(INDEX('02 MONITOR'!$N$7:$N$106,SUMPRODUCT(('02 MONITOR'!$U$7:$U$106=96)*(ROW('02 MONITOR'!$B$7:$B$106)-6))),"") | Q19: =IFERROR(INDEX('02 MONITOR'!$R$7:$R$106,SUMPRODUCT(('02 MONITOR'!$U$7:$U$106=96)*(ROW('02 MONITOR'!$B$7:$B$106)-6))),"")
B20: 6 | C20: =IFERROR(INDEX('02 MONITOR'!$C$7:$C$106,SUMPRODUCT(('02 MONITOR'!$U$7:$U$106=6)*(ROW('02 MONITOR'!$B$7:$B$106)-6))),"") | D20: =IFERROR(INDEX('02 MONITOR'!$D$7:$D$106,SUMPRODUCT(('02 MONITOR'!$U$7:$U$106=6)*(ROW('02 MONITOR'!$B$7:$B$106)-6))),"") | E20: =IFERROR(INDEX('02 MONITOR'!$B$7:$B$106,SUMPRODUCT(('02 MONITOR'!$U$7:$U$106=6)*(ROW('02 MONITOR'!$B$7:$B$106)-6))),"") | F20: =IFERROR(INDEX('02 MONITOR'!$M$7:$M$106,SUMPRODUCT(('02 MONITOR'!$U$7:$U$106=6)*(ROW('02 MONITOR'!$B$7:$B$106)-6))),"") | G20: =IFERROR(INDEX('02 MONITOR'!$N$7:$N$106,SUMPRODUCT(('02 MONITOR'!$U$7:$U$106=6)*(ROW('02 MONITOR'!$B$7:$B$106)-6))),"") | H20: =IFERROR(INDEX('02 MONITOR'!$R$7:$R$106,SUMPRODUCT(('02 MONITOR'!$U$7:$U$106=6)*(ROW('02 MONITOR'!$B$7:$B$106)-6))),"") | K20: 6 | L20: =IFERROR(INDEX('02 MONITOR'!$C$7:$C$106,SUMPRODUCT(('02 MONITOR'!$U$7:$U$106=95)*(ROW('02 MONITOR'!$B$7:$B$106)-6))),"") | M20: =IFERROR(INDEX('02 MONITOR'!$D$7:$D$106,SUMPRODUCT(('02 MONITOR'!$U$7:$U$106=95)*(ROW('02 MONITOR'!$B$7:$B$106)-6))),"") | N20: =IFERROR(INDEX('02 MONITOR'!$B$7:$B$106,SUMPRODUCT(('02 MONITOR'!$U$7:$U$106=95)*(ROW('02 MONITOR'!$B$7:$B$106)-6))),"") | O20: =IFERROR(INDEX('02 MONITOR'!$M$7:$M$106,SUMPRODUCT(('02 MONITOR'!$U$7:$U$106=95)*(ROW('02 MONITOR'!$B$7:$B$106)-6))),"") | P20: =IFERROR(INDEX('02 MONITOR'!$N$7:$N$106,SUMPRODUCT(('02 MONITOR'!$U$7:$U$106=95)*(ROW('02 MONITOR'!$B$7:$B$106)-6))),"") | Q20: =IFERROR(INDEX('02 MONITOR'!$R$7:$R$106,SUMPRODUCT(('02 MONITOR'!$U$7:$U$106=95)*(ROW('02 MONITOR'!$B$7:$B$106)-6))),"")
B21: 7 | C21: =IFERROR(INDEX('02 MONITOR'!$C$7:$C$106,SUMPRODUCT(('02 MONITOR'!$U$7:$U$106=7)*(ROW('02 MONITOR'!$B$7:$B$106)-6))),"") | D21: =IFERROR(INDEX('02 MONITOR'!$D$7:$D$106,SUMPRODUCT(('02 MONITOR'!$U$7:$U$106=7)*(ROW('02 MONITOR'!$B$7:$B$106)-6))),"") | E21: =IFERROR(INDEX('02 MONITOR'!$B$7:$B$106,SUMPRODUCT(('02 MONITOR'!$U$7:$U$106=7)*(ROW('02 MONITOR'!$B$7:$B$106)-6))),"") | F21: =IFERROR(INDEX('02 MONITOR'!$M$7:$M$106,SUMPRODUCT(('02 MONITOR'!$U$7:$U$106=7)*(ROW('02 MONITOR'!$B$7:$B$106)-6))),"") | G21: =IFERROR(INDEX('02 MONITOR'!$N$7:$N$106,SUMPRODUCT(('02 MONITOR'!$U$7:$U$106=7)*(ROW('02 MONITOR'!$B$7:$B$106)-6))),"") | H21: =IFERROR(INDEX('02 MONITOR'!$R$7:$R$106,SUMPRODUCT(('02 MONITOR'!$U$7:$U$106=7)*(ROW('02 MONITOR'!$B$7:$B$106)-6))),"") | K21: 7 | L21: =IFERROR(INDEX('02 MONITOR'!$C$7:$C$106,SUMPRODUCT(('02 MONITOR'!$U$7:$U$106=94)*(ROW('02 MONITOR'!$B$7:$B$106)-6))),"") | M21: =IFERROR(INDEX('02 MONITOR'!$D$7:$D$106,SUMPRODUCT(('02 MONITOR'!$U$7:$U$106=94)*(ROW('02 MONITOR'!$B$7:$B$106)-6))),"") | N21: =IFERROR(INDEX('02 MONITOR'!$B$7:$B$106,SUMPRODUCT(('02 MONITOR'!$U$7:$U$106=94)*(ROW('02 MONITOR'!$B$7:$B$106)-6))),"") | O21: =IFERROR(INDEX('02 MONITOR'!$M$7:$M$106,SUMPRODUCT(('02 MONITOR'!$U$7:$U$106=94)*(ROW('02 MONITOR'!$B$7:$B$106)-6))),"") | P21: =IFERROR(INDEX('02 MONITOR'!$N$7:$N$106,SUMPRODUCT(('02 MONITOR'!$U$7:$U$106=94)*(ROW('02 MONITOR'!$B$7:$B$106)-6))),"") | Q21: =IFERROR(INDEX('02 MONITOR'!$R$7:$R$106,SUMPRODUCT(('02 MONITOR'!$U$7:$U$106=94)*(ROW('02 MONITOR'!$B$7:$B$106)-6))),"")
B22: 8 | C22: =IFERROR(INDEX('02 MONITOR'!$C$7:$C$106,SUMPRODUCT(('02 MONITOR'!$U$7:$U$106=8)*(ROW('02 MONITOR'!$B$7:$B$106)-6))),"") | D22: =IFERROR(INDEX('02 MONITOR'!$D$7:$D$106,SUMPRODUCT(('02 MONITOR'!$U$7:$U$106=8)*(ROW('02 MONITOR'!$B$7:$B$106)-6))),"") | E22: =IFERROR(INDEX('02 MONITOR'!$B$7:$B$106,SUMPRODUCT(('02 MONITOR'!$U$7:$U$106=8)*(ROW('02 MONITOR'!$B$7:$B$106)-6))),"") | F22: =IFERROR(INDEX('02 MONITOR'!$M$7:$M$106,SUMPRODUCT(('02 MONITOR'!$U$7:$U$106=8)*(ROW('02 MONITOR'!$B$7:$B$106)-6))),"") | G22: =IFERROR(INDEX('02 MONITOR'!$N$7:$N$106,SUMPRODUCT(('02 MONITOR'!$U$7:$U$106=8)*(ROW('02 MONITOR'!$B$7:$B$106)-6))),"") | H22: =IFERROR(INDEX('02 MONITOR'!$R$7:$R$106,SUMPRODUCT(('02 MONITOR'!$U$7:$U$106=8)*(ROW('02 MONITOR'!$B$7:$B$106)-6))),"") | K22: 8 | L22: =IFERROR(INDEX('02 MONITOR'!$C$7:$C$106,SUMPRODUCT(('02 MONITOR'!$U$7:$U$106=93)*(ROW('02 MONITOR'!$B$7:$B$106)-6))),"") | M22: =IFERROR(INDEX('02 MONITOR'!$D$7:$D$106,SUMPRODUCT(('02 MONITOR'!$U$7:$U$106=93)*(ROW('02 MONITOR'!$B$7:$B$106)-6))),"") | N22: =IFERROR(INDEX('02 MONITOR'!$B$7:$B$106,SUMPRODUCT(('02 MONITOR'!$U$7:$U$106=93)*(ROW('02 MONITOR'!$B$7:$B$106)-6))),"") | O22: =IFERROR(INDEX('02 MONITOR'!$M$7:$M$106,SUMPRODUCT(('02 MONITOR'!$U$7:$U$106=93)*(ROW('02 MONITOR'!$B$7:$B$106)-6))),"") | P22: =IFERROR(INDEX('02 MONITOR'!$N$7:$N$106,SUMPRODUCT(('02 MONITOR'!$U$7:$U$106=93)*(ROW('02 MONITOR'!$B$7:$B$106)-6))),"") | Q22: =IFERROR(INDEX('02 MONITOR'!$R$7:$R$106,SUMPRODUCT(('02 MONITOR'!$U$7:$U$106=93)*(ROW('02 MONITOR'!$B$7:$B$106)-6))),"")
B23: 9 | C23: =IFERROR(INDEX('02 MONITOR'!$C$7:$C$106,SUMPRODUCT(('02 MONITOR'!$U$7:$U$106=9)*(ROW('02 MONITOR'!$B$7:$B$106)-6))),"") | D23: =IFERROR(INDEX('02 MONITOR'!$D$7:$D$106,SUMPRODUCT(('02 MONITOR'!$U$7:$U$106=9)*(ROW('02 MONITOR'!$B$7:$B$106)-6))),"") | E23: =IFERROR(INDEX('02 MONITOR'!$B$7:$B$106,SUMPRODUCT(('02 MONITOR'!$U$7:$U$106=9)*(ROW('02 MONITOR'!$B$7:$B$106)-6))),"") | F23: =IFERROR(INDEX('02 MONITOR'!$M$7:$M$106,SUMPRODUCT(('02 MONITOR'!$U$7:$U$106=9)*(ROW('02 MONITOR'!$B$7:$B$106)-6))),"") | G23: =IFERROR(INDEX('02 MONITOR'!$N$7:$N$106,SUMPRODUCT(('02 MONITOR'!$U$7:$U$106=9)*(ROW('02 MONITOR'!$B$7:$B$106)-6))),"") | H23: =IFERROR(INDEX('02 MONITOR'!$R$7:$R$106,SUMPRODUCT(('02 MONITOR'!$U$7:$U$106=9)*(ROW('02 MONITOR'!$B$7:$B$106)-6))),"") | K23: 9 | L23: =IFERROR(INDEX('02 MONITOR'!$C$7:$C$106,SUMPRODUCT(('02 MONITOR'!$U$7:$U$106=92)*(ROW('02 MONITOR'!$B$7:$B$106)-6))),"") | M23: =IFERROR(INDEX('02 MONITOR'!$D$7:$D$106,SUMPRODUCT(('02 MONITOR'!$U$7:$U$106=92)*(ROW('02 MONITOR'!$B$7:$B$106)-6))),"") | N23: =IFERROR(INDEX('02 MONITOR'!$B$7:$B$106,SUMPRODUCT(('02 MONITOR'!$U$7:$U$106=92)*(ROW('02 MONITOR'!$B$7:$B$106)-6))),"") | O23: =IFERROR(INDEX('02 MONITOR'!$M$7:$M$106,SUMPRODUCT(('02 MONITOR'!$U$7:$U$106=92)*(ROW('02 MONITOR'!$B$7:$B$106)-6))),"") | P23: =IFERROR(INDEX('02 MONITOR'!$N$7:$N$106,SUMPRODUCT(('02 MONITOR'!$U$7:$U$106=92)*(ROW('02 MONITOR'!$B$7:$B$106)-6))),"") | Q23: =IFERROR(INDEX('02 MONITOR'!$R$7:$R$106,SUMPRODUCT(('02 MONITOR'!$U$7:$U$106=92)*(ROW('02 MONITOR'!$B$7:$B$106)-6))),"")
B24: 10 | C24: =IFERROR(INDEX('02 MONITOR'!$C$7:$C$106,SUMPRODUCT(('02 MONITOR'!$U$7:$U$106=10)*(ROW('02 MONITOR'!$B$7:$B$106)-6))),"") | D24: =IFERROR(INDEX('02 MONITOR'!$D$7:$D$106,SUMPRODUCT(('02 MONITOR'!$U$7:$U$106=10)*(ROW('02 MONITOR'!$B$7:$B$106)-6))),"") | E24: =IFERROR(INDEX('02 MONITOR'!$B$7:$B$106,SUMPRODUCT(('02 MONITOR'!$U$7:$U$106=10)*(ROW('02 MONITOR'!$B$7:$B$106)-6))),"") | F24: =IFERROR(INDEX('02 MONITOR'!$M$7:$M$106,SUMPRODUCT(('02 MONITOR'!$U$7:$U$106=10)*(ROW('02 MONITOR'!$B$7:$B$106)-6))),"") | G24: =IFERROR(INDEX('02 MONITOR'!$N$7:$N$106,SUMPRODUCT(('02 MONITOR'!$U$7:$U$106=10)*(ROW('02 MONITOR'!$B$7:$B$106)-6))),"") | H24: =IFERROR(INDEX('02 MONITOR'!$R$7:$R$106,SUMPRODUCT(('02 MONITOR'!$U$7:$U$106=10)*(ROW('02 MONITOR'!$B$7:$B$106)-6))),"") | K24: 10 | L24: =IFERROR(INDEX('02 MONITOR'!$C$7:$C$106,SUMPRODUCT(('02 MONITOR'!$U$7:$U$106=91)*(ROW('02 MONITOR'!$B$7:$B$106)-6))),"") | M24: =IFERROR(INDEX('02 MONITOR'!$D$7:$D$106,SUMPRODUCT(('02 MONITOR'!$U$7:$U$106=91)*(ROW('02 MONITOR'!$B$7:$B$106)-6))),"") | N24: =IFERROR(INDEX('02 MONITOR'!$B$7:$B$106,SUMPRODUCT(('02 MONITOR'!$U$7:$U$106=91)*(ROW('02 MONITOR'!$B$7:$B$106)-6))),"") | O24: =IFERROR(INDEX('02 MONITOR'!$M$7:$M$106,SUMPRODUCT(('02 MONITOR'!$U$7:$U$106=91)*(ROW('02 MONITOR'!$B$7:$B$106)-6))),"") | P24: =IFERROR(INDEX('02 MONITOR'!$N$7:$N$106,SUMPRODUCT(('02 MONITOR'!$U$7:$U$106=91)*(ROW('02 MONITOR'!$B$7:$B$106)-6))),"") | Q24: =IFERROR(INDEX('02 MONITOR'!$R$7:$R$106,SUMPRODUCT(('02 MONITOR'!$U$7:$U$106=91)*(ROW('02 MONITOR'!$B$7:$B$106)-6))),"")
B25: 11 | C25: =IFERROR(INDEX('02 MONITOR'!$C$7:$C$106,SUMPRODUCT(('02 MONITOR'!$U$7:$U$106=11)*(ROW('02 MONITOR'!$B$7:$B$106)-6))),"") | D25: =IFERROR(INDEX('02 MONITOR'!$D$7:$D$106,SUMPRODUCT(('02 MONITOR'!$U$7:$U$106=11)*(ROW('02 MONITOR'!$B$7:$B$106)-6))),"") | E25: =IFERROR(INDEX('02 MONITOR'!$B$7:$B$106,SUMPRODUCT(('02 MONITOR'!$U$7:$U$106=11)*(ROW('02 MONITOR'!$B$7:$B$106)-6))),"") | F25: =IFERROR(INDEX('02 MONITOR'!$M$7:$M$106,SUMPRODUCT(('02 MONITOR'!$U$7:$U$106=11)*(ROW('02 MONITOR'!$B$7:$B$106)-6))),"") | G25: =IFERROR(INDEX('02 MONITOR'!$N$7:$N$106,SUMPRODUCT(('02 MONITOR'!$U$7:$U$106=11)*(ROW('02 MONITOR'!$B$7:$B$106)-6))),"") | H25: =IFERROR(INDEX('02 MONITOR'!$R$7:$R$106,SUMPRODUCT(('02 MONITOR'!$U$7:$U$106=11)*(ROW('02 MONITOR'!$B$7:$B$106)-6))),"") | K25: 11 | L25: =IFERROR(INDEX('02 MONITOR'!$C$7:$C$106,SUMPRODUCT(('02 MONITOR'!$U$7:$U$106=90)*(ROW('02 MONITOR'!$B$7:$B$106)-6))),"") | M25: =IFERROR(INDEX('02 MONITOR'!$D$7:$D$106,SUMPRODUCT(('02 MONITOR'!$U$7:$U$106=90)*(ROW('02 MONITOR'!$B$7:$B$106)-6))),"") | N25: =IFERROR(INDEX('02 MONITOR'!$B$7:$B$106,SUMPRODUCT(('02 MONITOR'!$U$7:$U$106=90)*(ROW('02 MONITOR'!$B$7:$B$106)-6))),"") | O25: =IFERROR(INDEX('02 MONITOR'!$M$7:$M$106,SUMPRODUCT(('02 MONITOR'!$U$7:$U$106=90)*(ROW('02 MONITOR'!$B$7:$B$106)-6))),"") | P25: =IFERROR(INDEX('02 MONITOR'!$N$7:$N$106,SUMPRODUCT(('02 MONITOR'!$U$7:$U$106=90)*(ROW('02 MONITOR'!$B$7:$B$106)-6))),"") | Q25: =IFERROR(INDEX('02 MONITOR'!$R$7:$R$106,SUMPRODUCT(('02 MONITOR'!$U$7:$U$106=90)*(ROW('02 MONITOR'!$B$7:$B$106)-6))),"")
B26: 12 | C26: =IFERROR(INDEX('02 MONITOR'!$C$7:$C$106,SUMPRODUCT(('02 MONITOR'!$U$7:$U$106=12)*(ROW('02 MONITOR'!$B$7:$B$106)-6))),"") | D26: =IFERROR(INDEX('02 MONITOR'!$D$7:$D$106,SUMPRODUCT(('02 MONITOR'!$U$7:$U$106=12)*(ROW('02 MONITOR'!$B$7:$B$106)-6))),"") | E26: =IFERROR(INDEX('02 MONITOR'!$B$7:$B$106,SUMPRODUCT(('02 MONITOR'!$U$7:$U$106=12)*(ROW('02 MONITOR'!$B$7:$B$106)-6))),"") | F26: =IFERROR(INDEX('02 MONITOR'!$M$7:$M$106,SUMPRODUCT(('02 MONITOR'!$U$7:$U$106=12)*(ROW('02 MONITOR'!$B$7:$B$106)-6))),"") | G26: =IFERROR(INDEX('02 MONITOR'!$N$7:$N$106,SUMPRODUCT(('02 MONITOR'!$U$7:$U$106=12)*(ROW('02 MONITOR'!$B$7:$B$106)-6))),"") | H26: =IFERROR(INDEX('02 MONITOR'!$R$7:$R$106,SUMPRODUCT(('02 MONITOR'!$U$7:$U$106=12)*(ROW('02 MONITOR'!$B$7:$B$106)-6))),"") | K26: 12 | L26: =IFERROR(INDEX('02 MONITOR'!$C$7:$C$106,SUMPRODUCT(('02 MONITOR'!$U$7:$U$106=89)*(ROW('02 MONITOR'!$B$7:$B$106)-6))),"") | M26: =IFERROR(INDEX('02 MONITOR'!$D$7:$D$106,SUMPRODUCT(('02 MONITOR'!$U$7:$U$106=89)*(ROW('02 MONITOR'!$B$7:$B$106)-6))),"") | N26: =IFERROR(INDEX('02 MONITOR'!$B$7:$B$106,SUMPRODUCT(('02 MONITOR'!$U$7:$U$106=89)*(ROW('02 MONITOR'!$B$7:$B$106)-6))),"") | O26: =IFERROR(INDEX('02 MONITOR'!$M$7:$M$106,SUMPRODUCT(('02 MONITOR'!$U$7:$U$106=89)*(ROW('02 MONITOR'!$B$7:$B$106)-6))),"") | P26: =IFERROR(INDEX('02 MONITOR'!$N$7:$N$106,SUMPRODUCT(('02 MONITOR'!$U$7:$U$106=89)*(ROW('02 MONITOR'!$B$7:$B$106)-6))),"") | Q26: =IFERROR(INDEX('02 MONITOR'!$R$7:$R$106,SUMPRODUCT(('02 MONITOR'!$U$7:$U$106=89)*(ROW('02 MONITOR'!$B$7:$B$106)-6))),"")
B27: 13 | C27: =IFERROR(INDEX('02 MONITOR'!$C$7:$C$106,SUMPRODUCT(('02 MONITOR'!$U$7:$U$106=13)*(ROW('02 MONITOR'!$B$7:$B$106)-6))),"") | D27: =IFERROR(INDEX('02 MONITOR'!$D$7:$D$106,SUMPRODUCT(('02 MONITOR'!$U$7:$U$106=13)*(ROW('02 MONITOR'!$B$7:$B$106)-6))),"") | E27: =IFERROR(INDEX('02 MONITOR'!$B$7:$B$106,SUMPRODUCT(('02 MONITOR'!$U$7:$U$106=13)*(ROW('02 MONITOR'!$B$7:$B$106)-6))),"") | F27: =IFERROR(INDEX('02 MONITOR'!$M$7:$M$106,SUMPRODUCT(('02 MONITOR'!$U$7:$U$106=13)*(ROW('02 MONITOR'!$B$7:$B$106)-6))),"") | G27: =IFERROR(INDEX('02 MONITOR'!$N$7:$N$106,SUMPRODUCT(('02 MONITOR'!$U$7:$U$106=13)*(ROW('02 MONITOR'!$B$7:$B$106)-6))),"") | H27: =IFERROR(INDEX('02 MONITOR'!$R$7:$R$106,SUMPRODUCT(('02 MONITOR'!$U$7:$U$106=13)*(ROW('02 MONITOR'!$B$7:$B$106)-6))),"") | K27: 13 | L27: =IFERROR(INDEX('02 MONITOR'!$C$7:$C$106,SUMPRODUCT(('02 MONITOR'!$U$7:$U$106=88)*(ROW('02 MONITOR'!$B$7:$B$106)-6))),"") | M27: =IFERROR(INDEX('02 MONITOR'!$D$7:$D$106,SUMPRODUCT(('02 MONITOR'!$U$7:$U$106=88)*(ROW('02 MONITOR'!$B$7:$B$106)-6))),"") | N27: =IFERROR(INDEX('02 MONITOR'!$B$7:$B$106,SUMPRODUCT(('02 MONITOR'!$U$7:$U$106=88)*(ROW('02 MONITOR'!$B$7:$B$106)-6))),"") | O27: =IFERROR(INDEX('02 MONITOR'!$M$7:$M$106,SUMPRODUCT(('02 MONITOR'!$U$7:$U$106=88)*(ROW('02 MONITOR'!$B$7:$B$106)-6))),"") | P27: =IFERROR(INDEX('02 MONITOR'!$N$7:$N$106,SUMPRODUCT(('02 MONITOR'!$U$7:$U$106=88)*(ROW('02 MONITOR'!$B$7:$B$106)-6))),"") | Q27: =IFERROR(INDEX('02 MONITOR'!$R$7:$R$106,SUMPRODUCT(('02 MONITOR'!$U$7:$U$106=88)*(ROW('02 MONITOR'!$B$7:$B$106)-6))),"")
B28: 14 | C28: =IFERROR(INDEX('02 MONITOR'!$C$7:$C$106,SUMPRODUCT(('02 MONITOR'!$U$7:$U$106=14)*(ROW('02 MONITOR'!$B$7:$B$106)-6))),"") | D28: =IFERROR(INDEX('02 MONITOR'!$D$7:$D$106,SUMPRODUCT(('02 MONITOR'!$U$7:$U$106=14)*(ROW('02 MONITOR'!$B$7:$B$106)-6))),"") | E28: =IFERROR(INDEX('02 MONITOR'!$B$7:$B$106,SUMPRODUCT(('02 MONITOR'!$U$7:$U$106=14)*(ROW('02 MONITOR'!$B$7:$B$106)-6))),"") | F28: =IFERROR(INDEX('02 MONITOR'!$M$7:$M$106,SUMPRODUCT(('02 MONITOR'!$U$7:$U$106=14)*(ROW('02 MONITOR'!$B$7:$B$106)-6))),"") | G28: =IFERROR(INDEX('02 MONITOR'!$N$7:$N$106,SUMPRODUCT(('02 MONITOR'!$U$7:$U$106=14)*(ROW('02 MONITOR'!$B$7:$B$106)-6))),"") | H28: =IFERROR(INDEX('02 MONITOR'!$R$7:$R$106,SUMPRODUCT(('02 MONITOR'!$U$7:$U$106=14)*(ROW('02 MONITOR'!$B$7:$B$106)-6))),"") | K28: 14 | L28: =IFERROR(INDEX('02 MONITOR'!$C$7:$C$106,SUMPRODUCT(('02 MONITOR'!$U$7:$U$106=87)*(ROW('02 MONITOR'!$B$7:$B$106)-6))),"") | M28: =IFERROR(INDEX('02 MONITOR'!$D$7:$D$106,SUMPRODUCT(('02 MONITOR'!$U$7:$U$106=87)*(ROW('02 MONITOR'!$B$7:$B$106)-6))),"") | N28: =IFERROR(INDEX('02 MONITOR'!$B$7:$B$106,SUMPRODUCT(('02 MONITOR'!$U$7:$U$106=87)*(ROW('02 MONITOR'!$B$7:$B$106)-6))),"") | O28: =IFERROR(INDEX('02 MONITOR'!$M$7:$M$106,SUMPRODUCT(('02 MONITOR'!$U$7:$U$106=87)*(ROW('02 MONITOR'!$B$7:$B$106)-6))),"") | P28: =IFERROR(INDEX('02 MONITOR'!$N$7:$N$106,SUMPRODUCT(('02 MONITOR'!$U$7:$U$106=87)*(ROW('02 MONITOR'!$B$7:$B$106)-6))),"") | Q28: =IFERROR(INDEX('02 MONITOR'!$R$7:$R$106,SUMPRODUCT(('02 MONITOR'!$U$7:$U$106=87)*(ROW('02 MONITOR'!$B$7:$B$106)-6))),"")
B29: 15 | C29: =IFERROR(INDEX('02 MONITOR'!$C$7:$C$106,SUMPRODUCT(('02 MONITOR'!$U$7:$U$106=15)*(ROW('02 MONITOR'!$B$7:$B$106)-6))),"") | D29: =IFERROR(INDEX('02 MONITOR'!$D$7:$D$106,SUMPRODUCT(('02 MONITOR'!$U$7:$U$106=15)*(ROW('02 MONITOR'!$B$7:$B$106)-6))),"") | E29: =IFERROR(INDEX('02 MONITOR'!$B$7:$B$106,SUMPRODUCT(('02 MONITOR'!$U$7:$U$106=15)*(ROW('02 MONITOR'!$B$7:$B$106)-6))),"") | F29: =IFERROR(INDEX('02 MONITOR'!$M$7:$M$106,SUMPRODUCT(('02 MONITOR'!$U$7:$U$106=15)*(ROW('02 MONITOR'!$B$7:$B$106)-6))),"") | G29: =IFERROR(INDEX('02 MONITOR'!$N$7:$N$106,SUMPRODUCT(('02 MONITOR'!$U$7:$U$106=15)*(ROW('02 MONITOR'!$B$7:$B$106)-6))),"") | H29: =IFERROR(INDEX('02 MONITOR'!$R$7:$R$106,SUMPRODUCT(('02 MONITOR'!$U$7:$U$106=15)*(ROW('02 MONITOR'!$B$7:$B$106)-6))),"") | K29: 15 | L29: =IFERROR(INDEX('02 MONITOR'!$C$7:$C$106,SUMPRODUCT(('02 MONITOR'!$U$7:$U$106=86)*(ROW('02 MONITOR'!$B$7:$B$106)-6))),"") | M29: =IFERROR(INDEX('02 MONITOR'!$D$7:$D$106,SUMPRODUCT(('02 MONITOR'!$U$7:$U$106=86)*(ROW('02 MONITOR'!$B$7:$B$106)-6))),"") | N29: =IFERROR(INDEX('02 MONITOR'!$B$7:$B$106,SUMPRODUCT(('02 MONITOR'!$U$7:$U$106=86)*(ROW('02 MONITOR'!$B$7:$B$106)-6))),"") | O29: =IFERROR(INDEX('02 MONITOR'!$M$7:$M$106,SUMPRODUCT(('02 MONITOR'!$U$7:$U$106=86)*(ROW('02 MONITOR'!$B$7:$B$106)-6))),"") | P29: =IFERROR(INDEX('02 MONITOR'!$N$7:$N$106,SUMPRODUCT(('02 MONITOR'!$U$7:$U$106=86)*(ROW('02 MONITOR'!$B$7:$B$106)-6))),"") | Q29: =IFERROR(INDEX('02 MONITOR'!$R$7:$R$106,SUMPRODUCT(('02 MONITOR'!$U$7:$U$106=86)*(ROW('02 MONITOR'!$B$7:$B$106)-6))),"")
B30: 16 | C30: =IFERROR(INDEX('02 MONITOR'!$C$7:$C$106,SUMPRODUCT(('02 MONITOR'!$U$7:$U$106=16)*(ROW('02 MONITOR'!$B$7:$B$106)-6))),"") | D30: =IFERROR(INDEX('02 MONITOR'!$D$7:$D$106,SUMPRODUCT(('02 MONITOR'!$U$7:$U$106=16)*(ROW('02 MONITOR'!$B$7:$B$106)-6))),"") | E30: =IFERROR(INDEX('02 MONITOR'!$B$7:$B$106,SUMPRODUCT(('02 MONITOR'!$U$7:$U$106=16)*(ROW('02 MONITOR'!$B$7:$B$106)-6))),"") | F30: =IFERROR(INDEX('02 MONITOR'!$M$7:$M$106,SUMPRODUCT(('02 MONITOR'!$U$7:$U$106=16)*(ROW('02 MONITOR'!$B$7:$B$106)-6))),"") | G30: =IFERROR(INDEX('02 MONITOR'!$N$7:$N$106,SUMPRODUCT(('02 MONITOR'!$U$7:$U$106=16)*(ROW('02 MONITOR'!$B$7:$B$106)-6))),"") | H30: =IFERROR(INDEX('02 MONITOR'!$R$7:$R$106,SUMPRODUCT(('02 MONITOR'!$U$7:$U$106=16)*(ROW('02 MONITOR'!$B$7:$B$106)-6))),"") | K30: 16 | L30: =IFERROR(INDEX('02 MONITOR'!$C$7:$C$106,SUMPRODUCT(('02 MONITOR'!$U$7:$U$106=85)*(ROW('02 MONITOR'!$B$7:$B$106)-6))),"") | M30: =IFERROR(INDEX('02 MONITOR'!$D$7:$D$106,SUMPRODUCT(('02 MONITOR'!$U$7:$U$106=85)*(ROW('02 MONITOR'!$B$7:$B$106)-6))),"") | N30: =IFERROR(INDEX('02 MONITOR'!$B$7:$B$106,SUMPRODUCT(('02 MONITOR'!$U$7:$U$106=85)*(ROW('02 MONITOR'!$B$7:$B$106)-6))),"") | O30: =IFERROR(INDEX('02 MONITOR'!$M$7:$M$106,SUMPRODUCT(('02 MONITOR'!$U$7:$U$106=85)*(ROW('02 MONITOR'!$B$7:$B$106)-6))),"") | P30: =IFERROR(INDEX('02 MONITOR'!$N$7:$N$106,SUMPRODUCT(('02 MONITOR'!$U$7:$U$106=85)*(ROW('02 MONITOR'!$B$7:$B$106)-6))),"") | Q30: =IFERROR(INDEX('02 MONITOR'!$R$7:$R$106,SUMPRODUCT(('02 MONITOR'!$U$7:$U$106=85)*(ROW('02 MONITOR'!$B$7:$B$106)-6))),"")
B31: 17 | C31: =IFERROR(INDEX('02 MONITOR'!$C$7:$C$106,SUMPRODUCT(('02 MONITOR'!$U$7:$U$106=17)*(ROW('02 MONITOR'!$B$7:$B$106)-6))),"") | D31: =IFERROR(INDEX('02 MONITOR'!$D$7:$D$106,SUMPRODUCT(('02 MONITOR'!$U$7:$U$106=17)*(ROW('02 MONITOR'!$B$7:$B$106)-6))),"") | E31: =IFERROR(INDEX('02 MONITOR'!$B$7:$B$106,SUMPRODUCT(('02 MONITOR'!$U$7:$U$106=17)*(ROW('02 MONITOR'!$B$7:$B$106)-6))),"") | F31: =IFERROR(INDEX('02 MONITOR'!$M$7:$M$106,SUMPRODUCT(('02 MONITOR'!$U$7:$U$106=17)*(ROW('02 MONITOR'!$B$7:$B$106)-6))),"") | G31: =IFERROR(INDEX('02 MONITOR'!$N$7:$N$106,SUMPRODUCT(('02 MONITOR'!$U$7:$U$106=17)*(ROW('02 MONITOR'!$B$7:$B$106)-6))),"") | H31: =IFERROR(INDEX('02 MONITOR'!$R$7:$R$106,SUMPRODUCT(('02 MONITOR'!$U$7:$U$106=17)*(ROW('02 MONITOR'!$B$7:$B$106)-6))),"") | K31: 17 | L31: =IFERROR(INDEX('02 MONITOR'!$C$7:$C$106,SUMPRODUCT(('02 MONITOR'!$U$7:$U$106=84)*(ROW('02 MONITOR'!$B$7:$B$106)-6))),"") | M31: =IFERROR(INDEX('02 MONITOR'!$D$7:$D$106,SUMPRODUCT(('02 MONITOR'!$U$7:$U$106=84)*(ROW('02 MONITOR'!$B$7:$B$106)-6))),"") | N31: =IFERROR(INDEX('02 MONITOR'!$B$7:$B$106,SUMPRODUCT(('02 MONITOR'!$U$7:$U$106=84)*(ROW('02 MONITOR'!$B$7:$B$106)-6))),"") | O31: =IFERROR(INDEX('02 MONITOR'!$M$7:$M$106,SUMPRODUCT(('02 MONITOR'!$U$7:$U$106=84)*(ROW('02 MONITOR'!$B$7:$B$106)-6))),"") | P31: =IFERROR(INDEX('02 MONITOR'!$N$7:$N$106,SUMPRODUCT(('02 MONITOR'!$U$7:$U$106=84)*(ROW('02 MONITOR'!$B$7:$B$106)-6))),"") | Q31: =IFERROR(INDEX('02 MONITOR'!$R$7:$R$106,SUMPRODUCT(('02 MONITOR'!$U$7:$U$106=84)*(ROW('02 MONITOR'!$B$7:$B$106)-6))),"")
B32: 18 | C32: =IFERROR(INDEX('02 MONITOR'!$C$7:$C$106,SUMPRODUCT(('02 MONITOR'!$U$7:$U$106=18)*(ROW('02 MONITOR'!$B$7:$B$106)-6))),"") | D32: =IFERROR(INDEX('02 MONITOR'!$D$7:$D$106,SUMPRODUCT(('02 MONITOR'!$U$7:$U$106=18)*(ROW('02 MONITOR'!$B$7:$B$106)-6))),"") | E32: =IFERROR(INDEX('02 MONITOR'!$B$7:$B$106,SUMPRODUCT(('02 MONITOR'!$U$7:$U$106=18)*(ROW('02 MONITOR'!$B$7:$B$106)-6))),"") | F32: =IFERROR(INDEX('02 MONITOR'!$M$7:$M$106,SUMPRODUCT(('02 MONITOR'!$U$7:$U$106=18)*(ROW('02 MONITOR'!$B$7:$B$106)-6))),"") | G32: =IFERROR(INDEX('02 MONITOR'!$N$7:$N$106,SUMPRODUCT(('02 MONITOR'!$U$7:$U$106=18)*(ROW('02 MONITOR'!$B$7:$B$106)-6))),"") | H32: =IFERROR(INDEX('02 MONITOR'!$R$7:$R$106,SUMPRODUCT(('02 MONITOR'!$U$7:$U$106=18)*(ROW('02 MONITOR'!$B$7:$B$106)-6))),"") | K32: 18 | L32: =IFERROR(INDEX('02 MONITOR'!$C$7:$C$106,SUMPRODUCT(('02 MONITOR'!$U$7:$U$106=83)*(ROW('02 MONITOR'!$B$7:$B$106)-6))),"") | M32: =IFERROR(INDEX('02 MONITOR'!$D$7:$D$106,SUMPRODUCT(('02 MONITOR'!$U$7:$U$106=83)*(ROW('02 MONITOR'!$B$7:$B$106)-6))),"") | N32: =IFERROR(INDEX('02 MONITOR'!$B$7:$B$106,SUMPRODUCT(('02 MONITOR'!$U$7:$U$106=83)*(ROW('02 MONITOR'!$B$7:$B$106)-6))),"") | O32: =IFERROR(INDEX('02 MONITOR'!$M$7:$M$106,SUMPRODUCT(('02 MONITOR'!$U$7:$U$106=83)*(ROW('02 MONITOR'!$B$7:$B$106)-6))),"") | P32: =IFERROR(INDEX('02 MONITOR'!$N$7:$N$106,SUMPRODUCT(('02 MONITOR'!$U$7:$U$106=83)*(ROW('02 MONITOR'!$B$7:$B$106)-6))),"") | Q32: =IFERROR(INDEX('02 MONITOR'!$R$7:$R$106,SUMPRODUCT(('02 MONITOR'!$U$7:$U$106=83)*(ROW('02 MONITOR'!$B$7:$B$106)-6))),"")
B33: 19 | C33: =IFERROR(INDEX('02 MONITOR'!$C$7:$C$106,SUMPRODUCT(('02 MONITOR'!$U$7:$U$106=19)*(ROW('02 MONITOR'!$B$7:$B$106)-6))),"") | D33: =IFERROR(INDEX('02 MONITOR'!$D$7:$D$106,SUMPRODUCT(('02 MONITOR'!$U$7:$U$106=19)*(ROW('02 MONITOR'!$B$7:$B$106)-6))),"") | E33: =IFERROR(INDEX('02 MONITOR'!$B$7:$B$106,SUMPRODUCT(('02 MONITOR'!$U$7:$U$106=19)*(ROW('02 MONITOR'!$B$7:$B$106)-6))),"") | F33: =IFERROR(INDEX('02 MONITOR'!$M$7:$M$106,SUMPRODUCT(('02 MONITOR'!$U$7:$U$106=19)*(ROW('02 MONITOR'!$B$7:$B$106)-6))),"") | G33: =IFERROR(INDEX('02 MONITOR'!$N$7:$N$106,SUMPRODUCT(('02 MONITOR'!$U$7:$U$106=19)*(ROW('02 MONITOR'!$B$7:$B$106)-6))),"") | H33: =IFERROR(INDEX('02 MONITOR'!$R$7:$R$106,SUMPRODUCT(('02 MONITOR'!$U$7:$U$106=19)*(ROW('02 MONITOR'!$B$7:$B$106)-6))),"") | K33: 19 | L33: =IFERROR(INDEX('02 MONITOR'!$C$7:$C$106,SUMPRODUCT(('02 MONITOR'!$U$7:$U$106=82)*(ROW('02 MONITOR'!$B$7:$B$106)-6))),"") | M33: =IFERROR(INDEX('02 MONITOR'!$D$7:$D$106,SUMPRODUCT(('02 MONITOR'!$U$7:$U$106=82)*(ROW('02 MONITOR'!$B$7:$B$106)-6))),"") | N33: =IFERROR(INDEX('02 MONITOR'!$B$7:$B$106,SUMPRODUCT(('02 MONITOR'!$U$7:$U$106=82)*(ROW('02 MONITOR'!$B$7:$B$106)-6))),"") | O33: =IFERROR(INDEX('02 MONITOR'!$M$7:$M$106,SUMPRODUCT(('02 MONITOR'!$U$7:$U$106=82)*(ROW('02 MONITOR'!$B$7:$B$106)-6))),"") | P33: =IFERROR(INDEX('02 MONITOR'!$N$7:$N$106,SUMPRODUCT(('02 MONITOR'!$U$7:$U$106=82)*(ROW('02 MONITOR'!$B$7:$B$106)-6))),"") | Q33: =IFERROR(INDEX('02 MONITOR'!$R$7:$R$106,SUMPRODUCT(('02 MONITOR'!$U$7:$U$106=82)*(ROW('02 MONITOR'!$B$7:$B$106)-6))),"")
B34: 20 | C34: =IFERROR(INDEX('02 MONITOR'!$C$7:$C$106,SUMPRODUCT(('02 MONITOR'!$U$7:$U$106=20)*(ROW('02 MONITOR'!$B$7:$B$106)-6))),"") | D34: =IFERROR(INDEX('02 MONITOR'!$D$7:$D$106,SUMPRODUCT(('02 MONITOR'!$U$7:$U$106=20)*(ROW('02 MONITOR'!$B$7:$B$106)-6))),"") | E34: =IFERROR(INDEX('02 MONITOR'!$B$7:$B$106,SUMPRODUCT(('02 MONITOR'!$U$7:$U$106=20)*(ROW('02 MONITOR'!$B$7:$B$106)-6))),"") | F34: =IFERROR(INDEX('02 MONITOR'!$M$7:$M$106,SUMPRODUCT(('02 MONITOR'!$U$7:$U$106=20)*(ROW('02 MONITOR'!$B$7:$B$106)-6))),"") | G34: =IFERROR(INDEX('02 MONITOR'!$N$7:$N$106,SUMPRODUCT(('02 MONITOR'!$U$7:$U$106=20)*(ROW('02 MONITOR'!$B$7:$B$106)-6))),"") | H34: =IFERROR(INDEX('02 MONITOR'!$R$7:$R$106,SUMPRODUCT(('02 MONITOR'!$U$7:$U$106=20)*(ROW('02 MONITOR'!$B$7:$B$106)-6))),"") | K34: 20 | L34: =IFERROR(INDEX('02 MONITOR'!$C$7:$C$106,SUMPRODUCT(('02 MONITOR'!$U$7:$U$106=81)*(ROW('02 MONITOR'!$B$7:$B$106)-6))),"") | M34: =IFERROR(INDEX('02 MONITOR'!$D$7:$D$106,SUMPRODUCT(('02 MONITOR'!$U$7:$U$106=81)*(ROW('02 MONITOR'!$B$7:$B$106)-6))),"") | N34: =IFERROR(INDEX('02 MONITOR'!$B$7:$B$106,SUMPRODUCT(('02 MONITOR'!$U$7:$U$106=81)*(ROW('02 MONITOR'!$B$7:$B$106)-6))),"") | O34: =IFERROR(INDEX('02 MONITOR'!$M$7:$M$106,SUMPRODUCT(('02 MONITOR'!$U$7:$U$106=81)*(ROW('02 MONITOR'!$B$7:$B$106)-6))),"") | P34: =IFERROR(INDEX('02 MONITOR'!$N$7:$N$106,SUMPRODUCT(('02 MONITOR'!$U$7:$U$106=81)*(ROW('02 MONITOR'!$B$7:$B$106)-6))),"") | Q34: =IFERROR(INDEX('02 MONITOR'!$R$7:$R$106,SUMPRODUCT(('02 MONITOR'!$U$7:$U$106=81)*(ROW('02 MONITOR'!$B$7:$B$106)-6))),"")
B35: 21 | C35: =IFERROR(INDEX('02 MONITOR'!$C$7:$C$106,SUMPRODUCT(('02 MONITOR'!$U$7:$U$106=21)*(ROW('02 MONITOR'!$B$7:$B$106)-6))),"") | D35: =IFERROR(INDEX('02 MONITOR'!$D$7:$D$106,SUMPRODUCT(('02 MONITOR'!$U$7:$U$106=21)*(ROW('02 MONITOR'!$B$7:$B$106)-6))),"") | E35: =IFERROR(INDEX('02 MONITOR'!$B$7:$B$106,SUMPRODUCT(('02 MONITOR'!$U$7:$U$106=21)*(ROW('02 MONITOR'!$B$7:$B$106)-6))),"") | F35: =IFERROR(INDEX('02 MONITOR'!$M$7:$M$106,SUMPRODUCT(('02 MONITOR'!$U$7:$U$106=21)*(ROW('02 MONITOR'!$B$7:$B$106)-6))),"") | G35: =IFERROR(INDEX('02 MONITOR'!$N$7:$N$106,SUMPRODUCT(('02 MONITOR'!$U$7:$U$106=21)*(ROW('02 MONITOR'!$B$7:$B$106)-6))),"") | H35: =IFERROR(INDEX('02 MONITOR'!$R$7:$R$106,SUMPRODUCT(('02 MONITOR'!$U$7:$U$106=21)*(ROW('02 MONITOR'!$B$7:$B$106)-6))),"") | K35: 21 | L35: =IFERROR(INDEX('02 MONITOR'!$C$7:$C$106,SUMPRODUCT(('02 MONITOR'!$U$7:$U$106=80)*(ROW('02 MONITOR'!$B$7:$B$106)-6))),"") | M35: =IFERROR(INDEX('02 MONITOR'!$D$7:$D$106,SUMPRODUCT(('02 MONITOR'!$U$7:$U$106=80)*(ROW('02 MONITOR'!$B$7:$B$106)-6))),"") | N35: =IFERROR(INDEX('02 MONITOR'!$B$7:$B$106,SUMPRODUCT(('02 MONITOR'!$U$7:$U$106=80)*(ROW('02 MONITOR'!$B$7:$B$106)-6))),"") | O35: =IFERROR(INDEX('02 MONITOR'!$M$7:$M$106,SUMPRODUCT(('02 MONITOR'!$U$7:$U$106=80)*(ROW('02 MONITOR'!$B$7:$B$106)-6))),"") | P35: =IFERROR(INDEX('02 MONITOR'!$N$7:$N$106,SUMPRODUCT(('02 MONITOR'!$U$7:$U$106=80)*(ROW('02 MONITOR'!$B$7:$B$106)-6))),"") | Q35: =IFERROR(INDEX('02 MONITOR'!$R$7:$R$106,SUMPRODUCT(('02 MONITOR'!$U$7:$U$106=80)*(ROW('02 MONITOR'!$B$7:$B$106)-6))),"")
B36: 22 | C36: =IFERROR(INDEX('02 MONITOR'!$C$7:$C$106,SUMPRODUCT(('02 MONITOR'!$U$7:$U$106=22)*(ROW('02 MONITOR'!$B$7:$B$106)-6))),"") | D36: =IFERROR(INDEX('02 MONITOR'!$D$7:$D$106,SUMPRODUCT(('02 MONITOR'!$U$7:$U$106=22)*(ROW('02 MONITOR'!$B$7:$B$106)-6))),"") | E36: =IFERROR(INDEX('02 MONITOR'!$B$7:$B$106,SUMPRODUCT(('02 MONITOR'!$U$7:$U$106=22)*(ROW('02 MONITOR'!$B$7:$B$106)-6))),"") | F36: =IFERROR(INDEX('02 MONITOR'!$M$7:$M$106,SUMPRODUCT(('02 MONITOR'!$U$7:$U$106=22)*(ROW('02 MONITOR'!$B$7:$B$106)-6))),"") | G36: =IFERROR(INDEX('02 MONITOR'!$N$7:$N$106,SUMPRODUCT(('02 MONITOR'!$U$7:$U$106=22)*(ROW('02 MONITOR'!$B$7:$B$106)-6))),"") | H36: =IFERROR(INDEX('02 MONITOR'!$R$7:$R$106,SUMPRODUCT(('02 MONITOR'!$U$7:$U$106=22)*(ROW('02 MONITOR'!$B$7:$B$106)-6))),"") | K36: 22 | L36: =IFERROR(INDEX('02 MONITOR'!$C$7:$C$106,SUMPRODUCT(('02 MONITOR'!$U$7:$U$106=79)*(ROW('02 MONITOR'!$B$7:$B$106)-6))),"") | M36: =IFERROR(INDEX('02 MONITOR'!$D$7:$D$106,SUMPRODUCT(('02 MONITOR'!$U$7:$U$106=79)*(ROW('02 MONITOR'!$B$7:$B$106)-6))),"") | N36: =IFERROR(INDEX('02 MONITOR'!$B$7:$B$106,SUMPRODUCT(('02 MONITOR'!$U$7:$U$106=79)*(ROW('02 MONITOR'!$B$7:$B$106)-6))),"") | O36: =IFERROR(INDEX('02 MONITOR'!$M$7:$M$106,SUMPRODUCT(('02 MONITOR'!$U$7:$U$106=79)*(ROW('02 MONITOR'!$B$7:$B$106)-6))),"") | P36: =IFERROR(INDEX('02 MONITOR'!$N$7:$N$106,SUMPRODUCT(('02 MONITOR'!$U$7:$U$106=79)*(ROW('02 MONITOR'!$B$7:$B$106)-6))),"") | Q36: =IFERROR(INDEX('02 MONITOR'!$R$7:$R$106,SUMPRODUCT(('02 MONITOR'!$U$7:$U$106=79)*(ROW('02 MONITOR'!$B$7:$B$106)-6))),"")
B37: 23 | C37: =IFERROR(INDEX('02 MONITOR'!$C$7:$C$106,SUMPRODUCT(('02 MONITOR'!$U$7:$U$106=23)*(ROW('02 MONITOR'!$B$7:$B$106)-6))),"") | D37: =IFERROR(INDEX('02 MONITOR'!$D$7:$D$106,SUMPRODUCT(('02 MONITOR'!$U$7:$U$106=23)*(ROW('02 MONITOR'!$B$7:$B$106)-6))),"") | E37: =IFERROR(INDEX('02 MONITOR'!$B$7:$B$106,SUMPRODUCT(('02 MONITOR'!$U$7:$U$106=23)*(ROW('02 MONITOR'!$B$7:$B$106)-6))),"") | F37: =IFERROR(INDEX('02 MONITOR'!$M$7:$M$106,SUMPRODUCT(('02 MONITOR'!$U$7:$U$106=23)*(ROW('02 MONITOR'!$B$7:$B$106)-6))),"") | G37: =IFERROR(INDEX('02 MONITOR'!$N$7:$N$106,SUMPRODUCT(('02 MONITOR'!$U$7:$U$106=23)*(ROW('02 MONITOR'!$B$7:$B$106)-6))),"") | H37: =IFERROR(INDEX('02 MONITOR'!$R$7:$R$106,SUMPRODUCT(('02 MONITOR'!$U$7:$U$106=23)*(ROW('02 MONITOR'!$B$7:$B$106)-6))),"") | K37: 23 | L37: =IFERROR(INDEX('02 MONITOR'!$C$7:$C$106,SUMPRODUCT(('02 MONITOR'!$U$7:$U$106=78)*(ROW('02 MONITOR'!$B$7:$B$106)-6))),"") | M37: =IFERROR(INDEX('02 MONITOR'!$D$7:$D$106,SUMPRODUCT(('02 MONITOR'!$U$7:$U$106=78)*(ROW('02 MONITOR'!$B$7:$B$106)-6))),"") | N37: =IFERROR(INDEX('02 MONITOR'!$B$7:$B$106,SUMPRODUCT(('02 MONITOR'!$U$7:$U$106=78)*(ROW('02 MONITOR'!$B$7:$B$106)-6))),"") | O37: =IFERROR(INDEX('02 MONITOR'!$M$7:$M$106,SUMPRODUCT(('02 MONITOR'!$U$7:$U$106=78)*(ROW('02 MONITOR'!$B$7:$B$106)-6))),"") | P37: =IFERROR(INDEX('02 MONITOR'!$N$7:$N$106,SUMPRODUCT(('02 MONITOR'!$U$7:$U$106=78)*(ROW('02 MONITOR'!$B$7:$B$106)-6))),"") | Q37: =IFERROR(INDEX('02 MONITOR'!$R$7:$R$106,SUMPRODUCT(('02 MONITOR'!$U$7:$U$106=78)*(ROW('02 MONITOR'!$B$7:$B$106)-6))),"")
B38: 24 | C38: =IFERROR(INDEX('02 MONITOR'!$C$7:$C$106,SUMPRODUCT(('02 MONITOR'!$U$7:$U$106=24)*(ROW('02 MONITOR'!$B$7:$B$106)-6))),"") | D38: =IFERROR(INDEX('02 MONITOR'!$D$7:$D$106,SUMPRODUCT(('02 MONITOR'!$U$7:$U$106=24)*(ROW('02 MONITOR'!$B$7:$B$106)-6))),"") | E38: =IFERROR(INDEX('02 MONITOR'!$B$7:$B$106,SUMPRODUCT(('02 MONITOR'!$U$7:$U$106=24)*(ROW('02 MONITOR'!$B$7:$B$106)-6))),"") | F38: =IFERROR(INDEX('02 MONITOR'!$M$7:$M$106,SUMPRODUCT(('02 MONITOR'!$U$7:$U$106=24)*(ROW('02 MONITOR'!$B$7:$B$106)-6))),"") | G38: =IFERROR(INDEX('02 MONITOR'!$N$7:$N$106,SUMPRODUCT(('02 MONITOR'!$U$7:$U$106=24)*(ROW('02 MONITOR'!$B$7:$B$106)-6))),"") | H38: =IFERROR(INDEX('02 MONITOR'!$R$7:$R$106,SUMPRODUCT(('02 MONITOR'!$U$7:$U$106=24)*(ROW('02 MONITOR'!$B$7:$B$106)-6))),"") | K38: 24 | L38: =IFERROR(INDEX('02 MONITOR'!$C$7:$C$106,SUMPRODUCT(('02 MONITOR'!$U$7:$U$106=77)*(ROW('02 MONITOR'!$B$7:$B$106)-6))),"") | M38: =IFERROR(INDEX('02 MONITOR'!$D$7:$D$106,SUMPRODUCT(('02 MONITOR'!$U$7:$U$106=77)*(ROW('02 MONITOR'!$B$7:$B$106)-6))),"") | N38: =IFERROR(INDEX('02 MONITOR'!$B$7:$B$106,SUMPRODUCT(('02 MONITOR'!$U$7:$U$106=77)*(ROW('02 MONITOR'!$B$7:$B$106)-6))),"") | O38: =IFERROR(INDEX('02 MONITOR'!$M$7:$M$106,SUMPRODUCT(('02 MONITOR'!$U$7:$U$106=77)*(ROW('02 MONITOR'!$B$7:$B$106)-6))),"") | P38: =IFERROR(INDEX('02 MONITOR'!$N$7:$N$106,SUMPRODUCT(('02 MONITOR'!$U$7:$U$106=77)*(ROW('02 MONITOR'!$B$7:$B$106)-6))),"") | Q38: =IFERROR(INDEX('02 MONITOR'!$R$7:$R$106,SUMPRODUCT(('02 MONITOR'!$U$7:$U$106=77)*(ROW('02 MONITOR'!$B$7:$B$106)-6))),"")
B39: 25 | C39: =IFERROR(INDEX('02 MONITOR'!$C$7:$C$106,SUMPRODUCT(('02 MONITOR'!$U$7:$U$106=25)*(ROW('02 MONITOR'!$B$7:$B$106)-6))),"") | D39: =IFERROR(INDEX('02 MONITOR'!$D$7:$D$106,SUMPRODUCT(('02 MONITOR'!$U$7:$U$106=25)*(ROW('02 MONITOR'!$B$7:$B$106)-6))),"") | E39: =IFERROR(INDEX('02 MONITOR'!$B$7:$B$106,SUMPRODUCT(('02 MONITOR'!$U$7:$U$106=25)*(ROW('02 MONITOR'!$B$7:$B$106)-6))),"") | F39: =IFERROR(INDEX('02 MONITOR'!$M$7:$M$106,SUMPRODUCT(('02 MONITOR'!$U$7:$U$106=25)*(ROW('02 MONITOR'!$B$7:$B$106)-6))),"") | G39: =IFERROR(INDEX('02 MONITOR'!$N$7:$N$106,SUMPRODUCT(('02 MONITOR'!$U$7:$U$106=25)*(ROW('02 MONITOR'!$B$7:$B$106)-6))),"") | H39: =IFERROR(INDEX('02 MONITOR'!$R$7:$R$106,SUMPRODUCT(('02 MONITOR'!$U$7:$U$106=25)*(ROW('02 MONITOR'!$B$7:$B$106)-6))),"") | K39: 25 | L39: =IFERROR(INDEX('02 MONITOR'!$C$7:$C$106,SUMPRODUCT(('02 MONITOR'!$U$7:$U$106=76)*(ROW('02 MONITOR'!$B$7:$B$106)-6))),"") | M39: =IFERROR(INDEX('02 MONITOR'!$D$7:$D$106,SUMPRODUCT(('02 MONITOR'!$U$7:$U$106=76)*(ROW('02 MONITOR'!$B$7:$B$106)-6))),"") | N39: =IFERROR(INDEX('02 MONITOR'!$B$7:$B$106,SUMPRODUCT(('02 MONITOR'!$U$7:$U$106=76)*(ROW('02 MONITOR'!$B$7:$B$106)-6))),"") | O39: =IFERROR(INDEX('02 MONITOR'!$M$7:$M$106,SUMPRODUCT(('02 MONITOR'!$U$7:$U$106=76)*(ROW('02 MONITOR'!$B$7:$B$106)-6))),"") | P39: =IFERROR(INDEX('02 MONITOR'!$N$7:$N$106,SUMPRODUCT(('02 MONITOR'!$U$7:$U$106=76)*(ROW('02 MONITOR'!$B$7:$B$106)-6))),"") | Q39: =IFERROR(INDEX('02 MONITOR'!$R$7:$R$106,SUMPRODUCT(('02 MONITOR'!$U$7:$U$106=76)*(ROW('02 MONITOR'!$B$7:$B$106)-6))),"")

Sheet 05 PORTFOLIO
A1: THE BOOK — 50 LONG, 50 SHORT
A2: Built mechanically from the value scores. Equal risk to each asset class, longs matched to shorts inside every class, conviction-weighted by |z|.
A4: CONSTRUCTION RULES, so you can defend it in a room: 1. Within each asset class, rank all instruments by value score. Long the cheap half, short the rich half. That makes the book neutral to every asset class by construction — no net equity, no net rates, no net FX bet. 2. Weight each position by conviction: |value score|, normalised so that each class's longs sum to one fifth of the long side and each class's shorts sum to one fifth of the short side. Five classes, equal risk each. 3. Zero any position whose |value score| is below the minimum on tab 01. Do not pay bid-offer for noise. 4. The result is dollar-neutral and class-neutral. It is NOT factor-neutral, and it is certainly not neutral to the dollar — see the diagnostics at the bottom.
A6: POSITIONS
B7: # | C7: Class | D7: Rank | E7: Instrument | F7: Ticker | G7: Value score | H7: Side | I7: Raw wt | J7: Weight % | K7: Notional (USD) | L7: Metric | M7: How you would actually put it on
B8: 1 | C8: EQUITY | D8: 1 | E8: =IFERROR(INDEX('02 MONITOR'!$C$7:$C$106,SUMPRODUCT(('02 MONITOR'!$B$7:$B$106="EQUITY")*('02 MONITOR'!$P$7:$P$106=1)*(ROW('02 MONITOR'!$B$7:$B$106)-6))),"") | F8: =IFERROR(INDEX('02 MONITOR'!$D$7:$D$106,SUMPRODUCT(('02 MONITOR'!$B$7:$B$106="EQUITY")*('02 MONITOR'!$P$7:$P$106=1)*(ROW('02 MONITOR'!$B$7:$B$106)-6))),"") | G8: =IFERROR(INDEX('02 MONITOR'!$M$7:$M$106,SUMPRODUCT(('02 MONITOR'!$B$7:$B$106="EQUITY")*('02 MONITOR'!$P$7:$P$106=1)*(ROW('02 MONITOR'!$B$7:$B$106)-6))),"") | H8: LONG | I8: =IFERROR(IF(ABS($G8)<SETTINGS_ZMIN,0,ABS($G8)),"") | J8: =IFERROR($I8/SUMPRODUCT(($C$8:$C$107=$C8)*($H$8:$H$107=$H8)*$I$8:$I$107)*(SETTINGS_GROSS/2/5),"") | K8: =IFERROR($J8*SETTINGS_CAP*IF($H8="SHORT",-1,1),"") | L8: Forward P/E | M8: Index future or total-return swap. Cash equity only if you must.
B9: 2 | C9: EQUITY | D9: 2 | E9: =IFERROR(INDEX('02 MONITOR'!$C$7:$C$106,SUMPRODUCT(('02 MONITOR'!$B$7:$B$106="EQUITY")*('02 MONITOR'!$P$7:$P$106=2)*(ROW('02 MONITOR'!$B$7:$B$106)-6))),"") | F9: =IFERROR(INDEX('02 MONITOR'!$D$7:$D$106,SUMPRODUCT(('02 MONITOR'!$B$7:$B$106="EQUITY")*('02 MONITOR'!$P$7:$P$106=2)*(ROW('02 MONITOR'!$B$7:$B$106)-6))),"") | G9: =IFERROR(INDEX('02 MONITOR'!$M$7:$M$106,SUMPRODUCT(('02 MONITOR'!$B$7:$B$106="EQUITY")*('02 MONITOR'!$P$7:$P$106=2)*(ROW('02 MONITOR'!$B$7:$B$106)-6))),"") | H9: LONG | I9: =IFERROR(IF(ABS($G9)<SETTINGS_ZMIN,0,ABS($G9)),"") | J9: =IFERROR($I9/SUMPRODUCT(($C$8:$C$107=$C9)*($H$8:$H$107=$H9)*$I$8:$I$107)*(SETTINGS_GROSS/2/5),"") | K9: =IFERROR($J9*SETTINGS_CAP*IF($H9="SHORT",-1,1),"") | L9: Forward P/E | M9: Index future or total-return swap. Cash equity only if you must.
B10: 3 | C10: EQUITY | D10: 3 | E10: =IFERROR(INDEX('02 MONITOR'!$C$7:$C$106,SUMPRODUCT(('02 MONITOR'!$B$7:$B$106="EQUITY")*('02 MONITOR'!$P$7:$P$106=3)*(ROW('02 MONITOR'!$B$7:$B$106)-6))),"") | F10: =IFERROR(INDEX('02 MONITOR'!$D$7:$D$106,SUMPRODUCT(('02 MONITOR'!$B$7:$B$106="EQUITY")*('02 MONITOR'!$P$7:$P$106=3)*(ROW('02 MONITOR'!$B$7:$B$106)-6))),"") | G10: =IFERROR(INDEX('02 MONITOR'!$M$7:$M$106,SUMPRODUCT(('02 MONITOR'!$B$7:$B$106="EQUITY")*('02 MONITOR'!$P$7:$P$106=3)*(ROW('02 MONITOR'!$B$7:$B$106)-6))),"") | H10: LONG | I10: =IFERROR(IF(ABS($G10)<SETTINGS_ZMIN,0,ABS($G10)),"") | J10: =IFERROR($I10/SUMPRODUCT(($C$8:$C$107=$C10)*($H$8:$H$107=$H10)*$I$8:$I$107)*(SETTINGS_GROSS/2/5),"") | K10: =IFERROR($J10*SETTINGS_CAP*IF($H10="SHORT",-1,1),"") | L10: Forward P/E | M10: Index future or total-return swap. Cash equity only if you must.
B11: 4 | C11: EQUITY | D11: 4 | E11: =IFERROR(INDEX('02 MONITOR'!$C$7:$C$106,SUMPRODUCT(('02 MONITOR'!$B$7:$B$106="EQUITY")*('02 MONITOR'!$P$7:$P$106=4)*(ROW('02 MONITOR'!$B$7:$B$106)-6))),"") | F11: =IFERROR(INDEX('02 MONITOR'!$D$7:$D$106,SUMPRODUCT(('02 MONITOR'!$B$7:$B$106="EQUITY")*('02 MONITOR'!$P$7:$P$106=4)*(ROW('02 MONITOR'!$B$7:$B$106)-6))),"") | G11: =IFERROR(INDEX('02 MONITOR'!$M$7:$M$106,SUMPRODUCT(('02 MONITOR'!$B$7:$B$106="EQUITY")*('02 MONITOR'!$P$7:$P$106=4)*(ROW('02 MONITOR'!$B$7:$B$106)-6))),"") | H11: LONG | I11: =IFERROR(IF(ABS($G11)<SETTINGS_ZMIN,0,ABS($G11)),"") | J11: =IFERROR($I11/SUMPRODUCT(($C$8:$C$107=$C11)*($H$8:$H$107=$H11)*$I$8:$I$107)*(SETTINGS_GROSS/2/5),"") | K11: =IFERROR($J11*SETTINGS_CAP*IF($H11="SHORT",-1,1),"") | L11: Forward P/E | M11: Index future or total-return swap. Cash equity only if you must.
B12: 5 | C12: EQUITY | D12: 5 | E12: =IFERROR(INDEX('02 MONITOR'!$C$7:$C$106,SUMPRODUCT(('02 MONITOR'!$B$7:$B$106="EQUITY")*('02 MONITOR'!$P$7:$P$106=5)*(ROW('02 MONITOR'!$B$7:$B$106)-6))),"") | F12: =IFERROR(INDEX('02 MONITOR'!$D$7:$D$106,SUMPRODUCT(('02 MONITOR'!$B$7:$B$106="EQUITY")*('02 MONITOR'!$P$7:$P$106=5)*(ROW('02 MONITOR'!$B$7:$B$106)-6))),"") | G12: =IFERROR(INDEX('02 MONITOR'!$M$7:$M$106,SUMPRODUCT(('02 MONITOR'!$B$7:$B$106="EQUITY")*('02 MONITOR'!$P$7:$P$106=5)*(ROW('02 MONITOR'!$B$7:$B$106)-6))),"") | H12: LONG | I12: =IFERROR(IF(ABS($G12)<SETTINGS_ZMIN,0,ABS($G12)),"") | J12: =IFERROR($I12/SUMPRODUCT(($C$8:$C$107=$C12)*($H$8:$H$107=$H12)*$I$8:$I$107)*(SETTINGS_GROSS/2/5),"") | K12: =IFERROR($J12*SETTINGS_CAP*IF($H12="SHORT",-1,1),"") | L12: Forward P/E | M12: Index future or total-return swap. Cash equity only if you must.
B13: 6 | C13: EQUITY | D13: 6 | E13: =IFERROR(INDEX('02 MONITOR'!$C$7:$C$106,SUMPRODUCT(('02 MONITOR'!$B$7:$B$106="EQUITY")*('02 MONITOR'!$P$7:$P$106=6)*(ROW('02 MONITOR'!$B$7:$B$106)-6))),"") | F13: =IFERROR(INDEX('02 MONITOR'!$D$7:$D$106,SUMPRODUCT(('02 MONITOR'!$B$7:$B$106="EQUITY")*('02 MONITOR'!$P$7:$P$106=6)*(ROW('02 MONITOR'!$B$7:$B$106)-6))),"") | G13: =IFERROR(INDEX('02 MONITOR'!$M$7:$M$106,SUMPRODUCT(('02 MONITOR'!$B$7:$B$106="EQUITY")*('02 MONITOR'!$P$7:$P$106=6)*(ROW('02 MONITOR'!$B$7:$B$106)-6))),"") | H13: LONG | I13: =IFERROR(IF(ABS($G13)<SETTINGS_ZMIN,0,ABS($G13)),"") | J13: =IFERROR($I13/SUMPRODUCT(($C$8:$C$107=$C13)*($H$8:$H$107=$H13)*$I$8:$I$107)*(SETTINGS_GROSS/2/5),"") | K13: =IFERROR($J13*SETTINGS_CAP*IF($H13="SHORT",-1,1),"") | L13: Forward P/E | M13: Index future or total-return swap. Cash equity only if you must.
B14: 7 | C14: EQUITY | D14: 7 | E14: =IFERROR(INDEX('02 MONITOR'!$C$7:$C$106,SUMPRODUCT(('02 MONITOR'!$B$7:$B$106="EQUITY")*('02 MONITOR'!$P$7:$P$106=7)*(ROW('02 MONITOR'!$B$7:$B$106)-6))),"") | F14: =IFERROR(INDEX('02 MONITOR'!$D$7:$D$106,SUMPRODUCT(('02 MONITOR'!$B$7:$B$106="EQUITY")*('02 MONITOR'!$P$7:$P$106=7)*(ROW('02 MONITOR'!$B$7:$B$106)-6))),"") | G14: =IFERROR(INDEX('02 MONITOR'!$M$7:$M$106,SUMPRODUCT(('02 MONITOR'!$B$7:$B$106="EQUITY")*('02 MONITOR'!$P$7:$P$106=7)*(ROW('02 MONITOR'!$B$7:$B$106)-6))),"") | H14: LONG | I14: =IFERROR(IF(ABS($G14)<SETTINGS_ZMIN,0,ABS($G14)),"") | J14: =IFERROR($I14/SUMPRODUCT(($C$8:$C$107=$C14)*($H$8:$H$107=$H14)*$I$8:$I$107)*(SETTINGS_GROSS/2/5),"") | K14: =IFERROR($J14*SETTINGS_CAP*IF($H14="SHORT",-1,1),"") | L14: Forward P/E | M14: Index future or total-return swap. Cash equity only if you must.
B15: 8 | C15: EQUITY | D15: 8 | E15: =IFERROR(INDEX('02 MONITOR'!$C$7:$C$106,SUMPRODUCT(('02 MONITOR'!$B$7:$B$106="EQUITY")*('02 MONITOR'!$P$7:$P$106=8)*(ROW('02 MONITOR'!$B$7:$B$106)-6))),"") | F15: =IFERROR(INDEX('02 MONITOR'!$D$7:$D$106,SUMPRODUCT(('02 MONITOR'!$B$7:$B$106="EQUITY")*('02 MONITOR'!$P$7:$P$106=8)*(ROW('02 MONITOR'!$B$7:$B$106)-6))),"") | G15: =IFERROR(INDEX('02 MONITOR'!$M$7:$M$106,SUMPRODUCT(('02 MONITOR'!$B$7:$B$106="EQUITY")*('02 MONITOR'!$P$7:$P$106=8)*(ROW('02 MONITOR'!$B$7:$B$106)-6))),"") | H15: LONG | I15: =IFERROR(IF(ABS($G15)<SETTINGS_ZMIN,0,ABS($G15)),"") | J15: =IFERROR($I15/SUMPRODUCT(($C$8:$C$107=$C15)*($H$8:$H$107=$H15)*$I$8:$I$107)*(SETTINGS_GROSS/2/5),"") | K15: =IFERROR($J15*SETTINGS_CAP*IF($H15="SHORT",-1,1),"") | L15: Forward P/E | M15: Index future or total-return swap. Cash equity only if you must.
B16: 9 | C16: EQUITY | D16: 9 | E16: =IFERROR(INDEX('02 MONITOR'!$C$7:$C$106,SUMPRODUCT(('02 MONITOR'!$B$7:$B$106="EQUITY")*('02 MONITOR'!$P$7:$P$106=9)*(ROW('02 MONITOR'!$B$7:$B$106)-6))),"") | F16: =IFERROR(INDEX('02 MONITOR'!$D$7:$D$106,SUMPRODUCT(('02 MONITOR'!$B$7:$B$106="EQUITY")*('02 MONITOR'!$P$7:$P$106=9)*(ROW('02 MONITOR'!$B$7:$B$106)-6))),"") | G16: =IFERROR(INDEX('02 MONITOR'!$M$7:$M$106,SUMPRODUCT(('02 MONITOR'!$B$7:$B$106="EQUITY")*('02 MONITOR'!$P$7:$P$106=9)*(ROW('02 MONITOR'!$B$7:$B$106)-6))),"") | H16: LONG | I16: =IFERROR(IF(ABS($G16)<SETTINGS_ZMIN,0,ABS($G16)),"") | J16: =IFERROR($I16/SUMPRODUCT(($C$8:$C$107=$C16)*($H$8:$H$107=$H16)*$I$8:$I$107)*(SETTINGS_GROSS/2/5),"") | K16: =IFERROR($J16*SETTINGS_CAP*IF($H16="SHORT",-1,1),"") | L16: Forward P/E | M16: Index future or total-return swap. Cash equity only if you must.
B17: 10 | C17: EQUITY | D17: 10 | E17: =IFERROR(INDEX('02 MONITOR'!$C$7:$C$106,SUMPRODUCT(('02 MONITOR'!$B$7:$B$106="EQUITY")*('02 MONITOR'!$P$7:$P$106=10)*(ROW('02 MONITOR'!$B$7:$B$106)-6))),"") | F17: =IFERROR(INDEX('02 MONITOR'!$D$7:$D$106,SUMPRODUCT(('02 MONITOR'!$B$7:$B$106="EQUITY")*('02 MONITOR'!$P$7:$P$106=10)*(ROW('02 MONITOR'!$B$7:$B$106)-6))),"") | G17: =IFERROR(INDEX('02 MONITOR'!$M$7:$M$106,SUMPRODUCT(('02 MONITOR'!$B$7:$B$106="EQUITY")*('02 MONITOR'!$P$7:$P$106=10)*(ROW('02 MONITOR'!$B$7:$B$106)-6))),"") | H17: LONG | I17: =IFERROR(IF(ABS($G17)<SETTINGS_ZMIN,0,ABS($G17)),"") | J17: =IFERROR($I17/SUMPRODUCT(($C$8:$C$107=$C17)*($H$8:$H$107=$H17)*$I$8:$I$107)*(SETTINGS_GROSS/2/5),"") | K17: =IFERROR($J17*SETTINGS_CAP*IF($H17="SHORT",-1,1),"") | L17: Forward P/E | M17: Index future or total-return swap. Cash equity only if you must.
B18: 11 | C18: EQUITY | D18: 11 | E18: =IFERROR(INDEX('02 MONITOR'!$C$7:$C$106,SUMPRODUCT(('02 MONITOR'!$B$7:$B$106="EQUITY")*('02 MONITOR'!$P$7:$P$106=11)*(ROW('02 MONITOR'!$B$7:$B$106)-6))),"") | F18: =IFERROR(INDEX('02 MONITOR'!$D$7:$D$106,SUMPRODUCT(('02 MONITOR'!$B$7:$B$106="EQUITY")*('02 MONITOR'!$P$7:$P$106=11)*(ROW('02 MONITOR'!$B$7:$B$106)-6))),"") | G18: =IFERROR(INDEX('02 MONITOR'!$M$7:$M$106,SUMPRODUCT(('02 MONITOR'!$B$7:$B$106="EQUITY")*('02 MONITOR'!$P$7:$P$106=11)*(ROW('02 MONITOR'!$B$7:$B$106)-6))),"") | H18: LONG | I18: =IFERROR(IF(ABS($G18)<SETTINGS_ZMIN,0,ABS($G18)),"") | J18: =IFERROR($I18/SUMPRODUCT(($C$8:$C$107=$C18)*($H$8:$H$107=$H18)*$I$8:$I$107)*(SETTINGS_GROSS/2/5),"") | K18: =IFERROR($J18*SETTINGS_CAP*IF($H18="SHORT",-1,1),"") | L18: Forward P/E | M18: Index future or total-return swap. Cash equity only if you must.
B19: 12 | C19: EQUITY | D19: 12 | E19: =IFERROR(INDEX('02 MONITOR'!$C$7:$C$106,SUMPRODUCT(('02 MONITOR'!$B$7:$B$106="EQUITY")*('02 MONITOR'!$P$7:$P$106=12)*(ROW('02 MONITOR'!$B$7:$B$106)-6))),"") | F19: =IFERROR(INDEX('02 MONITOR'!$D$7:$D$106,SUMPRODUCT(('02 MONITOR'!$B$7:$B$106="EQUITY")*('02 MONITOR'!$P$7:$P$106=12)*(ROW('02 MONITOR'!$B$7:$B$106)-6))),"") | G19: =IFERROR(INDEX('02 MONITOR'!$M$7:$M$106,SUMPRODUCT(('02 MONITOR'!$B$7:$B$106="EQUITY")*('02 MONITOR'!$P$7:$P$106=12)*(ROW('02 MONITOR'!$B$7:$B$106)-6))),"") | H19: LONG | I19: =IFERROR(IF(ABS($G19)<SETTINGS_ZMIN,0,ABS($G19)),"") | J19: =IFERROR($I19/SUMPRODUCT(($C$8:$C$107=$C19)*($H$8:$H$107=$H19)*$I$8:$I$107)*(SETTINGS_GROSS/2/5),"") | K19: =IFERROR($J19*SETTINGS_CAP*IF($H19="SHORT",-1,1),"") | L19: Forward P/E | M19: Index future or total-return swap. Cash equity only if you must.
B20: 13 | C20: EQUITY | D20: 13 | E20: =IFERROR(INDEX('02 MONITOR'!$C$7:$C$106,SUMPRODUCT(('02 MONITOR'!$B$7:$B$106="EQUITY")*('02 MONITOR'!$P$7:$P$106=13)*(ROW('02 MONITOR'!$B$7:$B$106)-6))),"") | F20: =IFERROR(INDEX('02 MONITOR'!$D$7:$D$106,SUMPRODUCT(('02 MONITOR'!$B$7:$B$106="EQUITY")*('02 MONITOR'!$P$7:$P$106=13)*(ROW('02 MONITOR'!$B$7:$B$106)-6))),"") | G20: =IFERROR(INDEX('02 MONITOR'!$M$7:$M$106,SUMPRODUCT(('02 MONITOR'!$B$7:$B$106="EQUITY")*('02 MONITOR'!$P$7:$P$106=13)*(ROW('02 MONITOR'!$B$7:$B$106)-6))),"") | H20: SHORT | I20: =IFERROR(IF(ABS($G20)<SETTINGS_ZMIN,0,ABS($G20)),"") | J20: =IFERROR($I20/SUMPRODUCT(($C$8:$C$107=$C20)*($H$8:$H$107=$H20)*$I$8:$I$107)*(SETTINGS_GROSS/2/5),"") | K20: =IFERROR($J20*SETTINGS_CAP*IF($H20="SHORT",-1,1),"") | L20: Forward P/E | M20: Index future or total-return swap. Cash equity only if you must.
B21: 14 | C21: EQUITY | D21: 14 | E21: =IFERROR(INDEX('02 MONITOR'!$C$7:$C$106,SUMPRODUCT(('02 MONITOR'!$B$7:$B$106="EQUITY")*('02 MONITOR'!$P$7:$P$106=14)*(ROW('02 MONITOR'!$B$7:$B$106)-6))),"") | F21: =IFERROR(INDEX('02 MONITOR'!$D$7:$D$106,SUMPRODUCT(('02 MONITOR'!$B$7:$B$106="EQUITY")*('02 MONITOR'!$P$7:$P$106=14)*(ROW('02 MONITOR'!$B$7:$B$106)-6))),"") | G21: =IFERROR(INDEX('02 MONITOR'!$M$7:$M$106,SUMPRODUCT(('02 MONITOR'!$B$7:$B$106="EQUITY")*('02 MONITOR'!$P$7:$P$106=14)*(ROW('02 MONITOR'!$B$7:$B$106)-6))),"") | H21: SHORT | I21: =IFERROR(IF(ABS($G21)<SETTINGS_ZMIN,0,ABS($G21)),"") | J21: =IFERROR($I21/SUMPRODUCT(($C$8:$C$107=$C21)*($H$8:$H$107=$H21)*$I$8:$I$107)*(SETTINGS_GROSS/2/5),"") | K21: =IFERROR($J21*SETTINGS_CAP*IF($H21="SHORT",-1,1),"") | L21: Forward P/E | M21: Index future or total-return swap. Cash equity only if you must.
B22: 15 | C22: EQUITY | D22: 15 | E22: =IFERROR(INDEX('02 MONITOR'!$C$7:$C$106,SUMPRODUCT(('02 MONITOR'!$B$7:$B$106="EQUITY")*('02 MONITOR'!$P$7:$P$106=15)*(ROW('02 MONITOR'!$B$7:$B$106)-6))),"") | F22: =IFERROR(INDEX('02 MONITOR'!$D$7:$D$106,SUMPRODUCT(('02 MONITOR'!$B$7:$B$106="EQUITY")*('02 MONITOR'!$P$7:$P$106=15)*(ROW('02 MONITOR'!$B$7:$B$106)-6))),"") | G22: =IFERROR(INDEX('02 MONITOR'!$M$7:$M$106,SUMPRODUCT(('02 MONITOR'!$B$7:$B$106="EQUITY")*('02 MONITOR'!$P$7:$P$106=15)*(ROW('02 MONITOR'!$B$7:$B$106)-6))),"") | H22: SHORT | I22: =IFERROR(IF(ABS($G22)<SETTINGS_ZMIN,0,ABS($G22)),"") | J22: =IFERROR($I22/SUMPRODUCT(($C$8:$C$107=$C22)*($H$8:$H$107=$H22)*$I$8:$I$107)*(SETTINGS_GROSS/2/5),"") | K22: =IFERROR($J22*SETTINGS_CAP*IF($H22="SHORT",-1,1),"") | L22: Forward P/E | M22: Index future or total-return swap. Cash equity only if you must.
B23: 16 | C23: EQUITY | D23: 16 | E23: =IFERROR(INDEX('02 MONITOR'!$C$7:$C$106,SUMPRODUCT(('02 MONITOR'!$B$7:$B$106="EQUITY")*('02 MONITOR'!$P$7:$P$106=16)*(ROW('02 MONITOR'!$B$7:$B$106)-6))),"") | F23: =IFERROR(INDEX('02 MONITOR'!$D$7:$D$106,SUMPRODUCT(('02 MONITOR'!$B$7:$B$106="EQUITY")*('02 MONITOR'!$P$7:$P$106=16)*(ROW('02 MONITOR'!$B$7:$B$106)-6))),"") | G23: =IFERROR(INDEX('02 MONITOR'!$M$7:$M$106,SUMPRODUCT(('02 MONITOR'!$B$7:$B$106="EQUITY")*('02 MONITOR'!$P$7:$P$106=16)*(ROW('02 MONITOR'!$B$7:$B$106)-6))),"") | H23: SHORT | I23: =IFERROR(IF(ABS($G23)<SETTINGS_ZMIN,0,ABS($G23)),"") | J23: =IFERROR($I23/SUMPRODUCT(($C$8:$C$107=$C23)*($H$8:$H$107=$H23)*$I$8:$I$107)*(SETTINGS_GROSS/2/5),"") | K23: =IFERROR($J23*SETTINGS_CAP*IF($H23="SHORT",-1,1),"") | L23: Forward P/E | M23: Index future or total-return swap. Cash equity only if you must.
B24: 17 | C24: EQUITY | D24: 17 | E24: =IFERROR(INDEX('02 MONITOR'!$C$7:$C$106,SUMPRODUCT(('02 MONITOR'!$B$7:$B$106="EQUITY")*('02 MONITOR'!$P$7:$P$106=17)*(ROW('02 MONITOR'!$B$7:$B$106)-6))),"") | F24: =IFERROR(INDEX('02 MONITOR'!$D$7:$D$106,SUMPRODUCT(('02 MONITOR'!$B$7:$B$106="EQUITY")*('02 MONITOR'!$P$7:$P$106=17)*(ROW('02 MONITOR'!$B$7:$B$106)-6))),"") | G24: =IFERROR(INDEX('02 MONITOR'!$M$7:$M$106,SUMPRODUCT(('02 MONITOR'!$B$7:$B$106="EQUITY")*('02 MONITOR'!$P$7:$P$106=17)*(ROW('02 MONITOR'!$B$7:$B$106)-6))),"") | H24: SHORT | I24: =IFERROR(IF(ABS($G24)<SETTINGS_ZMIN,0,ABS($G24)),"") | J24: =IFERROR($I24/SUMPRODUCT(($C$8:$C$107=$C24)*($H$8:$H$107=$H24)*$I$8:$I$107)*(SETTINGS_GROSS/2/5),"") | K24: =IFERROR($J24*SETTINGS_CAP*IF($H24="SHORT",-1,1),"") | L24: Forward P/E | M24: Index future or total-return swap. Cash equity only if you must.
B25: 18 | C25: EQUITY | D25: 18 | E25: =IFERROR(INDEX('02 MONITOR'!$C$7:$C$106,SUMPRODUCT(('02 MONITOR'!$B$7:$B$106="EQUITY")*('02 MONITOR'!$P$7:$P$106=18)*(ROW('02 MONITOR'!$B$7:$B$106)-6))),"") | F25: =IFERROR(INDEX('02 MONITOR'!$D$7:$D$106,SUMPRODUCT(('02 MONITOR'!$B$7:$B$106="EQUITY")*('02 MONITOR'!$P$7:$P$106=18)*(ROW('02 MONITOR'!$B$7:$B$106)-6))),"") | G25: =IFERROR(INDEX('02 MONITOR'!$M$7:$M$106,SUMPRODUCT(('02 MONITOR'!$B$7:$B$106="EQUITY")*('02 MONITOR'!$P$7:$P$106=18)*(ROW('02 MONITOR'!$B$7:$B$106)-6))),"") | H25: SHORT | I25: =IFERROR(IF(ABS($G25)<SETTINGS_ZMIN,0,ABS($G25)),"") | J25: =IFERROR($I25/SUMPRODUCT(($C$8:$C$107=$C25)*($H$8:$H$107=$H25)*$I$8:$I$107)*(SETTINGS_GROSS/2/5),"") | K25: =IFERROR($J25*SETTINGS_CAP*IF($H25="SHORT",-1,1),"") | L25: Forward P/E | M25: Index future or total-return swap. Cash equity only if you must.
B26: 19 | C26: EQUITY | D26: 19 | E26: =IFERROR(INDEX('02 MONITOR'!$C$7:$C$106,SUMPRODUCT(('02 MONITOR'!$B$7:$B$106="EQUITY")*('02 MONITOR'!$P$7:$P$106=19)*(ROW('02 MONITOR'!$B$7:$B$106)-6))),"") | F26: =IFERROR(INDEX('02 MONITOR'!$D$7:$D$106,SUMPRODUCT(('02 MONITOR'!$B$7:$B$106="EQUITY")*('02 MONITOR'!$P$7:$P$106=19)*(ROW('02 MONITOR'!$B$7:$B$106)-6))),"") | G26: =IFERROR(INDEX('02 MONITOR'!$M$7:$M$106,SUMPRODUCT(('02 MONITOR'!$B$7:$B$106="EQUITY")*('02 MONITOR'!$P$7:$P$106=19)*(ROW('02 MONITOR'!$B$7:$B$106)-6))),"") | H26: SHORT | I26: =IFERROR(IF(ABS($G26)<SETTINGS_ZMIN,0,ABS($G26)),"") | J26: =IFERROR($I26/SUMPRODUCT(($C$8:$C$107=$C26)*($H$8:$H$107=$H26)*$I$8:$I$107)*(SETTINGS_GROSS/2/5),"") | K26: =IFERROR($J26*SETTINGS_CAP*IF($H26="SHORT",-1,1),"") | L26: Forward P/E | M26: Index future or total-return swap. Cash equity only if you must.
B27: 20 | C27: EQUITY | D27: 20 | E27: =IFERROR(INDEX('02 MONITOR'!$C$7:$C$106,SUMPRODUCT(('02 MONITOR'!$B$7:$B$106="EQUITY")*('02 MONITOR'!$P$7:$P$106=20)*(ROW('02 MONITOR'!$B$7:$B$106)-6))),"") | F27: =IFERROR(INDEX('02 MONITOR'!$D$7:$D$106,SUMPRODUCT(('02 MONITOR'!$B$7:$B$106="EQUITY")*('02 MONITOR'!$P$7:$P$106=20)*(ROW('02 MONITOR'!$B$7:$B$106)-6))),"") | G27: =IFERROR(INDEX('02 MONITOR'!$M$7:$M$106,SUMPRODUCT(('02 MONITOR'!$B$7:$B$106="EQUITY")*('02 MONITOR'!$P$7:$P$106=20)*(ROW('02 MONITOR'!$B$7:$B$106)-6))),"") | H27: SHORT | I27: =IFERROR(IF(ABS($G27)<SETTINGS_ZMIN,0,ABS($G27)),"") | J27: =IFERROR($I27/SUMPRODUCT(($C$8:$C$107=$C27)*($H$8:$H$107=$H27)*$I$8:$I$107)*(SETTINGS_GROSS/2/5),"") | K27: =IFERROR($J27*SETTINGS_CAP*IF($H27="SHORT",-1,1),"") | L27: Forward P/E | M27: Index future or total-return swap. Cash equity only if you must.
B28: 21 | C28: EQUITY | D28: 21 | E28: =IFERROR(INDEX('02 MONITOR'!$C$7:$C$106,SUMPRODUCT(('02 MONITOR'!$B$7:$B$106="EQUITY")*('02 MONITOR'!$P$7:$P$106=21)*(ROW('02 MONITOR'!$B$7:$B$106)-6))),"") | F28: =IFERROR(INDEX('02 MONITOR'!$D$7:$D$106,SUMPRODUCT(('02 MONITOR'!$B$7:$B$106="EQUITY")*('02 MONITOR'!$P$7:$P$106=21)*(ROW('02 MONITOR'!$B$7:$B$106)-6))),"") | G28: =IFERROR(INDEX('02 MONITOR'!$M$7:$M$106,SUMPRODUCT(('02 MONITOR'!$B$7:$B$106="EQUITY")*('02 MONITOR'!$P$7:$P$106=21)*(ROW('02 MONITOR'!$B$7:$B$106)-6))),"") | H28: SHORT | I28: =IFERROR(IF(ABS($G28)<SETTINGS_ZMIN,0,ABS($G28)),"") | J28: =IFERROR($I28/SUMPRODUCT(($C$8:$C$107=$C28)*($H$8:$H$107=$H28)*$I$8:$I$107)*(SETTINGS_GROSS/2/5),"") | K28: =IFERROR($J28*SETTINGS_CAP*IF($H28="SHORT",-1,1),"") | L28: Forward P/E | M28: Index future or total-return swap. Cash equity only if you must.
B29: 22 | C29: EQUITY | D29: 22 | E29: =IFERROR(INDEX('02 MONITOR'!$C$7:$C$106,SUMPRODUCT(('02 MONITOR'!$B$7:$B$106="EQUITY")*('02 MONITOR'!$P$7:$P$106=22)*(ROW('02 MONITOR'!$B$7:$B$106)-6))),"") | F29: =IFERROR(INDEX('02 MONITOR'!$D$7:$D$106,SUMPRODUCT(('02 MONITOR'!$B$7:$B$106="EQUITY")*('02 MONITOR'!$P$7:$P$106=22)*(ROW('02 MONITOR'!$B$7:$B$106)-6))),"") | G29: =IFERROR(INDEX('02 MONITOR'!$M$7:$M$106,SUMPRODUCT(('02 MONITOR'!$B$7:$B$106="EQUITY")*('02 MONITOR'!$P$7:$P$106=22)*(ROW('02 MONITOR'!$B$7:$B$106)-6))),"") | H29: SHORT | I29: =IFERROR(IF(ABS($G29)<SETTINGS_ZMIN,0,ABS($G29)),"") | J29: =IFERROR($I29/SUMPRODUCT(($C$8:$C$107=$C29)*($H$8:$H$107=$H29)*$I$8:$I$107)*(SETTINGS_GROSS/2/5),"") | K29: =IFERROR($J29*SETTINGS_CAP*IF($H29="SHORT",-1,1),"") | L29: Forward P/E | M29: Index future or total-return swap. Cash equity only if you must.
B30: 23 | C30: EQUITY | D30: 23 | E30: =IFERROR(INDEX('02 MONITOR'!$C$7:$C$106,SUMPRODUCT(('02 MONITOR'!$B$7:$B$106="EQUITY")*('02 MONITOR'!$P$7:$P$106=23)*(ROW('02 MONITOR'!$B$7:$B$106)-6))),"") | F30: =IFERROR(INDEX('02 MONITOR'!$D$7:$D$106,SUMPRODUCT(('02 MONITOR'!$B$7:$B$106="EQUITY")*('02 MONITOR'!$P$7:$P$106=23)*(ROW('02 MONITOR'!$B$7:$B$106)-6))),"") | G30: =IFERROR(INDEX('02 MONITOR'!$M$7:$M$106,SUMPRODUCT(('02 MONITOR'!$B$7:$B$106="EQUITY")*('02 MONITOR'!$P$7:$P$106=23)*(ROW('02 MONITOR'!$B$7:$B$106)-6))),"") | H30: SHORT | I30: =IFERROR(IF(ABS($G30)<SETTINGS_ZMIN,0,ABS($G30)),"") | J30: =IFERROR($I30/SUMPRODUCT(($C$8:$C$107=$C30)*($H$8:$H$107=$H30)*$I$8:$I$107)*(SETTINGS_GROSS/2/5),"") | K30: =IFERROR($J30*SETTINGS_CAP*IF($H30="SHORT",-1,1),"") | L30: Forward P/E | M30: Index future or total-return swap. Cash equity only if you must.
B31: 24 | C31: EQUITY | D31: 24 | E31: =IFERROR(INDEX('02 MONITOR'!$C$7:$C$106,SUMPRODUCT(('02 MONITOR'!$B$7:$B$106="EQUITY")*('02 MONITOR'!$P$7:$P$106=24)*(ROW('02 MONITOR'!$B$7:$B$106)-6))),"") | F31: =IFERROR(INDEX('02 MONITOR'!$D$7:$D$106,SUMPRODUCT(('02 MONITOR'!$B$7:$B$106="EQUITY")*('02 MONITOR'!$P$7:$P$106=24)*(ROW('02 MONITOR'!$B$7:$B$106)-6))),"") | G31: =IFERROR(INDEX('02 MONITOR'!$M$7:$M$106,SUMPRODUCT(('02 MONITOR'!$B$7:$B$106="EQUITY")*('02 MONITOR'!$P$7:$P$106=24)*(ROW('02 MONITOR'!$B$7:$B$106)-6))),"") | H31: SHORT | I31: =IFERROR(IF(ABS($G31)<SETTINGS_ZMIN,0,ABS($G31)),"") | J31: =IFERROR($I31/SUMPRODUCT(($C$8:$C$107=$C31)*($H$8:$H$107=$H31)*$I$8:$I$107)*(SETTINGS_GROSS/2/5),"") | K31: =IFERROR($J31*SETTINGS_CAP*IF($H31="SHORT",-1,1),"") | L31: Forward P/E | M31: Index future or total-return swap. Cash equity only if you must.
B32: 25 | C32: RATES | D32: 1 | E32: =IFERROR(INDEX('02 MONITOR'!$C$7:$C$106,SUMPRODUCT(('02 MONITOR'!$B$7:$B$106="RATES")*('02 MONITOR'!$P$7:$P$106=1)*(ROW('02 MONITOR'!$B$7:$B$106)-6))),"") | F32: =IFERROR(INDEX('02 MONITOR'!$D$7:$D$106,SUMPRODUCT(('02 MONITOR'!$B$7:$B$106="RATES")*('02 MONITOR'!$P$7:$P$106=1)*(ROW('02 MONITOR'!$B$7:$B$106)-6))),"") | G32: =IFERROR(INDEX('02 MONITOR'!$M$7:$M$106,SUMPRODUCT(('02 MONITOR'!$B$7:$B$106="RATES")*('02 MONITOR'!$P$7:$P$106=1)*(ROW('02 MONITOR'!$B$7:$B$106)-6))),"") | H32: LONG | I32: =IFERROR(IF(ABS($G32)<SETTINGS_ZMIN,0,ABS($G32)),"") | J32: =IFERROR($I32/SUMPRODUCT(($C$8:$C$107=$C32)*($H$8:$H$107=$H32)*$I$8:$I$107)*(SETTINGS_GROSS/2/5),"") | K32: =IFERROR($J32*SETTINGS_CAP*IF($H32="SHORT",-1,1),"") | L32: 10y nominal yield | M32: Receive or pay the 10y point in IRS, or the bond vs swaps. Size in DV01, not notional.
B33: 26 | C33: RATES | D33: 2 | E33: =IFERROR(INDEX('02 MONITOR'!$C$7:$C$106,SUMPRODUCT(('02 MONITOR'!$B$7:$B$106="RATES")*('02 MONITOR'!$P$7:$P$106=2)*(ROW('02 MONITOR'!$B$7:$B$106)-6))),"") | F33: =IFERROR(INDEX('02 MONITOR'!$D$7:$D$106,SUMPRODUCT(('02 MONITOR'!$B$7:$B$106="RATES")*('02 MONITOR'!$P$7:$P$106=2)*(ROW('02 MONITOR'!$B$7:$B$106)-6))),"") | G33: =IFERROR(INDEX('02 MONITOR'!$M$7:$M$106,SUMPRODUCT(('02 MONITOR'!$B$7:$B$106="RATES")*('02 MONITOR'!$P$7:$P$106=2)*(ROW('02 MONITOR'!$B$7:$B$106)-6))),"") | H33: LONG | I33: =IFERROR(IF(ABS($G33)<SETTINGS_ZMIN,0,ABS($G33)),"") | J33: =IFERROR($I33/SUMPRODUCT(($C$8:$C$107=$C33)*($H$8:$H$107=$H33)*$I$8:$I$107)*(SETTINGS_GROSS/2/5),"") | K33: =IFERROR($J33*SETTINGS_CAP*IF($H33="SHORT",-1,1),"") | L33: 10y nominal yield | M33: Receive or pay the 10y point in IRS, or the bond vs swaps. Size in DV01, not notional.
B34: 27 | C34: RATES | D34: 3 | E34: =IFERROR(INDEX('02 MONITOR'!$C$7:$C$106,SUMPRODUCT(('02 MONITOR'!$B$7:$B$106="RATES")*('02 MONITOR'!$P$7:$P$106=3)*(ROW('02 MONITOR'!$B$7:$B$106)-6))),"") | F34: =IFERROR(INDEX('02 MONITOR'!$D$7:$D$106,SUMPRODUCT(('02 MONITOR'!$B$7:$B$106="RATES")*('02 MONITOR'!$P$7:$P$106=3)*(ROW('02 MONITOR'!$B$7:$B$106)-6))),"") | G34: =IFERROR(INDEX('02 MONITOR'!$M$7:$M$106,SUMPRODUCT(('02 MONITOR'!$B$7:$B$106="RATES")*('02 MONITOR'!$P$7:$P$106=3)*(ROW('02 MONITOR'!$B$7:$B$106)-6))),"") | H34: LONG | I34: =IFERROR(IF(ABS($G34)<SETTINGS_ZMIN,0,ABS($G34)),"") | J34: =IFERROR($I34/SUMPRODUCT(($C$8:$C$107=$C34)*($H$8:$H$107=$H34)*$I$8:$I$107)*(SETTINGS_GROSS/2/5),"") | K34: =IFERROR($J34*SETTINGS_CAP*IF($H34="SHORT",-1,1),"") | L34: 10y nominal yield | M34: Receive or pay the 10y point in IRS, or the bond vs swaps. Size in DV01, not notional.
B35: 28 | C35: RATES | D35: 4 | E35: =IFERROR(INDEX('02 MONITOR'!$C$7:$C$106,SUMPRODUCT(('02 MONITOR'!$B$7:$B$106="RATES")*('02 MONITOR'!$P$7:$P$106=4)*(ROW('02 MONITOR'!$B$7:$B$106)-6))),"") | F35: =IFERROR(INDEX('02 MONITOR'!$D$7:$D$106,SUMPRODUCT(('02 MONITOR'!$B$7:$B$106="RATES")*('02 MONITOR'!$P$7:$P$106=4)*(ROW('02 MONITOR'!$B$7:$B$106)-6))),"") | G35: =IFERROR(INDEX('02 MONITOR'!$M$7:$M$106,SUMPRODUCT(('02 MONITOR'!$B$7:$B$106="RATES")*('02 MONITOR'!$P$7:$P$106=4)*(ROW('02 MONITOR'!$B$7:$B$106)-6))),"") | H35: LONG | I35: =IFERROR(IF(ABS($G35)<SETTINGS_ZMIN,0,ABS($G35)),"") | J35: =IFERROR($I35/SUMPRODUCT(($C$8:$C$107=$C35)*($H$8:$H$107=$H35)*$I$8:$I$107)*(SETTINGS_GROSS/2/5),"") | K35: =IFERROR($J35*SETTINGS_CAP*IF($H35="SHORT",-1,1),"") | L35: 10y nominal yield | M35: Receive or pay the 10y point in IRS, or the bond vs swaps. Size in DV01, not notional.
B36: 29 | C36: RATES | D36: 5 | E36: =IFERROR(INDEX('02 MONITOR'!$C$7:$C$106,SUMPRODUCT(('02 MONITOR'!$B$7:$B$106="RATES")*('02 MONITOR'!$P$7:$P$106=5)*(ROW('02 MONITOR'!$B$7:$B$106)-6))),"") | F36: =IFERROR(INDEX('02 MONITOR'!$D$7:$D$106,SUMPRODUCT(('02 MONITOR'!$B$7:$B$106="RATES")*('02 MONITOR'!$P$7:$P$106=5)*(ROW('02 MONITOR'!$B$7:$B$106)-6))),"") | G36: =IFERROR(INDEX('02 MONITOR'!$M$7:$M$106,SUMPRODUCT(('02 MONITOR'!$B$7:$B$106="RATES")*('02 MONITOR'!$P$7:$P$106=5)*(ROW('02 MONITOR'!$B$7:$B$106)-6))),"") | H36: LONG | I36: =IFERROR(IF(ABS($G36)<SETTINGS_ZMIN,0,ABS($G36)),"") | J36: =IFERROR($I36/SUMPRODUCT(($C$8:$C$107=$C36)*($H$8:$H$107=$H36)*$I$8:$I$107)*(SETTINGS_GROSS/2/5),"") | K36: =IFERROR($J36*SETTINGS_CAP*IF($H36="SHORT",-1,1),"") | L36: 10y nominal yield | M36: Receive or pay the 10y point in IRS, or the bond vs swaps. Size in DV01, not notional.
B37: 30 | C37: RATES | D37: 6 | E37: =IFERROR(INDEX('02 MONITOR'!$C$7:$C$106,SUMPRODUCT(('02 MONITOR'!$B$7:$B$106="RATES")*('02 MONITOR'!$P$7:$P$106=6)*(ROW('02 MONITOR'!$B$7:$B$106)-6))),"") | F37: =IFERROR(INDEX('02 MONITOR'!$D$7:$D$106,SUMPRODUCT(('02 MONITOR'!$B$7:$B$106="RATES")*('02 MONITOR'!$P$7:$P$106=6)*(ROW('02 MONITOR'!$B$7:$B$106)-6))),"") | G37: =IFERROR(INDEX('02 MONITOR'!$M$7:$M$106,SUMPRODUCT(('02 MONITOR'!$B$7:$B$106="RATES")*('02 MONITOR'!$P$7:$P$106=6)*(ROW('02 MONITOR'!$B$7:$B$106)-6))),"") | H37: LONG | I37: =IFERROR(IF(ABS($G37)<SETTINGS_ZMIN,0,ABS($G37)),"") | J37: =IFERROR($I37/SUMPRODUCT(($C$8:$C$107=$C37)*($H$8:$H$107=$H37)*$I$8:$I$107)*(SETTINGS_GROSS/2/5),"") | K37: =IFERROR($J37*SETTINGS_CAP*IF($H37="SHORT",-1,1),"") | L37: 10y nominal yield | M37: Receive or pay the 10y point in IRS, or the bond vs swaps. Size in DV01, not notional.
B38: 31 | C38: RATES | D38: 7 | E38: =IFERROR(INDEX('02 MONITOR'!$C$7:$C$106,SUMPRODUCT(('02 MONITOR'!$B$7:$B$106="RATES")*('02 MONITOR'!$P$7:$P$106=7)*(ROW('02 MONITOR'!$B$7:$B$106)-6))),"") | F38: =IFERROR(INDEX('02 MONITOR'!$D$7:$D$106,SUMPRODUCT(('02 MONITOR'!$B$7:$B$106="RATES")*('02 MONITOR'!$P$7:$P$106=7)*(ROW('02 MONITOR'!$B$7:$B$106)-6))),"") | G38: =IFERROR(INDEX('02 MONITOR'!$M$7:$M$106,SUMPRODUCT(('02 MONITOR'!$B$7:$B$106="RATES")*('02 MONITOR'!$P$7:$P$106=7)*(ROW('02 MONITOR'!$B$7:$B$106)-6))),"") | H38: LONG | I38: =IFERROR(IF(ABS($G38)<SETTINGS_ZMIN,0,ABS($G38)),"") | J38: =IFERROR($I38/SUMPRODUCT(($C$8:$C$107=$C38)*($H$8:$H$107=$H38)*$I$8:$I$107)*(SETTINGS_GROSS/2/5),"") | K38: =IFERROR($J38*SETTINGS_CAP*IF($H38="SHORT",-1,1),"") | L38: 10y nominal yield | M38: Receive or pay the 10y point in IRS, or the bond vs swaps. Size in DV01, not notional.
B39: 32 | C39: RATES | D39: 8 | E39: =IFERROR(INDEX('02 MONITOR'!$C$7:$C$106,SUMPRODUCT(('02 MONITOR'!$B$7:$B$106="RATES")*('02 MONITOR'!$P$7:$P$106=8)*(ROW('02 MONITOR'!$B$7:$B$106)-6))),"") | F39: =IFERROR(INDEX('02 MONITOR'!$D$7:$D$106,SUMPRODUCT(('02 MONITOR'!$B$7:$B$106="RATES")*('02 MONITOR'!$P$7:$P$106=8)*(ROW('02 MONITOR'!$B$7:$B$106)-6))),"") | G39: =IFERROR(INDEX('02 MONITOR'!$M$7:$M$106,SUMPRODUCT(('02 MONITOR'!$B$7:$B$106="RATES")*('02 MONITOR'!$P$7:$P$106=8)*(ROW('02 MONITOR'!$B$7:$B$106)-6))),"") | H39: LONG | I39: =IFERROR(IF(ABS($G39)<SETTINGS_ZMIN,0,ABS($G39)),"") | J39: =IFERROR($I39/SUMPRODUCT(($C$8:$C$107=$C39)*($H$8:$H$107=$H39)*$I$8:$I$107)*(SETTINGS_GROSS/2/5),"") | K39: =IFERROR($J39*SETTINGS_CAP*IF($H39="SHORT",-1,1),"") | L39: 10y nominal yield | M39: Receive or pay the 10y point in IRS, or the bond vs swaps. Size in DV01, not notional.
B40: 33 | C40: RATES | D40: 9 | E40: =IFERROR(INDEX('02 MONITOR'!$C$7:$C$106,SUMPRODUCT(('02 MONITOR'!$B$7:$B$106="RATES")*('02 MONITOR'!$P$7:$P$106=9)*(ROW('02 MONITOR'!$B$7:$B$106)-6))),"") | F40: =IFERROR(INDEX('02 MONITOR'!$D$7:$D$106,SUMPRODUCT(('02 MONITOR'!$B$7:$B$106="RATES")*('02 MONITOR'!$P$7:$P$106=9)*(ROW('02 MONITOR'!$B$7:$B$106)-6))),"") | G40: =IFERROR(INDEX('02 MONITOR'!$M$7:$M$106,SUMPRODUCT(('02 MONITOR'!$B$7:$B$106="RATES")*('02 MONITOR'!$P$7:$P$106=9)*(ROW('02 MONITOR'!$B$7:$B$106)-6))),"") | H40: LONG | I40: =IFERROR(IF(ABS($G40)<SETTINGS_ZMIN,0,ABS($G40)),"") | J40: =IFERROR($I40/SUMPRODUCT(($C$8:$C$107=$C40)*($H$8:$H$107=$H40)*$I$8:$I$107)*(SETTINGS_GROSS/2/5),"") | K40: =IFERROR($J40*SETTINGS_CAP*IF($H40="SHORT",-1,1),"") | L40: 10y nominal yield | M40: Receive or pay the 10y point in IRS, or the bond vs swaps. Size in DV01, not notional.
B41: 34 | C41: RATES | D41: 10 | E41: =IFERROR(INDEX('02 MONITOR'!$C$7:$C$106,SUMPRODUCT(('02 MONITOR'!$B$7:$B$106="RATES")*('02 MONITOR'!$P$7:$P$106=10)*(ROW('02 MONITOR'!$B$7:$B$106)-6))),"") | F41: =IFERROR(INDEX('02 MONITOR'!$D$7:$D$106,SUMPRODUCT(('02 MONITOR'!$B$7:$B$106="RATES")*('02 MONITOR'!$P$7:$P$106=10)*(ROW('02 MONITOR'!$B$7:$B$106)-6))),"") | G41: =IFERROR(INDEX('02 MONITOR'!$M$7:$M$106,SUMPRODUCT(('02 MONITOR'!$B$7:$B$106="RATES")*('02 MONITOR'!$P$7:$P$106=10)*(ROW('02 MONITOR'!$B$7:$B$106)-6))),"") | H41: LONG | I41: =IFERROR(IF(ABS($G41)<SETTINGS_ZMIN,0,ABS($G41)),"") | J41: =IFERROR($I41/SUMPRODUCT(($C$8:$C$107=$C41)*($H$8:$H$107=$H41)*$I$8:$I$107)*(SETTINGS_GROSS/2/5),"") | K41: =IFERROR($J41*SETTINGS_CAP*IF($H41="SHORT",-1,1),"") | L41: 10y nominal yield | M41: Receive or pay the 10y point in IRS, or the bond vs swaps. Size in DV01, not notional.
B42: 35 | C42: RATES | D42: 11 | E42: =IFERROR(INDEX('02 MONITOR'!$C$7:$C$106,SUMPRODUCT(('02 MONITOR'!$B$7:$B$106="RATES")*('02 MONITOR'!$P$7:$P$106=11)*(ROW('02 MONITOR'!$B$7:$B$106)-6))),"") | F42: =IFERROR(INDEX('02 MONITOR'!$D$7:$D$106,SUMPRODUCT(('02 MONITOR'!$B$7:$B$106="RATES")*('02 MONITOR'!$P$7:$P$106=11)*(ROW('02 MONITOR'!$B$7:$B$106)-6))),"") | G42: =IFERROR(INDEX('02 MONITOR'!$M$7:$M$106,SUMPRODUCT(('02 MONITOR'!$B$7:$B$106="RATES")*('02 MONITOR'!$P$7:$P$106=11)*(ROW('02 MONITOR'!$B$7:$B$106)-6))),"") | H42: SHORT | I42: =IFERROR(IF(ABS($G42)<SETTINGS_ZMIN,0,ABS($G42)),"") | J42: =IFERROR($I42/SUMPRODUCT(($C$8:$C$107=$C42)*($H$8:$H$107=$H42)*$I$8:$I$107)*(SETTINGS_GROSS/2/5),"") | K42: =IFERROR($J42*SETTINGS_CAP*IF($H42="SHORT",-1,1),"") | L42: 10y nominal yield | M42: Receive or pay the 10y point in IRS, or the bond vs swaps. Size in DV01, not notional.
B43: 36 | C43: RATES | D43: 12 | E43: =IFERROR(INDEX('02 MONITOR'!$C$7:$C$106,SUMPRODUCT(('02 MONITOR'!$B$7:$B$106="RATES")*('02 MONITOR'!$P$7:$P$106=12)*(ROW('02 MONITOR'!$B$7:$B$106)-6))),"") | F43: =IFERROR(INDEX('02 MONITOR'!$D$7:$D$106,SUMPRODUCT(('02 MONITOR'!$B$7:$B$106="RATES")*('02 MONITOR'!$P$7:$P$106=12)*(ROW('02 MONITOR'!$B$7:$B$106)-6))),"") | G43: =IFERROR(INDEX('02 MONITOR'!$M$7:$M$106,SUMPRODUCT(('02 MONITOR'!$B$7:$B$106="RATES")*('02 MONITOR'!$P$7:$P$106=12)*(ROW('02 MONITOR'!$B$7:$B$106)-6))),"") | H43: SHORT | I43: =IFERROR(IF(ABS($G43)<SETTINGS_ZMIN,0,ABS($G43)),"") | J43: =IFERROR($I43/SUMPRODUCT(($C$8:$C$107=$C43)*($H$8:$H$107=$H43)*$I$8:$I$107)*(SETTINGS_GROSS/2/5),"") | K43: =IFERROR($J43*SETTINGS_CAP*IF($H43="SHORT",-1,1),"") | L43: 10y nominal yield | M43: Receive or pay the 10y point in IRS, or the bond vs swaps. Size in DV01, not notional.
B44: 37 | C44: RATES | D44: 13 | E44: =IFERROR(INDEX('02 MONITOR'!$C$7:$C$106,SUMPRODUCT(('02 MONITOR'!$B$7:$B$106="RATES")*('02 MONITOR'!$P$7:$P$106=13)*(ROW('02 MONITOR'!$B$7:$B$106)-6))),"") | F44: =IFERROR(INDEX('02 MONITOR'!$D$7:$D$106,SUMPRODUCT(('02 MONITOR'!$B$7:$B$106="RATES")*('02 MONITOR'!$P$7:$P$106=13)*(ROW('02 MONITOR'!$B$7:$B$106)-6))),"") | G44: =IFERROR(INDEX('02 MONITOR'!$M$7:$M$106,SUMPRODUCT(('02 MONITOR'!$B$7:$B$106="RATES")*('02 MONITOR'!$P$7:$P$106=13)*(ROW('02 MONITOR'!$B$7:$B$106)-6))),"") | H44: SHORT | I44: =IFERROR(IF(ABS($G44)<SETTINGS_ZMIN,0,ABS($G44)),"") | J44: =IFERROR($I44/SUMPRODUCT(($C$8:$C$107=$C44)*($H$8:$H$107=$H44)*$I$8:$I$107)*(SETTINGS_GROSS/2/5),"") | K44: =IFERROR($J44*SETTINGS_CAP*IF($H44="SHORT",-1,1),"") | L44: 10y nominal yield | M44: Receive or pay the 10y point in IRS, or the bond vs swaps. Size in DV01, not notional.
B45: 38 | C45: RATES | D45: 14 | E45: =IFERROR(INDEX('02 MONITOR'!$C$7:$C$106,SUMPRODUCT(('02 MONITOR'!$B$7:$B$106="RATES")*('02 MONITOR'!$P$7:$P$106=14)*(ROW('02 MONITOR'!$B$7:$B$106)-6))),"") | F45: =IFERROR(INDEX('02 MONITOR'!$D$7:$D$106,SUMPRODUCT(('02 MONITOR'!$B$7:$B$106="RATES")*('02 MONITOR'!$P$7:$P$106=14)*(ROW('02 MONITOR'!$B$7:$B$106)-6))),"") | G45: =IFERROR(INDEX('02 MONITOR'!$M$7:$M$106,SUMPRODUCT(('02 MONITOR'!$B$7:$B$106="RATES")*('02 MONITOR'!$P$7:$P$106=14)*(ROW('02 MONITOR'!$B$7:$B$106)-6))),"") | H45: SHORT | I45: =IFERROR(IF(ABS($G45)<SETTINGS_ZMIN,0,ABS($G45)),"") | J45: =IFERROR($I45/SUMPRODUCT(($C$8:$C$107=$C45)*($H$8:$H$107=$H45)*$I$8:$I$107)*(SETTINGS_GROSS/2/5),"") | K45: =IFERROR($J45*SETTINGS_CAP*IF($H45="SHORT",-1,1),"") | L45: 10y nominal yield | M45: Receive or pay the 10y point in IRS, or the bond vs swaps. Size in DV01, not notional.
B46: 39 | C46: RATES | D46: 15 | E46: =IFERROR(INDEX('02 MONITOR'!$C$7:$C$106,SUMPRODUCT(('02 MONITOR'!$B$7:$B$106="RATES")*('02 MONITOR'!$P$7:$P$106=15)*(ROW('02 MONITOR'!$B$7:$B$106)-6))),"") | F46: =IFERROR(INDEX('02 MONITOR'!$D$7:$D$106,SUMPRODUCT(('02 MONITOR'!$B$7:$B$106="RATES")*('02 MONITOR'!$P$7:$P$106=15)*(ROW('02 MONITOR'!$B$7:$B$106)-6))),"") | G46: =IFERROR(INDEX('02 MONITOR'!$M$7:$M$106,SUMPRODUCT(('02 MONITOR'!$B$7:$B$106="RATES")*('02 MONITOR'!$P$7:$P$106=15)*(ROW('02 MONITOR'!$B$7:$B$106)-6))),"") | H46: SHORT | I46: =IFERROR(IF(ABS($G46)<SETTINGS_ZMIN,0,ABS($G46)),"") | J46: =IFERROR($I46/SUMPRODUCT(($C$8:$C$107=$C46)*($H$8:$H$107=$H46)*$I$8:$I$107)*(SETTINGS_GROSS/2/5),"") | K46: =IFERROR($J46*SETTINGS_CAP*IF($H46="SHORT",-1,1),"") | L46: 10y nominal yield | M46: Receive or pay the 10y point in IRS, or the bond vs swaps. Size in DV01, not notional.
B47: 40 | C47: RATES | D47: 16 | E47: =IFERROR(INDEX('02 MONITOR'!$C$7:$C$106,SUMPRODUCT(('02 MONITOR'!$B$7:$B$106="RATES")*('02 MONITOR'!$P$7:$P$106=16)*(ROW('02 MONITOR'!$B$7:$B$106)-6))),"") | F47: =IFERROR(INDEX('02 MONITOR'!$D$7:$D$106,SUMPRODUCT(('02 MONITOR'!$B$7:$B$106="RATES")*('02 MONITOR'!$P$7:$P$106=16)*(ROW('02 MONITOR'!$B$7:$B$106)-6))),"") | G47: =IFERROR(INDEX('02 MONITOR'!$M$7:$M$106,SUMPRODUCT(('02 MONITOR'!$B$7:$B$106="RATES")*('02 MONITOR'!$P$7:$P$106=16)*(ROW('02 MONITOR'!$B$7:$B$106)-6))),"") | H47: SHORT | I47: =IFERROR(IF(ABS($G47)<SETTINGS_ZMIN,0,ABS($G47)),"") | J47: =IFERROR($I47/SUMPRODUCT(($C$8:$C$107=$C47)*($H$8:$H$107=$H47)*$I$8:$I$107)*(SETTINGS_GROSS/2/5),"") | K47: =IFERROR($J47*SETTINGS_CAP*IF($H47="SHORT",-1,1),"") | L47: 10y nominal yield | M47: Receive or pay the 10y point in IRS, or the bond vs swaps. Size in DV01, not notional.
B48: 41 | C48: RATES | D48: 17 | E48: =IFERROR(INDEX('02 MONITOR'!$C$7:$C$106,SUMPRODUCT(('02 MONITOR'!$B$7:$B$106="RATES")*('02 MONITOR'!$P$7:$P$106=17)*(ROW('02 MONITOR'!$B$7:$B$106)-6))),"") | F48: =IFERROR(INDEX('02 MONITOR'!$D$7:$D$106,SUMPRODUCT(('02 MONITOR'!$B$7:$B$106="RATES")*('02 MONITOR'!$P$7:$P$106=17)*(ROW('02 MONITOR'!$B$7:$B$106)-6))),"") | G48: =IFERROR(INDEX('02 MONITOR'!$M$7:$M$106,SUMPRODUCT(('02 MONITOR'!$B$7:$B$106="RATES")*('02 MONITOR'!$P$7:$P$106=17)*(ROW('02 MONITOR'!$B$7:$B$106)-6))),"") | H48: SHORT | I48: =IFERROR(IF(ABS($G48)<SETTINGS_ZMIN,0,ABS($G48)),"") | J48: =IFERROR($I48/SUMPRODUCT(($C$8:$C$107=$C48)*($H$8:$H$107=$H48)*$I$8:$I$107)*(SETTINGS_GROSS/2/5),"") | K48: =IFERROR($J48*SETTINGS_CAP*IF($H48="SHORT",-1,1),"") | L48: 10y nominal yield | M48: Receive or pay the 10y point in IRS, or the bond vs swaps. Size in DV01, not notional.
B49: 42 | C49: RATES | D49: 18 | E49: =IFERROR(INDEX('02 MONITOR'!$C$7:$C$106,SUMPRODUCT(('02 MONITOR'!$B$7:$B$106="RATES")*('02 MONITOR'!$P$7:$P$106=18)*(ROW('02 MONITOR'!$B$7:$B$106)-6))),"") | F49: =IFERROR(INDEX('02 MONITOR'!$D$7:$D$106,SUMPRODUCT(('02 MONITOR'!$B$7:$B$106="RATES")*('02 MONITOR'!$P$7:$P$106=18)*(ROW('02 MONITOR'!$B$7:$B$106)-6))),"") | G49: =IFERROR(INDEX('02 MONITOR'!$M$7:$M$106,SUMPRODUCT(('02 MONITOR'!$B$7:$B$106="RATES")*('02 MONITOR'!$P$7:$P$106=18)*(ROW('02 MONITOR'!$B$7:$B$106)-6))),"") | H49: SHORT | I49: =IFERROR(IF(ABS($G49)<SETTINGS_ZMIN,0,ABS($G49)),"") | J49: =IFERROR($I49/SUMPRODUCT(($C$8:$C$107=$C49)*($H$8:$H$107=$H49)*$I$8:$I$107)*(SETTINGS_GROSS/2/5),"") | K49: =IFERROR($J49*SETTINGS_CAP*IF($H49="SHORT",-1,1),"") | L49: 10y nominal yield | M49: Receive or pay the 10y point in IRS, or the bond vs swaps. Size in DV01, not notional.
B50: 43 | C50: RATES | D50: 19 | E50: =IFERROR(INDEX('02 MONITOR'!$C$7:$C$106,SUMPRODUCT(('02 MONITOR'!$B$7:$B$106="RATES")*('02 MONITOR'!$P$7:$P$106=19)*(ROW('02 MONITOR'!$B$7:$B$106)-6))),"") | F50: =IFERROR(INDEX('02 MONITOR'!$D$7:$D$106,SUMPRODUCT(('02 MONITOR'!$B$7:$B$106="RATES")*('02 MONITOR'!$P$7:$P$106=19)*(ROW('02 MONITOR'!$B$7:$B$106)-6))),"") | G50: =IFERROR(INDEX('02 MONITOR'!$M$7:$M$106,SUMPRODUCT(('02 MONITOR'!$B$7:$B$106="RATES")*('02 MONITOR'!$P$7:$P$106=19)*(ROW('02 MONITOR'!$B$7:$B$106)-6))),"") | H50: SHORT | I50: =IFERROR(IF(ABS($G50)<SETTINGS_ZMIN,0,ABS($G50)),"") | J50: =IFERROR($I50/SUMPRODUCT(($C$8:$C$107=$C50)*($H$8:$H$107=$H50)*$I$8:$I$107)*(SETTINGS_GROSS/2/5),"") | K50: =IFERROR($J50*SETTINGS_CAP*IF($H50="SHORT",-1,1),"") | L50: 10y nominal yield | M50: Receive or pay the 10y point in IRS, or the bond vs swaps. Size in DV01, not notional.
B51: 44 | C51: RATES | D51: 20 | E51: =IFERROR(INDEX('02 MONITOR'!$C$7:$C$106,SUMPRODUCT(('02 MONITOR'!$B$7:$B$106="RATES")*('02 MONITOR'!$P$7:$P$106=20)*(ROW('02 MONITOR'!$B$7:$B$106)-6))),"") | F51: =IFERROR(INDEX('02 MONITOR'!$D$7:$D$106,SUMPRODUCT(('02 MONITOR'!$B$7:$B$106="RATES")*('02 MONITOR'!$P$7:$P$106=20)*(ROW('02 MONITOR'!$B$7:$B$106)-6))),"") | G51: =IFERROR(INDEX('02 MONITOR'!$M$7:$M$106,SUMPRODUCT(('02 MONITOR'!$B$7:$B$106="RATES")*('02 MONITOR'!$P$7:$P$106=20)*(ROW('02 MONITOR'!$B$7:$B$106)-6))),"") | H51: SHORT | I51: =IFERROR(IF(ABS($G51)<SETTINGS_ZMIN,0,ABS($G51)),"") | J51: =IFERROR($I51/SUMPRODUCT(($C$8:$C$107=$C51)*($H$8:$H$107=$H51)*$I$8:$I$107)*(SETTINGS_GROSS/2/5),"") | K51: =IFERROR($J51*SETTINGS_CAP*IF($H51="SHORT",-1,1),"") | L51: 10y nominal yield | M51: Receive or pay the 10y point in IRS, or the bond vs swaps. Size in DV01, not notional.
B52: 45 | C52: FX | D52: 1 | E52: =IFERROR(INDEX('02 MONITOR'!$C$7:$C$106,SUMPRODUCT(('02 MONITOR'!$B$7:$B$106="FX")*('02 MONITOR'!$P$7:$P$106=1)*(ROW('02 MONITOR'!$B$7:$B$106)-6))),"") | F52: =IFERROR(INDEX('02 MONITOR'!$D$7:$D$106,SUMPRODUCT(('02 MONITOR'!$B$7:$B$106="FX")*('02 MONITOR'!$P$7:$P$106=1)*(ROW('02 MONITOR'!$B$7:$B$106)-6))),"") | G52: =IFERROR(INDEX('02 MONITOR'!$M$7:$M$106,SUMPRODUCT(('02 MONITOR'!$B$7:$B$106="FX")*('02 MONITOR'!$P$7:$P$106=1)*(ROW('02 MONITOR'!$B$7:$B$106)-6))),"") | H52: LONG | I52: =IFERROR(IF(ABS($G52)<SETTINGS_ZMIN,0,ABS($G52)),"") | J52: =IFERROR($I52/SUMPRODUCT(($C$8:$C$107=$C52)*($H$8:$H$107=$H52)*$I$8:$I$107)*(SETTINGS_GROSS/2/5),"") | K52: =IFERROR($J52*SETTINGS_CAP*IF($H52="SHORT",-1,1),"") | L52: Spot (or REER) | M52: 3m NDF or deliverable forward. Long the cheap currency, short the rich one.
B53: 46 | C53: FX | D53: 2 | E53: =IFERROR(INDEX('02 MONITOR'!$C$7:$C$106,SUMPRODUCT(('02 MONITOR'!$B$7:$B$106="FX")*('02 MONITOR'!$P$7:$P$106=2)*(ROW('02 MONITOR'!$B$7:$B$106)-6))),"") | F53: =IFERROR(INDEX('02 MONITOR'!$D$7:$D$106,SUMPRODUCT(('02 MONITOR'!$B$7:$B$106="FX")*('02 MONITOR'!$P$7:$P$106=2)*(ROW('02 MONITOR'!$B$7:$B$106)-6))),"") | G53: =IFERROR(INDEX('02 MONITOR'!$M$7:$M$106,SUMPRODUCT(('02 MONITOR'!$B$7:$B$106="FX")*('02 MONITOR'!$P$7:$P$106=2)*(ROW('02 MONITOR'!$B$7:$B$106)-6))),"") | H53: LONG | I53: =IFERROR(IF(ABS($G53)<SETTINGS_ZMIN,0,ABS($G53)),"") | J53: =IFERROR($I53/SUMPRODUCT(($C$8:$C$107=$C53)*($H$8:$H$107=$H53)*$I$8:$I$107)*(SETTINGS_GROSS/2/5),"") | K53: =IFERROR($J53*SETTINGS_CAP*IF($H53="SHORT",-1,1),"") | L53: Spot (or REER) | M53: 3m NDF or deliverable forward. Long the cheap currency, short the rich one.
B54: 47 | C54: FX | D54: 3 | E54: =IFERROR(INDEX('02 MONITOR'!$C$7:$C$106,SUMPRODUCT(('02 MONITOR'!$B$7:$B$106="FX")*('02 MONITOR'!$P$7:$P$106=3)*(ROW('02 MONITOR'!$B$7:$B$106)-6))),"") | F54: =IFERROR(INDEX('02 MONITOR'!$D$7:$D$106,SUMPRODUCT(('02 MONITOR'!$B$7:$B$106="FX")*('02 MONITOR'!$P$7:$P$106=3)*(ROW('02 MONITOR'!$B$7:$B$106)-6))),"") | G54: =IFERROR(INDEX('02 MONITOR'!$M$7:$M$106,SUMPRODUCT(('02 MONITOR'!$B$7:$B$106="FX")*('02 MONITOR'!$P$7:$P$106=3)*(ROW('02 MONITOR'!$B$7:$B$106)-6))),"") | H54: LONG | I54: =IFERROR(IF(ABS($G54)<SETTINGS_ZMIN,0,ABS($G54)),"") | J54: =IFERROR($I54/SUMPRODUCT(($C$8:$C$107=$C54)*($H$8:$H$107=$H54)*$I$8:$I$107)*(SETTINGS_GROSS/2/5),"") | K54: =IFERROR($J54*SETTINGS_CAP*IF($H54="SHORT",-1,1),"") | L54: Spot (or REER) | M54: 3m NDF or deliverable forward. Long the cheap currency, short the rich one.
B55: 48 | C55: FX | D55: 4 | E55: =IFERROR(INDEX('02 MONITOR'!$C$7:$C$106,SUMPRODUCT(('02 MONITOR'!$B$7:$B$106="FX")*('02 MONITOR'!$P$7:$P$106=4)*(ROW('02 MONITOR'!$B$7:$B$106)-6))),"") | F55: =IFERROR(INDEX('02 MONITOR'!$D$7:$D$106,SUMPRODUCT(('02 MONITOR'!$B$7:$B$106="FX")*('02 MONITOR'!$P$7:$P$106=4)*(ROW('02 MONITOR'!$B$7:$B$106)-6))),"") | G55: =IFERROR(INDEX('02 MONITOR'!$M$7:$M$106,SUMPRODUCT(('02 MONITOR'!$B$7:$B$106="FX")*('02 MONITOR'!$P$7:$P$106=4)*(ROW('02 MONITOR'!$B$7:$B$106)-6))),"") | H55: LONG | I55: =IFERROR(IF(ABS($G55)<SETTINGS_ZMIN,0,ABS($G55)),"") | J55: =IFERROR($I55/SUMPRODUCT(($C$8:$C$107=$C55)*($H$8:$H$107=$H55)*$I$8:$I$107)*(SETTINGS_GROSS/2/5),"") | K55: =IFERROR($J55*SETTINGS_CAP*IF($H55="SHORT",-1,1),"") | L55: Spot (or REER) | M55: 3m NDF or deliverable forward. Long the cheap currency, short the rich one.
B56: 49 | C56: FX | D56: 5 | E56: =IFERROR(INDEX('02 MONITOR'!$C$7:$C$106,SUMPRODUCT(('02 MONITOR'!$B$7:$B$106="FX")*('02 MONITOR'!$P$7:$P$106=5)*(ROW('02 MONITOR'!$B$7:$B$106)-6))),"") | F56: =IFERROR(INDEX('02 MONITOR'!$D$7:$D$106,SUMPRODUCT(('02 MONITOR'!$B$7:$B$106="FX")*('02 MONITOR'!$P$7:$P$106=5)*(ROW('02 MONITOR'!$B$7:$B$106)-6))),"") | G56: =IFERROR(INDEX('02 MONITOR'!$M$7:$M$106,SUMPRODUCT(('02 MONITOR'!$B$7:$B$106="FX")*('02 MONITOR'!$P$7:$P$106=5)*(ROW('02 MONITOR'!$B$7:$B$106)-6))),"") | H56: LONG | I56: =IFERROR(IF(ABS($G56)<SETTINGS_ZMIN,0,ABS($G56)),"") | J56: =IFERROR($I56/SUMPRODUCT(($C$8:$C$107=$C56)*($H$8:$H$107=$H56)*$I$8:$I$107)*(SETTINGS_GROSS/2/5),"") | K56: =IFERROR($J56*SETTINGS_CAP*IF($H56="SHORT",-1,1),"") | L56: Spot (or REER) | M56: 3m NDF or deliverable forward. Long the cheap currency, short the rich one.
B57: 50 | C57: FX | D57: 6 | E57: =IFERROR(INDEX('02 MONITOR'!$C$7:$C$106,SUMPRODUCT(('02 MONITOR'!$B$7:$B$106="FX")*('02 MONITOR'!$P$7:$P$106=6)*(ROW('02 MONITOR'!$B$7:$B$106)-6))),"") | F57: =IFERROR(INDEX('02 MONITOR'!$D$7:$D$106,SUMPRODUCT(('02 MONITOR'!$B$7:$B$106="FX")*('02 MONITOR'!$P$7:$P$106=6)*(ROW('02 MONITOR'!$B$7:$B$106)-6))),"") | G57: =IFERROR(INDEX('02 MONITOR'!$M$7:$M$106,SUMPRODUCT(('02 MONITOR'!$B$7:$B$106="FX")*('02 MONITOR'!$P$7:$P$106=6)*(ROW('02 MONITOR'!$B$7:$B$106)-6))),"") | H57: LONG | I57: =IFERROR(IF(ABS($G57)<SETTINGS_ZMIN,0,ABS($G57)),"") | J57: =IFERROR($I57/SUMPRODUCT(($C$8:$C$107=$C57)*($H$8:$H$107=$H57)*$I$8:$I$107)*(SETTINGS_GROSS/2/5),"") | K57: =IFERROR($J57*SETTINGS_CAP*IF($H57="SHORT",-1,1),"") | L57: Spot (or REER) | M57: 3m NDF or deliverable forward. Long the cheap currency, short the rich one.
B58: 51 | C58: FX | D58: 7 | E58: =IFERROR(INDEX('02 MONITOR'!$C$7:$C$106,SUMPRODUCT(('02 MONITOR'!$B$7:$B$106="FX")*('02 MONITOR'!$P$7:$P$106=7)*(ROW('02 MONITOR'!$B$7:$B$106)-6))),"") | F58: =IFERROR(INDEX('02 MONITOR'!$D$7:$D$106,SUMPRODUCT(('02 MONITOR'!$B$7:$B$106="FX")*('02 MONITOR'!$P$7:$P$106=7)*(ROW('02 MONITOR'!$B$7:$B$106)-6))),"") | G58: =IFERROR(INDEX('02 MONITOR'!$M$7:$M$106,SUMPRODUCT(('02 MONITOR'!$B$7:$B$106="FX")*('02 MONITOR'!$P$7:$P$106=7)*(ROW('02 MONITOR'!$B$7:$B$106)-6))),"") | H58: LONG | I58: =IFERROR(IF(ABS($G58)<SETTINGS_ZMIN,0,ABS($G58)),"") | J58: =IFERROR($I58/SUMPRODUCT(($C$8:$C$107=$C58)*($H$8:$H$107=$H58)*$I$8:$I$107)*(SETTINGS_GROSS/2/5),"") | K58: =IFERROR($J58*SETTINGS_CAP*IF($H58="SHORT",-1,1),"") | L58: Spot (or REER) | M58: 3m NDF or deliverable forward. Long the cheap currency, short the rich one.
B59: 52 | C59: FX | D59: 8 | E59: =IFERROR(INDEX('02 MONITOR'!$C$7:$C$106,SUMPRODUCT(('02 MONITOR'!$B$7:$B$106="FX")*('02 MONITOR'!$P$7:$P$106=8)*(ROW('02 MONITOR'!$B$7:$B$106)-6))),"") | F59: =IFERROR(INDEX('02 MONITOR'!$D$7:$D$106,SUMPRODUCT(('02 MONITOR'!$B$7:$B$106="FX")*('02 MONITOR'!$P$7:$P$106=8)*(ROW('02 MONITOR'!$B$7:$B$106)-6))),"") | G59: =IFERROR(INDEX('02 MONITOR'!$M$7:$M$106,SUMPRODUCT(('02 MONITOR'!$B$7:$B$106="FX")*('02 MONITOR'!$P$7:$P$106=8)*(ROW('02 MONITOR'!$B$7:$B$106)-6))),"") | H59: LONG | I59: =IFERROR(IF(ABS($G59)<SETTINGS_ZMIN,0,ABS($G59)),"") | J59: =IFERROR($I59/SUMPRODUCT(($C$8:$C$107=$C59)*($H$8:$H$107=$H59)*$I$8:$I$107)*(SETTINGS_GROSS/2/5),"") | K59: =IFERROR($J59*SETTINGS_CAP*IF($H59="SHORT",-1,1),"") | L59: Spot (or REER) | M59: 3m NDF or deliverable forward. Long the cheap currency, short the rich one.
B60: 53 | C60: FX | D60: 9 | E60: =IFERROR(INDEX('02 MONITOR'!$C$7:$C$106,SUMPRODUCT(('02 MONITOR'!$B$7:$B$106="FX")*('02 MONITOR'!$P$7:$P$106=9)*(ROW('02 MONITOR'!$B$7:$B$106)-6))),"") | F60: =IFERROR(INDEX('02 MONITOR'!$D$7:$D$106,SUMPRODUCT(('02 MONITOR'!$B$7:$B$106="FX")*('02 MONITOR'!$P$7:$P$106=9)*(ROW('02 MONITOR'!$B$7:$B$106)-6))),"") | G60: =IFERROR(INDEX('02 MONITOR'!$M$7:$M$106,SUMPRODUCT(('02 MONITOR'!$B$7:$B$106="FX")*('02 MONITOR'!$P$7:$P$106=9)*(ROW('02 MONITOR'!$B$7:$B$106)-6))),"") | H60: LONG | I60: =IFERROR(IF(ABS($G60)<SETTINGS_ZMIN,0,ABS($G60)),"") | J60: =IFERROR($I60/SUMPRODUCT(($C$8:$C$107=$C60)*($H$8:$H$107=$H60)*$I$8:$I$107)*(SETTINGS_GROSS/2/5),"") | K60: =IFERROR($J60*SETTINGS_CAP*IF($H60="SHORT",-1,1),"") | L60: Spot (or REER) | M60: 3m NDF or deliverable forward. Long the cheap currency, short the rich one.
B61: 54 | C61: FX | D61: 10 | E61: =IFERROR(INDEX('02 MONITOR'!$C$7:$C$106,SUMPRODUCT(('02 MONITOR'!$B$7:$B$106="FX")*('02 MONITOR'!$P$7:$P$106=10)*(ROW('02 MONITOR'!$B$7:$B$106)-6))),"") | F61: =IFERROR(INDEX('02 MONITOR'!$D$7:$D$106,SUMPRODUCT(('02 MONITOR'!$B$7:$B$106="FX")*('02 MONITOR'!$P$7:$P$106=10)*(ROW('02 MONITOR'!$B$7:$B$106)-6))),"") | G61: =IFERROR(INDEX('02 MONITOR'!$M$7:$M$106,SUMPRODUCT(('02 MONITOR'!$B$7:$B$106="FX")*('02 MONITOR'!$P$7:$P$106=10)*(ROW('02 MONITOR'!$B$7:$B$106)-6))),"") | H61: LONG | I61: =IFERROR(IF(ABS($G61)<SETTINGS_ZMIN,0,ABS($G61)),"") | J61: =IFERROR($I61/SUMPRODUCT(($C$8:$C$107=$C61)*($H$8:$H$107=$H61)*$I$8:$I$107)*(SETTINGS_GROSS/2/5),"") | K61: =IFERROR($J61*SETTINGS_CAP*IF($H61="SHORT",-1,1),"") | L61: Spot (or REER) | M61: 3m NDF or deliverable forward. Long the cheap currency, short the rich one.
B62: 55 | C62: FX | D62: 11 | E62: =IFERROR(INDEX('02 MONITOR'!$C$7:$C$106,SUMPRODUCT(('02 MONITOR'!$B$7:$B$106="FX")*('02 MONITOR'!$P$7:$P$106=11)*(ROW('02 MONITOR'!$B$7:$B$106)-6))),"") | F62: =IFERROR(INDEX('02 MONITOR'!$D$7:$D$106,SUMPRODUCT(('02 MONITOR'!$B$7:$B$106="FX")*('02 MONITOR'!$P$7:$P$106=11)*(ROW('02 MONITOR'!$B$7:$B$106)-6))),"") | G62: =IFERROR(INDEX('02 MONITOR'!$M$7:$M$106,SUMPRODUCT(('02 MONITOR'!$B$7:$B$106="FX")*('02 MONITOR'!$P$7:$P$106=11)*(ROW('02 MONITOR'!$B$7:$B$106)-6))),"") | H62: LONG | I62: =IFERROR(IF(ABS($G62)<SETTINGS_ZMIN,0,ABS($G62)),"") | J62: =IFERROR($I62/SUMPRODUCT(($C$8:$C$107=$C62)*($H$8:$H$107=$H62)*$I$8:$I$107)*(SETTINGS_GROSS/2/5),"") | K62: =IFERROR($J62*SETTINGS_CAP*IF($H62="SHORT",-1,1),"") | L62: Spot (or REER) | M62: 3m NDF or deliverable forward. Long the cheap currency, short the rich one.
B63: 56 | C63: FX | D63: 12 | E63: =IFERROR(INDEX('02 MONITOR'!$C$7:$C$106,SUMPRODUCT(('02 MONITOR'!$B$7:$B$106="FX")*('02 MONITOR'!$P$7:$P$106=12)*(ROW('02 MONITOR'!$B$7:$B$106)-6))),"") | F63: =IFERROR(INDEX('02 MONITOR'!$D$7:$D$106,SUMPRODUCT(('02 MONITOR'!$B$7:$B$106="FX")*('02 MONITOR'!$P$7:$P$106=12)*(ROW('02 MONITOR'!$B$7:$B$106)-6))),"") | G63: =IFERROR(INDEX('02 MONITOR'!$M$7:$M$106,SUMPRODUCT(('02 MONITOR'!$B$7:$B$106="FX")*('02 MONITOR'!$P$7:$P$106=12)*(ROW('02 MONITOR'!$B$7:$B$106)-6))),"") | H63: LONG | I63: =IFERROR(IF(ABS($G63)<SETTINGS_ZMIN,0,ABS($G63)),"") | J63: =IFERROR($I63/SUMPRODUCT(($C$8:$C$107=$C63)*($H$8:$H$107=$H63)*$I$8:$I$107)*(SETTINGS_GROSS/2/5),"") | K63: =IFERROR($J63*SETTINGS_CAP*IF($H63="SHORT",-1,1),"") | L63: Spot (or REER) | M63: 3m NDF or deliverable forward. Long the cheap currency, short the rich one.
B64: 57 | C64: FX | D64: 13 | E64: =IFERROR(INDEX('02 MONITOR'!$C$7:$C$106,SUMPRODUCT(('02 MONITOR'!$B$7:$B$106="FX")*('02 MONITOR'!$P$7:$P$106=13)*(ROW('02 MONITOR'!$B$7:$B$106)-6))),"") | F64: =IFERROR(INDEX('02 MONITOR'!$D$7:$D$106,SUMPRODUCT(('02 MONITOR'!$B$7:$B$106="FX")*('02 MONITOR'!$P$7:$P$106=13)*(ROW('02 MONITOR'!$B$7:$B$106)-6))),"") | G64: =IFERROR(INDEX('02 MONITOR'!$M$7:$M$106,SUMPRODUCT(('02 MONITOR'!$B$7:$B$106="FX")*('02 MONITOR'!$P$7:$P$106=13)*(ROW('02 MONITOR'!$B$7:$B$106)-6))),"") | H64: LONG | I64: =IFERROR(IF(ABS($G64)<SETTINGS_ZMIN,0,ABS($G64)),"") | J64: =IFERROR($I64/SUMPRODUCT(($C$8:$C$107=$C64)*($H$8:$H$107=$H64)*$I$8:$I$107)*(SETTINGS_GROSS/2/5),"") | K64: =IFERROR($J64*SETTINGS_CAP*IF($H64="SHORT",-1,1),"") | L64: Spot (or REER) | M64: 3m NDF or deliverable forward. Long the cheap currency, short the rich one.
B65: 58 | C65: FX | D65: 14 | E65: =IFERROR(INDEX('02 MONITOR'!$C$7:$C$106,SUMPRODUCT(('02 MONITOR'!$B$7:$B$106="FX")*('02 MONITOR'!$P$7:$P$106=14)*(ROW('02 MONITOR'!$B$7:$B$106)-6))),"") | F65: =IFERROR(INDEX('02 MONITOR'!$D$7:$D$106,SUMPRODUCT(('02 MONITOR'!$B$7:$B$106="FX")*('02 MONITOR'!$P$7:$P$106=14)*(ROW('02 MONITOR'!$B$7:$B$106)-6))),"") | G65: =IFERROR(INDEX('02 MONITOR'!$M$7:$M$106,SUMPRODUCT(('02 MONITOR'!$B$7:$B$106="FX")*('02 MONITOR'!$P$7:$P$106=14)*(ROW('02 MONITOR'!$B$7:$B$106)-6))),"") | H65: SHORT | I65: =IFERROR(IF(ABS($G65)<SETTINGS_ZMIN,0,ABS($G65)),"") | J65: =IFERROR($I65/SUMPRODUCT(($C$8:$C$107=$C65)*($H$8:$H$107=$H65)*$I$8:$I$107)*(SETTINGS_GROSS/2/5),"") | K65: =IFERROR($J65*SETTINGS_CAP*IF($H65="SHORT",-1,1),"") | L65: Spot (or REER) | M65: 3m NDF or deliverable forward. Long the cheap currency, short the rich one.
B66: 59 | C66: FX | D66: 15 | E66: =IFERROR(INDEX('02 MONITOR'!$C$7:$C$106,SUMPRODUCT(('02 MONITOR'!$B$7:$B$106="FX")*('02 MONITOR'!$P$7:$P$106=15)*(ROW('02 MONITOR'!$B$7:$B$106)-6))),"") | F66: =IFERROR(INDEX('02 MONITOR'!$D$7:$D$106,SUMPRODUCT(('02 MONITOR'!$B$7:$B$106="FX")*('02 MONITOR'!$P$7:$P$106=15)*(ROW('02 MONITOR'!$B$7:$B$106)-6))),"") | G66: =IFERROR(INDEX('02 MONITOR'!$M$7:$M$106,SUMPRODUCT(('02 MONITOR'!$B$7:$B$106="FX")*('02 MONITOR'!$P$7:$P$106=15)*(ROW('02 MONITOR'!$B$7:$B$106)-6))),"") | H66: SHORT | I66: =IFERROR(IF(ABS($G66)<SETTINGS_ZMIN,0,ABS($G66)),"") | J66: =IFERROR($I66/SUMPRODUCT(($C$8:$C$107=$C66)*($H$8:$H$107=$H66)*$I$8:$I$107)*(SETTINGS_GROSS/2/5),"") | K66: =IFERROR($J66*SETTINGS_CAP*IF($H66="SHORT",-1,1),"") | L66: Spot (or REER) | M66: 3m NDF or deliverable forward. Long the cheap currency, short the rich one.
B67: 60 | C67: FX | D67: 16 | E67: =IFERROR(INDEX('02 MONITOR'!$C$7:$C$106,SUMPRODUCT(('02 MONITOR'!$B$7:$B$106="FX")*('02 MONITOR'!$P$7:$P$106=16)*(ROW('02 MONITOR'!$B$7:$B$106)-6))),"") | F67: =IFERROR(INDEX('02 MONITOR'!$D$7:$D$106,SUMPRODUCT(('02 MONITOR'!$B$7:$B$106="FX")*('02 MONITOR'!$P$7:$P$106=16)*(ROW('02 MONITOR'!$B$7:$B$106)-6))),"") | G67: =IFERROR(INDEX('02 MONITOR'!$M$7:$M$106,SUMPRODUCT(('02 MONITOR'!$B$7:$B$106="FX")*('02 MONITOR'!$P$7:$P$106=16)*(ROW('02 MONITOR'!$B$7:$B$106)-6))),"") | H67: SHORT | I67: =IFERROR(IF(ABS($G67)<SETTINGS_ZMIN,0,ABS($G67)),"") | J67: =IFERROR($I67/SUMPRODUCT(($C$8:$C$107=$C67)*($H$8:$H$107=$H67)*$I$8:$I$107)*(SETTINGS_GROSS/2/5),"") | K67: =IFERROR($J67*SETTINGS_CAP*IF($H67="SHORT",-1,1),"") | L67: Spot (or REER) | M67: 3m NDF or deliverable forward. Long the cheap currency, short the rich one.
B68: 61 | C68: FX | D68: 17 | E68: =IFERROR(INDEX('02 MONITOR'!$C$7:$C$106,SUMPRODUCT(('02 MONITOR'!$B$7:$B$106="FX")*('02 MONITOR'!$P$7:$P$106=17)*(ROW('02 MONITOR'!$B$7:$B$106)-6))),"") | F68: =IFERROR(INDEX('02 MONITOR'!$D$7:$D$106,SUMPRODUCT(('02 MONITOR'!$B$7:$B$106="FX")*('02 MONITOR'!$P$7:$P$106=17)*(ROW('02 MONITOR'!$B$7:$B$106)-6))),"") | G68: =IFERROR(INDEX('02 MONITOR'!$M$7:$M$106,SUMPRODUCT(('02 MONITOR'!$B$7:$B$106="FX")*('02 MONITOR'!$P$7:$P$106=17)*(ROW('02 MONITOR'!$B$7:$B$106)-6))),"") | H68: SHORT | I68: =IFERROR(IF(ABS($G68)<SETTINGS_ZMIN,0,ABS($G68)),"") | J68: =IFERROR($I68/SUMPRODUCT(($C$8:$C$107=$C68)*($H$8:$H$107=$H68)*$I$8:$I$107)*(SETTINGS_GROSS/2/5),"") | K68: =IFERROR($J68*SETTINGS_CAP*IF($H68="SHORT",-1,1),"") | L68: Spot (or REER) | M68: 3m NDF or deliverable forward. Long the cheap currency, short the rich one.
B69: 62 | C69: FX | D69: 18 | E69: =IFERROR(INDEX('02 MONITOR'!$C$7:$C$106,SUMPRODUCT(('02 MONITOR'!$B$7:$B$106="FX")*('02 MONITOR'!$P$7:$P$106=18)*(ROW('02 MONITOR'!$B$7:$B$106)-6))),"") | F69: =IFERROR(INDEX('02 MONITOR'!$D$7:$D$106,SUMPRODUCT(('02 MONITOR'!$B$7:$B$106="FX")*('02 MONITOR'!$P$7:$P$106=18)*(ROW('02 MONITOR'!$B$7:$B$106)-6))),"") | G69: =IFERROR(INDEX('02 MONITOR'!$M$7:$M$106,SUMPRODUCT(('02 MONITOR'!$B$7:$B$106="FX")*('02 MONITOR'!$P$7:$P$106=18)*(ROW('02 MONITOR'!$B$7:$B$106)-6))),"") | H69: SHORT | I69: =IFERROR(IF(ABS($G69)<SETTINGS_ZMIN,0,ABS($G69)),"") | J69: =IFERROR($I69/SUMPRODUCT(($C$8:$C$107=$C69)*($H$8:$H$107=$H69)*$I$8:$I$107)*(SETTINGS_GROSS/2/5),"") | K69: =IFERROR($J69*SETTINGS_CAP*IF($H69="SHORT",-1,1),"") | L69: Spot (or REER) | M69: 3m NDF or deliverable forward. Long the cheap currency, short the rich one.
B70: 63 | C70: FX | D70: 19 | E70: =IFERROR(INDEX('02 MONITOR'!$C$7:$C$106,SUMPRODUCT(('02 MONITOR'!$B$7:$B$106="FX")*('02 MONITOR'!$P$7:$P$106=19)*(ROW('02 MONITOR'!$B$7:$B$106)-6))),"") | F70: =IFERROR(INDEX('02 MONITOR'!$D$7:$D$106,SUMPRODUCT(('02 MONITOR'!$B$7:$B$106="FX")*('02 MONITOR'!$P$7:$P$106=19)*(ROW('02 MONITOR'!$B$7:$B$106)-6))),"") | G70: =IFERROR(INDEX('02 MONITOR'!$M$7:$M$106,SUMPRODUCT(('02 MONITOR'!$B$7:$B$106="FX")*('02 MONITOR'!$P$7:$P$106=19)*(ROW('02 MONITOR'!$B$7:$B$106)-6))),"") | H70: SHORT | I70: =IFERROR(IF(ABS($G70)<SETTINGS_ZMIN,0,ABS($G70)),"") | J70: =IFERROR($I70/SUMPRODUCT(($C$8:$C$107=$C70)*($H$8:$H$107=$H70)*$I$8:$I$107)*(SETTINGS_GROSS/2/5),"") | K70: =IFERROR($J70*SETTINGS_CAP*IF($H70="SHORT",-1,1),"") | L70: Spot (or REER) | M70: 3m NDF or deliverable forward. Long the cheap currency, short the rich one.
