Workbook

Sheet Data
A1: S&P 500 Constituents — Total Return Performance
A3: Refresh | B3: =Settings!B4 | D3: Custom date | E3: =Settings!B8 | G3: # Tickers loaded | H3: 506
A5: Bloomberg Ticker | B5: Name | C5: GICS Sector | D5: Price | E5: TR YTD | F5: TR 1M | G5: TR 3M | H5: TR vs Custom
A6: A US Equity | B6: =IFERROR(BDP(A6,"NAME"),"") | C6: =IFERROR(BDP(A6,"GICS_SECTOR_NAME"),"") | D6: =IFERROR(BDP(A6,"PX_LAST"),"") | E6: =IFERROR(BDP(A6,"CUST_TRR_RETURN_HOLDING_PER","CUST_TRR_START_DT",Settings!$C$5,"CUST_TRR_END_DT",Settings!$C$4)/100,"") | F6: =IFERROR(BDP(A6,"CUST_TRR_RETURN_HOLDING_PER","CUST_TRR_START_DT",Settings!$C$6,"CUST_TRR_END_DT",Settings!$C$4)/100,"") | G6: =IFERROR(BDP(A6,"CUST_TRR_RETURN_HOLDING_PER","CUST_TRR_START_DT",Settings!$C$7,"CUST_TRR_END_DT",Settings!$C$4)/100,"") | H6: =IFERROR(BDP(A6,"CUST_TRR_RETURN_HOLDING_PER","CUST_TRR_START_DT",Settings!$C$8,"CUST_TRR_END_DT",Settings!$C$4)/100,"")
A7: AAL US Equity | B7: =IFERROR(BDP(A7,"NAME"),"") | C7: =IFERROR(BDP(A7,"GICS_SECTOR_NAME"),"") | D7: =IFERROR(BDP(A7,"PX_LAST"),"") | E7: =IFERROR(BDP(A7,"CUST_TRR_RETURN_HOLDING_PER","CUST_TRR_START_DT",Settings!$C$5,"CUST_TRR_END_DT",Settings!$C$4)/100,"") | F7: =IFERROR(BDP(A7,"CUST_TRR_RETURN_HOLDING_PER","CUST_TRR_START_DT",Settings!$C$6,"CUST_TRR_END_DT",Settings!$C$4)/100,"") | G7: =IFERROR(BDP(A7,"CUST_TRR_RETURN_HOLDING_PER","CUST_TRR_START_DT",Settings!$C$7,"CUST_TRR_END_DT",Settings!$C$4)/100,"") | H7: =IFERROR(BDP(A7,"CUST_TRR_RETURN_HOLDING_PER","CUST_TRR_START_DT",Settings!$C$8,"CUST_TRR_END_DT",Settings!$C$4)/100,"")
A8: AAPL US Equity | B8: =IFERROR(BDP(A8,"NAME"),"") | C8: =IFERROR(BDP(A8,"GICS_SECTOR_NAME"),"") | D8: =IFERROR(BDP(A8,"PX_LAST"),"") | E8: =IFERROR(BDP(A8,"CUST_TRR_RETURN_HOLDING_PER","CUST_TRR_START_DT",Settings!$C$5,"CUST_TRR_END_DT",Settings!$C$4)/100,"") | F8: =IFERROR(BDP(A8,"CUST_TRR_RETURN_HOLDING_PER","CUST_TRR_START_DT",Settings!$C$6,"CUST_TRR_END_DT",Settings!$C$4)/100,"") | G8: =IFERROR(BDP(A8,"CUST_TRR_RETURN_HOLDING_PER","CUST_TRR_START_DT",Settings!$C$7,"CUST_TRR_END_DT",Settings!$C$4)/100,"") | H8: =IFERROR(BDP(A8,"CUST_TRR_RETURN_HOLDING_PER","CUST_TRR_START_DT",Settings!$C$8,"CUST_TRR_END_DT",Settings!$C$4)/100,"")
A9: ABBV US Equity | B9: =IFERROR(BDP(A9,"NAME"),"") | C9: =IFERROR(BDP(A9,"GICS_SECTOR_NAME"),"") | D9: =IFERROR(BDP(A9,"PX_LAST"),"") | E9: =IFERROR(BDP(A9,"CUST_TRR_RETURN_HOLDING_PER","CUST_TRR_START_DT",Settings!$C$5,"CUST_TRR_END_DT",Settings!$C$4)/100,"") | F9: =IFERROR(BDP(A9,"CUST_TRR_RETURN_HOLDING_PER","CUST_TRR_START_DT",Settings!$C$6,"CUST_TRR_END_DT",Settings!$C$4)/100,"") | G9: =IFERROR(BDP(A9,"CUST_TRR_RETURN_HOLDING_PER","CUST_TRR_START_DT",Settings!$C$7,"CUST_TRR_END_DT",Settings!$C$4)/100,"") | H9: =IFERROR(BDP(A9,"CUST_TRR_RETURN_HOLDING_PER","CUST_TRR_START_DT",Settings!$C$8,"CUST_TRR_END_DT",Settings!$C$4)/100,"")
A10: ABNB US Equity | B10: =IFERROR(BDP(A10,"NAME"),"") | C10: =IFERROR(BDP(A10,"GICS_SECTOR_NAME"),"") | D10: =IFERROR(BDP(A10,"PX_LAST"),"") | E10: =IFERROR(BDP(A10,"CUST_TRR_RETURN_HOLDING_PER","CUST_TRR_START_DT",Settings!$C$5,"CUST_TRR_END_DT",Settings!$C$4)/100,"") | F10: =IFERROR(BDP(A10,"CUST_TRR_RETURN_HOLDING_PER","CUST_TRR_START_DT",Settings!$C$6,"CUST_TRR_END_DT",Settings!$C$4)/100,"") | G10: =IFERROR(BDP(A10,"CUST_TRR_RETURN_HOLDING_PER","CUST_TRR_START_DT",Settings!$C$7,"CUST_TRR_END_DT",Settings!$C$4)/100,"") | H10: =IFERROR(BDP(A10,"CUST_TRR_RETURN_HOLDING_PER","CUST_TRR_START_DT",Settings!$C$8,"CUST_TRR_END_DT",Settings!$C$4)/100,"")
A11: ABT US Equity | B11: =IFERROR(BDP(A11,"NAME"),"") | C11: =IFERROR(BDP(A11,"GICS_SECTOR_NAME"),"") | D11: =IFERROR(BDP(A11,"PX_LAST"),"") | E11: =IFERROR(BDP(A11,"CUST_TRR_RETURN_HOLDING_PER","CUST_TRR_START_DT",Settings!$C$5,"CUST_TRR_END_DT",Settings!$C$4)/100,"") | F11: =IFERROR(BDP(A11,"CUST_TRR_RETURN_HOLDING_PER","CUST_TRR_START_DT",Settings!$C$6,"CUST_TRR_END_DT",Settings!$C$4)/100,"") | G11: =IFERROR(BDP(A11,"CUST_TRR_RETURN_HOLDING_PER","CUST_TRR_START_DT",Settings!$C$7,"CUST_TRR_END_DT",Settings!$C$4)/100,"") | H11: =IFERROR(BDP(A11,"CUST_TRR_RETURN_HOLDING_PER","CUST_TRR_START_DT",Settings!$C$8,"CUST_TRR_END_DT",Settings!$C$4)/100,"")
A12: ACGL US Equity | B12: =IFERROR(BDP(A12,"NAME"),"") | C12: =IFERROR(BDP(A12,"GICS_SECTOR_NAME"),"") | D12: =IFERROR(BDP(A12,"PX_LAST"),"") | E12: =IFERROR(BDP(A12,"CUST_TRR_RETURN_HOLDING_PER","CUST_TRR_START_DT",Settings!$C$5,"CUST_TRR_END_DT",Settings!$C$4)/100,"") | F12: =IFERROR(BDP(A12,"CUST_TRR_RETURN_HOLDING_PER","CUST_TRR_START_DT",Settings!$C$6,"CUST_TRR_END_DT",Settings!$C$4)/100,"") | G12: =IFERROR(BDP(A12,"CUST_TRR_RETURN_HOLDING_PER","CUST_TRR_START_DT",Settings!$C$7,"CUST_TRR_END_DT",Settings!$C$4)/100,"") | H12: =IFERROR(BDP(A12,"CUST_TRR_RETURN_HOLDING_PER","CUST_TRR_START_DT",Settings!$C$8,"CUST_TRR_END_DT",Settings!$C$4)/100,"")
A13: ACN US Equity | B13: =IFERROR(BDP(A13,"NAME"),"") | C13: =IFERROR(BDP(A13,"GICS_SECTOR_NAME"),"") | D13: =IFERROR(BDP(A13,"PX_LAST"),"") | E13: =IFERROR(BDP(A13,"CUST_TRR_RETURN_HOLDING_PER","CUST_TRR_START_DT",Settings!$C$5,"CUST_TRR_END_DT",Settings!$C$4)/100,"") | F13: =IFERROR(BDP(A13,"CUST_TRR_RETURN_HOLDING_PER","CUST_TRR_START_DT",Settings!$C$6,"CUST_TRR_END_DT",Settings!$C$4)/100,"") | G13: =IFERROR(BDP(A13,"CUST_TRR_RETURN_HOLDING_PER","CUST_TRR_START_DT",Settings!$C$7,"CUST_TRR_END_DT",Settings!$C$4)/100,"") | H13: =IFERROR(BDP(A13,"CUST_TRR_RETURN_HOLDING_PER","CUST_TRR_START_DT",Settings!$C$8,"CUST_TRR_END_DT",Settings!$C$4)/100,"")
A14: ADBE US Equity | B14: =IFERROR(BDP(A14,"NAME"),"") | C14: =IFERROR(BDP(A14,"GICS_SECTOR_NAME"),"") | D14: =IFERROR(BDP(A14,"PX_LAST"),"") | E14: =IFERROR(BDP(A14,"CUST_TRR_RETURN_HOLDING_PER","CUST_TRR_START_DT",Settings!$C$5,"CUST_TRR_END_DT",Settings!$C$4)/100,"") | F14: =IFERROR(BDP(A14,"CUST_TRR_RETURN_HOLDING_PER","CUST_TRR_START_DT",Settings!$C$6,"CUST_TRR_END_DT",Settings!$C$4)/100,"") | G14: =IFERROR(BDP(A14,"CUST_TRR_RETURN_HOLDING_PER","CUST_TRR_START_DT",Settings!$C$7,"CUST_TRR_END_DT",Settings!$C$4)/100,"") | H14: =IFERROR(BDP(A14,"CUST_TRR_RETURN_HOLDING_PER","CUST_TRR_START_DT",Settings!$C$8,"CUST_TRR_END_DT",Settings!$C$4)/100,"")
A15: ADI US Equity | B15: =IFERROR(BDP(A15,"NAME"),"") | C15: =IFERROR(BDP(A15,"GICS_SECTOR_NAME"),"") | D15: =IFERROR(BDP(A15,"PX_LAST"),"") | E15: =IFERROR(BDP(A15,"CUST_TRR_RETURN_HOLDING_PER","CUST_TRR_START_DT",Settings!$C$5,"CUST_TRR_END_DT",Settings!$C$4)/100,"") | F15: =IFERROR(BDP(A15,"CUST_TRR_RETURN_HOLDING_PER","CUST_TRR_START_DT",Settings!$C$6,"CUST_TRR_END_DT",Settings!$C$4)/100,"") | G15: =IFERROR(BDP(A15,"CUST_TRR_RETURN_HOLDING_PER","CUST_TRR_START_DT",Settings!$C$7,"CUST_TRR_END_DT",Settings!$C$4)/100,"") | H15: =IFERROR(BDP(A15,"CUST_TRR_RETURN_HOLDING_PER","CUST_TRR_START_DT",Settings!$C$8,"CUST_TRR_END_DT",Settings!$C$4)/100,"")
A16: ADM US Equity | B16: =IFERROR(BDP(A16,"NAME"),"") | C16: =IFERROR(BDP(A16,"GICS_SECTOR_NAME"),"") | D16: =IFERROR(BDP(A16,"PX_LAST"),"") | E16: =IFERROR(BDP(A16,"CUST_TRR_RETURN_HOLDING_PER","CUST_TRR_START_DT",Settings!$C$5,"CUST_TRR_END_DT",Settings!$C$4)/100,"") | F16: =IFERROR(BDP(A16,"CUST_TRR_RETURN_HOLDING_PER","CUST_TRR_START_DT",Settings!$C$6,"CUST_TRR_END_DT",Settings!$C$4)/100,"") | G16: =IFERROR(BDP(A16,"CUST_TRR_RETURN_HOLDING_PER","CUST_TRR_START_DT",Settings!$C$7,"CUST_TRR_END_DT",Settings!$C$4)/100,"") | H16: =IFERROR(BDP(A16,"CUST_TRR_RETURN_HOLDING_PER","CUST_TRR_START_DT",Settings!$C$8,"CUST_TRR_END_DT",Settings!$C$4)/100,"")
A17: ADP US Equity | B17: =IFERROR(BDP(A17,"NAME"),"") | C17: =IFERROR(BDP(A17,"GICS_SECTOR_NAME"),"") | D17: =IFERROR(BDP(A17,"PX_LAST"),"") | E17: =IFERROR(BDP(A17,"CUST_TRR_RETURN_HOLDING_PER","CUST_TRR_START_DT",Settings!$C$5,"CUST_TRR_END_DT",Settings!$C$4)/100,"") | F17: =IFERROR(BDP(A17,"CUST_TRR_RETURN_HOLDING_PER","CUST_TRR_START_DT",Settings!$C$6,"CUST_TRR_END_DT",Settings!$C$4)/100,"") | G17: =IFERROR(BDP(A17,"CUST_TRR_RETURN_HOLDING_PER","CUST_TRR_START_DT",Settings!$C$7,"CUST_TRR_END_DT",Settings!$C$4)/100,"") | H17: =IFERROR(BDP(A17,"CUST_TRR_RETURN_HOLDING_PER","CUST_TRR_START_DT",Settings!$C$8,"CUST_TRR_END_DT",Settings!$C$4)/100,"")
... A511: ZTS US Equity | B511: =IFERROR(BDP(A511,"NAME"),"") | C511: =IFERROR(BDP(A511,"GICS_SECTOR_NAME"),"") | D511: =IFERROR(BDP(A511,"PX_LAST"),"") | E511: =IFERROR(BDP(A511,"CUST_TRR_RETURN_HOLDING_PER","CUST_TRR_START_DT",Settings!$C$5,"CUST_TRR_END_DT",Settings!$C$4)/100,"") | F511: =IFERROR(BDP(A511,"CUST_TRR_RETURN_HOLDING_PER","CUST_TRR_START_DT",Settings!$C$6,"CUST_TRR_END_DT",Settings!$C$4)/100,"") | G511: =IFERROR(BDP(A511,"CUST_TRR_RETURN_HOLDING_PER","CUST_TRR_START_DT",Settings!$C$7,"CUST_TRR_END_DT",Settings!$C$4)/100,"") | H511: =IFERROR(BDP(A511,"CUST_TRR_RETURN_HOLDING_PER","CUST_TRR_START_DT",Settings!$C$8,"CUST_TRR_END_DT",Settings!$C$4)/100,"")
A513: Notes:
A514: • Blue = Bloomberg ticker (edit / paste your full S&P 500 list here). Formulas on each row auto-pull Name, Sector, Price, TR.
A515: • Sort or filter by column to rank winners/losers per window.
A516: • If your firm prefers gross dividend TR, swap CUST_TRR_RETURN_HOLDING_PER for the appropriate field.

Sheet Best & Worst YTD
A1: S&P 500 — Top 10 & Bottom 10 Stocks (Year-to-Date Total Return)
A2: Pulled live from the Data tab. Sort/refresh in Excel with Bloomberg connected.
A4: TOP 10 — Best YTD Total Return
A5: Rank | B5: Ticker | C5: Name | D5: GICS Sector | E5: Price | F5: TR YTD
A6: 1 | B6: =IFERROR(INDEX(Data!$A$6:$A$511,MATCH(LARGE(Data!$E$6:$E$511,1),Data!$E$6:$E$511,0)),"") | C6: =IFERROR(INDEX(Data!$B$6:$B$511,MATCH(LARGE(Data!$E$6:$E$511,1),Data!$E$6:$E$511,0)),"") | D6: =IFERROR(INDEX(Data!$C$6:$C$511,MATCH(LARGE(Data!$E$6:$E$511,1),Data!$E$6:$E$511,0)),"") | E6: =IFERROR(INDEX(Data!$D$6:$D$511,MATCH(LARGE(Data!$E$6:$E$511,1),Data!$E$6:$E$511,0)),"") | F6: =IFERROR(LARGE(Data!$E$6:$E$511,1),"")
A7: 2 | B7: =IFERROR(INDEX(Data!$A$6:$A$511,MATCH(LARGE(Data!$E$6:$E$511,2),Data!$E$6:$E$511,0)),"") | C7: =IFERROR(INDEX(Data!$B$6:$B$511,MATCH(LARGE(Data!$E$6:$E$511,2),Data!$E$6:$E$511,0)),"") | D7: =IFERROR(INDEX(Data!$C$6:$C$511,MATCH(LARGE(Data!$E$6:$E$511,2),Data!$E$6:$E$511,0)),"") | E7: =IFERROR(INDEX(Data!$D$6:$D$511,MATCH(LARGE(Data!$E$6:$E$511,2),Data!$E$6:$E$511,0)),"") | F7: =IFERROR(LARGE(Data!$E$6:$E$511,2),"")
A8: 3 | B8: =IFERROR(INDEX(Data!$A$6:$A$511,MATCH(LARGE(Data!$E$6:$E$511,3),Data!$E$6:$E$511,0)),"") | C8: =IFERROR(INDEX(Data!$B$6:$B$511,MATCH(LARGE(Data!$E$6:$E$511,3),Data!$E$6:$E$511,0)),"") | D8: =IFERROR(INDEX(Data!$C$6:$C$511,MATCH(LARGE(Data!$E$6:$E$511,3),Data!$E$6:$E$511,0)),"") | E8: =IFERROR(INDEX(Data!$D$6:$D$511,MATCH(LARGE(Data!$E$6:$E$511,3),Data!$E$6:$E$511,0)),"") | F8: =IFERROR(LARGE(Data!$E$6:$E$511,3),"")
A9: 4 | B9: =IFERROR(INDEX(Data!$A$6:$A$511,MATCH(LARGE(Data!$E$6:$E$511,4),Data!$E$6:$E$511,0)),"") | C9: =IFERROR(INDEX(Data!$B$6:$B$511,MATCH(LARGE(Data!$E$6:$E$511,4),Data!$E$6:$E$511,0)),"") | D9: =IFERROR(INDEX(Data!$C$6:$C$511,MATCH(LARGE(Data!$E$6:$E$511,4),Data!$E$6:$E$511,0)),"") | E9: =IFERROR(INDEX(Data!$D$6:$D$511,MATCH(LARGE(Data!$E$6:$E$511,4),Data!$E$6:$E$511,0)),"") | F9: =IFERROR(LARGE(Data!$E$6:$E$511,4),"")
A10: 5 | B10: =IFERROR(INDEX(Data!$A$6:$A$511,MATCH(LARGE(Data!$E$6:$E$511,5),Data!$E$6:$E$511,0)),"") | C10: =IFERROR(INDEX(Data!$B$6:$B$511,MATCH(LARGE(Data!$E$6:$E$511,5),Data!$E$6:$E$511,0)),"") | D10: =IFERROR(INDEX(Data!$C$6:$C$511,MATCH(LARGE(Data!$E$6:$E$511,5),Data!$E$6:$E$511,0)),"") | E10: =IFERROR(INDEX(Data!$D$6:$D$511,MATCH(LARGE(Data!$E$6:$E$511,5),Data!$E$6:$E$511,0)),"") | F10: =IFERROR(LARGE(Data!$E$6:$E$511,5),"")
A11: 6 | B11: =IFERROR(INDEX(Data!$A$6:$A$511,MATCH(LARGE(Data!$E$6:$E$511,6),Data!$E$6:$E$511,0)),"") | C11: =IFERROR(INDEX(Data!$B$6:$B$511,MATCH(LARGE(Data!$E$6:$E$511,6),Data!$E$6:$E$511,0)),"") | D11: =IFERROR(INDEX(Data!$C$6:$C$511,MATCH(LARGE(Data!$E$6:$E$511,6),Data!$E$6:$E$511,0)),"") | E11: =IFERROR(INDEX(Data!$D$6:$D$511,MATCH(LARGE(Data!$E$6:$E$511,6),Data!$E$6:$E$511,0)),"") | F11: =IFERROR(LARGE(Data!$E$6:$E$511,6),"")
A12: 7 | B12: =IFERROR(INDEX(Data!$A$6:$A$511,MATCH(LARGE(Data!$E$6:$E$511,7),Data!$E$6:$E$511,0)),"") | C12: =IFERROR(INDEX(Data!$B$6:$B$511,MATCH(LARGE(Data!$E$6:$E$511,7),Data!$E$6:$E$511,0)),"") | D12: =IFERROR(INDEX(Data!$C$6:$C$511,MATCH(LARGE(Data!$E$6:$E$511,7),Data!$E$6:$E$511,0)),"") | E12: =IFERROR(INDEX(Data!$D$6:$D$511,MATCH(LARGE(Data!$E$6:$E$511,7),Data!$E$6:$E$511,0)),"") | F12: =IFERROR(LARGE(Data!$E$6:$E$511,7),"")
A13: 8 | B13: =IFERROR(INDEX(Data!$A$6:$A$511,MATCH(LARGE(Data!$E$6:$E$511,8),Data!$E$6:$E$511,0)),"") | C13: =IFERROR(INDEX(Data!$B$6:$B$511,MATCH(LARGE(Data!$E$6:$E$511,8),Data!$E$6:$E$511,0)),"") | D13: =IFERROR(INDEX(Data!$C$6:$C$511,MATCH(LARGE(Data!$E$6:$E$511,8),Data!$E$6:$E$511,0)),"") | E13: =IFERROR(INDEX(Data!$D$6:$D$511,MATCH(LARGE(Data!$E$6:$E$511,8),Data!$E$6:$E$511,0)),"") | F13: =IFERROR(LARGE(Data!$E$6:$E$511,8),"")
A14: 9 | B14: =IFERROR(INDEX(Data!$A$6:$A$511,MATCH(LARGE(Data!$E$6:$E$511,9),Data!$E$6:$E$511,0)),"") | C14: =IFERROR(INDEX(Data!$B$6:$B$511,MATCH(LARGE(Data!$E$6:$E$511,9),Data!$E$6:$E$511,0)),"") | D14: =IFERROR(INDEX(Data!$C$6:$C$511,MATCH(LARGE(Data!$E$6:$E$511,9),Data!$E$6:$E$511,0)),"") | E14: =IFERROR(INDEX(Data!$D$6:$D$511,MATCH(LARGE(Data!$E$6:$E$511,9),Data!$E$6:$E$511,0)),"") | F14: =IFERROR(LARGE(Data!$E$6:$E$511,9),"")
A15: 10 | B15: =IFERROR(INDEX(Data!$A$6:$A$511,MATCH(LARGE(Data!$E$6:$E$511,10),Data!$E$6:$E$511,0)),"") | C15: =IFERROR(INDEX(Data!$B$6:$B$511,MATCH(LARGE(Data!$E$6:$E$511,10),Data!$E$6:$E$511,0)),"") | D15: =IFERROR(INDEX(Data!$C$6:$C$511,MATCH(LARGE(Data!$E$6:$E$511,10),Data!$E$6:$E$511,0)),"") | E15: =IFERROR(INDEX(Data!$D$6:$D$511,MATCH(LARGE(Data!$E$6:$E$511,10),Data!$E$6:$E$511,0)),"") | F15: =IFERROR(LARGE(Data!$E$6:$E$511,10),"")
A18: BOTTOM 10 — Worst YTD Total Return
A19: Rank | B19: Ticker | C19: Name | D19: GICS Sector | E19: Price | F19: TR YTD
A20: 1 | B20: =IFERROR(INDEX(Data!$A$6:$A$511,MATCH(SMALL(Data!$E$6:$E$511,1),Data!$E$6:$E$511,0)),"") | C20: =IFERROR(INDEX(Data!$B$6:$B$511,MATCH(SMALL(Data!$E$6:$E$511,1),Data!$E$6:$E$511,0)),"") | D20: =IFERROR(INDEX(Data!$C$6:$C$511,MATCH(SMALL(Data!$E$6:$E$511,1),Data!$E$6:$E$511,0)),"") | E20: =IFERROR(INDEX(Data!$D$6:$D$511,MATCH(SMALL(Data!$E$6:$E$511,1),Data!$E$6:$E$511,0)),"") | F20: =IFERROR(SMALL(Data!$E$6:$E$511,1),"")
A21: 2 | B21: =IFERROR(INDEX(Data!$A$6:$A$511,MATCH(SMALL(Data!$E$6:$E$511,2),Data!$E$6:$E$511,0)),"") | C21: =IFERROR(INDEX(Data!$B$6:$B$511,MATCH(SMALL(Data!$E$6:$E$511,2),Data!$E$6:$E$511,0)),"") | D21: =IFERROR(INDEX(Data!$C$6:$C$511,MATCH(SMALL(Data!$E$6:$E$511,2),Data!$E$6:$E$511,0)),"") | E21: =IFERROR(INDEX(Data!$D$6:$D$511,MATCH(SMALL(Data!$E$6:$E$511,2),Data!$E$6:$E$511,0)),"") | F21: =IFERROR(SMALL(Data!$E$6:$E$511,2),"")
A22: 3 | B22: =IFERROR(INDEX(Data!$A$6:$A$511,MATCH(SMALL(Data!$E$6:$E$511,3),Data!$E$6:$E$511,0)),"") | C22: =IFERROR(INDEX(Data!$B$6:$B$511,MATCH(SMALL(Data!$E$6:$E$511,3),Data!$E$6:$E$511,0)),"") | D22: =IFERROR(INDEX(Data!$C$6:$C$511,MATCH(SMALL(Data!$E$6:$E$511,3),Data!$E$6:$E$511,0)),"") | E22: =IFERROR(INDEX(Data!$D$6:$D$511,MATCH(SMALL(Data!$E$6:$E$511,3),Data!$E$6:$E$511,0)),"") | F22: =IFERROR(SMALL(Data!$E$6:$E$511,3),"")
A23: 4 | B23: =IFERROR(INDEX(Data!$A$6:$A$511,MATCH(SMALL(Data!$E$6:$E$511,4),Data!$E$6:$E$511,0)),"") | C23: =IFERROR(INDEX(Data!$B$6:$B$511,MATCH(SMALL(Data!$E$6:$E$511,4),Data!$E$6:$E$511,0)),"") | D23: =IFERROR(INDEX(Data!$C$6:$C$511,MATCH(SMALL(Data!$E$6:$E$511,4),Data!$E$6:$E$511,0)),"") | E23: =IFERROR(INDEX(Data!$D$6:$D$511,MATCH(SMALL(Data!$E$6:$E$511,4),Data!$E$6:$E$511,0)),"") | F23: =IFERROR(SMALL(Data!$E$6:$E$511,4),"")
A24: 5 | B24: =IFERROR(INDEX(Data!$A$6:$A$511,MATCH(SMALL(Data!$E$6:$E$511,5),Data!$E$6:$E$511,0)),"") | C24: =IFERROR(INDEX(Data!$B$6:$B$511,MATCH(SMALL(Data!$E$6:$E$511,5),Data!$E$6:$E$511,0)),"") | D24: =IFERROR(INDEX(Data!$C$6:$C$511,MATCH(SMALL(Data!$E$6:$E$511,5),Data!$E$6:$E$511,0)),"") | E24: =IFERROR(INDEX(Data!$D$6:$D$511,MATCH(SMALL(Data!$E$6:$E$511,5),Data!$E$6:$E$511,0)),"") | F24: =IFERROR(SMALL(Data!$E$6:$E$511,5),"")
A25: 6 | B25: =IFERROR(INDEX(Data!$A$6:$A$511,MATCH(SMALL(Data!$E$6:$E$511,6),Data!$E$6:$E$511,0)),"") | C25: =IFERROR(INDEX(Data!$B$6:$B$511,MATCH(SMALL(Data!$E$6:$E$511,6),Data!$E$6:$E$511,0)),"") | D25: =IFERROR(INDEX(Data!$C$6:$C$511,MATCH(SMALL(Data!$E$6:$E$511,6),Data!$E$6:$E$511,0)),"") | E25: =IFERROR(INDEX(Data!$D$6:$D$511,MATCH(SMALL(Data!$E$6:$E$511,6),Data!$E$6:$E$511,0)),"") | F25: =IFERROR(SMALL(Data!$E$6:$E$511,6),"")
A26: 7 | B26: =IFERROR(INDEX(Data!$A$6:$A$511,MATCH(SMALL(Data!$E$6:$E$511,7),Data!$E$6:$E$511,0)),"") | C26: =IFERROR(INDEX(Data!$B$6:$B$511,MATCH(SMALL(Data!$E$6:$E$511,7),Data!$E$6:$E$511,0)),"") | D26: =IFERROR(INDEX(Data!$C$6:$C$511,MATCH(SMALL(Data!$E$6:$E$511,7),Data!$E$6:$E$511,0)),"") | E26: =IFERROR(INDEX(Data!$D$6:$D$511,MATCH(SMALL(Data!$E$6:$E$511,7),Data!$E$6:$E$511,0)),"") | F26: =IFERROR(SMALL(Data!$E$6:$E$511,7),"")
A27: 8 | B27: =IFERROR(INDEX(Data!$A$6:$A$511,MATCH(SMALL(Data!$E$6:$E$511,8),Data!$E$6:$E$511,0)),"") | C27: =IFERROR(INDEX(Data!$B$6:$B$511,MATCH(SMALL(Data!$E$6:$E$511,8),Data!$E$6:$E$511,0)),"") | D27: =IFERROR(INDEX(Data!$C$6:$C$511,MATCH(SMALL(Data!$E$6:$E$511,8),Data!$E$6:$E$511,0)),"") | E27: =IFERROR(INDEX(Data!$D$6:$D$511,MATCH(SMALL(Data!$E$6:$E$511,8),Data!$E$6:$E$511,0)),"") | F27: =IFERROR(SMALL(Data!$E$6:$E$511,8),"")
A28: 9 | B28: =IFERROR(INDEX(Data!$A$6:$A$511,MATCH(SMALL(Data!$E$6:$E$511,9),Data!$E$6:$E$511,0)),"") | C28: =IFERROR(INDEX(Data!$B$6:$B$511,MATCH(SMALL(Data!$E$6:$E$511,9),Data!$E$6:$E$511,0)),"") | D28: =IFERROR(INDEX(Data!$C$6:$C$511,MATCH(SMALL(Data!$E$6:$E$511,9),Data!$E$6:$E$511,0)),"") | E28: =IFERROR(INDEX(Data!$D$6:$D$511,MATCH(SMALL(Data!$E$6:$E$511,9),Data!$E$6:$E$511,0)),"") | F28: =IFERROR(SMALL(Data!$E$6:$E$511,9),"")
A29: 10 | B29: =IFERROR(INDEX(Data!$A$6:$A$511,MATCH(SMALL(Data!$E$6:$E$511,10),Data!$E$6:$E$511,0)),"") | C29: =IFERROR(INDEX(Data!$B$6:$B$511,MATCH(SMALL(Data!$E$6:$E$511,10),Data!$E$6:$E$511,0)),"") | D29: =IFERROR(INDEX(Data!$C$6:$C$511,MATCH(SMALL(Data!$E$6:$E$511,10),Data!$E$6:$E$511,0)),"") | E29: =IFERROR(INDEX(Data!$D$6:$D$511,MATCH(SMALL(Data!$E$6:$E$511,10),Data!$E$6:$E$511,0)),"") | F29: =IFERROR(SMALL(Data!$E$6:$E$511,10),"")
A31: Notes:
A32: • Rankings update automatically when Bloomberg refreshes the Data tab.
A33: • Ties: if two stocks tie on a YTD figure, MATCH returns the first occurrence in the Data tab — so the second tied name may appear at the next rank.
A34: • Want a different window (1M / 3M / Custom)? Copy this sheet and replace 'Data!$E$' with '$F$' (1M), '$G$' (3M), or '$H$' (Custom).

Sheet Settings
A1: S&P 500 Performance — Date Settings
A3: Label | B3: Date | C3: YYYYMMDD (Bloomberg) | D3: Used for
A4: Today | B4: =TODAY() | C4: =TEXT(B4,"yyyymmdd") | D4: End date for all windows
A5: YTD baseline | B5: =DATE(YEAR(TODAY())-1,12,31) | C5: =TEXT(B5,"yyyymmdd") | D5: Prior year-end close
A6: 1M ago | B6: =EDATE(TODAY(),-1) | C6: =TEXT(B6,"yyyymmdd") | D6: One month trailing
A7: 3M ago | B7: =EDATE(TODAY(),-3) | C7: =TEXT(B7,"yyyymmdd") | D7: Three months trailing
A8: Custom date | B8: =EDATE(TODAY(),-6) | C8: =TEXT(B8,"yyyymmdd") | D8: EDIT ME — pick any reference date
A10: Notes
A11: Edit B8 to compare today vs any date.
A12: TR uses CUST_TRR_RETURN_HOLDING_PER with date overrides — includes dividends.
A13: Formulas divide CUST_TRR by 100 to give a decimal then format as %. If your Bloomberg returns decimals, drop the /100.
A14: To extend the list: type or paste additional Bloomberg tickers into column A on the Data sheet — formulas will auto-fill.
