Workbook

Sheet Control
A1: US RATES & CREDIT MONITOR
A2: Bloomberg-linked. Every cell is a formula; nothing is pasted as a value. Built for A. Rojas, UBS CIO Americas.
A4: SETTINGS — every data pull and every calculation on every tab points at these cells
E5: Horizon | F5: Obs back (rows)
A6: History start — daily block | B6: =EDATE(TODAY(),-126) | E6: 1D | F6: 2 | H6: 10.5y buffer so the 10y window is always full
A7: History end | B7: =TODAY() | E7: 1W | F7: 6 | H7: BDH end date
A8: History start — monthly block | B8: =EDATE(TODAY(),-301) | E8: 1M | F8: 23 | H8: 25y of month-ends for deep percentiles
A9: Daily observations pulled | B9: 2610 | E9: 3M | F9: 66 | H9: weekdays; block is HIST_D rows 8:2617
A10: Monthly observations pulled | B10: 301 | E10: 6M | F10: 131 | H10: month-ends; block is HIST_M rows 8:308
A11: bp per 1% | B11: 100 | E11: 1Y | F11: 262 | H11: scaling constant used by every change column
A12: Total-return horizon (years) | B12: 1 | E12: 2Y | F12: 523 | H12: used on Credit_TR and the rates TR grid
A13: Cash hurdle (%) | B13: 4.5 | E13: 3Y | F13: 784 | H13: your stated hurdle for 'EM still attractive vs cash'
A14: Coupon frequency (per year) | B14: 2 | E14: 5Y | F14: 1305 | H14: semi-annual UST convention
A15: Point-in-time: 1W ago date | B15: =WORKDAY(TODAY(),-5) | E15: 10Y | F15: 2610 | H15: used by single-point BDH pulls (futures strip)
A16: Point-in-time: 1M ago date | B16: =WORKDAY(TODAY(),-22) | E16: YTD — row of last obs of prior year | F16: =MATCH(DATE(YEAR(TODAY()),1,1),HIST_D!$A$8:$A$2617,-1)+1 | H16: same
A17: Point-in-time: prior year-end | B17: =DATE(YEAR(TODAY())-1,12,31) | E17: Row 1 = today. Row n = n-1 weekdays ago (Days=W, Fill=P holds the calendar even on holidays). | H17: same
A19: HOW TO REFRESH
A20: 1. Open on a Bloomberg terminal with the Excel add-in loaded. Everything recalculates on open (fullCalcOnLoad is set).
A21: 2. If a history column shows only one number instead of a full column, you are on pre-dynamic-array Excel: select the block and re-enter the BDH with Ctrl+Shift+Enter.
A22: 3. To change any ticker, edit it ONCE on the Tickers tab. Every pull and every downstream calculation reads the ticker from there.
A23: 4. To change a lookback window, edit the 'Obs back' table above. Nothing else needs touching.
A24: 5. Yellow cells are the only ones you should ever type in.
A27: COLOUR LEGEND
A28: Yellow fill, blue text | E28: Hardcoded input or scenario lever — yours to change
A29: Purple text | E29: Live Bloomberg pull (BDH / BDP)
A30: Green text | E30: Link to another tab in this workbook
A31: Black text | E31: Calculation from cells in this workbook
A32: Grey italic | E32: Note, source, or method caveat
A34: HOW THE NUMBERS ARE BUILT — so you can audit any cell in one step
A35: History | E35: HIST_D holds a 10y weekday block, newest first (Sort=D). HIST_M holds 25y of month-ends. Every level, change, percentile and z-score on every other tab is INDEX() into those two blocks — no duplicate pulls.
A36: Changes | E36: Change over horizon h = (row 1 − row h) × 100, where h comes from the 'Obs back' table. Yields and OAS therefore always change in bp.
A37: Percentiles | E37: PERCENTRANK over the first N rows of the block, N from the same table. 0% = tightest/lowest ever in that window, 100% = widest/highest.
A38: 4y and 15y UST | E38: There is no clean cash-Treasury generic at 4y or 15y. Both are built as: linear interpolation of the neighbouring UST nodes PLUS the curvature the SOFR OIS curve actually shows at that tenor (OIS4 minus the linear interp of OIS3/OIS5). That is a real market-observed shape, not a straight line. The components are shown so you can see the adjustment.
A39: Forwards | E39: Bootstrapped from spot par yields as compounded ratios, e.g. 5y5y = ((1+y10)^10 / (1+y5)^5)^(1/5) − 1. Par-yield approximation; fine for monitoring, not for pricing.
A40: Duration / DV01 | E40: Exact par-bond algebra, semi-annual: Dmod = (1 − (1+y/2)^(−2n)) / (y/2) / 2. No table lookups, no hardcoded durations.
A41: Rates total return | E41: Full repricing, not a duration approximation. The bond is priced off the annuity formula at the horizon yield with (n − horizon) years left, plus coupons received. Convexity is therefore captured exactly.
A42: Credit total return | E42: Carry (yield-to-worst × horizon) + roll + (−OAD × Δrate) + (−spread duration × Δspread) − credit loss. Each leg is its own visible cell.
A43: Why the legs stay separate | E43: The EM USD case rests on the Treasury leg providing ballast. Rate and spread P&L are never merged into one number anywhere in this workbook.
A45: TICKER CONFIDENCE — read this before you trust a number
A46: Tickers on the Tickers tab are flagged High or Verify. High = standard Bloomberg security I would defend. Verify = the concept is right but the exact ticker or field should be confirmed in SECF / FLDS before you quote the number to anyone.
A47: Rather than substitute a modelled proxy for anything I could not confirm, the cell is left pointing at a named ticker with the flag on it. A Verify row that returns an error is telling you the truth: fix the ticker on the Tickers tab and the whole workbook follows.
A48: Where a field may not exist on an index security (index duration, index yield-to-worst), the cell is IFERROR(live pull, your fallback input) and the column beside it prints LIVE or FALLBACK so you always know which one you are looking at.

Sheet Dashboard
A1: US RATES & CREDIT — THE BOARD
A2: =("As of "&TEXT(TODAY(),"dd mmm yyyy")&" · every figure below is a link; nothing here is typed in")
A4: RATES
B5: Level | C5: 1D | D5: 1W | E5: 1M | F5: YTD | G5: 1Y | H5: %ile 1y | I5: %ile 5y | J5: %ile 25y | K5: z (5y) | L5: Note
A6: UST 2Y | B6: =INDEX(HIST_D!$F$8:$F$2617,1) | C6: =IFERROR((INDEX(HIST_D!$F$8:$F$2617,1)-INDEX(HIST_D!$F$8:$F$2617,Control!$F$6))*Control!$B$11,"") | D6: =IFERROR((INDEX(HIST_D!$F$8:$F$2617,1)-INDEX(HIST_D!$F$8:$F$2617,Control!$F$7))*Control!$B$11,"") | E6: =IFERROR((INDEX(HIST_D!$F$8:$F$2617,1)-INDEX(HIST_D!$F$8:$F$2617,Control!$F$8))*Control!$B$11,"") | F6: =IFERROR((INDEX(HIST_D!$F$8:$F$2617,1)-INDEX(HIST_D!$F$8:$F$2617,Control!$F$16))*Control!$B$11,"") | G6: =IFERROR((INDEX(HIST_D!$F$8:$F$2617,1)-INDEX(HIST_D!$F$8:$F$2617,Control!$F$11))*Control!$B$11,"") | H6: =IFERROR(PERCENTRANK(HIST_D!$F$8:INDEX(HIST_D!$F$8:$F$2617,Control!$F$11),INDEX(HIST_D!$F$8:$F$2617,1)),"") | I6: =IFERROR(PERCENTRANK(HIST_D!$F$8:INDEX(HIST_D!$F$8:$F$2617,Control!$F$14),INDEX(HIST_D!$F$8:$F$2617,1)),"") | J6: =IFERROR(PERCENTRANK(HIST_M!$B$8:$B$308,INDEX(HIST_D!$F$8:$F$2617,1)),"") | K6: =IFERROR((INDEX(HIST_D!$F$8:$F$2617,1)-AVERAGE(HIST_D!$F$8:INDEX(HIST_D!$F$8:$F$2617,Control!$F$14)))/STDEV(HIST_D!$F$8:INDEX(HIST_D!$F$8:$F$2617,Control!$F$14)),"")
A7: UST 5Y | B7: =INDEX(HIST_D!$H$8:$H$2617,1) | C7: =IFERROR((INDEX(HIST_D!$H$8:$H$2617,1)-INDEX(HIST_D!$H$8:$H$2617,Control!$F$6))*Control!$B$11,"") | D7: =IFERROR((INDEX(HIST_D!$H$8:$H$2617,1)-INDEX(HIST_D!$H$8:$H$2617,Control!$F$7))*Control!$B$11,"") | E7: =IFERROR((INDEX(HIST_D!$H$8:$H$2617,1)-INDEX(HIST_D!$H$8:$H$2617,Control!$F$8))*Control!$B$11,"") | F7: =IFERROR((INDEX(HIST_D!$H$8:$H$2617,1)-INDEX(HIST_D!$H$8:$H$2617,Control!$F$16))*Control!$B$11,"") | G7: =IFERROR((INDEX(HIST_D!$H$8:$H$2617,1)-INDEX(HIST_D!$H$8:$H$2617,Control!$F$11))*Control!$B$11,"") | H7: =IFERROR(PERCENTRANK(HIST_D!$H$8:INDEX(HIST_D!$H$8:$H$2617,Control!$F$11),INDEX(HIST_D!$H$8:$H$2617,1)),"") | I7: =IFERROR(PERCENTRANK(HIST_D!$H$8:INDEX(HIST_D!$H$8:$H$2617,Control!$F$14),INDEX(HIST_D!$H$8:$H$2617,1)),"") | J7: =IFERROR(PERCENTRANK(HIST_M!$C$8:$C$308,INDEX(HIST_D!$H$8:$H$2617,1)),"") | K7: =IFERROR((INDEX(HIST_D!$H$8:$H$2617,1)-AVERAGE(HIST_D!$H$8:INDEX(HIST_D!$H$8:$H$2617,Control!$F$14)))/STDEV(HIST_D!$H$8:INDEX(HIST_D!$H$8:$H$2617,Control!$F$14)),"")
A8: UST 10Y | B8: =INDEX(HIST_D!$J$8:$J$2617,1) | C8: =IFERROR((INDEX(HIST_D!$J$8:$J$2617,1)-INDEX(HIST_D!$J$8:$J$2617,Control!$F$6))*Control!$B$11,"") | D8: =IFERROR((INDEX(HIST_D!$J$8:$J$2617,1)-INDEX(HIST_D!$J$8:$J$2617,Control!$F$7))*Control!$B$11,"") | E8: =IFERROR((INDEX(HIST_D!$J$8:$J$2617,1)-INDEX(HIST_D!$J$8:$J$2617,Control!$F$8))*Control!$B$11,"") | F8: =IFERROR((INDEX(HIST_D!$J$8:$J$2617,1)-INDEX(HIST_D!$J$8:$J$2617,Control!$F$16))*Control!$B$11,"") | G8: =IFERROR((INDEX(HIST_D!$J$8:$J$2617,1)-INDEX(HIST_D!$J$8:$J$2617,Control!$F$11))*Control!$B$11,"") | H8: =IFERROR(PERCENTRANK(HIST_D!$J$8:INDEX(HIST_D!$J$8:$J$2617,Control!$F$11),INDEX(HIST_D!$J$8:$J$2617,1)),"") | I8: =IFERROR(PERCENTRANK(HIST_D!$J$8:INDEX(HIST_D!$J$8:$J$2617,Control!$F$14),INDEX(HIST_D!$J$8:$J$2617,1)),"") | J8: =IFERROR(PERCENTRANK(HIST_M!$D$8:$D$308,INDEX(HIST_D!$J$8:$J$2617,1)),"") | K8: =IFERROR((INDEX(HIST_D!$J$8:$J$2617,1)-AVERAGE(HIST_D!$J$8:INDEX(HIST_D!$J$8:$J$2617,Control!$F$14)))/STDEV(HIST_D!$J$8:INDEX(HIST_D!$J$8:$J$2617,Control!$F$14)),"")
A9: UST 30Y | B9: =INDEX(HIST_D!$L$8:$L$2617,1) | C9: =IFERROR((INDEX(HIST_D!$L$8:$L$2617,1)-INDEX(HIST_D!$L$8:$L$2617,Control!$F$6))*Control!$B$11,"") | D9: =IFERROR((INDEX(HIST_D!$L$8:$L$2617,1)-INDEX(HIST_D!$L$8:$L$2617,Control!$F$7))*Control!$B$11,"") | E9: =IFERROR((INDEX(HIST_D!$L$8:$L$2617,1)-INDEX(HIST_D!$L$8:$L$2617,Control!$F$8))*Control!$B$11,"") | F9: =IFERROR((INDEX(HIST_D!$L$8:$L$2617,1)-INDEX(HIST_D!$L$8:$L$2617,Control!$F$16))*Control!$B$11,"") | G9: =IFERROR((INDEX(HIST_D!$L$8:$L$2617,1)-INDEX(HIST_D!$L$8:$L$2617,Control!$F$11))*Control!$B$11,"") | H9: =IFERROR(PERCENTRANK(HIST_D!$L$8:INDEX(HIST_D!$L$8:$L$2617,Control!$F$11),INDEX(HIST_D!$L$8:$L$2617,1)),"") | I9: =IFERROR(PERCENTRANK(HIST_D!$L$8:INDEX(HIST_D!$L$8:$L$2617,Control!$F$14),INDEX(HIST_D!$L$8:$L$2617,1)),"") | J9: =IFERROR(PERCENTRANK(HIST_M!$E$8:$E$308,INDEX(HIST_D!$L$8:$L$2617,1)),"") | K9: =IFERROR((INDEX(HIST_D!$L$8:$L$2617,1)-AVERAGE(HIST_D!$L$8:INDEX(HIST_D!$L$8:$L$2617,Control!$F$14)))/STDEV(HIST_D!$L$8:INDEX(HIST_D!$L$8:$L$2617,Control!$F$14)),"")
A10: 2s10s | B10: =INDEX(HIST_D!$AV$8:$AV$2617,1) | C10: =IFERROR((INDEX(HIST_D!$AV$8:$AV$2617,1)-INDEX(HIST_D!$AV$8:$AV$2617,Control!$F$6))*1,"") | D10: =IFERROR((INDEX(HIST_D!$AV$8:$AV$2617,1)-INDEX(HIST_D!$AV$8:$AV$2617,Control!$F$7))*1,"") | E10: =IFERROR((INDEX(HIST_D!$AV$8:$AV$2617,1)-INDEX(HIST_D!$AV$8:$AV$2617,Control!$F$8))*1,"") | F10: =IFERROR((INDEX(HIST_D!$AV$8:$AV$2617,1)-INDEX(HIST_D!$AV$8:$AV$2617,Control!$F$16))*1,"") | G10: =IFERROR((INDEX(HIST_D!$AV$8:$AV$2617,1)-INDEX(HIST_D!$AV$8:$AV$2617,Control!$F$11))*1,"") | H10: =IFERROR(PERCENTRANK(HIST_D!$AV$8:INDEX(HIST_D!$AV$8:$AV$2617,Control!$F$11),INDEX(HIST_D!$AV$8:$AV$2617,1)),"") | I10: =IFERROR(PERCENTRANK(HIST_D!$AV$8:INDEX(HIST_D!$AV$8:$AV$2617,Control!$F$14),INDEX(HIST_D!$AV$8:$AV$2617,1)),"") | J10: =IFERROR(PERCENTRANK(HIST_M!$J$8:$J$308,INDEX(HIST_D!$AV$8:$AV$2617,1)),"") | K10: =IFERROR((INDEX(HIST_D!$AV$8:$AV$2617,1)-AVERAGE(HIST_D!$AV$8:INDEX(HIST_D!$AV$8:$AV$2617,Control!$F$14)))/STDEV(HIST_D!$AV$8:INDEX(HIST_D!$AV$8:$AV$2617,Control!$F$14)),"")
A11: 5s30s | B11: =INDEX(HIST_D!$AY$8:$AY$2617,1) | C11: =IFERROR((INDEX(HIST_D!$AY$8:$AY$2617,1)-INDEX(HIST_D!$AY$8:$AY$2617,Control!$F$6))*1,"") | D11: =IFERROR((INDEX(HIST_D!$AY$8:$AY$2617,1)-INDEX(HIST_D!$AY$8:$AY$2617,Control!$F$7))*1,"") | E11: =IFERROR((INDEX(HIST_D!$AY$8:$AY$2617,1)-INDEX(HIST_D!$AY$8:$AY$2617,Control!$F$8))*1,"") | F11: =IFERROR((INDEX(HIST_D!$AY$8:$AY$2617,1)-INDEX(HIST_D!$AY$8:$AY$2617,Control!$F$16))*1,"") | G11: =IFERROR((INDEX(HIST_D!$AY$8:$AY$2617,1)-INDEX(HIST_D!$AY$8:$AY$2617,Control!$F$11))*1,"") | H11: =IFERROR(PERCENTRANK(HIST_D!$AY$8:INDEX(HIST_D!$AY$8:$AY$2617,Control!$F$11),INDEX(HIST_D!$AY$8:$AY$2617,1)),"") | I11: =IFERROR(PERCENTRANK(HIST_D!$AY$8:INDEX(HIST_D!$AY$8:$AY$2617,Control!$F$14),INDEX(HIST_D!$AY$8:$AY$2617,1)),"") | J11: =IFERROR(PERCENTRANK(HIST_M!$L$8:$L$308,INDEX(HIST_D!$AY$8:$AY$2617,1)),"") | K11: =IFERROR((INDEX(HIST_D!$AY$8:$AY$2617,1)-AVERAGE(HIST_D!$AY$8:INDEX(HIST_D!$AY$8:$AY$2617,Control!$F$14)))/STDEV(HIST_D!$AY$8:INDEX(HIST_D!$AY$8:$AY$2617,Control!$F$14)),"")
A12: 10Y real yield | B12: =INDEX(HIST_D!$X$8:$X$2617,1) | C12: =IFERROR((INDEX(HIST_D!$X$8:$X$2617,1)-INDEX(HIST_D!$X$8:$X$2617,Control!$F$6))*Control!$B$11,"") | D12: =IFERROR((INDEX(HIST_D!$X$8:$X$2617,1)-INDEX(HIST_D!$X$8:$X$2617,Control!$F$7))*Control!$B$11,"") | E12: =IFERROR((INDEX(HIST_D!$X$8:$X$2617,1)-INDEX(HIST_D!$X$8:$X$2617,Control!$F$8))*Control!$B$11,"") | F12: =IFERROR((INDEX(HIST_D!$X$8:$X$2617,1)-INDEX(HIST_D!$X$8:$X$2617,Control!$F$16))*Control!$B$11,"") | G12: =IFERROR((INDEX(HIST_D!$X$8:$X$2617,1)-INDEX(HIST_D!$X$8:$X$2617,Control!$F$11))*Control!$B$11,"") | H12: =IFERROR(PERCENTRANK(HIST_D!$X$8:INDEX(HIST_D!$X$8:$X$2617,Control!$F$11),INDEX(HIST_D!$X$8:$X$2617,1)),"") | I12: =IFERROR(PERCENTRANK(HIST_D!$X$8:INDEX(HIST_D!$X$8:$X$2617,Control!$F$14),INDEX(HIST_D!$X$8:$X$2617,1)),"") | K12: =IFERROR((INDEX(HIST_D!$X$8:$X$2617,1)-AVERAGE(HIST_D!$X$8:INDEX(HIST_D!$X$8:$X$2617,Control!$F$14)))/STDEV(HIST_D!$X$8:INDEX(HIST_D!$X$8:$X$2617,Control!$F$14)),"")
A13: 10Y breakeven | B13: =INDEX(HIST_D!$Z$8:$Z$2617,1) | C13: =IFERROR((INDEX(HIST_D!$Z$8:$Z$2617,1)-INDEX(HIST_D!$Z$8:$Z$2617,Control!$F$6))*Control!$B$11,"") | D13: =IFERROR((INDEX(HIST_D!$Z$8:$Z$2617,1)-INDEX(HIST_D!$Z$8:$Z$2617,Control!$F$7))*Control!$B$11,"") | E13: =IFERROR((INDEX(HIST_D!$Z$8:$Z$2617,1)-INDEX(HIST_D!$Z$8:$Z$2617,Control!$F$8))*Control!$B$11,"") | F13: =IFERROR((INDEX(HIST_D!$Z$8:$Z$2617,1)-INDEX(HIST_D!$Z$8:$Z$2617,Control!$F$16))*Control!$B$11,"") | G13: =IFERROR((INDEX(HIST_D!$Z$8:$Z$2617,1)-INDEX(HIST_D!$Z$8:$Z$2617,Control!$F$11))*Control!$B$11,"") | H13: =IFERROR(PERCENTRANK(HIST_D!$Z$8:INDEX(HIST_D!$Z$8:$Z$2617,Control!$F$11),INDEX(HIST_D!$Z$8:$Z$2617,1)),"") | I13: =IFERROR(PERCENTRANK(HIST_D!$Z$8:INDEX(HIST_D!$Z$8:$Z$2617,Control!$F$14),INDEX(HIST_D!$Z$8:$Z$2617,1)),"") | K13: =IFERROR((INDEX(HIST_D!$Z$8:$Z$2617,1)-AVERAGE(HIST_D!$Z$8:INDEX(HIST_D!$Z$8:$Z$2617,Control!$F$14)))/STDEV(HIST_D!$Z$8:INDEX(HIST_D!$Z$8:$Z$2617,Control!$F$14)),"")
A14: MOVE | B14: =INDEX(HIST_D!$AB$8:$AB$2617,1) | C14: =IFERROR((INDEX(HIST_D!$AB$8:$AB$2617,1)-INDEX(HIST_D!$AB$8:$AB$2617,Control!$F$6))*1,"") | D14: =IFERROR((INDEX(HIST_D!$AB$8:$AB$2617,1)-INDEX(HIST_D!$AB$8:$AB$2617,Control!$F$7))*1,"") | E14: =IFERROR((INDEX(HIST_D!$AB$8:$AB$2617,1)-INDEX(HIST_D!$AB$8:$AB$2617,Control!$F$8))*1,"") | F14: =IFERROR((INDEX(HIST_D!$AB$8:$AB$2617,1)-INDEX(HIST_D!$AB$8:$AB$2617,Control!$F$16))*1,"") | G14: =IFERROR((INDEX(HIST_D!$AB$8:$AB$2617,1)-INDEX(HIST_D!$AB$8:$AB$2617,Control!$F$11))*1,"") | H14: =IFERROR(PERCENTRANK(HIST_D!$AB$8:INDEX(HIST_D!$AB$8:$AB$2617,Control!$F$11),INDEX(HIST_D!$AB$8:$AB$2617,1)),"") | I14: =IFERROR(PERCENTRANK(HIST_D!$AB$8:INDEX(HIST_D!$AB$8:$AB$2617,Control!$F$14),INDEX(HIST_D!$AB$8:$AB$2617,1)),"") | J14: =IFERROR(PERCENTRANK(HIST_M!$I$8:$I$308,INDEX(HIST_D!$AB$8:$AB$2617,1)),"") | K14: =IFERROR((INDEX(HIST_D!$AB$8:$AB$2617,1)-AVERAGE(HIST_D!$AB$8:INDEX(HIST_D!$AB$8:$AB$2617,Control!$F$14)))/STDEV(HIST_D!$AB$8:INDEX(HIST_D!$AB$8:$AB$2617,Control!$F$14)),"")
A16: POLICY
B17: Value | C17: Unit | D17: Note
A18: Spot EFFR | B18: =Policy!$F$9 | C18: % | D18: live
A19: Market terminal (strip trough) | B19: =Policy!$E$36 | C19: % | D19: lowest implied month-average on the FF strip
A20: Cuts priced to the trough | B20: =Policy!$G$36 | C20: # of 25bp
A21: Cuts priced 12m out | B21: =Policy!$G$28 | C21: # of 25bp | D21: FF12 contract vs spot EFFR
A22: OIS 1y1y | B22: =IFERROR(((1+INDEX(HIST_D!$N$8:$N$2617,1)/100)^2/(1+INDEX(HIST_D!$M$8:$M$2617,1)/100))*100-100,"") | C22: % | D22: policy 12–24m out
A23: OIS 5y5y | B23: =IFERROR(((1+INDEX(HIST_D!$S$8:$S$2617,1)/100)^10/(1+INDEX(HIST_D!$Q$8:$Q$2617,1)/100)^5)^(1/5)*100-100,"") | C23: % | D23: long-run anchor
A25: FUNDING & LIQUIDITY
B26: Value | C26: Unit | D26: Status | E26: Note
A27: SOFR − IORB | B27: =Liquidity!$B$44 | C27: bp | D27: =IF($B27>5,"TIGHT","OK") | E27: the scarcity tell
A28: ON RRP volume | B28: =INDEX(HIST_D!$AP$8:$AP$2617,1) | C28: $bn | D28: =IF($B28<50,"BUFFER GONE","OK") | E28: below ~$50bn every drain hits reserves
A29: MOVE percentile (3y) | B29: =IFERROR(PERCENTRANK(HIST_D!$AB$8:INDEX(HIST_D!$AB$8:$AB$2617,Control!$F$13),INDEX(HIST_D!$AB$8:$AB$2617,1)),"") | C29: %ile | D29: =IF($B29>0.8,"STRESSED","OK") | E29: the transmission channel into EM
A30: Swap spread 10Y | B30: =INDEX(HIST_D!$BE$8:$BE$2617,1) | C30: bp | D30: =IF(IFERROR((INDEX(HIST_D!$BE$8:$BE$2617,1)-AVERAGE(HIST_D!$BE$8:INDEX(HIST_D!$BE$8:$BE$2617,Control!$F$14)))/STDEV(HIST_D!$BE$8:INDEX(HIST_D!$BE$8:$BE$2617,Control!$F$14)),"")<-1.5,"BALANCE SHEET SCARCE","OK") | E30: dealer capacity
A32: CREDIT
B33: Level | C33: 1D | D33: 1W | E33: 1M | F33: YTD | G33: 1Y | H33: %ile 1y | I33: %ile 5y | J33: %ile 25y | K33: z (5y) | L33: Note
A34: US IG OAS | B34: =INDEX(HIST_D!$AF$8:$AF$2617,1) | C34: =IFERROR((INDEX(HIST_D!$AF$8:$AF$2617,1)-INDEX(HIST_D!$AF$8:$AF$2617,Control!$F$6))*1,"") | D34: =IFERROR((INDEX(HIST_D!$AF$8:$AF$2617,1)-INDEX(HIST_D!$AF$8:$AF$2617,Control!$F$7))*1,"") | E34: =IFERROR((INDEX(HIST_D!$AF$8:$AF$2617,1)-INDEX(HIST_D!$AF$8:$AF$2617,Control!$F$8))*1,"") | F34: =IFERROR((INDEX(HIST_D!$AF$8:$AF$2617,1)-INDEX(HIST_D!$AF$8:$AF$2617,Control!$F$16))*1,"") | G34: =IFERROR((INDEX(HIST_D!$AF$8:$AF$2617,1)-INDEX(HIST_D!$AF$8:$AF$2617,Control!$F$11))*1,"") | H34: =IFERROR(PERCENTRANK(HIST_D!$AF$8:INDEX(HIST_D!$AF$8:$AF$2617,Control!$F$11),INDEX(HIST_D!$AF$8:$AF$2617,1)),"") | I34: =IFERROR(PERCENTRANK(HIST_D!$AF$8:INDEX(HIST_D!$AF$8:$AF$2617,Control!$F$14),INDEX(HIST_D!$AF$8:$AF$2617,1)),"") | J34: =IFERROR(PERCENTRANK(HIST_M!$F$8:$F$308,INDEX(HIST_D!$AF$8:$AF$2617,1)),"") | K34: =IFERROR((INDEX(HIST_D!$AF$8:$AF$2617,1)-AVERAGE(HIST_D!$AF$8:INDEX(HIST_D!$AF$8:$AF$2617,Control!$F$14)))/STDEV(HIST_D!$AF$8:INDEX(HIST_D!$AF$8:$AF$2617,Control!$F$14)),"")
A35: US HY OAS | B35: =INDEX(HIST_D!$AG$8:$AG$2617,1) | C35: =IFERROR((INDEX(HIST_D!$AG$8:$AG$2617,1)-INDEX(HIST_D!$AG$8:$AG$2617,Control!$F$6))*1,"") | D35: =IFERROR((INDEX(HIST_D!$AG$8:$AG$2617,1)-INDEX(HIST_D!$AG$8:$AG$2617,Control!$F$7))*1,"") | E35: =IFERROR((INDEX(HIST_D!$AG$8:$AG$2617,1)-INDEX(HIST_D!$AG$8:$AG$2617,Control!$F$8))*1,"") | F35: =IFERROR((INDEX(HIST_D!$AG$8:$AG$2617,1)-INDEX(HIST_D!$AG$8:$AG$2617,Control!$F$16))*1,"") | G35: =IFERROR((INDEX(HIST_D!$AG$8:$AG$2617,1)-INDEX(HIST_D!$AG$8:$AG$2617,Control!$F$11))*1,"") | H35: =IFERROR(PERCENTRANK(HIST_D!$AG$8:INDEX(HIST_D!$AG$8:$AG$2617,Control!$F$11),INDEX(HIST_D!$AG$8:$AG$2617,1)),"") | I35: =IFERROR(PERCENTRANK(HIST_D!$AG$8:INDEX(HIST_D!$AG$8:$AG$2617,Control!$F$14),INDEX(HIST_D!$AG$8:$AG$2617,1)),"") | J35: =IFERROR(PERCENTRANK(HIST_M!$G$8:$G$308,INDEX(HIST_D!$AG$8:$AG$2617,1)),"") | K35: =IFERROR((INDEX(HIST_D!$AG$8:$AG$2617,1)-AVERAGE(HIST_D!$AG$8:INDEX(HIST_D!$AG$8:$AG$2617,Control!$F$14)))/STDEV(HIST_D!$AG$8:INDEX(HIST_D!$AG$8:$AG$2617,Control!$F$14)),"")
A36: HY − IG | B36: =INDEX(HIST_D!$BG$8:$BG$2617,1) | C36: =IFERROR((INDEX(HIST_D!$BG$8:$BG$2617,1)-INDEX(HIST_D!$BG$8:$BG$2617,Control!$F$6))*1,"") | D36: =IFERROR((INDEX(HIST_D!$BG$8:$BG$2617,1)-INDEX(HIST_D!$BG$8:$BG$2617,Control!$F$7))*1,"") | E36: =IFERROR((INDEX(HIST_D!$BG$8:$BG$2617,1)-INDEX(HIST_D!$BG$8:$BG$2617,Control!$F$8))*1,"") | F36: =IFERROR((INDEX(HIST_D!$BG$8:$BG$2617,1)-INDEX(HIST_D!$BG$8:$BG$2617,Control!$F$16))*1,"") | G36: =IFERROR((INDEX(HIST_D!$BG$8:$BG$2617,1)-INDEX(HIST_D!$BG$8:$BG$2617,Control!$F$11))*1,"") | H36: =IFERROR(PERCENTRANK(HIST_D!$BG$8:INDEX(HIST_D!$BG$8:$BG$2617,Control!$F$11),INDEX(HIST_D!$BG$8:$BG$2617,1)),"") | I36: =IFERROR(PERCENTRANK(HIST_D!$BG$8:INDEX(HIST_D!$BG$8:$BG$2617,Control!$F$14),INDEX(HIST_D!$BG$8:$BG$2617,1)),"") | J36: =IFERROR(PERCENTRANK(HIST_M!$N$8:$N$308,INDEX(HIST_D!$BG$8:$BG$2617,1)),"") | K36: =IFERROR((INDEX(HIST_D!$BG$8:$BG$2617,1)-AVERAGE(HIST_D!$BG$8:INDEX(HIST_D!$BG$8:$BG$2617,Control!$F$14)))/STDEV(HIST_D!$BG$8:INDEX(HIST_D!$BG$8:$BG$2617,Control!$F$14)),"")
A37: HY / IG | B37: =INDEX(HIST_D!$BH$8:$BH$2617,1) | C37: =IFERROR((INDEX(HIST_D!$BH$8:$BH$2617,1)-INDEX(HIST_D!$BH$8:$BH$2617,Control!$F$6))*1,"") | D37: =IFERROR((INDEX(HIST_D!$BH$8:$BH$2617,1)-INDEX(HIST_D!$BH$8:$BH$2617,Control!$F$7))*1,"") | E37: =IFERROR((INDEX(HIST_D!$BH$8:$BH$2617,1)-INDEX(HIST_D!$BH$8:$BH$2617,Control!$F$8))*1,"") | F37: =IFERROR((INDEX(HIST_D!$BH$8:$BH$2617,1)-INDEX(HIST_D!$BH$8:$BH$2617,Control!$F$16))*1,"") | G37: =IFERROR((INDEX(HIST_D!$BH$8:$BH$2617,1)-INDEX(HIST_D!$BH$8:$BH$2617,Control!$F$11))*1,"") | H37: =IFERROR(PERCENTRANK(HIST_D!$BH$8:INDEX(HIST_D!$BH$8:$BH$2617,Control!$F$11),INDEX(HIST_D!$BH$8:$BH$2617,1)),"") | I37: =IFERROR(PERCENTRANK(HIST_D!$BH$8:INDEX(HIST_D!$BH$8:$BH$2617,Control!$F$14),INDEX(HIST_D!$BH$8:$BH$2617,1)),"") | J37: =IFERROR(PERCENTRANK(HIST_M!$O$8:$O$308,INDEX(HIST_D!$BH$8:$BH$2617,1)),"") | K37: =IFERROR((INDEX(HIST_D!$BH$8:$BH$2617,1)-AVERAGE(HIST_D!$BH$8:INDEX(HIST_D!$BH$8:$BH$2617,Control!$F$14)))/STDEV(HIST_D!$BH$8:INDEX(HIST_D!$BH$8:$BH$2617,Control!$F$14)),"")
B39: 12m TR, ceteris paribus | C39: vs cash hurdle | D39: bp widening to break even | E39: bp to the 5y median
A40: US IG | B40: =Credit_TR!$B$19 | C40: =Credit_TR!$B$19-Control!$B$13/100 | D40: =Credit_TR!$B$21 | E40: =IFERROR(PERCENTILE(HIST_D!$AF$8:INDEX(HIST_D!$AF$8:$AF$2617,Control!$F$14),0.5)-INDEX(HIST_D!$AF$8:$AF$2617,1),"")
A41: US HY | B41: =Credit_TR!$C$19 | C41: =Credit_TR!$C$19-Control!$B$13/100 | D41: =Credit_TR!$C$21 | E41: =IFERROR(PERCENTILE(HIST_D!$AG$8:INDEX(HIST_D!$AG$8:$AG$2617,Control!$F$14),0.5)-INDEX(HIST_D!$AG$8:$AG$2617,1),"")
A42: EM USD Agg | B42: =Credit_TR!$D$19 | C42: =Credit_TR!$D$19-Control!$B$13/100 | D42: =Credit_TR!$D$21 | E42: =IFERROR(PERCENTILE(HIST_D!$AJ$8:INDEX(HIST_D!$AJ$8:$AJ$2617,Control!$F$14),0.5)-INDEX(HIST_D!$AJ$8:$AJ$2617,1),"")
A43: Breakeven column is on Credit_TR; the widening-to-median column says how far a normalisation would actually be.
A45: EM READ-THROUGH
B46: Value | C46: Unit | D46: Note
A47: EMBIGD stripped spread | B47: =EM_Link!$B$6 | C47: bp | D47: your tracker, not Bloomberg
A48: EM / HY ratio | B48: =INDEX(HIST_D!$BJ$8:$BJ$2617,1) | C48: x | D48: cross-market value
A49: EM / HY percentile (5y) | B49: =IFERROR(PERCENTRANK(HIST_D!$BJ$8:INDEX(HIST_D!$BJ$8:$BJ$2617,Control!$F$14),INDEX(HIST_D!$BJ$8:$BJ$2617,1)),"") | C49: %ile
A50: Beta: Δ EM OAS to Δ UST 10Y (1y) | B50: =IFERROR(SLOPE(HIST_D!$BP$8:INDEX(HIST_D!$BP$8:$BP$2617,Control!$F$11),HIST_D!$BL$8:INDEX(HIST_D!$BL$8:$BL$2617,Control!$F$11)),"") | C50: x | D50: negative = ballast intact
A51: EMBIGD 12m TR — your base case | B51: =EM_Link!$G$56 | C51: %
A52: … vs cash hurdle | B52: =EM_Link!$G$56-Control!$B$13/100 | C52: %
A54: READING THE BOARD
A55: ="Curve: 2s10s at "&TEXT(INDEX(HIST_D!$AV$8:$AV$2617,1),"0")&"bp, the "&TEXT(IFERROR(PERCENTRANK(HIST_D!$AV$8:INDEX(HIST_D!$AV$8:$AV$2617,Control!$F$14),INDEX(HIST_D!$AV$8:$AV$2617,1)),""),"0%")&" percentile of the last five years. "&IF(INDEX(HIST_D!$AV$8:$AV$2617,1)<0,"Still inverted.",IF(INDEX(HIST_D!$AV$8:$AV$2617,1)<50,"Flat.","Steep."))
A56: ="Policy: the strip prices "&TEXT(Policy!$G$36,"0.0")&" cuts to the trough and "&TEXT(Policy!$G$28,"0.0")&" inside twelve months."
A57: ="Credit: IG at "&TEXT(INDEX(HIST_D!$AF$8:$AF$2617,1),"0")&"bp ("&TEXT(IFERROR(PERCENTRANK(HIST_D!$AF$8:INDEX(HIST_D!$AF$8:$AF$2617,Control!$F$14),INDEX(HIST_D!$AF$8:$AF$2617,1)),""),"0%")&" of its 5y range), HY at "&TEXT(INDEX(HIST_D!$AG$8:$AG$2617,1),"0")&"bp ("&TEXT(IFERROR(PERCENTRANK(HIST_D!$AG$8:INDEX(HIST_D!$AG$8:$AG$2617,Control!$F$14),INDEX(HIST_D!$AG$8:$AG$2617,1)),""),"0%")&" of its 5y range). "&IF(IFERROR(PERCENTRANK(HIST_D!$AG$8:INDEX(HIST_D!$AG$8:$AG$2617,Control!$F$14),INDEX(HIST_D!$AG$8:$AG$2617,1)),"")<0.15,"There is very little room left in the spread leg.","")
A58: ="EM: paid "&TEXT(INDEX(HIST_D!$BJ$8:$BJ$2617,1),"0.00")&"x US HY. The one-year beta of EM spreads to UST yields is "&TEXT(IFERROR(SLOPE(HIST_D!$BP$8:INDEX(HIST_D!$BP$8:$BP$2617,Control!$F$11),HIST_D!$BL$8:INDEX(HIST_D!$BL$8:$BL$2617,Control!$F$11)),0),"0.00")&"; negative means the Treasury leg is still doing the ballast job the EM USD case depends on."

Sheet Curve
A1: US TREASURY CURVE — every node
A2: Levels, changes, distribution and carry/roll economics for each node. Changes in bp. Percentiles: 0% = lowest yield in the window, 100% = highest.
A4: US TREASURY PAR YIELDS
A5: Instrument | B5: Source | C5: Unit | D5: Level | E5: 1D | F5: 1W | G5: 1M | H5: 3M | I5: 6M | J5: YTD | K5: 1Y | L5: 1y min | M5: 1y max | N5: %ile 1y | O5: %ile 3y | P5: %ile 5y | Q5: %ile 10y | R5: %ile 25y | S5: z (5y) | T5: Yrs | U5: y at n−1yr | V5: Roll-down | W5: Mod dur | X5: DV01 $/1mm | Y5: 12m TR @ unch curve | Z5: B/E yield rise
A6: UST 1M | B6: =Tickers!$C$6 | C6: % | D6: =INDEX(HIST_D!$B$8:$B$2617,1) | E6: =IFERROR((INDEX(HIST_D!$B$8:$B$2617,1)-INDEX(HIST_D!$B$8:$B$2617,Control!$F$6))*Control!$B$11,"") | F6: =IFERROR((INDEX(HIST_D!$B$8:$B$2617,1)-INDEX(HIST_D!$B$8:$B$2617,Control!$F$7))*Control!$B$11,"") | G6: =IFERROR((INDEX(HIST_D!$B$8:$B$2617,1)-INDEX(HIST_D!$B$8:$B$2617,Control!$F$8))*Control!$B$11,"") | H6: =IFERROR((INDEX(HIST_D!$B$8:$B$2617,1)-INDEX(HIST_D!$B$8:$B$2617,Control!$F$9))*Control!$B$11,"") | I6: =IFERROR((INDEX(HIST_D!$B$8:$B$2617,1)-INDEX(HIST_D!$B$8:$B$2617,Control!$F$10))*Control!$B$11,"") | J6: =IFERROR((INDEX(HIST_D!$B$8:$B$2617,1)-INDEX(HIST_D!$B$8:$B$2617,Control!$F$16))*Control!$B$11,"") | K6: =IFERROR((INDEX(HIST_D!$B$8:$B$2617,1)-INDEX(HIST_D!$B$8:$B$2617,Control!$F$11))*Control!$B$11,"") | L6: =IFERROR(MIN(HIST_D!$B$8:INDEX(HIST_D!$B$8:$B$2617,Control!$F$11)),"") | M6: =IFERROR(MAX(HIST_D!$B$8:INDEX(HIST_D!$B$8:$B$2617,Control!$F$11)),"") | N6: =IFERROR(PERCENTRANK(HIST_D!$B$8:INDEX(HIST_D!$B$8:$B$2617,Control!$F$11),INDEX(HIST_D!$B$8:$B$2617,1)),"") | O6: =IFERROR(PERCENTRANK(HIST_D!$B$8:INDEX(HIST_D!$B$8:$B$2617,Control!$F$13),INDEX(HIST_D!$B$8:$B$2617,1)),"") | P6: =IFERROR(PERCENTRANK(HIST_D!$B$8:INDEX(HIST_D!$B$8:$B$2617,Control!$F$14),INDEX(HIST_D!$B$8:$B$2617,1)),"") | Q6: =IFERROR(PERCENTRANK(HIST_D!$B$8:INDEX(HIST_D!$B$8:$B$2617,Control!$F$15),INDEX(HIST_D!$B$8:$B$2617,1)),"") | S6: =IFERROR((INDEX(HIST_D!$B$8:$B$2617,1)-AVERAGE(HIST_D!$B$8:INDEX(HIST_D!$B$8:$B$2617,Control!$F$14)))/STDEV(HIST_D!$B$8:INDEX(HIST_D!$B$8:$B$2617,Control!$F$14)),"") | T6: 0.083333333 | U6: =IF(MAX($T6-Control!$B$12,0.0833)<=INDEX($T$6:$T$18,1),INDEX($D$6:$D$18,1),IF(MAX($T6-Control!$B$12,0.0833)>=INDEX($T$6:$T$18,COUNT($T$6:$T$18)),INDEX($D$6:$D$18,COUNT($T$6:$T$18)),INDEX($D$6:$D$18,MATCH(MAX($T6-Control!$B$12,0.0833),$T$6:$T$18,1))+(MAX($T6-Control!$B$12,0.0833)-INDEX($T$6:$T$18,MATCH(MAX($T6-Control!$B$12,0.0833),$T$6:$T$18,1)))/(INDEX($T$6:$T$18,MATCH(MAX($T6-Control!$B$12,0.0833),$T$6:$T$18,1)+1)-INDEX($T$6:$T$18,MATCH(MAX($T6-Control!$B$12,0.0833),$T$6:$T$18,1)))*(INDEX($D$6:$D$18,MATCH(MAX($T6-Control!$B$12,0.0833),$T$6:$T$18,1)+1)-INDEX($D$6:$D$18,MATCH(MAX($T6-Control!$B$12,0.0833),$T$6:$T$18,1))))) | V6: =IF($T6<=Control!$B$12,"",($D6-$U6)*Control!$B$11) | W6: =IFERROR((1-(1+$D6/100/Control!$B$14)^(-Control!$B$14*($T6)))/($D6/100/Control!$B$14)/Control!$B$14,"") | X6: =IFERROR($W6*100*1000000/10000,"") | Y6: =IF($T6<=Control!$B$12,$D6*Control!$B$12/100,IFERROR((IFERROR(($D6/Control!$B$14)*(1-(1+$U6/100/Control!$B$14)^(-Control!$B$14*($T6-Control!$B$12)))/($U6/100/Control!$B$14)+100*(1+$U6/100/Control!$B$14)^(-Control!$B$14*($T6-Control!$B$12)),"")+$D6*Control!$B$12-100)/100,"")) | Z6: =IF($T6<=Control!$B$12,"n/a",IFERROR($Y6*100/IFERROR((1-(1+$U6/100/Control!$B$14)^(-Control!$B$14*($T6-Control!$B$12)))/($U6/100/Control!$B$14)/Control!$B$14,"")*Control!$B$11,""))
A7: UST 3M | B7: =Tickers!$C$7 | C7: % | D7: =INDEX(HIST_D!$C$8:$C$2617,1) | E7: =IFERROR((INDEX(HIST_D!$C$8:$C$2617,1)-INDEX(HIST_D!$C$8:$C$2617,Control!$F$6))*Control!$B$11,"") | F7: =IFERROR((INDEX(HIST_D!$C$8:$C$2617,1)-INDEX(HIST_D!$C$8:$C$2617,Control!$F$7))*Control!$B$11,"") | G7: =IFERROR((INDEX(HIST_D!$C$8:$C$2617,1)-INDEX(HIST_D!$C$8:$C$2617,Control!$F$8))*Control!$B$11,"") | H7: =IFERROR((INDEX(HIST_D!$C$8:$C$2617,1)-INDEX(HIST_D!$C$8:$C$2617,Control!$F$9))*Control!$B$11,"") | I7: =IFERROR((INDEX(HIST_D!$C$8:$C$2617,1)-INDEX(HIST_D!$C$8:$C$2617,Control!$F$10))*Control!$B$11,"") | J7: =IFERROR((INDEX(HIST_D!$C$8:$C$2617,1)-INDEX(HIST_D!$C$8:$C$2617,Control!$F$16))*Control!$B$11,"") | K7: =IFERROR((INDEX(HIST_D!$C$8:$C$2617,1)-INDEX(HIST_D!$C$8:$C$2617,Control!$F$11))*Control!$B$11,"") | L7: =IFERROR(MIN(HIST_D!$C$8:INDEX(HIST_D!$C$8:$C$2617,Control!$F$11)),"") | M7: =IFERROR(MAX(HIST_D!$C$8:INDEX(HIST_D!$C$8:$C$2617,Control!$F$11)),"") | N7: =IFERROR(PERCENTRANK(HIST_D!$C$8:INDEX(HIST_D!$C$8:$C$2617,Control!$F$11),INDEX(HIST_D!$C$8:$C$2617,1)),"") | O7: =IFERROR(PERCENTRANK(HIST_D!$C$8:INDEX(HIST_D!$C$8:$C$2617,Control!$F$13),INDEX(HIST_D!$C$8:$C$2617,1)),"") | P7: =IFERROR(PERCENTRANK(HIST_D!$C$8:INDEX(HIST_D!$C$8:$C$2617,Control!$F$14),INDEX(HIST_D!$C$8:$C$2617,1)),"") | Q7: =IFERROR(PERCENTRANK(HIST_D!$C$8:INDEX(HIST_D!$C$8:$C$2617,Control!$F$15),INDEX(HIST_D!$C$8:$C$2617,1)),"") | S7: =IFERROR((INDEX(HIST_D!$C$8:$C$2617,1)-AVERAGE(HIST_D!$C$8:INDEX(HIST_D!$C$8:$C$2617,Control!$F$14)))/STDEV(HIST_D!$C$8:INDEX(HIST_D!$C$8:$C$2617,Control!$F$14)),"") | T7: 0.25 | U7: =IF(MAX($T7-Control!$B$12,0.0833)<=INDEX($T$6:$T$18,1),INDEX($D$6:$D$18,1),IF(MAX($T7-Control!$B$12,0.0833)>=INDEX($T$6:$T$18,COUNT($T$6:$T$18)),INDEX($D$6:$D$18,COUNT($T$6:$T$18)),INDEX($D$6:$D$18,MATCH(MAX($T7-Control!$B$12,0.0833),$T$6:$T$18,1))+(MAX($T7-Control!$B$12,0.0833)-INDEX($T$6:$T$18,MATCH(MAX($T7-Control!$B$12,0.0833),$T$6:$T$18,1)))/(INDEX($T$6:$T$18,MATCH(MAX($T7-Control!$B$12,0.0833),$T$6:$T$18,1)+1)-INDEX($T$6:$T$18,MATCH(MAX($T7-Control!$B$12,0.0833),$T$6:$T$18,1)))*(INDEX($D$6:$D$18,MATCH(MAX($T7-Control!$B$12,0.0833),$T$6:$T$18,1)+1)-INDEX($D$6:$D$18,MATCH(MAX($T7-Control!$B$12,0.0833),$T$6:$T$18,1))))) | V7: =IF($T7<=Control!$B$12,"",($D7-$U7)*Control!$B$11) | W7: =IFERROR((1-(1+$D7/100/Control!$B$14)^(-Control!$B$14*($T7)))/($D7/100/Control!$B$14)/Control!$B$14,"") | X7: =IFERROR($W7*100*1000000/10000,"") | Y7: =IF($T7<=Control!$B$12,$D7*Control!$B$12/100,IFERROR((IFERROR(($D7/Control!$B$14)*(1-(1+$U7/100/Control!$B$14)^(-Control!$B$14*($T7-Control!$B$12)))/($U7/100/Control!$B$14)+100*(1+$U7/100/Control!$B$14)^(-Control!$B$14*($T7-Control!$B$12)),"")+$D7*Control!$B$12-100)/100,"")) | Z7: =IF($T7<=Control!$B$12,"n/a",IFERROR($Y7*100/IFERROR((1-(1+$U7/100/Control!$B$14)^(-Control!$B$14*($T7-Control!$B$12)))/($U7/100/Control!$B$14)/Control!$B$14,"")*Control!$B$11,""))
A8: UST 6M | B8: =Tickers!$C$8 | C8: % | D8: =INDEX(HIST_D!$D$8:$D$2617,1) | E8: =IFERROR((INDEX(HIST_D!$D$8:$D$2617,1)-INDEX(HIST_D!$D$8:$D$2617,Control!$F$6))*Control!$B$11,"") | F8: =IFERROR((INDEX(HIST_D!$D$8:$D$2617,1)-INDEX(HIST_D!$D$8:$D$2617,Control!$F$7))*Control!$B$11,"") | G8: =IFERROR((INDEX(HIST_D!$D$8:$D$2617,1)-INDEX(HIST_D!$D$8:$D$2617,Control!$F$8))*Control!$B$11,"") | H8: =IFERROR((INDEX(HIST_D!$D$8:$D$2617,1)-INDEX(HIST_D!$D$8:$D$2617,Control!$F$9))*Control!$B$11,"") | I8: =IFERROR((INDEX(HIST_D!$D$8:$D$2617,1)-INDEX(HIST_D!$D$8:$D$2617,Control!$F$10))*Control!$B$11,"") | J8: =IFERROR((INDEX(HIST_D!$D$8:$D$2617,1)-INDEX(HIST_D!$D$8:$D$2617,Control!$F$16))*Control!$B$11,"") | K8: =IFERROR((INDEX(HIST_D!$D$8:$D$2617,1)-INDEX(HIST_D!$D$8:$D$2617,Control!$F$11))*Control!$B$11,"") | L8: =IFERROR(MIN(HIST_D!$D$8:INDEX(HIST_D!$D$8:$D$2617,Control!$F$11)),"") | M8: =IFERROR(MAX(HIST_D!$D$8:INDEX(HIST_D!$D$8:$D$2617,Control!$F$11)),"") | N8: =IFERROR(PERCENTRANK(HIST_D!$D$8:INDEX(HIST_D!$D$8:$D$2617,Control!$F$11),INDEX(HIST_D!$D$8:$D$2617,1)),"") | O8: =IFERROR(PERCENTRANK(HIST_D!$D$8:INDEX(HIST_D!$D$8:$D$2617,Control!$F$13),INDEX(HIST_D!$D$8:$D$2617,1)),"") | P8: =IFERROR(PERCENTRANK(HIST_D!$D$8:INDEX(HIST_D!$D$8:$D$2617,Control!$F$14),INDEX(HIST_D!$D$8:$D$2617,1)),"") | Q8: =IFERROR(PERCENTRANK(HIST_D!$D$8:INDEX(HIST_D!$D$8:$D$2617,Control!$F$15),INDEX(HIST_D!$D$8:$D$2617,1)),"") | S8: =IFERROR((INDEX(HIST_D!$D$8:$D$2617,1)-AVERAGE(HIST_D!$D$8:INDEX(HIST_D!$D$8:$D$2617,Control!$F$14)))/STDEV(HIST_D!$D$8:INDEX(HIST_D!$D$8:$D$2617,Control!$F$14)),"") | T8: 0.5 | U8: =IF(MAX($T8-Control!$B$12,0.0833)<=INDEX($T$6:$T$18,1),INDEX($D$6:$D$18,1),IF(MAX($T8-Control!$B$12,0.0833)>=INDEX($T$6:$T$18,COUNT($T$6:$T$18)),INDEX($D$6:$D$18,COUNT($T$6:$T$18)),INDEX($D$6:$D$18,MATCH(MAX($T8-Control!$B$12,0.0833),$T$6:$T$18,1))+(MAX($T8-Control!$B$12,0.0833)-INDEX($T$6:$T$18,MATCH(MAX($T8-Control!$B$12,0.0833),$T$6:$T$18,1)))/(INDEX($T$6:$T$18,MATCH(MAX($T8-Control!$B$12,0.0833),$T$6:$T$18,1)+1)-INDEX($T$6:$T$18,MATCH(MAX($T8-Control!$B$12,0.0833),$T$6:$T$18,1)))*(INDEX($D$6:$D$18,MATCH(MAX($T8-Control!$B$12,0.0833),$T$6:$T$18,1)+1)-INDEX($D$6:$D$18,MATCH(MAX($T8-Control!$B$12,0.0833),$T$6:$T$18,1))))) | V8: =IF($T8<=Control!$B$12,"",($D8-$U8)*Control!$B$11) | W8: =IFERROR((1-(1+$D8/100/Control!$B$14)^(-Control!$B$14*($T8)))/($D8/100/Control!$B$14)/Control!$B$14,"") | X8: =IFERROR($W8*100*1000000/10000,"") | Y8: =IF($T8<=Control!$B$12,$D8*Control!$B$12/100,IFERROR((IFERROR(($D8/Control!$B$14)*(1-(1+$U8/100/Control!$B$14)^(-Control!$B$14*($T8-Control!$B$12)))/($U8/100/Control!$B$14)+100*(1+$U8/100/Control!$B$14)^(-Control!$B$14*($T8-Control!$B$12)),"")+$D8*Control!$B$12-100)/100,"")) | Z8: =IF($T8<=Control!$B$12,"n/a",IFERROR($Y8*100/IFERROR((1-(1+$U8/100/Control!$B$14)^(-Control!$B$14*($T8-Control!$B$12)))/($U8/100/Control!$B$14)/Control!$B$14,"")*Control!$B$11,""))
A9: UST 1Y | B9: =Tickers!$C$9 | C9: % | D9: =INDEX(HIST_D!$E$8:$E$2617,1) | E9: =IFERROR((INDEX(HIST_D!$E$8:$E$2617,1)-INDEX(HIST_D!$E$8:$E$2617,Control!$F$6))*Control!$B$11,"") | F9: =IFERROR((INDEX(HIST_D!$E$8:$E$2617,1)-INDEX(HIST_D!$E$8:$E$2617,Control!$F$7))*Control!$B$11,"") | G9: =IFERROR((INDEX(HIST_D!$E$8:$E$2617,1)-INDEX(HIST_D!$E$8:$E$2617,Control!$F$8))*Control!$B$11,"") | H9: =IFERROR((INDEX(HIST_D!$E$8:$E$2617,1)-INDEX(HIST_D!$E$8:$E$2617,Control!$F$9))*Control!$B$11,"") | I9: =IFERROR((INDEX(HIST_D!$E$8:$E$2617,1)-INDEX(HIST_D!$E$8:$E$2617,Control!$F$10))*Control!$B$11,"") | J9: =IFERROR((INDEX(HIST_D!$E$8:$E$2617,1)-INDEX(HIST_D!$E$8:$E$2617,Control!$F$16))*Control!$B$11,"") | K9: =IFERROR((INDEX(HIST_D!$E$8:$E$2617,1)-INDEX(HIST_D!$E$8:$E$2617,Control!$F$11))*Control!$B$11,"") | L9: =IFERROR(MIN(HIST_D!$E$8:INDEX(HIST_D!$E$8:$E$2617,Control!$F$11)),"") | M9: =IFERROR(MAX(HIST_D!$E$8:INDEX(HIST_D!$E$8:$E$2617,Control!$F$11)),"") | N9: =IFERROR(PERCENTRANK(HIST_D!$E$8:INDEX(HIST_D!$E$8:$E$2617,Control!$F$11),INDEX(HIST_D!$E$8:$E$2617,1)),"") | O9: =IFERROR(PERCENTRANK(HIST_D!$E$8:INDEX(HIST_D!$E$8:$E$2617,Control!$F$13),INDEX(HIST_D!$E$8:$E$2617,1)),"") | P9: =IFERROR(PERCENTRANK(HIST_D!$E$8:INDEX(HIST_D!$E$8:$E$2617,Control!$F$14),INDEX(HIST_D!$E$8:$E$2617,1)),"") | Q9: =IFERROR(PERCENTRANK(HIST_D!$E$8:INDEX(HIST_D!$E$8:$E$2617,Control!$F$15),INDEX(HIST_D!$E$8:$E$2617,1)),"") | S9: =IFERROR((INDEX(HIST_D!$E$8:$E$2617,1)-AVERAGE(HIST_D!$E$8:INDEX(HIST_D!$E$8:$E$2617,Control!$F$14)))/STDEV(HIST_D!$E$8:INDEX(HIST_D!$E$8:$E$2617,Control!$F$14)),"") | T9: 1 | U9: =IF(MAX($T9-Control!$B$12,0.0833)<=INDEX($T$6:$T$18,1),INDEX($D$6:$D$18,1),IF(MAX($T9-Control!$B$12,0.0833)>=INDEX($T$6:$T$18,COUNT($T$6:$T$18)),INDEX($D$6:$D$18,COUNT($T$6:$T$18)),INDEX($D$6:$D$18,MATCH(MAX($T9-Control!$B$12,0.0833),$T$6:$T$18,1))+(MAX($T9-Control!$B$12,0.0833)-INDEX($T$6:$T$18,MATCH(MAX($T9-Control!$B$12,0.0833),$T$6:$T$18,1)))/(INDEX($T$6:$T$18,MATCH(MAX($T9-Control!$B$12,0.0833),$T$6:$T$18,1)+1)-INDEX($T$6:$T$18,MATCH(MAX($T9-Control!$B$12,0.0833),$T$6:$T$18,1)))*(INDEX($D$6:$D$18,MATCH(MAX($T9-Control!$B$12,0.0833),$T$6:$T$18,1)+1)-INDEX($D$6:$D$18,MATCH(MAX($T9-Control!$B$12,0.0833),$T$6:$T$18,1))))) | V9: =IF($T9<=Control!$B$12,"",($D9-$U9)*Control!$B$11) | W9: =IFERROR((1-(1+$D9/100/Control!$B$14)^(-Control!$B$14*($T9)))/($D9/100/Control!$B$14)/Control!$B$14,"") | X9: =IFERROR($W9*100*1000000/10000,"") | Y9: =IF($T9<=Control!$B$12,$D9*Control!$B$12/100,IFERROR((IFERROR(($D9/Control!$B$14)*(1-(1+$U9/100/Control!$B$14)^(-Control!$B$14*($T9-Control!$B$12)))/($U9/100/Control!$B$14)+100*(1+$U9/100/Control!$B$14)^(-Control!$B$14*($T9-Control!$B$12)),"")+$D9*Control!$B$12-100)/100,"")) | Z9: =IF($T9<=Control!$B$12,"n/a",IFERROR($Y9*100/IFERROR((1-(1+$U9/100/Control!$B$14)^(-Control!$B$14*($T9-Control!$B$12)))/($U9/100/Control!$B$14)/Control!$B$14,"")*Control!$B$11,""))
A10: UST 2Y | B10: =Tickers!$C$10 | C10: % | D10: =INDEX(HIST_D!$F$8:$F$2617,1) | E10: =IFERROR((INDEX(HIST_D!$F$8:$F$2617,1)-INDEX(HIST_D!$F$8:$F$2617,Control!$F$6))*Control!$B$11,"") | F10: =IFERROR((INDEX(HIST_D!$F$8:$F$2617,1)-INDEX(HIST_D!$F$8:$F$2617,Control!$F$7))*Control!$B$11,"") | G10: =IFERROR((INDEX(HIST_D!$F$8:$F$2617,1)-INDEX(HIST_D!$F$8:$F$2617,Control!$F$8))*Control!$B$11,"") | H10: =IFERROR((INDEX(HIST_D!$F$8:$F$2617,1)-INDEX(HIST_D!$F$8:$F$2617,Control!$F$9))*Control!$B$11,"") | I10: =IFERROR((INDEX(HIST_D!$F$8:$F$2617,1)-INDEX(HIST_D!$F$8:$F$2617,Control!$F$10))*Control!$B$11,"") | J10: =IFERROR((INDEX(HIST_D!$F$8:$F$2617,1)-INDEX(HIST_D!$F$8:$F$2617,Control!$F$16))*Control!$B$11,"") | K10: =IFERROR((INDEX(HIST_D!$F$8:$F$2617,1)-INDEX(HIST_D!$F$8:$F$2617,Control!$F$11))*Control!$B$11,"") | L10: =IFERROR(MIN(HIST_D!$F$8:INDEX(HIST_D!$F$8:$F$2617,Control!$F$11)),"") | M10: =IFERROR(MAX(HIST_D!$F$8:INDEX(HIST_D!$F$8:$F$2617,Control!$F$11)),"") | N10: =IFERROR(PERCENTRANK(HIST_D!$F$8:INDEX(HIST_D!$F$8:$F$2617,Control!$F$11),INDEX(HIST_D!$F$8:$F$2617,1)),"") | O10: =IFERROR(PERCENTRANK(HIST_D!$F$8:INDEX(HIST_D!$F$8:$F$2617,Control!$F$13),INDEX(HIST_D!$F$8:$F$2617,1)),"") | P10: =IFERROR(PERCENTRANK(HIST_D!$F$8:INDEX(HIST_D!$F$8:$F$2617,Control!$F$14),INDEX(HIST_D!$F$8:$F$2617,1)),"") | Q10: =IFERROR(PERCENTRANK(HIST_D!$F$8:INDEX(HIST_D!$F$8:$F$2617,Control!$F$15),INDEX(HIST_D!$F$8:$F$2617,1)),"") | R10: =IFERROR(PERCENTRANK(HIST_M!$B$8:$B$308,INDEX(HIST_D!$F$8:$F$2617,1)),"") | S10: =IFERROR((INDEX(HIST_D!$F$8:$F$2617,1)-AVERAGE(HIST_D!$F$8:INDEX(HIST_D!$F$8:$F$2617,Control!$F$14)))/STDEV(HIST_D!$F$8:INDEX(HIST_D!$F$8:$F$2617,Control!$F$14)),"") | T10: 2 | U10: =IF(MAX($T10-Control!$B$12,0.0833)<=INDEX($T$6:$T$18,1),INDEX($D$6:$D$18,1),IF(MAX($T10-Control!$B$12,0.0833)>=INDEX($T$6:$T$18,COUNT($T$6:$T$18)),INDEX($D$6:$D$18,COUNT($T$6:$T$18)),INDEX($D$6:$D$18,MATCH(MAX($T10-Control!$B$12,0.0833),$T$6:$T$18,1))+(MAX($T10-Control!$B$12,0.0833)-INDEX($T$6:$T$18,MATCH(MAX($T10-Control!$B$12,0.0833),$T$6:$T$18,1)))/(INDEX($T$6:$T$18,MATCH(MAX($T10-Control!$B$12,0.0833),$T$6:$T$18,1)+1)-INDEX($T$6:$T$18,MATCH(MAX($T10-Control!$B$12,0.0833),$T$6:$T$18,1)))*(INDEX($D$6:$D$18,MATCH(MAX($T10-Control!$B$12,0.0833),$T$6:$T$18,1)+1)-INDEX($D$6:$D$18,MATCH(MAX($T10-Control!$B$12,0.0833),$T$6:$T$18,1))))) | V10: =IF($T10<=Control!$B$12,"",($D10-$U10)*Control!$B$11) | W10: =IFERROR((1-(1+$D10/100/Control!$B$14)^(-Control!$B$14*($T10)))/($D10/100/Control!$B$14)/Control!$B$14,"") | X10: =IFERROR($W10*100*1000000/10000,"") | Y10: =IF($T10<=Control!$B$12,$D10*Control!$B$12/100,IFERROR((IFERROR(($D10/Control!$B$14)*(1-(1+$U10/100/Control!$B$14)^(-Control!$B$14*($T10-Control!$B$12)))/($U10/100/Control!$B$14)+100*(1+$U10/100/Control!$B$14)^(-Control!$B$14*($T10-Control!$B$12)),"")+$D10*Control!$B$12-100)/100,"")) | Z10: =IF($T10<=Control!$B$12,"n/a",IFERROR($Y10*100/IFERROR((1-(1+$U10/100/Control!$B$14)^(-Control!$B$14*($T10-Control!$B$12)))/($U10/100/Control!$B$14)/Control!$B$14,"")*Control!$B$11,""))
A11: UST 3Y | B11: =Tickers!$C$11 | C11: % | D11: =INDEX(HIST_D!$G$8:$G$2617,1) | E11: =IFERROR((INDEX(HIST_D!$G$8:$G$2617,1)-INDEX(HIST_D!$G$8:$G$2617,Control!$F$6))*Control!$B$11,"") | F11: =IFERROR((INDEX(HIST_D!$G$8:$G$2617,1)-INDEX(HIST_D!$G$8:$G$2617,Control!$F$7))*Control!$B$11,"") | G11: =IFERROR((INDEX(HIST_D!$G$8:$G$2617,1)-INDEX(HIST_D!$G$8:$G$2617,Control!$F$8))*Control!$B$11,"") | H11: =IFERROR((INDEX(HIST_D!$G$8:$G$2617,1)-INDEX(HIST_D!$G$8:$G$2617,Control!$F$9))*Control!$B$11,"") | I11: =IFERROR((INDEX(HIST_D!$G$8:$G$2617,1)-INDEX(HIST_D!$G$8:$G$2617,Control!$F$10))*Control!$B$11,"") | J11: =IFERROR((INDEX(HIST_D!$G$8:$G$2617,1)-INDEX(HIST_D!$G$8:$G$2617,Control!$F$16))*Control!$B$11,"") | K11: =IFERROR((INDEX(HIST_D!$G$8:$G$2617,1)-INDEX(HIST_D!$G$8:$G$2617,Control!$F$11))*Control!$B$11,"") | L11: =IFERROR(MIN(HIST_D!$G$8:INDEX(HIST_D!$G$8:$G$2617,Control!$F$11)),"") | M11: =IFERROR(MAX(HIST_D!$G$8:INDEX(HIST_D!$G$8:$G$2617,Control!$F$11)),"") | N11: =IFERROR(PERCENTRANK(HIST_D!$G$8:INDEX(HIST_D!$G$8:$G$2617,Control!$F$11),INDEX(HIST_D!$G$8:$G$2617,1)),"") | O11: =IFERROR(PERCENTRANK(HIST_D!$G$8:INDEX(HIST_D!$G$8:$G$2617,Control!$F$13),INDEX(HIST_D!$G$8:$G$2617,1)),"") | P11: =IFERROR(PERCENTRANK(HIST_D!$G$8:INDEX(HIST_D!$G$8:$G$2617,Control!$F$14),INDEX(HIST_D!$G$8:$G$2617,1)),"") | Q11: =IFERROR(PERCENTRANK(HIST_D!$G$8:INDEX(HIST_D!$G$8:$G$2617,Control!$F$15),INDEX(HIST_D!$G$8:$G$2617,1)),"") | S11: =IFERROR((INDEX(HIST_D!$G$8:$G$2617,1)-AVERAGE(HIST_D!$G$8:INDEX(HIST_D!$G$8:$G$2617,Control!$F$14)))/STDEV(HIST_D!$G$8:INDEX(HIST_D!$G$8:$G$2617,Control!$F$14)),"") | T11: 3 | U11: =IF(MAX($T11-Control!$B$12,0.0833)<=INDEX($T$6:$T$18,1),INDEX($D$6:$D$18,1),IF(MAX($T11-Control!$B$12,0.0833)>=INDEX($T$6:$T$18,COUNT($T$6:$T$18)),INDEX($D$6:$D$18,COUNT($T$6:$T$18)),INDEX($D$6:$D$18,MATCH(MAX($T11-Control!$B$12,0.0833),$T$6:$T$18,1))+(MAX($T11-Control!$B$12,0.0833)-INDEX($T$6:$T$18,MATCH(MAX($T11-Control!$B$12,0.0833),$T$6:$T$18,1)))/(INDEX($T$6:$T$18,MATCH(MAX($T11-Control!$B$12,0.0833),$T$6:$T$18,1)+1)-INDEX($T$6:$T$18,MATCH(MAX($T11-Control!$B$12,0.0833),$T$6:$T$18,1)))*(INDEX($D$6:$D$18,MATCH(MAX($T11-Control!$B$12,0.0833),$T$6:$T$18,1)+1)-INDEX($D$6:$D$18,MATCH(MAX($T11-Control!$B$12,0.0833),$T$6:$T$18,1))))) | V11: =IF($T11<=Control!$B$12,"",($D11-$U11)*Control!$B$11) | W11: =IFERROR((1-(1+$D11/100/Control!$B$14)^(-Control!$B$14*($T11)))/($D11/100/Control!$B$14)/Control!$B$14,"") | X11: =IFERROR($W11*100*1000000/10000,"") | Y11: =IF($T11<=Control!$B$12,$D11*Control!$B$12/100,IFERROR((IFERROR(($D11/Control!$B$14)*(1-(1+$U11/100/Control!$B$14)^(-Control!$B$14*($T11-Control!$B$12)))/($U11/100/Control!$B$14)+100*(1+$U11/100/Control!$B$14)^(-Control!$B$14*($T11-Control!$B$12)),"")+$D11*Control!$B$12-100)/100,"")) | Z11: =IF($T11<=Control!$B$12,"n/a",IFERROR($Y11*100/IFERROR((1-(1+$U11/100/Control!$B$14)^(-Control!$B$14*($T11-Control!$B$12)))/($U11/100/Control!$B$14)/Control!$B$14,"")*Control!$B$11,""))
A12: UST 4Y | B12: derived on HIST_D | C12: % | D12: =INDEX(HIST_D!$AR$8:$AR$2617,1) | E12: =IFERROR((INDEX(HIST_D!$AR$8:$AR$2617,1)-INDEX(HIST_D!$AR$8:$AR$2617,Control!$F$6))*Control!$B$11,"") | F12: =IFERROR((INDEX(HIST_D!$AR$8:$AR$2617,1)-INDEX(HIST_D!$AR$8:$AR$2617,Control!$F$7))*Control!$B$11,"") | G12: =IFERROR((INDEX(HIST_D!$AR$8:$AR$2617,1)-INDEX(HIST_D!$AR$8:$AR$2617,Control!$F$8))*Control!$B$11,"") | H12: =IFERROR((INDEX(HIST_D!$AR$8:$AR$2617,1)-INDEX(HIST_D!$AR$8:$AR$2617,Control!$F$9))*Control!$B$11,"") | I12: =IFERROR((INDEX(HIST_D!$AR$8:$AR$2617,1)-INDEX(HIST_D!$AR$8:$AR$2617,Control!$F$10))*Control!$B$11,"") | J12: =IFERROR((INDEX(HIST_D!$AR$8:$AR$2617,1)-INDEX(HIST_D!$AR$8:$AR$2617,Control!$F$16))*Control!$B$11,"") | K12: =IFERROR((INDEX(HIST_D!$AR$8:$AR$2617,1)-INDEX(HIST_D!$AR$8:$AR$2617,Control!$F$11))*Control!$B$11,"") | L12: =IFERROR(MIN(HIST_D!$AR$8:INDEX(HIST_D!$AR$8:$AR$2617,Control!$F$11)),"") | M12: =IFERROR(MAX(HIST_D!$AR$8:INDEX(HIST_D!$AR$8:$AR$2617,Control!$F$11)),"") | N12: =IFERROR(PERCENTRANK(HIST_D!$AR$8:INDEX(HIST_D!$AR$8:$AR$2617,Control!$F$11),INDEX(HIST_D!$AR$8:$AR$2617,1)),"") | O12: =IFERROR(PERCENTRANK(HIST_D!$AR$8:INDEX(HIST_D!$AR$8:$AR$2617,Control!$F$13),INDEX(HIST_D!$AR$8:$AR$2617,1)),"") | P12: =IFERROR(PERCENTRANK(HIST_D!$AR$8:INDEX(HIST_D!$AR$8:$AR$2617,Control!$F$14),INDEX(HIST_D!$AR$8:$AR$2617,1)),"") | Q12: =IFERROR(PERCENTRANK(HIST_D!$AR$8:INDEX(HIST_D!$AR$8:$AR$2617,Control!$F$15),INDEX(HIST_D!$AR$8:$AR$2617,1)),"") | S12: =IFERROR((INDEX(HIST_D!$AR$8:$AR$2617,1)-AVERAGE(HIST_D!$AR$8:INDEX(HIST_D!$AR$8:$AR$2617,Control!$F$14)))/STDEV(HIST_D!$AR$8:INDEX(HIST_D!$AR$8:$AR$2617,Control!$F$14)),"") | T12: 4 | U12: =IF(MAX($T12-Control!$B$12,0.0833)<=INDEX($T$6:$T$18,1),INDEX($D$6:$D$18,1),IF(MAX($T12-Control!$B$12,0.0833)>=INDEX($T$6:$T$18,COUNT($T$6:$T$18)),INDEX($D$6:$D$18,COUNT($T$6:$T$18)),INDEX($D$6:$D$18,MATCH(MAX($T12-Control!$B$12,0.0833),$T$6:$T$18,1))+(MAX($T12-Control!$B$12,0.0833)-INDEX($T$6:$T$18,MATCH(MAX($T12-Control!$B$12,0.0833),$T$6:$T$18,1)))/(INDEX($T$6:$T$18,MATCH(MAX($T12-Control!$B$12,0.0833),$T$6:$T$18,1)+1)-INDEX($T$6:$T$18,MATCH(MAX($T12-Control!$B$12,0.0833),$T$6:$T$18,1)))*(INDEX($D$6:$D$18,MATCH(MAX($T12-Control!$B$12,0.0833),$T$6:$T$18,1)+1)-INDEX($D$6:$D$18,MATCH(MAX($T12-Control!$B$12,0.0833),$T$6:$T$18,1))))) | V12: =IF($T12<=Control!$B$12,"",($D12-$U12)*Control!$B$11) | W12: =IFERROR((1-(1+$D12/100/Control!$B$14)^(-Control!$B$14*($T12)))/($D12/100/Control!$B$14)/Control!$B$14,"") | X12: =IFERROR($W12*100*1000000/10000,"") | Y12: =IF($T12<=Control!$B$12,$D12*Control!$B$12/100,IFERROR((IFERROR(($D12/Control!$B$14)*(1-(1+$U12/100/Control!$B$14)^(-Control!$B$14*($T12-Control!$B$12)))/($U12/100/Control!$B$14)+100*(1+$U12/100/Control!$B$14)^(-Control!$B$14*($T12-Control!$B$12)),"")+$D12*Control!$B$12-100)/100,"")) | Z12: =IF($T12<=Control!$B$12,"n/a",IFERROR($Y12*100/IFERROR((1-(1+$U12/100/Control!$B$14)^(-Control!$B$14*($T12-Control!$B$12)))/($U12/100/Control!$B$14)/Control!$B$14,"")*Control!$B$11,""))
A13: UST 5Y | B13: =Tickers!$C$12 | C13: % | D13: =INDEX(HIST_D!$H$8:$H$2617,1) | E13: =IFERROR((INDEX(HIST_D!$H$8:$H$2617,1)-INDEX(HIST_D!$H$8:$H$2617,Control!$F$6))*Control!$B$11,"") | F13: =IFERROR((INDEX(HIST_D!$H$8:$H$2617,1)-INDEX(HIST_D!$H$8:$H$2617,Control!$F$7))*Control!$B$11,"") | G13: =IFERROR((INDEX(HIST_D!$H$8:$H$2617,1)-INDEX(HIST_D!$H$8:$H$2617,Control!$F$8))*Control!$B$11,"") | H13: =IFERROR((INDEX(HIST_D!$H$8:$H$2617,1)-INDEX(HIST_D!$H$8:$H$2617,Control!$F$9))*Control!$B$11,"") | I13: =IFERROR((INDEX(HIST_D!$H$8:$H$2617,1)-INDEX(HIST_D!$H$8:$H$2617,Control!$F$10))*Control!$B$11,"") | J13: =IFERROR((INDEX(HIST_D!$H$8:$H$2617,1)-INDEX(HIST_D!$H$8:$H$2617,Control!$F$16))*Control!$B$11,"") | K13: =IFERROR((INDEX(HIST_D!$H$8:$H$2617,1)-INDEX(HIST_D!$H$8:$H$2617,Control!$F$11))*Control!$B$11,"") | L13: =IFERROR(MIN(HIST_D!$H$8:INDEX(HIST_D!$H$8:$H$2617,Control!$F$11)),"") | M13: =IFERROR(MAX(HIST_D!$H$8:INDEX(HIST_D!$H$8:$H$2617,Control!$F$11)),"") | N13: =IFERROR(PERCENTRANK(HIST_D!$H$8:INDEX(HIST_D!$H$8:$H$2617,Control!$F$11),INDEX(HIST_D!$H$8:$H$2617,1)),"") | O13: =IFERROR(PERCENTRANK(HIST_D!$H$8:INDEX(HIST_D!$H$8:$H$2617,Control!$F$13),INDEX(HIST_D!$H$8:$H$2617,1)),"") | P13: =IFERROR(PERCENTRANK(HIST_D!$H$8:INDEX(HIST_D!$H$8:$H$2617,Control!$F$14),INDEX(HIST_D!$H$8:$H$2617,1)),"") | Q13: =IFERROR(PERCENTRANK(HIST_D!$H$8:INDEX(HIST_D!$H$8:$H$2617,Control!$F$15),INDEX(HIST_D!$H$8:$H$2617,1)),"") | R13: =IFERROR(PERCENTRANK(HIST_M!$C$8:$C$308,INDEX(HIST_D!$H$8:$H$2617,1)),"") | S13: =IFERROR((INDEX(HIST_D!$H$8:$H$2617,1)-AVERAGE(HIST_D!$H$8:INDEX(HIST_D!$H$8:$H$2617,Control!$F$14)))/STDEV(HIST_D!$H$8:INDEX(HIST_D!$H$8:$H$2617,Control!$F$14)),"") | T13: 5 | U13: =IF(MAX($T13-Control!$B$12,0.0833)<=INDEX($T$6:$T$18,1),INDEX($D$6:$D$18,1),IF(MAX($T13-Control!$B$12,0.0833)>=INDEX($T$6:$T$18,COUNT($T$6:$T$18)),INDEX($D$6:$D$18,COUNT($T$6:$T$18)),INDEX($D$6:$D$18,MATCH(MAX($T13-Control!$B$12,0.0833),$T$6:$T$18,1))+(MAX($T13-Control!$B$12,0.0833)-INDEX($T$6:$T$18,MATCH(MAX($T13-Control!$B$12,0.0833),$T$6:$T$18,1)))/(INDEX($T$6:$T$18,MATCH(MAX($T13-Control!$B$12,0.0833),$T$6:$T$18,1)+1)-INDEX($T$6:$T$18,MATCH(MAX($T13-Control!$B$12,0.0833),$T$6:$T$18,1)))*(INDEX($D$6:$D$18,MATCH(MAX($T13-Control!$B$12,0.0833),$T$6:$T$18,1)+1)-INDEX($D$6:$D$18,MATCH(MAX($T13-Control!$B$12,0.0833),$T$6:$T$18,1))))) | V13: =IF($T13<=Control!$B$12,"",($D13-$U13)*Control!$B$11) | W13: =IFERROR((1-(1+$D13/100/Control!$B$14)^(-Control!$B$14*($T13)))/($D13/100/Control!$B$14)/Control!$B$14,"") | X13: =IFERROR($W13*100*1000000/10000,"") | Y13: =IF($T13<=Control!$B$12,$D13*Control!$B$12/100,IFERROR((IFERROR(($D13/Control!$B$14)*(1-(1+$U13/100/Control!$B$14)^(-Control!$B$14*($T13-Control!$B$12)))/($U13/100/Control!$B$14)+100*(1+$U13/100/Control!$B$14)^(-Control!$B$14*($T13-Control!$B$12)),"")+$D13*Control!$B$12-100)/100,"")) | Z13: =IF($T13<=Control!$B$12,"n/a",IFERROR($Y13*100/IFERROR((1-(1+$U13/100/Control!$B$14)^(-Control!$B$14*($T13-Control!$B$12)))/($U13/100/Control!$B$14)/Control!$B$14,"")*Control!$B$11,""))
A14: UST 7Y | B14: =Tickers!$C$13 | C14: % | D14: =INDEX(HIST_D!$I$8:$I$2617,1) | E14: =IFERROR((INDEX(HIST_D!$I$8:$I$2617,1)-INDEX(HIST_D!$I$8:$I$2617,Control!$F$6))*Control!$B$11,"") | F14: =IFERROR((INDEX(HIST_D!$I$8:$I$2617,1)-INDEX(HIST_D!$I$8:$I$2617,Control!$F$7))*Control!$B$11,"") | G14: =IFERROR((INDEX(HIST_D!$I$8:$I$2617,1)-INDEX(HIST_D!$I$8:$I$2617,Control!$F$8))*Control!$B$11,"") | H14: =IFERROR((INDEX(HIST_D!$I$8:$I$2617,1)-INDEX(HIST_D!$I$8:$I$2617,Control!$F$9))*Control!$B$11,"") | I14: =IFERROR((INDEX(HIST_D!$I$8:$I$2617,1)-INDEX(HIST_D!$I$8:$I$2617,Control!$F$10))*Control!$B$11,"") | J14: =IFERROR((INDEX(HIST_D!$I$8:$I$2617,1)-INDEX(HIST_D!$I$8:$I$2617,Control!$F$16))*Control!$B$11,"") | K14: =IFERROR((INDEX(HIST_D!$I$8:$I$2617,1)-INDEX(HIST_D!$I$8:$I$2617,Control!$F$11))*Control!$B$11,"") | L14: =IFERROR(MIN(HIST_D!$I$8:INDEX(HIST_D!$I$8:$I$2617,Control!$F$11)),"") | M14: =IFERROR(MAX(HIST_D!$I$8:INDEX(HIST_D!$I$8:$I$2617,Control!$F$11)),"") | N14: =IFERROR(PERCENTRANK(HIST_D!$I$8:INDEX(HIST_D!$I$8:$I$2617,Control!$F$11),INDEX(HIST_D!$I$8:$I$2617,1)),"") | O14: =IFERROR(PERCENTRANK(HIST_D!$I$8:INDEX(HIST_D!$I$8:$I$2617,Control!$F$13),INDEX(HIST_D!$I$8:$I$2617,1)),"") | P14: =IFERROR(PERCENTRANK(HIST_D!$I$8:INDEX(HIST_D!$I$8:$I$2617,Control!$F$14),INDEX(HIST_D!$I$8:$I$2617,1)),"") | Q14: =IFERROR(PERCENTRANK(HIST_D!$I$8:INDEX(HIST_D!$I$8:$I$2617,Control!$F$15),INDEX(HIST_D!$I$8:$I$2617,1)),"") | S14: =IFERROR((INDEX(HIST_D!$I$8:$I$2617,1)-AVERAGE(HIST_D!$I$8:INDEX(HIST_D!$I$8:$I$2617,Control!$F$14)))/STDEV(HIST_D!$I$8:INDEX(HIST_D!$I$8:$I$2617,Control!$F$14)),"") | T14: 7 | U14: =IF(MAX($T14-Control!$B$12,0.0833)<=INDEX($T$6:$T$18,1),INDEX($D$6:$D$18,1),IF(MAX($T14-Control!$B$12,0.0833)>=INDEX($T$6:$T$18,COUNT($T$6:$T$18)),INDEX($D$6:$D$18,COUNT($T$6:$T$18)),INDEX($D$6:$D$18,MATCH(MAX($T14-Control!$B$12,0.0833),$T$6:$T$18,1))+(MAX($T14-Control!$B$12,0.0833)-INDEX($T$6:$T$18,MATCH(MAX($T14-Control!$B$12,0.0833),$T$6:$T$18,1)))/(INDEX($T$6:$T$18,MATCH(MAX($T14-Control!$B$12,0.0833),$T$6:$T$18,1)+1)-INDEX($T$6:$T$18,MATCH(MAX($T14-Control!$B$12,0.0833),$T$6:$T$18,1)))*(INDEX($D$6:$D$18,MATCH(MAX($T14-Control!$B$12,0.0833),$T$6:$T$18,1)+1)-INDEX($D$6:$D$18,MATCH(MAX($T14-Control!$B$12,0.0833),$T$6:$T$18,1))))) | V14: =IF($T14<=Control!$B$12,"",($D14-$U14)*Control!$B$11) | W14: =IFERROR((1-(1+$D14/100/Control!$B$14)^(-Control!$B$14*($T14)))/($D14/100/Control!$B$14)/Control!$B$14,"") | X14: =IFERROR($W14*100*1000000/10000,"") | Y14: =IF($T14<=Control!$B$12,$D14*Control!$B$12/100,IFERROR((IFERROR(($D14/Control!$B$14)*(1-(1+$U14/100/Control!$B$14)^(-Control!$B$14*($T14-Control!$B$12)))/($U14/100/Control!$B$14)+100*(1+$U14/100/Control!$B$14)^(-Control!$B$14*($T14-Control!$B$12)),"")+$D14*Control!$B$12-100)/100,"")) | Z14: =IF($T14<=Control!$B$12,"n/a",IFERROR($Y14*100/IFERROR((1-(1+$U14/100/Control!$B$14)^(-Control!$B$14*($T14-Control!$B$12)))/($U14/100/Control!$B$14)/Control!$B$14,"")*Control!$B$11,""))
A15: UST 10Y | B15: =Tickers!$C$14 | C15: % | D15: =INDEX(HIST_D!$J$8:$J$2617,1) | E15: =IFERROR((INDEX(HIST_D!$J$8:$J$2617,1)-INDEX(HIST_D!$J$8:$J$2617,Control!$F$6))*Control!$B$11,"") | F15: =IFERROR((INDEX(HIST_D!$J$8:$J$2617,1)-INDEX(HIST_D!$J$8:$J$2617,Control!$F$7))*Control!$B$11,"") | G15: =IFERROR((INDEX(HIST_D!$J$8:$J$2617,1)-INDEX(HIST_D!$J$8:$J$2617,Control!$F$8))*Control!$B$11,"") | H15: =IFERROR((INDEX(HIST_D!$J$8:$J$2617,1)-INDEX(HIST_D!$J$8:$J$2617,Control!$F$9))*Control!$B$11,"") | I15: =IFERROR((INDEX(HIST_D!$J$8:$J$2617,1)-INDEX(HIST_D!$J$8:$J$2617,Control!$F$10))*Control!$B$11,"") | J15: =IFERROR((INDEX(HIST_D!$J$8:$J$2617,1)-INDEX(HIST_D!$J$8:$J$2617,Control!$F$16))*Control!$B$11,"") | K15: =IFERROR((INDEX(HIST_D!$J$8:$J$2617,1)-INDEX(HIST_D!$J$8:$J$2617,Control!$F$11))*Control!$B$11,"") | L15: =IFERROR(MIN(HIST_D!$J$8:INDEX(HIST_D!$J$8:$J$2617,Control!$F$11)),"") | M15: =IFERROR(MAX(HIST_D!$J$8:INDEX(HIST_D!$J$8:$J$2617,Control!$F$11)),"") | N15: =IFERROR(PERCENTRANK(HIST_D!$J$8:INDEX(HIST_D!$J$8:$J$2617,Control!$F$11),INDEX(HIST_D!$J$8:$J$2617,1)),"") | O15: =IFERROR(PERCENTRANK(HIST_D!$J$8:INDEX(HIST_D!$J$8:$J$2617,Control!$F$13),INDEX(HIST_D!$J$8:$J$2617,1)),"") | P15: =IFERROR(PERCENTRANK(HIST_D!$J$8:INDEX(HIST_D!$J$8:$J$2617,Control!$F$14),INDEX(HIST_D!$J$8:$J$2617,1)),"") | Q15: =IFERROR(PERCENTRANK(HIST_D!$J$8:INDEX(HIST_D!$J$8:$J$2617,Control!$F$15),INDEX(HIST_D!$J$8:$J$2617,1)),"") | R15: =IFERROR(PERCENTRANK(HIST_M!$D$8:$D$308,INDEX(HIST_D!$J$8:$J$2617,1)),"") | S15: =IFERROR((INDEX(HIST_D!$J$8:$J$2617,1)-AVERAGE(HIST_D!$J$8:INDEX(HIST_D!$J$8:$J$2617,Control!$F$14)))/STDEV(HIST_D!$J$8:INDEX(HIST_D!$J$8:$J$2617,Control!$F$14)),"") | T15: 10 | U15: =IF(MAX($T15-Control!$B$12,0.0833)<=INDEX($T$6:$T$18,1),INDEX($D$6:$D$18,1),IF(MAX($T15-Control!$B$12,0.0833)>=INDEX($T$6:$T$18,COUNT($T$6:$T$18)),INDEX($D$6:$D$18,COUNT($T$6:$T$18)),INDEX($D$6:$D$18,MATCH(MAX($T15-Control!$B$12,0.0833),$T$6:$T$18,1))+(MAX($T15-Control!$B$12,0.0833)-INDEX($T$6:$T$18,MATCH(MAX($T15-Control!$B$12,0.0833),$T$6:$T$18,1)))/(INDEX($T$6:$T$18,MATCH(MAX($T15-Control!$B$12,0.0833),$T$6:$T$18,1)+1)-INDEX($T$6:$T$18,MATCH(MAX($T15-Control!$B$12,0.0833),$T$6:$T$18,1)))*(INDEX($D$6:$D$18,MATCH(MAX($T15-Control!$B$12,0.0833),$T$6:$T$18,1)+1)-INDEX($D$6:$D$18,MATCH(MAX($T15-Control!$B$12,0.0833),$T$6:$T$18,1))))) | V15: =IF($T15<=Control!$B$12,"",($D15-$U15)*Control!$B$11) | W15: =IFERROR((1-(1+$D15/100/Control!$B$14)^(-Control!$B$14*($T15)))/($D15/100/Control!$B$14)/Control!$B$14,"") | X15: =IFERROR($W15*100*1000000/10000,"") | Y15: =IF($T15<=Control!$B$12,$D15*Control!$B$12/100,IFERROR((IFERROR(($D15/Control!$B$14)*(1-(1+$U15/100/Control!$B$14)^(-Control!$B$14*($T15-Control!$B$12)))/($U15/100/Control!$B$14)+100*(1+$U15/100/Control!$B$14)^(-Control!$B$14*($T15-Control!$B$12)),"")+$D15*Control!$B$12-100)/100,"")) | Z15: =IF($T15<=Control!$B$12,"n/a",IFERROR($Y15*100/IFERROR((1-(1+$U15/100/Control!$B$14)^(-Control!$B$14*($T15-Control!$B$12)))/($U15/100/Control!$B$14)/Control!$B$14,"")*Control!$B$11,""))
A16: UST 15Y | B16: derived on HIST_D | C16: % | D16: =INDEX(HIST_D!$AS$8:$AS$2617,1) | E16: =IFERROR((INDEX(HIST_D!$AS$8:$AS$2617,1)-INDEX(HIST_D!$AS$8:$AS$2617,Control!$F$6))*Control!$B$11,"") | F16: =IFERROR((INDEX(HIST_D!$AS$8:$AS$2617,1)-INDEX(HIST_D!$AS$8:$AS$2617,Control!$F$7))*Control!$B$11,"") | G16: =IFERROR((INDEX(HIST_D!$AS$8:$AS$2617,1)-INDEX(HIST_D!$AS$8:$AS$2617,Control!$F$8))*Control!$B$11,"") | H16: =IFERROR((INDEX(HIST_D!$AS$8:$AS$2617,1)-INDEX(HIST_D!$AS$8:$AS$2617,Control!$F$9))*Control!$B$11,"") | I16: =IFERROR((INDEX(HIST_D!$AS$8:$AS$2617,1)-INDEX(HIST_D!$AS$8:$AS$2617,Control!$F$10))*Control!$B$11,"") | J16: =IFERROR((INDEX(HIST_D!$AS$8:$AS$2617,1)-INDEX(HIST_D!$AS$8:$AS$2617,Control!$F$16))*Control!$B$11,"") | K16: =IFERROR((INDEX(HIST_D!$AS$8:$AS$2617,1)-INDEX(HIST_D!$AS$8:$AS$2617,Control!$F$11))*Control!$B$11,"") | L16: =IFERROR(MIN(HIST_D!$AS$8:INDEX(HIST_D!$AS$8:$AS$2617,Control!$F$11)),"") | M16: =IFERROR(MAX(HIST_D!$AS$8:INDEX(HIST_D!$AS$8:$AS$2617,Control!$F$11)),"") | N16: =IFERROR(PERCENTRANK(HIST_D!$AS$8:INDEX(HIST_D!$AS$8:$AS$2617,Control!$F$11),INDEX(HIST_D!$AS$8:$AS$2617,1)),"") | O16: =IFERROR(PERCENTRANK(HIST_D!$AS$8:INDEX(HIST_D!$AS$8:$AS$2617,Control!$F$13),INDEX(HIST_D!$AS$8:$AS$2617,1)),"") | P16: =IFERROR(PERCENTRANK(HIST_D!$AS$8:INDEX(HIST_D!$AS$8:$AS$2617,Control!$F$14),INDEX(HIST_D!$AS$8:$AS$2617,1)),"") | Q16: =IFERROR(PERCENTRANK(HIST_D!$AS$8:INDEX(HIST_D!$AS$8:$AS$2617,Control!$F$15),INDEX(HIST_D!$AS$8:$AS$2617,1)),"") | S16: =IFERROR((INDEX(HIST_D!$AS$8:$AS$2617,1)-AVERAGE(HIST_D!$AS$8:INDEX(HIST_D!$AS$8:$AS$2617,Control!$F$14)))/STDEV(HIST_D!$AS$8:INDEX(HIST_D!$AS$8:$AS$2617,Control!$F$14)),"") | T16: 15 | U16: =IF(MAX($T16-Control!$B$12,0.0833)<=INDEX($T$6:$T$18,1),INDEX($D$6:$D$18,1),IF(MAX($T16-Control!$B$12,0.0833)>=INDEX($T$6:$T$18,COUNT($T$6:$T$18)),INDEX($D$6:$D$18,COUNT($T$6:$T$18)),INDEX($D$6:$D$18,MATCH(MAX($T16-Control!$B$12,0.0833),$T$6:$T$18,1))+(MAX($T16-Control!$B$12,0.0833)-INDEX($T$6:$T$18,MATCH(MAX($T16-Control!$B$12,0.0833),$T$6:$T$18,1)))/(INDEX($T$6:$T$18,MATCH(MAX($T16-Control!$B$12,0.0833),$T$6:$T$18,1)+1)-INDEX($T$6:$T$18,MATCH(MAX($T16-Control!$B$12,0.0833),$T$6:$T$18,1)))*(INDEX($D$6:$D$18,MATCH(MAX($T16-Control!$B$12,0.0833),$T$6:$T$18,1)+1)-INDEX($D$6:$D$18,MATCH(MAX($T16-Control!$B$12,0.0833),$T$6:$T$18,1))))) | V16: =IF($T16<=Control!$B$12,"",($D16-$U16)*Control!$B$11) | W16: =IFERROR((1-(1+$D16/100/Control!$B$14)^(-Control!$B$14*($T16)))/($D16/100/Control!$B$14)/Control!$B$14,"") | X16: =IFERROR($W16*100*1000000/10000,"") | Y16: =IF($T16<=Control!$B$12,$D16*Control!$B$12/100,IFERROR((IFERROR(($D16/Control!$B$14)*(1-(1+$U16/100/Control!$B$14)^(-Control!$B$14*($T16-Control!$B$12)))/($U16/100/Control!$B$14)+100*(1+$U16/100/Control!$B$14)^(-Control!$B$14*($T16-Control!$B$12)),"")+$D16*Control!$B$12-100)/100,"")) | Z16: =IF($T16<=Control!$B$12,"n/a",IFERROR($Y16*100/IFERROR((1-(1+$U16/100/Control!$B$14)^(-Control!$B$14*($T16-Control!$B$12)))/($U16/100/Control!$B$14)/Control!$B$14,"")*Control!$B$11,""))
A17: UST 20Y | B17: =Tickers!$C$15 | C17: % | D17: =INDEX(HIST_D!$K$8:$K$2617,1) | E17: =IFERROR((INDEX(HIST_D!$K$8:$K$2617,1)-INDEX(HIST_D!$K$8:$K$2617,Control!$F$6))*Control!$B$11,"") | F17: =IFERROR((INDEX(HIST_D!$K$8:$K$2617,1)-INDEX(HIST_D!$K$8:$K$2617,Control!$F$7))*Control!$B$11,"") | G17: =IFERROR((INDEX(HIST_D!$K$8:$K$2617,1)-INDEX(HIST_D!$K$8:$K$2617,Control!$F$8))*Control!$B$11,"") | H17: =IFERROR((INDEX(HIST_D!$K$8:$K$2617,1)-INDEX(HIST_D!$K$8:$K$2617,Control!$F$9))*Control!$B$11,"") | I17: =IFERROR((INDEX(HIST_D!$K$8:$K$2617,1)-INDEX(HIST_D!$K$8:$K$2617,Control!$F$10))*Control!$B$11,"") | J17: =IFERROR((INDEX(HIST_D!$K$8:$K$2617,1)-INDEX(HIST_D!$K$8:$K$2617,Control!$F$16))*Control!$B$11,"") | K17: =IFERROR((INDEX(HIST_D!$K$8:$K$2617,1)-INDEX(HIST_D!$K$8:$K$2617,Control!$F$11))*Control!$B$11,"") | L17: =IFERROR(MIN(HIST_D!$K$8:INDEX(HIST_D!$K$8:$K$2617,Control!$F$11)),"") | M17: =IFERROR(MAX(HIST_D!$K$8:INDEX(HIST_D!$K$8:$K$2617,Control!$F$11)),"") | N17: =IFERROR(PERCENTRANK(HIST_D!$K$8:INDEX(HIST_D!$K$8:$K$2617,Control!$F$11),INDEX(HIST_D!$K$8:$K$2617,1)),"") | O17: =IFERROR(PERCENTRANK(HIST_D!$K$8:INDEX(HIST_D!$K$8:$K$2617,Control!$F$13),INDEX(HIST_D!$K$8:$K$2617,1)),"") | P17: =IFERROR(PERCENTRANK(HIST_D!$K$8:INDEX(HIST_D!$K$8:$K$2617,Control!$F$14),INDEX(HIST_D!$K$8:$K$2617,1)),"") | Q17: =IFERROR(PERCENTRANK(HIST_D!$K$8:INDEX(HIST_D!$K$8:$K$2617,Control!$F$15),INDEX(HIST_D!$K$8:$K$2617,1)),"") | S17: =IFERROR((INDEX(HIST_D!$K$8:$K$2617,1)-AVERAGE(HIST_D!$K$8:INDEX(HIST_D!$K$8:$K$2617,Control!$F$14)))/STDEV(HIST_D!$K$8:INDEX(HIST_D!$K$8:$K$2617,Control!$F$14)),"") | T17: 20 | U17: =IF(MAX($T17-Control!$B$12,0.0833)<=INDEX($T$6:$T$18,1),INDEX($D$6:$D$18,1),IF(MAX($T17-Control!$B$12,0.0833)>=INDEX($T$6:$T$18,COUNT($T$6:$T$18)),INDEX($D$6:$D$18,COUNT($T$6:$T$18)),INDEX($D$6:$D$18,MATCH(MAX($T17-Control!$B$12,0.0833),$T$6:$T$18,1))+(MAX($T17-Control!$B$12,0.0833)-INDEX($T$6:$T$18,MATCH(MAX($T17-Control!$B$12,0.0833),$T$6:$T$18,1)))/(INDEX($T$6:$T$18,MATCH(MAX($T17-Control!$B$12,0.0833),$T$6:$T$18,1)+1)-INDEX($T$6:$T$18,MATCH(MAX($T17-Control!$B$12,0.0833),$T$6:$T$18,1)))*(INDEX($D$6:$D$18,MATCH(MAX($T17-Control!$B$12,0.0833),$T$6:$T$18,1)+1)-INDEX($D$6:$D$18,MATCH(MAX($T17-Control!$B$12,0.0833),$T$6:$T$18,1))))) | V17: =IF($T17<=Control!$B$12,"",($D17-$U17)*Control!$B$11) | W17: =IFERROR((1-(1+$D17/100/Control!$B$14)^(-Control!$B$14*($T17)))/($D17/100/Control!$B$14)/Control!$B$14,"") | X17: =IFERROR($W17*100*1000000/10000,"") | Y17: =IF($T17<=Control!$B$12,$D17*Control!$B$12/100,IFERROR((IFERROR(($D17/Control!$B$14)*(1-(1+$U17/100/Control!$B$14)^(-Control!$B$14*($T17-Control!$B$12)))/($U17/100/Control!$B$14)+100*(1+$U17/100/Control!$B$14)^(-Control!$B$14*($T17-Control!$B$12)),"")+$D17*Control!$B$12-100)/100,"")) | Z17: =IF($T17<=Control!$B$12,"n/a",IFERROR($Y17*100/IFERROR((1-(1+$U17/100/Control!$B$14)^(-Control!$B$14*($T17-Control!$B$12)))/($U17/100/Control!$B$14)/Control!$B$14,"")*Control!$B$11,""))
A18: UST 30Y | B18: =Tickers!$C$16 | C18: % | D18: =INDEX(HIST_D!$L$8:$L$2617,1) | E18: =IFERROR((INDEX(HIST_D!$L$8:$L$2617,1)-INDEX(HIST_D!$L$8:$L$2617,Control!$F$6))*Control!$B$11,"") | F18: =IFERROR((INDEX(HIST_D!$L$8:$L$2617,1)-INDEX(HIST_D!$L$8:$L$2617,Control!$F$7))*Control!$B$11,"") | G18: =IFERROR((INDEX(HIST_D!$L$8:$L$2617,1)-INDEX(HIST_D!$L$8:$L$2617,Control!$F$8))*Control!$B$11,"") | H18: =IFERROR((INDEX(HIST_D!$L$8:$L$2617,1)-INDEX(HIST_D!$L$8:$L$2617,Control!$F$9))*Control!$B$11,"") | I18: =IFERROR((INDEX(HIST_D!$L$8:$L$2617,1)-INDEX(HIST_D!$L$8:$L$2617,Control!$F$10))*Control!$B$11,"") | J18: =IFERROR((INDEX(HIST_D!$L$8:$L$2617,1)-INDEX(HIST_D!$L$8:$L$2617,Control!$F$16))*Control!$B$11,"") | K18: =IFERROR((INDEX(HIST_D!$L$8:$L$2617,1)-INDEX(HIST_D!$L$8:$L$2617,Control!$F$11))*Control!$B$11,"") | L18: =IFERROR(MIN(HIST_D!$L$8:INDEX(HIST_D!$L$8:$L$2617,Control!$F$11)),"") | M18: =IFERROR(MAX(HIST_D!$L$8:INDEX(HIST_D!$L$8:$L$2617,Control!$F$11)),"") | N18: =IFERROR(PERCENTRANK(HIST_D!$L$8:INDEX(HIST_D!$L$8:$L$2617,Control!$F$11),INDEX(HIST_D!$L$8:$L$2617,1)),"") | O18: =IFERROR(PERCENTRANK(HIST_D!$L$8:INDEX(HIST_D!$L$8:$L$2617,Control!$F$13),INDEX(HIST_D!$L$8:$L$2617,1)),"") | P18: =IFERROR(PERCENTRANK(HIST_D!$L$8:INDEX(HIST_D!$L$8:$L$2617,Control!$F$14),INDEX(HIST_D!$L$8:$L$2617,1)),"") | Q18: =IFERROR(PERCENTRANK(HIST_D!$L$8:INDEX(HIST_D!$L$8:$L$2617,Control!$F$15),INDEX(HIST_D!$L$8:$L$2617,1)),"") | R18: =IFERROR(PERCENTRANK(HIST_M!$E$8:$E$308,INDEX(HIST_D!$L$8:$L$2617,1)),"") | S18: =IFERROR((INDEX(HIST_D!$L$8:$L$2617,1)-AVERAGE(HIST_D!$L$8:INDEX(HIST_D!$L$8:$L$2617,Control!$F$14)))/STDEV(HIST_D!$L$8:INDEX(HIST_D!$L$8:$L$2617,Control!$F$14)),"") | T18: 30 | U18: =IF(MAX($T18-Control!$B$12,0.0833)<=INDEX($T$6:$T$18,1),INDEX($D$6:$D$18,1),IF(MAX($T18-Control!$B$12,0.0833)>=INDEX($T$6:$T$18,COUNT($T$6:$T$18)),INDEX($D$6:$D$18,COUNT($T$6:$T$18)),INDEX($D$6:$D$18,MATCH(MAX($T18-Control!$B$12,0.0833),$T$6:$T$18,1))+(MAX($T18-Control!$B$12,0.0833)-INDEX($T$6:$T$18,MATCH(MAX($T18-Control!$B$12,0.0833),$T$6:$T$18,1)))/(INDEX($T$6:$T$18,MATCH(MAX($T18-Control!$B$12,0.0833),$T$6:$T$18,1)+1)-INDEX($T$6:$T$18,MATCH(MAX($T18-Control!$B$12,0.0833),$T$6:$T$18,1)))*(INDEX($D$6:$D$18,MATCH(MAX($T18-Control!$B$12,0.0833),$T$6:$T$18,1)+1)-INDEX($D$6:$D$18,MATCH(MAX($T18-Control!$B$12,0.0833),$T$6:$T$18,1))))) | V18: =IF($T18<=Control!$B$12,"",($D18-$U18)*Control!$B$11) | W18: =IFERROR((1-(1+$D18/100/Control!$B$14)^(-Control!$B$14*($T18)))/($D18/100/Control!$B$14)/Control!$B$14,"") | X18: =IFERROR($W18*100*1000000/10000,"") | Y18: =IF($T18<=Control!$B$12,$D18*Control!$B$12/100,IFERROR((IFERROR(($D18/Control!$B$14)*(1-(1+$U18/100/Control!$B$14)^(-Control!$B$14*($T18-Control!$B$12)))/($U18/100/Control!$B$14)+100*(1+$U18/100/Control!$B$14)^(-Control!$B$14*($T18-Control!$B$12)),"")+$D18*Control!$B$12-100)/100,"")) | Z18: =IF($T18<=Control!$B$12,"n/a",IFERROR($Y18*100/IFERROR((1-(1+$U18/100/Control!$B$14)^(-Control!$B$14*($T18-Control!$B$12)))/($U18/100/Control!$B$14)/Control!$B$14,"")*Control!$B$11,""))
A19: 4Y and 15Y are built, not quoted — see the construction audit at the bottom of this tab. Roll-down assumes the curve is unchanged and the bond ages by the horizon on Control. 12m TR is a full repricing (annuity + redemption), so it carries convexity exactly; coupon reinvestment is ignored.
A21: SOFR OIS CURVE (the 4Y and 15Y nodes the cash curve does not quote)
A22: Instrument | B22: Source | C22: Unit | D22: Level | E22: 1D | F22: 1W | G22: 1M | H22: 3M | I22: 6M | J22: YTD | K22: 1Y | L22: 1y min | M22: 1y max | N22: %ile 1y | O22: %ile 3y | P22: %ile 5y | Q22: %ile 10y | R22: %ile 25y | S22: z (5y)
A23: SOFR OIS 1Y | B23: =Tickers!$C$17 | C23: % | D23: =INDEX(HIST_D!$M$8:$M$2617,1) | E23: =IFERROR((INDEX(HIST_D!$M$8:$M$2617,1)-INDEX(HIST_D!$M$8:$M$2617,Control!$F$6))*Control!$B$11,"") | F23: =IFERROR((INDEX(HIST_D!$M$8:$M$2617,1)-INDEX(HIST_D!$M$8:$M$2617,Control!$F$7))*Control!$B$11,"") | G23: =IFERROR((INDEX(HIST_D!$M$8:$M$2617,1)-INDEX(HIST_D!$M$8:$M$2617,Control!$F$8))*Control!$B$11,"") | H23: =IFERROR((INDEX(HIST_D!$M$8:$M$2617,1)-INDEX(HIST_D!$M$8:$M$2617,Control!$F$9))*Control!$B$11,"") | I23: =IFERROR((INDEX(HIST_D!$M$8:$M$2617,1)-INDEX(HIST_D!$M$8:$M$2617,Control!$F$10))*Control!$B$11,"") | J23: =IFERROR((INDEX(HIST_D!$M$8:$M$2617,1)-INDEX(HIST_D!$M$8:$M$2617,Control!$F$16))*Control!$B$11,"") | K23: =IFERROR((INDEX(HIST_D!$M$8:$M$2617,1)-INDEX(HIST_D!$M$8:$M$2617,Control!$F$11))*Control!$B$11,"") | L23: =IFERROR(MIN(HIST_D!$M$8:INDEX(HIST_D!$M$8:$M$2617,Control!$F$11)),"") | M23: =IFERROR(MAX(HIST_D!$M$8:INDEX(HIST_D!$M$8:$M$2617,Control!$F$11)),"") | N23: =IFERROR(PERCENTRANK(HIST_D!$M$8:INDEX(HIST_D!$M$8:$M$2617,Control!$F$11),INDEX(HIST_D!$M$8:$M$2617,1)),"") | O23: =IFERROR(PERCENTRANK(HIST_D!$M$8:INDEX(HIST_D!$M$8:$M$2617,Control!$F$13),INDEX(HIST_D!$M$8:$M$2617,1)),"") | P23: =IFERROR(PERCENTRANK(HIST_D!$M$8:INDEX(HIST_D!$M$8:$M$2617,Control!$F$14),INDEX(HIST_D!$M$8:$M$2617,1)),"") | Q23: =IFERROR(PERCENTRANK(HIST_D!$M$8:INDEX(HIST_D!$M$8:$M$2617,Control!$F$15),INDEX(HIST_D!$M$8:$M$2617,1)),"") | S23: =IFERROR((INDEX(HIST_D!$M$8:$M$2617,1)-AVERAGE(HIST_D!$M$8:INDEX(HIST_D!$M$8:$M$2617,Control!$F$14)))/STDEV(HIST_D!$M$8:INDEX(HIST_D!$M$8:$M$2617,Control!$F$14)),"")
A24: SOFR OIS 2Y | B24: =Tickers!$C$18 | C24: % | D24: =INDEX(HIST_D!$N$8:$N$2617,1) | E24: =IFERROR((INDEX(HIST_D!$N$8:$N$2617,1)-INDEX(HIST_D!$N$8:$N$2617,Control!$F$6))*Control!$B$11,"") | F24: =IFERROR((INDEX(HIST_D!$N$8:$N$2617,1)-INDEX(HIST_D!$N$8:$N$2617,Control!$F$7))*Control!$B$11,"") | G24: =IFERROR((INDEX(HIST_D!$N$8:$N$2617,1)-INDEX(HIST_D!$N$8:$N$2617,Control!$F$8))*Control!$B$11,"") | H24: =IFERROR((INDEX(HIST_D!$N$8:$N$2617,1)-INDEX(HIST_D!$N$8:$N$2617,Control!$F$9))*Control!$B$11,"") | I24: =IFERROR((INDEX(HIST_D!$N$8:$N$2617,1)-INDEX(HIST_D!$N$8:$N$2617,Control!$F$10))*Control!$B$11,"") | J24: =IFERROR((INDEX(HIST_D!$N$8:$N$2617,1)-INDEX(HIST_D!$N$8:$N$2617,Control!$F$16))*Control!$B$11,"") | K24: =IFERROR((INDEX(HIST_D!$N$8:$N$2617,1)-INDEX(HIST_D!$N$8:$N$2617,Control!$F$11))*Control!$B$11,"") | L24: =IFERROR(MIN(HIST_D!$N$8:INDEX(HIST_D!$N$8:$N$2617,Control!$F$11)),"") | M24: =IFERROR(MAX(HIST_D!$N$8:INDEX(HIST_D!$N$8:$N$2617,Control!$F$11)),"") | N24: =IFERROR(PERCENTRANK(HIST_D!$N$8:INDEX(HIST_D!$N$8:$N$2617,Control!$F$11),INDEX(HIST_D!$N$8:$N$2617,1)),"") | O24: =IFERROR(PERCENTRANK(HIST_D!$N$8:INDEX(HIST_D!$N$8:$N$2617,Control!$F$13),INDEX(HIST_D!$N$8:$N$2617,1)),"") | P24: =IFERROR(PERCENTRANK(HIST_D!$N$8:INDEX(HIST_D!$N$8:$N$2617,Control!$F$14),INDEX(HIST_D!$N$8:$N$2617,1)),"") | Q24: =IFERROR(PERCENTRANK(HIST_D!$N$8:INDEX(HIST_D!$N$8:$N$2617,Control!$F$15),INDEX(HIST_D!$N$8:$N$2617,1)),"") | S24: =IFERROR((INDEX(HIST_D!$N$8:$N$2617,1)-AVERAGE(HIST_D!$N$8:INDEX(HIST_D!$N$8:$N$2617,Control!$F$14)))/STDEV(HIST_D!$N$8:INDEX(HIST_D!$N$8:$N$2617,Control!$F$14)),"")
A25: SOFR OIS 3Y | B25: =Tickers!$C$19 | C25: % | D25: =INDEX(HIST_D!$O$8:$O$2617,1) | E25: =IFERROR((INDEX(HIST_D!$O$8:$O$2617,1)-INDEX(HIST_D!$O$8:$O$2617,Control!$F$6))*Control!$B$11,"") | F25: =IFERROR((INDEX(HIST_D!$O$8:$O$2617,1)-INDEX(HIST_D!$O$8:$O$2617,Control!$F$7))*Control!$B$11,"") | G25: =IFERROR((INDEX(HIST_D!$O$8:$O$2617,1)-INDEX(HIST_D!$O$8:$O$2617,Control!$F$8))*Control!$B$11,"") | H25: =IFERROR((INDEX(HIST_D!$O$8:$O$2617,1)-INDEX(HIST_D!$O$8:$O$2617,Control!$F$9))*Control!$B$11,"") | I25: =IFERROR((INDEX(HIST_D!$O$8:$O$2617,1)-INDEX(HIST_D!$O$8:$O$2617,Control!$F$10))*Control!$B$11,"") | J25: =IFERROR((INDEX(HIST_D!$O$8:$O$2617,1)-INDEX(HIST_D!$O$8:$O$2617,Control!$F$16))*Control!$B$11,"") | K25: =IFERROR((INDEX(HIST_D!$O$8:$O$2617,1)-INDEX(HIST_D!$O$8:$O$2617,Control!$F$11))*Control!$B$11,"") | L25: =IFERROR(MIN(HIST_D!$O$8:INDEX(HIST_D!$O$8:$O$2617,Control!$F$11)),"") | M25: =IFERROR(MAX(HIST_D!$O$8:INDEX(HIST_D!$O$8:$O$2617,Control!$F$11)),"") | N25: =IFERROR(PERCENTRANK(HIST_D!$O$8:INDEX(HIST_D!$O$8:$O$2617,Control!$F$11),INDEX(HIST_D!$O$8:$O$2617,1)),"") | O25: =IFERROR(PERCENTRANK(HIST_D!$O$8:INDEX(HIST_D!$O$8:$O$2617,Control!$F$13),INDEX(HIST_D!$O$8:$O$2617,1)),"") | P25: =IFERROR(PERCENTRANK(HIST_D!$O$8:INDEX(HIST_D!$O$8:$O$2617,Control!$F$14),INDEX(HIST_D!$O$8:$O$2617,1)),"") | Q25: =IFERROR(PERCENTRANK(HIST_D!$O$8:INDEX(HIST_D!$O$8:$O$2617,Control!$F$15),INDEX(HIST_D!$O$8:$O$2617,1)),"") | S25: =IFERROR((INDEX(HIST_D!$O$8:$O$2617,1)-AVERAGE(HIST_D!$O$8:INDEX(HIST_D!$O$8:$O$2617,Control!$F$14)))/STDEV(HIST_D!$O$8:INDEX(HIST_D!$O$8:$O$2617,Control!$F$14)),"")
A26: SOFR OIS 4Y | B26: =Tickers!$C$20 | C26: % | D26: =INDEX(HIST_D!$P$8:$P$2617,1) | E26: =IFERROR((INDEX(HIST_D!$P$8:$P$2617,1)-INDEX(HIST_D!$P$8:$P$2617,Control!$F$6))*Control!$B$11,"") | F26: =IFERROR((INDEX(HIST_D!$P$8:$P$2617,1)-INDEX(HIST_D!$P$8:$P$2617,Control!$F$7))*Control!$B$11,"") | G26: =IFERROR((INDEX(HIST_D!$P$8:$P$2617,1)-INDEX(HIST_D!$P$8:$P$2617,Control!$F$8))*Control!$B$11,"") | H26: =IFERROR((INDEX(HIST_D!$P$8:$P$2617,1)-INDEX(HIST_D!$P$8:$P$2617,Control!$F$9))*Control!$B$11,"") | I26: =IFERROR((INDEX(HIST_D!$P$8:$P$2617,1)-INDEX(HIST_D!$P$8:$P$2617,Control!$F$10))*Control!$B$11,"") | J26: =IFERROR((INDEX(HIST_D!$P$8:$P$2617,1)-INDEX(HIST_D!$P$8:$P$2617,Control!$F$16))*Control!$B$11,"") | K26: =IFERROR((INDEX(HIST_D!$P$8:$P$2617,1)-INDEX(HIST_D!$P$8:$P$2617,Control!$F$11))*Control!$B$11,"") | L26: =IFERROR(MIN(HIST_D!$P$8:INDEX(HIST_D!$P$8:$P$2617,Control!$F$11)),"") | M26: =IFERROR(MAX(HIST_D!$P$8:INDEX(HIST_D!$P$8:$P$2617,Control!$F$11)),"") | N26: =IFERROR(PERCENTRANK(HIST_D!$P$8:INDEX(HIST_D!$P$8:$P$2617,Control!$F$11),INDEX(HIST_D!$P$8:$P$2617,1)),"") | O26: =IFERROR(PERCENTRANK(HIST_D!$P$8:INDEX(HIST_D!$P$8:$P$2617,Control!$F$13),INDEX(HIST_D!$P$8:$P$2617,1)),"") | P26: =IFERROR(PERCENTRANK(HIST_D!$P$8:INDEX(HIST_D!$P$8:$P$2617,Control!$F$14),INDEX(HIST_D!$P$8:$P$2617,1)),"") | Q26: =IFERROR(PERCENTRANK(HIST_D!$P$8:INDEX(HIST_D!$P$8:$P$2617,Control!$F$15),INDEX(HIST_D!$P$8:$P$2617,1)),"") | S26: =IFERROR((INDEX(HIST_D!$P$8:$P$2617,1)-AVERAGE(HIST_D!$P$8:INDEX(HIST_D!$P$8:$P$2617,Control!$F$14)))/STDEV(HIST_D!$P$8:INDEX(HIST_D!$P$8:$P$2617,Control!$F$14)),"")
A27: SOFR OIS 5Y | B27: =Tickers!$C$21 | C27: % | D27: =INDEX(HIST_D!$Q$8:$Q$2617,1) | E27: =IFERROR((INDEX(HIST_D!$Q$8:$Q$2617,1)-INDEX(HIST_D!$Q$8:$Q$2617,Control!$F$6))*Control!$B$11,"") | F27: =IFERROR((INDEX(HIST_D!$Q$8:$Q$2617,1)-INDEX(HIST_D!$Q$8:$Q$2617,Control!$F$7))*Control!$B$11,"") | G27: =IFERROR((INDEX(HIST_D!$Q$8:$Q$2617,1)-INDEX(HIST_D!$Q$8:$Q$2617,Control!$F$8))*Control!$B$11,"") | H27: =IFERROR((INDEX(HIST_D!$Q$8:$Q$2617,1)-INDEX(HIST_D!$Q$8:$Q$2617,Control!$F$9))*Control!$B$11,"") | I27: =IFERROR((INDEX(HIST_D!$Q$8:$Q$2617,1)-INDEX(HIST_D!$Q$8:$Q$2617,Control!$F$10))*Control!$B$11,"") | J27: =IFERROR((INDEX(HIST_D!$Q$8:$Q$2617,1)-INDEX(HIST_D!$Q$8:$Q$2617,Control!$F$16))*Control!$B$11,"") | K27: =IFERROR((INDEX(HIST_D!$Q$8:$Q$2617,1)-INDEX(HIST_D!$Q$8:$Q$2617,Control!$F$11))*Control!$B$11,"") | L27: =IFERROR(MIN(HIST_D!$Q$8:INDEX(HIST_D!$Q$8:$Q$2617,Control!$F$11)),"") | M27: =IFERROR(MAX(HIST_D!$Q$8:INDEX(HIST_D!$Q$8:$Q$2617,Control!$F$11)),"") | N27: =IFERROR(PERCENTRANK(HIST_D!$Q$8:INDEX(HIST_D!$Q$8:$Q$2617,Control!$F$11),INDEX(HIST_D!$Q$8:$Q$2617,1)),"") | O27: =IFERROR(PERCENTRANK(HIST_D!$Q$8:INDEX(HIST_D!$Q$8:$Q$2617,Control!$F$13),INDEX(HIST_D!$Q$8:$Q$2617,1)),"") | P27: =IFERROR(PERCENTRANK(HIST_D!$Q$8:INDEX(HIST_D!$Q$8:$Q$2617,Control!$F$14),INDEX(HIST_D!$Q$8:$Q$2617,1)),"") | Q27: =IFERROR(PERCENTRANK(HIST_D!$Q$8:INDEX(HIST_D!$Q$8:$Q$2617,Control!$F$15),INDEX(HIST_D!$Q$8:$Q$2617,1)),"") | S27: =IFERROR((INDEX(HIST_D!$Q$8:$Q$2617,1)-AVERAGE(HIST_D!$Q$8:INDEX(HIST_D!$Q$8:$Q$2617,Control!$F$14)))/STDEV(HIST_D!$Q$8:INDEX(HIST_D!$Q$8:$Q$2617,Control!$F$14)),"")
A28: SOFR OIS 7Y | B28: =Tickers!$C$22 | C28: % | D28: =INDEX(HIST_D!$R$8:$R$2617,1) | E28: =IFERROR((INDEX(HIST_D!$R$8:$R$2617,1)-INDEX(HIST_D!$R$8:$R$2617,Control!$F$6))*Control!$B$11,"") | F28: =IFERROR((INDEX(HIST_D!$R$8:$R$2617,1)-INDEX(HIST_D!$R$8:$R$2617,Control!$F$7))*Control!$B$11,"") | G28: =IFERROR((INDEX(HIST_D!$R$8:$R$2617,1)-INDEX(HIST_D!$R$8:$R$2617,Control!$F$8))*Control!$B$11,"") | H28: =IFERROR((INDEX(HIST_D!$R$8:$R$2617,1)-INDEX(HIST_D!$R$8:$R$2617,Control!$F$9))*Control!$B$11,"") | I28: =IFERROR((INDEX(HIST_D!$R$8:$R$2617,1)-INDEX(HIST_D!$R$8:$R$2617,Control!$F$10))*Control!$B$11,"") | J28: =IFERROR((INDEX(HIST_D!$R$8:$R$2617,1)-INDEX(HIST_D!$R$8:$R$2617,Control!$F$16))*Control!$B$11,"") | K28: =IFERROR((INDEX(HIST_D!$R$8:$R$2617,1)-INDEX(HIST_D!$R$8:$R$2617,Control!$F$11))*Control!$B$11,"") | L28: =IFERROR(MIN(HIST_D!$R$8:INDEX(HIST_D!$R$8:$R$2617,Control!$F$11)),"") | M28: =IFERROR(MAX(HIST_D!$R$8:INDEX(HIST_D!$R$8:$R$2617,Control!$F$11)),"") | N28: =IFERROR(PERCENTRANK(HIST_D!$R$8:INDEX(HIST_D!$R$8:$R$2617,Control!$F$11),INDEX(HIST_D!$R$8:$R$2617,1)),"") | O28: =IFERROR(PERCENTRANK(HIST_D!$R$8:INDEX(HIST_D!$R$8:$R$2617,Control!$F$13),INDEX(HIST_D!$R$8:$R$2617,1)),"") | P28: =IFERROR(PERCENTRANK(HIST_D!$R$8:INDEX(HIST_D!$R$8:$R$2617,Control!$F$14),INDEX(HIST_D!$R$8:$R$2617,1)),"") | Q28: =IFERROR(PERCENTRANK(HIST_D!$R$8:INDEX(HIST_D!$R$8:$R$2617,Control!$F$15),INDEX(HIST_D!$R$8:$R$2617,1)),"") | S28: =IFERROR((INDEX(HIST_D!$R$8:$R$2617,1)-AVERAGE(HIST_D!$R$8:INDEX(HIST_D!$R$8:$R$2617,Control!$F$14)))/STDEV(HIST_D!$R$8:INDEX(HIST_D!$R$8:$R$2617,Control!$F$14)),"")
A29: SOFR OIS 10Y | B29: =Tickers!$C$23 | C29: % | D29: =INDEX(HIST_D!$S$8:$S$2617,1) | E29: =IFERROR((INDEX(HIST_D!$S$8:$S$2617,1)-INDEX(HIST_D!$S$8:$S$2617,Control!$F$6))*Control!$B$11,"") | F29: =IFERROR((INDEX(HIST_D!$S$8:$S$2617,1)-INDEX(HIST_D!$S$8:$S$2617,Control!$F$7))*Control!$B$11,"") | G29: =IFERROR((INDEX(HIST_D!$S$8:$S$2617,1)-INDEX(HIST_D!$S$8:$S$2617,Control!$F$8))*Control!$B$11,"") | H29: =IFERROR((INDEX(HIST_D!$S$8:$S$2617,1)-INDEX(HIST_D!$S$8:$S$2617,Control!$F$9))*Control!$B$11,"") | I29: =IFERROR((INDEX(HIST_D!$S$8:$S$2617,1)-INDEX(HIST_D!$S$8:$S$2617,Control!$F$10))*Control!$B$11,"") | J29: =IFERROR((INDEX(HIST_D!$S$8:$S$2617,1)-INDEX(HIST_D!$S$8:$S$2617,Control!$F$16))*Control!$B$11,"") | K29: =IFERROR((INDEX(HIST_D!$S$8:$S$2617,1)-INDEX(HIST_D!$S$8:$S$2617,Control!$F$11))*Control!$B$11,"") | L29: =IFERROR(MIN(HIST_D!$S$8:INDEX(HIST_D!$S$8:$S$2617,Control!$F$11)),"") | M29: =IFERROR(MAX(HIST_D!$S$8:INDEX(HIST_D!$S$8:$S$2617,Control!$F$11)),"") | N29: =IFERROR(PERCENTRANK(HIST_D!$S$8:INDEX(HIST_D!$S$8:$S$2617,Control!$F$11),INDEX(HIST_D!$S$8:$S$2617,1)),"") | O29: =IFERROR(PERCENTRANK(HIST_D!$S$8:INDEX(HIST_D!$S$8:$S$2617,Control!$F$13),INDEX(HIST_D!$S$8:$S$2617,1)),"") | P29: =IFERROR(PERCENTRANK(HIST_D!$S$8:INDEX(HIST_D!$S$8:$S$2617,Control!$F$14),INDEX(HIST_D!$S$8:$S$2617,1)),"") | Q29: =IFERROR(PERCENTRANK(HIST_D!$S$8:INDEX(HIST_D!$S$8:$S$2617,Control!$F$15),INDEX(HIST_D!$S$8:$S$2617,1)),"") | S29: =IFERROR((INDEX(HIST_D!$S$8:$S$2617,1)-AVERAGE(HIST_D!$S$8:INDEX(HIST_D!$S$8:$S$2617,Control!$F$14)))/STDEV(HIST_D!$S$8:INDEX(HIST_D!$S$8:$S$2617,Control!$F$14)),"")
A30: SOFR OIS 15Y | B30: =Tickers!$C$24 | C30: % | D30: =INDEX(HIST_D!$T$8:$T$2617,1) | E30: =IFERROR((INDEX(HIST_D!$T$8:$T$2617,1)-INDEX(HIST_D!$T$8:$T$2617,Control!$F$6))*Control!$B$11,"") | F30: =IFERROR((INDEX(HIST_D!$T$8:$T$2617,1)-INDEX(HIST_D!$T$8:$T$2617,Control!$F$7))*Control!$B$11,"") | G30: =IFERROR((INDEX(HIST_D!$T$8:$T$2617,1)-INDEX(HIST_D!$T$8:$T$2617,Control!$F$8))*Control!$B$11,"") | H30: =IFERROR((INDEX(HIST_D!$T$8:$T$2617,1)-INDEX(HIST_D!$T$8:$T$2617,Control!$F$9))*Control!$B$11,"") | I30: =IFERROR((INDEX(HIST_D!$T$8:$T$2617,1)-INDEX(HIST_D!$T$8:$T$2617,Control!$F$10))*Control!$B$11,"") | J30: =IFERROR((INDEX(HIST_D!$T$8:$T$2617,1)-INDEX(HIST_D!$T$8:$T$2617,Control!$F$16))*Control!$B$11,"") | K30: =IFERROR((INDEX(HIST_D!$T$8:$T$2617,1)-INDEX(HIST_D!$T$8:$T$2617,Control!$F$11))*Control!$B$11,"") | L30: =IFERROR(MIN(HIST_D!$T$8:INDEX(HIST_D!$T$8:$T$2617,Control!$F$11)),"") | M30: =IFERROR(MAX(HIST_D!$T$8:INDEX(HIST_D!$T$8:$T$2617,Control!$F$11)),"") | N30: =IFERROR(PERCENTRANK(HIST_D!$T$8:INDEX(HIST_D!$T$8:$T$2617,Control!$F$11),INDEX(HIST_D!$T$8:$T$2617,1)),"") | O30: =IFERROR(PERCENTRANK(HIST_D!$T$8:INDEX(HIST_D!$T$8:$T$2617,Control!$F$13),INDEX(HIST_D!$T$8:$T$2617,1)),"") | P30: =IFERROR(PERCENTRANK(HIST_D!$T$8:INDEX(HIST_D!$T$8:$T$2617,Control!$F$14),INDEX(HIST_D!$T$8:$T$2617,1)),"") | Q30: =IFERROR(PERCENTRANK(HIST_D!$T$8:INDEX(HIST_D!$T$8:$T$2617,Control!$F$15),INDEX(HIST_D!$T$8:$T$2617,1)),"") | S30: =IFERROR((INDEX(HIST_D!$T$8:$T$2617,1)-AVERAGE(HIST_D!$T$8:INDEX(HIST_D!$T$8:$T$2617,Control!$F$14)))/STDEV(HIST_D!$T$8:INDEX(HIST_D!$T$8:$T$2617,Control!$F$14)),"")
A31: SOFR OIS 20Y | B31: =Tickers!$C$25 | C31: % | D31: =INDEX(HIST_D!$U$8:$U$2617,1) | E31: =IFERROR((INDEX(HIST_D!$U$8:$U$2617,1)-INDEX(HIST_D!$U$8:$U$2617,Control!$F$6))*Control!$B$11,"") | F31: =IFERROR((INDEX(HIST_D!$U$8:$U$2617,1)-INDEX(HIST_D!$U$8:$U$2617,Control!$F$7))*Control!$B$11,"") | G31: =IFERROR((INDEX(HIST_D!$U$8:$U$2617,1)-INDEX(HIST_D!$U$8:$U$2617,Control!$F$8))*Control!$B$11,"") | H31: =IFERROR((INDEX(HIST_D!$U$8:$U$2617,1)-INDEX(HIST_D!$U$8:$U$2617,Control!$F$9))*Control!$B$11,"") | I31: =IFERROR((INDEX(HIST_D!$U$8:$U$2617,1)-INDEX(HIST_D!$U$8:$U$2617,Control!$F$10))*Control!$B$11,"") | J31: =IFERROR((INDEX(HIST_D!$U$8:$U$2617,1)-INDEX(HIST_D!$U$8:$U$2617,Control!$F$16))*Control!$B$11,"") | K31: =IFERROR((INDEX(HIST_D!$U$8:$U$2617,1)-INDEX(HIST_D!$U$8:$U$2617,Control!$F$11))*Control!$B$11,"") | L31: =IFERROR(MIN(HIST_D!$U$8:INDEX(HIST_D!$U$8:$U$2617,Control!$F$11)),"") | M31: =IFERROR(MAX(HIST_D!$U$8:INDEX(HIST_D!$U$8:$U$2617,Control!$F$11)),"") | N31: =IFERROR(PERCENTRANK(HIST_D!$U$8:INDEX(HIST_D!$U$8:$U$2617,Control!$F$11),INDEX(HIST_D!$U$8:$U$2617,1)),"") | O31: =IFERROR(PERCENTRANK(HIST_D!$U$8:INDEX(HIST_D!$U$8:$U$2617,Control!$F$13),INDEX(HIST_D!$U$8:$U$2617,1)),"") | P31: =IFERROR(PERCENTRANK(HIST_D!$U$8:INDEX(HIST_D!$U$8:$U$2617,Control!$F$14),INDEX(HIST_D!$U$8:$U$2617,1)),"") | Q31: =IFERROR(PERCENTRANK(HIST_D!$U$8:INDEX(HIST_D!$U$8:$U$2617,Control!$F$15),INDEX(HIST_D!$U$8:$U$2617,1)),"") | S31: =IFERROR((INDEX(HIST_D!$U$8:$U$2617,1)-AVERAGE(HIST_D!$U$8:INDEX(HIST_D!$U$8:$U$2617,Control!$F$14)))/STDEV(HIST_D!$U$8:INDEX(HIST_D!$U$8:$U$2617,Control!$F$14)),"")
A32: SOFR OIS 30Y | B32: =Tickers!$C$26 | C32: % | D32: =INDEX(HIST_D!$V$8:$V$2617,1) | E32: =IFERROR((INDEX(HIST_D!$V$8:$V$2617,1)-INDEX(HIST_D!$V$8:$V$2617,Control!$F$6))*Control!$B$11,"") | F32: =IFERROR((INDEX(HIST_D!$V$8:$V$2617,1)-INDEX(HIST_D!$V$8:$V$2617,Control!$F$7))*Control!$B$11,"") | G32: =IFERROR((INDEX(HIST_D!$V$8:$V$2617,1)-INDEX(HIST_D!$V$8:$V$2617,Control!$F$8))*Control!$B$11,"") | H32: =IFERROR((INDEX(HIST_D!$V$8:$V$2617,1)-INDEX(HIST_D!$V$8:$V$2617,Control!$F$9))*Control!$B$11,"") | I32: =IFERROR((INDEX(HIST_D!$V$8:$V$2617,1)-INDEX(HIST_D!$V$8:$V$2617,Control!$F$10))*Control!$B$11,"") | J32: =IFERROR((INDEX(HIST_D!$V$8:$V$2617,1)-INDEX(HIST_D!$V$8:$V$2617,Control!$F$16))*Control!$B$11,"") | K32: =IFERROR((INDEX(HIST_D!$V$8:$V$2617,1)-INDEX(HIST_D!$V$8:$V$2617,Control!$F$11))*Control!$B$11,"") | L32: =IFERROR(MIN(HIST_D!$V$8:INDEX(HIST_D!$V$8:$V$2617,Control!$F$11)),"") | M32: =IFERROR(MAX(HIST_D!$V$8:INDEX(HIST_D!$V$8:$V$2617,Control!$F$11)),"") | N32: =IFERROR(PERCENTRANK(HIST_D!$V$8:INDEX(HIST_D!$V$8:$V$2617,Control!$F$11),INDEX(HIST_D!$V$8:$V$2617,1)),"") | O32: =IFERROR(PERCENTRANK(HIST_D!$V$8:INDEX(HIST_D!$V$8:$V$2617,Control!$F$13),INDEX(HIST_D!$V$8:$V$2617,1)),"") | P32: =IFERROR(PERCENTRANK(HIST_D!$V$8:INDEX(HIST_D!$V$8:$V$2617,Control!$F$14),INDEX(HIST_D!$V$8:$V$2617,1)),"") | Q32: =IFERROR(PERCENTRANK(HIST_D!$V$8:INDEX(HIST_D!$V$8:$V$2617,Control!$F$15),INDEX(HIST_D!$V$8:$V$2617,1)),"") | S32: =IFERROR((INDEX(HIST_D!$V$8:$V$2617,1)-AVERAGE(HIST_D!$V$8:INDEX(HIST_D!$V$8:$V$2617,Control!$F$14)))/STDEV(HIST_D!$V$8:INDEX(HIST_D!$V$8:$V$2617,Control!$F$14)),"")
A34: SWAP SPREADS (OIS − UST; the balance-sheet / collateral premium at each node)
A35: Instrument | B35: Source | C35: Unit | D35: Level | E35: 1D | F35: 1W | G35: 1M | H35: 3M | I35: 6M | J35: YTD | K35: 1Y | L35: 1y min | M35: 1y max | N35: %ile 1y | O35: %ile 3y | P35: %ile 5y | Q35: %ile 10y | R35: %ile 25y | S35: z (5y)
A36: Swap spread 2Y | B36: derived on HIST_D | C36: bp | D36: =INDEX(HIST_D!$BC$8:$BC$2617,1) | E36: =IFERROR((INDEX(HIST_D!$BC$8:$BC$2617,1)-INDEX(HIST_D!$BC$8:$BC$2617,Control!$F$6))*1,"") | F36: =IFERROR((INDEX(HIST_D!$BC$8:$BC$2617,1)-INDEX(HIST_D!$BC$8:$BC$2617,Control!$F$7))*1,"") | G36: =IFERROR((INDEX(HIST_D!$BC$8:$BC$2617,1)-INDEX(HIST_D!$BC$8:$BC$2617,Control!$F$8))*1,"") | H36: =IFERROR((INDEX(HIST_D!$BC$8:$BC$2617,1)-INDEX(HIST_D!$BC$8:$BC$2617,Control!$F$9))*1,"") | I36: =IFERROR((INDEX(HIST_D!$BC$8:$BC$2617,1)-INDEX(HIST_D!$BC$8:$BC$2617,Control!$F$10))*1,"") | J36: =IFERROR((INDEX(HIST_D!$BC$8:$BC$2617,1)-INDEX(HIST_D!$BC$8:$BC$2617,Control!$F$16))*1,"") | K36: =IFERROR((INDEX(HIST_D!$BC$8:$BC$2617,1)-INDEX(HIST_D!$BC$8:$BC$2617,Control!$F$11))*1,"") | L36: =IFERROR(MIN(HIST_D!$BC$8:INDEX(HIST_D!$BC$8:$BC$2617,Control!$F$11)),"") | M36: =IFERROR(MAX(HIST_D!$BC$8:INDEX(HIST_D!$BC$8:$BC$2617,Control!$F$11)),"") | N36: =IFERROR(PERCENTRANK(HIST_D!$BC$8:INDEX(HIST_D!$BC$8:$BC$2617,Control!$F$11),INDEX(HIST_D!$BC$8:$BC$2617,1)),"") | O36: =IFERROR(PERCENTRANK(HIST_D!$BC$8:INDEX(HIST_D!$BC$8:$BC$2617,Control!$F$13),INDEX(HIST_D!$BC$8:$BC$2617,1)),"") | P36: =IFERROR(PERCENTRANK(HIST_D!$BC$8:INDEX(HIST_D!$BC$8:$BC$2617,Control!$F$14),INDEX(HIST_D!$BC$8:$BC$2617,1)),"") | Q36: =IFERROR(PERCENTRANK(HIST_D!$BC$8:INDEX(HIST_D!$BC$8:$BC$2617,Control!$F$15),INDEX(HIST_D!$BC$8:$BC$2617,1)),"") | S36: =IFERROR((INDEX(HIST_D!$BC$8:$BC$2617,1)-AVERAGE(HIST_D!$BC$8:INDEX(HIST_D!$BC$8:$BC$2617,Control!$F$14)))/STDEV(HIST_D!$BC$8:INDEX(HIST_D!$BC$8:$BC$2617,Control!$F$14)),"")
A37: Swap spread 5Y | B37: derived on HIST_D | C37: bp | D37: =INDEX(HIST_D!$BD$8:$BD$2617,1) | E37: =IFERROR((INDEX(HIST_D!$BD$8:$BD$2617,1)-INDEX(HIST_D!$BD$8:$BD$2617,Control!$F$6))*1,"") | F37: =IFERROR((INDEX(HIST_D!$BD$8:$BD$2617,1)-INDEX(HIST_D!$BD$8:$BD$2617,Control!$F$7))*1,"") | G37: =IFERROR((INDEX(HIST_D!$BD$8:$BD$2617,1)-INDEX(HIST_D!$BD$8:$BD$2617,Control!$F$8))*1,"") | H37: =IFERROR((INDEX(HIST_D!$BD$8:$BD$2617,1)-INDEX(HIST_D!$BD$8:$BD$2617,Control!$F$9))*1,"") | I37: =IFERROR((INDEX(HIST_D!$BD$8:$BD$2617,1)-INDEX(HIST_D!$BD$8:$BD$2617,Control!$F$10))*1,"") | J37: =IFERROR((INDEX(HIST_D!$BD$8:$BD$2617,1)-INDEX(HIST_D!$BD$8:$BD$2617,Control!$F$16))*1,"") | K37: =IFERROR((INDEX(HIST_D!$BD$8:$BD$2617,1)-INDEX(HIST_D!$BD$8:$BD$2617,Control!$F$11))*1,"") | L37: =IFERROR(MIN(HIST_D!$BD$8:INDEX(HIST_D!$BD$8:$BD$2617,Control!$F$11)),"") | M37: =IFERROR(MAX(HIST_D!$BD$8:INDEX(HIST_D!$BD$8:$BD$2617,Control!$F$11)),"") | N37: =IFERROR(PERCENTRANK(HIST_D!$BD$8:INDEX(HIST_D!$BD$8:$BD$2617,Control!$F$11),INDEX(HIST_D!$BD$8:$BD$2617,1)),"") | O37: =IFERROR(PERCENTRANK(HIST_D!$BD$8:INDEX(HIST_D!$BD$8:$BD$2617,Control!$F$13),INDEX(HIST_D!$BD$8:$BD$2617,1)),"") | P37: =IFERROR(PERCENTRANK(HIST_D!$BD$8:INDEX(HIST_D!$BD$8:$BD$2617,Control!$F$14),INDEX(HIST_D!$BD$8:$BD$2617,1)),"") | Q37: =IFERROR(PERCENTRANK(HIST_D!$BD$8:INDEX(HIST_D!$BD$8:$BD$2617,Control!$F$15),INDEX(HIST_D!$BD$8:$BD$2617,1)),"") | S37: =IFERROR((INDEX(HIST_D!$BD$8:$BD$2617,1)-AVERAGE(HIST_D!$BD$8:INDEX(HIST_D!$BD$8:$BD$2617,Control!$F$14)))/STDEV(HIST_D!$BD$8:INDEX(HIST_D!$BD$8:$BD$2617,Control!$F$14)),"")
A38: Swap spread 10Y | B38: derived on HIST_D | C38: bp | D38: =INDEX(HIST_D!$BE$8:$BE$2617,1) | E38: =IFERROR((INDEX(HIST_D!$BE$8:$BE$2617,1)-INDEX(HIST_D!$BE$8:$BE$2617,Control!$F$6))*1,"") | F38: =IFERROR((INDEX(HIST_D!$BE$8:$BE$2617,1)-INDEX(HIST_D!$BE$8:$BE$2617,Control!$F$7))*1,"") | G38: =IFERROR((INDEX(HIST_D!$BE$8:$BE$2617,1)-INDEX(HIST_D!$BE$8:$BE$2617,Control!$F$8))*1,"") | H38: =IFERROR((INDEX(HIST_D!$BE$8:$BE$2617,1)-INDEX(HIST_D!$BE$8:$BE$2617,Control!$F$9))*1,"") | I38: =IFERROR((INDEX(HIST_D!$BE$8:$BE$2617,1)-INDEX(HIST_D!$BE$8:$BE$2617,Control!$F$10))*1,"") | J38: =IFERROR((INDEX(HIST_D!$BE$8:$BE$2617,1)-INDEX(HIST_D!$BE$8:$BE$2617,Control!$F$16))*1,"") | K38: =IFERROR((INDEX(HIST_D!$BE$8:$BE$2617,1)-INDEX(HIST_D!$BE$8:$BE$2617,Control!$F$11))*1,"") | L38: =IFERROR(MIN(HIST_D!$BE$8:INDEX(HIST_D!$BE$8:$BE$2617,Control!$F$11)),"") | M38: =IFERROR(MAX(HIST_D!$BE$8:INDEX(HIST_D!$BE$8:$BE$2617,Control!$F$11)),"") | N38: =IFERROR(PERCENTRANK(HIST_D!$BE$8:INDEX(HIST_D!$BE$8:$BE$2617,Control!$F$11),INDEX(HIST_D!$BE$8:$BE$2617,1)),"") | O38: =IFERROR(PERCENTRANK(HIST_D!$BE$8:INDEX(HIST_D!$BE$8:$BE$2617,Control!$F$13),INDEX(HIST_D!$BE$8:$BE$2617,1)),"") | P38: =IFERROR(PERCENTRANK(HIST_D!$BE$8:INDEX(HIST_D!$BE$8:$BE$2617,Control!$F$14),INDEX(HIST_D!$BE$8:$BE$2617,1)),"") | Q38: =IFERROR(PERCENTRANK(HIST_D!$BE$8:INDEX(HIST_D!$BE$8:$BE$2617,Control!$F$15),INDEX(HIST_D!$BE$8:$BE$2617,1)),"") | S38: =IFERROR((INDEX(HIST_D!$BE$8:$BE$2617,1)-AVERAGE(HIST_D!$BE$8:INDEX(HIST_D!$BE$8:$BE$2617,Control!$F$14)))/STDEV(HIST_D!$BE$8:INDEX(HIST_D!$BE$8:$BE$2617,Control!$F$14)),"")
A39: Swap spread 30Y | B39: derived on HIST_D | C39: bp | D39: =INDEX(HIST_D!$BF$8:$BF$2617,1) | E39: =IFERROR((INDEX(HIST_D!$BF$8:$BF$2617,1)-INDEX(HIST_D!$BF$8:$BF$2617,Control!$F$6))*1,"") | F39: =IFERROR((INDEX(HIST_D!$BF$8:$BF$2617,1)-INDEX(HIST_D!$BF$8:$BF$2617,Control!$F$7))*1,"") | G39: =IFERROR((INDEX(HIST_D!$BF$8:$BF$2617,1)-INDEX(HIST_D!$BF$8:$BF$2617,Control!$F$8))*1,"") | H39: =IFERROR((INDEX(HIST_D!$BF$8:$BF$2617,1)-INDEX(HIST_D!$BF$8:$BF$2617,Control!$F$9))*1,"") | I39: =IFERROR((INDEX(HIST_D!$BF$8:$BF$2617,1)-INDEX(HIST_D!$BF$8:$BF$2617,Control!$F$10))*1,"") | J39: =IFERROR((INDEX(HIST_D!$BF$8:$BF$2617,1)-INDEX(HIST_D!$BF$8:$BF$2617,Control!$F$16))*1,"") | K39: =IFERROR((INDEX(HIST_D!$BF$8:$BF$2617,1)-INDEX(HIST_D!$BF$8:$BF$2617,Control!$F$11))*1,"") | L39: =IFERROR(MIN(HIST_D!$BF$8:INDEX(HIST_D!$BF$8:$BF$2617,Control!$F$11)),"") | M39: =IFERROR(MAX(HIST_D!$BF$8:INDEX(HIST_D!$BF$8:$BF$2617,Control!$F$11)),"") | N39: =IFERROR(PERCENTRANK(HIST_D!$BF$8:INDEX(HIST_D!$BF$8:$BF$2617,Control!$F$11),INDEX(HIST_D!$BF$8:$BF$2617,1)),"") | O39: =IFERROR(PERCENTRANK(HIST_D!$BF$8:INDEX(HIST_D!$BF$8:$BF$2617,Control!$F$13),INDEX(HIST_D!$BF$8:$BF$2617,1)),"") | P39: =IFERROR(PERCENTRANK(HIST_D!$BF$8:INDEX(HIST_D!$BF$8:$BF$2617,Control!$F$14),INDEX(HIST_D!$BF$8:$BF$2617,1)),"") | Q39: =IFERROR(PERCENTRANK(HIST_D!$BF$8:INDEX(HIST_D!$BF$8:$BF$2617,Control!$F$15),INDEX(HIST_D!$BF$8:$BF$2617,1)),"") | S39: =IFERROR((INDEX(HIST_D!$BF$8:$BF$2617,1)-AVERAGE(HIST_D!$BF$8:INDEX(HIST_D!$BF$8:$BF$2617,Control!$F$14)))/STDEV(HIST_D!$BF$8:INDEX(HIST_D!$BF$8:$BF$2617,Control!$F$14)),"")
A40: Negative and widening (more negative) swap spreads = the market paying up for balance sheet / dealers full of Treasuries. This is the cleanest single read on Treasury market capacity, and it is why it sits next to the liquidity tab.
A42: REAL YIELDS, BREAKEVENS AND TERM PREMIUM
A43: Instrument | B43: Source | C43: Unit | D43: Level | E43: 1D | F43: 1W | G43: 1M | H43: 3M | I43: 6M | J43: YTD | K43: 1Y | L43: 1y min | M43: 1y max | N43: %ile 1y | O43: %ile 3y | P43: %ile 5y | Q43: %ile 10y | R43: %ile 25y | S43: z (5y)
A44: TIPS real 5Y | B44: =Tickers!$C$27 | C44: % | D44: =INDEX(HIST_D!$W$8:$W$2617,1) | E44: =IFERROR((INDEX(HIST_D!$W$8:$W$2617,1)-INDEX(HIST_D!$W$8:$W$2617,Control!$F$6))*Control!$B$11,"") | F44: =IFERROR((INDEX(HIST_D!$W$8:$W$2617,1)-INDEX(HIST_D!$W$8:$W$2617,Control!$F$7))*Control!$B$11,"") | G44: =IFERROR((INDEX(HIST_D!$W$8:$W$2617,1)-INDEX(HIST_D!$W$8:$W$2617,Control!$F$8))*Control!$B$11,"") | H44: =IFERROR((INDEX(HIST_D!$W$8:$W$2617,1)-INDEX(HIST_D!$W$8:$W$2617,Control!$F$9))*Control!$B$11,"") | I44: =IFERROR((INDEX(HIST_D!$W$8:$W$2617,1)-INDEX(HIST_D!$W$8:$W$2617,Control!$F$10))*Control!$B$11,"") | J44: =IFERROR((INDEX(HIST_D!$W$8:$W$2617,1)-INDEX(HIST_D!$W$8:$W$2617,Control!$F$16))*Control!$B$11,"") | K44: =IFERROR((INDEX(HIST_D!$W$8:$W$2617,1)-INDEX(HIST_D!$W$8:$W$2617,Control!$F$11))*Control!$B$11,"") | L44: =IFERROR(MIN(HIST_D!$W$8:INDEX(HIST_D!$W$8:$W$2617,Control!$F$11)),"") | M44: =IFERROR(MAX(HIST_D!$W$8:INDEX(HIST_D!$W$8:$W$2617,Control!$F$11)),"") | N44: =IFERROR(PERCENTRANK(HIST_D!$W$8:INDEX(HIST_D!$W$8:$W$2617,Control!$F$11),INDEX(HIST_D!$W$8:$W$2617,1)),"") | O44: =IFERROR(PERCENTRANK(HIST_D!$W$8:INDEX(HIST_D!$W$8:$W$2617,Control!$F$13),INDEX(HIST_D!$W$8:$W$2617,1)),"") | P44: =IFERROR(PERCENTRANK(HIST_D!$W$8:INDEX(HIST_D!$W$8:$W$2617,Control!$F$14),INDEX(HIST_D!$W$8:$W$2617,1)),"") | Q44: =IFERROR(PERCENTRANK(HIST_D!$W$8:INDEX(HIST_D!$W$8:$W$2617,Control!$F$15),INDEX(HIST_D!$W$8:$W$2617,1)),"") | S44: =IFERROR((INDEX(HIST_D!$W$8:$W$2617,1)-AVERAGE(HIST_D!$W$8:INDEX(HIST_D!$W$8:$W$2617,Control!$F$14)))/STDEV(HIST_D!$W$8:INDEX(HIST_D!$W$8:$W$2617,Control!$F$14)),"")
A45: TIPS real 10Y | B45: =Tickers!$C$28 | C45: % | D45: =INDEX(HIST_D!$X$8:$X$2617,1) | E45: =IFERROR((INDEX(HIST_D!$X$8:$X$2617,1)-INDEX(HIST_D!$X$8:$X$2617,Control!$F$6))*Control!$B$11,"") | F45: =IFERROR((INDEX(HIST_D!$X$8:$X$2617,1)-INDEX(HIST_D!$X$8:$X$2617,Control!$F$7))*Control!$B$11,"") | G45: =IFERROR((INDEX(HIST_D!$X$8:$X$2617,1)-INDEX(HIST_D!$X$8:$X$2617,Control!$F$8))*Control!$B$11,"") | H45: =IFERROR((INDEX(HIST_D!$X$8:$X$2617,1)-INDEX(HIST_D!$X$8:$X$2617,Control!$F$9))*Control!$B$11,"") | I45: =IFERROR((INDEX(HIST_D!$X$8:$X$2617,1)-INDEX(HIST_D!$X$8:$X$2617,Control!$F$10))*Control!$B$11,"") | J45: =IFERROR((INDEX(HIST_D!$X$8:$X$2617,1)-INDEX(HIST_D!$X$8:$X$2617,Control!$F$16))*Control!$B$11,"") | K45: =IFERROR((INDEX(HIST_D!$X$8:$X$2617,1)-INDEX(HIST_D!$X$8:$X$2617,Control!$F$11))*Control!$B$11,"") | L45: =IFERROR(MIN(HIST_D!$X$8:INDEX(HIST_D!$X$8:$X$2617,Control!$F$11)),"") | M45: =IFERROR(MAX(HIST_D!$X$8:INDEX(HIST_D!$X$8:$X$2617,Control!$F$11)),"") | N45: =IFERROR(PERCENTRANK(HIST_D!$X$8:INDEX(HIST_D!$X$8:$X$2617,Control!$F$11),INDEX(HIST_D!$X$8:$X$2617,1)),"") | O45: =IFERROR(PERCENTRANK(HIST_D!$X$8:INDEX(HIST_D!$X$8:$X$2617,Control!$F$13),INDEX(HIST_D!$X$8:$X$2617,1)),"") | P45: =IFERROR(PERCENTRANK(HIST_D!$X$8:INDEX(HIST_D!$X$8:$X$2617,Control!$F$14),INDEX(HIST_D!$X$8:$X$2617,1)),"") | Q45: =IFERROR(PERCENTRANK(HIST_D!$X$8:INDEX(HIST_D!$X$8:$X$2617,Control!$F$15),INDEX(HIST_D!$X$8:$X$2617,1)),"") | S45: =IFERROR((INDEX(HIST_D!$X$8:$X$2617,1)-AVERAGE(HIST_D!$X$8:INDEX(HIST_D!$X$8:$X$2617,Control!$F$14)))/STDEV(HIST_D!$X$8:INDEX(HIST_D!$X$8:$X$2617,Control!$F$14)),"")
A46: Breakeven 5Y | B46: =Tickers!$C$29 | C46: % | D46: =INDEX(HIST_D!$Y$8:$Y$2617,1) | E46: =IFERROR((INDEX(HIST_D!$Y$8:$Y$2617,1)-INDEX(HIST_D!$Y$8:$Y$2617,Control!$F$6))*Control!$B$11,"") | F46: =IFERROR((INDEX(HIST_D!$Y$8:$Y$2617,1)-INDEX(HIST_D!$Y$8:$Y$2617,Control!$F$7))*Control!$B$11,"") | G46: =IFERROR((INDEX(HIST_D!$Y$8:$Y$2617,1)-INDEX(HIST_D!$Y$8:$Y$2617,Control!$F$8))*Control!$B$11,"") | H46: =IFERROR((INDEX(HIST_D!$Y$8:$Y$2617,1)-INDEX(HIST_D!$Y$8:$Y$2617,Control!$F$9))*Control!$B$11,"") | I46: =IFERROR((INDEX(HIST_D!$Y$8:$Y$2617,1)-INDEX(HIST_D!$Y$8:$Y$2617,Control!$F$10))*Control!$B$11,"") | J46: =IFERROR((INDEX(HIST_D!$Y$8:$Y$2617,1)-INDEX(HIST_D!$Y$8:$Y$2617,Control!$F$16))*Control!$B$11,"") | K46: =IFERROR((INDEX(HIST_D!$Y$8:$Y$2617,1)-INDEX(HIST_D!$Y$8:$Y$2617,Control!$F$11))*Control!$B$11,"") | L46: =IFERROR(MIN(HIST_D!$Y$8:INDEX(HIST_D!$Y$8:$Y$2617,Control!$F$11)),"") | M46: =IFERROR(MAX(HIST_D!$Y$8:INDEX(HIST_D!$Y$8:$Y$2617,Control!$F$11)),"") | N46: =IFERROR(PERCENTRANK(HIST_D!$Y$8:INDEX(HIST_D!$Y$8:$Y$2617,Control!$F$11),INDEX(HIST_D!$Y$8:$Y$2617,1)),"") | O46: =IFERROR(PERCENTRANK(HIST_D!$Y$8:INDEX(HIST_D!$Y$8:$Y$2617,Control!$F$13),INDEX(HIST_D!$Y$8:$Y$2617,1)),"") | P46: =IFERROR(PERCENTRANK(HIST_D!$Y$8:INDEX(HIST_D!$Y$8:$Y$2617,Control!$F$14),INDEX(HIST_D!$Y$8:$Y$2617,1)),"") | Q46: =IFERROR(PERCENTRANK(HIST_D!$Y$8:INDEX(HIST_D!$Y$8:$Y$2617,Control!$F$15),INDEX(HIST_D!$Y$8:$Y$2617,1)),"") | S46: =IFERROR((INDEX(HIST_D!$Y$8:$Y$2617,1)-AVERAGE(HIST_D!$Y$8:INDEX(HIST_D!$Y$8:$Y$2617,Control!$F$14)))/STDEV(HIST_D!$Y$8:INDEX(HIST_D!$Y$8:$Y$2617,Control!$F$14)),"")
A47: Breakeven 10Y | B47: =Tickers!$C$30 | C47: % | D47: =INDEX(HIST_D!$Z$8:$Z$2617,1) | E47: =IFERROR((INDEX(HIST_D!$Z$8:$Z$2617,1)-INDEX(HIST_D!$Z$8:$Z$2617,Control!$F$6))*Control!$B$11,"") | F47: =IFERROR((INDEX(HIST_D!$Z$8:$Z$2617,1)-INDEX(HIST_D!$Z$8:$Z$2617,Control!$F$7))*Control!$B$11,"") | G47: =IFERROR((INDEX(HIST_D!$Z$8:$Z$2617,1)-INDEX(HIST_D!$Z$8:$Z$2617,Control!$F$8))*Control!$B$11,"") | H47: =IFERROR((INDEX(HIST_D!$Z$8:$Z$2617,1)-INDEX(HIST_D!$Z$8:$Z$2617,Control!$F$9))*Control!$B$11,"") | I47: =IFERROR((INDEX(HIST_D!$Z$8:$Z$2617,1)-INDEX(HIST_D!$Z$8:$Z$2617,Control!$F$10))*Control!$B$11,"") | J47: =IFERROR((INDEX(HIST_D!$Z$8:$Z$2617,1)-INDEX(HIST_D!$Z$8:$Z$2617,Control!$F$16))*Control!$B$11,"") | K47: =IFERROR((INDEX(HIST_D!$Z$8:$Z$2617,1)-INDEX(HIST_D!$Z$8:$Z$2617,Control!$F$11))*Control!$B$11,"") | L47: =IFERROR(MIN(HIST_D!$Z$8:INDEX(HIST_D!$Z$8:$Z$2617,Control!$F$11)),"") | M47: =IFERROR(MAX(HIST_D!$Z$8:INDEX(HIST_D!$Z$8:$Z$2617,Control!$F$11)),"") | N47: =IFERROR(PERCENTRANK(HIST_D!$Z$8:INDEX(HIST_D!$Z$8:$Z$2617,Control!$F$11),INDEX(HIST_D!$Z$8:$Z$2617,1)),"") | O47: =IFERROR(PERCENTRANK(HIST_D!$Z$8:INDEX(HIST_D!$Z$8:$Z$2617,Control!$F$13),INDEX(HIST_D!$Z$8:$Z$2617,1)),"") | P47: =IFERROR(PERCENTRANK(HIST_D!$Z$8:INDEX(HIST_D!$Z$8:$Z$2617,Control!$F$14),INDEX(HIST_D!$Z$8:$Z$2617,1)),"") | Q47: =IFERROR(PERCENTRANK(HIST_D!$Z$8:INDEX(HIST_D!$Z$8:$Z$2617,Control!$F$15),INDEX(HIST_D!$Z$8:$Z$2617,1)),"") | S47: =IFERROR((INDEX(HIST_D!$Z$8:$Z$2617,1)-AVERAGE(HIST_D!$Z$8:INDEX(HIST_D!$Z$8:$Z$2617,Control!$F$14)))/STDEV(HIST_D!$Z$8:INDEX(HIST_D!$Z$8:$Z$2617,Control!$F$14)),"")
A48: ACM term premium 10Y | B48: =Tickers!$C$31 | C48: % | D48: =INDEX(HIST_D!$AA$8:$AA$2617,1) | E48: =IFERROR((INDEX(HIST_D!$AA$8:$AA$2617,1)-INDEX(HIST_D!$AA$8:$AA$2617,Control!$F$6))*Control!$B$11,"") | F48: =IFERROR((INDEX(HIST_D!$AA$8:$AA$2617,1)-INDEX(HIST_D!$AA$8:$AA$2617,Control!$F$7))*Control!$B$11,"") | G48: =IFERROR((INDEX(HIST_D!$AA$8:$AA$2617,1)-INDEX(HIST_D!$AA$8:$AA$2617,Control!$F$8))*Control!$B$11,"") | H48: =IFERROR((INDEX(HIST_D!$AA$8:$AA$2617,1)-INDEX(HIST_D!$AA$8:$AA$2617,Control!$F$9))*Control!$B$11,"") | I48: =IFERROR((INDEX(HIST_D!$AA$8:$AA$2617,1)-INDEX(HIST_D!$AA$8:$AA$2617,Control!$F$10))*Control!$B$11,"") | J48: =IFERROR((INDEX(HIST_D!$AA$8:$AA$2617,1)-INDEX(HIST_D!$AA$8:$AA$2617,Control!$F$16))*Control!$B$11,"") | K48: =IFERROR((INDEX(HIST_D!$AA$8:$AA$2617,1)-INDEX(HIST_D!$AA$8:$AA$2617,Control!$F$11))*Control!$B$11,"") | L48: =IFERROR(MIN(HIST_D!$AA$8:INDEX(HIST_D!$AA$8:$AA$2617,Control!$F$11)),"") | M48: =IFERROR(MAX(HIST_D!$AA$8:INDEX(HIST_D!$AA$8:$AA$2617,Control!$F$11)),"") | N48: =IFERROR(PERCENTRANK(HIST_D!$AA$8:INDEX(HIST_D!$AA$8:$AA$2617,Control!$F$11),INDEX(HIST_D!$AA$8:$AA$2617,1)),"") | O48: =IFERROR(PERCENTRANK(HIST_D!$AA$8:INDEX(HIST_D!$AA$8:$AA$2617,Control!$F$13),INDEX(HIST_D!$AA$8:$AA$2617,1)),"") | P48: =IFERROR(PERCENTRANK(HIST_D!$AA$8:INDEX(HIST_D!$AA$8:$AA$2617,Control!$F$14),INDEX(HIST_D!$AA$8:$AA$2617,1)),"") | Q48: =IFERROR(PERCENTRANK(HIST_D!$AA$8:INDEX(HIST_D!$AA$8:$AA$2617,Control!$F$15),INDEX(HIST_D!$AA$8:$AA$2617,1)),"") | S48: =IFERROR((INDEX(HIST_D!$AA$8:$AA$2617,1)-AVERAGE(HIST_D!$AA$8:INDEX(HIST_D!$AA$8:$AA$2617,Control!$F$14)))/STDEV(HIST_D!$AA$8:INDEX(HIST_D!$AA$8:$AA$2617,Control!$F$14)),"")
A50: FORWARDS (bootstrapped from the spot par curve above)
A51: Forward | B51: Built from | C51: Level (%) | D51: Spot at the same tenor (%) | E51: Fwd − spot (bp) | F51: What it is telling you
A52: 1y1y | B52: UST 1Y & UST 2Y | C52: =IFERROR(((1+INDEX(HIST_D!$F$8:$F$2617,1)/100)^2/(1+INDEX(HIST_D!$E$8:$E$2617,1)/100)^1)^(1/1)*100-100,"") | D52: =INDEX(HIST_D!$F$8:$F$2617,1) | E52: =($C52-$D52)*Control!$B$11 | F52: where the market puts policy in 12–24 months
A53: 2y1y | B53: UST 2Y & UST 3Y | C53: =IFERROR(((1+INDEX(HIST_D!$G$8:$G$2617,1)/100)^3/(1+INDEX(HIST_D!$F$8:$F$2617,1)/100)^2)^(1/1)*100-100,"") | D53: =INDEX(HIST_D!$G$8:$G$2617,1) | E53: =($C53-$D53)*Control!$B$11 | F53: the third year of the path — usually the trough/terminal read
A54: 1y2y | B54: UST 1Y & UST 3Y | C54: =IFERROR(((1+INDEX(HIST_D!$G$8:$G$2617,1)/100)^3/(1+INDEX(HIST_D!$E$8:$E$2617,1)/100)^1)^(1/2)*100-100,"") | D54: =INDEX(HIST_D!$G$8:$G$2617,1) | E54: =($C54-$D54)*Control!$B$11 | F54: 2-year rate, one year forward
A55: 2y3y | B55: UST 2Y & UST 5Y | C55: =IFERROR(((1+INDEX(HIST_D!$H$8:$H$2617,1)/100)^5/(1+INDEX(HIST_D!$F$8:$F$2617,1)/100)^2)^(1/3)*100-100,"") | D55: =INDEX(HIST_D!$H$8:$H$2617,1) | E55: =($C55-$D55)*Control!$B$11 | F55: belly forward — the classic 2s5s carry trade reference
A56: 5y5y | B56: UST 5Y & UST 10Y | C56: =IFERROR(((1+INDEX(HIST_D!$J$8:$J$2617,1)/100)^10/(1+INDEX(HIST_D!$H$8:$H$2617,1)/100)^5)^(1/5)*100-100,"") | D56: =INDEX(HIST_D!$J$8:$J$2617,1) | E56: =($C56-$D56)*Control!$B$11 | F56: the market's long-run nominal anchor; compare with 2.0% + term premium
A57: 10y20y | B57: UST 10Y & UST 30Y | C57: =IFERROR(((1+INDEX(HIST_D!$L$8:$L$2617,1)/100)^30/(1+INDEX(HIST_D!$J$8:$J$2617,1)/100)^10)^(1/20)*100-100,"") | D57: =INDEX(HIST_D!$L$8:$L$2617,1) | E57: =($C57-$D57)*Control!$B$11 | F57: long-end forward; where duration buyers are being paid
A58: OIS 1y1y | B58: SOFR OIS 1Y & SOFR OIS 2Y | C58: =IFERROR(((1+INDEX(HIST_D!$N$8:$N$2617,1)/100)^2/(1+INDEX(HIST_D!$M$8:$M$2617,1)/100)^1)^(1/1)*100-100,"") | D58: =INDEX(HIST_D!$N$8:$N$2617,1) | E58: =($C58-$D58)*Control!$B$11 | F58: same as above without the cash-Treasury premium
A59: OIS 5y5y | B59: SOFR OIS 5Y & SOFR OIS 10Y | C59: =IFERROR(((1+INDEX(HIST_D!$S$8:$S$2617,1)/100)^10/(1+INDEX(HIST_D!$Q$8:$Q$2617,1)/100)^5)^(1/5)*100-100,"") | D59: =INDEX(HIST_D!$S$8:$S$2617,1) | E59: =($C59-$D59)*Control!$B$11 | F59: cleanest long-run policy anchor
A60: Par-yield compounding, not a zero-coupon bootstrap. Good to ~1–2bp for monitoring; do not price off it.
A62: CONSTRUCTION AUDIT — how the 4Y and 15Y nodes are built
A63: Node | B63: Linear interp of cash neighbours | C63: OIS at the tenor | D63: Linear interp of OIS neighbours | E63: Curvature adjustment (bp) | F63: Built level (%) | G63: Cross-check: OIS − built UST (bp)
A64: UST 4Y | B64: =(INDEX(HIST_D!$G$8:$G$2617,1)+INDEX(HIST_D!$H$8:$H$2617,1))/2 | C64: =INDEX(HIST_D!$P$8:$P$2617,1) | D64: =(INDEX(HIST_D!$O$8:$O$2617,1)+INDEX(HIST_D!$Q$8:$Q$2617,1))/2 | E64: =($C64-$D64)*Control!$B$11 | F64: =INDEX(HIST_D!$AR$8:$AR$2617,1) | G64: =($C64-$F64)*Control!$B$11
A65: UST 15Y | B65: =(INDEX(HIST_D!$J$8:$J$2617,1)+INDEX(HIST_D!$K$8:$K$2617,1))/2 | C65: =INDEX(HIST_D!$T$8:$T$2617,1) | D65: =(INDEX(HIST_D!$S$8:$S$2617,1)+INDEX(HIST_D!$U$8:$U$2617,1))/2 | E65: =($C65-$D65)*Control!$B$11 | F65: =INDEX(HIST_D!$AS$8:$AS$2617,1) | G65: =($C65-$F65)*Control!$B$11
A66: Built level = linear interpolation of the neighbouring cash nodes PLUS the curvature the OIS curve actually shows at that tenor. A straight line would understate the belly at 4Y and overstate it at 15Y. If you would rather trade an actual bond there, use the off-the-run comparators on the Nodes tab — those are quoted securities.

Sheet Slopes
A1: CURVE SHAPE — slopes, flies, swap spreads
A2: All stored in bp on HIST_D, so the percentiles and z-scores below are percentiles of the SPREAD itself, not of its legs.
A4: SLOPES
A5: Instrument | B5: Source | C5: Unit | D5: Level | E5: 1D | F5: 1W | G5: 1M | H5: 3M | I5: 6M | J5: YTD | K5: 1Y | L5: 1y min | M5: 1y max | N5: %ile 1y | O5: %ile 3y | P5: %ile 5y | Q5: %ile 10y | R5: %ile 25y | S5: z (5y)
A6: 3m10y | B6: derived on HIST_D | C6: bp | D6: =INDEX(HIST_D!$AT$8:$AT$2617,1) | E6: =IFERROR((INDEX(HIST_D!$AT$8:$AT$2617,1)-INDEX(HIST_D!$AT$8:$AT$2617,Control!$F$6))*1,"") | F6: =IFERROR((INDEX(HIST_D!$AT$8:$AT$2617,1)-INDEX(HIST_D!$AT$8:$AT$2617,Control!$F$7))*1,"") | G6: =IFERROR((INDEX(HIST_D!$AT$8:$AT$2617,1)-INDEX(HIST_D!$AT$8:$AT$2617,Control!$F$8))*1,"") | H6: =IFERROR((INDEX(HIST_D!$AT$8:$AT$2617,1)-INDEX(HIST_D!$AT$8:$AT$2617,Control!$F$9))*1,"") | I6: =IFERROR((INDEX(HIST_D!$AT$8:$AT$2617,1)-INDEX(HIST_D!$AT$8:$AT$2617,Control!$F$10))*1,"") | J6: =IFERROR((INDEX(HIST_D!$AT$8:$AT$2617,1)-INDEX(HIST_D!$AT$8:$AT$2617,Control!$F$16))*1,"") | K6: =IFERROR((INDEX(HIST_D!$AT$8:$AT$2617,1)-INDEX(HIST_D!$AT$8:$AT$2617,Control!$F$11))*1,"") | L6: =IFERROR(MIN(HIST_D!$AT$8:INDEX(HIST_D!$AT$8:$AT$2617,Control!$F$11)),"") | M6: =IFERROR(MAX(HIST_D!$AT$8:INDEX(HIST_D!$AT$8:$AT$2617,Control!$F$11)),"") | N6: =IFERROR(PERCENTRANK(HIST_D!$AT$8:INDEX(HIST_D!$AT$8:$AT$2617,Control!$F$11),INDEX(HIST_D!$AT$8:$AT$2617,1)),"") | O6: =IFERROR(PERCENTRANK(HIST_D!$AT$8:INDEX(HIST_D!$AT$8:$AT$2617,Control!$F$13),INDEX(HIST_D!$AT$8:$AT$2617,1)),"") | P6: =IFERROR(PERCENTRANK(HIST_D!$AT$8:INDEX(HIST_D!$AT$8:$AT$2617,Control!$F$14),INDEX(HIST_D!$AT$8:$AT$2617,1)),"") | Q6: =IFERROR(PERCENTRANK(HIST_D!$AT$8:INDEX(HIST_D!$AT$8:$AT$2617,Control!$F$15),INDEX(HIST_D!$AT$8:$AT$2617,1)),"") | S6: =IFERROR((INDEX(HIST_D!$AT$8:$AT$2617,1)-AVERAGE(HIST_D!$AT$8:INDEX(HIST_D!$AT$8:$AT$2617,Control!$F$14)))/STDEV(HIST_D!$AT$8:INDEX(HIST_D!$AT$8:$AT$2617,Control!$F$14)),"")
A7: 2s5s | B7: derived on HIST_D | C7: bp | D7: =INDEX(HIST_D!$AU$8:$AU$2617,1) | E7: =IFERROR((INDEX(HIST_D!$AU$8:$AU$2617,1)-INDEX(HIST_D!$AU$8:$AU$2617,Control!$F$6))*1,"") | F7: =IFERROR((INDEX(HIST_D!$AU$8:$AU$2617,1)-INDEX(HIST_D!$AU$8:$AU$2617,Control!$F$7))*1,"") | G7: =IFERROR((INDEX(HIST_D!$AU$8:$AU$2617,1)-INDEX(HIST_D!$AU$8:$AU$2617,Control!$F$8))*1,"") | H7: =IFERROR((INDEX(HIST_D!$AU$8:$AU$2617,1)-INDEX(HIST_D!$AU$8:$AU$2617,Control!$F$9))*1,"") | I7: =IFERROR((INDEX(HIST_D!$AU$8:$AU$2617,1)-INDEX(HIST_D!$AU$8:$AU$2617,Control!$F$10))*1,"") | J7: =IFERROR((INDEX(HIST_D!$AU$8:$AU$2617,1)-INDEX(HIST_D!$AU$8:$AU$2617,Control!$F$16))*1,"") | K7: =IFERROR((INDEX(HIST_D!$AU$8:$AU$2617,1)-INDEX(HIST_D!$AU$8:$AU$2617,Control!$F$11))*1,"") | L7: =IFERROR(MIN(HIST_D!$AU$8:INDEX(HIST_D!$AU$8:$AU$2617,Control!$F$11)),"") | M7: =IFERROR(MAX(HIST_D!$AU$8:INDEX(HIST_D!$AU$8:$AU$2617,Control!$F$11)),"") | N7: =IFERROR(PERCENTRANK(HIST_D!$AU$8:INDEX(HIST_D!$AU$8:$AU$2617,Control!$F$11),INDEX(HIST_D!$AU$8:$AU$2617,1)),"") | O7: =IFERROR(PERCENTRANK(HIST_D!$AU$8:INDEX(HIST_D!$AU$8:$AU$2617,Control!$F$13),INDEX(HIST_D!$AU$8:$AU$2617,1)),"") | P7: =IFERROR(PERCENTRANK(HIST_D!$AU$8:INDEX(HIST_D!$AU$8:$AU$2617,Control!$F$14),INDEX(HIST_D!$AU$8:$AU$2617,1)),"") | Q7: =IFERROR(PERCENTRANK(HIST_D!$AU$8:INDEX(HIST_D!$AU$8:$AU$2617,Control!$F$15),INDEX(HIST_D!$AU$8:$AU$2617,1)),"") | S7: =IFERROR((INDEX(HIST_D!$AU$8:$AU$2617,1)-AVERAGE(HIST_D!$AU$8:INDEX(HIST_D!$AU$8:$AU$2617,Control!$F$14)))/STDEV(HIST_D!$AU$8:INDEX(HIST_D!$AU$8:$AU$2617,Control!$F$14)),"")
A8: 2s10s | B8: derived on HIST_D | C8: bp | D8: =INDEX(HIST_D!$AV$8:$AV$2617,1) | E8: =IFERROR((INDEX(HIST_D!$AV$8:$AV$2617,1)-INDEX(HIST_D!$AV$8:$AV$2617,Control!$F$6))*1,"") | F8: =IFERROR((INDEX(HIST_D!$AV$8:$AV$2617,1)-INDEX(HIST_D!$AV$8:$AV$2617,Control!$F$7))*1,"") | G8: =IFERROR((INDEX(HIST_D!$AV$8:$AV$2617,1)-INDEX(HIST_D!$AV$8:$AV$2617,Control!$F$8))*1,"") | H8: =IFERROR((INDEX(HIST_D!$AV$8:$AV$2617,1)-INDEX(HIST_D!$AV$8:$AV$2617,Control!$F$9))*1,"") | I8: =IFERROR((INDEX(HIST_D!$AV$8:$AV$2617,1)-INDEX(HIST_D!$AV$8:$AV$2617,Control!$F$10))*1,"") | J8: =IFERROR((INDEX(HIST_D!$AV$8:$AV$2617,1)-INDEX(HIST_D!$AV$8:$AV$2617,Control!$F$16))*1,"") | K8: =IFERROR((INDEX(HIST_D!$AV$8:$AV$2617,1)-INDEX(HIST_D!$AV$8:$AV$2617,Control!$F$11))*1,"") | L8: =IFERROR(MIN(HIST_D!$AV$8:INDEX(HIST_D!$AV$8:$AV$2617,Control!$F$11)),"") | M8: =IFERROR(MAX(HIST_D!$AV$8:INDEX(HIST_D!$AV$8:$AV$2617,Control!$F$11)),"") | N8: =IFERROR(PERCENTRANK(HIST_D!$AV$8:INDEX(HIST_D!$AV$8:$AV$2617,Control!$F$11),INDEX(HIST_D!$AV$8:$AV$2617,1)),"") | O8: =IFERROR(PERCENTRANK(HIST_D!$AV$8:INDEX(HIST_D!$AV$8:$AV$2617,Control!$F$13),INDEX(HIST_D!$AV$8:$AV$2617,1)),"") | P8: =IFERROR(PERCENTRANK(HIST_D!$AV$8:INDEX(HIST_D!$AV$8:$AV$2617,Control!$F$14),INDEX(HIST_D!$AV$8:$AV$2617,1)),"") | Q8: =IFERROR(PERCENTRANK(HIST_D!$AV$8:INDEX(HIST_D!$AV$8:$AV$2617,Control!$F$15),INDEX(HIST_D!$AV$8:$AV$2617,1)),"") | R8: =IFERROR(PERCENTRANK(HIST_M!$J$8:$J$308,INDEX(HIST_D!$AV$8:$AV$2617,1)),"") | S8: =IFERROR((INDEX(HIST_D!$AV$8:$AV$2617,1)-AVERAGE(HIST_D!$AV$8:INDEX(HIST_D!$AV$8:$AV$2617,Control!$F$14)))/STDEV(HIST_D!$AV$8:INDEX(HIST_D!$AV$8:$AV$2617,Control!$F$14)),"")
A9: 2s30s | B9: derived on HIST_D | C9: bp | D9: =INDEX(HIST_D!$AW$8:$AW$2617,1) | E9: =IFERROR((INDEX(HIST_D!$AW$8:$AW$2617,1)-INDEX(HIST_D!$AW$8:$AW$2617,Control!$F$6))*1,"") | F9: =IFERROR((INDEX(HIST_D!$AW$8:$AW$2617,1)-INDEX(HIST_D!$AW$8:$AW$2617,Control!$F$7))*1,"") | G9: =IFERROR((INDEX(HIST_D!$AW$8:$AW$2617,1)-INDEX(HIST_D!$AW$8:$AW$2617,Control!$F$8))*1,"") | H9: =IFERROR((INDEX(HIST_D!$AW$8:$AW$2617,1)-INDEX(HIST_D!$AW$8:$AW$2617,Control!$F$9))*1,"") | I9: =IFERROR((INDEX(HIST_D!$AW$8:$AW$2617,1)-INDEX(HIST_D!$AW$8:$AW$2617,Control!$F$10))*1,"") | J9: =IFERROR((INDEX(HIST_D!$AW$8:$AW$2617,1)-INDEX(HIST_D!$AW$8:$AW$2617,Control!$F$16))*1,"") | K9: =IFERROR((INDEX(HIST_D!$AW$8:$AW$2617,1)-INDEX(HIST_D!$AW$8:$AW$2617,Control!$F$11))*1,"") | L9: =IFERROR(MIN(HIST_D!$AW$8:INDEX(HIST_D!$AW$8:$AW$2617,Control!$F$11)),"") | M9: =IFERROR(MAX(HIST_D!$AW$8:INDEX(HIST_D!$AW$8:$AW$2617,Control!$F$11)),"") | N9: =IFERROR(PERCENTRANK(HIST_D!$AW$8:INDEX(HIST_D!$AW$8:$AW$2617,Control!$F$11),INDEX(HIST_D!$AW$8:$AW$2617,1)),"") | O9: =IFERROR(PERCENTRANK(HIST_D!$AW$8:INDEX(HIST_D!$AW$8:$AW$2617,Control!$F$13),INDEX(HIST_D!$AW$8:$AW$2617,1)),"") | P9: =IFERROR(PERCENTRANK(HIST_D!$AW$8:INDEX(HIST_D!$AW$8:$AW$2617,Control!$F$14),INDEX(HIST_D!$AW$8:$AW$2617,1)),"") | Q9: =IFERROR(PERCENTRANK(HIST_D!$AW$8:INDEX(HIST_D!$AW$8:$AW$2617,Control!$F$15),INDEX(HIST_D!$AW$8:$AW$2617,1)),"") | R9: =IFERROR(PERCENTRANK(HIST_M!$K$8:$K$308,INDEX(HIST_D!$AW$8:$AW$2617,1)),"") | S9: =IFERROR((INDEX(HIST_D!$AW$8:$AW$2617,1)-AVERAGE(HIST_D!$AW$8:INDEX(HIST_D!$AW$8:$AW$2617,Control!$F$14)))/STDEV(HIST_D!$AW$8:INDEX(HIST_D!$AW$8:$AW$2617,Control!$F$14)),"")
A10: 5s10s | B10: derived on HIST_D | C10: bp | D10: =INDEX(HIST_D!$AX$8:$AX$2617,1) | E10: =IFERROR((INDEX(HIST_D!$AX$8:$AX$2617,1)-INDEX(HIST_D!$AX$8:$AX$2617,Control!$F$6))*1,"") | F10: =IFERROR((INDEX(HIST_D!$AX$8:$AX$2617,1)-INDEX(HIST_D!$AX$8:$AX$2617,Control!$F$7))*1,"") | G10: =IFERROR((INDEX(HIST_D!$AX$8:$AX$2617,1)-INDEX(HIST_D!$AX$8:$AX$2617,Control!$F$8))*1,"") | H10: =IFERROR((INDEX(HIST_D!$AX$8:$AX$2617,1)-INDEX(HIST_D!$AX$8:$AX$2617,Control!$F$9))*1,"") | I10: =IFERROR((INDEX(HIST_D!$AX$8:$AX$2617,1)-INDEX(HIST_D!$AX$8:$AX$2617,Control!$F$10))*1,"") | J10: =IFERROR((INDEX(HIST_D!$AX$8:$AX$2617,1)-INDEX(HIST_D!$AX$8:$AX$2617,Control!$F$16))*1,"") | K10: =IFERROR((INDEX(HIST_D!$AX$8:$AX$2617,1)-INDEX(HIST_D!$AX$8:$AX$2617,Control!$F$11))*1,"") | L10: =IFERROR(MIN(HIST_D!$AX$8:INDEX(HIST_D!$AX$8:$AX$2617,Control!$F$11)),"") | M10: =IFERROR(MAX(HIST_D!$AX$8:INDEX(HIST_D!$AX$8:$AX$2617,Control!$F$11)),"") | N10: =IFERROR(PERCENTRANK(HIST_D!$AX$8:INDEX(HIST_D!$AX$8:$AX$2617,Control!$F$11),INDEX(HIST_D!$AX$8:$AX$2617,1)),"") | O10: =IFERROR(PERCENTRANK(HIST_D!$AX$8:INDEX(HIST_D!$AX$8:$AX$2617,Control!$F$13),INDEX(HIST_D!$AX$8:$AX$2617,1)),"") | P10: =IFERROR(PERCENTRANK(HIST_D!$AX$8:INDEX(HIST_D!$AX$8:$AX$2617,Control!$F$14),INDEX(HIST_D!$AX$8:$AX$2617,1)),"") | Q10: =IFERROR(PERCENTRANK(HIST_D!$AX$8:INDEX(HIST_D!$AX$8:$AX$2617,Control!$F$15),INDEX(HIST_D!$AX$8:$AX$2617,1)),"") | S10: =IFERROR((INDEX(HIST_D!$AX$8:$AX$2617,1)-AVERAGE(HIST_D!$AX$8:INDEX(HIST_D!$AX$8:$AX$2617,Control!$F$14)))/STDEV(HIST_D!$AX$8:INDEX(HIST_D!$AX$8:$AX$2617,Control!$F$14)),"")
A11: 5s30s | B11: derived on HIST_D | C11: bp | D11: =INDEX(HIST_D!$AY$8:$AY$2617,1) | E11: =IFERROR((INDEX(HIST_D!$AY$8:$AY$2617,1)-INDEX(HIST_D!$AY$8:$AY$2617,Control!$F$6))*1,"") | F11: =IFERROR((INDEX(HIST_D!$AY$8:$AY$2617,1)-INDEX(HIST_D!$AY$8:$AY$2617,Control!$F$7))*1,"") | G11: =IFERROR((INDEX(HIST_D!$AY$8:$AY$2617,1)-INDEX(HIST_D!$AY$8:$AY$2617,Control!$F$8))*1,"") | H11: =IFERROR((INDEX(HIST_D!$AY$8:$AY$2617,1)-INDEX(HIST_D!$AY$8:$AY$2617,Control!$F$9))*1,"") | I11: =IFERROR((INDEX(HIST_D!$AY$8:$AY$2617,1)-INDEX(HIST_D!$AY$8:$AY$2617,Control!$F$10))*1,"") | J11: =IFERROR((INDEX(HIST_D!$AY$8:$AY$2617,1)-INDEX(HIST_D!$AY$8:$AY$2617,Control!$F$16))*1,"") | K11: =IFERROR((INDEX(HIST_D!$AY$8:$AY$2617,1)-INDEX(HIST_D!$AY$8:$AY$2617,Control!$F$11))*1,"") | L11: =IFERROR(MIN(HIST_D!$AY$8:INDEX(HIST_D!$AY$8:$AY$2617,Control!$F$11)),"") | M11: =IFERROR(MAX(HIST_D!$AY$8:INDEX(HIST_D!$AY$8:$AY$2617,Control!$F$11)),"") | N11: =IFERROR(PERCENTRANK(HIST_D!$AY$8:INDEX(HIST_D!$AY$8:$AY$2617,Control!$F$11),INDEX(HIST_D!$AY$8:$AY$2617,1)),"") | O11: =IFERROR(PERCENTRANK(HIST_D!$AY$8:INDEX(HIST_D!$AY$8:$AY$2617,Control!$F$13),INDEX(HIST_D!$AY$8:$AY$2617,1)),"") | P11: =IFERROR(PERCENTRANK(HIST_D!$AY$8:INDEX(HIST_D!$AY$8:$AY$2617,Control!$F$14),INDEX(HIST_D!$AY$8:$AY$2617,1)),"") | Q11: =IFERROR(PERCENTRANK(HIST_D!$AY$8:INDEX(HIST_D!$AY$8:$AY$2617,Control!$F$15),INDEX(HIST_D!$AY$8:$AY$2617,1)),"") | R11: =IFERROR(PERCENTRANK(HIST_M!$L$8:$L$308,INDEX(HIST_D!$AY$8:$AY$2617,1)),"") | S11: =IFERROR((INDEX(HIST_D!$AY$8:$AY$2617,1)-AVERAGE(HIST_D!$AY$8:INDEX(HIST_D!$AY$8:$AY$2617,Control!$F$14)))/STDEV(HIST_D!$AY$8:INDEX(HIST_D!$AY$8:$AY$2617,Control!$F$14)),"")
A12: 10s30s | B12: derived on HIST_D | C12: bp | D12: =INDEX(HIST_D!$AZ$8:$AZ$2617,1) | E12: =IFERROR((INDEX(HIST_D!$AZ$8:$AZ$2617,1)-INDEX(HIST_D!$AZ$8:$AZ$2617,Control!$F$6))*1,"") | F12: =IFERROR((INDEX(HIST_D!$AZ$8:$AZ$2617,1)-INDEX(HIST_D!$AZ$8:$AZ$2617,Control!$F$7))*1,"") | G12: =IFERROR((INDEX(HIST_D!$AZ$8:$AZ$2617,1)-INDEX(HIST_D!$AZ$8:$AZ$2617,Control!$F$8))*1,"") | H12: =IFERROR((INDEX(HIST_D!$AZ$8:$AZ$2617,1)-INDEX(HIST_D!$AZ$8:$AZ$2617,Control!$F$9))*1,"") | I12: =IFERROR((INDEX(HIST_D!$AZ$8:$AZ$2617,1)-INDEX(HIST_D!$AZ$8:$AZ$2617,Control!$F$10))*1,"") | J12: =IFERROR((INDEX(HIST_D!$AZ$8:$AZ$2617,1)-INDEX(HIST_D!$AZ$8:$AZ$2617,Control!$F$16))*1,"") | K12: =IFERROR((INDEX(HIST_D!$AZ$8:$AZ$2617,1)-INDEX(HIST_D!$AZ$8:$AZ$2617,Control!$F$11))*1,"") | L12: =IFERROR(MIN(HIST_D!$AZ$8:INDEX(HIST_D!$AZ$8:$AZ$2617,Control!$F$11)),"") | M12: =IFERROR(MAX(HIST_D!$AZ$8:INDEX(HIST_D!$AZ$8:$AZ$2617,Control!$F$11)),"") | N12: =IFERROR(PERCENTRANK(HIST_D!$AZ$8:INDEX(HIST_D!$AZ$8:$AZ$2617,Control!$F$11),INDEX(HIST_D!$AZ$8:$AZ$2617,1)),"") | O12: =IFERROR(PERCENTRANK(HIST_D!$AZ$8:INDEX(HIST_D!$AZ$8:$AZ$2617,Control!$F$13),INDEX(HIST_D!$AZ$8:$AZ$2617,1)),"") | P12: =IFERROR(PERCENTRANK(HIST_D!$AZ$8:INDEX(HIST_D!$AZ$8:$AZ$2617,Control!$F$14),INDEX(HIST_D!$AZ$8:$AZ$2617,1)),"") | Q12: =IFERROR(PERCENTRANK(HIST_D!$AZ$8:INDEX(HIST_D!$AZ$8:$AZ$2617,Control!$F$15),INDEX(HIST_D!$AZ$8:$AZ$2617,1)),"") | R12: =IFERROR(PERCENTRANK(HIST_M!$M$8:$M$308,INDEX(HIST_D!$AZ$8:$AZ$2617,1)),"") | S12: =IFERROR((INDEX(HIST_D!$AZ$8:$AZ$2617,1)-AVERAGE(HIST_D!$AZ$8:INDEX(HIST_D!$AZ$8:$AZ$2617,Control!$F$14)))/STDEV(HIST_D!$AZ$8:INDEX(HIST_D!$AZ$8:$AZ$2617,Control!$F$14)),"")
A14: BUTTERFLIES (2 × belly − wings; positive = belly cheap)
A15: Instrument | B15: Source | C15: Unit | D15: Level | E15: 1D | F15: 1W | G15: 1M | H15: 3M | I15: 6M | J15: YTD | K15: 1Y | L15: 1y min | M15: 1y max | N15: %ile 1y | O15: %ile 3y | P15: %ile 5y | Q15: %ile 10y | R15: %ile 25y | S15: z (5y)
A16: 2s5s10s | B16: derived on HIST_D | C16: bp | D16: =INDEX(HIST_D!$BA$8:$BA$2617,1) | E16: =IFERROR((INDEX(HIST_D!$BA$8:$BA$2617,1)-INDEX(HIST_D!$BA$8:$BA$2617,Control!$F$6))*1,"") | F16: =IFERROR((INDEX(HIST_D!$BA$8:$BA$2617,1)-INDEX(HIST_D!$BA$8:$BA$2617,Control!$F$7))*1,"") | G16: =IFERROR((INDEX(HIST_D!$BA$8:$BA$2617,1)-INDEX(HIST_D!$BA$8:$BA$2617,Control!$F$8))*1,"") | H16: =IFERROR((INDEX(HIST_D!$BA$8:$BA$2617,1)-INDEX(HIST_D!$BA$8:$BA$2617,Control!$F$9))*1,"") | I16: =IFERROR((INDEX(HIST_D!$BA$8:$BA$2617,1)-INDEX(HIST_D!$BA$8:$BA$2617,Control!$F$10))*1,"") | J16: =IFERROR((INDEX(HIST_D!$BA$8:$BA$2617,1)-INDEX(HIST_D!$BA$8:$BA$2617,Control!$F$16))*1,"") | K16: =IFERROR((INDEX(HIST_D!$BA$8:$BA$2617,1)-INDEX(HIST_D!$BA$8:$BA$2617,Control!$F$11))*1,"") | L16: =IFERROR(MIN(HIST_D!$BA$8:INDEX(HIST_D!$BA$8:$BA$2617,Control!$F$11)),"") | M16: =IFERROR(MAX(HIST_D!$BA$8:INDEX(HIST_D!$BA$8:$BA$2617,Control!$F$11)),"") | N16: =IFERROR(PERCENTRANK(HIST_D!$BA$8:INDEX(HIST_D!$BA$8:$BA$2617,Control!$F$11),INDEX(HIST_D!$BA$8:$BA$2617,1)),"") | O16: =IFERROR(PERCENTRANK(HIST_D!$BA$8:INDEX(HIST_D!$BA$8:$BA$2617,Control!$F$13),INDEX(HIST_D!$BA$8:$BA$2617,1)),"") | P16: =IFERROR(PERCENTRANK(HIST_D!$BA$8:INDEX(HIST_D!$BA$8:$BA$2617,Control!$F$14),INDEX(HIST_D!$BA$8:$BA$2617,1)),"") | Q16: =IFERROR(PERCENTRANK(HIST_D!$BA$8:INDEX(HIST_D!$BA$8:$BA$2617,Control!$F$15),INDEX(HIST_D!$BA$8:$BA$2617,1)),"") | S16: =IFERROR((INDEX(HIST_D!$BA$8:$BA$2617,1)-AVERAGE(HIST_D!$BA$8:INDEX(HIST_D!$BA$8:$BA$2617,Control!$F$14)))/STDEV(HIST_D!$BA$8:INDEX(HIST_D!$BA$8:$BA$2617,Control!$F$14)),"")
A17: 5s10s30s | B17: derived on HIST_D | C17: bp | D17: =INDEX(HIST_D!$BB$8:$BB$2617,1) | E17: =IFERROR((INDEX(HIST_D!$BB$8:$BB$2617,1)-INDEX(HIST_D!$BB$8:$BB$2617,Control!$F$6))*1,"") | F17: =IFERROR((INDEX(HIST_D!$BB$8:$BB$2617,1)-INDEX(HIST_D!$BB$8:$BB$2617,Control!$F$7))*1,"") | G17: =IFERROR((INDEX(HIST_D!$BB$8:$BB$2617,1)-INDEX(HIST_D!$BB$8:$BB$2617,Control!$F$8))*1,"") | H17: =IFERROR((INDEX(HIST_D!$BB$8:$BB$2617,1)-INDEX(HIST_D!$BB$8:$BB$2617,Control!$F$9))*1,"") | I17: =IFERROR((INDEX(HIST_D!$BB$8:$BB$2617,1)-INDEX(HIST_D!$BB$8:$BB$2617,Control!$F$10))*1,"") | J17: =IFERROR((INDEX(HIST_D!$BB$8:$BB$2617,1)-INDEX(HIST_D!$BB$8:$BB$2617,Control!$F$16))*1,"") | K17: =IFERROR((INDEX(HIST_D!$BB$8:$BB$2617,1)-INDEX(HIST_D!$BB$8:$BB$2617,Control!$F$11))*1,"") | L17: =IFERROR(MIN(HIST_D!$BB$8:INDEX(HIST_D!$BB$8:$BB$2617,Control!$F$11)),"") | M17: =IFERROR(MAX(HIST_D!$BB$8:INDEX(HIST_D!$BB$8:$BB$2617,Control!$F$11)),"") | N17: =IFERROR(PERCENTRANK(HIST_D!$BB$8:INDEX(HIST_D!$BB$8:$BB$2617,Control!$F$11),INDEX(HIST_D!$BB$8:$BB$2617,1)),"") | O17: =IFERROR(PERCENTRANK(HIST_D!$BB$8:INDEX(HIST_D!$BB$8:$BB$2617,Control!$F$13),INDEX(HIST_D!$BB$8:$BB$2617,1)),"") | P17: =IFERROR(PERCENTRANK(HIST_D!$BB$8:INDEX(HIST_D!$BB$8:$BB$2617,Control!$F$14),INDEX(HIST_D!$BB$8:$BB$2617,1)),"") | Q17: =IFERROR(PERCENTRANK(HIST_D!$BB$8:INDEX(HIST_D!$BB$8:$BB$2617,Control!$F$15),INDEX(HIST_D!$BB$8:$BB$2617,1)),"") | S17: =IFERROR((INDEX(HIST_D!$BB$8:$BB$2617,1)-AVERAGE(HIST_D!$BB$8:INDEX(HIST_D!$BB$8:$BB$2617,Control!$F$14)))/STDEV(HIST_D!$BB$8:INDEX(HIST_D!$BB$8:$BB$2617,Control!$F$14)),"")
A19: SWAP SPREADS
A20: Instrument | B20: Source | C20: Unit | D20: Level | E20: 1D | F20: 1W | G20: 1M | H20: 3M | I20: 6M | J20: YTD | K20: 1Y | L20: 1y min | M20: 1y max | N20: %ile 1y | O20: %ile 3y | P20: %ile 5y | Q20: %ile 10y | R20: %ile 25y | S20: z (5y)
A21: Swap spread 2Y | B21: derived on HIST_D | C21: bp | D21: =INDEX(HIST_D!$BC$8:$BC$2617,1) | E21: =IFERROR((INDEX(HIST_D!$BC$8:$BC$2617,1)-INDEX(HIST_D!$BC$8:$BC$2617,Control!$F$6))*1,"") | F21: =IFERROR((INDEX(HIST_D!$BC$8:$BC$2617,1)-INDEX(HIST_D!$BC$8:$BC$2617,Control!$F$7))*1,"") | G21: =IFERROR((INDEX(HIST_D!$BC$8:$BC$2617,1)-INDEX(HIST_D!$BC$8:$BC$2617,Control!$F$8))*1,"") | H21: =IFERROR((INDEX(HIST_D!$BC$8:$BC$2617,1)-INDEX(HIST_D!$BC$8:$BC$2617,Control!$F$9))*1,"") | I21: =IFERROR((INDEX(HIST_D!$BC$8:$BC$2617,1)-INDEX(HIST_D!$BC$8:$BC$2617,Control!$F$10))*1,"") | J21: =IFERROR((INDEX(HIST_D!$BC$8:$BC$2617,1)-INDEX(HIST_D!$BC$8:$BC$2617,Control!$F$16))*1,"") | K21: =IFERROR((INDEX(HIST_D!$BC$8:$BC$2617,1)-INDEX(HIST_D!$BC$8:$BC$2617,Control!$F$11))*1,"") | L21: =IFERROR(MIN(HIST_D!$BC$8:INDEX(HIST_D!$BC$8:$BC$2617,Control!$F$11)),"") | M21: =IFERROR(MAX(HIST_D!$BC$8:INDEX(HIST_D!$BC$8:$BC$2617,Control!$F$11)),"") | N21: =IFERROR(PERCENTRANK(HIST_D!$BC$8:INDEX(HIST_D!$BC$8:$BC$2617,Control!$F$11),INDEX(HIST_D!$BC$8:$BC$2617,1)),"") | O21: =IFERROR(PERCENTRANK(HIST_D!$BC$8:INDEX(HIST_D!$BC$8:$BC$2617,Control!$F$13),INDEX(HIST_D!$BC$8:$BC$2617,1)),"") | P21: =IFERROR(PERCENTRANK(HIST_D!$BC$8:INDEX(HIST_D!$BC$8:$BC$2617,Control!$F$14),INDEX(HIST_D!$BC$8:$BC$2617,1)),"") | Q21: =IFERROR(PERCENTRANK(HIST_D!$BC$8:INDEX(HIST_D!$BC$8:$BC$2617,Control!$F$15),INDEX(HIST_D!$BC$8:$BC$2617,1)),"") | S21: =IFERROR((INDEX(HIST_D!$BC$8:$BC$2617,1)-AVERAGE(HIST_D!$BC$8:INDEX(HIST_D!$BC$8:$BC$2617,Control!$F$14)))/STDEV(HIST_D!$BC$8:INDEX(HIST_D!$BC$8:$BC$2617,Control!$F$14)),"")
A22: Swap spread 5Y | B22: derived on HIST_D | C22: bp | D22: =INDEX(HIST_D!$BD$8:$BD$2617,1) | E22: =IFERROR((INDEX(HIST_D!$BD$8:$BD$2617,1)-INDEX(HIST_D!$BD$8:$BD$2617,Control!$F$6))*1,"") | F22: =IFERROR((INDEX(HIST_D!$BD$8:$BD$2617,1)-INDEX(HIST_D!$BD$8:$BD$2617,Control!$F$7))*1,"") | G22: =IFERROR((INDEX(HIST_D!$BD$8:$BD$2617,1)-INDEX(HIST_D!$BD$8:$BD$2617,Control!$F$8))*1,"") | H22: =IFERROR((INDEX(HIST_D!$BD$8:$BD$2617,1)-INDEX(HIST_D!$BD$8:$BD$2617,Control!$F$9))*1,"") | I22: =IFERROR((INDEX(HIST_D!$BD$8:$BD$2617,1)-INDEX(HIST_D!$BD$8:$BD$2617,Control!$F$10))*1,"") | J22: =IFERROR((INDEX(HIST_D!$BD$8:$BD$2617,1)-INDEX(HIST_D!$BD$8:$BD$2617,Control!$F$16))*1,"") | K22: =IFERROR((INDEX(HIST_D!$BD$8:$BD$2617,1)-INDEX(HIST_D!$BD$8:$BD$2617,Control!$F$11))*1,"") | L22: =IFERROR(MIN(HIST_D!$BD$8:INDEX(HIST_D!$BD$8:$BD$2617,Control!$F$11)),"") | M22: =IFERROR(MAX(HIST_D!$BD$8:INDEX(HIST_D!$BD$8:$BD$2617,Control!$F$11)),"") | N22: =IFERROR(PERCENTRANK(HIST_D!$BD$8:INDEX(HIST_D!$BD$8:$BD$2617,Control!$F$11),INDEX(HIST_D!$BD$8:$BD$2617,1)),"") | O22: =IFERROR(PERCENTRANK(HIST_D!$BD$8:INDEX(HIST_D!$BD$8:$BD$2617,Control!$F$13),INDEX(HIST_D!$BD$8:$BD$2617,1)),"") | P22: =IFERROR(PERCENTRANK(HIST_D!$BD$8:INDEX(HIST_D!$BD$8:$BD$2617,Control!$F$14),INDEX(HIST_D!$BD$8:$BD$2617,1)),"") | Q22: =IFERROR(PERCENTRANK(HIST_D!$BD$8:INDEX(HIST_D!$BD$8:$BD$2617,Control!$F$15),INDEX(HIST_D!$BD$8:$BD$2617,1)),"") | S22: =IFERROR((INDEX(HIST_D!$BD$8:$BD$2617,1)-AVERAGE(HIST_D!$BD$8:INDEX(HIST_D!$BD$8:$BD$2617,Control!$F$14)))/STDEV(HIST_D!$BD$8:INDEX(HIST_D!$BD$8:$BD$2617,Control!$F$14)),"")
A23: Swap spread 10Y | B23: derived on HIST_D | C23: bp | D23: =INDEX(HIST_D!$BE$8:$BE$2617,1) | E23: =IFERROR((INDEX(HIST_D!$BE$8:$BE$2617,1)-INDEX(HIST_D!$BE$8:$BE$2617,Control!$F$6))*1,"") | F23: =IFERROR((INDEX(HIST_D!$BE$8:$BE$2617,1)-INDEX(HIST_D!$BE$8:$BE$2617,Control!$F$7))*1,"") | G23: =IFERROR((INDEX(HIST_D!$BE$8:$BE$2617,1)-INDEX(HIST_D!$BE$8:$BE$2617,Control!$F$8))*1,"") | H23: =IFERROR((INDEX(HIST_D!$BE$8:$BE$2617,1)-INDEX(HIST_D!$BE$8:$BE$2617,Control!$F$9))*1,"") | I23: =IFERROR((INDEX(HIST_D!$BE$8:$BE$2617,1)-INDEX(HIST_D!$BE$8:$BE$2617,Control!$F$10))*1,"") | J23: =IFERROR((INDEX(HIST_D!$BE$8:$BE$2617,1)-INDEX(HIST_D!$BE$8:$BE$2617,Control!$F$16))*1,"") | K23: =IFERROR((INDEX(HIST_D!$BE$8:$BE$2617,1)-INDEX(HIST_D!$BE$8:$BE$2617,Control!$F$11))*1,"") | L23: =IFERROR(MIN(HIST_D!$BE$8:INDEX(HIST_D!$BE$8:$BE$2617,Control!$F$11)),"") | M23: =IFERROR(MAX(HIST_D!$BE$8:INDEX(HIST_D!$BE$8:$BE$2617,Control!$F$11)),"") | N23: =IFERROR(PERCENTRANK(HIST_D!$BE$8:INDEX(HIST_D!$BE$8:$BE$2617,Control!$F$11),INDEX(HIST_D!$BE$8:$BE$2617,1)),"") | O23: =IFERROR(PERCENTRANK(HIST_D!$BE$8:INDEX(HIST_D!$BE$8:$BE$2617,Control!$F$13),INDEX(HIST_D!$BE$8:$BE$2617,1)),"") | P23: =IFERROR(PERCENTRANK(HIST_D!$BE$8:INDEX(HIST_D!$BE$8:$BE$2617,Control!$F$14),INDEX(HIST_D!$BE$8:$BE$2617,1)),"") | Q23: =IFERROR(PERCENTRANK(HIST_D!$BE$8:INDEX(HIST_D!$BE$8:$BE$2617,Control!$F$15),INDEX(HIST_D!$BE$8:$BE$2617,1)),"") | S23: =IFERROR((INDEX(HIST_D!$BE$8:$BE$2617,1)-AVERAGE(HIST_D!$BE$8:INDEX(HIST_D!$BE$8:$BE$2617,Control!$F$14)))/STDEV(HIST_D!$BE$8:INDEX(HIST_D!$BE$8:$BE$2617,Control!$F$14)),"")
A24: Swap spread 30Y | B24: derived on HIST_D | C24: bp | D24: =INDEX(HIST_D!$BF$8:$BF$2617,1) | E24: =IFERROR((INDEX(HIST_D!$BF$8:$BF$2617,1)-INDEX(HIST_D!$BF$8:$BF$2617,Control!$F$6))*1,"") | F24: =IFERROR((INDEX(HIST_D!$BF$8:$BF$2617,1)-INDEX(HIST_D!$BF$8:$BF$2617,Control!$F$7))*1,"") | G24: =IFERROR((INDEX(HIST_D!$BF$8:$BF$2617,1)-INDEX(HIST_D!$BF$8:$BF$2617,Control!$F$8))*1,"") | H24: =IFERROR((INDEX(HIST_D!$BF$8:$BF$2617,1)-INDEX(HIST_D!$BF$8:$BF$2617,Control!$F$9))*1,"") | I24: =IFERROR((INDEX(HIST_D!$BF$8:$BF$2617,1)-INDEX(HIST_D!$BF$8:$BF$2617,Control!$F$10))*1,"") | J24: =IFERROR((INDEX(HIST_D!$BF$8:$BF$2617,1)-INDEX(HIST_D!$BF$8:$BF$2617,Control!$F$16))*1,"") | K24: =IFERROR((INDEX(HIST_D!$BF$8:$BF$2617,1)-INDEX(HIST_D!$BF$8:$BF$2617,Control!$F$11))*1,"") | L24: =IFERROR(MIN(HIST_D!$BF$8:INDEX(HIST_D!$BF$8:$BF$2617,Control!$F$11)),"") | M24: =IFERROR(MAX(HIST_D!$BF$8:INDEX(HIST_D!$BF$8:$BF$2617,Control!$F$11)),"") | N24: =IFERROR(PERCENTRANK(HIST_D!$BF$8:INDEX(HIST_D!$BF$8:$BF$2617,Control!$F$11),INDEX(HIST_D!$BF$8:$BF$2617,1)),"") | O24: =IFERROR(PERCENTRANK(HIST_D!$BF$8:INDEX(HIST_D!$BF$8:$BF$2617,Control!$F$13),INDEX(HIST_D!$BF$8:$BF$2617,1)),"") | P24: =IFERROR(PERCENTRANK(HIST_D!$BF$8:INDEX(HIST_D!$BF$8:$BF$2617,Control!$F$14),INDEX(HIST_D!$BF$8:$BF$2617,1)),"") | Q24: =IFERROR(PERCENTRANK(HIST_D!$BF$8:INDEX(HIST_D!$BF$8:$BF$2617,Control!$F$15),INDEX(HIST_D!$BF$8:$BF$2617,1)),"") | S24: =IFERROR((INDEX(HIST_D!$BF$8:$BF$2617,1)-AVERAGE(HIST_D!$BF$8:INDEX(HIST_D!$BF$8:$BF$2617,Control!$F$14)))/STDEV(HIST_D!$BF$8:INDEX(HIST_D!$BF$8:$BF$2617,Control!$F$14)),"")
A27: CURVE REGIME — what kind of move was it?
A28: Window | B28: Δ 10Y (bp) | C28: Δ 2s10s (bp) | D28: Regime | E28: What it usually means for EM USD
A29: 1W | B29: =(INDEX(HIST_D!$J$8:$J$2617,1)-INDEX(HIST_D!$J$8:$J$2617,Control!$F$7))*Control!$B$11 | C29: =INDEX(HIST_D!$AV$8:$AV$2617,1)-INDEX(HIST_D!$AV$8:$AV$2617,Control!$F$7) | D29: =IF($B29<0,IF($C29>0,"Bull steepening","Bull flattening"),IF($C29>0,"Bear steepening","Bear flattening")) | E29: =IF($B29<0,IF($C29>0,"Front-end rallying on cuts. Historically the best EM USD backdrop: duration works and spreads usually follow.","Growth scare pricing. Duration helps, spreads normally widen; net EM return depends on beta, check the EM_Link tab."),IF($C29>0,"Term premium / supply-led. The Treasury leg stops being ballast — this is the regime that hurts EM total returns most.","Hawkish repricing. Carry survives, duration hurts; short-dated EM outperforms."))
A30: 1M | B30: =(INDEX(HIST_D!$J$8:$J$2617,1)-INDEX(HIST_D!$J$8:$J$2617,Control!$F$8))*Control!$B$11 | C30: =INDEX(HIST_D!$AV$8:$AV$2617,1)-INDEX(HIST_D!$AV$8:$AV$2617,Control!$F$8) | D30: =IF($B30<0,IF($C30>0,"Bull steepening","Bull flattening"),IF($C30>0,"Bear steepening","Bear flattening")) | E30: =IF($B30<0,IF($C30>0,"Front-end rallying on cuts. Historically the best EM USD backdrop: duration works and spreads usually follow.","Growth scare pricing. Duration helps, spreads normally widen; net EM return depends on beta, check the EM_Link tab."),IF($C30>0,"Term premium / supply-led. The Treasury leg stops being ballast — this is the regime that hurts EM total returns most.","Hawkish repricing. Carry survives, duration hurts; short-dated EM outperforms."))
A31: 3M | B31: =(INDEX(HIST_D!$J$8:$J$2617,1)-INDEX(HIST_D!$J$8:$J$2617,Control!$F$9))*Control!$B$11 | C31: =INDEX(HIST_D!$AV$8:$AV$2617,1)-INDEX(HIST_D!$AV$8:$AV$2617,Control!$F$9) | D31: =IF($B31<0,IF($C31>0,"Bull steepening","Bull flattening"),IF($C31>0,"Bear steepening","Bear flattening")) | E31: =IF($B31<0,IF($C31>0,"Front-end rallying on cuts. Historically the best EM USD backdrop: duration works and spreads usually follow.","Growth scare pricing. Duration helps, spreads normally widen; net EM return depends on beta, check the EM_Link tab."),IF($C31>0,"Term premium / supply-led. The Treasury leg stops being ballast — this is the regime that hurts EM total returns most.","Hawkish repricing. Carry survives, duration hurts; short-dated EM outperforms."))
A32: 6M | B32: =(INDEX(HIST_D!$J$8:$J$2617,1)-INDEX(HIST_D!$J$8:$J$2617,Control!$F$10))*Control!$B$11 | C32: =INDEX(HIST_D!$AV$8:$AV$2617,1)-INDEX(HIST_D!$AV$8:$AV$2617,Control!$F$10) | D32: =IF($B32<0,IF($C32>0,"Bull steepening","Bull flattening"),IF($C32>0,"Bear steepening","Bear flattening")) | E32: =IF($B32<0,IF($C32>0,"Front-end rallying on cuts. Historically the best EM USD backdrop: duration works and spreads usually follow.","Growth scare pricing. Duration helps, spreads normally widen; net EM return depends on beta, check the EM_Link tab."),IF($C32>0,"Term premium / supply-led. The Treasury leg stops being ballast — this is the regime that hurts EM total returns most.","Hawkish repricing. Carry survives, duration hurts; short-dated EM outperforms."))
A33: 1Y | B33: =(INDEX(HIST_D!$J$8:$J$2617,1)-INDEX(HIST_D!$J$8:$J$2617,Control!$F$11))*Control!$B$11 | C33: =INDEX(HIST_D!$AV$8:$AV$2617,1)-INDEX(HIST_D!$AV$8:$AV$2617,Control!$F$11) | D33: =IF($B33<0,IF($C33>0,"Bull steepening","Bull flattening"),IF($C33>0,"Bear steepening","Bear flattening")) | E33: =IF($B33<0,IF($C33>0,"Front-end rallying on cuts. Historically the best EM USD backdrop: duration works and spreads usually follow.","Growth scare pricing. Duration helps, spreads normally widen; net EM return depends on beta, check the EM_Link tab."),IF($C33>0,"Term premium / supply-led. The Treasury leg stops being ballast — this is the regime that hurts EM total returns most.","Hawkish repricing. Carry survives, duration hurts; short-dated EM outperforms."))

Sheet Policy
A1: IMPLIED POLICY RATE
A2: Fed funds futures are month-AVERAGE effective funds contracts. The meeting block below does the calendar split properly rather than reading the strip as if each contract were a meeting.
A4: SPOT ANCHORS
A5: Item | B5: Bloomberg ticker | C5: Field | D5: Live pull | E5: Your fallback | F5: Used | G5: Status | H5: Unit | I5: Note
A6: Fed funds target — upper | B6: FDTR Index | C6: PX_LAST | D6: =IFERROR(BDP($B6,$C6),"") | E6: 4.25 | F6: =IF(ISNUMBER($D6),$D6,$E6) | G6: =IF(ISNUMBER($D6),"LIVE","FALLBACK") | H6: % | I6: target band top
A7: Fed funds target — lower | B7: FDTRFTRL Index | C7: PX_LAST | D7: =IFERROR(BDP($B7,$C7),"") | E7: 4 | F7: =IF(ISNUMBER($D7),$D7,$E7) | G7: =IF(ISNUMBER($D7),"LIVE","FALLBACK") | H7: % | I7: VERIFY ticker in SECF
A8: Interest on reserve balances | B8: IORB Index | C8: PX_LAST | D8: =IFERROR(BDP($B8,$C8),"") | E8: 4.15 | F8: =IF(ISNUMBER($D8),$D8,$E8) | G8: =IF(ISNUMBER($D8),"LIVE","FALLBACK") | H8: % | I8: VERIFY ticker in SECF
A9: EFFR | B9: FEDL01 Index | C9: PX_LAST | D9: =IFERROR(BDP($B9,$C9),"") | E9: 4.08 | F9: =IF(ISNUMBER($D9),$D9,$E9) | G9: =IF(ISNUMBER($D9),"LIVE","FALLBACK") | H9: % | I9: also on HIST_D as EFFR
A10: SOFR | B10: SOFRRATE Index | C10: PX_LAST | D10: =IFERROR(BDP($B10,$C10),"") | E10: 4.1 | F10: =IF(ISNUMBER($D10),$D10,$E10) | G10: =IF(ISNUMBER($D10),"LIVE","FALLBACK") | H10: % | I10: also on HIST_D as SOFR
A11: Target midpoint | F11: =AVERAGE($F$6,$F$7)
A12: EFFR − IORB (bp) | F12: =($F$9-$F$8)*Control!$B$11 | I12: Positive and rising = reserves getting scarce. This is the single most useful funding tell.
A13: SOFR − IORB (bp) | F13: =($F$10-$F$8)*Control!$B$11 | I13: Repo pressure. Sustained above IORB means collateral is heavy and balance sheet is scarce.
A15: FED FUNDS FUTURES STRIP
A16: # | B16: Ticker | C16: Contract month | D16: Price | E16: Implied avg EFFR (%) | F16: vs spot EFFR (bp) | G16: Cuts priced (25bp, + = easing) | H16: Price 1W ago | I16: Δ 1W (bp) | J16: Price 1M ago | K16: Δ 1M (bp) | L16: Month key | M16: Note
A17: 1 | B17: ="FF"&$A17&" Comdty" | C17: =IFERROR(BDP($B17,"LAST_TRADEABLE_DT"),"") | D17: =IFERROR(BDP($B17,"PX_LAST"),"") | E17: =IFERROR(100-$D17,"") | F17: =IFERROR(($E17-'Policy'!$F$9)*Control!$B$11,"") | G17: =IFERROR(('Policy'!$F$9-$E17)/0.25,"") | H17: =IFERROR(BDH($B17,"PX_LAST",Control!$B$15,Control!$B$15),"") | I17: =IFERROR(($H17-$D17)*Control!$B$11,"") | J17: =IFERROR(BDH($B17,"PX_LAST",Control!$B$16,Control!$B$16),"") | K17: =IFERROR(($J17-$D17)*Control!$B$11,"") | L17: =IFERROR(YEAR($C17)*12+MONTH($C17),"")
A18: 2 | B18: ="FF"&$A18&" Comdty" | C18: =IFERROR(BDP($B18,"LAST_TRADEABLE_DT"),"") | D18: =IFERROR(BDP($B18,"PX_LAST"),"") | E18: =IFERROR(100-$D18,"") | F18: =IFERROR(($E18-'Policy'!$F$9)*Control!$B$11,"") | G18: =IFERROR(('Policy'!$F$9-$E18)/0.25,"") | H18: =IFERROR(BDH($B18,"PX_LAST",Control!$B$15,Control!$B$15),"") | I18: =IFERROR(($H18-$D18)*Control!$B$11,"") | J18: =IFERROR(BDH($B18,"PX_LAST",Control!$B$16,Control!$B$16),"") | K18: =IFERROR(($J18-$D18)*Control!$B$11,"") | L18: =IFERROR(YEAR($C18)*12+MONTH($C18),"")
A19: 3 | B19: ="FF"&$A19&" Comdty" | C19: =IFERROR(BDP($B19,"LAST_TRADEABLE_DT"),"") | D19: =IFERROR(BDP($B19,"PX_LAST"),"") | E19: =IFERROR(100-$D19,"") | F19: =IFERROR(($E19-'Policy'!$F$9)*Control!$B$11,"") | G19: =IFERROR(('Policy'!$F$9-$E19)/0.25,"") | H19: =IFERROR(BDH($B19,"PX_LAST",Control!$B$15,Control!$B$15),"") | I19: =IFERROR(($H19-$D19)*Control!$B$11,"") | J19: =IFERROR(BDH($B19,"PX_LAST",Control!$B$16,Control!$B$16),"") | K19: =IFERROR(($J19-$D19)*Control!$B$11,"") | L19: =IFERROR(YEAR($C19)*12+MONTH($C19),"")
A20: 4 | B20: ="FF"&$A20&" Comdty" | C20: =IFERROR(BDP($B20,"LAST_TRADEABLE_DT"),"") | D20: =IFERROR(BDP($B20,"PX_LAST"),"") | E20: =IFERROR(100-$D20,"") | F20: =IFERROR(($E20-'Policy'!$F$9)*Control!$B$11,"") | G20: =IFERROR(('Policy'!$F$9-$E20)/0.25,"") | H20: =IFERROR(BDH($B20,"PX_LAST",Control!$B$15,Control!$B$15),"") | I20: =IFERROR(($H20-$D20)*Control!$B$11,"") | J20: =IFERROR(BDH($B20,"PX_LAST",Control!$B$16,Control!$B$16),"") | K20: =IFERROR(($J20-$D20)*Control!$B$11,"") | L20: =IFERROR(YEAR($C20)*12+MONTH($C20),"")
A21: 5 | B21: ="FF"&$A21&" Comdty" | C21: =IFERROR(BDP($B21,"LAST_TRADEABLE_DT"),"") | D21: =IFERROR(BDP($B21,"PX_LAST"),"") | E21: =IFERROR(100-$D21,"") | F21: =IFERROR(($E21-'Policy'!$F$9)*Control!$B$11,"") | G21: =IFERROR(('Policy'!$F$9-$E21)/0.25,"") | H21: =IFERROR(BDH($B21,"PX_LAST",Control!$B$15,Control!$B$15),"") | I21: =IFERROR(($H21-$D21)*Control!$B$11,"") | J21: =IFERROR(BDH($B21,"PX_LAST",Control!$B$16,Control!$B$16),"") | K21: =IFERROR(($J21-$D21)*Control!$B$11,"") | L21: =IFERROR(YEAR($C21)*12+MONTH($C21),"")
A22: 6 | B22: ="FF"&$A22&" Comdty" | C22: =IFERROR(BDP($B22,"LAST_TRADEABLE_DT"),"") | D22: =IFERROR(BDP($B22,"PX_LAST"),"") | E22: =IFERROR(100-$D22,"") | F22: =IFERROR(($E22-'Policy'!$F$9)*Control!$B$11,"") | G22: =IFERROR(('Policy'!$F$9-$E22)/0.25,"") | H22: =IFERROR(BDH($B22,"PX_LAST",Control!$B$15,Control!$B$15),"") | I22: =IFERROR(($H22-$D22)*Control!$B$11,"") | J22: =IFERROR(BDH($B22,"PX_LAST",Control!$B$16,Control!$B$16),"") | K22: =IFERROR(($J22-$D22)*Control!$B$11,"") | L22: =IFERROR(YEAR($C22)*12+MONTH($C22),"")
A23: 7 | B23: ="FF"&$A23&" Comdty" | C23: =IFERROR(BDP($B23,"LAST_TRADEABLE_DT"),"") | D23: =IFERROR(BDP($B23,"PX_LAST"),"") | E23: =IFERROR(100-$D23,"") | F23: =IFERROR(($E23-'Policy'!$F$9)*Control!$B$11,"") | G23: =IFERROR(('Policy'!$F$9-$E23)/0.25,"") | H23: =IFERROR(BDH($B23,"PX_LAST",Control!$B$15,Control!$B$15),"") | I23: =IFERROR(($H23-$D23)*Control!$B$11,"") | J23: =IFERROR(BDH($B23,"PX_LAST",Control!$B$16,Control!$B$16),"") | K23: =IFERROR(($J23-$D23)*Control!$B$11,"") | L23: =IFERROR(YEAR($C23)*12+MONTH($C23),"")
A24: 8 | B24: ="FF"&$A24&" Comdty" | C24: =IFERROR(BDP($B24,"LAST_TRADEABLE_DT"),"") | D24: =IFERROR(BDP($B24,"PX_LAST"),"") | E24: =IFERROR(100-$D24,"") | F24: =IFERROR(($E24-'Policy'!$F$9)*Control!$B$11,"") | G24: =IFERROR(('Policy'!$F$9-$E24)/0.25,"") | H24: =IFERROR(BDH($B24,"PX_LAST",Control!$B$15,Control!$B$15),"") | I24: =IFERROR(($H24-$D24)*Control!$B$11,"") | J24: =IFERROR(BDH($B24,"PX_LAST",Control!$B$16,Control!$B$16),"") | K24: =IFERROR(($J24-$D24)*Control!$B$11,"") | L24: =IFERROR(YEAR($C24)*12+MONTH($C24),"")
A25: 9 | B25: ="FF"&$A25&" Comdty" | C25: =IFERROR(BDP($B25,"LAST_TRADEABLE_DT"),"") | D25: =IFERROR(BDP($B25,"PX_LAST"),"") | E25: =IFERROR(100-$D25,"") | F25: =IFERROR(($E25-'Policy'!$F$9)*Control!$B$11,"") | G25: =IFERROR(('Policy'!$F$9-$E25)/0.25,"") | H25: =IFERROR(BDH($B25,"PX_LAST",Control!$B$15,Control!$B$15),"") | I25: =IFERROR(($H25-$D25)*Control!$B$11,"") | J25: =IFERROR(BDH($B25,"PX_LAST",Control!$B$16,Control!$B$16),"") | K25: =IFERROR(($J25-$D25)*Control!$B$11,"") | L25: =IFERROR(YEAR($C25)*12+MONTH($C25),"")
A26: 10 | B26: ="FF"&$A26&" Comdty" | C26: =IFERROR(BDP($B26,"LAST_TRADEABLE_DT"),"") | D26: =IFERROR(BDP($B26,"PX_LAST"),"") | E26: =IFERROR(100-$D26,"") | F26: =IFERROR(($E26-'Policy'!$F$9)*Control!$B$11,"") | G26: =IFERROR(('Policy'!$F$9-$E26)/0.25,"") | H26: =IFERROR(BDH($B26,"PX_LAST",Control!$B$15,Control!$B$15),"") | I26: =IFERROR(($H26-$D26)*Control!$B$11,"") | J26: =IFERROR(BDH($B26,"PX_LAST",Control!$B$16,Control!$B$16),"") | K26: =IFERROR(($J26-$D26)*Control!$B$11,"") | L26: =IFERROR(YEAR($C26)*12+MONTH($C26),"")
A27: 11 | B27: ="FF"&$A27&" Comdty" | C27: =IFERROR(BDP($B27,"LAST_TRADEABLE_DT"),"") | D27: =IFERROR(BDP($B27,"PX_LAST"),"") | E27: =IFERROR(100-$D27,"") | F27: =IFERROR(($E27-'Policy'!$F$9)*Control!$B$11,"") | G27: =IFERROR(('Policy'!$F$9-$E27)/0.25,"") | H27: =IFERROR(BDH($B27,"PX_LAST",Control!$B$15,Control!$B$15),"") | I27: =IFERROR(($H27-$D27)*Control!$B$11,"") | J27: =IFERROR(BDH($B27,"PX_LAST",Control!$B$16,Control!$B$16),"") | K27: =IFERROR(($J27-$D27)*Control!$B$11,"") | L27: =IFERROR(YEAR($C27)*12+MONTH($C27),"")
A28: 12 | B28: ="FF"&$A28&" Comdty" | C28: =IFERROR(BDP($B28,"LAST_TRADEABLE_DT"),"") | D28: =IFERROR(BDP($B28,"PX_LAST"),"") | E28: =IFERROR(100-$D28,"") | F28: =IFERROR(($E28-'Policy'!$F$9)*Control!$B$11,"") | G28: =IFERROR(('Policy'!$F$9-$E28)/0.25,"") | H28: =IFERROR(BDH($B28,"PX_LAST",Control!$B$15,Control!$B$15),"") | I28: =IFERROR(($H28-$D28)*Control!$B$11,"") | J28: =IFERROR(BDH($B28,"PX_LAST",Control!$B$16,Control!$B$16),"") | K28: =IFERROR(($J28-$D28)*Control!$B$11,"") | L28: =IFERROR(YEAR($C28)*12+MONTH($C28),"")
... A34: 18 | B34: ="FF"&$A34&" Comdty" | C34: =IFERROR(BDP($B34,"LAST_TRADEABLE_DT"),"") | D34: =IFERROR(BDP($B34,"PX_LAST"),"") | E34: =IFERROR(100-$D34,"") | F34: =IFERROR(($E34-'Policy'!$F$9)*Control!$B$11,"") | G34: =IFERROR(('Policy'!$F$9-$E34)/0.25,"") | H34: =IFERROR(BDH($B34,"PX_LAST",Control!$B$15,Control!$B$15),"") | I34: =IFERROR(($H34-$D34)*Control!$B$11,"") | J34: =IFERROR(BDH($B34,"PX_LAST",Control!$B$16,Control!$B$16),"") | K34: =IFERROR(($J34-$D34)*Control!$B$11,"") | L34: =IFERROR(YEAR($C34)*12+MONTH($C34),"")
A35: Δ 1W/1M are in implied-RATE bp (a lower price = a higher implied rate), so a positive number means the market repriced HAWKISH.
A36: Market trough (lowest implied avg rate on the strip) | E36: =IFERROR(MIN($E$17:$E$34),"") | F36: =IFERROR(($E36-'Policy'!$F$9)*Control!$B$11,"") | G36: =IFERROR(('Policy'!$F$9-$E36)/0.25,"")
A38: MEETING-BY-MEETING IMPLIED PATH (proper intra-month split)
A39: FOMC date | B39: Status | C39: Days in month | D39: Meeting day | E39: FF avg — meeting month (%) | F39: FF avg — prior month (%) | G39: FF avg — next month (%) | H39: Rate after meeting, exact split (%) | I39: Move priced (bp) | J39: Cumulative vs spot (bp) | K39: Cumulative cuts (25bp, + = easing) | L39: Split − next-month read (bp) | M39: Month key
A40: 46281 | B40: PLACEHOLDER | C40: =DAY(EOMONTH($A40,0)) | D40: =DAY($A40) | E40: =IFERROR(INDEX($E$17:$E$34,MATCH((YEAR($A40)*12+MONTH($A40)),$L$17:$L$34,0)),"") | F40: =IFERROR(INDEX($E$17:$E$34,MATCH((YEAR($A40)*12+MONTH($A40))-1,$L$17:$L$34,0)),'Policy'!$F$9) | G40: =IFERROR(INDEX($E$17:$E$34,MATCH((YEAR($A40)*12+MONTH($A40))+1,$L$17:$L$34,0)),"") | H40: =IFERROR(($E40*$C40-$F40*($D40-1))/($C40-$D40+1),"") | I40: =IFERROR(($G40-$F40)*Control!$B$11,"") | J40: =IFERROR(($G40-'Policy'!$F$9)*Control!$B$11,"") | K40: =IFERROR(('Policy'!$F$9-$G40)/0.25,"") | L40: =IFERROR(($H40-$G40)*Control!$B$11,"") | M40: =(YEAR($A40)*12+MONTH($A40))
A41: 46323 | B41: PLACEHOLDER | C41: =DAY(EOMONTH($A41,0)) | D41: =DAY($A41) | E41: =IFERROR(INDEX($E$17:$E$34,MATCH((YEAR($A41)*12+MONTH($A41)),$L$17:$L$34,0)),"") | F41: =IFERROR(INDEX($E$17:$E$34,MATCH((YEAR($A41)*12+MONTH($A41))-1,$L$17:$L$34,0)),'Policy'!$F$9) | G41: =IFERROR(INDEX($E$17:$E$34,MATCH((YEAR($A41)*12+MONTH($A41))+1,$L$17:$L$34,0)),"") | H41: =IFERROR(($E41*$C41-$F41*($D41-1))/($C41-$D41+1),"") | I41: =IFERROR(($G41-$F41)*Control!$B$11,"") | J41: =IFERROR(($G41-'Policy'!$F$9)*Control!$B$11,"") | K41: =IFERROR(('Policy'!$F$9-$G41)/0.25,"") | L41: =IFERROR(($H41-$G41)*Control!$B$11,"") | M41: =(YEAR($A41)*12+MONTH($A41))
A42: 46365 | B42: PLACEHOLDER | C42: =DAY(EOMONTH($A42,0)) | D42: =DAY($A42) | E42: =IFERROR(INDEX($E$17:$E$34,MATCH((YEAR($A42)*12+MONTH($A42)),$L$17:$L$34,0)),"") | F42: =IFERROR(INDEX($E$17:$E$34,MATCH((YEAR($A42)*12+MONTH($A42))-1,$L$17:$L$34,0)),'Policy'!$F$9) | G42: =IFERROR(INDEX($E$17:$E$34,MATCH((YEAR($A42)*12+MONTH($A42))+1,$L$17:$L$34,0)),"") | H42: =IFERROR(($E42*$C42-$F42*($D42-1))/($C42-$D42+1),"") | I42: =IFERROR(($G42-$F42)*Control!$B$11,"") | J42: =IFERROR(($G42-'Policy'!$F$9)*Control!$B$11,"") | K42: =IFERROR(('Policy'!$F$9-$G42)/0.25,"") | L42: =IFERROR(($H42-$G42)*Control!$B$11,"") | M42: =(YEAR($A42)*12+MONTH($A42))
A43: 46414 | B43: PLACEHOLDER | C43: =DAY(EOMONTH($A43,0)) | D43: =DAY($A43) | E43: =IFERROR(INDEX($E$17:$E$34,MATCH((YEAR($A43)*12+MONTH($A43)),$L$17:$L$34,0)),"") | F43: =IFERROR(INDEX($E$17:$E$34,MATCH((YEAR($A43)*12+MONTH($A43))-1,$L$17:$L$34,0)),'Policy'!$F$9) | G43: =IFERROR(INDEX($E$17:$E$34,MATCH((YEAR($A43)*12+MONTH($A43))+1,$L$17:$L$34,0)),"") | H43: =IFERROR(($E43*$C43-$F43*($D43-1))/($C43-$D43+1),"") | I43: =IFERROR(($G43-$F43)*Control!$B$11,"") | J43: =IFERROR(($G43-'Policy'!$F$9)*Control!$B$11,"") | K43: =IFERROR(('Policy'!$F$9-$G43)/0.25,"") | L43: =IFERROR(($H43-$G43)*Control!$B$11,"") | M43: =(YEAR($A43)*12+MONTH($A43))
A44: 46463 | B44: PLACEHOLDER | C44: =DAY(EOMONTH($A44,0)) | D44: =DAY($A44) | E44: =IFERROR(INDEX($E$17:$E$34,MATCH((YEAR($A44)*12+MONTH($A44)),$L$17:$L$34,0)),"") | F44: =IFERROR(INDEX($E$17:$E$34,MATCH((YEAR($A44)*12+MONTH($A44))-1,$L$17:$L$34,0)),'Policy'!$F$9) | G44: =IFERROR(INDEX($E$17:$E$34,MATCH((YEAR($A44)*12+MONTH($A44))+1,$L$17:$L$34,0)),"") | H44: =IFERROR(($E44*$C44-$F44*($D44-1))/($C44-$D44+1),"") | I44: =IFERROR(($G44-$F44)*Control!$B$11,"") | J44: =IFERROR(($G44-'Policy'!$F$9)*Control!$B$11,"") | K44: =IFERROR(('Policy'!$F$9-$G44)/0.25,"") | L44: =IFERROR(($H44-$G44)*Control!$B$11,"") | M44: =(YEAR($A44)*12+MONTH($A44))
A45: 46505 | B45: PLACEHOLDER | C45: =DAY(EOMONTH($A45,0)) | D45: =DAY($A45) | E45: =IFERROR(INDEX($E$17:$E$34,MATCH((YEAR($A45)*12+MONTH($A45)),$L$17:$L$34,0)),"") | F45: =IFERROR(INDEX($E$17:$E$34,MATCH((YEAR($A45)*12+MONTH($A45))-1,$L$17:$L$34,0)),'Policy'!$F$9) | G45: =IFERROR(INDEX($E$17:$E$34,MATCH((YEAR($A45)*12+MONTH($A45))+1,$L$17:$L$34,0)),"") | H45: =IFERROR(($E45*$C45-$F45*($D45-1))/($C45-$D45+1),"") | I45: =IFERROR(($G45-$F45)*Control!$B$11,"") | J45: =IFERROR(($G45-'Policy'!$F$9)*Control!$B$11,"") | K45: =IFERROR(('Policy'!$F$9-$G45)/0.25,"") | L45: =IFERROR(($H45-$G45)*Control!$B$11,"") | M45: =(YEAR($A45)*12+MONTH($A45))
A46: 46554 | B46: PLACEHOLDER | C46: =DAY(EOMONTH($A46,0)) | D46: =DAY($A46) | E46: =IFERROR(INDEX($E$17:$E$34,MATCH((YEAR($A46)*12+MONTH($A46)),$L$17:$L$34,0)),"") | F46: =IFERROR(INDEX($E$17:$E$34,MATCH((YEAR($A46)*12+MONTH($A46))-1,$L$17:$L$34,0)),'Policy'!$F$9) | G46: =IFERROR(INDEX($E$17:$E$34,MATCH((YEAR($A46)*12+MONTH($A46))+1,$L$17:$L$34,0)),"") | H46: =IFERROR(($E46*$C46-$F46*($D46-1))/($C46-$D46+1),"") | I46: =IFERROR(($G46-$F46)*Control!$B$11,"") | J46: =IFERROR(($G46-'Policy'!$F$9)*Control!$B$11,"") | K46: =IFERROR(('Policy'!$F$9-$G46)/0.25,"") | L46: =IFERROR(($H46-$G46)*Control!$B$11,"") | M46: =(YEAR($A46)*12+MONTH($A46))
A47: 46596 | B47: PLACEHOLDER | C47: =DAY(EOMONTH($A47,0)) | D47: =DAY($A47) | E47: =IFERROR(INDEX($E$17:$E$34,MATCH((YEAR($A47)*12+MONTH($A47)),$L$17:$L$34,0)),"") | F47: =IFERROR(INDEX($E$17:$E$34,MATCH((YEAR($A47)*12+MONTH($A47))-1,$L$17:$L$34,0)),'Policy'!$F$9) | G47: =IFERROR(INDEX($E$17:$E$34,MATCH((YEAR($A47)*12+MONTH($A47))+1,$L$17:$L$34,0)),"") | H47: =IFERROR(($E47*$C47-$F47*($D47-1))/($C47-$D47+1),"") | I47: =IFERROR(($G47-$F47)*Control!$B$11,"") | J47: =IFERROR(($G47-'Policy'!$F$9)*Control!$B$11,"") | K47: =IFERROR(('Policy'!$F$9-$G47)/0.25,"") | L47: =IFERROR(($H47-$G47)*Control!$B$11,"") | M47: =(YEAR($A47)*12+MONTH($A47))
A48: 46652 | B48: PLACEHOLDER | C48: =DAY(EOMONTH($A48,0)) | D48: =DAY($A48) | E48: =IFERROR(INDEX($E$17:$E$34,MATCH((YEAR($A48)*12+MONTH($A48)),$L$17:$L$34,0)),"") | F48: =IFERROR(INDEX($E$17:$E$34,MATCH((YEAR($A48)*12+MONTH($A48))-1,$L$17:$L$34,0)),'Policy'!$F$9) | G48: =IFERROR(INDEX($E$17:$E$34,MATCH((YEAR($A48)*12+MONTH($A48))+1,$L$17:$L$34,0)),"") | H48: =IFERROR(($E48*$C48-$F48*($D48-1))/($C48-$D48+1),"") | I48: =IFERROR(($G48-$F48)*Control!$B$11,"") | J48: =IFERROR(($G48-'Policy'!$F$9)*Control!$B$11,"") | K48: =IFERROR(('Policy'!$F$9-$G48)/0.25,"") | L48: =IFERROR(($H48-$G48)*Control!$B$11,"") | M48: =(YEAR($A48)*12+MONTH($A48))
A49: 46694 | B49: PLACEHOLDER | C49: =DAY(EOMONTH($A49,0)) | D49: =DAY($A49) | E49: =IFERROR(INDEX($E$17:$E$34,MATCH((YEAR($A49)*12+MONTH($A49)),$L$17:$L$34,0)),"") | F49: =IFERROR(INDEX($E$17:$E$34,MATCH((YEAR($A49)*12+MONTH($A49))-1,$L$17:$L$34,0)),'Policy'!$F$9) | G49: =IFERROR(INDEX($E$17:$E$34,MATCH((YEAR($A49)*12+MONTH($A49))+1,$L$17:$L$34,0)),"") | H49: =IFERROR(($E49*$C49-$F49*($D49-1))/($C49-$D49+1),"") | I49: =IFERROR(($G49-$F49)*Control!$B$11,"") | J49: =IFERROR(($G49-'Policy'!$F$9)*Control!$B$11,"") | K49: =IFERROR(('Policy'!$F$9-$G49)/0.25,"") | L49: =IFERROR(($H49-$G49)*Control!$B$11,"") | M49: =(YEAR($A49)*12+MONTH($A49))
A50: 46736 | B50: PLACEHOLDER | C50: =DAY(EOMONTH($A50,0)) | D50: =DAY($A50) | E50: =IFERROR(INDEX($E$17:$E$34,MATCH((YEAR($A50)*12+MONTH($A50)),$L$17:$L$34,0)),"") | F50: =IFERROR(INDEX($E$17:$E$34,MATCH((YEAR($A50)*12+MONTH($A50))-1,$L$17:$L$34,0)),'Policy'!$F$9) | G50: =IFERROR(INDEX($E$17:$E$34,MATCH((YEAR($A50)*12+MONTH($A50))+1,$L$17:$L$34,0)),"") | H50: =IFERROR(($E50*$C50-$F50*($D50-1))/($C50-$D50+1),"") | I50: =IFERROR(($G50-$F50)*Control!$B$11,"") | J50: =IFERROR(($G50-'Policy'!$F$9)*Control!$B$11,"") | K50: =IFERROR(('Policy'!$F$9-$G50)/0.25,"") | L50: =IFERROR(($H50-$G50)*Control!$B$11,"") | M50: =(YEAR($A50)*12+MONTH($A50))
A51: FOMC dates above are PLACEHOLDERS following the usual eight-meeting pattern. Replace column A from the Fed's published calendar (FOMC <GO>) before quoting anything from this block — everything to the right is live and follows column A.
A52: Method. A fed funds contract settles on the AVERAGE effective rate over its calendar month, so no single contract is a meeting. Column G reads the rate straight off the first full month after the meeting — stable, and the number to use. Column H is the exact intra-month algebra instead: if a meeting falls on day d of a D-day month, avg = r_before×(d−1)/D + r_after×(D−d+1)/D, solved for r_after. Column L is the gap between the two.
A53: Read column L as a noise check, not as a second opinion. A few bp is the usual month-shape effect (and the fact that a decision is effective the day AFTER the meeting). Twenty bp or more means one contract in the strip is stale or the meeting date in column A is wrong.
A54: Where a meeting month sits beyond the end of the strip, columns E–H return blank. Lengthen the strip above if you need a longer path.
A56: MARKET vs HOUSE
B57: Level (%) | C57: vs market (bp) | D57: Note
A58: Market terminal (strip trough) | B58: =IFERROR(MIN($E$17:$E$34),"") | D58: from the futures strip above
A59: Your terminal view | B59: 3.25 | C59: =IFERROR(($B59-$B$58)*Control!$B$11,"") | D59: yours — type it
A60: UBS house terminal view | B60: 3.5 | C60: =IFERROR(($B60-$B$58)*Control!$B$11,"") | D60: house — type it
A61: Spot EFFR | B61: ='Policy'!$F$9 | C61: =IFERROR(($B61-$B$58)*Control!$B$11,"")

Sheet Liquidity
A1: FUNDING & LIQUIDITY
A2: Two questions: is cash getting scarce (funding block), and is the Treasury market able to absorb risk (market-capacity block).
A4: FUNDING RATES vs THE CORRIDOR
A5: Item | B5: Bloomberg ticker | C5: Field | D5: Live pull | E5: Your fallback | F5: Used | G5: Status | H5: Unit | I5: Note
A6: SOFR | B6: SOFRRATE Index | C6: PX_LAST | D6: =IFERROR(BDP($B6,$C6),"") | E6: 4.1 | F6: =IF(ISNUMBER($D6),$D6,$E6) | G6: =IF(ISNUMBER($D6),"LIVE","FALLBACK") | H6: % | I6: secured, the benchmark
A7: SOFR 99th percentile | B7: SOFR99 Index | C7: PX_LAST | D7: =IFERROR(BDP($B7,$C7),"") | E7: 4.2 | F7: =IF(ISNUMBER($D7),$D7,$E7) | G7: =IF(ISNUMBER($D7),"LIVE","FALLBACK") | H7: % | I7: VERIFY — tail prints are the early warning
A8: Broad general collateral (BGCR) | B8: BGCRATE Index | C8: PX_LAST | D8: =IFERROR(BDP($B8,$C8),"") | E8: 4.09 | F8: =IF(ISNUMBER($D8),$D8,$E8) | G8: =IF(ISNUMBER($D8),"LIVE","FALLBACK") | H8: % | I8: VERIFY
A9: Tri-party general collateral (TGCR) | B9: TGCRATE Index | C9: PX_LAST | D9: =IFERROR(BDP($B9,$C9),"") | E9: 4.08 | F9: =IF(ISNUMBER($D9),$D9,$E9) | G9: =IF(ISNUMBER($D9),"LIVE","FALLBACK") | H9: % | I9: VERIFY
A10: EFFR | B10: FEDL01 Index | C10: PX_LAST | D10: =IFERROR(BDP($B10,$C10),"") | E10: 4.08 | F10: =IF(ISNUMBER($D10),$D10,$E10) | G10: =IF(ISNUMBER($D10),"LIVE","FALLBACK") | H10: % | I10: unsecured
A11: OBFR | B11: OBFR01 Index | C11: PX_LAST | D11: =IFERROR(BDP($B11,$C11),"") | E11: 4.08 | F11: =IF(ISNUMBER($D11),$D11,$E11) | G11: =IF(ISNUMBER($D11),"LIVE","FALLBACK") | H11: % | I11: VERIFY — broader unsecured
A12: Interest on reserve balances | B12: IORB Index | C12: PX_LAST | D12: =IFERROR(BDP($B12,$C12),"") | E12: 4.15 | F12: =IF(ISNUMBER($D12),$D12,$E12) | G12: =IF(ISNUMBER($D12),"LIVE","FALLBACK") | H12: % | I12: VERIFY — the ceiling that matters
A13: ON RRP offering rate | B13: RRPRATE Index | C13: PX_LAST | D13: =IFERROR(BDP($B13,$C13),"") | E13: 4 | F13: =IF(ISNUMBER($D13),$D13,$E13) | G13: =IF(ISNUMBER($D13),"LIVE","FALLBACK") | H13: % | I13: VERIFY — the floor
A15: SOFR − IORB (bp) | F15: =($F$6-$F$12)*Control!$B$11 | I15: the cleanest scarcity signal; persistent positives are the story
A16: EFFR − IORB (bp) | F16: =($F$10-$F$12)*Control!$B$11 | I16: unsecured side of the same question
A17: SOFR − ON RRP (bp) | F17: =($F$6-$F$13)*Control!$B$11 | I17: how far repo sits above the floor
A18: SOFR − EFFR (bp) | F18: =($F$6-$F$10)*Control!$B$11 | I18: secured vs unsecured; widens when collateral is heavy
A20: THE LIQUIDITY STOCK (H.4.1 / Fed, weekly — treat the dates with care)
A21: Item | B21: Bloomberg ticker | C21: Field | D21: Live pull | E21: Your fallback | F21: Used | G21: Status | H21: Unit | I21: Note
A22: Fed total assets | B22: FARBAST Index | C22: PX_LAST | D22: =IFERROR(BDP($B22,$C22),"") | E22: 6600000 | F22: =IF(ISNUMBER($D22),$D22,$E22) | G22: =IF(ISNUMBER($D22),"LIVE","FALLBACK") | H22: $mn | I22: VERIFY
A23: Reserve balances at the Fed | B23: FARBREBA Index | C23: PX_LAST | D23: =IFERROR(BDP($B23,$C23),"") | E23: 3000000 | F23: =IF(ISNUMBER($D23),$D23,$E23) | G23: =IF(ISNUMBER($D23),"LIVE","FALLBACK") | H23: $mn | I23: VERIFY
A24: Treasury General Account | B24: FDTRGENA Index | C24: PX_LAST | D24: =IFERROR(BDP($B24,$C24),"") | E24: 700000 | F24: =IF(ISNUMBER($D24),$D24,$E24) | G24: =IF(ISNUMBER($D24),"LIVE","FALLBACK") | H24: $mn | I24: VERIFY
A25: ON RRP volume | B25: RRPONTSY Index | C25: PX_LAST | D25: =IFERROR(BDP($B25,$C25),"") | E25: 25000 | F25: =IF(ISNUMBER($D25),$D25,$E25) | G25: =IF(ISNUMBER($D25),"LIVE","FALLBACK") | H25: $mn | I25: VERIFY — the shock absorber
A26: Standing Repo Facility usage | B26: FARBSRFO Index | C26: PX_LAST | D26: =IFERROR(BDP($B26,$C26),"") | E26: 0 | F26: =IF(ISNUMBER($D26),$D26,$E26) | G26: =IF(ISNUMBER($D26),"LIVE","FALLBACK") | H26: $mn | I26: VERIFY — non-zero is a real signal
A28: "Net liquidity" = Fed assets − TGA − ON RRP | F28: =$F$22-$F$24-$F$25 | I28: A heuristic, not an identity. It is popular because it tracked risk assets for a few years, not because it is a balance-sheet truth. Use the direction, not the level.
A29: Reserves + RRP (the actual cash buffer) | F29: =$F$23+$F$25 | I29: When RRP is near zero, every further drain comes straight out of reserves. That is when funding spreads start moving.
A31: MARKET CAPACITY (can the Treasury market absorb risk?)
A32: Instrument | B32: Source | C32: Unit | D32: Level | E32: 1D | F32: 1W | G32: 1M | H32: 3M | I32: 6M | J32: YTD | K32: 1Y | L32: 1y min | M32: 1y max | N32: %ile 1y | O32: %ile 3y | P32: %ile 5y | Q32: %ile 10y | R32: %ile 25y | S32: z (5y)
A33: MOVE (rates vol) | B33: =Tickers!$C$32 | C33: bp | D33: =INDEX(HIST_D!$AB$8:$AB$2617,1) | E33: =IFERROR((INDEX(HIST_D!$AB$8:$AB$2617,1)-INDEX(HIST_D!$AB$8:$AB$2617,Control!$F$6))*1,"") | F33: =IFERROR((INDEX(HIST_D!$AB$8:$AB$2617,1)-INDEX(HIST_D!$AB$8:$AB$2617,Control!$F$7))*1,"") | G33: =IFERROR((INDEX(HIST_D!$AB$8:$AB$2617,1)-INDEX(HIST_D!$AB$8:$AB$2617,Control!$F$8))*1,"") | H33: =IFERROR((INDEX(HIST_D!$AB$8:$AB$2617,1)-INDEX(HIST_D!$AB$8:$AB$2617,Control!$F$9))*1,"") | I33: =IFERROR((INDEX(HIST_D!$AB$8:$AB$2617,1)-INDEX(HIST_D!$AB$8:$AB$2617,Control!$F$10))*1,"") | J33: =IFERROR((INDEX(HIST_D!$AB$8:$AB$2617,1)-INDEX(HIST_D!$AB$8:$AB$2617,Control!$F$16))*1,"") | K33: =IFERROR((INDEX(HIST_D!$AB$8:$AB$2617,1)-INDEX(HIST_D!$AB$8:$AB$2617,Control!$F$11))*1,"") | L33: =IFERROR(MIN(HIST_D!$AB$8:INDEX(HIST_D!$AB$8:$AB$2617,Control!$F$11)),"") | M33: =IFERROR(MAX(HIST_D!$AB$8:INDEX(HIST_D!$AB$8:$AB$2617,Control!$F$11)),"") | N33: =IFERROR(PERCENTRANK(HIST_D!$AB$8:INDEX(HIST_D!$AB$8:$AB$2617,Control!$F$11),INDEX(HIST_D!$AB$8:$AB$2617,1)),"") | O33: =IFERROR(PERCENTRANK(HIST_D!$AB$8:INDEX(HIST_D!$AB$8:$AB$2617,Control!$F$13),INDEX(HIST_D!$AB$8:$AB$2617,1)),"") | P33: =IFERROR(PERCENTRANK(HIST_D!$AB$8:INDEX(HIST_D!$AB$8:$AB$2617,Control!$F$14),INDEX(HIST_D!$AB$8:$AB$2617,1)),"") | Q33: =IFERROR(PERCENTRANK(HIST_D!$AB$8:INDEX(HIST_D!$AB$8:$AB$2617,Control!$F$15),INDEX(HIST_D!$AB$8:$AB$2617,1)),"") | R33: =IFERROR(PERCENTRANK(HIST_M!$I$8:$I$308,INDEX(HIST_D!$AB$8:$AB$2617,1)),"") | S33: =IFERROR((INDEX(HIST_D!$AB$8:$AB$2617,1)-AVERAGE(HIST_D!$AB$8:INDEX(HIST_D!$AB$8:$AB$2617,Control!$F$14)))/STDEV(HIST_D!$AB$8:INDEX(HIST_D!$AB$8:$AB$2617,Control!$F$14)),"")
A34: Swap spread 10Y | B34: derived on HIST_D | C34: bp | D34: =INDEX(HIST_D!$BE$8:$BE$2617,1) | E34: =IFERROR((INDEX(HIST_D!$BE$8:$BE$2617,1)-INDEX(HIST_D!$BE$8:$BE$2617,Control!$F$6))*1,"") | F34: =IFERROR((INDEX(HIST_D!$BE$8:$BE$2617,1)-INDEX(HIST_D!$BE$8:$BE$2617,Control!$F$7))*1,"") | G34: =IFERROR((INDEX(HIST_D!$BE$8:$BE$2617,1)-INDEX(HIST_D!$BE$8:$BE$2617,Control!$F$8))*1,"") | H34: =IFERROR((INDEX(HIST_D!$BE$8:$BE$2617,1)-INDEX(HIST_D!$BE$8:$BE$2617,Control!$F$9))*1,"") | I34: =IFERROR((INDEX(HIST_D!$BE$8:$BE$2617,1)-INDEX(HIST_D!$BE$8:$BE$2617,Control!$F$10))*1,"") | J34: =IFERROR((INDEX(HIST_D!$BE$8:$BE$2617,1)-INDEX(HIST_D!$BE$8:$BE$2617,Control!$F$16))*1,"") | K34: =IFERROR((INDEX(HIST_D!$BE$8:$BE$2617,1)-INDEX(HIST_D!$BE$8:$BE$2617,Control!$F$11))*1,"") | L34: =IFERROR(MIN(HIST_D!$BE$8:INDEX(HIST_D!$BE$8:$BE$2617,Control!$F$11)),"") | M34: =IFERROR(MAX(HIST_D!$BE$8:INDEX(HIST_D!$BE$8:$BE$2617,Control!$F$11)),"") | N34: =IFERROR(PERCENTRANK(HIST_D!$BE$8:INDEX(HIST_D!$BE$8:$BE$2617,Control!$F$11),INDEX(HIST_D!$BE$8:$BE$2617,1)),"") | O34: =IFERROR(PERCENTRANK(HIST_D!$BE$8:INDEX(HIST_D!$BE$8:$BE$2617,Control!$F$13),INDEX(HIST_D!$BE$8:$BE$2617,1)),"") | P34: =IFERROR(PERCENTRANK(HIST_D!$BE$8:INDEX(HIST_D!$BE$8:$BE$2617,Control!$F$14),INDEX(HIST_D!$BE$8:$BE$2617,1)),"") | Q34: =IFERROR(PERCENTRANK(HIST_D!$BE$8:INDEX(HIST_D!$BE$8:$BE$2617,Control!$F$15),INDEX(HIST_D!$BE$8:$BE$2617,1)),"") | S34: =IFERROR((INDEX(HIST_D!$BE$8:$BE$2617,1)-AVERAGE(HIST_D!$BE$8:INDEX(HIST_D!$BE$8:$BE$2617,Control!$F$14)))/STDEV(HIST_D!$BE$8:INDEX(HIST_D!$BE$8:$BE$2617,Control!$F$14)),"")
A35: Swap spread 30Y | B35: derived on HIST_D | C35: bp | D35: =INDEX(HIST_D!$BF$8:$BF$2617,1) | E35: =IFERROR((INDEX(HIST_D!$BF$8:$BF$2617,1)-INDEX(HIST_D!$BF$8:$BF$2617,Control!$F$6))*1,"") | F35: =IFERROR((INDEX(HIST_D!$BF$8:$BF$2617,1)-INDEX(HIST_D!$BF$8:$BF$2617,Control!$F$7))*1,"") | G35: =IFERROR((INDEX(HIST_D!$BF$8:$BF$2617,1)-INDEX(HIST_D!$BF$8:$BF$2617,Control!$F$8))*1,"") | H35: =IFERROR((INDEX(HIST_D!$BF$8:$BF$2617,1)-INDEX(HIST_D!$BF$8:$BF$2617,Control!$F$9))*1,"") | I35: =IFERROR((INDEX(HIST_D!$BF$8:$BF$2617,1)-INDEX(HIST_D!$BF$8:$BF$2617,Control!$F$10))*1,"") | J35: =IFERROR((INDEX(HIST_D!$BF$8:$BF$2617,1)-INDEX(HIST_D!$BF$8:$BF$2617,Control!$F$16))*1,"") | K35: =IFERROR((INDEX(HIST_D!$BF$8:$BF$2617,1)-INDEX(HIST_D!$BF$8:$BF$2617,Control!$F$11))*1,"") | L35: =IFERROR(MIN(HIST_D!$BF$8:INDEX(HIST_D!$BF$8:$BF$2617,Control!$F$11)),"") | M35: =IFERROR(MAX(HIST_D!$BF$8:INDEX(HIST_D!$BF$8:$BF$2617,Control!$F$11)),"") | N35: =IFERROR(PERCENTRANK(HIST_D!$BF$8:INDEX(HIST_D!$BF$8:$BF$2617,Control!$F$11),INDEX(HIST_D!$BF$8:$BF$2617,1)),"") | O35: =IFERROR(PERCENTRANK(HIST_D!$BF$8:INDEX(HIST_D!$BF$8:$BF$2617,Control!$F$13),INDEX(HIST_D!$BF$8:$BF$2617,1)),"") | P35: =IFERROR(PERCENTRANK(HIST_D!$BF$8:INDEX(HIST_D!$BF$8:$BF$2617,Control!$F$14),INDEX(HIST_D!$BF$8:$BF$2617,1)),"") | Q35: =IFERROR(PERCENTRANK(HIST_D!$BF$8:INDEX(HIST_D!$BF$8:$BF$2617,Control!$F$15),INDEX(HIST_D!$BF$8:$BF$2617,1)),"") | S35: =IFERROR((INDEX(HIST_D!$BF$8:$BF$2617,1)-AVERAGE(HIST_D!$BF$8:INDEX(HIST_D!$BF$8:$BF$2617,Control!$F$14)))/STDEV(HIST_D!$BF$8:INDEX(HIST_D!$BF$8:$BF$2617,Control!$F$14)),"")
A36: ON RRP volume ($bn) | B36: =Tickers!$C$46 | C36: $bn | D36: =INDEX(HIST_D!$AP$8:$AP$2617,1) | E36: =IFERROR((INDEX(HIST_D!$AP$8:$AP$2617,1)-INDEX(HIST_D!$AP$8:$AP$2617,Control!$F$6))*1,"") | F36: =IFERROR((INDEX(HIST_D!$AP$8:$AP$2617,1)-INDEX(HIST_D!$AP$8:$AP$2617,Control!$F$7))*1,"") | G36: =IFERROR((INDEX(HIST_D!$AP$8:$AP$2617,1)-INDEX(HIST_D!$AP$8:$AP$2617,Control!$F$8))*1,"") | H36: =IFERROR((INDEX(HIST_D!$AP$8:$AP$2617,1)-INDEX(HIST_D!$AP$8:$AP$2617,Control!$F$9))*1,"") | I36: =IFERROR((INDEX(HIST_D!$AP$8:$AP$2617,1)-INDEX(HIST_D!$AP$8:$AP$2617,Control!$F$10))*1,"") | J36: =IFERROR((INDEX(HIST_D!$AP$8:$AP$2617,1)-INDEX(HIST_D!$AP$8:$AP$2617,Control!$F$16))*1,"") | K36: =IFERROR((INDEX(HIST_D!$AP$8:$AP$2617,1)-INDEX(HIST_D!$AP$8:$AP$2617,Control!$F$11))*1,"") | L36: =IFERROR(MIN(HIST_D!$AP$8:INDEX(HIST_D!$AP$8:$AP$2617,Control!$F$11)),"") | M36: =IFERROR(MAX(HIST_D!$AP$8:INDEX(HIST_D!$AP$8:$AP$2617,Control!$F$11)),"") | N36: =IFERROR(PERCENTRANK(HIST_D!$AP$8:INDEX(HIST_D!$AP$8:$AP$2617,Control!$F$11),INDEX(HIST_D!$AP$8:$AP$2617,1)),"") | O36: =IFERROR(PERCENTRANK(HIST_D!$AP$8:INDEX(HIST_D!$AP$8:$AP$2617,Control!$F$13),INDEX(HIST_D!$AP$8:$AP$2617,1)),"") | P36: =IFERROR(PERCENTRANK(HIST_D!$AP$8:INDEX(HIST_D!$AP$8:$AP$2617,Control!$F$14),INDEX(HIST_D!$AP$8:$AP$2617,1)),"") | Q36: =IFERROR(PERCENTRANK(HIST_D!$AP$8:INDEX(HIST_D!$AP$8:$AP$2617,Control!$F$15),INDEX(HIST_D!$AP$8:$AP$2617,1)),"") | S36: =IFERROR((INDEX(HIST_D!$AP$8:$AP$2617,1)-AVERAGE(HIST_D!$AP$8:INDEX(HIST_D!$AP$8:$AP$2617,Control!$F$14)))/STDEV(HIST_D!$AP$8:INDEX(HIST_D!$AP$8:$AP$2617,Control!$F$14)),"")
A37: VIX | B37: =Tickers!$C$33 | C37: pt | D37: =INDEX(HIST_D!$AC$8:$AC$2617,1) | E37: =IFERROR((INDEX(HIST_D!$AC$8:$AC$2617,1)-INDEX(HIST_D!$AC$8:$AC$2617,Control!$F$6))*1,"") | F37: =IFERROR((INDEX(HIST_D!$AC$8:$AC$2617,1)-INDEX(HIST_D!$AC$8:$AC$2617,Control!$F$7))*1,"") | G37: =IFERROR((INDEX(HIST_D!$AC$8:$AC$2617,1)-INDEX(HIST_D!$AC$8:$AC$2617,Control!$F$8))*1,"") | H37: =IFERROR((INDEX(HIST_D!$AC$8:$AC$2617,1)-INDEX(HIST_D!$AC$8:$AC$2617,Control!$F$9))*1,"") | I37: =IFERROR((INDEX(HIST_D!$AC$8:$AC$2617,1)-INDEX(HIST_D!$AC$8:$AC$2617,Control!$F$10))*1,"") | J37: =IFERROR((INDEX(HIST_D!$AC$8:$AC$2617,1)-INDEX(HIST_D!$AC$8:$AC$2617,Control!$F$16))*1,"") | K37: =IFERROR((INDEX(HIST_D!$AC$8:$AC$2617,1)-INDEX(HIST_D!$AC$8:$AC$2617,Control!$F$11))*1,"") | L37: =IFERROR(MIN(HIST_D!$AC$8:INDEX(HIST_D!$AC$8:$AC$2617,Control!$F$11)),"") | M37: =IFERROR(MAX(HIST_D!$AC$8:INDEX(HIST_D!$AC$8:$AC$2617,Control!$F$11)),"") | N37: =IFERROR(PERCENTRANK(HIST_D!$AC$8:INDEX(HIST_D!$AC$8:$AC$2617,Control!$F$11),INDEX(HIST_D!$AC$8:$AC$2617,1)),"") | O37: =IFERROR(PERCENTRANK(HIST_D!$AC$8:INDEX(HIST_D!$AC$8:$AC$2617,Control!$F$13),INDEX(HIST_D!$AC$8:$AC$2617,1)),"") | P37: =IFERROR(PERCENTRANK(HIST_D!$AC$8:INDEX(HIST_D!$AC$8:$AC$2617,Control!$F$14),INDEX(HIST_D!$AC$8:$AC$2617,1)),"") | Q37: =IFERROR(PERCENTRANK(HIST_D!$AC$8:INDEX(HIST_D!$AC$8:$AC$2617,Control!$F$15),INDEX(HIST_D!$AC$8:$AC$2617,1)),"") | S37: =IFERROR((INDEX(HIST_D!$AC$8:$AC$2617,1)-AVERAGE(HIST_D!$AC$8:INDEX(HIST_D!$AC$8:$AC$2617,Control!$F$14)))/STDEV(HIST_D!$AC$8:INDEX(HIST_D!$AC$8:$AC$2617,Control!$F$14)),"")
A39: Item | B39: Bloomberg ticker | C39: Field | D39: Live pull | E39: Your fallback | F39: Used | G39: Status | H39: Unit | I39: Note
A40: Bloomberg US govt securities liquidity index | B40: USGGLIQ Index | C40: PX_LAST | D40: =IFERROR(BDP($B40,$C40),"") | E40: 2.5 | F40: =IF(ISNUMBER($D40),$D40,$E40) | G40: =IF(ISNUMBER($D40),"LIVE","FALLBACK") | H40: idx | I40: VERIFY ticker — average yield error across the curve; higher = worse liquidity
A42: READ-THROUGH (thresholds are yellow — set them where you want them)
A43: Signal | B43: Now | C43: Threshold | D43: Status | E43: What it means
A44: SOFR − IORB (bp) | B44: =($F$6-$F$12)*Control!$B$11 | C44: 5 | D44: =IF($B44>$C44,"TIGHT","OK") | E44: Above threshold = reserves scarce. The Fed responds to this before it responds to risk assets.
A45: ON RRP volume ($bn) | B45: =INDEX(HIST_D!$AP$8:$AP$2617,1) | C45: 50 | D45: =IF($B45<$C45,"BUFFER GONE","OK") | E45: Below threshold, further drains hit reserves directly.
A46: MOVE percentile (3y) | B46: =IFERROR(PERCENTRANK(HIST_D!$AB$8:INDEX(HIST_D!$AB$8:$AB$2617,Control!$F$13),INDEX(HIST_D!$AB$8:$AB$2617,1)),"") | C46: 0.8 | D46: =IF($B46>$C46,"STRESSED","OK") | E46: High rates vol is the usual transmission channel from Treasuries into EM spreads.
A47: Swap spread 10Y z-score (5y) | B47: =IFERROR((INDEX(HIST_D!$BE$8:$BE$2617,1)-AVERAGE(HIST_D!$BE$8:INDEX(HIST_D!$BE$8:$BE$2617,Control!$F$14)))/STDEV(HIST_D!$BE$8:INDEX(HIST_D!$BE$8:$BE$2617,Control!$F$14)),"") | C47: -1.5 | D47: =IF($B47<$C47,"BALANCE SHEET SCARCE","OK") | E47: Sharply negative swap spreads = dealers cannot warehouse more Treasuries.

Sheet Nodes
A1: NODE LIQUIDITY — where you can actually trade
A2: A node is liquid if the round trip is cheap relative to the risk you are taking. That is the bid-ask in YIELD bp column, not the price ticks.
A4: ON-THE-RUN CASH TREASURIES
A5: Node | B5: Ticker | C5: Bid | D5: Ask | E5: Mid price | F5: Yield (%) | G5: Bid-ask (32nds) | H5: Mod dur | I5: Bid-ask (yield bp) | J5: Rank | K5: Round trip on $100mm ($) | L5: Note
A6: On-the-run 2Y | B6: CT2 Govt | C6: =IFERROR(BDP($B6,"PX_BID"),"") | D6: =IFERROR(BDP($B6,"PX_ASK"),"") | E6: =IFERROR(($C6+$D6)/2,"") | F6: =IFERROR(BDP($B6,"YLD_YTM_MID"),INDEX(HIST_D!$F$8:$F$2617,1)) | G6: =IFERROR(($D6-$C6)*32,"") | H6: =Curve!$W$10 | I6: =IFERROR(($D6-$C6)/($H6*$E6/10000),"") | J6: =IFERROR(RANK($I6,$I$6:$I$12,1),"") | K6: =IFERROR(($D6-$C6)/100*100000000,"")
A7: On-the-run 3Y | B7: CT3 Govt | C7: =IFERROR(BDP($B7,"PX_BID"),"") | D7: =IFERROR(BDP($B7,"PX_ASK"),"") | E7: =IFERROR(($C7+$D7)/2,"") | F7: =IFERROR(BDP($B7,"YLD_YTM_MID"),INDEX(HIST_D!$G$8:$G$2617,1)) | G7: =IFERROR(($D7-$C7)*32,"") | H7: =Curve!$W$11 | I7: =IFERROR(($D7-$C7)/($H7*$E7/10000),"") | J7: =IFERROR(RANK($I7,$I$6:$I$12,1),"") | K7: =IFERROR(($D7-$C7)/100*100000000,"")
A8: On-the-run 5Y | B8: CT5 Govt | C8: =IFERROR(BDP($B8,"PX_BID"),"") | D8: =IFERROR(BDP($B8,"PX_ASK"),"") | E8: =IFERROR(($C8+$D8)/2,"") | F8: =IFERROR(BDP($B8,"YLD_YTM_MID"),INDEX(HIST_D!$H$8:$H$2617,1)) | G8: =IFERROR(($D8-$C8)*32,"") | H8: =Curve!$W$13 | I8: =IFERROR(($D8-$C8)/($H8*$E8/10000),"") | J8: =IFERROR(RANK($I8,$I$6:$I$12,1),"") | K8: =IFERROR(($D8-$C8)/100*100000000,"")
A9: On-the-run 7Y | B9: CT7 Govt | C9: =IFERROR(BDP($B9,"PX_BID"),"") | D9: =IFERROR(BDP($B9,"PX_ASK"),"") | E9: =IFERROR(($C9+$D9)/2,"") | F9: =IFERROR(BDP($B9,"YLD_YTM_MID"),INDEX(HIST_D!$I$8:$I$2617,1)) | G9: =IFERROR(($D9-$C9)*32,"") | H9: =Curve!$W$14 | I9: =IFERROR(($D9-$C9)/($H9*$E9/10000),"") | J9: =IFERROR(RANK($I9,$I$6:$I$12,1),"") | K9: =IFERROR(($D9-$C9)/100*100000000,"")
A10: On-the-run 10Y | B10: CT10 Govt | C10: =IFERROR(BDP($B10,"PX_BID"),"") | D10: =IFERROR(BDP($B10,"PX_ASK"),"") | E10: =IFERROR(($C10+$D10)/2,"") | F10: =IFERROR(BDP($B10,"YLD_YTM_MID"),INDEX(HIST_D!$J$8:$J$2617,1)) | G10: =IFERROR(($D10-$C10)*32,"") | H10: =Curve!$W$15 | I10: =IFERROR(($D10-$C10)/($H10*$E10/10000),"") | J10: =IFERROR(RANK($I10,$I$6:$I$12,1),"") | K10: =IFERROR(($D10-$C10)/100*100000000,"")
A11: On-the-run 20Y | B11: CT20 Govt | C11: =IFERROR(BDP($B11,"PX_BID"),"") | D11: =IFERROR(BDP($B11,"PX_ASK"),"") | E11: =IFERROR(($C11+$D11)/2,"") | F11: =IFERROR(BDP($B11,"YLD_YTM_MID"),INDEX(HIST_D!$K$8:$K$2617,1)) | G11: =IFERROR(($D11-$C11)*32,"") | H11: =Curve!$W$17 | I11: =IFERROR(($D11-$C11)/($H11*$E11/10000),"") | J11: =IFERROR(RANK($I11,$I$6:$I$12,1),"") | K11: =IFERROR(($D11-$C11)/100*100000000,"")
A12: On-the-run 30Y | B12: CT30 Govt | C12: =IFERROR(BDP($B12,"PX_BID"),"") | D12: =IFERROR(BDP($B12,"PX_ASK"),"") | E12: =IFERROR(($C12+$D12)/2,"") | F12: =IFERROR(BDP($B12,"YLD_YTM_MID"),INDEX(HIST_D!$L$8:$L$2617,1)) | G12: =IFERROR(($D12-$C12)*32,"") | H12: =Curve!$W$18 | I12: =IFERROR(($D12-$C12)/($H12*$E12/10000),"") | J12: =IFERROR(RANK($I12,$I$6:$I$12,1),"") | K12: =IFERROR(($D12-$C12)/100*100000000,"")
A13: Rank 1 = cheapest round trip per bp of risk. Quotes are indicative CBBT-style composites; on a bad afternoon the real spread is wider.
A15: OFF-THE-RUN COMPARATORS (paste the CUSIP tickers you actually get shown)
A16: Node | B16: Ticker | C16: Bid | D16: Ask | E16: Mid price | F16: Yield (%) | G16: Bid-ask (32nds) | H16: OTR yield (%) | I16: Concession vs OTR (bp)
A17: Old 2Y | B17: T 3 3/4 08/31/28 Govt | C17: =IFERROR(BDP($B17,"PX_BID"),"") | D17: =IFERROR(BDP($B17,"PX_ASK"),"") | E17: =IFERROR(($C17+$D17)/2,"") | F17: =IFERROR(BDP($B17,"YLD_YTM_MID"),"") | G17: =IFERROR(($D17-$C17)*32,"") | H17: =INDEX(HIST_D!$F$8:$F$2617,1) | I17: =IFERROR(($F17-$H17)*Control!$B$11,"")
A18: Old 5Y | B18: T 4 08/31/31 Govt | C18: =IFERROR(BDP($B18,"PX_BID"),"") | D18: =IFERROR(BDP($B18,"PX_ASK"),"") | E18: =IFERROR(($C18+$D18)/2,"") | F18: =IFERROR(BDP($B18,"YLD_YTM_MID"),"") | G18: =IFERROR(($D18-$C18)*32,"") | H18: =INDEX(HIST_D!$H$8:$H$2617,1) | I18: =IFERROR(($F18-$H18)*Control!$B$11,"")
A19: Old 10Y | B19: T 4 1/4 05/15/36 Govt | C19: =IFERROR(BDP($B19,"PX_BID"),"") | D19: =IFERROR(BDP($B19,"PX_ASK"),"") | E19: =IFERROR(($C19+$D19)/2,"") | F19: =IFERROR(BDP($B19,"YLD_YTM_MID"),"") | G19: =IFERROR(($D19-$C19)*32,"") | H19: =INDEX(HIST_D!$J$8:$J$2617,1) | I19: =IFERROR(($F19-$H19)*Control!$B$11,"")
A20: Old 30Y | B20: T 4 3/4 05/15/56 Govt | C20: =IFERROR(BDP($B20,"PX_BID"),"") | D20: =IFERROR(BDP($B20,"PX_ASK"),"") | E20: =IFERROR(($C20+$D20)/2,"") | F20: =IFERROR(BDP($B20,"YLD_YTM_MID"),"") | G20: =IFERROR(($D20-$C20)*32,"") | H20: =INDEX(HIST_D!$L$8:$L$2617,1) | I20: =IFERROR(($F20-$H20)*Control!$B$11,"")
A21: 4Y area | B21: paste ticker | C21: =IFERROR(BDP($B21,"PX_BID"),"") | D21: =IFERROR(BDP($B21,"PX_ASK"),"") | E21: =IFERROR(($C21+$D21)/2,"") | F21: =IFERROR(BDP($B21,"YLD_YTM_MID"),"") | G21: =IFERROR(($D21-$C21)*32,"") | H21: =INDEX(HIST_D!$AR$8:$AR$2617,1) | I21: =IFERROR(($F21-$H21)*Control!$B$11,"")
A22: 15Y area | B22: paste ticker | C22: =IFERROR(BDP($B22,"PX_BID"),"") | D22: =IFERROR(BDP($B22,"PX_ASK"),"") | E22: =IFERROR(($C22+$D22)/2,"") | F22: =IFERROR(BDP($B22,"YLD_YTM_MID"),"") | G22: =IFERROR(($D22-$C22)*32,"") | H22: =INDEX(HIST_D!$AS$8:$AS$2617,1) | I22: =IFERROR(($F22-$H22)*Control!$B$11,"")
A23: The example CUSIP tickers are PLACEHOLDERS — they roll. Overwrite column B with the current old bonds. A positive concession means the off-the-run yields more than the on-the-run: that is the liquidity premium you are paid to give up liquidity, and at 4Y and 15Y it is the only way to own those points in cash.
A25: TREASURY FUTURES — where the risk actually clears
A26: Contract | B26: Ticker | C26: Price | D26: Volume | E26: Open interest | F26: DV01 $/contract (live) | G26: DV01 fallback | H26: DV01 used | I26: Risk in OI ($/bp) | J26: Share of complex | K26: Turnover (vol/OI) | L26: Note
A27: 2Y note | B27: TU1 Comdty | C27: =IFERROR(BDP($B27,"PX_LAST"),"") | D27: =IFERROR(BDP($B27,"VOLUME"),"") | E27: =IFERROR(BDP($B27,"OPEN_INT"),"") | F27: =IFERROR(BDP($B27,"FUT_DV01"),"") | G27: 38 | H27: =IF(ISNUMBER($F27),$F27,$G27) | I27: =IFERROR($E27*$H27,"") | J27: =IFERROR($I27/SUM($I$27:$I$32),"") | K27: =IFERROR($D27/$E27,"") | L27: the front-end expression; cheapest risk transfer anywhere in rates
A28: 5Y note | B28: FV1 Comdty | C28: =IFERROR(BDP($B28,"PX_LAST"),"") | D28: =IFERROR(BDP($B28,"VOLUME"),"") | E28: =IFERROR(BDP($B28,"OPEN_INT"),"") | F28: =IFERROR(BDP($B28,"FUT_DV01"),"") | G28: 44 | H28: =IF(ISNUMBER($F28),$F28,$G28) | I28: =IFERROR($E28*$H28,"") | J28: =IFERROR($I28/SUM($I$27:$I$32),"") | K28: =IFERROR($D28/$E28,"") | L28: belly of the curve
A29: 10Y note | B29: TY1 Comdty | C29: =IFERROR(BDP($B29,"PX_LAST"),"") | D29: =IFERROR(BDP($B29,"VOLUME"),"") | E29: =IFERROR(BDP($B29,"OPEN_INT"),"") | F29: =IFERROR(BDP($B29,"FUT_DV01"),"") | G29: 67 | H29: =IF(ISNUMBER($F29),$F29,$G29) | I29: =IFERROR($E29*$H29,"") | J29: =IFERROR($I29/SUM($I$27:$I$32),"") | K29: =IFERROR($D29/$E29,"") | L29: the benchmark contract; deepest book in the world
A30: Ultra 10Y | B30: UXY1 Comdty | C30: =IFERROR(BDP($B30,"PX_LAST"),"") | D30: =IFERROR(BDP($B30,"VOLUME"),"") | E30: =IFERROR(BDP($B30,"OPEN_INT"),"") | F30: =IFERROR(BDP($B30,"FUT_DV01"),"") | G30: 93 | H30: =IF(ISNUMBER($F30),$F30,$G30) | I30: =IFERROR($E30*$H30,"") | J30: =IFERROR($I30/SUM($I$27:$I$32),"") | K30: =IFERROR($D30/$E30,"") | L30: the closest listed proxy to a true 10y point
A31: Classic bond | B31: US1 Comdty | C31: =IFERROR(BDP($B31,"PX_LAST"),"") | D31: =IFERROR(BDP($B31,"VOLUME"),"") | E31: =IFERROR(BDP($B31,"OPEN_INT"),"") | F31: =IFERROR(BDP($B31,"FUT_DV01"),"") | G31: 145 | H31: =IF(ISNUMBER($F31),$F31,$G31) | I31: =IFERROR($E31*$H31,"") | J31: =IFERROR($I31/SUM($I$27:$I$32),"") | K31: =IFERROR($D31/$E31,"") | L31: 15–25y CTD — this is your 15Y-area risk
A32: Ultra bond | B32: WN1 Comdty | C32: =IFERROR(BDP($B32,"PX_LAST"),"") | D32: =IFERROR(BDP($B32,"VOLUME"),"") | E32: =IFERROR(BDP($B32,"OPEN_INT"),"") | F32: =IFERROR(BDP($B32,"FUT_DV01"),"") | G32: 215 | H32: =IF(ISNUMBER($F32),$F32,$G32) | I32: =IFERROR($E32*$H32,"") | J32: =IFERROR($I32/SUM($I$27:$I$32),"") | K32: =IFERROR($D32/$E32,"") | L32: 25–30y; where long-end convexity trades
A33: Total risk in the listed complex ($/bp) | I33: =SUM($I$27:$I$32)
A35: SO WHERE DO YOU PUT THE TRADE?
A36: Most liquid, in order: the 10Y (TY plus the on-the-run note), then 5Y and 2Y, then 30Y. Anything you can do in those, do in those.
A37: Least liquid: 4Y, 15Y and 20Y. There is no futures contract at 4Y or 15Y and no on-the-run bond either — 20Y has an auction but trades at a persistent concession, which is exactly what the off-the-run block above measures.
A38: Practical rule: express curve views at 2/5/10/30 in futures or on-the-runs, and take the 4Y and 15Y points only when the concession in the block above pays you more than the extra bid-ask in column I.
A39: The 15Y point is really the classic bond future's CTD. If you want 15Y risk without the off-the-run bid-ask, US1 Comdty is the honest way to own it.
A40: Every number above is indicative. On a day when MOVE is in the top decile (see Liquidity), assume the quoted spreads double and the off-the-run concessions gap.

Sheet Credit
A1: US CREDIT — IG and HY
A2: Where spreads sit versus their own history over five windows, and what the indices actually pay you.
A4: SPREAD LEVELS AND DISTRIBUTION
A5: Instrument | B5: Source | C5: Unit | D5: Level | E5: 1D | F5: 1W | G5: 1M | H5: 3M | I5: 6M | J5: YTD | K5: 1Y | L5: 1y min | M5: 1y max | N5: %ile 1y | O5: %ile 3y | P5: %ile 5y | Q5: %ile 10y | R5: %ile 25y | S5: z (5y)
A6: US IG OAS | B6: =Tickers!$C$36 | C6: bp | D6: =INDEX(HIST_D!$AF$8:$AF$2617,1) | E6: =IFERROR((INDEX(HIST_D!$AF$8:$AF$2617,1)-INDEX(HIST_D!$AF$8:$AF$2617,Control!$F$6))*1,"") | F6: =IFERROR((INDEX(HIST_D!$AF$8:$AF$2617,1)-INDEX(HIST_D!$AF$8:$AF$2617,Control!$F$7))*1,"") | G6: =IFERROR((INDEX(HIST_D!$AF$8:$AF$2617,1)-INDEX(HIST_D!$AF$8:$AF$2617,Control!$F$8))*1,"") | H6: =IFERROR((INDEX(HIST_D!$AF$8:$AF$2617,1)-INDEX(HIST_D!$AF$8:$AF$2617,Control!$F$9))*1,"") | I6: =IFERROR((INDEX(HIST_D!$AF$8:$AF$2617,1)-INDEX(HIST_D!$AF$8:$AF$2617,Control!$F$10))*1,"") | J6: =IFERROR((INDEX(HIST_D!$AF$8:$AF$2617,1)-INDEX(HIST_D!$AF$8:$AF$2617,Control!$F$16))*1,"") | K6: =IFERROR((INDEX(HIST_D!$AF$8:$AF$2617,1)-INDEX(HIST_D!$AF$8:$AF$2617,Control!$F$11))*1,"") | L6: =IFERROR(MIN(HIST_D!$AF$8:INDEX(HIST_D!$AF$8:$AF$2617,Control!$F$11)),"") | M6: =IFERROR(MAX(HIST_D!$AF$8:INDEX(HIST_D!$AF$8:$AF$2617,Control!$F$11)),"") | N6: =IFERROR(PERCENTRANK(HIST_D!$AF$8:INDEX(HIST_D!$AF$8:$AF$2617,Control!$F$11),INDEX(HIST_D!$AF$8:$AF$2617,1)),"") | O6: =IFERROR(PERCENTRANK(HIST_D!$AF$8:INDEX(HIST_D!$AF$8:$AF$2617,Control!$F$13),INDEX(HIST_D!$AF$8:$AF$2617,1)),"") | P6: =IFERROR(PERCENTRANK(HIST_D!$AF$8:INDEX(HIST_D!$AF$8:$AF$2617,Control!$F$14),INDEX(HIST_D!$AF$8:$AF$2617,1)),"") | Q6: =IFERROR(PERCENTRANK(HIST_D!$AF$8:INDEX(HIST_D!$AF$8:$AF$2617,Control!$F$15),INDEX(HIST_D!$AF$8:$AF$2617,1)),"") | R6: =IFERROR(PERCENTRANK(HIST_M!$F$8:$F$308,INDEX(HIST_D!$AF$8:$AF$2617,1)),"") | S6: =IFERROR((INDEX(HIST_D!$AF$8:$AF$2617,1)-AVERAGE(HIST_D!$AF$8:INDEX(HIST_D!$AF$8:$AF$2617,Control!$F$14)))/STDEV(HIST_D!$AF$8:INDEX(HIST_D!$AF$8:$AF$2617,Control!$F$14)),"")
A7: US HY OAS | B7: =Tickers!$C$37 | C7: bp | D7: =INDEX(HIST_D!$AG$8:$AG$2617,1) | E7: =IFERROR((INDEX(HIST_D!$AG$8:$AG$2617,1)-INDEX(HIST_D!$AG$8:$AG$2617,Control!$F$6))*1,"") | F7: =IFERROR((INDEX(HIST_D!$AG$8:$AG$2617,1)-INDEX(HIST_D!$AG$8:$AG$2617,Control!$F$7))*1,"") | G7: =IFERROR((INDEX(HIST_D!$AG$8:$AG$2617,1)-INDEX(HIST_D!$AG$8:$AG$2617,Control!$F$8))*1,"") | H7: =IFERROR((INDEX(HIST_D!$AG$8:$AG$2617,1)-INDEX(HIST_D!$AG$8:$AG$2617,Control!$F$9))*1,"") | I7: =IFERROR((INDEX(HIST_D!$AG$8:$AG$2617,1)-INDEX(HIST_D!$AG$8:$AG$2617,Control!$F$10))*1,"") | J7: =IFERROR((INDEX(HIST_D!$AG$8:$AG$2617,1)-INDEX(HIST_D!$AG$8:$AG$2617,Control!$F$16))*1,"") | K7: =IFERROR((INDEX(HIST_D!$AG$8:$AG$2617,1)-INDEX(HIST_D!$AG$8:$AG$2617,Control!$F$11))*1,"") | L7: =IFERROR(MIN(HIST_D!$AG$8:INDEX(HIST_D!$AG$8:$AG$2617,Control!$F$11)),"") | M7: =IFERROR(MAX(HIST_D!$AG$8:INDEX(HIST_D!$AG$8:$AG$2617,Control!$F$11)),"") | N7: =IFERROR(PERCENTRANK(HIST_D!$AG$8:INDEX(HIST_D!$AG$8:$AG$2617,Control!$F$11),INDEX(HIST_D!$AG$8:$AG$2617,1)),"") | O7: =IFERROR(PERCENTRANK(HIST_D!$AG$8:INDEX(HIST_D!$AG$8:$AG$2617,Control!$F$13),INDEX(HIST_D!$AG$8:$AG$2617,1)),"") | P7: =IFERROR(PERCENTRANK(HIST_D!$AG$8:INDEX(HIST_D!$AG$8:$AG$2617,Control!$F$14),INDEX(HIST_D!$AG$8:$AG$2617,1)),"") | Q7: =IFERROR(PERCENTRANK(HIST_D!$AG$8:INDEX(HIST_D!$AG$8:$AG$2617,Control!$F$15),INDEX(HIST_D!$AG$8:$AG$2617,1)),"") | R7: =IFERROR(PERCENTRANK(HIST_M!$G$8:$G$308,INDEX(HIST_D!$AG$8:$AG$2617,1)),"") | S7: =IFERROR((INDEX(HIST_D!$AG$8:$AG$2617,1)-AVERAGE(HIST_D!$AG$8:INDEX(HIST_D!$AG$8:$AG$2617,Control!$F$14)))/STDEV(HIST_D!$AG$8:INDEX(HIST_D!$AG$8:$AG$2617,Control!$F$14)),"")
A8: EM USD Agg OAS | B8: =Tickers!$C$40 | C8: bp | D8: =INDEX(HIST_D!$AJ$8:$AJ$2617,1) | E8: =IFERROR((INDEX(HIST_D!$AJ$8:$AJ$2617,1)-INDEX(HIST_D!$AJ$8:$AJ$2617,Control!$F$6))*1,"") | F8: =IFERROR((INDEX(HIST_D!$AJ$8:$AJ$2617,1)-INDEX(HIST_D!$AJ$8:$AJ$2617,Control!$F$7))*1,"") | G8: =IFERROR((INDEX(HIST_D!$AJ$8:$AJ$2617,1)-INDEX(HIST_D!$AJ$8:$AJ$2617,Control!$F$8))*1,"") | H8: =IFERROR((INDEX(HIST_D!$AJ$8:$AJ$2617,1)-INDEX(HIST_D!$AJ$8:$AJ$2617,Control!$F$9))*1,"") | I8: =IFERROR((INDEX(HIST_D!$AJ$8:$AJ$2617,1)-INDEX(HIST_D!$AJ$8:$AJ$2617,Control!$F$10))*1,"") | J8: =IFERROR((INDEX(HIST_D!$AJ$8:$AJ$2617,1)-INDEX(HIST_D!$AJ$8:$AJ$2617,Control!$F$16))*1,"") | K8: =IFERROR((INDEX(HIST_D!$AJ$8:$AJ$2617,1)-INDEX(HIST_D!$AJ$8:$AJ$2617,Control!$F$11))*1,"") | L8: =IFERROR(MIN(HIST_D!$AJ$8:INDEX(HIST_D!$AJ$8:$AJ$2617,Control!$F$11)),"") | M8: =IFERROR(MAX(HIST_D!$AJ$8:INDEX(HIST_D!$AJ$8:$AJ$2617,Control!$F$11)),"") | N8: =IFERROR(PERCENTRANK(HIST_D!$AJ$8:INDEX(HIST_D!$AJ$8:$AJ$2617,Control!$F$11),INDEX(HIST_D!$AJ$8:$AJ$2617,1)),"") | O8: =IFERROR(PERCENTRANK(HIST_D!$AJ$8:INDEX(HIST_D!$AJ$8:$AJ$2617,Control!$F$13),INDEX(HIST_D!$AJ$8:$AJ$2617,1)),"") | P8: =IFERROR(PERCENTRANK(HIST_D!$AJ$8:INDEX(HIST_D!$AJ$8:$AJ$2617,Control!$F$14),INDEX(HIST_D!$AJ$8:$AJ$2617,1)),"") | Q8: =IFERROR(PERCENTRANK(HIST_D!$AJ$8:INDEX(HIST_D!$AJ$8:$AJ$2617,Control!$F$15),INDEX(HIST_D!$AJ$8:$AJ$2617,1)),"") | R8: =IFERROR(PERCENTRANK(HIST_M!$H$8:$H$308,INDEX(HIST_D!$AJ$8:$AJ$2617,1)),"") | S8: =IFERROR((INDEX(HIST_D!$AJ$8:$AJ$2617,1)-AVERAGE(HIST_D!$AJ$8:INDEX(HIST_D!$AJ$8:$AJ$2617,Control!$F$14)))/STDEV(HIST_D!$AJ$8:INDEX(HIST_D!$AJ$8:$AJ$2617,Control!$F$14)),"")
A9: HY − IG (bp) | B9: derived on HIST_D | C9: bp | D9: =INDEX(HIST_D!$BG$8:$BG$2617,1) | E9: =IFERROR((INDEX(HIST_D!$BG$8:$BG$2617,1)-INDEX(HIST_D!$BG$8:$BG$2617,Control!$F$6))*1,"") | F9: =IFERROR((INDEX(HIST_D!$BG$8:$BG$2617,1)-INDEX(HIST_D!$BG$8:$BG$2617,Control!$F$7))*1,"") | G9: =IFERROR((INDEX(HIST_D!$BG$8:$BG$2617,1)-INDEX(HIST_D!$BG$8:$BG$2617,Control!$F$8))*1,"") | H9: =IFERROR((INDEX(HIST_D!$BG$8:$BG$2617,1)-INDEX(HIST_D!$BG$8:$BG$2617,Control!$F$9))*1,"") | I9: =IFERROR((INDEX(HIST_D!$BG$8:$BG$2617,1)-INDEX(HIST_D!$BG$8:$BG$2617,Control!$F$10))*1,"") | J9: =IFERROR((INDEX(HIST_D!$BG$8:$BG$2617,1)-INDEX(HIST_D!$BG$8:$BG$2617,Control!$F$16))*1,"") | K9: =IFERROR((INDEX(HIST_D!$BG$8:$BG$2617,1)-INDEX(HIST_D!$BG$8:$BG$2617,Control!$F$11))*1,"") | L9: =IFERROR(MIN(HIST_D!$BG$8:INDEX(HIST_D!$BG$8:$BG$2617,Control!$F$11)),"") | M9: =IFERROR(MAX(HIST_D!$BG$8:INDEX(HIST_D!$BG$8:$BG$2617,Control!$F$11)),"") | N9: =IFERROR(PERCENTRANK(HIST_D!$BG$8:INDEX(HIST_D!$BG$8:$BG$2617,Control!$F$11),INDEX(HIST_D!$BG$8:$BG$2617,1)),"") | O9: =IFERROR(PERCENTRANK(HIST_D!$BG$8:INDEX(HIST_D!$BG$8:$BG$2617,Control!$F$13),INDEX(HIST_D!$BG$8:$BG$2617,1)),"") | P9: =IFERROR(PERCENTRANK(HIST_D!$BG$8:INDEX(HIST_D!$BG$8:$BG$2617,Control!$F$14),INDEX(HIST_D!$BG$8:$BG$2617,1)),"") | Q9: =IFERROR(PERCENTRANK(HIST_D!$BG$8:INDEX(HIST_D!$BG$8:$BG$2617,Control!$F$15),INDEX(HIST_D!$BG$8:$BG$2617,1)),"") | R9: =IFERROR(PERCENTRANK(HIST_M!$N$8:$N$308,INDEX(HIST_D!$BG$8:$BG$2617,1)),"") | S9: =IFERROR((INDEX(HIST_D!$BG$8:$BG$2617,1)-AVERAGE(HIST_D!$BG$8:INDEX(HIST_D!$BG$8:$BG$2617,Control!$F$14)))/STDEV(HIST_D!$BG$8:INDEX(HIST_D!$BG$8:$BG$2617,Control!$F$14)),"")
A10: HY / IG (x) | B10: derived on HIST_D | C10: x | D10: =INDEX(HIST_D!$BH$8:$BH$2617,1) | E10: =IFERROR((INDEX(HIST_D!$BH$8:$BH$2617,1)-INDEX(HIST_D!$BH$8:$BH$2617,Control!$F$6))*1,"") | F10: =IFERROR((INDEX(HIST_D!$BH$8:$BH$2617,1)-INDEX(HIST_D!$BH$8:$BH$2617,Control!$F$7))*1,"") | G10: =IFERROR((INDEX(HIST_D!$BH$8:$BH$2617,1)-INDEX(HIST_D!$BH$8:$BH$2617,Control!$F$8))*1,"") | H10: =IFERROR((INDEX(HIST_D!$BH$8:$BH$2617,1)-INDEX(HIST_D!$BH$8:$BH$2617,Control!$F$9))*1,"") | I10: =IFERROR((INDEX(HIST_D!$BH$8:$BH$2617,1)-INDEX(HIST_D!$BH$8:$BH$2617,Control!$F$10))*1,"") | J10: =IFERROR((INDEX(HIST_D!$BH$8:$BH$2617,1)-INDEX(HIST_D!$BH$8:$BH$2617,Control!$F$16))*1,"") | K10: =IFERROR((INDEX(HIST_D!$BH$8:$BH$2617,1)-INDEX(HIST_D!$BH$8:$BH$2617,Control!$F$11))*1,"") | L10: =IFERROR(MIN(HIST_D!$BH$8:INDEX(HIST_D!$BH$8:$BH$2617,Control!$F$11)),"") | M10: =IFERROR(MAX(HIST_D!$BH$8:INDEX(HIST_D!$BH$8:$BH$2617,Control!$F$11)),"") | N10: =IFERROR(PERCENTRANK(HIST_D!$BH$8:INDEX(HIST_D!$BH$8:$BH$2617,Control!$F$11),INDEX(HIST_D!$BH$8:$BH$2617,1)),"") | O10: =IFERROR(PERCENTRANK(HIST_D!$BH$8:INDEX(HIST_D!$BH$8:$BH$2617,Control!$F$13),INDEX(HIST_D!$BH$8:$BH$2617,1)),"") | P10: =IFERROR(PERCENTRANK(HIST_D!$BH$8:INDEX(HIST_D!$BH$8:$BH$2617,Control!$F$14),INDEX(HIST_D!$BH$8:$BH$2617,1)),"") | Q10: =IFERROR(PERCENTRANK(HIST_D!$BH$8:INDEX(HIST_D!$BH$8:$BH$2617,Control!$F$15),INDEX(HIST_D!$BH$8:$BH$2617,1)),"") | R10: =IFERROR(PERCENTRANK(HIST_M!$O$8:$O$308,INDEX(HIST_D!$BH$8:$BH$2617,1)),"") | S10: =IFERROR((INDEX(HIST_D!$BH$8:$BH$2617,1)-AVERAGE(HIST_D!$BH$8:INDEX(HIST_D!$BH$8:$BH$2617,Control!$F$14)))/STDEV(HIST_D!$BH$8:INDEX(HIST_D!$BH$8:$BH$2617,Control!$F$14)),"")
A11: EM − IG (bp) | B11: derived on HIST_D | C11: bp | D11: =INDEX(HIST_D!$BI$8:$BI$2617,1) | E11: =IFERROR((INDEX(HIST_D!$BI$8:$BI$2617,1)-INDEX(HIST_D!$BI$8:$BI$2617,Control!$F$6))*1,"") | F11: =IFERROR((INDEX(HIST_D!$BI$8:$BI$2617,1)-INDEX(HIST_D!$BI$8:$BI$2617,Control!$F$7))*1,"") | G11: =IFERROR((INDEX(HIST_D!$BI$8:$BI$2617,1)-INDEX(HIST_D!$BI$8:$BI$2617,Control!$F$8))*1,"") | H11: =IFERROR((INDEX(HIST_D!$BI$8:$BI$2617,1)-INDEX(HIST_D!$BI$8:$BI$2617,Control!$F$9))*1,"") | I11: =IFERROR((INDEX(HIST_D!$BI$8:$BI$2617,1)-INDEX(HIST_D!$BI$8:$BI$2617,Control!$F$10))*1,"") | J11: =IFERROR((INDEX(HIST_D!$BI$8:$BI$2617,1)-INDEX(HIST_D!$BI$8:$BI$2617,Control!$F$16))*1,"") | K11: =IFERROR((INDEX(HIST_D!$BI$8:$BI$2617,1)-INDEX(HIST_D!$BI$8:$BI$2617,Control!$F$11))*1,"") | L11: =IFERROR(MIN(HIST_D!$BI$8:INDEX(HIST_D!$BI$8:$BI$2617,Control!$F$11)),"") | M11: =IFERROR(MAX(HIST_D!$BI$8:INDEX(HIST_D!$BI$8:$BI$2617,Control!$F$11)),"") | N11: =IFERROR(PERCENTRANK(HIST_D!$BI$8:INDEX(HIST_D!$BI$8:$BI$2617,Control!$F$11),INDEX(HIST_D!$BI$8:$BI$2617,1)),"") | O11: =IFERROR(PERCENTRANK(HIST_D!$BI$8:INDEX(HIST_D!$BI$8:$BI$2617,Control!$F$13),INDEX(HIST_D!$BI$8:$BI$2617,1)),"") | P11: =IFERROR(PERCENTRANK(HIST_D!$BI$8:INDEX(HIST_D!$BI$8:$BI$2617,Control!$F$14),INDEX(HIST_D!$BI$8:$BI$2617,1)),"") | Q11: =IFERROR(PERCENTRANK(HIST_D!$BI$8:INDEX(HIST_D!$BI$8:$BI$2617,Control!$F$15),INDEX(HIST_D!$BI$8:$BI$2617,1)),"") | R11: =IFERROR(PERCENTRANK(HIST_M!$Q$8:$Q$308,INDEX(HIST_D!$BI$8:$BI$2617,1)),"") | S11: =IFERROR((INDEX(HIST_D!$BI$8:$BI$2617,1)-AVERAGE(HIST_D!$BI$8:INDEX(HIST_D!$BI$8:$BI$2617,Control!$F$14)))/STDEV(HIST_D!$BI$8:INDEX(HIST_D!$BI$8:$BI$2617,Control!$F$14)),"")
A12: EM / HY (x) | B12: derived on HIST_D | C12: x | D12: =INDEX(HIST_D!$BJ$8:$BJ$2617,1) | E12: =IFERROR((INDEX(HIST_D!$BJ$8:$BJ$2617,1)-INDEX(HIST_D!$BJ$8:$BJ$2617,Control!$F$6))*1,"") | F12: =IFERROR((INDEX(HIST_D!$BJ$8:$BJ$2617,1)-INDEX(HIST_D!$BJ$8:$BJ$2617,Control!$F$7))*1,"") | G12: =IFERROR((INDEX(HIST_D!$BJ$8:$BJ$2617,1)-INDEX(HIST_D!$BJ$8:$BJ$2617,Control!$F$8))*1,"") | H12: =IFERROR((INDEX(HIST_D!$BJ$8:$BJ$2617,1)-INDEX(HIST_D!$BJ$8:$BJ$2617,Control!$F$9))*1,"") | I12: =IFERROR((INDEX(HIST_D!$BJ$8:$BJ$2617,1)-INDEX(HIST_D!$BJ$8:$BJ$2617,Control!$F$10))*1,"") | J12: =IFERROR((INDEX(HIST_D!$BJ$8:$BJ$2617,1)-INDEX(HIST_D!$BJ$8:$BJ$2617,Control!$F$16))*1,"") | K12: =IFERROR((INDEX(HIST_D!$BJ$8:$BJ$2617,1)-INDEX(HIST_D!$BJ$8:$BJ$2617,Control!$F$11))*1,"") | L12: =IFERROR(MIN(HIST_D!$BJ$8:INDEX(HIST_D!$BJ$8:$BJ$2617,Control!$F$11)),"") | M12: =IFERROR(MAX(HIST_D!$BJ$8:INDEX(HIST_D!$BJ$8:$BJ$2617,Control!$F$11)),"") | N12: =IFERROR(PERCENTRANK(HIST_D!$BJ$8:INDEX(HIST_D!$BJ$8:$BJ$2617,Control!$F$11),INDEX(HIST_D!$BJ$8:$BJ$2617,1)),"") | O12: =IFERROR(PERCENTRANK(HIST_D!$BJ$8:INDEX(HIST_D!$BJ$8:$BJ$2617,Control!$F$13),INDEX(HIST_D!$BJ$8:$BJ$2617,1)),"") | P12: =IFERROR(PERCENTRANK(HIST_D!$BJ$8:INDEX(HIST_D!$BJ$8:$BJ$2617,Control!$F$14),INDEX(HIST_D!$BJ$8:$BJ$2617,1)),"") | Q12: =IFERROR(PERCENTRANK(HIST_D!$BJ$8:INDEX(HIST_D!$BJ$8:$BJ$2617,Control!$F$15),INDEX(HIST_D!$BJ$8:$BJ$2617,1)),"") | R12: =IFERROR(PERCENTRANK(HIST_M!$P$8:$P$308,INDEX(HIST_D!$BJ$8:$BJ$2617,1)),"") | S12: =IFERROR((INDEX(HIST_D!$BJ$8:$BJ$2617,1)-AVERAGE(HIST_D!$BJ$8:INDEX(HIST_D!$BJ$8:$BJ$2617,Control!$F$14)))/STDEV(HIST_D!$BJ$8:INDEX(HIST_D!$BJ$8:$BJ$2617,Control!$F$14)),"")
A13: CDX IG 5Y | B13: =Tickers!$C$42 | C13: bp | D13: =INDEX(HIST_D!$AL$8:$AL$2617,1) | E13: =IFERROR((INDEX(HIST_D!$AL$8:$AL$2617,1)-INDEX(HIST_D!$AL$8:$AL$2617,Control!$F$6))*1,"") | F13: =IFERROR((INDEX(HIST_D!$AL$8:$AL$2617,1)-INDEX(HIST_D!$AL$8:$AL$2617,Control!$F$7))*1,"") | G13: =IFERROR((INDEX(HIST_D!$AL$8:$AL$2617,1)-INDEX(HIST_D!$AL$8:$AL$2617,Control!$F$8))*1,"") | H13: =IFERROR((INDEX(HIST_D!$AL$8:$AL$2617,1)-INDEX(HIST_D!$AL$8:$AL$2617,Control!$F$9))*1,"") | I13: =IFERROR((INDEX(HIST_D!$AL$8:$AL$2617,1)-INDEX(HIST_D!$AL$8:$AL$2617,Control!$F$10))*1,"") | J13: =IFERROR((INDEX(HIST_D!$AL$8:$AL$2617,1)-INDEX(HIST_D!$AL$8:$AL$2617,Control!$F$16))*1,"") | K13: =IFERROR((INDEX(HIST_D!$AL$8:$AL$2617,1)-INDEX(HIST_D!$AL$8:$AL$2617,Control!$F$11))*1,"") | L13: =IFERROR(MIN(HIST_D!$AL$8:INDEX(HIST_D!$AL$8:$AL$2617,Control!$F$11)),"") | M13: =IFERROR(MAX(HIST_D!$AL$8:INDEX(HIST_D!$AL$8:$AL$2617,Control!$F$11)),"") | N13: =IFERROR(PERCENTRANK(HIST_D!$AL$8:INDEX(HIST_D!$AL$8:$AL$2617,Control!$F$11),INDEX(HIST_D!$AL$8:$AL$2617,1)),"") | O13: =IFERROR(PERCENTRANK(HIST_D!$AL$8:INDEX(HIST_D!$AL$8:$AL$2617,Control!$F$13),INDEX(HIST_D!$AL$8:$AL$2617,1)),"") | P13: =IFERROR(PERCENTRANK(HIST_D!$AL$8:INDEX(HIST_D!$AL$8:$AL$2617,Control!$F$14),INDEX(HIST_D!$AL$8:$AL$2617,1)),"") | Q13: =IFERROR(PERCENTRANK(HIST_D!$AL$8:INDEX(HIST_D!$AL$8:$AL$2617,Control!$F$15),INDEX(HIST_D!$AL$8:$AL$2617,1)),"") | S13: =IFERROR((INDEX(HIST_D!$AL$8:$AL$2617,1)-AVERAGE(HIST_D!$AL$8:INDEX(HIST_D!$AL$8:$AL$2617,Control!$F$14)))/STDEV(HIST_D!$AL$8:INDEX(HIST_D!$AL$8:$AL$2617,Control!$F$14)),"")
A14: CDX HY 5Y (px) | B14: =Tickers!$C$43 | C14: px | D14: =INDEX(HIST_D!$AM$8:$AM$2617,1) | E14: =IFERROR((INDEX(HIST_D!$AM$8:$AM$2617,1)-INDEX(HIST_D!$AM$8:$AM$2617,Control!$F$6))*1,"") | F14: =IFERROR((INDEX(HIST_D!$AM$8:$AM$2617,1)-INDEX(HIST_D!$AM$8:$AM$2617,Control!$F$7))*1,"") | G14: =IFERROR((INDEX(HIST_D!$AM$8:$AM$2617,1)-INDEX(HIST_D!$AM$8:$AM$2617,Control!$F$8))*1,"") | H14: =IFERROR((INDEX(HIST_D!$AM$8:$AM$2617,1)-INDEX(HIST_D!$AM$8:$AM$2617,Control!$F$9))*1,"") | I14: =IFERROR((INDEX(HIST_D!$AM$8:$AM$2617,1)-INDEX(HIST_D!$AM$8:$AM$2617,Control!$F$10))*1,"") | J14: =IFERROR((INDEX(HIST_D!$AM$8:$AM$2617,1)-INDEX(HIST_D!$AM$8:$AM$2617,Control!$F$16))*1,"") | K14: =IFERROR((INDEX(HIST_D!$AM$8:$AM$2617,1)-INDEX(HIST_D!$AM$8:$AM$2617,Control!$F$11))*1,"") | L14: =IFERROR(MIN(HIST_D!$AM$8:INDEX(HIST_D!$AM$8:$AM$2617,Control!$F$11)),"") | M14: =IFERROR(MAX(HIST_D!$AM$8:INDEX(HIST_D!$AM$8:$AM$2617,Control!$F$11)),"") | N14: =IFERROR(PERCENTRANK(HIST_D!$AM$8:INDEX(HIST_D!$AM$8:$AM$2617,Control!$F$11),INDEX(HIST_D!$AM$8:$AM$2617,1)),"") | O14: =IFERROR(PERCENTRANK(HIST_D!$AM$8:INDEX(HIST_D!$AM$8:$AM$2617,Control!$F$13),INDEX(HIST_D!$AM$8:$AM$2617,1)),"") | P14: =IFERROR(PERCENTRANK(HIST_D!$AM$8:INDEX(HIST_D!$AM$8:$AM$2617,Control!$F$14),INDEX(HIST_D!$AM$8:$AM$2617,1)),"") | Q14: =IFERROR(PERCENTRANK(HIST_D!$AM$8:INDEX(HIST_D!$AM$8:$AM$2617,Control!$F$15),INDEX(HIST_D!$AM$8:$AM$2617,1)),"") | S14: =IFERROR((INDEX(HIST_D!$AM$8:$AM$2617,1)-AVERAGE(HIST_D!$AM$8:INDEX(HIST_D!$AM$8:$AM$2617,Control!$F$14)))/STDEV(HIST_D!$AM$8:INDEX(HIST_D!$AM$8:$AM$2617,Control!$F$14)),"")
A15: The %ile 25y column uses the monthly block. Everything else is daily. A spread at the 5th percentile is not a sell signal on its own — it is a statement about how little room there is for the spread leg to help you.
A17: HOW FAR IS 'CHEAP'? Distance from each percentile, in bp
A18: Index | B18: Now (bp) | C18: 10th %ile | D18: 25th %ile | E18: Median | F18: 75th %ile | G18: 90th %ile | H18: bp to median | I18: bp to 75th | J18: bp to 90th | K18: Window
A19: US IG OAS | B19: =INDEX(HIST_D!$AF$8:$AF$2617,1) | C19: =IFERROR(PERCENTILE(HIST_D!$AF$8:INDEX(HIST_D!$AF$8:$AF$2617,Control!$F$14),0.1),"") | D19: =IFERROR(PERCENTILE(HIST_D!$AF$8:INDEX(HIST_D!$AF$8:$AF$2617,Control!$F$14),0.25),"") | E19: =IFERROR(PERCENTILE(HIST_D!$AF$8:INDEX(HIST_D!$AF$8:$AF$2617,Control!$F$14),0.5),"") | F19: =IFERROR(PERCENTILE(HIST_D!$AF$8:INDEX(HIST_D!$AF$8:$AF$2617,Control!$F$14),0.75),"") | G19: =IFERROR(PERCENTILE(HIST_D!$AF$8:INDEX(HIST_D!$AF$8:$AF$2617,Control!$F$14),0.9),"") | H19: =$E19-$B19 | I19: =$F19-$B19 | J19: =$G19-$B19 | K19: 5y
A20: US IG OAS | B20: =INDEX(HIST_D!$AF$8:$AF$2617,1) | C20: =IFERROR(PERCENTILE(HIST_D!$AF$8:INDEX(HIST_D!$AF$8:$AF$2617,Control!$F$15),0.1),"") | D20: =IFERROR(PERCENTILE(HIST_D!$AF$8:INDEX(HIST_D!$AF$8:$AF$2617,Control!$F$15),0.25),"") | E20: =IFERROR(PERCENTILE(HIST_D!$AF$8:INDEX(HIST_D!$AF$8:$AF$2617,Control!$F$15),0.5),"") | F20: =IFERROR(PERCENTILE(HIST_D!$AF$8:INDEX(HIST_D!$AF$8:$AF$2617,Control!$F$15),0.75),"") | G20: =IFERROR(PERCENTILE(HIST_D!$AF$8:INDEX(HIST_D!$AF$8:$AF$2617,Control!$F$15),0.9),"") | H20: =$E20-$B20 | I20: =$F20-$B20 | J20: =$G20-$B20 | K20: 10y
A21: US HY OAS | B21: =INDEX(HIST_D!$AG$8:$AG$2617,1) | C21: =IFERROR(PERCENTILE(HIST_D!$AG$8:INDEX(HIST_D!$AG$8:$AG$2617,Control!$F$14),0.1),"") | D21: =IFERROR(PERCENTILE(HIST_D!$AG$8:INDEX(HIST_D!$AG$8:$AG$2617,Control!$F$14),0.25),"") | E21: =IFERROR(PERCENTILE(HIST_D!$AG$8:INDEX(HIST_D!$AG$8:$AG$2617,Control!$F$14),0.5),"") | F21: =IFERROR(PERCENTILE(HIST_D!$AG$8:INDEX(HIST_D!$AG$8:$AG$2617,Control!$F$14),0.75),"") | G21: =IFERROR(PERCENTILE(HIST_D!$AG$8:INDEX(HIST_D!$AG$8:$AG$2617,Control!$F$14),0.9),"") | H21: =$E21-$B21 | I21: =$F21-$B21 | J21: =$G21-$B21 | K21: 5y
A22: US HY OAS | B22: =INDEX(HIST_D!$AG$8:$AG$2617,1) | C22: =IFERROR(PERCENTILE(HIST_D!$AG$8:INDEX(HIST_D!$AG$8:$AG$2617,Control!$F$15),0.1),"") | D22: =IFERROR(PERCENTILE(HIST_D!$AG$8:INDEX(HIST_D!$AG$8:$AG$2617,Control!$F$15),0.25),"") | E22: =IFERROR(PERCENTILE(HIST_D!$AG$8:INDEX(HIST_D!$AG$8:$AG$2617,Control!$F$15),0.5),"") | F22: =IFERROR(PERCENTILE(HIST_D!$AG$8:INDEX(HIST_D!$AG$8:$AG$2617,Control!$F$15),0.75),"") | G22: =IFERROR(PERCENTILE(HIST_D!$AG$8:INDEX(HIST_D!$AG$8:$AG$2617,Control!$F$15),0.9),"") | H22: =$E22-$B22 | I22: =$F22-$B22 | J22: =$G22-$B22 | K22: 10y
A23: EM USD Agg OAS | B23: =INDEX(HIST_D!$AJ$8:$AJ$2617,1) | C23: =IFERROR(PERCENTILE(HIST_D!$AJ$8:INDEX(HIST_D!$AJ$8:$AJ$2617,Control!$F$14),0.1),"") | D23: =IFERROR(PERCENTILE(HIST_D!$AJ$8:INDEX(HIST_D!$AJ$8:$AJ$2617,Control!$F$14),0.25),"") | E23: =IFERROR(PERCENTILE(HIST_D!$AJ$8:INDEX(HIST_D!$AJ$8:$AJ$2617,Control!$F$14),0.5),"") | F23: =IFERROR(PERCENTILE(HIST_D!$AJ$8:INDEX(HIST_D!$AJ$8:$AJ$2617,Control!$F$14),0.75),"") | G23: =IFERROR(PERCENTILE(HIST_D!$AJ$8:INDEX(HIST_D!$AJ$8:$AJ$2617,Control!$F$14),0.9),"") | H23: =$E23-$B23 | I23: =$F23-$B23 | J23: =$G23-$B23 | K23: 5y
A24: EM USD Agg OAS | B24: =INDEX(HIST_D!$AJ$8:$AJ$2617,1) | C24: =IFERROR(PERCENTILE(HIST_D!$AJ$8:INDEX(HIST_D!$AJ$8:$AJ$2617,Control!$F$15),0.1),"") | D24: =IFERROR(PERCENTILE(HIST_D!$AJ$8:INDEX(HIST_D!$AJ$8:$AJ$2617,Control!$F$15),0.25),"") | E24: =IFERROR(PERCENTILE(HIST_D!$AJ$8:INDEX(HIST_D!$AJ$8:$AJ$2617,Control!$F$15),0.5),"") | F24: =IFERROR(PERCENTILE(HIST_D!$AJ$8:INDEX(HIST_D!$AJ$8:$AJ$2617,Control!$F$15),0.75),"") | G24: =IFERROR(PERCENTILE(HIST_D!$AJ$8:INDEX(HIST_D!$AJ$8:$AJ$2617,Control!$F$15),0.9),"") | H24: =$E24-$B24 | I24: =$F24-$B24 | J24: =$G24-$B24 | K24: 10y
A25: Columns H–J are the widening it would take to get there. Put them next to the carry on Credit_TR: if 12m carry is 320bp and the move to the 75th percentile is 90bp of widening on 3.5 years of spread duration, the carry does not cover it.
A27: WHAT THE INDICES PAY (fallback inputs are live where the field works)
A28: Index | B28: Bloomberg ticker | C28: Field | D28: Live pull | E28: Your fallback | F28: Used | G28: Status | H28: Unit | I28: Note
A29: IG yield to worst | B29: LUACYW Index | C29: PX_LAST | D29: =IFERROR(BDP($B29,$C29),"") | E29: 5.3 | F29: =IF(ISNUMBER($D29),$D29,$E29) | G29: =IF(ISNUMBER($D29),"LIVE","FALLBACK") | H29: % | I29: VERIFY ticker
A30: IG duration | B30: LUACTRUU Index | C30: DUR_ADJ_MID | D30: =IFERROR(BDP($B30,$C30),"") | E30: 7 | F30: =IF(ISNUMBER($D30),$D30,$E30) | G30: =IF(ISNUMBER($D30),"LIVE","FALLBACK") | H30: yrs | I30: VERIFY field in FLDS
A31: HY yield to worst | B31: LF98YW Index | C31: PX_LAST | D31: =IFERROR(BDP($B31,$C31),"") | E31: 7.4 | F31: =IF(ISNUMBER($D31),$D31,$E31) | G31: =IF(ISNUMBER($D31),"LIVE","FALLBACK") | H31: % | I31: VERIFY ticker
A32: HY duration | B32: LF98TRUU Index | C32: DUR_ADJ_MID | D32: =IFERROR(BDP($B32,$C32),"") | E32: 3.3 | F32: =IF(ISNUMBER($D32),$D32,$E32) | G32: =IF(ISNUMBER($D32),"LIVE","FALLBACK") | H32: yrs | I32: VERIFY field in FLDS
A33: EM USD Agg yield to worst | B33: EMUSYW Index | C33: PX_LAST | D33: =IFERROR(BDP($B33,$C33),"") | E33: 6.2 | F33: =IF(ISNUMBER($D33),$D33,$E33) | G33: =IF(ISNUMBER($D33),"LIVE","FALLBACK") | H33: % | I33: VERIFY ticker
A34: EM USD Agg duration | B34: EMUSTRUU Index | C34: DUR_ADJ_MID | D34: =IFERROR(BDP($B34,$C34),"") | E34: 6.2 | F34: =IF(ISNUMBER($D34),$D34,$E34) | G34: =IF(ISNUMBER($D34),"LIVE","FALLBACK") | H34: yrs | I34: VERIFY field in FLDS
A36: Spread per year of duration (bp/yr) | B36: IG | C36: HY | D36: EM
A37: OAS ÷ duration | B37: =IFERROR(INDEX(HIST_D!$AF$8:$AF$2617,1)/Credit!$F$30,"") | C37: =IFERROR(INDEX(HIST_D!$AG$8:$AG$2617,1)/Credit!$F$32,"") | D37: =IFERROR(INDEX(HIST_D!$AJ$8:$AJ$2617,1)/Credit!$F$34,"") | F37: Compensation per unit of spread risk. The honest way to compare HY (short duration, fat spread) with EM and IG.
A39: TOTAL RETURN, REALISED (straight from the total-return sub-indices — no duration decomposition)
A40: Index | B40: 1M | C40: 3M | D40: 6M | E40: YTD | F40: 1Y | G40: 3Y ann. | H40: 5Y ann.
A41: US IG | B41: =IFERROR(INDEX(HIST_D!$AH$8:$AH$2617,1)/INDEX(HIST_D!$AH$8:$AH$2617,Control!$F$8)-1,"") | C41: =IFERROR(INDEX(HIST_D!$AH$8:$AH$2617,1)/INDEX(HIST_D!$AH$8:$AH$2617,Control!$F$9)-1,"") | D41: =IFERROR(INDEX(HIST_D!$AH$8:$AH$2617,1)/INDEX(HIST_D!$AH$8:$AH$2617,Control!$F$10)-1,"") | E41: =IFERROR(INDEX(HIST_D!$AH$8:$AH$2617,1)/INDEX(HIST_D!$AH$8:$AH$2617,Control!$F$16)-1,"") | F41: =IFERROR(INDEX(HIST_D!$AH$8:$AH$2617,1)/INDEX(HIST_D!$AH$8:$AH$2617,Control!$F$11)-1,"") | G41: =IFERROR((INDEX(HIST_D!$AH$8:$AH$2617,1)/INDEX(HIST_D!$AH$8:$AH$2617,Control!$F$13))^(1/3)-1,"") | H41: =IFERROR((INDEX(HIST_D!$AH$8:$AH$2617,1)/INDEX(HIST_D!$AH$8:$AH$2617,Control!$F$14))^(1/5)-1,"")
A42: US HY | B42: =IFERROR(INDEX(HIST_D!$AI$8:$AI$2617,1)/INDEX(HIST_D!$AI$8:$AI$2617,Control!$F$8)-1,"") | C42: =IFERROR(INDEX(HIST_D!$AI$8:$AI$2617,1)/INDEX(HIST_D!$AI$8:$AI$2617,Control!$F$9)-1,"") | D42: =IFERROR(INDEX(HIST_D!$AI$8:$AI$2617,1)/INDEX(HIST_D!$AI$8:$AI$2617,Control!$F$10)-1,"") | E42: =IFERROR(INDEX(HIST_D!$AI$8:$AI$2617,1)/INDEX(HIST_D!$AI$8:$AI$2617,Control!$F$16)-1,"") | F42: =IFERROR(INDEX(HIST_D!$AI$8:$AI$2617,1)/INDEX(HIST_D!$AI$8:$AI$2617,Control!$F$11)-1,"") | G42: =IFERROR((INDEX(HIST_D!$AI$8:$AI$2617,1)/INDEX(HIST_D!$AI$8:$AI$2617,Control!$F$13))^(1/3)-1,"") | H42: =IFERROR((INDEX(HIST_D!$AI$8:$AI$2617,1)/INDEX(HIST_D!$AI$8:$AI$2617,Control!$F$14))^(1/5)-1,"")
A43: EM USD Agg | B43: =IFERROR(INDEX(HIST_D!$AK$8:$AK$2617,1)/INDEX(HIST_D!$AK$8:$AK$2617,Control!$F$8)-1,"") | C43: =IFERROR(INDEX(HIST_D!$AK$8:$AK$2617,1)/INDEX(HIST_D!$AK$8:$AK$2617,Control!$F$9)-1,"") | D43: =IFERROR(INDEX(HIST_D!$AK$8:$AK$2617,1)/INDEX(HIST_D!$AK$8:$AK$2617,Control!$F$10)-1,"") | E43: =IFERROR(INDEX(HIST_D!$AK$8:$AK$2617,1)/INDEX(HIST_D!$AK$8:$AK$2617,Control!$F$16)-1,"") | F43: =IFERROR(INDEX(HIST_D!$AK$8:$AK$2617,1)/INDEX(HIST_D!$AK$8:$AK$2617,Control!$F$11)-1,"") | G43: =IFERROR((INDEX(HIST_D!$AK$8:$AK$2617,1)/INDEX(HIST_D!$AK$8:$AK$2617,Control!$F$13))^(1/3)-1,"") | H43: =IFERROR((INDEX(HIST_D!$AK$8:$AK$2617,1)/INDEX(HIST_D!$AK$8:$AK$2617,Control!$F$14))^(1/5)-1,"")
A44: End/start − 1 on the total-return index. Same convention as your EMBI tracker, and for the same reason: duration-derived decompositions of realised return do not reconcile.

Sheet Credit_TR
A1: CREDIT TOTAL RETURN — ceteris paribus and under stress
A2: Horizon and cash hurdle come from Control. The rate leg and the spread leg are never merged: the grid axes ARE the decomposition.
A4: INPUTS (green = linked from Credit, yellow = yours)
A5: Input | B5: US IG | C5: US HY | D5: EM USD Agg | E5: Note
A6: Current OAS (bp) | B6: =INDEX(HIST_D!$AF$8:$AF$2617,1) | C6: =INDEX(HIST_D!$AG$8:$AG$2617,1) | D6: =INDEX(HIST_D!$AJ$8:$AJ$2617,1) | E6: live from HIST_D
A7: Yield to worst (%) | B7: =Credit!$F$29 | C7: =Credit!$F$31 | D7: =Credit!$F$33 | E7: the carry leg
A8: Rate duration (yrs) | B8: =Credit!$F$30 | C8: =Credit!$F$32 | D8: =Credit!$F$34 | E8: applied to the Treasury leg
A9: Spread duration (yrs) | B9: =$B8 | C9: =$C8 | D9: =$D8 | E9: defaults to rate duration — override if you want them to differ
A10: Credit loss (bp per year) | B10: 5 | C10: 200 | D10: 45 | E10: default: IG ~nil, HY ≈ 3% default × 35% severity, EM sovereign lower. Yours to set.
A11: Cash hurdle (%) | B11: =Control!$B$13 | E11: from Control
A13: BASE CASE DECOMPOSITION (curve and spreads unchanged)
A14: Leg | B14: US IG | C14: US HY | D14: EM USD Agg | E14: Note
A15: Carry (YTW × horizon) | B15: =B7/100*Control!$B$12 | C15: =C7/100*Control!$B$12 | D15: =D7/100*Control!$B$12 | E15: what you earn for showing up
A16: Treasury leg (Δrate = 0) | B16: =0 | C16: =0 | D16: =0 | E16: zero by construction here — the grids below move it
A17: Spread leg (Δspread = 0) | B17: =0 | C17: =0 | D17: =0 | E17: same
A18: Credit loss | B18: =-B10/10000*Control!$B$12 | C18: =-C10/10000*Control!$B$12 | D18: =-D10/10000*Control!$B$12 | E18: your assumption, not the market's
A19: TOTAL 12m return, ceteris paribus | B19: =SUM(B15:B18) | C19: =SUM(C15:C18) | D19: =SUM(D15:D18)
A20: Excess over cash hurdle | B20: =B19-Control!$B$13/100 | C20: =C19-Control!$B$13/100 | D20: =D19-Control!$B$13/100 | F20: Carry alone, before any market move, against sitting in bills.
A21: Breakeven spread widening (bp) | B21: =IFERROR(B19/B9*10000,"") | C21: =IFERROR(C19/C9*10000,"") | D21: =IFERROR(D19/D9*10000,"") | F21: How much the spread can widen over the horizon before the total return is zero. Compare with 'bp to median' on Credit.
A22: Breakeven UST yield rise (bp) | B22: =IFERROR(B19/B8*10000,"") | C22: =IFERROR(C19/C8*10000,"") | D22: =IFERROR(D19/D8*10000,"") | F22: Same question for the Treasury leg, held separately on purpose.
A24: SENSITIVITY GRIDS — 12m total return (%)
A25: US INVESTMENT GRADE
A26: Δ spread (bp) ↓ / Δ UST yield (bp) → | B26: -100 | C26: -75 | D26: -50 | E26: -25 | F26: 0 | G26: 25 | H26: 50 | I26: 75 | J26: 100
A27: -100 | B27: =IFERROR($B7/100*Control!$B$12-$B8*(B$26/10000)-$B9*($A27/10000)-$B10/10000*Control!$B$12,"") | C27: =IFERROR($B7/100*Control!$B$12-$B8*(C$26/10000)-$B9*($A27/10000)-$B10/10000*Control!$B$12,"") | D27: =IFERROR($B7/100*Control!$B$12-$B8*(D$26/10000)-$B9*($A27/10000)-$B10/10000*Control!$B$12,"") | E27: =IFERROR($B7/100*Control!$B$12-$B8*(E$26/10000)-$B9*($A27/10000)-$B10/10000*Control!$B$12,"") | F27: =IFERROR($B7/100*Control!$B$12-$B8*(F$26/10000)-$B9*($A27/10000)-$B10/10000*Control!$B$12,"") | G27: =IFERROR($B7/100*Control!$B$12-$B8*(G$26/10000)-$B9*($A27/10000)-$B10/10000*Control!$B$12,"") | H27: =IFERROR($B7/100*Control!$B$12-$B8*(H$26/10000)-$B9*($A27/10000)-$B10/10000*Control!$B$12,"") | I27: =IFERROR($B7/100*Control!$B$12-$B8*(I$26/10000)-$B9*($A27/10000)-$B10/10000*Control!$B$12,"") | J27: =IFERROR($B7/100*Control!$B$12-$B8*(J$26/10000)-$B9*($A27/10000)-$B10/10000*Control!$B$12,"")
A28: -75 | B28: =IFERROR($B7/100*Control!$B$12-$B8*(B$26/10000)-$B9*($A28/10000)-$B10/10000*Control!$B$12,"") | C28: =IFERROR($B7/100*Control!$B$12-$B8*(C$26/10000)-$B9*($A28/10000)-$B10/10000*Control!$B$12,"") | D28: =IFERROR($B7/100*Control!$B$12-$B8*(D$26/10000)-$B9*($A28/10000)-$B10/10000*Control!$B$12,"") | E28: =IFERROR($B7/100*Control!$B$12-$B8*(E$26/10000)-$B9*($A28/10000)-$B10/10000*Control!$B$12,"") | F28: =IFERROR($B7/100*Control!$B$12-$B8*(F$26/10000)-$B9*($A28/10000)-$B10/10000*Control!$B$12,"") | G28: =IFERROR($B7/100*Control!$B$12-$B8*(G$26/10000)-$B9*($A28/10000)-$B10/10000*Control!$B$12,"") | H28: =IFERROR($B7/100*Control!$B$12-$B8*(H$26/10000)-$B9*($A28/10000)-$B10/10000*Control!$B$12,"") | I28: =IFERROR($B7/100*Control!$B$12-$B8*(I$26/10000)-$B9*($A28/10000)-$B10/10000*Control!$B$12,"") | J28: =IFERROR($B7/100*Control!$B$12-$B8*(J$26/10000)-$B9*($A28/10000)-$B10/10000*Control!$B$12,"")
A29: -50 | B29: =IFERROR($B7/100*Control!$B$12-$B8*(B$26/10000)-$B9*($A29/10000)-$B10/10000*Control!$B$12,"") | C29: =IFERROR($B7/100*Control!$B$12-$B8*(C$26/10000)-$B9*($A29/10000)-$B10/10000*Control!$B$12,"") | D29: =IFERROR($B7/100*Control!$B$12-$B8*(D$26/10000)-$B9*($A29/10000)-$B10/10000*Control!$B$12,"") | E29: =IFERROR($B7/100*Control!$B$12-$B8*(E$26/10000)-$B9*($A29/10000)-$B10/10000*Control!$B$12,"") | F29: =IFERROR($B7/100*Control!$B$12-$B8*(F$26/10000)-$B9*($A29/10000)-$B10/10000*Control!$B$12,"") | G29: =IFERROR($B7/100*Control!$B$12-$B8*(G$26/10000)-$B9*($A29/10000)-$B10/10000*Control!$B$12,"") | H29: =IFERROR($B7/100*Control!$B$12-$B8*(H$26/10000)-$B9*($A29/10000)-$B10/10000*Control!$B$12,"") | I29: =IFERROR($B7/100*Control!$B$12-$B8*(I$26/10000)-$B9*($A29/10000)-$B10/10000*Control!$B$12,"") | J29: =IFERROR($B7/100*Control!$B$12-$B8*(J$26/10000)-$B9*($A29/10000)-$B10/10000*Control!$B$12,"")
A30: -25 | B30: =IFERROR($B7/100*Control!$B$12-$B8*(B$26/10000)-$B9*($A30/10000)-$B10/10000*Control!$B$12,"") | C30: =IFERROR($B7/100*Control!$B$12-$B8*(C$26/10000)-$B9*($A30/10000)-$B10/10000*Control!$B$12,"") | D30: =IFERROR($B7/100*Control!$B$12-$B8*(D$26/10000)-$B9*($A30/10000)-$B10/10000*Control!$B$12,"") | E30: =IFERROR($B7/100*Control!$B$12-$B8*(E$26/10000)-$B9*($A30/10000)-$B10/10000*Control!$B$12,"") | F30: =IFERROR($B7/100*Control!$B$12-$B8*(F$26/10000)-$B9*($A30/10000)-$B10/10000*Control!$B$12,"") | G30: =IFERROR($B7/100*Control!$B$12-$B8*(G$26/10000)-$B9*($A30/10000)-$B10/10000*Control!$B$12,"") | H30: =IFERROR($B7/100*Control!$B$12-$B8*(H$26/10000)-$B9*($A30/10000)-$B10/10000*Control!$B$12,"") | I30: =IFERROR($B7/100*Control!$B$12-$B8*(I$26/10000)-$B9*($A30/10000)-$B10/10000*Control!$B$12,"") | J30: =IFERROR($B7/100*Control!$B$12-$B8*(J$26/10000)-$B9*($A30/10000)-$B10/10000*Control!$B$12,"")
A31: 0 | B31: =IFERROR($B7/100*Control!$B$12-$B8*(B$26/10000)-$B9*($A31/10000)-$B10/10000*Control!$B$12,"") | C31: =IFERROR($B7/100*Control!$B$12-$B8*(C$26/10000)-$B9*($A31/10000)-$B10/10000*Control!$B$12,"") | D31: =IFERROR($B7/100*Control!$B$12-$B8*(D$26/10000)-$B9*($A31/10000)-$B10/10000*Control!$B$12,"") | E31: =IFERROR($B7/100*Control!$B$12-$B8*(E$26/10000)-$B9*($A31/10000)-$B10/10000*Control!$B$12,"") | F31: =IFERROR($B7/100*Control!$B$12-$B8*(F$26/10000)-$B9*($A31/10000)-$B10/10000*Control!$B$12,"") | G31: =IFERROR($B7/100*Control!$B$12-$B8*(G$26/10000)-$B9*($A31/10000)-$B10/10000*Control!$B$12,"") | H31: =IFERROR($B7/100*Control!$B$12-$B8*(H$26/10000)-$B9*($A31/10000)-$B10/10000*Control!$B$12,"") | I31: =IFERROR($B7/100*Control!$B$12-$B8*(I$26/10000)-$B9*($A31/10000)-$B10/10000*Control!$B$12,"") | J31: =IFERROR($B7/100*Control!$B$12-$B8*(J$26/10000)-$B9*($A31/10000)-$B10/10000*Control!$B$12,"")
A32: 25 | B32: =IFERROR($B7/100*Control!$B$12-$B8*(B$26/10000)-$B9*($A32/10000)-$B10/10000*Control!$B$12,"") | C32: =IFERROR($B7/100*Control!$B$12-$B8*(C$26/10000)-$B9*($A32/10000)-$B10/10000*Control!$B$12,"") | D32: =IFERROR($B7/100*Control!$B$12-$B8*(D$26/10000)-$B9*($A32/10000)-$B10/10000*Control!$B$12,"") | E32: =IFERROR($B7/100*Control!$B$12-$B8*(E$26/10000)-$B9*($A32/10000)-$B10/10000*Control!$B$12,"") | F32: =IFERROR($B7/100*Control!$B$12-$B8*(F$26/10000)-$B9*($A32/10000)-$B10/10000*Control!$B$12,"") | G32: =IFERROR($B7/100*Control!$B$12-$B8*(G$26/10000)-$B9*($A32/10000)-$B10/10000*Control!$B$12,"") | H32: =IFERROR($B7/100*Control!$B$12-$B8*(H$26/10000)-$B9*($A32/10000)-$B10/10000*Control!$B$12,"") | I32: =IFERROR($B7/100*Control!$B$12-$B8*(I$26/10000)-$B9*($A32/10000)-$B10/10000*Control!$B$12,"") | J32: =IFERROR($B7/100*Control!$B$12-$B8*(J$26/10000)-$B9*($A32/10000)-$B10/10000*Control!$B$12,"")
